Workbook

Sheet Lista_CUIT
A1: CUIT | B1: RAZON SOCIAL | C1: Tipo de Gasto | D1: PROVINCIA
A2: =21779325 -> 21779325 | B2: BERAN Claudia Beatriz | C2: Gastos mantenimiento | G2: Mercaderia
A3: =12999779 -> 12999779 | B3: CORBALAN, MAFALDA ISABEL | G3: Servicios Gas, Luz, etc.
A4: =475785 -> 475785 | B4: GARCIA Ricardo Enrique | G4: Gastos catering
A5: =32052462 -> 32052462 | B5: Graells Luis Miguel | G5: Combustibe
A6: 33709585229 | B6: GOOGLE ARGENTINA S.R.L. | C6: Servicios de publicidad | G6: Gastos Varios
A7: 30526874249 | B7: FRAVEGA S A C I E I | C7: Gastos comercializacion | G7: Gastos seguridad
A8: 30716711621 | B8: TC TIENDAS AR S.R.L. | C8: insumos | D8: BUENOS AIRES | G8: Librería
A9: 30713550201 | B9: WAIKI S.A. | G9: Gastos mantenimiento
A10: 20357182914 | B10: GAIGA RENZO MIGUEL | G10: Gastos comercializacion
A11: 30715380567 | B11: SENS GROUP SRL | G11: Alquiler
A12: 33716435909 | B12: F&R S.A.S. | G12: Honorarios contables
A13: 30715313967 | B13: JD SOURCING S.R.L | G13: Gastos administrativos
A14: 27240934499 | B14: VITTOR LORENA MARCELA | G14: Seguro
A15: 20367341808 | B15: FEIDAS FERNANDO EMILIANO | G15: Extracto
A16: 30717477681 | B16: GRUPO FAM SA | G16: Flete
A17: 30717973166 | B17: STM ESTILO S.R.L | G17: Honorarios Legales
A18: 30717170594 | B18: INDUSTRIA4 S.R.L. | G18: Insumo
A19: 30716778041 | B19: PERROS Y GATOS FOOD S.A.S. | G19: Muebles y Utiles
A20: 20284212488 | B20: BARLETTA MAXIMILIANO SEBASTIAN | G20: Otros
... A22: 30715941763 | B22: TOURMALHYN S.R.L. | G22: Alojamiento-Varios
A23: 20252582704 | B23: GARCIA VAUTRIN ANDRES ALBERTO
A24: 20391525227 | B24: BARISCI MATIAS NICOLAS
A25: 30715380567 | B25: SENS GROUP SRL
A26: 20367341808 | B26: FEIDAS FERNANDO EMILIANO
A27: 33716435909 | B27: F&R S.A.S.
A28: 30708026200 | B28: BORGES BUENOS AIRES SRL
A29: 30707040900 | B29: TODOVISION S.A
A30: 23380288079 | B30: CASTROMAN AGUSTIN
A31: 27341104845 | B31: BOSSI MARIA PAULA
A32: 20300985158 | B32: GONZALEZ NESTOR RICARDO
A33: 33712058019 | B33: FLEET KYAN SRL
A34: 20369492528 | B34: GRIMALDI NICOLAS
... A54: 27386311000 | B54: OPANASIUK MACARENA ANTONELLA
A55: 20400104094 | B55: BOTINDARI FEDERICO DANIEL | C55: HONORARIOS CONTABLE
A56: 30688955749 | B56: LISERAR S A
A57: 30716234815 | B57: LEVINT PARTNERS S.R.L.
A58: 20319747975 | B58: CRESPO LEONARDO GUILLERMO
A59: 20369499956 | B59: LAMARI FRANCO AGUSTIN
A60: 20178248201 | B60: FRANCISCO ADRIAN MARCELO
A61: 30716549107 | B61: LAMATEC S.R.L.
A62: 20320573948 | B62: CAVALLOTTI MARCOS DANIEL
A63: 20277452872 | B63: GERVASI MAXIMILIANO ARIEL
A64: 20238882975 | B64: NARVAEZ SANTIAGO GABRIEL
A65: 27312707980 | B65: FERRARETTO CARLA ROMINA
A66: 30718044894 | B66: GRUPO NACER ECOLOGICO S.R.L
A67: 30586172308 | B67: SANTA FE COMERCIAL SOCIEDAD DE RESPONSABILIDAD LIMITADA
... A113: 30708153199 | B113: BT SECURITIES ARGENTINA S. A.

Sheet Ene-26
B1: LIBRO IVA COMPRAS | G1: RABLEB SRL | N1: 46023
B3: TOTAL COMPRAS | G3: TOTAL CREDITO FISCAL | J3: TOTAL VENTAS NETAS | M3: TOTAL DEBITO FISCAL | P3: RESULTADO
B4: =SUM(compras_mes1[[#Totals],[NETO GRAVADO]])+extracto_banco_mes1[[#Totals],[NETO]] -> 4830419.7 | G4: =compras_mes1[[#Totals],[IVA 21 %]]+compras_mes1[[#Totals],[IVA 27%]]+compras_mes1[[#Totals],[IVA 10,5%]]+extracto_banco_mes1[[#Totals],[IVA 21%]]+extracto_banco_mes1[[#Totals],[IVA 10,5%]] -> 1014388.1 | J4: =venta_a_mes1[[#Totals],[IMPORTE NETO]]+ventas_b_mes1[[#Totals],[IMPORTE NETO]] -> 10038329 | M4: =venta_a_mes1[[#Totals],[IVA 21%]]+venta_a_mes1[[#Totals],[IVA 10,5%]]+ventas_b_mes1[[#Totals],[IVA 21%]]+ventas_b_mes1[[#Totals],[IVA 10,5%]] -> 2108049.2 | P4: =G4-M4 -> -1093661
B8: FECHA | C8: TIPO | D8: PTO VTA | E8: NRO. CPTE | F8: CUIT | G8: RAZON SOCIAL | H8: NETO GRAVADO | I8: IVA 21 % | J8: IVA 27% | K8: IVA 10,5% | L8: PERC. IVA | M8: PERC IIBB BS AS | N8: PERC. IIBB CABA | O8: Otros / No Grav. | P8: TOTAL | Q8: Tipo de Gasto | R8: Provincia
B9: 02/01/2026 | C9: 1 | D9: 2 | E9: 1622 | F9: 30718631730 | G9: =IFERROR(IF(compras_mes1[[#This Row],[CUIT]]="","-",VLOOKUP(compras_mes1[[#This Row],[CUIT]],Lista_CUIT[#All],2,0)),"CUIT NO CARGADO") -> SIMZ S. R. L. | H9: 147686 | I9: =IF(compras_mes1[[#This Row],[NETO GRAVADO]]="","",compras_mes1[[#This Row],[NETO GRAVADO]]*0.21) -> 31014.06 | P9: =SUM(compras_mes1[[#This Row],[NETO GRAVADO]:[Otros / No Grav.]]) -> 178700.06 | Q9: =IFERROR(IF(compras_mes1[[#This Row],[CUIT]]="","-",VLOOKUP(compras_mes1[[#This Row],[CUIT]],Lista_CUIT[#All],3,0)),"CUIT NO CARGADO") -> 0 | R9: =IFERROR(IF(compras_mes1[[#This Row],[CUIT]]="","-",VLOOKUP(compras_mes1[[#This Row],[CUIT]],Lista_CUIT[#All],4,0)),"CUIT NO CARGADO") -> 0
B10: 08/01/2026 | C10: 1 | D10: 2 | E10: 1672954 | F10: 30710173652 | G10: =IFERROR(IF(compras_mes1[[#This Row],[CUIT]]="","-",VLOOKUP(compras_mes1[[#This Row],[CUIT]],Lista_CUIT[#All],2,0)),"CUIT NO CARGADO") -> DATTATEC.COM S.R.L. | H10: 33057.85 | I10: =IF(compras_mes1[[#This Row],[NETO GRAVADO]]="","",compras_mes1[[#This Row],[NETO GRAVADO]]*0.21) -> 6942.1485 | P10: =SUM(compras_mes1[[#This Row],[NETO GRAVADO]:[Otros / No Grav.]]) -> 39999.999 | Q10: =IFERROR(IF(compras_mes1[[#This Row],[CUIT]]="","-",VLOOKUP(compras_mes1[[#This Row],[CUIT]],Lista_CUIT[#All],3,0)),"CUIT NO CARGADO") -> 0 | R10: =IFERROR(IF(compras_mes1[[#This Row],[CUIT]]="","-",VLOOKUP(compras_mes1[[#This Row],[CUIT]],Lista_CUIT[#All],4,0)),"CUIT NO CARGADO") -> 0
B11: 12/01/2026 | C11: 1 | D11: 2 | E11: 1675699 | F11: 30710173652 | G11: =IFERROR(IF(compras_mes1[[#This Row],[CUIT]]="","-",VLOOKUP(compras_mes1[[#This Row],[CUIT]],Lista_CUIT[#All],2,0)),"CUIT NO CARGADO") -> DATTATEC.COM S.R.L. | H11: 33057.85 | I11: =IF(compras_mes1[[#This Row],[NETO GRAVADO]]="","",compras_mes1[[#This Row],[NETO GRAVADO]]*0.21) -> 6942.1485 | P11: =SUM(compras_mes1[[#This Row],[NETO GRAVADO]:[Otros / No Grav.]]) -> 39999.999 | Q11: =IFERROR(IF(compras_mes1[[#This Row],[CUIT]]="","-",VLOOKUP(compras_mes1[[#This Row],[CUIT]],Lista_CUIT[#All],3,0)),"CUIT NO CARGADO") -> 0 | R11: =IFERROR(IF(compras_mes1[[#This Row],[CUIT]]="","-",VLOOKUP(compras_mes1[[#This Row],[CUIT]],Lista_CUIT[#All],4,0)),"CUIT NO CARGADO") -> 0
B12: 21/01/2026 | C12: 1 | D12: 11 | E12: 1268196 | F12: 33709585229 | G12: =IFERROR(IF(compras_mes1[[#This Row],[CUIT]]="","-",VLOOKUP(compras_mes1[[#This Row],[CUIT]],Lista_CUIT[#All],2,0)),"CUIT NO CARGADO") -> GOOGLE ARGENTINA S.R.L. | H12: 15313.17 | I12: =IF(compras_mes1[[#This Row],[NETO GRAVADO]]="","",compras_mes1[[#This Row],[NETO GRAVADO]]*0.21) -> 3215.7657 | N12: 229.7 | O12: 459.4 | P12: =SUM(compras_mes1[[#This Row],[NETO GRAVADO]:[Otros / No Grav.]]) -> 19218.036 | Q12: =IFERROR(IF(compras_mes1[[#This Row],[CUIT]]="","-",VLOOKUP(compras_mes1[[#This Row],[CUIT]],Lista_CUIT[#All],3,0)),"CUIT NO CARGADO") -> Servicios de publicidad | R12: =IFERROR(IF(compras_mes1[[#This Row],[CUIT]]="","-",VLOOKUP(compras_mes1[[#This Row],[CUIT]],Lista_CUIT[#All],4,0)),"CUIT NO CARGADO") -> 0
B13: 30/01/2026 | C13: 1 | D13: 2 | E13: 1689272 | F13: 30710173652 | G13: =IFERROR(IF(compras_mes1[[#This Row],[CUIT]]="","-",VLOOKUP(compras_mes1[[#This Row],[CUIT]],Lista_CUIT[#All],2,0)),"CUIT NO CARGADO") -> DATTATEC.COM S.R.L. | H13: 145206.61 | I13: =IF(compras_mes1[[#This Row],[NETO GRAVADO]]="","",compras_mes1[[#This Row],[NETO GRAVADO]]*0.21) -> 30493.388 | P13: =SUM(compras_mes1[[#This Row],[NETO GRAVADO]:[Otros / No Grav.]]) -> 175700 | Q13: =IFERROR(IF(compras_mes1[[#This Row],[CUIT]]="","-",VLOOKUP(compras_mes1[[#This Row],[CUIT]],Lista_CUIT[#All],3,0)),"CUIT NO CARGADO") -> 0 | R13: =IFERROR(IF(compras_mes1[[#This Row],[CUIT]]="","-",VLOOKUP(compras_mes1[[#This Row],[CUIT]],Lista_CUIT[#All],4,0)),"CUIT NO CARGADO") -> 0
B14: 30/01/2026 | C14: 1 | D14: 2 | E14: 1689097 | F14: 30710173652 | G14: =IFERROR(IF(compras_mes1[[#This Row],[CUIT]]="","-",VLOOKUP(compras_mes1[[#This Row],[CUIT]],Lista_CUIT[#All],2,0)),"CUIT NO CARGADO") -> DATTATEC.COM S.R.L. | H14: 31660 | I14: =IF(compras_mes1[[#This Row],[NETO GRAVADO]]="","",compras_mes1[[#This Row],[NETO GRAVADO]]*0.21) -> 6648.6 | P14: =SUM(compras_mes1[[#This Row],[NETO GRAVADO]:[Otros / No Grav.]]) -> 38308.6 | Q14: =IFERROR(IF(compras_mes1[[#This Row],[CUIT]]="","-",VLOOKUP(compras_mes1[[#This Row],[CUIT]],Lista_CUIT[#All],3,0)),"CUIT NO CARGADO") -> 0 | R14: =IFERROR(IF(compras_mes1[[#This Row],[CUIT]]="","-",VLOOKUP(compras_mes1[[#This Row],[CUIT]],Lista_CUIT[#All],4,0)),"CUIT NO CARGADO") -> 0
B15: 31/01/2026 | C15: 1 | D15: 2 | E15: 1689950 | F15: 30710173652 | G15: =IFERROR(IF(compras_mes1[[#This Row],[CUIT]]="","-",VLOOKUP(compras_mes1[[#This Row],[CUIT]],Lista_CUIT[#All],2,0)),"CUIT NO CARGADO") -> DATTATEC.COM S.R.L. | H15: 33057.85 | I15: =IF(compras_mes1[[#This Row],[NETO GRAVADO]]="","",compras_mes1[[#This Row],[NETO GRAVADO]]*0.21) -> 6942.1485 | P15: =SUM(compras_mes1[[#This Row],[NETO GRAVADO]:[Otros / No Grav.]]) -> 39999.999 | Q15: =IFERROR(IF(compras_mes1[[#This Row],[CUIT]]="","-",VLOOKUP(compras_mes1[[#This Row],[CUIT]],Lista_CUIT[#All],3,0)),"CUIT NO CARGADO") -> 0 | R15: =IFERROR(IF(compras_mes1[[#This Row],[CUIT]]="","-",VLOOKUP(compras_mes1[[#This Row],[CUIT]],Lista_CUIT[#All],4,0)),"CUIT NO CARGADO") -> 0
B16: 31/01/2026 | C16: 1 | D16: 11 | E16: 1276363 | F16: 33709585229 | G16: =IFERROR(IF(compras_mes1[[#This Row],[CUIT]]="","-",VLOOKUP(compras_mes1[[#This Row],[CUIT]],Lista_CUIT[#All],2,0)),"CUIT NO CARGADO") -> GOOGLE ARGENTINA S.R.L. | H16: 2788520.6 | I16: =IF(compras_mes1[[#This Row],[NETO GRAVADO]]="","",compras_mes1[[#This Row],[NETO GRAVADO]]*0.21) -> 585589.33 | N16: 41827.81 | O16: 83655.62 | P16: =SUM(compras_mes1[[#This Row],[NETO GRAVADO]:[Otros / No Grav.]]) -> 3499593.4 | Q16: =IFERROR(IF(compras_mes1[[#This Row],[CUIT]]="","-",VLOOKUP(compras_mes1[[#This Row],[CUIT]],Lista_CUIT[#All],3,0)),"CUIT NO CARGADO") -> Servicios de publicidad | R16: =IFERROR(IF(compras_mes1[[#This Row],[CUIT]]="","-",VLOOKUP(compras_mes1[[#This Row],[CUIT]],Lista_CUIT[#All],4,0)),"CUIT NO CARGADO") -> 0
B17: 31/01/2026 | C17: 1 | D17: 11 | E17: 1279137 | F17: 33709585229 | G17: =IFERROR(IF(compras_mes1[[#This Row],[CUIT]]="","-",VLOOKUP(compras_mes1[[#This Row],[CUIT]],Lista_CUIT[#All],2,0)),"CUIT NO CARGADO") -> GOOGLE ARGENTINA S.R.L. | H17: 1603005.7 | I17: =IF(compras_mes1[[#This Row],[NETO GRAVADO]]="","",compras_mes1[[#This Row],[NETO GRAVADO]]*0.21) -> 336631.19 | N17: 24045.09 | O17: 48090.17 | P17: =SUM(compras_mes1[[#This Row],[NETO GRAVADO]:[Otros / No Grav.]]) -> 2011772.1 | Q17: =IFERROR(IF(compras_mes1[[#This Row],[CUIT]]="","-",VLOOKUP(compras_mes1[[#This Row],[CUIT]],Lista_CUIT[#All],3,0)),"CUIT NO CARGADO") -> Servicios de publicidad | R17: =IFERROR(IF(compras_mes1[[#This Row],[CUIT]]="","-",VLOOKUP(compras_mes1[[#This Row],[CUIT]],Lista_CUIT[#All],4,0)),"CUIT NO CARGADO") -> 0
B18: 31/01/2026 | C18: 3 | D18: 11 | E18: 909322 | F18: 33709585229 | G18: =IFERROR(IF(compras_mes1[[#This Row],[CUIT]]="","-",VLOOKUP(compras_mes1[[#This Row],[CUIT]],Lista_CUIT[#All],2,0)),"CUIT NO CARGADO") -> GOOGLE ARGENTINA S.R.L. | H18: -145.97 | I18: =IF(compras_mes1[[#This Row],[NETO GRAVADO]]="","",compras_mes1[[#This Row],[NETO GRAVADO]]*0.21) -> -30.6537 | N18: -2.19 | P18: =SUM(compras_mes1[[#This Row],[NETO GRAVADO]:[Otros / No Grav.]]) -> -178.8137 | Q18: =IFERROR(IF(compras_mes1[[#This Row],[CUIT]]="","-",VLOOKUP(compras_mes1[[#This Row],[CUIT]],Lista_CUIT[#All],3,0)),"CUIT NO CARGADO") -> Servicios de publicidad | R18: =IFERROR(IF(compras_mes1[[#This Row],[CUIT]]="","-",VLOOKUP(compras_mes1[[#This Row],[CUIT]],Lista_CUIT[#All],4,0)),"CUIT NO CARGADO") -> 0
G19: =IFERROR(IF(compras_mes1[[#This Row],[CUIT]]="","-",VLOOKUP(compras_mes1[[#This Row],[CUIT]],Lista_CUIT[#All],2,0)),"CUIT NO CARGADO") -> - | I19: =IF(compras_mes1[[#This Row],[NETO GRAVADO]]="","",compras_mes1[[#This Row],[NETO GRAVADO]]*0.21) | P19: =SUM(compras_mes1[[#This Row],[NETO GRAVADO]:[Otros / No Grav.]]) -> 0 | Q19: =IFERROR(IF(compras_mes1[[#This Row],[CUIT]]="","-",VLOOKUP(compras_mes1[[#This Row],[CUIT]],Lista_CUIT[#All],3,0)),"CUIT NO CARGADO") -> - | R19: =IFERROR(IF(compras_mes1[[#This Row],[CUIT]]="","-",VLOOKUP(compras_mes1[[#This Row],[CUIT]],Lista_CUIT[#All],4,0)),"CUIT NO CARGADO") -> -
G20: =IFERROR(IF(compras_mes1[[#This Row],[CUIT]]="","-",VLOOKUP(compras_mes1[[#This Row],[CUIT]],Lista_CUIT[#All],2,0)),"CUIT NO CARGADO") -> - | I20: =IF(compras_mes1[[#This Row],[NETO GRAVADO]]="","",compras_mes1[[#This Row],[NETO GRAVADO]]*0.21) | P20: =SUM(compras_mes1[[#This Row],[NETO GRAVADO]:[Otros / No Grav.]]) -> 0 | Q20: =IFERROR(IF(compras_mes1[[#This Row],[CUIT]]="","-",VLOOKUP(compras_mes1[[#This Row],[CUIT]],Lista_CUIT[#All],3,0)),"CUIT NO CARGADO") -> - | R20: =IFERROR(IF(compras_mes1[[#This Row],[CUIT]]="","-",VLOOKUP(compras_mes1[[#This Row],[CUIT]],Lista_CUIT[#All],4,0)),"CUIT NO CARGADO") -> -
G21: =IFERROR(IF(compras_mes1[[#This Row],[CUIT]]="","-",VLOOKUP(compras_mes1[[#This Row],[CUIT]],Lista_CUIT[#All],2,0)),"CUIT NO CARGADO") -> - | I21: =IF(compras_mes1[[#This Row],[NETO GRAVADO]]="","",compras_mes1[[#This Row],[NETO GRAVADO]]*0.21) | P21: =SUM(compras_mes1[[#This Row],[NETO GRAVADO]:[Otros / No Grav.]]) -> 0 | Q21: =IFERROR(IF(compras_mes1[[#This Row],[CUIT]]="","-",VLOOKUP(compras_mes1[[#This Row],[CUIT]],Lista_CUIT[#All],3,0)),"CUIT NO CARGADO") -> - | R21: =IFERROR(IF(compras_mes1[[#This Row],[CUIT]]="","-",VLOOKUP(compras_mes1[[#This Row],[CUIT]],Lista_CUIT[#All],4,0)),"CUIT NO CARGADO") -> -
G22: =IFERROR(IF(compras_mes1[[#This Row],[CUIT]]="","-",VLOOKUP(compras_mes1[[#This Row],[CUIT]],Lista_CUIT[#All],2,0)),"CUIT NO CARGADO") -> - | I22: =IF(compras_mes1[[#This Row],[NETO GRAVADO]]="","",compras_mes1[[#This Row],[NETO GRAVADO]]*0.21) | P22: =SUM(compras_mes1[[#This Row],[NETO GRAVADO]:[Otros / No Grav.]]) -> 0 | Q22: =IFERROR(IF(compras_mes1[[#This Row],[CUIT]]="","-",VLOOKUP(compras_mes1[[#This Row],[CUIT]],Lista_CUIT[#All],3,0)),"CUIT NO CARGADO") -> - | R22: =IFERROR(IF(compras_mes1[[#This Row],[CUIT]]="","-",VLOOKUP(compras_mes1[[#This Row],[CUIT]],Lista_CUIT[#All],4,0)),"CUIT NO CARGADO") -> -
G23: =IFERROR(IF(compras_mes1[[#This Row],[CUIT]]="","-",VLOOKUP(compras_mes1[[#This Row],[CUIT]],Lista_CUIT[#All],2,0)),"CUIT NO CARGADO") -> - | I23: =IF(compras_mes1[[#This Row],[NETO GRAVADO]]="","",compras_mes1[[#This Row],[NETO GRAVADO]]*0.21) | P23: =SUM(compras_mes1[[#This Row],[NETO GRAVADO]:[Otros / No Grav.]]) -> 0 | Q23: =IFERROR(IF(compras_mes1[[#This Row],[CUIT]]="","-",VLOOKUP(compras_mes1[[#This Row],[CUIT]],Lista_CUIT[#All],3,0)),"CUIT NO CARGADO") -> - | R23: =IFERROR(IF(compras_mes1[[#This Row],[CUIT]]="","-",VLOOKUP(compras_mes1[[#This Row],[CUIT]],Lista_CUIT[#All],4,0)),"CUIT NO CARGADO") -> -
G24: =IFERROR(IF(compras_mes1[[#This Row],[CUIT]]="","-",VLOOKUP(compras_mes1[[#This Row],[CUIT]],Lista_CUIT[#All],2,0)),"CUIT NO CARGADO") -> - | I24: =IF(compras_mes1[[#This Row],[NETO GRAVADO]]="","",compras_mes1[[#This Row],[NETO GRAVADO]]*0.21) | P24: =SUM(compras_mes1[[#This Row],[NETO GRAVADO]:[Otros / No Grav.]]) -> 0 | Q24: =IFERROR(IF(compras_mes1[[#This Row],[CUIT]]="","-",VLOOKUP(compras_mes1[[#This Row],[CUIT]],Lista_CUIT[#All],3,0)),"CUIT NO CARGADO") -> - | R24: =IFERROR(IF(compras_mes1[[#This Row],[CUIT]]="","-",VLOOKUP(compras_mes1[[#This Row],[CUIT]],Lista_CUIT[#All],4,0)),"CUIT NO CARGADO") -> -
G25: =IFERROR(IF(compras_mes1[[#This Row],[CUIT]]="","-",VLOOKUP(compras_mes1[[#This Row],[CUIT]],Lista_CUIT[#All],2,0)),"CUIT NO CARGADO") -> - | I25: =IF(compras_mes1[[#This Row],[NETO GRAVADO]]="","",compras_mes1[[#This Row],[NETO GRAVADO]]*0.21) | P25: =SUM(compras_mes1[[#This Row],[NETO GRAVADO]:[Otros / No Grav.]]) -> 0 | Q25: =IFERROR(IF(compras_mes1[[#This Row],[CUIT]]="","-",VLOOKUP(compras_mes1[[#This Row],[CUIT]],Lista_CUIT[#All],3,0)),"CUIT NO CARGADO") -> - | R25: =IFERROR(IF(compras_mes1[[#This Row],[CUIT]]="","-",VLOOKUP(compras_mes1[[#This Row],[CUIT]],Lista_CUIT[#All],4,0)),"CUIT NO CARGADO") -> -
G26: =IFERROR(IF(compras_mes1[[#This Row],[CUIT]]="","-",VLOOKUP(compras_mes1[[#This Row],[CUIT]],Lista_CUIT[#All],2,0)),"CUIT NO CARGADO") -> - | I26: =IF(compras_mes1[[#This Row],[NETO GRAVADO]]="","",compras_mes1[[#This Row],[NETO GRAVADO]]*0.21) | P26: =SUM(compras_mes1[[#This Row],[NETO GRAVADO]:[Otros / No Grav.]]) -> 0 | Q26: =IFERROR(IF(compras_mes1[[#This Row],[CUIT]]="","-",VLOOKUP(compras_mes1[[#This Row],[CUIT]],Lista_CUIT[#All],3,0)),"CUIT NO CARGADO") -> - | R26: =IFERROR(IF(compras_mes1[[#This Row],[CUIT]]="","-",VLOOKUP(compras_mes1[[#This Row],[CUIT]],Lista_CUIT[#All],4,0)),"CUIT NO CARGADO") -> -
G27: =IFERROR(IF(compras_mes1[[#This Row],[CUIT]]="","-",VLOOKUP(compras_mes1[[#This Row],[CUIT]],Lista_CUIT[#All],2,0)),"CUIT NO CARGADO") -> - | I27: =IF(compras_mes1[[#This Row],[NETO GRAVADO]]="","",compras_mes1[[#This Row],[NETO GRAVADO]]*0.21) | P27: =SUM(compras_mes1[[#This Row],[NETO GRAVADO]:[Otros / No Grav.]]) -> 0 | Q27: =IFERROR(IF(compras_mes1[[#This Row],[CUIT]]="","-",VLOOKUP(compras_mes1[[#This Row],[CUIT]],Lista_CUIT[#All],3,0)),"CUIT NO CARGADO") -> - | R27: =IFERROR(IF(compras_mes1[[#This Row],[CUIT]]="","-",VLOOKUP(compras_mes1[[#This Row],[CUIT]],Lista_CUIT[#All],4,0)),"CUIT NO CARGADO") -> -
G28: =IFERROR(IF(compras_mes1[[#This Row],[CUIT]]="","-",VLOOKUP(compras_mes1[[#This Row],[CUIT]],Lista_CUIT[#All],2,0)),"CUIT NO CARGADO") -> - | I28: =IF(compras_mes1[[#This Row],[NETO GRAVADO]]="","",compras_mes1[[#This Row],[NETO GRAVADO]]*0.21) | P28: =SUM(compras_mes1[[#This Row],[NETO GRAVADO]:[Otros / No Grav.]]) -> 0 | Q28: =IFERROR(IF(compras_mes1[[#This Row],[CUIT]]="","-",VLOOKUP(compras_mes1[[#This Row],[CUIT]],Lista_CUIT[#All],3,0)),"CUIT NO CARGADO") -> - | R28: =IFERROR(IF(compras_mes1[[#This Row],[CUIT]]="","-",VLOOKUP(compras_mes1[[#This Row],[CUIT]],Lista_CUIT[#All],4,0)),"CUIT NO CARGADO") -> -
G29: =IFERROR(IF(compras_mes1[[#This Row],[CUIT]]="","-",VLOOKUP(compras_mes1[[#This Row],[CUIT]],Lista_CUIT[#All],2,0)),"CUIT NO CARGADO") -> - | I29: =IF(compras_mes1[[#This Row],[NETO GRAVADO]]="","",compras_mes1[[#This Row],[NETO GRAVADO]]*0.21) | P29: =SUM(compras_mes1[[#This Row],[NETO GRAVADO]:[Otros / No Grav.]]) -> 0 | Q29: =IFERROR(IF(compras_mes1[[#This Row],[CUIT]]="","-",VLOOKUP(compras_mes1[[#This Row],[CUIT]],Lista_CUIT[#All],3,0)),"CUIT NO CARGADO") -> - | R29: =IFERROR(IF(compras_mes1[[#This Row],[CUIT]]="","-",VLOOKUP(compras_mes1[[#This Row],[CUIT]],Lista_CUIT[#All],4,0)),"CUIT NO CARGADO") -> -
G30: =IFERROR(IF(compras_mes1[[#This Row],[CUIT]]="","-",VLOOKUP(compras_mes1[[#This Row],[CUIT]],Lista_CUIT[#All],2,0)),"CUIT NO CARGADO") -> - | I30: =IF(compras_mes1[[#This Row],[NETO GRAVADO]]="","",compras_mes1[[#This Row],[NETO GRAVADO]]*0.21) | P30: =SUM(compras_mes1[[#This Row],[NETO GRAVADO]:[Otros / No Grav.]]) -> 0 | Q30: =IFERROR(IF(compras_mes1[[#This Row],[CUIT]]="","-",VLOOKUP(compras_mes1[[#This Row],[CUIT]],Lista_CUIT[#All],3,0)),"CUIT NO CARGADO") -> - | R30: =IFERROR(IF(compras_mes1[[#This Row],[CUIT]]="","-",VLOOKUP(compras_mes1[[#This Row],[CUIT]],Lista_CUIT[#All],4,0)),"CUIT NO CARGADO") -> -
G31: =IFERROR(IF(compras_mes1[[#This Row],[CUIT]]="","-",VLOOKUP(compras_mes1[[#This Row],[CUIT]],Lista_CUIT[#All],2,0)),"CUIT NO CARGADO") -> - | I31: =IF(compras_mes1[[#This Row],[NETO GRAVADO]]="","",compras_mes1[[#This Row],[NETO GRAVADO]]*0.21) | P31: =SUM(compras_mes1[[#This Row],[NETO GRAVADO]:[Otros / No Grav.]]) -> 0 | Q31: =IFERROR(IF(compras_mes1[[#This Row],[CUIT]]="","-",VLOOKUP(compras_mes1[[#This Row],[CUIT]],Lista_CUIT[#All],3,0)),"CUIT NO CARGADO") -> - | R31: =IFERROR(IF(compras_mes1[[#This Row],[CUIT]]="","-",VLOOKUP(compras_mes1[[#This Row],[CUIT]],Lista_CUIT[#All],4,0)),"CUIT NO CARGADO") -> -
G32: =IFERROR(IF(compras_mes1[[#This Row],[CUIT]]="","-",VLOOKUP(compras_mes1[[#This Row],[CUIT]],Lista_CUIT[#All],2,0)),"CUIT NO CARGADO") -> - | P32: =SUM(compras_mes1[[#This Row],[NETO GRAVADO]:[Otros / No Grav.]]) -> 0 | Q32: =IFERROR(IF(compras_mes1[[#This Row],[CUIT]]="","-",VLOOKUP(compras_mes1[[#This Row],[CUIT]],Lista_CUIT[#All],3,0)),"CUIT NO CARGADO") -> - | R32: =IFERROR(IF(compras_mes1[[#This Row],[CUIT]]="","-",VLOOKUP(compras_mes1[[#This Row],[CUIT]],Lista_CUIT[#All],4,0)),"CUIT NO CARGADO") -> -
G33: =IFERROR(IF(compras_mes1[[#This Row],[CUIT]]="","-",VLOOKUP(compras_mes1[[#This Row],[CUIT]],Lista_CUIT[#All],2,0)),"CUIT NO CARGADO") -> - | I33: =IF(compras_mes1[[#This Row],[NETO GRAVADO]]="","",compras_mes1[[#This Row],[NETO GRAVADO]]*0.21) | P33: =SUM(compras_mes1[[#This Row],[NETO GRAVADO]:[Otros / No Grav.]]) -> 0 | Q33: =IFERROR(IF(compras_mes1[[#This Row],[CUIT]]="","-",VLOOKUP(compras_mes1[[#This Row],[CUIT]],Lista_CUIT[#All],3,0)),"CUIT NO CARGADO") -> - | R33: =IFERROR(IF(compras_mes1[[#This Row],[CUIT]]="","-",VLOOKUP(compras_mes1[[#This Row],[CUIT]],Lista_CUIT[#All],4,0)),"CUIT NO CARGADO") -> -
G34: =IFERROR(IF(compras_mes1[[#This Row],[CUIT]]="","-",VLOOKUP(compras_mes1[[#This Row],[CUIT]],Lista_CUIT[#All],2,0)),"CUIT NO CARGADO") -> - | I34: =IF(compras_mes1[[#This Row],[NETO GRAVADO]]="","",compras_mes1[[#This Row],[NETO GRAVADO]]*0.21) | P34: =SUM(compras_mes1[[#This Row],[NETO GRAVADO]:[Otros / No Grav.]]) -> 0 | Q34: =IFERROR(IF(compras_mes1[[#This Row],[CUIT]]="","-",VLOOKUP(compras_mes1[[#This Row],[CUIT]],Lista_CUIT[#All],3,0)),"CUIT NO CARGADO") -> - | R34: =IFERROR(IF(compras_mes1[[#This Row],[CUIT]]="","-",VLOOKUP(compras_mes1[[#This Row],[CUIT]],Lista_CUIT[#All],4,0)),"CUIT NO CARGADO") -> -
G35: =IFERROR(IF(compras_mes1[[#This Row],[CUIT]]="","-",VLOOKUP(compras_mes1[[#This Row],[CUIT]],Lista_CUIT[#All],2,0)),"CUIT NO CARGADO") -> - | I35: =IF(compras_mes1[[#This Row],[NETO GRAVADO]]="","",compras_mes1[[#This Row],[NETO GRAVADO]]*0.21) | P35: =SUM(compras_mes1[[#This Row],[NETO GRAVADO]:[Otros / No Grav.]]) -> 0 | Q35: =IFERROR(IF(compras_mes1[[#This Row],[CUIT]]="","-",VLOOKUP(compras_mes1[[#This Row],[CUIT]],Lista_CUIT[#All],3,0)),"CUIT NO CARGADO") -> - | R35: =IFERROR(IF(compras_mes1[[#This Row],[CUIT]]="","-",VLOOKUP(compras_mes1[[#This Row],[CUIT]],Lista_CUIT[#All],4,0)),"CUIT NO CARGADO") -> -
G36: =IFERROR(IF(compras_mes1[[#This Row],[CUIT]]="","-",VLOOKUP(compras_mes1[[#This Row],[CUIT]],Lista_CUIT[#All],2,0)),"CUIT NO CARGADO") -> - | I36: =IF(compras_mes1[[#This Row],[NETO GRAVADO]]="","",compras_mes1[[#This Row],[NETO GRAVADO]]*0.21) | P36: =SUM(compras_mes1[[#This Row],[NETO GRAVADO]:[Otros / No Grav.]]) -> 0 | Q36: =IFERROR(IF(compras_mes1[[#This Row],[CUIT]]="","-",VLOOKUP(compras_mes1[[#This Row],[CUIT]],Lista_CUIT[#All],3,0)),"CUIT NO CARGADO") -> - | R36: =IFERROR(IF(compras_mes1[[#This Row],[CUIT]]="","-",VLOOKUP(compras_mes1[[#This Row],[CUIT]],Lista_CUIT[#All],4,0)),"CUIT NO CARGADO") -> -
G37: =IFERROR(IF(compras_mes1[[#This Row],[CUIT]]="","-",VLOOKUP(compras_mes1[[#This Row],[CUIT]],Lista_CUIT[#All],2,0)),"CUIT NO CARGADO") -> - | I37: =IF(compras_mes1[[#This Row],[NETO GRAVADO]]="","",compras_mes1[[#This Row],[NETO GRAVADO]]*0.21) | P37: =SUM(compras_mes1[[#This Row],[NETO GRAVADO]:[Otros / No Grav.]]) -> 0 | Q37: =IFERROR(IF(compras_mes1[[#This Row],[CUIT]]="","-",VLOOKUP(compras_mes1[[#This Row],[CUIT]],Lista_CUIT[#All],3,0)),"CUIT NO CARGADO") -> - | R37: =IFERROR(IF(compras_mes1[[#This Row],[CUIT]]="","-",VLOOKUP(compras_mes1[[#This Row],[CUIT]],Lista_CUIT[#All],4,0)),"CUIT NO CARGADO") -> -
G38: =IFERROR(IF(compras_mes1[[#This Row],[CUIT]]="","-",VLOOKUP(compras_mes1[[#This Row],[CUIT]],Lista_CUIT[#All],2,0)),"CUIT NO CARGADO") -> - | I38: =IF(compras_mes1[[#This Row],[NETO GRAVADO]]="","",compras_mes1[[#This Row],[NETO GRAVADO]]*0.21) | P38: =SUM(compras_mes1[[#This Row],[NETO GRAVADO]:[Otros / No Grav.]]) -> 0 | Q38: =IFERROR(IF(compras_mes1[[#This Row],[CUIT]]="","-",VLOOKUP(compras_mes1[[#This Row],[CUIT]],Lista_CUIT[#All],3,0)),"CUIT NO CARGADO") -> - | R38: =IFERROR(IF(compras_mes1[[#This Row],[CUIT]]="","-",VLOOKUP(compras_mes1[[#This Row],[CUIT]],Lista_CUIT[#All],4,0)),"CUIT NO CARGADO") -> -
G39: =IFERROR(IF(compras_mes1[[#This Row],[CUIT]]="","-",VLOOKUP(compras_mes1[[#This Row],[CUIT]],Lista_CUIT[#All],2,0)),"CUIT NO CARGADO") -> - | I39: =IF(compras_mes1[[#This Row],[NETO GRAVADO]]="","",compras_mes1[[#This Row],[NETO GRAVADO]]*0.21) | P39: =SUM(compras_mes1[[#This Row],[NETO GRAVADO]:[Otros / No Grav.]]) -> 0 | Q39: =IFERROR(IF(compras_mes1[[#This Row],[CUIT]]="","-",VLOOKUP(compras_mes1[[#This Row],[CUIT]],Lista_CUIT[#All],3,0)),"CUIT NO CARGADO") -> - | R39: =IFERROR(IF(compras_mes1[[#This Row],[CUIT]]="","-",VLOOKUP(compras_mes1[[#This Row],[CUIT]],Lista_CUIT[#All],4,0)),"CUIT NO CARGADO") -> -
G40: =IFERROR(IF(compras_mes1[[#This Row],[CUIT]]="","-",VLOOKUP(compras_mes1[[#This Row],[CUIT]],Lista_CUIT[#All],2,0)),"CUIT NO CARGADO") -> - | I40: =IF(compras_mes1[[#This Row],[NETO GRAVADO]]="","",compras_mes1[[#This Row],[NETO GRAVADO]]*0.21) | P40: =SUM(compras_mes1[[#This Row],[NETO GRAVADO]:[Otros / No Grav.]]) -> 0 | Q40: =IFERROR(IF(compras_mes1[[#This Row],[CUIT]]="","-",VLOOKUP(compras_mes1[[#This Row],[CUIT]],Lista_CUIT[#All],3,0)),"CUIT NO CARGADO") -> - | R40: =IFERROR(IF(compras_mes1[[#This Row],[CUIT]]="","-",VLOOKUP(compras_mes1[[#This Row],[CUIT]],Lista_CUIT[#All],4,0)),"CUIT NO CARGADO") -> -
G41: =IFERROR(IF(compras_mes1[[#This Row],[CUIT]]="","-",VLOOKUP(compras_mes1[[#This Row],[CUIT]],Lista_CUIT[#All],2,0)),"CUIT NO CARGADO") -> - | I41: =IF(compras_mes1[[#This Row],[NETO GRAVADO]]="","",compras_mes1[[#This Row],[NETO GRAVADO]]*0.21) | P41: =SUM(compras_mes1[[#This Row],[NETO GRAVADO]:[Otros / No Grav.]]) -> 0 | Q41: =IFERROR(IF(compras_mes1[[#This Row],[CUIT]]="","-",VLOOKUP(compras_mes1[[#This Row],[CUIT]],Lista_CUIT[#All],3,0)),"CUIT NO CARGADO") -> - | R41: =IFERROR(IF(compras_mes1[[#This Row],[CUIT]]="","-",VLOOKUP(compras_mes1[[#This Row],[CUIT]],Lista_CUIT[#All],4,0)),"CUIT NO CARGADO") -> -
G42: =IFERROR(IF(compras_mes1[[#This Row],[CUIT]]="","-",VLOOKUP(compras_mes1[[#This Row],[CUIT]],Lista_CUIT[#All],2,0)),"CUIT NO CARGADO") -> - | I42: =IF(compras_mes1[[#This Row],[NETO GRAVADO]]="","",compras_mes1[[#This Row],[NETO GRAVADO]]*0.21) | P42: =SUM(compras_mes1[[#This Row],[NETO GRAVADO]:[Otros / No Grav.]]) -> 0 | Q42: =IFERROR(IF(compras_mes1[[#This Row],[CUIT]]="","-",VLOOKUP(compras_mes1[[#This Row],[CUIT]],Lista_CUIT[#All],3,0)),"CUIT NO CARGADO") -> - | R42: =IFERROR(IF(compras_mes1[[#This Row],[CUIT]]="","-",VLOOKUP(compras_mes1[[#This Row],[CUIT]],Lista_CUIT[#All],4,0)),"CUIT NO CARGADO") -> -
G43: =IFERROR(IF(compras_mes1[[#This Row],[CUIT]]="","-",VLOOKUP(compras_mes1[[#This Row],[CUIT]],Lista_CUIT[#All],2,0)),"CUIT NO CARGADO") -> - | I43: =IF(compras_mes1[[#This Row],[NETO GRAVADO]]="","",compras_mes1[[#This Row],[NETO GRAVADO]]*0.21) | P43: =SUM(compras_mes1[[#This Row],[NETO GRAVADO]:[Otros / No Grav.]]) -> 0 | Q43: =IFERROR(IF(compras_mes1[[#This Row],[CUIT]]="","-",VLOOKUP(compras_mes1[[#This Row],[CUIT]],Lista_CUIT[#All],3,0)),"CUIT NO CARGADO") -> - | R43: =IFERROR(IF(compras_mes1[[#This Row],[CUIT]]="","-",VLOOKUP(compras_mes1[[#This Row],[CUIT]],Lista_CUIT[#All],4,0)),"CUIT NO CARGADO") -> -
G44: =IFERROR(IF(compras_mes1[[#This Row],[CUIT]]="","-",VLOOKUP(compras_mes1[[#This Row],[CUIT]],Lista_CUIT[#All],2,0)),"CUIT NO CARGADO") -> - | I44: =IF(compras_mes1[[#This Row],[NETO GRAVADO]]="","",compras_mes1[[#This Row],[NETO GRAVADO]]*0.21) | P44: =SUM(compras_mes1[[#This Row],[NETO GRAVADO]:[Otros / No Grav.]]) -> 0 | Q44: =IFERROR(IF(compras_mes1[[#This Row],[CUIT]]="","-",VLOOKUP(compras_mes1[[#This Row],[CUIT]],Lista_CUIT[#All],3,0)),"CUIT NO CARGADO") -> - | R44: =IFERROR(IF(compras_mes1[[#This Row],[CUIT]]="","-",VLOOKUP(compras_mes1[[#This Row],[CUIT]],Lista_CUIT[#All],4,0)),"CUIT NO CARGADO") -> -
B45: Total | H45: =SUBTOTAL(109,compras_mes1[NETO GRAVADO]) -> 4830419.7 | I45: =SUBTOTAL(109,compras_mes1[IVA 21 %]) -> 1014388.1 | J45: =SUBTOTAL(109,compras_mes1[IVA 27%]) -> 0 | K45: =SUBTOTAL(109,compras_mes1[IVA 10,5%]) -> 0 | L45: =SUBTOTAL(109,compras_mes1[PERC. IVA]) -> 0 | M45: =SUBTOTAL(109,compras_mes1[PERC IIBB BS AS]) -> 0 | N45: =SUBTOTAL(109,compras_mes1[PERC. IIBB CABA]) -> 66100.41 | O45: =SUBTOTAL(109,compras_mes1[Otros / No Grav.]) -> 132205.19 | P45: =SUBTOTAL(109,compras_mes1[TOTAL]) -> 6043113.4
D50: LIQUIDACION EXTRACTOS BANCARIOS-TARJETAS
D51: FECHA | E51: NRO CPTE | F51: BANCO | G51: NETO | H51: IVA 21% | I51: IVA 10,5% | J51: RET IIBB CABA | K51: PERC IVA | L51: PERC IIBB
H52: =extracto_banco_mes1[[#This Row],[NETO]]*0.21 -> 0 | N52: =compras_mes1[[#Totals],[IVA 21 %]]+extracto_banco_mes1[[#Totals],[IVA 21%]] -> 1014388.1
H53: =extracto_banco_mes1[[#This Row],[NETO]]*0.21 -> 0
H54: =extracto_banco_mes1[[#This Row],[NETO]]*0.21 -> 0
D55: Total | G55: =SUBTOTAL(109,extracto_banco_mes1[NETO]) -> 0 | H55: =SUBTOTAL(109,extracto_banco_mes1[IVA 21%]) -> 0 | I55: =SUBTOTAL(109,extracto_banco_mes1[IVA 10,5%]) -> 0 | J55: =SUBTOTAL(109,extracto_banco_mes1[RET IIBB CABA]) -> 0 | K55: =SUBTOTAL(109,extracto_banco_mes1[PERC IVA]) -> 0 | L55: =SUBTOTAL(109,extracto_banco_mes1[PERC IIBB]) -> 0
D59: FACTURAS C
D60: FECHA | E60: PTO VTA | F60: FC Nº | G60: CUIT | H60: RAZON SOCIAL | I60: TOTAL | J60: TIPO DE GASTO | K60: Provincia
D61: 02/01/2026 | E61: 2 | F61: 158 | G61: 27341104845 | H61: =IFERROR(IF(factura_c_mes1[[#This Row],[CUIT]]="","-",VLOOKUP(factura_c_mes1[[#This Row],[CUIT]],Lista_CUIT[#All],2,0)),"CUIT NO CARGADO") -> BOSSI MARIA PAULA | I61: 310600 | J61: =IFERROR(IF(factura_c_mes1[[#This Row],[CUIT]]="","-",VLOOKUP(factura_c_mes1[[#This Row],[CUIT]],Lista_CUIT[#All],3,0)),"CUIT NO CARGADO") -> 0 | K61: =IFERROR(IF(factura_c_mes1[[#This Row],[CUIT]]="","-",VLOOKUP(factura_c_mes1[[#This Row],[CUIT]],Lista_CUIT[#All],4,0)),"CUIT NO CARGADO") -> 0
D62: 05/01/2026 | E62: 2 | F62: 1102 | G62: 20400104094 | H62: =IFERROR(IF(factura_c_mes1[[#This Row],[CUIT]]="","-",VLOOKUP(factura_c_mes1[[#This Row],[CUIT]],Lista_CUIT[#All],2,0)),"CUIT NO CARGADO") -> BOTINDARI FEDERICO DANIEL | I62: 300000 | J62: =IFERROR(IF(factura_c_mes1[[#This Row],[CUIT]]="","-",VLOOKUP(factura_c_mes1[[#This Row],[CUIT]],Lista_CUIT[#All],3,0)),"CUIT NO CARGADO") -> HONORARIOS CONTABLE | K62: =IFERROR(IF(factura_c_mes1[[#This Row],[CUIT]]="","-",VLOOKUP(factura_c_mes1[[#This Row],[CUIT]],Lista_CUIT[#All],4,0)),"CUIT NO CARGADO") -> 0
D63: 06/01/2026 | E63: 1 | F63: 2 | G63: 27403975821 | H63: =IFERROR(IF(factura_c_mes1[[#This Row],[CUIT]]="","-",VLOOKUP(factura_c_mes1[[#This Row],[CUIT]],Lista_CUIT[#All],2,0)),"CUIT NO CARGADO") -> BARROSO VALENTINA | I63: 537085 | J63: =IFERROR(IF(factura_c_mes1[[#This Row],[CUIT]]="","-",VLOOKUP(factura_c_mes1[[#This Row],[CUIT]],Lista_CUIT[#All],3,0)),"CUIT NO CARGADO") -> 0 | K63: =IFERROR(IF(factura_c_mes1[[#This Row],[CUIT]]="","-",VLOOKUP(factura_c_mes1[[#This Row],[CUIT]],Lista_CUIT[#All],4,0)),"CUIT NO CARGADO") -> 0
D64: 12/01/2026 | E64: 51 | F64: 191 | G64: 20300985158 | H64: =IFERROR(IF(factura_c_mes1[[#This Row],[CUIT]]="","-",VLOOKUP(factura_c_mes1[[#This Row],[CUIT]],Lista_CUIT[#All],2,0)),"CUIT NO CARGADO") -> GONZALEZ NESTOR RICARDO | I64: 900000 | J64: =IFERROR(IF(factura_c_mes1[[#This Row],[CUIT]]="","-",VLOOKUP(factura_c_mes1[[#This Row],[CUIT]],Lista_CUIT[#All],3,0)),"CUIT NO CARGADO") -> 0 | K64: =IFERROR(IF(factura_c_mes1[[#This Row],[CUIT]]="","-",VLOOKUP(factura_c_mes1[[#This Row],[CUIT]],Lista_CUIT[#All],4,0)),"CUIT NO CARGADO") -> 0
D65: 12/01/2026 | E65: 1 | F65: 327 | G65: 27386311000 | H65: =IFERROR(IF(factura_c_mes1[[#This Row],[CUIT]]="","-",VLOOKUP(factura_c_mes1[[#This Row],[CUIT]],Lista_CUIT[#All],2,0)),"CUIT NO CARGADO") -> OPANASIUK MACARENA ANTONELLA | I65: 850000 | J65: =IFERROR(IF(factura_c_mes1[[#This Row],[CUIT]]="","-",VLOOKUP(factura_c_mes1[[#This Row],[CUIT]],Lista_CUIT[#All],3,0)),"CUIT NO CARGADO") -> 0 | K65: =IFERROR(IF(factura_c_mes1[[#This Row],[CUIT]]="","-",VLOOKUP(factura_c_mes1[[#This Row],[CUIT]],Lista_CUIT[#All],4,0)),"CUIT NO CARGADO") -> 0
D66: 16/01/2026 | E66: 2 | F66: 62 | G66: 23380288079 | H66: =IFERROR(IF(factura_c_mes1[[#This Row],[CUIT]]="","-",VLOOKUP(factura_c_mes1[[#This Row],[CUIT]],Lista_CUIT[#All],2,0)),"CUIT NO CARGADO") -> CASTROMAN AGUSTIN | I66: 538500 | J66: =IFERROR(IF(factura_c_mes1[[#This Row],[CUIT]]="","-",VLOOKUP(factura_c_mes1[[#This Row],[CUIT]],Lista_CUIT[#All],3,0)),"CUIT NO CARGADO") -> 0 | K66: =IFERROR(IF(factura_c_mes1[[#This Row],[CUIT]]="","-",VLOOKUP(factura_c_mes1[[#This Row],[CUIT]],Lista_CUIT[#All],4,0)),"CUIT NO CARGADO") -> 0
H67: =IFERROR(IF(factura_c_mes1[[#This Row],[CUIT]]="","-",VLOOKUP(factura_c_mes1[[#This Row],[CUIT]],Lista_CUIT[#All],2,0)),"CUIT NO CARGADO") -> - | J67: =IFERROR(IF(factura_c_mes1[[#This Row],[CUIT]]="","-",VLOOKUP(factura_c_mes1[[#This Row],[CUIT]],Lista_CUIT[#All],3,0)),"CUIT NO CARGADO") -> - | K67: =IFERROR(IF(factura_c_mes1[[#This Row],[CUIT]]="","-",VLOOKUP(factura_c_mes1[[#This Row],[CUIT]],Lista_CUIT[#All],4,0)),"CUIT NO CARGADO") -> -
H68: =IFERROR(IF(factura_c_mes1[[#This Row],[CUIT]]="","-",VLOOKUP(factura_c_mes1[[#This Row],[CUIT]],Lista_CUIT[#All],2,0)),"CUIT NO CARGADO") -> - | J68: =IFERROR(IF(factura_c_mes1[[#This Row],[CUIT]]="","-",VLOOKUP(factura_c_mes1[[#This Row],[CUIT]],Lista_CUIT[#All],3,0)),"CUIT NO CARGADO") -> - | K68: =IFERROR(IF(factura_c_mes1[[#This Row],[CUIT]]="","-",VLOOKUP(factura_c_mes1[[#This Row],[CUIT]],Lista_CUIT[#All],4,0)),"CUIT NO CARGADO") -> -
H69: =IFERROR(IF(factura_c_mes1[[#This Row],[CUIT]]="","-",VLOOKUP(factura_c_mes1[[#This Row],[CUIT]],Lista_CUIT[#All],2,0)),"CUIT NO CARGADO") -> - | J69: =IFERROR(IF(factura_c_mes1[[#This Row],[CUIT]]="","-",VLOOKUP(factura_c_mes1[[#This Row],[CUIT]],Lista_CUIT[#All],3,0)),"CUIT NO CARGADO") -> - | K69: =IFERROR(IF(factura_c_mes1[[#This Row],[CUIT]]="","-",VLOOKUP(factura_c_mes1[[#This Row],[CUIT]],Lista_CUIT[#All],4,0)),"CUIT NO CARGADO") -> -
H70: =IFERROR(IF(factura_c_mes1[[#This Row],[CUIT]]="","-",VLOOKUP(factura_c_mes1[[#This Row],[CUIT]],Lista_CUIT[#All],2,0)),"CUIT NO CARGADO") -> - | J70: =IFERROR(IF(factura_c_mes1[[#This Row],[CUIT]]="","-",VLOOKUP(factura_c_mes1[[#This Row],[CUIT]],Lista_CUIT[#All],3,0)),"CUIT NO CARGADO") -> - | K70: =IFERROR(IF(factura_c_mes1[[#This Row],[CUIT]]="","-",VLOOKUP(factura_c_mes1[[#This Row],[CUIT]],Lista_CUIT[#All],4,0)),"CUIT NO CARGADO") -> -
H71: =IFERROR(IF(factura_c_mes1[[#This Row],[CUIT]]="","-",VLOOKUP(factura_c_mes1[[#This Row],[CUIT]],Lista_CUIT[#All],2,0)),"CUIT NO CARGADO") -> - | J71: =IFERROR(IF(factura_c_mes1[[#This Row],[CUIT]]="","-",VLOOKUP(factura_c_mes1[[#This Row],[CUIT]],Lista_CUIT[#All],3,0)),"CUIT NO CARGADO") -> - | K71: =IFERROR(IF(factura_c_mes1[[#This Row],[CUIT]]="","-",VLOOKUP(factura_c_mes1[[#This Row],[CUIT]],Lista_CUIT[#All],4,0)),"CUIT NO CARGADO") -> -
H72: =IFERROR(IF(factura_c_mes1[[#This Row],[CUIT]]="","-",VLOOKUP(factura_c_mes1[[#This Row],[CUIT]],Lista_CUIT[#All],2,0)),"CUIT NO CARGADO") -> - | J72: =IFERROR(IF(factura_c_mes1[[#This Row],[CUIT]]="","-",VLOOKUP(factura_c_mes1[[#This Row],[CUIT]],Lista_CUIT[#All],3,0)),"CUIT NO CARGADO") -> - | K72: =IFERROR(IF(factura_c_mes1[[#This Row],[CUIT]]="","-",VLOOKUP(factura_c_mes1[[#This Row],[CUIT]],Lista_CUIT[#All],4,0)),"CUIT NO CARGADO") -> -
H73: =IFERROR(IF(factura_c_mes1[[#This Row],[CUIT]]="","-",VLOOKUP(factura_c_mes1[[#This Row],[CUIT]],Lista_CUIT[#All],2,0)),"CUIT NO CARGADO") -> - | J73: =IFERROR(IF(factura_c_mes1[[#This Row],[CUIT]]="","-",VLOOKUP(factura_c_mes1[[#This Row],[CUIT]],Lista_CUIT[#All],3,0)),"CUIT NO CARGADO") -> - | K73: =IFERROR(IF(factura_c_mes1[[#This Row],[CUIT]]="","-",VLOOKUP(factura_c_mes1[[#This Row],[CUIT]],Lista_CUIT[#All],4,0)),"CUIT NO CARGADO") -> -
D74: Total | I74: =SUBTOTAL(109,factura_c_mes1[TOTAL]) -> 3436185
B78: LIBRO IVA VENTAS | K78: =N1 -> 46023
B80: VENTAS "A"
B81: FECHA | C81: TIPO | D81: PTO VENTA | E81: Nº FACTURA | F81: CUIT | G81: RAZON SOCIAL | H81: IMPORTE NETO | I81: IVA 21% | J81: IVA 10,5% | K81: EXENTO | L81: TOTAL | M81: Provincia
B82: 02/01/2026 | C82: 1 | D82: 1 | E82: 630 | F82: 30717465101 | G82: =IFERROR(IF(venta_a_mes1[[#This Row],[CUIT]]="","-",VLOOKUP(venta_a_mes1[[#This Row],[CUIT]],Lista_CUIT[#All],2,0)),"CUIT NO CARGADO") -> EMPRENDIMIENTOS SHOPGLASS S. R. L. | H82: 147107.43 | I82: =venta_a_mes1[[#This Row],[IMPORTE NETO]]*0.21 -> 30892.56 | L82: =SUM(venta_a_mes1[[#This Row],[IMPORTE NETO]:[EXENTO]]) -> 177999.99
B83: 02/01/2026 | C83: 1 | D83: 1 | E83: 617 | F83: 30715751557 | G83: =IFERROR(IF(venta_a_mes1[[#This Row],[CUIT]]="","-",VLOOKUP(venta_a_mes1[[#This Row],[CUIT]],Lista_CUIT[#All],2,0)),"CUIT NO CARGADO") -> TIXIT SRL | H83: 590909.1 | I83: =venta_a_mes1[[#This Row],[IMPORTE NETO]]*0.21 -> 124090.91 | L83: =SUM(venta_a_mes1[[#This Row],[IMPORTE NETO]:[EXENTO]]) -> 715000.01
B84: 02/01/2026 | C84: 1 | D84: 1 | E84: 618 | F84: 30714375241 | G84: =IFERROR(IF(venta_a_mes1[[#This Row],[CUIT]]="","-",VLOOKUP(venta_a_mes1[[#This Row],[CUIT]],Lista_CUIT[#All],2,0)),"CUIT NO CARGADO") -> POWER-RECORDS S.A | H84: 590909.1 | I84: =venta_a_mes1[[#This Row],[IMPORTE NETO]]*0.21 -> 124090.91 | L84: =SUM(venta_a_mes1[[#This Row],[IMPORTE NETO]:[EXENTO]]) -> 715000.01
B85: 02/01/2026 | C85: 1 | D85: 1 | E85: 631 | F85: 30709058807 | G85: =IFERROR(IF(venta_a_mes1[[#This Row],[CUIT]]="","-",VLOOKUP(venta_a_mes1[[#This Row],[CUIT]],Lista_CUIT[#All],2,0)),"CUIT NO CARGADO") -> LA VALENZIANA S.R.L. | H85: 4863163.5 | I85: =venta_a_mes1[[#This Row],[IMPORTE NETO]]*0.21 -> 1021264.3 | L85: =SUM(venta_a_mes1[[#This Row],[IMPORTE NETO]:[EXENTO]]) -> 5884427.9
B86: 02/01/2026 | C86: 1 | D86: 1 | E86: 619 | F86: 30718553357 | G86: =IFERROR(IF(venta_a_mes1[[#This Row],[CUIT]]="","-",VLOOKUP(venta_a_mes1[[#This Row],[CUIT]],Lista_CUIT[#All],2,0)),"CUIT NO CARGADO") -> EMIGRA CON TU MASCOTA S.R.L. | H86: 590909.1 | I86: =venta_a_mes1[[#This Row],[IMPORTE NETO]]*0.21 -> 124090.91 | L86: =SUM(venta_a_mes1[[#This Row],[IMPORTE NETO]:[EXENTO]]) -> 715000.01
B87: 02/01/2026 | C87: 1 | D87: 1 | E87: 632 | F87: 30714864803 | G87: =IFERROR(IF(venta_a_mes1[[#This Row],[CUIT]]="","-",VLOOKUP(venta_a_mes1[[#This Row],[CUIT]],Lista_CUIT[#All],2,0)),"CUIT NO CARGADO") -> DIAZ Y GIUSEPPETTI S. R. L. | H87: 283347.57 | I87: =venta_a_mes1[[#This Row],[IMPORTE NETO]]*0.21 -> 59502.99 | L87: =SUM(venta_a_mes1[[#This Row],[IMPORTE NETO]:[EXENTO]]) -> 342850.56
B88: 02/01/2026 | C88: 1 | D88: 1 | E88: 620 | F88: 30714236888 | G88: =IFERROR(IF(venta_a_mes1[[#This Row],[CUIT]]="","-",VLOOKUP(venta_a_mes1[[#This Row],[CUIT]],Lista_CUIT[#All],2,0)),"CUIT NO CARGADO") -> NANOTEC S.R.L. | H88: 590909.1 | I88: =venta_a_mes1[[#This Row],[IMPORTE NETO]]*0.21 -> 124090.91 | L88: =SUM(venta_a_mes1[[#This Row],[IMPORTE NETO]:[EXENTO]]) -> 715000.01
B89: 02/01/2026 | C89: 1 | D89: 1 | E89: 621 | F89: 30708404485 | G89: =IFERROR(IF(venta_a_mes1[[#This Row],[CUIT]]="","-",VLOOKUP(venta_a_mes1[[#This Row],[CUIT]],Lista_CUIT[#All],2,0)),"CUIT NO CARGADO") -> SOLDARGEN S.A. | H89: 590909.1 | I89: =venta_a_mes1[[#This Row],[IMPORTE NETO]]*0.21 -> 124090.91 | L89: =SUM(venta_a_mes1[[#This Row],[IMPORTE NETO]:[EXENTO]]) -> 715000.01
B90: 02/01/2026 | C90: 1 | D90: 1 | E90: 622 | F90: 33714651779 | G90: =IFERROR(IF(venta_a_mes1[[#This Row],[CUIT]]="","-",VLOOKUP(venta_a_mes1[[#This Row],[CUIT]],Lista_CUIT[#All],2,0)),"CUIT NO CARGADO") -> COOPERATIVA DE TRABAJO MADYGRAF LTDA | H90: 660000 | I90: =venta_a_mes1[[#This Row],[IMPORTE NETO]]*0.21 -> 138600 | L90: =SUM(venta_a_mes1[[#This Row],[IMPORTE NETO]:[EXENTO]]) -> 798600
B91: 02/01/2026 | C91: 1 | D91: 1 | E91: 623 | F91: 30708604255 | G91: =IFERROR(IF(venta_a_mes1[[#This Row],[CUIT]]="","-",VLOOKUP(venta_a_mes1[[#This Row],[CUIT]],Lista_CUIT[#All],2,0)),"CUIT NO CARGADO") -> NAR TECHNOLOGIES S.R.L. | H91: 545454.57 | I91: =venta_a_mes1[[#This Row],[IMPORTE NETO]]*0.21 -> 114545.46 | L91: =SUM(venta_a_mes1[[#This Row],[IMPORTE NETO]:[EXENTO]]) -> 660000.03
B92: 02/01/2026 | C92: 1 | D92: 1 | E92: 624 | F92: 24368969350 | G92: =IFERROR(IF(venta_a_mes1[[#This Row],[CUIT]]="","-",VLOOKUP(venta_a_mes1[[#This Row],[CUIT]],Lista_CUIT[#All],2,0)),"CUIT NO CARGADO") -> MARANO CORVALAN MARTIN MARIANO | H92: 295454.57 | I92: =venta_a_mes1[[#This Row],[IMPORTE NETO]]*0.21 -> 62045.46 | L92: =SUM(venta_a_mes1[[#This Row],[IMPORTE NETO]:[EXENTO]]) -> 357500.03
B93: 02/01/2026 | C93: 1 | D93: 1 | E93: 625 | F93: 30688955749 | G93: =IFERROR(IF(venta_a_mes1[[#This Row],[CUIT]]="","-",VLOOKUP(venta_a_mes1[[#This Row],[CUIT]],Lista_CUIT[#All],2,0)),"CUIT NO CARGADO") -> LISERAR S A | H93: 196694.24 | I93: =venta_a_mes1[[#This Row],[IMPORTE NETO]]*0.21 -> 41305.79 | L93: =SUM(venta_a_mes1[[#This Row],[IMPORTE NETO]:[EXENTO]]) -> 238000.03
... B98: 30/01/2026 | C98: 3 | D98: 1 | E98: 50 | F98: 30708604255 | G98: =IFERROR(IF(venta_a_mes1[[#This Row],[CUIT]]="","-",VLOOKUP(venta_a_mes1[[#This Row],[CUIT]],Lista_CUIT[#All],2,0)),"CUIT NO CARGADO") -> NAR TECHNOLOGIES S.R.L. | H98: -545454.57 | I98: =venta_a_mes1[[#This Row],[IMPORTE NETO]]*0.21 -> -114545.46 | L98: =SUM(venta_a_mes1[[#This Row],[IMPORTE NETO]:[EXENTO]]) -> -660000.03
G99: =IFERROR(IF(venta_a_mes1[[#This Row],[CUIT]]="","-",VLOOKUP(venta_a_mes1[[#This Row],[CUIT]],Lista_CUIT[#All],2,0)),"CUIT NO CARGADO") -> - | I99: =venta_a_mes1[[#This Row],[IMPORTE NETO]]*0.21 -> 0 | L99: =SUM(venta_a_mes1[[#This Row],[IMPORTE NETO]:[EXENTO]]) -> 0
G100: =IFERROR(IF(venta_a_mes1[[#This Row],[CUIT]]="","-",VLOOKUP(venta_a_mes1[[#This Row],[CUIT]],Lista_CUIT[#All],2,0)),"CUIT NO CARGADO") -> - | I100: =venta_a_mes1[[#This Row],[IMPORTE NETO]]*0.21 -> 0 | L100: =SUM(venta_a_mes1[[#This Row],[IMPORTE NETO]:[EXENTO]]) -> 0
G101: =IFERROR(IF(venta_a_mes1[[#This Row],[CUIT]]="","-",VLOOKUP(venta_a_mes1[[#This Row],[CUIT]],Lista_CUIT[#All],2,0)),"CUIT NO CARGADO") -> - | I101: =venta_a_mes1[[#This Row],[IMPORTE NETO]]*0.21 -> 0 | L101: =SUM(venta_a_mes1[[#This Row],[IMPORTE NETO]:[EXENTO]]) -> 0
G102: =IFERROR(IF(venta_a_mes1[[#This Row],[CUIT]]="","-",VLOOKUP(venta_a_mes1[[#This Row],[CUIT]],Lista_CUIT[#All],2,0)),"CUIT NO CARGADO") -> - | I102: =venta_a_mes1[[#This Row],[IMPORTE NETO]]*0.21 -> 0 | L102: =SUM(venta_a_mes1[[#This Row],[IMPORTE NETO]:[EXENTO]]) -> 0
G103: =IFERROR(IF(venta_a_mes1[[#This Row],[CUIT]]="","-",VLOOKUP(venta_a_mes1[[#This Row],[CUIT]],Lista_CUIT[#All],2,0)),"CUIT NO CARGADO") -> - | I103: =venta_a_mes1[[#This Row],[IMPORTE NETO]]*0.21 -> 0 | L103: =SUM(venta_a_mes1[[#This Row],[IMPORTE NETO]:[EXENTO]]) -> 0
G104: =IFERROR(IF(venta_a_mes1[[#This Row],[CUIT]]="","-",VLOOKUP(venta_a_mes1[[#This Row],[CUIT]],Lista_CUIT[#All],2,0)),"CUIT NO CARGADO") -> - | I104: =venta_a_mes1[[#This Row],[IMPORTE NETO]]*0.21 -> 0 | L104: =SUM(venta_a_mes1[[#This Row],[IMPORTE NETO]:[EXENTO]]) -> 0
G105: =IFERROR(IF(venta_a_mes1[[#This Row],[CUIT]]="","-",VLOOKUP(venta_a_mes1[[#This Row],[CUIT]],Lista_CUIT[#All],2,0)),"CUIT NO CARGADO") -> - | I105: =venta_a_mes1[[#This Row],[IMPORTE NETO]]*0.21 -> 0 | L105: =SUM(venta_a_mes1[[#This Row],[IMPORTE NETO]:[EXENTO]]) -> 0
G106: =IFERROR(IF(venta_a_mes1[[#This Row],[CUIT]]="","-",VLOOKUP(venta_a_mes1[[#This Row],[CUIT]],Lista_CUIT[#All],2,0)),"CUIT NO CARGADO") -> - | I106: =venta_a_mes1[[#This Row],[IMPORTE NETO]]*0.21 -> 0 | L106: =SUM(venta_a_mes1[[#This Row],[IMPORTE NETO]:[EXENTO]]) -> 0
G107: =IFERROR(IF(venta_a_mes1[[#This Row],[CUIT]]="","-",VLOOKUP(venta_a_mes1[[#This Row],[CUIT]],Lista_CUIT[#All],2,0)),"CUIT NO CARGADO") -> - | I107: =venta_a_mes1[[#This Row],[IMPORTE NETO]]*0.21 -> 0 | L107: =SUM(venta_a_mes1[[#This Row],[IMPORTE NETO]:[EXENTO]]) -> 0
G108: =IFERROR(IF(venta_a_mes1[[#This Row],[CUIT]]="","-",VLOOKUP(venta_a_mes1[[#This Row],[CUIT]],Lista_CUIT[#All],2,0)),"CUIT NO CARGADO") -> - | I108: =venta_a_mes1[[#This Row],[IMPORTE NETO]]*0.21 -> 0 | L108: =SUM(venta_a_mes1[[#This Row],[IMPORTE NETO]:[EXENTO]]) -> 0
G109: =IFERROR(IF(venta_a_mes1[[#This Row],[CUIT]]="","-",VLOOKUP(venta_a_mes1[[#This Row],[CUIT]],Lista_CUIT[#All],2,0)),"CUIT NO CARGADO") -> - | I109: =venta_a_mes1[[#This Row],[IMPORTE NETO]]*0.21 -> 0 | L109: =SUM(venta_a_mes1[[#This Row],[IMPORTE NETO]:[EXENTO]]) -> 0
B110: Total | H110: =SUBTOTAL(109,venta_a_mes1[IMPORTE NETO]) -> 10038329 | I110: =SUBTOTAL(109,venta_a_mes1[IVA 21%]) -> 2108049.2 | J110: =SUBTOTAL(109,venta_a_mes1[IVA 10,5%]) -> 0 | K110: =SUBTOTAL(109,venta_a_mes1[EXENTO]) -> 0 | L110: =SUBTOTAL(109,venta_a_mes1[TOTAL]) -> 12146379 | M110: =SUBTOTAL(103,venta_a_mes1[Provincia]) -> 0
B112: VENTAS "B"
B113: FECHA | C113: TIPO | D113: PTO VENTA | E113: Nº FACTURA | F113: CUIT | G113: RAZON SOCIAL | H113: IMPORTE NETO | I113: IVA 21% | J113: IVA 10,5% | K113: EXENTO | L113: TOTAL | M113: Provincia
G114: =IFERROR(IF(ventas_b_mes1[[#This Row],[CUIT]]="","-",VLOOKUP(ventas_b_mes1[[#This Row],[CUIT]],Lista_CUIT[#All],2,0)),"CUIT NO CARGADO") -> - | I114: =ventas_b_mes1[[#This Row],[IMPORTE NETO]]*0.21 -> 0
G115: =IFERROR(IF(ventas_b_mes1[[#This Row],[CUIT]]="","-",VLOOKUP(ventas_b_mes1[[#This Row],[CUIT]],Lista_CUIT[#All],2,0)),"CUIT NO CARGADO") -> - | I115: =ventas_b_mes1[[#This Row],[IMPORTE NETO]]*0.21 -> 0
G116: =IFERROR(IF(ventas_b_mes1[[#This Row],[CUIT]]="","-",VLOOKUP(ventas_b_mes1[[#This Row],[CUIT]],Lista_CUIT[#All],2,0)),"CUIT NO CARGADO") -> - | I116: =ventas_b_mes1[[#This Row],[IMPORTE NETO]]*0.21 -> 0
G117: =IFERROR(IF(ventas_b_mes1[[#This Row],[CUIT]]="","-",VLOOKUP(ventas_b_mes1[[#This Row],[CUIT]],Lista_CUIT[#All],2,0)),"CUIT NO CARGADO") -> - | I117: =ventas_b_mes1[[#This Row],[IMPORTE NETO]]*0.21 -> 0
G118: =IFERROR(IF(ventas_b_mes1[[#This Row],[CUIT]]="","-",VLOOKUP(ventas_b_mes1[[#This Row],[CUIT]],Lista_CUIT[#All],2,0)),"CUIT NO CARGADO") -> - | H118: =ventas_b_mes1[[#This Row],[TOTAL]]/1.21 -> 0 | I118: =ventas_b_mes1[[#This Row],[IMPORTE NETO]]*0.21 -> 0
H119: =ventas_b_mes1[[#This Row],[TOTAL]]/1.21 -> 0 | I119: =ventas_b_mes1[[#This Row],[IMPORTE NETO]]*0.21 -> 0
B120: Total | H120: =SUBTOTAL(109,ventas_b_mes1[IMPORTE NETO]) -> 0 | I120: =SUBTOTAL(109,ventas_b_mes1[IVA 21%]) -> 0 | J120: =SUBTOTAL(109,ventas_b_mes1[IVA 10,5%]) -> 0 | K120: =SUBTOTAL(109,ventas_b_mes1[EXENTO]) -> 0 | L120: =SUBTOTAL(109,ventas_b_mes1[TOTAL]) -> 0 | M120: =SUBTOTAL(103,ventas_b_mes1[Provincia]) -> 0
...

Sheet Feb-26
B1: LIBRO IVA COMPRAS | G1: ='Ene-26'!G1:M1 -> RABLEB SRL | N1: =EDATE('Ene-26'!N1,1) -> 46054
B3: TOTAL COMPRAS | G3: TOTAL CREDITO FISCAL | J3: TOTAL VENTAS NETAS | M3: TOTAL DEBITO FISCAL | P3: RESULTADO
B4: =SUM(compras_mes2[[#Totals],[NETO GRAVADO]])+extracto_banco_mes2[[#Totals],[NETO]] -> 6207525.6 | G4: =compras_mes2[[#Totals],[IVA 21 %]]+compras_mes2[[#Totals],[IVA 27%]]+compras_mes2[[#Totals],[IVA 10,5%]]+extracto_banco_mes2[[#Totals],[IVA 21%]]+extracto_banco_mes2[[#Totals],[IVA 10,5%]] -> 1303580.4 | J4: =venta_a_mes2[[#Totals],[IMPORTE NETO]]+ventas_b_mes2[[#Totals],[IMPORTE NETO]] -> 9787785.5 | M4: =venta_a_mes2[[#Totals],[IVA 21%]]+venta_a_mes2[[#Totals],[IVA 10,5%]]+ventas_b_mes2[[#Totals],[IVA 21%]]+ventas_b_mes2[[#Totals],[IVA 10,5%]] -> 2055435 | P4: =G4-M4 -> -751854.58
B8: FECHA | C8: TIPO | D8: PTO VTA | E8: NRO. CPTE | F8: CUIT | G8: RAZON SOCIAL | H8: NETO GRAVADO | I8: IVA 21 % | J8: IVA 27% | K8: IVA 10,5% | L8: PERC. IVA | M8: PERC IIBB BS AS | N8: PERC. IIBB CABA | O8: Otros / No Grav. | P8: TOTAL | Q8: Tipo de Gasto | R8: Provincia
B9: 01/02/2026 | C9: 1 | D9: 2 | E9: 1690412 | F9: 30710173652 | G9: =IFERROR(IF(compras_mes2[[#This Row],[CUIT]]="","-",VLOOKUP(compras_mes2[[#This Row],[CUIT]],Lista_CUIT[#All],2,0)),"CUIT NO CARGADO") -> DATTATEC.COM S.R.L. | H9: 33057.85 | I9: =compras_mes2[[#This Row],[NETO GRAVADO]]*0.21 -> 6942.1485 | P9: =SUM(compras_mes2[[#This Row],[NETO GRAVADO]:[Otros / No Grav.]]) -> 39999.999 | Q9: =IFERROR(IF(compras_mes2[[#This Row],[CUIT]]="","-",VLOOKUP(compras_mes2[[#This Row],[CUIT]],Lista_CUIT[#All],3,0)),"CUIT NO CARGADO") -> 0 | R9: =IFERROR(IF(compras_mes2[[#This Row],[CUIT]]="","-",VLOOKUP(compras_mes2[[#This Row],[CUIT]],Lista_CUIT[#All],4,0)),"CUIT NO CARGADO") -> 0
B10: 02/02/2026 | C10: 1 | D10: 2 | E10: 1744 | F10: 30718631730 | G10: =IFERROR(IF(compras_mes2[[#This Row],[CUIT]]="","-",VLOOKUP(compras_mes2[[#This Row],[CUIT]],Lista_CUIT[#All],2,0)),"CUIT NO CARGADO") -> SIMZ S. R. L. | H10: 142884 | I10: =compras_mes2[[#This Row],[NETO GRAVADO]]*0.21 -> 30005.64 | P10: =SUM(compras_mes2[[#This Row],[NETO GRAVADO]:[Otros / No Grav.]]) -> 172889.64 | Q10: =IFERROR(IF(compras_mes2[[#This Row],[CUIT]]="","-",VLOOKUP(compras_mes2[[#This Row],[CUIT]],Lista_CUIT[#All],3,0)),"CUIT NO CARGADO") -> 0 | R10: =IFERROR(IF(compras_mes2[[#This Row],[CUIT]]="","-",VLOOKUP(compras_mes2[[#This Row],[CUIT]],Lista_CUIT[#All],4,0)),"CUIT NO CARGADO") -> 0
B11: 25/02/2026 | C11: 1 | D11: 2 | E11: 1709683 | F11: 30710173652 | G11: =IFERROR(IF(compras_mes2[[#This Row],[CUIT]]="","-",VLOOKUP(compras_mes2[[#This Row],[CUIT]],Lista_CUIT[#All],2,0)),"CUIT NO CARGADO") -> DATTATEC.COM S.R.L. | H11: 33057.85 | I11: =compras_mes2[[#This Row],[NETO GRAVADO]]*0.21 -> 6942.1485 | P11: =SUM(compras_mes2[[#This Row],[NETO GRAVADO]:[Otros / No Grav.]]) -> 39999.999 | Q11: =IFERROR(IF(compras_mes2[[#This Row],[CUIT]]="","-",VLOOKUP(compras_mes2[[#This Row],[CUIT]],Lista_CUIT[#All],3,0)),"CUIT NO CARGADO") -> 0 | R11: =IFERROR(IF(compras_mes2[[#This Row],[CUIT]]="","-",VLOOKUP(compras_mes2[[#This Row],[CUIT]],Lista_CUIT[#All],4,0)),"CUIT NO CARGADO") -> 0
B12: 28/02/2026 | C12: 1 | D12: 11 | E12: 1283132 | F12: 33709585229 | G12: =IFERROR(IF(compras_mes2[[#This Row],[CUIT]]="","-",VLOOKUP(compras_mes2[[#This Row],[CUIT]],Lista_CUIT[#All],2,0)),"CUIT NO CARGADO") -> GOOGLE ARGENTINA S.R.L. | H12: 1519996.9 | I12: =compras_mes2[[#This Row],[NETO GRAVADO]]*0.21 -> 319199.36 | L12: 45599.91 | N12: 22799.95 | P12: =SUM(compras_mes2[[#This Row],[NETO GRAVADO]:[Otros / No Grav.]]) -> 1907596.1 | Q12: =IFERROR(IF(compras_mes2[[#This Row],[CUIT]]="","-",VLOOKUP(compras_mes2[[#This Row],[CUIT]],Lista_CUIT[#All],3,0)),"CUIT NO CARGADO") -> Servicios de publicidad | R12: =IFERROR(IF(compras_mes2[[#This Row],[CUIT]]="","-",VLOOKUP(compras_mes2[[#This Row],[CUIT]],Lista_CUIT[#All],4,0)),"CUIT NO CARGADO") -> 0
B13: 28/02/2026 | C13: 1 | D13: 11 | E13: 1293337 | F13: 33709585229 | G13: =IFERROR(IF(compras_mes2[[#This Row],[CUIT]]="","-",VLOOKUP(compras_mes2[[#This Row],[CUIT]],Lista_CUIT[#All],2,0)),"CUIT NO CARGADO") -> GOOGLE ARGENTINA S.R.L. | H13: 4426055.6 | I13: =compras_mes2[[#This Row],[NETO GRAVADO]]*0.21 -> 929471.67 | L13: 132781.67 | N13: 66390.83 | P13: =SUM(compras_mes2[[#This Row],[NETO GRAVADO]:[Otros / No Grav.]]) -> 5554699.7 | Q13: =IFERROR(IF(compras_mes2[[#This Row],[CUIT]]="","-",VLOOKUP(compras_mes2[[#This Row],[CUIT]],Lista_CUIT[#All],3,0)),"CUIT NO CARGADO") -> Servicios de publicidad | R13: =IFERROR(IF(compras_mes2[[#This Row],[CUIT]]="","-",VLOOKUP(compras_mes2[[#This Row],[CUIT]],Lista_CUIT[#All],4,0)),"CUIT NO CARGADO") -> 0
B14: 28/02/2026 | C14: 3 | D14: 11 | E14: 914238 | F14: 33709585229 | G14: =IFERROR(IF(compras_mes2[[#This Row],[CUIT]]="","-",VLOOKUP(compras_mes2[[#This Row],[CUIT]],Lista_CUIT[#All],2,0)),"CUIT NO CARGADO") -> GOOGLE ARGENTINA S.R.L. | H14: -1025.59 | I14: =compras_mes2[[#This Row],[NETO GRAVADO]]*0.21 -> -215.3739 | N14: -15.38 | P14: =SUM(compras_mes2[[#This Row],[NETO GRAVADO]:[Otros / No Grav.]]) -> -1256.3439 | Q14: =IFERROR(IF(compras_mes2[[#This Row],[CUIT]]="","-",VLOOKUP(compras_mes2[[#This Row],[CUIT]],Lista_CUIT[#All],3,0)),"CUIT NO CARGADO") -> Servicios de publicidad | R14: =IFERROR(IF(compras_mes2[[#This Row],[CUIT]]="","-",VLOOKUP(compras_mes2[[#This Row],[CUIT]],Lista_CUIT[#All],4,0)),"CUIT NO CARGADO") -> 0
B15: 28/02/2026 | C15: 3 | D15: 11 | E15: 920713 | F15: 33709585229 | G15: =IFERROR(IF(compras_mes2[[#This Row],[CUIT]]="","-",VLOOKUP(compras_mes2[[#This Row],[CUIT]],Lista_CUIT[#All],2,0)),"CUIT NO CARGADO") -> GOOGLE ARGENTINA S.R.L. | H15: -6501.02 | I15: =compras_mes2[[#This Row],[NETO GRAVADO]]*0.21 -> -1365.2142 | N15: -97.52 | O15: -195.03 | P15: =SUM(compras_mes2[[#This Row],[NETO GRAVADO]:[Otros / No Grav.]]) -> -8158.7842 | Q15: =IFERROR(IF(compras_mes2[[#This Row],[CUIT]]="","-",VLOOKUP(compras_mes2[[#This Row],[CUIT]],Lista_CUIT[#All],3,0)),"CUIT NO CARGADO") -> Servicios de publicidad | R15: =IFERROR(IF(compras_mes2[[#This Row],[CUIT]]="","-",VLOOKUP(compras_mes2[[#This Row],[CUIT]],Lista_CUIT[#All],4,0)),"CUIT NO CARGADO") -> 0
G16: =IFERROR(IF(compras_mes2[[#This Row],[CUIT]]="","-",VLOOKUP(compras_mes2[[#This Row],[CUIT]],Lista_CUIT[#All],2,0)),"CUIT NO CARGADO") -> - | I16: =compras_mes2[[#This Row],[NETO GRAVADO]]*0.21 -> 0 | P16: =SUM(compras_mes2[[#This Row],[NETO GRAVADO]:[Otros / No Grav.]]) -> 0 | Q16: =IFERROR(IF(compras_mes2[[#This Row],[CUIT]]="","-",VLOOKUP(compras_mes2[[#This Row],[CUIT]],Lista_CUIT[#All],3,0)),"CUIT NO CARGADO") -> - | R16: =IFERROR(IF(compras_mes2[[#This Row],[CUIT]]="","-",VLOOKUP(compras_mes2[[#This Row],[CUIT]],Lista_CUIT[#All],4,0)),"CUIT NO CARGADO") -> -
G17: =IFERROR(IF(compras_mes2[[#This Row],[CUIT]]="","-",VLOOKUP(compras_mes2[[#This Row],[CUIT]],Lista_CUIT[#All],2,0)),"CUIT NO CARGADO") -> - | I17: =compras_mes2[[#This Row],[NETO GRAVADO]]*0.21 -> 0 | P17: =SUM(compras_mes2[[#This Row],[NETO GRAVADO]:[Otros / No Grav.]]) -> 0 | Q17: =IFERROR(IF(compras_mes2[[#This Row],[CUIT]]="","-",VLOOKUP(compras_mes2[[#This Row],[CUIT]],Lista_CUIT[#All],3,0)),"CUIT NO CARGADO") -> - | R17: =IFERROR(IF(compras_mes2[[#This Row],[CUIT]]="","-",VLOOKUP(compras_mes2[[#This Row],[CUIT]],Lista_CUIT[#All],4,0)),"CUIT NO CARGADO") -> -
G18: =IFERROR(IF(compras_mes2[[#This Row],[CUIT]]="","-",VLOOKUP(compras_mes2[[#This Row],[CUIT]],Lista_CUIT[#All],2,0)),"CUIT NO CARGADO") -> - | I18: =compras_mes2[[#This Row],[NETO GRAVADO]]*0.21 -> 0 | P18: =SUM(compras_mes2[[#This Row],[NETO GRAVADO]:[Otros / No Grav.]]) -> 0 | Q18: =IFERROR(IF(compras_mes2[[#This Row],[CUIT]]="","-",VLOOKUP(compras_mes2[[#This Row],[CUIT]],Lista_CUIT[#All],3,0)),"CUIT NO CARGADO") -> - | R18: =IFERROR(IF(compras_mes2[[#This Row],[CUIT]]="","-",VLOOKUP(compras_mes2[[#This Row],[CUIT]],Lista_CUIT[#All],4,0)),"CUIT NO CARGADO") -> -
G19: =IFERROR(IF(compras_mes2[[#This Row],[CUIT]]="","-",VLOOKUP(compras_mes2[[#This Row],[CUIT]],Lista_CUIT[#All],2,0)),"CUIT NO CARGADO") -> - | I19: =compras_mes2[[#This Row],[NETO GRAVADO]]*0.21 -> 0 | P19: =SUM(compras_mes2[[#This Row],[NETO GRAVADO]:[Otros / No Grav.]]) -> 0 | Q19: =IFERROR(IF(compras_mes2[[#This Row],[CUIT]]="","-",VLOOKUP(compras_mes2[[#This Row],[CUIT]],Lista_CUIT[#All],3,0)),"CUIT NO CARGADO") -> - | R19: =IFERROR(IF(compras_mes2[[#This Row],[CUIT]]="","-",VLOOKUP(compras_mes2[[#This Row],[CUIT]],Lista_CUIT[#All],4,0)),"CUIT NO CARGADO") -> -
G20: =IFERROR(IF(compras_mes2[[#This Row],[CUIT]]="","-",VLOOKUP(compras_mes2[[#This Row],[CUIT]],Lista_CUIT[#All],2,0)),"CUIT NO CARGADO") -> - | I20: =compras_mes2[[#This Row],[NETO GRAVADO]]*0.21 -> 0 | P20: =SUM(compras_mes2[[#This Row],[NETO GRAVADO]:[Otros / No Grav.]]) -> 0 | Q20: =IFERROR(IF(compras_mes2[[#This Row],[CUIT]]="","-",VLOOKUP(compras_mes2[[#This Row],[CUIT]],Lista_CUIT[#All],3,0)),"CUIT NO CARGADO") -> - | R20: =IFERROR(IF(compras_mes2[[#This Row],[CUIT]]="","-",VLOOKUP(compras_mes2[[#This Row],[CUIT]],Lista_CUIT[#All],4,0)),"CUIT NO CARGADO") -> -
G21: =IFERROR(IF(compras_mes2[[#This Row],[CUIT]]="","-",VLOOKUP(compras_mes2[[#This Row],[CUIT]],Lista_CUIT[#All],2,0)),"CUIT NO CARGADO") -> - | I21: =compras_mes2[[#This Row],[NETO GRAVADO]]*0.21 -> 0 | P21: =SUM(compras_mes2[[#This Row],[NETO GRAVADO]:[Otros / No Grav.]]) -> 0 | Q21: =IFERROR(IF(compras_mes2[[#This Row],[CUIT]]="","-",VLOOKUP(compras_mes2[[#This Row],[CUIT]],Lista_CUIT[#All],3,0)),"CUIT NO CARGADO") -> - | R21: =IFERROR(IF(compras_mes2[[#This Row],[CUIT]]="","-",VLOOKUP(compras_mes2[[#This Row],[CUIT]],Lista_CUIT[#All],4,0)),"CUIT NO CARGADO") -> -
G22: =IFERROR(IF(compras_mes2[[#This Row],[CUIT]]="","-",VLOOKUP(compras_mes2[[#This Row],[CUIT]],Lista_CUIT[#All],2,0)),"CUIT NO CARGADO") -> - | I22: =compras_mes2[[#This Row],[NETO GRAVADO]]*0.21 -> 0 | P22: =SUM(compras_mes2[[#This Row],[NETO GRAVADO]:[Otros / No Grav.]]) -> 0 | Q22: =IFERROR(IF(compras_mes2[[#This Row],[CUIT]]="","-",VLOOKUP(compras_mes2[[#This Row],[CUIT]],Lista_CUIT[#All],3,0)),"CUIT NO CARGADO") -> - | R22: =IFERROR(IF(compras_mes2[[#This Row],[CUIT]]="","-",VLOOKUP(compras_mes2[[#This Row],[CUIT]],Lista_CUIT[#All],4,0)),"CUIT NO CARGADO") -> -
G23: =IFERROR(IF(compras_mes2[[#This Row],[CUIT]]="","-",VLOOKUP(compras_mes2[[#This Row],[CUIT]],Lista_CUIT[#All],2,0)),"CUIT NO CARGADO") -> - | I23: =compras_mes2[[#This Row],[NETO GRAVADO]]*0.21 -> 0 | P23: =SUM(compras_mes2[[#This Row],[NETO GRAVADO]:[Otros / No Grav.]]) -> 0 | Q23: =IFERROR(IF(compras_mes2[[#This Row],[CUIT]]="","-",VLOOKUP(compras_mes2[[#This Row],[CUIT]],Lista_CUIT[#All],3,0)),"CUIT NO CARGADO") -> - | R23: =IFERROR(IF(compras_mes2[[#This Row],[CUIT]]="","-",VLOOKUP(compras_mes2[[#This Row],[CUIT]],Lista_CUIT[#All],4,0)),"CUIT NO CARGADO") -> -
G24: =IFERROR(IF(compras_mes2[[#This Row],[CUIT]]="","-",VLOOKUP(compras_mes2[[#This Row],[CUIT]],Lista_CUIT[#All],2,0)),"CUIT NO CARGADO") -> - | I24: =compras_mes2[[#This Row],[NETO GRAVADO]]*0.21 -> 0 | P24: =SUM(compras_mes2[[#This Row],[NETO GRAVADO]:[Otros / No Grav.]]) -> 0 | Q24: =IFERROR(IF(compras_mes2[[#This Row],[CUIT]]="","-",VLOOKUP(compras_mes2[[#This Row],[CUIT]],Lista_CUIT[#All],3,0)),"CUIT NO CARGADO") -> - | R24: =IFERROR(IF(compras_mes2[[#This Row],[CUIT]]="","-",VLOOKUP(compras_mes2[[#This Row],[CUIT]],Lista_CUIT[#All],4,0)),"CUIT NO CARGADO") -> -
G25: =IFERROR(IF(compras_mes2[[#This Row],[CUIT]]="","-",VLOOKUP(compras_mes2[[#This Row],[CUIT]],Lista_CUIT[#All],2,0)),"CUIT NO CARGADO") -> - | I25: =compras_mes2[[#This Row],[NETO GRAVADO]]*0.21 -> 0 | P25: =SUM(compras_mes2[[#This Row],[NETO GRAVADO]:[Otros / No Grav.]]) -> 0 | Q25: =IFERROR(IF(compras_mes2[[#This Row],[CUIT]]="","-",VLOOKUP(compras_mes2[[#This Row],[CUIT]],Lista_CUIT[#All],3,0)),"CUIT NO CARGADO") -> - | R25: =IFERROR(IF(compras_mes2[[#This Row],[CUIT]]="","-",VLOOKUP(compras_mes2[[#This Row],[CUIT]],Lista_CUIT[#All],4,0)),"CUIT NO CARGADO") -> -
G26: =IFERROR(IF(compras_mes2[[#This Row],[CUIT]]="","-",VLOOKUP(compras_mes2[[#This Row],[CUIT]],Lista_CUIT[#All],2,0)),"CUIT NO CARGADO") -> - | I26: =compras_mes2[[#This Row],[NETO GRAVADO]]*0.21 -> 0 | P26: =SUM(compras_mes2[[#This Row],[NETO GRAVADO]:[Otros / No Grav.]]) -> 0 | Q26: =IFERROR(IF(compras_mes2[[#This Row],[CUIT]]="","-",VLOOKUP(compras_mes2[[#This Row],[CUIT]],Lista_CUIT[#All],3,0)),"CUIT NO CARGADO") -> - | R26: =IFERROR(IF(compras_mes2[[#This Row],[CUIT]]="","-",VLOOKUP(compras_mes2[[#This Row],[CUIT]],Lista_CUIT[#All],4,0)),"CUIT NO CARGADO") -> -
B27: Total | H27: =SUBTOTAL(109,compras_mes2[NETO GRAVADO]) -> 6147525.6 | I27: =SUBTOTAL(109,compras_mes2[IVA 21 %]) -> 1290980.4 | J27: =SUBTOTAL(109,compras_mes2[IVA 27%]) -> 0 | K27: =SUBTOTAL(109,compras_mes2[IVA 10,5%]) -> 0 | L27: =SUBTOTAL(109,compras_mes2[PERC. IVA]) -> 178381.58 | M27: =SUBTOTAL(109,compras_mes2[PERC IIBB BS AS]) -> 0 | N27: =SUBTOTAL(109,compras_mes2[PERC. IIBB CABA]) -> 89077.88 | O27: =SUBTOTAL(109,compras_mes2[Otros / No Grav.]) -> -195.03 | P27: =SUBTOTAL(109,compras_mes2[TOTAL]) -> 7705770.4
D32: LIQUIDACION EXTRACTOS BANCARIOS-TARJETAS
D33: FECHA | E33: NRO CPTE | F33: BANCO | G33: NETO | H33: IVA 21% | I33: IVA 10,5% | J33: RET IIBB CABA | K33: PERC IVA | L33: PERC IIBB | M33: TOTAL
D34: 46081 | E34: 28022026 | F34: GALICIA | G34: 60000 | H34: 12600 | J34: 873.39 | K34: 1746.77 | M34: =SUM(G34:L34) -> 75220.16
D37: Total | G37: =SUBTOTAL(109,extracto_banco_mes2[NETO]) -> 60000 | H37: =SUBTOTAL(109,extracto_banco_mes2[IVA 21%]) -> 12600 | I37: =SUBTOTAL(109,extracto_banco_mes2[IVA 10,5%]) -> 0 | J37: =SUBTOTAL(109,extracto_banco_mes2[RET IIBB CABA]) -> 873.39 | K37: =SUBTOTAL(109,extracto_banco_mes2[PERC IVA]) -> 1746.77 | L37: =SUBTOTAL(109,extracto_banco_mes2[PERC IIBB]) -> 0
D41: FACTURAS C
D42: FECHA | E42: PTO VTA | F42: FC Nº | G42: CUIT | H42: RAZON SOCIAL | I42: TOTAL | J42: TIPO DE GASTO | K42: Provincia
D43: 02/02/2026 | E43: 2 | F43: 63 | G43: 23380288079 | H43: =IFERROR(IF(factura_c_mes2[[#This Row],[CUIT]]="","-",VLOOKUP(factura_c_mes2[[#This Row],[CUIT]],Lista_CUIT[#All],2,0)),"CUIT NO CARGADO") -> CASTROMAN AGUSTIN | I43: 538500 | J43: =IFERROR(IF(factura_c_mes2[[#This Row],[CUIT]]="","-",VLOOKUP(factura_c_mes2[[#This Row],[CUIT]],Lista_CUIT[#All],3,0)),"CUIT NO CARGADO") -> 0 | K43: =IFERROR(IF(factura_c_mes2[[#This Row],[CUIT]]="","-",VLOOKUP(factura_c_mes2[[#This Row],[CUIT]],Lista_CUIT[#All],4,0)),"CUIT NO CARGADO") -> 0
D44: 02/02/2026 | E44: 2 | F44: 1117 | G44: 20400104094 | H44: =IFERROR(IF(factura_c_mes2[[#This Row],[CUIT]]="","-",VLOOKUP(factura_c_mes2[[#This Row],[CUIT]],Lista_CUIT[#All],2,0)),"CUIT NO CARGADO") -> BOTINDARI FEDERICO DANIEL | I44: 300000 | J44: =IFERROR(IF(factura_c_mes2[[#This Row],[CUIT]]="","-",VLOOKUP(factura_c_mes2[[#This Row],[CUIT]],Lista_CUIT[#All],3,0)),"CUIT NO CARGADO") -> HONORARIOS CONTABLE | K44: =IFERROR(IF(factura_c_mes2[[#This Row],[CUIT]]="","-",VLOOKUP(factura_c_mes2[[#This Row],[CUIT]],Lista_CUIT[#All],4,0)),"CUIT NO CARGADO") -> 0
D45: 06/02/2026 | E45: 2 | F45: 160 | G45: 27341104845 | H45: =IFERROR(IF(factura_c_mes2[[#This Row],[CUIT]]="","-",VLOOKUP(factura_c_mes2[[#This Row],[CUIT]],Lista_CUIT[#All],2,0)),"CUIT NO CARGADO") -> BOSSI MARIA PAULA | I45: 342000 | J45: =IFERROR(IF(factura_c_mes2[[#This Row],[CUIT]]="","-",VLOOKUP(factura_c_mes2[[#This Row],[CUIT]],Lista_CUIT[#All],3,0)),"CUIT NO CARGADO") -> 0 | K45: =IFERROR(IF(factura_c_mes2[[#This Row],[CUIT]]="","-",VLOOKUP(factura_c_mes2[[#This Row],[CUIT]],Lista_CUIT[#All],4,0)),"CUIT NO CARGADO") -> 0
D46: 10/02/2026 | E46: 1 | F46: 3 | G46: 27403975821 | H46: =IFERROR(IF(factura_c_mes2[[#This Row],[CUIT]]="","-",VLOOKUP(factura_c_mes2[[#This Row],[CUIT]],Lista_CUIT[#All],2,0)),"CUIT NO CARGADO") -> BARROSO VALENTINA | I46: 538500 | J46: =IFERROR(IF(factura_c_mes2[[#This Row],[CUIT]]="","-",VLOOKUP(factura_c_mes2[[#This Row],[CUIT]],Lista_CUIT[#All],3,0)),"CUIT NO CARGADO") -> 0 | K46: =IFERROR(IF(factura_c_mes2[[#This Row],[CUIT]]="","-",VLOOKUP(factura_c_mes2[[#This Row],[CUIT]],Lista_CUIT[#All],4,0)),"CUIT NO CARGADO") -> 0
D47: 12/02/2026 | E47: 1 | F47: 328 | G47: 27386311000 | H47: =IFERROR(IF(factura_c_mes2[[#This Row],[CUIT]]="","-",VLOOKUP(factura_c_mes2[[#This Row],[CUIT]],Lista_CUIT[#All],2,0)),"CUIT NO CARGADO") -> OPANASIUK MACARENA ANTONELLA | I47: 850000 | J47: =IFERROR(IF(factura_c_mes2[[#This Row],[CUIT]]="","-",VLOOKUP(factura_c_mes2[[#This Row],[CUIT]],Lista_CUIT[#All],3,0)),"CUIT NO CARGADO") -> 0 | K47: =IFERROR(IF(factura_c_mes2[[#This Row],[CUIT]]="","-",VLOOKUP(factura_c_mes2[[#This Row],[CUIT]],Lista_CUIT[#All],4,0)),"CUIT NO CARGADO") -> 0
D48: 12/02/2026 | E48: 51 | F48: 193 | G48: 20300985158 | H48: =IFERROR(IF(factura_c_mes2[[#This Row],[CUIT]]="","-",VLOOKUP(factura_c_mes2[[#This Row],[CUIT]],Lista_CUIT[#All],2,0)),"CUIT NO CARGADO") -> GONZALEZ NESTOR RICARDO | I48: 1007250 | J48: =IFERROR(IF(factura_c_mes2[[#This Row],[CUIT]]="","-",VLOOKUP(factura_c_mes2[[#This Row],[CUIT]],Lista_CUIT[#All],3,0)),"CUIT NO CARGADO") -> 0 | K48: =IFERROR(IF(factura_c_mes2[[#This Row],[CUIT]]="","-",VLOOKUP(factura_c_mes2[[#This Row],[CUIT]],Lista_CUIT[#All],4,0)),"CUIT NO CARGADO") -> 0
H49: =IFERROR(IF(factura_c_mes2[[#This Row],[CUIT]]="","-",VLOOKUP(factura_c_mes2[[#This Row],[CUIT]],Lista_CUIT[#All],2,0)),"CUIT NO CARGADO") -> - | J49: =IFERROR(IF(factura_c_mes2[[#This Row],[CUIT]]="","-",VLOOKUP(factura_c_mes2[[#This Row],[CUIT]],Lista_CUIT[#All],3,0)),"CUIT NO CARGADO") -> - | K49: =IFERROR(IF(factura_c_mes2[[#This Row],[CUIT]]="","-",VLOOKUP(factura_c_mes2[[#This Row],[CUIT]],Lista_CUIT[#All],4,0)),"CUIT NO CARGADO") -> -
H50: =IFERROR(IF(factura_c_mes2[[#This Row],[CUIT]]="","-",VLOOKUP(factura_c_mes2[[#This Row],[CUIT]],Lista_CUIT[#All],2,0)),"CUIT NO CARGADO") -> - | J50: =IFERROR(IF(factura_c_mes2[[#This Row],[CUIT]]="","-",VLOOKUP(factura_c_mes2[[#This Row],[CUIT]],Lista_CUIT[#All],3,0)),"CUIT NO CARGADO") -> - | K50: =IFERROR(IF(factura_c_mes2[[#This Row],[CUIT]]="","-",VLOOKUP(factura_c_mes2[[#This Row],[CUIT]],Lista_CUIT[#All],4,0)),"CUIT NO CARGADO") -> -
H51: =IFERROR(IF(factura_c_mes2[[#This Row],[CUIT]]="","-",VLOOKUP(factura_c_mes2[[#This Row],[CUIT]],Lista_CUIT[#All],2,0)),"CUIT NO CARGADO") -> - | J51: =IFERROR(IF(factura_c_mes2[[#This Row],[CUIT]]="","-",VLOOKUP(factura_c_mes2[[#This Row],[CUIT]],Lista_CUIT[#All],3,0)),"CUIT NO CARGADO") -> - | K51: =IFERROR(IF(factura_c_mes2[[#This Row],[CUIT]]="","-",VLOOKUP(factura_c_mes2[[#This Row],[CUIT]],Lista_CUIT[#All],4,0)),"CUIT NO CARGADO") -> -
D52: Total | I52: =SUBTOTAL(109,factura_c_mes2[TOTAL]) -> 3576250
B57: LIBRO IVA VENTAS | K57: =N1 -> 46054
B59: VENTAS "A"
B60: FECHA | C60: TIPO | D60: PTO VENTA | E60: Nº FACTURA | F60: CUIT | G60: RAZON SOCIAL | H60: IMPORTE NETO | I60: IVA 21% | J60: IVA 10,5% | K60: EXENTO | L60: TOTAL | M60: Provincia
B61: 02/02/2026 | C61: 1 | D61: 1 | E61: 636 | F61: 30714236888 | G61: =IFERROR(IF(venta_a_mes2[[#This Row],[CUIT]]="","-",VLOOKUP(venta_a_mes2[[#This Row],[CUIT]],Lista_CUIT[#All],2,0)),"CUIT NO CARGADO") -> NANOTEC S.R.L. | H61: 590909.1 | I61: =venta_a_mes2[[#This Row],[IMPORTE NETO]]*0.21 -> 124090.91 | L61: =SUM(venta_a_mes2[[#This Row],[IMPORTE NETO]:[EXENTO]]) -> 715000.01
B62: 02/02/2026 | C62: 1 | D62: 1 | E62: 637 | F62: 30708404485 | G62: =IFERROR(IF(venta_a_mes2[[#This Row],[CUIT]]="","-",VLOOKUP(venta_a_mes2[[#This Row],[CUIT]],Lista_CUIT[#All],2,0)),"CUIT NO CARGADO") -> SOLDARGEN S.A. | H62: 590909.1 | I62: =venta_a_mes2[[#This Row],[IMPORTE NETO]]*0.21 -> 124090.91 | L62: =SUM(venta_a_mes2[[#This Row],[IMPORTE NETO]:[EXENTO]]) -> 715000.01
B63: 02/02/2026 | C63: 1 | D63: 1 | E63: 635 | F63: 30718553357 | G63: =IFERROR(IF(venta_a_mes2[[#This Row],[CUIT]]="","-",VLOOKUP(venta_a_mes2[[#This Row],[CUIT]],Lista_CUIT[#All],2,0)),"CUIT NO CARGADO") -> EMIGRA CON TU MASCOTA S.R.L. | H63: 590909.1 | I63: =venta_a_mes2[[#This Row],[IMPORTE NETO]]*0.21 -> 124090.91 | L63: =SUM(venta_a_mes2[[#This Row],[IMPORTE NETO]:[EXENTO]]) -> 715000.01
B64: 02/02/2026 | C64: 1 | D64: 1 | E64: 638 | F64: 30708604255 | G64: =IFERROR(IF(venta_a_mes2[[#This Row],[CUIT]]="","-",VLOOKUP(venta_a_mes2[[#This Row],[CUIT]],Lista_CUIT[#All],2,0)),"CUIT NO CARGADO") -> NAR TECHNOLOGIES S.R.L. | H64: 545454.57 | I64: =venta_a_mes2[[#This Row],[IMPORTE NETO]]*0.21 -> 114545.46 | L64: =SUM(venta_a_mes2[[#This Row],[IMPORTE NETO]:[EXENTO]]) -> 660000.03
B65: 02/02/2026 | C65: 1 | D65: 1 | E65: 639 | F65: 24368969350 | G65: =IFERROR(IF(venta_a_mes2[[#This Row],[CUIT]]="","-",VLOOKUP(venta_a_mes2[[#This Row],[CUIT]],Lista_CUIT[#All],2,0)),"CUIT NO CARGADO") -> MARANO CORVALAN MARTIN MARIANO | H65: 295454.57 | I65: =venta_a_mes2[[#This Row],[IMPORTE NETO]]*0.21 -> 62045.46 | L65: =SUM(venta_a_mes2[[#This Row],[IMPORTE NETO]:[EXENTO]]) -> 357500.03
B66: 02/02/2026 | C66: 1 | D66: 1 | E66: 647 | F66: 30714864803 | G66: =IFERROR(IF(venta_a_mes2[[#This Row],[CUIT]]="","-",VLOOKUP(venta_a_mes2[[#This Row],[CUIT]],Lista_CUIT[#All],2,0)),"CUIT NO CARGADO") -> DIAZ Y GIUSEPPETTI S. R. L. | H66: 259141.19 | I66: =venta_a_mes2[[#This Row],[IMPORTE NETO]]*0.21 -> 54419.65 | L66: =SUM(venta_a_mes2[[#This Row],[IMPORTE NETO]:[EXENTO]]) -> 313560.84
B67: 02/02/2026 | C67: 1 | D67: 1 | E67: 646 | F67: 30709058807 | G67: =IFERROR(IF(venta_a_mes2[[#This Row],[CUIT]]="","-",VLOOKUP(venta_a_mes2[[#This Row],[CUIT]],Lista_CUIT[#All],2,0)),"CUIT NO CARGADO") -> LA VALENZIANA S.R.L. | H67: 4876040.9 | I67: =venta_a_mes2[[#This Row],[IMPORTE NETO]]*0.21 -> 1023968.6 | L67: =SUM(venta_a_mes2[[#This Row],[IMPORTE NETO]:[EXENTO]]) -> 5900009.5
B68: 02/02/2026 | C68: 1 | D68: 1 | E68: 634 | F68: 30714375241 | G68: =IFERROR(IF(venta_a_mes2[[#This Row],[CUIT]]="","-",VLOOKUP(venta_a_mes2[[#This Row],[CUIT]],Lista_CUIT[#All],2,0)),"CUIT NO CARGADO") -> POWER-RECORDS S.A | H68: 590909.1 | I68: =venta_a_mes2[[#This Row],[IMPORTE NETO]]*0.21 -> 124090.91 | L68: =SUM(venta_a_mes2[[#This Row],[IMPORTE NETO]:[EXENTO]]) -> 715000.01
B69: 02/02/2026 | C69: 1 | D69: 1 | E69: 633 | F69: 30715751557 | G69: =IFERROR(IF(venta_a_mes2[[#This Row],[CUIT]]="","-",VLOOKUP(venta_a_mes2[[#This Row],[CUIT]],Lista_CUIT[#All],2,0)),"CUIT NO CARGADO") -> TIXIT SRL | H69: 590909.1 | I69: =venta_a_mes2[[#This Row],[IMPORTE NETO]]*0.21 -> 124090.91 | L69: =SUM(venta_a_mes2[[#This Row],[IMPORTE NETO]:[EXENTO]]) -> 715000.01
B70: 02/02/2026 | C70: 1 | D70: 1 | E70: 642 | F70: 20279415656 | G70: =IFERROR(IF(venta_a_mes2[[#This Row],[CUIT]]="","-",VLOOKUP(venta_a_mes2[[#This Row],[CUIT]],Lista_CUIT[#All],2,0)),"CUIT NO CARGADO") -> CECCO ALVARO GONZALO | H70: 147107.43 | I70: =venta_a_mes2[[#This Row],[IMPORTE NETO]]*0.21 -> 30892.56 | L70: =SUM(venta_a_mes2[[#This Row],[IMPORTE NETO]:[EXENTO]]) -> 177999.99
B71: 02/02/2026 | C71: 1 | D71: 1 | E71: 643 | F71: 30717973166 | G71: =IFERROR(IF(venta_a_mes2[[#This Row],[CUIT]]="","-",VLOOKUP(venta_a_mes2[[#This Row],[CUIT]],Lista_CUIT[#All],2,0)),"CUIT NO CARGADO") -> STM ESTILO S.R.L | H71: 147107.43 | I71: =venta_a_mes2[[#This Row],[IMPORTE NETO]]*0.21 -> 30892.56 | L71: =SUM(venta_a_mes2[[#This Row],[IMPORTE NETO]:[EXENTO]]) -> 177999.99
B72: 02/02/2026 | C72: 1 | D72: 1 | E72: 644 | F72: 20287305460 | G72: =IFERROR(IF(venta_a_mes2[[#This Row],[CUIT]]="","-",VLOOKUP(venta_a_mes2[[#This Row],[CUIT]],Lista_CUIT[#All],2,0)),"CUIT NO CARGADO") -> LANDI GERONIMO | H72: 147107.43 | I72: =venta_a_mes2[[#This Row],[IMPORTE NETO]]*0.21 -> 30892.56 | L72: =SUM(venta_a_mes2[[#This Row],[IMPORTE NETO]:[EXENTO]]) -> 177999.99
... B79: 27/02/2026 | C79: 3 | D79: 1 | E79: 51 | F79: 30708604255 | G79: =IFERROR(IF(venta_a_mes2[[#This Row],[CUIT]]="","-",VLOOKUP(venta_a_mes2[[#This Row],[CUIT]],Lista_CUIT[#All],2,0)),"CUIT NO CARGADO") -> NAR TECHNOLOGIES S.R.L. | H79: -545454.57 | I79: =venta_a_mes2[[#This Row],[IMPORTE NETO]]*0.21 -> -114545.46 | L79: =SUM(venta_a_mes2[[#This Row],[IMPORTE NETO]:[EXENTO]]) -> -660000.03
G80: =IFERROR(IF(venta_a_mes2[[#This Row],[CUIT]]="","-",VLOOKUP(venta_a_mes2[[#This Row],[CUIT]],Lista_CUIT[#All],2,0)),"CUIT NO CARGADO") -> - | I80: =venta_a_mes2[[#This Row],[IMPORTE NETO]]*0.21 -> 0 | L80: =SUM(venta_a_mes2[[#This Row],[IMPORTE NETO]:[EXENTO]]) -> 0
G81: =IFERROR(IF(venta_a_mes2[[#This Row],[CUIT]]="","-",VLOOKUP(venta_a_mes2[[#This Row],[CUIT]],Lista_CUIT[#All],2,0)),"CUIT NO CARGADO") -> - | I81: =venta_a_mes2[[#This Row],[IMPORTE NETO]]*0.21 -> 0 | L81: =SUM(venta_a_mes2[[#This Row],[IMPORTE NETO]:[EXENTO]]) -> 0
G82: =IFERROR(IF(venta_a_mes2[[#This Row],[CUIT]]="","-",VLOOKUP(venta_a_mes2[[#This Row],[CUIT]],Lista_CUIT[#All],2,0)),"CUIT NO CARGADO") -> - | I82: =venta_a_mes2[[#This Row],[IMPORTE NETO]]*0.21 -> 0 | L82: =SUM(venta_a_mes2[[#This Row],[IMPORTE NETO]:[EXENTO]]) -> 0
G83: =IFERROR(IF(venta_a_mes2[[#This Row],[CUIT]]="","-",VLOOKUP(venta_a_mes2[[#This Row],[CUIT]],Lista_CUIT[#All],2,0)),"CUIT NO CARGADO") -> - | I83: =venta_a_mes2[[#This Row],[IMPORTE NETO]]*0.21 -> 0 | L83: =SUM(venta_a_mes2[[#This Row],[IMPORTE NETO]:[EXENTO]]) -> 0
G84: =IFERROR(IF(venta_a_mes2[[#This Row],[CUIT]]="","-",VLOOKUP(venta_a_mes2[[#This Row],[CUIT]],Lista_CUIT[#All],2,0)),"CUIT NO CARGADO") -> - | I84: =venta_a_mes2[[#This Row],[IMPORTE NETO]]*0.21 -> 0 | L84: =SUM(venta_a_mes2[[#This Row],[IMPORTE NETO]:[EXENTO]]) -> 0
G85: =IFERROR(IF(venta_a_mes2[[#This Row],[CUIT]]="","-",VLOOKUP(venta_a_mes2[[#This Row],[CUIT]],Lista_CUIT[#All],2,0)),"CUIT NO CARGADO") -> - | I85: =venta_a_mes2[[#This Row],[IMPORTE NETO]]*0.21 -> 0 | L85: =SUM(venta_a_mes2[[#This Row],[IMPORTE NETO]:[EXENTO]]) -> 0
G86: =IFERROR(IF(venta_a_mes2[[#This Row],[CUIT]]="","-",VLOOKUP(venta_a_mes2[[#This Row],[CUIT]],Lista_CUIT[#All],2,0)),"CUIT NO CARGADO") -> - | I86: =venta_a_mes2[[#This Row],[IMPORTE NETO]]*0.21 -> 0 | L86: =SUM(venta_a_mes2[[#This Row],[IMPORTE NETO]:[EXENTO]]) -> 0
G87: =IFERROR(IF(venta_a_mes2[[#This Row],[CUIT]]="","-",VLOOKUP(venta_a_mes2[[#This Row],[CUIT]],Lista_CUIT[#All],2,0)),"CUIT NO CARGADO") -> - | I87: =venta_a_mes2[[#This Row],[IMPORTE NETO]]*0.21 -> 0 | L87: =SUM(venta_a_mes2[[#This Row],[IMPORTE NETO]:[EXENTO]]) -> 0
G88: =IFERROR(IF(venta_a_mes2[[#This Row],[CUIT]]="","-",VLOOKUP(venta_a_mes2[[#This Row],[CUIT]],Lista_CUIT[#All],2,0)),"CUIT NO CARGADO") -> - | I88: =venta_a_mes2[[#This Row],[IMPORTE NETO]]*0.21 -> 0 | L88: =SUM(venta_a_mes2[[#This Row],[IMPORTE NETO]:[EXENTO]]) -> 0
G89: =IFERROR(IF(venta_a_mes2[[#This Row],[CUIT]]="","-",VLOOKUP(venta_a_mes2[[#This Row],[CUIT]],Lista_CUIT[#All],2,0)),"CUIT NO CARGADO") -> - | I89: =venta_a_mes2[[#This Row],[IMPORTE NETO]]*0.21 -> 0 | L89: =SUM(venta_a_mes2[[#This Row],[IMPORTE NETO]:[EXENTO]]) -> 0
B90: Total | H90: =SUBTOTAL(109,venta_a_mes2[IMPORTE NETO]) -> 9787785.5 | I90: =SUBTOTAL(109,venta_a_mes2[IVA 21%]) -> 2055435 | J90: =SUBTOTAL(109,venta_a_mes2[IVA 10,5%]) -> 0 | K90: =SUBTOTAL(109,venta_a_mes2[EXENTO]) -> 0 | L90: =SUBTOTAL(109,venta_a_mes2[TOTAL]) -> 11843220 | M90: =SUBTOTAL(103,venta_a_mes2[Provincia]) -> 0
B92: VENTAS "B"
B93: FECHA | C93: TIPO | D93: PTO VENTA | E93: Nº FACTURA | F93: CUIT | G93: RAZON SOCIAL | H93: IMPORTE NETO | I93: IVA 21% | J93: IVA 10,5% | K93: EXENTO | L93: TOTAL | M93: Provincia
G94: =IFERROR(IF(ventas_b_mes2[[#This Row],[CUIT]]="","-",VLOOKUP(ventas_b_mes2[[#This Row],[CUIT]],Lista_CUIT[#All],2,0)),"CUIT NO CARGADO") -> - | H94: =ventas_b_mes2[[#This Row],[TOTAL]]/1.21 -> 0 | I94: =ventas_b_mes2[[#This Row],[IMPORTE NETO]]*0.21 -> 0
G95: =IFERROR(IF(ventas_b_mes2[[#This Row],[CUIT]]="","-",VLOOKUP(ventas_b_mes2[[#This Row],[CUIT]],Lista_CUIT[#All],2,0)),"CUIT NO CARGADO") -> - | H95: =ventas_b_mes2[[#This Row],[TOTAL]]/1.21 -> 0 | I95: =ventas_b_mes2[[#This Row],[IMPORTE NETO]]*0.21 -> 0
G96: =IFERROR(IF(ventas_b_mes2[[#This Row],[CUIT]]="","-",VLOOKUP(ventas_b_mes2[[#This Row],[CUIT]],Lista_CUIT[#All],2,0)),"CUIT NO CARGADO") -> - | H96: =ventas_b_mes2[[#This Row],[TOTAL]]/1.21 -> 0 | I96: =ventas_b_mes2[[#This Row],[IMPORTE NETO]]*0.21 -> 0
G97: =IFERROR(IF(ventas_b_mes2[[#This Row],[CUIT]]="","-",VLOOKUP(ventas_b_mes2[[#This Row],[CUIT]],Lista_CUIT[#All],2,0)),"CUIT NO CARGADO") -> - | H97: =ventas_b_mes2[[#This Row],[TOTAL]]/1.21 -> 0 | I97: =ventas_b_mes2[[#This Row],[IMPORTE NETO]]*0.21 -> 0
G98: =IFERROR(IF(ventas_b_mes2[[#This Row],[CUIT]]="","-",VLOOKUP(ventas_b_mes2[[#This Row],[CUIT]],Lista_CUIT[#All],2,0)),"CUIT NO CARGADO") -> - | H98: =ventas_b_mes2[[#This Row],[TOTAL]]/1.21 -> 0 | I98: =ventas_b_mes2[[#This Row],[IMPORTE NETO]]*0.21 -> 0
G99: =IFERROR(IF(ventas_b_mes2[[#This Row],[CUIT]]="","-",VLOOKUP(ventas_b_mes2[[#This Row],[CUIT]],Lista_CUIT[#All],2,0)),"CUIT NO CARGADO") -> - | H99: =ventas_b_mes2[[#This Row],[TOTAL]]/1.21 -> 0 | I99: =ventas_b_mes2[[#This Row],[IMPORTE NETO]]*0.21 -> 0
G100: =IFERROR(IF(ventas_b_mes2[[#This Row],[CUIT]]="","-",VLOOKUP(ventas_b_mes2[[#This Row],[CUIT]],Lista_CUIT[#All],2,0)),"CUIT NO CARGADO") -> - | H100: =ventas_b_mes2[[#This Row],[TOTAL]]/1.21 -> 0 | I100: =ventas_b_mes2[[#This Row],[IMPORTE NETO]]*0.21 -> 0
G101: =IFERROR(IF(ventas_b_mes2[[#This Row],[CUIT]]="","-",VLOOKUP(ventas_b_mes2[[#This Row],[CUIT]],Lista_CUIT[#All],2,0)),"CUIT NO CARGADO") -> - | H101: =ventas_b_mes2[[#This Row],[TOTAL]]/1.21 -> 0 | I101: =ventas_b_mes2[[#This Row],[IMPORTE NETO]]*0.21 -> 0
G102: =IFERROR(IF(ventas_b_mes2[[#This Row],[CUIT]]="","-",VLOOKUP(ventas_b_mes2[[#This Row],[CUIT]],Lista_CUIT[#All],2,0)),"CUIT NO CARGADO") -> - | H102: =ventas_b_mes2[[#This Row],[TOTAL]]/1.21 -> 0 | I102: =ventas_b_mes2[[#This Row],[IMPORTE NETO]]*0.21 -> 0
G103: =IFERROR(IF(ventas_b_mes2[[#This Row],[CUIT]]="","-",VLOOKUP(ventas_b_mes2[[#This Row],[CUIT]],Lista_CUIT[#All],2,0)),"CUIT NO CARGADO") -> - | H103: =ventas_b_mes2[[#This Row],[TOTAL]]/1.21 -> 0 | I103: =ventas_b_mes2[[#This Row],[IMPORTE NETO]]*0.21 -> 0
G104: =IFERROR(IF(ventas_b_mes2[[#This Row],[CUIT]]="","-",VLOOKUP(ventas_b_mes2[[#This Row],[CUIT]],Lista_CUIT[#All],2,0)),"CUIT NO CARGADO") -> - | I104: =ventas_b_mes2[[#This Row],[IMPORTE NETO]]*0.21 -> 0
G105: =IFERROR(IF(ventas_b_mes2[[#This Row],[CUIT]]="","-",VLOOKUP(ventas_b_mes2[[#This Row],[CUIT]],Lista_CUIT[#All],2,0)),"CUIT NO CARGADO") -> - | I105: =ventas_b_mes2[[#This Row],[IMPORTE NETO]]*0.21 -> 0
G106: =IFERROR(IF(ventas_b_mes2[[#This Row],[CUIT]]="","-",VLOOKUP(ventas_b_mes2[[#This Row],[CUIT]],Lista_CUIT[#All],2,0)),"CUIT NO CARGADO") -> - | I106: =ventas_b_mes2[[#This Row],[IMPORTE NETO]]*0.21 -> 0
G107: =IFERROR(IF(ventas_b_mes2[[#This Row],[CUIT]]="","-",VLOOKUP(ventas_b_mes2[[#This Row],[CUIT]],Lista_CUIT[#All],2,0)),"CUIT NO CARGADO") -> - | I107: =ventas_b_mes2[[#This Row],[IMPORTE NETO]]*0.21 -> 0
G108: =IFERROR(IF(ventas_b_mes2[[#This Row],[CUIT]]="","-",VLOOKUP(ventas_b_mes2[[#This Row],[CUIT]],Lista_CUIT[#All],2,0)),"CUIT NO CARGADO") -> - | I108: =ventas_b_mes2[[#This Row],[IMPORTE NETO]]*0.21 -> 0
G109: =IFERROR(IF(ventas_b_mes2[[#This Row],[CUIT]]="","-",VLOOKUP(ventas_b_mes2[[#This Row],[CUIT]],Lista_CUIT[#All],2,0)),"CUIT NO CARGADO") -> - | H109: =ventas_b_mes2[[#This Row],[TOTAL]]/1.21 -> 0 | I109: =ventas_b_mes2[[#This Row],[IMPORTE NETO]]*0.21 -> 0
B110: Total | H110: =SUBTOTAL(109,ventas_b_mes2[IMPORTE NETO]) -> 0 | I110: =SUBTOTAL(109,ventas_b_mes2[IVA 21%]) -> 0 | J110: =SUBTOTAL(109,ventas_b_mes2[IVA 10,5%]) -> 0 | K110: =SUBTOTAL(109,ventas_b_mes2[EXENTO]) -> 0 | L110: =SUBTOTAL(109,ventas_b_mes2[TOTAL]) -> 0 | M110: =SUBTOTAL(103,ventas_b_mes2[Provincia]) -> 0
C118: RETENCIONES
C119: FECHA | D119: COMP Nº | E119: Columna1 | F119: CUIT | G119: RAZON SOCIAL | H119: Ganancias | I119: IVA | J119: SUSS | K119: IIBB BSAS | L119: IIBB CABA
G120: =IFERROR(IF(Retenciones_mes2[[#This Row],[CUIT]]="","-",VLOOKUP(Retenciones_mes2[[#This Row],[CUIT]],Lista_CUIT[#All],2,0)),"CUIT NO CARGADO") -> -
G121: =IFERROR(IF(Retenciones_mes2[[#This Row],[CUIT]]="","-",VLOOKUP(Retenciones_mes2[[#This Row],[CUIT]],Lista_CUIT[#All],2,0)),"CUIT NO CARGADO") -> -
G122: =IFERROR(IF(Retenciones_mes2[[#This Row],[CUIT]]="","-",VLOOKUP(Retenciones_mes2[[#This Row],[CUIT]],Lista_CUIT[#All],2,0)),"CUIT NO CARGADO") -> -
G123: =IFERROR(IF(Retenciones_mes2[[#This Row],[CUIT]]="","-",VLOOKUP(Retenciones_mes2[[#This Row],[CUIT]],Lista_CUIT[#All],2,0)),"CUIT NO CARGADO") -> -
G124: =IFERROR(IF(Retenciones_mes2[[#This Row],[CUIT]]="","-",VLOOKUP(Retenciones_mes2[[#This Row],[CUIT]],Lista_CUIT[#All],2,0)),"CUIT NO CARGADO") -> -

Sheet Mar-26
B1: LIBRO IVA COMPRAS | G1: ='Ene-26'!G1:M1 -> RABLEB SRL | N1: =EDATE('Ene-26'!N1,2) -> 46082
B3: TOTAL COMPRAS | G3: TOTAL CREDITO FISCAL | J3: TOTAL VENTAS NETAS | M3: TOTAL DEBITO FISCAL | P3: RESULTADO
B4: =SUM(compras_mes3[[#Totals],[NETO GRAVADO]])+extracto_banco_mes3[[#Totals],[NETO]] -> 6402101 | G4: =compras_mes3[[#Totals],[IVA 21 %]]+compras_mes3[[#Totals],[IVA 27%]]+compras_mes3[[#Totals],[IVA 10,5%]]+extracto_banco_mes3[[#Totals],[IVA 21%]]+extracto_banco_mes3[[#Totals],[IVA 10,5%]] -> 1344441.2 | J4: =venta_a_mes3[[#Totals],[IMPORTE NETO]]+ventas_b_mes3[[#Totals],[IMPORTE NETO]] -> 8636886.1 | M4: =venta_a_mes3[[#Totals],[IVA 21%]]+venta_a_mes3[[#Totals],[IVA 10,5%]]+ventas_b_mes3[[#Totals],[IVA 21%]]+ventas_b_mes3[[#Totals],[IVA 10,5%]] -> 1813746.1 | P4: =G4-M4 -> -469304.87
B8: FECHA | C8: TIPO | D8: PTO VTA | E8: NRO. CPTE | F8: CUIT | G8: RAZON SOCIAL | H8: NETO GRAVADO | I8: IVA 21 % | J8: IVA 27% | K8: IVA 10,5% | L8: PERC. IVA | M8: PERC IIBB BS AS | N8: PERC. IIBB CABA | O8: Otros / No Grav. | P8: TOTAL | Q8: Tipo de Gasto | R8: Provincia
B9: 02/03/2026 | C9: 1 | D9: 2 | E9: 1861 | F9: 30718631730 | G9: =IFERROR(IF(compras_mes3[[#This Row],[CUIT]]="","-",VLOOKUP(compras_mes3[[#This Row],[CUIT]],Lista_CUIT[#All],2,0)),"CUIT NO CARGADO") -> SIMZ S. R. L. | H9: 138866 | I9: =IF(compras_mes3[[#This Row],[NETO GRAVADO]]="","",compras_mes3[[#This Row],[NETO GRAVADO]]*0.21) -> 29161.86 | O9: 0 | P9: =SUM(compras_mes3[[#This Row],[NETO GRAVADO]:[Otros / No Grav.]]) -> 168027.86 | Q9: =IFERROR(IF(compras_mes3[[#This Row],[CUIT]]="","-",VLOOKUP(compras_mes3[[#This Row],[CUIT]],Lista_CUIT[#All],3,0)),"CUIT NO CARGADO") -> 0 | R9: =IFERROR(IF(compras_mes3[[#This Row],[CUIT]]="","-",VLOOKUP(compras_mes3[[#This Row],[CUIT]],Lista_CUIT[#All],4,0)),"CUIT NO CARGADO") -> 0
B10: 31/03/2026 | C10: 3 | D10: 11 | E10: 924152 | F10: 33709585229 | G10: =IFERROR(IF(compras_mes3[[#This Row],[CUIT]]="","-",VLOOKUP(compras_mes3[[#This Row],[CUIT]],Lista_CUIT[#All],2,0)),"CUIT NO CARGADO") -> GOOGLE ARGENTINA S.R.L. | I10: =IF(compras_mes3[[#This Row],[NETO GRAVADO]]="","",compras_mes3[[#This Row],[NETO GRAVADO]]*0.21) | P10: =SUM(compras_mes3[[#This Row],[NETO GRAVADO]:[Otros / No Grav.]]) -> 0 | Q10: =IFERROR(IF(compras_mes3[[#This Row],[CUIT]]="","-",VLOOKUP(compras_mes3[[#This Row],[CUIT]],Lista_CUIT[#All],3,0)),"CUIT NO CARGADO") -> Servicios de publicidad | R10: =IFERROR(IF(compras_mes3[[#This Row],[CUIT]]="","-",VLOOKUP(compras_mes3[[#This Row],[CUIT]],Lista_CUIT[#All],4,0)),"CUIT NO CARGADO") -> 0
B11: 31/03/2026 | C11: 1 | D11: 11 | E11: 1296131 | F11: 33709585229 | G11: =IFERROR(IF(compras_mes3[[#This Row],[CUIT]]="","-",VLOOKUP(compras_mes3[[#This Row],[CUIT]],Lista_CUIT[#All],2,0)),"CUIT NO CARGADO") -> GOOGLE ARGENTINA S.R.L. | H11: 1479018.4 | I11: =IF(compras_mes3[[#This Row],[NETO GRAVADO]]="","",compras_mes3[[#This Row],[NETO GRAVADO]]*0.21) -> 310593.87 | N11: 22185.28 | O11: 44370.55 | P11: =SUM(compras_mes3[[#This Row],[NETO GRAVADO]:[Otros / No Grav.]]) -> 1856168.1 | Q11: =IFERROR(IF(compras_mes3[[#This Row],[CUIT]]="","-",VLOOKUP(compras_mes3[[#This Row],[CUIT]],Lista_CUIT[#All],3,0)),"CUIT NO CARGADO") -> Servicios de publicidad | R11: =IFERROR(IF(compras_mes3[[#This Row],[CUIT]]="","-",VLOOKUP(compras_mes3[[#This Row],[CUIT]],Lista_CUIT[#All],4,0)),"CUIT NO CARGADO") -> 0
B12: 31/03/2026 | C12: 1 | D12: 11 | E12: 1299487 | F12: 33709585229 | G12: =IFERROR(IF(compras_mes3[[#This Row],[CUIT]]="","-",VLOOKUP(compras_mes3[[#This Row],[CUIT]],Lista_CUIT[#All],2,0)),"CUIT NO CARGADO") -> GOOGLE ARGENTINA S.R.L. | H12: 4560000 | I12: =IF(compras_mes3[[#This Row],[NETO GRAVADO]]="","",compras_mes3[[#This Row],[NETO GRAVADO]]*0.21) -> 957600 | N12: 68400 | O12: 136800 | P12: =SUM(compras_mes3[[#This Row],[NETO GRAVADO]:[Otros / No Grav.]]) -> 5722800 | Q12: =IFERROR(IF(compras_mes3[[#This Row],[CUIT]]="","-",VLOOKUP(compras_mes3[[#This Row],[CUIT]],Lista_CUIT[#All],3,0)),"CUIT NO CARGADO") -> Servicios de publicidad | R12: =IFERROR(IF(compras_mes3[[#This Row],[CUIT]]="","-",VLOOKUP(compras_mes3[[#This Row],[CUIT]],Lista_CUIT[#All],4,0)),"CUIT NO CARGADO") -> 0
B13: 20/03/2026 | C13: 1 | D13: 2 | E13: 1728524 | F13: 30710173652 | G13: =IFERROR(IF(compras_mes3[[#This Row],[CUIT]]="","-",VLOOKUP(compras_mes3[[#This Row],[CUIT]],Lista_CUIT[#All],2,0)),"CUIT NO CARGADO") -> DATTATEC.COM S.R.L. | H13: 33057.85 | I13: =IF(compras_mes3[[#This Row],[NETO GRAVADO]]="","",compras_mes3[[#This Row],[NETO GRAVADO]]*0.21) -> 6942.1485 | O13: 0 | P13: =SUM(compras_mes3[[#This Row],[NETO GRAVADO]:[Otros / No Grav.]]) -> 39999.999 | Q13: =IFERROR(IF(compras_mes3[[#This Row],[CUIT]]="","-",VLOOKUP(compras_mes3[[#This Row],[CUIT]],Lista_CUIT[#All],3,0)),"CUIT NO CARGADO") -> 0 | R13: =IFERROR(IF(compras_mes3[[#This Row],[CUIT]]="","-",VLOOKUP(compras_mes3[[#This Row],[CUIT]],Lista_CUIT[#All],4,0)),"CUIT NO CARGADO") -> 0
B14: 20/03/2026 | C14: 1 | D14: 2 | E14: 1728525 | F14: 30710173652 | G14: =IFERROR(IF(compras_mes3[[#This Row],[CUIT]]="","-",VLOOKUP(compras_mes3[[#This Row],[CUIT]],Lista_CUIT[#All],2,0)),"CUIT NO CARGADO") -> DATTATEC.COM S.R.L. | H14: 79150 | I14: =IF(compras_mes3[[#This Row],[NETO GRAVADO]]="","",compras_mes3[[#This Row],[NETO GRAVADO]]*0.21) -> 16621.5 | O14: 0 | P14: =SUM(compras_mes3[[#This Row],[NETO GRAVADO]:[Otros / No Grav.]]) -> 95771.5 | Q14: =IFERROR(IF(compras_mes3[[#This Row],[CUIT]]="","-",VLOOKUP(compras_mes3[[#This Row],[CUIT]],Lista_CUIT[#All],3,0)),"CUIT NO CARGADO") -> 0 | R14: =IFERROR(IF(compras_mes3[[#This Row],[CUIT]]="","-",VLOOKUP(compras_mes3[[#This Row],[CUIT]],Lista_CUIT[#All],4,0)),"CUIT NO CARGADO") -> 0
B15: 24/03/2026 | C15: 1 | D15: 2 | E15: 1730436 | F15: 30710173652 | G15: =IFERROR(IF(compras_mes3[[#This Row],[CUIT]]="","-",VLOOKUP(compras_mes3[[#This Row],[CUIT]],Lista_CUIT[#All],2,0)),"CUIT NO CARGADO") -> DATTATEC.COM S.R.L. | H15: 31660 | I15: =IF(compras_mes3[[#This Row],[NETO GRAVADO]]="","",compras_mes3[[#This Row],[NETO GRAVADO]]*0.21) -> 6648.6 | O15: 0 | P15: =SUM(compras_mes3[[#This Row],[NETO GRAVADO]:[Otros / No Grav.]]) -> 38308.6 | Q15: =IFERROR(IF(compras_mes3[[#This Row],[CUIT]]="","-",VLOOKUP(compras_mes3[[#This Row],[CUIT]],Lista_CUIT[#All],3,0)),"CUIT NO CARGADO") -> 0 | R15: =IFERROR(IF(compras_mes3[[#This Row],[CUIT]]="","-",VLOOKUP(compras_mes3[[#This Row],[CUIT]],Lista_CUIT[#All],4,0)),"CUIT NO CARGADO") -> 0
G16: =IFERROR(IF(compras_mes3[[#This Row],[CUIT]]="","-",VLOOKUP(compras_mes3[[#This Row],[CUIT]],Lista_CUIT[#All],2,0)),"CUIT NO CARGADO") -> - | I16: =IF(compras_mes3[[#This Row],[NETO GRAVADO]]="","",compras_mes3[[#This Row],[NETO GRAVADO]]*0.21) | P16: =SUM(compras_mes3[[#This Row],[NETO GRAVADO]:[Otros / No Grav.]]) -> 0 | Q16: =IFERROR(IF(compras_mes3[[#This Row],[CUIT]]="","-",VLOOKUP(compras_mes3[[#This Row],[CUIT]],Lista_CUIT[#All],3,0)),"CUIT NO CARGADO") -> - | R16: =IFERROR(IF(compras_mes3[[#This Row],[CUIT]]="","-",VLOOKUP(compras_mes3[[#This Row],[CUIT]],Lista_CUIT[#All],4,0)),"CUIT NO CARGADO") -> -
G17: =IFERROR(IF(compras_mes3[[#This Row],[CUIT]]="","-",VLOOKUP(compras_mes3[[#This Row],[CUIT]],Lista_CUIT[#All],2,0)),"CUIT NO CARGADO") -> - | I17: =IF(compras_mes3[[#This Row],[NETO GRAVADO]]="","",compras_mes3[[#This Row],[NETO GRAVADO]]*0.21) | P17: =SUM(compras_mes3[[#This Row],[NETO GRAVADO]:[Otros / No Grav.]]) -> 0 | Q17: =IFERROR(IF(compras_mes3[[#This Row],[CUIT]]="","-",VLOOKUP(compras_mes3[[#This Row],[CUIT]],Lista_CUIT[#All],3,0)),"CUIT NO CARGADO") -> - | R17: =IFERROR(IF(compras_mes3[[#This Row],[CUIT]]="","-",VLOOKUP(compras_mes3[[#This Row],[CUIT]],Lista_CUIT[#All],4,0)),"CUIT NO CARGADO") -> -
G18: =IFERROR(IF(compras_mes3[[#This Row],[CUIT]]="","-",VLOOKUP(compras_mes3[[#This Row],[CUIT]],Lista_CUIT[#All],2,0)),"CUIT NO CARGADO") -> - | I18: =IF(compras_mes3[[#This Row],[NETO GRAVADO]]="","",compras_mes3[[#This Row],[NETO GRAVADO]]*0.21) | P18: =SUM(compras_mes3[[#This Row],[NETO GRAVADO]:[Otros / No Grav.]]) -> 0 | Q18: =IFERROR(IF(compras_mes3[[#This Row],[CUIT]]="","-",VLOOKUP(compras_mes3[[#This Row],[CUIT]],Lista_CUIT[#All],3,0)),"CUIT NO CARGADO") -> - | R18: =IFERROR(IF(compras_mes3[[#This Row],[CUIT]]="","-",VLOOKUP(compras_mes3[[#This Row],[CUIT]],Lista_CUIT[#All],4,0)),"CUIT NO CARGADO") -> -
G19: =IFERROR(IF(compras_mes3[[#This Row],[CUIT]]="","-",VLOOKUP(compras_mes3[[#This Row],[CUIT]],Lista_CUIT[#All],2,0)),"CUIT NO CARGADO") -> - | I19: =IF(compras_mes3[[#This Row],[NETO GRAVADO]]="","",compras_mes3[[#This Row],[NETO GRAVADO]]*0.21) | P19: =SUM(compras_mes3[[#This Row],[NETO GRAVADO]:[Otros / No Grav.]]) -> 0 | Q19: =IFERROR(IF(compras_mes3[[#This Row],[CUIT]]="","-",VLOOKUP(compras_mes3[[#This Row],[CUIT]],Lista_CUIT[#All],3,0)),"CUIT NO CARGADO") -> - | R19: =IFERROR(IF(compras_mes3[[#This Row],[CUIT]]="","-",VLOOKUP(compras_mes3[[#This Row],[CUIT]],Lista_CUIT[#All],4,0)),"CUIT NO CARGADO") -> -
G20: =IFERROR(IF(compras_mes3[[#This Row],[CUIT]]="","-",VLOOKUP(compras_mes3[[#This Row],[CUIT]],Lista_CUIT[#All],2,0)),"CUIT NO CARGADO") -> - | I20: =IF(compras_mes3[[#This Row],[NETO GRAVADO]]="","",compras_mes3[[#This Row],[NETO GRAVADO]]*0.21) | P20: =SUM(compras_mes3[[#This Row],[NETO GRAVADO]:[Otros / No Grav.]]) -> 0 | Q20: =IFERROR(IF(compras_mes3[[#This Row],[CUIT]]="","-",VLOOKUP(compras_mes3[[#This Row],[CUIT]],Lista_CUIT[#All],3,0)),"CUIT NO CARGADO") -> - | R20: =IFERROR(IF(compras_mes3[[#This Row],[CUIT]]="","-",VLOOKUP(compras_mes3[[#This Row],[CUIT]],Lista_CUIT[#All],4,0)),"CUIT NO CARGADO") -> -
G21: =IFERROR(IF(compras_mes3[[#This Row],[CUIT]]="","-",VLOOKUP(compras_mes3[[#This Row],[CUIT]],Lista_CUIT[#All],2,0)),"CUIT NO CARGADO") -> - | I21: =IF(compras_mes3[[#This Row],[NETO GRAVADO]]="","",compras_mes3[[#This Row],[NETO GRAVADO]]*0.21) | P21: =SUM(compras_mes3[[#This Row],[NETO GRAVADO]:[Otros / No Grav.]]) -> 0 | Q21: =IFERROR(IF(compras_mes3[[#This Row],[CUIT]]="","-",VLOOKUP(compras_mes3[[#This Row],[CUIT]],Lista_CUIT[#All],3,0)),"CUIT NO CARGADO") -> - | R21: =IFERROR(IF(compras_mes3[[#This Row],[CUIT]]="","-",VLOOKUP(compras_mes3[[#This Row],[CUIT]],Lista_CUIT[#All],4,0)),"CUIT NO CARGADO") -> -
G22: =IFERROR(IF(compras_mes3[[#This Row],[CUIT]]="","-",VLOOKUP(compras_mes3[[#This Row],[CUIT]],Lista_CUIT[#All],2,0)),"CUIT NO CARGADO") -> - | I22: =IF(compras_mes3[[#This Row],[NETO GRAVADO]]="","",compras_mes3[[#This Row],[NETO GRAVADO]]*0.21) | P22: =SUM(compras_mes3[[#This Row],[NETO GRAVADO]:[Otros / No Grav.]]) -> 0 | Q22: =IFERROR(IF(compras_mes3[[#This Row],[CUIT]]="","-",VLOOKUP(compras_mes3[[#This Row],[CUIT]],Lista_CUIT[#All],3,0)),"CUIT NO CARGADO") -> - | R22: =IFERROR(IF(compras_mes3[[#This Row],[CUIT]]="","-",VLOOKUP(compras_mes3[[#This Row],[CUIT]],Lista_CUIT[#All],4,0)),"CUIT NO CARGADO") -> -
G23: =IFERROR(IF(compras_mes3[[#This Row],[CUIT]]="","-",VLOOKUP(compras_mes3[[#This Row],[CUIT]],Lista_CUIT[#All],2,0)),"CUIT NO CARGADO") -> - | I23: =IF(compras_mes3[[#This Row],[NETO GRAVADO]]="","",compras_mes3[[#This Row],[NETO GRAVADO]]*0.21) | P23: =SUM(compras_mes3[[#This Row],[NETO GRAVADO]:[Otros / No Grav.]]) -> 0 | Q23: =IFERROR(IF(compras_mes3[[#This Row],[CUIT]]="","-",VLOOKUP(compras_mes3[[#This Row],[CUIT]],Lista_CUIT[#All],3,0)),"CUIT NO CARGADO") -> - | R23: =IFERROR(IF(compras_mes3[[#This Row],[CUIT]]="","-",VLOOKUP(compras_mes3[[#This Row],[CUIT]],Lista_CUIT[#All],4,0)),"CUIT NO CARGADO") -> -
G24: =IFERROR(IF(compras_mes3[[#This Row],[CUIT]]="","-",VLOOKUP(compras_mes3[[#This Row],[CUIT]],Lista_CUIT[#All],2,0)),"CUIT NO CARGADO") -> - | I24: =IF(compras_mes3[[#This Row],[NETO GRAVADO]]="","",compras_mes3[[#This Row],[NETO GRAVADO]]*0.21) | P24: =SUM(compras_mes3[[#This Row],[NETO GRAVADO]:[Otros / No Grav.]]) -> 0 | Q24: =IFERROR(IF(compras_mes3[[#This Row],[CUIT]]="","-",VLOOKUP(compras_mes3[[#This Row],[CUIT]],Lista_CUIT[#All],3,0)),"CUIT NO CARGADO") -> - | R24: =IFERROR(IF(compras_mes3[[#This Row],[CUIT]]="","-",VLOOKUP(compras_mes3[[#This Row],[CUIT]],Lista_CUIT[#All],4,0)),"CUIT NO CARGADO") -> -
G25: =IFERROR(IF(compras_mes3[[#This Row],[CUIT]]="","-",VLOOKUP(compras_mes3[[#This Row],[CUIT]],Lista_CUIT[#All],2,0)),"CUIT NO CARGADO") -> - | I25: =IF(compras_mes3[[#This Row],[NETO GRAVADO]]="","",compras_mes3[[#This Row],[NETO GRAVADO]]*0.21) | P25: =SUM(compras_mes3[[#This Row],[NETO GRAVADO]:[Otros / No Grav.]]) -> 0 | Q25: =IFERROR(IF(compras_mes3[[#This Row],[CUIT]]="","-",VLOOKUP(compras_mes3[[#This Row],[CUIT]],Lista_CUIT[#All],3,0)),"CUIT NO CARGADO") -> - | R25: =IFERROR(IF(compras_mes3[[#This Row],[CUIT]]="","-",VLOOKUP(compras_mes3[[#This Row],[CUIT]],Lista_CUIT[#All],4,0)),"CUIT NO CARGADO") -> -
G26: =IFERROR(IF(compras_mes3[[#This Row],[CUIT]]="","-",VLOOKUP(compras_mes3[[#This Row],[CUIT]],Lista_CUIT[#All],2,0)),"CUIT NO CARGADO") -> - | I26: =IF(compras_mes3[[#This Row],[NETO GRAVADO]]="","",compras_mes3[[#This Row],[NETO GRAVADO]]*0.21) | P26: =SUM(compras_mes3[[#This Row],[NETO GRAVADO]:[Otros / No Grav.]]) -> 0 | Q26: =IFERROR(IF(compras_mes3[[#This Row],[CUIT]]="","-",VLOOKUP(compras_mes3[[#This Row],[CUIT]],Lista_CUIT[#All],3,0)),"CUIT NO CARGADO") -> - | R26: =IFERROR(IF(compras_mes3[[#This Row],[CUIT]]="","-",VLOOKUP(compras_mes3[[#This Row],[CUIT]],Lista_CUIT[#All],4,0)),"CUIT NO CARGADO") -> -
G27: =IFERROR(IF(compras_mes3[[#This Row],[CUIT]]="","-",VLOOKUP(compras_mes3[[#This Row],[CUIT]],Lista_CUIT[#All],2,0)),"CUIT NO CARGADO") -> - | I27: =IF(compras_mes3[[#This Row],[NETO GRAVADO]]="","",compras_mes3[[#This Row],[NETO GRAVADO]]*0.21) | P27: =SUM(compras_mes3[[#This Row],[NETO GRAVADO]:[Otros / No Grav.]]) -> 0 | Q27: =IFERROR(IF(compras_mes3[[#This Row],[CUIT]]="","-",VLOOKUP(compras_mes3[[#This Row],[CUIT]],Lista_CUIT[#All],3,0)),"CUIT NO CARGADO") -> - | R27: =IFERROR(IF(compras_mes3[[#This Row],[CUIT]]="","-",VLOOKUP(compras_mes3[[#This Row],[CUIT]],Lista_CUIT[#All],4,0)),"CUIT NO CARGADO") -> -
... G41: =IFERROR(IF(compras_mes3[[#This Row],[CUIT]]="","-",VLOOKUP(compras_mes3[[#This Row],[CUIT]],Lista_CUIT[#All],2,0)),"CUIT NO CARGADO") -> - | I41: =IF(compras_mes3[[#This Row],[NETO GRAVADO]]="","",compras_mes3[[#This Row],[NETO GRAVADO]]*0.21) | P41: =SUM(compras_mes3[[#This Row],[NETO GRAVADO]:[Otros / No Grav.]]) -> 0 | Q41: =IFERROR(IF(compras_mes3[[#This Row],[CUIT]]="","-",VLOOKUP(compras_mes3[[#This Row],[CUIT]],Lista_CUIT[#All],3,0)),"CUIT NO CARGADO") -> - | R41: =IFERROR(IF(compras_mes3[[#This Row],[CUIT]]="","-",VLOOKUP(compras_mes3[[#This Row],[CUIT]],Lista_CUIT[#All],4,0)),"CUIT NO CARGADO") -> -
G42: =IFERROR(IF(compras_mes3[[#This Row],[CUIT]]="","-",VLOOKUP(compras_mes3[[#This Row],[CUIT]],Lista_CUIT[#All],2,0)),"CUIT NO CARGADO") -> - | I42: =IF(compras_mes3[[#This Row],[NETO GRAVADO]]="","",compras_mes3[[#This Row],[NETO GRAVADO]]*0.21) | N42: -36.51 | O42: -73.01 | P42: =SUM(compras_mes3[[#This Row],[NETO GRAVADO]:[Otros / No Grav.]]) -> -109.52 | Q42: =IFERROR(IF(compras_mes3[[#This Row],[CUIT]]="","-",VLOOKUP(compras_mes3[[#This Row],[CUIT]],Lista_CUIT[#All],3,0)),"CUIT NO CARGADO") -> - | R42: =IFERROR(IF(compras_mes3[[#This Row],[CUIT]]="","-",VLOOKUP(compras_mes3[[#This Row],[CUIT]],Lista_CUIT[#All],4,0)),"CUIT NO CARGADO") -> -
B43: Total | H43: =SUBTOTAL(109,compras_mes3[NETO GRAVADO]) -> 6321752.3 | I43: =SUBTOTAL(109,compras_mes3[IVA 21 %]) -> 1327568 | J43: =SUBTOTAL(109,compras_mes3[IVA 27%]) -> 0 | K43: =SUBTOTAL(109,compras_mes3[IVA 10,5%]) -> 0 | L43: =SUBTOTAL(109,compras_mes3[PERC. IVA]) -> 0 | M43: =SUBTOTAL(109,compras_mes3[PERC IIBB BS AS]) -> 0 | N43: =SUBTOTAL(109,compras_mes3[PERC. IIBB CABA]) -> 90548.77 | O43: =SUBTOTAL(109,compras_mes3[Otros / No Grav.]) -> 181097.54 | P43: =SUBTOTAL(109,compras_mes3[TOTAL]) -> 7920966.5
D48: LIQUIDACION EXTRACTOS BANCARIOS-TARJETAS
D49: FECHA | E49: NRO CPTE | F49: BANCO | G49: NETO | H49: IVA 21% | I49: IVA 10,5% | J49: RET IIBB CABA | K49: PERC IVA | L49: PERC IIBB | M49: TOTAL
D50: 46112 | E50: 31032026 | F50: GALICIA | G50: =extracto_banco_mes3[[#This Row],[IVA 21%]]/0.21 -> 80348.762 | H50: 16873.24 | J50: 1205.23 | K50: 2410.46 | M50: =SUM(G50:L50) -> 100837.69
G51: =extracto_banco_mes3[[#This Row],[IVA 21%]]/0.21 -> 0 | I51: =extracto_banco_mes3[[#This Row],[NETO]]*0.105 -> 0 | M51: =SUM(G51:L51) -> 0
G52: =extracto_banco_mes3[[#This Row],[IVA 21%]]/0.21 -> 0 | I52: =extracto_banco_mes3[[#This Row],[NETO]]*0.105 -> 0 | M52: =SUM(G52:L52) -> 0
D53: Total | G53: =SUBTOTAL(109,extracto_banco_mes3[NETO]) -> 80348.762 | H53: =SUBTOTAL(109,extracto_banco_mes3[IVA 21%]) -> 16873.24 | I53: =SUBTOTAL(109,extracto_banco_mes3[IVA 10,5%]) -> 0 | J53: =SUBTOTAL(109,extracto_banco_mes3[RET IIBB CABA]) -> 1205.23 | K53: =SUBTOTAL(109,extracto_banco_mes3[PERC IVA]) -> 2410.46 | L53: =SUBTOTAL(109,extracto_banco_mes3[PERC IIBB]) -> 0
D57: FACTURAS C
D58: FECHA | E58: PTO VTA | F58: FC Nº | G58: CUIT | H58: RAZON SOCIAL | I58: TOTAL | J58: TIPO DE GASTO | K58: Provincia
D59: 02/03/2026 | E59: 1 | F59: 4 | G59: 27403975821 | H59: =IFERROR(IF(factura_c_mes3[[#This Row],[CUIT]]="","-",VLOOKUP(factura_c_mes3[[#This Row],[CUIT]],Lista_CUIT[#All],2,0)),"CUIT NO CARGADO") -> BARROSO VALENTINA | I59: 538500 | J59: =IFERROR(IF(factura_c_mes3[[#This Row],[CUIT]]="","-",VLOOKUP(factura_c_mes3[[#This Row],[CUIT]],Lista_CUIT[#All],3,0)),"CUIT NO CARGADO") -> 0 | K59: =IFERROR(IF(factura_c_mes3[[#This Row],[CUIT]]="","-",VLOOKUP(factura_c_mes3[[#This Row],[CUIT]],Lista_CUIT[#All],4,0)),"CUIT NO CARGADO") -> 0
D60: 03/03/2026 | E60: 2 | F60: 1133 | G60: 20400104094 | H60: =IFERROR(IF(factura_c_mes3[[#This Row],[CUIT]]="","-",VLOOKUP(factura_c_mes3[[#This Row],[CUIT]],Lista_CUIT[#All],2,0)),"CUIT NO CARGADO") -> BOTINDARI FEDERICO DANIEL | I60: 300000 | J60: =IFERROR(IF(factura_c_mes3[[#This Row],[CUIT]]="","-",VLOOKUP(factura_c_mes3[[#This Row],[CUIT]],Lista_CUIT[#All],3,0)),"CUIT NO CARGADO") -> HONORARIOS CONTABLE | K60: =IFERROR(IF(factura_c_mes3[[#This Row],[CUIT]]="","-",VLOOKUP(factura_c_mes3[[#This Row],[CUIT]],Lista_CUIT[#All],4,0)),"CUIT NO CARGADO") -> 0
D61: 09/03/2026 | E61: 2 | F61: 64 | G61: 23380288079 | H61: =IFERROR(IF(factura_c_mes3[[#This Row],[CUIT]]="","-",VLOOKUP(factura_c_mes3[[#This Row],[CUIT]],Lista_CUIT[#All],2,0)),"CUIT NO CARGADO") -> CASTROMAN AGUSTIN | I61: 598000 | J61: =IFERROR(IF(factura_c_mes3[[#This Row],[CUIT]]="","-",VLOOKUP(factura_c_mes3[[#This Row],[CUIT]],Lista_CUIT[#All],3,0)),"CUIT NO CARGADO") -> 0 | K61: =IFERROR(IF(factura_c_mes3[[#This Row],[CUIT]]="","-",VLOOKUP(factura_c_mes3[[#This Row],[CUIT]],Lista_CUIT[#All],4,0)),"CUIT NO CARGADO") -> 0
D62: 13/03/2026 | E62: 2 | F62: 164 | G62: 27341104845 | H62: =IFERROR(IF(factura_c_mes3[[#This Row],[CUIT]]="","-",VLOOKUP(factura_c_mes3[[#This Row],[CUIT]],Lista_CUIT[#All],2,0)),"CUIT NO CARGADO") -> BOSSI MARIA PAULA | I62: 342000 | J62: =IFERROR(IF(factura_c_mes3[[#This Row],[CUIT]]="","-",VLOOKUP(factura_c_mes3[[#This Row],[CUIT]],Lista_CUIT[#All],3,0)),"CUIT NO CARGADO") -> 0 | K62: =IFERROR(IF(factura_c_mes3[[#This Row],[CUIT]]="","-",VLOOKUP(factura_c_mes3[[#This Row],[CUIT]],Lista_CUIT[#All],4,0)),"CUIT NO CARGADO") -> 0
D63: 16/03/2026 | E63: 1 | F63: 330 | G63: 27386311000 | H63: =IFERROR(IF(factura_c_mes3[[#This Row],[CUIT]]="","-",VLOOKUP(factura_c_mes3[[#This Row],[CUIT]],Lista_CUIT[#All],2,0)),"CUIT NO CARGADO") -> OPANASIUK MACARENA ANTONELLA | I63: 1000000 | J63: =IFERROR(IF(factura_c_mes3[[#This Row],[CUIT]]="","-",VLOOKUP(factura_c_mes3[[#This Row],[CUIT]],Lista_CUIT[#All],3,0)),"CUIT NO CARGADO") -> 0 | K63: =IFERROR(IF(factura_c_mes3[[#This Row],[CUIT]]="","-",VLOOKUP(factura_c_mes3[[#This Row],[CUIT]],Lista_CUIT[#All],4,0)),"CUIT NO CARGADO") -> 0
D64: 24/03/2026 | E64: 51 | F64: 195 | G64: 20300985158 | H64: =IFERROR(IF(factura_c_mes3[[#This Row],[CUIT]]="","-",VLOOKUP(factura_c_mes3[[#This Row],[CUIT]],Lista_CUIT[#All],2,0)),"CUIT NO CARGADO") -> GONZALEZ NESTOR RICARDO | I64: 900000 | J64: =IFERROR(IF(factura_c_mes3[[#This Row],[CUIT]]="","-",VLOOKUP(factura_c_mes3[[#This Row],[CUIT]],Lista_CUIT[#All],3,0)),"CUIT NO CARGADO") -> 0 | K64: =IFERROR(IF(factura_c_mes3[[#This Row],[CUIT]]="","-",VLOOKUP(factura_c_mes3[[#This Row],[CUIT]],Lista_CUIT[#All],4,0)),"CUIT NO CARGADO") -> 0
H65: =IFERROR(IF(factura_c_mes3[[#This Row],[CUIT]]="","-",VLOOKUP(factura_c_mes3[[#This Row],[CUIT]],Lista_CUIT[#All],2,0)),"CUIT NO CARGADO") -> - | J65: =IFERROR(IF(factura_c_mes3[[#This Row],[CUIT]]="","-",VLOOKUP(factura_c_mes3[[#This Row],[CUIT]],Lista_CUIT[#All],3,0)),"CUIT NO CARGADO") -> - | K65: =IFERROR(IF(factura_c_mes3[[#This Row],[CUIT]]="","-",VLOOKUP(factura_c_mes3[[#This Row],[CUIT]],Lista_CUIT[#All],4,0)),"CUIT NO CARGADO") -> -
H66: =IFERROR(IF(factura_c_mes3[[#This Row],[CUIT]]="","-",VLOOKUP(factura_c_mes3[[#This Row],[CUIT]],Lista_CUIT[#All],2,0)),"CUIT NO CARGADO") -> - | J66: =IFERROR(IF(factura_c_mes3[[#This Row],[CUIT]]="","-",VLOOKUP(factura_c_mes3[[#This Row],[CUIT]],Lista_CUIT[#All],3,0)),"CUIT NO CARGADO") -> - | K66: =IFERROR(IF(factura_c_mes3[[#This Row],[CUIT]]="","-",VLOOKUP(factura_c_mes3[[#This Row],[CUIT]],Lista_CUIT[#All],4,0)),"CUIT NO CARGADO") -> -
D67: Total | I67: =SUBTOTAL(109,factura_c_mes3[TOTAL]) -> 3678500
B73: LIBRO IVA VENTAS | K73: =N1 -> 46082
B75: VENTAS "A"
B76: FECHA | C76: TIPO | D76: PTO VENTA | E76: Nº FACTURA | F76: CUIT | G76: RAZON SOCIAL | H76: IMPORTE NETO | I76: IVA 21% | J76: IVA 10,5% | K76: EXENTO | L76: TOTAL | M76: Provincia
B77: 31/03/2026 | C77: 3 | D77: 1 | E77: 54 | F77: 30708604255 | G77: =IFERROR(IF(venta_a_mes3[[#This Row],[CUIT]]="","-",VLOOKUP(venta_a_mes3[[#This Row],[CUIT]],Lista_CUIT[#All],2,0)),"CUIT NO CARGADO") -> NAR TECHNOLOGIES S.R.L. | H77: -590909.1 | I77: =venta_a_mes3[[#This Row],[IMPORTE NETO]]*0.21 -> -124090.91 | L77: =SUM(venta_a_mes3[[#This Row],[IMPORTE NETO]:[EXENTO]]) -> -715000.01
B78: 31/03/2026 | C78: 3 | D78: 1 | E78: 55 | F78: 20287305460 | G78: =IFERROR(IF(venta_a_mes3[[#This Row],[CUIT]]="","-",VLOOKUP(venta_a_mes3[[#This Row],[CUIT]],Lista_CUIT[#All],2,0)),"CUIT NO CARGADO") -> LANDI GERONIMO | H78: -147107.43 | I78: =venta_a_mes3[[#This Row],[IMPORTE NETO]]*0.21 -> -30892.56 | L78: =SUM(venta_a_mes3[[#This Row],[IMPORTE NETO]:[EXENTO]]) -> -177999.99
B79: 31/03/2026 | C79: 3 | D79: 1 | E79: 56 | F79: 30717465101 | G79: =IFERROR(IF(venta_a_mes3[[#This Row],[CUIT]]="","-",VLOOKUP(venta_a_mes3[[#This Row],[CUIT]],Lista_CUIT[#All],2,0)),"CUIT NO CARGADO") -> EMPRENDIMIENTOS SHOPGLASS S. R. L. | H79: -147107.43 | I79: =venta_a_mes3[[#This Row],[IMPORTE NETO]]*0.21 -> -30892.56 | L79: =SUM(venta_a_mes3[[#This Row],[IMPORTE NETO]:[EXENTO]]) -> -177999.99
B80: 31/03/2026 | C80: 3 | D80: 1 | E80: 57 | F80: 30714864803 | G80: =IFERROR(IF(venta_a_mes3[[#This Row],[CUIT]]="","-",VLOOKUP(venta_a_mes3[[#This Row],[CUIT]],Lista_CUIT[#All],2,0)),"CUIT NO CARGADO") -> DIAZ Y GIUSEPPETTI S. R. L. | H80: -202612.24 | I80: =venta_a_mes3[[#This Row],[IMPORTE NETO]]*0.21 -> -42548.57 | L80: =SUM(venta_a_mes3[[#This Row],[IMPORTE NETO]:[EXENTO]]) -> -245160.81
B81: 02/03/2026 | C81: 1 | D81: 1 | E81: 649 | F81: 30715751557 | G81: =IFERROR(IF(venta_a_mes3[[#This Row],[CUIT]]="","-",VLOOKUP(venta_a_mes3[[#This Row],[CUIT]],Lista_CUIT[#All],2,0)),"CUIT NO CARGADO") -> TIXIT SRL | H81: 590909.1 | I81: =venta_a_mes3[[#This Row],[IMPORTE NETO]]*0.21 -> 124090.91 | L81: =SUM(venta_a_mes3[[#This Row],[IMPORTE NETO]:[EXENTO]]) -> 715000.01
B82: 02/03/2026 | C82: 1 | D82: 1 | E82: 650 | F82: 30714375241 | G82: =IFERROR(IF(venta_a_mes3[[#This Row],[CUIT]]="","-",VLOOKUP(venta_a_mes3[[#This Row],[CUIT]],Lista_CUIT[#All],2,0)),"CUIT NO CARGADO") -> POWER-RECORDS S.A | H82: 590909.1 | I82: =venta_a_mes3[[#This Row],[IMPORTE NETO]]*0.21 -> 124090.91 | L82: =SUM(venta_a_mes3[[#This Row],[IMPORTE NETO]:[EXENTO]]) -> 715000.01
B83: 02/03/2026 | C83: 1 | D83: 1 | E83: 651 | F83: 30718553357 | G83: =IFERROR(IF(venta_a_mes3[[#This Row],[CUIT]]="","-",VLOOKUP(venta_a_mes3[[#This Row],[CUIT]],Lista_CUIT[#All],2,0)),"CUIT NO CARGADO") -> EMIGRA CON TU MASCOTA S.R.L. | H83: 590909.1 | I83: =venta_a_mes3[[#This Row],[IMPORTE NETO]]*0.21 -> 124090.91 | L83: =SUM(venta_a_mes3[[#This Row],[IMPORTE NETO]:[EXENTO]]) -> 715000.01
B84: 02/03/2026 | C84: 1 | D84: 1 | E84: 652 | F84: 30708404485 | G84: =IFERROR(IF(venta_a_mes3[[#This Row],[CUIT]]="","-",VLOOKUP(venta_a_mes3[[#This Row],[CUIT]],Lista_CUIT[#All],2,0)),"CUIT NO CARGADO") -> SOLDARGEN S.A. | H84: 590909.1 | I84: =venta_a_mes3[[#This Row],[IMPORTE NETO]]*0.21 -> 124090.91 | L84: =SUM(venta_a_mes3[[#This Row],[IMPORTE NETO]:[EXENTO]]) -> 715000.01
B85: 02/03/2026 | C85: 1 | D85: 1 | E85: 653 | F85: 30708604255 | G85: =IFERROR(IF(venta_a_mes3[[#This Row],[CUIT]]="","-",VLOOKUP(venta_a_mes3[[#This Row],[CUIT]],Lista_CUIT[#All],2,0)),"CUIT NO CARGADO") -> NAR TECHNOLOGIES S.R.L. | H85: 590909.1 | I85: =venta_a_mes3[[#This Row],[IMPORTE NETO]]*0.21 -> 124090.91 | L85: =SUM(venta_a_mes3[[#This Row],[IMPORTE NETO]:[EXENTO]]) -> 715000.01
B86: 02/03/2026 | C86: 1 | D86: 1 | E86: 654 | F86: 24368969350 | G86: =IFERROR(IF(venta_a_mes3[[#This Row],[CUIT]]="","-",VLOOKUP(venta_a_mes3[[#This Row],[CUIT]],Lista_CUIT[#All],2,0)),"CUIT NO CARGADO") -> MARANO CORVALAN MARTIN MARIANO | H86: 295454.57 | I86: =venta_a_mes3[[#This Row],[IMPORTE NETO]]*0.21 -> 62045.46 | L86: =SUM(venta_a_mes3[[#This Row],[IMPORTE NETO]:[EXENTO]]) -> 357500.03
B87: 02/03/2026 | C87: 1 | D87: 1 | E87: 655 | F87: 30688955749 | G87: =IFERROR(IF(venta_a_mes3[[#This Row],[CUIT]]="","-",VLOOKUP(venta_a_mes3[[#This Row],[CUIT]],Lista_CUIT[#All],2,0)),"CUIT NO CARGADO") -> LISERAR S A | H87: 196694.24 | I87: =venta_a_mes3[[#This Row],[IMPORTE NETO]]*0.21 -> 41305.79 | L87: =SUM(venta_a_mes3[[#This Row],[IMPORTE NETO]:[EXENTO]]) -> 238000.03
B88: 02/03/2026 | C88: 1 | D88: 1 | E88: 656 | F88: 20279415656 | G88: =IFERROR(IF(venta_a_mes3[[#This Row],[CUIT]]="","-",VLOOKUP(venta_a_mes3[[#This Row],[CUIT]],Lista_CUIT[#All],2,0)),"CUIT NO CARGADO") -> CECCO ALVARO GONZALO | H88: 147107.43 | I88: =venta_a_mes3[[#This Row],[IMPORTE NETO]]*0.21 -> 30892.56 | L88: =SUM(venta_a_mes3[[#This Row],[IMPORTE NETO]:[EXENTO]]) -> 177999.99
... B95: 02/03/2026 | C95: 1 | D95: 1 | E95: 663 | F95: 20320573948 | G95: =IFERROR(IF(venta_a_mes3[[#This Row],[CUIT]]="","-",VLOOKUP(venta_a_mes3[[#This Row],[CUIT]],Lista_CUIT[#All],2,0)),"CUIT NO CARGADO") -> CAVALLOTTI MARCOS DANIEL | H95: 196694.24 | I95: =venta_a_mes3[[#This Row],[IMPORTE NETO]]*0.21 -> 41305.79 | L95: =SUM(venta_a_mes3[[#This Row],[IMPORTE NETO]:[EXENTO]]) -> 238000.03
G96: =IFERROR(IF(venta_a_mes3[[#This Row],[CUIT]]="","-",VLOOKUP(venta_a_mes3[[#This Row],[CUIT]],Lista_CUIT[#All],2,0)),"CUIT NO CARGADO") -> - | I96: =venta_a_mes3[[#This Row],[IMPORTE NETO]]*0.21 -> 0 | L96: =SUM(venta_a_mes3[[#This Row],[IMPORTE NETO]:[EXENTO]]) -> 0
G97: =IFERROR(IF(venta_a_mes3[[#This Row],[CUIT]]="","-",VLOOKUP(venta_a_mes3[[#This Row],[CUIT]],Lista_CUIT[#All],2,0)),"CUIT NO CARGADO") -> - | I97: =venta_a_mes3[[#This Row],[IMPORTE NETO]]*0.21 -> 0 | L97: =SUM(venta_a_mes3[[#This Row],[IMPORTE NETO]:[EXENTO]]) -> 0
G98: =IFERROR(IF(venta_a_mes3[[#This Row],[CUIT]]="","-",VLOOKUP(venta_a_mes3[[#This Row],[CUIT]],Lista_CUIT[#All],2,0)),"CUIT NO CARGADO") -> - | I98: =venta_a_mes3[[#This Row],[IMPORTE NETO]]*0.21 -> 0 | L98: =SUM(venta_a_mes3[[#This Row],[IMPORTE NETO]:[EXENTO]]) -> 0
G99: =IFERROR(IF(venta_a_mes3[[#This Row],[CUIT]]="","-",VLOOKUP(venta_a_mes3[[#This Row],[CUIT]],Lista_CUIT[#All],2,0)),"CUIT NO CARGADO") -> - | I99: =venta_a_mes3[[#This Row],[IMPORTE NETO]]*0.21 -> 0 | L99: =SUM(venta_a_mes3[[#This Row],[IMPORTE NETO]:[EXENTO]]) -> 0
G100: =IFERROR(IF(venta_a_mes3[[#This Row],[CUIT]]="","-",VLOOKUP(venta_a_mes3[[#This Row],[CUIT]],Lista_CUIT[#All],2,0)),"CUIT NO CARGADO") -> - | I100: =venta_a_mes3[[#This Row],[IMPORTE NETO]]*0.21 -> 0 | L100: =SUM(venta_a_mes3[[#This Row],[IMPORTE NETO]:[EXENTO]]) -> 0
G101: =IFERROR(IF(venta_a_mes3[[#This Row],[CUIT]]="","-",VLOOKUP(venta_a_mes3[[#This Row],[CUIT]],Lista_CUIT[#All],2,0)),"CUIT NO CARGADO") -> - | I101: =venta_a_mes3[[#This Row],[IMPORTE NETO]]*0.21 -> 0 | L101: =SUM(venta_a_mes3[[#This Row],[IMPORTE NETO]:[EXENTO]]) -> 0
G102: =IFERROR(IF(venta_a_mes3[[#This Row],[CUIT]]="","-",VLOOKUP(venta_a_mes3[[#This Row],[CUIT]],Lista_CUIT[#All],2,0)),"CUIT NO CARGADO") -> - | I102: =venta_a_mes3[[#This Row],[IMPORTE NETO]]*0.21 -> 0 | L102: =SUM(venta_a_mes3[[#This Row],[IMPORTE NETO]:[EXENTO]]) -> 0
G103: =IFERROR(IF(venta_a_mes3[[#This Row],[CUIT]]="","-",VLOOKUP(venta_a_mes3[[#This Row],[CUIT]],Lista_CUIT[#All],2,0)),"CUIT NO CARGADO") -> - | I103: =venta_a_mes3[[#This Row],[IMPORTE NETO]]*0.21 -> 0 | L103: =SUM(venta_a_mes3[[#This Row],[IMPORTE NETO]:[EXENTO]]) -> 0
G104: =IFERROR(IF(venta_a_mes3[[#This Row],[CUIT]]="","-",VLOOKUP(venta_a_mes3[[#This Row],[CUIT]],Lista_CUIT[#All],2,0)),"CUIT NO CARGADO") -> - | I104: =venta_a_mes3[[#This Row],[IMPORTE NETO]]*0.21 -> 0 | L104: =SUM(venta_a_mes3[[#This Row],[IMPORTE NETO]:[EXENTO]]) -> 0
G105: =IFERROR(IF(venta_a_mes3[[#This Row],[CUIT]]="","-",VLOOKUP(venta_a_mes3[[#This Row],[CUIT]],Lista_CUIT[#All],2,0)),"CUIT NO CARGADO") -> - | I105: =venta_a_mes3[[#This Row],[IMPORTE NETO]]*0.21 -> 0 | L105: =SUM(venta_a_mes3[[#This Row],[IMPORTE NETO]:[EXENTO]]) -> 0
G106: =IFERROR(IF(venta_a_mes3[[#This Row],[CUIT]]="","-",VLOOKUP(venta_a_mes3[[#This Row],[CUIT]],Lista_CUIT[#All],2,0)),"CUIT NO CARGADO") -> - | I106: =venta_a_mes3[[#This Row],[IMPORTE NETO]]*0.21 -> 0 | L106: =SUM(venta_a_mes3[[#This Row],[IMPORTE NETO]:[EXENTO]]) -> 0
B107: Total | H107: =SUBTOTAL(109,venta_a_mes3[IMPORTE NETO]) -> 8636886.1 | I107: =SUBTOTAL(109,venta_a_mes3[IVA 21%]) -> 1813746.1 | J107: =SUBTOTAL(109,venta_a_mes3[IVA 10,5%]) -> 0 | K107: =SUBTOTAL(109,venta_a_mes3[EXENTO]) -> 0 | L107: =SUBTOTAL(109,venta_a_mes3[TOTAL]) -> 10450632 | M107: =SUBTOTAL(103,venta_a_mes3[Provincia]) -> 0
B109: VENTAS "B"
B110: FECHA | C110: TIPO | D110: PTO VENTA | E110: Nº FACTURA | F110: CUIT | G110: RAZON SOCIAL | H110: IMPORTE NETO | I110: IVA 21% | J110: IVA 10,5% | K110: EXENTO | L110: TOTAL | M110: Provincia
I111: =ventas_b_mes3[[#This Row],[IMPORTE NETO]]*0.21 -> 0 | L111: =SUM(ventas_b_mes3[[#This Row],[IMPORTE NETO]:[EXENTO]]) -> 0
G112: =IFERROR(IF(ventas_b_mes3[[#This Row],[CUIT]]="","-",VLOOKUP(ventas_b_mes3[[#This Row],[CUIT]],Lista_CUIT[#All],2,0)),"CUIT NO CARGADO") -> - | I112: =ventas_b_mes3[[#This Row],[IMPORTE NETO]]*0.21 -> 0 | L112: =SUM(ventas_b_mes3[[#This Row],[IMPORTE NETO]:[EXENTO]]) -> 0
G113: =IFERROR(IF(ventas_b_mes3[[#This Row],[CUIT]]="","-",VLOOKUP(ventas_b_mes3[[#This Row],[CUIT]],Lista_CUIT[#All],2,0)),"CUIT NO CARGADO") -> - | I113: =ventas_b_mes3[[#This Row],[IMPORTE NETO]]*0.21 -> 0 | L113: =SUM(ventas_b_mes3[[#This Row],[IMPORTE NETO]:[EXENTO]]) -> 0
G114: =IFERROR(IF(ventas_b_mes3[[#This Row],[CUIT]]="","-",VLOOKUP(ventas_b_mes3[[#This Row],[CUIT]],Lista_CUIT[#All],2,0)),"CUIT NO CARGADO") -> - | I114: =ventas_b_mes3[[#This Row],[IMPORTE NETO]]*0.21 -> 0 | L114: =SUM(ventas_b_mes3[[#This Row],[IMPORTE NETO]:[EXENTO]]) -> 0
G115: =IFERROR(IF(ventas_b_mes3[[#This Row],[CUIT]]="","-",VLOOKUP(ventas_b_mes3[[#This Row],[CUIT]],Lista_CUIT[#All],2,0)),"CUIT NO CARGADO") -> - | I115: =ventas_b_mes3[[#This Row],[IMPORTE NETO]]*0.21 -> 0 | L115: =SUM(ventas_b_mes3[[#This Row],[IMPORTE NETO]:[EXENTO]]) -> 0
I116: =ventas_b_mes3[[#This Row],[IMPORTE NETO]]*0.21 -> 0 | L116: =SUM(ventas_b_mes3[[#This Row],[IMPORTE NETO]:[EXENTO]]) -> 0
B117: Total | H117: =SUBTOTAL(109,ventas_b_mes3[IMPORTE NETO]) -> 0 | I117: =SUBTOTAL(109,ventas_b_mes3[IVA 21%]) -> 0 | J117: =SUBTOTAL(109,ventas_b_mes3[IVA 10,5%]) -> 0 | K117: =SUBTOTAL(109,ventas_b_mes3[EXENTO]) -> 0 | L117: =SUBTOTAL(109,ventas_b_mes3[TOTAL]) -> 0 | M117: =SUBTOTAL(103,ventas_b_mes3[Provincia]) -> 0
C125: RETENCIONES
C126: FECHA | D126: COMP Nº | E126: Columna1 | F126: CUIT | G126: RAZON SOCIAL | H126: Ganancias | I126: IVA | J126: SUSS | K126: IIBB BSAS | L126: IIBB CABA
G127: =IFERROR(IF(Retenciones_mes3[[#This Row],[CUIT]]="","-",VLOOKUP(Retenciones_mes3[[#This Row],[CUIT]],Lista_CUIT[#All],2,0)),"CUIT NO CARGADO") -> -
G128: =IFERROR(IF(Retenciones_mes3[[#This Row],[CUIT]]="","-",VLOOKUP(Retenciones_mes3[[#This Row],[CUIT]],Lista_CUIT[#All],2,0)),"CUIT NO CARGADO") -> -
G129: =IFERROR(IF(Retenciones_mes3[[#This Row],[CUIT]]="","-",VLOOKUP(Retenciones_mes3[[#This Row],[CUIT]],Lista_CUIT[#All],2,0)),"CUIT NO CARGADO") -> -
G130: =IFERROR(IF(Retenciones_mes3[[#This Row],[CUIT]]="","-",VLOOKUP(Retenciones_mes3[[#This Row],[CUIT]],Lista_CUIT[#All],2,0)),"CUIT NO CARGADO") -> -
G131: =IFERROR(IF(Retenciones_mes3[[#This Row],[CUIT]]="","-",VLOOKUP(Retenciones_mes3[[#This Row],[CUIT]],Lista_CUIT[#All],2,0)),"CUIT NO CARGADO") -> -

Sheet Abr-26
B1: LIBRO IVA COMPRAS | G1: ='Ene-26'!G1:M1 -> RABLEB SRL | N1: =EDATE('Ene-26'!N1,3) -> 46113
B3: TOTAL COMPRAS | G3: TOTAL CREDITO FISCAL | J3: TOTAL VENTAS NETAS | M3: TOTAL DEBITO FISCAL | P3: RESULTADO
B4: =SUM(compras_mes4[[#Totals],[NETO GRAVADO]])+extracto_banco_mes4[[#Totals],[NETO]] -> 5277662.1 | G4: =compras_mes4[[#Totals],[IVA 21 %]]+compras_mes4[[#Totals],[IVA 27%]]+compras_mes4[[#Totals],[IVA 10,5%]]+extracto_banco_mes4[[#Totals],[IVA 21%]]+extracto_banco_mes4[[#Totals],[IVA 10,5%]] -> 1108309 | J4: =venta_a_mes4[[#Totals],[IMPORTE NETO]]+ventas_b_mes4[[#Totals],[IMPORTE NETO]] -> 8141816.9 | M4: =venta_a_mes4[[#Totals],[IVA 21%]]+venta_a_mes4[[#Totals],[IVA 10,5%]]+ventas_b_mes4[[#Totals],[IVA 21%]]+ventas_b_mes4[[#Totals],[IVA 10,5%]] -> 1709781.5 | P4: =G4-M4 -> -601472.51
B8: FECHA | C8: TIPO | D8: PTO VTA | E8: NRO. CPTE | F8: CUIT | G8: RAZON SOCIAL | H8: NETO GRAVADO | I8: IVA 21 % | J8: IVA 27% | K8: IVA 10,5% | L8: PERC. IVA | M8: PERC IIBB BS AS | N8: PERC. IIBB CABA | O8: Otros / No Grav. | P8: TOTAL | Q8: Tipo de Gasto | R8: Provincia
B9: 01/04/2026 | C9: 1 | D9: 2 | E9: 1974 | F9: 30718631730 | G9: =IFERROR(IF(compras_mes4[[#This Row],[CUIT]]="","-",VLOOKUP(compras_mes4[[#This Row],[CUIT]],Lista_CUIT[#All],2,0)),"CUIT NO CARGADO") -> SIMZ S. R. L. | H9: 139552 | I9: =IF(compras_mes4[[#This Row],[NETO GRAVADO]]="","",compras_mes4[[#This Row],[NETO GRAVADO]]*0.21) -> 29305.92 | O9: 0 | P9: =SUM(compras_mes4[[#This Row],[NETO GRAVADO]:[Otros / No Grav.]]) -> 168857.92 | Q9: =IFERROR(IF(compras_mes4[[#This Row],[CUIT]]="","-",VLOOKUP(compras_mes4[[#This Row],[CUIT]],Lista_CUIT[#All],3,0)),"CUIT NO CARGADO") -> 0 | R9: =IFERROR(IF(compras_mes4[[#This Row],[CUIT]]="","-",VLOOKUP(compras_mes4[[#This Row],[CUIT]],Lista_CUIT[#All],4,0)),"CUIT NO CARGADO") -> 0
B10: 30/04/2026 | C10: 1 | D10: 11 | E10: 1309149 | F10: 33709585229 | G10: =IFERROR(IF(compras_mes4[[#This Row],[CUIT]]="","-",VLOOKUP(compras_mes4[[#This Row],[CUIT]],Lista_CUIT[#All],2,0)),"CUIT NO CARGADO") -> GOOGLE ARGENTINA S.R.L. | H10: 4559868.5 | I10: =IF(compras_mes4[[#This Row],[NETO GRAVADO]]="","",compras_mes4[[#This Row],[NETO GRAVADO]]*0.21) -> 957572.39 | N10: 68398.03 | O10: 136796.06 | P10: =SUM(compras_mes4[[#This Row],[NETO GRAVADO]:[Otros / No Grav.]]) -> 5722635 | Q10: =IFERROR(IF(compras_mes4[[#This Row],[CUIT]]="","-",VLOOKUP(compras_mes4[[#This Row],[CUIT]],Lista_CUIT[#All],3,0)),"CUIT NO CARGADO") -> Servicios de publicidad | R10: =IFERROR(IF(compras_mes4[[#This Row],[CUIT]]="","-",VLOOKUP(compras_mes4[[#This Row],[CUIT]],Lista_CUIT[#All],4,0)),"CUIT NO CARGADO") -> 0
B11: 30/04/2026 | C11: 1 | D11: 11 | E11: 1319730 | F11: 33709585229 | G11: =IFERROR(IF(compras_mes4[[#This Row],[CUIT]]="","-",VLOOKUP(compras_mes4[[#This Row],[CUIT]],Lista_CUIT[#All],2,0)),"CUIT NO CARGADO") -> GOOGLE ARGENTINA S.R.L. | H11: 578598.29 | I11: =IF(compras_mes4[[#This Row],[NETO GRAVADO]]="","",compras_mes4[[#This Row],[NETO GRAVADO]]*0.21) -> 121505.64 | N11: 8678.97 | O11: 17357.95 | P11: =SUM(compras_mes4[[#This Row],[NETO GRAVADO]:[Otros / No Grav.]]) -> 726140.85 | Q11: =IFERROR(IF(compras_mes4[[#This Row],[CUIT]]="","-",VLOOKUP(compras_mes4[[#This Row],[CUIT]],Lista_CUIT[#All],3,0)),"CUIT NO CARGADO") -> Servicios de publicidad | R11: =IFERROR(IF(compras_mes4[[#This Row],[CUIT]]="","-",VLOOKUP(compras_mes4[[#This Row],[CUIT]],Lista_CUIT[#All],4,0)),"CUIT NO CARGADO") -> 0
B12: 30/04/2026 | C12: 3 | D12: 11 | E12: 937726 | F12: 33709585229 | G12: =IFERROR(IF(compras_mes4[[#This Row],[CUIT]]="","-",VLOOKUP(compras_mes4[[#This Row],[CUIT]],Lista_CUIT[#All],2,0)),"CUIT NO CARGADO") -> GOOGLE ARGENTINA S.R.L. | H12: -356.76 | I12: =IF(compras_mes4[[#This Row],[NETO GRAVADO]]="","",compras_mes4[[#This Row],[NETO GRAVADO]]*0.21) -> -74.9196 | N12: -5.35 | P12: =SUM(compras_mes4[[#This Row],[NETO GRAVADO]:[Otros / No Grav.]]) -> -437.0296 | Q12: =IFERROR(IF(compras_mes4[[#This Row],[CUIT]]="","-",VLOOKUP(compras_mes4[[#This Row],[CUIT]],Lista_CUIT[#All],3,0)),"CUIT NO CARGADO") -> Servicios de publicidad | R12: =IFERROR(IF(compras_mes4[[#This Row],[CUIT]]="","-",VLOOKUP(compras_mes4[[#This Row],[CUIT]],Lista_CUIT[#All],4,0)),"CUIT NO CARGADO") -> 0
G13: =IFERROR(IF(compras_mes4[[#This Row],[CUIT]]="","-",VLOOKUP(compras_mes4[[#This Row],[CUIT]],Lista_CUIT[#All],2,0)),"CUIT NO CARGADO") -> - | I13: =IF(compras_mes4[[#This Row],[NETO GRAVADO]]="","",compras_mes4[[#This Row],[NETO GRAVADO]]*0.21) | P13: =SUM(compras_mes4[[#This Row],[NETO GRAVADO]:[Otros / No Grav.]]) -> 0 | Q13: =IFERROR(IF(compras_mes4[[#This Row],[CUIT]]="","-",VLOOKUP(compras_mes4[[#This Row],[CUIT]],Lista_CUIT[#All],3,0)),"CUIT NO CARGADO") -> - | R13: =IFERROR(IF(compras_mes4[[#This Row],[CUIT]]="","-",VLOOKUP(compras_mes4[[#This Row],[CUIT]],Lista_CUIT[#All],4,0)),"CUIT NO CARGADO") -> -
G14: =IFERROR(IF(compras_mes4[[#This Row],[CUIT]]="","-",VLOOKUP(compras_mes4[[#This Row],[CUIT]],Lista_CUIT[#All],2,0)),"CUIT NO CARGADO") -> - | I14: =IF(compras_mes4[[#This Row],[NETO GRAVADO]]="","",compras_mes4[[#This Row],[NETO GRAVADO]]*0.21) | P14: =SUM(compras_mes4[[#This Row],[NETO GRAVADO]:[Otros / No Grav.]]) -> 0 | Q14: =IFERROR(IF(compras_mes4[[#This Row],[CUIT]]="","-",VLOOKUP(compras_mes4[[#This Row],[CUIT]],Lista_CUIT[#All],3,0)),"CUIT NO CARGADO") -> - | R14: =IFERROR(IF(compras_mes4[[#This Row],[CUIT]]="","-",VLOOKUP(compras_mes4[[#This Row],[CUIT]],Lista_CUIT[#All],4,0)),"CUIT NO CARGADO") -> -
G15: =IFERROR(IF(compras_mes4[[#This Row],[CUIT]]="","-",VLOOKUP(compras_mes4[[#This Row],[CUIT]],Lista_CUIT[#All],2,0)),"CUIT NO CARGADO") -> - | I15: =IF(compras_mes4[[#This Row],[NETO GRAVADO]]="","",compras_mes4[[#This Row],[NETO GRAVADO]]*0.21) | P15: =SUM(compras_mes4[[#This Row],[NETO GRAVADO]:[Otros / No Grav.]]) -> 0 | Q15: =IFERROR(IF(compras_mes4[[#This Row],[CUIT]]="","-",VLOOKUP(compras_mes4[[#This Row],[CUIT]],Lista_CUIT[#All],3,0)),"CUIT NO CARGADO") -> - | R15: =IFERROR(IF(compras_mes4[[#This Row],[CUIT]]="","-",VLOOKUP(compras_mes4[[#This Row],[CUIT]],Lista_CUIT[#All],4,0)),"CUIT NO CARGADO") -> -
G16: =IFERROR(IF(compras_mes4[[#This Row],[CUIT]]="","-",VLOOKUP(compras_mes4[[#This Row],[CUIT]],Lista_CUIT[#All],2,0)),"CUIT NO CARGADO") -> - | I16: =IF(compras_mes4[[#This Row],[NETO GRAVADO]]="","",compras_mes4[[#This Row],[NETO GRAVADO]]*0.21) | P16: =SUM(compras_mes4[[#This Row],[NETO GRAVADO]:[Otros / No Grav.]]) -> 0 | Q16: =IFERROR(IF(compras_mes4[[#This Row],[CUIT]]="","-",VLOOKUP(compras_mes4[[#This Row],[CUIT]],Lista_CUIT[#All],3,0)),"CUIT NO CARGADO") -> - | R16: =IFERROR(IF(compras_mes4[[#This Row],[CUIT]]="","-",VLOOKUP(compras_mes4[[#This Row],[CUIT]],Lista_CUIT[#All],4,0)),"CUIT NO CARGADO") -> -
G17: =IFERROR(IF(compras_mes4[[#This Row],[CUIT]]="","-",VLOOKUP(compras_mes4[[#This Row],[CUIT]],Lista_CUIT[#All],2,0)),"CUIT NO CARGADO") -> - | I17: =IF(compras_mes4[[#This Row],[NETO GRAVADO]]="","",compras_mes4[[#This Row],[NETO GRAVADO]]*0.21) | P17: =SUM(compras_mes4[[#This Row],[NETO GRAVADO]:[Otros / No Grav.]]) -> 0 | Q17: =IFERROR(IF(compras_mes4[[#This Row],[CUIT]]="","-",VLOOKUP(compras_mes4[[#This Row],[CUIT]],Lista_CUIT[#All],3,0)),"CUIT NO CARGADO") -> - | R17: =IFERROR(IF(compras_mes4[[#This Row],[CUIT]]="","-",VLOOKUP(compras_mes4[[#This Row],[CUIT]],Lista_CUIT[#All],4,0)),"CUIT NO CARGADO") -> -
G18: =IFERROR(IF(compras_mes4[[#This Row],[CUIT]]="","-",VLOOKUP(compras_mes4[[#This Row],[CUIT]],Lista_CUIT[#All],2,0)),"CUIT NO CARGADO") -> - | I18: =IF(compras_mes4[[#This Row],[NETO GRAVADO]]="","",compras_mes4[[#This Row],[NETO GRAVADO]]*0.21) | P18: =SUM(compras_mes4[[#This Row],[NETO GRAVADO]:[Otros / No Grav.]]) -> 0 | Q18: =IFERROR(IF(compras_mes4[[#This Row],[CUIT]]="","-",VLOOKUP(compras_mes4[[#This Row],[CUIT]],Lista_CUIT[#All],3,0)),"CUIT NO CARGADO") -> - | R18: =IFERROR(IF(compras_mes4[[#This Row],[CUIT]]="","-",VLOOKUP(compras_mes4[[#This Row],[CUIT]],Lista_CUIT[#All],4,0)),"CUIT NO CARGADO") -> -
G19: =IFERROR(IF(compras_mes4[[#This Row],[CUIT]]="","-",VLOOKUP(compras_mes4[[#This Row],[CUIT]],Lista_CUIT[#All],2,0)),"CUIT NO CARGADO") -> - | I19: =IF(compras_mes4[[#This Row],[NETO GRAVADO]]="","",compras_mes4[[#This Row],[NETO GRAVADO]]*0.21) | P19: =SUM(compras_mes4[[#This Row],[NETO GRAVADO]:[Otros / No Grav.]]) -> 0 | Q19: =IFERROR(IF(compras_mes4[[#This Row],[CUIT]]="","-",VLOOKUP(compras_mes4[[#This Row],[CUIT]],Lista_CUIT[#All],3,0)),"CUIT NO CARGADO") -> - | R19: =IFERROR(IF(compras_mes4[[#This Row],[CUIT]]="","-",VLOOKUP(compras_mes4[[#This Row],[CUIT]],Lista_CUIT[#All],4,0)),"CUIT NO CARGADO") -> -
G20: =IFERROR(IF(compras_mes4[[#This Row],[CUIT]]="","-",VLOOKUP(compras_mes4[[#This Row],[CUIT]],Lista_CUIT[#All],2,0)),"CUIT NO CARGADO") -> - | I20: =IF(compras_mes4[[#This Row],[NETO GRAVADO]]="","",compras_mes4[[#This Row],[NETO GRAVADO]]*0.21) | P20: =SUM(compras_mes4[[#This Row],[NETO GRAVADO]:[Otros / No Grav.]]) -> 0 | Q20: =IFERROR(IF(compras_mes4[[#This Row],[CUIT]]="","-",VLOOKUP(compras_mes4[[#This Row],[CUIT]],Lista_CUIT[#All],3,0)),"CUIT NO CARGADO") -> - | R20: =IFERROR(IF(compras_mes4[[#This Row],[CUIT]]="","-",VLOOKUP(compras_mes4[[#This Row],[CUIT]],Lista_CUIT[#All],4,0)),"CUIT NO CARGADO") -> -
G21: =IFERROR(IF(compras_mes4[[#This Row],[CUIT]]="","-",VLOOKUP(compras_mes4[[#This Row],[CUIT]],Lista_CUIT[#All],2,0)),"CUIT NO CARGADO") -> - | I21: =IF(compras_mes4[[#This Row],[NETO GRAVADO]]="","",compras_mes4[[#This Row],[NETO GRAVADO]]*0.21) | P21: =SUM(compras_mes4[[#This Row],[NETO GRAVADO]:[Otros / No Grav.]]) -> 0 | Q21: =IFERROR(IF(compras_mes4[[#This Row],[CUIT]]="","-",VLOOKUP(compras_mes4[[#This Row],[CUIT]],Lista_CUIT[#All],3,0)),"CUIT NO CARGADO") -> - | R21: =IFERROR(IF(compras_mes4[[#This Row],[CUIT]]="","-",VLOOKUP(compras_mes4[[#This Row],[CUIT]],Lista_CUIT[#All],4,0)),"CUIT NO CARGADO") -> -
G22: =IFERROR(IF(compras_mes4[[#This Row],[CUIT]]="","-",VLOOKUP(compras_mes4[[#This Row],[CUIT]],Lista_CUIT[#All],2,0)),"CUIT NO CARGADO") -> - | I22: =IF(compras_mes4[[#This Row],[NETO GRAVADO]]="","",compras_mes4[[#This Row],[NETO GRAVADO]]*0.21) | P22: =SUM(compras_mes4[[#This Row],[NETO GRAVADO]:[Otros / No Grav.]]) -> 0 | Q22: =IFERROR(IF(compras_mes4[[#This Row],[CUIT]]="","-",VLOOKUP(compras_mes4[[#This Row],[CUIT]],Lista_CUIT[#All],3,0)),"CUIT NO CARGADO") -> - | R22: =IFERROR(IF(compras_mes4[[#This Row],[CUIT]]="","-",VLOOKUP(compras_mes4[[#This Row],[CUIT]],Lista_CUIT[#All],4,0)),"CUIT NO CARGADO") -> -
G23: =IFERROR(IF(compras_mes4[[#This Row],[CUIT]]="","-",VLOOKUP(compras_mes4[[#This Row],[CUIT]],Lista_CUIT[#All],2,0)),"CUIT NO CARGADO") -> - | I23: =IF(compras_mes4[[#This Row],[NETO GRAVADO]]="","",compras_mes4[[#This Row],[NETO GRAVADO]]*0.21) | P23: =SUM(compras_mes4[[#This Row],[NETO GRAVADO]:[Otros / No Grav.]]) -> 0 | Q23: =IFERROR(IF(compras_mes4[[#This Row],[CUIT]]="","-",VLOOKUP(compras_mes4[[#This Row],[CUIT]],Lista_CUIT[#All],3,0)),"CUIT NO CARGADO") -> - | R23: =IFERROR(IF(compras_mes4[[#This Row],[CUIT]]="","-",VLOOKUP(compras_mes4[[#This Row],[CUIT]],Lista_CUIT[#All],4,0)),"CUIT NO CARGADO") -> -
G24: =IFERROR(IF(compras_mes4[[#This Row],[CUIT]]="","-",VLOOKUP(compras_mes4[[#This Row],[CUIT]],Lista_CUIT[#All],2,0)),"CUIT NO CARGADO") -> - | I24: =IF(compras_mes4[[#This Row],[NETO GRAVADO]]="","",compras_mes4[[#This Row],[NETO GRAVADO]]*0.21) | P24: =SUM(compras_mes4[[#This Row],[NETO GRAVADO]:[Otros / No Grav.]]) -> 0 | Q24: =IFERROR(IF(compras_mes4[[#This Row],[CUIT]]="","-",VLOOKUP(compras_mes4[[#This Row],[CUIT]],Lista_CUIT[#All],3,0)),"CUIT NO CARGADO") -> - | R24: =IFERROR(IF(compras_mes4[[#This Row],[CUIT]]="","-",VLOOKUP(compras_mes4[[#This Row],[CUIT]],Lista_CUIT[#All],4,0)),"CUIT NO CARGADO") -> -
... G37: =IFERROR(IF(compras_mes4[[#This Row],[CUIT]]="","-",VLOOKUP(compras_mes4[[#This Row],[CUIT]],Lista_CUIT[#All],2,0)),"CUIT NO CARGADO") -> - | I37: =IF(compras_mes4[[#This Row],[NETO GRAVADO]]="","",compras_mes4[[#This Row],[NETO GRAVADO]]*0.21) | P37: =SUM(compras_mes4[[#This Row],[NETO GRAVADO]:[Otros / No Grav.]]) -> 0 | Q37: =IFERROR(IF(compras_mes4[[#This Row],[CUIT]]="","-",VLOOKUP(compras_mes4[[#This Row],[CUIT]],Lista_CUIT[#All],3,0)),"CUIT NO CARGADO") -> - | R37: =IFERROR(IF(compras_mes4[[#This Row],[CUIT]]="","-",VLOOKUP(compras_mes4[[#This Row],[CUIT]],Lista_CUIT[#All],4,0)),"CUIT NO CARGADO") -> -
B38: Total | H38: =SUBTOTAL(109,compras_mes4[NETO GRAVADO]) -> 5277662.1 | I38: =SUBTOTAL(109,compras_mes4[IVA 21 %]) -> 1108309 | J38: =SUBTOTAL(109,compras_mes4[IVA 27%]) -> 0 | K38: =SUBTOTAL(109,compras_mes4[IVA 10,5%]) -> 0 | L38: =SUBTOTAL(109,compras_mes4[PERC. IVA]) -> 0 | M38: =SUBTOTAL(109,compras_mes4[PERC IIBB BS AS]) -> 0 | N38: =SUBTOTAL(109,compras_mes4[PERC. IIBB CABA]) -> 77071.65 | O38: =SUBTOTAL(109,compras_mes4[Otros / No Grav.]) -> 154154.01 | P38: =SUBTOTAL(109,compras_mes4[TOTAL]) -> 6617196.8
D43: LIQUIDACION EXTRACTOS BANCARIOS-TARJETAS
D44: FECHA | E44: NRO CPTE | F44: BANCO | G44: NETO | H44: IVA 21% | I44: IVA 10,5% | J44: RET IIBB CABA | K44: PERC IVA | L44: PERC IIBB
D48: Total | G48: =SUBTOTAL(109,extracto_banco_mes4[NETO]) -> 0 | H48: =SUBTOTAL(109,extracto_banco_mes4[IVA 21%]) -> 0 | I48: =SUBTOTAL(109,extracto_banco_mes4[IVA 10,5%]) -> 0 | J48: =SUBTOTAL(109,extracto_banco_mes4[RET IIBB CABA]) -> 0 | K48: =SUBTOTAL(109,extracto_banco_mes4[PERC IVA]) -> 0 | L48: =SUBTOTAL(109,extracto_banco_mes4[PERC IIBB]) -> 0
D52: FACTURAS C
D53: FECHA | E53: PTO VTA | F53: FC Nº | G53: CUIT | H53: RAZON SOCIAL | I53: TOTAL | J53: TIPO DE GASTO | K53: Provincia
D54: 01/04/2026 | E54: 1 | F54: 335 | G54: 27386311000 | H54: =IFERROR(IF(factura_c_mes4[[#This Row],[CUIT]]="","-",VLOOKUP(factura_c_mes4[[#This Row],[CUIT]],Lista_CUIT[#All],2,0)),"CUIT NO CARGADO") -> OPANASIUK MACARENA ANTONELLA | I54: 1000000 | J54: =IFERROR(IF(factura_c_mes4[[#This Row],[CUIT]]="","-",VLOOKUP(factura_c_mes4[[#This Row],[CUIT]],Lista_CUIT[#All],3,0)),"CUIT NO CARGADO") -> 0 | K54: =IFERROR(IF(factura_c_mes4[[#This Row],[CUIT]]="","-",VLOOKUP(factura_c_mes4[[#This Row],[CUIT]],Lista_CUIT[#All],4,0)),"CUIT NO CARGADO") -> 0
D55: 01/04/2026 | E55: 2 | F55: 1150 | G55: 20400104094 | H55: =IFERROR(IF(factura_c_mes4[[#This Row],[CUIT]]="","-",VLOOKUP(factura_c_mes4[[#This Row],[CUIT]],Lista_CUIT[#All],2,0)),"CUIT NO CARGADO") -> BOTINDARI FEDERICO DANIEL | I55: 300000 | J55: =IFERROR(IF(factura_c_mes4[[#This Row],[CUIT]]="","-",VLOOKUP(factura_c_mes4[[#This Row],[CUIT]],Lista_CUIT[#All],3,0)),"CUIT NO CARGADO") -> HONORARIOS CONTABLE | K55: =IFERROR(IF(factura_c_mes4[[#This Row],[CUIT]]="","-",VLOOKUP(factura_c_mes4[[#This Row],[CUIT]],Lista_CUIT[#All],4,0)),"CUIT NO CARGADO") -> 0
D56: 13/04/2026 | E56: 2 | F56: 66 | G56: 23380288079 | H56: =IFERROR(IF(factura_c_mes4[[#This Row],[CUIT]]="","-",VLOOKUP(factura_c_mes4[[#This Row],[CUIT]],Lista_CUIT[#All],2,0)),"CUIT NO CARGADO") -> CASTROMAN AGUSTIN | I56: 598000 | J56: =IFERROR(IF(factura_c_mes4[[#This Row],[CUIT]]="","-",VLOOKUP(factura_c_mes4[[#This Row],[CUIT]],Lista_CUIT[#All],3,0)),"CUIT NO CARGADO") -> 0 | K56: =IFERROR(IF(factura_c_mes4[[#This Row],[CUIT]]="","-",VLOOKUP(factura_c_mes4[[#This Row],[CUIT]],Lista_CUIT[#All],4,0)),"CUIT NO CARGADO") -> 0
D57: 23/04/2026 | E57: 2 | F57: 442 | G57: 27206941419 | H57: =IFERROR(IF(factura_c_mes4[[#This Row],[CUIT]]="","-",VLOOKUP(factura_c_mes4[[#This Row],[CUIT]],Lista_CUIT[#All],2,0)),"CUIT NO CARGADO") -> DOBARRO PAULA MARCELA | I57: 200000 | J57: =IFERROR(IF(factura_c_mes4[[#This Row],[CUIT]]="","-",VLOOKUP(factura_c_mes4[[#This Row],[CUIT]],Lista_CUIT[#All],3,0)),"CUIT NO CARGADO") -> 0 | K57: =IFERROR(IF(factura_c_mes4[[#This Row],[CUIT]]="","-",VLOOKUP(factura_c_mes4[[#This Row],[CUIT]],Lista_CUIT[#All],4,0)),"CUIT NO CARGADO") -> 0
D58: 23/04/2026 | E58: 2 | F58: 1162 | G58: 20400104094 | H58: =IFERROR(IF(factura_c_mes4[[#This Row],[CUIT]]="","-",VLOOKUP(factura_c_mes4[[#This Row],[CUIT]],Lista_CUIT[#All],2,0)),"CUIT NO CARGADO") -> BOTINDARI FEDERICO DANIEL | I58: 400000 | J58: =IFERROR(IF(factura_c_mes4[[#This Row],[CUIT]]="","-",VLOOKUP(factura_c_mes4[[#This Row],[CUIT]],Lista_CUIT[#All],3,0)),"CUIT NO CARGADO") -> HONORARIOS CONTABLE | K58: =IFERROR(IF(factura_c_mes4[[#This Row],[CUIT]]="","-",VLOOKUP(factura_c_mes4[[#This Row],[CUIT]],Lista_CUIT[#All],4,0)),"CUIT NO CARGADO") -> 0
D59: 26/04/2026 | E59: 1 | F59: 5 | G59: 27403975821 | H59: =IFERROR(IF(factura_c_mes4[[#This Row],[CUIT]]="","-",VLOOKUP(factura_c_mes4[[#This Row],[CUIT]],Lista_CUIT[#All],2,0)),"CUIT NO CARGADO") -> BARROSO VALENTINA | I59: 600700 | J59: =IFERROR(IF(factura_c_mes4[[#This Row],[CUIT]]="","-",VLOOKUP(factura_c_mes4[[#This Row],[CUIT]],Lista_CUIT[#All],3,0)),"CUIT NO CARGADO") -> 0 | K59: =IFERROR(IF(factura_c_mes4[[#This Row],[CUIT]]="","-",VLOOKUP(factura_c_mes4[[#This Row],[CUIT]],Lista_CUIT[#All],4,0)),"CUIT NO CARGADO") -> 0
D60: 27/04/2026 | E60: 51 | F60: 196 | G60: 20300985158 | H60: =IFERROR(IF(factura_c_mes4[[#This Row],[CUIT]]="","-",VLOOKUP(factura_c_mes4[[#This Row],[CUIT]],Lista_CUIT[#All],2,0)),"CUIT NO CARGADO") -> GONZALEZ NESTOR RICARDO | I60: 250000 | J60: =IFERROR(IF(factura_c_mes4[[#This Row],[CUIT]]="","-",VLOOKUP(factura_c_mes4[[#This Row],[CUIT]],Lista_CUIT[#All],3,0)),"CUIT NO CARGADO") -> 0 | K60: =IFERROR(IF(factura_c_mes4[[#This Row],[CUIT]]="","-",VLOOKUP(factura_c_mes4[[#This Row],[CUIT]],Lista_CUIT[#All],4,0)),"CUIT NO CARGADO") -> 0
H61: =IFERROR(IF(factura_c_mes4[[#This Row],[CUIT]]="","-",VLOOKUP(factura_c_mes4[[#This Row],[CUIT]],Lista_CUIT[#All],2,0)),"CUIT NO CARGADO") -> - | J61: =IFERROR(IF(factura_c_mes4[[#This Row],[CUIT]]="","-",VLOOKUP(factura_c_mes4[[#This Row],[CUIT]],Lista_CUIT[#All],3,0)),"CUIT NO CARGADO") -> - | K61: =IFERROR(IF(factura_c_mes4[[#This Row],[CUIT]]="","-",VLOOKUP(factura_c_mes4[[#This Row],[CUIT]],Lista_CUIT[#All],4,0)),"CUIT NO CARGADO") -> -
H62: =IFERROR(IF(factura_c_mes4[[#This Row],[CUIT]]="","-",VLOOKUP(factura_c_mes4[[#This Row],[CUIT]],Lista_CUIT[#All],2,0)),"CUIT NO CARGADO") -> - | J62: =IFERROR(IF(factura_c_mes4[[#This Row],[CUIT]]="","-",VLOOKUP(factura_c_mes4[[#This Row],[CUIT]],Lista_CUIT[#All],3,0)),"CUIT NO CARGADO") -> - | K62: =IFERROR(IF(factura_c_mes4[[#This Row],[CUIT]]="","-",VLOOKUP(factura_c_mes4[[#This Row],[CUIT]],Lista_CUIT[#All],4,0)),"CUIT NO CARGADO") -> -
H63: =IFERROR(IF(factura_c_mes4[[#This Row],[CUIT]]="","-",VLOOKUP(factura_c_mes4[[#This Row],[CUIT]],Lista_CUIT[#All],2,0)),"CUIT NO CARGADO") -> - | J63: =IFERROR(IF(factura_c_mes4[[#This Row],[CUIT]]="","-",VLOOKUP(factura_c_mes4[[#This Row],[CUIT]],Lista_CUIT[#All],3,0)),"CUIT NO CARGADO") -> - | K63: =IFERROR(IF(factura_c_mes4[[#This Row],[CUIT]]="","-",VLOOKUP(factura_c_mes4[[#This Row],[CUIT]],Lista_CUIT[#All],4,0)),"CUIT NO CARGADO") -> -
H64: =IFERROR(IF(factura_c_mes4[[#This Row],[CUIT]]="","-",VLOOKUP(factura_c_mes4[[#This Row],[CUIT]],Lista_CUIT[#All],2,0)),"CUIT NO CARGADO") -> - | J64: =IFERROR(IF(factura_c_mes4[[#This Row],[CUIT]]="","-",VLOOKUP(factura_c_mes4[[#This Row],[CUIT]],Lista_CUIT[#All],3,0)),"CUIT NO CARGADO") -> - | K64: =IFERROR(IF(factura_c_mes4[[#This Row],[CUIT]]="","-",VLOOKUP(factura_c_mes4[[#This Row],[CUIT]],Lista_CUIT[#All],4,0)),"CUIT NO CARGADO") -> -
H65: =IFERROR(IF(factura_c_mes4[[#This Row],[CUIT]]="","-",VLOOKUP(factura_c_mes4[[#This Row],[CUIT]],Lista_CUIT[#All],2,0)),"CUIT NO CARGADO") -> - | J65: =IFERROR(IF(factura_c_mes4[[#This Row],[CUIT]]="","-",VLOOKUP(factura_c_mes4[[#This Row],[CUIT]],Lista_CUIT[#All],3,0)),"CUIT NO CARGADO") -> - | K65: =IFERROR(IF(factura_c_mes4[[#This Row],[CUIT]]="","-",VLOOKUP(factura_c_mes4[[#This Row],[CUIT]],Lista_CUIT[#All],4,0)),"CUIT NO CARGADO") -> -
D66: Total | I66: =SUBTOTAL(109,factura_c_mes4[TOTAL]) -> 3348700
B70: LIBRO IVA VENTAS | K70: =N1 -> 46113
B72: VENTAS "A"
B73: FECHA | C73: TIPO | D73: PTO VENTA | E73: Nº FACTURA | F73: CUIT | G73: RAZON SOCIAL | H73: IMPORTE NETO | I73: IVA 21% | J73: IVA 10,5% | K73: EXENTO | L73: TOTAL | M73: Provincia
B74: 01/04/2026 | C74: 1 | D74: 1 | E74: 668 | F74: 30708404485 | G74: =IFERROR(IF(venta_a_mes4[[#This Row],[CUIT]]="","-",VLOOKUP(venta_a_mes4[[#This Row],[CUIT]],Lista_CUIT[#All],2,0)),"CUIT NO CARGADO") -> SOLDARGEN S.A. | H74: 590909.1 | I74: =venta_a_mes4[[#This Row],[IMPORTE NETO]]*0.21 -> 124090.91 | L74: =SUM(venta_a_mes4[[#This Row],[IMPORTE NETO]:[EXENTO]]) -> 715000.01
B75: 01/04/2026 | C75: 1 | D75: 1 | E75: 669 | F75: 30708604255 | G75: =IFERROR(IF(venta_a_mes4[[#This Row],[CUIT]]="","-",VLOOKUP(venta_a_mes4[[#This Row],[CUIT]],Lista_CUIT[#All],2,0)),"CUIT NO CARGADO") -> NAR TECHNOLOGIES S.R.L. | H75: 590909.1 | I75: =venta_a_mes4[[#This Row],[IMPORTE NETO]]*0.21 -> 124090.91 | L75: =SUM(venta_a_mes4[[#This Row],[IMPORTE NETO]:[EXENTO]]) -> 715000.01
B76: 01/04/2026 | C76: 1 | D76: 1 | E76: 670 | F76: 30717465101 | G76: =IFERROR(IF(venta_a_mes4[[#This Row],[CUIT]]="","-",VLOOKUP(venta_a_mes4[[#This Row],[CUIT]],Lista_CUIT[#All],2,0)),"CUIT NO CARGADO") -> EMPRENDIMIENTOS SHOPGLASS S. R. L. | H76: 147107.43 | I76: =venta_a_mes4[[#This Row],[IMPORTE NETO]]*0.21 -> 30892.56 | L76: =SUM(venta_a_mes4[[#This Row],[IMPORTE NETO]:[EXENTO]]) -> 177999.99
B77: 01/04/2026 | C77: 1 | D77: 1 | E77: 664 | F77: 20287305460 | G77: =IFERROR(IF(venta_a_mes4[[#This Row],[CUIT]]="","-",VLOOKUP(venta_a_mes4[[#This Row],[CUIT]],Lista_CUIT[#All],2,0)),"CUIT NO CARGADO") -> LANDI GERONIMO | H77: 147107.43 | I77: =venta_a_mes4[[#This Row],[IMPORTE NETO]]*0.21 -> 30892.56 | L77: =SUM(venta_a_mes4[[#This Row],[IMPORTE NETO]:[EXENTO]]) -> 177999.99
B78: 01/04/2026 | C78: 1 | D78: 1 | E78: 665 | F78: 30715751557 | G78: =IFERROR(IF(venta_a_mes4[[#This Row],[CUIT]]="","-",VLOOKUP(venta_a_mes4[[#This Row],[CUIT]],Lista_CUIT[#All],2,0)),"CUIT NO CARGADO") -> TIXIT SRL | H78: 590909.1 | I78: =venta_a_mes4[[#This Row],[IMPORTE NETO]]*0.21 -> 124090.91 | L78: =SUM(venta_a_mes4[[#This Row],[IMPORTE NETO]:[EXENTO]]) -> 715000.01
B79: 01/04/2026 | C79: 1 | D79: 1 | E79: 666 | F79: 30714375241 | G79: =IFERROR(IF(venta_a_mes4[[#This Row],[CUIT]]="","-",VLOOKUP(venta_a_mes4[[#This Row],[CUIT]],Lista_CUIT[#All],2,0)),"CUIT NO CARGADO") -> POWER-RECORDS S.A | H79: 590909.1 | I79: =venta_a_mes4[[#This Row],[IMPORTE NETO]]*0.21 -> 124090.91 | L79: =SUM(venta_a_mes4[[#This Row],[IMPORTE NETO]:[EXENTO]]) -> 715000.01
B80: 01/04/2026 | C80: 1 | D80: 1 | E80: 667 | F80: 30718553357 | G80: =IFERROR(IF(venta_a_mes4[[#This Row],[CUIT]]="","-",VLOOKUP(venta_a_mes4[[#This Row],[CUIT]],Lista_CUIT[#All],2,0)),"CUIT NO CARGADO") -> EMIGRA CON TU MASCOTA S.R.L. | H80: 590909.1 | I80: =venta_a_mes4[[#This Row],[IMPORTE NETO]]*0.21 -> 124090.91 | L80: =SUM(venta_a_mes4[[#This Row],[IMPORTE NETO]:[EXENTO]]) -> 715000.01
B81: 01/04/2026 | C81: 1 | D81: 1 | E81: 674 | F81: 20287305460 | G81: =IFERROR(IF(venta_a_mes4[[#This Row],[CUIT]]="","-",VLOOKUP(venta_a_mes4[[#This Row],[CUIT]],Lista_CUIT[#All],2,0)),"CUIT NO CARGADO") -> LANDI GERONIMO | H81: 147107.43 | I81: =venta_a_mes4[[#This Row],[IMPORTE NETO]]*0.21 -> 30892.56 | L81: =SUM(venta_a_mes4[[#This Row],[IMPORTE NETO]:[EXENTO]]) -> 177999.99
B82: 01/04/2026 | C82: 1 | D82: 1 | E82: 671 | F82: 30709058807 | G82: =IFERROR(IF(venta_a_mes4[[#This Row],[CUIT]]="","-",VLOOKUP(venta_a_mes4[[#This Row],[CUIT]],Lista_CUIT[#All],2,0)),"CUIT NO CARGADO") -> LA VALENZIANA S.R.L. | H82: 4382375 | I82: =venta_a_mes4[[#This Row],[IMPORTE NETO]]*0.21 -> 920298.75 | L82: =SUM(venta_a_mes4[[#This Row],[IMPORTE NETO]:[EXENTO]]) -> 5302673.8
B83: 01/04/2026 | C83: 1 | D83: 1 | E83: 672 | F83: 30714864803 | G83: =IFERROR(IF(venta_a_mes4[[#This Row],[CUIT]]="","-",VLOOKUP(venta_a_mes4[[#This Row],[CUIT]],Lista_CUIT[#All],2,0)),"CUIT NO CARGADO") -> DIAZ Y GIUSEPPETTI S. R. L. | H83: 209044.9 | I83: =venta_a_mes4[[#This Row],[IMPORTE NETO]]*0.21 -> 43899.429 | L83: =SUM(venta_a_mes4[[#This Row],[IMPORTE NETO]:[EXENTO]]) -> 252944.33
B84: 01/04/2026 | C84: 1 | D84: 1 | E84: 673 | F84: 30718228723 | G84: =IFERROR(IF(venta_a_mes4[[#This Row],[CUIT]]="","-",VLOOKUP(venta_a_mes4[[#This Row],[CUIT]],Lista_CUIT[#All],2,0)),"CUIT NO CARGADO") -> ESCOBARFLOORING S.A. | H84: 715000 | I84: =venta_a_mes4[[#This Row],[IMPORTE NETO]]*0.21 -> 150150 | L84: =SUM(venta_a_mes4[[#This Row],[IMPORTE NETO]:[EXENTO]]) -> 865150
B85: 15/04/2026 | C85: 1 | D85: 1 | E85: 675 | F85: 30718590937 | G85: =IFERROR(IF(venta_a_mes4[[#This Row],[CUIT]]="","-",VLOOKUP(venta_a_mes4[[#This Row],[CUIT]],Lista_CUIT[#All],2,0)),"CUIT NO CARGADO") -> AGILE MAR SOLUTIONS S.R.L. | H85: 715000 | I85: =venta_a_mes4[[#This Row],[IMPORTE NETO]]*0.21 -> 150150 | L85: =SUM(venta_a_mes4[[#This Row],[IMPORTE NETO]:[EXENTO]]) -> 865150
... B90: 30/04/2026 | C90: 3 | D90: 1 | E90: 59 | F90: 30708604255 | G90: =IFERROR(IF(venta_a_mes4[[#This Row],[CUIT]]="","-",VLOOKUP(venta_a_mes4[[#This Row],[CUIT]],Lista_CUIT[#All],2,0)),"CUIT NO CARGADO") -> NAR TECHNOLOGIES S.R.L. | H90: -590909.1 | I90: =venta_a_mes4[[#This Row],[IMPORTE NETO]]*0.21 -> -124090.91 | L90: =SUM(venta_a_mes4[[#This Row],[IMPORTE NETO]:[EXENTO]]) -> -715000.01
G91: =IFERROR(IF(venta_a_mes4[[#This Row],[CUIT]]="","-",VLOOKUP(venta_a_mes4[[#This Row],[CUIT]],Lista_CUIT[#All],2,0)),"CUIT NO CARGADO") -> - | I91: =venta_a_mes4[[#This Row],[IMPORTE NETO]]*0.21 -> 0 | L91: =SUM(venta_a_mes4[[#This Row],[IMPORTE NETO]:[EXENTO]]) -> 0
G92: =IFERROR(IF(venta_a_mes4[[#This Row],[CUIT]]="","-",VLOOKUP(venta_a_mes4[[#This Row],[CUIT]],Lista_CUIT[#All],2,0)),"CUIT NO CARGADO") -> - | I92: =venta_a_mes4[[#This Row],[IMPORTE NETO]]*0.21 -> 0 | L92: =SUM(venta_a_mes4[[#This Row],[IMPORTE NETO]:[EXENTO]]) -> 0
G93: =IFERROR(IF(venta_a_mes4[[#This Row],[CUIT]]="","-",VLOOKUP(venta_a_mes4[[#This Row],[CUIT]],Lista_CUIT[#All],2,0)),"CUIT NO CARGADO") -> - | I93: =venta_a_mes4[[#This Row],[IMPORTE NETO]]*0.21 -> 0 | L93: =SUM(venta_a_mes4[[#This Row],[IMPORTE NETO]:[EXENTO]]) -> 0
G94: =IFERROR(IF(venta_a_mes4[[#This Row],[CUIT]]="","-",VLOOKUP(venta_a_mes4[[#This Row],[CUIT]],Lista_CUIT[#All],2,0)),"CUIT NO CARGADO") -> - | I94: =venta_a_mes4[[#This Row],[IMPORTE NETO]]*0.21 -> 0 | L94: =SUM(venta_a_mes4[[#This Row],[IMPORTE NETO]:[EXENTO]]) -> 0
G95: =IFERROR(IF(venta_a_mes4[[#This Row],[CUIT]]="","-",VLOOKUP(venta_a_mes4[[#This Row],[CUIT]],Lista_CUIT[#All],2,0)),"CUIT NO CARGADO") -> - | I95: =venta_a_mes4[[#This Row],[IMPORTE NETO]]*0.21 -> 0 | L95: =SUM(venta_a_mes4[[#This Row],[IMPORTE NETO]:[EXENTO]]) -> 0
G96: =IFERROR(IF(venta_a_mes4[[#This Row],[CUIT]]="","-",VLOOKUP(venta_a_mes4[[#This Row],[CUIT]],Lista_CUIT[#All],2,0)),"CUIT NO CARGADO") -> - | I96: =venta_a_mes4[[#This Row],[IMPORTE NETO]]*0.21 -> 0 | L96: =SUM(venta_a_mes4[[#This Row],[IMPORTE NETO]:[EXENTO]]) -> 0
G97: =IFERROR(IF(venta_a_mes4[[#This Row],[CUIT]]="","-",VLOOKUP(venta_a_mes4[[#This Row],[CUIT]],Lista_CUIT[#All],2,0)),"CUIT NO CARGADO") -> - | I97: =venta_a_mes4[[#This Row],[IMPORTE NETO]]*0.21 -> 0 | L97: =SUM(venta_a_mes4[[#This Row],[IMPORTE NETO]:[EXENTO]]) -> 0
G98: =IFERROR(IF(venta_a_mes4[[#This Row],[CUIT]]="","-",VLOOKUP(venta_a_mes4[[#This Row],[CUIT]],Lista_CUIT[#All],2,0)),"CUIT NO CARGADO") -> - | I98: =venta_a_mes4[[#This Row],[IMPORTE NETO]]*0.21 -> 0 | L98: =SUM(venta_a_mes4[[#This Row],[IMPORTE NETO]:[EXENTO]]) -> 0
G99: =IFERROR(IF(venta_a_mes4[[#This Row],[CUIT]]="","-",VLOOKUP(venta_a_mes4[[#This Row],[CUIT]],Lista_CUIT[#All],2,0)),"CUIT NO CARGADO") -> - | I99: =venta_a_mes4[[#This Row],[IMPORTE NETO]]*0.21 -> 0 | L99: =SUM(venta_a_mes4[[#This Row],[IMPORTE NETO]:[EXENTO]]) -> 0
G100: =IFERROR(IF(venta_a_mes4[[#This Row],[CUIT]]="","-",VLOOKUP(venta_a_mes4[[#This Row],[CUIT]],Lista_CUIT[#All],2,0)),"CUIT NO CARGADO") -> - | I100: =venta_a_mes4[[#This Row],[IMPORTE NETO]]*0.21 -> 0 | L100: =SUM(venta_a_mes4[[#This Row],[IMPORTE NETO]:[EXENTO]]) -> 0
G101: =IFERROR(IF(venta_a_mes4[[#This Row],[CUIT]]="","-",VLOOKUP(venta_a_mes4[[#This Row],[CUIT]],Lista_CUIT[#All],2,0)),"CUIT NO CARGADO") -> - | I101: =venta_a_mes4[[#This Row],[IMPORTE NETO]]*0.21 -> 0 | L101: =SUM(venta_a_mes4[[#This Row],[IMPORTE NETO]:[EXENTO]]) -> 0
G102: =IFERROR(IF(venta_a_mes4[[#This Row],[CUIT]]="","-",VLOOKUP(venta_a_mes4[[#This Row],[CUIT]],Lista_CUIT[#All],2,0)),"CUIT NO CARGADO") -> - | I102: =venta_a_mes4[[#This Row],[IMPORTE NETO]]*0.21 -> 0 | L102: =SUM(venta_a_mes4[[#This Row],[IMPORTE NETO]:[EXENTO]]) -> 0
B103: Total | H103: =SUBTOTAL(109,venta_a_mes4[IMPORTE NETO]) -> 8141816.9 | I103: =SUBTOTAL(109,venta_a_mes4[IVA 21%]) -> 1709781.5 | J103: =SUBTOTAL(109,venta_a_mes4[IVA 10,5%]) -> 0 | K103: =SUBTOTAL(109,venta_a_mes4[EXENTO]) -> 0 | L103: =SUBTOTAL(109,venta_a_mes4[TOTAL]) -> 9851598.4 | M103: =SUBTOTAL(103,venta_a_mes4[Provincia]) -> 0
B104: VENTAS "B"
B105: FECHA | C105: TIPO | D105: PTO VENTA | E105: Nº FACTURA | F105: CUIT | G105: RAZON SOCIAL | H105: IMPORTE NETO | I105: IVA 21% | J105: IVA 10,5% | K105: EXENTO | L105: TOTAL | M105: Provincia
G106: =IFERROR(IF(ventas_b_mes4[[#This Row],[CUIT]]="","-",VLOOKUP(ventas_b_mes4[[#This Row],[CUIT]],Lista_CUIT[#All],2,0)),"CUIT NO CARGADO") -> - | I106: =ventas_b_mes4[[#This Row],[IMPORTE NETO]]*0.21 -> 0 | L106: =SUM(ventas_b_mes4[[#This Row],[IMPORTE NETO]:[EXENTO]]) -> 0
G107: =IFERROR(IF(ventas_b_mes4[[#This Row],[CUIT]]="","-",VLOOKUP(ventas_b_mes4[[#This Row],[CUIT]],Lista_CUIT[#All],2,0)),"CUIT NO CARGADO") -> - | I107: =ventas_b_mes4[[#This Row],[IMPORTE NETO]]*0.21 -> 0 | L107: =SUM(ventas_b_mes4[[#This Row],[IMPORTE NETO]:[EXENTO]]) -> 0
I108: =ventas_b_mes4[[#This Row],[IMPORTE NETO]]*0.21 -> 0 | L108: =SUM(ventas_b_mes4[[#This Row],[IMPORTE NETO]:[EXENTO]]) -> 0
I109: =ventas_b_mes4[[#This Row],[IMPORTE NETO]]*0.21 -> 0 | L109: =SUM(ventas_b_mes4[[#This Row],[IMPORTE NETO]:[EXENTO]]) -> 0
I110: =ventas_b_mes4[[#This Row],[IMPORTE NETO]]*0.21 -> 0 | L110: =SUM(ventas_b_mes4[[#This Row],[IMPORTE NETO]:[EXENTO]]) -> 0
I111: =ventas_b_mes4[[#This Row],[IMPORTE NETO]]*0.21 -> 0 | L111: =SUM(ventas_b_mes4[[#This Row],[IMPORTE NETO]:[EXENTO]]) -> 0
B112: Total | H112: =SUBTOTAL(109,ventas_b_mes4[IMPORTE NETO]) -> 0 | I112: =SUBTOTAL(109,ventas_b_mes4[IVA 21%]) -> 0 | J112: =SUBTOTAL(109,ventas_b_mes4[IVA 10,5%]) -> 0 | K112: =SUBTOTAL(109,ventas_b_mes4[EXENTO]) -> 0 | L112: =SUBTOTAL(109,ventas_b_mes4[TOTAL]) -> 0 | M112: =SUBTOTAL(103,ventas_b_mes4[Provincia]) -> 0
C120: RETENCIONES
C121: FECHA | D121: COMP Nº | E121: Columna1 | F121: CUIT | G121: RAZON SOCIAL | H121: Ganancias | I121: IVA | J121: SUSS | K121: IIBB BSAS | L121: IIBB CABA
G122: =IFERROR(IF(Retenciones_mes4[[#This Row],[CUIT]]="","-",VLOOKUP(Retenciones_mes4[[#This Row],[CUIT]],Lista_CUIT[#All],2,0)),"CUIT NO CARGADO") -> -
G123: =IFERROR(IF(Retenciones_mes4[[#This Row],[CUIT]]="","-",VLOOKUP(Retenciones_mes4[[#This Row],[CUIT]],Lista_CUIT[#All],2,0)),"CUIT NO CARGADO") -> -
G124: =IFERROR(IF(Retenciones_mes4[[#This Row],[CUIT]]="","-",VLOOKUP(Retenciones_mes4[[#This Row],[CUIT]],Lista_CUIT[#All],2,0)),"CUIT NO CARGADO") -> -
G125: =IFERROR(IF(Retenciones_mes4[[#This Row],[CUIT]]="","-",VLOOKUP(Retenciones_mes4[[#This Row],[CUIT]],Lista_CUIT[#All],2,0)),"CUIT NO CARGADO") -> -
G126: =IFERROR(IF(Retenciones_mes4[[#This Row],[CUIT]]="","-",VLOOKUP(Retenciones_mes4[[#This Row],[CUIT]],Lista_CUIT[#All],2,0)),"CUIT NO CARGADO") -> -

Sheet May-26
B1: LIBRO IVA COMPRAS | G1: ='Ene-26'!G1:M1 -> RABLEB SRL | N1: =EDATE('Ene-26'!N1,4) -> 46143
B3: TOTAL COMPRAS | G3: TOTAL CREDITO FISCAL | J3: TOTAL VENTAS NETAS | M3: TOTAL DEBITO FISCAL | P3: RESULTADO
B4: =SUM(compras_mes5[[#Totals],[NETO GRAVADO]])+extracto_banco_mes5[[#Totals],[NETO]] -> 0 | G4: =compras_mes5[[#Totals],[IVA 21 %]]+compras_mes5[[#Totals],[IVA 27%]]+compras_mes5[[#Totals],[IVA 10,5%]]+extracto_banco_mes5[[#Totals],[IVA 21%]]+extracto_banco_mes5[[#Totals],[IVA 10,5%]] -> 0 | J4: =venta_a_mes5[[#Totals],[IMPORTE NETO]]+ventas_b_mes5[[#Totals],[IMPORTE NETO]] -> 0 | M4: =venta_a_mes5[[#Totals],[IVA 21%]]+venta_a_mes5[[#Totals],[IVA 10,5%]]+ventas_b_mes5[[#Totals],[IVA 21%]]+ventas_b_mes5[[#Totals],[IVA 10,5%]] -> 0 | P4: =G4-M4 -> 0
B8: FECHA | C8: TIPO | D8: PTO VTA | E8: NRO. CPTE | F8: CUIT | G8: RAZON SOCIAL | H8: NETO GRAVADO | I8: IVA 21 % | J8: IVA 27% | K8: IVA 10,5% | L8: PERC. IVA | M8: PERC IIBB BS AS | N8: PERC. IIBB CABA | O8: Otros / No Grav. | P8: TOTAL | Q8: Tipo de Gasto | R8: Provincia
G9: =IFERROR(IF(compras_mes5[[#This Row],[CUIT]]="","-",VLOOKUP(compras_mes5[[#This Row],[CUIT]],Lista_CUIT[#All],2,0)),"CUIT NO CARGADO") -> - | I9: =IF(compras_mes5[[#This Row],[NETO GRAVADO]]="","",compras_mes5[[#This Row],[NETO GRAVADO]]*0.21) | P9: =SUM(compras_mes5[[#This Row],[NETO GRAVADO]:[Otros / No Grav.]]) -> 0 | Q9: =IFERROR(IF(compras_mes5[[#This Row],[CUIT]]="","-",VLOOKUP(compras_mes5[[#This Row],[CUIT]],Lista_CUIT[#All],3,0)),"CUIT NO CARGADO") -> - | R9: =IFERROR(IF(compras_mes5[[#This Row],[CUIT]]="","-",VLOOKUP(compras_mes5[[#This Row],[CUIT]],Lista_CUIT[#All],4,0)),"CUIT NO CARGADO") -> -
G10: =IFERROR(IF(compras_mes5[[#This Row],[CUIT]]="","-",VLOOKUP(compras_mes5[[#This Row],[CUIT]],Lista_CUIT[#All],2,0)),"CUIT NO CARGADO") -> - | I10: =IF(compras_mes5[[#This Row],[NETO GRAVADO]]="","",compras_mes5[[#This Row],[NETO GRAVADO]]*0.21) | P10: =SUM(compras_mes5[[#This Row],[NETO GRAVADO]:[Otros / No Grav.]]) -> 0 | Q10: =IFERROR(IF(compras_mes5[[#This Row],[CUIT]]="","-",VLOOKUP(compras_mes5[[#This Row],[CUIT]],Lista_CUIT[#All],3,0)),"CUIT NO CARGADO") -> - | R10: =IFERROR(IF(compras_mes5[[#This Row],[CUIT]]="","-",VLOOKUP(compras_mes5[[#This Row],[CUIT]],Lista_CUIT[#All],4,0)),"CUIT NO CARGADO") -> -
G11: =IFERROR(IF(compras_mes5[[#This Row],[CUIT]]="","-",VLOOKUP(compras_mes5[[#This Row],[CUIT]],Lista_CUIT[#All],2,0)),"CUIT NO CARGADO") -> - | I11: =IF(compras_mes5[[#This Row],[NETO GRAVADO]]="","",compras_mes5[[#This Row],[NETO GRAVADO]]*0.21) | P11: =SUM(compras_mes5[[#This Row],[NETO GRAVADO]:[Otros / No Grav.]]) -> 0 | Q11: =IFERROR(IF(compras_mes5[[#This Row],[CUIT]]="","-",VLOOKUP(compras_mes5[[#This Row],[CUIT]],Lista_CUIT[#All],3,0)),"CUIT NO CARGADO") -> - | R11: =IFERROR(IF(compras_mes5[[#This Row],[CUIT]]="","-",VLOOKUP(compras_mes5[[#This Row],[CUIT]],Lista_CUIT[#All],4,0)),"CUIT NO CARGADO") -> -
G12: =IFERROR(IF(compras_mes5[[#This Row],[CUIT]]="","-",VLOOKUP(compras_mes5[[#This Row],[CUIT]],Lista_CUIT[#All],2,0)),"CUIT NO CARGADO") -> - | I12: =IF(compras_mes5[[#This Row],[NETO GRAVADO]]="","",compras_mes5[[#This Row],[NETO GRAVADO]]*0.21) | P12: =SUM(compras_mes5[[#This Row],[NETO GRAVADO]:[Otros / No Grav.]]) -> 0 | Q12: =IFERROR(IF(compras_mes5[[#This Row],[CUIT]]="","-",VLOOKUP(compras_mes5[[#This Row],[CUIT]],Lista_CUIT[#All],3,0)),"CUIT NO CARGADO") -> - | R12: =IFERROR(IF(compras_mes5[[#This Row],[CUIT]]="","-",VLOOKUP(compras_mes5[[#This Row],[CUIT]],Lista_CUIT[#All],4,0)),"CUIT NO CARGADO") -> -
G13: =IFERROR(IF(compras_mes5[[#This Row],[CUIT]]="","-",VLOOKUP(compras_mes5[[#This Row],[CUIT]],Lista_CUIT[#All],2,0)),"CUIT NO CARGADO") -> - | I13: =IF(compras_mes5[[#This Row],[NETO GRAVADO]]="","",compras_mes5[[#This Row],[NETO GRAVADO]]*0.21) | P13: =SUM(compras_mes5[[#This Row],[NETO GRAVADO]:[Otros / No Grav.]]) -> 0 | Q13: =IFERROR(IF(compras_mes5[[#This Row],[CUIT]]="","-",VLOOKUP(compras_mes5[[#This Row],[CUIT]],Lista_CUIT[#All],3,0)),"CUIT NO CARGADO") -> - | R13: =IFERROR(IF(compras_mes5[[#This Row],[CUIT]]="","-",VLOOKUP(compras_mes5[[#This Row],[CUIT]],Lista_CUIT[#All],4,0)),"CUIT NO CARGADO") -> -
G14: =IFERROR(IF(compras_mes5[[#This Row],[CUIT]]="","-",VLOOKUP(compras_mes5[[#This Row],[CUIT]],Lista_CUIT[#All],2,0)),"CUIT NO CARGADO") -> - | I14: =IF(compras_mes5[[#This Row],[NETO GRAVADO]]="","",compras_mes5[[#This Row],[NETO GRAVADO]]*0.21) | P14: =SUM(compras_mes5[[#This Row],[NETO GRAVADO]:[Otros / No Grav.]]) -> 0 | Q14: =IFERROR(IF(compras_mes5[[#This Row],[CUIT]]="","-",VLOOKUP(compras_mes5[[#This Row],[CUIT]],Lista_CUIT[#All],3,0)),"CUIT NO CARGADO") -> - | R14: =IFERROR(IF(compras_mes5[[#This Row],[CUIT]]="","-",VLOOKUP(compras_mes5[[#This Row],[CUIT]],Lista_CUIT[#All],4,0)),"CUIT NO CARGADO") -> -
G15: =IFERROR(IF(compras_mes5[[#This Row],[CUIT]]="","-",VLOOKUP(compras_mes5[[#This Row],[CUIT]],Lista_CUIT[#All],2,0)),"CUIT NO CARGADO") -> - | I15: =IF(compras_mes5[[#This Row],[NETO GRAVADO]]="","",compras_mes5[[#This Row],[NETO GRAVADO]]*0.21) | P15: =SUM(compras_mes5[[#This Row],[NETO GRAVADO]:[Otros / No Grav.]]) -> 0 | Q15: =IFERROR(IF(compras_mes5[[#This Row],[CUIT]]="","-",VLOOKUP(compras_mes5[[#This Row],[CUIT]],Lista_CUIT[#All],3,0)),"CUIT NO CARGADO") -> - | R15: =IFERROR(IF(compras_mes5[[#This Row],[CUIT]]="","-",VLOOKUP(compras_mes5[[#This Row],[CUIT]],Lista_CUIT[#All],4,0)),"CUIT NO CARGADO") -> -
G16: =IFERROR(IF(compras_mes5[[#This Row],[CUIT]]="","-",VLOOKUP(compras_mes5[[#This Row],[CUIT]],Lista_CUIT[#All],2,0)),"CUIT NO CARGADO") -> - | I16: =IF(compras_mes5[[#This Row],[NETO GRAVADO]]="","",compras_mes5[[#This Row],[NETO GRAVADO]]*0.21) | P16: =SUM(compras_mes5[[#This Row],[NETO GRAVADO]:[Otros / No Grav.]]) -> 0 | Q16: =IFERROR(IF(compras_mes5[[#This Row],[CUIT]]="","-",VLOOKUP(compras_mes5[[#This Row],[CUIT]],Lista_CUIT[#All],3,0)),"CUIT NO CARGADO") -> - | R16: =IFERROR(IF(compras_mes5[[#This Row],[CUIT]]="","-",VLOOKUP(compras_mes5[[#This Row],[CUIT]],Lista_CUIT[#All],4,0)),"CUIT NO CARGADO") -> -
G17: =IFERROR(IF(compras_mes5[[#This Row],[CUIT]]="","-",VLOOKUP(compras_mes5[[#This Row],[CUIT]],Lista_CUIT[#All],2,0)),"CUIT NO CARGADO") -> - | I17: =IF(compras_mes5[[#This Row],[NETO GRAVADO]]="","",compras_mes5[[#This Row],[NETO GRAVADO]]*0.21) | P17: =SUM(compras_mes5[[#This Row],[NETO GRAVADO]:[Otros / No Grav.]]) -> 0 | Q17: =IFERROR(IF(compras_mes5[[#This Row],[CUIT]]="","-",VLOOKUP(compras_mes5[[#This Row],[CUIT]],Lista_CUIT[#All],3,0)),"CUIT NO CARGADO") -> - | R17: =IFERROR(IF(compras_mes5[[#This Row],[CUIT]]="","-",VLOOKUP(compras_mes5[[#This Row],[CUIT]],Lista_CUIT[#All],4,0)),"CUIT NO CARGADO") -> -
G18: =IFERROR(IF(compras_mes5[[#This Row],[CUIT]]="","-",VLOOKUP(compras_mes5[[#This Row],[CUIT]],Lista_CUIT[#All],2,0)),"CUIT NO CARGADO") -> - | I18: =IF(compras_mes5[[#This Row],[NETO GRAVADO]]="","",compras_mes5[[#This Row],[NETO GRAVADO]]*0.21) | P18: =SUM(compras_mes5[[#This Row],[NETO GRAVADO]:[Otros / No Grav.]]) -> 0 | Q18: =IFERROR(IF(compras_mes5[[#This Row],[CUIT]]="","-",VLOOKUP(compras_mes5[[#This Row],[CUIT]],Lista_CUIT[#All],3,0)),"CUIT NO CARGADO") -> - | R18: =IFERROR(IF(compras_mes5[[#This Row],[CUIT]]="","-",VLOOKUP(compras_mes5[[#This Row],[CUIT]],Lista_CUIT[#All],4,0)),"CUIT NO CARGADO") -> -
G19: =IFERROR(IF(compras_mes5[[#This Row],[CUIT]]="","-",VLOOKUP(compras_mes5[[#This Row],[CUIT]],Lista_CUIT[#All],2,0)),"CUIT NO CARGADO") -> - | I19: =IF(compras_mes5[[#This Row],[NETO GRAVADO]]="","",compras_mes5[[#This Row],[NETO GRAVADO]]*0.21) | P19: =SUM(compras_mes5[[#This Row],[NETO GRAVADO]:[Otros / No Grav.]]) -> 0 | Q19: =IFERROR(IF(compras_mes5[[#This Row],[CUIT]]="","-",VLOOKUP(compras_mes5[[#This Row],[CUIT]],Lista_CUIT[#All],3,0)),"CUIT NO CARGADO") -> - | R19: =IFERROR(IF(compras_mes5[[#This Row],[CUIT]]="","-",VLOOKUP(compras_mes5[[#This Row],[CUIT]],Lista_CUIT[#All],4,0)),"CUIT NO CARGADO") -> -
G20: =IFERROR(IF(compras_mes5[[#This Row],[CUIT]]="","-",VLOOKUP(compras_mes5[[#This Row],[CUIT]],Lista_CUIT[#All],2,0)),"CUIT NO CARGADO") -> - | I20: =IF(compras_mes5[[#This Row],[NETO GRAVADO]]="","",compras_mes5[[#This Row],[NETO GRAVADO]]*0.21) | P20: =SUM(compras_mes5[[#This Row],[NETO GRAVADO]:[Otros / No Grav.]]) -> 0 | Q20: =IFERROR(IF(compras_mes5[[#This Row],[CUIT]]="","-",VLOOKUP(compras_mes5[[#This Row],[CUIT]],Lista_CUIT[#All],3,0)),"CUIT NO CARGADO") -> - | R20: =IFERROR(IF(compras_mes5[[#This Row],[CUIT]]="","-",VLOOKUP(compras_mes5[[#This Row],[CUIT]],Lista_CUIT[#All],4,0)),"CUIT NO CARGADO") -> -
... G22: =IFERROR(IF(compras_mes5[[#This Row],[CUIT]]="","-",VLOOKUP(compras_mes5[[#This Row],[CUIT]],Lista_CUIT[#All],2,0)),"CUIT NO CARGADO") -> - | I22: =IF(compras_mes5[[#This Row],[NETO GRAVADO]]="","",compras_mes5[[#This Row],[NETO GRAVADO]]*0.21) | P22: =SUM(compras_mes5[[#This Row],[NETO GRAVADO]:[Otros / No Grav.]]) -> 0 | Q22: =IFERROR(IF(compras_mes5[[#This Row],[CUIT]]="","-",VLOOKUP(compras_mes5[[#This Row],[CUIT]],Lista_CUIT[#All],3,0)),"CUIT NO CARGADO") -> - | R22: =IFERROR(IF(compras_mes5[[#This Row],[CUIT]]="","-",VLOOKUP(compras_mes5[[#This Row],[CUIT]],Lista_CUIT[#All],4,0)),"CUIT NO CARGADO") -> -
B23: Total | H23: =SUBTOTAL(109,compras_mes5[NETO GRAVADO]) -> 0 | I23: =SUBTOTAL(109,compras_mes5[IVA 21 %]) -> 0 | J23: =SUBTOTAL(109,compras_mes5[IVA 27%]) -> 0 | K23: =SUBTOTAL(109,compras_mes5[IVA 10,5%]) -> 0 | L23: =SUBTOTAL(109,compras_mes5[PERC. IVA]) -> 0 | M23: =SUBTOTAL(109,compras_mes5[PERC IIBB BS AS]) -> 0 | N23: =SUBTOTAL(109,compras_mes5[PERC. IIBB CABA]) -> 0 | O23: =SUBTOTAL(109,compras_mes5[Otros / No Grav.]) -> 0 | P23: =SUBTOTAL(109,compras_mes5[TOTAL]) -> 0
D28: LIQUIDACION EXTRACTOS BANCARIOS-TARJETAS
D29: FECHA | E29: NRO CPTE | F29: BANCO | G29: NETO | H29: IVA 21% | I29: IVA 10,5% | J29: RET IIBB CABA | K29: PERC IVA | L29: PERC IIBB
D33: Total | G33: =SUBTOTAL(109,extracto_banco_mes5[NETO]) -> 0 | H33: =SUBTOTAL(109,extracto_banco_mes5[IVA 21%]) -> 0 | I33: =SUBTOTAL(109,extracto_banco_mes5[IVA 10,5%]) -> 0 | J33: =SUBTOTAL(109,extracto_banco_mes5[RET IIBB CABA]) -> 0 | K33: =SUBTOTAL(109,extracto_banco_mes5[PERC IVA]) -> 0 | L33: =SUBTOTAL(109,extracto_banco_mes5[PERC IIBB]) -> 0
D37: FACTURAS C
D38: FECHA | E38: PTO VTA | F38: FC Nº | G38: CUIT | H38: RAZON SOCIAL | I38: TOTAL | J38: TIPO DE GASTO | K38: Provincia
H39: =IFERROR(IF(factura_c_mes5[[#This Row],[CUIT]]="","-",VLOOKUP(factura_c_mes5[[#This Row],[CUIT]],Lista_CUIT[#All],2,0)),"CUIT NO CARGADO") -> - | J39: =IFERROR(IF(factura_c_mes5[[#This Row],[CUIT]]="","-",VLOOKUP(factura_c_mes5[[#This Row],[CUIT]],Lista_CUIT[#All],3,0)),"CUIT NO CARGADO") -> - | K39: =IFERROR(IF(factura_c_mes5[[#This Row],[CUIT]]="","-",VLOOKUP(factura_c_mes5[[#This Row],[CUIT]],Lista_CUIT[#All],4,0)),"CUIT NO CARGADO") -> -
H40: =IFERROR(IF(factura_c_mes5[[#This Row],[CUIT]]="","-",VLOOKUP(factura_c_mes5[[#This Row],[CUIT]],Lista_CUIT[#All],2,0)),"CUIT NO CARGADO") -> - | J40: =IFERROR(IF(factura_c_mes5[[#This Row],[CUIT]]="","-",VLOOKUP(factura_c_mes5[[#This Row],[CUIT]],Lista_CUIT[#All],3,0)),"CUIT NO CARGADO") -> - | K40: =IFERROR(IF(factura_c_mes5[[#This Row],[CUIT]]="","-",VLOOKUP(factura_c_mes5[[#This Row],[CUIT]],Lista_CUIT[#All],4,0)),"CUIT NO CARGADO") -> -
H41: =IFERROR(IF(factura_c_mes5[[#This Row],[CUIT]]="","-",VLOOKUP(factura_c_mes5[[#This Row],[CUIT]],Lista_CUIT[#All],2,0)),"CUIT NO CARGADO") -> - | J41: =IFERROR(IF(factura_c_mes5[[#This Row],[CUIT]]="","-",VLOOKUP(factura_c_mes5[[#This Row],[CUIT]],Lista_CUIT[#All],3,0)),"CUIT NO CARGADO") -> - | K41: =IFERROR(IF(factura_c_mes5[[#This Row],[CUIT]]="","-",VLOOKUP(factura_c_mes5[[#This Row],[CUIT]],Lista_CUIT[#All],4,0)),"CUIT NO CARGADO") -> -
H42: =IFERROR(IF(factura_c_mes5[[#This Row],[CUIT]]="","-",VLOOKUP(factura_c_mes5[[#This Row],[CUIT]],Lista_CUIT[#All],2,0)),"CUIT NO CARGADO") -> - | J42: =IFERROR(IF(factura_c_mes5[[#This Row],[CUIT]]="","-",VLOOKUP(factura_c_mes5[[#This Row],[CUIT]],Lista_CUIT[#All],3,0)),"CUIT NO CARGADO") -> - | K42: =IFERROR(IF(factura_c_mes5[[#This Row],[CUIT]]="","-",VLOOKUP(factura_c_mes5[[#This Row],[CUIT]],Lista_CUIT[#All],4,0)),"CUIT NO CARGADO") -> -
H43: =IFERROR(IF(factura_c_mes5[[#This Row],[CUIT]]="","-",VLOOKUP(factura_c_mes5[[#This Row],[CUIT]],Lista_CUIT[#All],2,0)),"CUIT NO CARGADO") -> - | J43: =IFERROR(IF(factura_c_mes5[[#This Row],[CUIT]]="","-",VLOOKUP(factura_c_mes5[[#This Row],[CUIT]],Lista_CUIT[#All],3,0)),"CUIT NO CARGADO") -> - | K43: =IFERROR(IF(factura_c_mes5[[#This Row],[CUIT]]="","-",VLOOKUP(factura_c_mes5[[#This Row],[CUIT]],Lista_CUIT[#All],4,0)),"CUIT NO CARGADO") -> -
D44: Total | I44: =SUBTOTAL(109,factura_c_mes5[TOTAL]) -> 0
B49: LIBRO IVA VENTAS | K49: =N1 -> 46143
B51: VENTAS "A"
B52: FECHA | C52: TIPO | D52: PTO VENTA | E52: Nº FACTURA | F52: CUIT | G52: RAZON SOCIAL | H52: IMPORTE NETO | I52: IVA 21% | J52: IVA 10,5% | K52: EXENTO | L52: TOTAL | M52: Provincia
G53: =IFERROR(IF(venta_a_mes5[[#This Row],[CUIT]]="","-",VLOOKUP(venta_a_mes5[[#This Row],[CUIT]],Lista_CUIT[#All],2,0)),"CUIT NO CARGADO") -> - | I53: =venta_a_mes5[[#This Row],[IMPORTE NETO]]*0.21 -> 0 | L53: =SUM(venta_a_mes5[[#This Row],[IMPORTE NETO]:[EXENTO]]) -> 0
G54: =IFERROR(IF(venta_a_mes5[[#This Row],[CUIT]]="","-",VLOOKUP(venta_a_mes5[[#This Row],[CUIT]],Lista_CUIT[#All],2,0)),"CUIT NO CARGADO") -> - | I54: =venta_a_mes5[[#This Row],[IMPORTE NETO]]*0.21 -> 0 | L54: =SUM(venta_a_mes5[[#This Row],[IMPORTE NETO]:[EXENTO]]) -> 0
G55: =IFERROR(IF(venta_a_mes5[[#This Row],[CUIT]]="","-",VLOOKUP(venta_a_mes5[[#This Row],[CUIT]],Lista_CUIT[#All],2,0)),"CUIT NO CARGADO") -> - | I55: =venta_a_mes5[[#This Row],[IMPORTE NETO]]*0.21 -> 0 | L55: =SUM(venta_a_mes5[[#This Row],[IMPORTE NETO]:[EXENTO]]) -> 0
G56: =IFERROR(IF(venta_a_mes5[[#This Row],[CUIT]]="","-",VLOOKUP(venta_a_mes5[[#This Row],[CUIT]],Lista_CUIT[#All],2,0)),"CUIT NO CARGADO") -> - | I56: =venta_a_mes5[[#This Row],[IMPORTE NETO]]*0.21 -> 0 | L56: =SUM(venta_a_mes5[[#This Row],[IMPORTE NETO]:[EXENTO]]) -> 0
G57: =IFERROR(IF(venta_a_mes5[[#This Row],[CUIT]]="","-",VLOOKUP(venta_a_mes5[[#This Row],[CUIT]],Lista_CUIT[#All],2,0)),"CUIT NO CARGADO") -> - | I57: =venta_a_mes5[[#This Row],[IMPORTE NETO]]*0.21 -> 0 | L57: =SUM(venta_a_mes5[[#This Row],[IMPORTE NETO]:[EXENTO]]) -> 0
G58: =IFERROR(IF(venta_a_mes5[[#This Row],[CUIT]]="","-",VLOOKUP(venta_a_mes5[[#This Row],[CUIT]],Lista_CUIT[#All],2,0)),"CUIT NO CARGADO") -> - | I58: =venta_a_mes5[[#This Row],[IMPORTE NETO]]*0.21 -> 0 | L58: =SUM(venta_a_mes5[[#This Row],[IMPORTE NETO]:[EXENTO]]) -> 0
G59: =IFERROR(IF(venta_a_mes5[[#This Row],[CUIT]]="","-",VLOOKUP(venta_a_mes5[[#This Row],[CUIT]],Lista_CUIT[#All],2,0)),"CUIT NO CARGADO") -> - | I59: =venta_a_mes5[[#This Row],[IMPORTE NETO]]*0.21 -> 0 | L59: =SUM(venta_a_mes5[[#This Row],[IMPORTE NETO]:[EXENTO]]) -> 0
G60: =IFERROR(IF(venta_a_mes5[[#This Row],[CUIT]]="","-",VLOOKUP(venta_a_mes5[[#This Row],[CUIT]],Lista_CUIT[#All],2,0)),"CUIT NO CARGADO") -> - | I60: =venta_a_mes5[[#This Row],[IMPORTE NETO]]*0.21 -> 0 | L60: =SUM(venta_a_mes5[[#This Row],[IMPORTE NETO]:[EXENTO]]) -> 0
G61: =IFERROR(IF(venta_a_mes5[[#This Row],[CUIT]]="","-",VLOOKUP(venta_a_mes5[[#This Row],[CUIT]],Lista_CUIT[#All],2,0)),"CUIT NO CARGADO") -> - | I61: =venta_a_mes5[[#This Row],[IMPORTE NETO]]*0.21 -> 0 | L61: =SUM(venta_a_mes5[[#This Row],[IMPORTE NETO]:[EXENTO]]) -> 0
G62: =IFERROR(IF(venta_a_mes5[[#This Row],[CUIT]]="","-",VLOOKUP(venta_a_mes5[[#This Row],[CUIT]],Lista_CUIT[#All],2,0)),"CUIT NO CARGADO") -> - | I62: =venta_a_mes5[[#This Row],[IMPORTE NETO]]*0.21 -> 0 | L62: =SUM(venta_a_mes5[[#This Row],[IMPORTE NETO]:[EXENTO]]) -> 0
G63: =IFERROR(IF(venta_a_mes5[[#This Row],[CUIT]]="","-",VLOOKUP(venta_a_mes5[[#This Row],[CUIT]],Lista_CUIT[#All],2,0)),"CUIT NO CARGADO") -> - | I63: =venta_a_mes5[[#This Row],[IMPORTE NETO]]*0.21 -> 0 | L63: =SUM(venta_a_mes5[[#This Row],[IMPORTE NETO]:[EXENTO]]) -> 0
G64: =IFERROR(IF(venta_a_mes5[[#This Row],[CUIT]]="","-",VLOOKUP(venta_a_mes5[[#This Row],[CUIT]],Lista_CUIT[#All],2,0)),"CUIT NO CARGADO") -> - | I64: =venta_a_mes5[[#This Row],[IMPORTE NETO]]*0.21 -> 0 | L64: =SUM(venta_a_mes5[[#This Row],[IMPORTE NETO]:[EXENTO]]) -> 0
... G72: =IFERROR(IF(venta_a_mes5[[#This Row],[CUIT]]="","-",VLOOKUP(venta_a_mes5[[#This Row],[CUIT]],Lista_CUIT[#All],2,0)),"CUIT NO CARGADO") -> - | I72: =venta_a_mes5[[#This Row],[IMPORTE NETO]]*0.21 -> 0 | L72: =SUM(venta_a_mes5[[#This Row],[IMPORTE NETO]:[EXENTO]]) -> 0
B73: Total | H73: =SUBTOTAL(109,venta_a_mes5[IMPORTE NETO]) -> 0 | I73: =SUBTOTAL(109,venta_a_mes5[IVA 21%]) -> 0 | J73: =SUBTOTAL(109,venta_a_mes5[IVA 10,5%]) -> 0 | K73: =SUBTOTAL(109,venta_a_mes5[EXENTO]) -> 0 | L73: =SUBTOTAL(109,venta_a_mes5[TOTAL]) -> 0 | M73: =SUBTOTAL(103,venta_a_mes5[Provincia]) -> 0
B75: VENTAS "B"
B76: FECHA | C76: TIPO | D76: PTO VENTA | E76: Nº FACTURA | F76: CUIT | G76: RAZON SOCIAL | H76: IMPORTE NETO | I76: IVA 21% | J76: IVA 10,5% | K76: EXENTO | L76: TOTAL | M76: Provincia
G77: =IFERROR(IF(ventas_b_mes5[[#This Row],[CUIT]]="","-",VLOOKUP(ventas_b_mes5[[#This Row],[CUIT]],Lista_CUIT[#All],2,0)),"CUIT NO CARGADO") -> - | I77: =ventas_b_mes5[[#This Row],[IMPORTE NETO]]*0.21 -> 0 | L77: =SUM(ventas_b_mes5[[#This Row],[IMPORTE NETO]:[EXENTO]]) -> 0
G78: =IFERROR(IF(ventas_b_mes5[[#This Row],[CUIT]]="","-",VLOOKUP(ventas_b_mes5[[#This Row],[CUIT]],Lista_CUIT[#All],2,0)),"CUIT NO CARGADO") -> - | I78: =ventas_b_mes5[[#This Row],[IMPORTE NETO]]*0.21 -> 0 | L78: =SUM(ventas_b_mes5[[#This Row],[IMPORTE NETO]:[EXENTO]]) -> 0
G79: =IFERROR(IF(ventas_b_mes5[[#This Row],[CUIT]]="","-",VLOOKUP(ventas_b_mes5[[#This Row],[CUIT]],Lista_CUIT[#All],2,0)),"CUIT NO CARGADO") -> - | I79: =ventas_b_mes5[[#This Row],[IMPORTE NETO]]*0.21 -> 0 | L79: =SUM(ventas_b_mes5[[#This Row],[IMPORTE NETO]:[EXENTO]]) -> 0
G80: =IFERROR(IF(ventas_b_mes5[[#This Row],[CUIT]]="","-",VLOOKUP(ventas_b_mes5[[#This Row],[CUIT]],Lista_CUIT[#All],2,0)),"CUIT NO CARGADO") -> - | I80: =ventas_b_mes5[[#This Row],[IMPORTE NETO]]*0.21 -> 0 | L80: =SUM(ventas_b_mes5[[#This Row],[IMPORTE NETO]:[EXENTO]]) -> 0
G81: =IFERROR(IF(ventas_b_mes5[[#This Row],[CUIT]]="","-",VLOOKUP(ventas_b_mes5[[#This Row],[CUIT]],Lista_CUIT[#All],2,0)),"CUIT NO CARGADO") -> - | I81: =ventas_b_mes5[[#This Row],[IMPORTE NETO]]*0.21 -> 0 | L81: =SUM(ventas_b_mes5[[#This Row],[IMPORTE NETO]:[EXENTO]]) -> 0
G82: =IFERROR(IF(ventas_b_mes5[[#This Row],[CUIT]]="","-",VLOOKUP(ventas_b_mes5[[#This Row],[CUIT]],Lista_CUIT[#All],2,0)),"CUIT NO CARGADO") -> - | I82: =ventas_b_mes5[[#This Row],[IMPORTE NETO]]*0.21 -> 0 | L82: =SUM(ventas_b_mes5[[#This Row],[IMPORTE NETO]:[EXENTO]]) -> 0
B83: Total | H83: =SUBTOTAL(109,ventas_b_mes5[IMPORTE NETO]) -> 0 | I83: =SUBTOTAL(109,ventas_b_mes5[IVA 21%]) -> 0 | J83: =SUBTOTAL(109,ventas_b_mes5[IVA 10,5%]) -> 0 | K83: =SUBTOTAL(109,ventas_b_mes5[EXENTO]) -> 0 | L83: =SUBTOTAL(109,ventas_b_mes5[TOTAL]) -> 0 | M83: =SUBTOTAL(103,ventas_b_mes5[Provincia]) -> 0
C91: RETENCIONES
C92: FECHA | D92: COMP Nº | E92: Columna1 | F92: CUIT | G92: RAZON SOCIAL | H92: Ganancias | I92: IVA | J92: SUSS | K92: IIBB BSAS | L92: IIBB CABA
G93: =IFERROR(IF(Retenciones_mes5[[#This Row],[CUIT]]="","-",VLOOKUP(Retenciones_mes5[[#This Row],[CUIT]],Lista_CUIT[#All],2,0)),"CUIT NO CARGADO") -> -
G94: =IFERROR(IF(Retenciones_mes5[[#This Row],[CUIT]]="","-",VLOOKUP(Retenciones_mes5[[#This Row],[CUIT]],Lista_CUIT[#All],2,0)),"CUIT NO CARGADO") -> -
G95: =IFERROR(IF(Retenciones_mes5[[#This Row],[CUIT]]="","-",VLOOKUP(Retenciones_mes5[[#This Row],[CUIT]],Lista_CUIT[#All],2,0)),"CUIT NO CARGADO") -> -
G96: =IFERROR(IF(Retenciones_mes5[[#This Row],[CUIT]]="","-",VLOOKUP(Retenciones_mes5[[#This Row],[CUIT]],Lista_CUIT[#All],2,0)),"CUIT NO CARGADO") -> -
G97: =IFERROR(IF(Retenciones_mes5[[#This Row],[CUIT]]="","-",VLOOKUP(Retenciones_mes5[[#This Row],[CUIT]],Lista_CUIT[#All],2,0)),"CUIT NO CARGADO") -> -

Sheet Jun-26
B1: LIBRO IVA COMPRAS | G1: ='Ene-26'!G1:M1 -> RABLEB SRL | N1: =EDATE('Ene-26'!N1,5) -> 46174
B3: TOTAL COMPRAS | G3: TOTAL CREDITO FISCAL | J3: TOTAL VENTAS NETAS | M3: TOTAL DEBITO FISCAL | P3: RESULTADO
B4: =SUM(compras_mes6[[#Totals],[NETO GRAVADO]])+extracto_banco_mes6[[#Totals],[NETO]] -> 0 | G4: =compras_mes6[[#Totals],[IVA 21 %]]+compras_mes6[[#Totals],[IVA 27%]]+compras_mes6[[#Totals],[IVA 10,5%]]+extracto_banco_mes6[[#Totals],[IVA 21%]]+extracto_banco_mes6[[#Totals],[IVA 10,5%]] -> 0 | J4: =venta_a_mes6[[#Totals],[IMPORTE NETO]]+ventas_b_mes6[[#Totals],[IMPORTE NETO]] -> 0 | M4: =venta_a_mes6[[#Totals],[IVA 21%]]+venta_a_mes6[[#Totals],[IVA 10,5%]]+ventas_b_mes6[[#Totals],[IVA 21%]]+ventas_b_mes6[[#Totals],[IVA 10,5%]] -> 0 | P4: =G4-M4 -> 0
B8: FECHA | C8: TIPO | D8: PTO VTA | E8: NRO. CPTE | F8: CUIT | G8: RAZON SOCIAL | H8: NETO GRAVADO | I8: IVA 21 % | J8: IVA 27% | K8: IVA 10,5% | L8: PERC. IVA | M8: PERC IIBB BS AS | N8: PERC. IIBB CABA | O8: Otros / No Grav. | P8: TOTAL | Q8: Tipo de Gasto | R8: Provincia
G9: =IFERROR(IF(compras_mes6[[#This Row],[CUIT]]="","-",VLOOKUP(compras_mes6[[#This Row],[CUIT]],Lista_CUIT[#All],2,0)),"CUIT NO CARGADO") -> - | I9: =IF(compras_mes6[[#This Row],[NETO GRAVADO]]="","",compras_mes6[[#This Row],[NETO GRAVADO]]*0.21) | P9: =SUM(compras_mes6[[#This Row],[NETO GRAVADO]:[Otros / No Grav.]]) -> 0 | Q9: =IFERROR(IF(compras_mes6[[#This Row],[CUIT]]="","-",VLOOKUP(compras_mes6[[#This Row],[CUIT]],Lista_CUIT[#All],3,0)),"CUIT NO CARGADO") -> - | R9: =IFERROR(IF(compras_mes6[[#This Row],[CUIT]]="","-",VLOOKUP(compras_mes6[[#This Row],[CUIT]],Lista_CUIT[#All],4,0)),"CUIT NO CARGADO") -> -
G10: =IFERROR(IF(compras_mes6[[#This Row],[CUIT]]="","-",VLOOKUP(compras_mes6[[#This Row],[CUIT]],Lista_CUIT[#All],2,0)),"CUIT NO CARGADO") -> - | I10: =IF(compras_mes6[[#This Row],[NETO GRAVADO]]="","",compras_mes6[[#This Row],[NETO GRAVADO]]*0.21) | P10: =SUM(compras_mes6[[#This Row],[NETO GRAVADO]:[Otros / No Grav.]]) -> 0 | Q10: =IFERROR(IF(compras_mes6[[#This Row],[CUIT]]="","-",VLOOKUP(compras_mes6[[#This Row],[CUIT]],Lista_CUIT[#All],3,0)),"CUIT NO CARGADO") -> - | R10: =IFERROR(IF(compras_mes6[[#This Row],[CUIT]]="","-",VLOOKUP(compras_mes6[[#This Row],[CUIT]],Lista_CUIT[#All],4,0)),"CUIT NO CARGADO") -> -
G11: =IFERROR(IF(compras_mes6[[#This Row],[CUIT]]="","-",VLOOKUP(compras_mes6[[#This Row],[CUIT]],Lista_CUIT[#All],2,0)),"CUIT NO CARGADO") -> - | I11: =IF(compras_mes6[[#This Row],[NETO GRAVADO]]="","",compras_mes6[[#This Row],[NETO GRAVADO]]*0.21) | P11: =SUM(compras_mes6[[#This Row],[NETO GRAVADO]:[Otros / No Grav.]]) -> 0 | Q11: =IFERROR(IF(compras_mes6[[#This Row],[CUIT]]="","-",VLOOKUP(compras_mes6[[#This Row],[CUIT]],Lista_CUIT[#All],3,0)),"CUIT NO CARGADO") -> - | R11: =IFERROR(IF(compras_mes6[[#This Row],[CUIT]]="","-",VLOOKUP(compras_mes6[[#This Row],[CUIT]],Lista_CUIT[#All],4,0)),"CUIT NO CARGADO") -> -
G12: =IFERROR(IF(compras_mes6[[#This Row],[CUIT]]="","-",VLOOKUP(compras_mes6[[#This Row],[CUIT]],Lista_CUIT[#All],2,0)),"CUIT NO CARGADO") -> - | I12: =IF(compras_mes6[[#This Row],[NETO GRAVADO]]="","",compras_mes6[[#This Row],[NETO GRAVADO]]*0.21) | P12: =SUM(compras_mes6[[#This Row],[NETO GRAVADO]:[Otros / No Grav.]]) -> 0 | Q12: =IFERROR(IF(compras_mes6[[#This Row],[CUIT]]="","-",VLOOKUP(compras_mes6[[#This Row],[CUIT]],Lista_CUIT[#All],3,0)),"CUIT NO CARGADO") -> - | R12: =IFERROR(IF(compras_mes6[[#This Row],[CUIT]]="","-",VLOOKUP(compras_mes6[[#This Row],[CUIT]],Lista_CUIT[#All],4,0)),"CUIT NO CARGADO") -> -
G13: =IFERROR(IF(compras_mes6[[#This Row],[CUIT]]="","-",VLOOKUP(compras_mes6[[#This Row],[CUIT]],Lista_CUIT[#All],2,0)),"CUIT NO CARGADO") -> - | I13: =IF(compras_mes6[[#This Row],[NETO GRAVADO]]="","",compras_mes6[[#This Row],[NETO GRAVADO]]*0.21) | P13: =SUM(compras_mes6[[#This Row],[NETO GRAVADO]:[Otros / No Grav.]]) -> 0 | Q13: =IFERROR(IF(compras_mes6[[#This Row],[CUIT]]="","-",VLOOKUP(compras_mes6[[#This Row],[CUIT]],Lista_CUIT[#All],3,0)),"CUIT NO CARGADO") -> - | R13: =IFERROR(IF(compras_mes6[[#This Row],[CUIT]]="","-",VLOOKUP(compras_mes6[[#This Row],[CUIT]],Lista_CUIT[#All],4,0)),"CUIT NO CARGADO") -> -
G14: =IFERROR(IF(compras_mes6[[#This Row],[CUIT]]="","-",VLOOKUP(compras_mes6[[#This Row],[CUIT]],Lista_CUIT[#All],2,0)),"CUIT NO CARGADO") -> - | I14: =IF(compras_mes6[[#This Row],[NETO GRAVADO]]="","",compras_mes6[[#This Row],[NETO GRAVADO]]*0.21) | P14: =SUM(compras_mes6[[#This Row],[NETO GRAVADO]:[Otros / No Grav.]]) -> 0 | Q14: =IFERROR(IF(compras_mes6[[#This Row],[CUIT]]="","-",VLOOKUP(compras_mes6[[#This Row],[CUIT]],Lista_CUIT[#All],3,0)),"CUIT NO CARGADO") -> - | R14: =IFERROR(IF(compras_mes6[[#This Row],[CUIT]]="","-",VLOOKUP(compras_mes6[[#This Row],[CUIT]],Lista_CUIT[#All],4,0)),"CUIT NO CARGADO") -> -
G15: =IFERROR(IF(compras_mes6[[#This Row],[CUIT]]="","-",VLOOKUP(compras_mes6[[#This Row],[CUIT]],Lista_CUIT[#All],2,0)),"CUIT NO CARGADO") -> - | I15: =IF(compras_mes6[[#This Row],[NETO GRAVADO]]="","",compras_mes6[[#This Row],[NETO GRAVADO]]*0.21) | P15: =SUM(compras_mes6[[#This Row],[NETO GRAVADO]:[Otros / No Grav.]]) -> 0 | Q15: =IFERROR(IF(compras_mes6[[#This Row],[CUIT]]="","-",VLOOKUP(compras_mes6[[#This Row],[CUIT]],Lista_CUIT[#All],3,0)),"CUIT NO CARGADO") -> - | R15: =IFERROR(IF(compras_mes6[[#This Row],[CUIT]]="","-",VLOOKUP(compras_mes6[[#This Row],[CUIT]],Lista_CUIT[#All],4,0)),"CUIT NO CARGADO") -> -
G16: =IFERROR(IF(compras_mes6[[#This Row],[CUIT]]="","-",VLOOKUP(compras_mes6[[#This Row],[CUIT]],Lista_CUIT[#All],2,0)),"CUIT NO CARGADO") -> - | I16: =IF(compras_mes6[[#This Row],[NETO GRAVADO]]="","",compras_mes6[[#This Row],[NETO GRAVADO]]*0.21) | P16: =SUM(compras_mes6[[#This Row],[NETO GRAVADO]:[Otros / No Grav.]]) -> 0 | Q16: =IFERROR(IF(compras_mes6[[#This Row],[CUIT]]="","-",VLOOKUP(compras_mes6[[#This Row],[CUIT]],Lista_CUIT[#All],3,0)),"CUIT NO CARGADO") -> - | R16: =IFERROR(IF(compras_mes6[[#This Row],[CUIT]]="","-",VLOOKUP(compras_mes6[[#This Row],[CUIT]],Lista_CUIT[#All],4,0)),"CUIT NO CARGADO") -> -
G17: =IFERROR(IF(compras_mes6[[#This Row],[CUIT]]="","-",VLOOKUP(compras_mes6[[#This Row],[CUIT]],Lista_CUIT[#All],2,0)),"CUIT NO CARGADO") -> - | I17: =IF(compras_mes6[[#This Row],[NETO GRAVADO]]="","",compras_mes6[[#This Row],[NETO GRAVADO]]*0.21) | P17: =SUM(compras_mes6[[#This Row],[NETO GRAVADO]:[Otros / No Grav.]]) -> 0 | Q17: =IFERROR(IF(compras_mes6[[#This Row],[CUIT]]="","-",VLOOKUP(compras_mes6[[#This Row],[CUIT]],Lista_CUIT[#All],3,0)),"CUIT NO CARGADO") -> - | R17: =IFERROR(IF(compras_mes6[[#This Row],[CUIT]]="","-",VLOOKUP(compras_mes6[[#This Row],[CUIT]],Lista_CUIT[#All],4,0)),"CUIT NO CARGADO") -> -
G18: =IFERROR(IF(compras_mes6[[#This Row],[CUIT]]="","-",VLOOKUP(compras_mes6[[#This Row],[CUIT]],Lista_CUIT[#All],2,0)),"CUIT NO CARGADO") -> - | I18: =IF(compras_mes6[[#This Row],[NETO GRAVADO]]="","",compras_mes6[[#This Row],[NETO GRAVADO]]*0.21) | P18: =SUM(compras_mes6[[#This Row],[NETO GRAVADO]:[Otros / No Grav.]]) -> 0 | Q18: =IFERROR(IF(compras_mes6[[#This Row],[CUIT]]="","-",VLOOKUP(compras_mes6[[#This Row],[CUIT]],Lista_CUIT[#All],3,0)),"CUIT NO CARGADO") -> - | R18: =IFERROR(IF(compras_mes6[[#This Row],[CUIT]]="","-",VLOOKUP(compras_mes6[[#This Row],[CUIT]],Lista_CUIT[#All],4,0)),"CUIT NO CARGADO") -> -
G19: =IFERROR(IF(compras_mes6[[#This Row],[CUIT]]="","-",VLOOKUP(compras_mes6[[#This Row],[CUIT]],Lista_CUIT[#All],2,0)),"CUIT NO CARGADO") -> - | I19: =IF(compras_mes6[[#This Row],[NETO GRAVADO]]="","",compras_mes6[[#This Row],[NETO GRAVADO]]*0.21) | P19: =SUM(compras_mes6[[#This Row],[NETO GRAVADO]:[Otros / No Grav.]]) -> 0 | Q19: =IFERROR(IF(compras_mes6[[#This Row],[CUIT]]="","-",VLOOKUP(compras_mes6[[#This Row],[CUIT]],Lista_CUIT[#All],3,0)),"CUIT NO CARGADO") -> - | R19: =IFERROR(IF(compras_mes6[[#This Row],[CUIT]]="","-",VLOOKUP(compras_mes6[[#This Row],[CUIT]],Lista_CUIT[#All],4,0)),"CUIT NO CARGADO") -> -
G20: =IFERROR(IF(compras_mes6[[#This Row],[CUIT]]="","-",VLOOKUP(compras_mes6[[#This Row],[CUIT]],Lista_CUIT[#All],2,0)),"CUIT NO CARGADO") -> - | I20: =IF(compras_mes6[[#This Row],[NETO GRAVADO]]="","",compras_mes6[[#This Row],[NETO GRAVADO]]*0.21) | P20: =SUM(compras_mes6[[#This Row],[NETO GRAVADO]:[Otros / No Grav.]]) -> 0 | Q20: =IFERROR(IF(compras_mes6[[#This Row],[CUIT]]="","-",VLOOKUP(compras_mes6[[#This Row],[CUIT]],Lista_CUIT[#All],3,0)),"CUIT NO CARGADO") -> - | R20: =IFERROR(IF(compras_mes6[[#This Row],[CUIT]]="","-",VLOOKUP(compras_mes6[[#This Row],[CUIT]],Lista_CUIT[#All],4,0)),"CUIT NO CARGADO") -> -
... G42: =IFERROR(IF(compras_mes6[[#This Row],[CUIT]]="","-",VLOOKUP(compras_mes6[[#This Row],[CUIT]],Lista_CUIT[#All],2,0)),"CUIT NO CARGADO") -> - | I42: =IF(compras_mes6[[#This Row],[NETO GRAVADO]]="","",compras_mes6[[#This Row],[NETO GRAVADO]]*0.21) | P42: =SUM(compras_mes6[[#This Row],[NETO GRAVADO]:[Otros / No Grav.]]) -> 0 | Q42: =IFERROR(IF(compras_mes6[[#This Row],[CUIT]]="","-",VLOOKUP(compras_mes6[[#This Row],[CUIT]],Lista_CUIT[#All],3,0)),"CUIT NO CARGADO") -> - | R42: =IFERROR(IF(compras_mes6[[#This Row],[CUIT]]="","-",VLOOKUP(compras_mes6[[#This Row],[CUIT]],Lista_CUIT[#All],4,0)),"CUIT NO CARGADO") -> -
B43: Total | H43: =SUBTOTAL(109,compras_mes6[NETO GRAVADO]) -> 0 | I43: =SUBTOTAL(109,compras_mes6[IVA 21 %]) -> 0 | J43: =SUBTOTAL(109,compras_mes6[IVA 27%]) -> 0 | K43: =SUBTOTAL(109,compras_mes6[IVA 10,5%]) -> 0 | L43: =SUBTOTAL(109,compras_mes6[PERC. IVA]) -> 0 | M43: =SUBTOTAL(109,compras_mes6[PERC IIBB BS AS]) -> 0 | N43: =SUBTOTAL(109,compras_mes6[PERC. IIBB CABA]) -> 0 | O43: =SUBTOTAL(109,compras_mes6[Otros / No Grav.]) -> 0 | P43: =SUBTOTAL(109,compras_mes6[TOTAL]) -> 0
D48: LIQUIDACION EXTRACTOS BANCARIOS-TARJETAS
D49: FECHA | E49: NRO CPTE | F49: BANCO | G49: NETO | H49: IVA 21% | I49: IVA 10,5% | J49: RET IIBB CABA | K49: PERC IVA | L49: PERC IIBB
H50: =extracto_banco_mes6[[#This Row],[NETO]]*0.21 -> 0
D53: Total | G53: =SUBTOTAL(109,extracto_banco_mes6[NETO]) -> 0 | H53: =SUBTOTAL(109,extracto_banco_mes6[IVA 21%]) -> 0 | I53: =SUBTOTAL(109,extracto_banco_mes6[IVA 10,5%]) -> 0 | J53: =SUBTOTAL(109,extracto_banco_mes6[RET IIBB CABA]) -> 0 | K53: =SUBTOTAL(109,extracto_banco_mes6[PERC IVA]) -> 0 | L53: =SUBTOTAL(109,extracto_banco_mes6[PERC IIBB]) -> 0
D57: FACTURAS C
D58: FECHA | E58: PTO VTA | F58: FC Nº | G58: CUIT | H58: RAZON SOCIAL | I58: TOTAL | J58: TIPO DE GASTO | K58: Provincia
H59: =IFERROR(IF(factura_c_mes6[[#This Row],[CUIT]]="","-",VLOOKUP(factura_c_mes6[[#This Row],[CUIT]],Lista_CUIT[#All],2,0)),"CUIT NO CARGADO") -> - | J59: =IFERROR(IF(factura_c_mes6[[#This Row],[CUIT]]="","-",VLOOKUP(factura_c_mes6[[#This Row],[CUIT]],Lista_CUIT[#All],3,0)),"CUIT NO CARGADO") -> - | K59: =IFERROR(IF(factura_c_mes6[[#This Row],[CUIT]]="","-",VLOOKUP(factura_c_mes6[[#This Row],[CUIT]],Lista_CUIT[#All],4,0)),"CUIT NO CARGADO") -> -
H60: =IFERROR(IF(factura_c_mes6[[#This Row],[CUIT]]="","-",VLOOKUP(factura_c_mes6[[#This Row],[CUIT]],Lista_CUIT[#All],2,0)),"CUIT NO CARGADO") -> - | J60: =IFERROR(IF(factura_c_mes6[[#This Row],[CUIT]]="","-",VLOOKUP(factura_c_mes6[[#This Row],[CUIT]],Lista_CUIT[#All],3,0)),"CUIT NO CARGADO") -> - | K60: =IFERROR(IF(factura_c_mes6[[#This Row],[CUIT]]="","-",VLOOKUP(factura_c_mes6[[#This Row],[CUIT]],Lista_CUIT[#All],4,0)),"CUIT NO CARGADO") -> -
H61: =IFERROR(IF(factura_c_mes6[[#This Row],[CUIT]]="","-",VLOOKUP(factura_c_mes6[[#This Row],[CUIT]],Lista_CUIT[#All],2,0)),"CUIT NO CARGADO") -> - | J61: =IFERROR(IF(factura_c_mes6[[#This Row],[CUIT]]="","-",VLOOKUP(factura_c_mes6[[#This Row],[CUIT]],Lista_CUIT[#All],3,0)),"CUIT NO CARGADO") -> - | K61: =IFERROR(IF(factura_c_mes6[[#This Row],[CUIT]]="","-",VLOOKUP(factura_c_mes6[[#This Row],[CUIT]],Lista_CUIT[#All],4,0)),"CUIT NO CARGADO") -> -
H62: =IFERROR(IF(factura_c_mes6[[#This Row],[CUIT]]="","-",VLOOKUP(factura_c_mes6[[#This Row],[CUIT]],Lista_CUIT[#All],2,0)),"CUIT NO CARGADO") -> - | J62: =IFERROR(IF(factura_c_mes6[[#This Row],[CUIT]]="","-",VLOOKUP(factura_c_mes6[[#This Row],[CUIT]],Lista_CUIT[#All],3,0)),"CUIT NO CARGADO") -> - | K62: =IFERROR(IF(factura_c_mes6[[#This Row],[CUIT]]="","-",VLOOKUP(factura_c_mes6[[#This Row],[CUIT]],Lista_CUIT[#All],4,0)),"CUIT NO CARGADO") -> -
H63: =IFERROR(IF(factura_c_mes6[[#This Row],[CUIT]]="","-",VLOOKUP(factura_c_mes6[[#This Row],[CUIT]],Lista_CUIT[#All],2,0)),"CUIT NO CARGADO") -> - | J63: =IFERROR(IF(factura_c_mes6[[#This Row],[CUIT]]="","-",VLOOKUP(factura_c_mes6[[#This Row],[CUIT]],Lista_CUIT[#All],3,0)),"CUIT NO CARGADO") -> - | K63: =IFERROR(IF(factura_c_mes6[[#This Row],[CUIT]]="","-",VLOOKUP(factura_c_mes6[[#This Row],[CUIT]],Lista_CUIT[#All],4,0)),"CUIT NO CARGADO") -> -
H64: =IFERROR(IF(factura_c_mes6[[#This Row],[CUIT]]="","-",VLOOKUP(factura_c_mes6[[#This Row],[CUIT]],Lista_CUIT[#All],2,0)),"CUIT NO CARGADO") -> - | J64: =IFERROR(IF(factura_c_mes6[[#This Row],[CUIT]]="","-",VLOOKUP(factura_c_mes6[[#This Row],[CUIT]],Lista_CUIT[#All],3,0)),"CUIT NO CARGADO") -> - | K64: =IFERROR(IF(factura_c_mes6[[#This Row],[CUIT]]="","-",VLOOKUP(factura_c_mes6[[#This Row],[CUIT]],Lista_CUIT[#All],4,0)),"CUIT NO CARGADO") -> -
D65: Total | I65: =SUBTOTAL(109,factura_c_mes6[TOTAL]) -> 0
B69: LIBRO IVA VENTAS | K69: =N1 -> 46174
B71: VENTAS "A"
B72: FECHA | C72: TIPO | D72: PTO VENTA | E72: Nº FACTURA | F72: CUIT | G72: RAZON SOCIAL | H72: IMPORTE NETO | I72: IVA 21% | J72: IVA 10,5% | K72: EXENTO | L72: TOTAL | M72: Provincia
G73: =IFERROR(IF(venta_a_mes6[[#This Row],[CUIT]]="","-",VLOOKUP(venta_a_mes6[[#This Row],[CUIT]],Lista_CUIT[#All],2,0)),"CUIT NO CARGADO") -> - | I73: =venta_a_mes6[[#This Row],[IMPORTE NETO]]*0.21 -> 0 | L73: =SUM(venta_a_mes6[[#This Row],[IMPORTE NETO]:[EXENTO]]) -> 0
G74: =IFERROR(IF(venta_a_mes6[[#This Row],[CUIT]]="","-",VLOOKUP(venta_a_mes6[[#This Row],[CUIT]],Lista_CUIT[#All],2,0)),"CUIT NO CARGADO") -> - | I74: =venta_a_mes6[[#This Row],[IMPORTE NETO]]*0.21 -> 0 | L74: =SUM(venta_a_mes6[[#This Row],[IMPORTE NETO]:[EXENTO]]) -> 0
G75: =IFERROR(IF(venta_a_mes6[[#This Row],[CUIT]]="","-",VLOOKUP(venta_a_mes6[[#This Row],[CUIT]],Lista_CUIT[#All],2,0)),"CUIT NO CARGADO") -> - | I75: =venta_a_mes6[[#This Row],[IMPORTE NETO]]*0.21 -> 0 | L75: =SUM(venta_a_mes6[[#This Row],[IMPORTE NETO]:[EXENTO]]) -> 0
G76: =IFERROR(IF(venta_a_mes6[[#This Row],[CUIT]]="","-",VLOOKUP(venta_a_mes6[[#This Row],[CUIT]],Lista_CUIT[#All],2,0)),"CUIT NO CARGADO") -> - | I76: =venta_a_mes6[[#This Row],[IMPORTE NETO]]*0.21 -> 0 | L76: =SUM(venta_a_mes6[[#This Row],[IMPORTE NETO]:[EXENTO]]) -> 0
G77: =IFERROR(IF(venta_a_mes6[[#This Row],[CUIT]]="","-",VLOOKUP(venta_a_mes6[[#This Row],[CUIT]],Lista_CUIT[#All],2,0)),"CUIT NO CARGADO") -> - | I77: =venta_a_mes6[[#This Row],[IMPORTE NETO]]*0.21 -> 0 | L77: =SUM(venta_a_mes6[[#This Row],[IMPORTE NETO]:[EXENTO]]) -> 0
G78: =IFERROR(IF(venta_a_mes6[[#This Row],[CUIT]]="","-",VLOOKUP(venta_a_mes6[[#This Row],[CUIT]],Lista_CUIT[#All],2,0)),"CUIT NO CARGADO") -> - | I78: =venta_a_mes6[[#This Row],[IMPORTE NETO]]*0.21 -> 0 | L78: =SUM(venta_a_mes6[[#This Row],[IMPORTE NETO]:[EXENTO]]) -> 0
G79: =IFERROR(IF(venta_a_mes6[[#This Row],[CUIT]]="","-",VLOOKUP(venta_a_mes6[[#This Row],[CUIT]],Lista_CUIT[#All],2,0)),"CUIT NO CARGADO") -> - | I79: =venta_a_mes6[[#This Row],[IMPORTE NETO]]*0.21 -> 0 | L79: =SUM(venta_a_mes6[[#This Row],[IMPORTE NETO]:[EXENTO]]) -> 0
G80: =IFERROR(IF(venta_a_mes6[[#This Row],[CUIT]]="","-",VLOOKUP(venta_a_mes6[[#This Row],[CUIT]],Lista_CUIT[#All],2,0)),"CUIT NO CARGADO") -> - | I80: =venta_a_mes6[[#This Row],[IMPORTE NETO]]*0.21 -> 0 | L80: =SUM(venta_a_mes6[[#This Row],[IMPORTE NETO]:[EXENTO]]) -> 0
G81: =IFERROR(IF(venta_a_mes6[[#This Row],[CUIT]]="","-",VLOOKUP(venta_a_mes6[[#This Row],[CUIT]],Lista_CUIT[#All],2,0)),"CUIT NO CARGADO") -> - | I81: =venta_a_mes6[[#This Row],[IMPORTE NETO]]*0.21 -> 0 | L81: =SUM(venta_a_mes6[[#This Row],[IMPORTE NETO]:[EXENTO]]) -> 0
G82: =IFERROR(IF(venta_a_mes6[[#This Row],[CUIT]]="","-",VLOOKUP(venta_a_mes6[[#This Row],[CUIT]],Lista_CUIT[#All],2,0)),"CUIT NO CARGADO") -> - | I82: =venta_a_mes6[[#This Row],[IMPORTE NETO]]*0.21 -> 0 | L82: =SUM(venta_a_mes6[[#This Row],[IMPORTE NETO]:[EXENTO]]) -> 0
G83: =IFERROR(IF(venta_a_mes6[[#This Row],[CUIT]]="","-",VLOOKUP(venta_a_mes6[[#This Row],[CUIT]],Lista_CUIT[#All],2,0)),"CUIT NO CARGADO") -> - | I83: =venta_a_mes6[[#This Row],[IMPORTE NETO]]*0.21 -> 0 | L83: =SUM(venta_a_mes6[[#This Row],[IMPORTE NETO]:[EXENTO]]) -> 0
G84: =IFERROR(IF(venta_a_mes6[[#This Row],[CUIT]]="","-",VLOOKUP(venta_a_mes6[[#This Row],[CUIT]],Lista_CUIT[#All],2,0)),"CUIT NO CARGADO") -> - | I84: =venta_a_mes6[[#This Row],[IMPORTE NETO]]*0.21 -> 0 | L84: =SUM(venta_a_mes6[[#This Row],[IMPORTE NETO]:[EXENTO]]) -> 0
... G100: =IFERROR(IF(venta_a_mes6[[#This Row],[CUIT]]="","-",VLOOKUP(venta_a_mes6[[#This Row],[CUIT]],Lista_CUIT[#All],2,0)),"CUIT NO CARGADO") -> - | I100: =venta_a_mes6[[#This Row],[IMPORTE NETO]]*0.21 -> 0 | L100: =SUM(venta_a_mes6[[#This Row],[IMPORTE NETO]:[EXENTO]]) -> 0
B101: Total | H101: =SUBTOTAL(109,venta_a_mes6[IMPORTE NETO]) -> 0 | I101: =SUBTOTAL(109,venta_a_mes6[IVA 21%]) -> 0 | J101: =SUBTOTAL(109,venta_a_mes6[IVA 10,5%]) -> 0 | K101: =SUBTOTAL(109,venta_a_mes6[EXENTO]) -> 0 | L101: =SUBTOTAL(109,venta_a_mes6[TOTAL]) -> 0 | M101: =SUBTOTAL(103,venta_a_mes6[Provincia]) -> 0
B102: VENTAS "B"
B103: FECHA | C103: TIPO | D103: PTO VENTA | E103: Nº FACTURA | F103: CUIT | G103: RAZON SOCIAL | H103: IMPORTE NETO | I103: IVA 21% | J103: IVA 10,5% | K103: EXENTO | L103: TOTAL | M103: Provincia
G104: =IFERROR(IF(ventas_b_mes6[[#This Row],[CUIT]]="","-",VLOOKUP(ventas_b_mes6[[#This Row],[CUIT]],Lista_CUIT[#All],2,0)),"CUIT NO CARGADO") -> - | L104: =SUM(ventas_b_mes6[[#This Row],[IMPORTE NETO]:[EXENTO]]) -> 0
G105: =IFERROR(IF(ventas_b_mes6[[#This Row],[CUIT]]="","-",VLOOKUP(ventas_b_mes6[[#This Row],[CUIT]],Lista_CUIT[#All],2,0)),"CUIT NO CARGADO") -> - | L105: =SUM(ventas_b_mes6[[#This Row],[IMPORTE NETO]:[EXENTO]]) -> 0
G106: =IFERROR(IF(ventas_b_mes6[[#This Row],[CUIT]]="","-",VLOOKUP(ventas_b_mes6[[#This Row],[CUIT]],Lista_CUIT[#All],2,0)),"CUIT NO CARGADO") -> - | L106: =SUM(ventas_b_mes6[[#This Row],[IMPORTE NETO]:[EXENTO]]) -> 0
G107: =IFERROR(IF(ventas_b_mes6[[#This Row],[CUIT]]="","-",VLOOKUP(ventas_b_mes6[[#This Row],[CUIT]],Lista_CUIT[#All],2,0)),"CUIT NO CARGADO") -> - | L107: =SUM(ventas_b_mes6[[#This Row],[IMPORTE NETO]:[EXENTO]]) -> 0
G108: =IFERROR(IF(ventas_b_mes6[[#This Row],[CUIT]]="","-",VLOOKUP(ventas_b_mes6[[#This Row],[CUIT]],Lista_CUIT[#All],2,0)),"CUIT NO CARGADO") -> - | L108: =SUM(ventas_b_mes6[[#This Row],[IMPORTE NETO]:[EXENTO]]) -> 0
G109: =IFERROR(IF(ventas_b_mes6[[#This Row],[CUIT]]="","-",VLOOKUP(ventas_b_mes6[[#This Row],[CUIT]],Lista_CUIT[#All],2,0)),"CUIT NO CARGADO") -> - | L109: =SUM(ventas_b_mes6[[#This Row],[IMPORTE NETO]:[EXENTO]]) -> 0
B110: Total | H110: =SUBTOTAL(109,ventas_b_mes6[IMPORTE NETO]) -> 0 | I110: =SUBTOTAL(109,ventas_b_mes6[IVA 21%]) -> 0 | J110: =SUBTOTAL(109,ventas_b_mes6[IVA 10,5%]) -> 0 | K110: =SUBTOTAL(109,ventas_b_mes6[EXENTO]) -> 0 | L110: =SUBTOTAL(109,ventas_b_mes6[TOTAL]) -> 0 | M110: =SUBTOTAL(103,ventas_b_mes6[Provincia]) -> 0
C118: RETENCIONES
C119: FECHA | D119: COMP Nº | E119: Columna1 | F119: CUIT | G119: RAZON SOCIAL | H119: Ganancias | I119: IVA | J119: SUSS | K119: IIBB BSAS | L119: IIBB CABA
G120: =IFERROR(IF(Retenciones_mes6[[#This Row],[CUIT]]="","-",VLOOKUP(Retenciones_mes6[[#This Row],[CUIT]],Lista_CUIT[#All],2,0)),"CUIT NO CARGADO") -> -
G121: =IFERROR(IF(Retenciones_mes6[[#This Row],[CUIT]]="","-",VLOOKUP(Retenciones_mes6[[#This Row],[CUIT]],Lista_CUIT[#All],2,0)),"CUIT NO CARGADO") -> -
G122: =IFERROR(IF(Retenciones_mes6[[#This Row],[CUIT]]="","-",VLOOKUP(Retenciones_mes6[[#This Row],[CUIT]],Lista_CUIT[#All],2,0)),"CUIT NO CARGADO") -> -
G123: =IFERROR(IF(Retenciones_mes6[[#This Row],[CUIT]]="","-",VLOOKUP(Retenciones_mes6[[#This Row],[CUIT]],Lista_CUIT[#All],2,0)),"CUIT NO CARGADO") -> -
G124: =IFERROR(IF(Retenciones_mes6[[#This Row],[CUIT]]="","-",VLOOKUP(Retenciones_mes6[[#This Row],[CUIT]],Lista_CUIT[#All],2,0)),"CUIT NO CARGADO") -> -

Sheet Jul-26
B1: LIBRO IVA COMPRAS | G1: ='Ene-26'!G1:M1 -> RABLEB SRL | N1: =EDATE('Ene-26'!N1,6) -> 46204
B3: TOTAL COMPRAS | G3: TOTAL CREDITO FISCAL | J3: TOTAL VENTAS NETAS | M3: TOTAL DEBITO FISCAL | P3: RESULTADO
B4: =SUM(compras_mes7[[#Totals],[NETO GRAVADO]])+extracto_banco_mes7[[#Totals],[NETO]] -> 0 | G4: =compras_mes7[[#Totals],[IVA 21 %]]+compras_mes7[[#Totals],[IVA 27%]]+compras_mes7[[#Totals],[IVA 10,5%]]+extracto_banco_mes7[[#Totals],[IVA 21%]]+extracto_banco_mes7[[#Totals],[IVA 10,5%]] -> 0 | J4: =venta_a_mes7[[#Totals],[IMPORTE NETO]]+ventas_b_mes7[[#Totals],[IMPORTE NETO]] -> 0 | M4: =venta_a_mes7[[#Totals],[IVA 21%]]+venta_a_mes7[[#Totals],[IVA 10,5%]]+ventas_b_mes7[[#Totals],[IVA 21%]]+ventas_b_mes7[[#Totals],[IVA 10,5%]] -> 0 | P4: =G4-M4 -> 0
B8: FECHA | C8: TIPO | D8: PTO VTA | E8: NRO. CPTE | F8: CUIT | G8: RAZON SOCIAL | H8: NETO GRAVADO | I8: IVA 21 % | J8: IVA 27% | K8: IVA 10,5% | L8: PERC. IVA | M8: PERC IIBB BS AS | N8: PERC. IIBB CABA | O8: Otros / No Grav. | P8: TOTAL | Q8: Tipo de Gasto | R8: Provincia
G9: =IFERROR(IF(compras_mes7[[#This Row],[CUIT]]="","-",VLOOKUP(compras_mes7[[#This Row],[CUIT]],Lista_CUIT[#All],2,0)),"CUIT NO CARGADO") -> - | I9: =IF(compras_mes7[[#This Row],[NETO GRAVADO]]="","",compras_mes7[[#This Row],[NETO GRAVADO]]*0.21) | P9: =SUM(compras_mes7[[#This Row],[NETO GRAVADO]:[Otros / No Grav.]]) -> 0 | Q9: =IFERROR(IF(compras_mes7[[#This Row],[CUIT]]="","-",VLOOKUP(compras_mes7[[#This Row],[CUIT]],Lista_CUIT[#All],3,0)),"CUIT NO CARGADO") -> - | R9: =IFERROR(IF(compras_mes7[[#This Row],[CUIT]]="","-",VLOOKUP(compras_mes7[[#This Row],[CUIT]],Lista_CUIT[#All],4,0)),"CUIT NO CARGADO") -> -
G10: =IFERROR(IF(compras_mes7[[#This Row],[CUIT]]="","-",VLOOKUP(compras_mes7[[#This Row],[CUIT]],Lista_CUIT[#All],2,0)),"CUIT NO CARGADO") -> - | I10: =IF(compras_mes7[[#This Row],[NETO GRAVADO]]="","",compras_mes7[[#This Row],[NETO GRAVADO]]*0.21) | P10: =SUM(compras_mes7[[#This Row],[NETO GRAVADO]:[Otros / No Grav.]]) -> 0 | Q10: =IFERROR(IF(compras_mes7[[#This Row],[CUIT]]="","-",VLOOKUP(compras_mes7[[#This Row],[CUIT]],Lista_CUIT[#All],3,0)),"CUIT NO CARGADO") -> - | R10: =IFERROR(IF(compras_mes7[[#This Row],[CUIT]]="","-",VLOOKUP(compras_mes7[[#This Row],[CUIT]],Lista_CUIT[#All],4,0)),"CUIT NO CARGADO") -> -
G11: =IFERROR(IF(compras_mes7[[#This Row],[CUIT]]="","-",VLOOKUP(compras_mes7[[#This Row],[CUIT]],Lista_CUIT[#All],2,0)),"CUIT NO CARGADO") -> - | I11: =IF(compras_mes7[[#This Row],[NETO GRAVADO]]="","",compras_mes7[[#This Row],[NETO GRAVADO]]*0.21) | P11: =SUM(compras_mes7[[#This Row],[NETO GRAVADO]:[Otros / No Grav.]]) -> 0 | Q11: =IFERROR(IF(compras_mes7[[#This Row],[CUIT]]="","-",VLOOKUP(compras_mes7[[#This Row],[CUIT]],Lista_CUIT[#All],3,0)),"CUIT NO CARGADO") -> - | R11: =IFERROR(IF(compras_mes7[[#This Row],[CUIT]]="","-",VLOOKUP(compras_mes7[[#This Row],[CUIT]],Lista_CUIT[#All],4,0)),"CUIT NO CARGADO") -> -
G12: =IFERROR(IF(compras_mes7[[#This Row],[CUIT]]="","-",VLOOKUP(compras_mes7[[#This Row],[CUIT]],Lista_CUIT[#All],2,0)),"CUIT NO CARGADO") -> - | P12: =SUM(compras_mes7[[#This Row],[NETO GRAVADO]:[Otros / No Grav.]]) -> 0 | Q12: =IFERROR(IF(compras_mes7[[#This Row],[CUIT]]="","-",VLOOKUP(compras_mes7[[#This Row],[CUIT]],Lista_CUIT[#All],3,0)),"CUIT NO CARGADO") -> - | R12: =IFERROR(IF(compras_mes7[[#This Row],[CUIT]]="","-",VLOOKUP(compras_mes7[[#This Row],[CUIT]],Lista_CUIT[#All],4,0)),"CUIT NO CARGADO") -> -
G13: =IFERROR(IF(compras_mes7[[#This Row],[CUIT]]="","-",VLOOKUP(compras_mes7[[#This Row],[CUIT]],Lista_CUIT[#All],2,0)),"CUIT NO CARGADO") -> - | I13: =IF(compras_mes7[[#This Row],[NETO GRAVADO]]="","",compras_mes7[[#This Row],[NETO GRAVADO]]*0.21) | P13: =SUM(compras_mes7[[#This Row],[NETO GRAVADO]:[Otros / No Grav.]]) -> 0 | Q13: =IFERROR(IF(compras_mes7[[#This Row],[CUIT]]="","-",VLOOKUP(compras_mes7[[#This Row],[CUIT]],Lista_CUIT[#All],3,0)),"CUIT NO CARGADO") -> - | R13: =IFERROR(IF(compras_mes7[[#This Row],[CUIT]]="","-",VLOOKUP(compras_mes7[[#This Row],[CUIT]],Lista_CUIT[#All],4,0)),"CUIT NO CARGADO") -> -
G14: =IFERROR(IF(compras_mes7[[#This Row],[CUIT]]="","-",VLOOKUP(compras_mes7[[#This Row],[CUIT]],Lista_CUIT[#All],2,0)),"CUIT NO CARGADO") -> - | I14: =IF(compras_mes7[[#This Row],[NETO GRAVADO]]="","",compras_mes7[[#This Row],[NETO GRAVADO]]*0.21) | P14: =SUM(compras_mes7[[#This Row],[NETO GRAVADO]:[Otros / No Grav.]]) -> 0 | Q14: =IFERROR(IF(compras_mes7[[#This Row],[CUIT]]="","-",VLOOKUP(compras_mes7[[#This Row],[CUIT]],Lista_CUIT[#All],3,0)),"CUIT NO CARGADO") -> - | R14: =IFERROR(IF(compras_mes7[[#This Row],[CUIT]]="","-",VLOOKUP(compras_mes7[[#This Row],[CUIT]],Lista_CUIT[#All],4,0)),"CUIT NO CARGADO") -> -
G15: =IFERROR(IF(compras_mes7[[#This Row],[CUIT]]="","-",VLOOKUP(compras_mes7[[#This Row],[CUIT]],Lista_CUIT[#All],2,0)),"CUIT NO CARGADO") -> - | I15: =IF(compras_mes7[[#This Row],[NETO GRAVADO]]="","",compras_mes7[[#This Row],[NETO GRAVADO]]*0.21) | P15: =SUM(compras_mes7[[#This Row],[NETO GRAVADO]:[Otros / No Grav.]]) -> 0 | Q15: =IFERROR(IF(compras_mes7[[#This Row],[CUIT]]="","-",VLOOKUP(compras_mes7[[#This Row],[CUIT]],Lista_CUIT[#All],3,0)),"CUIT NO CARGADO") -> - | R15: =IFERROR(IF(compras_mes7[[#This Row],[CUIT]]="","-",VLOOKUP(compras_mes7[[#This Row],[CUIT]],Lista_CUIT[#All],4,0)),"CUIT NO CARGADO") -> -
G16: =IFERROR(IF(compras_mes7[[#This Row],[CUIT]]="","-",VLOOKUP(compras_mes7[[#This Row],[CUIT]],Lista_CUIT[#All],2,0)),"CUIT NO CARGADO") -> - | I16: =IF(compras_mes7[[#This Row],[NETO GRAVADO]]="","",compras_mes7[[#This Row],[NETO GRAVADO]]*0.21) | P16: =SUM(compras_mes7[[#This Row],[NETO GRAVADO]:[Otros / No Grav.]]) -> 0 | Q16: =IFERROR(IF(compras_mes7[[#This Row],[CUIT]]="","-",VLOOKUP(compras_mes7[[#This Row],[CUIT]],Lista_CUIT[#All],3,0)),"CUIT NO CARGADO") -> - | R16: =IFERROR(IF(compras_mes7[[#This Row],[CUIT]]="","-",VLOOKUP(compras_mes7[[#This Row],[CUIT]],Lista_CUIT[#All],4,0)),"CUIT NO CARGADO") -> -
G17: =IFERROR(IF(compras_mes7[[#This Row],[CUIT]]="","-",VLOOKUP(compras_mes7[[#This Row],[CUIT]],Lista_CUIT[#All],2,0)),"CUIT NO CARGADO") -> - | I17: =IF(compras_mes7[[#This Row],[NETO GRAVADO]]="","",compras_mes7[[#This Row],[NETO GRAVADO]]*0.21) | P17: =SUM(compras_mes7[[#This Row],[NETO GRAVADO]:[Otros / No Grav.]]) -> 0 | Q17: =IFERROR(IF(compras_mes7[[#This Row],[CUIT]]="","-",VLOOKUP(compras_mes7[[#This Row],[CUIT]],Lista_CUIT[#All],3,0)),"CUIT NO CARGADO") -> - | R17: =IFERROR(IF(compras_mes7[[#This Row],[CUIT]]="","-",VLOOKUP(compras_mes7[[#This Row],[CUIT]],Lista_CUIT[#All],4,0)),"CUIT NO CARGADO") -> -
G18: =IFERROR(IF(compras_mes7[[#This Row],[CUIT]]="","-",VLOOKUP(compras_mes7[[#This Row],[CUIT]],Lista_CUIT[#All],2,0)),"CUIT NO CARGADO") -> - | I18: =IF(compras_mes7[[#This Row],[NETO GRAVADO]]="","",compras_mes7[[#This Row],[NETO GRAVADO]]*0.21) | P18: =SUM(compras_mes7[[#This Row],[NETO GRAVADO]:[Otros / No Grav.]]) -> 0 | Q18: =IFERROR(IF(compras_mes7[[#This Row],[CUIT]]="","-",VLOOKUP(compras_mes7[[#This Row],[CUIT]],Lista_CUIT[#All],3,0)),"CUIT NO CARGADO") -> - | R18: =IFERROR(IF(compras_mes7[[#This Row],[CUIT]]="","-",VLOOKUP(compras_mes7[[#This Row],[CUIT]],Lista_CUIT[#All],4,0)),"CUIT NO CARGADO") -> -
G19: =IFERROR(IF(compras_mes7[[#This Row],[CUIT]]="","-",VLOOKUP(compras_mes7[[#This Row],[CUIT]],Lista_CUIT[#All],2,0)),"CUIT NO CARGADO") -> - | I19: =IF(compras_mes7[[#This Row],[NETO GRAVADO]]="","",compras_mes7[[#This Row],[NETO GRAVADO]]*0.21) | P19: =SUM(compras_mes7[[#This Row],[NETO GRAVADO]:[Otros / No Grav.]]) -> 0 | Q19: =IFERROR(IF(compras_mes7[[#This Row],[CUIT]]="","-",VLOOKUP(compras_mes7[[#This Row],[CUIT]],Lista_CUIT[#All],3,0)),"CUIT NO CARGADO") -> - | R19: =IFERROR(IF(compras_mes7[[#This Row],[CUIT]]="","-",VLOOKUP(compras_mes7[[#This Row],[CUIT]],Lista_CUIT[#All],4,0)),"CUIT NO CARGADO") -> -
G20: =IFERROR(IF(compras_mes7[[#This Row],[CUIT]]="","-",VLOOKUP(compras_mes7[[#This Row],[CUIT]],Lista_CUIT[#All],2,0)),"CUIT NO CARGADO") -> - | I20: =IF(compras_mes7[[#This Row],[NETO GRAVADO]]="","",compras_mes7[[#This Row],[NETO GRAVADO]]*0.21) | P20: =SUM(compras_mes7[[#This Row],[NETO GRAVADO]:[Otros / No Grav.]]) -> 0 | Q20: =IFERROR(IF(compras_mes7[[#This Row],[CUIT]]="","-",VLOOKUP(compras_mes7[[#This Row],[CUIT]],Lista_CUIT[#All],3,0)),"CUIT NO CARGADO") -> - | R20: =IFERROR(IF(compras_mes7[[#This Row],[CUIT]]="","-",VLOOKUP(compras_mes7[[#This Row],[CUIT]],Lista_CUIT[#All],4,0)),"CUIT NO CARGADO") -> -
G21: =IFERROR(IF(compras_mes7[[#This Row],[CUIT]]="","-",VLOOKUP(compras_mes7[[#This Row],[CUIT]],Lista_CUIT[#All],2,0)),"CUIT NO CARGADO") -> - | I21: =IF(compras_mes7[[#This Row],[NETO GRAVADO]]="","",compras_mes7[[#This Row],[NETO GRAVADO]]*0.21) | P21: =SUM(compras_mes7[[#This Row],[NETO GRAVADO]:[Otros / No Grav.]]) -> 0 | Q21: =IFERROR(IF(compras_mes7[[#This Row],[CUIT]]="","-",VLOOKUP(compras_mes7[[#This Row],[CUIT]],Lista_CUIT[#All],3,0)),"CUIT NO CARGADO") -> - | R21: =IFERROR(IF(compras_mes7[[#This Row],[CUIT]]="","-",VLOOKUP(compras_mes7[[#This Row],[CUIT]],Lista_CUIT[#All],4,0)),"CUIT NO CARGADO") -> -
G22: =IFERROR(IF(compras_mes7[[#This Row],[CUIT]]="","-",VLOOKUP(compras_mes7[[#This Row],[CUIT]],Lista_CUIT[#All],2,0)),"CUIT NO CARGADO") -> - | I22: =IF(compras_mes7[[#This Row],[NETO GRAVADO]]="","",compras_mes7[[#This Row],[NETO GRAVADO]]*0.21) | P22: =SUM(compras_mes7[[#This Row],[NETO GRAVADO]:[Otros / No Grav.]]) -> 0 | Q22: =IFERROR(IF(compras_mes7[[#This Row],[CUIT]]="","-",VLOOKUP(compras_mes7[[#This Row],[CUIT]],Lista_CUIT[#All],3,0)),"CUIT NO CARGADO") -> - | R22: =IFERROR(IF(compras_mes7[[#This Row],[CUIT]]="","-",VLOOKUP(compras_mes7[[#This Row],[CUIT]],Lista_CUIT[#All],4,0)),"CUIT NO CARGADO") -> -
G23: =IFERROR(IF(compras_mes7[[#This Row],[CUIT]]="","-",VLOOKUP(compras_mes7[[#This Row],[CUIT]],Lista_CUIT[#All],2,0)),"CUIT NO CARGADO") -> - | I23: =IF(compras_mes7[[#This Row],[NETO GRAVADO]]="","",compras_mes7[[#This Row],[NETO GRAVADO]]*0.21) | P23: =SUM(compras_mes7[[#This Row],[NETO GRAVADO]:[Otros / No Grav.]]) -> 0 | Q23: =IFERROR(IF(compras_mes7[[#This Row],[CUIT]]="","-",VLOOKUP(compras_mes7[[#This Row],[CUIT]],Lista_CUIT[#All],3,0)),"CUIT NO CARGADO") -> - | R23: =IFERROR(IF(compras_mes7[[#This Row],[CUIT]]="","-",VLOOKUP(compras_mes7[[#This Row],[CUIT]],Lista_CUIT[#All],4,0)),"CUIT NO CARGADO") -> -
G24: =IFERROR(IF(compras_mes7[[#This Row],[CUIT]]="","-",VLOOKUP(compras_mes7[[#This Row],[CUIT]],Lista_CUIT[#All],2,0)),"CUIT NO CARGADO") -> - | I24: =IF(compras_mes7[[#This Row],[NETO GRAVADO]]="","",compras_mes7[[#This Row],[NETO GRAVADO]]*0.21) | P24: =SUM(compras_mes7[[#This Row],[NETO GRAVADO]:[Otros / No Grav.]]) -> 0 | Q24: =IFERROR(IF(compras_mes7[[#This Row],[CUIT]]="","-",VLOOKUP(compras_mes7[[#This Row],[CUIT]],Lista_CUIT[#All],3,0)),"CUIT NO CARGADO") -> - | R24: =IFERROR(IF(compras_mes7[[#This Row],[CUIT]]="","-",VLOOKUP(compras_mes7[[#This Row],[CUIT]],Lista_CUIT[#All],4,0)),"CUIT NO CARGADO") -> -
B25: Total | H25: =SUBTOTAL(109,compras_mes7[NETO GRAVADO]) -> 0 | I25: =SUBTOTAL(109,compras_mes7[IVA 21 %]) -> 0 | J25: =SUBTOTAL(109,compras_mes7[IVA 27%]) -> 0 | K25: =SUBTOTAL(109,compras_mes7[IVA 10,5%]) -> 0 | L25: =SUBTOTAL(109,compras_mes7[PERC. IVA]) -> 0 | M25: =SUBTOTAL(109,compras_mes7[PERC IIBB BS AS]) -> 0 | N25: =SUBTOTAL(109,compras_mes7[PERC. IIBB CABA]) -> 0 | O25: =SUBTOTAL(109,compras_mes7[Otros / No Grav.]) -> 0 | P25: =SUBTOTAL(109,compras_mes7[TOTAL]) -> 0
D30: LIQUIDACION EXTRACTOS BANCARIOS-TARJETAS
D31: FECHA | E31: NRO CPTE | F31: BANCO | G31: NETO | H31: IVA 21% | I31: IVA 10,5% | J31: RET IIBB CABA | K31: PERC IVA | L31: PERC IIBB
D35: Total | G35: =SUBTOTAL(109,extracto_banco_mes7[NETO]) -> 0 | H35: =SUBTOTAL(109,extracto_banco_mes7[IVA 21%]) -> 0 | I35: =SUBTOTAL(109,extracto_banco_mes7[IVA 10,5%]) -> 0 | J35: =SUBTOTAL(109,extracto_banco_mes7[RET IIBB CABA]) -> 0 | K35: =SUBTOTAL(109,extracto_banco_mes7[PERC IVA]) -> 0 | L35: =SUBTOTAL(109,extracto_banco_mes7[PERC IIBB]) -> 0
D39: FACTURAS C
D40: FECHA | E40: PTO VTA | F40: FC Nº | G40: CUIT | H40: RAZON SOCIAL | I40: TOTAL | J40: TIPO DE GASTO | K40: Provincia
H41: =IFERROR(IF(factura_c_mes7[[#This Row],[CUIT]]="","-",VLOOKUP(factura_c_mes7[[#This Row],[CUIT]],Lista_CUIT[#All],2,0)),"CUIT NO CARGADO") -> - | J41: =IFERROR(IF(factura_c_mes7[[#This Row],[CUIT]]="","-",VLOOKUP(factura_c_mes7[[#This Row],[CUIT]],Lista_CUIT[#All],3,0)),"CUIT NO CARGADO") -> - | K41: =IFERROR(IF(factura_c_mes7[[#This Row],[CUIT]]="","-",VLOOKUP(factura_c_mes7[[#This Row],[CUIT]],Lista_CUIT[#All],4,0)),"CUIT NO CARGADO") -> -
H42: =IFERROR(IF(factura_c_mes7[[#This Row],[CUIT]]="","-",VLOOKUP(factura_c_mes7[[#This Row],[CUIT]],Lista_CUIT[#All],2,0)),"CUIT NO CARGADO") -> - | J42: =IFERROR(IF(factura_c_mes7[[#This Row],[CUIT]]="","-",VLOOKUP(factura_c_mes7[[#This Row],[CUIT]],Lista_CUIT[#All],3,0)),"CUIT NO CARGADO") -> - | K42: =IFERROR(IF(factura_c_mes7[[#This Row],[CUIT]]="","-",VLOOKUP(factura_c_mes7[[#This Row],[CUIT]],Lista_CUIT[#All],4,0)),"CUIT NO CARGADO") -> -
H43: =IFERROR(IF(factura_c_mes7[[#This Row],[CUIT]]="","-",VLOOKUP(factura_c_mes7[[#This Row],[CUIT]],Lista_CUIT[#All],2,0)),"CUIT NO CARGADO") -> - | J43: =IFERROR(IF(factura_c_mes7[[#This Row],[CUIT]]="","-",VLOOKUP(factura_c_mes7[[#This Row],[CUIT]],Lista_CUIT[#All],3,0)),"CUIT NO CARGADO") -> - | K43: =IFERROR(IF(factura_c_mes7[[#This Row],[CUIT]]="","-",VLOOKUP(factura_c_mes7[[#This Row],[CUIT]],Lista_CUIT[#All],4,0)),"CUIT NO CARGADO") -> -
H44: =IFERROR(IF(factura_c_mes7[[#This Row],[CUIT]]="","-",VLOOKUP(factura_c_mes7[[#This Row],[CUIT]],Lista_CUIT[#All],2,0)),"CUIT NO CARGADO") -> - | J44: =IFERROR(IF(factura_c_mes7[[#This Row],[CUIT]]="","-",VLOOKUP(factura_c_mes7[[#This Row],[CUIT]],Lista_CUIT[#All],3,0)),"CUIT NO CARGADO") -> - | K44: =IFERROR(IF(factura_c_mes7[[#This Row],[CUIT]]="","-",VLOOKUP(factura_c_mes7[[#This Row],[CUIT]],Lista_CUIT[#All],4,0)),"CUIT NO CARGADO") -> -
H45: =IFERROR(IF(factura_c_mes7[[#This Row],[CUIT]]="","-",VLOOKUP(factura_c_mes7[[#This Row],[CUIT]],Lista_CUIT[#All],2,0)),"CUIT NO CARGADO") -> - | J45: =IFERROR(IF(factura_c_mes7[[#This Row],[CUIT]]="","-",VLOOKUP(factura_c_mes7[[#This Row],[CUIT]],Lista_CUIT[#All],3,0)),"CUIT NO CARGADO") -> - | K45: =IFERROR(IF(factura_c_mes7[[#This Row],[CUIT]]="","-",VLOOKUP(factura_c_mes7[[#This Row],[CUIT]],Lista_CUIT[#All],4,0)),"CUIT NO CARGADO") -> -
D46: Total | I46: =SUBTOTAL(109,factura_c_mes7[TOTAL]) -> 0
B51: LIBRO IVA VENTAS | K51: =N1 -> 46204
B53: VENTAS "A"
B54: FECHA | C54: TIPO | D54: PTO VENTA | E54: Nº FACTURA | F54: CUIT | G54: RAZON SOCIAL | H54: IMPORTE NETO | I54: IVA 21% | J54: IVA 10,5% | K54: EXENTO | L54: TOTAL | M54: Provincia
G55: =IFERROR(IF(venta_a_mes7[[#This Row],[CUIT]]="","-",VLOOKUP(venta_a_mes7[[#This Row],[CUIT]],Lista_CUIT[#All],2,0)),"CUIT NO CARGADO") -> - | L55: =SUM(venta_a_mes7[[#This Row],[IMPORTE NETO]:[EXENTO]]) -> 0
G56: =IFERROR(IF(venta_a_mes7[[#This Row],[CUIT]]="","-",VLOOKUP(venta_a_mes7[[#This Row],[CUIT]],Lista_CUIT[#All],2,0)),"CUIT NO CARGADO") -> - | L56: =SUM(venta_a_mes7[[#This Row],[IMPORTE NETO]:[EXENTO]]) -> 0
G57: =IFERROR(IF(venta_a_mes7[[#This Row],[CUIT]]="","-",VLOOKUP(venta_a_mes7[[#This Row],[CUIT]],Lista_CUIT[#All],2,0)),"CUIT NO CARGADO") -> - | L57: =SUM(venta_a_mes7[[#This Row],[IMPORTE NETO]:[EXENTO]]) -> 0
G58: =IFERROR(IF(venta_a_mes7[[#This Row],[CUIT]]="","-",VLOOKUP(venta_a_mes7[[#This Row],[CUIT]],Lista_CUIT[#All],2,0)),"CUIT NO CARGADO") -> - | L58: =SUM(venta_a_mes7[[#This Row],[IMPORTE NETO]:[EXENTO]]) -> 0
G59: =IFERROR(IF(venta_a_mes7[[#This Row],[CUIT]]="","-",VLOOKUP(venta_a_mes7[[#This Row],[CUIT]],Lista_CUIT[#All],2,0)),"CUIT NO CARGADO") -> - | L59: =SUM(venta_a_mes7[[#This Row],[IMPORTE NETO]:[EXENTO]]) -> 0
G60: =IFERROR(IF(venta_a_mes7[[#This Row],[CUIT]]="","-",VLOOKUP(venta_a_mes7[[#This Row],[CUIT]],Lista_CUIT[#All],2,0)),"CUIT NO CARGADO") -> - | L60: =SUM(venta_a_mes7[[#This Row],[IMPORTE NETO]:[EXENTO]]) -> 0
G61: =IFERROR(IF(venta_a_mes7[[#This Row],[CUIT]]="","-",VLOOKUP(venta_a_mes7[[#This Row],[CUIT]],Lista_CUIT[#All],2,0)),"CUIT NO CARGADO") -> - | L61: =SUM(venta_a_mes7[[#This Row],[IMPORTE NETO]:[EXENTO]]) -> 0
G62: =IFERROR(IF(venta_a_mes7[[#This Row],[CUIT]]="","-",VLOOKUP(venta_a_mes7[[#This Row],[CUIT]],Lista_CUIT[#All],2,0)),"CUIT NO CARGADO") -> - | L62: =SUM(venta_a_mes7[[#This Row],[IMPORTE NETO]:[EXENTO]]) -> 0
G63: =IFERROR(IF(venta_a_mes7[[#This Row],[CUIT]]="","-",VLOOKUP(venta_a_mes7[[#This Row],[CUIT]],Lista_CUIT[#All],2,0)),"CUIT NO CARGADO") -> - | L63: =SUM(venta_a_mes7[[#This Row],[IMPORTE NETO]:[EXENTO]]) -> 0
G64: =IFERROR(IF(venta_a_mes7[[#This Row],[CUIT]]="","-",VLOOKUP(venta_a_mes7[[#This Row],[CUIT]],Lista_CUIT[#All],2,0)),"CUIT NO CARGADO") -> - | L64: =SUM(venta_a_mes7[[#This Row],[IMPORTE NETO]:[EXENTO]]) -> 0
G65: =IFERROR(IF(venta_a_mes7[[#This Row],[CUIT]]="","-",VLOOKUP(venta_a_mes7[[#This Row],[CUIT]],Lista_CUIT[#All],2,0)),"CUIT NO CARGADO") -> - | L65: =SUM(venta_a_mes7[[#This Row],[IMPORTE NETO]:[EXENTO]]) -> 0
G66: =IFERROR(IF(venta_a_mes7[[#This Row],[CUIT]]="","-",VLOOKUP(venta_a_mes7[[#This Row],[CUIT]],Lista_CUIT[#All],2,0)),"CUIT NO CARGADO") -> - | L66: =SUM(venta_a_mes7[[#This Row],[IMPORTE NETO]:[EXENTO]]) -> 0
... G78: =IFERROR(IF(venta_a_mes7[[#This Row],[CUIT]]="","-",VLOOKUP(venta_a_mes7[[#This Row],[CUIT]],Lista_CUIT[#All],2,0)),"CUIT NO CARGADO") -> - | L78: =SUM(venta_a_mes7[[#This Row],[IMPORTE NETO]:[EXENTO]]) -> 0
G79: =IFERROR(IF(venta_a_mes7[[#This Row],[CUIT]]="","-",VLOOKUP(venta_a_mes7[[#This Row],[CUIT]],Lista_CUIT[#All],2,0)),"CUIT NO CARGADO") -> - | I79: =venta_a_mes7[[#This Row],[IMPORTE NETO]]*0.21 -> 0 | L79: =SUM(venta_a_mes7[[#This Row],[IMPORTE NETO]:[EXENTO]]) -> 0
B80: Total | H80: =SUBTOTAL(109,venta_a_mes7[IMPORTE NETO]) -> 0 | I80: =SUBTOTAL(109,venta_a_mes7[IVA 21%]) -> 0 | J80: =SUBTOTAL(109,venta_a_mes7[IVA 10,5%]) -> 0 | K80: =SUBTOTAL(109,venta_a_mes7[EXENTO]) -> 0 | L80: =SUBTOTAL(109,venta_a_mes7[TOTAL]) -> 0 | M80: =SUBTOTAL(103,venta_a_mes7[Provincia]) -> 0
B81: VENTAS "B"
