Workbook
Name partner_id: Configuracion!$B$332

Sheet Configuracion
F1: CUIT | G1: Cargar sin guiones
F2: RAZON SOCIAL | G2: Maximo 30 caracteres
A3: CUIT | B3: RAZON SOCIAL | C3: DETALLE | F3: DETALLE | G3: Cargar tipo de gasto
A4: 30628205090 | B4: ALBAMIE SA | C4: CLIENTE
A5: 30711678820 | B5: 2PSI INGENIERIA SRL | C5: PROVEEDOR
A6: 33716367539 | B6: 3PI S.A.S. | C6: PROVEEDOR
A7: 30660373108 | B7: ABC SA | C7: VARIOS
A8: 20300210881 | B8: ABOY DIEGO OSCAR | C8: PROVEEDOR
A9: 27229910782 | B9: ABUGAUCH MARIA DE LOS ANGELES | C9: PROVEEDOR
A10: 20242709897 | B10: ABUGAUCH VICTOR HUGO | C10: PROVEEDOR
A11: 20281669053 | B11: ACOSTA JAVIER GUSTAVO | C11: FLETE
A12: 20174240125 | B12: ACOSTA OSCAR ISIDRO | C12: VARIOS
A13: 30641659106 | B13: AGRISOL SA | C13: VARIOS
A14: 33709914109 | B14: ALAN COLLECTION SA | C14: VARIOS
A15: 20267161616 | B15: ALBAJARI DIEGO MARCOS | C15: VARIOS
... A155: 30537679855 | B155: ESTACION LIMA SA | C155: VARIOS
A156: 30-56864959-8 | B156: EXPRESO BISONTE SRL | C156: FLETE
A157: 30708542349 | B157: EXPRESO FORMOSA SRL | C157: FLETE
A158: 30526582884 | B158: EXPRESO MAR DEL PLATA SA | C158: FLETE
A159: 30577744579 | B159: EXPRESO TROLE SRL | C159: FLETE
A160: 30715949292 | B160: EYPAPEL SAS | C160: GASTOS VARIOS
A161: 30715980807 | B161: FABORT SRL | C161: PROVEEDOR
A162: 20359718765 | B162: FAIL ABRAHAM | C162: VARIOS
A163: 30643518364 | B163: FARMACIA DE MEDRANO SCS | C163: PROVEEDOR
A164: 30692138747 | B164: FARMACITY SA | C164: VARIOS
A165: 33712234429 | B165: FEDAGAS SA | C165: VARIOS
A166: 20353576012 | B166: FEDERICO PABLO FEOLA | C166: VARIOS
A167: 20343766441 | B167: FERNANDEZ MAURO | C167: TALLER
A168: 27062343449 | B168: FERREIRA LILIANA INES | C168: FLETE
... A530: 30606274161 | B530: EGESAC SA | C530: CLIENTE

Sheet Julio 
A1: ORTOPEDIA GEMINIS S.A. | J1: 45108
A4: LIBRO IVA COMPRAS
A6: FACTURAS A
A7: FECHA | B7: PTO VTA | C7: FAC A | D7: CUIT | E7: RAZON SOCIAL | F7: NETO | G7: IVA 21% | H7: IVA 27% | I7: IVA 10,5% | J7: P IVA | K7: IIBB CF | L7: IIBB BS | M7: NO GRAV | N7: OTROS | O7: TOTAL | P7: DETALLE
A8: 19/07/2023 | B8: 4 | C8: 1241 | D8: 20224819049 | E8: =VLOOKUP(D8,Configuracion!$A$4:$C$591,2,FALSE) -> ALFONSO BOAVENTURA | F8: 29008.27 | G8: =F8*21% -> 6091.7367 | O8: =SUM(F8:N8) -> 35100.007 | P8: =VLOOKUP(D8,Configuracion!$A$4:$C$591,3,FALSE) -> VARIOS
A9: 31/07/2023 | B9: 8 | C9: 1493 | D9: 30708973501 | E9: =VLOOKUP(D9,Configuracion!$A$4:$C$591,2,FALSE) -> ASIAL SRL | F9: 290825 | G9: =F9*21% -> 61073.25 | O9: =SUM(F9:N9) -> 351898.25 | P9: =VLOOKUP(D9,Configuracion!$A$4:$C$591,3,FALSE) -> INSUMOS
A10: 31/07/2023 | B10: 8 | C10: 1494 | D10: 30708973501 | E10: =VLOOKUP(D10,Configuracion!$A$4:$C$591,2,FALSE) -> ASIAL SRL | F10: 94600 | G10: =F10*21% -> 19866 | O10: =SUM(F10:N10) -> 114466 | P10: =VLOOKUP(D10,Configuracion!$A$4:$C$591,3,FALSE) -> INSUMOS
A11: 20/07/2023 | B11: 4 | C11: 411 | D11: 20379223185 | E11: =VLOOKUP(D11,Configuracion!$A$4:$C$591,2,FALSE) -> AYALA MAURICIO JUAN JOSE | F11: 74720 | G11: =F11*21% -> 15691.2 | O11: =SUM(F11:N11) -> 90411.2 | P11: =VLOOKUP(D11,Configuracion!$A$4:$C$591,3,FALSE) -> PROVEEDOR
A12: 19/07/2023 | B12: 11 | C12: 985 | D12: 20920321292 | E12: =VLOOKUP(D12,Configuracion!$A$4:$C$591,2,FALSE) -> BELLINI FILIPPINI ALBERTO | F12: 77008.35 | G12: =F12*21% -> 16171.754 | O12: =SUM(F12:N12) -> 93180.104 | P12: =VLOOKUP(D12,Configuracion!$A$4:$C$591,3,FALSE) -> VARIOS
A13: 18/07/2023 | B13: 4 | C13: 4062 | D13: 20129871947 | E13: =VLOOKUP(D13,Configuracion!$A$4:$C$591,2,FALSE) -> CARLOS RODOLFO FERNANDEZ | F13: 23310.01 | G13: =F13*21% -> 4895.1021 | O13: =SUM(F13:N13) -> 28205.112 | P13: =VLOOKUP(D13,Configuracion!$A$4:$C$591,3,FALSE) -> PROVEEDOR
A14: 17/07/2023 | B14: 27 | C14: 5383 | D14: 33712276539 | E14: =VLOOKUP(D14,Configuracion!$A$4:$C$591,2,FALSE) -> CASTAÑO AUTOVOX SRL | F14: 12929.87 | G14: =F14*21% -> 2715.2727 | K14: 452.55 | N14: 855.21 | O14: =SUM(F14:N14) -> 16952.903 | P14: =VLOOKUP(D14,Configuracion!$A$4:$C$591,3,FALSE) -> VARIOS
A15: 21/07/2023 | B15: 34 | C15: 46 | D15: 33712276539 | E15: =VLOOKUP(D15,Configuracion!$A$4:$C$591,2,FALSE) -> CASTAÑO AUTOVOX SRL | F15: 7836.04 | G15: =F15*21% -> 1645.5684 | K15: 274.26 | N15: 518.29 | O15: =SUM(F15:N15) -> 10274.158 | P15: =VLOOKUP(D15,Configuracion!$A$4:$C$591,3,FALSE) -> VARIOS
A16: 03/07/2023 | B16: 2 | C16: 188 | D16: 30605344352 | E16: =VLOOKUP(D16,Configuracion!$A$4:$C$591,2,FALSE) -> CONSORCIO BARTOLME MITRE 2466 | F16: 230000 | G16: =F16*21% -> 48300 | O16: =SUM(F16:N16) -> 278300 | P16: =VLOOKUP(D16,Configuracion!$A$4:$C$591,3,FALSE) -> CONSORCIO
A17: 45107 | B17: 20 | C17: 153063 | D17: 30696850972 | E17: =VLOOKUP(D17,Configuracion!$A$4:$C$591,2,FALSE) -> CPS COMUNICACIONES SA | F17: 4125.01 | H17: 1113.75 | K17: 144.37 | O17: =SUM(F17:N17) -> 5383.13 | P17: =VLOOKUP(D17,Configuracion!$A$4:$C$591,3,FALSE) -> SERVICIO
A18: 26/07/2023 | B18: 2016 | C18: 45392 | D18: 30516186670 | E18: =VLOOKUP(D18,Configuracion!$A$4:$C$591,2,FALSE) -> DEHEZA SAICFeI | F18: 14541.31 | G18: =F18*21% -> 3053.6751 | J18: 436.24 | K18: 543.89 | N18: =102.19+896.12 -> 998.31 | O18: =SUM(F18:N18) -> 19573.425 | P18: =VLOOKUP(D18,Configuracion!$A$4:$C$591,3,FALSE) -> VARIOS
A19: 06/07/2023 | B19: 2019 | C19: 144251 | D19: 30516186670 | E19: =VLOOKUP(D19,Configuracion!$A$4:$C$591,2,FALSE) -> DEHEZA SAICFeI | F19: 7341.38 | G19: =F19*21% -> 1541.6898 | J19: 220.24 | K19: 296.7 | N19: =1070.32+65.58 -> 1135.9 | O19: =SUM(F19:N19) -> 10535.91 | P19: =VLOOKUP(D19,Configuracion!$A$4:$C$591,3,FALSE) -> VARIOS
A20: 06/07/2023 | B20: 3 | C20: 7899 | D20: 20045615473 | E20: =VLOOKUP(D20,Configuracion!$A$4:$C$591,2,FALSE) -> DI FEO HUGO PASCUAL GUILLERMO | F20: 35930 | G20: =F20*21% -> 7545.3 | O20: =SUM(F20:N20) -> 43475.3 | P20: =VLOOKUP(D20,Configuracion!$A$4:$C$591,3,FALSE) -> INSUMOS
A21: 13/07/2023 | B21: 3 | C21: 7909 | D21: 20045615473 | E21: =VLOOKUP(D21,Configuracion!$A$4:$C$591,2,FALSE) -> DI FEO HUGO PASCUAL GUILLERMO | F21: 33340 | G21: =F21*21% -> 7001.4 | O21: =SUM(F21:N21) -> 40341.4 | P21: =VLOOKUP(D21,Configuracion!$A$4:$C$591,3,FALSE) -> INSUMOS
A22: 20/07/2023 | B22: 3 | C22: 7927 | D22: 20045615473 | E22: =VLOOKUP(D22,Configuracion!$A$4:$C$591,2,FALSE) -> DI FEO HUGO PASCUAL GUILLERMO | F22: 34710 | G22: =F22*21% -> 7289.1 | O22: =SUM(F22:N22) -> 41999.1 | P22: =VLOOKUP(D22,Configuracion!$A$4:$C$591,3,FALSE) -> INSUMOS
A23: 27/07/2023 | B23: 3 | C23: 7942 | D23: 20045615473 | E23: =VLOOKUP(D23,Configuracion!$A$4:$C$591,2,FALSE) -> DI FEO HUGO PASCUAL GUILLERMO | F23: 88020 | G23: =F23*21% -> 18484.2 | O23: =SUM(F23:N23) -> 106504.2 | P23: =VLOOKUP(D23,Configuracion!$A$4:$C$591,3,FALSE) -> INSUMOS
A24: 27/07/2023 | B24: 3 | C24: 7943 | D24: 20045615473 | E24: =VLOOKUP(D24,Configuracion!$A$4:$C$591,2,FALSE) -> DI FEO HUGO PASCUAL GUILLERMO | F24: 3680 | G24: =F24*21% -> 772.8 | O24: =SUM(F24:N24) -> 4452.8 | P24: =VLOOKUP(D24,Configuracion!$A$4:$C$591,3,FALSE) -> INSUMOS
A25: 05/07/2023 | B25: 7 | C25: 27447 | D25: 20271532483 | E25: =VLOOKUP(D25,Configuracion!$A$4:$C$591,2,FALSE) -> DIEGO MARTIN RIOS | F25: 1283367.4 | G25: =F25*21% -> 269507.15 | K25: 44917.86 | O25: =SUM(F25:N25) -> 1597792.4 | P25: =VLOOKUP(D25,Configuracion!$A$4:$C$591,3,FALSE) -> PROVEEDOR
A26: 05/07/2023 | B26: 7 | C26: 27449 | D26: 20271532483 | E26: =VLOOKUP(D26,Configuracion!$A$4:$C$591,2,FALSE) -> DIEGO MARTIN RIOS | F26: 2069487.7 | G26: =F26*21% -> 434592.42 | K26: 72432.07 | O26: =SUM(F26:N26) -> 2576512.2 | P26: =VLOOKUP(D26,Configuracion!$A$4:$C$591,3,FALSE) -> PROVEEDOR
A27: 10/07/2023 | B27: 7 | C27: 27491 | D27: 20271532483 | E27: =VLOOKUP(D27,Configuracion!$A$4:$C$591,2,FALSE) -> DIEGO MARTIN RIOS | F27: 2169893.8 | G27: =F27*21% -> 455677.7 | K27: 75946.28 | O27: =SUM(F27:N27) -> 2701517.8 | P27: =VLOOKUP(D27,Configuracion!$A$4:$C$591,3,FALSE) -> PROVEEDOR
A28: 10/07/2023 | B28: 7 | C28: 27501 | D28: 20271532483 | E28: =VLOOKUP(D28,Configuracion!$A$4:$C$591,2,FALSE) -> DIEGO MARTIN RIOS | F28: 1343840.6 | G28: =F28*21% -> 282206.52 | K28: 47034.42 | O28: =SUM(F28:N28) -> 1673081.5 | P28: =VLOOKUP(D28,Configuracion!$A$4:$C$591,3,FALSE) -> PROVEEDOR
A29: 14/07/2023 | B29: 7 | C29: 27571 | D29: 20271532483 | E29: =VLOOKUP(D29,Configuracion!$A$4:$C$591,2,FALSE) -> DIEGO MARTIN RIOS | F29: 892899.98 | G29: =F29*21% -> 187509 | K29: 31251.5 | O29: =SUM(F29:N29) -> 1111660.5 | P29: =VLOOKUP(D29,Configuracion!$A$4:$C$591,3,FALSE) -> PROVEEDOR
A30: 19/07/2023 | B30: 7 | C30: 925 | D30: 20271532483 | E30: =VLOOKUP(D30,Configuracion!$A$4:$C$591,2,FALSE) -> DIEGO MARTIN RIOS | F30: -764001.73 | G30: =F30*21% -> -160440.36 | K30: -26740.06 | O30: =SUM(F30:N30) -> -951182.15 | P30: =VLOOKUP(D30,Configuracion!$A$4:$C$591,3,FALSE) -> PROVEEDOR
A31: 21/07/2023 | B31: 18 | C31: 1090 | D31: 30711727236 | E31: =VLOOKUP(D31,Configuracion!$A$4:$C$591,2,FALSE) -> DULCE ESTILO SA | F31: 22092.27 | G31: =F31*21% -> 4639.3767 | O31: =SUM(F31:N31) -> 26731.647 | P31: =VLOOKUP(D31,Configuracion!$A$4:$C$591,3,FALSE) -> VARIOS
A32: 18/07/2023 | B32: 3 | C32: 47573 | D32: 30577744579 | E32: =VLOOKUP(D32,Configuracion!$A$4:$C$591,2,FALSE) -> EXPRESO TROLE SRL | F32: 10495.87 | G32: =F32*21% -> 2204.1327 | O32: =SUM(F32:N32) -> 12700.003 | P32: =VLOOKUP(D32,Configuracion!$A$4:$C$591,3,FALSE) -> FLETE
A33: 19/07/2023 | B33: 3 | C33: 784 | D33: 30715869663 | E33: =VLOOKUP(D33,Configuracion!$A$4:$C$591,2,FALSE) -> F & F COLOR SRL | F33: 24109.01 | G33: =F33*21% -> 5062.8921 | O33: =SUM(F33:N33) -> 29171.902 | P33: =VLOOKUP(D33,Configuracion!$A$4:$C$591,3,FALSE) -> VARIOS
A34: 06/07/2023 | B34: 3 | C34: 1180 | D34: 30715980807 | E34: =VLOOKUP(D34,Configuracion!$A$4:$C$591,2,FALSE) -> FABORT SRL | F34: 180800 | G34: =F34*21% -> 37968 | O34: =SUM(F34:N34) -> 218768 | P34: =VLOOKUP(D34,Configuracion!$A$4:$C$591,3,FALSE) -> PROVEEDOR
A35: 18/07/2023 | B35: 3648 | C35: 513 | D35: 30526874249 | E35: =VLOOKUP(D35,Configuracion!$A$4:$C$591,2,FALSE) -> FRAVEGA SACIEI | F35: 190081.82 | G35: =F35*21% -> 39917.182 | O35: =SUM(F35:N35) -> 229999 | P35: =VLOOKUP(D35,Configuracion!$A$4:$C$591,3,FALSE) -> VARIOS
A36: 04/07/2023 | B36: 5 | C36: 2807 | D36: 27119878468 | E36: =VLOOKUP(D36,Configuracion!$A$4:$C$591,2,FALSE) -> FREUND GABRIELA | F36: 126446.28 | G36: =F36*21% -> 26553.719 | O36: =SUM(F36:N36) -> 153000 | P36: =VLOOKUP(D36,Configuracion!$A$4:$C$591,3,FALSE) -> PROVEEDOR
A37: 25/07/2023 | B37: 7 | C37: 2026 | D37: 20284183534 | E37: =VLOOKUP(D37,Configuracion!$A$4:$C$591,2,FALSE) -> FURLANETTO MARTIN | F37: 2471.07 | G37: =F37*21% -> 518.9247 | O37: =SUM(F37:N37) -> 2989.9947 | P37: =VLOOKUP(D37,Configuracion!$A$4:$C$591,3,FALSE) -> VARIOS
A38: 14/07/2023 | B38: 2 | C38: 26557 | D38: 30714696153 | E38: =VLOOKUP(D38,Configuracion!$A$4:$C$591,2,FALSE) -> HOSPIMED SA | F38: 62155.1 | G38: =F38*21% -> 13052.571 | O38: =SUM(F38:N38) -> 75207.671 | P38: =VLOOKUP(D38,Configuracion!$A$4:$C$591,3,FALSE) -> PROVEEDOR
A39: 26/07/2023 | B39: 2 | C39: 26697 | D39: 30714696153 | E39: =VLOOKUP(D39,Configuracion!$A$4:$C$591,2,FALSE) -> HOSPIMED SA | F39: 20592 | G39: =F39*21% -> 4324.32 | O39: =SUM(F39:N39) -> 24916.32 | P39: =VLOOKUP(D39,Configuracion!$A$4:$C$591,3,FALSE) -> PROVEEDOR
A40: 31/07/2023 | B40: 5 | C40: 771 | D40: 20242126158 | E40: =VLOOKUP(D40,Configuracion!$A$4:$C$591,2,FALSE) -> IALLONARDO SERGIO | F40: 141483 | G40: =F40*21% -> 29711.43 | O40: =SUM(F40:N40) -> 171194.43 | P40: =VLOOKUP(D40,Configuracion!$A$4:$C$591,3,FALSE) -> PROVEEDOR
A41: 07/07/2023 | B41: 5 | C41: 1305 | D41: 30712187316 | E41: =VLOOKUP(D41,Configuracion!$A$4:$C$591,2,FALSE) -> ITALOMED PRODUCTOS SRL | F41: 84321.97 | G41: =F41*21% -> 17707.614 | O41: =SUM(F41:N41) -> 102029.58 | P41: =VLOOKUP(D41,Configuracion!$A$4:$C$591,3,FALSE) -> PROVEEDOR
A42: 07/07/2023 | B42: 5 | C42: 1306 | D42: 30712187316 | E42: =VLOOKUP(D42,Configuracion!$A$4:$C$591,2,FALSE) -> ITALOMED PRODUCTOS SRL | F42: 84321.97 | G42: =F42*21% -> 17707.614 | O42: =SUM(F42:N42) -> 102029.58 | P42: =VLOOKUP(D42,Configuracion!$A$4:$C$591,3,FALSE) -> PROVEEDOR
A43: 24/07/2023 | B43: 5 | C43: 1330 | D43: 30712187316 | E43: =VLOOKUP(D43,Configuracion!$A$4:$C$591,2,FALSE) -> ITALOMED PRODUCTOS SRL | F43: 86801.3 | G43: =F43*21% -> 18228.273 | O43: =SUM(F43:N43) -> 105029.57 | P43: =VLOOKUP(D43,Configuracion!$A$4:$C$591,3,FALSE) -> PROVEEDOR
A44: 45043 | B44: 7 | C44: 806 | D44: 30712187316 | E44: =VLOOKUP(D44,Configuracion!$A$4:$C$591,2,FALSE) -> ITALOMED PRODUCTOS SRL | F44: 42758.53 | G44: =F44*21% -> 8979.2913 | O44: =SUM(F44:N44) -> 51737.821 | P44: =VLOOKUP(D44,Configuracion!$A$4:$C$591,3,FALSE) -> PROVEEDOR
A45: 24/07/2023 | B45: 5 | C45: 1332 | D45: 30712187316 | E45: =VLOOKUP(D45,Configuracion!$A$4:$C$591,2,FALSE) -> ITALOMED PRODUCTOS SRL | F45: 92417.3 | G45: =F45*21% -> 19407.633 | O45: =SUM(F45:N45) -> 111824.93 | P45: =VLOOKUP(D45,Configuracion!$A$4:$C$591,3,FALSE) -> PROVEEDOR
A46: 06/07/2023 | B46: 7 | C46: 874 | D46: 30712187316 | E46: =VLOOKUP(D46,Configuracion!$A$4:$C$591,2,FALSE) -> ITALOMED PRODUCTOS SRL | F46: 53415.53 | G46: =F46*21% -> 11217.261 | O46: =SUM(F46:N46) -> 64632.791 | P46: =VLOOKUP(D46,Configuracion!$A$4:$C$591,3,FALSE) -> PROVEEDOR
A47: 07/07/2023 | B47: 7 | C47: 881 | D47: 30712187316 | E47: =VLOOKUP(D47,Configuracion!$A$4:$C$591,2,FALSE) -> ITALOMED PRODUCTOS SRL | F47: 95298.09 | G47: =F47*21% -> 20012.599 | O47: =SUM(F47:N47) -> 115310.69 | P47: =VLOOKUP(D47,Configuracion!$A$4:$C$591,3,FALSE) -> PROVEEDOR
A48: 11/07/2023 | B48: 7 | C48: 883 | D48: 30712187316 | E48: =VLOOKUP(D48,Configuracion!$A$4:$C$591,2,FALSE) -> ITALOMED PRODUCTOS SRL | F48: 56028.36 | G48: =F48*21% -> 11765.956 | O48: =SUM(F48:N48) -> 67794.316 | P48: =VLOOKUP(D48,Configuracion!$A$4:$C$591,3,FALSE) -> PROVEEDOR
A49: 12/07/2023 | B49: 7 | C49: 885 | D49: 30712187316 | E49: =VLOOKUP(D49,Configuracion!$A$4:$C$591,2,FALSE) -> ITALOMED PRODUCTOS SRL | F49: 56028.36 | G49: =F49*21% -> 11765.956 | O49: =SUM(F49:N49) -> 67794.316 | P49: =VLOOKUP(D49,Configuracion!$A$4:$C$591,3,FALSE) -> PROVEEDOR
A50: 13/07/2023 | B50: 7 | C50: 889 | D50: 30712187316 | E50: =VLOOKUP(D50,Configuracion!$A$4:$C$591,2,FALSE) -> ITALOMED PRODUCTOS SRL | F50: 56028.36 | G50: =F50*21% -> 11765.956 | O50: =SUM(F50:N50) -> 67794.316 | P50: =VLOOKUP(D50,Configuracion!$A$4:$C$591,3,FALSE) -> PROVEEDOR
A51: 21/07/2023 | B51: 7 | C51: 2 | D51: 30712187316 | E51: =VLOOKUP(D51,Configuracion!$A$4:$C$591,2,FALSE) -> ITALOMED PRODUCTOS SRL | F51: 8209 | G51: =F51*21% -> 1723.89 | O51: =SUM(F51:N51) -> 9932.89 | P51: =VLOOKUP(D51,Configuracion!$A$4:$C$591,3,FALSE) -> PROVEEDOR
A52: 12/07/2023 | B52: 4 | C52: 919 | D52: 30711645884 | E52: =VLOOKUP(D52,Configuracion!$A$4:$C$591,2,FALSE) -> LABORATORIOS SLR | F52: 43223.14 | G52: =F52*21% -> 9076.8594 | O52: =SUM(F52:N52) -> 52299.999 | P52: =VLOOKUP(D52,Configuracion!$A$4:$C$591,3,FALSE) -> VARIOS
A53: 24/07/2023 | B53: 10 | C53: 338 | D53: 30716229552 | E53: =VLOOKUP(D53,Configuracion!$A$4:$C$591,2,FALSE) -> LUBRICANTES RUTA DE P e H SRL | F53: 2462.81 | G53: =F53*21% -> 517.1901 | O53: =SUM(F53:N53) -> 2980.0001 | P53: =VLOOKUP(D53,Configuracion!$A$4:$C$591,3,FALSE) -> VARIOS
A54: 18/07/2023 | B54: 5 | C54: 18 | D54: 20929183143 | E54: =VLOOKUP(D54,Configuracion!$A$4:$C$591,2,FALSE) -> MA JUN | F54: 12000 | G54: =F54*21% -> 2520 | O54: =SUM(F54:N54) -> 14520 | P54: =VLOOKUP(D54,Configuracion!$A$4:$C$591,3,FALSE) -> VARIOS
A55: 18/07/2023 | B55: 3 | C55: 5871 | D55: 33708218699 | E55: =VLOOKUP(D55,Configuracion!$A$4:$C$591,2,FALSE) -> MANGGINI PABLO Y M ULISES SH | F55: 3500 | G55: =F55*21% -> 735 | O55: =SUM(F55:N55) -> 4235 | P55: =VLOOKUP(D55,Configuracion!$A$4:$C$591,3,FALSE) -> VARIOS
A56: 03/07/2023 | B56: 3 | C56: 84 | D56: 20334976433 | E56: =VLOOKUP(D56,Configuracion!$A$4:$C$591,2,FALSE) -> NARDOMARINO EZEQUIEL EDUARDO | F56: 128543.8 | G56: =F56*21% -> 26994.198 | O56: =SUM(F56:N56) -> 155538 | P56: =VLOOKUP(D56,Configuracion!$A$4:$C$591,3,FALSE) -> FLETE
... A59: 26/07/2023 | B59: 3 | C59: 88 | D59: 20334976433 | E59: =VLOOKUP(D59,Configuracion!$A$4:$C$591,2,FALSE) -> NARDOMARINO EZEQUIEL EDUARDO | F59: 106578.51 | G59: =F59*21% -> 22381.487 | O59: =SUM(F59:N59) -> 128960 | P59: =VLOOKUP(D59,Configuracion!$A$4:$C$591,3,FALSE) -> FLETE
A60: 21/07/2023 | B60: 5 | C60: 2821947 | D60: 30702652975 | E60: =VLOOKUP(D60,Configuracion!$A$4:$C$591,2,FALSE) -> NSS SA - IPLAN | F60: 8185.37 | G60: =F60*21% -> 1718.9277 | K60: 286.49 | O60: =SUM(F60:N60) -> 10190.788 | P60: =VLOOKUP(D60,Configuracion!$A$4:$C$591,3,FALSE) -> SERVICIO
A61: 21/07/2023 | B61: 1001 | C61: 15234 | D61: 30715393251 | E61: =VLOOKUP(D61,Configuracion!$A$4:$C$591,2,FALSE) -> OMNICHANNEL SA | F61: 8284.3 | G61: =F61*21% -> 1739.703 | O61: =SUM(F61:N61) -> 10024.003 | P61: =VLOOKUP(D61,Configuracion!$A$4:$C$591,3,FALSE) -> VARIOS
A62: 24/07/2023 | B62: 1001 | C62: 15285 | D62: 30715393251 | E62: =VLOOKUP(D62,Configuracion!$A$4:$C$591,2,FALSE) -> OMNICHANNEL SA | F62: 17023.14 | G62: =F62*21% -> 3574.8594 | O62: =SUM(F62:N62) -> 20597.999 | P62: =VLOOKUP(D62,Configuracion!$A$4:$C$591,3,FALSE) -> VARIOS
A63: 25/07/2023 | B63: 1001 | C63: 15410 | D63: 30715393251 | E63: =VLOOKUP(D63,Configuracion!$A$4:$C$591,2,FALSE) -> OMNICHANNEL SA | F63: 9999.17 | G63: =F63*21% -> 2099.8257 | O63: =SUM(F63:N63) -> 12098.996 | P63: =VLOOKUP(D63,Configuracion!$A$4:$C$591,3,FALSE) -> VARIOS
A64: 07/07/2023 | B64: 2 | C64: 8774 | D64: 30714331082 | E64: =VLOOKUP(D64,Configuracion!$A$4:$C$591,2,FALSE) -> ORTOPEDIA CASA ESCALADA SRL | F64: 406198.69 | G64: =F64*21% -> 85301.725 | O64: =SUM(F64:N64) -> 491500.41 | P64: =VLOOKUP(D64,Configuracion!$A$4:$C$591,3,FALSE) -> PROVEEDOR
A65: 14/07/2023 | B65: 2 | C65: 8818 | D65: 30714331082 | E65: =VLOOKUP(D65,Configuracion!$A$4:$C$591,2,FALSE) -> ORTOPEDIA CASA ESCALADA SRL | F65: 87848 | G65: =F65*21% -> 18448.08 | O65: =SUM(F65:N65) -> 106296.08 | P65: =VLOOKUP(D65,Configuracion!$A$4:$C$591,3,FALSE) -> PROVEEDOR
A66: 18/07/2023 | B66: 2 | C66: 8827 | D66: 30714331082 | E66: =VLOOKUP(D66,Configuracion!$A$4:$C$591,2,FALSE) -> ORTOPEDIA CASA ESCALADA SRL | F66: 140925.9 | G66: =F66*21% -> 29594.439 | O66: =SUM(F66:N66) -> 170520.34 | P66: =VLOOKUP(D66,Configuracion!$A$4:$C$591,3,FALSE) -> PROVEEDOR
A67: 19/07/2023 | B67: 2 | C67: 8837 | D67: 30714331082 | E67: =VLOOKUP(D67,Configuracion!$A$4:$C$591,2,FALSE) -> ORTOPEDIA CASA ESCALADA SRL | F67: 384292.95 | G67: =F67*21% -> 80701.519 | O67: =SUM(F67:N67) -> 464994.47 | P67: =VLOOKUP(D67,Configuracion!$A$4:$C$591,3,FALSE) -> PROVEEDOR
A68: 26/07/2023 | B68: 2 | C68: 8859 | D68: 30714331082 | E68: =VLOOKUP(D68,Configuracion!$A$4:$C$591,2,FALSE) -> ORTOPEDIA CASA ESCALADA SRL | F68: 301992.64 | G68: =F68*21% -> 63418.454 | O68: =SUM(F68:N68) -> 365411.09 | P68: =VLOOKUP(D68,Configuracion!$A$4:$C$591,3,FALSE) -> PROVEEDOR
A69: 12/07/2023 | B69: 4 | C69: 65113 | D69: 33709738459 | E69: =VLOOKUP(D69,Configuracion!$A$4:$C$591,2,FALSE) -> ORTOPEDICOS ALFOLATEX SA | F69: 123774.94 | G69: =F69*21% -> 25992.737 | O69: =SUM(F69:N69) -> 149767.68 | P69: =VLOOKUP(D69,Configuracion!$A$4:$C$591,3,FALSE) -> PROVEEDOR
A70: 19/07/2023 | B70: 4 | C70: 65240 | D70: 33709738459 | E70: =VLOOKUP(D70,Configuracion!$A$4:$C$591,2,FALSE) -> ORTOPEDICOS ALFOLATEX SA | F70: 170802.85 | G70: =F70*21% -> 35868.599 | O70: =SUM(F70:N70) -> 206671.45 | P70: =VLOOKUP(D70,Configuracion!$A$4:$C$591,3,FALSE) -> PROVEEDOR
A71: 31/07/2023 | B71: 120 | C71: 3043 | D71: 30587197215 | E71: =VLOOKUP(D71,Configuracion!$A$4:$C$591,2,FALSE) -> PANATEL SOCIEDAD ANONIMA | F71: 16528.93 | G71: =F71*21% -> 3471.0753 | O71: =SUM(F71:N71) -> 20000.005 | P71: =VLOOKUP(D71,Configuracion!$A$4:$C$591,3,FALSE) -> VARIOS
A72: 06/07/2023 | B72: 12 | C72: 1625536 | D72: 30709776564 | E72: =VLOOKUP(D72,Configuracion!$A$4:$C$591,2,FALSE) -> PROSEGUR ACTIVA ARG SA | F72: 21032.5 | G72: =F72*21% -> 4416.825 | K72: 736.14 | O72: =SUM(F72:N72) -> 26185.465 | P72: =VLOOKUP(D72,Configuracion!$A$4:$C$591,3,FALSE) -> SEGUROS
A73: 05/07/2023 | B73: 1001 | C73: 263 | D73: 30707370552 | E73: =VLOOKUP(D73,Configuracion!$A$4:$C$591,2,FALSE) -> RAKE SA | F73: 82231.4 | G73: =F73*21% -> 17268.594 | O73: =SUM(F73:N73) -> 99499.994 | P73: =VLOOKUP(D73,Configuracion!$A$4:$C$591,3,FALSE) -> PROVEEDOR
A74: 05/07/2023 | B74: 1001 | C74: 264 | D74: 30707370552 | E74: =VLOOKUP(D74,Configuracion!$A$4:$C$591,2,FALSE) -> RAKE SA | F74: 114876.03 | G74: =F74*21% -> 24123.966 | O74: =SUM(F74:N74) -> 139000 | P74: =VLOOKUP(D74,Configuracion!$A$4:$C$591,3,FALSE) -> PROVEEDOR
A75: 05/07/2023 | B75: 1001 | C75: 265 | D75: 30707370552 | E75: =VLOOKUP(D75,Configuracion!$A$4:$C$591,2,FALSE) -> RAKE SA | F75: 262330.58 | G75: =F75*21% -> 55089.422 | O75: =SUM(F75:N75) -> 317420 | P75: =VLOOKUP(D75,Configuracion!$A$4:$C$591,3,FALSE) -> PROVEEDOR
A76: 05/07/2023 | B76: 7 | C76: 15878 | D76: 30709214078 | E76: =VLOOKUP(D76,Configuracion!$A$4:$C$591,2,FALSE) -> REHAVITA SA | F76: 1228948 | G76: 237770.19 | I76: 10154.45 | O76: =SUM(F76:N76) -> 1476872.6 | P76: =VLOOKUP(D76,Configuracion!$A$4:$C$591,3,FALSE) -> PROVEEDOR
A77: 07/07/2023 | B77: 7 | C77: 15944 | D77: 30709214078 | E77: =VLOOKUP(D77,Configuracion!$A$4:$C$591,2,FALSE) -> REHAVITA SA | F77: 106144 | I77: 11145.12 | O77: =SUM(F77:N77) -> 117289.12 | P77: =VLOOKUP(D77,Configuracion!$A$4:$C$591,3,FALSE) -> PROVEEDOR
A78: 11/07/2023 | B78: 7 | C78: 1072 | D78: 30709214078 | E78: =VLOOKUP(D78,Configuracion!$A$4:$C$591,2,FALSE) -> REHAVITA SA | F78: -106144 | I78: -11145.12 | O78: =SUM(F78:N78) -> -117289.12 | P78: =VLOOKUP(D78,Configuracion!$A$4:$C$591,3,FALSE) -> PROVEEDOR
A79: 14/07/2023 | B79: 7 | C79: 15999 | D79: 30709214078 | E79: =VLOOKUP(D79,Configuracion!$A$4:$C$591,2,FALSE) -> REHAVITA SA | F79: 808392.46 | G79: =F79*21% -> 169762.42 | O79: =SUM(F79:N79) -> 978154.88 | P79: =VLOOKUP(D79,Configuracion!$A$4:$C$591,3,FALSE) -> PROVEEDOR
A80: 14/07/2023 | B80: 7 | C80: 16000 | D80: 30709214078 | E80: =VLOOKUP(D80,Configuracion!$A$4:$C$591,2,FALSE) -> REHAVITA SA | F80: 1515333.5 | G80: =F80*21% -> 318220.03 | O80: =SUM(F80:N80) -> 1833553.5 | P80: =VLOOKUP(D80,Configuracion!$A$4:$C$591,3,FALSE) -> PROVEEDOR
A81: 12/07/2023 | B81: 17 | C81: 1137 | D81: 30711764921 | E81: =VLOOKUP(D81,Configuracion!$A$4:$C$591,2,FALSE) -> RELIEF CENTER SRL | F81: 26481 | G81: =F81*21% -> 5561.01 | O81: =SUM(F81:N81) -> 32042.01 | P81: =VLOOKUP(D81,Configuracion!$A$4:$C$591,3,FALSE) -> PROVEEDOR
A82: 22/06/2023 | B82: 1 | C82: 622 | D82: 30715048066 | E82: =VLOOKUP(D82,Configuracion!$A$4:$C$591,2,FALSE) -> ROLLS Y EMPANADAS SA | F82: 288240 | G82: =F82*21% -> 60530.4 | O82: =SUM(F82:N82) -> 348770.4 | P82: =VLOOKUP(D82,Configuracion!$A$4:$C$591,3,FALSE) -> VARIOS
A83: 14/07/2023 | B83: 6 | C83: 75063 | D83: 30711553564 | E83: =VLOOKUP(D83,Configuracion!$A$4:$C$591,2,FALSE) -> SALUDTEX SA | F83: 260716 | G83: =F83*21% -> 54750.36 | O83: =SUM(F83:N83) -> 315466.36 | P83: =VLOOKUP(D83,Configuracion!$A$4:$C$591,3,FALSE) -> PROVEEDOR
A84: 12/07/2023 | B84: 5 | C84: 2878 | D84: 33693506099 | E84: =VLOOKUP(D84,Configuracion!$A$4:$C$591,2,FALSE) -> SCALISE A. FALANGA C SH | F84: 1680.03 | I84: 176.4 | O84: =SUM(F84:N84) -> 1856.43 | P84: =VLOOKUP(D84,Configuracion!$A$4:$C$591,3,FALSE) -> VARIOS
A85: 11/07/2023 | B85: 5 | C85: 145403 | D85: 30598960093 | E85: =VLOOKUP(D85,Configuracion!$A$4:$C$591,2,FALSE) -> SILVESTRIN FABRIS SRL | F85: 641866.2 | G85: =F85*21% -> 134791.9 | K85: 22465.32 | O85: =SUM(F85:N85) -> 799123.42 | P85: =VLOOKUP(D85,Configuracion!$A$4:$C$591,3,FALSE) -> PROVEEDOR
A86: 17/07/2023 | B86: 5 | C86: 145686 | D86: 30598960093 | E86: =VLOOKUP(D86,Configuracion!$A$4:$C$591,2,FALSE) -> SILVESTRIN FABRIS SRL | F86: 192725.1 | G86: =F86*21% -> 40472.271 | K86: 6745.38 | O86: =SUM(F86:N86) -> 239942.75 | P86: =VLOOKUP(D86,Configuracion!$A$4:$C$591,3,FALSE) -> PROVEEDOR
A87: 21/07/2023 | B87: 5 | C87: 145889 | D87: 30598960093 | E87: =VLOOKUP(D87,Configuracion!$A$4:$C$591,2,FALSE) -> SILVESTRIN FABRIS SRL | F87: 153941.8 | G87: =F87*21% -> 32327.778 | K87: 5387.96 | O87: =SUM(F87:N87) -> 191657.54 | P87: =VLOOKUP(D87,Configuracion!$A$4:$C$591,3,FALSE) -> PROVEEDOR
A88: 06/07/2023 | B88: 6 | C88: 49061 | D88: 30710177658 | E88: =VLOOKUP(D88,Configuracion!$A$4:$C$591,2,FALSE) -> TARGET MEDICAL SA | F88: 171247.68 | G88: =F88*21% -> 35962.013 | O88: =SUM(F88:N88) -> 207209.69 | P88: =VLOOKUP(D88,Configuracion!$A$4:$C$591,3,FALSE) -> PROVEEDOR
A89: 12/07/2023 | B89: 6 | C89: 49128 | D89: 30710177658 | E89: =VLOOKUP(D89,Configuracion!$A$4:$C$591,2,FALSE) -> TARGET MEDICAL SA | F89: 115274.8 | G89: =F89*21% -> 24207.708 | O89: =SUM(F89:N89) -> 139482.51 | P89: =VLOOKUP(D89,Configuracion!$A$4:$C$591,3,FALSE) -> PROVEEDOR
A90: 13/07/2023 | B90: 6 | C90: 49150 | D90: 30710177658 | E90: =VLOOKUP(D90,Configuracion!$A$4:$C$591,2,FALSE) -> TARGET MEDICAL SA | F90: 22580 | G90: =F90*21% -> 4741.8 | O90: =SUM(F90:N90) -> 27321.8 | P90: =VLOOKUP(D90,Configuracion!$A$4:$C$591,3,FALSE) -> PROVEEDOR
A91: 17/07/2023 | B91: 6 | C91: 49191 | D91: 30710177658 | E91: =VLOOKUP(D91,Configuracion!$A$4:$C$591,2,FALSE) -> TARGET MEDICAL SA | F91: 111800 | G91: =F91*21% -> 23478 | O91: =SUM(F91:N91) -> 135278 | P91: =VLOOKUP(D91,Configuracion!$A$4:$C$591,3,FALSE) -> PROVEEDOR
A92: 09/07/2023 | B92: 948 | C92: 1010874 | D92: 30639453975 | E92: =VLOOKUP(D92,Configuracion!$A$4:$C$591,2,FALSE) -> TELEFONICA ARG SA | F92: 13098 | H92: 3536.46 | J92: 392.94 | K92: 458.43 | O92: =SUM(F92:N92) -> 17485.83 | P92: =VLOOKUP(D92,Configuracion!$A$4:$C$591,3,FALSE) -> SERVICIO
A93: 24/07/2023 | B93: 6 | C93: 653 | D93: 20247225243 | E93: =VLOOKUP(D93,Configuracion!$A$4:$C$591,2,FALSE) -> VENTO HUGO GABRIEL | F93: 10409 | G93: =F93*21% -> 2185.89 | O93: =SUM(F93:N93) -> 12594.89 | P93: =VLOOKUP(D93,Configuracion!$A$4:$C$591,3,FALSE) -> PROVEEDOR
A94: 04/07/2023 | B94: 4 | C94: 50 | D94: 20317488476 | E94: =VLOOKUP(D94,Configuracion!$A$4:$C$591,2,FALSE) -> VILLALBA MIGUEL ANGEL | F94: 256856 | G94: =F94*21% -> 53939.76 | O94: =SUM(F94:N94) -> 310795.76 | P94: =VLOOKUP(D94,Configuracion!$A$4:$C$591,3,FALSE) -> PROVEEDOR
A95: 17/07/2023 | B95: 4 | C95: 54 | D95: 20317488476 | E95: =VLOOKUP(D95,Configuracion!$A$4:$C$591,2,FALSE) -> VILLALBA MIGUEL ANGEL | F95: 228864 | G95: =F95*21% -> 48061.44 | O95: =SUM(F95:N95) -> 276925.44 | P95: =VLOOKUP(D95,Configuracion!$A$4:$C$591,3,FALSE) -> PROVEEDOR
E96: =VLOOKUP(D96,Configuracion!$A$4:$C$591,2,FALSE) -> #N/A | G96: =F96*21% -> 0 | O96: =SUM(F96:N96) -> 0 | P96: =VLOOKUP(D96,Configuracion!$A$4:$C$591,3,FALSE) -> #N/A
E97: =VLOOKUP(D97,Configuracion!$A$4:$C$591,2,FALSE) -> #N/A | G97: =F97*21% -> 0 | O97: =SUM(F97:N97) -> 0 | P97: =VLOOKUP(D97,Configuracion!$A$4:$C$591,3,FALSE) -> #N/A
E98: =VLOOKUP(D98,Configuracion!$A$4:$C$591,2,FALSE) -> #N/A | G98: =F98*21% -> 0 | O98: =SUM(F98:N98) -> 0 | P98: =VLOOKUP(D98,Configuracion!$A$4:$C$591,3,FALSE) -> #N/A
E99: =VLOOKUP(D99,Configuracion!$A$4:$C$591,2,FALSE) -> #N/A | G99: =F99*21% -> 0 | O99: =SUM(F99:N99) -> 0 | P99: =VLOOKUP(D99,Configuracion!$A$4:$C$591,3,FALSE) -> #N/A
E100: =VLOOKUP(D100,Configuracion!$A$4:$C$591,2,FALSE) -> #N/A | G100: =F100*21% -> 0 | O100: =SUM(F100:N100) -> 0 | P100: =VLOOKUP(D100,Configuracion!$A$4:$C$591,3,FALSE) -> #N/A
E101: =VLOOKUP(D101,Configuracion!$A$4:$C$591,2,FALSE) -> #N/A | G101: =F101*21% -> 0 | O101: =SUM(F101:N101) -> 0 | P101: =VLOOKUP(D101,Configuracion!$A$4:$C$591,3,FALSE) -> #N/A
E102: =VLOOKUP(D102,Configuracion!$A$4:$C$591,2,FALSE) -> #N/A | G102: =F102*21% -> 0 | O102: =SUM(F102:N102) -> 0 | P102: =VLOOKUP(D102,Configuracion!$A$4:$C$591,3,FALSE) -> #N/A
E103: =VLOOKUP(D103,Configuracion!$A$4:$C$591,2,FALSE) -> #N/A | G103: =F103*21% -> 0 | O103: =SUM(F103:N103) -> 0 | P103: =VLOOKUP(D103,Configuracion!$A$4:$C$591,3,FALSE) -> #N/A
E104: =VLOOKUP(D104,Configuracion!$A$4:$C$591,2,FALSE) -> #N/A | G104: =F104*21% -> 0 | O104: =SUM(F104:N104) -> 0 | P104: =VLOOKUP(D104,Configuracion!$A$4:$C$591,3,FALSE) -> #N/A
E105: =VLOOKUP(D105,Configuracion!$A$4:$C$591,2,FALSE) -> #N/A | G105: =F105*21% -> 0 | O105: =SUM(F105:N105) -> 0 | P105: =VLOOKUP(D105,Configuracion!$A$4:$C$591,3,FALSE) -> #N/A
...

Sheet Calculo IVA
B1: ORTOPEDIA GEMINIS
A2: Calculo Iva | D2: 45108
B4: VENTAS
B5: Neto | C5: Iva | D5: Total
A6: FAC. "A" | B6: =+'Julio '!F202 -> 0 | C6: =(B6*0.21) -> 0 | D6: =(B6+C6) -> 0
A7: FAC. "B" | B7: =+'Julio '!F212 -> 0 | C7: =(B7*0.21) -> 0 | D7: =(B7+C7) -> 0
A8: FAC. "A" - Odoo | B8: =+'Julio '!B221+'Julio '!B223+'Julio '!B224+'Julio '!B222 -> 48946882 | C8: =+B8*0.21 -> 10278845 | D8: =(B8+C8) -> 59225727
A9: FAC. "B" - Odoo | B9: =+'Julio '!B225+'Julio '!B226 -> 3568047.7 | C9: =+B9*0.21 -> 749290.01 | D9: =(B9+C9) -> 4317337.7
B10: =SUM(B6:B9) -> 52514930 | C10: =SUM(C6:C9) -> 11028135 | D10: =SUM(D6:D9) -> 63543065
B13: COMPRAS
B14: Neto | C14: Iva | D14: Total
B15: =+'Julio '!F116 -> 18282027 | C15: =+'Julio '!G116+'Julio '!H116+'Julio '!I116 -> 3829928.2 | D15: =(B15+C15) -> 22111955
B17: =SUM(B15:B16) -> 18282027 | C17: =SUM(C15:C16) -> 3829928.2 | D17: =SUM(D15:D16) -> 22111955
A20: RETENCIONES | B20: N° Cuit | C20: Importe | D20: Nro. Retencion | E20: Fecha
A21: AFIP - No están informadas las retenciones de IVA en el sistema de AFIP
C36: =+'Julio '!G189 -> 884.57
A38: PERCEPCIONES | B38: N° Cuit | C38: Importe | D38: Nro. Retencion | E38: Fecha
C42: =SUM(C39:C41) -> 0
A44: Total Deducciociones | C44: =+C42+C36 -> 884.57
C47: (Montos en Positivo)
A48: 1er Saldo Tecnico del Período | C48: =+C10-C17 -> 7198207.1
A50: Saldo Tecnico de período Anterior (a favor) | D50: (resta en el total)
A52: Saldo Neto Técnico | C52: =+C48-C50 -> 7198207.1
A56: Saldo L.D. del Período | C56: =+C42+C36 -> 884.57
A58: Saldo L.D. del Período Anterior
A60: Neto S.L.D | C60: =+C56+C58 -> 884.57
A63: I V A | C63: =+C52-C60 -> 7197322.5
A64: NOTA: Sin Tomar posibles Retenciones que se hayan hecho

Sheet Ventas Odoo 07 2023
A1: Ventas Libro de IVA 01/07/2023 - 31/07/2023
A2: Ortopedia Geminis S.A.
A4: Fecha | B4: Comprobante | C4: Nombre | D4: Cond. IVA | E4: CUIT o Doc. | F4: Gravado | G4: No Gravado | H4: IVA 2,5% | I4: IVA 5% | J4: IVA 10.5% | K4: IVA 21% | L4: IVA 27% | M4: Otros Imp | N4: Total Compr.
A5: 03/07/2023 | B5: FA-B 0005-00008258 | C5: .CONSUMIDOR FINAL | D5: Consumidor Final | F5: 12066.12 | G5: 0 | H5: 0 | I5: 0 | J5: 0 | K5: 2533.88 | L5: 0 | M5: 0 | N5: 14600
A6: 03/07/2023 | B6: FA-B 0005-00008259 | C6: .CONSUMIDOR FINAL | D6: Consumidor Final | F6: 6776.86 | G6: 0 | H6: 0 | I6: 0 | J6: 0 | K6: 1423.14 | L6: 0 | M6: 0 | N6: 8200
A7: 03/07/2023 | B7: FA-B 0005-00008260 | C7: .CONSUMIDOR FINAL | D7: Consumidor Final | F7: 13388.43 | G7: 0 | H7: 0 | I7: 0 | J7: 0 | K7: 2811.57 | L7: 0 | M7: 0 | N7: 16200
A8: 03/07/2023 | B8: FA-B 0005-00008261 | C8: .CONSUMIDOR FINAL | D8: Consumidor Final | F8: 3966.94 | G8: 0 | H8: 0 | I8: 0 | J8: 0 | K8: 833.06 | L8: 0 | M8: 0 | N8: 4800
A9: 03/07/2023 | B9: FA-B 0005-00008262 | C9: .CONSUMIDOR FINAL | D9: Consumidor Final | F9: 7024.79 | G9: 0 | H9: 0 | I9: 0 | J9: 0 | K9: 1475.21 | L9: 0 | M9: 0 | N9: 8500
A10: 03/07/2023 | B10: FA-B 0005-00008263 | C10: .CONSUMIDOR FINAL | D10: Consumidor Final | F10: 2727.27 | G10: 0 | H10: 0 | I10: 0 | J10: 0 | K10: 572.73 | L10: 0 | M10: 0 | N10: 3300
A11: 03/07/2023 | B11: FA-B 0005-00008264 | C11: .CONSUMIDOR FINAL | D11: Consumidor Final | F11: 7024.79 | G11: 0 | H11: 0 | I11: 0 | J11: 0 | K11: 1475.21 | L11: 0 | M11: 0 | N11: 8500
A12: 03/07/2023 | B12: FA-B 0005-00008265 | C12: .CONSUMIDOR FINAL | D12: Consumidor Final | F12: 4462.81 | G12: 0 | H12: 0 | I12: 0 | J12: 0 | K12: 937.19 | L12: 0 | M12: 0 | N12: 5400
A13: 03/07/2023 | B13: FA-B 0005-00008266 | C13: .CONSUMIDOR FINAL | D13: Consumidor Final | F13: 3347.11 | G13: 0 | H13: 0 | I13: 0 | J13: 0 | K13: 702.89 | L13: 0 | M13: 0 | N13: 4050
A14: 03/07/2023 | B14: FA-A 0006-00000363 | C14: Galeno Argentina Sociedad Anonima | D14: IVA Responsable Inscripto | E14: 30522428163 | F14: 4682644.6 | G14: 0 | H14: 0 | I14: 0 | J14: 0 | K14: 983355.36 | L14: 0 | M14: 0 | N14: 5666000
A15: 03/07/2023 | B15: NC-A 0007-00000095 | C15: Alexander Fleming S A | D15: IVA Responsable Inscripto | E15: 30645337979 | F15: -12167.57 | G15: 0 | H15: 0 | I15: 0 | J15: 0 | K15: -2555.19 | L15: 0 | M15: 0 | N15: -14722.76
A16: 03/07/2023 | B16: FA-A 0007-00001499 | C16: Hc Homecare Internacion Domiciliaria S.A. | D16: IVA Responsable Inscripto | E16: 30710538014 | F16: 18800 | G16: 0 | H16: 0 | I16: 0 | J16: 0 | K16: 3948 | L16: 0 | M16: 0 | N16: 22748
A17: 03/07/2023 | B17: FA-A 0007-00001500 | C17: Amparo Salud S.R.L. | D17: IVA Responsable Inscripto | E17: 30715186655 | F17: 73448.76 | G17: 0 | H17: 0 | I17: 0 | J17: 0 | K17: 15424.24 | L17: 0 | M17: 0 | N17: 88873
A18: 03/07/2023 | B18: FA-A 0007-00001501 | C18: Zc Diabetes Srl | D18: IVA Responsable Inscripto | E18: 30710961790 | F18: 43133.88 | G18: 0 | H18: 0 | I18: 0 | J18: 0 | K18: 9058.11 | L18: 0 | M18: 0 | N18: 52191.99
A19: 03/07/2023 | B19: FA-A 0007-00001502 | C19: Login Door S.A | D19: IVA Responsable Inscripto | E19: 30711244383 | F19: 6375.37 | G19: 0 | H19: 0 | I19: 0 | J19: 0 | K19: 1338.83 | L19: 0 | M19: 0 | N19: 7714.2
A20: 03/07/2023 | B20: FA-A 0007-00001503 | C20: Alexander Fleming S A | D20: IVA Responsable Inscripto | E20: 30645337979 | F20: 12167.57 | G20: 0 | H20: 0 | I20: 0 | J20: 0 | K20: 2555.19 | L20: 0 | M20: 0 | N20: 14722.76
A21: 03/07/2023 | B21: FA-A 0007-00001504 | C21: Alexander Fleming S A | D21: IVA Responsable Inscripto | E21: 30645337979 | F21: 12167.57 | G21: 0 | H21: 0 | I21: 0 | J21: 0 | K21: 2555.19 | L21: 0 | M21: 0 | N21: 14722.76
A22: 03/07/2023 | B22: FA-A 0007-00001505 | C22: Medicus Sociedad Anonima De Asistencia Medica Y Cientifica | D22: IVA Responsable Inscripto | E22: 30546771314 | F22: 10880.99 | G22: 0 | H22: 0 | I22: 0 | J22: 0 | K22: 2285.01 | L22: 0 | M22: 0 | N22: 13166
A23: 03/07/2023 | B23: FA-A 0007-00001506 | C23: Medincare Argentina S.A. | D23: IVA Responsable Inscripto | E23: 30713669004 | F23: 9404.96 | G23: 0 | H23: 0 | I23: 0 | J23: 0 | K23: 1975.04 | L23: 0 | M23: 0 | N23: 11380
A24: 03/07/2023 | B24: FA-A 0007-00001507 | C24: Centro Medico Amenabar Srl | D24: IVA Responsable Inscripto | E24: 30707612971 | F24: 15487.6 | G24: 0 | H24: 0 | I24: 0 | J24: 0 | K24: 3252.4 | L24: 0 | M24: 0 | N24: 18740
A25: 03/07/2023 | B25: FA-A 0007-00001508 | C25: Fundacion Empresaria Maderera | D25: IVA Responsable Inscripto | E25: 30657418877 | F25: 3325.53 | G25: 0 | H25: 0 | I25: 0 | J25: 0 | K25: 698.36 | L25: 0 | M25: 0 | N25: 4023.89
... A27: 03/07/2023 | B27: FA-B 0007-00004469 | C27: Obra Social De Los Trabajadores De La Industria Del Gas | D27: IVA Sujeto Exento | E27: 30658137642 | F27: 55438.84 | G27: 0 | H27: 0 | I27: 0 | J27: 0 | K27: 11642.16 | L27: 0 | M27: 0 | N27: 67081
A28: 04/07/2023 | B28: FA-B 0005-00008267 | C28: .CONSUMIDOR FINAL | D28: Consumidor Final | F28: 3636.36 | G28: 0 | H28: 0 | I28: 0 | J28: 0 | K28: 763.64 | L28: 0 | M28: 0 | N28: 4400
A29: 04/07/2023 | B29: FA-B 0005-00008268 | C29: .CONSUMIDOR FINAL | D29: Consumidor Final | F29: 3305.79 | G29: 0 | H29: 0 | I29: 0 | J29: 0 | K29: 694.21 | L29: 0 | M29: 0 | N29: 4000
A30: 04/07/2023 | B30: FA-B 0005-00008269 | C30: .CONSUMIDOR FINAL | D30: Consumidor Final | F30: 3388.43 | G30: 0 | H30: 0 | I30: 0 | J30: 0 | K30: 711.57 | L30: 0 | M30: 0 | N30: 4100
A31: 04/07/2023 | B31: FA-B 0005-00008270 | C31: .CONSUMIDOR FINAL | D31: Consumidor Final | F31: 12066.12 | G31: 0 | H31: 0 | I31: 0 | J31: 0 | K31: 2533.88 | L31: 0 | M31: 0 | N31: 14600
A32: 04/07/2023 | B32: FA-B 0005-00008271 | C32: .CONSUMIDOR FINAL | D32: Consumidor Final | F32: 2644.63 | G32: 0 | H32: 0 | I32: 0 | J32: 0 | K32: 555.37 | L32: 0 | M32: 0 | N32: 3200
A33: 04/07/2023 | B33: FA-B 0005-00008272 | C33: .CONSUMIDOR FINAL | D33: Consumidor Final | F33: 11570.25 | G33: 0 | H33: 0 | I33: 0 | J33: 0 | K33: 2429.75 | L33: 0 | M33: 0 | N33: 14000
A34: 04/07/2023 | B34: FA-B 0005-00008273 | C34: .CONSUMIDOR FINAL | D34: Consumidor Final | F34: 5785.12 | G34: 0 | H34: 0 | I34: 0 | J34: 0 | K34: 1214.88 | L34: 0 | M34: 0 | N34: 7000
A35: 04/07/2023 | B35: FA-B 0005-00008274 | C35: .CONSUMIDOR FINAL | D35: Consumidor Final | F35: 2809.92 | G35: 0 | H35: 0 | I35: 0 | J35: 0 | K35: 590.08 | L35: 0 | M35: 0 | N35: 3400
A36: 04/07/2023 | B36: FA-B 0005-00008275 | C36: .CONSUMIDOR FINAL | D36: Consumidor Final | F36: 9090.91 | G36: 0 | H36: 0 | I36: 0 | J36: 0 | K36: 1909.09 | L36: 0 | M36: 0 | N36: 11000
A37: 04/07/2023 | B37: FA-B 0005-00008276 | C37: .CONSUMIDOR FINAL | D37: Consumidor Final | F37: 2727.27 | G37: 0 | H37: 0 | I37: 0 | J37: 0 | K37: 572.73 | L37: 0 | M37: 0 | N37: 3300
A38: 04/07/2023 | B38: FA-A 0006-00000364 | C38: Galeno Argentina Sociedad Anonima | D38: IVA Responsable Inscripto | E38: 30522428163 | F38: 19008264 | G38: 0 | H38: 0 | I38: 0 | J38: 0 | K38: 3991735.5 | L38: 0 | M38: 0 | N38: 23000000
A39: 04/07/2023 | B39: FA-A 0006-00000365 | C39: Galeno Argentina Sociedad Anonima | D39: IVA Responsable Inscripto | E39: 30522428163 | F39: 5227520.7 | G39: 0 | H39: 0 | I39: 0 | J39: 0 | K39: 1097779.3 | L39: 0 | M39: 0 | N39: 6325300
A40: 04/07/2023 | B40: NC-A 0007-00000096 | C40: Galeno Argentina Sociedad Anonima | D40: IVA Responsable Inscripto | E40: 30522428163 | F40: -4682644.6 | G40: 0 | H40: 0 | I40: 0 | J40: 0 | K40: -983355.36 | L40: 0 | M40: 0 | N40: -5666000
A41: 04/07/2023 | B41: FA-A 0007-00001510 | C41: Obra Social Del Personal De Las Telecomunicaciones De La Republica Argentina | D41: IVA Responsable Inscripto | E41: 30608716390 | F41: 14545.46 | G41: 0 | H41: 0 | I41: 0 | J41: 0 | K41: 3054.55 | L41: 0 | M41: 0 | N41: 17600.01
A42: 04/07/2023 | B42: FA-A 0007-00001511 | C42: Obra Social Del Personal De Las Telecomunicaciones De La Republica Argentina | D42: IVA Responsable Inscripto | E42: 30608716390 | F42: 16727.26 | G42: 0 | H42: 0 | I42: 0 | J42: 0 | K42: 3512.72 | L42: 0 | M42: 0 | N42: 20239.98
A43: 04/07/2023 | B43: FA-A 0007-00001512 | C43: MGR IMPLANTES SA | D43: IVA Responsable Inscripto | E43: 30709016012 | F43: 68619.8 | G43: 0 | H43: 0 | I43: 0 | J43: 0 | K43: 14410.15 | L43: 0 | M43: 0 | N43: 83029.95
A44: 04/07/2023 | B44: FA-A 0007-00001513 | C44: MGR IMPLANTES SA | D44: IVA Responsable Inscripto | E44: 30709016012 | F44: 10041.32 | G44: 0 | H44: 0 | I44: 0 | J44: 0 | K44: 2108.68 | L44: 0 | M44: 0 | N44: 12150
A45: 04/07/2023 | B45: FA-B 0007-00004470 | C45: ENRIQUETA MARIA DEL SOCORRO MAJO | D45: Consumidor Final | E45: 3192296 | F45: 3719.01 | G45: 0 | H45: 0 | I45: 0 | J45: 0 | K45: 780.99 | L45: 0 | M45: 0 | N45: 4500
A46: 04/07/2023 | B46: FA-B 0007-00004471 | C46: Chiari Maria Enriqueta del Socorro | D46: Consumidor Final | E46: 13211322 | F46: 3719.01 | G46: 0 | H46: 0 | I46: 0 | J46: 0 | K46: 780.99 | L46: 0 | M46: 0 | N46: 4500
A47: 04/07/2023 | B47: FA-B 0007-00004472 | C47: Herman Patricia | D47: Consumidor Final | E47: 21645724 | F47: 8677.68 | G47: 0 | H47: 0 | I47: 0 | J47: 0 | K47: 1822.32 | L47: 0 | M47: 0 | N47: 10500
A48: 04/07/2023 | B48: FA-B 0007-00004473 | C48: MARIA ELENA RODRIGUEZ | D48: Consumidor Final | E48: 382591 | F48: 5619.83 | G48: 0 | H48: 0 | I48: 0 | J48: 0 | K48: 1180.17 | L48: 0 | M48: 0 | N48: 6800
A49: 04/07/2023 | B49: FA-B 0007-00004474 | C49: LOCOCO, CARMEN | D49: Consumidor Final | E49: 17198648 | F49: 22809.91 | G49: 0 | H49: 0 | I49: 0 | J49: 0 | K49: 4790.09 | L49: 0 | M49: 0 | N49: 27600
A50: 04/07/2023 | B50: FA-B 0007-00004475 | C50: IZZO, ADRIANA | D50: Consumidor Final | E50: 14547747 | F50: 7438.02 | G50: 0 | H50: 0 | I50: 0 | J50: 0 | K50: 1561.98 | L50: 0 | M50: 0 | N50: 9000
A51: 05/07/2023 | B51: FA-B 0005-00008277 | C51: .CONSUMIDOR FINAL | D51: Consumidor Final | F51: 13429.75 | G51: 0 | H51: 0 | I51: 0 | J51: 0 | K51: 2820.25 | L51: 0 | M51: 0 | N51: 16250
A52: 05/07/2023 | B52: FA-B 0005-00008278 | C52: .CONSUMIDOR FINAL | D52: Consumidor Final | F52: 13553.72 | G52: 0 | H52: 0 | I52: 0 | J52: 0 | K52: 2846.28 | L52: 0 | M52: 0 | N52: 16400
A53: 05/07/2023 | B53: FA-B 0005-00008279 | C53: .CONSUMIDOR FINAL | D53: Consumidor Final | F53: 11363.64 | G53: 0 | H53: 0 | I53: 0 | J53: 0 | K53: 2386.36 | L53: 0 | M53: 0 | N53: 13750
A54: 05/07/2023 | B54: FA-B 0005-00008280 | C54: .CONSUMIDOR FINAL | D54: Consumidor Final | F54: 3388.43 | G54: 0 | H54: 0 | I54: 0 | J54: 0 | K54: 711.57 | L54: 0 | M54: 0 | N54: 4100
A55: 05/07/2023 | B55: FA-B 0005-00008281 | C55: DAPEÑA NOELIA | D55: Consumidor Final | E55: 33111382 | F55: 6776.86 | G55: 0 | H55: 0 | I55: 0 | J55: 0 | K55: 1423.14 | L55: 0 | M55: 0 | N55: 8200
A56: 05/07/2023 | B56: FA-B 0005-00008282 | C56: .CONSUMIDOR FINAL | D56: Consumidor Final | F56: 8677.69 | G56: 0 | H56: 0 | I56: 0 | J56: 0 | K56: 1822.31 | L56: 0 | M56: 0 | N56: 10500
A57: 05/07/2023 | B57: FA-B 0005-00008283 | C57: .CONSUMIDOR FINAL | D57: Consumidor Final | F57: 3140.5 | G57: 0 | H57: 0 | I57: 0 | J57: 0 | K57: 659.5 | L57: 0 | M57: 0 | N57: 3800
A58: 05/07/2023 | B58: FA-B 0005-00008284 | C58: .CONSUMIDOR FINAL | D58: Consumidor Final | F58: 2892.56 | G58: 0 | H58: 0 | I58: 0 | J58: 0 | K58: 607.44 | L58: 0 | M58: 0 | N58: 3500
A59: 05/07/2023 | B59: FA-B 0005-00008285 | C59: .CONSUMIDOR FINAL | D59: Consumidor Final | F59: 19297.52 | G59: 0 | H59: 0 | I59: 0 | J59: 0 | K59: 4052.48 | L59: 0 | M59: 0 | N59: 23350
A60: 05/07/2023 | B60: FA-B 0005-00008286 | C60: .CONSUMIDOR FINAL | D60: Consumidor Final | F60: 6033.06 | G60: 0 | H60: 0 | I60: 0 | J60: 0 | K60: 1266.94 | L60: 0 | M60: 0 | N60: 7300
A61: 05/07/2023 | B61: FA-B 0005-00008287 | C61: MARTINEZ VALENTINA | D61: Consumidor Final | E61: 46274672 | F61: 12066.12 | G61: 0 | H61: 0 | I61: 0 | J61: 0 | K61: 2533.88 | L61: 0 | M61: 0 | N61: 14600
A62: 05/07/2023 | B62: FA-B 0005-00008288 | C62: .CONSUMIDOR FINAL | D62: Consumidor Final | F62: 35041.32 | G62: 0 | H62: 0 | I62: 0 | J62: 0 | K62: 7358.68 | L62: 0 | M62: 0 | N62: 42400
A63: 05/07/2023 | B63: NC-A 0006-00000040 | C63: Galeno Argentina Sociedad Anonima | D63: IVA Responsable Inscripto | E63: 30522428163 | F63: -358677.69 | G63: 0 | H63: 0 | I63: 0 | J63: 0 | K63: -75322.31 | L63: 0 | M63: 0 | N63: -434000
A64: 05/07/2023 | B64: FA-A 0006-00000366 | C64: Galeno Argentina Sociedad Anonima | D64: IVA Responsable Inscripto | E64: 30522428163 | F64: 2549182.6 | G64: 0 | H64: 0 | I64: 0 | J64: 0 | K64: 535328.34 | L64: 0 | M64: 0 | N64: 3084510.9
A65: 05/07/2023 | B65: NC-A 0007-00000097 | C65: Galeno Argentina Sociedad Anonima | D65: IVA Responsable Inscripto | E65: 30522428163 | F65: -153930.99 | G65: 0 | H65: 0 | I65: 0 | J65: 0 | K65: -32325.51 | L65: 0 | M65: 0 | N65: -186256.5
A66: 05/07/2023 | B66: FA-A 0007-00001514 | C66: Galeno Argentina Sociedad Anonima | D66: IVA Responsable Inscripto | E66: 30522428163 | F66: 242682 | G66: 0 | H66: 0 | I66: 0 | J66: 0 | K66: 50963.22 | L66: 0 | M66: 0 | N66: 293645.22
A67: 05/07/2023 | B67: FA-A 0007-00001515 | C67: Galeno Argentina Sociedad Anonima | D67: IVA Responsable Inscripto | E67: 30522428163 | F67: 20089.03 | G67: 0 | H67: 0 | I67: 0 | J67: 0 | K67: 4218.7 | L67: 0 | M67: 0 | N67: 24307.73
A68: 05/07/2023 | B68: FA-A 0007-00001516 | C68: Galeno Argentina Sociedad Anonima | D68: IVA Responsable Inscripto | E68: 30522428163 | F68: 366991.4 | G68: 0 | H68: 0 | I68: 0 | J68: 0 | K68: 77068.19 | L68: 0 | M68: 0 | N68: 444059.59
A69: 05/07/2023 | B69: FA-A 0007-00001517 | C69: Galeno Argentina Sociedad Anonima | D69: IVA Responsable Inscripto | E69: 30522428163 | F69: 237629.19 | G69: 0 | H69: 0 | I69: 0 | J69: 0 | K69: 49902.13 | L69: 0 | M69: 0 | N69: 287531.32
A70: 05/07/2023 | B70: FA-A 0007-00001518 | C70: Galeno Argentina Sociedad Anonima | D70: IVA Responsable Inscripto | E70: 30522428163 | F70: 172466.7 | G70: 0 | H70: 0 | I70: 0 | J70: 0 | K70: 36218.01 | L70: 0 | M70: 0 | N70: 208684.71
A71: 05/07/2023 | B71: FA-B 0007-00004476 | C71: Asociacion Mutual Sancor Salud | D71: IVA Sujeto Exento | E71: 30590354798 | F71: 501517.08 | G71: 0 | H71: 0 | I71: 0 | J71: 0 | K71: 105318.59 | L71: 0 | M71: 0 | N71: 606835.67
A72: 05/07/2023 | B72: FA-B 0007-00004477 | C72: VOLPI, ALBERTO JAVIER | D72: Consumidor Final | E72: 21363216 | F72: 5785.12 | G72: 0 | H72: 0 | I72: 0 | J72: 0 | K72: 1214.88 | L72: 0 | M72: 0 | N72: 7000
A73: 05/07/2023 | B73: FA-B 0007-00004478 | C73: ALEJANDRA SIFFREDI TORRES SANMARCO | D73: Consumidor Final | E73: 5804480 | F73: 9917.36 | G73: 0 | H73: 0 | I73: 0 | J73: 0 | K73: 2082.64 | L73: 0 | M73: 0 | N73: 12000
A74: 06/07/2023 | B74: FA-B 0005-00008289 | C74: .CONSUMIDOR FINAL | D74: Consumidor Final | F74: 2727.27 | G74: 0 | H74: 0 | I74: 0 | J74: 0 | K74: 572.73 | L74: 0 | M74: 0 | N74: 3300
A75: 06/07/2023 | B75: FA-B 0005-00008290 | C75: LISI LUIS EDUARDO | D75: Consumidor Final | E75: 8573316 | F75: 4545.45 | G75: 0 | H75: 0 | I75: 0 | J75: 0 | K75: 954.55 | L75: 0 | M75: 0 | N75: 5500
A76: 06/07/2023 | B76: FA-B 0005-00008291 | C76: .CONSUMIDOR FINAL | D76: Consumidor Final | F76: 7851.24 | G76: 0 | H76: 0 | I76: 0 | J76: 0 | K76: 1648.76 | L76: 0 | M76: 0 | N76: 9500
A77: 06/07/2023 | B77: FA-B 0005-00008292 | C77: .CONSUMIDOR FINAL | D77: Consumidor Final | F77: 7892.56 | G77: 0 | H77: 0 | I77: 0 | J77: 0 | K77: 1657.44 | L77: 0 | M77: 0 | N77: 9550
A78: 06/07/2023 | B78: FA-B 0005-00008293 | C78: .CONSUMIDOR FINAL | D78: Consumidor Final | F78: 4132.23 | G78: 0 | H78: 0 | I78: 0 | J78: 0 | K78: 867.77 | L78: 0 | M78: 0 | N78: 5000
A79: 06/07/2023 | B79: FA-B 0005-00008294 | C79: .CONSUMIDOR FINAL | D79: Consumidor Final | F79: 12618.18 | G79: 0 | H79: 0 | I79: 0 | J79: 0 | K79: 2649.82 | L79: 0 | M79: 0 | N79: 15268
A80: 06/07/2023 | B80: FA-B 0005-00008295 | C80: .CONSUMIDOR FINAL | D80: Consumidor Final | F80: 6776.86 | G80: 0 | H80: 0 | I80: 0 | J80: 0 | K80: 1423.14 | L80: 0 | M80: 0 | N80: 8200
A81: 06/07/2023 | B81: FA-B 0005-00008296 | C81: .CONSUMIDOR FINAL | D81: Consumidor Final | F81: 4545.45 | G81: 0 | H81: 0 | I81: 0 | J81: 0 | K81: 954.55 | L81: 0 | M81: 0 | N81: 5500
A82: 06/07/2023 | B82: FA-B 0005-00008297 | C82: .CONSUMIDOR FINAL | D82: Consumidor Final | F82: 9504.13 | G82: 0 | H82: 0 | I82: 0 | J82: 0 | K82: 1995.87 | L82: 0 | M82: 0 | N82: 11500
A83: 06/07/2023 | B83: FA-B 0005-00008298 | C83: .CONSUMIDOR FINAL | D83: Consumidor Final | F83: 4958.68 | G83: 0 | H83: 0 | I83: 0 | J83: 0 | K83: 1041.32 | L83: 0 | M83: 0 | N83: 6000
A84: 06/07/2023 | B84: FA-B 0005-00008299 | C84: .CONSUMIDOR FINAL | D84: Consumidor Final | F84: 10578.51 | G84: 0 | H84: 0 | I84: 0 | J84: 0 | K84: 2221.49 | L84: 0 | M84: 0 | N84: 12800
A85: 06/07/2023 | B85: FA-B 0005-00008300 | C85: .CONSUMIDOR FINAL | D85: Consumidor Final | F85: 4958.68 | G85: 0 | H85: 0 | I85: 0 | J85: 0 | K85: 1041.32 | L85: 0 | M85: 0 | N85: 6000
A86: 06/07/2023 | B86: FA-B 0005-00008301 | C86: .CONSUMIDOR FINAL | D86: Consumidor Final | F86: 4545.45 | G86: 0 | H86: 0 | I86: 0 | J86: 0 | K86: 954.55 | L86: 0 | M86: 0 | N86: 5500
A87: 06/07/2023 | B87: NC-A 0006-00000041 | C87: Galeno Argentina Sociedad Anonima | D87: IVA Responsable Inscripto | E87: 30522428163 | F87: -523262.6 | G87: 0 | H87: 0 | I87: 0 | J87: 0 | K87: -109885.15 | L87: 0 | M87: 0 | N87: -633147.75
A88: 06/07/2023 | B88: FA-A 0007-00001519 | C88: Galeno Argentina Sociedad Anonima | D88: IVA Responsable Inscripto | E88: 30522428163 | F88: 237212.36 | G88: 0 | H88: 0 | I88: 0 | J88: 0 | K88: 49814.6 | L88: 0 | M88: 0 | N88: 287026.96
A89: 07/07/2023 | B89: FA-B 0005-00008302 | C89: .CONSUMIDOR FINAL | D89: Consumidor Final | F89: 5537.19 | G89: 0 | H89: 0 | I89: 0 | J89: 0 | K89: 1162.81 | L89: 0 | M89: 0 | N89: 6700
A90: 07/07/2023 | B90: FA-B 0005-00008303 | C90: .CONSUMIDOR FINAL | D90: Consumidor Final | F90: 9504.13 | G90: 0 | H90: 0 | I90: 0 | J90: 0 | K90: 1995.87 | L90: 0 | M90: 0 | N90: 11500
A91: 07/07/2023 | B91: FA-B 0005-00008304 | C91: .CONSUMIDOR FINAL | D91: Consumidor Final | F91: 6776.86 | G91: 0 | H91: 0 | I91: 0 | J91: 0 | K91: 1423.14 | L91: 0 | M91: 0 | N91: 8200
A92: 07/07/2023 | B92: FA-B 0005-00008305 | C92: .CONSUMIDOR FINAL | D92: Consumidor Final | F92: 1818.18 | G92: 0 | H92: 0 | I92: 0 | J92: 0 | K92: 381.82 | L92: 0 | M92: 0 | N92: 2200
A93: 07/07/2023 | B93: FA-B 0005-00008306 | C93: .CONSUMIDOR FINAL | D93: Consumidor Final | F93: 2809.92 | G93: 0 | H93: 0 | I93: 0 | J93: 0 | K93: 590.08 | L93: 0 | M93: 0 | N93: 3400
A94: 07/07/2023 | B94: FA-B 0005-00008307 | C94: .CONSUMIDOR FINAL | D94: Consumidor Final | F94: 10000 | G94: 0 | H94: 0 | I94: 0 | J94: 0 | K94: 2100 | L94: 0 | M94: 0 | N94: 12100
A95: 07/07/2023 | B95: FA-B 0005-00008308 | C95: .CONSUMIDOR FINAL | D95: Consumidor Final | F95: 5785.12 | G95: 0 | H95: 0 | I95: 0 | J95: 0 | K95: 1214.88 | L95: 0 | M95: 0 | N95: 7000
A96: 07/07/2023 | B96: FA-B 0005-00008309 | C96: .CONSUMIDOR FINAL | D96: Consumidor Final | F96: 2727.27 | G96: 0 | H96: 0 | I96: 0 | J96: 0 | K96: 572.73 | L96: 0 | M96: 0 | N96: 3300
A97: 07/07/2023 | B97: FA-B 0005-00008310 | C97: .CONSUMIDOR FINAL | D97: Consumidor Final | F97: 7851.24 | G97: 0 | H97: 0 | I97: 0 | J97: 0 | K97: 1648.76 | L97: 0 | M97: 0 | N97: 9500
A98: 07/07/2023 | B98: FA-A 0006-00000367 | C98: Galeno Argentina Sociedad Anonima | D98: IVA Responsable Inscripto | E98: 30522428163 | F98: 4272727.3 | G98: 0 | H98: 0 | I98: 0 | J98: 0 | K98: 897272.73 | L98: 0 | M98: 0 | N98: 5170000
A99: 07/07/2023 | B99: FA-B 0007-00004479 | C99: JUAN PABLO MINVIELLE | D99: Consumidor Final | E99: 36622635 | F99: 12892.56 | G99: 0 | H99: 0 | I99: 0 | J99: 0 | K99: 2707.44 | L99: 0 | M99: 0 | N99: 15600
A100: 07/07/2023 | B100: FA-B 0007-00004480 | C100: GLORIA FULLGRAFF | D100: Consumidor Final | E100: 92316435 | F100: 6611.57 | G100: 0 | H100: 0 | I100: 0 | J100: 0 | K100: 1388.43 | L100: 0 | M100: 0 | N100: 8000
A101: 07/07/2023 | B101: FA-B 0007-00004481 | C101: ROMEO, NELIDA ZULMA | D101: Consumidor Final | E101: 2925288 | F101: 14049.59 | G101: 0 | H101: 0 | I101: 0 | J101: 0 | K101: 2950.41 | L101: 0 | M101: 0 | N101: 17000
A102: 07/07/2023 | B102: FA-B 0007-00004482 | C102: MATHOV ENRIQUE JOSE | D102: Consumidor Final | E102: 5274861 | F102: 8677.68 | G102: 0 | H102: 0 | I102: 0 | J102: 0 | K102: 1822.32 | L102: 0 | M102: 0 | N102: 10500
...
