Workbook

Sheet Lista_CUIT
A1: CUIT | B1: RAZON SOCIAL | C1: Tipo de Gasto | D1: PROVINCIA
A2: 30575019524 | B2: 100000 LAMPARAS SRL | G2: Mercaderia
A3: 30709829730 | B3: 4KRC SA | C3: Mantenimiento | G3: Servicios Gas, Luz, etc.
A4: 30715223704 | B4: 5 CEPAS S.R.L. | C4: MERCADERIA | G4: Gastos catering
A5: 30714869937 | B5: 60 LIBRAS SRL | G5: Combustibe
A6: 30692212130 | B6: A R C CONSTRUCCIONES S.A. | G6: Gastos Varios
A7: 30687722007 | B7: A. RUSSONIELLO SA | C7: SERVICIOS | G7: Gastos seguridad
A8: 30503874497 | B8: A.M. PESCIO S.C.A | C8: Mercaderia | G8: Librería
A9: 30702017498 | B9: ABBS POINT DESING S.A. | G9: Gastos mantenimiento
A10: 20182999661 | B10: ABEL JAVIER KLAINER | C10: Mercaderia | G10: Gastos comercializacion
A11: 30652000076 | B11: ABELSON SA | C11: Mercaderia | G11: Alquiler
A12: 30690536079 | B12: ACCESOR SRL | C12: Gastos Varios | G12: Honorarios contables
A13: 30515585415 | B13: ACEROSALFA SA | C13: Mercaderia | G13: Gastos administrativos
A14: 33711942659 | B14: ACLOS ASOC. CIVIL PARA LA LONG | C14: Mercaderia | G14: Seguro
A15: 30715243349 | B15: ADSE S.A | G15: Extracto
A16: 20174004146 | B16: ADUEARDO FRANCISCO NARDOMARINO | C16: Mercaderia | G16: Flete
A17: 30708555548 | B17: AGH S.A | C17: Mercaderia | G17: Honorarios Legales
A18: 30708263342 | B18: AGRACO S.A | C18: MERCADERIA | G18: Insumo
A19: 30709565075 | B19: AGUA Y SANEAMIENTOS ARG SA | C19: SERVICIOS | G19: Muebles y Utiles
A20: 30500229973 | B20: AKIAN GRAFICA EDITORA SA | C20: Mercaderia | G20: Otros
A21: 30710799241 | B21: ALANAR S.R.L. | G21: Telefonia
A22: 20236101127 | B22: ALEJANDRO DARIO LOPEZ | G22: Alojamiento-Varios
A23: 20291929126 | B23: ALEJANDRO MIGUEL DAUBLER
A24: 30709604887 | B24: ALFABIS SRL. | C24: Mantenimiento
A25: 20083925680 | B25: ALFREDO DANIEL FERNANDEZ | C25: Gastos Varios
A26: 30656038752 | B26: ALFREDO OMAR POTENZA SRL | C26: Mercaderia
A27: 30504563894 | B27: ALI HERMANOS SRL | C27: Mercaderia
A28: 30602699826 | B28: ALKO SRL
A29: 30715190385 | B29: ALL FEDERAL SA.
A30: 23945042079 | B30: ALVARENGA VILLAR LUIS F | C30: Gastos Varios
A31: 20040616498 | B31: ALVAREZ MARCELINO
A32: 30710587147 | B32: AMAKOR SA | C32: SERVICIOS
A33: 30663288497 | B33: AMX ARG SA
A34: 27108310559 | B34: ANA MARIA VALDEZ
A35: 30502375535 | B35: ANAVI S.C.A.
A36: 30709251739 | B36: ANDES LINEAS AEREAS SA
A37: 30709948667 | B37: ANTAGGER SRL | C37: Mercaderia
A38: 30683702060 | B38: ANTARES INDUST. ORTOP SA | C38: Mercaderia
A39: 30715985124 | B39: ANTOLFO S.R.L.
A40: 30714344656 | B40: AQUALAF S.A. | C40: Mercaderia
A41: 30712000372 | B41: AQUÍ MERCEDES SRL | C41: Mercaderia
A42: 30714741167 | B42: ARALIMP S.R.L.
A43: 20927832136 | B43: ARANCIBIA IBACETA CIPRIANO | C43: Gastos Varios
A44: 27135302835 | B44: ARENAS MONICA MARIEL
A45: 27276671109 | B45: AREVALO LORENA ELIZABETH | C45: Mercaderia
A46: 30711597499 | B46: ARGENVODA SA
A47: 30600907553 | B47: ARMAGALLI SA
A48: 30709585262 | B48: ARMY TECHNOLOGIES S.A. | C48: Mantenimiento
A49: 30614941509 | B49: ARREDO
A50: 30560443648 | B50: ARSA ELECTRICIDAD SRL
A51: 30708547790 | B51: ARTELEC ARGENTINA SRL
A52: 30711624402 | B52: ARTES REGIONALES SRL
A53: 20045180620 | B53: ARUGUETE ENRIQUE JORGE | C53: Gastos Varios
A54: 30692175243 | B54: ASAHI MOTORS SA
A55: 30708973501 | B55: ASIAL SRL | C55: Mercaderia
A56: 30590354798 | B56: ASOC. MUTUAL SANCOR SALUD
A57: 30709860840 | B57: AUMECON SA
A58: 30544712833 | B58: AURELIO GUNDIN SA | C58: Mercaderia
A59: 30715031252 | B59: AUTO VENETO S.A.
A60: 30711934754 | B60: AUTOBIZ SA
A61: 30670528592 | B61: AUTOMOTORES FIORASI Y CORRADI
A62: 30574876474 | B62: AUTOP. URBANAS SA
A63: 30677237119 | B63: AUTOPISTAS DEL SOL SA
A64: 30607371799 | B64: AUTOSERVICIO DIARCO SA
A65: 20278462790 | B65: VARAS TOLEDO SEBASTIAN
A66: 30715963872 | B66: MARAKANA SRL
A67: 20083762102 | B67: AVANCE-MAG
A68: 20287830980 | B68: AVILA MARTIN LEONARDO
A69: 30506919009 | B69: AXION ENERGY ARG SA | C69: COMBUSTIBLE
A70: 30535612117 | B70: AYUDA MUT. DEL PERS. DE GENDAR
A71: 33711430879 | B71: BALANZE S.A. | C71: Mercaderia
A72: 20179619483 | B72: BALE JORGE CARLOS
A73: 30711941718 | B73: BALLERINI ATILIO Y SOTO RAUL C | C73: Mercaderia
A74: 30580189411 | B74: BANCO ITAU ARG SA
A75: 30500008454 | B75: BANCO SANTANDER RIO SA | C75: Extracto
A76: 30646362675 | B76: BAUMGARTEN GRAFICA ARG SA
A77: 30712458468 | B77: BEEL SUL S.A. | C77: Gastos Varios
A78: 30714675601 | B78: BELGRANO NEUMATICOS S.A.
A79: 30568222187 | B79: BELLINI HNOS SRL
A80: 27248212646 | B80: BELLOMO MARIA MERCEDES
A81: 27115740666 | B81: BEN Y BEN
A82: 27129411010 | B82: BENITEZ ANA MARIA
A83: 23301961944 | B83: BERGOC CECILIA ANDREA
A84: 30710067763 | B84: BI POOL S.R.L.
A85: 30712387315 | B85: BIALA SRL | C85: Gastos Varios
A86: 30715210637 | B86: BIAUS SRL | C86: Mercaderia
A87: 30712230459 | B87: BIOMAX INSUMOS MEDICOS | C87: Mercaderia
A88: 30697652694 | B88: BISTRO SA
A89: 30712476857 | B89: BODEGA DON BOSCO | C89: MERCADERIA
A90: 30708270462 | B90: body group feliz srl
A91: 23253931159 | B91: BOECHI JUAN
A92: 30655186693 | B92: BOSAN SA
A93: 20389908569 | B93: BOTINDARI JUAN IGNACIO | C93: Honorarios Contables
A94: 30515676178 | B94: BROGAS SA | C94: Mercaderia
A95: 33711821649 | B95: BRUBEN DUDAMERICANA
A96: 30715122657 | B96: BRUNETTE SRL
A97: 30715549871 | B97: BSMS SRL
A98: 20085280512 | B98: BULONERA HURLINGHAM | C98: Mercaderia
A99: 30595442369 | B99: BULONERA MATADEROS SRL | C99: Mercaderia
A100: 27289847141 | B100: BUSACCA PAOLA EDITH | C100: LIBRERÍA
...

Sheet Abr-26
B1: LIBRO IVA COMPRAS | G1: CORITEC S. R. L. | N1: 45748
B3: TOTAL COMPRAS NETAS | G3: TOTAL CREDITO FISCAL | J3: TOTAL VENTAS NETAS | M3: TOTAL DEBITO FISCAL | P3: RESULTADO
B4: =SUM('Abr-26'!$H$40)+'Abr-26'!$G$57 -> 4745586.6 | G4: ='Abr-26'!$I$40+'Abr-26'!$J$40+'Abr-26'!$K$40+I58 -> 862296.52 | J4: ='Abr-26'!$H$96+'Abr-26'!$H$106 -> 82452311 | M4: ='Abr-26'!$I$96+'Abr-26'!$J$96+'Abr-26'!$I$106+'Abr-26'!$J$106 -> 10463262 | P4: =G4-M4 -> -9600965.4
B8: FECHA | C8: TIPO | D8: PTO VTA | E8: NRO. CPTE | F8: CUIT | G8: RAZON SOCIAL | H8: NETO GRAVADO | I8: IVA 21 % | J8: IVA 27% | K8: IVA 10,5% | L8: PERC. IVA | M8: PERC IIBB BS AS | N8: PERC. IIBB CABA | O8: Otros / No Grav. | P8: TOTAL | Q8: Tipo de Gasto | R8: Provincia
B9: 46113 | C9: 1 | D9: 5 | E9: 7888 | F9: 20231333593 | G9: =IFERROR(IF('Abr-26'!$F9="","-",VLOOKUP('Abr-26'!$F9,Lista_CUIT!$A$1:$D$2241,2,0)),"CUIT NO CARGADO") -> BOLLINI CLAUDIO DANIEL | H9: 80000 | I9: ='Abr-26'!$H9*0.21 -> 16800 | P9: =SUM('Abr-26'!$H9:$O9) -> 96800 | Q9: =IFERROR(IF('Abr-26'!$F9="","-",VLOOKUP('Abr-26'!$F9,Lista_CUIT!$A$1:$D$2241,3,0)),"CUIT NO CARGADO") -> Mantenimiento | R9: =IFERROR(IF('Abr-26'!$F9="","-",VLOOKUP('Abr-26'!$F9,Lista_CUIT!$A$1:$D$2241,4,0)),"CUIT NO CARGADO") -> 0
B10: 46113 | C10: 1 | D10: 3 | E10: 302589 | F10: 30707135596 | G10: =IFERROR(IF('Abr-26'!$F10="","-",VLOOKUP('Abr-26'!$F10,Lista_CUIT!$A$1:$D$2241,2,0)),"CUIT NO CARGADO") -> CITILAN ARGENTINA S.A. | H10: 43155 | I10: ='Abr-26'!$H10*0.21 -> 9062.55 | P10: =SUM('Abr-26'!$H10:$O10) -> 52217.55 | Q10: =IFERROR(IF('Abr-26'!$F10="","-",VLOOKUP('Abr-26'!$F10,Lista_CUIT!$A$1:$D$2241,3,0)),"CUIT NO CARGADO") -> Telefonia | R10: =IFERROR(IF('Abr-26'!$F10="","-",VLOOKUP('Abr-26'!$F10,Lista_CUIT!$A$1:$D$2241,4,0)),"CUIT NO CARGADO") -> 0
B11: 46113 | C11: 1 | D11: 3 | E11: 944 | F11: 30715402765 | G11: =IFERROR(IF('Abr-26'!$F11="","-",VLOOKUP('Abr-26'!$F11,Lista_CUIT!$A$1:$D$2241,2,0)),"CUIT NO CARGADO") -> RIO 265 S.R.L. | H11: 140495.86 | I11: ='Abr-26'!$H11*0.21 -> 29504.131 | P11: =SUM('Abr-26'!$H11:$O11) -> 169999.99 | Q11: =IFERROR(IF('Abr-26'!$F11="","-",VLOOKUP('Abr-26'!$F11,Lista_CUIT!$A$1:$D$2241,3,0)),"CUIT NO CARGADO") -> GASTOS VARIOS | R11: =IFERROR(IF('Abr-26'!$F11="","-",VLOOKUP('Abr-26'!$F11,Lista_CUIT!$A$1:$D$2241,4,0)),"CUIT NO CARGADO") -> 0
B12: 46114 | C12: 1 | D12: 4 | E12: 28806 | F12: 30714440779 | G12: =IFERROR(IF('Abr-26'!$F12="","-",VLOOKUP('Abr-26'!$F12,Lista_CUIT!$A$1:$D$2241,2,0)),"CUIT NO CARGADO") -> KITA S.R.L. | H12: 18165.29 | I12: ='Abr-26'!$H12*0.21 -> 3814.7109 | P12: =SUM('Abr-26'!$H12:$O12) -> 21980.001 | Q12: =IFERROR(IF('Abr-26'!$F12="","-",VLOOKUP('Abr-26'!$F12,Lista_CUIT!$A$1:$D$2241,3,0)),"CUIT NO CARGADO") -> 0 | R12: =IFERROR(IF('Abr-26'!$F12="","-",VLOOKUP('Abr-26'!$F12,Lista_CUIT!$A$1:$D$2241,4,0)),"CUIT NO CARGADO") -> 0
B13: 46117 | C13: 1 | D13: 6 | E13: 129364 | F13: 30714971782 | G13: =IFERROR(IF('Abr-26'!$F13="","-",VLOOKUP('Abr-26'!$F13,Lista_CUIT!$A$1:$D$2241,2,0)),"CUIT NO CARGADO") -> PINTOS SCHMIDT ALDANA MARCELA Y SACK ADRIANA CRISTINA SH | H13: 18380.99 | I13: ='Abr-26'!$H13*0.21 -> 3860.0079 | P13: =SUM('Abr-26'!$H13:$O13) -> 22240.998 | Q13: =IFERROR(IF('Abr-26'!$F13="","-",VLOOKUP('Abr-26'!$F13,Lista_CUIT!$A$1:$D$2241,3,0)),"CUIT NO CARGADO") -> 0 | R13: =IFERROR(IF('Abr-26'!$F13="","-",VLOOKUP('Abr-26'!$F13,Lista_CUIT!$A$1:$D$2241,4,0)),"CUIT NO CARGADO") -> 0
B14: 46118 | C14: 1 | D14: 1 | E14: 3389 | F14: 30717248267 | G14: =IFERROR(IF('Abr-26'!$F14="","-",VLOOKUP('Abr-26'!$F14,Lista_CUIT!$A$1:$D$2241,2,0)),"CUIT NO CARGADO") -> KARTELACRIL | H14: 85000 | I14: ='Abr-26'!$H14*0.21 -> 17850 | P14: =SUM('Abr-26'!$H14:$O14) -> 102850 | Q14: =IFERROR(IF('Abr-26'!$F14="","-",VLOOKUP('Abr-26'!$F14,Lista_CUIT!$A$1:$D$2241,3,0)),"CUIT NO CARGADO") -> 0 | R14: =IFERROR(IF('Abr-26'!$F14="","-",VLOOKUP('Abr-26'!$F14,Lista_CUIT!$A$1:$D$2241,4,0)),"CUIT NO CARGADO") -> 0
B15: 46119 | C15: 1 | D15: 63 | E15: 3750571 | F15: 30640897267 | G15: =IFERROR(IF('Abr-26'!$F15="","-",VLOOKUP('Abr-26'!$F15,Lista_CUIT!$A$1:$D$2241,2,0)),"CUIT NO CARGADO") -> TELECENTRO SA | H15: 75540 | I15: ='Abr-26'!$H15*0.21 -> 15863.4 | O15: 2266.2 | P15: =SUM('Abr-26'!$H15:$O15) -> 93669.6 | Q15: =IFERROR(IF('Abr-26'!$F15="","-",VLOOKUP('Abr-26'!$F15,Lista_CUIT!$A$1:$D$2241,3,0)),"CUIT NO CARGADO") -> SERVICIOS | R15: =IFERROR(IF('Abr-26'!$F15="","-",VLOOKUP('Abr-26'!$F15,Lista_CUIT!$A$1:$D$2241,4,0)),"CUIT NO CARGADO") -> 0
B16: 46127 | C16: 1 | D16: 3 | E16: 443194 | F16: 33643358749 | G16: =IFERROR(IF('Abr-26'!$F16="","-",VLOOKUP('Abr-26'!$F16,Lista_CUIT!$A$1:$D$2241,2,0)),"CUIT NO CARGADO") -> POLYTECH S A | H16: 1357772.5 | I16: 33370.73 | K16: 125880.75 | P16: =SUM('Abr-26'!$H16:$O16) -> 1517024 | Q16: =IFERROR(IF('Abr-26'!$F16="","-",VLOOKUP('Abr-26'!$F16,Lista_CUIT!$A$1:$D$2241,3,0)),"CUIT NO CARGADO") -> Servicios Informaticos | R16: =IFERROR(IF('Abr-26'!$F16="","-",VLOOKUP('Abr-26'!$F16,Lista_CUIT!$A$1:$D$2241,4,0)),"CUIT NO CARGADO") -> 0
B17: 46128 | C17: 1 | D17: 4 | E17: 1821707 | F17: 30716620634 | G17: =IFERROR(IF('Abr-26'!$F17="","-",VLOOKUP('Abr-26'!$F17,Lista_CUIT!$A$1:$D$2241,2,0)),"CUIT NO CARGADO") -> FIRSTLABEL SRL | H17: 8806.61 | I17: ='Abr-26'!$H17*0.21 -> 1849.3881 | P17: =SUM('Abr-26'!$H17:$O17) -> 10655.998 | Q17: =IFERROR(IF('Abr-26'!$F17="","-",VLOOKUP('Abr-26'!$F17,Lista_CUIT!$A$1:$D$2241,3,0)),"CUIT NO CARGADO") -> GASTOS VARIOS | R17: =IFERROR(IF('Abr-26'!$F17="","-",VLOOKUP('Abr-26'!$F17,Lista_CUIT!$A$1:$D$2241,4,0)),"CUIT NO CARGADO") -> 0
B18: 46128 | C18: 1 | D18: 7 | E18: 2924 | F18: 20324801236 | G18: =IFERROR(IF('Abr-26'!$F18="","-",VLOOKUP('Abr-26'!$F18,Lista_CUIT!$A$1:$D$2241,2,0)),"CUIT NO CARGADO") -> CAMPAGNA SEBASTIAN PABLO | H18: 18428.1 | I18: ='Abr-26'!$H18*0.21 -> 3869.901 | P18: =SUM('Abr-26'!$H18:$O18) -> 22298.001 | Q18: =IFERROR(IF('Abr-26'!$F18="","-",VLOOKUP('Abr-26'!$F18,Lista_CUIT!$A$1:$D$2241,3,0)),"CUIT NO CARGADO") -> Papeleria | R18: =IFERROR(IF('Abr-26'!$F18="","-",VLOOKUP('Abr-26'!$F18,Lista_CUIT!$A$1:$D$2241,4,0)),"CUIT NO CARGADO") -> 0
B19: 46128 | C19: 1 | D19: 106 | E19: 940902 | F19: 30594494187 | G19: =IFERROR(IF('Abr-26'!$F19="","-",VLOOKUP('Abr-26'!$F19,Lista_CUIT!$A$1:$D$2241,2,0)),"CUIT NO CARGADO") -> FEDERAL EXPRESS CORPORATION | H19: 0 | I19: ='Abr-26'!$H19*0.21 -> 0 | O19: 1103171 | P19: =SUM('Abr-26'!$H19:$O19) -> 1103171 | Q19: =IFERROR(IF('Abr-26'!$F19="","-",VLOOKUP('Abr-26'!$F19,Lista_CUIT!$A$1:$D$2241,3,0)),"CUIT NO CARGADO") -> Mercaderia | R19: =IFERROR(IF('Abr-26'!$F19="","-",VLOOKUP('Abr-26'!$F19,Lista_CUIT!$A$1:$D$2241,4,0)),"CUIT NO CARGADO") -> 0
B20: 46128 | C20: 1 | D20: 7 | E20: 3179 | F20: 30716542773 | G20: =IFERROR(IF('Abr-26'!$F20="","-",VLOOKUP('Abr-26'!$F20,Lista_CUIT!$A$1:$D$2241,2,0)),"CUIT NO CARGADO") -> CFV | H20: 12059.5 | I20: ='Abr-26'!$H20*0.21 -> 2532.495 | P20: =SUM('Abr-26'!$H20:$O20) -> 14591.995 | Q20: =IFERROR(IF('Abr-26'!$F20="","-",VLOOKUP('Abr-26'!$F20,Lista_CUIT!$A$1:$D$2241,3,0)),"CUIT NO CARGADO") -> GASTOS VARIOS | R20: =IFERROR(IF('Abr-26'!$F20="","-",VLOOKUP('Abr-26'!$F20,Lista_CUIT!$A$1:$D$2241,4,0)),"CUIT NO CARGADO") -> 0
B21: 46129 | C21: 1 | D21: 13 | E21: 120984 | F21: 30709256420 | G21: =IFERROR(IF('Abr-26'!$F21="","-",VLOOKUP('Abr-26'!$F21,Lista_CUIT!$A$1:$D$2241,2,0)),"CUIT NO CARGADO") -> NGA SRL | H21: 3490.45 | I21: ='Abr-26'!$H21*0.21 -> 732.9945 | P21: =SUM('Abr-26'!$H21:$O21) -> 4223.4445 | Q21: =IFERROR(IF('Abr-26'!$F21="","-",VLOOKUP('Abr-26'!$F21,Lista_CUIT!$A$1:$D$2241,3,0)),"CUIT NO CARGADO") -> GASTOS VARIOS | R21: =IFERROR(IF('Abr-26'!$F21="","-",VLOOKUP('Abr-26'!$F21,Lista_CUIT!$A$1:$D$2241,4,0)),"CUIT NO CARGADO") -> 0
B22: 46129 | C22: 1 | D22: 3 | E22: 10961 | F22: 30715039369 | G22: =IFERROR(IF('Abr-26'!$F22="","-",VLOOKUP('Abr-26'!$F22,Lista_CUIT!$A$1:$D$2241,2,0)),"CUIT NO CARGADO") -> GIANGIU S.A. | H22: 7891.74 | I22: ='Abr-26'!$H22*0.21 -> 1657.2654 | P22: =SUM('Abr-26'!$H22:$O22) -> 9549.0054 | Q22: =IFERROR(IF('Abr-26'!$F22="","-",VLOOKUP('Abr-26'!$F22,Lista_CUIT!$A$1:$D$2241,3,0)),"CUIT NO CARGADO") -> 0 | R22: =IFERROR(IF('Abr-26'!$F22="","-",VLOOKUP('Abr-26'!$F22,Lista_CUIT!$A$1:$D$2241,4,0)),"CUIT NO CARGADO") -> 0
B23: 46129 | C23: 1 | D23: 50 | E23: 544339 | F23: 30610333822 | G23: =IFERROR(IF('Abr-26'!$F23="","-",VLOOKUP('Abr-26'!$F23,Lista_CUIT!$A$1:$D$2241,2,0)),"CUIT NO CARGADO") -> MASIVOS S A | H23: 4475.21 | I23: ='Abr-26'!$H23*0.21 -> 939.7941 | P23: =SUM('Abr-26'!$H23:$O23) -> 5415.0041 | Q23: =IFERROR(IF('Abr-26'!$F23="","-",VLOOKUP('Abr-26'!$F23,Lista_CUIT!$A$1:$D$2241,3,0)),"CUIT NO CARGADO") -> GASTOS VARIOS | R23: =IFERROR(IF('Abr-26'!$F23="","-",VLOOKUP('Abr-26'!$F23,Lista_CUIT!$A$1:$D$2241,4,0)),"CUIT NO CARGADO") -> 0
B24: 46131 | C24: 1 | D24: 30 | E24: 3215 | F24: 27259980815 | G24: =IFERROR(IF('Abr-26'!$F24="","-",VLOOKUP('Abr-26'!$F24,Lista_CUIT!$A$1:$D$2241,2,0)),"CUIT NO CARGADO") -> COLOMBO LORENA ALEJANDRA | H24: 3305.79 | I24: ='Abr-26'!$H24*0.21 -> 694.2159 | P24: =SUM('Abr-26'!$H24:$O24) -> 4000.0059 | Q24: =IFERROR(IF('Abr-26'!$F24="","-",VLOOKUP('Abr-26'!$F24,Lista_CUIT!$A$1:$D$2241,3,0)),"CUIT NO CARGADO") -> 0 | R24: =IFERROR(IF('Abr-26'!$F24="","-",VLOOKUP('Abr-26'!$F24,Lista_CUIT!$A$1:$D$2241,4,0)),"CUIT NO CARGADO") -> 0
B25: 46132 | C25: 1 | D25: 3 | E25: 382 | F25: 20921575743 | G25: =IFERROR(IF('Abr-26'!$F25="","-",VLOOKUP('Abr-26'!$F25,Lista_CUIT!$A$1:$D$2241,2,0)),"CUIT NO CARGADO") -> RIOS GOMEZ JOSE ANTONIO | H25: 372500 | I25: ='Abr-26'!$H25*0.21 -> 78225 | P25: =SUM('Abr-26'!$H25:$O25) -> 450725 | Q25: =IFERROR(IF('Abr-26'!$F25="","-",VLOOKUP('Abr-26'!$F25,Lista_CUIT!$A$1:$D$2241,3,0)),"CUIT NO CARGADO") -> Papeleria | R25: =IFERROR(IF('Abr-26'!$F25="","-",VLOOKUP('Abr-26'!$F25,Lista_CUIT!$A$1:$D$2241,4,0)),"CUIT NO CARGADO") -> 0
B26: 46133 | C26: 1 | D26: 3 | E26: 16172 | F26: 20936786775 | G26: =IFERROR(IF('Abr-26'!$F26="","-",VLOOKUP('Abr-26'!$F26,Lista_CUIT!$A$1:$D$2241,2,0)),"CUIT NO CARGADO") -> HUNG HSI PAO | H26: 15280.17 | I26: ='Abr-26'!$H26*0.21 -> 3208.8357 | P26: =SUM('Abr-26'!$H26:$O26) -> 18489.006 | Q26: =IFERROR(IF('Abr-26'!$F26="","-",VLOOKUP('Abr-26'!$F26,Lista_CUIT!$A$1:$D$2241,3,0)),"CUIT NO CARGADO") -> 0 | R26: =IFERROR(IF('Abr-26'!$F26="","-",VLOOKUP('Abr-26'!$F26,Lista_CUIT!$A$1:$D$2241,4,0)),"CUIT NO CARGADO") -> 0
B27: 46134 | C27: 1 | D27: 122 | E27: 427147 | F27: 30594494187 | G27: =IFERROR(IF('Abr-26'!$F27="","-",VLOOKUP('Abr-26'!$F27,Lista_CUIT!$A$1:$D$2241,2,0)),"CUIT NO CARGADO") -> FEDERAL EXPRESS CORPORATION | H27: 99036 | I27: ='Abr-26'!$H27*0.21 -> 20797.56 | O27: 495014.94 | P27: =SUM('Abr-26'!$H27:$O27) -> 614848.5 | Q27: =IFERROR(IF('Abr-26'!$F27="","-",VLOOKUP('Abr-26'!$F27,Lista_CUIT!$A$1:$D$2241,3,0)),"CUIT NO CARGADO") -> Mercaderia | R27: =IFERROR(IF('Abr-26'!$F27="","-",VLOOKUP('Abr-26'!$F27,Lista_CUIT!$A$1:$D$2241,4,0)),"CUIT NO CARGADO") -> 0
B28: 46135 | C28: 1 | D28: 9 | E28: 52531 | F28: 30710879199 | G28: =IFERROR(IF('Abr-26'!$F28="","-",VLOOKUP('Abr-26'!$F28,Lista_CUIT!$A$1:$D$2241,2,0)),"CUIT NO CARGADO") -> C C AGRO & TEC S.A. | H28: 113487.6 | I28: ='Abr-26'!$H28*0.21 -> 23832.396 | P28: =SUM('Abr-26'!$H28:$O28) -> 137320 | Q28: =IFERROR(IF('Abr-26'!$F28="","-",VLOOKUP('Abr-26'!$F28,Lista_CUIT!$A$1:$D$2241,3,0)),"CUIT NO CARGADO") -> 0 | R28: =IFERROR(IF('Abr-26'!$F28="","-",VLOOKUP('Abr-26'!$F28,Lista_CUIT!$A$1:$D$2241,4,0)),"CUIT NO CARGADO") -> 0
B29: 46136 | C29: 1 | D29: 2 | E29: 4327 | F29: 30718133412 | G29: =IFERROR(IF('Abr-26'!$F29="","-",VLOOKUP('Abr-26'!$F29,Lista_CUIT!$A$1:$D$2241,2,0)),"CUIT NO CARGADO") -> FULL HOUSE TIENDA S.R.L. | H29: 230926.29 | I29: ='Abr-26'!$H29*0.21 -> 48494.521 | P29: =SUM('Abr-26'!$H29:$O29) -> 279420.81 | Q29: =IFERROR(IF('Abr-26'!$F29="","-",VLOOKUP('Abr-26'!$F29,Lista_CUIT!$A$1:$D$2241,3,0)),"CUIT NO CARGADO") -> 0 | R29: =IFERROR(IF('Abr-26'!$F29="","-",VLOOKUP('Abr-26'!$F29,Lista_CUIT!$A$1:$D$2241,4,0)),"CUIT NO CARGADO") -> 0
B30: 46136 | C30: 1 | D30: 2 | E30: 4328 | F30: 30718133412 | G30: =IFERROR(IF('Abr-26'!$F30="","-",VLOOKUP('Abr-26'!$F30,Lista_CUIT!$A$1:$D$2241,2,0)),"CUIT NO CARGADO") -> FULL HOUSE TIENDA S.R.L. | H30: 293465.29 | I30: ='Abr-26'!$H30*0.21 -> 61627.711 | P30: =SUM('Abr-26'!$H30:$O30) -> 355093 | Q30: =IFERROR(IF('Abr-26'!$F30="","-",VLOOKUP('Abr-26'!$F30,Lista_CUIT!$A$1:$D$2241,3,0)),"CUIT NO CARGADO") -> 0 | R30: =IFERROR(IF('Abr-26'!$F30="","-",VLOOKUP('Abr-26'!$F30,Lista_CUIT!$A$1:$D$2241,4,0)),"CUIT NO CARGADO") -> 0
B31: 46136 | C31: 1 | D31: 100 | E31: 11979 | F31: 30562265844 | G31: =IFERROR(IF('Abr-26'!$F31="","-",VLOOKUP('Abr-26'!$F31,Lista_CUIT!$A$1:$D$2241,2,0)),"CUIT NO CARGADO") -> LA MADRILEÑA SOCIEDAD ANONIMA COMERCIAL INDUSTRIAL AGROPECUARIA FINANCIERA E INMOBILIARIA | H31: 99877.52 | I31: ='Abr-26'!$H31*0.21 -> 20974.279 | P31: =SUM('Abr-26'!$H31:$O31) -> 120851.8 | Q31: =IFERROR(IF('Abr-26'!$F31="","-",VLOOKUP('Abr-26'!$F31,Lista_CUIT!$A$1:$D$2241,3,0)),"CUIT NO CARGADO") -> Ropa de Trabajo | R31: =IFERROR(IF('Abr-26'!$F31="","-",VLOOKUP('Abr-26'!$F31,Lista_CUIT!$A$1:$D$2241,4,0)),"CUIT NO CARGADO") -> 0
B32: 46136 | C32: 1 | D32: 2 | E32: 1127 | F32: 30500805222 | G32: =IFERROR(IF('Abr-26'!$F32="","-",VLOOKUP('Abr-26'!$F32,Lista_CUIT!$A$1:$D$2241,2,0)),"CUIT NO CARGADO") -> KAVCIC SRL | H32: 1227160 | I32: ='Abr-26'!$H32*0.21 -> 257703.6 | P32: =SUM('Abr-26'!$H32:$O32) -> 1484863.6 | Q32: =IFERROR(IF('Abr-26'!$F32="","-",VLOOKUP('Abr-26'!$F32,Lista_CUIT!$A$1:$D$2241,3,0)),"CUIT NO CARGADO") -> Mercaderia | R32: =IFERROR(IF('Abr-26'!$F32="","-",VLOOKUP('Abr-26'!$F32,Lista_CUIT!$A$1:$D$2241,4,0)),"CUIT NO CARGADO") -> 0
B33: 46140 | C33: 1 | D33: 3 | E33: 34267 | F33: 33718350749 | G33: =IFERROR(IF('Abr-26'!$F33="","-",VLOOKUP('Abr-26'!$F33,Lista_CUIT!$A$1:$D$2241,2,0)),"CUIT NO CARGADO") -> MTL3 | H33: 14033.06 | I33: ='Abr-26'!$H33*0.21 -> 2946.9426 | P33: =SUM('Abr-26'!$H33:$O33) -> 16980.003 | Q33: =IFERROR(IF('Abr-26'!$F33="","-",VLOOKUP('Abr-26'!$F33,Lista_CUIT!$A$1:$D$2241,3,0)),"CUIT NO CARGADO") -> 0 | R33: =IFERROR(IF('Abr-26'!$F33="","-",VLOOKUP('Abr-26'!$F33,Lista_CUIT!$A$1:$D$2241,4,0)),"CUIT NO CARGADO") -> 0
B34: 46140 | C34: 1 | D34: 106 | E34: 944699 | F34: 30594494187 | G34: =IFERROR(IF('Abr-26'!$F34="","-",VLOOKUP('Abr-26'!$F34,Lista_CUIT!$A$1:$D$2241,2,0)),"CUIT NO CARGADO") -> FEDERAL EXPRESS CORPORATION | H34: 101880 | I34: ='Abr-26'!$H34*0.21 -> 21394.8 | O34: 495014.94 | P34: =SUM('Abr-26'!$H34:$O34) -> 618289.74 | Q34: =IFERROR(IF('Abr-26'!$F34="","-",VLOOKUP('Abr-26'!$F34,Lista_CUIT!$A$1:$D$2241,3,0)),"CUIT NO CARGADO") -> Mercaderia | R34: =IFERROR(IF('Abr-26'!$F34="","-",VLOOKUP('Abr-26'!$F34,Lista_CUIT!$A$1:$D$2241,4,0)),"CUIT NO CARGADO") -> 0
B35: 46140 | C35: 1 | D35: 443 | E35: 471995 | F35: 30546764040 | G35: =IFERROR(IF('Abr-26'!$F35="","-",VLOOKUP('Abr-26'!$F35,Lista_CUIT!$A$1:$D$2241,2,0)),"CUIT NO CARGADO") -> NESTLE ARG S.A | H35: 15702.48 | I35: ='Abr-26'!$H35*0.21 -> 3297.5208 | O35: 471.08 | P35: =SUM('Abr-26'!$H35:$O35) -> 19471.081 | Q35: =IFERROR(IF('Abr-26'!$F35="","-",VLOOKUP('Abr-26'!$F35,Lista_CUIT!$A$1:$D$2241,3,0)),"CUIT NO CARGADO") -> CATERING | R35: =IFERROR(IF('Abr-26'!$F35="","-",VLOOKUP('Abr-26'!$F35,Lista_CUIT!$A$1:$D$2241,4,0)),"CUIT NO CARGADO") -> 0
B36: 46141 | C36: 1 | D36: 7 | E36: 66133 | F36: 20372347296 | G36: =IFERROR(IF('Abr-26'!$F36="","-",VLOOKUP('Abr-26'!$F36,Lista_CUIT!$A$1:$D$2241,2,0)),"CUIT NO CARGADO") -> GHERTNER SEBASTIAN | H36: 79961.09 | K36: 8395.91 | P36: =SUM('Abr-26'!$H36:$O36) -> 88357 | Q36: =IFERROR(IF('Abr-26'!$F36="","-",VLOOKUP('Abr-26'!$F36,Lista_CUIT!$A$1:$D$2241,3,0)),"CUIT NO CARGADO") -> 0 | R36: =IFERROR(IF('Abr-26'!$F36="","-",VLOOKUP('Abr-26'!$F36,Lista_CUIT!$A$1:$D$2241,4,0)),"CUIT NO CARGADO") -> 0
B37: 46142 | C37: 1 | D37: 5 | E37: 114890 | F37: 30708166673 | G37: =IFERROR(IF('Abr-26'!$F37="","-",VLOOKUP('Abr-26'!$F37,Lista_CUIT!$A$1:$D$2241,2,0)),"CUIT NO CARGADO") -> SUMINISTROS WHITE S.A. | H37: 28924.79 | I37: ='Abr-26'!$H37*0.21 -> 6074.2059 | P37: =SUM('Abr-26'!$H37:$O37) -> 34998.996 | Q37: =IFERROR(IF('Abr-26'!$F37="","-",VLOOKUP('Abr-26'!$F37,Lista_CUIT!$A$1:$D$2241,3,0)),"CUIT NO CARGADO") -> 0 | R37: =IFERROR(IF('Abr-26'!$F37="","-",VLOOKUP('Abr-26'!$F37,Lista_CUIT!$A$1:$D$2241,4,0)),"CUIT NO CARGADO") -> 0
B38: 46135 | C38: 3 | D38: 122 | E38: 85443 | F38: 30594494187 | G38: =IFERROR(IF('Abr-26'!$F38="","-",VLOOKUP('Abr-26'!$F38,Lista_CUIT!$A$1:$D$2241,2,0)),"CUIT NO CARGADO") -> FEDERAL EXPRESS CORPORATION | H38: -99036 | I38: ='Abr-26'!$H38*0.21 -> -20797.56 | O38: -495014.94 | P38: =SUM('Abr-26'!$H38:$O38) -> -614848.5 | Q38: =IFERROR(IF('Abr-26'!$F38="","-",VLOOKUP('Abr-26'!$F38,Lista_CUIT!$A$1:$D$2241,3,0)),"CUIT NO CARGADO") -> Mercaderia | R38: =IFERROR(IF('Abr-26'!$F38="","-",VLOOKUP('Abr-26'!$F38,Lista_CUIT!$A$1:$D$2241,4,0)),"CUIT NO CARGADO") -> 0
G39: =IFERROR(IF('Abr-26'!$F39="","-",VLOOKUP('Abr-26'!$F39,Lista_CUIT!$A$1:$D$2241,2,0)),"CUIT NO CARGADO") -> - | I39: ='Abr-26'!$H39*0.21 -> 0 | P39: =SUM('Abr-26'!$H39:$O39) -> 0 | Q39: =IFERROR(IF('Abr-26'!$F39="","-",VLOOKUP('Abr-26'!$F39,Lista_CUIT!$A$1:$D$2241,3,0)),"CUIT NO CARGADO") -> - | R39: =IFERROR(IF('Abr-26'!$F39="","-",VLOOKUP('Abr-26'!$F39,Lista_CUIT!$A$1:$D$2241,4,0)),"CUIT NO CARGADO") -> -
B40: Total | H40: =SUBTOTAL(109,'Abr-26'!$H$9:$H$39) -> 4470165.3 | I40: =SUBTOTAL(109,'Abr-26'!$I$9:$I$39) -> 670181.4 | J40: =SUBTOTAL(109,'Abr-26'!$J$9:$J$39) -> 0 | K40: =SUBTOTAL(109,'Abr-26'!$K$9:$K$39) -> 134276.66 | L40: =SUBTOTAL(109,'Abr-26'!$L$9:$L$39) -> 0 | M40: =SUBTOTAL(109,'Abr-26'!$M$9:$M$39) -> 0 | N40: =SUBTOTAL(109,'Abr-26'!$N$9:$N$39) -> 0 | O40: =SUBTOTAL(109,'Abr-26'!$O$9:$O$39) -> 1600923.2 | P40: =SUBTOTAL(109,'Abr-26'!$P$9:$P$39) -> 6875546.6
D45: LIQUIDACION EXTRACTOS BANCARIOS-TARJETAS
D46: FECHA | E46: NRO CPTE | F46: BANCO | G46: NETO | H46: IVA 21% | I46: IVA 10,5% | J46: RET IIBB CABA | K46: PERC IVA | L46: PERC IIBB | M46: total
F47: CREDICOOP | G47: =57838.46/0.21 -> 275421.24 | H47: ='Abr-26'!$G47*0.21 -> 57838.46 | K47: 8172.64 | M47: ='Abr-26'!$G47+'Abr-26'!$H47+'Abr-26'!$I47+'Abr-26'!$J47+'Abr-26'!$K47 -> 341432.34
H48: ='Abr-26'!$G48*0.21 -> 0 | M48: ='Abr-26'!$G48+'Abr-26'!$H48+'Abr-26'!$I48+'Abr-26'!$J48+'Abr-26'!$K48 -> 0
H49: ='Abr-26'!$G49*0.21 -> 0 | M49: ='Abr-26'!$G49+'Abr-26'!$H49+'Abr-26'!$I49+'Abr-26'!$J49+'Abr-26'!$K49 -> 0
H50: ='Abr-26'!$G50*0.21 -> 0 | M50: ='Abr-26'!$G50+'Abr-26'!$H50+'Abr-26'!$I50+'Abr-26'!$J50+'Abr-26'!$K50 -> 0
H51: ='Abr-26'!$G51*0.21 -> 0 | M51: ='Abr-26'!$G51+'Abr-26'!$H51+'Abr-26'!$I51+'Abr-26'!$J51+'Abr-26'!$K51 -> 0
H52: ='Abr-26'!$G52*0.21 -> 0 | M52: ='Abr-26'!$G52+'Abr-26'!$H52+'Abr-26'!$I52+'Abr-26'!$J52+'Abr-26'!$K52 -> 0
H53: ='Abr-26'!$G53*0.21 -> 0 | M53: ='Abr-26'!$G53+'Abr-26'!$H53+'Abr-26'!$I53+'Abr-26'!$J53+'Abr-26'!$K53 -> 0
H54: ='Abr-26'!$G54*0.21 -> 0 | M54: ='Abr-26'!$G54+'Abr-26'!$H54+'Abr-26'!$I54+'Abr-26'!$J54+'Abr-26'!$K54 -> 0
H55: ='Abr-26'!$G55*0.21 -> 0 | M55: ='Abr-26'!$G55+'Abr-26'!$H55+'Abr-26'!$I55+'Abr-26'!$J55+'Abr-26'!$K55 -> 0
H56: ='Abr-26'!$G56*0.21 -> 0 | M56: ='Abr-26'!$G56+'Abr-26'!$H56+'Abr-26'!$I56+'Abr-26'!$J56+'Abr-26'!$K56 -> 0
D57: Total | G57: =SUBTOTAL(109,'Abr-26'!$G$47:$G$56) -> 275421.24 | H57: =SUBTOTAL(109,'Abr-26'!$H$47:$H$56) -> 57838.46 | I57: =SUBTOTAL(109,'Abr-26'!$I$47:$I$56) -> 0 | J57: =SUBTOTAL(109,'Abr-26'!$J$47:$J$56) -> 0 | K57: =SUBTOTAL(109,'Abr-26'!$K$47:$K$56) -> 8172.64 | L57: =SUBTOTAL(109,'Abr-26'!$L$47:$L$56) -> 0
H58: TOTAL: | I58: =SUM('Abr-26'!$H$57:$I$57) -> 57838.46 | J58: > ya esta sumado al total
D61: FACTURAS C
D62: FECHA | E62: PTO VTA | F62: FC Nº | G62: CUIT | H62: RAZON SOCIAL | I62: TOTAL | J62: TIPO DE GASTO | K62: Provincia
D63: 46113 | E63: 4 | F63: 157 | G63: 20086277523 | H63: =IFERROR(IF('Abr-26'!$G63="","-",VLOOKUP('Abr-26'!$G63,Lista_CUIT!$A$1:$D$2241,2,0)),"CUIT NO CARGADO") -> ESTUDIO BOTINDARI | I63: 520000 | J63: =IFERROR(IF('Abr-26'!$G63="","-",VLOOKUP('Abr-26'!$G63,Lista_CUIT!$A$1:$D$2241,3,0)),"CUIT NO CARGADO") -> Honorarios Contables | K63: =IFERROR(IF('Abr-26'!$G63="","-",VLOOKUP('Abr-26'!$G63,Lista_CUIT!$A$1:$D$2241,4,0)),"CUIT NO CARGADO") -> 0
D64: 46113 | E64: 1 | F64: 193 | G64: 20389908569 | H64: =IFERROR(IF('Abr-26'!$G64="","-",VLOOKUP('Abr-26'!$G64,Lista_CUIT!$A$1:$D$2241,2,0)),"CUIT NO CARGADO") -> BOTINDARI JUAN IGNACIO | I64: 150000 | J64: =IFERROR(IF('Abr-26'!$G64="","-",VLOOKUP('Abr-26'!$G64,Lista_CUIT!$A$1:$D$2241,3,0)),"CUIT NO CARGADO") -> Honorarios Contables | K64: =IFERROR(IF('Abr-26'!$G64="","-",VLOOKUP('Abr-26'!$G64,Lista_CUIT!$A$1:$D$2241,4,0)),"CUIT NO CARGADO") -> 0
D65: 46113 | E65: 2 | F65: 194 | G65: 20136544625 | H65: =IFERROR(IF('Abr-26'!$G65="","-",VLOOKUP('Abr-26'!$G65,Lista_CUIT!$A$1:$D$2241,2,0)),"CUIT NO CARGADO") -> RODRIGUEZ DE LA FUEN HECTOR MARCELO | I65: 1395000 | J65: =IFERROR(IF('Abr-26'!$G65="","-",VLOOKUP('Abr-26'!$G65,Lista_CUIT!$A$1:$D$2241,3,0)),"CUIT NO CARGADO") -> Honorarios Admin | K65: =IFERROR(IF('Abr-26'!$G65="","-",VLOOKUP('Abr-26'!$G65,Lista_CUIT!$A$1:$D$2241,4,0)),"CUIT NO CARGADO") -> 0
D66: 46118 | E66: 2 | F66: 31 | G66: 23118167279 | H66: =IFERROR(IF('Abr-26'!$G66="","-",VLOOKUP('Abr-26'!$G66,Lista_CUIT!$A$1:$D$2241,2,0)),"CUIT NO CARGADO") -> ABELEDO ENRIQUE JUAN | I66: 2835000 | J66: =IFERROR(IF('Abr-26'!$G66="","-",VLOOKUP('Abr-26'!$G66,Lista_CUIT!$A$1:$D$2241,3,0)),"CUIT NO CARGADO") -> Honorarios Admin | K66: =IFERROR(IF('Abr-26'!$G66="","-",VLOOKUP('Abr-26'!$G66,Lista_CUIT!$A$1:$D$2241,4,0)),"CUIT NO CARGADO") -> 0
D67: 46119 | E67: 2 | F67: 312 | G67: 27173820866 | H67: =IFERROR(IF('Abr-26'!$G67="","-",VLOOKUP('Abr-26'!$G67,Lista_CUIT!$A$1:$D$2241,2,0)),"CUIT NO CARGADO") -> FREIER SANDRA DANIELA | I67: 1610000 | J67: =IFERROR(IF('Abr-26'!$G67="","-",VLOOKUP('Abr-26'!$G67,Lista_CUIT!$A$1:$D$2241,3,0)),"CUIT NO CARGADO") -> Honorarios Prof | K67: =IFERROR(IF('Abr-26'!$G67="","-",VLOOKUP('Abr-26'!$G67,Lista_CUIT!$A$1:$D$2241,4,0)),"CUIT NO CARGADO") -> 0
D68: 46125 | E68: 1 | F68: 131 | G68: 20341465134 | H68: =IFERROR(IF('Abr-26'!$G68="","-",VLOOKUP('Abr-26'!$G68,Lista_CUIT!$A$1:$D$2241,2,0)),"CUIT NO CARGADO") -> ABELEDO AGUSTIN ENRIQUE | I68: 3430000 | J68: =IFERROR(IF('Abr-26'!$G68="","-",VLOOKUP('Abr-26'!$G68,Lista_CUIT!$A$1:$D$2241,3,0)),"CUIT NO CARGADO") -> Mantenimiento | K68: =IFERROR(IF('Abr-26'!$G68="","-",VLOOKUP('Abr-26'!$G68,Lista_CUIT!$A$1:$D$2241,4,0)),"CUIT NO CARGADO") -> CABA
D69: 46128 | E69: 10 | F69: 95996 | G69: 30525346389 | H69: =IFERROR(IF('Abr-26'!$G69="","-",VLOOKUP('Abr-26'!$G69,Lista_CUIT!$A$1:$D$2241,2,0)),"CUIT NO CARGADO") -> MORIXE HERMANOS SOCIEDAD ANONIMA COMERCIAL E INDUSTRIAL | I69: 8500 | J69: =IFERROR(IF('Abr-26'!$G69="","-",VLOOKUP('Abr-26'!$G69,Lista_CUIT!$A$1:$D$2241,3,0)),"CUIT NO CARGADO") -> 0 | K69: =IFERROR(IF('Abr-26'!$G69="","-",VLOOKUP('Abr-26'!$G69,Lista_CUIT!$A$1:$D$2241,4,0)),"CUIT NO CARGADO") -> 0
H70: =IFERROR(IF('Abr-26'!$G70="","-",VLOOKUP('Abr-26'!$G70,Lista_CUIT!$A$1:$D$2241,2,0)),"CUIT NO CARGADO") -> - | J70: =IFERROR(IF('Abr-26'!$G70="","-",VLOOKUP('Abr-26'!$G70,Lista_CUIT!$A$1:$D$2241,3,0)),"CUIT NO CARGADO") -> - | K70: =IFERROR(IF('Abr-26'!$G70="","-",VLOOKUP('Abr-26'!$G70,Lista_CUIT!$A$1:$D$2241,4,0)),"CUIT NO CARGADO") -> -
H71: =IFERROR(IF('Abr-26'!$G71="","-",VLOOKUP('Abr-26'!$G71,Lista_CUIT!$A$1:$D$2241,2,0)),"CUIT NO CARGADO") -> - | J71: =IFERROR(IF('Abr-26'!$G71="","-",VLOOKUP('Abr-26'!$G71,Lista_CUIT!$A$1:$D$2241,3,0)),"CUIT NO CARGADO") -> - | K71: =IFERROR(IF('Abr-26'!$G71="","-",VLOOKUP('Abr-26'!$G71,Lista_CUIT!$A$1:$D$2241,4,0)),"CUIT NO CARGADO") -> -
H72: =IFERROR(IF('Abr-26'!$G72="","-",VLOOKUP('Abr-26'!$G72,Lista_CUIT!$A$1:$D$2241,2,0)),"CUIT NO CARGADO") -> - | J72: =IFERROR(IF('Abr-26'!$G72="","-",VLOOKUP('Abr-26'!$G72,Lista_CUIT!$A$1:$D$2241,3,0)),"CUIT NO CARGADO") -> - | K72: =IFERROR(IF('Abr-26'!$G72="","-",VLOOKUP('Abr-26'!$G72,Lista_CUIT!$A$1:$D$2241,4,0)),"CUIT NO CARGADO") -> -
H73: =IFERROR(IF('Abr-26'!$G73="","-",VLOOKUP('Abr-26'!$G73,Lista_CUIT!$A$1:$D$2241,2,0)),"CUIT NO CARGADO") -> - | J73: =IFERROR(IF('Abr-26'!$G73="","-",VLOOKUP('Abr-26'!$G73,Lista_CUIT!$A$1:$D$2241,3,0)),"CUIT NO CARGADO") -> - | K73: =IFERROR(IF('Abr-26'!$G73="","-",VLOOKUP('Abr-26'!$G73,Lista_CUIT!$A$1:$D$2241,4,0)),"CUIT NO CARGADO") -> -
H74: =IFERROR(IF('Abr-26'!$G74="","-",VLOOKUP('Abr-26'!$G74,Lista_CUIT!$A$1:$D$2241,2,0)),"CUIT NO CARGADO") -> - | J74: =IFERROR(IF('Abr-26'!$G74="","-",VLOOKUP('Abr-26'!$G74,Lista_CUIT!$A$1:$D$2241,3,0)),"CUIT NO CARGADO") -> - | K74: =IFERROR(IF('Abr-26'!$G74="","-",VLOOKUP('Abr-26'!$G74,Lista_CUIT!$A$1:$D$2241,4,0)),"CUIT NO CARGADO") -> -
H75: =IFERROR(IF('Abr-26'!$G75="","-",VLOOKUP('Abr-26'!$G75,Lista_CUIT!$A$1:$D$2241,2,0)),"CUIT NO CARGADO") -> - | J75: =IFERROR(IF('Abr-26'!$G75="","-",VLOOKUP('Abr-26'!$G75,Lista_CUIT!$A$1:$D$2241,3,0)),"CUIT NO CARGADO") -> - | K75: =IFERROR(IF('Abr-26'!$G75="","-",VLOOKUP('Abr-26'!$G75,Lista_CUIT!$A$1:$D$2241,4,0)),"CUIT NO CARGADO") -> -
H76: =IFERROR(IF('Abr-26'!$G76="","-",VLOOKUP('Abr-26'!$G76,Lista_CUIT!$A$1:$D$2241,2,0)),"CUIT NO CARGADO") -> - | J76: =IFERROR(IF('Abr-26'!$G76="","-",VLOOKUP('Abr-26'!$G76,Lista_CUIT!$A$1:$D$2241,3,0)),"CUIT NO CARGADO") -> - | K76: =IFERROR(IF('Abr-26'!$G76="","-",VLOOKUP('Abr-26'!$G76,Lista_CUIT!$A$1:$D$2241,4,0)),"CUIT NO CARGADO") -> -
H77: =IFERROR(IF('Abr-26'!$G77="","-",VLOOKUP('Abr-26'!$G77,Lista_CUIT!$A$1:$D$2241,2,0)),"CUIT NO CARGADO") -> - | J77: =IFERROR(IF('Abr-26'!$G77="","-",VLOOKUP('Abr-26'!$G77,Lista_CUIT!$A$1:$D$2241,3,0)),"CUIT NO CARGADO") -> - | K77: =IFERROR(IF('Abr-26'!$G77="","-",VLOOKUP('Abr-26'!$G77,Lista_CUIT!$A$1:$D$2241,4,0)),"CUIT NO CARGADO") -> -
H78: =IFERROR(IF('Abr-26'!$G78="","-",VLOOKUP('Abr-26'!$G78,Lista_CUIT!$A$1:$D$2241,2,0)),"CUIT NO CARGADO") -> - | J78: =IFERROR(IF('Abr-26'!$G78="","-",VLOOKUP('Abr-26'!$G78,Lista_CUIT!$A$1:$D$2241,3,0)),"CUIT NO CARGADO") -> - | K78: =IFERROR(IF('Abr-26'!$G78="","-",VLOOKUP('Abr-26'!$G78,Lista_CUIT!$A$1:$D$2241,4,0)),"CUIT NO CARGADO") -> -
H79: =IFERROR(IF('Abr-26'!$G79="","-",VLOOKUP('Abr-26'!$G79,Lista_CUIT!$A$1:$D$2241,2,0)),"CUIT NO CARGADO") -> - | J79: =IFERROR(IF('Abr-26'!$G79="","-",VLOOKUP('Abr-26'!$G79,Lista_CUIT!$A$1:$D$2241,3,0)),"CUIT NO CARGADO") -> - | K79: =IFERROR(IF('Abr-26'!$G79="","-",VLOOKUP('Abr-26'!$G79,Lista_CUIT!$A$1:$D$2241,4,0)),"CUIT NO CARGADO") -> -
D80: Total | I80: =SUBTOTAL(109,'Abr-26'!$I$63:$I$79) -> 9948500
B82: LIBRO IVA VENTAS | K82: =N1 -> 45748
B84: VENTAS "A"
B85: FECHA | C85: TIPO | D85: PTO VENTA | E85: Nº FACTURA | F85: CUIT | G85: RAZON SOCIAL | H85: IMPORTE NETO | I85: IVA 21% | J85: IVA 10,5% | K85: EXENTO | L85: TOTAL | M85: Provincia
B86: 46113 | C86: 1 | D86: 3 | E86: 320 | F86: 30638318470 | G86: =IFERROR(IF('Abr-26'!$F86="","-",VLOOKUP('Abr-26'!$F86,Lista_CUIT!$A$1:$D$2241,2,0)),"CUIT NO CARGADO") -> DELTA COMPRESION S R L | H86: 29750875 | J86: 3123848.9 | L86: =SUM('Abr-26'!$H86:$K86) -> 32874724
B87: 46113 | C87: 1 | D87: 3 | E87: 317 | F87: 33717088269 | G87: =IFERROR(IF('Abr-26'!$F87="","-",VLOOKUP('Abr-26'!$F87,Lista_CUIT!$A$1:$D$2241,2,0)),"CUIT NO CARGADO") -> NEXT SERVICE GNC S.R.L. | H87: 15093861 | I87: 3169710.8 | L87: =SUM('Abr-26'!$H87:$K87) -> 18263572
B88: 46113 | C88: 1 | D88: 3 | E88: 318 | F88: 20266916680 | G88: =IFERROR(IF('Abr-26'!$F88="","-",VLOOKUP('Abr-26'!$F88,Lista_CUIT!$A$1:$D$2241,2,0)),"CUIT NO CARGADO") -> SPRENGLER FERNANDO JAVIER | H88: 15033500 | I88: 88515 | J88: 1534260 | L88: =SUM('Abr-26'!$H88:$K88) -> 16656275
B89: 46113 | C89: 1 | D89: 3 | E89: 319 | F89: 30628274327 | G89: =IFERROR(IF('Abr-26'!$F89="","-",VLOOKUP('Abr-26'!$F89,Lista_CUIT!$A$1:$D$2241,2,0)),"CUIT NO CARGADO") -> AGIRA S A | H89: 12841700 | J89: 1348378.5 | L89: =SUM('Abr-26'!$H89:$K89) -> 14190078
B90: 46119 | C90: 1 | D90: 3 | E90: 321 | F90: 30718629418 | G90: =IFERROR(IF('Abr-26'!$F90="","-",VLOOKUP('Abr-26'!$F90,Lista_CUIT!$A$1:$D$2241,2,0)),"CUIT NO CARGADO") -> ALTIUS S.R.L. | H90: 247625 | I90: 52001.25 | L90: =SUM('Abr-26'!$H90:$K90) -> 299626.25
B91: 46120 | C91: 1 | D91: 3 | E91: 322 | F91: 27250312437 | G91: =IFERROR(IF('Abr-26'!$F91="","-",VLOOKUP('Abr-26'!$F91,Lista_CUIT!$A$1:$D$2241,2,0)),"CUIT NO CARGADO") -> PONCE CECILIA LEONOR | H91: 421500 | I91: 88515 | L91: =SUM('Abr-26'!$H91:$K91) -> 510015
B92: 46129 | C92: 3 | D92: 3 | E92: 37 | F92: 30638318470 | G92: =IFERROR(IF('Abr-26'!$F92="","-",VLOOKUP('Abr-26'!$F92,Lista_CUIT!$A$1:$D$2241,2,0)),"CUIT NO CARGADO") -> DELTA COMPRESION S R L | H92: -386750.08 | I92: -81217.52 | L92: =SUM('Abr-26'!$H92:$K92) -> -467967.6
B93: 46133 | C93: 1 | D93: 3 | E93: 323 | F93: 30712459227 | G93: =IFERROR(IF('Abr-26'!$F93="","-",VLOOKUP('Abr-26'!$F93,Lista_CUIT!$A$1:$D$2241,2,0)),"CUIT NO CARGADO") -> DIAGONALES Y BOULEVARES S.A. | H93: 8050000 | J93: 845250 | L93: =SUM('Abr-26'!$H93:$K93) -> 8895250
B94: 46134 | C94: 1 | D94: 3 | E94: 324 | F94: 30716041596 | G94: =IFERROR(IF('Abr-26'!$F94="","-",VLOOKUP('Abr-26'!$F94,Lista_CUIT!$A$1:$D$2241,2,0)),"CUIT NO CARGADO") -> EXA COMPRESION S.R.L. | H94: 1400000 | I94: 294000 | L94: =SUM('Abr-26'!$H94:$K94) -> 1694000
G95: =IFERROR(IF('Abr-26'!$F95="","-",VLOOKUP('Abr-26'!$F95,Lista_CUIT!$A$1:$D$2241,2,0)),"CUIT NO CARGADO") -> - | L95: =SUM('Abr-26'!$H95:$K95) -> 0
B96: Total | H96: =SUBTOTAL(109,'Abr-26'!$H$86:$H$95) -> 82452311 | I96: =SUBTOTAL(109,'Abr-26'!$I$86:$I$95) -> 3611524.6 | J96: =SUBTOTAL(109,'Abr-26'!$J$86:$J$95) -> 6851737.4 | K96: =SUBTOTAL(109,'Abr-26'!$K$86:$K$95) -> 0 | L96: =SUBTOTAL(109,'Abr-26'!$L$86:$L$95) -> 92915573 | M96: =SUBTOTAL(103,'Abr-26'!$M$86:$M$95) -> 0
B98: VENTAS "B"
B99: FECHA | C99: TIPO | D99: PTO VENTA | E99: Nº FACTURA | F99: CUIT | G99: RAZON SOCIAL | H99: IMPORTE NETO | I99: IVA 21% | J99: IVA 10,5% | K99: EXENTO | L99: TOTAL | M99: Provincia
G100: =IFERROR(IF('Abr-26'!$F100="","-",VLOOKUP('Abr-26'!$F100,Lista_CUIT!$A$1:$D$2241,2,0)),"CUIT NO CARGADO") -> -
B106: Total | H106: =SUBTOTAL(109,'Abr-26'!$H$100:$H$105) -> 0 | I106: =SUBTOTAL(109,'Abr-26'!$I$100:$I$105) -> 0 | J106: =SUBTOTAL(109,'Abr-26'!$J$100:$J$105) -> 0 | K106: =SUBTOTAL(109,'Abr-26'!$K$100:$K$105) -> 0 | L106: =SUBTOTAL(109,'Abr-26'!$L$100:$L$105) -> 0 | M106: =SUBTOTAL(103,'Abr-26'!$M$100:$M$105) -> 0
B109: VENTAS "E"
B110: FECHA | C110: TIPO | D110: PTO VENTA | E110: Nº FACTURA | F110: CUIT | G110: RAZON SOCIAL | H110: USD | I110: Columna2 | J110: Columna1 | K110: TIPO DE CAMBIO2 | L110: TOTAL | M110: Provincia
B111: 46139 | D111: 30 | E111: 134 | F111: 55000000050 | G111: =IFERROR(IF('Abr-26'!$F111="","-",VLOOKUP('Abr-26'!$F111,Lista_CUIT!$A$1:$D$2241,2,0)),"CUIT NO CARGADO") -> GAS FUTURO SISTEMAS DE COMPRESSÃO LTDA | H111: 1920 | K111: 1399.5 | L111: ='Abr-26'!$H111*'Abr-26'!$K111 -> 2687040
G112: =IFERROR(IF('Abr-26'!$F112="","-",VLOOKUP('Abr-26'!$F112,Lista_CUIT!$A$1:$D$2241,2,0)),"CUIT NO CARGADO") -> - | L112: ='Abr-26'!$H112*'Abr-26'!$K112 -> 0
G113: =IFERROR(IF('Abr-26'!$F113="","-",VLOOKUP('Abr-26'!$F113,Lista_CUIT!$A$1:$D$2241,2,0)),"CUIT NO CARGADO") -> -
G114: =IFERROR(IF('Abr-26'!$F114="","-",VLOOKUP('Abr-26'!$F114,Lista_CUIT!$A$1:$D$2241,2,0)),"CUIT NO CARGADO") -> - | I114: ='Abr-26'!$H114*0.21 -> 0
B115: Total | H115: =SUBTOTAL(109,'Abr-26'!$H$111:$H$114) -> 1920 | I115: =SUBTOTAL(109,'Abr-26'!$I$111:$I$114) -> 0 | J115: =SUBTOTAL(109,'Abr-26'!$J$111:$J$114) -> 0 | K115: =SUBTOTAL(109,'Abr-26'!$K$111:$K$114) -> 1399.5 | L115: =SUBTOTAL(109,'Abr-26'!$L$111:$L$114) -> 2687040 | M115: =SUBTOTAL(103,'Abr-26'!$M$111:$M$114) -> 0
C117: RETENCIONES
C118: FECHA | D118: COMP Nº | E118: Columna1 | F118: CUIT | G118: RAZON SOCIAL | H118: Ganancias | I118: IVA | J118: SUSS | K118: IIBB BSAS | L118: IIBB CABA
G119: =IFERROR(IF('Abr-26'!$F119="","-",VLOOKUP('Abr-26'!$F119,Lista_CUIT!$A$1:$D$2241,2,0)),"CUIT NO CARGADO") -> -
G120: =IFERROR(IF('Abr-26'!$F120="","-",VLOOKUP('Abr-26'!$F120,Lista_CUIT!$A$1:$D$2241,2,0)),"CUIT NO CARGADO") -> -
G121: =IFERROR(IF('Abr-26'!$F121="","-",VLOOKUP('Abr-26'!$F121,Lista_CUIT!$A$1:$D$2241,2,0)),"CUIT NO CARGADO") -> -
...

Sheet May-26
B1: LIBRO IVA COMPRAS | G1: ='Abr-26'!G1:M1 -> CORITEC S. R. L. | N1: 45778
B3: TOTAL COMPRAS | G3: TOTAL CREDITO FISCAL | J3: TOTAL VENTAS NETAS | M3: TOTAL DEBITO FISCAL | P3: RESULTADO
B4: =SUM('May-26'!$H$30)+'May-26'!$G$43 -> 6550641.4 | G4: ='May-26'!$I$30+'May-26'!$J$30+'May-26'!$K$30+'May-26'!$H$43+'May-26'!$I$43 -> 1377661.8 | J4: =SUM('May-26'!$H$81+'May-26'!$H$93) -> 1.2597229e+08 | M4: =SUM('May-26'!$I$81+'May-26'!$J$81+'May-26'!$I$93+'May-26'!$J$93) -> 15754768 | P4: =G4-M4 -> -14377106
B8: FECHA | C8: TIPO | D8: PTO VTA | E8: NRO. CPTE | F8: CUIT | G8: RAZON SOCIAL | H8: NETO GRAVADO | I8: IVA 21 % | J8: IVA 27% | K8: IVA 10,5% | L8: PERC. IVA | M8: PERC IIBB BS AS | N8: PERC. IIBB CABA | O8: Otros / No Grav. | P8: TOTAL | Q8: Tipo de Gasto | R8: Provincia
B9: 45778 | C9: 1 | D9: 3 | E9: 265149 | F9: 30707135596 | G9: =IFERROR(IF('May-26'!$F9="","-",VLOOKUP('May-26'!$F9,Lista_CUIT!$A$1:$D$2241,2,0)),"CUIT NO CARGADO") -> CITILAN ARGENTINA S.A. | H9: 28785 | I9: =IF('May-26'!$H9="","",'May-26'!$H9*0.21) -> 6044.85 | P9: =SUM('May-26'!$H9:$O9) -> 34829.85 | Q9: =IFERROR(IF('May-26'!$F9="","-",VLOOKUP('May-26'!$F9,Lista_CUIT!$A$1:$D$2241,3,0)),"CUIT NO CARGADO") -> Telefonia | R9: =IFERROR(IF('May-26'!$F9="","-",VLOOKUP('May-26'!$F9,Lista_CUIT!$A$1:$D$2241,4,0)),"CUIT NO CARGADO") -> 0
B10: 45778 | C10: 1 | D10: 3 | E10: 857 | F10: 30715402765 | G10: =IFERROR(IF('May-26'!$F10="","-",VLOOKUP('May-26'!$F10,Lista_CUIT!$A$1:$D$2241,2,0)),"CUIT NO CARGADO") -> RIO 265 S.R.L. | H10: 90909.1 | I10: =IF('May-26'!$H10="","",'May-26'!$H10*0.21) -> 19090.911 | P10: =SUM('May-26'!$H10:$O10) -> 110000.01 | Q10: =IFERROR(IF('May-26'!$F10="","-",VLOOKUP('May-26'!$F10,Lista_CUIT!$A$1:$D$2241,3,0)),"CUIT NO CARGADO") -> GASTOS VARIOS | R10: =IFERROR(IF('May-26'!$F10="","-",VLOOKUP('May-26'!$F10,Lista_CUIT!$A$1:$D$2241,4,0)),"CUIT NO CARGADO") -> 0
B11: 45782 | C11: 1 | D11: 2 | E11: 864 | F11: 20296550184 | G11: =IFERROR(IF('May-26'!$F11="","-",VLOOKUP('May-26'!$F11,Lista_CUIT!$A$1:$D$2241,2,0)),"CUIT NO CARGADO") -> COSTA DIEGO ALEJANDRO | H11: 763250 | I11: =IF('May-26'!$H11="","",'May-26'!$H11*0.21) -> 160282.5 | P11: =SUM('May-26'!$H11:$O11) -> 923532.5 | Q11: =IFERROR(IF('May-26'!$F11="","-",VLOOKUP('May-26'!$F11,Lista_CUIT!$A$1:$D$2241,3,0)),"CUIT NO CARGADO") -> Mat. Prima | R11: =IFERROR(IF('May-26'!$F11="","-",VLOOKUP('May-26'!$F11,Lista_CUIT!$A$1:$D$2241,4,0)),"CUIT NO CARGADO") -> 0
B12: 45784 | C12: 1 | D12: 2 | E12: 213 | F12: 20125142851 | G12: =IFERROR(IF('May-26'!$F12="","-",VLOOKUP('May-26'!$F12,Lista_CUIT!$A$1:$D$2241,2,0)),"CUIT NO CARGADO") -> FEDERICI NICOLAS JOSE | H12: 2228424.5 | I12: =IF('May-26'!$H12="","",'May-26'!$H12*0.21) -> 467969.14 | P12: =SUM('May-26'!$H12:$O12) -> 2696393.6 | Q12: =IFERROR(IF('May-26'!$F12="","-",VLOOKUP('May-26'!$F12,Lista_CUIT!$A$1:$D$2241,3,0)),"CUIT NO CARGADO") -> INSUMO | R12: =IFERROR(IF('May-26'!$F12="","-",VLOOKUP('May-26'!$F12,Lista_CUIT!$A$1:$D$2241,4,0)),"CUIT NO CARGADO") -> 0
B13: 45788 | C13: 1 | D13: 2466 | E13: 789845 | F13: 30678814357 | G13: =IFERROR(IF('May-26'!$F13="","-",VLOOKUP('May-26'!$F13,Lista_CUIT!$A$1:$D$2241,2,0)),"CUIT NO CARGADO") -> TELEFONICA MOVILES ARG | H13: 33785 | J13: 9121.95 | L13: 1013.55 | O13: 1778.14 | P13: =SUM('May-26'!$H13:$O13) -> 45698.64 | Q13: =IFERROR(IF('May-26'!$F13="","-",VLOOKUP('May-26'!$F13,Lista_CUIT!$A$1:$D$2241,3,0)),"CUIT NO CARGADO") -> Telefonia | R13: =IFERROR(IF('May-26'!$F13="","-",VLOOKUP('May-26'!$F13,Lista_CUIT!$A$1:$D$2241,4,0)),"CUIT NO CARGADO") -> 0
B14: 45792 | C14: 1 | D14: 5 | E14: 23382 | F14: 30716006391 | G14: =IFERROR(IF('May-26'!$F14="","-",VLOOKUP('May-26'!$F14,Lista_CUIT!$A$1:$D$2241,2,0)),"CUIT NO CARGADO") -> ALLISING | H14: 31885.95 | I14: =IF('May-26'!$H14="","",'May-26'!$H14*0.21) -> 6696.0495 | P14: =SUM('May-26'!$H14:$O14) -> 38581.999 | Q14: =IFERROR(IF('May-26'!$F14="","-",VLOOKUP('May-26'!$F14,Lista_CUIT!$A$1:$D$2241,3,0)),"CUIT NO CARGADO") -> GASTOS VARIOS | R14: =IFERROR(IF('May-26'!$F14="","-",VLOOKUP('May-26'!$F14,Lista_CUIT!$A$1:$D$2241,4,0)),"CUIT NO CARGADO") -> 0
B15: 45793 | C15: 1 | D15: 106 | E15: 841105 | F15: 30594494187 | G15: =IFERROR(IF('May-26'!$F15="","-",VLOOKUP('May-26'!$F15,Lista_CUIT!$A$1:$D$2241,2,0)),"CUIT NO CARGADO") -> FEDERAL EXPRESS CORPORATION | H15: 0 | I15: =IF('May-26'!$H15="","",'May-26'!$H15*0.21) -> 0 | O15: 581628.9 | P15: =SUM('May-26'!$H15:$O15) -> 581628.9 | Q15: =IFERROR(IF('May-26'!$F15="","-",VLOOKUP('May-26'!$F15,Lista_CUIT!$A$1:$D$2241,3,0)),"CUIT NO CARGADO") -> Mercaderia | R15: =IFERROR(IF('May-26'!$F15="","-",VLOOKUP('May-26'!$F15,Lista_CUIT!$A$1:$D$2241,4,0)),"CUIT NO CARGADO") -> 0
B16: 45797 | C16: 1 | D16: 4 | E16: 108370 | F16: 30559932236 | G16: =IFERROR(IF('May-26'!$F16="","-",VLOOKUP('May-26'!$F16,Lista_CUIT!$A$1:$D$2241,2,0)),"CUIT NO CARGADO") -> ELECTRONICA ELEMON S A | H16: 225187.46 | I16: =IF('May-26'!$H16="","",'May-26'!$H16*0.21) -> 47289.367 | P16: =SUM('May-26'!$H16:$O16) -> 272476.83 | Q16: =IFERROR(IF('May-26'!$F16="","-",VLOOKUP('May-26'!$F16,Lista_CUIT!$A$1:$D$2241,3,0)),"CUIT NO CARGADO") -> Mat. Prima | R16: =IFERROR(IF('May-26'!$F16="","-",VLOOKUP('May-26'!$F16,Lista_CUIT!$A$1:$D$2241,4,0)),"CUIT NO CARGADO") -> 0
B17: 45797 | C17: 1 | D17: 1 | E17: 813 | F17: 30717231135 | G17: =IFERROR(IF('May-26'!$F17="","-",VLOOKUP('May-26'!$F17,Lista_CUIT!$A$1:$D$2241,2,0)),"CUIT NO CARGADO") -> WAREHOUSE ARGENTINA S.A.S. | H17: 125619.86 | I17: =IF('May-26'!$H17="","",'May-26'!$H17*0.21) -> 26380.171 | P17: =SUM('May-26'!$H17:$O17) -> 152000.03 | Q17: =IFERROR(IF('May-26'!$F17="","-",VLOOKUP('May-26'!$F17,Lista_CUIT!$A$1:$D$2241,3,0)),"CUIT NO CARGADO") -> INSUMO | R17: =IFERROR(IF('May-26'!$F17="","-",VLOOKUP('May-26'!$F17,Lista_CUIT!$A$1:$D$2241,4,0)),"CUIT NO CARGADO") -> 0
B18: 45799 | C18: 1 | D18: 251 | E18: 4102 | F18: 30710276273 | G18: =IFERROR(IF('May-26'!$F18="","-",VLOOKUP('May-26'!$F18,Lista_CUIT!$A$1:$D$2241,2,0)),"CUIT NO CARGADO") -> SEDEX ARGENTINA SA | H18: 15206.62 | I18: =IF('May-26'!$H18="","",'May-26'!$H18*0.21) -> 3193.3902 | P18: =SUM('May-26'!$H18:$O18) -> 18400.01 | Q18: =IFERROR(IF('May-26'!$F18="","-",VLOOKUP('May-26'!$F18,Lista_CUIT!$A$1:$D$2241,3,0)),"CUIT NO CARGADO") -> FLETE-LOGISTICA | R18: =IFERROR(IF('May-26'!$F18="","-",VLOOKUP('May-26'!$F18,Lista_CUIT!$A$1:$D$2241,4,0)),"CUIT NO CARGADO") -> 0
B19: 45799 | C19: 1 | D19: 5 | E19: 84621 | F19: 30692857611 | G19: =IFERROR(IF('May-26'!$F19="","-",VLOOKUP('May-26'!$F19,Lista_CUIT!$A$1:$D$2241,2,0)),"CUIT NO CARGADO") -> BAGUI S A | H19: 1106796.6 | I19: =IF('May-26'!$H19="","",'May-26'!$H19*0.21) -> 232427.29 | P19: =SUM('May-26'!$H19:$O19) -> 1339223.9 | Q19: =IFERROR(IF('May-26'!$F19="","-",VLOOKUP('May-26'!$F19,Lista_CUIT!$A$1:$D$2241,3,0)),"CUIT NO CARGADO") -> INSUMO | R19: =IFERROR(IF('May-26'!$F19="","-",VLOOKUP('May-26'!$F19,Lista_CUIT!$A$1:$D$2241,4,0)),"CUIT NO CARGADO") -> 0
B20: 45799 | C20: 1 | D20: 2 | E20: 17544 | F20: 30624684628 | G20: =IFERROR(IF('May-26'!$F20="","-",VLOOKUP('May-26'!$F20,Lista_CUIT!$A$1:$D$2241,2,0)),"CUIT NO CARGADO") -> MITSUKO ARGENTINA S R L | H20: 844740 | I20: =IF('May-26'!$H20="","",'May-26'!$H20*0.21) -> 177395.4 | P20: =SUM('May-26'!$H20:$O20) -> 1022135.4 | Q20: =IFERROR(IF('May-26'!$F20="","-",VLOOKUP('May-26'!$F20,Lista_CUIT!$A$1:$D$2241,3,0)),"CUIT NO CARGADO") -> INSUMO | R20: =IFERROR(IF('May-26'!$F20="","-",VLOOKUP('May-26'!$F20,Lista_CUIT!$A$1:$D$2241,4,0)),"CUIT NO CARGADO") -> 0
B21: 45802 | C21: 1 | D21: 3326 | E21: 16665 | F21: 30526874249 | G21: =IFERROR(IF('May-26'!$F21="","-",VLOOKUP('May-26'!$F21,Lista_CUIT!$A$1:$D$2241,2,0)),"CUIT NO CARGADO") -> FRAVEGA | H21: 330577.69 | I21: =IF('May-26'!$H21="","",'May-26'!$H21*0.21) -> 69421.315 | P21: =SUM('May-26'!$H21:$O21) -> 399999 | Q21: =IFERROR(IF('May-26'!$F21="","-",VLOOKUP('May-26'!$F21,Lista_CUIT!$A$1:$D$2241,3,0)),"CUIT NO CARGADO") -> Gastos Varios | R21: =IFERROR(IF('May-26'!$F21="","-",VLOOKUP('May-26'!$F21,Lista_CUIT!$A$1:$D$2241,4,0)),"CUIT NO CARGADO") -> 0
B22: 45803 | C22: 1 | D22: 700 | E22: 794725 | F22: 30580111315 | G22: =IFERROR(IF('May-26'!$F22="","-",VLOOKUP('May-26'!$F22,Lista_CUIT!$A$1:$D$2241,2,0)),"CUIT NO CARGADO") -> DHL EXPRESS (ARGENTINA) S.A. | H22: 0 | I22: =IF('May-26'!$H22="","",'May-26'!$H22*0.21) -> 0 | O22: =202.59*1150 -> 232978.5 | P22: =SUM('May-26'!$H22:$O22) -> 232978.5 | Q22: =IFERROR(IF('May-26'!$F22="","-",VLOOKUP('May-26'!$F22,Lista_CUIT!$A$1:$D$2241,3,0)),"CUIT NO CARGADO") -> Mercaderia | R22: =IFERROR(IF('May-26'!$F22="","-",VLOOKUP('May-26'!$F22,Lista_CUIT!$A$1:$D$2241,4,0)),"CUIT NO CARGADO") -> 0
B23: 45805 | C23: 1 | D23: 122 | E23: 368811 | F23: 30594494187 | G23: =IFERROR(IF('May-26'!$F23="","-",VLOOKUP('May-26'!$F23,Lista_CUIT!$A$1:$D$2241,2,0)),"CUIT NO CARGADO") -> FEDERAL EXPRESS CORPORATION | H23: 83232 | I23: =IF('May-26'!$H23="","",'May-26'!$H23*0.21) -> 17478.72 | O23: 277532.48 | P23: =SUM('May-26'!$H23:$O23) -> 378243.2 | Q23: =IFERROR(IF('May-26'!$F23="","-",VLOOKUP('May-26'!$F23,Lista_CUIT!$A$1:$D$2241,3,0)),"CUIT NO CARGADO") -> Mercaderia | R23: =IFERROR(IF('May-26'!$F23="","-",VLOOKUP('May-26'!$F23,Lista_CUIT!$A$1:$D$2241,4,0)),"CUIT NO CARGADO") -> 0
B24: 45805 | C24: 1 | D24: 5 | E24: 33681 | F24: 30646938755 | G24: =IFERROR(IF('May-26'!$F24="","-",VLOOKUP('May-26'!$F24,Lista_CUIT!$A$1:$D$2241,2,0)),"CUIT NO CARGADO") -> LASARTE HNOS SRL | H24: 209583 | I24: =IF('May-26'!$H24="","",'May-26'!$H24*0.21) -> 44012.43 | P24: =SUM('May-26'!$H24:$O24) -> 253595.43 | Q24: =IFERROR(IF('May-26'!$F24="","-",VLOOKUP('May-26'!$F24,Lista_CUIT!$A$1:$D$2241,3,0)),"CUIT NO CARGADO") -> Mantenimiento | R24: =IFERROR(IF('May-26'!$F24="","-",VLOOKUP('May-26'!$F24,Lista_CUIT!$A$1:$D$2241,4,0)),"CUIT NO CARGADO") -> 0
B25: 45807 | C25: 1 | D25: 5 | E25: 6083 | F25: 20231333593 | G25: =IFERROR(IF('May-26'!$F25="","-",VLOOKUP('May-26'!$F25,Lista_CUIT!$A$1:$D$2241,2,0)),"CUIT NO CARGADO") -> BOLLINI CLAUDIO DANIEL | H25: 80000 | I25: =IF('May-26'!$H25="","",'May-26'!$H25*0.21) -> 16800 | P25: =SUM('May-26'!$H25:$O25) -> 96800 | Q25: =IFERROR(IF('May-26'!$F25="","-",VLOOKUP('May-26'!$F25,Lista_CUIT!$A$1:$D$2241,3,0)),"CUIT NO CARGADO") -> Mantenimiento | R25: =IFERROR(IF('May-26'!$F25="","-",VLOOKUP('May-26'!$F25,Lista_CUIT!$A$1:$D$2241,4,0)),"CUIT NO CARGADO") -> 0
B26: 45807 | C26: 1 | D26: 35 | E26: 3756 | F26: 30516199292 | G26: =IFERROR(IF('May-26'!$F26="","-",VLOOKUP('May-26'!$F26,Lista_CUIT!$A$1:$D$2241,2,0)),"CUIT NO CARGADO") -> S V A SACIFI | H26: 246385.21 | I26: =IF('May-26'!$H26="","",'May-26'!$H26*0.21) -> 51740.894 | P26: =SUM('May-26'!$H26:$O26) -> 298126.1 | Q26: =IFERROR(IF('May-26'!$F26="","-",VLOOKUP('May-26'!$F26,Lista_CUIT!$A$1:$D$2241,3,0)),"CUIT NO CARGADO") -> Mant. Vehiculo | R26: =IFERROR(IF('May-26'!$F26="","-",VLOOKUP('May-26'!$F26,Lista_CUIT!$A$1:$D$2241,4,0)),"CUIT NO CARGADO") -> 0
B27: 45808 | C27: 1 | D27: 3 | E27: 9638 | F27: 30710585411 | G27: =IFERROR(IF('May-26'!$F27="","-",VLOOKUP('May-26'!$F27,Lista_CUIT!$A$1:$D$2241,2,0)),"CUIT NO CARGADO") -> POSITIF PLANIFIER S.A. | H27: 107563.64 | I27: =IF('May-26'!$H27="","",'May-26'!$H27*0.21) -> 22588.364 | P27: =SUM('May-26'!$H27:$O27) -> 130152 | Q27: =IFERROR(IF('May-26'!$F27="","-",VLOOKUP('May-26'!$F27,Lista_CUIT!$A$1:$D$2241,3,0)),"CUIT NO CARGADO") -> Gastos de Comercializacion | R27: =IFERROR(IF('May-26'!$F27="","-",VLOOKUP('May-26'!$F27,Lista_CUIT!$A$1:$D$2241,4,0)),"CUIT NO CARGADO") -> 0
B28: 45806 | C28: 3 | D28: 122 | E28: 71417 | F28: 30594494187 | G28: =IFERROR(IF('May-26'!$F28="","-",VLOOKUP('May-26'!$F28,Lista_CUIT!$A$1:$D$2241,2,0)),"CUIT NO CARGADO") -> FEDERAL EXPRESS CORPORATION | H28: -83232 | I28: =IF('May-26'!$H28="","",'May-26'!$H28*0.21) -> -17478.72 | O28: -277532.48 | P28: =SUM('May-26'!$H28:$O28) -> -378243.2 | Q28: =IFERROR(IF('May-26'!$F28="","-",VLOOKUP('May-26'!$F28,Lista_CUIT!$A$1:$D$2241,3,0)),"CUIT NO CARGADO") -> Mercaderia | R28: =IFERROR(IF('May-26'!$F28="","-",VLOOKUP('May-26'!$F28,Lista_CUIT!$A$1:$D$2241,4,0)),"CUIT NO CARGADO") -> 0
G29: =IFERROR(IF('May-26'!$F29="","-",VLOOKUP('May-26'!$F29,Lista_CUIT!$A$1:$D$2241,2,0)),"CUIT NO CARGADO") -> - | I29: =IF('May-26'!$H29="","",'May-26'!$H29*0.21) | P29: =SUM('May-26'!$H29:$O29) -> 0 | Q29: =IFERROR(IF('May-26'!$F29="","-",VLOOKUP('May-26'!$F29,Lista_CUIT!$A$1:$D$2241,3,0)),"CUIT NO CARGADO") -> - | R29: =IFERROR(IF('May-26'!$F29="","-",VLOOKUP('May-26'!$F29,Lista_CUIT!$A$1:$D$2241,4,0)),"CUIT NO CARGADO") -> -
B30: Total | H30: =SUBTOTAL(109,'May-26'!$H$9:$H$29) -> 6468699.6 | I30: =SUBTOTAL(109,'May-26'!$I$9:$I$29) -> 1351332.1 | J30: =SUBTOTAL(109,'May-26'!$J$9:$J$29) -> 9121.95 | K30: =SUBTOTAL(109,'May-26'!$K$9:$K$29) -> 0 | L30: =SUBTOTAL(109,'May-26'!$L$9:$L$29) -> 1013.55 | M30: =SUBTOTAL(109,'May-26'!$M$9:$M$29) -> 0 | N30: =SUBTOTAL(109,'May-26'!$N$9:$N$29) -> 0 | O30: =SUBTOTAL(109,'May-26'!$O$9:$O$29) -> 816385.54 | P30: =SUBTOTAL(109,'May-26'!$P$9:$P$29) -> 8646552.7
D35: LIQUIDACION EXTRACTOS BANCARIOS-TARJETAS
D36: FECHA | E36: NRO CPTE | F36: BANCO | G36: NETO | H36: IVA 21% | I36: IVA 10,5% | J36: RET IIBB CABA | K36: PERC IVA | L36: PERC IIBB
D37: 45808 | F37: CREDICOOP | G37: 81941.81 | H37: ='May-26'!$G37*0.21 -> 17207.78 | K37: 2216.75
H38: ='May-26'!$G38*0.21 -> 0
H39: ='May-26'!$G39*0.21 -> 0
H40: ='May-26'!$G40*0.21 -> 0
H41: ='May-26'!$G41*0.21 -> 0
H42: ='May-26'!$G42*0.21 -> 0
D43: Total | G43: =SUBTOTAL(109,'May-26'!$G$37:$G$42) -> 81941.81 | H43: =SUBTOTAL(109,'May-26'!$H$37:$H$42) -> 17207.78 | I43: =SUBTOTAL(109,'May-26'!$I$37:$I$42) -> 0 | J43: =SUBTOTAL(109,'May-26'!$J$37:$J$42) -> 0 | K43: =SUBTOTAL(109,'May-26'!$K$37:$K$42) -> 2216.75 | L43: =SUBTOTAL(109,'May-26'!$L$37:$L$42) -> 0
D47: FACTURAS C
D48: FECHA | E48: PTO VTA | F48: FC Nº | G48: CUIT | H48: RAZON SOCIAL | I48: TOTAL | J48: TIPO DE GASTO | K48: Provincia
D49: 45778 | E49: 4 | F49: 20 | G49: 20086277523 | H49: =IFERROR(IF('May-26'!$G49="","-",VLOOKUP('May-26'!$G49,Lista_CUIT!$A$1:$D$2241,2,0)),"CUIT NO CARGADO") -> ESTUDIO BOTINDARI | I49: 335000 | J49: =IFERROR(IF('May-26'!$G49="","-",VLOOKUP('May-26'!$G49,Lista_CUIT!$A$1:$D$2241,3,0)),"CUIT NO CARGADO") -> Honorarios Contables | K49: =IFERROR(IF('May-26'!$G49="","-",VLOOKUP('May-26'!$G49,Lista_CUIT!$A$1:$D$2241,4,0)),"CUIT NO CARGADO") -> 0
D50: 45778 | E50: 1 | F50: 49 | G50: 20365938688 | H50: =IFERROR(IF('May-26'!$G50="","-",VLOOKUP('May-26'!$G50,Lista_CUIT!$A$1:$D$2241,2,0)),"CUIT NO CARGADO") -> LIPANOVICH JUAN CRUZ | I50: 1583679 | J50: =IFERROR(IF('May-26'!$G50="","-",VLOOKUP('May-26'!$G50,Lista_CUIT!$A$1:$D$2241,3,0)),"CUIT NO CARGADO") -> SOFTWARE | K50: =IFERROR(IF('May-26'!$G50="","-",VLOOKUP('May-26'!$G50,Lista_CUIT!$A$1:$D$2241,4,0)),"CUIT NO CARGADO") -> 0
D51: 45778 | E51: 2 | F51: 183 | G51: 20136544625 | H51: =IFERROR(IF('May-26'!$G51="","-",VLOOKUP('May-26'!$G51,Lista_CUIT!$A$1:$D$2241,2,0)),"CUIT NO CARGADO") -> RODRIGUEZ DE LA FUEN HECTOR MARCELO | I51: 1283000 | J51: =IFERROR(IF('May-26'!$G51="","-",VLOOKUP('May-26'!$G51,Lista_CUIT!$A$1:$D$2241,3,0)),"CUIT NO CARGADO") -> Honorarios Admin | K51: =IFERROR(IF('May-26'!$G51="","-",VLOOKUP('May-26'!$G51,Lista_CUIT!$A$1:$D$2241,4,0)),"CUIT NO CARGADO") -> 0
D52: 45778 | E52: 2 | F52: 278 | G52: 27173820866 | H52: =IFERROR(IF('May-26'!$G52="","-",VLOOKUP('May-26'!$G52,Lista_CUIT!$A$1:$D$2241,2,0)),"CUIT NO CARGADO") -> FREIER SANDRA DANIELA | I52: 1120000 | J52: =IFERROR(IF('May-26'!$G52="","-",VLOOKUP('May-26'!$G52,Lista_CUIT!$A$1:$D$2241,3,0)),"CUIT NO CARGADO") -> Honorarios Prof | K52: =IFERROR(IF('May-26'!$G52="","-",VLOOKUP('May-26'!$G52,Lista_CUIT!$A$1:$D$2241,4,0)),"CUIT NO CARGADO") -> 0
D53: 45779 | E53: 1 | F53: 112 | G53: 20341465134 | H53: =IFERROR(IF('May-26'!$G53="","-",VLOOKUP('May-26'!$G53,Lista_CUIT!$A$1:$D$2241,2,0)),"CUIT NO CARGADO") -> ABELEDO AGUSTIN ENRIQUE | I53: 2248500 | J53: =IFERROR(IF('May-26'!$G53="","-",VLOOKUP('May-26'!$G53,Lista_CUIT!$A$1:$D$2241,3,0)),"CUIT NO CARGADO") -> Mantenimiento | K53: =IFERROR(IF('May-26'!$G53="","-",VLOOKUP('May-26'!$G53,Lista_CUIT!$A$1:$D$2241,4,0)),"CUIT NO CARGADO") -> CABA
D54: 45782 | E54: 1 | F54: 148 | G54: 20389908569 | H54: =IFERROR(IF('May-26'!$G54="","-",VLOOKUP('May-26'!$G54,Lista_CUIT!$A$1:$D$2241,2,0)),"CUIT NO CARGADO") -> BOTINDARI JUAN IGNACIO | I54: 102700 | J54: =IFERROR(IF('May-26'!$G54="","-",VLOOKUP('May-26'!$G54,Lista_CUIT!$A$1:$D$2241,3,0)),"CUIT NO CARGADO") -> Honorarios Contables | K54: =IFERROR(IF('May-26'!$G54="","-",VLOOKUP('May-26'!$G54,Lista_CUIT!$A$1:$D$2241,4,0)),"CUIT NO CARGADO") -> 0
D55: 45782 | E55: 4 | F55: 92 | G55: 23214737914 | H55: =IFERROR(IF('May-26'!$G55="","-",VLOOKUP('May-26'!$G55,Lista_CUIT!$A$1:$D$2241,2,0)),"CUIT NO CARGADO") -> SBARRA GABRIELA BEATRIZ | I55: 1046270 | J55: =IFERROR(IF('May-26'!$G55="","-",VLOOKUP('May-26'!$G55,Lista_CUIT!$A$1:$D$2241,3,0)),"CUIT NO CARGADO") -> Honorarios Admin | K55: =IFERROR(IF('May-26'!$G55="","-",VLOOKUP('May-26'!$G55,Lista_CUIT!$A$1:$D$2241,4,0)),"CUIT NO CARGADO") -> 0
D56: 45782 | E56: 1 | F56: 40 | G56: 27387896150 | H56: =IFERROR(IF('May-26'!$G56="","-",VLOOKUP('May-26'!$G56,Lista_CUIT!$A$1:$D$2241,2,0)),"CUIT NO CARGADO") -> LIPANOVICH MARIA SOL | I56: 1666000 | J56: =IFERROR(IF('May-26'!$G56="","-",VLOOKUP('May-26'!$G56,Lista_CUIT!$A$1:$D$2241,3,0)),"CUIT NO CARGADO") -> consultoria informatica | K56: =IFERROR(IF('May-26'!$G56="","-",VLOOKUP('May-26'!$G56,Lista_CUIT!$A$1:$D$2241,4,0)),"CUIT NO CARGADO") -> 0
D57: 45783 | E57: 2 | F57: 19 | G57: 23118167279 | H57: =IFERROR(IF('May-26'!$G57="","-",VLOOKUP('May-26'!$G57,Lista_CUIT!$A$1:$D$2241,2,0)),"CUIT NO CARGADO") -> ABELEDO ENRIQUE JUAN | I57: 1984000 | J57: =IFERROR(IF('May-26'!$G57="","-",VLOOKUP('May-26'!$G57,Lista_CUIT!$A$1:$D$2241,3,0)),"CUIT NO CARGADO") -> Honorarios Admin | K57: =IFERROR(IF('May-26'!$G57="","-",VLOOKUP('May-26'!$G57,Lista_CUIT!$A$1:$D$2241,4,0)),"CUIT NO CARGADO") -> 0
D58: 45783 | E58: 2 | F58: 190 | G58: 27125997835 | H58: =IFERROR(IF('May-26'!$G58="","-",VLOOKUP('May-26'!$G58,Lista_CUIT!$A$1:$D$2241,2,0)),"CUIT NO CARGADO") -> DANSKY ULLMANN VIVIANA EVA YOLANDA | I58: 170000 | J58: =IFERROR(IF('May-26'!$G58="","-",VLOOKUP('May-26'!$G58,Lista_CUIT!$A$1:$D$2241,3,0)),"CUIT NO CARGADO") -> Honorarios Prof | K58: =IFERROR(IF('May-26'!$G58="","-",VLOOKUP('May-26'!$G58,Lista_CUIT!$A$1:$D$2241,4,0)),"CUIT NO CARGADO") -> 0
D59: 45790 | E59: 4 | F59: 48 | G59: 20341462933 | H59: =IFERROR(IF('May-26'!$G59="","-",VLOOKUP('May-26'!$G59,Lista_CUIT!$A$1:$D$2241,2,0)),"CUIT NO CARGADO") -> CASTIGLIONI MATIAS EZEQUIEL | I59: 2558000 | J59: =IFERROR(IF('May-26'!$G59="","-",VLOOKUP('May-26'!$G59,Lista_CUIT!$A$1:$D$2241,3,0)),"CUIT NO CARGADO") -> ASESORAMIENTO | K59: =IFERROR(IF('May-26'!$G59="","-",VLOOKUP('May-26'!$G59,Lista_CUIT!$A$1:$D$2241,4,0)),"CUIT NO CARGADO") -> BUENOS AIRES
D60: 45806 | E60: 1 | F60: 813 | G60: 20332167481 | H60: =IFERROR(IF('May-26'!$G60="","-",VLOOKUP('May-26'!$G60,Lista_CUIT!$A$1:$D$2241,2,0)),"CUIT NO CARGADO") -> AGUIRRE GABRIEL ADRIAN | I60: 25800 | J60: =IFERROR(IF('May-26'!$G60="","-",VLOOKUP('May-26'!$G60,Lista_CUIT!$A$1:$D$2241,3,0)),"CUIT NO CARGADO") -> GASTOS VARIOS | K60: =IFERROR(IF('May-26'!$G60="","-",VLOOKUP('May-26'!$G60,Lista_CUIT!$A$1:$D$2241,4,0)),"CUIT NO CARGADO") -> 0
H61: =IFERROR(IF('May-26'!$G61="","-",VLOOKUP('May-26'!$G61,Lista_CUIT!$A$1:$D$2241,2,0)),"CUIT NO CARGADO") -> - | J61: =IFERROR(IF('May-26'!$G61="","-",VLOOKUP('May-26'!$G61,Lista_CUIT!$A$1:$D$2241,3,0)),"CUIT NO CARGADO") -> - | K61: =IFERROR(IF('May-26'!$G61="","-",VLOOKUP('May-26'!$G61,Lista_CUIT!$A$1:$D$2241,4,0)),"CUIT NO CARGADO") -> -
D62: Total | I62: =SUBTOTAL(109,'May-26'!$I$49:$I$61) -> 14122949
B68: LIBRO IVA VENTAS | K68: =N1 -> 45778
B70: VENTAS "A"
B71: FECHA | C71: TIPO | D71: PTO VENTA | E71: Nº FACTURA | F71: CUIT | G71: RAZON SOCIAL | H71: IMPORTE NETO | I71: IVA 21% | J71: IVA 10,5% | K71: EXENTO | L71: TOTAL | M71: Provincia
B72: 45782 | C72: 1 | D72: 3 | E72: 270 | F72: 30628274327 | G72: =IFERROR(IF('May-26'!$F72="","-",VLOOKUP('May-26'!$F72,Lista_CUIT!$A$1:$D$2241,2,0)),"CUIT NO CARGADO") -> AGIRA S A | H72: 20473600 | I72: =84*1120 -> 94080 | J72: =1877.4*1120 -> 2102688 | L72: =SUM('May-26'!$H72:$K72) -> 22670368
B73: 45782 | C73: 1 | D73: 3 | E73: 269 | F73: 30638318470 | G73: =IFERROR(IF('May-26'!$F73="","-",VLOOKUP('May-26'!$F73,Lista_CUIT!$A$1:$D$2241,2,0)),"CUIT NO CARGADO") -> DELTA COMPRESION S R L | H73: 57398460 | I73: =1235.64*1190 -> 1470411.6 | J73: =4446.75*1190 -> 5291632.5 | L73: =SUM('May-26'!$H73:$K73) -> 64160504
B74: 45785 | C74: 1 | D74: 3 | E74: 271 | F74: 33717088269 | G74: =IFERROR(IF('May-26'!$F74="","-",VLOOKUP('May-26'!$F74,Lista_CUIT!$A$1:$D$2241,2,0)),"CUIT NO CARGADO") -> NEXT SERVICE GNC S.R.L. | H74: 4110299 | I74: ='May-26'!$H74*0.21 -> 863162.79 | L74: =SUM('May-26'!$H74:$K74) -> 4973461.8
B75: 45789 | C75: 1 | D75: 3 | E75: 272 | F75: 30638318470 | G75: =IFERROR(IF('May-26'!$F75="","-",VLOOKUP('May-26'!$F75,Lista_CUIT!$A$1:$D$2241,2,0)),"CUIT NO CARGADO") -> DELTA COMPRESION S R L | H75: 6097530 | I75: ='May-26'!$H75*0.21 -> 1280481.3 | L75: =SUM('May-26'!$H75:$K75) -> 7378011.3
B76: 45793 | C76: 1 | D76: 3 | E76: 273 | F76: 30638318470 | G76: =IFERROR(IF('May-26'!$F76="","-",VLOOKUP('May-26'!$F76,Lista_CUIT!$A$1:$D$2241,2,0)),"CUIT NO CARGADO") -> DELTA COMPRESION S R L | H76: 91060 | I76: ='May-26'!$H76*0.21 -> 19122.6 | L76: =SUM('May-26'!$H76:$K76) -> 110182.6
B77: 45799 | C77: 1 | D77: 3 | E77: 275 | F77: 30716041596 | G77: =IFERROR(IF('May-26'!$F77="","-",VLOOKUP('May-26'!$F77,Lista_CUIT!$A$1:$D$2241,2,0)),"CUIT NO CARGADO") -> EXA COMPRESION S.R.L. | H77: 2829750 | I77: ='May-26'!$H77*0.21 -> 594247.5 | L77: =SUM('May-26'!$H77:$K77) -> 3423997.5
B78: 45799 | C78: 1 | D78: 3 | E78: 274 | F78: 30638318470 | G78: =IFERROR(IF('May-26'!$F78="","-",VLOOKUP('May-26'!$F78,Lista_CUIT!$A$1:$D$2241,2,0)),"CUIT NO CARGADO") -> DELTA COMPRESION S R L | H78: 24851096 | I78: =71.63*1155 -> 82732.65 | J78: =2223.38*1155 -> 2568003.9 | L78: =SUM('May-26'!$H78:$K78) -> 27501832
B79: 45804 | C79: 1 | D79: 3 | E79: 276 | F79: 30718512545 | G79: =IFERROR(IF('May-26'!$F79="","-",VLOOKUP('May-26'!$F79,Lista_CUIT!$A$1:$D$2241,2,0)),"CUIT NO CARGADO") -> MAJUBEN MDP SERVICIOS S.R.L. | H79: 8365500 | I79: =241.5*1170 -> 282555 | J79: =630*1170 -> 737100 | L79: =SUM('May-26'!$H79:$K79) -> 9385155
B80: 45804 | C80: 1 | D80: 3 | E80: 277 | F80: 30716403900 | G80: =IFERROR(IF('May-26'!$F80="","-",VLOOKUP('May-26'!$F80,Lista_CUIT!$A$1:$D$2241,2,0)),"CUIT NO CARGADO") -> PARQUE CONSTITUCION SRL | H80: 1755000 | I80: ='May-26'!$H80*0.21 -> 368550 | L80: =SUM('May-26'!$H80:$K80) -> 2123550
B81: Total | H81: =SUBTOTAL(109,'May-26'!$H$72:$H$80) -> 1.2597229e+08 | I81: =SUBTOTAL(109,'May-26'!$I$72:$I$80) -> 5055343.4 | J81: =SUBTOTAL(109,'May-26'!$J$72:$J$80) -> 10699424 | K81: =SUBTOTAL(109,'May-26'!$K$72:$K$80) -> 0 | L81: =SUBTOTAL(109,'May-26'!$L$72:$L$80) -> 1.4172706e+08
B86: VENTAS "B"
B87: FECHA | C87: TIPO | D87: PTO VENTA | E87: Nº FACTURA | F87: CUIT | G87: RAZON SOCIAL | H87: IMPORTE NETO | I87: IVA 21% | J87: IVA 10,5% | K87: EXENTO | L87: TOTAL | M87: Provincia
G88: =IFERROR(IF('May-26'!$F88="","-",VLOOKUP('May-26'!$F88,Lista_CUIT!$A$1:$D$2241,2,0)),"CUIT NO CARGADO") -> - | I88: ='May-26'!$H88*0.21 -> 0 | L88: ='May-26'!$K88+'May-26'!$J88+'May-26'!$I88+'May-26'!$H88 -> 0
G89: =IFERROR(IF('May-26'!$F89="","-",VLOOKUP('May-26'!$F89,Lista_CUIT!$A$1:$D$2241,2,0)),"CUIT NO CARGADO") -> - | I89: ='May-26'!$H89*0.21 -> 0 | L89: ='May-26'!$K89+'May-26'!$J89+'May-26'!$I89+'May-26'!$H89 -> 0
G90: =IFERROR(IF('May-26'!$F90="","-",VLOOKUP('May-26'!$F90,Lista_CUIT!$A$1:$D$2241,2,0)),"CUIT NO CARGADO") -> - | I90: ='May-26'!$H90*0.21 -> 0 | L90: ='May-26'!$K90+'May-26'!$J90+'May-26'!$I90+'May-26'!$H90 -> 0
G91: =IFERROR(IF('May-26'!$F91="","-",VLOOKUP('May-26'!$F91,Lista_CUIT!$A$1:$D$2241,2,0)),"CUIT NO CARGADO") -> - | I91: ='May-26'!$H91*0.21 -> 0 | L91: ='May-26'!$K91+'May-26'!$J91+'May-26'!$I91+'May-26'!$H91 -> 0
G92: =IFERROR(IF('May-26'!$F92="","-",VLOOKUP('May-26'!$F92,Lista_CUIT!$A$1:$D$2241,2,0)),"CUIT NO CARGADO") -> - | I92: ='May-26'!$H92*0.21 -> 0 | L92: ='May-26'!$K92+'May-26'!$J92+'May-26'!$I92+'May-26'!$H92 -> 0
B93: Total | H93: =SUBTOTAL(109,'May-26'!$H$88:$H$92) -> 0 | I93: =SUBTOTAL(109,'May-26'!$I$88:$I$92) -> 0 | J93: =SUBTOTAL(109,'May-26'!$J$88:$J$92) -> 0 | K93: =SUBTOTAL(109,'May-26'!$K$88:$K$92) -> 0 | L93: =SUBTOTAL(109,'May-26'!$L$88:$L$92) -> 0 | M93: =SUBTOTAL(103,'May-26'!$M$88:$M$92) -> 0
B96: VENTAS "E"
B97: FECHA | C97: TIPO | D97: PTO VENTA | E97: Nº FACTURA | F97: CUIT | G97: RAZON SOCIAL | H97: USD | I97: Columna2 | J97: Columna1 | K97: TIPO DE CAMBIO2 | L97: TOTAL | M97: Provincia
B98: 45784 | D98: 30 | E98: 106 | G98: =IFERROR(IF('May-26'!$F98="","-",VLOOKUP('May-26'!$F98,Lista_CUIT!$A$1:$D$2241,2,0)),"CUIT NO CARGADO") -> - | H98: 650 | K98: 1194 | L98: =H98*K98 -> 776100
B99: 45798 | D99: 30 | E99: 107 | G99: =IFERROR(IF('May-26'!$F99="","-",VLOOKUP('May-26'!$F99,Lista_CUIT!$A$1:$D$2241,2,0)),"CUIT NO CARGADO") -> - | H99: 1920 | K99: 1142.5 | L99: =H99*K99 -> 2193600
B100: 45804 | D100: 30 | E100: 108 | G100: =IFERROR(IF('May-26'!$F100="","-",VLOOKUP('May-26'!$F100,Lista_CUIT!$A$1:$D$2241,2,0)),"CUIT NO CARGADO") -> - | H100: 7215 | K100: 1143 | L100: =H100*K100 -> 8246745
B101: Total | H101: =SUBTOTAL(109,'May-26'!$H$98:$H$100) -> 9785 | I101: =SUBTOTAL(109,'May-26'!$I$98:$I$100) -> 0 | J101: =SUBTOTAL(109,'May-26'!$J$98:$J$100) -> 0 | L101: =SUBTOTAL(109,'May-26'!$L$98:$L$100) -> 11216445 | M101: =SUBTOTAL(103,'May-26'!$M$98:$M$100) -> 0
C106: RETENCIONES
C107: FECHA | D107: COMP Nº | E107: Columna1 | F107: CUIT | G107: RAZON SOCIAL | H107: Ganancias | I107: IVA | J107: SUSS | K107: IIBB BSAS | L107: IIBB CABA
G108: =IFERROR(IF('May-26'!$F108="","-",VLOOKUP('May-26'!$F108,Lista_CUIT!$A$1:$D$2241,2,0)),"CUIT NO CARGADO") -> -
G109: =IFERROR(IF('May-26'!$F109="","-",VLOOKUP('May-26'!$F109,Lista_CUIT!$A$1:$D$2241,2,0)),"CUIT NO CARGADO") -> -
G110: =IFERROR(IF('May-26'!$F110="","-",VLOOKUP('May-26'!$F110,Lista_CUIT!$A$1:$D$2241,2,0)),"CUIT NO CARGADO") -> -
G111: =IFERROR(IF('May-26'!$F111="","-",VLOOKUP('May-26'!$F111,Lista_CUIT!$A$1:$D$2241,2,0)),"CUIT NO CARGADO") -> -
G112: =IFERROR(IF('May-26'!$F112="","-",VLOOKUP('May-26'!$F112,Lista_CUIT!$A$1:$D$2241,2,0)),"CUIT NO CARGADO") -> -
G113: =IFERROR(IF('May-26'!$F113="","-",VLOOKUP('May-26'!$F113,Lista_CUIT!$A$1:$D$2241,2,0)),"CUIT NO CARGADO") -> -
G114: =IFERROR(IF('May-26'!$F114="","-",VLOOKUP('May-26'!$F114,Lista_CUIT!$A$1:$D$2241,2,0)),"CUIT NO CARGADO") -> -
G115: =IFERROR(IF('May-26'!$F115="","-",VLOOKUP('May-26'!$F115,Lista_CUIT!$A$1:$D$2241,2,0)),"CUIT NO CARGADO") -> -
G116: =IFERROR(IF('May-26'!$F116="","-",VLOOKUP('May-26'!$F116,Lista_CUIT!$A$1:$D$2241,2,0)),"CUIT NO CARGADO") -> -
G117: =IFERROR(IF('May-26'!$F117="","-",VLOOKUP('May-26'!$F117,Lista_CUIT!$A$1:$D$2241,2,0)),"CUIT NO CARGADO") -> -
G118: =IFERROR(IF('May-26'!$F118="","-",VLOOKUP('May-26'!$F118,Lista_CUIT!$A$1:$D$2241,2,0)),"CUIT NO CARGADO") -> -
G119: =IFERROR(IF('May-26'!$F119="","-",VLOOKUP('May-26'!$F119,Lista_CUIT!$A$1:$D$2241,2,0)),"CUIT NO CARGADO") -> -
... G134: =IFERROR(IF('May-26'!$F134="","-",VLOOKUP('May-26'!$F134,Lista_CUIT!$A$1:$D$2241,2,0)),"CUIT NO CARGADO") -> -

Sheet Jun-26
B1: LIBRO IVA COMPRAS | G1: ='Abr-26'!G1:M1 -> CORITEC S. R. L. | N1: =EDATE('Abr-26'!N1,2) -> 45809
B3: TOTAL COMPRAS | G3: TOTAL CREDITO FISCAL | J3: TOTAL VENTAS NETAS | M3: TOTAL DEBITO FISCAL | P3: RESULTADO
B4: =SUM('Jun-26'!$H$44)+'Jun-26'!$G$53 -> 12776359 | G4: ='Jun-26'!$I$44+'Jun-26'!$J$44+'Jun-26'!$K$44+'Jun-26'!$H$53+'Jun-26'!$I$53 -> 2683035.3 | J4: ='Jun-26'!$H$93+'Jun-26'!$H$104 -> 68234426 | M4: ='Jun-26'!$I$93+'Jun-26'!$J$93+'Jun-26'!$I$104+'Jun-26'!$J$104 -> 8091956 | P4: =G4-M4 -> -5408920.7
B8: FECHA | C8: TIPO | D8: PTO VTA | E8: NRO. CPTE | F8: CUIT | G8: RAZON SOCIAL | H8: NETO GRAVADO | I8: IVA 21 % | J8: IVA 27% | K8: IVA 10,5% | L8: PERC. IVA | M8: PERC IIBB BS AS | N8: PERC. IIBB CABA | O8: Otros / No Grav. | P8: TOTAL | Q8: Tipo de Gasto | R8: Provincia
B9: 45809 | C9: 1 | D9: 3 | E9: 268474 | F9: 30707135596 | G9: =IFERROR(IF('Jun-26'!$F9="","-",VLOOKUP('Jun-26'!$F9,Lista_CUIT!$A$1:$D$2241,2,0)),"CUIT NO CARGADO") -> CITILAN ARGENTINA S.A. | H9: 28851.11 | I9: =IF('Jun-26'!$H9="","",'Jun-26'!$H9*0.21) -> 6058.7331 | P9: =SUM('Jun-26'!$H9:$O9) -> 34909.843 | Q9: =IFERROR(IF('Jun-26'!$F9="","-",VLOOKUP('Jun-26'!$F9,Lista_CUIT!$A$1:$D$2241,3,0)),"CUIT NO CARGADO") -> Telefonia | R9: =IFERROR(IF('Jun-26'!$F9="","-",VLOOKUP('Jun-26'!$F9,Lista_CUIT!$A$1:$D$2241,4,0)),"CUIT NO CARGADO") -> 0
B10: 45809 | C10: 1 | D10: 3 | E10: 866 | F10: 30715402765 | G10: =IFERROR(IF('Jun-26'!$F10="","-",VLOOKUP('Jun-26'!$F10,Lista_CUIT!$A$1:$D$2241,2,0)),"CUIT NO CARGADO") -> RIO 265 S.R.L. | H10: 93388.43 | I10: =IF('Jun-26'!$H10="","",'Jun-26'!$H10*0.21) -> 19611.57 | P10: =SUM('Jun-26'!$H10:$O10) -> 113000 | Q10: =IFERROR(IF('Jun-26'!$F10="","-",VLOOKUP('Jun-26'!$F10,Lista_CUIT!$A$1:$D$2241,3,0)),"CUIT NO CARGADO") -> GASTOS VARIOS | R10: =IFERROR(IF('Jun-26'!$F10="","-",VLOOKUP('Jun-26'!$F10,Lista_CUIT!$A$1:$D$2241,4,0)),"CUIT NO CARGADO") -> 0
B11: 45810 | C11: 1 | D11: 106 | E11: 846433 | F11: 30594494187 | G11: =IFERROR(IF('Jun-26'!$F11="","-",VLOOKUP('Jun-26'!$F11,Lista_CUIT!$A$1:$D$2241,2,0)),"CUIT NO CARGADO") -> FEDERAL EXPRESS CORPORATION | H11: 86040 | I11: =IF('Jun-26'!$H11="","",'Jun-26'!$H11*0.21) -> 18068.4 | O11: 277532.48 | P11: =SUM('Jun-26'!$H11:$O11) -> 381640.88 | Q11: =IFERROR(IF('Jun-26'!$F11="","-",VLOOKUP('Jun-26'!$F11,Lista_CUIT!$A$1:$D$2241,3,0)),"CUIT NO CARGADO") -> Mercaderia | R11: =IFERROR(IF('Jun-26'!$F11="","-",VLOOKUP('Jun-26'!$F11,Lista_CUIT!$A$1:$D$2241,4,0)),"CUIT NO CARGADO") -> 0
B12: 45811 | C12: 1 | D12: 10 | E12: 50250 | F12: 20357275882 | G12: =IFERROR(IF('Jun-26'!$F12="","-",VLOOKUP('Jun-26'!$F12,Lista_CUIT!$A$1:$D$2241,2,0)),"CUIT NO CARGADO") -> LAVADERO BLANCANIEVES | H12: 7429.75 | I12: =IF('Jun-26'!$H12="","",'Jun-26'!$H12*0.21) -> 1560.2475 | P12: =SUM('Jun-26'!$H12:$O12) -> 8989.9975 | Q12: =IFERROR(IF('Jun-26'!$F12="","-",VLOOKUP('Jun-26'!$F12,Lista_CUIT!$A$1:$D$2241,3,0)),"CUIT NO CARGADO") -> Seg e Higiene | R12: =IFERROR(IF('Jun-26'!$F12="","-",VLOOKUP('Jun-26'!$F12,Lista_CUIT!$A$1:$D$2241,4,0)),"CUIT NO CARGADO") -> 0
B13: 45811 | C13: 1 | D13: 3 | E13: 5326 | F13: 30718266420 | G13: =IFERROR(IF('Jun-26'!$F13="","-",VLOOKUP('Jun-26'!$F13,Lista_CUIT!$A$1:$D$2241,2,0)),"CUIT NO CARGADO") -> GOLDEN CAN ARGENTINA S.A.S. | H13: 28522.31 | I13: =IF('Jun-26'!$H13="","",'Jun-26'!$H13*0.21) -> 5989.6851 | P13: =SUM('Jun-26'!$H13:$O13) -> 34511.995 | Q13: =IFERROR(IF('Jun-26'!$F13="","-",VLOOKUP('Jun-26'!$F13,Lista_CUIT!$A$1:$D$2241,3,0)),"CUIT NO CARGADO") -> Gastos Oficina | R13: =IFERROR(IF('Jun-26'!$F13="","-",VLOOKUP('Jun-26'!$F13,Lista_CUIT!$A$1:$D$2241,4,0)),"CUIT NO CARGADO") -> 0
B14: 45811 | C14: 1 | D14: 5 | E14: 85054 | F14: 30692857611 | G14: =IFERROR(IF('Jun-26'!$F14="","-",VLOOKUP('Jun-26'!$F14,Lista_CUIT!$A$1:$D$2241,2,0)),"CUIT NO CARGADO") -> BAGUI S A | H14: 436035.6 | I14: =IF('Jun-26'!$H14="","",'Jun-26'!$H14*0.21) -> 91567.476 | P14: =SUM('Jun-26'!$H14:$O14) -> 527603.08 | Q14: =IFERROR(IF('Jun-26'!$F14="","-",VLOOKUP('Jun-26'!$F14,Lista_CUIT!$A$1:$D$2241,3,0)),"CUIT NO CARGADO") -> INSUMO | R14: =IFERROR(IF('Jun-26'!$F14="","-",VLOOKUP('Jun-26'!$F14,Lista_CUIT!$A$1:$D$2241,4,0)),"CUIT NO CARGADO") -> 0
B15: 45812 | C15: 1 | D15: 10 | E15: 50297 | F15: 20357275882 | G15: =IFERROR(IF('Jun-26'!$F15="","-",VLOOKUP('Jun-26'!$F15,Lista_CUIT!$A$1:$D$2241,2,0)),"CUIT NO CARGADO") -> LAVADERO BLANCANIEVES | H15: 7429.75 | I15: =IF('Jun-26'!$H15="","",'Jun-26'!$H15*0.21) -> 1560.2475 | P15: =SUM('Jun-26'!$H15:$O15) -> 8989.9975 | Q15: =IFERROR(IF('Jun-26'!$F15="","-",VLOOKUP('Jun-26'!$F15,Lista_CUIT!$A$1:$D$2241,3,0)),"CUIT NO CARGADO") -> Seg e Higiene | R15: =IFERROR(IF('Jun-26'!$F15="","-",VLOOKUP('Jun-26'!$F15,Lista_CUIT!$A$1:$D$2241,4,0)),"CUIT NO CARGADO") -> 0
B16: 45812 | C16: 1 | D16: 8 | E16: 46596 | F16: 30709953482 | G16: =IFERROR(IF('Jun-26'!$F16="","-",VLOOKUP('Jun-26'!$F16,Lista_CUIT!$A$1:$D$2241,2,0)),"CUIT NO CARGADO") -> HONRE S.A | H16: 7189.26 | I16: =IF('Jun-26'!$H16="","",'Jun-26'!$H16*0.21) -> 1509.7446 | P16: =SUM('Jun-26'!$H16:$O16) -> 8699.0046 | Q16: =IFERROR(IF('Jun-26'!$F16="","-",VLOOKUP('Jun-26'!$F16,Lista_CUIT!$A$1:$D$2241,3,0)),"CUIT NO CARGADO") -> GASTOS VARIOS | R16: =IFERROR(IF('Jun-26'!$F16="","-",VLOOKUP('Jun-26'!$F16,Lista_CUIT!$A$1:$D$2241,4,0)),"CUIT NO CARGADO") -> 0
B17: 45812 | C17: 1 | D17: 8 | E17: 46506 | F17: 30709953482 | G17: =IFERROR(IF('Jun-26'!$F17="","-",VLOOKUP('Jun-26'!$F17,Lista_CUIT!$A$1:$D$2241,2,0)),"CUIT NO CARGADO") -> HONRE S.A | H17: 7189.26 | I17: =IF('Jun-26'!$H17="","",'Jun-26'!$H17*0.21) -> 1509.7446 | P17: =SUM('Jun-26'!$H17:$O17) -> 8699.0046 | Q17: =IFERROR(IF('Jun-26'!$F17="","-",VLOOKUP('Jun-26'!$F17,Lista_CUIT!$A$1:$D$2241,3,0)),"CUIT NO CARGADO") -> GASTOS VARIOS | R17: =IFERROR(IF('Jun-26'!$F17="","-",VLOOKUP('Jun-26'!$F17,Lista_CUIT!$A$1:$D$2241,4,0)),"CUIT NO CARGADO") -> 0
B18: 45812 | C18: 1 | D18: 3 | E18: 1588 | F18: 30717805174 | G18: =IFERROR(IF('Jun-26'!$F18="","-",VLOOKUP('Jun-26'!$F18,Lista_CUIT!$A$1:$D$2241,2,0)),"CUIT NO CARGADO") -> LUXONO S. R. L. | H18: 29326.83 | I18: =IF('Jun-26'!$H18="","",'Jun-26'!$H18*0.21) -> 6158.6343 | P18: =SUM('Jun-26'!$H18:$O18) -> 35485.464 | Q18: =IFERROR(IF('Jun-26'!$F18="","-",VLOOKUP('Jun-26'!$F18,Lista_CUIT!$A$1:$D$2241,3,0)),"CUIT NO CARGADO") -> INSUMO | R18: =IFERROR(IF('Jun-26'!$F18="","-",VLOOKUP('Jun-26'!$F18,Lista_CUIT!$A$1:$D$2241,4,0)),"CUIT NO CARGADO") -> 0
B19: 45812 | C19: 1 | D19: 14 | E19: 92231 | F19: 20271822058 | G19: =IFERROR(IF('Jun-26'!$F19="","-",VLOOKUP('Jun-26'!$F19,Lista_CUIT!$A$1:$D$2241,2,0)),"CUIT NO CARGADO") -> CASSINI MARTIN | H19: 5697.2 | I19: =IF('Jun-26'!$H19="","",'Jun-26'!$H19*0.21) -> 1196.412 | P19: =SUM('Jun-26'!$H19:$O19) -> 6893.612 | Q19: =IFERROR(IF('Jun-26'!$F19="","-",VLOOKUP('Jun-26'!$F19,Lista_CUIT!$A$1:$D$2241,3,0)),"CUIT NO CARGADO") -> Seg e Higiene | R19: =IFERROR(IF('Jun-26'!$F19="","-",VLOOKUP('Jun-26'!$F19,Lista_CUIT!$A$1:$D$2241,4,0)),"CUIT NO CARGADO") -> 0
B20: 45813 | C20: 1 | D20: 8 | E20: 181168 | F20: 33606484599 | G20: =IFERROR(IF('Jun-26'!$F20="","-",VLOOKUP('Jun-26'!$F20,Lista_CUIT!$A$1:$D$2241,2,0)),"CUIT NO CARGADO") -> JORVICAL ACEROS S A | H20: 6346990.8 | I20: =IF('Jun-26'!$H20="","",'Jun-26'!$H20*0.21) -> 1332868.1 | P20: =SUM('Jun-26'!$H20:$O20) -> 7679858.9 | Q20: =IFERROR(IF('Jun-26'!$F20="","-",VLOOKUP('Jun-26'!$F20,Lista_CUIT!$A$1:$D$2241,3,0)),"CUIT NO CARGADO") -> INSUMO | R20: =IFERROR(IF('Jun-26'!$F20="","-",VLOOKUP('Jun-26'!$F20,Lista_CUIT!$A$1:$D$2241,4,0)),"CUIT NO CARGADO") -> 0
B21: 45813 | C21: 1 | D21: 1 | E21: 947 | F21: 30715048066 | G21: =IFERROR(IF('Jun-26'!$F21="","-",VLOOKUP('Jun-26'!$F21,Lista_CUIT!$A$1:$D$2241,2,0)),"CUIT NO CARGADO") -> ROLLS Y EMPANADAS SA | H21: 780930 | I21: =IF('Jun-26'!$H21="","",'Jun-26'!$H21*0.21) -> 163995.3 | P21: =SUM('Jun-26'!$H21:$O21) -> 944925.3 | Q21: =IFERROR(IF('Jun-26'!$F21="","-",VLOOKUP('Jun-26'!$F21,Lista_CUIT!$A$1:$D$2241,3,0)),"CUIT NO CARGADO") -> CATERING | R21: =IFERROR(IF('Jun-26'!$F21="","-",VLOOKUP('Jun-26'!$F21,Lista_CUIT!$A$1:$D$2241,4,0)),"CUIT NO CARGADO") -> 0
B22: 45815 | C22: 1 | D22: 6 | E22: 14894 | F22: 20304916401 | G22: =IFERROR(IF('Jun-26'!$F22="","-",VLOOKUP('Jun-26'!$F22,Lista_CUIT!$A$1:$D$2241,2,0)),"CUIT NO CARGADO") -> RODRIGUEZ ADRIAN EZEQUIEL | H22: 3694.21 | I22: =IF('Jun-26'!$H22="","",'Jun-26'!$H22*0.21) -> 775.7841 | P22: =SUM('Jun-26'!$H22:$O22) -> 4469.9941 | Q22: =IFERROR(IF('Jun-26'!$F22="","-",VLOOKUP('Jun-26'!$F22,Lista_CUIT!$A$1:$D$2241,3,0)),"CUIT NO CARGADO") -> INSUMO | R22: =IFERROR(IF('Jun-26'!$F22="","-",VLOOKUP('Jun-26'!$F22,Lista_CUIT!$A$1:$D$2241,4,0)),"CUIT NO CARGADO") -> 0
B23: 45817 | C23: 1 | D23: 2 | E23: 799 | F23: 30718028112 | G23: =IFERROR(IF('Jun-26'!$F23="","-",VLOOKUP('Jun-26'!$F23,Lista_CUIT!$A$1:$D$2241,2,0)),"CUIT NO CARGADO") -> WARDON S. R. L. | H23: 3363.62 | I23: =IF('Jun-26'!$H23="","",'Jun-26'!$H23*0.21) -> 706.3602 | P23: =SUM('Jun-26'!$H23:$O23) -> 4069.9802 | Q23: =IFERROR(IF('Jun-26'!$F23="","-",VLOOKUP('Jun-26'!$F23,Lista_CUIT!$A$1:$D$2241,3,0)),"CUIT NO CARGADO") -> Servicios Informaticos | R23: =IFERROR(IF('Jun-26'!$F23="","-",VLOOKUP('Jun-26'!$F23,Lista_CUIT!$A$1:$D$2241,4,0)),"CUIT NO CARGADO") -> 0
B24: 45817 | C24: 1 | D24: 2 | E24: 214 | F24: 20125142851 | G24: =IFERROR(IF('Jun-26'!$F24="","-",VLOOKUP('Jun-26'!$F24,Lista_CUIT!$A$1:$D$2241,2,0)),"CUIT NO CARGADO") -> FEDERICI NICOLAS JOSE | H24: 96536 | I24: =IF('Jun-26'!$H24="","",'Jun-26'!$H24*0.21) -> 20272.56 | P24: =SUM('Jun-26'!$H24:$O24) -> 116808.56 | Q24: =IFERROR(IF('Jun-26'!$F24="","-",VLOOKUP('Jun-26'!$F24,Lista_CUIT!$A$1:$D$2241,3,0)),"CUIT NO CARGADO") -> INSUMO | R24: =IFERROR(IF('Jun-26'!$F24="","-",VLOOKUP('Jun-26'!$F24,Lista_CUIT!$A$1:$D$2241,4,0)),"CUIT NO CARGADO") -> 0
B25: 45825 | C25: 1 | D25: 106 | E25: 849425 | F25: 30594494187 | G25: =IFERROR(IF('Jun-26'!$F25="","-",VLOOKUP('Jun-26'!$F25,Lista_CUIT!$A$1:$D$2241,2,0)),"CUIT NO CARGADO") -> FEDERAL EXPRESS CORPORATION | H25: 100800 | I25: =IF('Jun-26'!$H25="","",'Jun-26'!$H25*0.21) -> 21168 | O25: 546498.3 | P25: =SUM('Jun-26'!$H25:$O25) -> 668466.3 | Q25: =IFERROR(IF('Jun-26'!$F25="","-",VLOOKUP('Jun-26'!$F25,Lista_CUIT!$A$1:$D$2241,3,0)),"CUIT NO CARGADO") -> Mercaderia | R25: =IFERROR(IF('Jun-26'!$F25="","-",VLOOKUP('Jun-26'!$F25,Lista_CUIT!$A$1:$D$2241,4,0)),"CUIT NO CARGADO") -> 0
B26: 45825 | C26: 1 | D26: 106 | E26: 850560 | F26: 30594494187 | G26: =IFERROR(IF('Jun-26'!$F26="","-",VLOOKUP('Jun-26'!$F26,Lista_CUIT!$A$1:$D$2241,2,0)),"CUIT NO CARGADO") -> FEDERAL EXPRESS CORPORATION | H26: 0 | I26: =IF('Jun-26'!$H26="","",'Jun-26'!$H26*0.21) -> 0 | O26: 492360 | P26: =SUM('Jun-26'!$H26:$O26) -> 492360 | Q26: =IFERROR(IF('Jun-26'!$F26="","-",VLOOKUP('Jun-26'!$F26,Lista_CUIT!$A$1:$D$2241,3,0)),"CUIT NO CARGADO") -> Mercaderia | R26: =IFERROR(IF('Jun-26'!$F26="","-",VLOOKUP('Jun-26'!$F26,Lista_CUIT!$A$1:$D$2241,4,0)),"CUIT NO CARGADO") -> 0
B27: 45826 | C27: 1 | D27: 2 | E27: 215 | F27: 20125142851 | G27: =IFERROR(IF('Jun-26'!$F27="","-",VLOOKUP('Jun-26'!$F27,Lista_CUIT!$A$1:$D$2241,2,0)),"CUIT NO CARGADO") -> FEDERICI NICOLAS JOSE | H27: 2285563.7 | I27: =IF('Jun-26'!$H27="","",'Jun-26'!$H27*0.21) -> 479968.37 | P27: =SUM('Jun-26'!$H27:$O27) -> 2765532 | Q27: =IFERROR(IF('Jun-26'!$F27="","-",VLOOKUP('Jun-26'!$F27,Lista_CUIT!$A$1:$D$2241,3,0)),"CUIT NO CARGADO") -> INSUMO | R27: =IFERROR(IF('Jun-26'!$F27="","-",VLOOKUP('Jun-26'!$F27,Lista_CUIT!$A$1:$D$2241,4,0)),"CUIT NO CARGADO") -> 0
B28: 45827 | C28: 1 | D28: 9 | E28: 13627 | F28: 30709531960 | G28: =IFERROR(IF('Jun-26'!$F28="","-",VLOOKUP('Jun-26'!$F28,Lista_CUIT!$A$1:$D$2241,2,0)),"CUIT NO CARGADO") -> CENTRO DE DISTRIBUCION SUR S R L | H28: 34518.43 | I28: =IF('Jun-26'!$H28="","",'Jun-26'!$H28*0.21) -> 7248.8703 | P28: =SUM('Jun-26'!$H28:$O28) -> 41767.3 | Q28: =IFERROR(IF('Jun-26'!$F28="","-",VLOOKUP('Jun-26'!$F28,Lista_CUIT!$A$1:$D$2241,3,0)),"CUIT NO CARGADO") -> LIMPIEZA | R28: =IFERROR(IF('Jun-26'!$F28="","-",VLOOKUP('Jun-26'!$F28,Lista_CUIT!$A$1:$D$2241,4,0)),"CUIT NO CARGADO") -> 0
B29: 45827 | C29: 1 | D29: 9 | E29: 13628 | F29: 30709531960 | G29: =IFERROR(IF('Jun-26'!$F29="","-",VLOOKUP('Jun-26'!$F29,Lista_CUIT!$A$1:$D$2241,2,0)),"CUIT NO CARGADO") -> CENTRO DE DISTRIBUCION SUR S R L | H29: 27561.59 | I29: =IF('Jun-26'!$H29="","",'Jun-26'!$H29*0.21) -> 5787.9339 | P29: =SUM('Jun-26'!$H29:$O29) -> 33349.524 | Q29: =IFERROR(IF('Jun-26'!$F29="","-",VLOOKUP('Jun-26'!$F29,Lista_CUIT!$A$1:$D$2241,3,0)),"CUIT NO CARGADO") -> LIMPIEZA | R29: =IFERROR(IF('Jun-26'!$F29="","-",VLOOKUP('Jun-26'!$F29,Lista_CUIT!$A$1:$D$2241,4,0)),"CUIT NO CARGADO") -> 0
B30: 45828 | C30: 1 | D30: 7002 | E30: 22393 | F30: 30678774495 | G30: =IFERROR(IF('Jun-26'!$F30="","-",VLOOKUP('Jun-26'!$F30,Lista_CUIT!$A$1:$D$2241,2,0)),"CUIT NO CARGADO") -> OPER. DE EST. DE SERV. SA | H30: 32105.45 | I30: =IF('Jun-26'!$H30="","",'Jun-26'!$H30*0.21) -> 6742.1445 | O30: 8962.43 | P30: =SUM('Jun-26'!$H30:$O30) -> 47810.024 | Q30: =IFERROR(IF('Jun-26'!$F30="","-",VLOOKUP('Jun-26'!$F30,Lista_CUIT!$A$1:$D$2241,3,0)),"CUIT NO CARGADO") -> COMBUSTIBLE | R30: =IFERROR(IF('Jun-26'!$F30="","-",VLOOKUP('Jun-26'!$F30,Lista_CUIT!$A$1:$D$2241,4,0)),"CUIT NO CARGADO") -> 0
B31: 45831 | C31: 1 | D31: 1 | E31: 955 | F31: 30715048066 | G31: =IFERROR(IF('Jun-26'!$F31="","-",VLOOKUP('Jun-26'!$F31,Lista_CUIT!$A$1:$D$2241,2,0)),"CUIT NO CARGADO") -> ROLLS Y EMPANADAS SA | H31: 845210 | I31: =IF('Jun-26'!$H31="","",'Jun-26'!$H31*0.21) -> 177494.1 | P31: =SUM('Jun-26'!$H31:$O31) -> 1022704.1 | Q31: =IFERROR(IF('Jun-26'!$F31="","-",VLOOKUP('Jun-26'!$F31,Lista_CUIT!$A$1:$D$2241,3,0)),"CUIT NO CARGADO") -> CATERING | R31: =IFERROR(IF('Jun-26'!$F31="","-",VLOOKUP('Jun-26'!$F31,Lista_CUIT!$A$1:$D$2241,4,0)),"CUIT NO CARGADO") -> 0
B32: 45831 | C32: 1 | D32: 2 | E32: 216 | F32: 20125142851 | G32: =IFERROR(IF('Jun-26'!$F32="","-",VLOOKUP('Jun-26'!$F32,Lista_CUIT!$A$1:$D$2241,2,0)),"CUIT NO CARGADO") -> FEDERICI NICOLAS JOSE | H32: 245728 | I32: =IF('Jun-26'!$H32="","",'Jun-26'!$H32*0.21) -> 51602.88 | P32: =SUM('Jun-26'!$H32:$O32) -> 297330.88 | Q32: =IFERROR(IF('Jun-26'!$F32="","-",VLOOKUP('Jun-26'!$F32,Lista_CUIT!$A$1:$D$2241,3,0)),"CUIT NO CARGADO") -> INSUMO | R32: =IFERROR(IF('Jun-26'!$F32="","-",VLOOKUP('Jun-26'!$F32,Lista_CUIT!$A$1:$D$2241,4,0)),"CUIT NO CARGADO") -> 0
B33: 45832 | C33: 1 | D33: 2 | E33: 882 | F33: 20296550184 | G33: =IFERROR(IF('Jun-26'!$F33="","-",VLOOKUP('Jun-26'!$F33,Lista_CUIT!$A$1:$D$2241,2,0)),"CUIT NO CARGADO") -> COSTA DIEGO ALEJANDRO | H33: 1007200 | I33: =IF('Jun-26'!$H33="","",'Jun-26'!$H33*0.21) -> 211512 | P33: =SUM('Jun-26'!$H33:$O33) -> 1218712 | Q33: =IFERROR(IF('Jun-26'!$F33="","-",VLOOKUP('Jun-26'!$F33,Lista_CUIT!$A$1:$D$2241,3,0)),"CUIT NO CARGADO") -> Mat. Prima | R33: =IFERROR(IF('Jun-26'!$F33="","-",VLOOKUP('Jun-26'!$F33,Lista_CUIT!$A$1:$D$2241,4,0)),"CUIT NO CARGADO") -> 0
B34: 45833 | C34: 1 | D34: 6 | E34: 33256 | F34: 30708855533 | G34: =IFERROR(IF('Jun-26'!$F34="","-",VLOOKUP('Jun-26'!$F34,Lista_CUIT!$A$1:$D$2241,2,0)),"CUIT NO CARGADO") -> NOVARCHEM SA | H34: 107004 | I34: =IF('Jun-26'!$H34="","",'Jun-26'!$H34*0.21) -> 22470.84 | P34: =SUM('Jun-26'!$H34:$O34) -> 129474.84 | Q34: =IFERROR(IF('Jun-26'!$F34="","-",VLOOKUP('Jun-26'!$F34,Lista_CUIT!$A$1:$D$2241,3,0)),"CUIT NO CARGADO") -> INSUMO | R34: =IFERROR(IF('Jun-26'!$F34="","-",VLOOKUP('Jun-26'!$F34,Lista_CUIT!$A$1:$D$2241,4,0)),"CUIT NO CARGADO") -> 0
B35: 45833 | C35: 1 | D35: 11 | E35: 4271 | F35: 30646811062 | G35: =IFERROR(IF('Jun-26'!$F35="","-",VLOOKUP('Jun-26'!$F35,Lista_CUIT!$A$1:$D$2241,2,0)),"CUIT NO CARGADO") -> POLINORTE S A | H35: 107157.02 | I35: =IF('Jun-26'!$H35="","",'Jun-26'!$H35*0.21) -> 22502.974 | P35: =SUM('Jun-26'!$H35:$O35) -> 129659.99 | Q35: =IFERROR(IF('Jun-26'!$F35="","-",VLOOKUP('Jun-26'!$F35,Lista_CUIT!$A$1:$D$2241,3,0)),"CUIT NO CARGADO") -> INSUMO | R35: =IFERROR(IF('Jun-26'!$F35="","-",VLOOKUP('Jun-26'!$F35,Lista_CUIT!$A$1:$D$2241,4,0)),"CUIT NO CARGADO") -> 0
B36: 45834 | C36: 1 | D36: 11 | E36: 4282 | F36: 30646811062 | G36: =IFERROR(IF('Jun-26'!$F36="","-",VLOOKUP('Jun-26'!$F36,Lista_CUIT!$A$1:$D$2241,2,0)),"CUIT NO CARGADO") -> POLINORTE S A | H36: 107122.31 | I36: =IF('Jun-26'!$H36="","",'Jun-26'!$H36*0.21) -> 22495.685 | P36: =SUM('Jun-26'!$H36:$O36) -> 129618 | Q36: =IFERROR(IF('Jun-26'!$F36="","-",VLOOKUP('Jun-26'!$F36,Lista_CUIT!$A$1:$D$2241,3,0)),"CUIT NO CARGADO") -> INSUMO | R36: =IFERROR(IF('Jun-26'!$F36="","-",VLOOKUP('Jun-26'!$F36,Lista_CUIT!$A$1:$D$2241,4,0)),"CUIT NO CARGADO") -> 0
B37: 45838 | C37: 1 | D37: 106 | E37: 854361 | F37: 30594494187 | G37: =IFERROR(IF('Jun-26'!$F37="","-",VLOOKUP('Jun-26'!$F37,Lista_CUIT!$A$1:$D$2241,2,0)),"CUIT NO CARGADO") -> FEDERAL EXPRESS CORPORATION | H37: 0 | I37: =IF('Jun-26'!$H37="","",'Jun-26'!$H37*0.21) -> 0 | O37: 769778.1 | P37: =SUM('Jun-26'!$H37:$O37) -> 769778.1 | Q37: =IFERROR(IF('Jun-26'!$F37="","-",VLOOKUP('Jun-26'!$F37,Lista_CUIT!$A$1:$D$2241,3,0)),"CUIT NO CARGADO") -> Mercaderia | R37: =IFERROR(IF('Jun-26'!$F37="","-",VLOOKUP('Jun-26'!$F37,Lista_CUIT!$A$1:$D$2241,4,0)),"CUIT NO CARGADO") -> 0
B38: 45812 | C38: 3 | D38: 8 | E38: 6302 | F38: 30709953482 | G38: =IFERROR(IF('Jun-26'!$F38="","-",VLOOKUP('Jun-26'!$F38,Lista_CUIT!$A$1:$D$2241,2,0)),"CUIT NO CARGADO") -> HONRE S.A | H38: -7189.26 | I38: =IF('Jun-26'!$H38="","",'Jun-26'!$H38*0.21) -> -1509.7446 | P38: =SUM('Jun-26'!$H38:$O38) -> -8699.0046 | Q38: =IFERROR(IF('Jun-26'!$F38="","-",VLOOKUP('Jun-26'!$F38,Lista_CUIT!$A$1:$D$2241,3,0)),"CUIT NO CARGADO") -> GASTOS VARIOS | R38: =IFERROR(IF('Jun-26'!$F38="","-",VLOOKUP('Jun-26'!$F38,Lista_CUIT!$A$1:$D$2241,4,0)),"CUIT NO CARGADO") -> 0
B39: 45812 | C39: 3 | D39: 10 | E39: 4501 | F39: 20357275882 | G39: =IFERROR(IF('Jun-26'!$F39="","-",VLOOKUP('Jun-26'!$F39,Lista_CUIT!$A$1:$D$2241,2,0)),"CUIT NO CARGADO") -> LAVADERO BLANCANIEVES | H39: -7429.75 | I39: =IF('Jun-26'!$H39="","",'Jun-26'!$H39*0.21) -> -1560.2475 | P39: =SUM('Jun-26'!$H39:$O39) -> -8989.9975 | Q39: =IFERROR(IF('Jun-26'!$F39="","-",VLOOKUP('Jun-26'!$F39,Lista_CUIT!$A$1:$D$2241,3,0)),"CUIT NO CARGADO") -> Seg e Higiene | R39: =IFERROR(IF('Jun-26'!$F39="","-",VLOOKUP('Jun-26'!$F39,Lista_CUIT!$A$1:$D$2241,4,0)),"CUIT NO CARGADO") -> 0
B40: 45834 | C40: 3 | D40: 11 | E40: 247 | F40: 30646811062 | G40: =IFERROR(IF('Jun-26'!$F40="","-",VLOOKUP('Jun-26'!$F40,Lista_CUIT!$A$1:$D$2241,2,0)),"CUIT NO CARGADO") -> POLINORTE S A | H40: -107157.02 | I40: =IF('Jun-26'!$H40="","",'Jun-26'!$H40*0.21) -> -22502.974 | P40: =SUM('Jun-26'!$H40:$O40) -> -129659.99 | Q40: =IFERROR(IF('Jun-26'!$F40="","-",VLOOKUP('Jun-26'!$F40,Lista_CUIT!$A$1:$D$2241,3,0)),"CUIT NO CARGADO") -> INSUMO | R40: =IFERROR(IF('Jun-26'!$F40="","-",VLOOKUP('Jun-26'!$F40,Lista_CUIT!$A$1:$D$2241,4,0)),"CUIT NO CARGADO") -> 0
G41: =IFERROR(IF('Jun-26'!$F41="","-",VLOOKUP('Jun-26'!$F41,Lista_CUIT!$A$1:$D$2241,2,0)),"CUIT NO CARGADO") -> - | I41: =IF('Jun-26'!$H41="","",'Jun-26'!$H41*0.21) | P41: =SUM('Jun-26'!$H41:$O41) -> 0 | Q41: =IFERROR(IF('Jun-26'!$F41="","-",VLOOKUP('Jun-26'!$F41,Lista_CUIT!$A$1:$D$2241,3,0)),"CUIT NO CARGADO") -> - | R41: =IFERROR(IF('Jun-26'!$F41="","-",VLOOKUP('Jun-26'!$F41,Lista_CUIT!$A$1:$D$2241,4,0)),"CUIT NO CARGADO") -> - | S41: COD 5
G42: =IFERROR(IF('Jun-26'!$F42="","-",VLOOKUP('Jun-26'!$F42,Lista_CUIT!$A$1:$D$2241,2,0)),"CUIT NO CARGADO") -> - | I42: =IF('Jun-26'!$H42="","",'Jun-26'!$H42*0.21) | P42: =SUM('Jun-26'!$H42:$O42) -> 0 | Q42: =IFERROR(IF('Jun-26'!$F42="","-",VLOOKUP('Jun-26'!$F42,Lista_CUIT!$A$1:$D$2241,3,0)),"CUIT NO CARGADO") -> - | R42: =IFERROR(IF('Jun-26'!$F42="","-",VLOOKUP('Jun-26'!$F42,Lista_CUIT!$A$1:$D$2241,4,0)),"CUIT NO CARGADO") -> - | S42: COD 5
G43: =IFERROR(IF('Jun-26'!$F43="","-",VLOOKUP('Jun-26'!$F43,Lista_CUIT!$A$1:$D$2241,2,0)),"CUIT NO CARGADO") -> - | I43: =IF('Jun-26'!$H43="","",'Jun-26'!$H43*0.21) | P43: =SUM('Jun-26'!$H43:$O43) -> 0 | Q43: =IFERROR(IF('Jun-26'!$F43="","-",VLOOKUP('Jun-26'!$F43,Lista_CUIT!$A$1:$D$2241,3,0)),"CUIT NO CARGADO") -> - | R43: =IFERROR(IF('Jun-26'!$F43="","-",VLOOKUP('Jun-26'!$F43,Lista_CUIT!$A$1:$D$2241,4,0)),"CUIT NO CARGADO") -> -
B44: Total | H44: =SUBTOTAL(109,'Jun-26'!$H$9:$H$43) -> 12746809 | I44: =SUBTOTAL(109,'Jun-26'!$I$9:$I$43) -> 2676829.8 | J44: =SUBTOTAL(109,'Jun-26'!$J$9:$J$43) -> 0 | K44: =SUBTOTAL(109,'Jun-26'!$K$9:$K$43) -> 0 | L44: =SUBTOTAL(109,'Jun-26'!$L$9:$L$43) -> 0 | M44: =SUBTOTAL(109,'Jun-26'!$M$9:$M$43) -> 0 | N44: =SUBTOTAL(109,'Jun-26'!$N$9:$N$43) -> 0 | O44: =SUBTOTAL(109,'Jun-26'!$O$9:$O$43) -> 2095131.3 | P44: =SUBTOTAL(109,'Jun-26'!$P$9:$P$43) -> 17518770
D48: LIQUIDACION EXTRACTOS BANCARIOS-TARJETAS
D49: FECHA | E49: NRO CPTE | F49: BANCO | G49: NETO | H49: IVA 21% | I49: IVA 10,5% | J49: RET IIBB CABA | K49: PERC IVA | L49: PERC IIBB
C50: SEG EMBQ | D50: 45821 | E50: 1119704000 | F50: CREDICOOP | G50: 29550 | H50: ='Jun-26'!$G50*0.21 -> 6205.5 | K50: 886.5
H51: ='Jun-26'!$G51*0.21 -> 0
H52: ='Jun-26'!$G52*0.21 -> 0
D53: Total | G53: =SUBTOTAL(109,'Jun-26'!$G$50:$G$52) -> 29550 | H53: =SUBTOTAL(109,'Jun-26'!$H$50:$H$52) -> 6205.5 | I53: =SUBTOTAL(109,'Jun-26'!$I$50:$I$52) -> 0 | J53: =SUBTOTAL(109,'Jun-26'!$J$50:$J$52) -> 0 | K53: =SUBTOTAL(109,'Jun-26'!$K$50:$K$52) -> 886.5 | L53: =SUBTOTAL(109,'Jun-26'!$L$50:$L$52) -> 0
D55: FACTURAS C
D56: FECHA | E56: PTO VTA | F56: FC Nº | G56: CUIT | H56: RAZON SOCIAL | I56: TOTAL | J56: TIPO DE GASTO | K56: Provincia
D57: 45809 | E57: 1 | F57: 50 | G57: 20365938688 | H57: =IFERROR(IF('Jun-26'!$G57="","-",VLOOKUP('Jun-26'!$G57,Lista_CUIT!$A$1:$D$2241,2,0)),"CUIT NO CARGADO") -> LIPANOVICH JUAN CRUZ | I57: 1476679 | J57: =IFERROR(IF('Jun-26'!$G57="","-",VLOOKUP('Jun-26'!$G57,Lista_CUIT!$A$1:$D$2241,3,0)),"CUIT NO CARGADO") -> SOFTWARE | K57: =IFERROR(IF('Jun-26'!$G57="","-",VLOOKUP('Jun-26'!$G57,Lista_CUIT!$A$1:$D$2241,4,0)),"CUIT NO CARGADO") -> 0
D58: 45810 | E58: 4 | F58: 30 | G58: 20086277523 | H58: =IFERROR(IF('Jun-26'!$G58="","-",VLOOKUP('Jun-26'!$G58,Lista_CUIT!$A$1:$D$2241,2,0)),"CUIT NO CARGADO") -> ESTUDIO BOTINDARI | I58: 335000 | J58: =IFERROR(IF('Jun-26'!$G58="","-",VLOOKUP('Jun-26'!$G58,Lista_CUIT!$A$1:$D$2241,3,0)),"CUIT NO CARGADO") -> Honorarios Contables | K58: =IFERROR(IF('Jun-26'!$G58="","-",VLOOKUP('Jun-26'!$G58,Lista_CUIT!$A$1:$D$2241,4,0)),"CUIT NO CARGADO") -> 0
D59: 45810 | E59: 1 | F59: 41 | G59: 27387896150 | H59: =IFERROR(IF('Jun-26'!$G59="","-",VLOOKUP('Jun-26'!$G59,Lista_CUIT!$A$1:$D$2241,2,0)),"CUIT NO CARGADO") -> LIPANOVICH MARIA SOL | I59: 1722951 | J59: =IFERROR(IF('Jun-26'!$G59="","-",VLOOKUP('Jun-26'!$G59,Lista_CUIT!$A$1:$D$2241,3,0)),"CUIT NO CARGADO") -> consultoria informatica | K59: =IFERROR(IF('Jun-26'!$G59="","-",VLOOKUP('Jun-26'!$G59,Lista_CUIT!$A$1:$D$2241,4,0)),"CUIT NO CARGADO") -> 0
D60: 45810 | E60: 1 | F60: 113 | G60: 20341465134 | H60: =IFERROR(IF('Jun-26'!$G60="","-",VLOOKUP('Jun-26'!$G60,Lista_CUIT!$A$1:$D$2241,2,0)),"CUIT NO CARGADO") -> ABELEDO AGUSTIN ENRIQUE | I60: 2248500 | J60: =IFERROR(IF('Jun-26'!$G60="","-",VLOOKUP('Jun-26'!$G60,Lista_CUIT!$A$1:$D$2241,3,0)),"CUIT NO CARGADO") -> Mantenimiento | K60: =IFERROR(IF('Jun-26'!$G60="","-",VLOOKUP('Jun-26'!$G60,Lista_CUIT!$A$1:$D$2241,4,0)),"CUIT NO CARGADO") -> CABA
D61: 45810 | E61: 2 | F61: 281 | G61: 27173820866 | H61: =IFERROR(IF('Jun-26'!$G61="","-",VLOOKUP('Jun-26'!$G61,Lista_CUIT!$A$1:$D$2241,2,0)),"CUIT NO CARGADO") -> FREIER SANDRA DANIELA | I61: 1120000 | J61: =IFERROR(IF('Jun-26'!$G61="","-",VLOOKUP('Jun-26'!$G61,Lista_CUIT!$A$1:$D$2241,3,0)),"CUIT NO CARGADO") -> Honorarios Prof | K61: =IFERROR(IF('Jun-26'!$G61="","-",VLOOKUP('Jun-26'!$G61,Lista_CUIT!$A$1:$D$2241,4,0)),"CUIT NO CARGADO") -> 0
D62: 45811 | E62: 1 | F62: 30 | G62: 20419155870 | H62: =IFERROR(IF('Jun-26'!$G62="","-",VLOOKUP('Jun-26'!$G62,Lista_CUIT!$A$1:$D$2241,2,0)),"CUIT NO CARGADO") -> GULLO GASPAR | I62: 75000 | J62: =IFERROR(IF('Jun-26'!$G62="","-",VLOOKUP('Jun-26'!$G62,Lista_CUIT!$A$1:$D$2241,3,0)),"CUIT NO CARGADO") -> Honorarios Contables | K62: =IFERROR(IF('Jun-26'!$G62="","-",VLOOKUP('Jun-26'!$G62,Lista_CUIT!$A$1:$D$2241,4,0)),"CUIT NO CARGADO") -> 0
D63: 45811 | E63: 2 | F63: 20 | G63: 23118167279 | H63: =IFERROR(IF('Jun-26'!$G63="","-",VLOOKUP('Jun-26'!$G63,Lista_CUIT!$A$1:$D$2241,2,0)),"CUIT NO CARGADO") -> ABELEDO ENRIQUE JUAN | I63: 2756000 | J63: =IFERROR(IF('Jun-26'!$G63="","-",VLOOKUP('Jun-26'!$G63,Lista_CUIT!$A$1:$D$2241,3,0)),"CUIT NO CARGADO") -> Honorarios Admin | K63: =IFERROR(IF('Jun-26'!$G63="","-",VLOOKUP('Jun-26'!$G63,Lista_CUIT!$A$1:$D$2241,4,0)),"CUIT NO CARGADO") -> 0
D64: 45811 | E64: 1 | F64: 152 | G64: 20389908569 | H64: =IFERROR(IF('Jun-26'!$G64="","-",VLOOKUP('Jun-26'!$G64,Lista_CUIT!$A$1:$D$2241,2,0)),"CUIT NO CARGADO") -> BOTINDARI JUAN IGNACIO | I64: 102700 | J64: =IFERROR(IF('Jun-26'!$G64="","-",VLOOKUP('Jun-26'!$G64,Lista_CUIT!$A$1:$D$2241,3,0)),"CUIT NO CARGADO") -> Honorarios Contables | K64: =IFERROR(IF('Jun-26'!$G64="","-",VLOOKUP('Jun-26'!$G64,Lista_CUIT!$A$1:$D$2241,4,0)),"CUIT NO CARGADO") -> 0
D65: 45812 | E65: 4 | F65: 94 | G65: 23214737914 | H65: =IFERROR(IF('Jun-26'!$G65="","-",VLOOKUP('Jun-26'!$G65,Lista_CUIT!$A$1:$D$2241,2,0)),"CUIT NO CARGADO") -> SBARRA GABRIELA BEATRIZ | I65: 1332330 | J65: =IFERROR(IF('Jun-26'!$G65="","-",VLOOKUP('Jun-26'!$G65,Lista_CUIT!$A$1:$D$2241,3,0)),"CUIT NO CARGADO") -> Honorarios Admin | K65: =IFERROR(IF('Jun-26'!$G65="","-",VLOOKUP('Jun-26'!$G65,Lista_CUIT!$A$1:$D$2241,4,0)),"CUIT NO CARGADO") -> 0
D66: 45813 | E66: 1 | F66: 137 | G66: 20307805880 | H66: =IFERROR(IF('Jun-26'!$G66="","-",VLOOKUP('Jun-26'!$G66,Lista_CUIT!$A$1:$D$2241,2,0)),"CUIT NO CARGADO") -> CUIT NO CARGADO | I66: 400000 | J66: =IFERROR(IF('Jun-26'!$G66="","-",VLOOKUP('Jun-26'!$G66,Lista_CUIT!$A$1:$D$2241,3,0)),"CUIT NO CARGADO") -> CUIT NO CARGADO | K66: =IFERROR(IF('Jun-26'!$G66="","-",VLOOKUP('Jun-26'!$G66,Lista_CUIT!$A$1:$D$2241,4,0)),"CUIT NO CARGADO") -> CUIT NO CARGADO
D67: 45814 | E67: 1 | F67: 829 | G67: 20332167481 | H67: =IFERROR(IF('Jun-26'!$G67="","-",VLOOKUP('Jun-26'!$G67,Lista_CUIT!$A$1:$D$2241,2,0)),"CUIT NO CARGADO") -> AGUIRRE GABRIEL ADRIAN | I67: 19280 | J67: =IFERROR(IF('Jun-26'!$G67="","-",VLOOKUP('Jun-26'!$G67,Lista_CUIT!$A$1:$D$2241,3,0)),"CUIT NO CARGADO") -> GASTOS VARIOS | K67: =IFERROR(IF('Jun-26'!$G67="","-",VLOOKUP('Jun-26'!$G67,Lista_CUIT!$A$1:$D$2241,4,0)),"CUIT NO CARGADO") -> 0
D68: 45814 | E68: 2 | F68: 184 | G68: 20136544625 | H68: =IFERROR(IF('Jun-26'!$G68="","-",VLOOKUP('Jun-26'!$G68,Lista_CUIT!$A$1:$D$2241,2,0)),"CUIT NO CARGADO") -> RODRIGUEZ DE LA FUEN HECTOR MARCELO | I68: 925000 | J68: =IFERROR(IF('Jun-26'!$G68="","-",VLOOKUP('Jun-26'!$G68,Lista_CUIT!$A$1:$D$2241,3,0)),"CUIT NO CARGADO") -> Honorarios Admin | K68: =IFERROR(IF('Jun-26'!$G68="","-",VLOOKUP('Jun-26'!$G68,Lista_CUIT!$A$1:$D$2241,4,0)),"CUIT NO CARGADO") -> 0
... D72: 45838 | E72: 2 | F72: 199 | G72: 27125997835 | H72: =IFERROR(IF('Jun-26'!$G72="","-",VLOOKUP('Jun-26'!$G72,Lista_CUIT!$A$1:$D$2241,2,0)),"CUIT NO CARGADO") -> DANSKY ULLMANN VIVIANA EVA YOLANDA | I72: 170000 | J72: =IFERROR(IF('Jun-26'!$G72="","-",VLOOKUP('Jun-26'!$G72,Lista_CUIT!$A$1:$D$2241,3,0)),"CUIT NO CARGADO") -> Honorarios Prof | K72: =IFERROR(IF('Jun-26'!$G72="","-",VLOOKUP('Jun-26'!$G72,Lista_CUIT!$A$1:$D$2241,4,0)),"CUIT NO CARGADO") -> 0
H73: =IFERROR(IF('Jun-26'!$G73="","-",VLOOKUP('Jun-26'!$G73,Lista_CUIT!$A$1:$D$2241,2,0)),"CUIT NO CARGADO") -> - | J73: =IFERROR(IF('Jun-26'!$G73="","-",VLOOKUP('Jun-26'!$G73,Lista_CUIT!$A$1:$D$2241,3,0)),"CUIT NO CARGADO") -> - | K73: =IFERROR(IF('Jun-26'!$G73="","-",VLOOKUP('Jun-26'!$G73,Lista_CUIT!$A$1:$D$2241,4,0)),"CUIT NO CARGADO") -> -
D74: Total | I74: =SUBTOTAL(109,'Jun-26'!$I$57:$I$73) -> 15450940
B80: LIBRO IVA VENTAS | K80: =N1 -> 45809
B82: VENTAS "A"
B83: FECHA | C83: TIPO | D83: PTO VENTA | E83: Nº FACTURA | F83: CUIT | G83: RAZON SOCIAL | H83: IMPORTE NETO | I83: IVA 21% | J83: IVA 10,5% | K83: EXENTO | L83: TOTAL | M83: Provincia
B84: 45814 | C84: 1 | D84: 3 | E84: 278 | F84: 20215856314 | G84: =IFERROR(IF('Jun-26'!$F84="","-",VLOOKUP('Jun-26'!$F84,Lista_CUIT!$A$1:$D$2241,2,0)),"CUIT NO CARGADO") -> GUGLIELMI GUSTAVO FABIAN | H84: =10400*1200 -> 12480000 | J84: =Table_19[[#This Row],[IMPORTE NETO]]*0.105 -> 1310400 | L84: =SUM('Jun-26'!$H84:$K84) -> 13790400
B85: 45821 | C85: 1 | D85: 3 | E85: 279 | F85: 30628274327 | G85: =IFERROR(IF('Jun-26'!$F85="","-",VLOOKUP('Jun-26'!$F85,Lista_CUIT!$A$1:$D$2241,2,0)),"CUIT NO CARGADO") -> AGIRA S A | H85: =22850*1175 -> 26848750 | J85: =Table_19[[#This Row],[IMPORTE NETO]]*0.105 -> 2819118.8 | L85: =SUM('Jun-26'!$H85:$K85) -> 29667869
B86: 45831 | C86: 1 | D86: 3 | E86: 280 | F86: 30638318470 | G86: =IFERROR(IF('Jun-26'!$F86="","-",VLOOKUP('Jun-26'!$F86,Lista_CUIT!$A$1:$D$2241,2,0)),"CUIT NO CARGADO") -> DELTA COMPRESION S R L | H86: =23989.6*1185 -> 28427676 | I86: =1480.42*1185 -> 1754297.7 | J86: =1778.7*1185 -> 2107759.5 | L86: =SUM('Jun-26'!$H86:$K86) -> 32289733
B87: 45833 | C87: 1 | D87: 3 | E87: 281 | F87: 30571048619 | G87: =IFERROR(IF('Jun-26'!$F87="","-",VLOOKUP('Jun-26'!$F87,Lista_CUIT!$A$1:$D$2241,2,0)),"CUIT NO CARGADO") -> SERVICIO ESCALADA SA | H87: =400*1195 -> 478000 | I87: ='Jun-26'!$H87*0.21 -> 100380 | L87: =SUM('Jun-26'!$H87:$K87) -> 578380
G88: =IFERROR(IF('Jun-26'!$F88="","-",VLOOKUP('Jun-26'!$F88,Lista_CUIT!$A$1:$D$2241,2,0)),"CUIT NO CARGADO") -> - | I88: ='Jun-26'!$H88*0.21 -> 0 | L88: =SUM('Jun-26'!$H88:$K88) -> 0
G89: =IFERROR(IF('Jun-26'!$F89="","-",VLOOKUP('Jun-26'!$F89,Lista_CUIT!$A$1:$D$2241,2,0)),"CUIT NO CARGADO") -> - | I89: ='Jun-26'!$H89*0.21 -> 0 | L89: =SUM('Jun-26'!$H89:$K89) -> 0
G90: =IFERROR(IF('Jun-26'!$F90="","-",VLOOKUP('Jun-26'!$F90,Lista_CUIT!$A$1:$D$2241,2,0)),"CUIT NO CARGADO") -> - | I90: ='Jun-26'!$H90*0.21 -> 0 | L90: =SUM('Jun-26'!$H90:$K90) -> 0
G91: =IFERROR(IF('Jun-26'!$F91="","-",VLOOKUP('Jun-26'!$F91,Lista_CUIT!$A$1:$D$2241,2,0)),"CUIT NO CARGADO") -> - | I91: ='Jun-26'!$H91*0.21 -> 0 | L91: =SUM('Jun-26'!$H91:$K91) -> 0
G92: =IFERROR(IF('Jun-26'!$F92="","-",VLOOKUP('Jun-26'!$F92,Lista_CUIT!$A$1:$D$2241,2,0)),"CUIT NO CARGADO") -> - | I92: ='Jun-26'!$H92*0.21 -> 0 | L92: =SUM('Jun-26'!$H92:$K92) -> 0
B93: Total | H93: =SUBTOTAL(109,'Jun-26'!$H$84:$H$92) -> 68234426 | I93: =SUBTOTAL(109,'Jun-26'!$I$84:$I$92) -> 1854677.7 | J93: =SUBTOTAL(109,'Jun-26'!$J$84:$J$92) -> 6237278.2 | K93: =SUBTOTAL(109,'Jun-26'!$K$84:$K$92) -> 0 | L93: =SUBTOTAL(109,'Jun-26'!$L$84:$L$92) -> 76326382 | M93: =SUBTOTAL(103,'Jun-26'!$M$84:$M$92) -> 0
B96: VENTAS "B"
B97: FECHA | C97: TIPO | D97: PTO VENTA | E97: Nº FACTURA | F97: CUIT | G97: RAZON SOCIAL | H97: IMPORTE NETO | I97: IVA 21% | J97: IVA 10,5% | K97: EXENTO | L97: TOTAL | M97: Provincia
G98: =IFERROR(IF('Jun-26'!$F98="","-",VLOOKUP('Jun-26'!$F98,Lista_CUIT!$A$1:$D$2241,2,0)),"CUIT NO CARGADO") -> - | L98: =SUM('Jun-26'!$H98:$K98) -> 0
L99: =SUM('Jun-26'!$H99:$K99) -> 0
L100: =SUM('Jun-26'!$H100:$K100) -> 0
L101: =SUM('Jun-26'!$H101:$K101) -> 0
L102: =SUM('Jun-26'!$H102:$K102) -> 0
L103: =SUM('Jun-26'!$H103:$K103) -> 0
B104: Total | H104: =SUBTOTAL(109,'Jun-26'!$H$98:$H$103) -> 0 | I104: =SUBTOTAL(109,'Jun-26'!$I$98:$I$103) -> 0 | J104: =SUBTOTAL(109,'Jun-26'!$J$98:$J$103) -> 0 | K104: =SUBTOTAL(109,'Jun-26'!$K$98:$K$103) -> 0 | L104: =SUBTOTAL(109,'Jun-26'!$L$98:$L$103) -> 0 | M104: =SUBTOTAL(103,'Jun-26'!$M$98:$M$103) -> 0
B107: VENTAS "E"
B108: FECHA | C108: TIPO | D108: PTO VENTA | E108: Nº FACTURA | F108: CUIT | G108: RAZON SOCIAL | H108: USD | I108: Columna2 | J108: Columna1 | K108: TIPO DE CAMBIO2 | L108: TOTAL | M108: Provincia
B109: 45811 | D109: 30 | E109: 24 | F109: 55000000050 | G109: =IFERROR(IF('Jun-26'!$F109="","-",VLOOKUP('Jun-26'!$F109,Lista_CUIT!$A$1:$D$2241,2,0)),"CUIT NO CARGADO") -> GAS FUTURO SISTEMAS DE COMPRESSÃO LTDA | H109: -7215 | K109: 1180.5 | L109: =H109*K109 -> -8517307.5
B110: 45813 | D110: 30 | E110: 109 | F110: 55000000050 | G110: =IFERROR(IF('Jun-26'!$F110="","-",VLOOKUP('Jun-26'!$F110,Lista_CUIT!$A$1:$D$2241,2,0)),"CUIT NO CARGADO") -> GAS FUTURO SISTEMAS DE COMPRESSÃO LTDA | H110: 7215 | K110: 1185.5 | L110: =H110*K110 -> 8553382.5
G111: =IFERROR(IF('Jun-26'!$F111="","-",VLOOKUP('Jun-26'!$F111,Lista_CUIT!$A$1:$D$2241,2,0)),"CUIT NO CARGADO") -> - | I111: ='Jun-26'!$H111*0.21 -> 0 | K111: ='Jun-26'!$H111*'Jun-26'!$J111 -> 0 | L111: =H111*K111 -> 0
G112: =IFERROR(IF('Jun-26'!$F112="","-",VLOOKUP('Jun-26'!$F112,Lista_CUIT!$A$1:$D$2241,2,0)),"CUIT NO CARGADO") -> - | I112: ='Jun-26'!$H112*0.21 -> 0 | K112: ='Jun-26'!$H112*'Jun-26'!$J112 -> 0 | L112: =H112*K112 -> 0
G113: =IFERROR(IF('Jun-26'!$F113="","-",VLOOKUP('Jun-26'!$F113,Lista_CUIT!$A$1:$D$2241,2,0)),"CUIT NO CARGADO") -> - | I113: ='Jun-26'!$H113*0.21 -> 0 | K113: ='Jun-26'!$H113*'Jun-26'!$J113 -> 0 | L113: =H113*K113 -> 0
G114: =IFERROR(IF('Jun-26'!$F114="","-",VLOOKUP('Jun-26'!$F114,Lista_CUIT!$A$1:$D$2241,2,0)),"CUIT NO CARGADO") -> - | I114: ='Jun-26'!$H114*0.21 -> 0 | K114: ='Jun-26'!$H114*'Jun-26'!$J114 -> 0 | L114: =H114*K114 -> 0
G115: =IFERROR(IF('Jun-26'!$F115="","-",VLOOKUP('Jun-26'!$F115,Lista_CUIT!$A$1:$D$2241,2,0)),"CUIT NO CARGADO") -> - | I115: ='Jun-26'!$H115*0.21 -> 0 | K115: ='Jun-26'!$H115*'Jun-26'!$J115 -> 0 | L115: =H115*K115 -> 0
G116: =IFERROR(IF('Jun-26'!$F116="","-",VLOOKUP('Jun-26'!$F116,Lista_CUIT!$A$1:$D$2241,2,0)),"CUIT NO CARGADO") -> - | I116: ='Jun-26'!$H116*0.21 -> 0 | K116: ='Jun-26'!$H116*'Jun-26'!$J116 -> 0 | L116: =H116*K116 -> 0
G117: =IFERROR(IF('Jun-26'!$F117="","-",VLOOKUP('Jun-26'!$F117,Lista_CUIT!$A$1:$D$2241,2,0)),"CUIT NO CARGADO") -> - | I117: ='Jun-26'!$H117*0.21 -> 0 | K117: ='Jun-26'!$H117*'Jun-26'!$J117 -> 0 | L117: =H117*K117 -> 0
G118: =IFERROR(IF('Jun-26'!$F118="","-",VLOOKUP('Jun-26'!$F118,Lista_CUIT!$A$1:$D$2241,2,0)),"CUIT NO CARGADO") -> - | I118: ='Jun-26'!$H118*0.21 -> 0 | K118: ='Jun-26'!$H118*'Jun-26'!$J118 -> 0 | L118: =H118*K118 -> 0
G119: =IFERROR(IF('Jun-26'!$F119="","-",VLOOKUP('Jun-26'!$F119,Lista_CUIT!$A$1:$D$2241,2,0)),"CUIT NO CARGADO") -> - | I119: ='Jun-26'!$H119*0.21 -> 0 | K119: ='Jun-26'!$H119*'Jun-26'!$J119 -> 0 | L119: =H119*K119 -> 0
G120: =IFERROR(IF('Jun-26'!$F120="","-",VLOOKUP('Jun-26'!$F120,Lista_CUIT!$A$1:$D$2241,2,0)),"CUIT NO CARGADO") -> - | I120: ='Jun-26'!$H120*0.21 -> 0 | K120: ='Jun-26'!$H120*'Jun-26'!$J120 -> 0 | L120: =H120*K120 -> 0
G121: =IFERROR(IF('Jun-26'!$F121="","-",VLOOKUP('Jun-26'!$F121,Lista_CUIT!$A$1:$D$2241,2,0)),"CUIT NO CARGADO") -> - | I121: ='Jun-26'!$H121*0.21 -> 0 | K121: ='Jun-26'!$H121*'Jun-26'!$J121 -> 0 | L121: =H121*K121 -> 0
...

Sheet Jul-26
B1: LIBRO IVA COMPRAS | G1: ='Abr-26'!G1:M1 -> CORITEC S. R. L. | N1: =EDATE('Abr-26'!N1,3) -> 45839
B3: TOTAL COMPRAS | G3: TOTAL CREDITO FISCAL | J3: TOTAL VENTAS NETAS | M3: TOTAL DEBITO FISCAL | P3: RESULTADO
B4: =SUM('Jul-26'!$H$35)+'Jul-26'!$G$47 -> 15690898 | G4: ='Jul-26'!$I$35+'Jul-26'!$J$35+'Jul-26'!$K$35+'Jul-26'!$H$47+'Jul-26'!$I$47 -> 3289065 | J4: ='Jul-26'!$H$90+'Jul-26'!$H$100 -> 52120400 | M4: ='Jul-26'!$I$90+'Jul-26'!$J$90+'Jul-26'!$I$100+'Jul-26'!$J$100 -> 5472642 | P4: =G4-M4 -> -2183577
B8: FECHA | C8: TIPO | D8: PTO VTA | E8: NRO. CPTE | F8: CUIT | G8: RAZON SOCIAL | H8: NETO GRAVADO | I8: IVA 21 % | J8: IVA 27% | K8: IVA 10,5% | L8: PERC. IVA | M8: PERC IIBB BS AS | N8: PERC. IIBB CABA | O8: Otros / No Grav. | P8: TOTAL | Q8: Tipo de Gasto | R8: Provincia
B9: 45839 | C9: 1 | D9: 3 | E9: 273296 | F9: 30707135596 | G9: =IFERROR(IF('Jul-26'!$F9="","-",VLOOKUP('Jul-26'!$F9,Lista_CUIT!$A$1:$D$2241,2,0)),"CUIT NO CARGADO") -> CITILAN ARGENTINA S.A. | H9: 32638.02 | I9: =IF('Jul-26'!$H9="","",'Jul-26'!$H9*0.21) -> 6853.9842 | P9: =SUM('Jul-26'!$H9:$O9) -> 39492.004 | Q9: =IFERROR(IF('Jul-26'!$F9="","-",VLOOKUP('Jul-26'!$F9,Lista_CUIT!$A$1:$D$2241,3,0)),"CUIT NO CARGADO") -> Telefonia | R9: =IFERROR(IF('Jul-26'!$F9="","-",VLOOKUP('Jul-26'!$F9,Lista_CUIT!$A$1:$D$2241,4,0)),"CUIT NO CARGADO") -> 0
B10: 45839 | C10: 1 | D10: 3 | E10: 184 | F10: 20297899830 | G10: =IFERROR(IF('Jul-26'!$F10="","-",VLOOKUP('Jul-26'!$F10,Lista_CUIT!$A$1:$D$2241,2,0)),"CUIT NO CARGADO") -> FUNK MATIAS NICOLAS | H10: 8621775 | I10: =IF('Jul-26'!$H10="","",'Jul-26'!$H10*0.21) -> 1810572.8 | P10: =SUM('Jul-26'!$H10:$O10) -> 10432348 | Q10: =IFERROR(IF('Jul-26'!$F10="","-",VLOOKUP('Jul-26'!$F10,Lista_CUIT!$A$1:$D$2241,3,0)),"CUIT NO CARGADO") -> INSUMO | R10: =IFERROR(IF('Jul-26'!$F10="","-",VLOOKUP('Jul-26'!$F10,Lista_CUIT!$A$1:$D$2241,4,0)),"CUIT NO CARGADO") -> 0
B11: 45839 | C11: 1 | D11: 3 | E11: 872 | F11: 30715402765 | G11: =IFERROR(IF('Jul-26'!$F11="","-",VLOOKUP('Jul-26'!$F11,Lista_CUIT!$A$1:$D$2241,2,0)),"CUIT NO CARGADO") -> RIO 265 S.R.L. | H11: 95867.76 | I11: =IF('Jul-26'!$H11="","",'Jul-26'!$H11*0.21) -> 20132.23 | P11: =SUM('Jul-26'!$H11:$O11) -> 115999.99 | Q11: =IFERROR(IF('Jul-26'!$F11="","-",VLOOKUP('Jul-26'!$F11,Lista_CUIT!$A$1:$D$2241,3,0)),"CUIT NO CARGADO") -> GASTOS VARIOS | R11: =IFERROR(IF('Jul-26'!$F11="","-",VLOOKUP('Jul-26'!$F11,Lista_CUIT!$A$1:$D$2241,4,0)),"CUIT NO CARGADO") -> 0
B12: 45842 | C12: 1 | D12: 4 | E12: 14068 | F12: 33710719549 | G12: =IFERROR(IF('Jul-26'!$F12="","-",VLOOKUP('Jul-26'!$F12,Lista_CUIT!$A$1:$D$2241,2,0)),"CUIT NO CARGADO") -> FIVELEC S.R.L. | H12: 45828.45 | I12: =IF('Jul-26'!$H12="","",'Jul-26'!$H12*0.21) -> 9623.9745 | P12: =SUM('Jul-26'!$H12:$O12) -> 55452.424 | Q12: =IFERROR(IF('Jul-26'!$F12="","-",VLOOKUP('Jul-26'!$F12,Lista_CUIT!$A$1:$D$2241,3,0)),"CUIT NO CARGADO") -> INSUMO | R12: =IFERROR(IF('Jul-26'!$F12="","-",VLOOKUP('Jul-26'!$F12,Lista_CUIT!$A$1:$D$2241,4,0)),"CUIT NO CARGADO") -> 0
B13: 45842 | C13: 1 | D13: 2 | E13: 721 | F13: 20265168478 | G13: =IFERROR(IF('Jul-26'!$F13="","-",VLOOKUP('Jul-26'!$F13,Lista_CUIT!$A$1:$D$2241,2,0)),"CUIT NO CARGADO") -> HERRERA GASTON ADRIAN | H13: 80000 | I13: =IF('Jul-26'!$H13="","",'Jul-26'!$H13*0.21) -> 16800 | P13: =SUM('Jul-26'!$H13:$O13) -> 96800 | Q13: =IFERROR(IF('Jul-26'!$F13="","-",VLOOKUP('Jul-26'!$F13,Lista_CUIT!$A$1:$D$2241,3,0)),"CUIT NO CARGADO") -> FLETE-LOGISTICA | R13: =IFERROR(IF('Jul-26'!$F13="","-",VLOOKUP('Jul-26'!$F13,Lista_CUIT!$A$1:$D$2241,4,0)),"CUIT NO CARGADO") -> 0
B14: 45845 | C14: 1 | D14: 1 | E14: 312 | F14: 30718507495 | G14: =IFERROR(IF('Jul-26'!$F14="","-",VLOOKUP('Jul-26'!$F14,Lista_CUIT!$A$1:$D$2241,2,0)),"CUIT NO CARGADO") -> WEBSITE | H14: 37046.28 | I14: =IF('Jul-26'!$H14="","",'Jul-26'!$H14*0.21) -> 7779.7188 | P14: =SUM('Jul-26'!$H14:$O14) -> 44825.999 | Q14: =IFERROR(IF('Jul-26'!$F14="","-",VLOOKUP('Jul-26'!$F14,Lista_CUIT!$A$1:$D$2241,3,0)),"CUIT NO CARGADO") -> 0 | R14: =IFERROR(IF('Jul-26'!$F14="","-",VLOOKUP('Jul-26'!$F14,Lista_CUIT!$A$1:$D$2241,4,0)),"CUIT NO CARGADO") -> 0
B15: 45845 | C15: 1 | D15: 5 | E15: 6333 | F15: 20231333593 | G15: =IFERROR(IF('Jul-26'!$F15="","-",VLOOKUP('Jul-26'!$F15,Lista_CUIT!$A$1:$D$2241,2,0)),"CUIT NO CARGADO") -> BOLLINI CLAUDIO DANIEL | H15: 80000 | I15: =IF('Jul-26'!$H15="","",'Jul-26'!$H15*0.21) -> 16800 | P15: =SUM('Jul-26'!$H15:$O15) -> 96800 | Q15: =IFERROR(IF('Jul-26'!$F15="","-",VLOOKUP('Jul-26'!$F15,Lista_CUIT!$A$1:$D$2241,3,0)),"CUIT NO CARGADO") -> Mantenimiento | R15: =IFERROR(IF('Jul-26'!$F15="","-",VLOOKUP('Jul-26'!$F15,Lista_CUIT!$A$1:$D$2241,4,0)),"CUIT NO CARGADO") -> 0
B16: 45845 | C16: 1 | D16: 5 | E16: 86126 | F16: 30692857611 | G16: =IFERROR(IF('Jul-26'!$F16="","-",VLOOKUP('Jul-26'!$F16,Lista_CUIT!$A$1:$D$2241,2,0)),"CUIT NO CARGADO") -> BAGUI S A | H16: 136972.2 | I16: =IF('Jul-26'!$H16="","",'Jul-26'!$H16*0.21) -> 28764.162 | P16: =SUM('Jul-26'!$H16:$O16) -> 165736.36 | Q16: =IFERROR(IF('Jul-26'!$F16="","-",VLOOKUP('Jul-26'!$F16,Lista_CUIT!$A$1:$D$2241,3,0)),"CUIT NO CARGADO") -> INSUMO | R16: =IFERROR(IF('Jul-26'!$F16="","-",VLOOKUP('Jul-26'!$F16,Lista_CUIT!$A$1:$D$2241,4,0)),"CUIT NO CARGADO") -> 0
B17: 45847 | C17: 1 | D17: 4 | E17: 123861 | F17: 30715577956 | G17: =IFERROR(IF('Jul-26'!$F17="","-",VLOOKUP('Jul-26'!$F17,Lista_CUIT!$A$1:$D$2241,2,0)),"CUIT NO CARGADO") -> NICKNAT S.R.L. | H17: 27513.22 | I17: =IF('Jul-26'!$H17="","",'Jul-26'!$H17*0.21) -> 5777.7762 | P17: =SUM('Jul-26'!$H17:$O17) -> 33290.996 | Q17: =IFERROR(IF('Jul-26'!$F17="","-",VLOOKUP('Jul-26'!$F17,Lista_CUIT!$A$1:$D$2241,3,0)),"CUIT NO CARGADO") -> 0 | R17: =IFERROR(IF('Jul-26'!$F17="","-",VLOOKUP('Jul-26'!$F17,Lista_CUIT!$A$1:$D$2241,4,0)),"CUIT NO CARGADO") -> 0
B18: 45850 | C18: 1 | D18: 8 | E18: 1515 | F18: 20293838713 | G18: =IFERROR(IF('Jul-26'!$F18="","-",VLOOKUP('Jul-26'!$F18,Lista_CUIT!$A$1:$D$2241,2,0)),"CUIT NO CARGADO") -> SCHMITZ PABLO ALEJANDRO | H18: 66077.11 | I18: =IF('Jul-26'!$H18="","",'Jul-26'!$H18*0.21) -> 13876.193 | P18: =SUM('Jul-26'!$H18:$O18) -> 79953.303 | Q18: =IFERROR(IF('Jul-26'!$F18="","-",VLOOKUP('Jul-26'!$F18,Lista_CUIT!$A$1:$D$2241,3,0)),"CUIT NO CARGADO") -> 0 | R18: =IFERROR(IF('Jul-26'!$F18="","-",VLOOKUP('Jul-26'!$F18,Lista_CUIT!$A$1:$D$2241,4,0)),"CUIT NO CARGADO") -> 0
B19: 45852 | C19: 1 | D19: 9 | E19: 4609 | F19: 33711308429 | G19: =IFERROR(IF('Jul-26'!$F19="","-",VLOOKUP('Jul-26'!$F19,Lista_CUIT!$A$1:$D$2241,2,0)),"CUIT NO CARGADO") -> MOTORES ELECTROMECANICA ATLAS S.A. | H19: 183500 | I19: =IF('Jul-26'!$H19="","",'Jul-26'!$H19*0.21) -> 38535 | P19: =SUM('Jul-26'!$H19:$O19) -> 222035 | Q19: =IFERROR(IF('Jul-26'!$F19="","-",VLOOKUP('Jul-26'!$F19,Lista_CUIT!$A$1:$D$2241,3,0)),"CUIT NO CARGADO") -> INSUMO | R19: =IFERROR(IF('Jul-26'!$F19="","-",VLOOKUP('Jul-26'!$F19,Lista_CUIT!$A$1:$D$2241,4,0)),"CUIT NO CARGADO") -> 0
B20: 45852 | C20: 1 | D20: 7 | E20: 689 | F20: 30679166073 | G20: =IFERROR(IF('Jul-26'!$F20="","-",VLOOKUP('Jul-26'!$F20,Lista_CUIT!$A$1:$D$2241,2,0)),"CUIT NO CARGADO") -> MASUMA INTERNACIONAL S A | H20: 493144.5 | I20: =IF('Jul-26'!$H20="","",'Jul-26'!$H20*0.21) -> 103560.34 | P20: =SUM('Jul-26'!$H20:$O20) -> 596704.84 | Q20: =IFERROR(IF('Jul-26'!$F20="","-",VLOOKUP('Jul-26'!$F20,Lista_CUIT!$A$1:$D$2241,3,0)),"CUIT NO CARGADO") -> INSUMO | R20: =IFERROR(IF('Jul-26'!$F20="","-",VLOOKUP('Jul-26'!$F20,Lista_CUIT!$A$1:$D$2241,4,0)),"CUIT NO CARGADO") -> 0
... B27: 45855 | C27: 1 | D27: 5 | E27: 86570 | F27: 30692857611 | G27: =IFERROR(IF('Jul-26'!$F27="","-",VLOOKUP('Jul-26'!$F27,Lista_CUIT!$A$1:$D$2241,2,0)),"CUIT NO CARGADO") -> BAGUI S A | H27: 153000 | I27: =IF('Jul-26'!$H27="","",'Jul-26'!$H27*0.21) -> 32130 | P27: =SUM('Jul-26'!$H27:$O27) -> 185130 | Q27: =IFERROR(IF('Jul-26'!$F27="","-",VLOOKUP('Jul-26'!$F27,Lista_CUIT!$A$1:$D$2241,3,0)),"CUIT NO CARGADO") -> INSUMO | R27: =IFERROR(IF('Jul-26'!$F27="","-",VLOOKUP('Jul-26'!$F27,Lista_CUIT!$A$1:$D$2241,4,0)),"CUIT NO CARGADO") -> 0
B28: 45860 | C28: 1 | D28: 4 | E28: 58055 | F28: 20303333038 | G28: =IFERROR(IF('Jul-26'!$F28="","-",VLOOKUP('Jul-26'!$F28,Lista_CUIT!$A$1:$D$2241,2,0)),"CUIT NO CARGADO") -> RAMIREZ DIAZ FEDERICO NAHUEL | H28: 55158.75 | K28: 5791.67 | P28: =SUM('Jul-26'!$H28:$O28) -> 60950.42 | Q28: =IFERROR(IF('Jul-26'!$F28="","-",VLOOKUP('Jul-26'!$F28,Lista_CUIT!$A$1:$D$2241,3,0)),"CUIT NO CARGADO") -> INSUMO | R28: =IFERROR(IF('Jul-26'!$F28="","-",VLOOKUP('Jul-26'!$F28,Lista_CUIT!$A$1:$D$2241,4,0)),"CUIT NO CARGADO") -> 0
B29: 45860 | C29: 1 | D29: 4 | E29: 58054 | F29: 20303333038 | G29: =IFERROR(IF('Jul-26'!$F29="","-",VLOOKUP('Jul-26'!$F29,Lista_CUIT!$A$1:$D$2241,2,0)),"CUIT NO CARGADO") -> RAMIREZ DIAZ FEDERICO NAHUEL | H29: 40640.13 | I29: 8070.81 | K29: 231.81 | P29: =SUM('Jul-26'!$H29:$O29) -> 48942.75 | Q29: =IFERROR(IF('Jul-26'!$F29="","-",VLOOKUP('Jul-26'!$F29,Lista_CUIT!$A$1:$D$2241,3,0)),"CUIT NO CARGADO") -> INSUMO | R29: =IFERROR(IF('Jul-26'!$F29="","-",VLOOKUP('Jul-26'!$F29,Lista_CUIT!$A$1:$D$2241,4,0)),"CUIT NO CARGADO") -> 0
B30: 45866 | C30: 1 | D30: 7 | E30: 17686 | F30: 30709788635 | G30: =IFERROR(IF('Jul-26'!$F30="","-",VLOOKUP('Jul-26'!$F30,Lista_CUIT!$A$1:$D$2241,2,0)),"CUIT NO CARGADO") -> EMELINT S.R.L. | H30: 31875.26 | I30: =IF('Jul-26'!$H30="","",'Jul-26'!$H30*0.21) -> 6693.8046 | P30: =SUM('Jul-26'!$H30:$O30) -> 38569.065 | Q30: =IFERROR(IF('Jul-26'!$F30="","-",VLOOKUP('Jul-26'!$F30,Lista_CUIT!$A$1:$D$2241,3,0)),"CUIT NO CARGADO") -> Electronica | R30: =IFERROR(IF('Jul-26'!$F30="","-",VLOOKUP('Jul-26'!$F30,Lista_CUIT!$A$1:$D$2241,4,0)),"CUIT NO CARGADO") -> 0
B31: 45867 | C31: 1 | D31: 10 | E31: 62258 | F31: 27268654017 | G31: =IFERROR(IF('Jul-26'!$F31="","-",VLOOKUP('Jul-26'!$F31,Lista_CUIT!$A$1:$D$2241,2,0)),"CUIT NO CARGADO") -> TAU DANIELA LEONOR | H31: 17128.93 | I31: =IF('Jul-26'!$H31="","",'Jul-26'!$H31*0.21) -> 3597.0753 | P31: =SUM('Jul-26'!$H31:$O31) -> 20726.005 | Q31: =IFERROR(IF('Jul-26'!$F31="","-",VLOOKUP('Jul-26'!$F31,Lista_CUIT!$A$1:$D$2241,3,0)),"CUIT NO CARGADO") -> 0 | R31: =IFERROR(IF('Jul-26'!$F31="","-",VLOOKUP('Jul-26'!$F31,Lista_CUIT!$A$1:$D$2241,4,0)),"CUIT NO CARGADO") -> 0
B32: 45863 | C32: 1 | D32: 11 | E32: 2400 | F32: 33696073169 | G32: =IFERROR(IF('Jul-26'!$F32="","-",VLOOKUP('Jul-26'!$F32,Lista_CUIT!$A$1:$D$2241,2,0)),"CUIT NO CARGADO") -> LANDES SRL | H32: 60578.48 | I32: =IF('Jul-26'!$H32="","",'Jul-26'!$H32*0.21) -> 12721.481 | P32: =SUM('Jul-26'!$H32:$O32) -> 73299.961 | Q32: =IFERROR(IF('Jul-26'!$F32="","-",VLOOKUP('Jul-26'!$F32,Lista_CUIT!$A$1:$D$2241,3,0)),"CUIT NO CARGADO") -> Catering | R32: =IFERROR(IF('Jul-26'!$F32="","-",VLOOKUP('Jul-26'!$F32,Lista_CUIT!$A$1:$D$2241,4,0)),"CUIT NO CARGADO") -> 0
G33: =IFERROR(IF('Jul-26'!$F33="","-",VLOOKUP('Jul-26'!$F33,Lista_CUIT!$A$1:$D$2241,2,0)),"CUIT NO CARGADO") -> - | I33: =IF('Jul-26'!$H33="","",'Jul-26'!$H33*0.21) | P33: =SUM('Jul-26'!$H33:$O33) -> 0 | Q33: =IFERROR(IF('Jul-26'!$F33="","-",VLOOKUP('Jul-26'!$F33,Lista_CUIT!$A$1:$D$2241,3,0)),"CUIT NO CARGADO") -> - | R33: =IFERROR(IF('Jul-26'!$F33="","-",VLOOKUP('Jul-26'!$F33,Lista_CUIT!$A$1:$D$2241,4,0)),"CUIT NO CARGADO") -> - | S33: COD 05
G34: =IFERROR(IF('Jul-26'!$F34="","-",VLOOKUP('Jul-26'!$F34,Lista_CUIT!$A$1:$D$2241,2,0)),"CUIT NO CARGADO") -> - | I34: =IF('Jul-26'!$H34="","",'Jul-26'!$H34*0.21) | P34: =SUM('Jul-26'!$H34:$O34) -> 0 | Q34: =IFERROR(IF('Jul-26'!$F34="","-",VLOOKUP('Jul-26'!$F34,Lista_CUIT!$A$1:$D$2241,3,0)),"CUIT NO CARGADO") -> - | R34: =IFERROR(IF('Jul-26'!$F34="","-",VLOOKUP('Jul-26'!$F34,Lista_CUIT!$A$1:$D$2241,4,0)),"CUIT NO CARGADO") -> - | S34: COD 81
B35: Total | H35: =SUBTOTAL(109,'Jul-26'!$H$9:$H$34) -> 15558231 | I35: =SUBTOTAL(109,'Jul-26'!$I$9:$I$34) -> 3255181.6 | J35: =SUBTOTAL(109,'Jul-26'!$J$9:$J$34) -> 0 | K35: =SUBTOTAL(109,'Jul-26'!$K$9:$K$34) -> 6023.48 | L35: =SUBTOTAL(109,'Jul-26'!$L$9:$L$34) -> 0 | M35: =SUBTOTAL(109,'Jul-26'!$M$9:$M$34) -> 0 | N35: =SUBTOTAL(109,'Jul-26'!$N$9:$N$34) -> 0 | O35: =SUBTOTAL(109,'Jul-26'!$O$9:$O$34) -> 0 | P35: =SUBTOTAL(109,'Jul-26'!$P$9:$P$34) -> 18819436
D40: LIQUIDACION EXTRACTOS BANCARIOS-TARJETAS
D41: FECHA | E41: NRO CPTE | F41: BANCO | G41: NETO | H41: IVA 21% | I41: IVA 10,5% | J41: RET IIBB CABA | K41: PERC IVA | L41: PERC IIBB
F42: CREDICOOP | G42: =Table_23[[#This Row],[IVA 21%]]/0.21 -> 132666.24 | H42: 27859.91 | K42: 3853.99
H43: ='Jul-26'!$G43*0.21 -> 0
H44: ='Jul-26'!$G44*0.21 -> 0
H45: ='Jul-26'!$G45*0.21 -> 0
H46: ='Jul-26'!$G46*0.21 -> 0
D47: Total | G47: =SUBTOTAL(109,'Jul-26'!$G$42:$G$46) -> 132666.24 | H47: =SUBTOTAL(109,'Jul-26'!$H$42:$H$46) -> 27859.91 | I47: =SUBTOTAL(109,'Jul-26'!$I$42:$I$46) -> 0 | J47: =SUBTOTAL(109,'Jul-26'!$J$42:$J$46) -> 0 | K47: =SUBTOTAL(109,'Jul-26'!$K$42:$K$46) -> 3853.99 | L47: =SUBTOTAL(109,'Jul-26'!$L$42:$L$46) -> 0
D51: FACTURAS C
D52: FECHA | E52: PTO VTA | F52: FC Nº | G52: CUIT | H52: RAZON SOCIAL | I52: TOTAL | J52: TIPO DE GASTO | K52: Provincia
D53: 45839 | E53: 4 | F53: 98 | G53: 23214737914 | H53: =IFERROR(IF('Jul-26'!$G53="","-",VLOOKUP('Jul-26'!$G53,Lista_CUIT!$A$1:$D$2241,2,0)),"CUIT NO CARGADO") -> SBARRA GABRIELA BEATRIZ | I53: 1175110 | J53: =IFERROR(IF('Jul-26'!$G53="","-",VLOOKUP('Jul-26'!$G53,Lista_CUIT!$A$1:$D$2241,3,0)),"CUIT NO CARGADO") -> Honorarios Admin | K53: =IFERROR(IF('Jul-26'!$G53="","-",VLOOKUP('Jul-26'!$G53,Lista_CUIT!$A$1:$D$2241,4,0)),"CUIT NO CARGADO") -> 0
D54: 45839 | E54: 1 | F54: 114 | G54: 20341465134 | H54: =IFERROR(IF('Jul-26'!$G54="","-",VLOOKUP('Jul-26'!$G54,Lista_CUIT!$A$1:$D$2241,2,0)),"CUIT NO CARGADO") -> ABELEDO AGUSTIN ENRIQUE | I54: 2248500 | J54: =IFERROR(IF('Jul-26'!$G54="","-",VLOOKUP('Jul-26'!$G54,Lista_CUIT!$A$1:$D$2241,3,0)),"CUIT NO CARGADO") -> Mantenimiento | K54: =IFERROR(IF('Jul-26'!$G54="","-",VLOOKUP('Jul-26'!$G54,Lista_CUIT!$A$1:$D$2241,4,0)),"CUIT NO CARGADO") -> CABA
D55: 45839 | E55: 1 | F55: 42 | G55: 27387896150 | H55: =IFERROR(IF('Jul-26'!$G55="","-",VLOOKUP('Jul-26'!$G55,Lista_CUIT!$A$1:$D$2241,2,0)),"CUIT NO CARGADO") -> LIPANOVICH MARIA SOL | I55: 1743950 | J55: =IFERROR(IF('Jul-26'!$G55="","-",VLOOKUP('Jul-26'!$G55,Lista_CUIT!$A$1:$D$2241,3,0)),"CUIT NO CARGADO") -> consultoria informatica | K55: =IFERROR(IF('Jul-26'!$G55="","-",VLOOKUP('Jul-26'!$G55,Lista_CUIT!$A$1:$D$2241,4,0)),"CUIT NO CARGADO") -> 0
D56: 45839 | E56: 1 | F56: 51 | G56: 20365938688 | H56: =IFERROR(IF('Jul-26'!$G56="","-",VLOOKUP('Jul-26'!$G56,Lista_CUIT!$A$1:$D$2241,2,0)),"CUIT NO CARGADO") -> LIPANOVICH JUAN CRUZ | I56: 1494679 | J56: =IFERROR(IF('Jul-26'!$G56="","-",VLOOKUP('Jul-26'!$G56,Lista_CUIT!$A$1:$D$2241,3,0)),"CUIT NO CARGADO") -> SOFTWARE | K56: =IFERROR(IF('Jul-26'!$G56="","-",VLOOKUP('Jul-26'!$G56,Lista_CUIT!$A$1:$D$2241,4,0)),"CUIT NO CARGADO") -> 0
D57: 45839 | E57: 2 | F57: 21 | G57: 23118167279 | H57: =IFERROR(IF('Jul-26'!$G57="","-",VLOOKUP('Jul-26'!$G57,Lista_CUIT!$A$1:$D$2241,2,0)),"CUIT NO CARGADO") -> ABELEDO ENRIQUE JUAN | I57: 2136000 | J57: =IFERROR(IF('Jul-26'!$G57="","-",VLOOKUP('Jul-26'!$G57,Lista_CUIT!$A$1:$D$2241,3,0)),"CUIT NO CARGADO") -> Honorarios Admin | K57: =IFERROR(IF('Jul-26'!$G57="","-",VLOOKUP('Jul-26'!$G57,Lista_CUIT!$A$1:$D$2241,4,0)),"CUIT NO CARGADO") -> 0
D58: 45840 | E58: 4 | F58: 40 | G58: 20086277523 | H58: =IFERROR(IF('Jul-26'!$G58="","-",VLOOKUP('Jul-26'!$G58,Lista_CUIT!$A$1:$D$2241,2,0)),"CUIT NO CARGADO") -> ESTUDIO BOTINDARI | I58: 335000 | J58: =IFERROR(IF('Jul-26'!$G58="","-",VLOOKUP('Jul-26'!$G58,Lista_CUIT!$A$1:$D$2241,3,0)),"CUIT NO CARGADO") -> Honorarios Contables | K58: =IFERROR(IF('Jul-26'!$G58="","-",VLOOKUP('Jul-26'!$G58,Lista_CUIT!$A$1:$D$2241,4,0)),"CUIT NO CARGADO") -> 0
D59: 45841 | E59: 1 | F59: 32 | G59: 20419155870 | H59: =IFERROR(IF('Jul-26'!$G59="","-",VLOOKUP('Jul-26'!$G59,Lista_CUIT!$A$1:$D$2241,2,0)),"CUIT NO CARGADO") -> GULLO GASPAR | I59: 75000 | J59: =IFERROR(IF('Jul-26'!$G59="","-",VLOOKUP('Jul-26'!$G59,Lista_CUIT!$A$1:$D$2241,3,0)),"CUIT NO CARGADO") -> Honorarios Contables | K59: =IFERROR(IF('Jul-26'!$G59="","-",VLOOKUP('Jul-26'!$G59,Lista_CUIT!$A$1:$D$2241,4,0)),"CUIT NO CARGADO") -> 0
D60: 45842 | E60: 2 | F60: 185 | G60: 20136544625 | H60: =IFERROR(IF('Jul-26'!$G60="","-",VLOOKUP('Jul-26'!$G60,Lista_CUIT!$A$1:$D$2241,2,0)),"CUIT NO CARGADO") -> RODRIGUEZ DE LA FUEN HECTOR MARCELO | I60: 1050000 | J60: =IFERROR(IF('Jul-26'!$G60="","-",VLOOKUP('Jul-26'!$G60,Lista_CUIT!$A$1:$D$2241,3,0)),"CUIT NO CARGADO") -> Honorarios Admin | K60: =IFERROR(IF('Jul-26'!$G60="","-",VLOOKUP('Jul-26'!$G60,Lista_CUIT!$A$1:$D$2241,4,0)),"CUIT NO CARGADO") -> 0
D61: 45842 | E61: 1 | F61: 156 | G61: 20389908569 | H61: =IFERROR(IF('Jul-26'!$G61="","-",VLOOKUP('Jul-26'!$G61,Lista_CUIT!$A$1:$D$2241,2,0)),"CUIT NO CARGADO") -> BOTINDARI JUAN IGNACIO | I61: 125000 | J61: =IFERROR(IF('Jul-26'!$G61="","-",VLOOKUP('Jul-26'!$G61,Lista_CUIT!$A$1:$D$2241,3,0)),"CUIT NO CARGADO") -> Honorarios Contables | K61: =IFERROR(IF('Jul-26'!$G61="","-",VLOOKUP('Jul-26'!$G61,Lista_CUIT!$A$1:$D$2241,4,0)),"CUIT NO CARGADO") -> 0
D62: 45842 | E62: 2 | F62: 284 | G62: 27173820866 | H62: =IFERROR(IF('Jul-26'!$G62="","-",VLOOKUP('Jul-26'!$G62,Lista_CUIT!$A$1:$D$2241,2,0)),"CUIT NO CARGADO") -> FREIER SANDRA DANIELA | I62: 1120000 | J62: =IFERROR(IF('Jul-26'!$G62="","-",VLOOKUP('Jul-26'!$G62,Lista_CUIT!$A$1:$D$2241,3,0)),"CUIT NO CARGADO") -> Honorarios Prof | K62: =IFERROR(IF('Jul-26'!$G62="","-",VLOOKUP('Jul-26'!$G62,Lista_CUIT!$A$1:$D$2241,4,0)),"CUIT NO CARGADO") -> 0
D63: 45846 | E63: 4 | F63: 52 | G63: 20341462933 | H63: =IFERROR(IF('Jul-26'!$G63="","-",VLOOKUP('Jul-26'!$G63,Lista_CUIT!$A$1:$D$2241,2,0)),"CUIT NO CARGADO") -> CASTIGLIONI MATIAS EZEQUIEL | I63: 2578000 | J63: =IFERROR(IF('Jul-26'!$G63="","-",VLOOKUP('Jul-26'!$G63,Lista_CUIT!$A$1:$D$2241,3,0)),"CUIT NO CARGADO") -> ASESORAMIENTO | K63: =IFERROR(IF('Jul-26'!$G63="","-",VLOOKUP('Jul-26'!$G63,Lista_CUIT!$A$1:$D$2241,4,0)),"CUIT NO CARGADO") -> BUENOS AIRES
D64: 45852 | E64: 2 | F64: 287 | G64: 27173820866 | H64: =IFERROR(IF('Jul-26'!$G64="","-",VLOOKUP('Jul-26'!$G64,Lista_CUIT!$A$1:$D$2241,2,0)),"CUIT NO CARGADO") -> FREIER SANDRA DANIELA | I64: 625000 | J64: =IFERROR(IF('Jul-26'!$G64="","-",VLOOKUP('Jul-26'!$G64,Lista_CUIT!$A$1:$D$2241,3,0)),"CUIT NO CARGADO") -> Honorarios Prof | K64: =IFERROR(IF('Jul-26'!$G64="","-",VLOOKUP('Jul-26'!$G64,Lista_CUIT!$A$1:$D$2241,4,0)),"CUIT NO CARGADO") -> 0
... D69: 45868 | E69: 12 | F69: 349 | G69: 30715401467 | H69: =IFERROR(IF('Jul-26'!$G69="","-",VLOOKUP('Jul-26'!$G69,Lista_CUIT!$A$1:$D$2241,2,0)),"CUIT NO CARGADO") -> AWARE SOLUTIONS S.R.L. | I69: 204620 | J69: =IFERROR(IF('Jul-26'!$G69="","-",VLOOKUP('Jul-26'!$G69,Lista_CUIT!$A$1:$D$2241,3,0)),"CUIT NO CARGADO") -> INSUMO | K69: =IFERROR(IF('Jul-26'!$G69="","-",VLOOKUP('Jul-26'!$G69,Lista_CUIT!$A$1:$D$2241,4,0)),"CUIT NO CARGADO") -> 0
D70: Total | I70: =SUBTOTAL(109,'Jul-26'!$I$53:$I$69) -> 15267359
B76: LIBRO IVA VENTAS | K76: =N1 -> 45839
B78: VENTAS "A"
B79: FECHA | C79: TIPO | D79: PTO VENTA | E79: Nº FACTURA | F79: CUIT | G79: RAZON SOCIAL | H79: IMPORTE NETO | I79: IVA 21% | J79: IVA 10,5% | K79: EXENTO | L79: TOTAL | M79: Provincia
B80: 45839 | C80: 1 | D80: 3 | E80: 282 | F80: 30628274327 | G80: =IFERROR(IF('Jul-26'!$F80="","-",VLOOKUP('Jul-26'!$F80,Lista_CUIT!$A$1:$D$2241,2,0)),"CUIT NO CARGADO") -> AGIRA S A | H80: 21844600 | J80: =Table_25[[#This Row],[IMPORTE NETO]]*0.105 -> 2293683 | L80: =SUM('Jul-26'!$H80:$K80) -> 24138283
B81: 45846 | C81: 1 | D81: 3 | E81: 283 | F81: 30628274327 | G81: =IFERROR(IF('Jul-26'!$F81="","-",VLOOKUP('Jul-26'!$F81,Lista_CUIT!$A$1:$D$2241,2,0)),"CUIT NO CARGADO") -> AGIRA S A | H81: 23489800 | J81: =Table_25[[#This Row],[IMPORTE NETO]]*0.105 -> 2466429 | L81: =SUM('Jul-26'!$H81:$K81) -> 25956229
B82: 45866 | C82: 1 | D82: 3 | E82: 284 | F82: 20266916680 | G82: =IFERROR(IF('Jul-26'!$F82="","-",VLOOKUP('Jul-26'!$F82,Lista_CUIT!$A$1:$D$2241,2,0)),"CUIT NO CARGADO") -> SPRENGLER FERNANDO JAVIER | H82: 6786000 | J82: =Table_25[[#This Row],[IMPORTE NETO]]*0.105 -> 712530 | L82: =SUM('Jul-26'!$H82:$K82) -> 7498530
G83: =IFERROR(IF('Jul-26'!$F83="","-",VLOOKUP('Jul-26'!$F83,Lista_CUIT!$A$1:$D$2241,2,0)),"CUIT NO CARGADO") -> - | I83: ='Jul-26'!$H83*0.21 -> 0 | L83: =SUM('Jul-26'!$H83:$K83) -> 0
G84: =IFERROR(IF('Jul-26'!$F84="","-",VLOOKUP('Jul-26'!$F84,Lista_CUIT!$A$1:$D$2241,2,0)),"CUIT NO CARGADO") -> - | I84: ='Jul-26'!$H84*0.21 -> 0 | L84: =SUM('Jul-26'!$H84:$K84) -> 0
G85: =IFERROR(IF('Jul-26'!$F85="","-",VLOOKUP('Jul-26'!$F85,Lista_CUIT!$A$1:$D$2241,2,0)),"CUIT NO CARGADO") -> - | I85: ='Jul-26'!$H85*0.21 -> 0 | L85: =SUM('Jul-26'!$H85:$K85) -> 0
G86: =IFERROR(IF('Jul-26'!$F86="","-",VLOOKUP('Jul-26'!$F86,Lista_CUIT!$A$1:$D$2241,2,0)),"CUIT NO CARGADO") -> - | I86: ='Jul-26'!$H86*0.21 -> 0 | L86: =SUM('Jul-26'!$H86:$K86) -> 0
G87: =IFERROR(IF('Jul-26'!$F87="","-",VLOOKUP('Jul-26'!$F87,Lista_CUIT!$A$1:$D$2241,2,0)),"CUIT NO CARGADO") -> - | I87: ='Jul-26'!$H87*0.21 -> 0 | L87: =SUM('Jul-26'!$H87:$K87) -> 0
G88: =IFERROR(IF('Jul-26'!$F88="","-",VLOOKUP('Jul-26'!$F88,Lista_CUIT!$A$1:$D$2241,2,0)),"CUIT NO CARGADO") -> - | I88: ='Jul-26'!$H88*0.21 -> 0 | L88: =SUM('Jul-26'!$H88:$K88) -> 0
G89: =IFERROR(IF('Jul-26'!$F89="","-",VLOOKUP('Jul-26'!$F89,Lista_CUIT!$A$1:$D$2241,2,0)),"CUIT NO CARGADO") -> - | I89: ='Jul-26'!$H89*0.21 -> 0 | L89: =SUM('Jul-26'!$H89:$K89) -> 0
B90: Total | H90: =SUBTOTAL(109,'Jul-26'!$H$80:$H$89) -> 52120400 | I90: =SUBTOTAL(109,'Jul-26'!$I$80:$I$89) -> 0 | J90: =SUBTOTAL(109,'Jul-26'!$J$80:$J$89) -> 5472642 | K90: =SUBTOTAL(109,'Jul-26'!$K$80:$K$89) -> 0 | L90: =SUBTOTAL(109,'Jul-26'!$L$80:$L$89) -> 57593042 | M90: =SUBTOTAL(103,'Jul-26'!$M$80:$M$89) -> 0
B92: VENTAS "B"
B93: FECHA | C93: TIPO | D93: PTO VENTA | E93: Nº FACTURA | F93: CUIT | G93: RAZON SOCIAL | H93: IMPORTE NETO | I93: IVA 21% | J93: IVA 10,5% | K93: EXENTO | L93: TOTAL | M93: Provincia
G94: =IFERROR(IF('Jul-26'!$F94="","-",VLOOKUP('Jul-26'!$F94,Lista_CUIT!$A$1:$D$2241,2,0)),"CUIT NO CARGADO") -> - | I94: ='Jul-26'!$H94*0.21 -> 0 | L94: =SUM('Jul-26'!$H94:$K94) -> 0
I95: ='Jul-26'!$H95*0.21 -> 0 | L95: =SUM('Jul-26'!$H95:$K95) -> 0
I96: ='Jul-26'!$H96*0.21 -> 0 | L96: =SUM('Jul-26'!$H96:$K96) -> 0
I97: ='Jul-26'!$H97*0.21 -> 0 | L97: =SUM('Jul-26'!$H97:$K97) -> 0
I98: ='Jul-26'!$H98*0.21 -> 0 | L98: =SUM('Jul-26'!$H98:$K98) -> 0
I99: ='Jul-26'!$H99*0.21 -> 0 | L99: =SUM('Jul-26'!$H99:$K99) -> 0
B100: Total | H100: =SUBTOTAL(109,'Jul-26'!$H$94:$H$99) -> 0 | I100: =SUBTOTAL(109,'Jul-26'!$I$94:$I$99) -> 0 | J100: =SUBTOTAL(109,'Jul-26'!$J$94:$J$99) -> 0 | K100: =SUBTOTAL(109,'Jul-26'!$K$94:$K$99) -> 0 | L100: =SUBTOTAL(109,'Jul-26'!$L$94:$L$99) -> 0 | M100: =SUBTOTAL(103,'Jul-26'!$M$94:$M$99) -> 0
B103: VENTAS "E"
B104: FECHA | C104: TIPO | D104: PTO VENTA | E104: Nº FACTURA | F104: CUIT | G104: RAZON SOCIAL | H104: USD | I104: TIPO DE CAMBIO2 | J104: TOTAL | K104: Pais
B105: 45855 | D105: 30 | E105: 110 | F105: 55000000050 | G105: =IFERROR(IF('Jul-26'!$F105="","-",VLOOKUP('Jul-26'!$F105,Lista_CUIT!$A$1:$D$2241,2,0)),"CUIT NO CARGADO") -> GAS FUTURO SISTEMAS DE COMPRESSÃO LTDA | H105: 14400 | I105: 1261 | J105: ='Jul-26'!$H105*'Jul-26'!$I105 -> 18158400
G106: =IFERROR(IF('Jul-26'!$F106="","-",VLOOKUP('Jul-26'!$F106,Lista_CUIT!$A$1:$D$2241,2,0)),"CUIT NO CARGADO") -> - | J106: ='Jul-26'!$H106*'Jul-26'!$I106 -> 0
B107: Total | H107: =SUBTOTAL(109,'Jul-26'!$H$105:$H$106) -> 14400 | I107: =SUBTOTAL(109,'Jul-26'!$I$105:$I$106) -> 1261 | J107: =SUBTOTAL(109,'Jul-26'!$J$105:$J$106) -> 18158400 | K107: =SUBTOTAL(103,'Jul-26'!$K$105:$K$106) -> 0
C111: RETENCIONES
C112: FECHA | D112: COMP Nº | E112: Columna1 | F112: CUIT | G112: RAZON SOCIAL | H112: Ganancias | I112: IVA | J112: SUSS | K112: IIBB BSAS | L112: IIBB CABA
G113: =IFERROR(IF('Jul-26'!$F113="","-",VLOOKUP('Jul-26'!$F113,Lista_CUIT!$A$1:$D$2241,2,0)),"CUIT NO CARGADO") -> - | I113: 9597.94 | J113: 914.09
G114: =IFERROR(IF('Jul-26'!$F114="","-",VLOOKUP('Jul-26'!$F114,Lista_CUIT!$A$1:$D$2241,2,0)),"CUIT NO CARGADO") -> -
G115: =IFERROR(IF('Jul-26'!$F115="","-",VLOOKUP('Jul-26'!$F115,Lista_CUIT!$A$1:$D$2241,2,0)),"CUIT NO CARGADO") -> -
G116: =IFERROR(IF('Jul-26'!$F116="","-",VLOOKUP('Jul-26'!$F116,Lista_CUIT!$A$1:$D$2241,2,0)),"CUIT NO CARGADO") -> -
G117: =IFERROR(IF('Jul-26'!$F117="","-",VLOOKUP('Jul-26'!$F117,Lista_CUIT!$A$1:$D$2241,2,0)),"CUIT NO CARGADO") -> -

Sheet Ago-26
B1: LIBRO IVA COMPRAS | G1: ='Abr-26'!G1:M1 -> CORITEC S. R. L. | N1: =EDATE('Abr-26'!N1,4) -> 45870
B3: TOTAL COMPRAS | G3: TOTAL CREDITO FISCAL | J3: TOTAL VENTAS NETAS | M3: TOTAL DEBITO FISCAL | P3: RESULTADO
B4: =SUM('Ago-26'!$H$36)+'Ago-26'!$G$48 -> 21954622 | G4: ='Ago-26'!$I$36+'Ago-26'!$J$36+'Ago-26'!$K$36+'Ago-26'!$H$48+'Ago-26'!$I$48 -> 4583461.7 | J4: ='Ago-26'!$H$91+'Ago-26'!$H$102 -> 6749750 | M4: ='Ago-26'!$I$91+'Ago-26'!$J$91+'Ago-26'!$I$102+'Ago-26'!$J$102 -> 1417433.8 | P4: =G4-M4 -> 3166027.9
B8: FECHA | C8: TIPO | D8: PTO VTA | E8: NRO. CPTE | F8: CUIT | G8: RAZON SOCIAL | H8: NETO GRAVADO | I8: IVA 21 % | J8: IVA 27% | K8: IVA 10,5% | L8: PERC. IVA | M8: PERC IIBB BS AS | N8: PERC. IIBB CABA | O8: Otros / No Grav. | P8: TOTAL | Q8: Tipo de Gasto | R8: Provincia
B9: 45870 | C9: 1 | D9: 3 | E9: 275199 | F9: 30707135596 | G9: =IFERROR(IF('Ago-26'!$F9="","-",VLOOKUP('Ago-26'!$F9,Lista_CUIT!$A$1:$D$2241,2,0)),"CUIT NO CARGADO") -> CITILAN ARGENTINA S.A. | H9: 32644.03 | I9: =IF('Ago-26'!$H9="","",'Ago-26'!$H9*0.21) -> 6855.2463 | P9: =SUM('Ago-26'!$H9:$O9) -> 39499.276 | Q9: =IFERROR(IF('Ago-26'!$F9="","-",VLOOKUP('Ago-26'!$F9,Lista_CUIT!$A$1:$D$2241,3,0)),"CUIT NO CARGADO") -> Telefonia | R9: =IFERROR(IF('Ago-26'!$F9="","-",VLOOKUP('Ago-26'!$F9,Lista_CUIT!$A$1:$D$2241,4,0)),"CUIT NO CARGADO") -> 0
B10: 45870 | C10: 1 | D10: 3 | E10: 879 | F10: 30715402765 | G10: =IFERROR(IF('Ago-26'!$F10="","-",VLOOKUP('Ago-26'!$F10,Lista_CUIT!$A$1:$D$2241,2,0)),"CUIT NO CARGADO") -> RIO 265 S.R.L. | H10: 99173.57 | I10: =IF('Ago-26'!$H10="","",'Ago-26'!$H10*0.21) -> 20826.45 | P10: =SUM('Ago-26'!$H10:$O10) -> 120000.02 | Q10: =IFERROR(IF('Ago-26'!$F10="","-",VLOOKUP('Ago-26'!$F10,Lista_CUIT!$A$1:$D$2241,3,0)),"CUIT NO CARGADO") -> GASTOS VARIOS | R10: =IFERROR(IF('Ago-26'!$F10="","-",VLOOKUP('Ago-26'!$F10,Lista_CUIT!$A$1:$D$2241,4,0)),"CUIT NO CARGADO") -> 0
B11: 45873 | C11: 1 | D11: 2 | E11: 3181 | F11: 30709131733 | G11: =IFERROR(IF('Ago-26'!$F11="","-",VLOOKUP('Ago-26'!$F11,Lista_CUIT!$A$1:$D$2241,2,0)),"CUIT NO CARGADO") -> DIGAS SRL | H11: 4504498 | I11: =IF('Ago-26'!$H11="","",'Ago-26'!$H11*0.21) -> 945944.58 | P11: =SUM('Ago-26'!$H11:$O11) -> 5450442.6 | Q11: =IFERROR(IF('Ago-26'!$F11="","-",VLOOKUP('Ago-26'!$F11,Lista_CUIT!$A$1:$D$2241,3,0)),"CUIT NO CARGADO") -> INSUMO | R11: =IFERROR(IF('Ago-26'!$F11="","-",VLOOKUP('Ago-26'!$F11,Lista_CUIT!$A$1:$D$2241,4,0)),"CUIT NO CARGADO") -> 0
B12: 45875 | C12: 1 | D12: 5 | E12: 6488 | F12: 20231333593 | G12: =IFERROR(IF('Ago-26'!$F12="","-",VLOOKUP('Ago-26'!$F12,Lista_CUIT!$A$1:$D$2241,2,0)),"CUIT NO CARGADO") -> BOLLINI CLAUDIO DANIEL | H12: 80000 | I12: =IF('Ago-26'!$H12="","",'Ago-26'!$H12*0.21) -> 16800 | P12: =SUM('Ago-26'!$H12:$O12) -> 96800 | Q12: =IFERROR(IF('Ago-26'!$F12="","-",VLOOKUP('Ago-26'!$F12,Lista_CUIT!$A$1:$D$2241,3,0)),"CUIT NO CARGADO") -> Mantenimiento | R12: =IFERROR(IF('Ago-26'!$F12="","-",VLOOKUP('Ago-26'!$F12,Lista_CUIT!$A$1:$D$2241,4,0)),"CUIT NO CARGADO") -> 0
B13: 45875 | C13: 1 | D13: 63 | E13: 3417543 | F13: 30640897267 | G13: =IFERROR(IF('Ago-26'!$F13="","-",VLOOKUP('Ago-26'!$F13,Lista_CUIT!$A$1:$D$2241,2,0)),"CUIT NO CARGADO") -> TELECENTRO SA | H13: 18407.02 | I13: =IF('Ago-26'!$H13="","",'Ago-26'!$H13*0.21) -> 3865.4742 | L13: 552.21 | P13: =SUM('Ago-26'!$H13:$O13) -> 22824.704 | Q13: =IFERROR(IF('Ago-26'!$F13="","-",VLOOKUP('Ago-26'!$F13,Lista_CUIT!$A$1:$D$2241,3,0)),"CUIT NO CARGADO") -> SERVICIOS | R13: =IFERROR(IF('Ago-26'!$F13="","-",VLOOKUP('Ago-26'!$F13,Lista_CUIT!$A$1:$D$2241,4,0)),"CUIT NO CARGADO") -> 0
B14: 45875 | C14: 1 | D14: 9 | E14: 22463 | F14: 30715899546 | G14: =IFERROR(IF('Ago-26'!$F14="","-",VLOOKUP('Ago-26'!$F14,Lista_CUIT!$A$1:$D$2241,2,0)),"CUIT NO CARGADO") -> COLLINS INDUSTRIAL SRL | H14: 67444.63 | I14: =IF('Ago-26'!$H14="","",'Ago-26'!$H14*0.21) -> 14163.372 | P14: =SUM('Ago-26'!$H14:$O14) -> 81608.002 | Q14: =IFERROR(IF('Ago-26'!$F14="","-",VLOOKUP('Ago-26'!$F14,Lista_CUIT!$A$1:$D$2241,3,0)),"CUIT NO CARGADO") -> 0 | R14: =IFERROR(IF('Ago-26'!$F14="","-",VLOOKUP('Ago-26'!$F14,Lista_CUIT!$A$1:$D$2241,4,0)),"CUIT NO CARGADO") -> 0
B15: 45876 | C15: 1 | D15: 4 | E15: 977 | F15: 20431994942 | G15: =IFERROR(IF('Ago-26'!$F15="","-",VLOOKUP('Ago-26'!$F15,Lista_CUIT!$A$1:$D$2241,2,0)),"CUIT NO CARGADO") -> CIOCCA SANTINO | H15: 23429.75 | I15: =IF('Ago-26'!$H15="","",'Ago-26'!$H15*0.21) -> 4920.2475 | P15: =SUM('Ago-26'!$H15:$O15) -> 28349.997 | Q15: =IFERROR(IF('Ago-26'!$F15="","-",VLOOKUP('Ago-26'!$F15,Lista_CUIT!$A$1:$D$2241,3,0)),"CUIT NO CARGADO") -> Materiales Electricos | R15: =IFERROR(IF('Ago-26'!$F15="","-",VLOOKUP('Ago-26'!$F15,Lista_CUIT!$A$1:$D$2241,4,0)),"CUIT NO CARGADO") -> 0
B16: 45876 | C16: 1 | D16: 6 | E16: 5860 | F16: 20351402270 | G16: =IFERROR(IF('Ago-26'!$F16="","-",VLOOKUP('Ago-26'!$F16,Lista_CUIT!$A$1:$D$2241,2,0)),"CUIT NO CARGADO") -> JUAREZ MANUEL ROBERTO | H16: 7437.19 | I16: =IF('Ago-26'!$H16="","",'Ago-26'!$H16*0.21) -> 1561.8099 | P16: =SUM('Ago-26'!$H16:$O16) -> 8998.9999 | Q16: =IFERROR(IF('Ago-26'!$F16="","-",VLOOKUP('Ago-26'!$F16,Lista_CUIT!$A$1:$D$2241,3,0)),"CUIT NO CARGADO") -> GASTOS VARIOS | R16: =IFERROR(IF('Ago-26'!$F16="","-",VLOOKUP('Ago-26'!$F16,Lista_CUIT!$A$1:$D$2241,4,0)),"CUIT NO CARGADO") -> 0
B17: 45880 | C17: 1 | D17: 4 | E17: 1936 | F17: 33714584079 | G17: =IFERROR(IF('Ago-26'!$F17="","-",VLOOKUP('Ago-26'!$F17,Lista_CUIT!$A$1:$D$2241,2,0)),"CUIT NO CARGADO") -> MAR IMPEX S.R.L. | H17: 30837.36 | I17: =IF('Ago-26'!$H17="","",'Ago-26'!$H17*0.21) -> 6475.8456 | P17: =SUM('Ago-26'!$H17:$O17) -> 37313.206 | Q17: =IFERROR(IF('Ago-26'!$F17="","-",VLOOKUP('Ago-26'!$F17,Lista_CUIT!$A$1:$D$2241,3,0)),"CUIT NO CARGADO") -> INSUMO | R17: =IFERROR(IF('Ago-26'!$F17="","-",VLOOKUP('Ago-26'!$F17,Lista_CUIT!$A$1:$D$2241,4,0)),"CUIT NO CARGADO") -> 0
B18: 45880 | C18: 1 | D18: 2 | E18: 217 | F18: 20125142851 | G18: =IFERROR(IF('Ago-26'!$F18="","-",VLOOKUP('Ago-26'!$F18,Lista_CUIT!$A$1:$D$2241,2,0)),"CUIT NO CARGADO") -> FEDERICI NICOLAS JOSE | H18: 388877.38 | I18: =IF('Ago-26'!$H18="","",'Ago-26'!$H18*0.21) -> 81664.25 | P18: =SUM('Ago-26'!$H18:$O18) -> 470541.63 | Q18: =IFERROR(IF('Ago-26'!$F18="","-",VLOOKUP('Ago-26'!$F18,Lista_CUIT!$A$1:$D$2241,3,0)),"CUIT NO CARGADO") -> INSUMO | R18: =IFERROR(IF('Ago-26'!$F18="","-",VLOOKUP('Ago-26'!$F18,Lista_CUIT!$A$1:$D$2241,4,0)),"CUIT NO CARGADO") -> 0
B19: 45880 | C19: 1 | D19: 12 | E19: 335 | F19: 30715401467 | G19: =IFERROR(IF('Ago-26'!$F19="","-",VLOOKUP('Ago-26'!$F19,Lista_CUIT!$A$1:$D$2241,2,0)),"CUIT NO CARGADO") -> AWARE SOLUTIONS S.R.L. | H19: 185176.47 | K19: 19443.53 | P19: =SUM('Ago-26'!$H19:$O19) -> 204620 | Q19: =IFERROR(IF('Ago-26'!$F19="","-",VLOOKUP('Ago-26'!$F19,Lista_CUIT!$A$1:$D$2241,3,0)),"CUIT NO CARGADO") -> INSUMO | R19: =IFERROR(IF('Ago-26'!$F19="","-",VLOOKUP('Ago-26'!$F19,Lista_CUIT!$A$1:$D$2241,4,0)),"CUIT NO CARGADO") -> 0
B20: 45880 | C20: 1 | D20: 5 | E20: 87478 | F20: 30692857611 | G20: =IFERROR(IF('Ago-26'!$F20="","-",VLOOKUP('Ago-26'!$F20,Lista_CUIT!$A$1:$D$2241,2,0)),"CUIT NO CARGADO") -> BAGUI S A | H20: 75040 | I20: =IF('Ago-26'!$H20="","",'Ago-26'!$H20*0.21) -> 15758.4 | P20: =SUM('Ago-26'!$H20:$O20) -> 90798.4 | Q20: =IFERROR(IF('Ago-26'!$F20="","-",VLOOKUP('Ago-26'!$F20,Lista_CUIT!$A$1:$D$2241,3,0)),"CUIT NO CARGADO") -> INSUMO | R20: =IFERROR(IF('Ago-26'!$F20="","-",VLOOKUP('Ago-26'!$F20,Lista_CUIT!$A$1:$D$2241,4,0)),"CUIT NO CARGADO") -> 0
B21: 45881 | C21: 1 | D21: 2 | E21: 17859 | F21: 30624684628 | G21: =IFERROR(IF('Ago-26'!$F21="","-",VLOOKUP('Ago-26'!$F21,Lista_CUIT!$A$1:$D$2241,2,0)),"CUIT NO CARGADO") -> MITSUKO ARGENTINA S R L | H21: 974700 | I21: =IF('Ago-26'!$H21="","",'Ago-26'!$H21*0.21) -> 204687 | P21: =SUM('Ago-26'!$H21:$O21) -> 1179387 | Q21: =IFERROR(IF('Ago-26'!$F21="","-",VLOOKUP('Ago-26'!$F21,Lista_CUIT!$A$1:$D$2241,3,0)),"CUIT NO CARGADO") -> INSUMO | R21: =IFERROR(IF('Ago-26'!$F21="","-",VLOOKUP('Ago-26'!$F21,Lista_CUIT!$A$1:$D$2241,4,0)),"CUIT NO CARGADO") -> 0
B22: 45881 | C22: 1 | D22: 9 | E22: 185679 | F22: 33715571639 | G22: =IFERROR(IF('Ago-26'!$F22="","-",VLOOKUP('Ago-26'!$F22,Lista_CUIT!$A$1:$D$2241,2,0)),"CUIT NO CARGADO") -> DUAITEK SRL | H22: 45245.45 | I22: 815.53 | K22: 4343.01 | P22: =SUM('Ago-26'!$H22:$O22) -> 50403.99 | Q22: =IFERROR(IF('Ago-26'!$F22="","-",VLOOKUP('Ago-26'!$F22,Lista_CUIT!$A$1:$D$2241,3,0)),"CUIT NO CARGADO") -> Materiales Electricos | R22: =IFERROR(IF('Ago-26'!$F22="","-",VLOOKUP('Ago-26'!$F22,Lista_CUIT!$A$1:$D$2241,4,0)),"CUIT NO CARGADO") -> 0
B23: 45883 | C23: 1 | D23: 6992 | E23: 34643 | F23: 30678774495 | G23: =IFERROR(IF('Ago-26'!$F23="","-",VLOOKUP('Ago-26'!$F23,Lista_CUIT!$A$1:$D$2241,2,0)),"CUIT NO CARGADO") -> OPER. DE EST. DE SERV. SA | H23: 48432.71 | I23: =IF('Ago-26'!$H23="","",'Ago-26'!$H23*0.21) -> 10170.869 | O23: 15557.45 | P23: =SUM('Ago-26'!$H23:$O23) -> 74161.029 | Q23: =IFERROR(IF('Ago-26'!$F23="","-",VLOOKUP('Ago-26'!$F23,Lista_CUIT!$A$1:$D$2241,3,0)),"CUIT NO CARGADO") -> COMBUSTIBLE | R23: =IFERROR(IF('Ago-26'!$F23="","-",VLOOKUP('Ago-26'!$F23,Lista_CUIT!$A$1:$D$2241,4,0)),"CUIT NO CARGADO") -> 0
B24: 45884 | C24: 1 | D24: 6 | E24: 39406 | F24: 30538456876 | G24: =IFERROR(IF('Ago-26'!$F24="","-",VLOOKUP('Ago-26'!$F24,Lista_CUIT!$A$1:$D$2241,2,0)),"CUIT NO CARGADO") -> RIO DE JANEIRO SA | H24: 30621.11 | I24: =IF('Ago-26'!$H24="","",'Ago-26'!$H24*0.21) -> 6430.4331 | O24: 8245.51 | P24: =SUM('Ago-26'!$H24:$O24) -> 45297.053 | Q24: =IFERROR(IF('Ago-26'!$F24="","-",VLOOKUP('Ago-26'!$F24,Lista_CUIT!$A$1:$D$2241,3,0)),"CUIT NO CARGADO") -> COMBUSTIBLE | R24: =IFERROR(IF('Ago-26'!$F24="","-",VLOOKUP('Ago-26'!$F24,Lista_CUIT!$A$1:$D$2241,4,0)),"CUIT NO CARGADO") -> 0
B25: 45887 | C25: 1 | D25: 5 | E25: 59090 | F25: 30609968792 | G25: =IFERROR(IF('Ago-26'!$F25="","-",VLOOKUP('Ago-26'!$F25,Lista_CUIT!$A$1:$D$2241,2,0)),"CUIT NO CARGADO") -> ABAC S R L | H25: 945100 | I25: =IF('Ago-26'!$H25="","",'Ago-26'!$H25*0.21) -> 198471 | P25: =SUM('Ago-26'!$H25:$O25) -> 1143571 | Q25: =IFERROR(IF('Ago-26'!$F25="","-",VLOOKUP('Ago-26'!$F25,Lista_CUIT!$A$1:$D$2241,3,0)),"CUIT NO CARGADO") -> INSUMO | R25: =IFERROR(IF('Ago-26'!$F25="","-",VLOOKUP('Ago-26'!$F25,Lista_CUIT!$A$1:$D$2241,4,0)),"CUIT NO CARGADO") -> 0
B26: 45887 | C26: 1 | D26: 5 | E26: 59089 | F26: 30609968792 | G26: =IFERROR(IF('Ago-26'!$F26="","-",VLOOKUP('Ago-26'!$F26,Lista_CUIT!$A$1:$D$2241,2,0)),"CUIT NO CARGADO") -> ABAC S R L | H26: 353808 | I26: 74295 | P26: =SUM('Ago-26'!$H26:$O26) -> 428103 | Q26: =IFERROR(IF('Ago-26'!$F26="","-",VLOOKUP('Ago-26'!$F26,Lista_CUIT!$A$1:$D$2241,3,0)),"CUIT NO CARGADO") -> INSUMO | R26: =IFERROR(IF('Ago-26'!$F26="","-",VLOOKUP('Ago-26'!$F26,Lista_CUIT!$A$1:$D$2241,4,0)),"CUIT NO CARGADO") -> 0
B27: 45887 | C27: 1 | D27: 106 | E27: 868588 | F27: 30594494187 | G27: =IFERROR(IF('Ago-26'!$F27="","-",VLOOKUP('Ago-26'!$F27,Lista_CUIT!$A$1:$D$2241,2,0)),"CUIT NO CARGADO") -> FEDERAL EXPRESS CORPORATION | H27: 0 | I27: =IF('Ago-26'!$H27="","",'Ago-26'!$H27*0.21) -> 0 | O27: 1226932.9 | P27: =SUM('Ago-26'!$H27:$O27) -> 1226932.9 | Q27: =IFERROR(IF('Ago-26'!$F27="","-",VLOOKUP('Ago-26'!$F27,Lista_CUIT!$A$1:$D$2241,3,0)),"CUIT NO CARGADO") -> Mercaderia | R27: =IFERROR(IF('Ago-26'!$F27="","-",VLOOKUP('Ago-26'!$F27,Lista_CUIT!$A$1:$D$2241,4,0)),"CUIT NO CARGADO") -> 0
B28: 45890 | C28: 1 | D28: 3 | E28: 6030 | F28: 30709665967 | G28: =IFERROR(IF('Ago-26'!$F28="","-",VLOOKUP('Ago-26'!$F28,Lista_CUIT!$A$1:$D$2241,2,0)),"CUIT NO CARGADO") -> INDUSTRIAS FEMAN S.R.L. | H28: 12633548 | I28: =IF('Ago-26'!$H28="","",'Ago-26'!$H28*0.21) -> 2653045.1 | P28: =SUM('Ago-26'!$H28:$O28) -> 15286593 | Q28: =IFERROR(IF('Ago-26'!$F28="","-",VLOOKUP('Ago-26'!$F28,Lista_CUIT!$A$1:$D$2241,3,0)),"CUIT NO CARGADO") -> INSUMO | R28: =IFERROR(IF('Ago-26'!$F28="","-",VLOOKUP('Ago-26'!$F28,Lista_CUIT!$A$1:$D$2241,4,0)),"CUIT NO CARGADO") -> 0
B29: 45890 | C29: 1 | D29: 106 | E29: 870014 | F29: 30594494187 | G29: =IFERROR(IF('Ago-26'!$F29="","-",VLOOKUP('Ago-26'!$F29,Lista_CUIT!$A$1:$D$2241,2,0)),"CUIT NO CARGADO") -> FEDERAL EXPRESS CORPORATION | H29: 94680 | I29: =IF('Ago-26'!$H29="","",'Ago-26'!$H29*0.21) -> 19882.8 | O29: 507357.96 | P29: =SUM('Ago-26'!$H29:$O29) -> 621920.76 | Q29: =IFERROR(IF('Ago-26'!$F29="","-",VLOOKUP('Ago-26'!$F29,Lista_CUIT!$A$1:$D$2241,3,0)),"CUIT NO CARGADO") -> Mercaderia | R29: =IFERROR(IF('Ago-26'!$F29="","-",VLOOKUP('Ago-26'!$F29,Lista_CUIT!$A$1:$D$2241,4,0)),"CUIT NO CARGADO") -> 0
B30: 45891 | C30: 1 | D30: 1 | E30: 979 | F30: 30715048066 | G30: =IFERROR(IF('Ago-26'!$F30="","-",VLOOKUP('Ago-26'!$F30,Lista_CUIT!$A$1:$D$2241,2,0)),"CUIT NO CARGADO") -> ROLLS Y EMPANADAS SA | H30: 845115 | I30: =IF('Ago-26'!$H30="","",'Ago-26'!$H30*0.21) -> 177474.15 | P30: =SUM('Ago-26'!$H30:$O30) -> 1022589.2 | Q30: =IFERROR(IF('Ago-26'!$F30="","-",VLOOKUP('Ago-26'!$F30,Lista_CUIT!$A$1:$D$2241,3,0)),"CUIT NO CARGADO") -> CATERING | R30: =IFERROR(IF('Ago-26'!$F30="","-",VLOOKUP('Ago-26'!$F30,Lista_CUIT!$A$1:$D$2241,4,0)),"CUIT NO CARGADO") -> 0
B31: 45895 | C31: 1 | D31: 2 | E31: 218 | F31: 20125142851 | G31: =IFERROR(IF('Ago-26'!$F31="","-",VLOOKUP('Ago-26'!$F31,Lista_CUIT!$A$1:$D$2241,2,0)),"CUIT NO CARGADO") -> FEDERICI NICOLAS JOSE | H31: 183344.62 | I31: =IF('Ago-26'!$H31="","",'Ago-26'!$H31*0.21) -> 38502.37 | P31: =SUM('Ago-26'!$H31:$O31) -> 221846.99 | Q31: =IFERROR(IF('Ago-26'!$F31="","-",VLOOKUP('Ago-26'!$F31,Lista_CUIT!$A$1:$D$2241,3,0)),"CUIT NO CARGADO") -> INSUMO | R31: =IFERROR(IF('Ago-26'!$F31="","-",VLOOKUP('Ago-26'!$F31,Lista_CUIT!$A$1:$D$2241,4,0)),"CUIT NO CARGADO") -> 0
B32: 45899 | C32: 1 | D32: 4 | E32: 546 | F32: 20279381123 | G32: =IFERROR(IF('Ago-26'!$F32="","-",VLOOKUP('Ago-26'!$F32,Lista_CUIT!$A$1:$D$2241,2,0)),"CUIT NO CARGADO") -> VOLPI FERNANDO ERNESTO | H32: 111562 | I32: =IF('Ago-26'!$H32="","",'Ago-26'!$H32*0.21) -> 23428.02 | P32: =SUM('Ago-26'!$H32:$O32) -> 134990.02 | Q32: =IFERROR(IF('Ago-26'!$F32="","-",VLOOKUP('Ago-26'!$F32,Lista_CUIT!$A$1:$D$2241,3,0)),"CUIT NO CARGADO") -> 0 | R32: =IFERROR(IF('Ago-26'!$F32="","-",VLOOKUP('Ago-26'!$F32,Lista_CUIT!$A$1:$D$2241,4,0)),"CUIT NO CARGADO") -> 0
B33: 45899 | C33: 1 | D33: 5 | E33: 78338 | F33: 30714430781 | G33: =IFERROR(IF('Ago-26'!$F33="","-",VLOOKUP('Ago-26'!$F33,Lista_CUIT!$A$1:$D$2241,2,0)),"CUIT NO CARGADO") -> JFC HACELA FACIL SRL | H33: 30644.34 | K33: 3217.66 | P33: =SUM('Ago-26'!$H33:$O33) -> 33862 | Q33: =IFERROR(IF('Ago-26'!$F33="","-",VLOOKUP('Ago-26'!$F33,Lista_CUIT!$A$1:$D$2241,3,0)),"CUIT NO CARGADO") -> Materiales Electricos | R33: =IFERROR(IF('Ago-26'!$F33="","-",VLOOKUP('Ago-26'!$F33,Lista_CUIT!$A$1:$D$2241,4,0)),"CUIT NO CARGADO") -> 0
G34: =IFERROR(IF('Ago-26'!$F34="","-",VLOOKUP('Ago-26'!$F34,Lista_CUIT!$A$1:$D$2241,2,0)),"CUIT NO CARGADO") -> - | I34: =IF('Ago-26'!$H34="","",'Ago-26'!$H34*0.21) | P34: =SUM('Ago-26'!$H34:$O34) -> 0 | Q34: =IFERROR(IF('Ago-26'!$F34="","-",VLOOKUP('Ago-26'!$F34,Lista_CUIT!$A$1:$D$2241,3,0)),"CUIT NO CARGADO") -> - | R34: =IFERROR(IF('Ago-26'!$F34="","-",VLOOKUP('Ago-26'!$F34,Lista_CUIT!$A$1:$D$2241,4,0)),"CUIT NO CARGADO") -> -
G35: =IFERROR(IF('Ago-26'!$F35="","-",VLOOKUP('Ago-26'!$F35,Lista_CUIT!$A$1:$D$2241,2,0)),"CUIT NO CARGADO") -> - | I35: =IF('Ago-26'!$H35="","",'Ago-26'!$H35*0.21) | P35: =SUM('Ago-26'!$H35:$O35) -> 0 | Q35: =IFERROR(IF('Ago-26'!$F35="","-",VLOOKUP('Ago-26'!$F35,Lista_CUIT!$A$1:$D$2241,3,0)),"CUIT NO CARGADO") -> - | R35: =IFERROR(IF('Ago-26'!$F35="","-",VLOOKUP('Ago-26'!$F35,Lista_CUIT!$A$1:$D$2241,4,0)),"CUIT NO CARGADO") -> -
B36: Total | H36: =SUBTOTAL(109,'Ago-26'!$H$9:$H$35) -> 21809767 | I36: =SUBTOTAL(109,'Ago-26'!$I$9:$I$35) -> 4526037.9 | J36: =SUBTOTAL(109,'Ago-26'!$J$9:$J$35) -> 0 | K36: =SUBTOTAL(109,'Ago-26'!$K$9:$K$35) -> 27004.2 | L36: =SUBTOTAL(109,'Ago-26'!$L$9:$L$35) -> 552.21 | M36: =SUBTOTAL(109,'Ago-26'!$M$9:$M$35) -> 0 | N36: =SUBTOTAL(109,'Ago-26'!$N$9:$N$35) -> 0 | O36: =SUBTOTAL(109,'Ago-26'!$O$9:$O$35) -> 1758093.8 | P36: =SUBTOTAL(109,'Ago-26'!$P$9:$P$35) -> 28121455
D41: LIQUIDACION EXTRACTOS BANCARIOS-TARJETAS
D42: FECHA | E42: NRO CPTE | F42: BANCO | G42: NETO | H42: IVA 21% | I42: IVA 10,5% | J42: RET IIBB CABA | K42: PERC IVA | L42: PERC IIBB | M42: TOTAL
C43: seg emb | D43: 45888 | E43: 1125687000 | F43: CREDICOOP | G43: 32312.5 | H43: ='Ago-26'!$G43*0.21 -> 6785.625 | K43: 969.38 | M43: =SUM('Ago-26'!$G43:$L43) -> 40067.505
C44: extrc | D44: 45900 | F44: CREDICOOP | G44: =23633.97/0.21 -> 112542.71 | H44: ='Ago-26'!$G44*0.21 -> 23633.97 | K44: 3113.57 | M44: =SUM('Ago-26'!$G44:$L44) -> 139290.25
H45: ='Ago-26'!$G45*0.21 -> 0 | M45: =SUM('Ago-26'!$G45:$L45) -> 0
H46: ='Ago-26'!$G46*0.21 -> 0 | M46: =SUM('Ago-26'!$G46:$L46) -> 0
H47: ='Ago-26'!$G47*0.21 -> 0 | M47: =SUM('Ago-26'!$G47:$L47) -> 0
D48: Total | G48: =SUBTOTAL(109,'Ago-26'!$G$43:$G$47) -> 144855.21 | H48: =SUBTOTAL(109,'Ago-26'!$H$43:$H$47) -> 30419.595 | I48: =SUBTOTAL(109,'Ago-26'!$I$43:$I$47) -> 0 | J48: =SUBTOTAL(109,'Ago-26'!$J$43:$J$47) -> 0 | K48: =SUBTOTAL(109,'Ago-26'!$K$43:$K$47) -> 4082.95 | L48: =SUBTOTAL(109,'Ago-26'!$L$43:$L$47) -> 0
D52: FACTURAS C
D53: FECHA | E53: PTO VTA | F53: FC Nº | G53: CUIT | H53: RAZON SOCIAL | I53: TOTAL | J53: TIPO DE GASTO | K53: Provincia
D54: 45870 | E54: 1 | F54: 34 | G54: 20419155870 | H54: =IFERROR(IF('Ago-26'!$G54="","-",VLOOKUP('Ago-26'!$G54,Lista_CUIT!$A$1:$D$2241,2,0)),"CUIT NO CARGADO") -> GULLO GASPAR | I54: 75000 | J54: =IFERROR(IF('Ago-26'!$G54="","-",VLOOKUP('Ago-26'!$G54,Lista_CUIT!$A$1:$D$2241,3,0)),"CUIT NO CARGADO") -> Honorarios Contables | K54: =IFERROR(IF('Ago-26'!$G54="","-",VLOOKUP('Ago-26'!$G54,Lista_CUIT!$A$1:$D$2241,4,0)),"CUIT NO CARGADO") -> 0
D55: 45870 | E55: 1 | F55: 115 | G55: 20341465134 | H55: =IFERROR(IF('Ago-26'!$G55="","-",VLOOKUP('Ago-26'!$G55,Lista_CUIT!$A$1:$D$2241,2,0)),"CUIT NO CARGADO") -> ABELEDO AGUSTIN ENRIQUE | I55: 2248500 | J55: =IFERROR(IF('Ago-26'!$G55="","-",VLOOKUP('Ago-26'!$G55,Lista_CUIT!$A$1:$D$2241,3,0)),"CUIT NO CARGADO") -> Mantenimiento | K55: =IFERROR(IF('Ago-26'!$G55="","-",VLOOKUP('Ago-26'!$G55,Lista_CUIT!$A$1:$D$2241,4,0)),"CUIT NO CARGADO") -> CABA
D56: 45870 | E56: 2 | F56: 22 | G56: 23118167279 | H56: =IFERROR(IF('Ago-26'!$G56="","-",VLOOKUP('Ago-26'!$G56,Lista_CUIT!$A$1:$D$2241,2,0)),"CUIT NO CARGADO") -> ABELEDO ENRIQUE JUAN | I56: 2875000 | J56: =IFERROR(IF('Ago-26'!$G56="","-",VLOOKUP('Ago-26'!$G56,Lista_CUIT!$A$1:$D$2241,3,0)),"CUIT NO CARGADO") -> Honorarios Admin | K56: =IFERROR(IF('Ago-26'!$G56="","-",VLOOKUP('Ago-26'!$G56,Lista_CUIT!$A$1:$D$2241,4,0)),"CUIT NO CARGADO") -> 0
D57: 45870 | E57: 4 | F57: 51 | G57: 20086277523 | H57: =IFERROR(IF('Ago-26'!$G57="","-",VLOOKUP('Ago-26'!$G57,Lista_CUIT!$A$1:$D$2241,2,0)),"CUIT NO CARGADO") -> ESTUDIO BOTINDARI | I57: 335000 | J57: =IFERROR(IF('Ago-26'!$G57="","-",VLOOKUP('Ago-26'!$G57,Lista_CUIT!$A$1:$D$2241,3,0)),"CUIT NO CARGADO") -> Honorarios Contables | K57: =IFERROR(IF('Ago-26'!$G57="","-",VLOOKUP('Ago-26'!$G57,Lista_CUIT!$A$1:$D$2241,4,0)),"CUIT NO CARGADO") -> 0
D58: 45873 | E58: 1 | F58: 43 | G58: 27387896150 | H58: =IFERROR(IF('Ago-26'!$G58="","-",VLOOKUP('Ago-26'!$G58,Lista_CUIT!$A$1:$D$2241,2,0)),"CUIT NO CARGADO") -> LIPANOVICH MARIA SOL | I58: 1960951 | J58: =IFERROR(IF('Ago-26'!$G58="","-",VLOOKUP('Ago-26'!$G58,Lista_CUIT!$A$1:$D$2241,3,0)),"CUIT NO CARGADO") -> consultoria informatica | K58: =IFERROR(IF('Ago-26'!$G58="","-",VLOOKUP('Ago-26'!$G58,Lista_CUIT!$A$1:$D$2241,4,0)),"CUIT NO CARGADO") -> 0
D59: 45873 | E59: 1 | F59: 44 | G59: 27387896150 | H59: =IFERROR(IF('Ago-26'!$G59="","-",VLOOKUP('Ago-26'!$G59,Lista_CUIT!$A$1:$D$2241,2,0)),"CUIT NO CARGADO") -> LIPANOVICH MARIA SOL | I59: 548000 | J59: =IFERROR(IF('Ago-26'!$G59="","-",VLOOKUP('Ago-26'!$G59,Lista_CUIT!$A$1:$D$2241,3,0)),"CUIT NO CARGADO") -> consultoria informatica | K59: =IFERROR(IF('Ago-26'!$G59="","-",VLOOKUP('Ago-26'!$G59,Lista_CUIT!$A$1:$D$2241,4,0)),"CUIT NO CARGADO") -> 0
D60: 45874 | E60: 2 | F60: 288 | G60: 27173820866 | H60: =IFERROR(IF('Ago-26'!$G60="","-",VLOOKUP('Ago-26'!$G60,Lista_CUIT!$A$1:$D$2241,2,0)),"CUIT NO CARGADO") -> FREIER SANDRA DANIELA | I60: 1550000 | J60: =IFERROR(IF('Ago-26'!$G60="","-",VLOOKUP('Ago-26'!$G60,Lista_CUIT!$A$1:$D$2241,3,0)),"CUIT NO CARGADO") -> Honorarios Prof | K60: =IFERROR(IF('Ago-26'!$G60="","-",VLOOKUP('Ago-26'!$G60,Lista_CUIT!$A$1:$D$2241,4,0)),"CUIT NO CARGADO") -> 0
D61: 45874 | E61: 1 | F61: 160 | G61: 20389908569 | H61: =IFERROR(IF('Ago-26'!$G61="","-",VLOOKUP('Ago-26'!$G61,Lista_CUIT!$A$1:$D$2241,2,0)),"CUIT NO CARGADO") -> BOTINDARI JUAN IGNACIO | I61: 125000 | J61: =IFERROR(IF('Ago-26'!$G61="","-",VLOOKUP('Ago-26'!$G61,Lista_CUIT!$A$1:$D$2241,3,0)),"CUIT NO CARGADO") -> Honorarios Contables | K61: =IFERROR(IF('Ago-26'!$G61="","-",VLOOKUP('Ago-26'!$G61,Lista_CUIT!$A$1:$D$2241,4,0)),"CUIT NO CARGADO") -> 0
D62: 45874 | E62: 2 | F62: 186 | G62: 20136544625 | H62: =IFERROR(IF('Ago-26'!$G62="","-",VLOOKUP('Ago-26'!$G62,Lista_CUIT!$A$1:$D$2241,2,0)),"CUIT NO CARGADO") -> RODRIGUEZ DE LA FUEN HECTOR MARCELO | I62: 1201000 | J62: =IFERROR(IF('Ago-26'!$G62="","-",VLOOKUP('Ago-26'!$G62,Lista_CUIT!$A$1:$D$2241,3,0)),"CUIT NO CARGADO") -> Honorarios Admin | K62: =IFERROR(IF('Ago-26'!$G62="","-",VLOOKUP('Ago-26'!$G62,Lista_CUIT!$A$1:$D$2241,4,0)),"CUIT NO CARGADO") -> 0
D63: 45883 | E63: 4 | F63: 54 | G63: 20341462933 | H63: =IFERROR(IF('Ago-26'!$G63="","-",VLOOKUP('Ago-26'!$G63,Lista_CUIT!$A$1:$D$2241,2,0)),"CUIT NO CARGADO") -> CASTIGLIONI MATIAS EZEQUIEL | I63: 2621000 | J63: =IFERROR(IF('Ago-26'!$G63="","-",VLOOKUP('Ago-26'!$G63,Lista_CUIT!$A$1:$D$2241,3,0)),"CUIT NO CARGADO") -> ASESORAMIENTO | K63: =IFERROR(IF('Ago-26'!$G63="","-",VLOOKUP('Ago-26'!$G63,Lista_CUIT!$A$1:$D$2241,4,0)),"CUIT NO CARGADO") -> BUENOS AIRES
D64: 45891 | E64: 1 | F64: 605 | G64: 27925308884 | H64: =IFERROR(IF('Ago-26'!$G64="","-",VLOOKUP('Ago-26'!$G64,Lista_CUIT!$A$1:$D$2241,2,0)),"CUIT NO CARGADO") -> LOPEZ LOPEZ FLAVIA | I64: 60000 | J64: =IFERROR(IF('Ago-26'!$G64="","-",VLOOKUP('Ago-26'!$G64,Lista_CUIT!$A$1:$D$2241,3,0)),"CUIT NO CARGADO") -> GASTOS VARIOS | K64: =IFERROR(IF('Ago-26'!$G64="","-",VLOOKUP('Ago-26'!$G64,Lista_CUIT!$A$1:$D$2241,4,0)),"CUIT NO CARGADO") -> 0
D65: 45897 | E65: 4 | F65: 103 | G65: 23214737914 | H65: =IFERROR(IF('Ago-26'!$G65="","-",VLOOKUP('Ago-26'!$G65,Lista_CUIT!$A$1:$D$2241,2,0)),"CUIT NO CARGADO") -> SBARRA GABRIELA BEATRIZ | I65: 1002210 | J65: =IFERROR(IF('Ago-26'!$G65="","-",VLOOKUP('Ago-26'!$G65,Lista_CUIT!$A$1:$D$2241,3,0)),"CUIT NO CARGADO") -> Honorarios Admin | K65: =IFERROR(IF('Ago-26'!$G65="","-",VLOOKUP('Ago-26'!$G65,Lista_CUIT!$A$1:$D$2241,4,0)),"CUIT NO CARGADO") -> 0
... D71: 45880 | E71: 12 | F71: 18 | G71: 30715401467 | H71: =IFERROR(IF('Ago-26'!$G71="","-",VLOOKUP('Ago-26'!$G71,Lista_CUIT!$A$1:$D$2241,2,0)),"CUIT NO CARGADO") -> AWARE SOLUTIONS S.R.L. | I71: -204620 | J71: =IFERROR(IF('Ago-26'!$G71="","-",VLOOKUP('Ago-26'!$G71,Lista_CUIT!$A$1:$D$2241,3,0)),"CUIT NO CARGADO") -> INSUMO | K71: =IFERROR(IF('Ago-26'!$G71="","-",VLOOKUP('Ago-26'!$G71,Lista_CUIT!$A$1:$D$2241,4,0)),"CUIT NO CARGADO") -> 0
D72: Total | I72: =SUBTOTAL(109,'Ago-26'!$I$54:$I$71) -> 14354541
B78: LIBRO IVA VENTAS | K78: =N1 -> 45870
B80: VENTAS "A"
B81: FECHA | C81: TIPO | D81: PTO VENTA | E81: Nº FACTURA | F81: CUIT | G81: RAZON SOCIAL | H81: IMPORTE NETO | I81: IVA 21% | J81: IVA 10,5% | K81: EXENTO | L81: TOTAL | M81: Provincia
B82: 45874 | C82: 1 | D82: 3 | E82: 285 | F82: 30638318470 | G82: =IFERROR(IF('Ago-26'!$F82="","-",VLOOKUP('Ago-26'!$F82,Lista_CUIT!$A$1:$D$2241,2,0)),"CUIT NO CARGADO") -> DELTA COMPRESION S R L | H82: 154125 | I82: =23.62*1370 -> 32359.4 | L82: =SUM('Ago-26'!$H82:$K82) -> 186484.4
B83: 45874 | C83: 2 | D83: 3 | E83: 11 | F83: 30638318470 | G83: =IFERROR(IF('Ago-26'!$F83="","-",VLOOKUP('Ago-26'!$F83,Lista_CUIT!$A$1:$D$2241,2,0)),"CUIT NO CARGADO") -> DELTA COMPRESION S R L | H83: 44305814 | I83: =6791.4*1370 -> 9304218 | L83: =SUM('Ago-26'!$H83:$K83) -> 53610032
B84: 45874 | C84: 3 | D84: 3 | E84: 29 | F84: 30638318470 | G84: =IFERROR(IF('Ago-26'!$F84="","-",VLOOKUP('Ago-26'!$F84,Lista_CUIT!$A$1:$D$2241,2,0)),"CUIT NO CARGADO") -> DELTA COMPRESION S R L | H84: -1147375 | I84: =-175.88*1370 -> -240955.6 | L84: =SUM('Ago-26'!$H84:$K84) -> -1388330.6
B85: 45881 | C85: 1 | D85: 3 | E85: 286 | F85: 30718512545 | G85: =IFERROR(IF('Ago-26'!$F85="","-",VLOOKUP('Ago-26'!$F85,Lista_CUIT!$A$1:$D$2241,2,0)),"CUIT NO CARGADO") -> MAJUBEN MDP SERVICIOS S.R.L. | H85: 3204000 | I85: =504*1335 -> 672840 | L85: =SUM('Ago-26'!$H85:$K85) -> 3876840
B86: 45881 | C86: 1 | D86: 3 | E86: 287 | F86: 30718833112 | G86: =IFERROR(IF('Ago-26'!$F86="","-",VLOOKUP('Ago-26'!$F86,Lista_CUIT!$A$1:$D$2241,2,0)),"CUIT NO CARGADO") -> GUGAGAS ENERGY S.R.L. | H86: 4539000 | I86: =714*1335 -> 953190 | L86: =SUM('Ago-26'!$H86:$K86) -> 5492190
B87: 45898 | C87: 3 | D87: 3 | E87: 30 | F87: 30638318470 | G87: =IFERROR(IF('Ago-26'!$F87="","-",VLOOKUP('Ago-26'!$F87,Lista_CUIT!$A$1:$D$2241,2,0)),"CUIT NO CARGADO") -> DELTA COMPRESION S R L | H87: -44305814 | I87: =-6791.4*1370 -> -9304218 | L87: =SUM('Ago-26'!$H87:$K87) -> -53610032
G88: =IFERROR(IF('Ago-26'!$F88="","-",VLOOKUP('Ago-26'!$F88,Lista_CUIT!$A$1:$D$2241,2,0)),"CUIT NO CARGADO") -> - | I88: ='Ago-26'!$H88*0.21 -> 0 | L88: =SUM('Ago-26'!$H88:$K88) -> 0
G89: =IFERROR(IF('Ago-26'!$F89="","-",VLOOKUP('Ago-26'!$F89,Lista_CUIT!$A$1:$D$2241,2,0)),"CUIT NO CARGADO") -> - | I89: ='Ago-26'!$H89*0.21 -> 0 | L89: =SUM('Ago-26'!$H89:$K89) -> 0
G90: =IFERROR(IF('Ago-26'!$F90="","-",VLOOKUP('Ago-26'!$F90,Lista_CUIT!$A$1:$D$2241,2,0)),"CUIT NO CARGADO") -> - | I90: ='Ago-26'!$H90*0.21 -> 0 | L90: =SUM('Ago-26'!$H90:$K90) -> 0
B91: Total | H91: =SUBTOTAL(109,'Ago-26'!$H$82:$H$90) -> 6749750 | I91: =SUBTOTAL(109,'Ago-26'!$I$82:$I$90) -> 1417433.8 | J91: =SUBTOTAL(109,'Ago-26'!$J$82:$J$90) -> 0 | K91: =SUBTOTAL(109,'Ago-26'!$K$82:$K$90) -> 0 | L91: =SUBTOTAL(109,'Ago-26'!$L$82:$L$90) -> 8167183.8 | M91: =SUBTOTAL(103,'Ago-26'!$M$82:$M$90) -> 0
B94: VENTAS "B"
B95: FECHA | C95: TIPO | D95: PTO VENTA | E95: Nº FACTURA | F95: CUIT | G95: RAZON SOCIAL | H95: IMPORTE NETO | I95: IVA 21% | J95: IVA 10,5% | K95: EXENTO | L95: TOTAL | M95: Provincia
G96: =IFERROR(IF('Ago-26'!$F96="","-",VLOOKUP('Ago-26'!$F96,Lista_CUIT!$A$1:$D$2241,2,0)),"CUIT NO CARGADO") -> - | H96: ='Ago-26'!$L96/1.21 -> 0 | I96: ='Ago-26'!$H96*0.21 -> 0
H97: ='Ago-26'!$L97/1.21 -> 0 | I97: ='Ago-26'!$H97*0.21 -> 0
H98: ='Ago-26'!$L98/1.21 -> 0 | I98: ='Ago-26'!$H98*0.21 -> 0
H99: ='Ago-26'!$L99/1.21 -> 0 | I99: ='Ago-26'!$H99*0.21 -> 0
H100: ='Ago-26'!$L100/1.21 -> 0 | I100: ='Ago-26'!$H100*0.21 -> 0
H101: ='Ago-26'!$L101/1.21 -> 0 | I101: ='Ago-26'!$H101*0.21 -> 0
B102: Total | H102: =SUBTOTAL(109,'Ago-26'!$H$96:$H$101) -> 0 | I102: =SUBTOTAL(109,'Ago-26'!$I$96:$I$101) -> 0 | J102: =SUBTOTAL(109,'Ago-26'!$J$96:$J$101) -> 0 | K102: =SUBTOTAL(109,'Ago-26'!$K$96:$K$101) -> 0 | L102: =SUBTOTAL(109,'Ago-26'!$L$96:$L$101) -> 0 | M102: =SUBTOTAL(103,'Ago-26'!$M$96:$M$101) -> 0
B105: VENTAS "E"
B106: FECHA | C106: TIPO | D106: PTO VENTA | E106: Nº FACTURA | F106: CUIT | G106: RAZON SOCIAL | H106: USD | I106: TIPO DE CAMBIO2 | J106: TOTAL | K106: Pais
G107: =IFERROR(IF('Ago-26'!$F107="","-",VLOOKUP('Ago-26'!$F107,Lista_CUIT!$A$1:$D$2241,2,0)),"CUIT NO CARGADO") -> - | J107: ='Ago-26'!$H107*'Ago-26'!$I107 -> 0
G108: =IFERROR(IF('Ago-26'!$F108="","-",VLOOKUP('Ago-26'!$F108,Lista_CUIT!$A$1:$D$2241,2,0)),"CUIT NO CARGADO") -> - | J108: ='Ago-26'!$H108*'Ago-26'!$I108 -> 0
G109: =IFERROR(IF('Ago-26'!$F109="","-",VLOOKUP('Ago-26'!$F109,Lista_CUIT!$A$1:$D$2241,2,0)),"CUIT NO CARGADO") -> - | J109: ='Ago-26'!$H109*'Ago-26'!$I109 -> 0
G110: =IFERROR(IF('Ago-26'!$F110="","-",VLOOKUP('Ago-26'!$F110,Lista_CUIT!$A$1:$D$2241,2,0)),"CUIT NO CARGADO") -> - | J110: ='Ago-26'!$H110*'Ago-26'!$I110 -> 0
G111: =IFERROR(IF('Ago-26'!$F111="","-",VLOOKUP('Ago-26'!$F111,Lista_CUIT!$A$1:$D$2241,2,0)),"CUIT NO CARGADO") -> - | J111: ='Ago-26'!$H111*'Ago-26'!$I111 -> 0
G112: =IFERROR(IF('Ago-26'!$F112="","-",VLOOKUP('Ago-26'!$F112,Lista_CUIT!$A$1:$D$2241,2,0)),"CUIT NO CARGADO") -> - | J112: ='Ago-26'!$H112*'Ago-26'!$I112 -> 0
G113: =IFERROR(IF('Ago-26'!$F113="","-",VLOOKUP('Ago-26'!$F113,Lista_CUIT!$A$1:$D$2241,2,0)),"CUIT NO CARGADO") -> - | J113: ='Ago-26'!$H113*'Ago-26'!$I113 -> 0
G114: =IFERROR(IF('Ago-26'!$F114="","-",VLOOKUP('Ago-26'!$F114,Lista_CUIT!$A$1:$D$2241,2,0)),"CUIT NO CARGADO") -> - | J114: ='Ago-26'!$H114*'Ago-26'!$I114 -> 0
G115: =IFERROR(IF('Ago-26'!$F115="","-",VLOOKUP('Ago-26'!$F115,Lista_CUIT!$A$1:$D$2241,2,0)),"CUIT NO CARGADO") -> - | J115: ='Ago-26'!$H115*'Ago-26'!$I115 -> 0
G116: =IFERROR(IF('Ago-26'!$F116="","-",VLOOKUP('Ago-26'!$F116,Lista_CUIT!$A$1:$D$2241,2,0)),"CUIT NO CARGADO") -> - | J116: ='Ago-26'!$H116*'Ago-26'!$I116 -> 0
B117: Total | H117: =SUBTOTAL(109,'Ago-26'!$H$107:$H$116) -> 0 | J117: =SUBTOTAL(109,'Ago-26'!$J$107:$J$116) -> 0 | K117: =SUBTOTAL(103,'Ago-26'!$K$107:$K$116) -> 0
C121: RETENCIONES
C122: FECHA | D122: COMP Nº | E122: Columna1 | F122: CUIT | G122: RAZON SOCIAL | H122: Ganancias | I122: IVA | J122: SUSS | K122: IIBB BSAS | L122: IIBB CABA
G123: =IFERROR(IF('Ago-26'!$F123="","-",VLOOKUP('Ago-26'!$F123,Lista_CUIT!$A$1:$D$2241,2,0)),"CUIT NO CARGADO") -> -
G124: =IFERROR(IF('Ago-26'!$F124="","-",VLOOKUP('Ago-26'!$F124,Lista_CUIT!$A$1:$D$2241,2,0)),"CUIT NO CARGADO") -> -
G125: =IFERROR(IF('Ago-26'!$F125="","-",VLOOKUP('Ago-26'!$F125,Lista_CUIT!$A$1:$D$2241,2,0)),"CUIT NO CARGADO") -> -
G126: =IFERROR(IF('Ago-26'!$F126="","-",VLOOKUP('Ago-26'!$F126,Lista_CUIT!$A$1:$D$2241,2,0)),"CUIT NO CARGADO") -> -
G127: =IFERROR(IF('Ago-26'!$F127="","-",VLOOKUP('Ago-26'!$F127,Lista_CUIT!$A$1:$D$2241,2,0)),"CUIT NO CARGADO") -> -

Sheet Sept-26
B1: LIBRO IVA COMPRAS | G1: ='Abr-26'!G1:M1 -> CORITEC S. R. L. | N1: =EDATE('Abr-26'!N1,5) -> 45901
B3: TOTAL COMPRAS | G3: TOTAL CREDITO FISCAL | J3: TOTAL VENTAS NETAS | M3: TOTAL DEBITO FISCAL | P3: RESULTADO
B4: =SUM('Sept-26'!$H$54)+'Sept-26'!$G$65 -> 4311230.9 | G4: ='Sept-26'!$I$54+'Sept-26'!$J$54+'Sept-26'!$K$54+'Sept-26'!$H$65+'Sept-26'!$I$65 -> 786124.91 | J4: ='Sept-26'!$H$105+'Sept-26'!$H$115 -> 29110800 | M4: ='Sept-26'!$I$105+'Sept-26'!$J$105+'Sept-26'!$I$115+'Sept-26'!$J$115 -> 3498085.5 | P4: =G4-M4 -> -2711960.6
B8: FECHA | C8: TIPO | D8: PTO VTA | E8: NRO. CPTE | F8: CUIT | G8: RAZON SOCIAL | H8: NETO GRAVADO | I8: IVA 21 % | J8: IVA 27% | K8: IVA 10,5% | L8: PERC. IVA | M8: PERC IIBB BS AS | N8: PERC. IIBB CABA | O8: Otros / No Grav. | P8: TOTAL | Q8: Tipo de Gasto | R8: Provincia
B9: 45901 | C9: 1 | D9: 3 | E9: 278524 | F9: 30707135596 | G9: =IFERROR(IF('Sept-26'!$F9="","-",VLOOKUP('Sept-26'!$F9,Lista_CUIT!$A$1:$D$2241,2,0)),"CUIT NO CARGADO") -> CITILAN ARGENTINA S.A. | H9: 32626 | I9: =IF('Sept-26'!$H9="","",'Sept-26'!$H9*0.21) -> 6851.46 | P9: =SUM('Sept-26'!$H9:$O9) -> 39477.46 | Q9: =IFERROR(IF('Sept-26'!$F9="","-",VLOOKUP('Sept-26'!$F9,Lista_CUIT!$A$1:$D$2241,3,0)),"CUIT NO CARGADO") -> Telefonia | R9: =IFERROR(IF('Sept-26'!$F9="","-",VLOOKUP('Sept-26'!$F9,Lista_CUIT!$A$1:$D$2241,4,0)),"CUIT NO CARGADO") -> 0
B10: 45901 | C10: 1 | D10: 106 | E10: 872838 | F10: 30594494187 | G10: =IFERROR(IF('Sept-26'!$F10="","-",VLOOKUP('Sept-26'!$F10,Lista_CUIT!$A$1:$D$2241,2,0)),"CUIT NO CARGADO") -> FEDERAL EXPRESS CORPORATION | H10: 0 | I10: =IF('Sept-26'!$H10="","",'Sept-26'!$H10*0.21) -> 0 | O10: 860181.3 | P10: =SUM('Sept-26'!$H10:$O10) -> 860181.3 | Q10: =IFERROR(IF('Sept-26'!$F10="","-",VLOOKUP('Sept-26'!$F10,Lista_CUIT!$A$1:$D$2241,3,0)),"CUIT NO CARGADO") -> Mercaderia | R10: =IFERROR(IF('Sept-26'!$F10="","-",VLOOKUP('Sept-26'!$F10,Lista_CUIT!$A$1:$D$2241,4,0)),"CUIT NO CARGADO") -> 0
B11: 45901 | C11: 1 | D11: 5 | E11: 6653 | F11: 20231333593 | G11: =IFERROR(IF('Sept-26'!$F11="","-",VLOOKUP('Sept-26'!$F11,Lista_CUIT!$A$1:$D$2241,2,0)),"CUIT NO CARGADO") -> BOLLINI CLAUDIO DANIEL | H11: 80000 | I11: =IF('Sept-26'!$H11="","",'Sept-26'!$H11*0.21) -> 16800 | P11: =SUM('Sept-26'!$H11:$O11) -> 96800 | Q11: =IFERROR(IF('Sept-26'!$F11="","-",VLOOKUP('Sept-26'!$F11,Lista_CUIT!$A$1:$D$2241,3,0)),"CUIT NO CARGADO") -> Mantenimiento | R11: =IFERROR(IF('Sept-26'!$F11="","-",VLOOKUP('Sept-26'!$F11,Lista_CUIT!$A$1:$D$2241,4,0)),"CUIT NO CARGADO") -> 0
B12: 45901 | C12: 1 | D12: 3 | E12: 887 | F12: 30715402765 | G12: =IFERROR(IF('Sept-26'!$F12="","-",VLOOKUP('Sept-26'!$F12,Lista_CUIT!$A$1:$D$2241,2,0)),"CUIT NO CARGADO") -> RIO 265 S.R.L. | H12: 99173.57 | I12: =IF('Sept-26'!$H12="","",'Sept-26'!$H12*0.21) -> 20826.45 | P12: =SUM('Sept-26'!$H12:$O12) -> 120000.02 | Q12: =IFERROR(IF('Sept-26'!$F12="","-",VLOOKUP('Sept-26'!$F12,Lista_CUIT!$A$1:$D$2241,3,0)),"CUIT NO CARGADO") -> GASTOS VARIOS | R12: =IFERROR(IF('Sept-26'!$F12="","-",VLOOKUP('Sept-26'!$F12,Lista_CUIT!$A$1:$D$2241,4,0)),"CUIT NO CARGADO") -> 0
B13: 45902 | C13: 1 | D13: 5 | E13: 69795 | F13: 20316749942 | G13: =IFERROR(IF('Sept-26'!$F13="","-",VLOOKUP('Sept-26'!$F13,Lista_CUIT!$A$1:$D$2241,2,0)),"CUIT NO CARGADO") -> PASTORIZA ALEJANDRO JAVIER | H13: 357747.26 | K13: 37563.46 | P13: =SUM('Sept-26'!$H13:$O13) -> 395310.72 | Q13: =IFERROR(IF('Sept-26'!$F13="","-",VLOOKUP('Sept-26'!$F13,Lista_CUIT!$A$1:$D$2241,3,0)),"CUIT NO CARGADO") -> 0 | R13: =IFERROR(IF('Sept-26'!$F13="","-",VLOOKUP('Sept-26'!$F13,Lista_CUIT!$A$1:$D$2241,4,0)),"CUIT NO CARGADO") -> 0
B14: 45903 | C14: 1 | D14: 18 | E14: 29918 | F14: 30582605021 | G14: =IFERROR(IF('Sept-26'!$F14="","-",VLOOKUP('Sept-26'!$F14,Lista_CUIT!$A$1:$D$2241,2,0)),"CUIT NO CARGADO") -> ELECTROCOMPONENTES SA | H14: 37013.57 | K14: 3886.43 | P14: =SUM('Sept-26'!$H14:$O14) -> 40900 | Q14: =IFERROR(IF('Sept-26'!$F14="","-",VLOOKUP('Sept-26'!$F14,Lista_CUIT!$A$1:$D$2241,3,0)),"CUIT NO CARGADO") -> 0 | R14: =IFERROR(IF('Sept-26'!$F14="","-",VLOOKUP('Sept-26'!$F14,Lista_CUIT!$A$1:$D$2241,4,0)),"CUIT NO CARGADO") -> 0
B15: 45903 | C15: 1 | D15: 3 | E15: 13024 | F15: 30718251040 | G15: =IFERROR(IF('Sept-26'!$F15="","-",VLOOKUP('Sept-26'!$F15,Lista_CUIT!$A$1:$D$2241,2,0)),"CUIT NO CARGADO") -> AMV-TIENDA ONLINE S.A. | H15: 90908.26 | I15: =IF('Sept-26'!$H15="","",'Sept-26'!$H15*0.21) -> 19090.735 | P15: =SUM('Sept-26'!$H15:$O15) -> 109998.99 | Q15: =IFERROR(IF('Sept-26'!$F15="","-",VLOOKUP('Sept-26'!$F15,Lista_CUIT!$A$1:$D$2241,3,0)),"CUIT NO CARGADO") -> 0 | R15: =IFERROR(IF('Sept-26'!$F15="","-",VLOOKUP('Sept-26'!$F15,Lista_CUIT!$A$1:$D$2241,4,0)),"CUIT NO CARGADO") -> 0
B16: 45903 | C16: 1 | D16: 1 | E16: 4287 | F16: 30715311778 | G16: =IFERROR(IF('Sept-26'!$F16="","-",VLOOKUP('Sept-26'!$F16,Lista_CUIT!$A$1:$D$2241,2,0)),"CUIT NO CARGADO") -> COMPAÑIA INTRODUCTORA DE COMPONENTES EQUIPOS Y MAQUINARIAS SRL | H16: 8400 | K16: 882 | P16: =SUM('Sept-26'!$H16:$O16) -> 9282 | Q16: =IFERROR(IF('Sept-26'!$F16="","-",VLOOKUP('Sept-26'!$F16,Lista_CUIT!$A$1:$D$2241,3,0)),"CUIT NO CARGADO") -> 0 | R16: =IFERROR(IF('Sept-26'!$F16="","-",VLOOKUP('Sept-26'!$F16,Lista_CUIT!$A$1:$D$2241,4,0)),"CUIT NO CARGADO") -> 0
B17: 45904 | C17: 1 | D17: 7 | E17: 20416 | F17: 30604413482 | G17: =IFERROR(IF('Sept-26'!$F17="","-",VLOOKUP('Sept-26'!$F17,Lista_CUIT!$A$1:$D$2241,2,0)),"CUIT NO CARGADO") -> BULONERA VIETRI SOCIEDAD DE RESPONSABILIDAD LIMITADA | H17: 337550.38 | I17: =IF('Sept-26'!$H17="","",'Sept-26'!$H17*0.21) -> 70885.58 | P17: =SUM('Sept-26'!$H17:$O17) -> 408435.96 | Q17: =IFERROR(IF('Sept-26'!$F17="","-",VLOOKUP('Sept-26'!$F17,Lista_CUIT!$A$1:$D$2241,3,0)),"CUIT NO CARGADO") -> INSUMO | R17: =IFERROR(IF('Sept-26'!$F17="","-",VLOOKUP('Sept-26'!$F17,Lista_CUIT!$A$1:$D$2241,4,0)),"CUIT NO CARGADO") -> 0
B18: 45905 | C18: 1 | D18: 6 | E18: 7376 | F18: 30716804360 | G18: =IFERROR(IF('Sept-26'!$F18="","-",VLOOKUP('Sept-26'!$F18,Lista_CUIT!$A$1:$D$2241,2,0)),"CUIT NO CARGADO") -> OFFIPLAST | H18: 1392.6 | I18: =IF('Sept-26'!$H18="","",'Sept-26'!$H18*0.21) -> 292.446 | P18: =SUM('Sept-26'!$H18:$O18) -> 1685.046 | Q18: =IFERROR(IF('Sept-26'!$F18="","-",VLOOKUP('Sept-26'!$F18,Lista_CUIT!$A$1:$D$2241,3,0)),"CUIT NO CARGADO") -> 0 | R18: =IFERROR(IF('Sept-26'!$F18="","-",VLOOKUP('Sept-26'!$F18,Lista_CUIT!$A$1:$D$2241,4,0)),"CUIT NO CARGADO") -> 0
B19: 45905 | C19: 1 | D19: 1 | E19: 990 | F19: 30715048066 | G19: =IFERROR(IF('Sept-26'!$F19="","-",VLOOKUP('Sept-26'!$F19,Lista_CUIT!$A$1:$D$2241,2,0)),"CUIT NO CARGADO") -> ROLLS Y EMPANADAS SA | H19: 844070 | I19: =IF('Sept-26'!$H19="","",'Sept-26'!$H19*0.21) -> 177254.7 | P19: =SUM('Sept-26'!$H19:$O19) -> 1021324.7 | Q19: =IFERROR(IF('Sept-26'!$F19="","-",VLOOKUP('Sept-26'!$F19,Lista_CUIT!$A$1:$D$2241,3,0)),"CUIT NO CARGADO") -> CATERING | R19: =IFERROR(IF('Sept-26'!$F19="","-",VLOOKUP('Sept-26'!$F19,Lista_CUIT!$A$1:$D$2241,4,0)),"CUIT NO CARGADO") -> 0
B20: 45906 | C20: 1 | D20: 6996 | E20: 35470 | F20: 30678774495 | G20: =IFERROR(IF('Sept-26'!$F20="","-",VLOOKUP('Sept-26'!$F20,Lista_CUIT!$A$1:$D$2241,2,0)),"CUIT NO CARGADO") -> OPER. DE EST. DE SERV. SA | H20: 33435.53 | I20: =IF('Sept-26'!$H20="","",'Sept-26'!$H20*0.21) -> 7021.4613 | P20: =SUM('Sept-26'!$H20:$O20) -> 49009.961 | Q20: =IFERROR(IF('Sept-26'!$F20="","-",VLOOKUP('Sept-26'!$F20,Lista_CUIT!$A$1:$D$2241,3,0)),"CUIT NO CARGADO") -> COMBUSTIBLE | R20: =IFERROR(IF('Sept-26'!$F20="","-",VLOOKUP('Sept-26'!$F20,Lista_CUIT!$A$1:$D$2241,4,0)),"CUIT NO CARGADO") -> 0
B21: 45906 | C21: 1 | D21: 63 | E21: 3459071 | F21: 30640897267 | G21: =IFERROR(IF('Sept-26'!$F21="","-",VLOOKUP('Sept-26'!$F21,Lista_CUIT!$A$1:$D$2241,2,0)),"CUIT NO CARGADO") -> TELECENTRO SA | H21: 17392.52 | I21: =IF('Sept-26'!$H21="","",'Sept-26'!$H21*0.21) -> 3652.4292 | P21: =SUM('Sept-26'!$H21:$O21) -> 21566.729 | Q21: =IFERROR(IF('Sept-26'!$F21="","-",VLOOKUP('Sept-26'!$F21,Lista_CUIT!$A$1:$D$2241,3,0)),"CUIT NO CARGADO") -> SERVICIOS | R21: =IFERROR(IF('Sept-26'!$F21="","-",VLOOKUP('Sept-26'!$F21,Lista_CUIT!$A$1:$D$2241,4,0)),"CUIT NO CARGADO") -> 0
B22: 45908 | C22: 1 | D22: 5 | E22: 35238 | F22: 30708261110 | G22: =IFERROR(IF('Sept-26'!$F22="","-",VLOOKUP('Sept-26'!$F22,Lista_CUIT!$A$1:$D$2241,2,0)),"CUIT NO CARGADO") -> MULTIPLES S R L | H22: 92700 | I22: =IF('Sept-26'!$H22="","",'Sept-26'!$H22*0.21) -> 19467 | P22: =SUM('Sept-26'!$H22:$O22) -> 112167 | Q22: =IFERROR(IF('Sept-26'!$F22="","-",VLOOKUP('Sept-26'!$F22,Lista_CUIT!$A$1:$D$2241,3,0)),"CUIT NO CARGADO") -> 0 | R22: =IFERROR(IF('Sept-26'!$F22="","-",VLOOKUP('Sept-26'!$F22,Lista_CUIT!$A$1:$D$2241,4,0)),"CUIT NO CARGADO") -> 0
B23: 45910 | C23: 1 | D23: 7 | E23: 56635 | F23: 20372347296 | G23: =IFERROR(IF('Sept-26'!$F23="","-",VLOOKUP('Sept-26'!$F23,Lista_CUIT!$A$1:$D$2241,2,0)),"CUIT NO CARGADO") -> GHERTNER SEBASTIAN | H23: 303320.36 | K23: 31848.64 | P23: =SUM('Sept-26'!$H23:$O23) -> 335169 | Q23: =IFERROR(IF('Sept-26'!$F23="","-",VLOOKUP('Sept-26'!$F23,Lista_CUIT!$A$1:$D$2241,3,0)),"CUIT NO CARGADO") -> 0 | R23: =IFERROR(IF('Sept-26'!$F23="","-",VLOOKUP('Sept-26'!$F23,Lista_CUIT!$A$1:$D$2241,4,0)),"CUIT NO CARGADO") -> 0
B24: 45910 | C24: 1 | D24: 7 | E24: 56636 | F24: 20372347296 | G24: =IFERROR(IF('Sept-26'!$F24="","-",VLOOKUP('Sept-26'!$F24,Lista_CUIT!$A$1:$D$2241,2,0)),"CUIT NO CARGADO") -> GHERTNER SEBASTIAN | H24: 513513.71 | I24: 23164.39 | K24: 42336.74 | P24: =SUM('Sept-26'!$H24:$O24) -> 579014.84 | Q24: =IFERROR(IF('Sept-26'!$F24="","-",VLOOKUP('Sept-26'!$F24,Lista_CUIT!$A$1:$D$2241,3,0)),"CUIT NO CARGADO") -> 0 | R24: =IFERROR(IF('Sept-26'!$F24="","-",VLOOKUP('Sept-26'!$F24,Lista_CUIT!$A$1:$D$2241,4,0)),"CUIT NO CARGADO") -> 0
B25: 45911 | C25: 1 | D25: 13 | E25: 1237 | F25: 20346807602 | G25: =IFERROR(IF('Sept-26'!$F25="","-",VLOOKUP('Sept-26'!$F25,Lista_CUIT!$A$1:$D$2241,2,0)),"CUIT NO CARGADO") -> GODOY JORGE LUIS | H25: 4256.2 | I25: =IF('Sept-26'!$H25="","",'Sept-26'!$H25*0.21) -> 893.802 | P25: =SUM('Sept-26'!$H25:$O25) -> 5150.002 | Q25: =IFERROR(IF('Sept-26'!$F25="","-",VLOOKUP('Sept-26'!$F25,Lista_CUIT!$A$1:$D$2241,3,0)),"CUIT NO CARGADO") -> 0 | R25: =IFERROR(IF('Sept-26'!$F25="","-",VLOOKUP('Sept-26'!$F25,Lista_CUIT!$A$1:$D$2241,4,0)),"CUIT NO CARGADO") -> 0
B26: 45911 | C26: 1 | D26: 4 | E26: 11789 | F26: 20234861973 | G26: =IFERROR(IF('Sept-26'!$F26="","-",VLOOKUP('Sept-26'!$F26,Lista_CUIT!$A$1:$D$2241,2,0)),"CUIT NO CARGADO") -> MILEO VICENTE SAMUEL | H26: 4876.03 | I26: =IF('Sept-26'!$H26="","",'Sept-26'!$H26*0.21) -> 1023.9663 | P26: =SUM('Sept-26'!$H26:$O26) -> 5899.9963 | Q26: =IFERROR(IF('Sept-26'!$F26="","-",VLOOKUP('Sept-26'!$F26,Lista_CUIT!$A$1:$D$2241,3,0)),"CUIT NO CARGADO") -> 0 | R26: =IFERROR(IF('Sept-26'!$F26="","-",VLOOKUP('Sept-26'!$F26,Lista_CUIT!$A$1:$D$2241,4,0)),"CUIT NO CARGADO") -> 0
B27: 45911 | C27: 1 | D27: 3 | E27: 17804 | F27: 20293627127 | G27: =IFERROR(IF('Sept-26'!$F27="","-",VLOOKUP('Sept-26'!$F27,Lista_CUIT!$A$1:$D$2241,2,0)),"CUIT NO CARGADO") -> GONZALEZ FERNANDO ARIEL | H27: 31193.43 | I27: =IF('Sept-26'!$H27="","",'Sept-26'!$H27*0.21) -> 6550.6203 | P27: =SUM('Sept-26'!$H27:$O27) -> 37744.05 | Q27: =IFERROR(IF('Sept-26'!$F27="","-",VLOOKUP('Sept-26'!$F27,Lista_CUIT!$A$1:$D$2241,3,0)),"CUIT NO CARGADO") -> GASTOS VARIOS | R27: =IFERROR(IF('Sept-26'!$F27="","-",VLOOKUP('Sept-26'!$F27,Lista_CUIT!$A$1:$D$2241,4,0)),"CUIT NO CARGADO") -> 0
B28: 45911 | C28: 1 | D28: 2 | E28: 15686 | F28: 30718473558 | G28: =IFERROR(IF('Sept-26'!$F28="","-",VLOOKUP('Sept-26'!$F28,Lista_CUIT!$A$1:$D$2241,2,0)),"CUIT NO CARGADO") -> BAZOKA S. A. S. | H28: 2734.71 | I28: =IF('Sept-26'!$H28="","",'Sept-26'!$H28*0.21) -> 574.2891 | P28: =SUM('Sept-26'!$H28:$O28) -> 3308.9991 | Q28: =IFERROR(IF('Sept-26'!$F28="","-",VLOOKUP('Sept-26'!$F28,Lista_CUIT!$A$1:$D$2241,3,0)),"CUIT NO CARGADO") -> 0 | R28: =IFERROR(IF('Sept-26'!$F28="","-",VLOOKUP('Sept-26'!$F28,Lista_CUIT!$A$1:$D$2241,4,0)),"CUIT NO CARGADO") -> 0
B29: 45911 | C29: 1 | D29: 13 | E29: 1247 | F29: 20346807602 | G29: =IFERROR(IF('Sept-26'!$F29="","-",VLOOKUP('Sept-26'!$F29,Lista_CUIT!$A$1:$D$2241,2,0)),"CUIT NO CARGADO") -> GODOY JORGE LUIS | H29: 4256.2 | I29: =IF('Sept-26'!$H29="","",'Sept-26'!$H29*0.21) -> 893.802 | P29: =SUM('Sept-26'!$H29:$O29) -> 5150.002 | Q29: =IFERROR(IF('Sept-26'!$F29="","-",VLOOKUP('Sept-26'!$F29,Lista_CUIT!$A$1:$D$2241,3,0)),"CUIT NO CARGADO") -> 0 | R29: =IFERROR(IF('Sept-26'!$F29="","-",VLOOKUP('Sept-26'!$F29,Lista_CUIT!$A$1:$D$2241,4,0)),"CUIT NO CARGADO") -> 0
B30: 45911 | C30: 1 | D30: 2 | E30: 15669 | F30: 30718473558 | G30: =IFERROR(IF('Sept-26'!$F30="","-",VLOOKUP('Sept-26'!$F30,Lista_CUIT!$A$1:$D$2241,2,0)),"CUIT NO CARGADO") -> BAZOKA S. A. S. | H30: 2734.71 | I30: =IF('Sept-26'!$H30="","",'Sept-26'!$H30*0.21) -> 574.2891 | P30: =SUM('Sept-26'!$H30:$O30) -> 3308.9991 | Q30: =IFERROR(IF('Sept-26'!$F30="","-",VLOOKUP('Sept-26'!$F30,Lista_CUIT!$A$1:$D$2241,3,0)),"CUIT NO CARGADO") -> 0 | R30: =IFERROR(IF('Sept-26'!$F30="","-",VLOOKUP('Sept-26'!$F30,Lista_CUIT!$A$1:$D$2241,4,0)),"CUIT NO CARGADO") -> 0
B31: 45911 | C31: 1 | D31: 3 | E31: GASTOS VARIOS | F31: 20921575743 | G31: =IFERROR(IF('Sept-26'!$F31="","-",VLOOKUP('Sept-26'!$F31,Lista_CUIT!$A$1:$D$2241,2,0)),"CUIT NO CARGADO") -> RIOS GOMEZ JOSE ANTONIO | H31: 234000 | I31: =IF('Sept-26'!$H31="","",'Sept-26'!$H31*0.21) -> 49140 | P31: =SUM('Sept-26'!$H31:$O31) -> 283140 | Q31: =IFERROR(IF('Sept-26'!$F31="","-",VLOOKUP('Sept-26'!$F31,Lista_CUIT!$A$1:$D$2241,3,0)),"CUIT NO CARGADO") -> Papeleria | R31: =IFERROR(IF('Sept-26'!$F31="","-",VLOOKUP('Sept-26'!$F31,Lista_CUIT!$A$1:$D$2241,4,0)),"CUIT NO CARGADO") -> 0
B32: 45912 | C32: 1 | D32: 100 | E32: 1539 | F32: 20143939740 | G32: =IFERROR(IF('Sept-26'!$F32="","-",VLOOKUP('Sept-26'!$F32,Lista_CUIT!$A$1:$D$2241,2,0)),"CUIT NO CARGADO") -> BERASALUCE JOSE IGNACIO | H32: 2502.44 | I32: =IF('Sept-26'!$H32="","",'Sept-26'!$H32*0.21) -> 525.5124 | P32: =SUM('Sept-26'!$H32:$O32) -> 3027.9524 | Q32: =IFERROR(IF('Sept-26'!$F32="","-",VLOOKUP('Sept-26'!$F32,Lista_CUIT!$A$1:$D$2241,3,0)),"CUIT NO CARGADO") -> 0 | R32: =IFERROR(IF('Sept-26'!$F32="","-",VLOOKUP('Sept-26'!$F32,Lista_CUIT!$A$1:$D$2241,4,0)),"CUIT NO CARGADO") -> 0
B33: 45912 | C33: 1 | D33: 100 | E33: 1548 | F33: 20143939740 | G33: =IFERROR(IF('Sept-26'!$F33="","-",VLOOKUP('Sept-26'!$F33,Lista_CUIT!$A$1:$D$2241,2,0)),"CUIT NO CARGADO") -> BERASALUCE JOSE IGNACIO | H33: 2502.44 | I33: =IF('Sept-26'!$H33="","",'Sept-26'!$H33*0.21) -> 525.5124 | P33: =SUM('Sept-26'!$H33:$O33) -> 3027.9524 | Q33: =IFERROR(IF('Sept-26'!$F33="","-",VLOOKUP('Sept-26'!$F33,Lista_CUIT!$A$1:$D$2241,3,0)),"CUIT NO CARGADO") -> 0 | R33: =IFERROR(IF('Sept-26'!$F33="","-",VLOOKUP('Sept-26'!$F33,Lista_CUIT!$A$1:$D$2241,4,0)),"CUIT NO CARGADO") -> 0
B34: 45912 | C34: 1 | D34: 13 | E34: 101182 | F34: 30709256420 | G34: =IFERROR(IF('Sept-26'!$F34="","-",VLOOKUP('Sept-26'!$F34,Lista_CUIT!$A$1:$D$2241,2,0)),"CUIT NO CARGADO") -> NGA SRL | H34: 1306.03 | I34: =IF('Sept-26'!$H34="","",'Sept-26'!$H34*0.21) -> 274.2663 | P34: =SUM('Sept-26'!$H34:$O34) -> 1580.2963 | Q34: =IFERROR(IF('Sept-26'!$F34="","-",VLOOKUP('Sept-26'!$F34,Lista_CUIT!$A$1:$D$2241,3,0)),"CUIT NO CARGADO") -> GASTOS VARIOS | R34: =IFERROR(IF('Sept-26'!$F34="","-",VLOOKUP('Sept-26'!$F34,Lista_CUIT!$A$1:$D$2241,4,0)),"CUIT NO CARGADO") -> 0
B35: 45912 | C35: 1 | D35: 13 | E35: 101183 | F35: 30709256420 | G35: =IFERROR(IF('Sept-26'!$F35="","-",VLOOKUP('Sept-26'!$F35,Lista_CUIT!$A$1:$D$2241,2,0)),"CUIT NO CARGADO") -> NGA SRL | H35: 7581.16 | I35: =IF('Sept-26'!$H35="","",'Sept-26'!$H35*0.21) -> 1592.0436 | P35: =SUM('Sept-26'!$H35:$O35) -> 9173.2036 | Q35: =IFERROR(IF('Sept-26'!$F35="","-",VLOOKUP('Sept-26'!$F35,Lista_CUIT!$A$1:$D$2241,3,0)),"CUIT NO CARGADO") -> GASTOS VARIOS | R35: =IFERROR(IF('Sept-26'!$F35="","-",VLOOKUP('Sept-26'!$F35,Lista_CUIT!$A$1:$D$2241,4,0)),"CUIT NO CARGADO") -> 0
B36: 45912 | C36: 1 | D36: 2 | E36: 999 | F36: 30718734203 | G36: =IFERROR(IF('Sept-26'!$F36="","-",VLOOKUP('Sept-26'!$F36,Lista_CUIT!$A$1:$D$2241,2,0)),"CUIT NO CARGADO") -> C&G LATAM | H36: 7759.5 | I36: =IF('Sept-26'!$H36="","",'Sept-26'!$H36*0.21) -> 1629.495 | P36: =SUM('Sept-26'!$H36:$O36) -> 9388.995 | Q36: =IFERROR(IF('Sept-26'!$F36="","-",VLOOKUP('Sept-26'!$F36,Lista_CUIT!$A$1:$D$2241,3,0)),"CUIT NO CARGADO") -> 0 | R36: =IFERROR(IF('Sept-26'!$F36="","-",VLOOKUP('Sept-26'!$F36,Lista_CUIT!$A$1:$D$2241,4,0)),"CUIT NO CARGADO") -> 0
B37: 45912 | C37: 1 | D37: 2 | E37: 1005 | F37: 30718734203 | G37: =IFERROR(IF('Sept-26'!$F37="","-",VLOOKUP('Sept-26'!$F37,Lista_CUIT!$A$1:$D$2241,2,0)),"CUIT NO CARGADO") -> C&G LATAM | H37: 7759.5 | I37: =IF('Sept-26'!$H37="","",'Sept-26'!$H37*0.21) -> 1629.495 | P37: =SUM('Sept-26'!$H37:$O37) -> 9388.995 | Q37: =IFERROR(IF('Sept-26'!$F37="","-",VLOOKUP('Sept-26'!$F37,Lista_CUIT!$A$1:$D$2241,3,0)),"CUIT NO CARGADO") -> 0 | R37: =IFERROR(IF('Sept-26'!$F37="","-",VLOOKUP('Sept-26'!$F37,Lista_CUIT!$A$1:$D$2241,4,0)),"CUIT NO CARGADO") -> 0
B38: 45912 | C38: 1 | D38: 2 | E38: 219 | F38: 20125142851 | G38: =IFERROR(IF('Sept-26'!$F38="","-",VLOOKUP('Sept-26'!$F38,Lista_CUIT!$A$1:$D$2241,2,0)),"CUIT NO CARGADO") -> FEDERICI NICOLAS JOSE | H38: 151227.81 | I38: =IF('Sept-26'!$H38="","",'Sept-26'!$H38*0.21) -> 31757.84 | P38: =SUM('Sept-26'!$H38:$O38) -> 182985.65 | Q38: =IFERROR(IF('Sept-26'!$F38="","-",VLOOKUP('Sept-26'!$F38,Lista_CUIT!$A$1:$D$2241,3,0)),"CUIT NO CARGADO") -> INSUMO | R38: =IFERROR(IF('Sept-26'!$F38="","-",VLOOKUP('Sept-26'!$F38,Lista_CUIT!$A$1:$D$2241,4,0)),"CUIT NO CARGADO") -> 0
B39: 45913 | C39: 1 | D39: 50 | E39: 487524 | F39: 30610333822 | G39: =IFERROR(IF('Sept-26'!$F39="","-",VLOOKUP('Sept-26'!$F39,Lista_CUIT!$A$1:$D$2241,2,0)),"CUIT NO CARGADO") -> MASIVOS S A | H39: 2001.65 | I39: =IF('Sept-26'!$H39="","",'Sept-26'!$H39*0.21) -> 420.3465 | P39: =SUM('Sept-26'!$H39:$O39) -> 2421.9965 | Q39: =IFERROR(IF('Sept-26'!$F39="","-",VLOOKUP('Sept-26'!$F39,Lista_CUIT!$A$1:$D$2241,3,0)),"CUIT NO CARGADO") -> GASTOS VARIOS | R39: =IFERROR(IF('Sept-26'!$F39="","-",VLOOKUP('Sept-26'!$F39,Lista_CUIT!$A$1:$D$2241,4,0)),"CUIT NO CARGADO") -> 0
B40: 45914 | C40: 1 | D40: 100 | E40: 996 | F40: 20384564373 | G40: =IFERROR(IF('Sept-26'!$F40="","-",VLOOKUP('Sept-26'!$F40,Lista_CUIT!$A$1:$D$2241,2,0)),"CUIT NO CARGADO") -> ABRECHT JUAN FRANCISCO JORGE | H40: 56131.4 | I40: =IF('Sept-26'!$H40="","",'Sept-26'!$H40*0.21) -> 11787.594 | P40: =SUM('Sept-26'!$H40:$O40) -> 67918.994 | Q40: =IFERROR(IF('Sept-26'!$F40="","-",VLOOKUP('Sept-26'!$F40,Lista_CUIT!$A$1:$D$2241,3,0)),"CUIT NO CARGADO") -> 0 | R40: =IFERROR(IF('Sept-26'!$F40="","-",VLOOKUP('Sept-26'!$F40,Lista_CUIT!$A$1:$D$2241,4,0)),"CUIT NO CARGADO") -> 0
B41: 45915 | C41: 1 | D41: 2002 | E41: 12351 | F41: 30715699865 | G41: =IFERROR(IF('Sept-26'!$F41="","-",VLOOKUP('Sept-26'!$F41,Lista_CUIT!$A$1:$D$2241,2,0)),"CUIT NO CARGADO") -> VALYRIA SRL | H41: 58920.99 | I41: =IF('Sept-26'!$H41="","",'Sept-26'!$H41*0.21) -> 12373.408 | P41: =SUM('Sept-26'!$H41:$O41) -> 71294.398 | Q41: =IFERROR(IF('Sept-26'!$F41="","-",VLOOKUP('Sept-26'!$F41,Lista_CUIT!$A$1:$D$2241,3,0)),"CUIT NO CARGADO") -> 0 | R41: =IFERROR(IF('Sept-26'!$F41="","-",VLOOKUP('Sept-26'!$F41,Lista_CUIT!$A$1:$D$2241,4,0)),"CUIT NO CARGADO") -> 0
B42: 45915 | C42: 1 | D42: 33 | E42: 3702 | F42: 30714295957 | G42: =IFERROR(IF('Sept-26'!$F42="","-",VLOOKUP('Sept-26'!$F42,Lista_CUIT!$A$1:$D$2241,2,0)),"CUIT NO CARGADO") -> IT BROKERS S.A. | H42: 53134.14 | I42: 5725.54 | K42: 2716.32 | P42: =SUM('Sept-26'!$H42:$O42) -> 61576 | Q42: =IFERROR(IF('Sept-26'!$F42="","-",VLOOKUP('Sept-26'!$F42,Lista_CUIT!$A$1:$D$2241,3,0)),"CUIT NO CARGADO") -> 0 | R42: =IFERROR(IF('Sept-26'!$F42="","-",VLOOKUP('Sept-26'!$F42,Lista_CUIT!$A$1:$D$2241,4,0)),"CUIT NO CARGADO") -> 0
B43: 45915 | C43: 1 | D43: 6 | E43: 20367 | F43: 20316399909 | G43: =IFERROR(IF('Sept-26'!$F43="","-",VLOOKUP('Sept-26'!$F43,Lista_CUIT!$A$1:$D$2241,2,0)),"CUIT NO CARGADO") -> LICROPANI LUCAS IVAN | H43: 30604.97 | I43: =IF('Sept-26'!$H43="","",'Sept-26'!$H43*0.21) -> 6427.0437 | P43: =SUM('Sept-26'!$H43:$O43) -> 37032.014 | Q43: =IFERROR(IF('Sept-26'!$F43="","-",VLOOKUP('Sept-26'!$F43,Lista_CUIT!$A$1:$D$2241,3,0)),"CUIT NO CARGADO") -> 0 | R43: =IFERROR(IF('Sept-26'!$F43="","-",VLOOKUP('Sept-26'!$F43,Lista_CUIT!$A$1:$D$2241,4,0)),"CUIT NO CARGADO") -> 0
B44: 45916 | C44: 1 | D44: 106 | E44: 877245 | F44: 30594494187 | G44: =IFERROR(IF('Sept-26'!$F44="","-",VLOOKUP('Sept-26'!$F44,Lista_CUIT!$A$1:$D$2241,2,0)),"CUIT NO CARGADO") -> FEDERAL EXPRESS CORPORATION | H44: 0 | I44: =IF('Sept-26'!$H44="","",'Sept-26'!$H44*0.21) -> 0 | O44: 192997.55 | P44: =SUM('Sept-26'!$H44:$O44) -> 192997.55 | Q44: =IFERROR(IF('Sept-26'!$F44="","-",VLOOKUP('Sept-26'!$F44,Lista_CUIT!$A$1:$D$2241,3,0)),"CUIT NO CARGADO") -> Mercaderia | R44: =IFERROR(IF('Sept-26'!$F44="","-",VLOOKUP('Sept-26'!$F44,Lista_CUIT!$A$1:$D$2241,4,0)),"CUIT NO CARGADO") -> 0
B45: 45917 | C45: 1 | D45: 2 | E45: 29098 | F45: 30718061977 | G45: =IFERROR(IF('Sept-26'!$F45="","-",VLOOKUP('Sept-26'!$F45,Lista_CUIT!$A$1:$D$2241,2,0)),"CUIT NO CARGADO") -> ANIAMITO S.R.L | H45: 55374.4 | I45: =IF('Sept-26'!$H45="","",'Sept-26'!$H45*0.21) -> 11628.624 | P45: =SUM('Sept-26'!$H45:$O45) -> 67003.024 | Q45: =IFERROR(IF('Sept-26'!$F45="","-",VLOOKUP('Sept-26'!$F45,Lista_CUIT!$A$1:$D$2241,3,0)),"CUIT NO CARGADO") -> 0 | R45: =IFERROR(IF('Sept-26'!$F45="","-",VLOOKUP('Sept-26'!$F45,Lista_CUIT!$A$1:$D$2241,4,0)),"CUIT NO CARGADO") -> 0
B46: 45922 | C46: 1 | D46: 2 | E46: 909 | F46: 20296550184 | G46: =IFERROR(IF('Sept-26'!$F46="","-",VLOOKUP('Sept-26'!$F46,Lista_CUIT!$A$1:$D$2241,2,0)),"CUIT NO CARGADO") -> COSTA DIEGO ALEJANDRO | H46: 530000 | I46: =IF('Sept-26'!$H46="","",'Sept-26'!$H46*0.21) -> 111300 | P46: =SUM('Sept-26'!$H46:$O46) -> 641300 | Q46: =IFERROR(IF('Sept-26'!$F46="","-",VLOOKUP('Sept-26'!$F46,Lista_CUIT!$A$1:$D$2241,3,0)),"CUIT NO CARGADO") -> Mat. Prima | R46: =IFERROR(IF('Sept-26'!$F46="","-",VLOOKUP('Sept-26'!$F46,Lista_CUIT!$A$1:$D$2241,4,0)),"CUIT NO CARGADO") -> 0
B47: 45926 | C47: 1 | D47: 7 | E47: 2304 | F47: 20371136046 | G47: =IFERROR(IF('Sept-26'!$F47="","-",VLOOKUP('Sept-26'!$F47,Lista_CUIT!$A$1:$D$2241,2,0)),"CUIT NO CARGADO") -> SCIARILLO NICOLAS DANIEL | H47: 24573.45 | I47: =IF('Sept-26'!$H47="","",'Sept-26'!$H47*0.21) -> 5160.4245 | P47: =SUM('Sept-26'!$H47:$O47) -> 29733.875 | Q47: =IFERROR(IF('Sept-26'!$F47="","-",VLOOKUP('Sept-26'!$F47,Lista_CUIT!$A$1:$D$2241,3,0)),"CUIT NO CARGADO") -> 0 | R47: =IFERROR(IF('Sept-26'!$F47="","-",VLOOKUP('Sept-26'!$F47,Lista_CUIT!$A$1:$D$2241,4,0)),"CUIT NO CARGADO") -> 0 | S47: COD 5
B48: 45930 | C48: 1 | D48: 7 | E48: 90 | F48: 20272258776 | G48: =IFERROR(IF('Sept-26'!$F48="","-",VLOOKUP('Sept-26'!$F48,Lista_CUIT!$A$1:$D$2241,2,0)),"CUIT NO CARGADO") -> STELKIC FEDERICO | H48: 5619.83 | I48: =IF('Sept-26'!$H48="","",'Sept-26'!$H48*0.21) -> 1180.1643 | P48: =SUM('Sept-26'!$H48:$O48) -> 6799.9943 | Q48: =IFERROR(IF('Sept-26'!$F48="","-",VLOOKUP('Sept-26'!$F48,Lista_CUIT!$A$1:$D$2241,3,0)),"CUIT NO CARGADO") -> 0 | R48: =IFERROR(IF('Sept-26'!$F48="","-",VLOOKUP('Sept-26'!$F48,Lista_CUIT!$A$1:$D$2241,4,0)),"CUIT NO CARGADO") -> 0
B49: 45911 | C49: 3 | D49: 13 | E49: 325 | F49: 20346807602 | G49: =IFERROR(IF('Sept-26'!$F49="","-",VLOOKUP('Sept-26'!$F49,Lista_CUIT!$A$1:$D$2241,2,0)),"CUIT NO CARGADO") -> GODOY JORGE LUIS | H49: -4256.2 | I49: =IF('Sept-26'!$H49="","",'Sept-26'!$H49*0.21) -> -893.802 | P49: =SUM('Sept-26'!$H49:$O49) -> -5150.002 | Q49: =IFERROR(IF('Sept-26'!$F49="","-",VLOOKUP('Sept-26'!$F49,Lista_CUIT!$A$1:$D$2241,3,0)),"CUIT NO CARGADO") -> 0 | R49: =IFERROR(IF('Sept-26'!$F49="","-",VLOOKUP('Sept-26'!$F49,Lista_CUIT!$A$1:$D$2241,4,0)),"CUIT NO CARGADO") -> 0
B50: 45912 | C50: 3 | D50: 2 | E50: 2316 | F50: 30718473558 | G50: =IFERROR(IF('Sept-26'!$F50="","-",VLOOKUP('Sept-26'!$F50,Lista_CUIT!$A$1:$D$2241,2,0)),"CUIT NO CARGADO") -> BAZOKA S. A. S. | H50: -2734.71 | I50: =IF('Sept-26'!$H50="","",'Sept-26'!$H50*0.21) -> -574.2891 | P50: =SUM('Sept-26'!$H50:$O50) -> -3308.9991 | Q50: =IFERROR(IF('Sept-26'!$F50="","-",VLOOKUP('Sept-26'!$F50,Lista_CUIT!$A$1:$D$2241,3,0)),"CUIT NO CARGADO") -> 0 | R50: =IFERROR(IF('Sept-26'!$F50="","-",VLOOKUP('Sept-26'!$F50,Lista_CUIT!$A$1:$D$2241,4,0)),"CUIT NO CARGADO") -> 0
B51: 45912 | C51: 3 | D51: 100 | E51: 82 | F51: 20143939740 | G51: =IFERROR(IF('Sept-26'!$F51="","-",VLOOKUP('Sept-26'!$F51,Lista_CUIT!$A$1:$D$2241,2,0)),"CUIT NO CARGADO") -> BERASALUCE JOSE IGNACIO | H51: -2502.44 | I51: =IF('Sept-26'!$H51="","",'Sept-26'!$H51*0.21) -> -525.5124 | P51: =SUM('Sept-26'!$H51:$O51) -> -3027.9524 | Q51: =IFERROR(IF('Sept-26'!$F51="","-",VLOOKUP('Sept-26'!$F51,Lista_CUIT!$A$1:$D$2241,3,0)),"CUIT NO CARGADO") -> 0 | R51: =IFERROR(IF('Sept-26'!$F51="","-",VLOOKUP('Sept-26'!$F51,Lista_CUIT!$A$1:$D$2241,4,0)),"CUIT NO CARGADO") -> 0
B52: 45912 | C52: 3 | D52: 2 | E52: 310 | F52: 30718734203 | G52: =IFERROR(IF('Sept-26'!$F52="","-",VLOOKUP('Sept-26'!$F52,Lista_CUIT!$A$1:$D$2241,2,0)),"CUIT NO CARGADO") -> C&G LATAM | H52: -7759.5 | I52: =IF('Sept-26'!$H52="","",'Sept-26'!$H52*0.21) -> -1629.495 | P52: =SUM('Sept-26'!$H52:$O52) -> -9388.995 | Q52: =IFERROR(IF('Sept-26'!$F52="","-",VLOOKUP('Sept-26'!$F52,Lista_CUIT!$A$1:$D$2241,3,0)),"CUIT NO CARGADO") -> 0 | R52: =IFERROR(IF('Sept-26'!$F52="","-",VLOOKUP('Sept-26'!$F52,Lista_CUIT!$A$1:$D$2241,4,0)),"CUIT NO CARGADO") -> 0
G53: =IFERROR(IF('Sept-26'!$F53="","-",VLOOKUP('Sept-26'!$F53,Lista_CUIT!$A$1:$D$2241,2,0)),"CUIT NO CARGADO") -> - | I53: =IF('Sept-26'!$H53="","",'Sept-26'!$H53*0.21) | P53: =SUM('Sept-26'!$H53:$O53) -> 0 | Q53: =IFERROR(IF('Sept-26'!$F53="","-",VLOOKUP('Sept-26'!$F53,Lista_CUIT!$A$1:$D$2241,3,0)),"CUIT NO CARGADO") -> - | R53: =IFERROR(IF('Sept-26'!$F53="","-",VLOOKUP('Sept-26'!$F53,Lista_CUIT!$A$1:$D$2241,4,0)),"CUIT NO CARGADO") -> -
B54: Total | H54: =SUBTOTAL(109,'Sept-26'!$H$9:$H$53) -> 4113041.9 | I54: =SUBTOTAL(109,'Sept-26'!$I$9:$I$53) -> 625271.63 | J54: =SUBTOTAL(109,'Sept-26'!$J$9:$J$53) -> 0 | K54: =SUBTOTAL(109,'Sept-26'!$K$9:$K$53) -> 119233.59 | L54: =SUBTOTAL(109,'Sept-26'!$L$9:$L$53) -> 521.78 | M54: =SUBTOTAL(109,'Sept-26'!$M$9:$M$53) -> 0 | N54: =SUBTOTAL(109,'Sept-26'!$N$9:$N$53) -> 0 | O54: =SUBTOTAL(109,'Sept-26'!$O$9:$O$53) -> 1061731.8 | P54: =SUBTOTAL(109,'Sept-26'!$P$9:$P$53) -> 5919800.7
D59: LIQUIDACION EXTRACTOS BANCARIOS-TARJETAS
D60: FECHA | E60: NRO CPTE | F60: BANCO | G60: NETO | H60: IVA 21% | I60: IVA 10,5% | J60: RET IIBB CABA | K60: PERC IVA | L60: PERC IIBB
C61: LIQ | D61: 45919 | E61: 928621000 | F61: CREDICOOP | G61: 110568.75 | H61: ='Sept-26'!$G61*0.21 -> 23219.438
C62: EXTRC | D62: 45930 | F62: CREDICOOP | G62: =18400.25/0.21 -> 87620.238 | H62: ='Sept-26'!$G62*0.21 -> 18400.25 | K62: 2547.61
H63: ='Sept-26'!$G63*0.21 -> 0
H64: ='Sept-26'!$G64*0.21 -> 0
D65: Total | G65: =SUBTOTAL(109,'Sept-26'!$G$61:$G$64) -> 198188.99 | H65: =SUBTOTAL(109,'Sept-26'!$H$61:$H$64) -> 41619.688 | I65: =SUBTOTAL(109,'Sept-26'!$I$61:$I$64) -> 0 | J65: =SUBTOTAL(109,'Sept-26'!$J$61:$J$64) -> 0 | K65: =SUBTOTAL(109,'Sept-26'!$K$61:$K$64) -> 2547.61 | L65: =SUBTOTAL(109,'Sept-26'!$L$61:$L$64) -> 0
D67: FACTURAS C
D68: FECHA | E68: PTO VTA | F68: FC Nº | G68: CUIT | H68: RAZON SOCIAL | I68: TOTAL | J68: TIPO DE GASTO | K68: Provincia
D69: 45901 | E69: 4 | F69: 61 | G69: 20086277523 | H69: =IFERROR(IF('Sept-26'!$G69="","-",VLOOKUP('Sept-26'!$G69,Lista_CUIT!$A$1:$D$2241,2,0)),"CUIT NO CARGADO") -> ESTUDIO BOTINDARI | I69: 400000 | J69: =IFERROR(IF('Sept-26'!$G69="","-",VLOOKUP('Sept-26'!$G69,Lista_CUIT!$A$1:$D$2241,3,0)),"CUIT NO CARGADO") -> Honorarios Contables | K69: =IFERROR(IF('Sept-26'!$G69="","-",VLOOKUP('Sept-26'!$G69,Lista_CUIT!$A$1:$D$2241,4,0)),"CUIT NO CARGADO") -> 0
D70: 45901 | E70: 1 | F70: 164 | G70: 20389908569 | H70: =IFERROR(IF('Sept-26'!$G70="","-",VLOOKUP('Sept-26'!$G70,Lista_CUIT!$A$1:$D$2241,2,0)),"CUIT NO CARGADO") -> BOTINDARI JUAN IGNACIO | I70: 125000 | J70: =IFERROR(IF('Sept-26'!$G70="","-",VLOOKUP('Sept-26'!$G70,Lista_CUIT!$A$1:$D$2241,3,0)),"CUIT NO CARGADO") -> Honorarios Contables | K70: =IFERROR(IF('Sept-26'!$G70="","-",VLOOKUP('Sept-26'!$G70,Lista_CUIT!$A$1:$D$2241,4,0)),"CUIT NO CARGADO") -> 0
D71: 45901 | E71: 2 | F71: 23 | G71: 23118167279 | H71: =IFERROR(IF('Sept-26'!$G71="","-",VLOOKUP('Sept-26'!$G71,Lista_CUIT!$A$1:$D$2241,2,0)),"CUIT NO CARGADO") -> ABELEDO ENRIQUE JUAN | I71: 2860000 | J71: =IFERROR(IF('Sept-26'!$G71="","-",VLOOKUP('Sept-26'!$G71,Lista_CUIT!$A$1:$D$2241,3,0)),"CUIT NO CARGADO") -> Honorarios Admin | K71: =IFERROR(IF('Sept-26'!$G71="","-",VLOOKUP('Sept-26'!$G71,Lista_CUIT!$A$1:$D$2241,4,0)),"CUIT NO CARGADO") -> 0
D72: 45901 | E72: 2 | F72: 187 | G72: 20136544625 | H72: =IFERROR(IF('Sept-26'!$G72="","-",VLOOKUP('Sept-26'!$G72,Lista_CUIT!$A$1:$D$2241,2,0)),"CUIT NO CARGADO") -> RODRIGUEZ DE LA FUEN HECTOR MARCELO | I72: 1217000 | J72: =IFERROR(IF('Sept-26'!$G72="","-",VLOOKUP('Sept-26'!$G72,Lista_CUIT!$A$1:$D$2241,3,0)),"CUIT NO CARGADO") -> Honorarios Admin | K72: =IFERROR(IF('Sept-26'!$G72="","-",VLOOKUP('Sept-26'!$G72,Lista_CUIT!$A$1:$D$2241,4,0)),"CUIT NO CARGADO") -> 0
D73: 45901 | E73: 1 | F73: 116 | G73: 20341465134 | H73: =IFERROR(IF('Sept-26'!$G73="","-",VLOOKUP('Sept-26'!$G73,Lista_CUIT!$A$1:$D$2241,2,0)),"CUIT NO CARGADO") -> ABELEDO AGUSTIN ENRIQUE | I73: 3147900 | J73: =IFERROR(IF('Sept-26'!$G73="","-",VLOOKUP('Sept-26'!$G73,Lista_CUIT!$A$1:$D$2241,3,0)),"CUIT NO CARGADO") -> Mantenimiento | K73: =IFERROR(IF('Sept-26'!$G73="","-",VLOOKUP('Sept-26'!$G73,Lista_CUIT!$A$1:$D$2241,4,0)),"CUIT NO CARGADO") -> CABA
D74: 45903 | E74: 1 | F74: 45 | G74: 27387896150 | H74: =IFERROR(IF('Sept-26'!$G74="","-",VLOOKUP('Sept-26'!$G74,Lista_CUIT!$A$1:$D$2241,2,0)),"CUIT NO CARGADO") -> LIPANOVICH MARIA SOL | I74: 613357.8 | J74: =IFERROR(IF('Sept-26'!$G74="","-",VLOOKUP('Sept-26'!$G74,Lista_CUIT!$A$1:$D$2241,3,0)),"CUIT NO CARGADO") -> consultoria informatica | K74: =IFERROR(IF('Sept-26'!$G74="","-",VLOOKUP('Sept-26'!$G74,Lista_CUIT!$A$1:$D$2241,4,0)),"CUIT NO CARGADO") -> 0
D75: 45903 | E75: 1 | F75: 46 | G75: 27387896150 | H75: =IFERROR(IF('Sept-26'!$G75="","-",VLOOKUP('Sept-26'!$G75,Lista_CUIT!$A$1:$D$2241,2,0)),"CUIT NO CARGADO") -> LIPANOVICH MARIA SOL | I75: 1925000 | J75: =IFERROR(IF('Sept-26'!$G75="","-",VLOOKUP('Sept-26'!$G75,Lista_CUIT!$A$1:$D$2241,3,0)),"CUIT NO CARGADO") -> consultoria informatica | K75: =IFERROR(IF('Sept-26'!$G75="","-",VLOOKUP('Sept-26'!$G75,Lista_CUIT!$A$1:$D$2241,4,0)),"CUIT NO CARGADO") -> 0
D76: 45908 | E76: 2 | F76: 1039 | G76: 20400104094 | H76: =IFERROR(IF('Sept-26'!$G76="","-",VLOOKUP('Sept-26'!$G76,Lista_CUIT!$A$1:$D$2241,2,0)),"CUIT NO CARGADO") -> FEDERICO BOTINDARI | I76: 3500000 | J76: =IFERROR(IF('Sept-26'!$G76="","-",VLOOKUP('Sept-26'!$G76,Lista_CUIT!$A$1:$D$2241,3,0)),"CUIT NO CARGADO") -> Honorarios Contables | K76: =IFERROR(IF('Sept-26'!$G76="","-",VLOOKUP('Sept-26'!$G76,Lista_CUIT!$A$1:$D$2241,4,0)),"CUIT NO CARGADO") -> 0
D77: 45908 | E77: 2 | F77: 293 | G77: 27173820866 | H77: =IFERROR(IF('Sept-26'!$G77="","-",VLOOKUP('Sept-26'!$G77,Lista_CUIT!$A$1:$D$2241,2,0)),"CUIT NO CARGADO") -> FREIER SANDRA DANIELA | I77: 1550000 | J77: =IFERROR(IF('Sept-26'!$G77="","-",VLOOKUP('Sept-26'!$G77,Lista_CUIT!$A$1:$D$2241,3,0)),"CUIT NO CARGADO") -> Honorarios Prof | K77: =IFERROR(IF('Sept-26'!$G77="","-",VLOOKUP('Sept-26'!$G77,Lista_CUIT!$A$1:$D$2241,4,0)),"CUIT NO CARGADO") -> 0
D78: 45923 | E78: 4 | F78: 56 | G78: 20341462933 | H78: =IFERROR(IF('Sept-26'!$G78="","-",VLOOKUP('Sept-26'!$G78,Lista_CUIT!$A$1:$D$2241,2,0)),"CUIT NO CARGADO") -> CASTIGLIONI MATIAS EZEQUIEL | I78: 2628000 | J78: =IFERROR(IF('Sept-26'!$G78="","-",VLOOKUP('Sept-26'!$G78,Lista_CUIT!$A$1:$D$2241,3,0)),"CUIT NO CARGADO") -> ASESORAMIENTO | K78: =IFERROR(IF('Sept-26'!$G78="","-",VLOOKUP('Sept-26'!$G78,Lista_CUIT!$A$1:$D$2241,4,0)),"CUIT NO CARGADO") -> BUENOS AIRES
D79: 45929 | E79: 4 | F79: 65 | G79: 20086277523 | H79: =IFERROR(IF('Sept-26'!$G79="","-",VLOOKUP('Sept-26'!$G79,Lista_CUIT!$A$1:$D$2241,2,0)),"CUIT NO CARGADO") -> ESTUDIO BOTINDARI | I79: 1150000 | J79: =IFERROR(IF('Sept-26'!$G79="","-",VLOOKUP('Sept-26'!$G79,Lista_CUIT!$A$1:$D$2241,3,0)),"CUIT NO CARGADO") -> Honorarios Contables | K79: =IFERROR(IF('Sept-26'!$G79="","-",VLOOKUP('Sept-26'!$G79,Lista_CUIT!$A$1:$D$2241,4,0)),"CUIT NO CARGADO") -> 0
D80: 45930 | E80: 4 | F80: 698 | G80: 20104903844 | H80: =IFERROR(IF('Sept-26'!$G80="","-",VLOOKUP('Sept-26'!$G80,Lista_CUIT!$A$1:$D$2241,2,0)),"CUIT NO CARGADO") -> URBIETA MARIO CESAR | I80: 33000 | J80: =IFERROR(IF('Sept-26'!$G80="","-",VLOOKUP('Sept-26'!$G80,Lista_CUIT!$A$1:$D$2241,3,0)),"CUIT NO CARGADO") -> 0 | K80: =IFERROR(IF('Sept-26'!$G80="","-",VLOOKUP('Sept-26'!$G80,Lista_CUIT!$A$1:$D$2241,4,0)),"CUIT NO CARGADO") -> 0
... D82: 45930 | E82: 1 | F82: 117 | G82: 20341465134 | H82: =IFERROR(IF('Sept-26'!$G82="","-",VLOOKUP('Sept-26'!$G82,Lista_CUIT!$A$1:$D$2241,2,0)),"CUIT NO CARGADO") -> ABELEDO AGUSTIN ENRIQUE | I82: 3147900 | J82: =IFERROR(IF('Sept-26'!$G82="","-",VLOOKUP('Sept-26'!$G82,Lista_CUIT!$A$1:$D$2241,3,0)),"CUIT NO CARGADO") -> Mantenimiento | K82: =IFERROR(IF('Sept-26'!$G82="","-",VLOOKUP('Sept-26'!$G82,Lista_CUIT!$A$1:$D$2241,4,0)),"CUIT NO CARGADO") -> CABA
D83: Total | I83: =SUBTOTAL(109,'Sept-26'!$I$69:$I$82) -> 22372158
B89: LIBRO IVA VENTAS | K89: =N1 -> 45901
B91: VENTAS "A"
B92: FECHA | C92: TIPO | D92: PTO VENTA | E92: Nº FACTURA | F92: CUIT | G92: RAZON SOCIAL | H92: IMPORTE NETO | I92: IVA 21% | J92: IVA 10,5% | K92: EXENTO | L92: TOTAL | M92: Provincia
B93: 45912 | C93: 1 | D93: 3 | E93: 288 | F93: 30716244330 | G93: =IFERROR(IF('Sept-26'!$F93="","-",VLOOKUP('Sept-26'!$F93,Lista_CUIT!$A$1:$D$2241,2,0)),"CUIT NO CARGADO") -> VULPIANI S.A. | H93: 1450000 | I93: ='Sept-26'!$H93*0.21 -> 304500 | L93: =SUM('Sept-26'!$H93:$K93) -> 1754500
B94: 45917 | C94: 1 | D94: 3 | E94: 289 | F94: 30628274327 | G94: =IFERROR(IF('Sept-26'!$F94="","-",VLOOKUP('Sept-26'!$F94,Lista_CUIT!$A$1:$D$2241,2,0)),"CUIT NO CARGADO") -> AGIRA S A | H94: 24906500 | J94: =Table_39[[#This Row],[IMPORTE NETO]]*0.105 -> 2615182.5 | L94: =SUM('Sept-26'!$H94:$K94) -> 27521682
B95: 45917 | C95: 1 | D95: 3 | E95: 291 | F95: 30638318470 | G95: =IFERROR(IF('Sept-26'!$F95="","-",VLOOKUP('Sept-26'!$F95,Lista_CUIT!$A$1:$D$2241,2,0)),"CUIT NO CARGADO") -> DELTA COMPRESION S R L | H95: 5190372 | I95: ='Sept-26'!$H95*0.21 -> 1089978.1 | L95: =SUM('Sept-26'!$H95:$K95) -> 6280350.1
B96: 45917 | C96: 1 | D96: 3 | E96: 290 | F96: 30638318470 | G96: =IFERROR(IF('Sept-26'!$F96="","-",VLOOKUP('Sept-26'!$F96,Lista_CUIT!$A$1:$D$2241,2,0)),"CUIT NO CARGADO") -> DELTA COMPRESION S R L | H96: 57914495 | I96: ='Sept-26'!$H96*0.21 -> 12162044 | L96: =SUM('Sept-26'!$H96:$K96) -> 70076539
B97: 45930 | C97: 1 | D97: 3 | E97: 292 | F97: 30716041596 | G97: =IFERROR(IF('Sept-26'!$F97="","-",VLOOKUP('Sept-26'!$F97,Lista_CUIT!$A$1:$D$2241,2,0)),"CUIT NO CARGADO") -> EXA COMPRESION S.R.L. | H97: 7293300 | I97: ='Sept-26'!$H97*0.21 -> 1531593 | L97: =SUM('Sept-26'!$H97:$K97) -> 8824893
B98: 45917 | C98: 2 | D98: 3 | E98: 12 | F98: 30638318470 | G98: =IFERROR(IF('Sept-26'!$F98="","-",VLOOKUP('Sept-26'!$F98,Lista_CUIT!$A$1:$D$2241,2,0)),"CUIT NO CARGADO") -> DELTA COMPRESION S R L | H98: 57914495 | I98: ='Sept-26'!$H98*0.21 -> 12162044 | L98: =SUM('Sept-26'!$H98:$K98) -> 70076539
B99: 45930 | C99: 2 | D99: 3 | E99: 13 | F99: 30638318470 | G99: =IFERROR(IF('Sept-26'!$F99="","-",VLOOKUP('Sept-26'!$F99,Lista_CUIT!$A$1:$D$2241,2,0)),"CUIT NO CARGADO") -> DELTA COMPRESION S R L | H99: 63104867 | I99: ='Sept-26'!$H99*0.21 -> 13252022 | L99: =SUM('Sept-26'!$H99:$K99) -> 76356889
B100: 45917 | C100: 3 | D100: 3 | E100: 31 | F100: 30638318470 | G100: =IFERROR(IF('Sept-26'!$F100="","-",VLOOKUP('Sept-26'!$F100,Lista_CUIT!$A$1:$D$2241,2,0)),"CUIT NO CARGADO") -> DELTA COMPRESION S R L | H100: -57914495 | I100: ='Sept-26'!$H100*0.21 -> -12162044 | L100: =SUM('Sept-26'!$H100:$K100) -> -70076539
B101: 45930 | C101: 3 | D101: 3 | E101: 35 | F101: 30718833112 | G101: =IFERROR(IF('Sept-26'!$F101="","-",VLOOKUP('Sept-26'!$F101,Lista_CUIT!$A$1:$D$2241,2,0)),"CUIT NO CARGADO") -> GUGAGAS ENERGY S.R.L. | H101: -4539000 | I101: ='Sept-26'!$H101*0.21 -> -953190 | L101: =SUM('Sept-26'!$H101:$K101) -> -5492190
B102: 45930 | C102: 3 | D102: 3 | E102: 33 | F102: 30638318470 | G102: =IFERROR(IF('Sept-26'!$F102="","-",VLOOKUP('Sept-26'!$F102,Lista_CUIT!$A$1:$D$2241,2,0)),"CUIT NO CARGADO") -> DELTA COMPRESION S R L | H102: -5190372 | I102: ='Sept-26'!$H102*0.21 -> -1089978.1 | L102: =SUM('Sept-26'!$H102:$K102) -> -6280350.1
B103: 45930 | C103: 3 | D103: 3 | E103: 34 | F103: 30638318470 | G103: =IFERROR(IF('Sept-26'!$F103="","-",VLOOKUP('Sept-26'!$F103,Lista_CUIT!$A$1:$D$2241,2,0)),"CUIT NO CARGADO") -> DELTA COMPRESION S R L | H103: -57914495 | I103: ='Sept-26'!$H103*0.21 -> -12162044 | L103: =SUM('Sept-26'!$H103:$K103) -> -70076539
B104: 45930 | C104: 3 | D104: 3 | E104: 32 | F104: 30638318470 | G104: =IFERROR(IF('Sept-26'!$F104="","-",VLOOKUP('Sept-26'!$F104,Lista_CUIT!$A$1:$D$2241,2,0)),"CUIT NO CARGADO") -> DELTA COMPRESION S R L | H104: -63104867 | I104: ='Sept-26'!$H104*0.21 -> -13252022 | L104: =SUM('Sept-26'!$H104:$K104) -> -76356889
B105: Total | H105: =SUBTOTAL(109,'Sept-26'!$H$93:$H$104) -> 29110800 | I105: =SUBTOTAL(109,'Sept-26'!$I$93:$I$104) -> 882903 | J105: =SUBTOTAL(109,'Sept-26'!$J$93:$J$104) -> 2615182.5 | K105: =SUBTOTAL(109,'Sept-26'!$K$93:$K$104) -> 0 | L105: =SUBTOTAL(109,'Sept-26'!$L$93:$L$104) -> 32608885 | M105: =SUBTOTAL(103,'Sept-26'!$M$93:$M$104) -> 0
B107: VENTAS "B"
B108: FECHA | C108: TIPO | D108: PTO VENTA | E108: Nº FACTURA | F108: CUIT | G108: RAZON SOCIAL | H108: IMPORTE NETO | I108: IVA 21% | J108: IVA 10,5% | K108: EXENTO | L108: TOTAL | M108: Provincia
G109: =IFERROR(IF('Sept-26'!$F109="","-",VLOOKUP('Sept-26'!$F109,Lista_CUIT!$A$1:$D$2241,2,0)),"CUIT NO CARGADO") -> - | L109: =SUM('Sept-26'!$H109:$K109) -> 0
L110: =SUM('Sept-26'!$H110:$K110) -> 0
L111: =SUM('Sept-26'!$H111:$K111) -> 0
L112: =SUM('Sept-26'!$H112:$K112) -> 0
L113: =SUM('Sept-26'!$H113:$K113) -> 0
L114: =SUM('Sept-26'!$H114:$K114) -> 0
B115: Total | H115: =SUBTOTAL(109,'Sept-26'!$H$109:$H$114) -> 0 | I115: =SUBTOTAL(109,'Sept-26'!$I$109:$I$114) -> 0 | J115: =SUBTOTAL(109,'Sept-26'!$J$109:$J$114) -> 0 | K115: =SUBTOTAL(109,'Sept-26'!$K$109:$K$114) -> 0 | L115: =SUBTOTAL(109,'Sept-26'!$L$109:$L$114) -> 0 | M115: =SUBTOTAL(103,'Sept-26'!$M$109:$M$114) -> 0
B117: VENTAS "E"
B118: FECHA | C118: TIPO | D118: PTO VENTA | E118: Nº FACTURA | F118: CUIT | G118: RAZON SOCIAL | H118: USD | I118: IVA 21% | J118: Columna1 | K118: TIPO DE CAMBIO2 | L118: TOTAL | M118: PAIS
...

Sheet Oct-26
B1: LIBRO IVA COMPRAS | G1: ='Abr-26'!G1:M1 -> CORITEC S. R. L. | N1: =EDATE('Abr-26'!N1,6) -> 45931
B3: TOTAL COMPRAS | G3: TOTAL CREDITO FISCAL | J3: TOTAL VENTAS NETAS | M3: TOTAL DEBITO FISCAL | P3: RESULTADO
B4: =SUM('Oct-26'!$H$29)+'Oct-26'!$G$40 -> 10905085 | G4: ='Oct-26'!$I$29+'Oct-26'!$J$29+'Oct-26'!$K$29+'Oct-26'!$H$40+'Oct-26'!$I$40 -> 2288272.9 | J4: ='Oct-26'!$H$85+'Oct-26'!$H$96 -> 571466.3 | M4: ='Oct-26'!$I$85+'Oct-26'!$J$85+'Oct-26'!$I$96+'Oct-26'!$J$96+I107+J107 -> 117636.75 | P4: =G4-M4 -> 2170636.2
B8: FECHA | C8: TIPO | D8: PTO VTA | E8: NRO. CPTE | F8: CUIT | G8: RAZON SOCIAL | H8: NETO GRAVADO | I8: IVA 21 % | J8: IVA 27% | K8: IVA 10,5% | L8: PERC. IVA | M8: PERC IIBB BS AS | N8: PERC. IIBB CABA | O8: Otros / No Grav. | P8: TOTAL | Q8: Tipo de Gasto | R8: Provincia
B9: 45931 | C9: 1 | D9: 7 | E9: 30060 | F9: 30712249338 | G9: =IFERROR(IF('Oct-26'!$F9="","-",VLOOKUP('Oct-26'!$F9,Lista_CUIT!$A$1:$D$2241,2,0)),"CUIT NO CARGADO") -> VOIP EXPERTS SOCIEDAD DE RESPONSABILIDAD LIMITADA | H9: 8250.09 | I9: 801.3 | K9: 465.61 | P9: =SUM('Oct-26'!$H9:$O9) -> 9517 | Q9: =IFERROR(IF('Oct-26'!$F9="","-",VLOOKUP('Oct-26'!$F9,Lista_CUIT!$A$1:$D$2241,3,0)),"CUIT NO CARGADO") -> 0 | R9: =IFERROR(IF('Oct-26'!$F9="","-",VLOOKUP('Oct-26'!$F9,Lista_CUIT!$A$1:$D$2241,4,0)),"CUIT NO CARGADO") -> 0
B10: 45931 | C10: 1 | D10: 8 | E10: 20900 | F10: 20304940019 | G10: =IFERROR(IF('Oct-26'!$F10="","-",VLOOKUP('Oct-26'!$F10,Lista_CUIT!$A$1:$D$2241,2,0)),"CUIT NO CARGADO") -> LAZZARIN LIMA MARTIN IGNACIO | H10: 12264.46 | I10: =IF('Oct-26'!$H10="","",'Oct-26'!$H10*0.21) -> 2575.5366 | P10: =SUM('Oct-26'!$H10:$O10) -> 14839.997 | Q10: =IFERROR(IF('Oct-26'!$F10="","-",VLOOKUP('Oct-26'!$F10,Lista_CUIT!$A$1:$D$2241,3,0)),"CUIT NO CARGADO") -> 0 | R10: =IFERROR(IF('Oct-26'!$F10="","-",VLOOKUP('Oct-26'!$F10,Lista_CUIT!$A$1:$D$2241,4,0)),"CUIT NO CARGADO") -> 0
B11: 45931 | C11: 1 | D11: 3 | E11: 281948 | F11: 30707135596 | G11: =IFERROR(IF('Oct-26'!$F11="","-",VLOOKUP('Oct-26'!$F11,Lista_CUIT!$A$1:$D$2241,2,0)),"CUIT NO CARGADO") -> CITILAN ARGENTINA S.A. | H11: 32626 | I11: =IF('Oct-26'!$H11="","",'Oct-26'!$H11*0.21) -> 6851.46 | P11: =SUM('Oct-26'!$H11:$O11) -> 39477.46 | Q11: =IFERROR(IF('Oct-26'!$F11="","-",VLOOKUP('Oct-26'!$F11,Lista_CUIT!$A$1:$D$2241,3,0)),"CUIT NO CARGADO") -> Telefonia | R11: =IFERROR(IF('Oct-26'!$F11="","-",VLOOKUP('Oct-26'!$F11,Lista_CUIT!$A$1:$D$2241,4,0)),"CUIT NO CARGADO") -> 0
B12: 45931 | C12: 1 | D12: 5 | E12: 6822 | F12: 20231333593 | G12: =IFERROR(IF('Oct-26'!$F12="","-",VLOOKUP('Oct-26'!$F12,Lista_CUIT!$A$1:$D$2241,2,0)),"CUIT NO CARGADO") -> BOLLINI CLAUDIO DANIEL | H12: 80000 | I12: =IF('Oct-26'!$H12="","",'Oct-26'!$H12*0.21) -> 16800 | P12: =SUM('Oct-26'!$H12:$O12) -> 96800 | Q12: =IFERROR(IF('Oct-26'!$F12="","-",VLOOKUP('Oct-26'!$F12,Lista_CUIT!$A$1:$D$2241,3,0)),"CUIT NO CARGADO") -> Mantenimiento | R12: =IFERROR(IF('Oct-26'!$F12="","-",VLOOKUP('Oct-26'!$F12,Lista_CUIT!$A$1:$D$2241,4,0)),"CUIT NO CARGADO") -> 0
B13: 45931 | C13: 1 | D13: 3 | E13: 896 | F13: 30715402765 | G13: =IFERROR(IF('Oct-26'!$F13="","-",VLOOKUP('Oct-26'!$F13,Lista_CUIT!$A$1:$D$2241,2,0)),"CUIT NO CARGADO") -> RIO 265 S.R.L. | H13: 107438 | I13: =IF('Oct-26'!$H13="","",'Oct-26'!$H13*0.21) -> 22561.98 | P13: =SUM('Oct-26'!$H13:$O13) -> 129999.98 | Q13: =IFERROR(IF('Oct-26'!$F13="","-",VLOOKUP('Oct-26'!$F13,Lista_CUIT!$A$1:$D$2241,3,0)),"CUIT NO CARGADO") -> GASTOS VARIOS | R13: =IFERROR(IF('Oct-26'!$F13="","-",VLOOKUP('Oct-26'!$F13,Lista_CUIT!$A$1:$D$2241,4,0)),"CUIT NO CARGADO") -> 0
B14: 45932 | C14: 1 | D14: 3 | E14: 196 | F14: 20297899830 | G14: =IFERROR(IF('Oct-26'!$F14="","-",VLOOKUP('Oct-26'!$F14,Lista_CUIT!$A$1:$D$2241,2,0)),"CUIT NO CARGADO") -> FUNK MATIAS NICOLAS | H14: 8898019 | I14: =IF('Oct-26'!$H14="","",'Oct-26'!$H14*0.21) -> 1868584 | P14: =SUM('Oct-26'!$H14:$O14) -> 10766603 | Q14: =IFERROR(IF('Oct-26'!$F14="","-",VLOOKUP('Oct-26'!$F14,Lista_CUIT!$A$1:$D$2241,3,0)),"CUIT NO CARGADO") -> INSUMO | R14: =IFERROR(IF('Oct-26'!$F14="","-",VLOOKUP('Oct-26'!$F14,Lista_CUIT!$A$1:$D$2241,4,0)),"CUIT NO CARGADO") -> 0
B15: 45933 | C15: 1 | D15: 10 | E15: 78926 | F15: 30528214483 | G15: =IFERROR(IF('Oct-26'!$F15="","-",VLOOKUP('Oct-26'!$F15,Lista_CUIT!$A$1:$D$2241,2,0)),"CUIT NO CARGADO") -> D WEINSTOCK S R L | H15: 54000 | I15: =IF('Oct-26'!$H15="","",'Oct-26'!$H15*0.21) -> 11340 | P15: =SUM('Oct-26'!$H15:$O15) -> 65340 | Q15: =IFERROR(IF('Oct-26'!$F15="","-",VLOOKUP('Oct-26'!$F15,Lista_CUIT!$A$1:$D$2241,3,0)),"CUIT NO CARGADO") -> INSUMO | R15: =IFERROR(IF('Oct-26'!$F15="","-",VLOOKUP('Oct-26'!$F15,Lista_CUIT!$A$1:$D$2241,4,0)),"CUIT NO CARGADO") -> 0
B16: 45933 | C16: 1 | D16: 122 | E16: 395079 | F16: 30594494187 | G16: =IFERROR(IF('Oct-26'!$F16="","-",VLOOKUP('Oct-26'!$F16,Lista_CUIT!$A$1:$D$2241,2,0)),"CUIT NO CARGADO") -> FEDERAL EXPRESS CORPORATION | H16: 170940 | I16: =IF('Oct-26'!$H16="","",'Oct-26'!$H16*0.21) -> 35897.4 | O16: 1963758.7 | P16: =SUM('Oct-26'!$H16:$O16) -> 2170596.1 | Q16: =IFERROR(IF('Oct-26'!$F16="","-",VLOOKUP('Oct-26'!$F16,Lista_CUIT!$A$1:$D$2241,3,0)),"CUIT NO CARGADO") -> Mercaderia | R16: =IFERROR(IF('Oct-26'!$F16="","-",VLOOKUP('Oct-26'!$F16,Lista_CUIT!$A$1:$D$2241,4,0)),"CUIT NO CARGADO") -> 0
B17: 45936 | C17: 1 | D17: 5 | E17: 71929 | F17: 30716711621 | G17: =IFERROR(IF('Oct-26'!$F17="","-",VLOOKUP('Oct-26'!$F17,Lista_CUIT!$A$1:$D$2241,2,0)),"CUIT NO CARGADO") -> TC TIENDAS AR SRL | H17: 12660.63 | K17: 1329.37 | P17: =SUM('Oct-26'!$H17:$O17) -> 13990 | Q17: =IFERROR(IF('Oct-26'!$F17="","-",VLOOKUP('Oct-26'!$F17,Lista_CUIT!$A$1:$D$2241,3,0)),"CUIT NO CARGADO") -> Gastos Oficina | R17: =IFERROR(IF('Oct-26'!$F17="","-",VLOOKUP('Oct-26'!$F17,Lista_CUIT!$A$1:$D$2241,4,0)),"CUIT NO CARGADO") -> 0
B18: 45936 | C18: 1 | D18: 63 | E18: 3500823 | F18: 30640897267 | G18: =IFERROR(IF('Oct-26'!$F18="","-",VLOOKUP('Oct-26'!$F18,Lista_CUIT!$A$1:$D$2241,2,0)),"CUIT NO CARGADO") -> TELECENTRO SA | H18: 17999.83 | I18: =IF('Oct-26'!$H18="","",'Oct-26'!$H18*0.21) -> 3779.9643 | O18: 539.99 | P18: =SUM('Oct-26'!$H18:$O18) -> 22319.784 | Q18: =IFERROR(IF('Oct-26'!$F18="","-",VLOOKUP('Oct-26'!$F18,Lista_CUIT!$A$1:$D$2241,3,0)),"CUIT NO CARGADO") -> SERVICIOS | R18: =IFERROR(IF('Oct-26'!$F18="","-",VLOOKUP('Oct-26'!$F18,Lista_CUIT!$A$1:$D$2241,4,0)),"CUIT NO CARGADO") -> 0
B19: 45939 | C19: 1 | D19: 106 | E19: 884098 | F19: 30594494187 | G19: =IFERROR(IF('Oct-26'!$F19="","-",VLOOKUP('Oct-26'!$F19,Lista_CUIT!$A$1:$D$2241,2,0)),"CUIT NO CARGADO") -> FEDERAL EXPRESS CORPORATION | H19: 174600 | I19: =IF('Oct-26'!$H19="","",'Oct-26'!$H19*0.21) -> 36666 | P19: =SUM('Oct-26'!$H19:$O19) -> 211266 | Q19: =IFERROR(IF('Oct-26'!$F19="","-",VLOOKUP('Oct-26'!$F19,Lista_CUIT!$A$1:$D$2241,3,0)),"CUIT NO CARGADO") -> Mercaderia | R19: =IFERROR(IF('Oct-26'!$F19="","-",VLOOKUP('Oct-26'!$F19,Lista_CUIT!$A$1:$D$2241,4,0)),"CUIT NO CARGADO") -> 0
B20: 45939 | C20: 1 | D20: 1 | E20: 1003 | F20: 30715048066 | G20: =IFERROR(IF('Oct-26'!$F20="","-",VLOOKUP('Oct-26'!$F20,Lista_CUIT!$A$1:$D$2241,2,0)),"CUIT NO CARGADO") -> ROLLS Y EMPANADAS SA | H20: 932210 | I20: =IF('Oct-26'!$H20="","",'Oct-26'!$H20*0.21) -> 195764.1 | P20: =SUM('Oct-26'!$H20:$O20) -> 1127974.1 | Q20: =IFERROR(IF('Oct-26'!$F20="","-",VLOOKUP('Oct-26'!$F20,Lista_CUIT!$A$1:$D$2241,3,0)),"CUIT NO CARGADO") -> CATERING | R20: =IFERROR(IF('Oct-26'!$F20="","-",VLOOKUP('Oct-26'!$F20,Lista_CUIT!$A$1:$D$2241,4,0)),"CUIT NO CARGADO") -> 0
B21: 45943 | C21: 1 | D21: 20 | E21: 3395 | F21: 33715334319 | G21: =IFERROR(IF('Oct-26'!$F21="","-",VLOOKUP('Oct-26'!$F21,Lista_CUIT!$A$1:$D$2241,2,0)),"CUIT NO CARGADO") -> PIERETTO RICARDO, PIERETTO JULIAN Y PIERETTO MAURICIO CAPITULO I SECCION IV LEY 19550 | H21: 22901.65 | I21: =IF('Oct-26'!$H21="","",'Oct-26'!$H21*0.21) -> 4809.3465 | P21: =SUM('Oct-26'!$H21:$O21) -> 27710.997 | Q21: =IFERROR(IF('Oct-26'!$F21="","-",VLOOKUP('Oct-26'!$F21,Lista_CUIT!$A$1:$D$2241,3,0)),"CUIT NO CARGADO") -> 0 | R21: =IFERROR(IF('Oct-26'!$F21="","-",VLOOKUP('Oct-26'!$F21,Lista_CUIT!$A$1:$D$2241,4,0)),"CUIT NO CARGADO") -> 0
