Workbook

Sheet Lista_CUIT
A1: CUIT | B1: RAZON SOCIAL | C1: Tipo de Gasto | D1: PROVINCIA
A2: 30575019524 | B2: 100000 LAMPARAS SRL | G2: Mercaderia
A3: 30709829730 | B3: 4KRC SA | C3: Mantenimiento | G3: Servicios Gas, Luz, etc.
A4: 30715223704 | B4: 5 CEPAS S.R.L. | C4: MERCADERIA | G4: Gastos catering
A5: 30714869937 | B5: 60 LIBRAS SRL | G5: Combustibe
A6: 30692212130 | B6: A R C CONSTRUCCIONES S.A. | G6: Gastos Varios
A7: 30687722007 | B7: A. RUSSONIELLO SA | C7: SERVICIOS | G7: Gastos seguridad
A8: 30503874497 | B8: A.M. PESCIO S.C.A | C8: Mercaderia | G8: Librería
A9: 30702017498 | B9: ABBS POINT DESING S.A. | G9: Gastos mantenimiento
A10: 20182999661 | B10: ABEL JAVIER KLAINER | C10: Mercaderia | G10: Gastos comercializacion
A11: 30652000076 | B11: ABELSON SA | C11: Mercaderia | G11: Alquiler
A12: 30690536079 | B12: ACCESOR SRL | C12: Gastos Varios | G12: Honorarios contables
A13: 30515585415 | B13: ACEROSALFA SA | C13: Mercaderia | G13: Gastos administrativos
A14: 33711942659 | B14: ACLOS ASOC. CIVIL PARA LA LONG | C14: Mercaderia | G14: Seguro
A15: 30715243349 | B15: ADSE S.A | G15: Extracto
A16: 20174004146 | B16: ADUEARDO FRANCISCO NARDOMARINO | C16: Mercaderia | G16: Flete
A17: 30708555548 | B17: AGH S.A | C17: Mercaderia | G17: Honorarios Legales
A18: 30708263342 | B18: AGRACO S.A | C18: MERCADERIA | G18: Insumo
A19: 30709565075 | B19: AGUA Y SANEAMIENTOS ARG SA | C19: SERVICIOS | G19: Muebles y Utiles
A20: 30500229973 | B20: AKIAN GRAFICA EDITORA SA | C20: Mercaderia | G20: Otros
A21: 30710799241 | B21: ALANAR S.R.L. | G21: Telefonia
A22: 20236101127 | B22: ALEJANDRO DARIO LOPEZ | G22: Alojamiento-Varios
A23: 20291929126 | B23: ALEJANDRO MIGUEL DAUBLER
A24: 30709604887 | B24: ALFABIS SRL. | C24: Mantenimiento
A25: 20083925680 | B25: ALFREDO DANIEL FERNANDEZ | C25: Gastos Varios
A26: 30656038752 | B26: ALFREDO OMAR POTENZA SRL | C26: Mercaderia
A27: 30504563894 | B27: ALI HERMANOS SRL | C27: Mercaderia
A28: 30602699826 | B28: ALKO SRL
A29: 30715190385 | B29: ALL FEDERAL SA.
A30: 23945042079 | B30: ALVARENGA VILLAR LUIS F | C30: Gastos Varios
A31: 20040616498 | B31: ALVAREZ MARCELINO
A32: 30710587147 | B32: AMAKOR SA | C32: SERVICIOS
A33: 30663288497 | B33: AMX ARG SA
A34: 27108310559 | B34: ANA MARIA VALDEZ
A35: 30502375535 | B35: ANAVI S.C.A.
A36: 30709251739 | B36: ANDES LINEAS AEREAS SA
A37: 30709948667 | B37: ANTAGGER SRL | C37: Mercaderia
A38: 30683702060 | B38: ANTARES INDUST. ORTOP SA | C38: Mercaderia
A39: 30715985124 | B39: ANTOLFO S.R.L.
A40: 30714344656 | B40: AQUALAF S.A. | C40: Mercaderia
A41: 30712000372 | B41: AQUÍ MERCEDES SRL | C41: Mercaderia
A42: 30714741167 | B42: ARALIMP S.R.L.
A43: 20927832136 | B43: ARANCIBIA IBACETA CIPRIANO | C43: Gastos Varios
A44: 27135302835 | B44: ARENAS MONICA MARIEL
A45: 27276671109 | B45: AREVALO LORENA ELIZABETH | C45: Mercaderia
A46: 30711597499 | B46: ARGENVODA SA
A47: 30600907553 | B47: ARMAGALLI SA
A48: 30709585262 | B48: ARMY TECHNOLOGIES S.A. | C48: Mantenimiento
A49: 30614941509 | B49: ARREDO
A50: 30560443648 | B50: ARSA ELECTRICIDAD SRL
A51: 30708547790 | B51: ARTELEC ARGENTINA SRL
A52: 30711624402 | B52: ARTES REGIONALES SRL
A53: 20045180620 | B53: ARUGUETE ENRIQUE JORGE | C53: Gastos Varios
A54: 30692175243 | B54: ASAHI MOTORS SA
A55: 30708973501 | B55: ASIAL SRL | C55: Mercaderia
A56: 30590354798 | B56: ASOC. MUTUAL SANCOR SALUD
A57: 30709860840 | B57: AUMECON SA
A58: 30544712833 | B58: AURELIO GUNDIN SA | C58: Mercaderia
A59: 30715031252 | B59: AUTO VENETO S.A.
A60: 30711934754 | B60: AUTOBIZ SA
A61: 30670528592 | B61: AUTOMOTORES FIORASI Y CORRADI
A62: 30574876474 | B62: AUTOP. URBANAS SA
A63: 30677237119 | B63: AUTOPISTAS DEL SOL SA
A64: 30607371799 | B64: AUTOSERVICIO DIARCO SA
A65: 20278462790 | B65: VARAS TOLEDO SEBASTIAN
A66: 30715963872 | B66: MARAKANA SRL
A67: 20083762102 | B67: AVANCE-MAG
A68: 20287830980 | B68: AVILA MARTIN LEONARDO
A69: 30506919009 | B69: AXION ENERGY ARG SA | C69: COMBUSTIBLE
A70: 30535612117 | B70: AYUDA MUT. DEL PERS. DE GENDAR
A71: 33711430879 | B71: BALANZE S.A. | C71: Mercaderia
A72: 20179619483 | B72: BALE JORGE CARLOS
A73: 30711941718 | B73: BALLERINI ATILIO Y SOTO RAUL C | C73: Mercaderia
A74: 30580189411 | B74: BANCO ITAU ARG SA
A75: 30500008454 | B75: BANCO SANTANDER RIO SA | C75: Extracto
A76: 30646362675 | B76: BAUMGARTEN GRAFICA ARG SA
A77: 30712458468 | B77: BEEL SUL S.A. | C77: Gastos Varios
A78: 30714675601 | B78: BELGRANO NEUMATICOS S.A.
A79: 30568222187 | B79: BELLINI HNOS SRL
A80: 27248212646 | B80: BELLOMO MARIA MERCEDES
A81: 27115740666 | B81: BEN Y BEN
A82: 27129411010 | B82: BENITEZ ANA MARIA
A83: 23301961944 | B83: BERGOC CECILIA ANDREA
A84: 30710067763 | B84: BI POOL S.R.L.
A85: 30712387315 | B85: BIALA SRL | C85: Gastos Varios
A86: 30715210637 | B86: BIAUS SRL | C86: Mercaderia
A87: 30712230459 | B87: BIOMAX INSUMOS MEDICOS | C87: Mercaderia
A88: 30697652694 | B88: BISTRO SA
A89: 30712476857 | B89: BODEGA DON BOSCO | C89: MERCADERIA
A90: 30708270462 | B90: body group feliz srl
A91: 23253931159 | B91: BOECHI JUAN
A92: 30655186693 | B92: BOSAN SA
A93: 20389908569 | B93: BOTINDARI JUAN IGNACIO | C93: HONORARIOS
A94: 30515676178 | B94: BROGAS SA | C94: Mercaderia
A95: 33711821649 | B95: BRUBEN DUDAMERICANA
A96: 30715122657 | B96: BRUNETTE SRL
A97: 30715549871 | B97: BSMS SRL
A98: 20085280512 | B98: BULONERA HURLINGHAM | C98: Mercaderia
A99: 30595442369 | B99: BULONERA MATADEROS SRL | C99: Mercaderia
A100: 27289847141 | B100: BUSACCA PAOLA EDITH | C100: LIBRERÍA
...

Sheet Hoja1
B3: FACTURAS C
B4: FECHA | C4: PTO VTA | D4: FC Nº | E4: CUIT | F4: RAZON SOCIAL | G4: TOTAL | H4: TIPO DE GASTO | I4: Provincia
F5: =IFERROR(IF(factura_c_mes182[[#This Row],[CUIT]]="","-",VLOOKUP(factura_c_mes182[[#This Row],[CUIT]],Lista_CUIT[#All],2,0)),"CUIT NO CARGADO") -> - | H5: =IFERROR(IF(factura_c_mes182[[#This Row],[CUIT]]="","-",VLOOKUP(factura_c_mes182[[#This Row],[CUIT]],Lista_CUIT[#All],3,0)),"CUIT NO CARGADO") -> - | I5: =IFERROR(IF(factura_c_mes182[[#This Row],[CUIT]]="","-",VLOOKUP(factura_c_mes182[[#This Row],[CUIT]],Lista_CUIT[#All],4,0)),"CUIT NO CARGADO") -> -
B6: 45026 | C6: 4 | D6: 12 | E6: 20341462933 | F6: =IFERROR(IF(factura_c_mes182[[#This Row],[CUIT]]="","-",VLOOKUP(factura_c_mes182[[#This Row],[CUIT]],Lista_CUIT[#All],2,0)),"CUIT NO CARGADO") -> CASTIGLIONI MATIAS EZEQUIEL | G6: 590500 | H6: Ingenieria Aplicada | I6: =IFERROR(IF(factura_c_mes182[[#This Row],[CUIT]]="","-",VLOOKUP(factura_c_mes182[[#This Row],[CUIT]],Lista_CUIT[#All],4,0)),"CUIT NO CARGADO") -> BUENOS AIRES | K6: 510.12 | L6: Honorarios Ingeniero | M6: 590500
B7: 45026 | C7: 8 | D7: 157469 | E7: 30709953482 | F7: =IFERROR(IF(factura_c_mes182[[#This Row],[CUIT]]="","-",VLOOKUP(factura_c_mes182[[#This Row],[CUIT]],Lista_CUIT[#All],2,0)),"CUIT NO CARGADO") -> HONRE S.A | G7: 1221.95 | H7: =IFERROR(IF(factura_c_mes182[[#This Row],[CUIT]]="","-",VLOOKUP(factura_c_mes182[[#This Row],[CUIT]],Lista_CUIT[#All],3,0)),"CUIT NO CARGADO") -> Gastos Varios | I7: =IFERROR(IF(factura_c_mes182[[#This Row],[CUIT]]="","-",VLOOKUP(factura_c_mes182[[#This Row],[CUIT]],Lista_CUIT[#All],4,0)),"CUIT NO CARGADO") -> 0 | K7: 500.05 | L7: Gastos varios | M7: 19561.95
B8: 45028 | C8: 4 | D8: 35528 | E8: 30716998718 | F8: =IFERROR(IF(factura_c_mes182[[#This Row],[CUIT]]="","-",VLOOKUP(factura_c_mes182[[#This Row],[CUIT]],Lista_CUIT[#All],2,0)),"CUIT NO CARGADO") -> FIDO ARGENTINA SRL | G8: 18340 | H8: =IFERROR(IF(factura_c_mes182[[#This Row],[CUIT]]="","-",VLOOKUP(factura_c_mes182[[#This Row],[CUIT]],Lista_CUIT[#All],3,0)),"CUIT NO CARGADO") -> Gastos Varios | I8: =IFERROR(IF(factura_c_mes182[[#This Row],[CUIT]]="","-",VLOOKUP(factura_c_mes182[[#This Row],[CUIT]],Lista_CUIT[#All],4,0)),"CUIT NO CARGADO") -> 0 | K8: 500.016 | L8: Honorarios Admnistrativos | M8: 148480
B9: 45041 | C9: 3 | D9: 50 | E9: 20403931420 | F9: =IFERROR(IF(factura_c_mes182[[#This Row],[CUIT]]="","-",VLOOKUP(factura_c_mes182[[#This Row],[CUIT]],Lista_CUIT[#All],2,0)),"CUIT NO CARGADO") -> FIORENTINO JORGE IGNACIO | G9: 148480 | H9: Honorarios Administrativos | I9: =IFERROR(IF(factura_c_mes182[[#This Row],[CUIT]]="","-",VLOOKUP(factura_c_mes182[[#This Row],[CUIT]],Lista_CUIT[#All],4,0)),"CUIT NO CARGADO") -> 0 | K9: 510.1 | L9: Honorarios Contables | M9: 79860
B10: 45019 | C10: 3 | D10: 717 | E10: 20086277523 | F10: =IFERROR(IF(factura_c_mes182[[#This Row],[CUIT]]="","-",VLOOKUP(factura_c_mes182[[#This Row],[CUIT]],Lista_CUIT[#All],2,0)),"CUIT NO CARGADO") -> ESTUDIO BOTINDARI | G10: 67000 | H10: Honorario Contable | I10: =IFERROR(IF(factura_c_mes182[[#This Row],[CUIT]]="","-",VLOOKUP(factura_c_mes182[[#This Row],[CUIT]],Lista_CUIT[#All],4,0)),"CUIT NO CARGADO") -> 0 | K10: 500.035 | L10: Desarrollo Software | M10: 90000
B11: 45028 | C11: 2 | D11: 200 | E11: 27173820866 | F11: =IFERROR(IF(factura_c_mes182[[#This Row],[CUIT]]="","-",VLOOKUP(factura_c_mes182[[#This Row],[CUIT]],Lista_CUIT[#All],2,0)),"CUIT NO CARGADO") -> FREIER SANDRA DANIELA | G11: 90000 | H11: Desarrollo Software | I11: =IFERROR(IF(factura_c_mes182[[#This Row],[CUIT]]="","-",VLOOKUP(factura_c_mes182[[#This Row],[CUIT]],Lista_CUIT[#All],4,0)),"CUIT NO CARGADO") -> 0 | K11: 500.03 | L11: Mantenimiento Software | M11: 373750
B12: 45029 | C12: 3 | D12: 723 | E12: 20086277523 | F12: =IFERROR(IF(factura_c_mes182[[#This Row],[CUIT]]="","-",VLOOKUP(factura_c_mes182[[#This Row],[CUIT]],Lista_CUIT[#All],2,0)),"CUIT NO CARGADO") -> ESTUDIO BOTINDARI | G12: 12860 | H12: Honorario Contable | I12: =IFERROR(IF(factura_c_mes182[[#This Row],[CUIT]]="","-",VLOOKUP(factura_c_mes182[[#This Row],[CUIT]],Lista_CUIT[#All],4,0)),"CUIT NO CARGADO") -> 0 | K12: 500.027 | L12: Mantenimiento Oficina | M12: 148935
B13: 45021 | C13: 1 | D13: 98 | E13: 20341465134 | F13: =IFERROR(IF(factura_c_mes182[[#This Row],[CUIT]]="","-",VLOOKUP(factura_c_mes182[[#This Row],[CUIT]],Lista_CUIT[#All],2,0)),"CUIT NO CARGADO") -> ABELEDO AGUSTIN ENRIQUE | G13: 373750 | H13: Mantenimiento Sofware | I13: =IFERROR(IF(factura_c_mes182[[#This Row],[CUIT]]="","-",VLOOKUP(factura_c_mes182[[#This Row],[CUIT]],Lista_CUIT[#All],4,0)),"CUIT NO CARGADO") -> CABA | K13: 500.034 | L13: Seguimientos de Clientes | M13: 128690
B14: 45041 | C14: 2 | D14: 21 | E14: 23326777269 | F14: =IFERROR(IF(factura_c_mes182[[#This Row],[CUIT]]="","-",VLOOKUP(factura_c_mes182[[#This Row],[CUIT]],Lista_CUIT[#All],2,0)),"CUIT NO CARGADO") -> DE BONIS IGNACIO LUIS | G14: 148935 | H14: Mantenimiento Oficvina | I14: =IFERROR(IF(factura_c_mes182[[#This Row],[CUIT]]="","-",VLOOKUP(factura_c_mes182[[#This Row],[CUIT]],Lista_CUIT[#All],4,0)),"CUIT NO CARGADO") -> 0 | K14: 500.03 | L14: Mantenimiento Software | M14: 371000
B15: 45043 | C15: 1 | D15: 17 | E15: 20417805878 | F15: =IFERROR(IF(factura_c_mes182[[#This Row],[CUIT]]="","-",VLOOKUP(factura_c_mes182[[#This Row],[CUIT]],Lista_CUIT[#All],2,0)),"CUIT NO CARGADO") -> FERABOLI OSPAL SANTIAGO HERNAN | G15: 128690 | H15: Control de Materiales | I15: =IFERROR(IF(factura_c_mes182[[#This Row],[CUIT]]="","-",VLOOKUP(factura_c_mes182[[#This Row],[CUIT]],Lista_CUIT[#All],4,0)),"CUIT NO CARGADO") -> 0 | M15: =SUM(M6:M14) -> 1950776.9
B16: 45040 | C16: 2 | D16: 82 | E16: 20244271740 | F16: =IFERROR(IF(factura_c_mes182[[#This Row],[CUIT]]="","-",VLOOKUP(factura_c_mes182[[#This Row],[CUIT]],Lista_CUIT[#All],2,0)),"CUIT NO CARGADO") -> KENNEL SEBASTIAN | G16: 371000 | H16: =IFERROR(IF(factura_c_mes182[[#This Row],[CUIT]]="","-",VLOOKUP(factura_c_mes182[[#This Row],[CUIT]],Lista_CUIT[#All],3,0)),"CUIT NO CARGADO") -> Software Mantenimiento | I16: =IFERROR(IF(factura_c_mes182[[#This Row],[CUIT]]="","-",VLOOKUP(factura_c_mes182[[#This Row],[CUIT]],Lista_CUIT[#All],4,0)),"CUIT NO CARGADO") -> 0
B17: Total | G17: =SUBTOTAL(109,factura_c_mes182[TOTAL]) -> 1950776.9
B19: FACTURAS C
B20: FECHA | C20: PTO VTA | D20: FC Nº | E20: CUIT | F20: RAZON SOCIAL | G20: TOTAL | H20: TIPO DE GASTO | I20: Provincia
B21: 45047 | C21: 1 | D21: 7 | E21: 27387896150 | F21: =IFERROR(IF(factura_c_mes283[[#This Row],[CUIT]]="","-",VLOOKUP(factura_c_mes283[[#This Row],[CUIT]],Lista_CUIT[#All],2,0)),"CUIT NO CARGADO") -> LIPANOVICH MARIA SOL | G21: 400000 | H21: Desarrollo Software | I21: =IFERROR(IF(factura_c_mes283[[#This Row],[CUIT]]="","-",VLOOKUP(factura_c_mes283[[#This Row],[CUIT]],Lista_CUIT[#All],4,0)),"CUIT NO CARGADO") -> 0 | K21: 510.12 | L21: Honorarios Ingeniero | M21: 510000
B22: 45077 | C22: 1 | D22: 8 | E22: 27387896150 | F22: =IFERROR(IF(factura_c_mes283[[#This Row],[CUIT]]="","-",VLOOKUP(factura_c_mes283[[#This Row],[CUIT]],Lista_CUIT[#All],2,0)),"CUIT NO CARGADO") -> LIPANOVICH MARIA SOL | G22: 400000 | H22: Desarrollo Software | I22: =IFERROR(IF(factura_c_mes283[[#This Row],[CUIT]]="","-",VLOOKUP(factura_c_mes283[[#This Row],[CUIT]],Lista_CUIT[#All],4,0)),"CUIT NO CARGADO") -> 0 | K22: 500.05 | L22: Gastos varios | M22: 108932.98
B23: 45062 | C23: 2 | D23: 203 | E23: 27173820866 | F23: =IFERROR(IF(factura_c_mes283[[#This Row],[CUIT]]="","-",VLOOKUP(factura_c_mes283[[#This Row],[CUIT]],Lista_CUIT[#All],2,0)),"CUIT NO CARGADO") -> FREIER SANDRA DANIELA | G23: 400000 | H23: Desarrollo Software | I23: =IFERROR(IF(factura_c_mes283[[#This Row],[CUIT]]="","-",VLOOKUP(factura_c_mes283[[#This Row],[CUIT]],Lista_CUIT[#All],4,0)),"CUIT NO CARGADO") -> 0 | K23: 500.016 | L23: Honorarios Admnistrativos | M23: 848510
B24: 45047 | C24: 1 | D24: 23 | E24: 20365938688 | F24: =IFERROR(IF(factura_c_mes283[[#This Row],[CUIT]]="","-",VLOOKUP(factura_c_mes283[[#This Row],[CUIT]],Lista_CUIT[#All],2,0)),"CUIT NO CARGADO") -> LIPANOVICH JUAN CRUZ | G24: 450000 | H24: Desarrollo Software | I24: =IFERROR(IF(factura_c_mes283[[#This Row],[CUIT]]="","-",VLOOKUP(factura_c_mes283[[#This Row],[CUIT]],Lista_CUIT[#All],4,0)),"CUIT NO CARGADO") -> 0 | K24: 510.1 | L24: Honorarios Contables | M24: 93860
B25: 45049 | C25: 2 | D25: 81043 | E25: 30554466806 | F25: =IFERROR(IF(factura_c_mes283[[#This Row],[CUIT]]="","-",VLOOKUP(factura_c_mes283[[#This Row],[CUIT]],Lista_CUIT[#All],2,0)),"CUIT NO CARGADO") -> ASOCIACION DE IMPORTADORES Y EXPORTADORES DE LA REPUBLICA ARGENTINA | G25: 3200 | H25: =IFERROR(IF(factura_c_mes283[[#This Row],[CUIT]]="","-",VLOOKUP(factura_c_mes283[[#This Row],[CUIT]],Lista_CUIT[#All],3,0)),"CUIT NO CARGADO") -> FLETE-LOGISTICA | I25: =IFERROR(IF(factura_c_mes283[[#This Row],[CUIT]]="","-",VLOOKUP(factura_c_mes283[[#This Row],[CUIT]],Lista_CUIT[#All],4,0)),"CUIT NO CARGADO") -> 0 | K25: 500.035 | L25: Desarrollo Software | M25: 850000
B26: 45054 | C26: 11 | D26: 37129 | E26: 30714867322 | F26: =IFERROR(IF(factura_c_mes283[[#This Row],[CUIT]]="","-",VLOOKUP(factura_c_mes283[[#This Row],[CUIT]],Lista_CUIT[#All],2,0)),"CUIT NO CARGADO") -> INITIUM SRL | G26: 3488.98 | H26: Gastos varios | I26: =IFERROR(IF(factura_c_mes283[[#This Row],[CUIT]]="","-",VLOOKUP(factura_c_mes283[[#This Row],[CUIT]],Lista_CUIT[#All],4,0)),"CUIT NO CARGADO") -> 0 | K26: 500.027 | L26: Mantenimiento Oficina | M26: -148935
B27: 45055 | C27: 1 | D27: 36 | E27: 27925308868 | F27: =IFERROR(IF(factura_c_mes283[[#This Row],[CUIT]]="","-",VLOOKUP(factura_c_mes283[[#This Row],[CUIT]],Lista_CUIT[#All],2,0)),"CUIT NO CARGADO") -> LOPEZ MOLINA MARIA | G27: 19200 | H27: Gastos varios | I27: =IFERROR(IF(factura_c_mes283[[#This Row],[CUIT]]="","-",VLOOKUP(factura_c_mes283[[#This Row],[CUIT]],Lista_CUIT[#All],4,0)),"CUIT NO CARGADO") -> 0 | K27: 500.034 | L27: Seguimientos de Clientes | M27: 128970
B28: 45061 | C28: 9 | D28: 3739576 | E28: 33715179119 | F28: =IFERROR(IF(factura_c_mes283[[#This Row],[CUIT]]="","-",VLOOKUP(factura_c_mes283[[#This Row],[CUIT]],Lista_CUIT[#All],2,0)),"CUIT NO CARGADO") -> FONDO DE COOPERACION TECNICA Y FINANCIERA - CECBA - SL Y T - LEY 23.412 | G28: 855 | H28: Gastos varios | I28: =IFERROR(IF(factura_c_mes283[[#This Row],[CUIT]]="","-",VLOOKUP(factura_c_mes283[[#This Row],[CUIT]],Lista_CUIT[#All],4,0)),"CUIT NO CARGADO") -> 0 | K28: 500.03 | L28: Mantenimiento Software | M28: 718570
B29: 45062 | C29: 2 | D29: 103 | E29: 27125997835 | F29: =IFERROR(IF(factura_c_mes283[[#This Row],[CUIT]]="","-",VLOOKUP(factura_c_mes283[[#This Row],[CUIT]],Lista_CUIT[#All],2,0)),"CUIT NO CARGADO") -> DANSKY ULLMANN VIVIANA EVA YOLANDA | G29: 50000 | H29: Gastos varios | I29: =IFERROR(IF(factura_c_mes283[[#This Row],[CUIT]]="","-",VLOOKUP(factura_c_mes283[[#This Row],[CUIT]],Lista_CUIT[#All],4,0)),"CUIT NO CARGADO") -> 0 | K29: 500.035 | L29: Desarrollo Software | M29: 800000
B30: 45057 | C30: 7 | D30: 313886 | E30: 20259150249 | F30: =IFERROR(IF(factura_c_mes283[[#This Row],[CUIT]]="","-",VLOOKUP(factura_c_mes283[[#This Row],[CUIT]],Lista_CUIT[#All],2,0)),"CUIT NO CARGADO") -> BIANCHI CRISTIAN MAXIMILIANO | G30: 18590 | H30: =IFERROR(IF(factura_c_mes283[[#This Row],[CUIT]]="","-",VLOOKUP(factura_c_mes283[[#This Row],[CUIT]],Lista_CUIT[#All],3,0)),"CUIT NO CARGADO") -> Gastos Varios | I30: =IFERROR(IF(factura_c_mes283[[#This Row],[CUIT]]="","-",VLOOKUP(factura_c_mes283[[#This Row],[CUIT]],Lista_CUIT[#All],4,0)),"CUIT NO CARGADO") -> 0 | K30: 507.13 | L30: Fletes-Logisdtica | M30: 3200
B31: 45061 | C31: 7 | D31: 314857 | E31: 20259150249 | F31: =IFERROR(IF(factura_c_mes283[[#This Row],[CUIT]]="","-",VLOOKUP(factura_c_mes283[[#This Row],[CUIT]],Lista_CUIT[#All],2,0)),"CUIT NO CARGADO") -> BIANCHI CRISTIAN MAXIMILIANO | G31: 16799 | H31: =IFERROR(IF(factura_c_mes283[[#This Row],[CUIT]]="","-",VLOOKUP(factura_c_mes283[[#This Row],[CUIT]],Lista_CUIT[#All],3,0)),"CUIT NO CARGADO") -> Gastos Varios | I31: =IFERROR(IF(factura_c_mes283[[#This Row],[CUIT]]="","-",VLOOKUP(factura_c_mes283[[#This Row],[CUIT]],Lista_CUIT[#All],4,0)),"CUIT NO CARGADO") -> 0 | K31: 121.122 | L31: Insumos --Accesorios | M31: 37400
B32: 45054 | C32: 2 | D32: 140 | E32: 20136544625 | F32: =IFERROR(IF(factura_c_mes283[[#This Row],[CUIT]]="","-",VLOOKUP(factura_c_mes283[[#This Row],[CUIT]],Lista_CUIT[#All],2,0)),"CUIT NO CARGADO") -> RODRIGUEZ DE LA FUEN HECTOR MARCELO | G32: 160000 | H32: =IFERROR(IF(factura_c_mes283[[#This Row],[CUIT]]="","-",VLOOKUP(factura_c_mes283[[#This Row],[CUIT]],Lista_CUIT[#All],3,0)),"CUIT NO CARGADO") -> Hon. Admin. | I32: =IFERROR(IF(factura_c_mes283[[#This Row],[CUIT]]="","-",VLOOKUP(factura_c_mes283[[#This Row],[CUIT]],Lista_CUIT[#All],4,0)),"CUIT NO CARGADO") -> 0 | K32: 500.034 | L32: Seguimientos de Clientes | M32: 84196
B33: 45054 | C33: 2 | D33: 141 | E33: 20136544625 | F33: =IFERROR(IF(factura_c_mes283[[#This Row],[CUIT]]="","-",VLOOKUP(factura_c_mes283[[#This Row],[CUIT]],Lista_CUIT[#All],2,0)),"CUIT NO CARGADO") -> RODRIGUEZ DE LA FUEN HECTOR MARCELO | G33: 140000 | H33: =IFERROR(IF(factura_c_mes283[[#This Row],[CUIT]]="","-",VLOOKUP(factura_c_mes283[[#This Row],[CUIT]],Lista_CUIT[#All],3,0)),"CUIT NO CARGADO") -> Hon. Admin. | I33: =IFERROR(IF(factura_c_mes283[[#This Row],[CUIT]]="","-",VLOOKUP(factura_c_mes283[[#This Row],[CUIT]],Lista_CUIT[#All],4,0)),"CUIT NO CARGADO") -> 0
B34: 45061 | C34: 2 | D34: 142 | E34: 20136544625 | F34: =IFERROR(IF(factura_c_mes283[[#This Row],[CUIT]]="","-",VLOOKUP(factura_c_mes283[[#This Row],[CUIT]],Lista_CUIT[#All],2,0)),"CUIT NO CARGADO") -> RODRIGUEZ DE LA FUEN HECTOR MARCELO | G34: 400000 | H34: =IFERROR(IF(factura_c_mes283[[#This Row],[CUIT]]="","-",VLOOKUP(factura_c_mes283[[#This Row],[CUIT]],Lista_CUIT[#All],3,0)),"CUIT NO CARGADO") -> Hon. Admin. | I34: =IFERROR(IF(factura_c_mes283[[#This Row],[CUIT]]="","-",VLOOKUP(factura_c_mes283[[#This Row],[CUIT]],Lista_CUIT[#All],4,0)),"CUIT NO CARGADO") -> 0 | M34: =SUM(M21:M32) -> 4034704
B35: 45069 | C35: 3 | D35: 52 | E35: 20403931420 | F35: =IFERROR(IF(factura_c_mes283[[#This Row],[CUIT]]="","-",VLOOKUP(factura_c_mes283[[#This Row],[CUIT]],Lista_CUIT[#All],2,0)),"CUIT NO CARGADO") -> FIORENTINO JORGE IGNACIO | G35: 148510 | H35: Honorarios Administrativos | I35: =IFERROR(IF(factura_c_mes283[[#This Row],[CUIT]]="","-",VLOOKUP(factura_c_mes283[[#This Row],[CUIT]],Lista_CUIT[#All],4,0)),"CUIT NO CARGADO") -> 0
B36: 45048 | C36: 3 | D36: 732 | E36: 20086277523 | F36: =IFERROR(IF(factura_c_mes283[[#This Row],[CUIT]]="","-",VLOOKUP(factura_c_mes283[[#This Row],[CUIT]],Lista_CUIT[#All],2,0)),"CUIT NO CARGADO") -> ESTUDIO BOTINDARI | G36: 81000 | H36: Honorarios Contables | I36: =IFERROR(IF(factura_c_mes283[[#This Row],[CUIT]]="","-",VLOOKUP(factura_c_mes283[[#This Row],[CUIT]],Lista_CUIT[#All],4,0)),"CUIT NO CARGADO") -> 0
B37: 45061 | C37: 3 | D37: 737 | E37: 20086277523 | F37: =IFERROR(IF(factura_c_mes283[[#This Row],[CUIT]]="","-",VLOOKUP(factura_c_mes283[[#This Row],[CUIT]],Lista_CUIT[#All],2,0)),"CUIT NO CARGADO") -> ESTUDIO BOTINDARI | G37: 12860 | H37: Honorarios Contables | I37: =IFERROR(IF(factura_c_mes283[[#This Row],[CUIT]]="","-",VLOOKUP(factura_c_mes283[[#This Row],[CUIT]],Lista_CUIT[#All],4,0)),"CUIT NO CARGADO") -> 0
B38: 45057 | C38: 4 | D38: 13 | E38: 20341462933 | F38: =IFERROR(IF(factura_c_mes283[[#This Row],[CUIT]]="","-",VLOOKUP(factura_c_mes283[[#This Row],[CUIT]],Lista_CUIT[#All],2,0)),"CUIT NO CARGADO") -> CASTIGLIONI MATIAS EZEQUIEL | G38: 510000 | H38: Ingenieria Aplicada | I38: =IFERROR(IF(factura_c_mes283[[#This Row],[CUIT]]="","-",VLOOKUP(factura_c_mes283[[#This Row],[CUIT]],Lista_CUIT[#All],4,0)),"CUIT NO CARGADO") -> BUENOS AIRES
B39: 45049 | C39: 1 | D39: 12 | E39: 20338344695 | F39: =IFERROR(IF(factura_c_mes283[[#This Row],[CUIT]]="","-",VLOOKUP(factura_c_mes283[[#This Row],[CUIT]],Lista_CUIT[#All],2,0)),"CUIT NO CARGADO") -> FUERTES DAMIAN MATIAS | G39: 37400 | H39: =IFERROR(IF(factura_c_mes283[[#This Row],[CUIT]]="","-",VLOOKUP(factura_c_mes283[[#This Row],[CUIT]],Lista_CUIT[#All],3,0)),"CUIT NO CARGADO") -> INSUMO | I39: =IFERROR(IF(factura_c_mes283[[#This Row],[CUIT]]="","-",VLOOKUP(factura_c_mes283[[#This Row],[CUIT]],Lista_CUIT[#All],4,0)),"CUIT NO CARGADO") -> 0
B40: 45049 | C40: 350 | D40: 186905 | E40: 30525558246 | F40: =IFERROR(IF(factura_c_mes283[[#This Row],[CUIT]]="","-",VLOOKUP(factura_c_mes283[[#This Row],[CUIT]],Lista_CUIT[#All],2,0)),"CUIT NO CARGADO") -> ANTONIO LUQUIN S A C I F E I | G40: 21399 | H40: Estaciones Mantenimiento | I40: =IFERROR(IF(factura_c_mes283[[#This Row],[CUIT]]="","-",VLOOKUP(factura_c_mes283[[#This Row],[CUIT]],Lista_CUIT[#All],4,0)),"CUIT NO CARGADO") -> 0
B41: 45049 | C41: 350 | D41: 186906 | E41: 30525558246 | F41: =IFERROR(IF(factura_c_mes283[[#This Row],[CUIT]]="","-",VLOOKUP(factura_c_mes283[[#This Row],[CUIT]],Lista_CUIT[#All],2,0)),"CUIT NO CARGADO") -> ANTONIO LUQUIN S A C I F E I | G41: 21399 | H41: Estaciones Mantenimiento | I41: =IFERROR(IF(factura_c_mes283[[#This Row],[CUIT]]="","-",VLOOKUP(factura_c_mes283[[#This Row],[CUIT]],Lista_CUIT[#All],4,0)),"CUIT NO CARGADO") -> 0
B42: 45049 | C42: 345 | D42: 332222 | E42: 30525558246 | F42: =IFERROR(IF(factura_c_mes283[[#This Row],[CUIT]]="","-",VLOOKUP(factura_c_mes283[[#This Row],[CUIT]],Lista_CUIT[#All],2,0)),"CUIT NO CARGADO") -> ANTONIO LUQUIN S A C I F E I | G42: 20699 | H42: Estaciones Mantenimiento | I42: =IFERROR(IF(factura_c_mes283[[#This Row],[CUIT]]="","-",VLOOKUP(factura_c_mes283[[#This Row],[CUIT]],Lista_CUIT[#All],4,0)),"CUIT NO CARGADO") -> 0
B43: 45049 | C43: 345 | D43: 332224 | E43: 30525558246 | F43: =IFERROR(IF(factura_c_mes283[[#This Row],[CUIT]]="","-",VLOOKUP(factura_c_mes283[[#This Row],[CUIT]],Lista_CUIT[#All],2,0)),"CUIT NO CARGADO") -> ANTONIO LUQUIN S A C I F E I | G43: 20699 | H43: Estaciones Mantenimiento | I43: =IFERROR(IF(factura_c_mes283[[#This Row],[CUIT]]="","-",VLOOKUP(factura_c_mes283[[#This Row],[CUIT]],Lista_CUIT[#All],4,0)),"CUIT NO CARGADO") -> 0
B44: 45068 | C44: 1 | D44: 18 | E44: 20417805878 | F44: =IFERROR(IF(factura_c_mes283[[#This Row],[CUIT]]="","-",VLOOKUP(factura_c_mes283[[#This Row],[CUIT]],Lista_CUIT[#All],2,0)),"CUIT NO CARGADO") -> FERABOLI OSPAL SANTIAGO HERNAN | G44: 128970 | H44: Control de Materiales | I44: =IFERROR(IF(factura_c_mes283[[#This Row],[CUIT]]="","-",VLOOKUP(factura_c_mes283[[#This Row],[CUIT]],Lista_CUIT[#All],4,0)),"CUIT NO CARGADO") -> 0
B45: 45062 | C45: 2 | D45: 2 | E45: 23326777269 | F45: =IFERROR(IF(factura_c_mes283[[#This Row],[CUIT]]="","-",VLOOKUP(factura_c_mes283[[#This Row],[CUIT]],Lista_CUIT[#All],2,0)),"CUIT NO CARGADO") -> DE BONIS IGNACIO LUIS | G45: -148935 | H45: Mantenimiento Oficvina | I45: =IFERROR(IF(factura_c_mes283[[#This Row],[CUIT]]="","-",VLOOKUP(factura_c_mes283[[#This Row],[CUIT]],Lista_CUIT[#All],4,0)),"CUIT NO CARGADO") -> 0
B46: 45068 | C46: 1 | D46: 99 | E46: 20341465134 | F46: =IFERROR(IF(factura_c_mes283[[#This Row],[CUIT]]="","-",VLOOKUP(factura_c_mes283[[#This Row],[CUIT]],Lista_CUIT[#All],2,0)),"CUIT NO CARGADO") -> ABELEDO AGUSTIN ENRIQUE | G46: 340570 | H46: Mantenimiento Sofware | I46: =IFERROR(IF(factura_c_mes283[[#This Row],[CUIT]]="","-",VLOOKUP(factura_c_mes283[[#This Row],[CUIT]],Lista_CUIT[#All],4,0)),"CUIT NO CARGADO") -> CABA
B47: 45065 | C47: 2 | D47: 83 | E47: 20244271740 | F47: =IFERROR(IF(factura_c_mes283[[#This Row],[CUIT]]="","-",VLOOKUP(factura_c_mes283[[#This Row],[CUIT]],Lista_CUIT[#All],2,0)),"CUIT NO CARGADO") -> KENNEL SEBASTIAN | G47: 378000 | H47: =IFERROR(IF(factura_c_mes283[[#This Row],[CUIT]]="","-",VLOOKUP(factura_c_mes283[[#This Row],[CUIT]],Lista_CUIT[#All],3,0)),"CUIT NO CARGADO") -> Software Mantenimiento | I47: =IFERROR(IF(factura_c_mes283[[#This Row],[CUIT]]="","-",VLOOKUP(factura_c_mes283[[#This Row],[CUIT]],Lista_CUIT[#All],4,0)),"CUIT NO CARGADO") -> 0
B48: Total | G48: =SUBTOTAL(109,factura_c_mes283[TOTAL]) -> 4034704
B51: FACTURAS C
B52: FECHA | C52: PTO VTA | D52: FC Nº | E52: CUIT | F52: RAZON SOCIAL | G52: TOTAL | H52: TIPO DE GASTO | I52: Provincia
B53: 45078 | C53: 4 | D53: 47 | E53: 23214737914 | F53: =IFERROR(IF(factura_c_mes384[[#This Row],[CUIT]]="","-",VLOOKUP(factura_c_mes384[[#This Row],[CUIT]],Lista_CUIT[#All],2,0)),"CUIT NO CARGADO") -> SBARRA GABRIELA BEATRIZ | G53: 301780 | H53: Control de Calidad | I53: =IFERROR(IF(factura_c_mes384[[#This Row],[CUIT]]="","-",VLOOKUP(factura_c_mes384[[#This Row],[CUIT]],Lista_CUIT[#All],4,0)),"CUIT NO CARGADO") -> 0 | K53: 510.12 | L53: Honorarios Ingeniero | M53: 488500
B54: 45089 | C54: 4 | D54: 48 | E54: 23214737914 | F54: =IFERROR(IF(factura_c_mes384[[#This Row],[CUIT]]="","-",VLOOKUP(factura_c_mes384[[#This Row],[CUIT]],Lista_CUIT[#All],2,0)),"CUIT NO CARGADO") -> SBARRA GABRIELA BEATRIZ | G54: 266770 | H54: Control de Calidad | I54: =IFERROR(IF(factura_c_mes384[[#This Row],[CUIT]]="","-",VLOOKUP(factura_c_mes384[[#This Row],[CUIT]],Lista_CUIT[#All],4,0)),"CUIT NO CARGADO") -> 0 | K54: 500.05 | L54: Gastos varios | M54: 42654.08
B55: 45078 | C55: 1 | D55: 24 | E55: 20365938688 | F55: =IFERROR(IF(factura_c_mes384[[#This Row],[CUIT]]="","-",VLOOKUP(factura_c_mes384[[#This Row],[CUIT]],Lista_CUIT[#All],2,0)),"CUIT NO CARGADO") -> LIPANOVICH JUAN CRUZ | G55: 450000 | H55: Desarrollo Software | I55: =IFERROR(IF(factura_c_mes384[[#This Row],[CUIT]]="","-",VLOOKUP(factura_c_mes384[[#This Row],[CUIT]],Lista_CUIT[#All],4,0)),"CUIT NO CARGADO") -> 0 | K55: 500.016 | L55: Honorarios Admnistrativos | M55: 449120
B56: 45078 | C56: 7 | D56: 316588 | E56: 20259150249 | F56: =IFERROR(IF(factura_c_mes384[[#This Row],[CUIT]]="","-",VLOOKUP(factura_c_mes384[[#This Row],[CUIT]],Lista_CUIT[#All],2,0)),"CUIT NO CARGADO") -> BIANCHI CRISTIAN MAXIMILIANO | G56: 15455.08 | H56: =IFERROR(IF(factura_c_mes384[[#This Row],[CUIT]]="","-",VLOOKUP(factura_c_mes384[[#This Row],[CUIT]],Lista_CUIT[#All],3,0)),"CUIT NO CARGADO") -> Gastos Varios | I56: =IFERROR(IF(factura_c_mes384[[#This Row],[CUIT]]="","-",VLOOKUP(factura_c_mes384[[#This Row],[CUIT]],Lista_CUIT[#All],4,0)),"CUIT NO CARGADO") -> 0 | K56: 510.1 | L56: Honorarios Contables | M56: 96432
B57: 45078 | C57: 4 | D57: 46218 | E57: 30716998718 | F57: =IFERROR(IF(factura_c_mes384[[#This Row],[CUIT]]="","-",VLOOKUP(factura_c_mes384[[#This Row],[CUIT]],Lista_CUIT[#All],2,0)),"CUIT NO CARGADO") -> FIDO ARGENTINA SRL | G57: 21628 | H57: =IFERROR(IF(factura_c_mes384[[#This Row],[CUIT]]="","-",VLOOKUP(factura_c_mes384[[#This Row],[CUIT]],Lista_CUIT[#All],3,0)),"CUIT NO CARGADO") -> Gastos Varios | I57: =IFERROR(IF(factura_c_mes384[[#This Row],[CUIT]]="","-",VLOOKUP(factura_c_mes384[[#This Row],[CUIT]],Lista_CUIT[#All],4,0)),"CUIT NO CARGADO") -> 0 | K57: 500.035 | L57: Desarrollo Software | M57: 450000
B58: 45100 | C58: 4 | D58: 94073 | E58: 20347495027 | F58: =IFERROR(IF(factura_c_mes384[[#This Row],[CUIT]]="","-",VLOOKUP(factura_c_mes384[[#This Row],[CUIT]],Lista_CUIT[#All],2,0)),"CUIT NO CARGADO") -> BARRAGAN FEDERICO ANDRES | G58: 5571 | H58: Gastos varios | I58: =IFERROR(IF(factura_c_mes384[[#This Row],[CUIT]]="","-",VLOOKUP(factura_c_mes384[[#This Row],[CUIT]],Lista_CUIT[#All],4,0)),"CUIT NO CARGADO") -> 0 | K58: 500.03 | L58: Mantenimiento Software | M58: 668060
B59: 45078 | C59: 2 | D59: 145 | E59: 20136544625 | F59: =IFERROR(IF(factura_c_mes384[[#This Row],[CUIT]]="","-",VLOOKUP(factura_c_mes384[[#This Row],[CUIT]],Lista_CUIT[#All],2,0)),"CUIT NO CARGADO") -> RODRIGUEZ DE LA FUEN HECTOR MARCELO | G59: 300000 | H59: =IFERROR(IF(factura_c_mes384[[#This Row],[CUIT]]="","-",VLOOKUP(factura_c_mes384[[#This Row],[CUIT]],Lista_CUIT[#All],3,0)),"CUIT NO CARGADO") -> Hon. Admin. | I59: =IFERROR(IF(factura_c_mes384[[#This Row],[CUIT]]="","-",VLOOKUP(factura_c_mes384[[#This Row],[CUIT]],Lista_CUIT[#All],4,0)),"CUIT NO CARGADO") -> 0
B60: 45084 | C60: 3 | D60: 53 | E60: 20403931420 | F60: =IFERROR(IF(factura_c_mes384[[#This Row],[CUIT]]="","-",VLOOKUP(factura_c_mes384[[#This Row],[CUIT]],Lista_CUIT[#All],2,0)),"CUIT NO CARGADO") -> FIORENTINO JORGE IGNACIO | G60: 149120 | H60: =IFERROR(IF(factura_c_mes384[[#This Row],[CUIT]]="","-",VLOOKUP(factura_c_mes384[[#This Row],[CUIT]],Lista_CUIT[#All],3,0)),"CUIT NO CARGADO") -> Hon. Admin. | I60: =IFERROR(IF(factura_c_mes384[[#This Row],[CUIT]]="","-",VLOOKUP(factura_c_mes384[[#This Row],[CUIT]],Lista_CUIT[#All],4,0)),"CUIT NO CARGADO") -> 0 | K60: 500.034 | L60: Seguimientos de Clientes | M60: 128720
B61: 45078 | C61: 3 | D61: 742 | E61: 20086277523 | F61: =IFERROR(IF(factura_c_mes384[[#This Row],[CUIT]]="","-",VLOOKUP(factura_c_mes384[[#This Row],[CUIT]],Lista_CUIT[#All],2,0)),"CUIT NO CARGADO") -> ESTUDIO BOTINDARI | G61: 81000 | H61: Honorarios Contables | I61: =IFERROR(IF(factura_c_mes384[[#This Row],[CUIT]]="","-",VLOOKUP(factura_c_mes384[[#This Row],[CUIT]],Lista_CUIT[#All],4,0)),"CUIT NO CARGADO") -> 0 | K61: 500.032 | L61: Verificacion y Control Equipos | M61: 568550
B62: 45089 | C62: 2 | D62: 572 | E62: 20400104094 | F62: =IFERROR(IF(factura_c_mes384[[#This Row],[CUIT]]="","-",VLOOKUP(factura_c_mes384[[#This Row],[CUIT]],Lista_CUIT[#All],2,0)),"CUIT NO CARGADO") -> FEDERICO BOTINDARI | G62: 15432 | H62: Honorarios Contables | I62: =IFERROR(IF(factura_c_mes384[[#This Row],[CUIT]]="","-",VLOOKUP(factura_c_mes384[[#This Row],[CUIT]],Lista_CUIT[#All],4,0)),"CUIT NO CARGADO") -> 0 | M62: =SUM(M53:M68) -> 2892036.1
B63: 45098 | C63: 4 | D63: 14 | E63: 20341462933 | F63: =IFERROR(IF(factura_c_mes384[[#This Row],[CUIT]]="","-",VLOOKUP(factura_c_mes384[[#This Row],[CUIT]],Lista_CUIT[#All],2,0)),"CUIT NO CARGADO") -> CASTIGLIONI MATIAS EZEQUIEL | G63: 488500 | H63: Ingenieria Aplicada | I63: =IFERROR(IF(factura_c_mes384[[#This Row],[CUIT]]="","-",VLOOKUP(factura_c_mes384[[#This Row],[CUIT]],Lista_CUIT[#All],4,0)),"CUIT NO CARGADO") -> BUENOS AIRES
B64: 45086 | C64: 1 | D64: 19 | E64: 20417805878 | F64: =IFERROR(IF(factura_c_mes384[[#This Row],[CUIT]]="","-",VLOOKUP(factura_c_mes384[[#This Row],[CUIT]],Lista_CUIT[#All],2,0)),"CUIT NO CARGADO") -> FERABOLI OSPAL SANTIAGO HERNAN | G64: 128720 | H64: Control de Materiales | I64: =IFERROR(IF(factura_c_mes384[[#This Row],[CUIT]]="","-",VLOOKUP(factura_c_mes384[[#This Row],[CUIT]],Lista_CUIT[#All],4,0)),"CUIT NO CARGADO") -> 0
B65: 45082 | C65: 1 | D65: 100 | E65: 20341465134 | F65: =IFERROR(IF(factura_c_mes384[[#This Row],[CUIT]]="","-",VLOOKUP(factura_c_mes384[[#This Row],[CUIT]],Lista_CUIT[#All],2,0)),"CUIT NO CARGADO") -> ABELEDO AGUSTIN ENRIQUE | G65: 281660 | H65: Mantenimiento Sofware | I65: =IFERROR(IF(factura_c_mes384[[#This Row],[CUIT]]="","-",VLOOKUP(factura_c_mes384[[#This Row],[CUIT]],Lista_CUIT[#All],4,0)),"CUIT NO CARGADO") -> CABA
B66: 45081 | C66: 2 | D66: 84 | E66: 20244271740 | F66: =IFERROR(IF(factura_c_mes384[[#This Row],[CUIT]]="","-",VLOOKUP(factura_c_mes384[[#This Row],[CUIT]],Lista_CUIT[#All],2,0)),"CUIT NO CARGADO") -> KENNEL SEBASTIAN | G66: 386400 | H66: Mantenimiento Sofware | I66: =IFERROR(IF(factura_c_mes384[[#This Row],[CUIT]]="","-",VLOOKUP(factura_c_mes384[[#This Row],[CUIT]],Lista_CUIT[#All],4,0)),"CUIT NO CARGADO") -> 0
B67: Total | G67: =SUBTOTAL(109,factura_c_mes384[TOTAL]) -> 2892036.1
B70: FACTURAS C
B71: FECHA | C71: PTO VTA | D71: FC Nº | E71: CUIT | F71: RAZON SOCIAL | G71: TOTAL | H71: TIPO DE GASTO | I71: Provincia | K71: 510.12 | L71: Honorarios Ingeniero | M71: 412000
B72: 45132 | C72: 4 | D72: 50 | E72: 23214737914 | F72: =IFERROR(IF(factura_c_mes485[[#This Row],[CUIT]]="","-",VLOOKUP(factura_c_mes485[[#This Row],[CUIT]],Lista_CUIT[#All],2,0)),"CUIT NO CARGADO") -> SBARRA GABRIELA BEATRIZ | G72: 360940 | H72: Control de Calidad | I72: =IFERROR(IF(factura_c_mes485[[#This Row],[CUIT]]="","-",VLOOKUP(factura_c_mes485[[#This Row],[CUIT]],Lista_CUIT[#All],4,0)),"CUIT NO CARGADO") -> 0 | K72: 500.05 | L72: Gastos varios | M72: 91875
B73: 45110 | C73: 1 | D73: 9 | E73: 27387896150 | F73: =IFERROR(IF(factura_c_mes485[[#This Row],[CUIT]]="","-",VLOOKUP(factura_c_mes485[[#This Row],[CUIT]],Lista_CUIT[#All],2,0)),"CUIT NO CARGADO") -> LIPANOVICH MARIA SOL | G73: 400000 | H73: Desarrollo Software | I73: =IFERROR(IF(factura_c_mes485[[#This Row],[CUIT]]="","-",VLOOKUP(factura_c_mes485[[#This Row],[CUIT]],Lista_CUIT[#All],4,0)),"CUIT NO CARGADO") -> 0 | K73: 500.016 | L73: Honorarios Admnistrativos | M73: 461275
B74: 45110 | C74: 1 | D74: 25 | E74: 20365938688 | F74: =IFERROR(IF(factura_c_mes485[[#This Row],[CUIT]]="","-",VLOOKUP(factura_c_mes485[[#This Row],[CUIT]],Lista_CUIT[#All],2,0)),"CUIT NO CARGADO") -> LIPANOVICH JUAN CRUZ | G74: 450000 | H74: Desarrollo Software | I74: =IFERROR(IF(factura_c_mes485[[#This Row],[CUIT]]="","-",VLOOKUP(factura_c_mes485[[#This Row],[CUIT]],Lista_CUIT[#All],4,0)),"CUIT NO CARGADO") -> 0 | K74: 510.1 | L74: Honorarios Contables | M74: 96432
B75: 45133 | C75: 1 | D75: 26 | E75: 20365938688 | F75: =IFERROR(IF(factura_c_mes485[[#This Row],[CUIT]]="","-",VLOOKUP(factura_c_mes485[[#This Row],[CUIT]],Lista_CUIT[#All],2,0)),"CUIT NO CARGADO") -> LIPANOVICH JUAN CRUZ | G75: 450000 | H75: Desarrollo Software | I75: =IFERROR(IF(factura_c_mes485[[#This Row],[CUIT]]="","-",VLOOKUP(factura_c_mes485[[#This Row],[CUIT]],Lista_CUIT[#All],4,0)),"CUIT NO CARGADO") -> 0 | K75: 500.035 | L75: Desarrollo Software | M75: 1300000
B76: 45108 | C76: 1 | D76: 11034 | E76: 30709917567 | F76: =IFERROR(IF(factura_c_mes485[[#This Row],[CUIT]]="","-",VLOOKUP(factura_c_mes485[[#This Row],[CUIT]],Lista_CUIT[#All],2,0)),"CUIT NO CARGADO") -> CONSORCIO DE PROPIETARIOS YATAY 138 | G76: 75000 | H76: Gastos varios | I76: =IFERROR(IF(factura_c_mes485[[#This Row],[CUIT]]="","-",VLOOKUP(factura_c_mes485[[#This Row],[CUIT]],Lista_CUIT[#All],4,0)),"CUIT NO CARGADO") -> BUENOS AIRES | K76: 500.03 | L76: Mantenimiento Software | M76: 469000
B77: 45120 | C77: 7 | D77: 61521 | E77: 30711744653 | F77: =IFERROR(IF(factura_c_mes485[[#This Row],[CUIT]]="","-",VLOOKUP(factura_c_mes485[[#This Row],[CUIT]],Lista_CUIT[#All],2,0)),"CUIT NO CARGADO") -> NITRO BIKES S.R.L. | G77: 16875 | H77: Gastos varios | I77: =IFERROR(IF(factura_c_mes485[[#This Row],[CUIT]]="","-",VLOOKUP(factura_c_mes485[[#This Row],[CUIT]],Lista_CUIT[#All],4,0)),"CUIT NO CARGADO") -> 0 | K77: 500.032 | L77: Verificacion y Control Equipos | M77: 360940
B78: 45133 | C78: 3 | D78: 56 | E78: 20403931420 | F78: =IFERROR(IF(factura_c_mes485[[#This Row],[CUIT]]="","-",VLOOKUP(factura_c_mes485[[#This Row],[CUIT]],Lista_CUIT[#All],2,0)),"CUIT NO CARGADO") -> FIORENTINO JORGE IGNACIO | G78: 161275 | H78: =IFERROR(IF(factura_c_mes485[[#This Row],[CUIT]]="","-",VLOOKUP(factura_c_mes485[[#This Row],[CUIT]],Lista_CUIT[#All],3,0)),"CUIT NO CARGADO") -> Hon. Admin. | I78: =IFERROR(IF(factura_c_mes485[[#This Row],[CUIT]]="","-",VLOOKUP(factura_c_mes485[[#This Row],[CUIT]],Lista_CUIT[#All],4,0)),"CUIT NO CARGADO") -> 0 | M78: =SUM(M71:M83) -> 3191522
B79: 45110 | C79: 2 | D79: 148 | E79: 20136544625 | F79: =IFERROR(IF(factura_c_mes485[[#This Row],[CUIT]]="","-",VLOOKUP(factura_c_mes485[[#This Row],[CUIT]],Lista_CUIT[#All],2,0)),"CUIT NO CARGADO") -> RODRIGUEZ DE LA FUEN HECTOR MARCELO | G79: 300000 | H79: =IFERROR(IF(factura_c_mes485[[#This Row],[CUIT]]="","-",VLOOKUP(factura_c_mes485[[#This Row],[CUIT]],Lista_CUIT[#All],3,0)),"CUIT NO CARGADO") -> Hon. Admin. | I79: =IFERROR(IF(factura_c_mes485[[#This Row],[CUIT]]="","-",VLOOKUP(factura_c_mes485[[#This Row],[CUIT]],Lista_CUIT[#All],4,0)),"CUIT NO CARGADO") -> 0
B80: 45121 | C80: 2 | D80: 593 | E80: 20400104094 | F80: =IFERROR(IF(factura_c_mes485[[#This Row],[CUIT]]="","-",VLOOKUP(factura_c_mes485[[#This Row],[CUIT]],Lista_CUIT[#All],2,0)),"CUIT NO CARGADO") -> FEDERICO BOTINDARI | G80: 15432 | H80: Honorarios Contables | I80: =IFERROR(IF(factura_c_mes485[[#This Row],[CUIT]]="","-",VLOOKUP(factura_c_mes485[[#This Row],[CUIT]],Lista_CUIT[#All],4,0)),"CUIT NO CARGADO") -> 0
B81: 45110 | C81: 3 | D81: 756 | E81: 20086277523 | F81: =IFERROR(IF(factura_c_mes485[[#This Row],[CUIT]]="","-",VLOOKUP(factura_c_mes485[[#This Row],[CUIT]],Lista_CUIT[#All],2,0)),"CUIT NO CARGADO") -> ESTUDIO BOTINDARI | G81: 81000 | H81: Honorarios Contables | I81: =IFERROR(IF(factura_c_mes485[[#This Row],[CUIT]]="","-",VLOOKUP(factura_c_mes485[[#This Row],[CUIT]],Lista_CUIT[#All],4,0)),"CUIT NO CARGADO") -> 0
B82: 45118 | C82: 4 | D82: 15 | E82: 20341462933 | F82: =IFERROR(IF(factura_c_mes485[[#This Row],[CUIT]]="","-",VLOOKUP(factura_c_mes485[[#This Row],[CUIT]],Lista_CUIT[#All],2,0)),"CUIT NO CARGADO") -> CASTIGLIONI MATIAS EZEQUIEL | G82: 412000 | H82: Ingenieria Aplicada | I82: =IFERROR(IF(factura_c_mes485[[#This Row],[CUIT]]="","-",VLOOKUP(factura_c_mes485[[#This Row],[CUIT]],Lista_CUIT[#All],4,0)),"CUIT NO CARGADO") -> BUENOS AIRES
B83: 45131 | C83: 2 | D83: 86 | E83: 20244271740 | F83: =IFERROR(IF(factura_c_mes485[[#This Row],[CUIT]]="","-",VLOOKUP(factura_c_mes485[[#This Row],[CUIT]],Lista_CUIT[#All],2,0)),"CUIT NO CARGADO") -> KENNEL SEBASTIAN | G83: 313500 | H83: Mantenimiento Sofware | I83: =IFERROR(IF(factura_c_mes485[[#This Row],[CUIT]]="","-",VLOOKUP(factura_c_mes485[[#This Row],[CUIT]],Lista_CUIT[#All],4,0)),"CUIT NO CARGADO") -> 0
B84: 45112 | C84: 1 | D84: 101 | E84: 20341465134 | F84: =IFERROR(IF(factura_c_mes485[[#This Row],[CUIT]]="","-",VLOOKUP(factura_c_mes485[[#This Row],[CUIT]],Lista_CUIT[#All],2,0)),"CUIT NO CARGADO") -> ABELEDO AGUSTIN ENRIQUE | G84: 155500 | H84: Mantenimiento Sofware | I84: =IFERROR(IF(factura_c_mes485[[#This Row],[CUIT]]="","-",VLOOKUP(factura_c_mes485[[#This Row],[CUIT]],Lista_CUIT[#All],4,0)),"CUIT NO CARGADO") -> CABA
B85: Total | G85: =SUBTOTAL(109,factura_c_mes485[TOTAL]) -> 3191522
B88: FACTURAS C | H88: AGOSTO
B89: FECHA | C89: PTO VTA | D89: FC Nº | E89: CUIT | F89: RAZON SOCIAL | G89: TOTAL | H89: TIPO DE GASTO | I89: Provincia | K89: 510.12 | L89: Honorarios Ingeniero | M89: 418000
B90: 45161 | C90: 1 | D90: 33 | E90: 20382910681 | F90: =IFERROR(IF(factura_c_mes586[[#This Row],[CUIT]]="","-",VLOOKUP(factura_c_mes586[[#This Row],[CUIT]],Lista_CUIT[#All],2,0)),"CUIT NO CARGADO") -> JULIAN FELIPE | G90: 349999 | H90: Programacion | I90: =IFERROR(IF(factura_c_mes586[[#This Row],[CUIT]]="","-",VLOOKUP(factura_c_mes586[[#This Row],[CUIT]],Lista_CUIT[#All],4,0)),"CUIT NO CARGADO") -> 0 | K90: 500.05 | L90: Gastos varios | M90: 31450
F91: =IFERROR(IF(factura_c_mes586[[#This Row],[CUIT]]="","-",VLOOKUP(factura_c_mes586[[#This Row],[CUIT]],Lista_CUIT[#All],2,0)),"CUIT NO CARGADO") -> - | H91: =IFERROR(IF(factura_c_mes586[[#This Row],[CUIT]]="","-",VLOOKUP(factura_c_mes586[[#This Row],[CUIT]],Lista_CUIT[#All],3,0)),"CUIT NO CARGADO") -> - | I91: =IFERROR(IF(factura_c_mes586[[#This Row],[CUIT]]="","-",VLOOKUP(factura_c_mes586[[#This Row],[CUIT]],Lista_CUIT[#All],4,0)),"CUIT NO CARGADO") -> - | K91: 500.016 | L91: Honorarios Admnistrativos | M91: 361520
F92: =IFERROR(IF(factura_c_mes586[[#This Row],[CUIT]]="","-",VLOOKUP(factura_c_mes586[[#This Row],[CUIT]],Lista_CUIT[#All],2,0)),"CUIT NO CARGADO") -> - | H92: =IFERROR(IF(factura_c_mes586[[#This Row],[CUIT]]="","-",VLOOKUP(factura_c_mes586[[#This Row],[CUIT]],Lista_CUIT[#All],3,0)),"CUIT NO CARGADO") -> - | I92: =IFERROR(IF(factura_c_mes586[[#This Row],[CUIT]]="","-",VLOOKUP(factura_c_mes586[[#This Row],[CUIT]],Lista_CUIT[#All],4,0)),"CUIT NO CARGADO") -> - | K92: 510.1 | L92: Honorarios Contables | M92: 110932
B93: 45160 | C93: 4 | D93: 52 | E93: 23214737914 | F93: =IFERROR(IF(factura_c_mes586[[#This Row],[CUIT]]="","-",VLOOKUP(factura_c_mes586[[#This Row],[CUIT]],Lista_CUIT[#All],2,0)),"CUIT NO CARGADO") -> SBARRA GABRIELA BEATRIZ | G93: 400270 | H93: Control de Calidad | I93: =IFERROR(IF(factura_c_mes586[[#This Row],[CUIT]]="","-",VLOOKUP(factura_c_mes586[[#This Row],[CUIT]],Lista_CUIT[#All],4,0)),"CUIT NO CARGADO") -> 0 | K93: 500.035 | L93: Desarrollo Software | M93: 1250000
B94: 45139 | C94: 1 | D94: 11 | E94: 27387896150 | F94: =IFERROR(IF(factura_c_mes586[[#This Row],[CUIT]]="","-",VLOOKUP(factura_c_mes586[[#This Row],[CUIT]],Lista_CUIT[#All],2,0)),"CUIT NO CARGADO") -> LIPANOVICH MARIA SOL | G94: 400000 | H94: Desarrollo Software | I94: =IFERROR(IF(factura_c_mes586[[#This Row],[CUIT]]="","-",VLOOKUP(factura_c_mes586[[#This Row],[CUIT]],Lista_CUIT[#All],4,0)),"CUIT NO CARGADO") -> 0 | K94: 507.1 | L94: Programacion | M94: 349999
B95: 45166 | C95: 1 | D95: 27 | E95: 20365938688 | F95: =IFERROR(IF(factura_c_mes586[[#This Row],[CUIT]]="","-",VLOOKUP(factura_c_mes586[[#This Row],[CUIT]],Lista_CUIT[#All],2,0)),"CUIT NO CARGADO") -> LIPANOVICH JUAN CRUZ | G95: 450000 | H95: Desarrollo Software | I95: =IFERROR(IF(factura_c_mes586[[#This Row],[CUIT]]="","-",VLOOKUP(factura_c_mes586[[#This Row],[CUIT]],Lista_CUIT[#All],4,0)),"CUIT NO CARGADO") -> 0 | K95: 500.03 | L95: Mantenimiento Software | M95: 199500
B96: 45169 | C96: 1 | D96: 13 | E96: 27387896150 | F96: =IFERROR(IF(factura_c_mes586[[#This Row],[CUIT]]="","-",VLOOKUP(factura_c_mes586[[#This Row],[CUIT]],Lista_CUIT[#All],2,0)),"CUIT NO CARGADO") -> LIPANOVICH MARIA SOL | G96: 400000 | H96: Desarrollo Software | I96: =IFERROR(IF(factura_c_mes586[[#This Row],[CUIT]]="","-",VLOOKUP(factura_c_mes586[[#This Row],[CUIT]],Lista_CUIT[#All],4,0)),"CUIT NO CARGADO") -> 0 | K96: 507.13 | L96: Fletes-Logisdtica | M96: 3200
B97: 45142 | C97: 2 | D97: 85533 | E97: 30554466806 | F97: =IFERROR(IF(factura_c_mes586[[#This Row],[CUIT]]="","-",VLOOKUP(factura_c_mes586[[#This Row],[CUIT]],Lista_CUIT[#All],2,0)),"CUIT NO CARGADO") -> ASOCIACION DE IMPORTADORES Y EXPORTADORES DE LA REPUBLICA ARGENTINA | G97: 3200 | H97: =IFERROR(IF(factura_c_mes586[[#This Row],[CUIT]]="","-",VLOOKUP(factura_c_mes586[[#This Row],[CUIT]],Lista_CUIT[#All],3,0)),"CUIT NO CARGADO") -> FLETE-LOGISTICA | I97: =IFERROR(IF(factura_c_mes586[[#This Row],[CUIT]]="","-",VLOOKUP(factura_c_mes586[[#This Row],[CUIT]],Lista_CUIT[#All],4,0)),"CUIT NO CARGADO") -> 0 | K97: 500.032 | L97: Verificacion y Control Equipos | M97: 400270
B98: 45152 | C98: 1 | D98: 162 | E98: 27925308868 | F98: =IFERROR(IF(factura_c_mes586[[#This Row],[CUIT]]="","-",VLOOKUP(factura_c_mes586[[#This Row],[CUIT]],Lista_CUIT[#All],2,0)),"CUIT NO CARGADO") -> LOPEZ MOLINA MARIA | G98: 14000 | H98: Gastos varios | I98: =IFERROR(IF(factura_c_mes586[[#This Row],[CUIT]]="","-",VLOOKUP(factura_c_mes586[[#This Row],[CUIT]],Lista_CUIT[#All],4,0)),"CUIT NO CARGADO") -> 0
B99: 45154 | C99: 1 | D99: 174 | E99: 27925308868 | F99: =IFERROR(IF(factura_c_mes586[[#This Row],[CUIT]]="","-",VLOOKUP(factura_c_mes586[[#This Row],[CUIT]],Lista_CUIT[#All],2,0)),"CUIT NO CARGADO") -> LOPEZ MOLINA MARIA | G99: 2000 | H99: Gastos varios | I99: =IFERROR(IF(factura_c_mes586[[#This Row],[CUIT]]="","-",VLOOKUP(factura_c_mes586[[#This Row],[CUIT]],Lista_CUIT[#All],4,0)),"CUIT NO CARGADO") -> 0 | M99: =SUM(M89:M101) -> 3124871
B100: 45161 | C100: 1 | D100: 633 | E100: 27349373225 | F100: =IFERROR(IF(factura_c_mes586[[#This Row],[CUIT]]="","-",VLOOKUP(factura_c_mes586[[#This Row],[CUIT]],Lista_CUIT[#All],2,0)),"CUIT NO CARGADO") -> LOPEZ DAIANA BELEN | G100: 8450 | H100: Gastos varios | I100: =IFERROR(IF(factura_c_mes586[[#This Row],[CUIT]]="","-",VLOOKUP(factura_c_mes586[[#This Row],[CUIT]],Lista_CUIT[#All],4,0)),"CUIT NO CARGADO") -> 0
B101: 45167 | C101: 1 | D101: 197 | E101: 27925308868 | F101: =IFERROR(IF(factura_c_mes586[[#This Row],[CUIT]]="","-",VLOOKUP(factura_c_mes586[[#This Row],[CUIT]],Lista_CUIT[#All],2,0)),"CUIT NO CARGADO") -> LOPEZ MOLINA MARIA | G101: 7000 | H101: Gastos varios | I101: =IFERROR(IF(factura_c_mes586[[#This Row],[CUIT]]="","-",VLOOKUP(factura_c_mes586[[#This Row],[CUIT]],Lista_CUIT[#All],4,0)),"CUIT NO CARGADO") -> 0
B102: 45139 | C102: 2 | D102: 149 | E102: 20136544625 | F102: =IFERROR(IF(factura_c_mes586[[#This Row],[CUIT]]="","-",VLOOKUP(factura_c_mes586[[#This Row],[CUIT]],Lista_CUIT[#All],2,0)),"CUIT NO CARGADO") -> RODRIGUEZ DE LA FUEN HECTOR MARCELO | G102: 200000 | H102: =IFERROR(IF(factura_c_mes586[[#This Row],[CUIT]]="","-",VLOOKUP(factura_c_mes586[[#This Row],[CUIT]],Lista_CUIT[#All],3,0)),"CUIT NO CARGADO") -> Hon. Admin. | I102: =IFERROR(IF(factura_c_mes586[[#This Row],[CUIT]]="","-",VLOOKUP(factura_c_mes586[[#This Row],[CUIT]],Lista_CUIT[#All],4,0)),"CUIT NO CARGADO") -> 0
B103: 45161 | C103: 3 | D103: 59 | E103: 20403931420 | F103: =IFERROR(IF(factura_c_mes586[[#This Row],[CUIT]]="","-",VLOOKUP(factura_c_mes586[[#This Row],[CUIT]],Lista_CUIT[#All],2,0)),"CUIT NO CARGADO") -> FIORENTINO JORGE IGNACIO | G103: 161520 | H103: =IFERROR(IF(factura_c_mes586[[#This Row],[CUIT]]="","-",VLOOKUP(factura_c_mes586[[#This Row],[CUIT]],Lista_CUIT[#All],3,0)),"CUIT NO CARGADO") -> Hon. Admin. | I103: =IFERROR(IF(factura_c_mes586[[#This Row],[CUIT]]="","-",VLOOKUP(factura_c_mes586[[#This Row],[CUIT]],Lista_CUIT[#All],4,0)),"CUIT NO CARGADO") -> 0
B104: 45140 | C104: 3 | D104: 765 | E104: 20086277523 | F104: =IFERROR(IF(factura_c_mes586[[#This Row],[CUIT]]="","-",VLOOKUP(factura_c_mes586[[#This Row],[CUIT]],Lista_CUIT[#All],2,0)),"CUIT NO CARGADO") -> ESTUDIO BOTINDARI | G104: 95500 | H104: Honorarios Contables | I104: =IFERROR(IF(factura_c_mes586[[#This Row],[CUIT]]="","-",VLOOKUP(factura_c_mes586[[#This Row],[CUIT]],Lista_CUIT[#All],4,0)),"CUIT NO CARGADO") -> 0
B105: 45153 | C105: 2 | D105: 614 | E105: 20400104094 | F105: =IFERROR(IF(factura_c_mes586[[#This Row],[CUIT]]="","-",VLOOKUP(factura_c_mes586[[#This Row],[CUIT]],Lista_CUIT[#All],2,0)),"CUIT NO CARGADO") -> FEDERICO BOTINDARI | G105: 15432 | H105: Honorarios Contables | I105: =IFERROR(IF(factura_c_mes586[[#This Row],[CUIT]]="","-",VLOOKUP(factura_c_mes586[[#This Row],[CUIT]],Lista_CUIT[#All],4,0)),"CUIT NO CARGADO") -> 0
B106: 45146 | C106: 4 | D106: 16 | E106: 20341462933 | F106: =IFERROR(IF(factura_c_mes586[[#This Row],[CUIT]]="","-",VLOOKUP(factura_c_mes586[[#This Row],[CUIT]],Lista_CUIT[#All],2,0)),"CUIT NO CARGADO") -> CASTIGLIONI MATIAS EZEQUIEL | G106: 418000 | H106: Ingenieria Aplicada | I106: =IFERROR(IF(factura_c_mes586[[#This Row],[CUIT]]="","-",VLOOKUP(factura_c_mes586[[#This Row],[CUIT]],Lista_CUIT[#All],4,0)),"CUIT NO CARGADO") -> BUENOS AIRES
B107: 45159 | C107: 2 | D107: 88 | E107: 20244271740 | F107: =IFERROR(IF(factura_c_mes586[[#This Row],[CUIT]]="","-",VLOOKUP(factura_c_mes586[[#This Row],[CUIT]],Lista_CUIT[#All],2,0)),"CUIT NO CARGADO") -> KENNEL SEBASTIAN | G107: 199500 | H107: Mantenimiento Sofware | I107: =IFERROR(IF(factura_c_mes586[[#This Row],[CUIT]]="","-",VLOOKUP(factura_c_mes586[[#This Row],[CUIT]],Lista_CUIT[#All],4,0)),"CUIT NO CARGADO") -> 0
B108: Total | G108: =SUBTOTAL(109,factura_c_mes586[TOTAL]) -> 3124871
B111: FACTURAS C
...

Sheet Abr-23
B1: LIBRO IVA COMPRAS | G1: CORITEC S. R. L. | N1: 45017
B3: TOTAL COMPRAS NETAS | G3: TOTAL CREDITO FISCAL | J3: TOTAL VENTAS NETAS | M3: TOTAL DEBITO FISCAL | P3: RESULTADO
B4: =SUM(compras_mes1[[#Totals],[NETO GRAVADO]])+extracto_banco_mes1[[#Totals],[NETO]] -> 4605652.9 | G4: =compras_mes1[[#Totals],[IVA 21 %]]+compras_mes1[[#Totals],[IVA 27%]]+compras_mes1[[#Totals],[IVA 10,5%]]+I76 -> 951044.47 | J4: =venta_a_mes1[[#Totals],[IMPORTE NETO]]+ventas_b_mes1[[#Totals],[IMPORTE NETO]] -> 9011565.4 | M4: =venta_a_mes1[[#Totals],[IVA 21%]]+venta_a_mes1[[#Totals],[IVA 10,5%]]+ventas_b_mes1[[#Totals],[IVA 21%]]+ventas_b_mes1[[#Totals],[IVA 10,5%]]+ventas_b_mes13[[#Totals],[IVA 21%]]+ventas_b_mes13[[#Totals],[Columna1]] -> 1894738.7 | P4: =G4-M4 -> -943694.27
B8: FECHA | C8: TIPO | D8: PTO VTA | E8: NRO. CPTE | F8: CUIT | G8: RAZON SOCIAL | H8: NETO GRAVADO | I8: IVA 21 % | J8: IVA 27% | K8: IVA 10,5% | L8: PERC. IVA | M8: PERC IIBB BS AS | N8: PERC. IIBB CABA | O8: Otros / No Grav. | P8: TOTAL | Q8: Tipo de Gasto | R8: Provincia
G9: =IFERROR(IF(compras_mes1[[#This Row],[CUIT]]="","-",VLOOKUP(compras_mes1[[#This Row],[CUIT]],Lista_CUIT[#All],2,0)),"CUIT NO CARGADO") -> - | I9: =compras_mes1[[#This Row],[NETO GRAVADO]]*0.21 -> 0 | P9: =SUM(compras_mes1[[#This Row],[NETO GRAVADO]:[Otros / No Grav.]]) -> 0 | Q9: =IFERROR(IF(compras_mes1[[#This Row],[CUIT]]="","-",VLOOKUP(compras_mes1[[#This Row],[CUIT]],Lista_CUIT[#All],3,0)),"CUIT NO CARGADO") -> - | R9: =IFERROR(IF(compras_mes1[[#This Row],[CUIT]]="","-",VLOOKUP(compras_mes1[[#This Row],[CUIT]],Lista_CUIT[#All],4,0)),"CUIT NO CARGADO") -> -
G10: =IFERROR(IF(compras_mes1[[#This Row],[CUIT]]="","-",VLOOKUP(compras_mes1[[#This Row],[CUIT]],Lista_CUIT[#All],2,0)),"CUIT NO CARGADO") -> - | I10: =compras_mes1[[#This Row],[NETO GRAVADO]]*0.21 -> 0 | P10: =SUM(compras_mes1[[#This Row],[NETO GRAVADO]:[Otros / No Grav.]]) -> 0 | Q10: =IFERROR(IF(compras_mes1[[#This Row],[CUIT]]="","-",VLOOKUP(compras_mes1[[#This Row],[CUIT]],Lista_CUIT[#All],3,0)),"CUIT NO CARGADO") -> - | R10: =IFERROR(IF(compras_mes1[[#This Row],[CUIT]]="","-",VLOOKUP(compras_mes1[[#This Row],[CUIT]],Lista_CUIT[#All],4,0)),"CUIT NO CARGADO") -> -
B11: 45044 | C11: 1 | D11: 1 | E11: 593 | F11: 30715048066 | G11: =IFERROR(IF(compras_mes1[[#This Row],[CUIT]]="","-",VLOOKUP(compras_mes1[[#This Row],[CUIT]],Lista_CUIT[#All],2,0)),"CUIT NO CARGADO") -> ROLLS Y EMPANADAS SA | H11: 105615 | I11: =compras_mes1[[#This Row],[NETO GRAVADO]]*0.21 -> 22179.15 | P11: =SUM(compras_mes1[[#This Row],[NETO GRAVADO]:[Otros / No Grav.]]) -> 127794.15 | Q11: =IFERROR(IF(compras_mes1[[#This Row],[CUIT]]="","-",VLOOKUP(compras_mes1[[#This Row],[CUIT]],Lista_CUIT[#All],3,0)),"CUIT NO CARGADO") -> CATERING | R11: =IFERROR(IF(compras_mes1[[#This Row],[CUIT]]="","-",VLOOKUP(compras_mes1[[#This Row],[CUIT]],Lista_CUIT[#All],4,0)),"CUIT NO CARGADO") -> 0
B12: 45017 | C12: 1 | D12: 11 | E12: 10726 | F12: 30708622423 | G12: =IFERROR(IF(compras_mes1[[#This Row],[CUIT]]="","-",VLOOKUP(compras_mes1[[#This Row],[CUIT]],Lista_CUIT[#All],2,0)),"CUIT NO CARGADO") -> TERGEN SRL | H12: 7921.33 | I12: =compras_mes1[[#This Row],[NETO GRAVADO]]*0.21 -> 1663.4793 | O12: 1816.21 | P12: =SUM(compras_mes1[[#This Row],[NETO GRAVADO]:[Otros / No Grav.]]) -> 11401.019 | Q12: =IFERROR(IF(compras_mes1[[#This Row],[CUIT]]="","-",VLOOKUP(compras_mes1[[#This Row],[CUIT]],Lista_CUIT[#All],3,0)),"CUIT NO CARGADO") -> COMBUSTIBLE | R12: =IFERROR(IF(compras_mes1[[#This Row],[CUIT]]="","-",VLOOKUP(compras_mes1[[#This Row],[CUIT]],Lista_CUIT[#All],4,0)),"CUIT NO CARGADO") -> 0
B13: 45032 | C13: 1 | D13: 12 | E13: 7602 | F13: 30708622423 | G13: =IFERROR(IF(compras_mes1[[#This Row],[CUIT]]="","-",VLOOKUP(compras_mes1[[#This Row],[CUIT]],Lista_CUIT[#All],2,0)),"CUIT NO CARGADO") -> TERGEN SRL | H13: 7954.67 | I13: =compras_mes1[[#This Row],[NETO GRAVADO]]*0.21 -> 1670.4807 | O13: 1675.53 | P13: =SUM(compras_mes1[[#This Row],[NETO GRAVADO]:[Otros / No Grav.]]) -> 11300.681 | Q13: =IFERROR(IF(compras_mes1[[#This Row],[CUIT]]="","-",VLOOKUP(compras_mes1[[#This Row],[CUIT]],Lista_CUIT[#All],3,0)),"CUIT NO CARGADO") -> COMBUSTIBLE | R13: =IFERROR(IF(compras_mes1[[#This Row],[CUIT]]="","-",VLOOKUP(compras_mes1[[#This Row],[CUIT]],Lista_CUIT[#All],4,0)),"CUIT NO CARGADO") -> 0
B14: 45019 | C14: 1 | D14: 2 | E14: 261 | F14: 20284880049 | G14: =IFERROR(IF(compras_mes1[[#This Row],[CUIT]]="","-",VLOOKUP(compras_mes1[[#This Row],[CUIT]],Lista_CUIT[#All],2,0)),"CUIT NO CARGADO") -> MOROLDO EMILIANO DANIEL | H14: 2361.4 | I14: 77.79 | K14: 209.05 | P14: =SUM(compras_mes1[[#This Row],[NETO GRAVADO]:[Otros / No Grav.]]) -> 2648.24 | Q14: =IFERROR(IF(compras_mes1[[#This Row],[CUIT]]="","-",VLOOKUP(compras_mes1[[#This Row],[CUIT]],Lista_CUIT[#All],3,0)),"CUIT NO CARGADO") -> Electronica | R14: =IFERROR(IF(compras_mes1[[#This Row],[CUIT]]="","-",VLOOKUP(compras_mes1[[#This Row],[CUIT]],Lista_CUIT[#All],4,0)),"CUIT NO CARGADO") -> 0
B15: 45020 | C15: 1 | D15: 50 | E15: 27861 | F15: 30710730845 | G15: =IFERROR(IF(compras_mes1[[#This Row],[CUIT]]="","-",VLOOKUP(compras_mes1[[#This Row],[CUIT]],Lista_CUIT[#All],2,0)),"CUIT NO CARGADO") -> D LED SOCIEDAD DE HECHO DE DIEGO NICOLAS BARSKY Y DAMIAN DANEL SPIVAK | H15: 3059.55 | I15: =compras_mes1[[#This Row],[NETO GRAVADO]]*0.21 -> 642.5055 | P15: =SUM(compras_mes1[[#This Row],[NETO GRAVADO]:[Otros / No Grav.]]) -> 3702.0555 | Q15: =IFERROR(IF(compras_mes1[[#This Row],[CUIT]]="","-",VLOOKUP(compras_mes1[[#This Row],[CUIT]],Lista_CUIT[#All],3,0)),"CUIT NO CARGADO") -> Electronica | R15: =IFERROR(IF(compras_mes1[[#This Row],[CUIT]]="","-",VLOOKUP(compras_mes1[[#This Row],[CUIT]],Lista_CUIT[#All],4,0)),"CUIT NO CARGADO") -> 0
B16: 45021 | C16: 1 | D16: 7 | E16: 3972 | F16: 30709788635 | G16: =IFERROR(IF(compras_mes1[[#This Row],[CUIT]]="","-",VLOOKUP(compras_mes1[[#This Row],[CUIT]],Lista_CUIT[#All],2,0)),"CUIT NO CARGADO") -> EMELINT S.R.L. | H16: 7230.05 | K16: 759.16 | P16: =SUM(compras_mes1[[#This Row],[NETO GRAVADO]:[Otros / No Grav.]]) -> 7989.21 | Q16: =IFERROR(IF(compras_mes1[[#This Row],[CUIT]]="","-",VLOOKUP(compras_mes1[[#This Row],[CUIT]],Lista_CUIT[#All],3,0)),"CUIT NO CARGADO") -> Electronica | R16: =IFERROR(IF(compras_mes1[[#This Row],[CUIT]]="","-",VLOOKUP(compras_mes1[[#This Row],[CUIT]],Lista_CUIT[#All],4,0)),"CUIT NO CARGADO") -> 0
B17: 45046 | C17: 1 | D17: 1 | E17: 308 | F17: 30715060759 | G17: =IFERROR(IF(compras_mes1[[#This Row],[CUIT]]="","-",VLOOKUP(compras_mes1[[#This Row],[CUIT]],Lista_CUIT[#All],2,0)),"CUIT NO CARGADO") -> BIRD COMERCIALIZACION IMPORTACION Y SERVICIOS S.R.L. | H17: 5650.43 | I17: =compras_mes1[[#This Row],[NETO GRAVADO]]*0.21 -> 1186.5903 | P17: =SUM(compras_mes1[[#This Row],[NETO GRAVADO]:[Otros / No Grav.]]) -> 6837.0203 | Q17: =IFERROR(IF(compras_mes1[[#This Row],[CUIT]]="","-",VLOOKUP(compras_mes1[[#This Row],[CUIT]],Lista_CUIT[#All],3,0)),"CUIT NO CARGADO") -> Electronica | R17: =IFERROR(IF(compras_mes1[[#This Row],[CUIT]]="","-",VLOOKUP(compras_mes1[[#This Row],[CUIT]],Lista_CUIT[#All],4,0)),"CUIT NO CARGADO") -> 0
B18: 45017 | C18: 1 | D18: 3 | E18: 635 | F18: 30715402765 | G18: =IFERROR(IF(compras_mes1[[#This Row],[CUIT]]="","-",VLOOKUP(compras_mes1[[#This Row],[CUIT]],Lista_CUIT[#All],2,0)),"CUIT NO CARGADO") -> RIO 265 S.R.L. | H18: 12809.9 | I18: =compras_mes1[[#This Row],[NETO GRAVADO]]*0.21 -> 2690.079 | P18: =SUM(compras_mes1[[#This Row],[NETO GRAVADO]:[Otros / No Grav.]]) -> 15499.979 | Q18: =IFERROR(IF(compras_mes1[[#This Row],[CUIT]]="","-",VLOOKUP(compras_mes1[[#This Row],[CUIT]],Lista_CUIT[#All],3,0)),"CUIT NO CARGADO") -> Gastos Varios | R18: =IFERROR(IF(compras_mes1[[#This Row],[CUIT]]="","-",VLOOKUP(compras_mes1[[#This Row],[CUIT]],Lista_CUIT[#All],4,0)),"CUIT NO CARGADO") -> 0
B19: 45019 | C19: 1 | D19: 5 | E19: 1990 | F19: 20309151489 | G19: =IFERROR(IF(compras_mes1[[#This Row],[CUIT]]="","-",VLOOKUP(compras_mes1[[#This Row],[CUIT]],Lista_CUIT[#All],2,0)),"CUIT NO CARGADO") -> GOMEZ FERNANDO ALBERTO | H19: 1206.61 | I19: =compras_mes1[[#This Row],[NETO GRAVADO]]*0.21 -> 253.3881 | P19: =SUM(compras_mes1[[#This Row],[NETO GRAVADO]:[Otros / No Grav.]]) -> 1459.9981 | Q19: =IFERROR(IF(compras_mes1[[#This Row],[CUIT]]="","-",VLOOKUP(compras_mes1[[#This Row],[CUIT]],Lista_CUIT[#All],3,0)),"CUIT NO CARGADO") -> Gastos Varios | R19: =IFERROR(IF(compras_mes1[[#This Row],[CUIT]]="","-",VLOOKUP(compras_mes1[[#This Row],[CUIT]],Lista_CUIT[#All],4,0)),"CUIT NO CARGADO") -> 0
B20: 45019 | C20: 1 | D20: 1 | E20: 2045 | F20: 20299039367 | G20: =IFERROR(IF(compras_mes1[[#This Row],[CUIT]]="","-",VLOOKUP(compras_mes1[[#This Row],[CUIT]],Lista_CUIT[#All],2,0)),"CUIT NO CARGADO") -> SIRTAUTAS ALBERTO IVAN | H20: 11860.53 | I20: 2263.02 | K20: 113.85 | P20: =SUM(compras_mes1[[#This Row],[NETO GRAVADO]:[Otros / No Grav.]]) -> 14237.4 | Q20: =IFERROR(IF(compras_mes1[[#This Row],[CUIT]]="","-",VLOOKUP(compras_mes1[[#This Row],[CUIT]],Lista_CUIT[#All],3,0)),"CUIT NO CARGADO") -> Gastos Varios | R20: =IFERROR(IF(compras_mes1[[#This Row],[CUIT]]="","-",VLOOKUP(compras_mes1[[#This Row],[CUIT]],Lista_CUIT[#All],4,0)),"CUIT NO CARGADO") -> 0
B21: 45020 | C21: 1 | D21: 5 | E21: 4539 | F21: 27217954369 | G21: =IFERROR(IF(compras_mes1[[#This Row],[CUIT]]="","-",VLOOKUP(compras_mes1[[#This Row],[CUIT]],Lista_CUIT[#All],2,0)),"CUIT NO CARGADO") -> FIGUEIRAS KARINA BEATRIZ | H21: 1287.6 | I21: =compras_mes1[[#This Row],[NETO GRAVADO]]*0.21 -> 270.396 | P21: =SUM(compras_mes1[[#This Row],[NETO GRAVADO]:[Otros / No Grav.]]) -> 1557.996 | Q21: =IFERROR(IF(compras_mes1[[#This Row],[CUIT]]="","-",VLOOKUP(compras_mes1[[#This Row],[CUIT]],Lista_CUIT[#All],3,0)),"CUIT NO CARGADO") -> Gastos Varios | R21: =IFERROR(IF(compras_mes1[[#This Row],[CUIT]]="","-",VLOOKUP(compras_mes1[[#This Row],[CUIT]],Lista_CUIT[#All],4,0)),"CUIT NO CARGADO") -> 0
B22: 45020 | C22: 1 | D22: 3 | E22: 22637 | F22: 30709511846 | G22: =IFERROR(IF(compras_mes1[[#This Row],[CUIT]]="","-",VLOOKUP(compras_mes1[[#This Row],[CUIT]],Lista_CUIT[#All],2,0)),"CUIT NO CARGADO") -> KURIABE S. A. | H22: 8196.39 | K22: 860.62 | P22: =SUM(compras_mes1[[#This Row],[NETO GRAVADO]:[Otros / No Grav.]]) -> 9057.01 | Q22: =IFERROR(IF(compras_mes1[[#This Row],[CUIT]]="","-",VLOOKUP(compras_mes1[[#This Row],[CUIT]],Lista_CUIT[#All],3,0)),"CUIT NO CARGADO") -> Gastos Varios | R22: =IFERROR(IF(compras_mes1[[#This Row],[CUIT]]="","-",VLOOKUP(compras_mes1[[#This Row],[CUIT]],Lista_CUIT[#All],4,0)),"CUIT NO CARGADO") -> 0
B23: 45020 | C23: 1 | D23: 3 | E23: 2360 | F23: 20319700081 | G23: =IFERROR(IF(compras_mes1[[#This Row],[CUIT]]="","-",VLOOKUP(compras_mes1[[#This Row],[CUIT]],Lista_CUIT[#All],2,0)),"CUIT NO CARGADO") -> REA PABLO | H23: 10037.19 | K23: 1053.91 | P23: =SUM(compras_mes1[[#This Row],[NETO GRAVADO]:[Otros / No Grav.]]) -> 11091.1 | Q23: =IFERROR(IF(compras_mes1[[#This Row],[CUIT]]="","-",VLOOKUP(compras_mes1[[#This Row],[CUIT]],Lista_CUIT[#All],3,0)),"CUIT NO CARGADO") -> Gastos Varios | R23: =IFERROR(IF(compras_mes1[[#This Row],[CUIT]]="","-",VLOOKUP(compras_mes1[[#This Row],[CUIT]],Lista_CUIT[#All],4,0)),"CUIT NO CARGADO") -> 0
B24: 45023 | C24: 1 | D24: 7 | E24: 1727 | F24: 20278028810 | G24: =IFERROR(IF(compras_mes1[[#This Row],[CUIT]]="","-",VLOOKUP(compras_mes1[[#This Row],[CUIT]],Lista_CUIT[#All],2,0)),"CUIT NO CARGADO") -> PONCE JUAN MANUEL | H24: 1454.55 | I24: =compras_mes1[[#This Row],[NETO GRAVADO]]*0.21 -> 305.4555 | P24: =SUM(compras_mes1[[#This Row],[NETO GRAVADO]:[Otros / No Grav.]]) -> 1760.0055 | Q24: =IFERROR(IF(compras_mes1[[#This Row],[CUIT]]="","-",VLOOKUP(compras_mes1[[#This Row],[CUIT]],Lista_CUIT[#All],3,0)),"CUIT NO CARGADO") -> Gastos Varios | R24: =IFERROR(IF(compras_mes1[[#This Row],[CUIT]]="","-",VLOOKUP(compras_mes1[[#This Row],[CUIT]],Lista_CUIT[#All],4,0)),"CUIT NO CARGADO") -> 0
B25: 45028 | C25: 1 | D25: 5 | E25: 312 | F25: 20247551337 | G25: =IFERROR(IF(compras_mes1[[#This Row],[CUIT]]="","-",VLOOKUP(compras_mes1[[#This Row],[CUIT]],Lista_CUIT[#All],2,0)),"CUIT NO CARGADO") -> HERRERO ANZORENA MATIAS | H25: 705.65 | I25: =compras_mes1[[#This Row],[NETO GRAVADO]]*0.21 -> 148.1865 | P25: =SUM(compras_mes1[[#This Row],[NETO GRAVADO]:[Otros / No Grav.]]) -> 853.8365 | Q25: =IFERROR(IF(compras_mes1[[#This Row],[CUIT]]="","-",VLOOKUP(compras_mes1[[#This Row],[CUIT]],Lista_CUIT[#All],3,0)),"CUIT NO CARGADO") -> Gastos Varios | R25: =IFERROR(IF(compras_mes1[[#This Row],[CUIT]]="","-",VLOOKUP(compras_mes1[[#This Row],[CUIT]],Lista_CUIT[#All],4,0)),"CUIT NO CARGADO") -> 0
B26: 45029 | C26: 1 | D26: 9 | E26: 73503 | F26: 33715571639 | G26: =IFERROR(IF(compras_mes1[[#This Row],[CUIT]]="","-",VLOOKUP(compras_mes1[[#This Row],[CUIT]],Lista_CUIT[#All],2,0)),"CUIT NO CARGADO") -> DUAITEK SRL | H26: 4463.62 | I26: 94.13 | K26: 421.61 | P26: =SUM(compras_mes1[[#This Row],[NETO GRAVADO]:[Otros / No Grav.]]) -> 4979.36 | Q26: =IFERROR(IF(compras_mes1[[#This Row],[CUIT]]="","-",VLOOKUP(compras_mes1[[#This Row],[CUIT]],Lista_CUIT[#All],3,0)),"CUIT NO CARGADO") -> Gastos Varios | R26: =IFERROR(IF(compras_mes1[[#This Row],[CUIT]]="","-",VLOOKUP(compras_mes1[[#This Row],[CUIT]],Lista_CUIT[#All],4,0)),"CUIT NO CARGADO") -> 0
B27: 45038 | C27: 1 | D27: 3 | E27: 1394130 | F27: 30712019359 | G27: =IFERROR(IF(compras_mes1[[#This Row],[CUIT]]="","-",VLOOKUP(compras_mes1[[#This Row],[CUIT]],Lista_CUIT[#All],2,0)),"CUIT NO CARGADO") -> LINKEDSTORE ARGENTINA S.R.L. | H27: 6032.23 | I27: =compras_mes1[[#This Row],[NETO GRAVADO]]*0.21 -> 1266.7683 | P27: =SUM(compras_mes1[[#This Row],[NETO GRAVADO]:[Otros / No Grav.]]) -> 7298.9983 | Q27: =IFERROR(IF(compras_mes1[[#This Row],[CUIT]]="","-",VLOOKUP(compras_mes1[[#This Row],[CUIT]],Lista_CUIT[#All],3,0)),"CUIT NO CARGADO") -> Gastos Varios | R27: =IFERROR(IF(compras_mes1[[#This Row],[CUIT]]="","-",VLOOKUP(compras_mes1[[#This Row],[CUIT]],Lista_CUIT[#All],4,0)),"CUIT NO CARGADO") -> 0
B28: 45019 | C28: 1 | D28: 106 | E28: 620759 | F28: 30594494187 | G28: =IFERROR(IF(compras_mes1[[#This Row],[CUIT]]="","-",VLOOKUP(compras_mes1[[#This Row],[CUIT]],Lista_CUIT[#All],2,0)),"CUIT NO CARGADO") -> FEDERAL EXPRESS CORPORATION | H28: 12441 | I28: =compras_mes1[[#This Row],[NETO GRAVADO]]*0.21 -> 2612.61 | O28: 4648.57 | P28: =SUM(compras_mes1[[#This Row],[NETO GRAVADO]:[Otros / No Grav.]]) -> 19702.18 | Q28: =IFERROR(IF(compras_mes1[[#This Row],[CUIT]]="","-",VLOOKUP(compras_mes1[[#This Row],[CUIT]],Lista_CUIT[#All],3,0)),"CUIT NO CARGADO") -> Gtos. Imp. | R28: =IFERROR(IF(compras_mes1[[#This Row],[CUIT]]="","-",VLOOKUP(compras_mes1[[#This Row],[CUIT]],Lista_CUIT[#All],4,0)),"CUIT NO CARGADO") -> 0
B29: 45025 | C29: 1 | D29: 280 | E29: 1424766 | F29: 30580111315 | G29: =IFERROR(IF(compras_mes1[[#This Row],[CUIT]]="","-",VLOOKUP(compras_mes1[[#This Row],[CUIT]],Lista_CUIT[#All],2,0)),"CUIT NO CARGADO") -> DHL EXPRESS (ARGENTINA) S.A. | H29: 228954.03 | I29: =compras_mes1[[#This Row],[NETO GRAVADO]]*0.21 -> 48080.347 | O29: -187073.32 | P29: =SUM(compras_mes1[[#This Row],[NETO GRAVADO]:[Otros / No Grav.]]) -> 89961.058 | Q29: =IFERROR(IF(compras_mes1[[#This Row],[CUIT]]="","-",VLOOKUP(compras_mes1[[#This Row],[CUIT]],Lista_CUIT[#All],3,0)),"CUIT NO CARGADO") -> Gtos. Imp. | R29: =IFERROR(IF(compras_mes1[[#This Row],[CUIT]]="","-",VLOOKUP(compras_mes1[[#This Row],[CUIT]],Lista_CUIT[#All],4,0)),"CUIT NO CARGADO") -> 0
B30: 45026 | C30: 1 | D30: 700 | E30: 508046 | F30: 30580111315 | G30: =IFERROR(IF(compras_mes1[[#This Row],[CUIT]]="","-",VLOOKUP(compras_mes1[[#This Row],[CUIT]],Lista_CUIT[#All],2,0)),"CUIT NO CARGADO") -> DHL EXPRESS (ARGENTINA) S.A. | H30: 0 | I30: =compras_mes1[[#This Row],[NETO GRAVADO]]*0.21 -> 0 | O30: 41814.345 | P30: =SUM(compras_mes1[[#This Row],[NETO GRAVADO]:[Otros / No Grav.]]) -> 41814.345 | Q30: =IFERROR(IF(compras_mes1[[#This Row],[CUIT]]="","-",VLOOKUP(compras_mes1[[#This Row],[CUIT]],Lista_CUIT[#All],3,0)),"CUIT NO CARGADO") -> Gtos. Imp. | R30: =IFERROR(IF(compras_mes1[[#This Row],[CUIT]]="","-",VLOOKUP(compras_mes1[[#This Row],[CUIT]],Lista_CUIT[#All],4,0)),"CUIT NO CARGADO") -> 0
B31: 45033 | C31: 1 | D31: 700 | E31: 510209 | F31: 30580111315 | G31: =IFERROR(IF(compras_mes1[[#This Row],[CUIT]]="","-",VLOOKUP(compras_mes1[[#This Row],[CUIT]],Lista_CUIT[#All],2,0)),"CUIT NO CARGADO") -> DHL EXPRESS (ARGENTINA) S.A. | H31: 3094 | I31: =compras_mes1[[#This Row],[NETO GRAVADO]]*0.21 -> 649.74 | O31: 92435.46 | P31: =SUM(compras_mes1[[#This Row],[NETO GRAVADO]:[Otros / No Grav.]]) -> 96179.2 | Q31: =IFERROR(IF(compras_mes1[[#This Row],[CUIT]]="","-",VLOOKUP(compras_mes1[[#This Row],[CUIT]],Lista_CUIT[#All],3,0)),"CUIT NO CARGADO") -> Gtos. Imp. | R31: =IFERROR(IF(compras_mes1[[#This Row],[CUIT]]="","-",VLOOKUP(compras_mes1[[#This Row],[CUIT]],Lista_CUIT[#All],4,0)),"CUIT NO CARGADO") -> 0
B32: 45033 | C32: 1 | D32: 280 | E32: 1425945 | F32: 30580111315 | G32: =IFERROR(IF(compras_mes1[[#This Row],[CUIT]]="","-",VLOOKUP(compras_mes1[[#This Row],[CUIT]],Lista_CUIT[#All],2,0)),"CUIT NO CARGADO") -> DHL EXPRESS (ARGENTINA) S.A. | H32: 229044.93 | I32: =compras_mes1[[#This Row],[NETO GRAVADO]]*0.21 -> 48099.436 | O32: -187050.96 | P32: =SUM(compras_mes1[[#This Row],[NETO GRAVADO]:[Otros / No Grav.]]) -> 90093.409 | Q32: =IFERROR(IF(compras_mes1[[#This Row],[CUIT]]="","-",VLOOKUP(compras_mes1[[#This Row],[CUIT]],Lista_CUIT[#All],3,0)),"CUIT NO CARGADO") -> Gtos. Imp. | R32: =IFERROR(IF(compras_mes1[[#This Row],[CUIT]]="","-",VLOOKUP(compras_mes1[[#This Row],[CUIT]],Lista_CUIT[#All],4,0)),"CUIT NO CARGADO") -> 0
B33: 45037 | C33: 1 | D33: 106 | E33: 625357 | F33: 30594494187 | G33: =IFERROR(IF(compras_mes1[[#This Row],[CUIT]]="","-",VLOOKUP(compras_mes1[[#This Row],[CUIT]],Lista_CUIT[#All],2,0)),"CUIT NO CARGADO") -> FEDERAL EXPRESS CORPORATION | H33: 16092 | I33: =compras_mes1[[#This Row],[NETO GRAVADO]]*0.21 -> 3379.32 | O33: 81504.98 | P33: =SUM(compras_mes1[[#This Row],[NETO GRAVADO]:[Otros / No Grav.]]) -> 100976.3 | Q33: =IFERROR(IF(compras_mes1[[#This Row],[CUIT]]="","-",VLOOKUP(compras_mes1[[#This Row],[CUIT]],Lista_CUIT[#All],3,0)),"CUIT NO CARGADO") -> Gtos. Imp. | R33: =IFERROR(IF(compras_mes1[[#This Row],[CUIT]]="","-",VLOOKUP(compras_mes1[[#This Row],[CUIT]],Lista_CUIT[#All],4,0)),"CUIT NO CARGADO") -> 0
B34: 45040 | C34: 1 | D34: 700 | E34: 512833 | F34: 30580111315 | G34: =IFERROR(IF(compras_mes1[[#This Row],[CUIT]]="","-",VLOOKUP(compras_mes1[[#This Row],[CUIT]],Lista_CUIT[#All],2,0)),"CUIT NO CARGADO") -> DHL EXPRESS (ARGENTINA) S.A. | H34: 3150 | I34: =compras_mes1[[#This Row],[NETO GRAVADO]]*0.21 -> 661.5 | O34: 155160 | P34: =SUM(compras_mes1[[#This Row],[NETO GRAVADO]:[Otros / No Grav.]]) -> 158971.5 | Q34: =IFERROR(IF(compras_mes1[[#This Row],[CUIT]]="","-",VLOOKUP(compras_mes1[[#This Row],[CUIT]],Lista_CUIT[#All],3,0)),"CUIT NO CARGADO") -> Gtos. Imp. | R34: =IFERROR(IF(compras_mes1[[#This Row],[CUIT]]="","-",VLOOKUP(compras_mes1[[#This Row],[CUIT]],Lista_CUIT[#All],4,0)),"CUIT NO CARGADO") -> 0
B35: 45040 | C35: 1 | D35: 280 | E35: 1427245 | F35: 30580111315 | G35: =IFERROR(IF(compras_mes1[[#This Row],[CUIT]]="","-",VLOOKUP(compras_mes1[[#This Row],[CUIT]],Lista_CUIT[#All],2,0)),"CUIT NO CARGADO") -> DHL EXPRESS (ARGENTINA) S.A. | H35: 241504.06 | I35: =compras_mes1[[#This Row],[NETO GRAVADO]]*0.21 -> 50715.852 | O35: -197435.3 | P35: =SUM(compras_mes1[[#This Row],[NETO GRAVADO]:[Otros / No Grav.]]) -> 94784.609 | Q35: =IFERROR(IF(compras_mes1[[#This Row],[CUIT]]="","-",VLOOKUP(compras_mes1[[#This Row],[CUIT]],Lista_CUIT[#All],3,0)),"CUIT NO CARGADO") -> Gtos. Imp. | R35: =IFERROR(IF(compras_mes1[[#This Row],[CUIT]]="","-",VLOOKUP(compras_mes1[[#This Row],[CUIT]],Lista_CUIT[#All],4,0)),"CUIT NO CARGADO") -> 0
B36: 45046 | C36: 1 | D36: 700 | E36: 516705 | F36: 30580111315 | G36: =IFERROR(IF(compras_mes1[[#This Row],[CUIT]]="","-",VLOOKUP(compras_mes1[[#This Row],[CUIT]],Lista_CUIT[#All],2,0)),"CUIT NO CARGADO") -> DHL EXPRESS (ARGENTINA) S.A. | H36: 3206 | I36: =compras_mes1[[#This Row],[NETO GRAVADO]]*0.21 -> 673.26 | O36: 128574.34 | P36: =SUM(compras_mes1[[#This Row],[NETO GRAVADO]:[Otros / No Grav.]]) -> 132453.6 | Q36: =IFERROR(IF(compras_mes1[[#This Row],[CUIT]]="","-",VLOOKUP(compras_mes1[[#This Row],[CUIT]],Lista_CUIT[#All],3,0)),"CUIT NO CARGADO") -> Gtos. Imp. | R36: =IFERROR(IF(compras_mes1[[#This Row],[CUIT]]="","-",VLOOKUP(compras_mes1[[#This Row],[CUIT]],Lista_CUIT[#All],4,0)),"CUIT NO CARGADO") -> 0
B37: 45022 | C37: 1 | D37: 6 | E37: 16511 | F37: 30714971782 | G37: =IFERROR(IF(compras_mes1[[#This Row],[CUIT]]="","-",VLOOKUP(compras_mes1[[#This Row],[CUIT]],Lista_CUIT[#All],2,0)),"CUIT NO CARGADO") -> PINTOS SCHMIDT ALDANA MARCELA Y SACK ADRIANA CRISTINA SH | H37: 1119.82 | I37: =compras_mes1[[#This Row],[NETO GRAVADO]]*0.21 -> 235.1622 | P37: =SUM(compras_mes1[[#This Row],[NETO GRAVADO]:[Otros / No Grav.]]) -> 1354.9822 | Q37: =IFERROR(IF(compras_mes1[[#This Row],[CUIT]]="","-",VLOOKUP(compras_mes1[[#This Row],[CUIT]],Lista_CUIT[#All],3,0)),"CUIT NO CARGADO") -> INSUMO | R37: =IFERROR(IF(compras_mes1[[#This Row],[CUIT]]="","-",VLOOKUP(compras_mes1[[#This Row],[CUIT]],Lista_CUIT[#All],4,0)),"CUIT NO CARGADO") -> 0
B38: 45027 | C38: 1 | D38: 2 | E38: 2385 | F38: 30709131733 | G38: =IFERROR(IF(compras_mes1[[#This Row],[CUIT]]="","-",VLOOKUP(compras_mes1[[#This Row],[CUIT]],Lista_CUIT[#All],2,0)),"CUIT NO CARGADO") -> DIGAS SRL | H38: 585234 | I38: =compras_mes1[[#This Row],[NETO GRAVADO]]*0.21 -> 122899.14 | P38: =SUM(compras_mes1[[#This Row],[NETO GRAVADO]:[Otros / No Grav.]]) -> 708133.14 | Q38: =IFERROR(IF(compras_mes1[[#This Row],[CUIT]]="","-",VLOOKUP(compras_mes1[[#This Row],[CUIT]],Lista_CUIT[#All],3,0)),"CUIT NO CARGADO") -> INSUMO | R38: =IFERROR(IF(compras_mes1[[#This Row],[CUIT]]="","-",VLOOKUP(compras_mes1[[#This Row],[CUIT]],Lista_CUIT[#All],4,0)),"CUIT NO CARGADO") -> 0
B39: 45027 | C39: 1 | D39: 9 | E39: 1554 | F39: 30631047145 | G39: =IFERROR(IF(compras_mes1[[#This Row],[CUIT]]="","-",VLOOKUP(compras_mes1[[#This Row],[CUIT]],Lista_CUIT[#All],2,0)),"CUIT NO CARGADO") -> SEMICONDUC. Y COMPON. SRL | H39: 164230 | I39: 9632.7 | K39: 12427.8 | P39: =SUM(compras_mes1[[#This Row],[NETO GRAVADO]:[Otros / No Grav.]]) -> 186290.5 | Q39: =IFERROR(IF(compras_mes1[[#This Row],[CUIT]]="","-",VLOOKUP(compras_mes1[[#This Row],[CUIT]],Lista_CUIT[#All],3,0)),"CUIT NO CARGADO") -> INSUMO | R39: =IFERROR(IF(compras_mes1[[#This Row],[CUIT]]="","-",VLOOKUP(compras_mes1[[#This Row],[CUIT]],Lista_CUIT[#All],4,0)),"CUIT NO CARGADO") -> 0
B40: 45028 | C40: 1 | D40: 2 | E40: 165 | F40: 20125142851 | G40: =IFERROR(IF(compras_mes1[[#This Row],[CUIT]]="","-",VLOOKUP(compras_mes1[[#This Row],[CUIT]],Lista_CUIT[#All],2,0)),"CUIT NO CARGADO") -> FEDERICI NICOLAS JOSE | H40: 10150.81 | I40: =compras_mes1[[#This Row],[NETO GRAVADO]]*0.21 -> 2131.6701 | P40: =SUM(compras_mes1[[#This Row],[NETO GRAVADO]:[Otros / No Grav.]]) -> 12282.48 | Q40: =IFERROR(IF(compras_mes1[[#This Row],[CUIT]]="","-",VLOOKUP(compras_mes1[[#This Row],[CUIT]],Lista_CUIT[#All],3,0)),"CUIT NO CARGADO") -> INSUMO | R40: =IFERROR(IF(compras_mes1[[#This Row],[CUIT]]="","-",VLOOKUP(compras_mes1[[#This Row],[CUIT]],Lista_CUIT[#All],4,0)),"CUIT NO CARGADO") -> 0
B41: 45028 | C41: 1 | D41: 2 | E41: 555 | F41: 30717334384 | G41: =IFERROR(IF(compras_mes1[[#This Row],[CUIT]]="","-",VLOOKUP(compras_mes1[[#This Row],[CUIT]],Lista_CUIT[#All],2,0)),"CUIT NO CARGADO") -> OLIVEAR S. R. L. | H41: 11320.66 | I41: =compras_mes1[[#This Row],[NETO GRAVADO]]*0.21 -> 2377.3386 | P41: =SUM(compras_mes1[[#This Row],[NETO GRAVADO]:[Otros / No Grav.]]) -> 13697.999 | Q41: =IFERROR(IF(compras_mes1[[#This Row],[CUIT]]="","-",VLOOKUP(compras_mes1[[#This Row],[CUIT]],Lista_CUIT[#All],3,0)),"CUIT NO CARGADO") -> INSUMO | R41: =IFERROR(IF(compras_mes1[[#This Row],[CUIT]]="","-",VLOOKUP(compras_mes1[[#This Row],[CUIT]],Lista_CUIT[#All],4,0)),"CUIT NO CARGADO") -> 0
B42: 45035 | C42: 1 | D42: 2 | E42: 166 | F42: 20125142851 | G42: =IFERROR(IF(compras_mes1[[#This Row],[CUIT]]="","-",VLOOKUP(compras_mes1[[#This Row],[CUIT]],Lista_CUIT[#All],2,0)),"CUIT NO CARGADO") -> FEDERICI NICOLAS JOSE | H42: 42633.38 | I42: =compras_mes1[[#This Row],[NETO GRAVADO]]*0.21 -> 8953.0098 | P42: =SUM(compras_mes1[[#This Row],[NETO GRAVADO]:[Otros / No Grav.]]) -> 51586.39 | Q42: =IFERROR(IF(compras_mes1[[#This Row],[CUIT]]="","-",VLOOKUP(compras_mes1[[#This Row],[CUIT]],Lista_CUIT[#All],3,0)),"CUIT NO CARGADO") -> INSUMO | R42: =IFERROR(IF(compras_mes1[[#This Row],[CUIT]]="","-",VLOOKUP(compras_mes1[[#This Row],[CUIT]],Lista_CUIT[#All],4,0)),"CUIT NO CARGADO") -> 0
B43: 45037 | C43: 1 | D43: 3 | E43: 7060 | F43: 30710212127 | G43: =IFERROR(IF(compras_mes1[[#This Row],[CUIT]]="","-",VLOOKUP(compras_mes1[[#This Row],[CUIT]],Lista_CUIT[#All],2,0)),"CUIT NO CARGADO") -> J Y M COMPONENTES ELECTRICOS S.A. | H43: 1810569.9 | I43: =compras_mes1[[#This Row],[NETO GRAVADO]]*0.21 -> 380219.67 | P43: =SUM(compras_mes1[[#This Row],[NETO GRAVADO]:[Otros / No Grav.]]) -> 2190789.5 | Q43: =IFERROR(IF(compras_mes1[[#This Row],[CUIT]]="","-",VLOOKUP(compras_mes1[[#This Row],[CUIT]],Lista_CUIT[#All],3,0)),"CUIT NO CARGADO") -> INSUMO | R43: =IFERROR(IF(compras_mes1[[#This Row],[CUIT]]="","-",VLOOKUP(compras_mes1[[#This Row],[CUIT]],Lista_CUIT[#All],4,0)),"CUIT NO CARGADO") -> 0
B44: 45041 | C44: 1 | D44: 2 | E44: 167 | F44: 20125142851 | G44: =IFERROR(IF(compras_mes1[[#This Row],[CUIT]]="","-",VLOOKUP(compras_mes1[[#This Row],[CUIT]],Lista_CUIT[#All],2,0)),"CUIT NO CARGADO") -> FEDERICI NICOLAS JOSE | H44: 66779.86 | I44: =compras_mes1[[#This Row],[NETO GRAVADO]]*0.21 -> 14023.771 | P44: =SUM(compras_mes1[[#This Row],[NETO GRAVADO]:[Otros / No Grav.]]) -> 80803.631 | Q44: =IFERROR(IF(compras_mes1[[#This Row],[CUIT]]="","-",VLOOKUP(compras_mes1[[#This Row],[CUIT]],Lista_CUIT[#All],3,0)),"CUIT NO CARGADO") -> INSUMO | R44: =IFERROR(IF(compras_mes1[[#This Row],[CUIT]]="","-",VLOOKUP(compras_mes1[[#This Row],[CUIT]],Lista_CUIT[#All],4,0)),"CUIT NO CARGADO") -> 0
B45: 45041 | C45: 1 | D45: 2 | E45: 168 | F45: 20125142851 | G45: =IFERROR(IF(compras_mes1[[#This Row],[CUIT]]="","-",VLOOKUP(compras_mes1[[#This Row],[CUIT]],Lista_CUIT[#All],2,0)),"CUIT NO CARGADO") -> FEDERICI NICOLAS JOSE | H45: 72262 | I45: =compras_mes1[[#This Row],[NETO GRAVADO]]*0.21 -> 15175.02 | P45: =SUM(compras_mes1[[#This Row],[NETO GRAVADO]:[Otros / No Grav.]]) -> 87437.02 | Q45: =IFERROR(IF(compras_mes1[[#This Row],[CUIT]]="","-",VLOOKUP(compras_mes1[[#This Row],[CUIT]],Lista_CUIT[#All],3,0)),"CUIT NO CARGADO") -> INSUMO | R45: =IFERROR(IF(compras_mes1[[#This Row],[CUIT]]="","-",VLOOKUP(compras_mes1[[#This Row],[CUIT]],Lista_CUIT[#All],4,0)),"CUIT NO CARGADO") -> 0
B46: 45041 | C46: 1 | D46: 2 | E46: 169 | F46: 20125142851 | G46: =IFERROR(IF(compras_mes1[[#This Row],[CUIT]]="","-",VLOOKUP(compras_mes1[[#This Row],[CUIT]],Lista_CUIT[#All],2,0)),"CUIT NO CARGADO") -> FEDERICI NICOLAS JOSE | H46: 31467.48 | I46: =compras_mes1[[#This Row],[NETO GRAVADO]]*0.21 -> 6608.1708 | P46: =SUM(compras_mes1[[#This Row],[NETO GRAVADO]:[Otros / No Grav.]]) -> 38075.651 | Q46: =IFERROR(IF(compras_mes1[[#This Row],[CUIT]]="","-",VLOOKUP(compras_mes1[[#This Row],[CUIT]],Lista_CUIT[#All],3,0)),"CUIT NO CARGADO") -> INSUMO | R46: =IFERROR(IF(compras_mes1[[#This Row],[CUIT]]="","-",VLOOKUP(compras_mes1[[#This Row],[CUIT]],Lista_CUIT[#All],4,0)),"CUIT NO CARGADO") -> 0
B47: 45017 | C47: 1 | D47: 8 | E47: 3130 | F47: 20304940019 | G47: =IFERROR(IF(compras_mes1[[#This Row],[CUIT]]="","-",VLOOKUP(compras_mes1[[#This Row],[CUIT]],Lista_CUIT[#All],2,0)),"CUIT NO CARGADO") -> LAZZARIN LIMA MARTIN IGNACIO | H47: 5525.91 | I47: 77.79 | K47: 541.32 | P47: =SUM(compras_mes1[[#This Row],[NETO GRAVADO]:[Otros / No Grav.]]) -> 6145.02 | Q47: =IFERROR(IF(compras_mes1[[#This Row],[CUIT]]="","-",VLOOKUP(compras_mes1[[#This Row],[CUIT]],Lista_CUIT[#All],3,0)),"CUIT NO CARGADO") -> Mantenimiento | R47: =IFERROR(IF(compras_mes1[[#This Row],[CUIT]]="","-",VLOOKUP(compras_mes1[[#This Row],[CUIT]],Lista_CUIT[#All],4,0)),"CUIT NO CARGADO") -> 0
B48: 45044 | C48: 1 | D48: 6 | E48: 11583 | F48: 30707756434 | G48: =IFERROR(IF(compras_mes1[[#This Row],[CUIT]]="","-",VLOOKUP(compras_mes1[[#This Row],[CUIT]],Lista_CUIT[#All],2,0)),"CUIT NO CARGADO") -> SERVICIO INTEGRAL DE LIMPIEZA SRL | H48: 30400 | I48: =compras_mes1[[#This Row],[NETO GRAVADO]]*0.21 -> 6384 | P48: =SUM(compras_mes1[[#This Row],[NETO GRAVADO]:[Otros / No Grav.]]) -> 36784 | Q48: =IFERROR(IF(compras_mes1[[#This Row],[CUIT]]="","-",VLOOKUP(compras_mes1[[#This Row],[CUIT]],Lista_CUIT[#All],3,0)),"CUIT NO CARGADO") -> Mantenimiento | R48: =IFERROR(IF(compras_mes1[[#This Row],[CUIT]]="","-",VLOOKUP(compras_mes1[[#This Row],[CUIT]],Lista_CUIT[#All],4,0)),"CUIT NO CARGADO") -> 0
B49: 45020 | C49: 1 | D49: 18 | E49: 9497 | F49: 30582605021 | G49: =IFERROR(IF(compras_mes1[[#This Row],[CUIT]]="","-",VLOOKUP(compras_mes1[[#This Row],[CUIT]],Lista_CUIT[#All],2,0)),"CUIT NO CARGADO") -> ELECTROCOMPONENTES SA | H49: 32614.94 | I49: =compras_mes1[[#This Row],[NETO GRAVADO]]*0.21 -> 6849.1374 | P49: =SUM(compras_mes1[[#This Row],[NETO GRAVADO]:[Otros / No Grav.]]) -> 39464.077 | Q49: =IFERROR(IF(compras_mes1[[#This Row],[CUIT]]="","-",VLOOKUP(compras_mes1[[#This Row],[CUIT]],Lista_CUIT[#All],3,0)),"CUIT NO CARGADO") -> Mat. Prima | R49: =IFERROR(IF(compras_mes1[[#This Row],[CUIT]]="","-",VLOOKUP(compras_mes1[[#This Row],[CUIT]],Lista_CUIT[#All],4,0)),"CUIT NO CARGADO") -> 0
B50: 45027 | C50: 1 | D50: 3 | E50: 4905 | F50: 30709665967 | G50: =IFERROR(IF(compras_mes1[[#This Row],[CUIT]]="","-",VLOOKUP(compras_mes1[[#This Row],[CUIT]],Lista_CUIT[#All],2,0)),"CUIT NO CARGADO") -> INDUSTRIAS FEMAN S.R.L. | H50: 185954 | I50: =compras_mes1[[#This Row],[NETO GRAVADO]]*0.21 -> 39050.34 | P50: =SUM(compras_mes1[[#This Row],[NETO GRAVADO]:[Otros / No Grav.]]) -> 225004.34 | Q50: =IFERROR(IF(compras_mes1[[#This Row],[CUIT]]="","-",VLOOKUP(compras_mes1[[#This Row],[CUIT]],Lista_CUIT[#All],3,0)),"CUIT NO CARGADO") -> Mat. Prima | R50: =IFERROR(IF(compras_mes1[[#This Row],[CUIT]]="","-",VLOOKUP(compras_mes1[[#This Row],[CUIT]],Lista_CUIT[#All],4,0)),"CUIT NO CARGADO") -> 0
B51: 45035 | C51: 1 | D51: 2 | E51: 612 | F51: 20296550184 | G51: =IFERROR(IF(compras_mes1[[#This Row],[CUIT]]="","-",VLOOKUP(compras_mes1[[#This Row],[CUIT]],Lista_CUIT[#All],2,0)),"CUIT NO CARGADO") -> COSTA DIEGO ALEJANDRO | H51: 172040 | I51: =compras_mes1[[#This Row],[NETO GRAVADO]]*0.21 -> 36128.4 | P51: =SUM(compras_mes1[[#This Row],[NETO GRAVADO]:[Otros / No Grav.]]) -> 208168.4 | Q51: =IFERROR(IF(compras_mes1[[#This Row],[CUIT]]="","-",VLOOKUP(compras_mes1[[#This Row],[CUIT]],Lista_CUIT[#All],3,0)),"CUIT NO CARGADO") -> Mat. Prima | R51: =IFERROR(IF(compras_mes1[[#This Row],[CUIT]]="","-",VLOOKUP(compras_mes1[[#This Row],[CUIT]],Lista_CUIT[#All],4,0)),"CUIT NO CARGADO") -> 0
B52: 45046 | C52: 1 | D52: 5 | E52: 1230 | F52: 30707397256 | G52: =IFERROR(IF(compras_mes1[[#This Row],[CUIT]]="","-",VLOOKUP(compras_mes1[[#This Row],[CUIT]],Lista_CUIT[#All],2,0)),"CUIT NO CARGADO") -> GRAFICA Y FOTOGRABADOS LA PLAZA SRL | H52: 347670 | I52: =compras_mes1[[#This Row],[NETO GRAVADO]]*0.21 -> 73010.7 | P52: =SUM(compras_mes1[[#This Row],[NETO GRAVADO]:[Otros / No Grav.]]) -> 420680.7 | Q52: =IFERROR(IF(compras_mes1[[#This Row],[CUIT]]="","-",VLOOKUP(compras_mes1[[#This Row],[CUIT]],Lista_CUIT[#All],3,0)),"CUIT NO CARGADO") -> MATERIALES | R52: =IFERROR(IF(compras_mes1[[#This Row],[CUIT]]="","-",VLOOKUP(compras_mes1[[#This Row],[CUIT]],Lista_CUIT[#All],4,0)),"CUIT NO CARGADO") -> 0
B53: 45037 | C53: 1 | D53: 24 | E53: 2624 | F53: 30535770294 | G53: =IFERROR(IF(compras_mes1[[#This Row],[CUIT]]="","-",VLOOKUP(compras_mes1[[#This Row],[CUIT]],Lista_CUIT[#All],2,0)),"CUIT NO CARGADO") -> ALAMTEC SRL | H53: 6694.23 | I53: =compras_mes1[[#This Row],[NETO GRAVADO]]*0.21 -> 1405.7883 | P53: =SUM(compras_mes1[[#This Row],[NETO GRAVADO]:[Otros / No Grav.]]) -> 8100.0183 | Q53: =IFERROR(IF(compras_mes1[[#This Row],[CUIT]]="","-",VLOOKUP(compras_mes1[[#This Row],[CUIT]],Lista_CUIT[#All],3,0)),"CUIT NO CARGADO") -> MERCADERIA | R53: =IFERROR(IF(compras_mes1[[#This Row],[CUIT]]="","-",VLOOKUP(compras_mes1[[#This Row],[CUIT]],Lista_CUIT[#All],4,0)),"CUIT NO CARGADO") -> 0 | S53: COD 5
B54: 45043 | C54: 1 | D54: 2 | E54: 4396 | F54: 27148854764 | G54: =IFERROR(IF(compras_mes1[[#This Row],[CUIT]]="","-",VLOOKUP(compras_mes1[[#This Row],[CUIT]],Lista_CUIT[#All],2,0)),"CUIT NO CARGADO") -> PAZ CLAUDIA SILVIA | H54: 1512.38 | I54: =compras_mes1[[#This Row],[NETO GRAVADO]]*0.21 -> 317.5998 | P54: =SUM(compras_mes1[[#This Row],[NETO GRAVADO]:[Otros / No Grav.]]) -> 1829.9798 | Q54: =IFERROR(IF(compras_mes1[[#This Row],[CUIT]]="","-",VLOOKUP(compras_mes1[[#This Row],[CUIT]],Lista_CUIT[#All],3,0)),"CUIT NO CARGADO") -> MERCADERIA | R54: =IFERROR(IF(compras_mes1[[#This Row],[CUIT]]="","-",VLOOKUP(compras_mes1[[#This Row],[CUIT]],Lista_CUIT[#All],4,0)),"CUIT NO CARGADO") -> 0 | S54: COD 5
B55: 45043 | C55: 1 | D55: 2 | E55: 4397 | F55: 27148854764 | G55: =IFERROR(IF(compras_mes1[[#This Row],[CUIT]]="","-",VLOOKUP(compras_mes1[[#This Row],[CUIT]],Lista_CUIT[#All],2,0)),"CUIT NO CARGADO") -> PAZ CLAUDIA SILVIA | H55: 4190.1 | I55: =compras_mes1[[#This Row],[NETO GRAVADO]]*0.21 -> 879.921 | P55: =SUM(compras_mes1[[#This Row],[NETO GRAVADO]:[Otros / No Grav.]]) -> 5070.021 | Q55: =IFERROR(IF(compras_mes1[[#This Row],[CUIT]]="","-",VLOOKUP(compras_mes1[[#This Row],[CUIT]],Lista_CUIT[#All],3,0)),"CUIT NO CARGADO") -> MERCADERIA | R55: =IFERROR(IF(compras_mes1[[#This Row],[CUIT]]="","-",VLOOKUP(compras_mes1[[#This Row],[CUIT]],Lista_CUIT[#All],4,0)),"CUIT NO CARGADO") -> 0 | S55: COD 5
B56: 45027 | C56: 1 | D56: 2466 | E56: 495978 | F56: 30678814357 | G56: =IFERROR(IF(compras_mes1[[#This Row],[CUIT]]="","-",VLOOKUP(compras_mes1[[#This Row],[CUIT]],Lista_CUIT[#All],2,0)),"CUIT NO CARGADO") -> TELEFONICA MOVILES ARG | H56: 4078 | J56: 1101.06 | L56: 122.34 | O56: 214.63 | P56: =SUM(compras_mes1[[#This Row],[NETO GRAVADO]:[Otros / No Grav.]]) -> 5516.03 | Q56: =IFERROR(IF(compras_mes1[[#This Row],[CUIT]]="","-",VLOOKUP(compras_mes1[[#This Row],[CUIT]],Lista_CUIT[#All],3,0)),"CUIT NO CARGADO") -> SERVICIOS | R56: =IFERROR(IF(compras_mes1[[#This Row],[CUIT]]="","-",VLOOKUP(compras_mes1[[#This Row],[CUIT]],Lista_CUIT[#All],4,0)),"CUIT NO CARGADO") -> 0
B57: 45017 | C57: 1 | D57: 3 | E57: 187694 | F57: 30707135596 | G57: =IFERROR(IF(compras_mes1[[#This Row],[CUIT]]="","-",VLOOKUP(compras_mes1[[#This Row],[CUIT]],Lista_CUIT[#All],2,0)),"CUIT NO CARGADO") -> CITILAN ARGENTINA S.A. | H57: 5123.55 | I57: =compras_mes1[[#This Row],[NETO GRAVADO]]*0.21 -> 1075.9455 | P57: =SUM(compras_mes1[[#This Row],[NETO GRAVADO]:[Otros / No Grav.]]) -> 6199.4955 | Q57: =IFERROR(IF(compras_mes1[[#This Row],[CUIT]]="","-",VLOOKUP(compras_mes1[[#This Row],[CUIT]],Lista_CUIT[#All],3,0)),"CUIT NO CARGADO") -> Servicios Gas, Luz, Etc | R57: =IFERROR(IF(compras_mes1[[#This Row],[CUIT]]="","-",VLOOKUP(compras_mes1[[#This Row],[CUIT]],Lista_CUIT[#All],4,0)),"CUIT NO CARGADO") -> 0
B58: Total | H58: =SUBTOTAL(109,compras_mes1[NETO GRAVADO]) -> 4526903.7 | I58: =SUBTOTAL(109,compras_mes1[IVA 21 %]) -> 917018.76 | J58: =SUBTOTAL(109,compras_mes1[IVA 27%]) -> 1101.06 | K58: =SUBTOTAL(109,compras_mes1[IVA 10,5%]) -> 16387.32 | L58: =SUBTOTAL(109,compras_mes1[PERC. IVA]) -> 122.34 | M58: =SUBTOTAL(109,compras_mes1[PERC IIBB BS AS]) -> 0 | N58: =SUBTOTAL(109,compras_mes1[PERC. IIBB CABA]) -> 0 | O58: =SUBTOTAL(109,compras_mes1[Otros / No Grav.]) -> -63715.517 | P58: =SUBTOTAL(109,compras_mes1[TOTAL]) -> 5397817.7
D63: LIQUIDACION EXTRACTOS BANCARIOS-TARJETAS
D64: FECHA | E64: NRO CPTE | F64: BANCO | G64: NETO | H64: IVA 21% | I64: IVA 10,5% | J64: RET IIBB CABA | K64: PERC IVA | L64: PERC IIBB | M64: total
D65: 45019 | E65: 102-7024 | F65: seg.permisos de embarque(Credicop) | G65: 5259.25 | H65: =extracto_banco_mes1[[#This Row],[NETO]]*0.21 -> 1104.4425 | K65: 157.78 | M65: =extracto_banco_mes1[[#This Row],[NETO]]+extracto_banco_mes1[[#This Row],[IVA 21%]]+extracto_banco_mes1[[#This Row],[IVA 10,5%]]+extracto_banco_mes1[[#This Row],[RET IIBB CABA]]+extracto_banco_mes1[[#This Row],[PERC IVA]] -> 6521.4725
D66: 45027 | E66: 102-8143 | F66: BCO CREDICOOP (LIQ C.I. MOSTRADOR) | G66: 5344 | H66: =extracto_banco_mes1[[#This Row],[NETO]]*0.21 -> 1122.24 | K66: 160.32 | M66: =extracto_banco_mes1[[#This Row],[NETO]]+extracto_banco_mes1[[#This Row],[IVA 21%]]+extracto_banco_mes1[[#This Row],[IVA 10,5%]]+extracto_banco_mes1[[#This Row],[RET IIBB CABA]]+extracto_banco_mes1[[#This Row],[PERC IVA]] -> 6626.56
D67: 45026 | E67: 825-849174 | F67: ANTIC.-FIN EXT | G67: 15841.5 | H67: =extracto_banco_mes1[[#This Row],[NETO]]*0.21 -> 3326.715 | K67: 475.25 | M67: =extracto_banco_mes1[[#This Row],[NETO]]+extracto_banco_mes1[[#This Row],[IVA 21%]]+extracto_banco_mes1[[#This Row],[IVA 10,5%]]+extracto_banco_mes1[[#This Row],[RET IIBB CABA]]+extracto_banco_mes1[[#This Row],[PERC IVA]] -> 19643.465
D68: 45008 | E68: 825-847664 | F68: ANTIC.-FIN EXT | G68: 15403.5 | H68: =extracto_banco_mes1[[#This Row],[NETO]]*0.21 -> 3234.735 | K68: 462.11 | M68: =extracto_banco_mes1[[#This Row],[NETO]]+extracto_banco_mes1[[#This Row],[IVA 21%]]+extracto_banco_mes1[[#This Row],[IVA 10,5%]]+extracto_banco_mes1[[#This Row],[RET IIBB CABA]]+extracto_banco_mes1[[#This Row],[PERC IVA]] -> 19100.345
D69: 45008 | E69: 825-847663 | F69: ANTIC.-FIN EXT | G69: 3080.7 | H69: =extracto_banco_mes1[[#This Row],[NETO]]*0.21 -> 646.947 | K69: 92.42 | M69: =extracto_banco_mes1[[#This Row],[NETO]]+extracto_banco_mes1[[#This Row],[IVA 21%]]+extracto_banco_mes1[[#This Row],[IVA 10,5%]]+extracto_banco_mes1[[#This Row],[RET IIBB CABA]]+extracto_banco_mes1[[#This Row],[PERC IVA]] -> 3820.067
D70: 45006 | E70: 1025742 | F70: seg.permisos de embarque(Credicop) | G70: 5125.5 | H70: =extracto_banco_mes1[[#This Row],[NETO]]*0.21 -> 1076.355 | K70: 153.77 | M70: =extracto_banco_mes1[[#This Row],[NETO]]+extracto_banco_mes1[[#This Row],[IVA 21%]]+extracto_banco_mes1[[#This Row],[IVA 10,5%]]+extracto_banco_mes1[[#This Row],[RET IIBB CABA]]+extracto_banco_mes1[[#This Row],[PERC IVA]] -> 6355.625
D71: 45000 | E71: 1024812 | F71: seg.permisos de embarque(Credicop) | G71: 5064 | H71: =extracto_banco_mes1[[#This Row],[NETO]]*0.21 -> 1063.44 | K71: 151.92 | M71: =extracto_banco_mes1[[#This Row],[NETO]]+extracto_banco_mes1[[#This Row],[IVA 21%]]+extracto_banco_mes1[[#This Row],[IVA 10,5%]]+extracto_banco_mes1[[#This Row],[RET IIBB CABA]]+extracto_banco_mes1[[#This Row],[PERC IVA]] -> 6279.36
D72: 45035 | E72: 53345 | F72: VISA-CREDICOOP | G72: 170 | H72: =extracto_banco_mes1[[#This Row],[NETO]]*0.21 -> 35.7 | M72: =extracto_banco_mes1[[#This Row],[NETO]]+extracto_banco_mes1[[#This Row],[IVA 21%]]+extracto_banco_mes1[[#This Row],[IVA 10,5%]]+extracto_banco_mes1[[#This Row],[RET IIBB CABA]]+extracto_banco_mes1[[#This Row],[PERC IVA]] -> 205.7
D73: 45044 | E73: 280423 | F73: EXTRACTO | G73: 8057.26 | H73: =extracto_banco_mes1[[#This Row],[NETO]]*0.21 -> 1692.0246 | K73: 123.71 | M73: =extracto_banco_mes1[[#This Row],[NETO]]+extracto_banco_mes1[[#This Row],[IVA 21%]]+extracto_banco_mes1[[#This Row],[IVA 10,5%]]+extracto_banco_mes1[[#This Row],[RET IIBB CABA]]+extracto_banco_mes1[[#This Row],[PERC IVA]] -> 9872.9946
D74: 45008 | E74: 825-847487 | F74: Anticipos - Fin Ext | G74: 15403.5 | H74: =extracto_banco_mes1[[#This Row],[NETO]]*0.21 -> 3234.735 | K74: 462.11 | M74: =extracto_banco_mes1[[#This Row],[NETO]]+extracto_banco_mes1[[#This Row],[IVA 21%]]+extracto_banco_mes1[[#This Row],[IVA 10,5%]]+extracto_banco_mes1[[#This Row],[RET IIBB CABA]]+extracto_banco_mes1[[#This Row],[PERC IVA]] -> 19100.345
D75: Total | G75: =SUBTOTAL(109,extracto_banco_mes1[NETO]) -> 78749.21 | H75: =SUBTOTAL(109,extracto_banco_mes1[IVA 21%]) -> 16537.334 | I75: =SUBTOTAL(109,extracto_banco_mes1[IVA 10,5%]) -> 0 | J75: =SUBTOTAL(109,extracto_banco_mes1[RET IIBB CABA]) -> 0 | K75: =SUBTOTAL(109,extracto_banco_mes1[PERC IVA]) -> 2239.39 | L75: =SUBTOTAL(109,extracto_banco_mes1[PERC IIBB]) -> 0
H76: TOTAL: | I76: =SUM(extracto_banco_mes1[[#Totals],[IVA 21%]:[IVA 10,5%]]) -> 16537.334 | J76: > ya esta sumado al total
D79: FACTURAS C
D80: FECHA | E80: PTO VTA | F80: FC Nº | G80: CUIT | H80: RAZON SOCIAL | I80: TOTAL | J80: TIPO DE GASTO | K80: Provincia
H81: =IFERROR(IF(factura_c_mes1[[#This Row],[CUIT]]="","-",VLOOKUP(factura_c_mes1[[#This Row],[CUIT]],Lista_CUIT[#All],2,0)),"CUIT NO CARGADO") -> - | J81: =IFERROR(IF(factura_c_mes1[[#This Row],[CUIT]]="","-",VLOOKUP(factura_c_mes1[[#This Row],[CUIT]],Lista_CUIT[#All],3,0)),"CUIT NO CARGADO") -> - | K81: =IFERROR(IF(factura_c_mes1[[#This Row],[CUIT]]="","-",VLOOKUP(factura_c_mes1[[#This Row],[CUIT]],Lista_CUIT[#All],4,0)),"CUIT NO CARGADO") -> -
D82: 45026 | E82: 4 | F82: 12 | G82: 20341462933 | H82: =IFERROR(IF(factura_c_mes1[[#This Row],[CUIT]]="","-",VLOOKUP(factura_c_mes1[[#This Row],[CUIT]],Lista_CUIT[#All],2,0)),"CUIT NO CARGADO") -> CASTIGLIONI MATIAS EZEQUIEL | I82: 590500 | J82: =IFERROR(IF(factura_c_mes1[[#This Row],[CUIT]]="","-",VLOOKUP(factura_c_mes1[[#This Row],[CUIT]],Lista_CUIT[#All],3,0)),"CUIT NO CARGADO") -> ASESORAMIENTO | K82: =IFERROR(IF(factura_c_mes1[[#This Row],[CUIT]]="","-",VLOOKUP(factura_c_mes1[[#This Row],[CUIT]],Lista_CUIT[#All],4,0)),"CUIT NO CARGADO") -> BUENOS AIRES
D83: 45026 | E83: 8 | F83: 157469 | G83: 30709953482 | H83: =IFERROR(IF(factura_c_mes1[[#This Row],[CUIT]]="","-",VLOOKUP(factura_c_mes1[[#This Row],[CUIT]],Lista_CUIT[#All],2,0)),"CUIT NO CARGADO") -> HONRE S.A | I83: 1221.95 | J83: =IFERROR(IF(factura_c_mes1[[#This Row],[CUIT]]="","-",VLOOKUP(factura_c_mes1[[#This Row],[CUIT]],Lista_CUIT[#All],3,0)),"CUIT NO CARGADO") -> Gastos Varios | K83: =IFERROR(IF(factura_c_mes1[[#This Row],[CUIT]]="","-",VLOOKUP(factura_c_mes1[[#This Row],[CUIT]],Lista_CUIT[#All],4,0)),"CUIT NO CARGADO") -> 0 | M83: Ingenieria Aplicada | N83: 590500
D84: 45028 | E84: 4 | F84: 35528 | G84: 30716998718 | H84: =IFERROR(IF(factura_c_mes1[[#This Row],[CUIT]]="","-",VLOOKUP(factura_c_mes1[[#This Row],[CUIT]],Lista_CUIT[#All],2,0)),"CUIT NO CARGADO") -> FIDO ARGENTINA SRL | I84: 18340 | J84: =IFERROR(IF(factura_c_mes1[[#This Row],[CUIT]]="","-",VLOOKUP(factura_c_mes1[[#This Row],[CUIT]],Lista_CUIT[#All],3,0)),"CUIT NO CARGADO") -> Gastos Varios | K84: =IFERROR(IF(factura_c_mes1[[#This Row],[CUIT]]="","-",VLOOKUP(factura_c_mes1[[#This Row],[CUIT]],Lista_CUIT[#All],4,0)),"CUIT NO CARGADO") -> 0 | M84: Gastos varios | N84: 19561.95
D85: 45041 | E85: 3 | F85: 50 | G85: 20403931420 | H85: =IFERROR(IF(factura_c_mes1[[#This Row],[CUIT]]="","-",VLOOKUP(factura_c_mes1[[#This Row],[CUIT]],Lista_CUIT[#All],2,0)),"CUIT NO CARGADO") -> FIORENTINO JORGE IGNACIO | I85: 148480 | J85: =IFERROR(IF(factura_c_mes1[[#This Row],[CUIT]]="","-",VLOOKUP(factura_c_mes1[[#This Row],[CUIT]],Lista_CUIT[#All],3,0)),"CUIT NO CARGADO") -> Hon. Admin. | K85: =IFERROR(IF(factura_c_mes1[[#This Row],[CUIT]]="","-",VLOOKUP(factura_c_mes1[[#This Row],[CUIT]],Lista_CUIT[#All],4,0)),"CUIT NO CARGADO") -> 0 | M85: Honorarios Admnistrativos | N85: 148480
D86: 45019 | E86: 3 | F86: 717 | G86: 20086277523 | H86: =IFERROR(IF(factura_c_mes1[[#This Row],[CUIT]]="","-",VLOOKUP(factura_c_mes1[[#This Row],[CUIT]],Lista_CUIT[#All],2,0)),"CUIT NO CARGADO") -> ESTUDIO BOTINDARI | I86: 67000 | J86: Honorario Contable | K86: =IFERROR(IF(factura_c_mes1[[#This Row],[CUIT]]="","-",VLOOKUP(factura_c_mes1[[#This Row],[CUIT]],Lista_CUIT[#All],4,0)),"CUIT NO CARGADO") -> 0 | M86: Honorarios Contables | N86: 89860
D87: 45028 | E87: 2 | F87: 200 | G87: 27173820866 | H87: =IFERROR(IF(factura_c_mes1[[#This Row],[CUIT]]="","-",VLOOKUP(factura_c_mes1[[#This Row],[CUIT]],Lista_CUIT[#All],2,0)),"CUIT NO CARGADO") -> FREIER SANDRA DANIELA | I87: 90000 | J87: Desarrollo Software | K87: =IFERROR(IF(factura_c_mes1[[#This Row],[CUIT]]="","-",VLOOKUP(factura_c_mes1[[#This Row],[CUIT]],Lista_CUIT[#All],4,0)),"CUIT NO CARGADO") -> 0 | M87: Desarrollo Software | N87: 90000
D88: 45029 | E88: 3 | F88: 723 | G88: 20086277523 | H88: =IFERROR(IF(factura_c_mes1[[#This Row],[CUIT]]="","-",VLOOKUP(factura_c_mes1[[#This Row],[CUIT]],Lista_CUIT[#All],2,0)),"CUIT NO CARGADO") -> ESTUDIO BOTINDARI | I88: 12860 | J88: Honorario Contable | K88: =IFERROR(IF(factura_c_mes1[[#This Row],[CUIT]]="","-",VLOOKUP(factura_c_mes1[[#This Row],[CUIT]],Lista_CUIT[#All],4,0)),"CUIT NO CARGADO") -> 0 | M88: Mantenimiento Sofware | N88: 373750
D89: 45021 | E89: 1 | F89: 98 | G89: 20341465134 | H89: =IFERROR(IF(factura_c_mes1[[#This Row],[CUIT]]="","-",VLOOKUP(factura_c_mes1[[#This Row],[CUIT]],Lista_CUIT[#All],2,0)),"CUIT NO CARGADO") -> ABELEDO AGUSTIN ENRIQUE | I89: 373750 | J89: Mantenimiento Sofware | K89: =IFERROR(IF(factura_c_mes1[[#This Row],[CUIT]]="","-",VLOOKUP(factura_c_mes1[[#This Row],[CUIT]],Lista_CUIT[#All],4,0)),"CUIT NO CARGADO") -> CABA | M89: Mantenimiento Oficvina | N89: 148935
D90: 45041 | E90: 2 | F90: 21 | G90: 23326777269 | H90: =IFERROR(IF(factura_c_mes1[[#This Row],[CUIT]]="","-",VLOOKUP(factura_c_mes1[[#This Row],[CUIT]],Lista_CUIT[#All],2,0)),"CUIT NO CARGADO") -> DE BONIS IGNACIO LUIS | I90: 148935 | J90: Mantenimiento Oficvina | K90: =IFERROR(IF(factura_c_mes1[[#This Row],[CUIT]]="","-",VLOOKUP(factura_c_mes1[[#This Row],[CUIT]],Lista_CUIT[#All],4,0)),"CUIT NO CARGADO") -> 0 | M90: Mantenim Materiales | N90: 128690
D91: 45043 | E91: 1 | F91: 17 | G91: 20417805878 | H91: =IFERROR(IF(factura_c_mes1[[#This Row],[CUIT]]="","-",VLOOKUP(factura_c_mes1[[#This Row],[CUIT]],Lista_CUIT[#All],2,0)),"CUIT NO CARGADO") -> FERABOLI OSPAL SANTIAGO HERNAN | I91: 128690 | J91: Mantenim Materiales | K91: =IFERROR(IF(factura_c_mes1[[#This Row],[CUIT]]="","-",VLOOKUP(factura_c_mes1[[#This Row],[CUIT]],Lista_CUIT[#All],4,0)),"CUIT NO CARGADO") -> 0 | M91: Mantenimiento Sofware | N91: 371000
D92: 45040 | E92: 2 | F92: 82 | G92: 20244271740 | H92: =IFERROR(IF(factura_c_mes1[[#This Row],[CUIT]]="","-",VLOOKUP(factura_c_mes1[[#This Row],[CUIT]],Lista_CUIT[#All],2,0)),"CUIT NO CARGADO") -> KENNEL SEBASTIAN | I92: 371000 | J92: =IFERROR(IF(factura_c_mes1[[#This Row],[CUIT]]="","-",VLOOKUP(factura_c_mes1[[#This Row],[CUIT]],Lista_CUIT[#All],3,0)),"CUIT NO CARGADO") -> Software Mantenimiento | K92: =IFERROR(IF(factura_c_mes1[[#This Row],[CUIT]]="","-",VLOOKUP(factura_c_mes1[[#This Row],[CUIT]],Lista_CUIT[#All],4,0)),"CUIT NO CARGADO") -> 0 | N92: =SUM(N83:N91) -> 1960776.9
D93: Total | I93: =SUBTOTAL(109,factura_c_mes1[TOTAL]) -> 1950776.9
B95: LIBRO IVA VENTAS | K95: =N1 -> 45017
B97: VENTAS "A"
B98: FECHA | C98: TIPO | D98: PTO VENTA | E98: Nº FACTURA | F98: CUIT | G98: RAZON SOCIAL | H98: IMPORTE NETO | I98: IVA 21% | J98: IVA 10,5% | K98: EXENTO | L98: TOTAL | M98: Provincia
B99: 45019 | C99: 1 | D99: 3 | E99: 121 | F99: 30628274327 | G99: =IFERROR(IF(venta_a_mes1[[#This Row],[CUIT]]="","-",VLOOKUP(venta_a_mes1[[#This Row],[CUIT]],Lista_CUIT[#All],2,0)),"CUIT NO CARGADO") -> AGIRA S A | H99: 4671373.5 | J99: 490494.22 | L99: =SUM(venta_a_mes1[[#This Row],[IMPORTE NETO]:[EXENTO]]) -> 5161867.7
B100: 45019 | C100: 1 | D100: 3 | E100: 122 | F100: 33717088269 | G100: =IFERROR(IF(venta_a_mes1[[#This Row],[CUIT]]="","-",VLOOKUP(venta_a_mes1[[#This Row],[CUIT]],Lista_CUIT[#All],2,0)),"CUIT NO CARGADO") -> NEXT SERVICE GNC S.R.L. | H100: 160937.7 | I100: =venta_a_mes1[[#This Row],[IMPORTE NETO]]*0.21 -> 33796.917 | L100: =SUM(venta_a_mes1[[#This Row],[IMPORTE NETO]:[EXENTO]]) -> 194734.62
B101: 45019 | C101: 1 | D101: 3 | E101: 123 | F101: 33717088269 | G101: =IFERROR(IF(venta_a_mes1[[#This Row],[CUIT]]="","-",VLOOKUP(venta_a_mes1[[#This Row],[CUIT]],Lista_CUIT[#All],2,0)),"CUIT NO CARGADO") -> NEXT SERVICE GNC S.R.L. | H101: 418020 | I101: =venta_a_mes1[[#This Row],[IMPORTE NETO]]*0.21 -> 87784.2 | L101: =SUM(venta_a_mes1[[#This Row],[IMPORTE NETO]:[EXENTO]]) -> 505804.2
B102: 45019 | C102: 1 | D102: 3 | E102: 124 | F102: 33708467699 | G102: =IFERROR(IF(venta_a_mes1[[#This Row],[CUIT]]="","-",VLOOKUP(venta_a_mes1[[#This Row],[CUIT]],Lista_CUIT[#All],2,0)),"CUIT NO CARGADO") -> COMPRESORES SERVICIO TECNICO S A | H102: 532975.5 | I102: =venta_a_mes1[[#This Row],[IMPORTE NETO]]*0.21 -> 111924.85 | L102: =SUM(venta_a_mes1[[#This Row],[IMPORTE NETO]:[EXENTO]]) -> 644900.35
B103: 45019 | C103: 1 | D103: 3 | E103: 120 | F103: 30628274327 | G103: =IFERROR(IF(venta_a_mes1[[#This Row],[CUIT]]="","-",VLOOKUP(venta_a_mes1[[#This Row],[CUIT]],Lista_CUIT[#All],2,0)),"CUIT NO CARGADO") -> AGIRA S A | H103: 84440.04 | I103: =venta_a_mes1[[#This Row],[IMPORTE NETO]]*0.21 -> 17732.408 | L103: =SUM(venta_a_mes1[[#This Row],[IMPORTE NETO]:[EXENTO]]) -> 102172.45
B104: 45044 | C104: 1 | D104: 3 | E104: 125 | F104: 27134325327 | G104: =IFERROR(IF(venta_a_mes1[[#This Row],[CUIT]]="","-",VLOOKUP(venta_a_mes1[[#This Row],[CUIT]],Lista_CUIT[#All],2,0)),"CUIT NO CARGADO") -> PEREZ EMILIA EUGENIA | H104: 262775 | I104: =venta_a_mes1[[#This Row],[IMPORTE NETO]]*0.21 -> 55182.75 | L104: =SUM(venta_a_mes1[[#This Row],[IMPORTE NETO]:[EXENTO]]) -> 317957.75
B105: 45044 | C105: 1 | D105: 3 | E105: 126 | F105: 30708844248 | G105: =IFERROR(IF(venta_a_mes1[[#This Row],[CUIT]]="","-",VLOOKUP(venta_a_mes1[[#This Row],[CUIT]],Lista_CUIT[#All],2,0)),"CUIT NO CARGADO") -> INGENIERIA GAMAR SOCIEDAD ANONIMA | H105: 1713750 | I105: =venta_a_mes1[[#This Row],[IMPORTE NETO]]*0.21 -> 359887.5 | L105: =SUM(venta_a_mes1[[#This Row],[IMPORTE NETO]:[EXENTO]]) -> 2073637.5
B106: 45019 | C106: 2 | D106: 3 | E106: 4 | F106: 30638318470 | G106: =IFERROR(IF(venta_a_mes1[[#This Row],[CUIT]]="","-",VLOOKUP(venta_a_mes1[[#This Row],[CUIT]],Lista_CUIT[#All],2,0)),"CUIT NO CARGADO") -> DELTA COMPRESION S R L | H106: 5838667.2 | I106: =venta_a_mes1[[#This Row],[IMPORTE NETO]]*0.21 -> 1226120.1 | L106: =SUM(venta_a_mes1[[#This Row],[IMPORTE NETO]:[EXENTO]]) -> 7064787.3
B107: 45036 | C107: 3 | D107: 3 | E107: 16 | F107: 30628274327 | G107: =IFERROR(IF(venta_a_mes1[[#This Row],[CUIT]]="","-",VLOOKUP(venta_a_mes1[[#This Row],[CUIT]],Lista_CUIT[#All],2,0)),"CUIT NO CARGADO") -> AGIRA S A | H107: -4671373.5 | J107: -490494.22 | L107: =SUM(venta_a_mes1[[#This Row],[IMPORTE NETO]:[EXENTO]]) -> -5161867.7
G108: =IFERROR(IF(venta_a_mes1[[#This Row],[CUIT]]="","-",VLOOKUP(venta_a_mes1[[#This Row],[CUIT]],Lista_CUIT[#All],2,0)),"CUIT NO CARGADO") -> - | I108: =venta_a_mes1[[#This Row],[IMPORTE NETO]]*0.21 -> 0 | L108: =SUM(venta_a_mes1[[#This Row],[IMPORTE NETO]:[EXENTO]]) -> 0
B109: Total | H109: =SUBTOTAL(109,venta_a_mes1[IMPORTE NETO]) -> 9011565.4 | I109: =SUBTOTAL(109,venta_a_mes1[IVA 21%]) -> 1892428.7 | J109: =SUBTOTAL(109,venta_a_mes1[IVA 10,5%]) -> 0 | K109: =SUBTOTAL(109,venta_a_mes1[EXENTO]) -> 0 | L109: =SUBTOTAL(109,venta_a_mes1[TOTAL]) -> 10903994 | M109: =SUBTOTAL(103,venta_a_mes1[Provincia]) -> 0
B111: VENTAS "B"
B112: FECHA | C112: TIPO | D112: PTO VENTA | E112: Nº FACTURA | F112: CUIT | G112: RAZON SOCIAL | H112: IMPORTE NETO | I112: IVA 21% | J112: IVA 10,5% | K112: EXENTO | L112: TOTAL | M112: Provincia
G113: =IFERROR(IF(ventas_b_mes1[[#This Row],[CUIT]]="","-",VLOOKUP(ventas_b_mes1[[#This Row],[CUIT]],Lista_CUIT[#All],2,0)),"CUIT NO CARGADO") -> -
...

Sheet May-23
B1: LIBRO IVA COMPRAS | G1: ='Abr-23'!G1:M1 -> CORITEC S. R. L. | N1: =EDATE('Abr-23'!N1,1) -> 45047
B3: TOTAL COMPRAS | G3: TOTAL CREDITO FISCAL | J3: TOTAL VENTAS NETAS | M3: TOTAL DEBITO FISCAL | P3: RESULTADO
B4: =SUM(compras_mes2[[#Totals],[NETO GRAVADO]])+extracto_banco_mes2[[#Totals],[NETO]] -> 5344969.9 | G4: =compras_mes2[[#Totals],[IVA 21 %]]+compras_mes2[[#Totals],[IVA 27%]]+compras_mes2[[#Totals],[IVA 10,5%]]+extracto_banco_mes2[[#Totals],[IVA 21%]]+extracto_banco_mes2[[#Totals],[IVA 10,5%]] -> 1119920 | J4: =venta_a_mes2[[#Totals],[IMPORTE NETO]]+ventas_b_mes2[[#Totals],[IMPORTE NETO]]+ventas_b_mes252[[#Totals],[IMPORTE NETO]] -> 13286930 | M4: =venta_a_mes2[[#Totals],[IVA 21%]]+venta_a_mes2[[#Totals],[IVA 10,5%]]+ventas_b_mes2[[#Totals],[IVA 21%]]+ventas_b_mes2[[#Totals],[IVA 10,5%]]+ventas_b_mes252[[#Totals],[IVA 21%]] -> 1647290.8 | P4: =G4-M4 -> -527370.89
B8: FECHA | C8: TIPO | D8: PTO VTA | E8: NRO. CPTE | F8: CUIT | G8: RAZON SOCIAL | H8: NETO GRAVADO | I8: IVA 21 % | J8: IVA 27% | K8: IVA 10,5% | L8: PERC. IVA | M8: PERC IIBB BS AS | N8: PERC. IIBB CABA | O8: Otros / No Grav. | P8: TOTAL | Q8: Tipo de Gasto | R8: Provincia
B9: 45063 | C9: 1 | D9: 2 | E9: 8665 | F9: 30707835563 | G9: =IFERROR(IF(compras_mes2[[#This Row],[CUIT]]="","-",VLOOKUP(compras_mes2[[#This Row],[CUIT]],Lista_CUIT[#All],2,0)),"CUIT NO CARGADO") -> SUTEL SRL | H9: 35796.69 | I9: =IF(compras_mes2[[#This Row],[NETO GRAVADO]]="","",compras_mes2[[#This Row],[NETO GRAVADO]]*0.21) -> 7517.3049 | P9: =SUM(compras_mes2[[#This Row],[NETO GRAVADO]:[Otros / No Grav.]]) -> 43313.995 | Q9: =IFERROR(IF(compras_mes2[[#This Row],[CUIT]]="","-",VLOOKUP(compras_mes2[[#This Row],[CUIT]],Lista_CUIT[#All],3,0)),"CUIT NO CARGADO") -> 0 | R9: =IFERROR(IF(compras_mes2[[#This Row],[CUIT]]="","-",VLOOKUP(compras_mes2[[#This Row],[CUIT]],Lista_CUIT[#All],4,0)),"CUIT NO CARGADO") -> 0
B10: 45064 | C10: 1 | D10: 2 | E10: 3885 | F10: 27271779289 | G10: =IFERROR(IF(compras_mes2[[#This Row],[CUIT]]="","-",VLOOKUP(compras_mes2[[#This Row],[CUIT]],Lista_CUIT[#All],2,0)),"CUIT NO CARGADO") -> BRACCO ROSANA | H10: 9600 | I10: =IF(compras_mes2[[#This Row],[NETO GRAVADO]]="","",compras_mes2[[#This Row],[NETO GRAVADO]]*0.21) -> 2016 | O10: 8832.23 | P10: =SUM(compras_mes2[[#This Row],[NETO GRAVADO]:[Otros / No Grav.]]) -> 20448.23 | Q10: =IFERROR(IF(compras_mes2[[#This Row],[CUIT]]="","-",VLOOKUP(compras_mes2[[#This Row],[CUIT]],Lista_CUIT[#All],3,0)),"CUIT NO CARGADO") -> 0 | R10: =IFERROR(IF(compras_mes2[[#This Row],[CUIT]]="","-",VLOOKUP(compras_mes2[[#This Row],[CUIT]],Lista_CUIT[#All],4,0)),"CUIT NO CARGADO") -> 0
B11: 45064 | C11: 1 | D11: 2 | E11: 11550 | F11: 30717014754 | G11: =IFERROR(IF(compras_mes2[[#This Row],[CUIT]]="","-",VLOOKUP(compras_mes2[[#This Row],[CUIT]],Lista_CUIT[#All],2,0)),"CUIT NO CARGADO") -> LITORAL TRADING SAS | H11: 4633.59 | I11: =IF(compras_mes2[[#This Row],[NETO GRAVADO]]="","",compras_mes2[[#This Row],[NETO GRAVADO]]*0.21) -> 973.0539 | P11: =SUM(compras_mes2[[#This Row],[NETO GRAVADO]:[Otros / No Grav.]]) -> 5606.6439 | Q11: =IFERROR(IF(compras_mes2[[#This Row],[CUIT]]="","-",VLOOKUP(compras_mes2[[#This Row],[CUIT]],Lista_CUIT[#All],3,0)),"CUIT NO CARGADO") -> 0 | R11: =IFERROR(IF(compras_mes2[[#This Row],[CUIT]]="","-",VLOOKUP(compras_mes2[[#This Row],[CUIT]],Lista_CUIT[#All],4,0)),"CUIT NO CARGADO") -> 0
B12: 45072 | C12: 1 | D12: 2 | E12: 8037 | F12: 30711726019 | G12: =IFERROR(IF(compras_mes2[[#This Row],[CUIT]]="","-",VLOOKUP(compras_mes2[[#This Row],[CUIT]],Lista_CUIT[#All],2,0)),"CUIT NO CARGADO") -> MAV GROUP S.A. | H12: 100050 | I12: =IF(compras_mes2[[#This Row],[NETO GRAVADO]]="","",compras_mes2[[#This Row],[NETO GRAVADO]]*0.21) -> 21010.5 | O12: 138310.26 | P12: =SUM(compras_mes2[[#This Row],[NETO GRAVADO]:[Otros / No Grav.]]) -> 259370.76 | Q12: =IFERROR(IF(compras_mes2[[#This Row],[CUIT]]="","-",VLOOKUP(compras_mes2[[#This Row],[CUIT]],Lista_CUIT[#All],3,0)),"CUIT NO CARGADO") -> 0 | R12: =IFERROR(IF(compras_mes2[[#This Row],[CUIT]]="","-",VLOOKUP(compras_mes2[[#This Row],[CUIT]],Lista_CUIT[#All],4,0)),"CUIT NO CARGADO") -> 0
B13: 45072 | C13: 1 | D13: 11 | E13: 670 | F13: 30711782997 | G13: =IFERROR(IF(compras_mes2[[#This Row],[CUIT]]="","-",VLOOKUP(compras_mes2[[#This Row],[CUIT]],Lista_CUIT[#All],2,0)),"CUIT NO CARGADO") -> GIOVO JUAN SEBASTIAN Y GIOVO JORGE DIEGO SOC. DE HECHO | H13: 14875.21 | I13: =IF(compras_mes2[[#This Row],[NETO GRAVADO]]="","",compras_mes2[[#This Row],[NETO GRAVADO]]*0.21) -> 3123.7941 | P13: =SUM(compras_mes2[[#This Row],[NETO GRAVADO]:[Otros / No Grav.]]) -> 17999.004 | Q13: =IFERROR(IF(compras_mes2[[#This Row],[CUIT]]="","-",VLOOKUP(compras_mes2[[#This Row],[CUIT]],Lista_CUIT[#All],3,0)),"CUIT NO CARGADO") -> 0 | R13: =IFERROR(IF(compras_mes2[[#This Row],[CUIT]]="","-",VLOOKUP(compras_mes2[[#This Row],[CUIT]],Lista_CUIT[#All],4,0)),"CUIT NO CARGADO") -> 0
B14: 45073 | C14: 1 | D14: 3 | E14: 199 | F14: 30716036711 | G14: =IFERROR(IF(compras_mes2[[#This Row],[CUIT]]="","-",VLOOKUP(compras_mes2[[#This Row],[CUIT]],Lista_CUIT[#All],2,0)),"CUIT NO CARGADO") -> POTENZA SHOP S.A.S. | H14: 10735.54 | I14: =IF(compras_mes2[[#This Row],[NETO GRAVADO]]="","",compras_mes2[[#This Row],[NETO GRAVADO]]*0.21) -> 2254.4634 | P14: =SUM(compras_mes2[[#This Row],[NETO GRAVADO]:[Otros / No Grav.]]) -> 12990.003 | Q14: =IFERROR(IF(compras_mes2[[#This Row],[CUIT]]="","-",VLOOKUP(compras_mes2[[#This Row],[CUIT]],Lista_CUIT[#All],3,0)),"CUIT NO CARGADO") -> 0 | R14: =IFERROR(IF(compras_mes2[[#This Row],[CUIT]]="","-",VLOOKUP(compras_mes2[[#This Row],[CUIT]],Lista_CUIT[#All],4,0)),"CUIT NO CARGADO") -> 0
B15: 45073 | C15: 1 | D15: 5 | E15: 977 | F15: 23287538839 | G15: =IFERROR(IF(compras_mes2[[#This Row],[CUIT]]="","-",VLOOKUP(compras_mes2[[#This Row],[CUIT]],Lista_CUIT[#All],2,0)),"CUIT NO CARGADO") -> MEIJOMIN PABLO MARTIN | H15: 7914.05 | I15: =IF(compras_mes2[[#This Row],[NETO GRAVADO]]="","",compras_mes2[[#This Row],[NETO GRAVADO]]*0.21) -> 1661.9505 | P15: =SUM(compras_mes2[[#This Row],[NETO GRAVADO]:[Otros / No Grav.]]) -> 9576.0005 | Q15: =IFERROR(IF(compras_mes2[[#This Row],[CUIT]]="","-",VLOOKUP(compras_mes2[[#This Row],[CUIT]],Lista_CUIT[#All],3,0)),"CUIT NO CARGADO") -> 0 | R15: =IFERROR(IF(compras_mes2[[#This Row],[CUIT]]="","-",VLOOKUP(compras_mes2[[#This Row],[CUIT]],Lista_CUIT[#All],4,0)),"CUIT NO CARGADO") -> 0
B16: 45074 | C16: 1 | D16: 7 | E16: 1503 | F16: 30716401525 | G16: =IFERROR(IF(compras_mes2[[#This Row],[CUIT]]="","-",VLOOKUP(compras_mes2[[#This Row],[CUIT]],Lista_CUIT[#All],2,0)),"CUIT NO CARGADO") -> SPOT VISION S.A.S. | H16: 40380.17 | I16: =IF(compras_mes2[[#This Row],[NETO GRAVADO]]="","",compras_mes2[[#This Row],[NETO GRAVADO]]*0.21) -> 8479.8357 | P16: =SUM(compras_mes2[[#This Row],[NETO GRAVADO]:[Otros / No Grav.]]) -> 48860.006 | Q16: =IFERROR(IF(compras_mes2[[#This Row],[CUIT]]="","-",VLOOKUP(compras_mes2[[#This Row],[CUIT]],Lista_CUIT[#All],3,0)),"CUIT NO CARGADO") -> 0 | R16: =IFERROR(IF(compras_mes2[[#This Row],[CUIT]]="","-",VLOOKUP(compras_mes2[[#This Row],[CUIT]],Lista_CUIT[#All],4,0)),"CUIT NO CARGADO") -> 0
B17: 45075 | C17: 1 | D17: 4 | E17: 496 | F17: 30716809893 | G17: =IFERROR(IF(compras_mes2[[#This Row],[CUIT]]="","-",VLOOKUP(compras_mes2[[#This Row],[CUIT]],Lista_CUIT[#All],2,0)),"CUIT NO CARGADO") -> BROCATTO SRL | H17: 6444.63 | I17: =IF(compras_mes2[[#This Row],[NETO GRAVADO]]="","",compras_mes2[[#This Row],[NETO GRAVADO]]*0.21) -> 1353.3723 | P17: =SUM(compras_mes2[[#This Row],[NETO GRAVADO]:[Otros / No Grav.]]) -> 7798.0023 | Q17: =IFERROR(IF(compras_mes2[[#This Row],[CUIT]]="","-",VLOOKUP(compras_mes2[[#This Row],[CUIT]],Lista_CUIT[#All],3,0)),"CUIT NO CARGADO") -> 0 | R17: =IFERROR(IF(compras_mes2[[#This Row],[CUIT]]="","-",VLOOKUP(compras_mes2[[#This Row],[CUIT]],Lista_CUIT[#All],4,0)),"CUIT NO CARGADO") -> 0
B18: 45077 | C18: 1 | D18: 1 | E18: 635 | F18: 30717405680 | G18: =IFERROR(IF(compras_mes2[[#This Row],[CUIT]]="","-",VLOOKUP(compras_mes2[[#This Row],[CUIT]],Lista_CUIT[#All],2,0)),"CUIT NO CARGADO") -> GLOBANS S.R.L. | H18: 4806.11 | I18: =IF(compras_mes2[[#This Row],[NETO GRAVADO]]="","",compras_mes2[[#This Row],[NETO GRAVADO]]*0.21) -> 1009.2831 | P18: =SUM(compras_mes2[[#This Row],[NETO GRAVADO]:[Otros / No Grav.]]) -> 5815.3931 | Q18: =IFERROR(IF(compras_mes2[[#This Row],[CUIT]]="","-",VLOOKUP(compras_mes2[[#This Row],[CUIT]],Lista_CUIT[#All],3,0)),"CUIT NO CARGADO") -> 0 | R18: =IFERROR(IF(compras_mes2[[#This Row],[CUIT]]="","-",VLOOKUP(compras_mes2[[#This Row],[CUIT]],Lista_CUIT[#All],4,0)),"CUIT NO CARGADO") -> 0
B19: 45062 | C19: 1 | D19: 2 | E19: 10325 | F19: 30712179909 | G19: =IFERROR(IF(compras_mes2[[#This Row],[CUIT]]="","-",VLOOKUP(compras_mes2[[#This Row],[CUIT]],Lista_CUIT[#All],2,0)),"CUIT NO CARGADO") -> LEPORT SH DE PORTELA JORGE FERNANDO Y LEAL JORGE ANGEL | H19: 110306 | I19: =IF(compras_mes2[[#This Row],[NETO GRAVADO]]="","",compras_mes2[[#This Row],[NETO GRAVADO]]*0.21) -> 23164.26 | P19: =SUM(compras_mes2[[#This Row],[NETO GRAVADO]:[Otros / No Grav.]]) -> 133470.26 | Q19: =IFERROR(IF(compras_mes2[[#This Row],[CUIT]]="","-",VLOOKUP(compras_mes2[[#This Row],[CUIT]],Lista_CUIT[#All],3,0)),"CUIT NO CARGADO") -> FLETE-LOGISTICA | R19: =IFERROR(IF(compras_mes2[[#This Row],[CUIT]]="","-",VLOOKUP(compras_mes2[[#This Row],[CUIT]],Lista_CUIT[#All],4,0)),"CUIT NO CARGADO") -> 0
B20: 45054 | C20: 1 | D20: 12 | E20: 21890 | F20: 30604942051 | G20: =IFERROR(IF(compras_mes2[[#This Row],[CUIT]]="","-",VLOOKUP(compras_mes2[[#This Row],[CUIT]],Lista_CUIT[#All],2,0)),"CUIT NO CARGADO") -> IMPORTADORA FOTOGRAFICA SOCIEDAD ANONIMA | H20: 52065.43 | I20: =IF(compras_mes2[[#This Row],[NETO GRAVADO]]="","",compras_mes2[[#This Row],[NETO GRAVADO]]*0.21) -> 10933.74 | P20: =SUM(compras_mes2[[#This Row],[NETO GRAVADO]:[Otros / No Grav.]]) -> 62999.17 | Q20: =IFERROR(IF(compras_mes2[[#This Row],[CUIT]]="","-",VLOOKUP(compras_mes2[[#This Row],[CUIT]],Lista_CUIT[#All],3,0)),"CUIT NO CARGADO") -> Gastos Oficina | R20: =IFERROR(IF(compras_mes2[[#This Row],[CUIT]]="","-",VLOOKUP(compras_mes2[[#This Row],[CUIT]],Lista_CUIT[#All],4,0)),"CUIT NO CARGADO") -> 0
B21: 45047 | C21: 1 | D21: 3 | E21: 644 | F21: 30715402765 | G21: =IFERROR(IF(compras_mes2[[#This Row],[CUIT]]="","-",VLOOKUP(compras_mes2[[#This Row],[CUIT]],Lista_CUIT[#All],2,0)),"CUIT NO CARGADO") -> RIO 265 S.R.L. | H21: 12809.92 | I21: =IF(compras_mes2[[#This Row],[NETO GRAVADO]]="","",compras_mes2[[#This Row],[NETO GRAVADO]]*0.21) -> 2690.0832 | P21: =SUM(compras_mes2[[#This Row],[NETO GRAVADO]:[Otros / No Grav.]]) -> 15500.003 | Q21: =IFERROR(IF(compras_mes2[[#This Row],[CUIT]]="","-",VLOOKUP(compras_mes2[[#This Row],[CUIT]],Lista_CUIT[#All],3,0)),"CUIT NO CARGADO") -> Gastos Varios | R21: =IFERROR(IF(compras_mes2[[#This Row],[CUIT]]="","-",VLOOKUP(compras_mes2[[#This Row],[CUIT]],Lista_CUIT[#All],4,0)),"CUIT NO CARGADO") -> 0
B22: 45065 | C22: 1 | D22: 5 | E22: 22491 | F22: 30708166673 | G22: =IFERROR(IF(compras_mes2[[#This Row],[CUIT]]="","-",VLOOKUP(compras_mes2[[#This Row],[CUIT]],Lista_CUIT[#All],2,0)),"CUIT NO CARGADO") -> SUMINISTROS WHITE S.A. | H22: 4725.45 | I22: =IF(compras_mes2[[#This Row],[NETO GRAVADO]]="","",compras_mes2[[#This Row],[NETO GRAVADO]]*0.21) -> 992.3445 | P22: =SUM(compras_mes2[[#This Row],[NETO GRAVADO]:[Otros / No Grav.]]) -> 5717.7945 | Q22: =IFERROR(IF(compras_mes2[[#This Row],[CUIT]]="","-",VLOOKUP(compras_mes2[[#This Row],[CUIT]],Lista_CUIT[#All],3,0)),"CUIT NO CARGADO") -> Gastos Varios | R22: =IFERROR(IF(compras_mes2[[#This Row],[CUIT]]="","-",VLOOKUP(compras_mes2[[#This Row],[CUIT]],Lista_CUIT[#All],4,0)),"CUIT NO CARGADO") -> 0
B23: 45077 | C23: 1 | D23: 3 | E23: 1449227 | F23: 30712019359 | G23: =IFERROR(IF(compras_mes2[[#This Row],[CUIT]]="","-",VLOOKUP(compras_mes2[[#This Row],[CUIT]],Lista_CUIT[#All],2,0)),"CUIT NO CARGADO") -> LINKEDSTORE ARGENTINA S.R.L. | H23: 6032.23 | I23: =IF(compras_mes2[[#This Row],[NETO GRAVADO]]="","",compras_mes2[[#This Row],[NETO GRAVADO]]*0.21) -> 1266.7683 | P23: =SUM(compras_mes2[[#This Row],[NETO GRAVADO]:[Otros / No Grav.]]) -> 7298.9983 | Q23: =IFERROR(IF(compras_mes2[[#This Row],[CUIT]]="","-",VLOOKUP(compras_mes2[[#This Row],[CUIT]],Lista_CUIT[#All],3,0)),"CUIT NO CARGADO") -> Gastos Varios | R23: =IFERROR(IF(compras_mes2[[#This Row],[CUIT]]="","-",VLOOKUP(compras_mes2[[#This Row],[CUIT]],Lista_CUIT[#All],4,0)),"CUIT NO CARGADO") -> 0
B24: 45048 | C24: 1 | D24: 106 | E24: 627952 | F24: 30594494187 | G24: =IFERROR(IF(compras_mes2[[#This Row],[CUIT]]="","-",VLOOKUP(compras_mes2[[#This Row],[CUIT]],Lista_CUIT[#All],2,0)),"CUIT NO CARGADO") -> FEDERAL EXPRESS CORPORATION | H24: 0 | I24: =IF(compras_mes2[[#This Row],[NETO GRAVADO]]="","",compras_mes2[[#This Row],[NETO GRAVADO]]*0.21) -> 0 | O24: 95430.75 | P24: =SUM(compras_mes2[[#This Row],[NETO GRAVADO]:[Otros / No Grav.]]) -> 95430.75 | Q24: =IFERROR(IF(compras_mes2[[#This Row],[CUIT]]="","-",VLOOKUP(compras_mes2[[#This Row],[CUIT]],Lista_CUIT[#All],3,0)),"CUIT NO CARGADO") -> Gtos. Imp. | R24: =IFERROR(IF(compras_mes2[[#This Row],[CUIT]]="","-",VLOOKUP(compras_mes2[[#This Row],[CUIT]],Lista_CUIT[#All],4,0)),"CUIT NO CARGADO") -> 0
B25: 45065 | C25: 1 | D25: 280 | E25: 1432129 | F25: 30580111315 | G25: =IFERROR(IF(compras_mes2[[#This Row],[CUIT]]="","-",VLOOKUP(compras_mes2[[#This Row],[CUIT]],Lista_CUIT[#All],2,0)),"CUIT NO CARGADO") -> DHL EXPRESS (ARGENTINA) S.A. | H25: 77059.521 | I25: =IF(compras_mes2[[#This Row],[NETO GRAVADO]]="","",compras_mes2[[#This Row],[NETO GRAVADO]]*0.21) -> 16182.499 | O25: -58904.659 | P25: =SUM(compras_mes2[[#This Row],[NETO GRAVADO]:[Otros / No Grav.]]) -> 34337.361 | Q25: =IFERROR(IF(compras_mes2[[#This Row],[CUIT]]="","-",VLOOKUP(compras_mes2[[#This Row],[CUIT]],Lista_CUIT[#All],3,0)),"CUIT NO CARGADO") -> Gtos. Imp. | R25: =IFERROR(IF(compras_mes2[[#This Row],[CUIT]]="","-",VLOOKUP(compras_mes2[[#This Row],[CUIT]],Lista_CUIT[#All],4,0)),"CUIT NO CARGADO") -> 0
B26: 45067 | C26: 1 | D26: 280 | E26: 1432518 | F26: 30580111315 | G26: =IFERROR(IF(compras_mes2[[#This Row],[CUIT]]="","-",VLOOKUP(compras_mes2[[#This Row],[CUIT]],Lista_CUIT[#All],2,0)),"CUIT NO CARGADO") -> DHL EXPRESS (ARGENTINA) S.A. | H26: 262672.34 | I26: =IF(compras_mes2[[#This Row],[NETO GRAVADO]]="","",compras_mes2[[#This Row],[NETO GRAVADO]]*0.21) -> 55161.191 | O26: -214865.49 | P26: =SUM(compras_mes2[[#This Row],[NETO GRAVADO]:[Otros / No Grav.]]) -> 102968.04 | Q26: =IFERROR(IF(compras_mes2[[#This Row],[CUIT]]="","-",VLOOKUP(compras_mes2[[#This Row],[CUIT]],Lista_CUIT[#All],3,0)),"CUIT NO CARGADO") -> Gtos. Imp. | R26: =IFERROR(IF(compras_mes2[[#This Row],[CUIT]]="","-",VLOOKUP(compras_mes2[[#This Row],[CUIT]],Lista_CUIT[#All],4,0)),"CUIT NO CARGADO") -> 0
B27: 45075 | C27: 2 | D27: 755 | E27: 2616 | F27: 30580111315 | G27: =IFERROR(IF(compras_mes2[[#This Row],[CUIT]]="","-",VLOOKUP(compras_mes2[[#This Row],[CUIT]],Lista_CUIT[#All],2,0)),"CUIT NO CARGADO") -> DHL EXPRESS (ARGENTINA) S.A. | H27: 0 | I27: =IF(compras_mes2[[#This Row],[NETO GRAVADO]]="","",compras_mes2[[#This Row],[NETO GRAVADO]]*0.21) -> 0 | O27: 3680.16 | P27: =SUM(compras_mes2[[#This Row],[NETO GRAVADO]:[Otros / No Grav.]]) -> 3680.16 | Q27: =IFERROR(IF(compras_mes2[[#This Row],[CUIT]]="","-",VLOOKUP(compras_mes2[[#This Row],[CUIT]],Lista_CUIT[#All],3,0)),"CUIT NO CARGADO") -> Gtos. Imp. | R27: =IFERROR(IF(compras_mes2[[#This Row],[CUIT]]="","-",VLOOKUP(compras_mes2[[#This Row],[CUIT]],Lista_CUIT[#All],4,0)),"CUIT NO CARGADO") -> 0
B28: 45050 | C28: 1 | D28: 2 | E28: 171 | F28: 20125142851 | G28: =IFERROR(IF(compras_mes2[[#This Row],[CUIT]]="","-",VLOOKUP(compras_mes2[[#This Row],[CUIT]],Lista_CUIT[#All],2,0)),"CUIT NO CARGADO") -> FEDERICI NICOLAS JOSE | H28: 73963.52 | I28: =IF(compras_mes2[[#This Row],[NETO GRAVADO]]="","",compras_mes2[[#This Row],[NETO GRAVADO]]*0.21) -> 15532.339 | P28: =SUM(compras_mes2[[#This Row],[NETO GRAVADO]:[Otros / No Grav.]]) -> 89495.859 | Q28: =IFERROR(IF(compras_mes2[[#This Row],[CUIT]]="","-",VLOOKUP(compras_mes2[[#This Row],[CUIT]],Lista_CUIT[#All],3,0)),"CUIT NO CARGADO") -> INSUMO | R28: =IFERROR(IF(compras_mes2[[#This Row],[CUIT]]="","-",VLOOKUP(compras_mes2[[#This Row],[CUIT]],Lista_CUIT[#All],4,0)),"CUIT NO CARGADO") -> 0
B29: 45050 | C29: 1 | D29: 2 | E29: 170 | F29: 20125142851 | G29: =IFERROR(IF(compras_mes2[[#This Row],[CUIT]]="","-",VLOOKUP(compras_mes2[[#This Row],[CUIT]],Lista_CUIT[#All],2,0)),"CUIT NO CARGADO") -> FEDERICI NICOLAS JOSE | H29: 66779.86 | I29: =IF(compras_mes2[[#This Row],[NETO GRAVADO]]="","",compras_mes2[[#This Row],[NETO GRAVADO]]*0.21) -> 14023.771 | P29: =SUM(compras_mes2[[#This Row],[NETO GRAVADO]:[Otros / No Grav.]]) -> 80803.631 | Q29: =IFERROR(IF(compras_mes2[[#This Row],[CUIT]]="","-",VLOOKUP(compras_mes2[[#This Row],[CUIT]],Lista_CUIT[#All],3,0)),"CUIT NO CARGADO") -> INSUMO | R29: =IFERROR(IF(compras_mes2[[#This Row],[CUIT]]="","-",VLOOKUP(compras_mes2[[#This Row],[CUIT]],Lista_CUIT[#All],4,0)),"CUIT NO CARGADO") -> 0
B30: 45077 | C30: 1 | D30: 9 | E30: 1615 | F30: 30631047145 | G30: =IFERROR(IF(compras_mes2[[#This Row],[CUIT]]="","-",VLOOKUP(compras_mes2[[#This Row],[CUIT]],Lista_CUIT[#All],2,0)),"CUIT NO CARGADO") -> SEMICONDUC. Y COMPON. SRL | H30: 271680.85 | I30: 56034.25 | K30: 509.37 | P30: =SUM(compras_mes2[[#This Row],[NETO GRAVADO]:[Otros / No Grav.]]) -> 328224.47 | Q30: =IFERROR(IF(compras_mes2[[#This Row],[CUIT]]="","-",VLOOKUP(compras_mes2[[#This Row],[CUIT]],Lista_CUIT[#All],3,0)),"CUIT NO CARGADO") -> INSUMO | R30: =IFERROR(IF(compras_mes2[[#This Row],[CUIT]]="","-",VLOOKUP(compras_mes2[[#This Row],[CUIT]],Lista_CUIT[#All],4,0)),"CUIT NO CARGADO") -> 0
B31: 45077 | C31: 3 | D31: 9 | E31: 77 | F31: 30631047145 | G31: =IFERROR(IF(compras_mes2[[#This Row],[CUIT]]="","-",VLOOKUP(compras_mes2[[#This Row],[CUIT]],Lista_CUIT[#All],2,0)),"CUIT NO CARGADO") -> SEMICONDUC. Y COMPON. SRL | H31: -39600 | I31: =IF(compras_mes2[[#This Row],[NETO GRAVADO]]="","",compras_mes2[[#This Row],[NETO GRAVADO]]*0.21) -> -8316 | P31: =SUM(compras_mes2[[#This Row],[NETO GRAVADO]:[Otros / No Grav.]]) -> -47916 | Q31: =IFERROR(IF(compras_mes2[[#This Row],[CUIT]]="","-",VLOOKUP(compras_mes2[[#This Row],[CUIT]],Lista_CUIT[#All],3,0)),"CUIT NO CARGADO") -> INSUMO | R31: =IFERROR(IF(compras_mes2[[#This Row],[CUIT]]="","-",VLOOKUP(compras_mes2[[#This Row],[CUIT]],Lista_CUIT[#All],4,0)),"CUIT NO CARGADO") -> 0
B32: 45077 | C32: 1 | D32: 6 | E32: 11830 | F32: 30707756434 | G32: =IFERROR(IF(compras_mes2[[#This Row],[CUIT]]="","-",VLOOKUP(compras_mes2[[#This Row],[CUIT]],Lista_CUIT[#All],2,0)),"CUIT NO CARGADO") -> SERVICIO INTEGRAL DE LIMPIEZA SRL | H32: 42000 | I32: =IF(compras_mes2[[#This Row],[NETO GRAVADO]]="","",compras_mes2[[#This Row],[NETO GRAVADO]]*0.21) -> 8820 | P32: =SUM(compras_mes2[[#This Row],[NETO GRAVADO]:[Otros / No Grav.]]) -> 50820 | Q32: =IFERROR(IF(compras_mes2[[#This Row],[CUIT]]="","-",VLOOKUP(compras_mes2[[#This Row],[CUIT]],Lista_CUIT[#All],3,0)),"CUIT NO CARGADO") -> Mantenimiento | R32: =IFERROR(IF(compras_mes2[[#This Row],[CUIT]]="","-",VLOOKUP(compras_mes2[[#This Row],[CUIT]],Lista_CUIT[#All],4,0)),"CUIT NO CARGADO") -> 0
B33: 45049 | C33: 1 | D33: 4 | E33: 94579 | F33: 30559932236 | G33: =IFERROR(IF(compras_mes2[[#This Row],[CUIT]]="","-",VLOOKUP(compras_mes2[[#This Row],[CUIT]],Lista_CUIT[#All],2,0)),"CUIT NO CARGADO") -> ELECTRONICA ELEMON S A | H33: 31720.85 | I33: 2111.49 | K33: 2274.94 | P33: =SUM(compras_mes2[[#This Row],[NETO GRAVADO]:[Otros / No Grav.]]) -> 36107.28 | Q33: =IFERROR(IF(compras_mes2[[#This Row],[CUIT]]="","-",VLOOKUP(compras_mes2[[#This Row],[CUIT]],Lista_CUIT[#All],3,0)),"CUIT NO CARGADO") -> Mat. Prima | R33: =IFERROR(IF(compras_mes2[[#This Row],[CUIT]]="","-",VLOOKUP(compras_mes2[[#This Row],[CUIT]],Lista_CUIT[#All],4,0)),"CUIT NO CARGADO") -> 0
B34: 45056 | C34: 1 | D34: 8 | E34: 163931 | F34: 33606484599 | G34: =IFERROR(IF(compras_mes2[[#This Row],[CUIT]]="","-",VLOOKUP(compras_mes2[[#This Row],[CUIT]],Lista_CUIT[#All],2,0)),"CUIT NO CARGADO") -> JORVICAL ACEROS S A | H34: 1493646.1 | I34: =IF(compras_mes2[[#This Row],[NETO GRAVADO]]="","",compras_mes2[[#This Row],[NETO GRAVADO]]*0.21) -> 313665.67 | P34: =SUM(compras_mes2[[#This Row],[NETO GRAVADO]:[Otros / No Grav.]]) -> 1807311.7 | Q34: =IFERROR(IF(compras_mes2[[#This Row],[CUIT]]="","-",VLOOKUP(compras_mes2[[#This Row],[CUIT]],Lista_CUIT[#All],3,0)),"CUIT NO CARGADO") -> Mat. Prima | R34: =IFERROR(IF(compras_mes2[[#This Row],[CUIT]]="","-",VLOOKUP(compras_mes2[[#This Row],[CUIT]],Lista_CUIT[#All],4,0)),"CUIT NO CARGADO") -> 0
B35: 45065 | C35: 1 | D35: 3 | E35: 9291 | F35: 30715864262 | G35: =IFERROR(IF(compras_mes2[[#This Row],[CUIT]]="","-",VLOOKUP(compras_mes2[[#This Row],[CUIT]],Lista_CUIT[#All],2,0)),"CUIT NO CARGADO") -> ACPLIND SRL | H35: 15080 | I35: =IF(compras_mes2[[#This Row],[NETO GRAVADO]]="","",compras_mes2[[#This Row],[NETO GRAVADO]]*0.21) -> 3166.8 | P35: =SUM(compras_mes2[[#This Row],[NETO GRAVADO]:[Otros / No Grav.]]) -> 18246.8 | Q35: =IFERROR(IF(compras_mes2[[#This Row],[CUIT]]="","-",VLOOKUP(compras_mes2[[#This Row],[CUIT]],Lista_CUIT[#All],3,0)),"CUIT NO CARGADO") -> Mat. Prima | R35: =IFERROR(IF(compras_mes2[[#This Row],[CUIT]]="","-",VLOOKUP(compras_mes2[[#This Row],[CUIT]],Lista_CUIT[#All],4,0)),"CUIT NO CARGADO") -> 0
B36: 45075 | C36: 1 | D36: 2 | E36: 625 | F36: 20296550184 | G36: =IFERROR(IF(compras_mes2[[#This Row],[CUIT]]="","-",VLOOKUP(compras_mes2[[#This Row],[CUIT]],Lista_CUIT[#All],2,0)),"CUIT NO CARGADO") -> COSTA DIEGO ALEJANDRO | H36: 58460 | I36: =IF(compras_mes2[[#This Row],[NETO GRAVADO]]="","",compras_mes2[[#This Row],[NETO GRAVADO]]*0.21) -> 12276.6 | P36: =SUM(compras_mes2[[#This Row],[NETO GRAVADO]:[Otros / No Grav.]]) -> 70736.6 | Q36: =IFERROR(IF(compras_mes2[[#This Row],[CUIT]]="","-",VLOOKUP(compras_mes2[[#This Row],[CUIT]],Lista_CUIT[#All],3,0)),"CUIT NO CARGADO") -> Mat. Prima | R36: =IFERROR(IF(compras_mes2[[#This Row],[CUIT]]="","-",VLOOKUP(compras_mes2[[#This Row],[CUIT]],Lista_CUIT[#All],4,0)),"CUIT NO CARGADO") -> 0
B37: 45077 | C37: 1 | D37: 5 | E37: 1274 | F37: 30707397256 | G37: =IFERROR(IF(compras_mes2[[#This Row],[CUIT]]="","-",VLOOKUP(compras_mes2[[#This Row],[CUIT]],Lista_CUIT[#All],2,0)),"CUIT NO CARGADO") -> GRAFICA Y FOTOGRABADOS LA PLAZA SRL | H37: 463560 | I37: =IF(compras_mes2[[#This Row],[NETO GRAVADO]]="","",compras_mes2[[#This Row],[NETO GRAVADO]]*0.21) -> 97347.6 | P37: =SUM(compras_mes2[[#This Row],[NETO GRAVADO]:[Otros / No Grav.]]) -> 560907.6 | Q37: =IFERROR(IF(compras_mes2[[#This Row],[CUIT]]="","-",VLOOKUP(compras_mes2[[#This Row],[CUIT]],Lista_CUIT[#All],3,0)),"CUIT NO CARGADO") -> MATERIALES | R37: =IFERROR(IF(compras_mes2[[#This Row],[CUIT]]="","-",VLOOKUP(compras_mes2[[#This Row],[CUIT]],Lista_CUIT[#All],4,0)),"CUIT NO CARGADO") -> 0
B38: 45064 | C38: 1 | D38: 3 | E38: 280 | F38: 20921575743 | G38: =IFERROR(IF(compras_mes2[[#This Row],[CUIT]]="","-",VLOOKUP(compras_mes2[[#This Row],[CUIT]],Lista_CUIT[#All],2,0)),"CUIT NO CARGADO") -> RIOS GOMEZ JOSE ANTONIO | H38: 595708 | I38: =IF(compras_mes2[[#This Row],[NETO GRAVADO]]="","",compras_mes2[[#This Row],[NETO GRAVADO]]*0.21) -> 125098.68 | P38: =SUM(compras_mes2[[#This Row],[NETO GRAVADO]:[Otros / No Grav.]]) -> 720806.68 | Q38: =IFERROR(IF(compras_mes2[[#This Row],[CUIT]]="","-",VLOOKUP(compras_mes2[[#This Row],[CUIT]],Lista_CUIT[#All],3,0)),"CUIT NO CARGADO") -> Papeleria e Insumos | R38: =IFERROR(IF(compras_mes2[[#This Row],[CUIT]]="","-",VLOOKUP(compras_mes2[[#This Row],[CUIT]],Lista_CUIT[#All],4,0)),"CUIT NO CARGADO") -> 0
B39: 45055 | C39: 1 | D39: 3 | E39: 65 | F39: 20297899830 | G39: =IFERROR(IF(compras_mes2[[#This Row],[CUIT]]="","-",VLOOKUP(compras_mes2[[#This Row],[CUIT]],Lista_CUIT[#All],2,0)),"CUIT NO CARGADO") -> FUNK MATIAS NICOLAS | H39: 1389803.2 | I39: =IF(compras_mes2[[#This Row],[NETO GRAVADO]]="","",compras_mes2[[#This Row],[NETO GRAVADO]]*0.21) -> 291858.68 | P39: =SUM(compras_mes2[[#This Row],[NETO GRAVADO]:[Otros / No Grav.]]) -> 1681661.9 | Q39: =IFERROR(IF(compras_mes2[[#This Row],[CUIT]]="","-",VLOOKUP(compras_mes2[[#This Row],[CUIT]],Lista_CUIT[#All],3,0)),"CUIT NO CARGADO") -> Servicios | R39: =IFERROR(IF(compras_mes2[[#This Row],[CUIT]]="","-",VLOOKUP(compras_mes2[[#This Row],[CUIT]],Lista_CUIT[#All],4,0)),"CUIT NO CARGADO") -> 0
B40: 45057 | C40: 1 | D40: 2466 | E40: 507853 | F40: 30678814357 | G40: =IFERROR(IF(compras_mes2[[#This Row],[CUIT]]="","-",VLOOKUP(compras_mes2[[#This Row],[CUIT]],Lista_CUIT[#All],2,0)),"CUIT NO CARGADO") -> TELEFONICA MOVILES ARG | H40: 4343 | J40: 1172.61 | L40: 130.29 | O40: 228.58 | P40: =SUM(compras_mes2[[#This Row],[NETO GRAVADO]:[Otros / No Grav.]]) -> 5874.48 | Q40: =IFERROR(IF(compras_mes2[[#This Row],[CUIT]]="","-",VLOOKUP(compras_mes2[[#This Row],[CUIT]],Lista_CUIT[#All],3,0)),"CUIT NO CARGADO") -> SERVICIOS | R40: =IFERROR(IF(compras_mes2[[#This Row],[CUIT]]="","-",VLOOKUP(compras_mes2[[#This Row],[CUIT]],Lista_CUIT[#All],4,0)),"CUIT NO CARGADO") -> 0
B41: 45047 | C41: 1 | D41: 3 | E41: 189273 | F41: 30707135596 | G41: =IFERROR(IF(compras_mes2[[#This Row],[CUIT]]="","-",VLOOKUP(compras_mes2[[#This Row],[CUIT]],Lista_CUIT[#All],2,0)),"CUIT NO CARGADO") -> CITILAN ARGENTINA S.A. | H41: 5115 | I41: =IF(compras_mes2[[#This Row],[NETO GRAVADO]]="","",compras_mes2[[#This Row],[NETO GRAVADO]]*0.21) -> 1074.15 | P41: =SUM(compras_mes2[[#This Row],[NETO GRAVADO]:[Otros / No Grav.]]) -> 6189.15 | Q41: =IFERROR(IF(compras_mes2[[#This Row],[CUIT]]="","-",VLOOKUP(compras_mes2[[#This Row],[CUIT]],Lista_CUIT[#All],3,0)),"CUIT NO CARGADO") -> Servicios Gas, Luz, Etc | R41: =IFERROR(IF(compras_mes2[[#This Row],[CUIT]]="","-",VLOOKUP(compras_mes2[[#This Row],[CUIT]],Lista_CUIT[#All],4,0)),"CUIT NO CARGADO") -> 0
B42: Total | H42: =SUBTOTAL(109,compras_mes2[NETO GRAVADO]) -> 5233167.3 | I42: =SUBTOTAL(109,compras_mes2[IVA 21 %]) -> 1092484.5 | J42: =SUBTOTAL(109,compras_mes2[IVA 27%]) -> 1172.61 | K42: =SUBTOTAL(109,compras_mes2[IVA 10,5%]) -> 2784.31 | L42: =SUBTOTAL(109,compras_mes2[PERC. IVA]) -> 130.29 | M42: =SUBTOTAL(109,compras_mes2[PERC IIBB BS AS]) -> 0 | N42: =SUBTOTAL(109,compras_mes2[PERC. IIBB CABA]) -> 0 | O42: =SUBTOTAL(109,compras_mes2[Otros / No Grav.]) -> -27288.169 | P42: =SUBTOTAL(109,compras_mes2[TOTAL]) -> 6302450.8
D47: LIQUIDACION EXTRACTOS BANCARIOS-TARJETAS
D48: FECHA | E48: NRO CPTE | F48: BANCO | G48: NETO | H48: IVA 21% | I48: IVA 10,5% | J48: RET IIBB CABA | K48: PERC IVA | L48: PERC IIBB
D49: 45068 | E49: 1033148 | F49: seg.permisos de embarque(Credicop) | G49: 5858.75 | H49: =extracto_banco_mes2[[#This Row],[NETO]]*0.21 -> 1230.3375 | K49: 175.76
D50: 45063 | E50: 617-547987000 | F50: BCO CREDICOOP (LIQ C.I. MOSTRADOR) | G50: 26576.524 | H50: =extracto_banco_mes2[[#This Row],[NETO]]*0.21 -> 5581.07 | K50: 797.3
D51: 45069 | E51: 818-708657000 | F51: ANTIC.-FIN EXT | G51: 61606.857 | H51: =extracto_banco_mes2[[#This Row],[NETO]]*0.21 -> 12937.44 | K51: 1848.21
D52: 45055 | E52: 230509 | F52: CREDICOOP RESUMEN (CTA CORRIENTE) | G52: 17590.5 | H52: =extracto_banco_mes2[[#This Row],[NETO]]*0.21 -> 3694.005
D53: 45070 | E53: 240523 | F53: Credicoop-VISA | G53: 170 | H53: =extracto_banco_mes2[[#This Row],[NETO]]*0.21 -> 35.7
H54: =extracto_banco_mes2[[#This Row],[NETO]]*0.21 -> 0
D55: Total | G55: =SUBTOTAL(109,extracto_banco_mes2[NETO]) -> 111802.63 | H55: =SUBTOTAL(109,extracto_banco_mes2[IVA 21%]) -> 23478.553 | I55: =SUBTOTAL(109,extracto_banco_mes2[IVA 10,5%]) -> 0 | J55: =SUBTOTAL(109,extracto_banco_mes2[RET IIBB CABA]) -> 0 | K55: =SUBTOTAL(109,extracto_banco_mes2[PERC IVA]) -> 2821.27 | L55: =SUBTOTAL(109,extracto_banco_mes2[PERC IIBB]) -> 0
D59: FACTURAS C
D60: FECHA | E60: PTO VTA | F60: FC Nº | G60: CUIT | H60: RAZON SOCIAL | I60: TOTAL | J60: TIPO DE GASTO | K60: Provincia
D61: 45054 | E61: 11 | F61: 37129 | G61: 30714867322 | H61: =IFERROR(IF(factura_c_mes2[[#This Row],[CUIT]]="","-",VLOOKUP(factura_c_mes2[[#This Row],[CUIT]],Lista_CUIT[#All],2,0)),"CUIT NO CARGADO") -> INITIUM SRL | I61: 3488.98 | J61: =IFERROR(IF(factura_c_mes2[[#This Row],[CUIT]]="","-",VLOOKUP(factura_c_mes2[[#This Row],[CUIT]],Lista_CUIT[#All],3,0)),"CUIT NO CARGADO") -> 0 | K61: =IFERROR(IF(factura_c_mes2[[#This Row],[CUIT]]="","-",VLOOKUP(factura_c_mes2[[#This Row],[CUIT]],Lista_CUIT[#All],4,0)),"CUIT NO CARGADO") -> 0
D62: 45055 | E62: 1 | F62: 36 | G62: 27925308868 | H62: =IFERROR(IF(factura_c_mes2[[#This Row],[CUIT]]="","-",VLOOKUP(factura_c_mes2[[#This Row],[CUIT]],Lista_CUIT[#All],2,0)),"CUIT NO CARGADO") -> LOPEZ MOLINA MARIA | I62: 19200 | J62: =IFERROR(IF(factura_c_mes2[[#This Row],[CUIT]]="","-",VLOOKUP(factura_c_mes2[[#This Row],[CUIT]],Lista_CUIT[#All],3,0)),"CUIT NO CARGADO") -> 0 | K62: =IFERROR(IF(factura_c_mes2[[#This Row],[CUIT]]="","-",VLOOKUP(factura_c_mes2[[#This Row],[CUIT]],Lista_CUIT[#All],4,0)),"CUIT NO CARGADO") -> 0
D63: 45061 | E63: 9 | F63: 3739576 | G63: 33715179119 | H63: =IFERROR(IF(factura_c_mes2[[#This Row],[CUIT]]="","-",VLOOKUP(factura_c_mes2[[#This Row],[CUIT]],Lista_CUIT[#All],2,0)),"CUIT NO CARGADO") -> FONDO DE COOPERACION TECNICA Y FINANCIERA - CECBA - SL Y T - LEY 23.412 | I63: 855 | J63: =IFERROR(IF(factura_c_mes2[[#This Row],[CUIT]]="","-",VLOOKUP(factura_c_mes2[[#This Row],[CUIT]],Lista_CUIT[#All],3,0)),"CUIT NO CARGADO") -> 0 | K63: =IFERROR(IF(factura_c_mes2[[#This Row],[CUIT]]="","-",VLOOKUP(factura_c_mes2[[#This Row],[CUIT]],Lista_CUIT[#All],4,0)),"CUIT NO CARGADO") -> 0
D64: 45062 | E64: 2 | F64: 103 | G64: 27125997835 | H64: =IFERROR(IF(factura_c_mes2[[#This Row],[CUIT]]="","-",VLOOKUP(factura_c_mes2[[#This Row],[CUIT]],Lista_CUIT[#All],2,0)),"CUIT NO CARGADO") -> DANSKY ULLMANN VIVIANA EVA YOLANDA | I64: 50000 | J64: =IFERROR(IF(factura_c_mes2[[#This Row],[CUIT]]="","-",VLOOKUP(factura_c_mes2[[#This Row],[CUIT]],Lista_CUIT[#All],3,0)),"CUIT NO CARGADO") -> 0 | K64: =IFERROR(IF(factura_c_mes2[[#This Row],[CUIT]]="","-",VLOOKUP(factura_c_mes2[[#This Row],[CUIT]],Lista_CUIT[#All],4,0)),"CUIT NO CARGADO") -> 0
D65: 45057 | E65: 4 | F65: 13 | G65: 20341462933 | H65: =IFERROR(IF(factura_c_mes2[[#This Row],[CUIT]]="","-",VLOOKUP(factura_c_mes2[[#This Row],[CUIT]],Lista_CUIT[#All],2,0)),"CUIT NO CARGADO") -> CASTIGLIONI MATIAS EZEQUIEL | I65: 510000 | J65: Ingenieria Aplicada | K65: =IFERROR(IF(factura_c_mes2[[#This Row],[CUIT]]="","-",VLOOKUP(factura_c_mes2[[#This Row],[CUIT]],Lista_CUIT[#All],4,0)),"CUIT NO CARGADO") -> BUENOS AIRES | N65: Honorarios Ingeniero | O65: 590500
D66: 45047 | E66: 1 | F66: 7 | G66: 27387896150 | H66: =IFERROR(IF(factura_c_mes2[[#This Row],[CUIT]]="","-",VLOOKUP(factura_c_mes2[[#This Row],[CUIT]],Lista_CUIT[#All],2,0)),"CUIT NO CARGADO") -> LIPANOVICH MARIA SOL | I66: 400000 | J66: =IFERROR(IF(factura_c_mes2[[#This Row],[CUIT]]="","-",VLOOKUP(factura_c_mes2[[#This Row],[CUIT]],Lista_CUIT[#All],3,0)),"CUIT NO CARGADO") -> consultoria informatica | K66: =IFERROR(IF(factura_c_mes2[[#This Row],[CUIT]]="","-",VLOOKUP(factura_c_mes2[[#This Row],[CUIT]],Lista_CUIT[#All],4,0)),"CUIT NO CARGADO") -> 0 | N66: Gastos varios | O66: 19561.95
D67: 45077 | E67: 1 | F67: 8 | G67: 27387896150 | H67: =IFERROR(IF(factura_c_mes2[[#This Row],[CUIT]]="","-",VLOOKUP(factura_c_mes2[[#This Row],[CUIT]],Lista_CUIT[#All],2,0)),"CUIT NO CARGADO") -> LIPANOVICH MARIA SOL | I67: 400000 | J67: =IFERROR(IF(factura_c_mes2[[#This Row],[CUIT]]="","-",VLOOKUP(factura_c_mes2[[#This Row],[CUIT]],Lista_CUIT[#All],3,0)),"CUIT NO CARGADO") -> consultoria informatica | K67: =IFERROR(IF(factura_c_mes2[[#This Row],[CUIT]]="","-",VLOOKUP(factura_c_mes2[[#This Row],[CUIT]],Lista_CUIT[#All],4,0)),"CUIT NO CARGADO") -> 0 | N67: Honorarios Admnistrativos | O67: 148480
D68: 45049 | E68: 2 | F68: 81043 | G68: 30554466806 | H68: =IFERROR(IF(factura_c_mes2[[#This Row],[CUIT]]="","-",VLOOKUP(factura_c_mes2[[#This Row],[CUIT]],Lista_CUIT[#All],2,0)),"CUIT NO CARGADO") -> ASOCIACION DE IMPORTADORES Y EXPORTADORES DE LA REPUBLICA ARGENTINA | I68: 3200 | J68: =IFERROR(IF(factura_c_mes2[[#This Row],[CUIT]]="","-",VLOOKUP(factura_c_mes2[[#This Row],[CUIT]],Lista_CUIT[#All],3,0)),"CUIT NO CARGADO") -> FLETE-LOGISTICA | K68: =IFERROR(IF(factura_c_mes2[[#This Row],[CUIT]]="","-",VLOOKUP(factura_c_mes2[[#This Row],[CUIT]],Lista_CUIT[#All],4,0)),"CUIT NO CARGADO") -> 0 | N68: Honorarios Contables | O68: 89860
D69: 45057 | E69: 7 | F69: 313886 | G69: 20259150249 | H69: =IFERROR(IF(factura_c_mes2[[#This Row],[CUIT]]="","-",VLOOKUP(factura_c_mes2[[#This Row],[CUIT]],Lista_CUIT[#All],2,0)),"CUIT NO CARGADO") -> BIANCHI CRISTIAN MAXIMILIANO | I69: 18590 | J69: =IFERROR(IF(factura_c_mes2[[#This Row],[CUIT]]="","-",VLOOKUP(factura_c_mes2[[#This Row],[CUIT]],Lista_CUIT[#All],3,0)),"CUIT NO CARGADO") -> Gastos Varios | K69: =IFERROR(IF(factura_c_mes2[[#This Row],[CUIT]]="","-",VLOOKUP(factura_c_mes2[[#This Row],[CUIT]],Lista_CUIT[#All],4,0)),"CUIT NO CARGADO") -> 0 | N69: Desarrollo Software | O69: 90000
D70: 45061 | E70: 7 | F70: 314857 | G70: 20259150249 | H70: =IFERROR(IF(factura_c_mes2[[#This Row],[CUIT]]="","-",VLOOKUP(factura_c_mes2[[#This Row],[CUIT]],Lista_CUIT[#All],2,0)),"CUIT NO CARGADO") -> BIANCHI CRISTIAN MAXIMILIANO | I70: 16799 | J70: =IFERROR(IF(factura_c_mes2[[#This Row],[CUIT]]="","-",VLOOKUP(factura_c_mes2[[#This Row],[CUIT]],Lista_CUIT[#All],3,0)),"CUIT NO CARGADO") -> Gastos Varios | K70: =IFERROR(IF(factura_c_mes2[[#This Row],[CUIT]]="","-",VLOOKUP(factura_c_mes2[[#This Row],[CUIT]],Lista_CUIT[#All],4,0)),"CUIT NO CARGADO") -> 0 | N70: Mantenimiento Sofware | O70: 373750
D71: 45054 | E71: 2 | F71: 140 | G71: 20136544625 | H71: =IFERROR(IF(factura_c_mes2[[#This Row],[CUIT]]="","-",VLOOKUP(factura_c_mes2[[#This Row],[CUIT]],Lista_CUIT[#All],2,0)),"CUIT NO CARGADO") -> RODRIGUEZ DE LA FUEN HECTOR MARCELO | I71: 160000 | J71: =IFERROR(IF(factura_c_mes2[[#This Row],[CUIT]]="","-",VLOOKUP(factura_c_mes2[[#This Row],[CUIT]],Lista_CUIT[#All],3,0)),"CUIT NO CARGADO") -> Hon. Admin. | K71: =IFERROR(IF(factura_c_mes2[[#This Row],[CUIT]]="","-",VLOOKUP(factura_c_mes2[[#This Row],[CUIT]],Lista_CUIT[#All],4,0)),"CUIT NO CARGADO") -> 0 | N71: Mantenimiento Oficvina | O71: 148935
D72: 45054 | E72: 2 | F72: 141 | G72: 20136544625 | H72: =IFERROR(IF(factura_c_mes2[[#This Row],[CUIT]]="","-",VLOOKUP(factura_c_mes2[[#This Row],[CUIT]],Lista_CUIT[#All],2,0)),"CUIT NO CARGADO") -> RODRIGUEZ DE LA FUEN HECTOR MARCELO | I72: 140000 | J72: =IFERROR(IF(factura_c_mes2[[#This Row],[CUIT]]="","-",VLOOKUP(factura_c_mes2[[#This Row],[CUIT]],Lista_CUIT[#All],3,0)),"CUIT NO CARGADO") -> Hon. Admin. | K72: =IFERROR(IF(factura_c_mes2[[#This Row],[CUIT]]="","-",VLOOKUP(factura_c_mes2[[#This Row],[CUIT]],Lista_CUIT[#All],4,0)),"CUIT NO CARGADO") -> 0 | N72: Mantenim Materiales | O72: 128690
D73: 45061 | E73: 2 | F73: 142 | G73: 20136544625 | H73: =IFERROR(IF(factura_c_mes2[[#This Row],[CUIT]]="","-",VLOOKUP(factura_c_mes2[[#This Row],[CUIT]],Lista_CUIT[#All],2,0)),"CUIT NO CARGADO") -> RODRIGUEZ DE LA FUEN HECTOR MARCELO | I73: 400000 | J73: =IFERROR(IF(factura_c_mes2[[#This Row],[CUIT]]="","-",VLOOKUP(factura_c_mes2[[#This Row],[CUIT]],Lista_CUIT[#All],3,0)),"CUIT NO CARGADO") -> Hon. Admin. | K73: =IFERROR(IF(factura_c_mes2[[#This Row],[CUIT]]="","-",VLOOKUP(factura_c_mes2[[#This Row],[CUIT]],Lista_CUIT[#All],4,0)),"CUIT NO CARGADO") -> 0 | N73: Mantenimiento Sofware | O73: 371000
D74: 45069 | E74: 3 | F74: 52 | G74: 20403931420 | H74: =IFERROR(IF(factura_c_mes2[[#This Row],[CUIT]]="","-",VLOOKUP(factura_c_mes2[[#This Row],[CUIT]],Lista_CUIT[#All],2,0)),"CUIT NO CARGADO") -> FIORENTINO JORGE IGNACIO | I74: 148510 | J74: =IFERROR(IF(factura_c_mes2[[#This Row],[CUIT]]="","-",VLOOKUP(factura_c_mes2[[#This Row],[CUIT]],Lista_CUIT[#All],3,0)),"CUIT NO CARGADO") -> Hon. Admin. | K74: =IFERROR(IF(factura_c_mes2[[#This Row],[CUIT]]="","-",VLOOKUP(factura_c_mes2[[#This Row],[CUIT]],Lista_CUIT[#All],4,0)),"CUIT NO CARGADO") -> 0 | O74: =SUM(O65:O73) -> 1960776.9
D75: 45048 | E75: 3 | F75: 732 | G75: 20086277523 | H75: =IFERROR(IF(factura_c_mes2[[#This Row],[CUIT]]="","-",VLOOKUP(factura_c_mes2[[#This Row],[CUIT]],Lista_CUIT[#All],2,0)),"CUIT NO CARGADO") -> ESTUDIO BOTINDARI | I75: 81000 | J75: Honorarios Contables | K75: =IFERROR(IF(factura_c_mes2[[#This Row],[CUIT]]="","-",VLOOKUP(factura_c_mes2[[#This Row],[CUIT]],Lista_CUIT[#All],4,0)),"CUIT NO CARGADO") -> 0
D76: 45061 | E76: 3 | F76: 737 | G76: 20086277523 | H76: =IFERROR(IF(factura_c_mes2[[#This Row],[CUIT]]="","-",VLOOKUP(factura_c_mes2[[#This Row],[CUIT]],Lista_CUIT[#All],2,0)),"CUIT NO CARGADO") -> ESTUDIO BOTINDARI | I76: 12860 | J76: Honorarios Contables | K76: =IFERROR(IF(factura_c_mes2[[#This Row],[CUIT]]="","-",VLOOKUP(factura_c_mes2[[#This Row],[CUIT]],Lista_CUIT[#All],4,0)),"CUIT NO CARGADO") -> 0
D77: 45062 | E77: 2 | F77: 203 | G77: 27173820866 | H77: =IFERROR(IF(factura_c_mes2[[#This Row],[CUIT]]="","-",VLOOKUP(factura_c_mes2[[#This Row],[CUIT]],Lista_CUIT[#All],2,0)),"CUIT NO CARGADO") -> FREIER SANDRA DANIELA | I77: 400000 | J77: =IFERROR(IF(factura_c_mes2[[#This Row],[CUIT]]="","-",VLOOKUP(factura_c_mes2[[#This Row],[CUIT]],Lista_CUIT[#All],3,0)),"CUIT NO CARGADO") -> HONORARIOS | K77: =IFERROR(IF(factura_c_mes2[[#This Row],[CUIT]]="","-",VLOOKUP(factura_c_mes2[[#This Row],[CUIT]],Lista_CUIT[#All],4,0)),"CUIT NO CARGADO") -> 0
D78: 45049 | E78: 1 | F78: 12 | G78: 20338344695 | H78: =IFERROR(IF(factura_c_mes2[[#This Row],[CUIT]]="","-",VLOOKUP(factura_c_mes2[[#This Row],[CUIT]],Lista_CUIT[#All],2,0)),"CUIT NO CARGADO") -> FUERTES DAMIAN MATIAS | I78: 37400 | J78: =IFERROR(IF(factura_c_mes2[[#This Row],[CUIT]]="","-",VLOOKUP(factura_c_mes2[[#This Row],[CUIT]],Lista_CUIT[#All],3,0)),"CUIT NO CARGADO") -> INSUMO | K78: =IFERROR(IF(factura_c_mes2[[#This Row],[CUIT]]="","-",VLOOKUP(factura_c_mes2[[#This Row],[CUIT]],Lista_CUIT[#All],4,0)),"CUIT NO CARGADO") -> 0
D79: 45049 | E79: 350 | F79: 186905 | G79: 30525558246 | H79: =IFERROR(IF(factura_c_mes2[[#This Row],[CUIT]]="","-",VLOOKUP(factura_c_mes2[[#This Row],[CUIT]],Lista_CUIT[#All],2,0)),"CUIT NO CARGADO") -> ANTONIO LUQUIN S A C I F E I | I79: 21399 | J79: =IFERROR(IF(factura_c_mes2[[#This Row],[CUIT]]="","-",VLOOKUP(factura_c_mes2[[#This Row],[CUIT]],Lista_CUIT[#All],3,0)),"CUIT NO CARGADO") -> Mantenimiento | K79: =IFERROR(IF(factura_c_mes2[[#This Row],[CUIT]]="","-",VLOOKUP(factura_c_mes2[[#This Row],[CUIT]],Lista_CUIT[#All],4,0)),"CUIT NO CARGADO") -> 0
D80: 45049 | E80: 350 | F80: 186906 | G80: 30525558246 | H80: =IFERROR(IF(factura_c_mes2[[#This Row],[CUIT]]="","-",VLOOKUP(factura_c_mes2[[#This Row],[CUIT]],Lista_CUIT[#All],2,0)),"CUIT NO CARGADO") -> ANTONIO LUQUIN S A C I F E I | I80: 21399 | J80: =IFERROR(IF(factura_c_mes2[[#This Row],[CUIT]]="","-",VLOOKUP(factura_c_mes2[[#This Row],[CUIT]],Lista_CUIT[#All],3,0)),"CUIT NO CARGADO") -> Mantenimiento | K80: =IFERROR(IF(factura_c_mes2[[#This Row],[CUIT]]="","-",VLOOKUP(factura_c_mes2[[#This Row],[CUIT]],Lista_CUIT[#All],4,0)),"CUIT NO CARGADO") -> 0
D81: 45049 | E81: 345 | F81: 332222 | G81: 30525558246 | H81: =IFERROR(IF(factura_c_mes2[[#This Row],[CUIT]]="","-",VLOOKUP(factura_c_mes2[[#This Row],[CUIT]],Lista_CUIT[#All],2,0)),"CUIT NO CARGADO") -> ANTONIO LUQUIN S A C I F E I | I81: 20699 | J81: =IFERROR(IF(factura_c_mes2[[#This Row],[CUIT]]="","-",VLOOKUP(factura_c_mes2[[#This Row],[CUIT]],Lista_CUIT[#All],3,0)),"CUIT NO CARGADO") -> Mantenimiento | K81: =IFERROR(IF(factura_c_mes2[[#This Row],[CUIT]]="","-",VLOOKUP(factura_c_mes2[[#This Row],[CUIT]],Lista_CUIT[#All],4,0)),"CUIT NO CARGADO") -> 0
D82: 45049 | E82: 345 | F82: 332224 | G82: 30525558246 | H82: =IFERROR(IF(factura_c_mes2[[#This Row],[CUIT]]="","-",VLOOKUP(factura_c_mes2[[#This Row],[CUIT]],Lista_CUIT[#All],2,0)),"CUIT NO CARGADO") -> ANTONIO LUQUIN S A C I F E I | I82: 20699 | J82: =IFERROR(IF(factura_c_mes2[[#This Row],[CUIT]]="","-",VLOOKUP(factura_c_mes2[[#This Row],[CUIT]],Lista_CUIT[#All],3,0)),"CUIT NO CARGADO") -> Mantenimiento | K82: =IFERROR(IF(factura_c_mes2[[#This Row],[CUIT]]="","-",VLOOKUP(factura_c_mes2[[#This Row],[CUIT]],Lista_CUIT[#All],4,0)),"CUIT NO CARGADO") -> 0
D83: 45062 | E83: 2 | F83: 2 | G83: 23326777269 | H83: =IFERROR(IF(factura_c_mes2[[#This Row],[CUIT]]="","-",VLOOKUP(factura_c_mes2[[#This Row],[CUIT]],Lista_CUIT[#All],2,0)),"CUIT NO CARGADO") -> DE BONIS IGNACIO LUIS | I83: -148935 | J83: =IFERROR(IF(factura_c_mes2[[#This Row],[CUIT]]="","-",VLOOKUP(factura_c_mes2[[#This Row],[CUIT]],Lista_CUIT[#All],3,0)),"CUIT NO CARGADO") -> Mantenimiento | K83: =IFERROR(IF(factura_c_mes2[[#This Row],[CUIT]]="","-",VLOOKUP(factura_c_mes2[[#This Row],[CUIT]],Lista_CUIT[#All],4,0)),"CUIT NO CARGADO") -> 0
D84: 45068 | E84: 1 | F84: 18 | G84: 20417805878 | H84: =IFERROR(IF(factura_c_mes2[[#This Row],[CUIT]]="","-",VLOOKUP(factura_c_mes2[[#This Row],[CUIT]],Lista_CUIT[#All],2,0)),"CUIT NO CARGADO") -> FERABOLI OSPAL SANTIAGO HERNAN | I84: 128970 | J84: =IFERROR(IF(factura_c_mes2[[#This Row],[CUIT]]="","-",VLOOKUP(factura_c_mes2[[#This Row],[CUIT]],Lista_CUIT[#All],3,0)),"CUIT NO CARGADO") -> Mantenimiento | K84: =IFERROR(IF(factura_c_mes2[[#This Row],[CUIT]]="","-",VLOOKUP(factura_c_mes2[[#This Row],[CUIT]],Lista_CUIT[#All],4,0)),"CUIT NO CARGADO") -> 0
D85: 45068 | E85: 1 | F85: 99 | G85: 20341465134 | H85: =IFERROR(IF(factura_c_mes2[[#This Row],[CUIT]]="","-",VLOOKUP(factura_c_mes2[[#This Row],[CUIT]],Lista_CUIT[#All],2,0)),"CUIT NO CARGADO") -> ABELEDO AGUSTIN ENRIQUE | I85: 340570 | J85: =IFERROR(IF(factura_c_mes2[[#This Row],[CUIT]]="","-",VLOOKUP(factura_c_mes2[[#This Row],[CUIT]],Lista_CUIT[#All],3,0)),"CUIT NO CARGADO") -> Mantenimiento | K85: =IFERROR(IF(factura_c_mes2[[#This Row],[CUIT]]="","-",VLOOKUP(factura_c_mes2[[#This Row],[CUIT]],Lista_CUIT[#All],4,0)),"CUIT NO CARGADO") -> CABA
D86: 45047 | E86: 1 | F86: 23 | G86: 20365938688 | H86: =IFERROR(IF(factura_c_mes2[[#This Row],[CUIT]]="","-",VLOOKUP(factura_c_mes2[[#This Row],[CUIT]],Lista_CUIT[#All],2,0)),"CUIT NO CARGADO") -> LIPANOVICH JUAN CRUZ | I86: 450000 | J86: =IFERROR(IF(factura_c_mes2[[#This Row],[CUIT]]="","-",VLOOKUP(factura_c_mes2[[#This Row],[CUIT]],Lista_CUIT[#All],3,0)),"CUIT NO CARGADO") -> SOFTWARE | K86: =IFERROR(IF(factura_c_mes2[[#This Row],[CUIT]]="","-",VLOOKUP(factura_c_mes2[[#This Row],[CUIT]],Lista_CUIT[#All],4,0)),"CUIT NO CARGADO") -> 0
D87: 45065 | E87: 2 | F87: 83 | G87: 20244271740 | H87: =IFERROR(IF(factura_c_mes2[[#This Row],[CUIT]]="","-",VLOOKUP(factura_c_mes2[[#This Row],[CUIT]],Lista_CUIT[#All],2,0)),"CUIT NO CARGADO") -> KENNEL SEBASTIAN | I87: 378000 | J87: =IFERROR(IF(factura_c_mes2[[#This Row],[CUIT]]="","-",VLOOKUP(factura_c_mes2[[#This Row],[CUIT]],Lista_CUIT[#All],3,0)),"CUIT NO CARGADO") -> Software Mantenimiento | K87: =IFERROR(IF(factura_c_mes2[[#This Row],[CUIT]]="","-",VLOOKUP(factura_c_mes2[[#This Row],[CUIT]],Lista_CUIT[#All],4,0)),"CUIT NO CARGADO") -> 0
D88: Total | I88: =SUBTOTAL(109,factura_c_mes2[TOTAL]) -> 4034704
B94: LIBRO IVA VENTAS | K94: =N1 -> 45047
B96: VENTAS "A"
B97: FECHA | C97: TIPO | D97: PTO VENTA | E97: Nº FACTURA | F97: CUIT | G97: RAZON SOCIAL | H97: IMPORTE NETO | I97: IVA 21% | J97: IVA 10,5% | K97: EXENTO | L97: TOTAL | M97: Provincia
B98: 45050 | C98: 1 | D98: 3 | E98: 127 | F98: 30707462228 | G98: =IFERROR(IF(venta_a_mes2[[#This Row],[CUIT]]="","-",VLOOKUP(venta_a_mes2[[#This Row],[CUIT]],Lista_CUIT[#All],2,0)),"CUIT NO CARGADO") -> BRAIN S.A. | H98: 22520 | I98: =venta_a_mes2[[#This Row],[IMPORTE NETO]]*0.21 -> 4729.2 | L98: =SUM(venta_a_mes2[[#This Row],[IMPORTE NETO]:[EXENTO]]) -> 27249.2
B99: 45055 | C99: 1 | D99: 3 | E99: 128 | F99: 30628274327 | G99: =IFERROR(IF(venta_a_mes2[[#This Row],[CUIT]]="","-",VLOOKUP(venta_a_mes2[[#This Row],[CUIT]],Lista_CUIT[#All],2,0)),"CUIT NO CARGADO") -> AGIRA S A | H99: 5087977.5 | J99: 534237.64 | L99: =SUM(venta_a_mes2[[#This Row],[IMPORTE NETO]:[EXENTO]]) -> 5622215.1
B100: 45063 | C100: 1 | D100: 3 | E100: 129 | F100: 30673387027 | G100: =IFERROR(IF(venta_a_mes2[[#This Row],[CUIT]]="","-",VLOOKUP(venta_a_mes2[[#This Row],[CUIT]],Lista_CUIT[#All],2,0)),"CUIT NO CARGADO") -> JURO S A | H100: 5098600 | J100: 535353 | L100: =SUM(venta_a_mes2[[#This Row],[IMPORTE NETO]:[EXENTO]]) -> 5633953
B101: 45063 | C101: 1 | D101: 3 | E101: 130 | F101: 30716244330 | G101: =IFERROR(IF(venta_a_mes2[[#This Row],[CUIT]]="","-",VLOOKUP(venta_a_mes2[[#This Row],[CUIT]],Lista_CUIT[#All],2,0)),"CUIT NO CARGADO") -> VULPIANI S.A. | H101: 42087.5 | I101: =venta_a_mes2[[#This Row],[IMPORTE NETO]]*0.21 -> 8838.375 | L101: =SUM(venta_a_mes2[[#This Row],[IMPORTE NETO]:[EXENTO]]) -> 50925.875
B102: 45064 | C102: 1 | D102: 3 | E102: 131 | F102: 30638318470 | G102: =IFERROR(IF(venta_a_mes2[[#This Row],[CUIT]]="","-",VLOOKUP(venta_a_mes2[[#This Row],[CUIT]],Lista_CUIT[#All],2,0)),"CUIT NO CARGADO") -> DELTA COMPRESION S R L | H102: 678039.55 | I102: =venta_a_mes2[[#This Row],[IMPORTE NETO]]*0.21 -> 142388.31 | L102: =SUM(venta_a_mes2[[#This Row],[IMPORTE NETO]:[EXENTO]]) -> 820427.86
B103: 45065 | C103: 1 | D103: 3 | E103: 132 | F103: 30628274327 | G103: =IFERROR(IF(venta_a_mes2[[#This Row],[CUIT]]="","-",VLOOKUP(venta_a_mes2[[#This Row],[CUIT]],Lista_CUIT[#All],2,0)),"CUIT NO CARGADO") -> AGIRA S A | H103: 5786775 | J103: 607611.38 | L103: =SUM(venta_a_mes2[[#This Row],[IMPORTE NETO]:[EXENTO]]) -> 6394386.4
B104: 45070 | C104: 1 | D104: 3 | E104: 133 | F104: 33717088269 | G104: =IFERROR(IF(venta_a_mes2[[#This Row],[CUIT]]="","-",VLOOKUP(venta_a_mes2[[#This Row],[CUIT]],Lista_CUIT[#All],2,0)),"CUIT NO CARGADO") -> NEXT SERVICE GNC S.R.L. | H104: 343640 | I104: =venta_a_mes2[[#This Row],[IMPORTE NETO]]*0.21 -> 72164.4 | L104: =SUM(venta_a_mes2[[#This Row],[IMPORTE NETO]:[EXENTO]]) -> 415804.4
B105: 45076 | C105: 1 | D105: 3 | E105: 134 | F105: 30716041596 | G105: =IFERROR(IF(venta_a_mes2[[#This Row],[CUIT]]="","-",VLOOKUP(venta_a_mes2[[#This Row],[CUIT]],Lista_CUIT[#All],2,0)),"CUIT NO CARGADO") -> EXA COMPRESION S.R.L. | H105: 1219840 | I105: =venta_a_mes2[[#This Row],[IMPORTE NETO]]*0.21 -> 256166.4 | L105: =SUM(venta_a_mes2[[#This Row],[IMPORTE NETO]:[EXENTO]]) -> 1476006.4
B106: 45065 | C106: 3 | D106: 3 | E106: 17 | F106: 30628274327 | G106: =IFERROR(IF(venta_a_mes2[[#This Row],[CUIT]]="","-",VLOOKUP(venta_a_mes2[[#This Row],[CUIT]],Lista_CUIT[#All],2,0)),"CUIT NO CARGADO") -> AGIRA S A | H106: -5087977.5 | J106: -534237.64 | L106: =SUM(venta_a_mes2[[#This Row],[IMPORTE NETO]:[EXENTO]]) -> -5622215.1
G107: =IFERROR(IF(venta_a_mes2[[#This Row],[CUIT]]="","-",VLOOKUP(venta_a_mes2[[#This Row],[CUIT]],Lista_CUIT[#All],2,0)),"CUIT NO CARGADO") -> - | I107: =venta_a_mes2[[#This Row],[IMPORTE NETO]]*0.21 -> 0 | L107: =SUM(venta_a_mes2[[#This Row],[IMPORTE NETO]:[EXENTO]]) -> 0
B108: Total | H108: =SUBTOTAL(109,venta_a_mes2[IMPORTE NETO]) -> 13191502 | I108: =SUBTOTAL(109,venta_a_mes2[IVA 21%]) -> 484286.68 | J108: =SUBTOTAL(109,venta_a_mes2[IVA 10,5%]) -> 1142964.4 | K108: =SUBTOTAL(109,venta_a_mes2[EXENTO]) -> 0 | L108: =SUBTOTAL(109,venta_a_mes2[TOTAL]) -> 14818753
B113: VENTAS "B"
B114: FECHA | C114: TIPO | D114: PTO VENTA | E114: Nº FACTURA | F114: CUIT | G114: RAZON SOCIAL | H114: IMPORTE NETO | I114: IVA 21% | J114: IVA 10,5% | K114: EXENTO | L114: TOTAL | M114: Provincia
B115: 45068 | C115: 6 | D115: 3 | E115: 3 | G115: =IFERROR(IF(ventas_b_mes252[[#This Row],[CUIT]]="","-",VLOOKUP(ventas_b_mes252[[#This Row],[CUIT]],Lista_CUIT[#All],2,0)),"CUIT NO CARGADO") -> - | H115: 95427.5 | I115: =ventas_b_mes252[[#This Row],[IMPORTE NETO]]*0.21 -> 20039.775 | L115: =ventas_b_mes252[[#This Row],[EXENTO]]+ventas_b_mes252[[#This Row],[IVA 10,5%]]+ventas_b_mes252[[#This Row],[IVA 21%]]+ventas_b_mes252[[#This Row],[IMPORTE NETO]] -> 115467.27
B116: 45068 | C116: 6 | D116: 3 | E116: 5 | G116: =IFERROR(IF(ventas_b_mes252[[#This Row],[CUIT]]="","-",VLOOKUP(ventas_b_mes252[[#This Row],[CUIT]],Lista_CUIT[#All],2,0)),"CUIT NO CARGADO") -> - | H116: 95427.5 | I116: =ventas_b_mes252[[#This Row],[IMPORTE NETO]]*0.21 -> 20039.775 | L116: =ventas_b_mes252[[#This Row],[EXENTO]]+ventas_b_mes252[[#This Row],[IVA 10,5%]]+ventas_b_mes252[[#This Row],[IVA 21%]]+ventas_b_mes252[[#This Row],[IMPORTE NETO]] -> 115467.27
B117: 45068 | C117: 6 | D117: 3 | E117: 4 | G117: =IFERROR(IF(ventas_b_mes252[[#This Row],[CUIT]]="","-",VLOOKUP(ventas_b_mes252[[#This Row],[CUIT]],Lista_CUIT[#All],2,0)),"CUIT NO CARGADO") -> - | H117: 95427.5 | I117: =ventas_b_mes252[[#This Row],[IMPORTE NETO]]*0.21 -> 20039.775 | L117: =ventas_b_mes252[[#This Row],[EXENTO]]+ventas_b_mes252[[#This Row],[IVA 10,5%]]+ventas_b_mes252[[#This Row],[IVA 21%]]+ventas_b_mes252[[#This Row],[IMPORTE NETO]] -> 115467.27
B118: 45068 | C118: 8 | D118: 3 | E118: 2 | G118: =IFERROR(IF(ventas_b_mes252[[#This Row],[CUIT]]="","-",VLOOKUP(ventas_b_mes252[[#This Row],[CUIT]],Lista_CUIT[#All],2,0)),"CUIT NO CARGADO") -> - | H118: -95427.5 | I118: =ventas_b_mes252[[#This Row],[IMPORTE NETO]]*0.21 -> -20039.775 | L118: =ventas_b_mes252[[#This Row],[EXENTO]]+ventas_b_mes252[[#This Row],[IVA 10,5%]]+ventas_b_mes252[[#This Row],[IVA 21%]]+ventas_b_mes252[[#This Row],[IMPORTE NETO]] -> -115467.27
B119: 45068 | C119: 8 | D119: 3 | E119: 1 | G119: =IFERROR(IF(ventas_b_mes252[[#This Row],[CUIT]]="","-",VLOOKUP(ventas_b_mes252[[#This Row],[CUIT]],Lista_CUIT[#All],2,0)),"CUIT NO CARGADO") -> - | H119: -95427.5 | I119: =ventas_b_mes252[[#This Row],[IMPORTE NETO]]*0.21 -> -20039.775 | L119: =ventas_b_mes252[[#This Row],[EXENTO]]+ventas_b_mes252[[#This Row],[IVA 10,5%]]+ventas_b_mes252[[#This Row],[IVA 21%]]+ventas_b_mes252[[#This Row],[IMPORTE NETO]] -> -115467.27
B120: Total | H120: =SUBTOTAL(109,ventas_b_mes252[IMPORTE NETO]) -> 95427.5 | I120: =SUBTOTAL(109,ventas_b_mes252[IVA 21%]) -> 20039.775 | J120: =SUBTOTAL(109,ventas_b_mes252[IVA 10,5%]) -> 0 | K120: =SUBTOTAL(109,ventas_b_mes252[EXENTO]) -> 0 | L120: =SUBTOTAL(109,ventas_b_mes252[TOTAL]) -> 115467.27 | M120: =SUBTOTAL(103,ventas_b_mes252[Provincia]) -> 0
B123: VENTAS "E"
...

Sheet Jun-23
B1: LIBRO IVA COMPRAS | G1: ='Abr-23'!G1:M1 -> CORITEC S. R. L. | N1: =EDATE('Abr-23'!N1,2) -> 45078
B3: TOTAL COMPRAS | G3: TOTAL CREDITO FISCAL | J3: TOTAL VENTAS NETAS | M3: TOTAL DEBITO FISCAL | P3: RESULTADO
B4: =SUM(compras_mes3[[#Totals],[NETO GRAVADO]])+extracto_banco_mes3[[#Totals],[NETO]] -> 2210365.2 | G4: =compras_mes3[[#Totals],[IVA 21 %]]+compras_mes3[[#Totals],[IVA 27%]]+compras_mes3[[#Totals],[IVA 10,5%]]+extracto_banco_mes3[[#Totals],[IVA 21%]]+extracto_banco_mes3[[#Totals],[IVA 10,5%]] -> 454975.11 | J4: =venta_a_mes3[[#Totals],[IMPORTE NETO]]+ventas_b_mes3[[#Totals],[IMPORTE NETO]] -> 17707270 | M4: =venta_a_mes3[[#Totals],[IVA 21%]]+venta_a_mes3[[#Totals],[IVA 10,5%]]+ventas_b_mes3[[#Totals],[IVA 21%]]+ventas_b_mes3[[#Totals],[IVA 10,5%]] -> 2621068.7 | P4: =G4-M4 -> -2166093.6
B8: FECHA | C8: TIPO | D8: PTO VTA | E8: NRO. CPTE | F8: CUIT | G8: RAZON SOCIAL | H8: NETO GRAVADO | I8: IVA 21 % | J8: IVA 27% | K8: IVA 10,5% | L8: PERC. IVA | M8: PERC IIBB BS AS | N8: PERC. IIBB CABA | O8: Otros / No Grav. | P8: TOTAL | Q8: Tipo de Gasto | R8: Provincia
B9: 45105 | C9: 1 | D9: 2 | E9: 1360 | F9: 30709045632 | G9: =IFERROR(IF(compras_mes3[[#This Row],[CUIT]]="","-",VLOOKUP(compras_mes3[[#This Row],[CUIT]],Lista_CUIT[#All],2,0)),"CUIT NO CARGADO") -> ACACIA Y LENGA S R L | H9: 7932.22 | I9: =IF(compras_mes3[[#This Row],[NETO GRAVADO]]="","",compras_mes3[[#This Row],[NETO GRAVADO]]*0.21) -> 1665.7662 | P9: =SUM(compras_mes3[[#This Row],[NETO GRAVADO]:[Otros / No Grav.]]) -> 9597.9862 | Q9: =IFERROR(IF(compras_mes3[[#This Row],[CUIT]]="","-",VLOOKUP(compras_mes3[[#This Row],[CUIT]],Lista_CUIT[#All],3,0)),"CUIT NO CARGADO") -> REPUESTOS | R9: =IFERROR(IF(compras_mes3[[#This Row],[CUIT]]="","-",VLOOKUP(compras_mes3[[#This Row],[CUIT]],Lista_CUIT[#All],4,0)),"CUIT NO CARGADO") -> CABA
B10: 45106 | C10: 1 | D10: 7 | E10: 12133 | F10: 20261680298 | G10: =IFERROR(IF(compras_mes3[[#This Row],[CUIT]]="","-",VLOOKUP(compras_mes3[[#This Row],[CUIT]],Lista_CUIT[#All],2,0)),"CUIT NO CARGADO") -> ADATTO MARCELO ADRIAN | H10: 4282.12 | I10: 170.08 | K10: 364.79 | P10: =SUM(compras_mes3[[#This Row],[NETO GRAVADO]:[Otros / No Grav.]]) -> 4816.99 | Q10: =IFERROR(IF(compras_mes3[[#This Row],[CUIT]]="","-",VLOOKUP(compras_mes3[[#This Row],[CUIT]],Lista_CUIT[#All],3,0)),"CUIT NO CARGADO") -> 0 | R10: =IFERROR(IF(compras_mes3[[#This Row],[CUIT]]="","-",VLOOKUP(compras_mes3[[#This Row],[CUIT]],Lista_CUIT[#All],4,0)),"CUIT NO CARGADO") -> 0
B11: 45096 | C11: 1 | D11: 1 | E11: 171 | F11: 30707153142 | G11: =IFERROR(IF(compras_mes3[[#This Row],[CUIT]]="","-",VLOOKUP(compras_mes3[[#This Row],[CUIT]],Lista_CUIT[#All],2,0)),"CUIT NO CARGADO") -> AM STUDIOS SRL | H11: 30821.72 | K11: 3236.28 | P11: =SUM(compras_mes3[[#This Row],[NETO GRAVADO]:[Otros / No Grav.]]) -> 34058 | Q11: =IFERROR(IF(compras_mes3[[#This Row],[CUIT]]="","-",VLOOKUP(compras_mes3[[#This Row],[CUIT]],Lista_CUIT[#All],3,0)),"CUIT NO CARGADO") -> INSUMO | R11: =IFERROR(IF(compras_mes3[[#This Row],[CUIT]]="","-",VLOOKUP(compras_mes3[[#This Row],[CUIT]],Lista_CUIT[#All],4,0)),"CUIT NO CARGADO") -> BUENOS AIRES
B12: 45107 | C12: 1 | D12: 3 | E12: 2641 | F12: 33644262249 | G12: =IFERROR(IF(compras_mes3[[#This Row],[CUIT]]="","-",VLOOKUP(compras_mes3[[#This Row],[CUIT]],Lista_CUIT[#All],2,0)),"CUIT NO CARGADO") -> BOHERDI ELECTRONICA S R L | H12: 519675 | I12: =IF(compras_mes3[[#This Row],[NETO GRAVADO]]="","",compras_mes3[[#This Row],[NETO GRAVADO]]*0.21) -> 109131.75 | P12: =SUM(compras_mes3[[#This Row],[NETO GRAVADO]:[Otros / No Grav.]]) -> 628806.75 | Q12: =IFERROR(IF(compras_mes3[[#This Row],[CUIT]]="","-",VLOOKUP(compras_mes3[[#This Row],[CUIT]],Lista_CUIT[#All],3,0)),"CUIT NO CARGADO") -> 0 | R12: =IFERROR(IF(compras_mes3[[#This Row],[CUIT]]="","-",VLOOKUP(compras_mes3[[#This Row],[CUIT]],Lista_CUIT[#All],4,0)),"CUIT NO CARGADO") -> 0
B13: 45079 | C13: 1 | D13: 7 | E13: 12365 | F13: 30604413482 | G13: =IFERROR(IF(compras_mes3[[#This Row],[CUIT]]="","-",VLOOKUP(compras_mes3[[#This Row],[CUIT]],Lista_CUIT[#All],2,0)),"CUIT NO CARGADO") -> BULONERA VIETRI SOCIEDAD DE RESPONSABILIDAD LIMITADA | H13: 60285 | I13: =IF(compras_mes3[[#This Row],[NETO GRAVADO]]="","",compras_mes3[[#This Row],[NETO GRAVADO]]*0.21) -> 12659.85 | P13: =SUM(compras_mes3[[#This Row],[NETO GRAVADO]:[Otros / No Grav.]]) -> 72944.85 | Q13: =IFERROR(IF(compras_mes3[[#This Row],[CUIT]]="","-",VLOOKUP(compras_mes3[[#This Row],[CUIT]],Lista_CUIT[#All],3,0)),"CUIT NO CARGADO") -> 0 | R13: =IFERROR(IF(compras_mes3[[#This Row],[CUIT]]="","-",VLOOKUP(compras_mes3[[#This Row],[CUIT]],Lista_CUIT[#All],4,0)),"CUIT NO CARGADO") -> 0
B14: 45078 | C14: 1 | D14: 3 | E14: 191879 | F14: 30707135596 | G14: =IFERROR(IF(compras_mes3[[#This Row],[CUIT]]="","-",VLOOKUP(compras_mes3[[#This Row],[CUIT]],Lista_CUIT[#All],2,0)),"CUIT NO CARGADO") -> CITILAN ARGENTINA S.A. | H14: 5133.87 | I14: =IF(compras_mes3[[#This Row],[NETO GRAVADO]]="","",compras_mes3[[#This Row],[NETO GRAVADO]]*0.21) -> 1078.1127 | P14: =SUM(compras_mes3[[#This Row],[NETO GRAVADO]:[Otros / No Grav.]]) -> 6211.9827 | Q14: =IFERROR(IF(compras_mes3[[#This Row],[CUIT]]="","-",VLOOKUP(compras_mes3[[#This Row],[CUIT]],Lista_CUIT[#All],3,0)),"CUIT NO CARGADO") -> Servicios Gas, Luz, Etc | R14: =IFERROR(IF(compras_mes3[[#This Row],[CUIT]]="","-",VLOOKUP(compras_mes3[[#This Row],[CUIT]],Lista_CUIT[#All],4,0)),"CUIT NO CARGADO") -> 0
B15: 45079 | C15: 1 | D15: 5 | E15: 1185 | F15: 20324025430 | G15: =IFERROR(IF(compras_mes3[[#This Row],[CUIT]]="","-",VLOOKUP(compras_mes3[[#This Row],[CUIT]],Lista_CUIT[#All],2,0)),"CUIT NO CARGADO") -> DABUL NICOLAS ADRIAN | H15: 93387.6 | I15: =IF(compras_mes3[[#This Row],[NETO GRAVADO]]="","",compras_mes3[[#This Row],[NETO GRAVADO]]*0.21) -> 19611.396 | P15: =SUM(compras_mes3[[#This Row],[NETO GRAVADO]:[Otros / No Grav.]]) -> 112999 | Q15: =IFERROR(IF(compras_mes3[[#This Row],[CUIT]]="","-",VLOOKUP(compras_mes3[[#This Row],[CUIT]],Lista_CUIT[#All],3,0)),"CUIT NO CARGADO") -> 0 | R15: =IFERROR(IF(compras_mes3[[#This Row],[CUIT]]="","-",VLOOKUP(compras_mes3[[#This Row],[CUIT]],Lista_CUIT[#All],4,0)),"CUIT NO CARGADO") -> 0
B16: 45099 | C16: 2 | D16: 755 | E16: 3366 | F16: 30580111315 | G16: =IFERROR(IF(compras_mes3[[#This Row],[CUIT]]="","-",VLOOKUP(compras_mes3[[#This Row],[CUIT]],Lista_CUIT[#All],2,0)),"CUIT NO CARGADO") -> DHL EXPRESS (ARGENTINA) S.A. | I16: =IF(compras_mes3[[#This Row],[NETO GRAVADO]]="","",compras_mes3[[#This Row],[NETO GRAVADO]]*0.21) | O16: 12011.18 | P16: =SUM(compras_mes3[[#This Row],[NETO GRAVADO]:[Otros / No Grav.]]) -> 12011.18 | Q16: =IFERROR(IF(compras_mes3[[#This Row],[CUIT]]="","-",VLOOKUP(compras_mes3[[#This Row],[CUIT]],Lista_CUIT[#All],3,0)),"CUIT NO CARGADO") -> Gtos. Imp. | R16: =IFERROR(IF(compras_mes3[[#This Row],[CUIT]]="","-",VLOOKUP(compras_mes3[[#This Row],[CUIT]],Lista_CUIT[#All],4,0)),"CUIT NO CARGADO") -> 0
B17: 45082 | C17: 1 | D17: 700 | E17: 530115 | F17: 30580111315 | G17: =IFERROR(IF(compras_mes3[[#This Row],[CUIT]]="","-",VLOOKUP(compras_mes3[[#This Row],[CUIT]],Lista_CUIT[#All],2,0)),"CUIT NO CARGADO") -> DHL EXPRESS (ARGENTINA) S.A. | H17: 3507 | I17: =IF(compras_mes3[[#This Row],[NETO GRAVADO]]="","",compras_mes3[[#This Row],[NETO GRAVADO]]*0.21) -> 736.47 | O17: 139753.95 | P17: =SUM(compras_mes3[[#This Row],[NETO GRAVADO]:[Otros / No Grav.]]) -> 143997.42 | Q17: =IFERROR(IF(compras_mes3[[#This Row],[CUIT]]="","-",VLOOKUP(compras_mes3[[#This Row],[CUIT]],Lista_CUIT[#All],3,0)),"CUIT NO CARGADO") -> Gtos. Imp. | R17: =IFERROR(IF(compras_mes3[[#This Row],[CUIT]]="","-",VLOOKUP(compras_mes3[[#This Row],[CUIT]],Lista_CUIT[#All],4,0)),"CUIT NO CARGADO") -> 0
B18: 45096 | C18: 1 | D18: 700 | E18: 535871 | F18: 30580111315 | G18: =IFERROR(IF(compras_mes3[[#This Row],[CUIT]]="","-",VLOOKUP(compras_mes3[[#This Row],[CUIT]],Lista_CUIT[#All],2,0)),"CUIT NO CARGADO") -> DHL EXPRESS (ARGENTINA) S.A. | I18: =IF(compras_mes3[[#This Row],[NETO GRAVADO]]="","",compras_mes3[[#This Row],[NETO GRAVADO]]*0.21) | O18: 17213.14 | P18: =SUM(compras_mes3[[#This Row],[NETO GRAVADO]:[Otros / No Grav.]]) -> 17213.14 | Q18: =IFERROR(IF(compras_mes3[[#This Row],[CUIT]]="","-",VLOOKUP(compras_mes3[[#This Row],[CUIT]],Lista_CUIT[#All],3,0)),"CUIT NO CARGADO") -> Gtos. Imp. | R18: =IFERROR(IF(compras_mes3[[#This Row],[CUIT]]="","-",VLOOKUP(compras_mes3[[#This Row],[CUIT]],Lista_CUIT[#All],4,0)),"CUIT NO CARGADO") -> 0
B19: 45078 | C19: 1 | D19: 280 | E19: 1434438 | F19: 30580111315 | G19: =IFERROR(IF(compras_mes3[[#This Row],[CUIT]]="","-",VLOOKUP(compras_mes3[[#This Row],[CUIT]],Lista_CUIT[#All],2,0)),"CUIT NO CARGADO") -> DHL EXPRESS (ARGENTINA) S.A. | H19: 266573.08 | I19: =IF(compras_mes3[[#This Row],[NETO GRAVADO]]="","",compras_mes3[[#This Row],[NETO GRAVADO]]*0.21) -> 55980.347 | O19: -217973.74 | P19: =SUM(compras_mes3[[#This Row],[NETO GRAVADO]:[Otros / No Grav.]]) -> 104579.69 | Q19: =IFERROR(IF(compras_mes3[[#This Row],[CUIT]]="","-",VLOOKUP(compras_mes3[[#This Row],[CUIT]],Lista_CUIT[#All],3,0)),"CUIT NO CARGADO") -> Gtos. Imp. | R19: =IFERROR(IF(compras_mes3[[#This Row],[CUIT]]="","-",VLOOKUP(compras_mes3[[#This Row],[CUIT]],Lista_CUIT[#All],4,0)),"CUIT NO CARGADO") -> 0
B20: 45078 | C20: 1 | D20: 280 | E20: 1435509 | F20: 30580111315 | G20: =IFERROR(IF(compras_mes3[[#This Row],[CUIT]]="","-",VLOOKUP(compras_mes3[[#This Row],[CUIT]],Lista_CUIT[#All],2,0)),"CUIT NO CARGADO") -> DHL EXPRESS (ARGENTINA) S.A. | H20: 259322.23 | I20: =IF(compras_mes3[[#This Row],[NETO GRAVADO]]="","",compras_mes3[[#This Row],[NETO GRAVADO]]*0.21) -> 54457.667 | O20: -211804.35 | P20: =SUM(compras_mes3[[#This Row],[NETO GRAVADO]:[Otros / No Grav.]]) -> 101975.54 | Q20: =IFERROR(IF(compras_mes3[[#This Row],[CUIT]]="","-",VLOOKUP(compras_mes3[[#This Row],[CUIT]],Lista_CUIT[#All],3,0)),"CUIT NO CARGADO") -> Gtos. Imp. | R20: =IFERROR(IF(compras_mes3[[#This Row],[CUIT]]="","-",VLOOKUP(compras_mes3[[#This Row],[CUIT]],Lista_CUIT[#All],4,0)),"CUIT NO CARGADO") -> 0
B21: 45086 | C21: 1 | D21: 5 | E21: 5957 | F21: 33711557119 | G21: =IFERROR(IF(compras_mes3[[#This Row],[CUIT]]="","-",VLOOKUP(compras_mes3[[#This Row],[CUIT]],Lista_CUIT[#All],2,0)),"CUIT NO CARGADO") -> ELECTROMINGO S.R.L. | H21: 1452.48 | I21: =IF(compras_mes3[[#This Row],[NETO GRAVADO]]="","",compras_mes3[[#This Row],[NETO GRAVADO]]*0.21) -> 305.0208 | P21: =SUM(compras_mes3[[#This Row],[NETO GRAVADO]:[Otros / No Grav.]]) -> 1757.5008 | Q21: =IFERROR(IF(compras_mes3[[#This Row],[CUIT]]="","-",VLOOKUP(compras_mes3[[#This Row],[CUIT]],Lista_CUIT[#All],3,0)),"CUIT NO CARGADO") -> INSUMO | R21: =IFERROR(IF(compras_mes3[[#This Row],[CUIT]]="","-",VLOOKUP(compras_mes3[[#This Row],[CUIT]],Lista_CUIT[#All],4,0)),"CUIT NO CARGADO") -> BUENOS AIRES
B22: 45090 | C22: 1 | D22: 5 | E22: 5982 | F22: 33711557119 | G22: =IFERROR(IF(compras_mes3[[#This Row],[CUIT]]="","-",VLOOKUP(compras_mes3[[#This Row],[CUIT]],Lista_CUIT[#All],2,0)),"CUIT NO CARGADO") -> ELECTROMINGO S.R.L. | H22: 3075.45 | I22: 313.23 | K22: 166.29 | P22: =SUM(compras_mes3[[#This Row],[NETO GRAVADO]:[Otros / No Grav.]]) -> 3554.97 | Q22: =IFERROR(IF(compras_mes3[[#This Row],[CUIT]]="","-",VLOOKUP(compras_mes3[[#This Row],[CUIT]],Lista_CUIT[#All],3,0)),"CUIT NO CARGADO") -> INSUMO | R22: =IFERROR(IF(compras_mes3[[#This Row],[CUIT]]="","-",VLOOKUP(compras_mes3[[#This Row],[CUIT]],Lista_CUIT[#All],4,0)),"CUIT NO CARGADO") -> BUENOS AIRES
B23: 45099 | C23: 1 | D23: 4 | E23: 95972 | F23: 30559932236 | G23: =IFERROR(IF(compras_mes3[[#This Row],[CUIT]]="","-",VLOOKUP(compras_mes3[[#This Row],[CUIT]],Lista_CUIT[#All],2,0)),"CUIT NO CARGADO") -> ELECTRONICA ELEMON S A | H23: 49153.13 | I23: =IF(compras_mes3[[#This Row],[NETO GRAVADO]]="","",compras_mes3[[#This Row],[NETO GRAVADO]]*0.21) -> 10322.157 | P23: =SUM(compras_mes3[[#This Row],[NETO GRAVADO]:[Otros / No Grav.]]) -> 59475.287 | Q23: =IFERROR(IF(compras_mes3[[#This Row],[CUIT]]="","-",VLOOKUP(compras_mes3[[#This Row],[CUIT]],Lista_CUIT[#All],3,0)),"CUIT NO CARGADO") -> Mat. Prima | R23: =IFERROR(IF(compras_mes3[[#This Row],[CUIT]]="","-",VLOOKUP(compras_mes3[[#This Row],[CUIT]],Lista_CUIT[#All],4,0)),"CUIT NO CARGADO") -> 0
B24: 45104 | C24: 1 | D24: 4 | E24: 15482 | F24: 30709362875 | G24: =IFERROR(IF(compras_mes3[[#This Row],[CUIT]]="","-",VLOOKUP(compras_mes3[[#This Row],[CUIT]],Lista_CUIT[#All],2,0)),"CUIT NO CARGADO") -> ELINDAR SRL | H24: 9375.72 | K24: 984.45 | P24: =SUM(compras_mes3[[#This Row],[NETO GRAVADO]:[Otros / No Grav.]]) -> 10360.17 | Q24: =IFERROR(IF(compras_mes3[[#This Row],[CUIT]]="","-",VLOOKUP(compras_mes3[[#This Row],[CUIT]],Lista_CUIT[#All],3,0)),"CUIT NO CARGADO") -> REPUESTOS | R24: =IFERROR(IF(compras_mes3[[#This Row],[CUIT]]="","-",VLOOKUP(compras_mes3[[#This Row],[CUIT]],Lista_CUIT[#All],4,0)),"CUIT NO CARGADO") -> BUENOS AIRES
B25: 45093 | C25: 1 | D25: 106 | E25: 641207 | F25: 30594494187 | G25: =IFERROR(IF(compras_mes3[[#This Row],[CUIT]]="","-",VLOOKUP(compras_mes3[[#This Row],[CUIT]],Lista_CUIT[#All],2,0)),"CUIT NO CARGADO") -> FEDERAL EXPRESS CORPORATION | H25: 0 | I25: =IF(compras_mes3[[#This Row],[NETO GRAVADO]]="","",compras_mes3[[#This Row],[NETO GRAVADO]]*0.21) -> 0 | O25: 83121.39 | P25: =SUM(compras_mes3[[#This Row],[NETO GRAVADO]:[Otros / No Grav.]]) -> 83121.39 | Q25: =IFERROR(IF(compras_mes3[[#This Row],[CUIT]]="","-",VLOOKUP(compras_mes3[[#This Row],[CUIT]],Lista_CUIT[#All],3,0)),"CUIT NO CARGADO") -> Gtos. Imp. | R25: =IFERROR(IF(compras_mes3[[#This Row],[CUIT]]="","-",VLOOKUP(compras_mes3[[#This Row],[CUIT]],Lista_CUIT[#All],4,0)),"CUIT NO CARGADO") -> 0
B26: 45089 | C26: 1 | D26: 2 | E26: 173 | F26: 20125142851 | G26: =IFERROR(IF(compras_mes3[[#This Row],[CUIT]]="","-",VLOOKUP(compras_mes3[[#This Row],[CUIT]],Lista_CUIT[#All],2,0)),"CUIT NO CARGADO") -> FEDERICI NICOLAS JOSE | H26: 100169.76 | I26: =IF(compras_mes3[[#This Row],[NETO GRAVADO]]="","",compras_mes3[[#This Row],[NETO GRAVADO]]*0.21) -> 21035.65 | P26: =SUM(compras_mes3[[#This Row],[NETO GRAVADO]:[Otros / No Grav.]]) -> 121205.41 | Q26: =IFERROR(IF(compras_mes3[[#This Row],[CUIT]]="","-",VLOOKUP(compras_mes3[[#This Row],[CUIT]],Lista_CUIT[#All],3,0)),"CUIT NO CARGADO") -> INSUMO | R26: =IFERROR(IF(compras_mes3[[#This Row],[CUIT]]="","-",VLOOKUP(compras_mes3[[#This Row],[CUIT]],Lista_CUIT[#All],4,0)),"CUIT NO CARGADO") -> 0
B27: 45089 | C27: 1 | D27: 2 | E27: 174 | F27: 20125142851 | G27: =IFERROR(IF(compras_mes3[[#This Row],[CUIT]]="","-",VLOOKUP(compras_mes3[[#This Row],[CUIT]],Lista_CUIT[#All],2,0)),"CUIT NO CARGADO") -> FEDERICI NICOLAS JOSE | H27: 123030.24 | I27: =IF(compras_mes3[[#This Row],[NETO GRAVADO]]="","",compras_mes3[[#This Row],[NETO GRAVADO]]*0.21) -> 25836.35 | P27: =SUM(compras_mes3[[#This Row],[NETO GRAVADO]:[Otros / No Grav.]]) -> 148866.59 | Q27: =IFERROR(IF(compras_mes3[[#This Row],[CUIT]]="","-",VLOOKUP(compras_mes3[[#This Row],[CUIT]],Lista_CUIT[#All],3,0)),"CUIT NO CARGADO") -> INSUMO | R27: =IFERROR(IF(compras_mes3[[#This Row],[CUIT]]="","-",VLOOKUP(compras_mes3[[#This Row],[CUIT]],Lista_CUIT[#All],4,0)),"CUIT NO CARGADO") -> 0
B28: 45092 | C28: 1 | D28: 2 | E28: 175 | F28: 20125142851 | G28: =IFERROR(IF(compras_mes3[[#This Row],[CUIT]]="","-",VLOOKUP(compras_mes3[[#This Row],[CUIT]],Lista_CUIT[#All],2,0)),"CUIT NO CARGADO") -> FEDERICI NICOLAS JOSE | H28: 66779.84 | I28: =IF(compras_mes3[[#This Row],[NETO GRAVADO]]="","",compras_mes3[[#This Row],[NETO GRAVADO]]*0.21) -> 14023.766 | P28: =SUM(compras_mes3[[#This Row],[NETO GRAVADO]:[Otros / No Grav.]]) -> 80803.606 | Q28: =IFERROR(IF(compras_mes3[[#This Row],[CUIT]]="","-",VLOOKUP(compras_mes3[[#This Row],[CUIT]],Lista_CUIT[#All],3,0)),"CUIT NO CARGADO") -> INSUMO | R28: =IFERROR(IF(compras_mes3[[#This Row],[CUIT]]="","-",VLOOKUP(compras_mes3[[#This Row],[CUIT]],Lista_CUIT[#All],4,0)),"CUIT NO CARGADO") -> 0
B29: 45092 | C29: 1 | D29: 2 | E29: 176 | F29: 20125142851 | G29: =IFERROR(IF(compras_mes3[[#This Row],[CUIT]]="","-",VLOOKUP(compras_mes3[[#This Row],[CUIT]],Lista_CUIT[#All],2,0)),"CUIT NO CARGADO") -> FEDERICI NICOLAS JOSE | H29: 82020.16 | I29: =IF(compras_mes3[[#This Row],[NETO GRAVADO]]="","",compras_mes3[[#This Row],[NETO GRAVADO]]*0.21) -> 17224.234 | P29: =SUM(compras_mes3[[#This Row],[NETO GRAVADO]:[Otros / No Grav.]]) -> 99244.394 | Q29: =IFERROR(IF(compras_mes3[[#This Row],[CUIT]]="","-",VLOOKUP(compras_mes3[[#This Row],[CUIT]],Lista_CUIT[#All],3,0)),"CUIT NO CARGADO") -> INSUMO | R29: =IFERROR(IF(compras_mes3[[#This Row],[CUIT]]="","-",VLOOKUP(compras_mes3[[#This Row],[CUIT]],Lista_CUIT[#All],4,0)),"CUIT NO CARGADO") -> 0
B30: 45102 | C30: 1 | D30: 2 | E30: 177 | F30: 20125142851 | G30: =IFERROR(IF(compras_mes3[[#This Row],[CUIT]]="","-",VLOOKUP(compras_mes3[[#This Row],[CUIT]],Lista_CUIT[#All],2,0)),"CUIT NO CARGADO") -> FEDERICI NICOLAS JOSE | H30: 69483 | I30: =IF(compras_mes3[[#This Row],[NETO GRAVADO]]="","",compras_mes3[[#This Row],[NETO GRAVADO]]*0.21) -> 14591.43 | P30: =SUM(compras_mes3[[#This Row],[NETO GRAVADO]:[Otros / No Grav.]]) -> 84074.43 | Q30: =IFERROR(IF(compras_mes3[[#This Row],[CUIT]]="","-",VLOOKUP(compras_mes3[[#This Row],[CUIT]],Lista_CUIT[#All],3,0)),"CUIT NO CARGADO") -> INSUMO | R30: =IFERROR(IF(compras_mes3[[#This Row],[CUIT]]="","-",VLOOKUP(compras_mes3[[#This Row],[CUIT]],Lista_CUIT[#All],4,0)),"CUIT NO CARGADO") -> 0
B31: 45104 | C31: 1 | D31: 6 | E31: 19055 | F31: 30709459399 | G31: =IFERROR(IF(compras_mes3[[#This Row],[CUIT]]="","-",VLOOKUP(compras_mes3[[#This Row],[CUIT]],Lista_CUIT[#All],2,0)),"CUIT NO CARGADO") -> LA JUNIO SRL | H31: 30010.86 | K31: 3151.14 | P31: =SUM(compras_mes3[[#This Row],[NETO GRAVADO]:[Otros / No Grav.]]) -> 33162 | Q31: =IFERROR(IF(compras_mes3[[#This Row],[CUIT]]="","-",VLOOKUP(compras_mes3[[#This Row],[CUIT]],Lista_CUIT[#All],3,0)),"CUIT NO CARGADO") -> INSUMO | R31: =IFERROR(IF(compras_mes3[[#This Row],[CUIT]]="","-",VLOOKUP(compras_mes3[[#This Row],[CUIT]],Lista_CUIT[#All],4,0)),"CUIT NO CARGADO") -> CABA
B32: 45100 | C32: 1 | D32: 3 | E32: 1493657 | F32: 30712019359 | G32: =IFERROR(IF(compras_mes3[[#This Row],[CUIT]]="","-",VLOOKUP(compras_mes3[[#This Row],[CUIT]],Lista_CUIT[#All],2,0)),"CUIT NO CARGADO") -> LINKEDSTORE ARGENTINA S.R.L. | H32: 6032.23 | I32: =IF(compras_mes3[[#This Row],[NETO GRAVADO]]="","",compras_mes3[[#This Row],[NETO GRAVADO]]*0.21) -> 1266.7683 | P32: =SUM(compras_mes3[[#This Row],[NETO GRAVADO]:[Otros / No Grav.]]) -> 7298.9983 | Q32: =IFERROR(IF(compras_mes3[[#This Row],[CUIT]]="","-",VLOOKUP(compras_mes3[[#This Row],[CUIT]],Lista_CUIT[#All],3,0)),"CUIT NO CARGADO") -> Gastos Varios | R32: =IFERROR(IF(compras_mes3[[#This Row],[CUIT]]="","-",VLOOKUP(compras_mes3[[#This Row],[CUIT]],Lista_CUIT[#All],4,0)),"CUIT NO CARGADO") -> 0
B33: 45104 | C33: 1 | D33: 4 | E33: 2928 | F33: 30715002848 | G33: =IFERROR(IF(compras_mes3[[#This Row],[CUIT]]="","-",VLOOKUP(compras_mes3[[#This Row],[CUIT]],Lista_CUIT[#All],2,0)),"CUIT NO CARGADO") -> MASTER LEADER MUNDIAL S.A. | H33: 8243.8 | I33: =IF(compras_mes3[[#This Row],[NETO GRAVADO]]="","",compras_mes3[[#This Row],[NETO GRAVADO]]*0.21) -> 1731.198 | P33: =SUM(compras_mes3[[#This Row],[NETO GRAVADO]:[Otros / No Grav.]]) -> 9974.998 | Q33: =IFERROR(IF(compras_mes3[[#This Row],[CUIT]]="","-",VLOOKUP(compras_mes3[[#This Row],[CUIT]],Lista_CUIT[#All],3,0)),"CUIT NO CARGADO") -> INSUMO | R33: =IFERROR(IF(compras_mes3[[#This Row],[CUIT]]="","-",VLOOKUP(compras_mes3[[#This Row],[CUIT]],Lista_CUIT[#All],4,0)),"CUIT NO CARGADO") -> BUENOS AIRES
B34: 45090 | C34: 1 | D34: 6992 | E34: 15386 | F34: 30678774495 | G34: =IFERROR(IF(compras_mes3[[#This Row],[CUIT]]="","-",VLOOKUP(compras_mes3[[#This Row],[CUIT]],Lista_CUIT[#All],2,0)),"CUIT NO CARGADO") -> OPER. DE EST. DE SERV. SA | H34: 7965.86 | I34: =IF(compras_mes3[[#This Row],[NETO GRAVADO]]="","",compras_mes3[[#This Row],[NETO GRAVADO]]*0.21) -> 1672.8306 | O34: 1463.11 | P34: =SUM(compras_mes3[[#This Row],[NETO GRAVADO]:[Otros / No Grav.]]) -> 11101.801 | Q34: =IFERROR(IF(compras_mes3[[#This Row],[CUIT]]="","-",VLOOKUP(compras_mes3[[#This Row],[CUIT]],Lista_CUIT[#All],3,0)),"CUIT NO CARGADO") -> COMBUSTIBLE | R34: =IFERROR(IF(compras_mes3[[#This Row],[CUIT]]="","-",VLOOKUP(compras_mes3[[#This Row],[CUIT]],Lista_CUIT[#All],4,0)),"CUIT NO CARGADO") -> 0
B35: 45078 | C35: 1 | D35: 3 | E35: 652 | F35: 30715402765 | G35: =IFERROR(IF(compras_mes3[[#This Row],[CUIT]]="","-",VLOOKUP(compras_mes3[[#This Row],[CUIT]],Lista_CUIT[#All],2,0)),"CUIT NO CARGADO") -> RIO 265 S.R.L. | H35: 14462.81 | I35: =IF(compras_mes3[[#This Row],[NETO GRAVADO]]="","",compras_mes3[[#This Row],[NETO GRAVADO]]*0.21) -> 3037.1901 | P35: =SUM(compras_mes3[[#This Row],[NETO GRAVADO]:[Otros / No Grav.]]) -> 17500 | Q35: =IFERROR(IF(compras_mes3[[#This Row],[CUIT]]="","-",VLOOKUP(compras_mes3[[#This Row],[CUIT]],Lista_CUIT[#All],3,0)),"CUIT NO CARGADO") -> Gastos Varios | R35: =IFERROR(IF(compras_mes3[[#This Row],[CUIT]]="","-",VLOOKUP(compras_mes3[[#This Row],[CUIT]],Lista_CUIT[#All],4,0)),"CUIT NO CARGADO") -> 0
B36: 45078 | C36: 1 | D36: 1 | E36: 613 | F36: 30715048066 | G36: =IFERROR(IF(compras_mes3[[#This Row],[CUIT]]="","-",VLOOKUP(compras_mes3[[#This Row],[CUIT]],Lista_CUIT[#All],2,0)),"CUIT NO CARGADO") -> ROLLS Y EMPANADAS SA | H36: 128860 | I36: =IF(compras_mes3[[#This Row],[NETO GRAVADO]]="","",compras_mes3[[#This Row],[NETO GRAVADO]]*0.21) -> 27060.6 | P36: =SUM(compras_mes3[[#This Row],[NETO GRAVADO]:[Otros / No Grav.]]) -> 155920.6 | Q36: =IFERROR(IF(compras_mes3[[#This Row],[CUIT]]="","-",VLOOKUP(compras_mes3[[#This Row],[CUIT]],Lista_CUIT[#All],3,0)),"CUIT NO CARGADO") -> CATERING | R36: =IFERROR(IF(compras_mes3[[#This Row],[CUIT]]="","-",VLOOKUP(compras_mes3[[#This Row],[CUIT]],Lista_CUIT[#All],4,0)),"CUIT NO CARGADO") -> 0
B37: 45099 | C37: 1 | D37: 1 | E37: 631 | F37: 30715048066 | G37: =IFERROR(IF(compras_mes3[[#This Row],[CUIT]]="","-",VLOOKUP(compras_mes3[[#This Row],[CUIT]],Lista_CUIT[#All],2,0)),"CUIT NO CARGADO") -> ROLLS Y EMPANADAS SA | H37: 134985 | I37: =IF(compras_mes3[[#This Row],[NETO GRAVADO]]="","",compras_mes3[[#This Row],[NETO GRAVADO]]*0.21) -> 28346.85 | P37: =SUM(compras_mes3[[#This Row],[NETO GRAVADO]:[Otros / No Grav.]]) -> 163331.85 | Q37: =IFERROR(IF(compras_mes3[[#This Row],[CUIT]]="","-",VLOOKUP(compras_mes3[[#This Row],[CUIT]],Lista_CUIT[#All],3,0)),"CUIT NO CARGADO") -> CATERING | R37: =IFERROR(IF(compras_mes3[[#This Row],[CUIT]]="","-",VLOOKUP(compras_mes3[[#This Row],[CUIT]],Lista_CUIT[#All],4,0)),"CUIT NO CARGADO") -> 0
B38: 45082 | C38: 1 | D38: 5 | E38: 4100 | F38: 20348111478 | G38: =IFERROR(IF(compras_mes3[[#This Row],[CUIT]]="","-",VLOOKUP(compras_mes3[[#This Row],[CUIT]],Lista_CUIT[#All],2,0)),"CUIT NO CARGADO") -> SAENZ GERMAN | H38: 11161.98 | I38: =IF(compras_mes3[[#This Row],[NETO GRAVADO]]="","",compras_mes3[[#This Row],[NETO GRAVADO]]*0.21) -> 2344.0158 | P38: =SUM(compras_mes3[[#This Row],[NETO GRAVADO]:[Otros / No Grav.]]) -> 13505.996 | Q38: =IFERROR(IF(compras_mes3[[#This Row],[CUIT]]="","-",VLOOKUP(compras_mes3[[#This Row],[CUIT]],Lista_CUIT[#All],3,0)),"CUIT NO CARGADO") -> INSUMO | R38: =IFERROR(IF(compras_mes3[[#This Row],[CUIT]]="","-",VLOOKUP(compras_mes3[[#This Row],[CUIT]],Lista_CUIT[#All],4,0)),"CUIT NO CARGADO") -> BUENOS AIRES
B39: 45098 | C39: 1 | D39: 15 | E39: 9453 | F39: 33708907869 | G39: =IFERROR(IF(compras_mes3[[#This Row],[CUIT]]="","-",VLOOKUP(compras_mes3[[#This Row],[CUIT]],Lista_CUIT[#All],2,0)),"CUIT NO CARGADO") -> SERCAP INSUMOS S.R.L. | H39: 14932.13 | K39: 1567.87 | P39: =SUM(compras_mes3[[#This Row],[NETO GRAVADO]:[Otros / No Grav.]]) -> 16500 | Q39: =IFERROR(IF(compras_mes3[[#This Row],[CUIT]]="","-",VLOOKUP(compras_mes3[[#This Row],[CUIT]],Lista_CUIT[#All],3,0)),"CUIT NO CARGADO") -> INSUMO | R39: =IFERROR(IF(compras_mes3[[#This Row],[CUIT]]="","-",VLOOKUP(compras_mes3[[#This Row],[CUIT]],Lista_CUIT[#All],4,0)),"CUIT NO CARGADO")
B40: 45107 | C40: 1 | D40: 6 | E40: 12077 | F40: 30707756434 | G40: =IFERROR(IF(compras_mes3[[#This Row],[CUIT]]="","-",VLOOKUP(compras_mes3[[#This Row],[CUIT]],Lista_CUIT[#All],2,0)),"CUIT NO CARGADO") -> SERVICIO INTEGRAL DE LIMPIEZA SRL | H40: 33600 | I40: =IF(compras_mes3[[#This Row],[NETO GRAVADO]]="","",compras_mes3[[#This Row],[NETO GRAVADO]]*0.21) -> 7056 | P40: =SUM(compras_mes3[[#This Row],[NETO GRAVADO]:[Otros / No Grav.]]) -> 40656 | Q40: =IFERROR(IF(compras_mes3[[#This Row],[CUIT]]="","-",VLOOKUP(compras_mes3[[#This Row],[CUIT]],Lista_CUIT[#All],3,0)),"CUIT NO CARGADO") -> Mantenimiento | R40: =IFERROR(IF(compras_mes3[[#This Row],[CUIT]]="","-",VLOOKUP(compras_mes3[[#This Row],[CUIT]],Lista_CUIT[#All],4,0)),"CUIT NO CARGADO") -> 0
B41: 45088 | C41: 1 | D41: 2466 | E41: 519676 | F41: 30678814357 | G41: =IFERROR(IF(compras_mes3[[#This Row],[CUIT]]="","-",VLOOKUP(compras_mes3[[#This Row],[CUIT]],Lista_CUIT[#All],2,0)),"CUIT NO CARGADO") -> TELEFONICA MOVILES ARG | H41: 4481 | J41: 1209.87 | L41: 134.43 | O41: 235.84 | P41: =SUM(compras_mes3[[#This Row],[NETO GRAVADO]:[Otros / No Grav.]]) -> 6061.14 | Q41: =IFERROR(IF(compras_mes3[[#This Row],[CUIT]]="","-",VLOOKUP(compras_mes3[[#This Row],[CUIT]],Lista_CUIT[#All],3,0)),"CUIT NO CARGADO") -> SERVICIOS | R41: =IFERROR(IF(compras_mes3[[#This Row],[CUIT]]="","-",VLOOKUP(compras_mes3[[#This Row],[CUIT]],Lista_CUIT[#All],4,0)),"CUIT NO CARGADO") -> 0 | S41: COD 5
B42: 45096 | C42: 1 | D42: 42 | E42: 6635 | F42: 30662533072 | G42: =IFERROR(IF(compras_mes3[[#This Row],[CUIT]]="","-",VLOOKUP(compras_mes3[[#This Row],[CUIT]],Lista_CUIT[#All],2,0)),"CUIT NO CARGADO") -> ULTRALIGHT SRL | H42: 15701.65 | I42: =IF(compras_mes3[[#This Row],[NETO GRAVADO]]="","",compras_mes3[[#This Row],[NETO GRAVADO]]*0.21) -> 3297.3465 | P42: =SUM(compras_mes3[[#This Row],[NETO GRAVADO]:[Otros / No Grav.]]) -> 18998.997 | Q42: =IFERROR(IF(compras_mes3[[#This Row],[CUIT]]="","-",VLOOKUP(compras_mes3[[#This Row],[CUIT]],Lista_CUIT[#All],3,0)),"CUIT NO CARGADO") -> INSUMO | R42: =IFERROR(IF(compras_mes3[[#This Row],[CUIT]]="","-",VLOOKUP(compras_mes3[[#This Row],[CUIT]],Lista_CUIT[#All],4,0)),"CUIT NO CARGADO") -> CABA | S42: COD 5
B43: 45084 | C43: 1 | D43: 10 | E43: 193 | F43: 20388544539 | G43: =IFERROR(IF(compras_mes3[[#This Row],[CUIT]]="","-",VLOOKUP(compras_mes3[[#This Row],[CUIT]],Lista_CUIT[#All],2,0)),"CUIT NO CARGADO") -> WARD IVAN NICOLAS | H43: 12578.51 | I43: =IF(compras_mes3[[#This Row],[NETO GRAVADO]]="","",compras_mes3[[#This Row],[NETO GRAVADO]]*0.21) -> 2641.4871 | P43: =SUM(compras_mes3[[#This Row],[NETO GRAVADO]:[Otros / No Grav.]]) -> 15219.997 | Q43: =IFERROR(IF(compras_mes3[[#This Row],[CUIT]]="","-",VLOOKUP(compras_mes3[[#This Row],[CUIT]],Lista_CUIT[#All],3,0)),"CUIT NO CARGADO") -> 0 | R43: =IFERROR(IF(compras_mes3[[#This Row],[CUIT]]="","-",VLOOKUP(compras_mes3[[#This Row],[CUIT]],Lista_CUIT[#All],4,0)),"CUIT NO CARGADO") -> 0
B44: Total | H44: =SUBTOTAL(109,compras_mes3[NETO GRAVADO]) -> 2178475.4 | I44: =SUBTOTAL(109,compras_mes3[IVA 21 %]) -> 437597.56 | J44: =SUBTOTAL(109,compras_mes3[IVA 27%]) -> 1209.87 | K44: =SUBTOTAL(109,compras_mes3[IVA 10,5%]) -> 9470.82 | L44: =SUBTOTAL(109,compras_mes3[PERC. IVA]) -> 134.43 | M44: =SUBTOTAL(109,compras_mes3[PERC IIBB BS AS]) -> 0 | N44: =SUBTOTAL(109,compras_mes3[PERC. IIBB CABA]) -> 0 | O44: =SUBTOTAL(109,compras_mes3[Otros / No Grav.]) -> -175979.48 | P44: =SUBTOTAL(109,compras_mes3[TOTAL]) -> 2450908.6
D49: LIQUIDACION EXTRACTOS BANCARIOS-TARJETAS
D50: FECHA | E50: NRO CPTE | F50: BANCO | G50: NETO | H50: IVA 21% | I50: IVA 10,5% | J50: RET IIBB CABA | K50: PERC IVA | L50: PERC IIBB
D51: 45079 | E51: 103467 | F51: seg.permisos de embarque(Credicop) | G51: 6021.25 | H51: =extracto_banco_mes3[[#This Row],[NETO]]*0.21 -> 1264.4625 | K51: 180.64
D52: 45107 | E52: 300623 | F52: BCO CREDICOOP | G52: 23306.54 | H52: =extracto_banco_mes3[[#This Row],[NETO]]*0.21 -> 4894.3734 | K52: 678.8
D53: 45106 | E53: 1037971 | F53: COMISION POR GESTION DE PERMISOS INCUMPLIDOS | G53: 2562 | H53: =extracto_banco_mes3[[#This Row],[NETO]]*0.21 -> 538.02 | K53: 76.86
D54: Total | G54: =SUBTOTAL(109,extracto_banco_mes3[NETO]) -> 31889.79 | H54: =SUBTOTAL(109,extracto_banco_mes3[IVA 21%]) -> 6696.8559 | I54: =SUBTOTAL(109,extracto_banco_mes3[IVA 10,5%]) -> 0 | J54: =SUBTOTAL(109,extracto_banco_mes3[RET IIBB CABA]) -> 0 | K54: =SUBTOTAL(109,extracto_banco_mes3[PERC IVA]) -> 936.3 | L54: =SUBTOTAL(109,extracto_banco_mes3[PERC IIBB]) -> 0
D56: FACTURAS C
D57: FECHA | E57: PTO VTA | F57: FC Nº | G57: CUIT | H57: RAZON SOCIAL | I57: TOTAL | J57: TIPO DE GASTO | K57: Provincia
D58: 45082 | E58: 1 | F58: 100 | G58: 20341465134 | H58: =IFERROR(IF(factura_c_mes3[[#This Row],[CUIT]]="","-",VLOOKUP(factura_c_mes3[[#This Row],[CUIT]],Lista_CUIT[#All],2,0)),"CUIT NO CARGADO") -> ABELEDO AGUSTIN ENRIQUE | I58: 281660 | J58: =IFERROR(IF(factura_c_mes3[[#This Row],[CUIT]]="","-",VLOOKUP(factura_c_mes3[[#This Row],[CUIT]],Lista_CUIT[#All],3,0)),"CUIT NO CARGADO") -> Mantenimiento | K58: =IFERROR(IF(factura_c_mes3[[#This Row],[CUIT]]="","-",VLOOKUP(factura_c_mes3[[#This Row],[CUIT]],Lista_CUIT[#All],4,0)),"CUIT NO CARGADO") -> CABA
D59: 45078 | E59: 4 | F59: 47 | G59: 23214737914 | H59: =IFERROR(IF(factura_c_mes3[[#This Row],[CUIT]]="","-",VLOOKUP(factura_c_mes3[[#This Row],[CUIT]],Lista_CUIT[#All],2,0)),"CUIT NO CARGADO") -> SBARRA GABRIELA BEATRIZ | I59: 301780 | J59: =IFERROR(IF(factura_c_mes3[[#This Row],[CUIT]]="","-",VLOOKUP(factura_c_mes3[[#This Row],[CUIT]],Lista_CUIT[#All],3,0)),"CUIT NO CARGADO") -> 0 | K59: =IFERROR(IF(factura_c_mes3[[#This Row],[CUIT]]="","-",VLOOKUP(factura_c_mes3[[#This Row],[CUIT]],Lista_CUIT[#All],4,0)),"CUIT NO CARGADO") -> 0
D60: 45078 | E60: 2 | F60: 145 | G60: 20136544625 | H60: =IFERROR(IF(factura_c_mes3[[#This Row],[CUIT]]="","-",VLOOKUP(factura_c_mes3[[#This Row],[CUIT]],Lista_CUIT[#All],2,0)),"CUIT NO CARGADO") -> RODRIGUEZ DE LA FUEN HECTOR MARCELO | I60: 300000 | J60: =IFERROR(IF(factura_c_mes3[[#This Row],[CUIT]]="","-",VLOOKUP(factura_c_mes3[[#This Row],[CUIT]],Lista_CUIT[#All],3,0)),"CUIT NO CARGADO") -> Hon. Admin. | K60: =IFERROR(IF(factura_c_mes3[[#This Row],[CUIT]]="","-",VLOOKUP(factura_c_mes3[[#This Row],[CUIT]],Lista_CUIT[#All],4,0)),"CUIT NO CARGADO") -> 0
D61: 45078 | E61: 1 | F61: 24 | G61: 20365938688 | H61: =IFERROR(IF(factura_c_mes3[[#This Row],[CUIT]]="","-",VLOOKUP(factura_c_mes3[[#This Row],[CUIT]],Lista_CUIT[#All],2,0)),"CUIT NO CARGADO") -> LIPANOVICH JUAN CRUZ | I61: 450000 | J61: =IFERROR(IF(factura_c_mes3[[#This Row],[CUIT]]="","-",VLOOKUP(factura_c_mes3[[#This Row],[CUIT]],Lista_CUIT[#All],3,0)),"CUIT NO CARGADO") -> SOFTWARE | K61: =IFERROR(IF(factura_c_mes3[[#This Row],[CUIT]]="","-",VLOOKUP(factura_c_mes3[[#This Row],[CUIT]],Lista_CUIT[#All],4,0)),"CUIT NO CARGADO") -> 0
D62: 45078 | E62: 3 | F62: 742 | G62: 20086277523 | H62: =IFERROR(IF(factura_c_mes3[[#This Row],[CUIT]]="","-",VLOOKUP(factura_c_mes3[[#This Row],[CUIT]],Lista_CUIT[#All],2,0)),"CUIT NO CARGADO") -> ESTUDIO BOTINDARI | I62: 81000 | J62: =IFERROR(IF(factura_c_mes3[[#This Row],[CUIT]]="","-",VLOOKUP(factura_c_mes3[[#This Row],[CUIT]],Lista_CUIT[#All],3,0)),"CUIT NO CARGADO") -> HONORARIOS | K62: =IFERROR(IF(factura_c_mes3[[#This Row],[CUIT]]="","-",VLOOKUP(factura_c_mes3[[#This Row],[CUIT]],Lista_CUIT[#All],4,0)),"CUIT NO CARGADO") -> 0
D63: 45081 | E63: 2 | F63: 84 | G63: 20244271740 | H63: =IFERROR(IF(factura_c_mes3[[#This Row],[CUIT]]="","-",VLOOKUP(factura_c_mes3[[#This Row],[CUIT]],Lista_CUIT[#All],2,0)),"CUIT NO CARGADO") -> KENNEL SEBASTIAN | I63: 386400 | J63: =IFERROR(IF(factura_c_mes3[[#This Row],[CUIT]]="","-",VLOOKUP(factura_c_mes3[[#This Row],[CUIT]],Lista_CUIT[#All],3,0)),"CUIT NO CARGADO") -> Software Mantenimiento | K63: =IFERROR(IF(factura_c_mes3[[#This Row],[CUIT]]="","-",VLOOKUP(factura_c_mes3[[#This Row],[CUIT]],Lista_CUIT[#All],4,0)),"CUIT NO CARGADO") -> 0
D64: 45084 | E64: 3 | F64: 53 | G64: 20403931420 | H64: =IFERROR(IF(factura_c_mes3[[#This Row],[CUIT]]="","-",VLOOKUP(factura_c_mes3[[#This Row],[CUIT]],Lista_CUIT[#All],2,0)),"CUIT NO CARGADO") -> FIORENTINO JORGE IGNACIO | I64: 149120 | J64: =IFERROR(IF(factura_c_mes3[[#This Row],[CUIT]]="","-",VLOOKUP(factura_c_mes3[[#This Row],[CUIT]],Lista_CUIT[#All],3,0)),"CUIT NO CARGADO") -> Hon. Admin. | K64: =IFERROR(IF(factura_c_mes3[[#This Row],[CUIT]]="","-",VLOOKUP(factura_c_mes3[[#This Row],[CUIT]],Lista_CUIT[#All],4,0)),"CUIT NO CARGADO") -> 0
D65: 45086 | E65: 1 | F65: 19 | G65: 20417805878 | H65: =IFERROR(IF(factura_c_mes3[[#This Row],[CUIT]]="","-",VLOOKUP(factura_c_mes3[[#This Row],[CUIT]],Lista_CUIT[#All],2,0)),"CUIT NO CARGADO") -> FERABOLI OSPAL SANTIAGO HERNAN | I65: 128720 | J65: =IFERROR(IF(factura_c_mes3[[#This Row],[CUIT]]="","-",VLOOKUP(factura_c_mes3[[#This Row],[CUIT]],Lista_CUIT[#All],3,0)),"CUIT NO CARGADO") -> Mantenimiento | K65: =IFERROR(IF(factura_c_mes3[[#This Row],[CUIT]]="","-",VLOOKUP(factura_c_mes3[[#This Row],[CUIT]],Lista_CUIT[#All],4,0)),"CUIT NO CARGADO") -> 0
D66: 45089 | E66: 2 | F66: 572 | G66: 20400104094 | H66: =IFERROR(IF(factura_c_mes3[[#This Row],[CUIT]]="","-",VLOOKUP(factura_c_mes3[[#This Row],[CUIT]],Lista_CUIT[#All],2,0)),"CUIT NO CARGADO") -> FEDERICO BOTINDARI | I66: 15432 | J66: =IFERROR(IF(factura_c_mes3[[#This Row],[CUIT]]="","-",VLOOKUP(factura_c_mes3[[#This Row],[CUIT]],Lista_CUIT[#All],3,0)),"CUIT NO CARGADO") -> HONORARIOS | K66: =IFERROR(IF(factura_c_mes3[[#This Row],[CUIT]]="","-",VLOOKUP(factura_c_mes3[[#This Row],[CUIT]],Lista_CUIT[#All],4,0)),"CUIT NO CARGADO") -> 0
D67: 45089 | E67: 4 | F67: 48 | G67: 23214737914 | H67: =IFERROR(IF(factura_c_mes3[[#This Row],[CUIT]]="","-",VLOOKUP(factura_c_mes3[[#This Row],[CUIT]],Lista_CUIT[#All],2,0)),"CUIT NO CARGADO") -> SBARRA GABRIELA BEATRIZ | I67: 266770 | J67: =IFERROR(IF(factura_c_mes3[[#This Row],[CUIT]]="","-",VLOOKUP(factura_c_mes3[[#This Row],[CUIT]],Lista_CUIT[#All],3,0)),"CUIT NO CARGADO") -> 0 | K67: =IFERROR(IF(factura_c_mes3[[#This Row],[CUIT]]="","-",VLOOKUP(factura_c_mes3[[#This Row],[CUIT]],Lista_CUIT[#All],4,0)),"CUIT NO CARGADO") -> 0
D68: 45098 | E68: 4 | F68: 14 | G68: 20341462933 | H68: =IFERROR(IF(factura_c_mes3[[#This Row],[CUIT]]="","-",VLOOKUP(factura_c_mes3[[#This Row],[CUIT]],Lista_CUIT[#All],2,0)),"CUIT NO CARGADO") -> CASTIGLIONI MATIAS EZEQUIEL | I68: 488500 | J68: =IFERROR(IF(factura_c_mes3[[#This Row],[CUIT]]="","-",VLOOKUP(factura_c_mes3[[#This Row],[CUIT]],Lista_CUIT[#All],3,0)),"CUIT NO CARGADO") -> ASESORAMIENTO | K68: =IFERROR(IF(factura_c_mes3[[#This Row],[CUIT]]="","-",VLOOKUP(factura_c_mes3[[#This Row],[CUIT]],Lista_CUIT[#All],4,0)),"CUIT NO CARGADO") -> BUENOS AIRES
D69: 45078 | E69: 7 | F69: 316588 | G69: 20259150249 | H69: =IFERROR(IF(factura_c_mes3[[#This Row],[CUIT]]="","-",VLOOKUP(factura_c_mes3[[#This Row],[CUIT]],Lista_CUIT[#All],2,0)),"CUIT NO CARGADO") -> BIANCHI CRISTIAN MAXIMILIANO | I69: 15455.08 | J69: =IFERROR(IF(factura_c_mes3[[#This Row],[CUIT]]="","-",VLOOKUP(factura_c_mes3[[#This Row],[CUIT]],Lista_CUIT[#All],3,0)),"CUIT NO CARGADO") -> Gastos Varios | K69: =IFERROR(IF(factura_c_mes3[[#This Row],[CUIT]]="","-",VLOOKUP(factura_c_mes3[[#This Row],[CUIT]],Lista_CUIT[#All],4,0)),"CUIT NO CARGADO") -> 0
... D71: 45100 | E71: 4 | F71: 94073 | G71: 20347495027 | H71: =IFERROR(IF(factura_c_mes3[[#This Row],[CUIT]]="","-",VLOOKUP(factura_c_mes3[[#This Row],[CUIT]],Lista_CUIT[#All],2,0)),"CUIT NO CARGADO") -> BARRAGAN FEDERICO ANDRES | I71: 5571 | J71: =IFERROR(IF(factura_c_mes3[[#This Row],[CUIT]]="","-",VLOOKUP(factura_c_mes3[[#This Row],[CUIT]],Lista_CUIT[#All],3,0)),"CUIT NO CARGADO") -> 0 | K71: =IFERROR(IF(factura_c_mes3[[#This Row],[CUIT]]="","-",VLOOKUP(factura_c_mes3[[#This Row],[CUIT]],Lista_CUIT[#All],4,0)),"CUIT NO CARGADO") -> 0
D72: Total | I72: =SUBTOTAL(109,factura_c_mes3[TOTAL]) -> 2892036.1
B78: LIBRO IVA VENTAS | K78: =N1 -> 45078
B80: VENTAS "A"
B81: FECHA | C81: TIPO | D81: PTO VENTA | E81: Nº FACTURA | F81: CUIT | G81: RAZON SOCIAL | H81: IMPORTE NETO | I81: IVA 21% | J81: IVA 10,5% | K81: EXENTO | L81: TOTAL | M81: Provincia
B82: 45089 | C82: 1 | D82: 3 | E82: 135 | F82: 30638318470 | G82: =IFERROR(IF(venta_a_mes3[[#This Row],[CUIT]]="","-",VLOOKUP(venta_a_mes3[[#This Row],[CUIT]],Lista_CUIT[#All],2,0)),"CUIT NO CARGADO") -> DELTA COMPRESION S R L | H82: 10451980 | J82: 1097457.9 | L82: =SUM(venta_a_mes3[[#This Row],[IMPORTE NETO]:[EXENTO]]) -> 11549438
B83: 45103 | C83: 1 | D83: 3 | E83: 137 | F83: 30638318470 | G83: =IFERROR(IF(venta_a_mes3[[#This Row],[CUIT]]="","-",VLOOKUP(venta_a_mes3[[#This Row],[CUIT]],Lista_CUIT[#All],2,0)),"CUIT NO CARGADO") -> DELTA COMPRESION S R L | H83: 720924.5 | I83: =venta_a_mes3[[#This Row],[IMPORTE NETO]]*0.21 -> 151394.14 | L83: =SUM(venta_a_mes3[[#This Row],[IMPORTE NETO]:[EXENTO]]) -> 872318.65
B84: 45103 | C84: 1 | D84: 3 | E84: 138 | F84: 30638318470 | G84: =IFERROR(IF(venta_a_mes3[[#This Row],[CUIT]]="","-",VLOOKUP(venta_a_mes3[[#This Row],[CUIT]],Lista_CUIT[#All],2,0)),"CUIT NO CARGADO") -> DELTA COMPRESION S R L | H84: 566720 | I84: =venta_a_mes3[[#This Row],[IMPORTE NETO]]*0.21 -> 119011.2 | L84: =SUM(venta_a_mes3[[#This Row],[IMPORTE NETO]:[EXENTO]]) -> 685731.2
B85: 45103 | C85: 1 | D85: 3 | E85: 136 | F85: 30638318470 | G85: =IFERROR(IF(venta_a_mes3[[#This Row],[CUIT]]="","-",VLOOKUP(venta_a_mes3[[#This Row],[CUIT]],Lista_CUIT[#All],2,0)),"CUIT NO CARGADO") -> DELTA COMPRESION S R L | H85: 662202.2 | I85: =venta_a_mes3[[#This Row],[IMPORTE NETO]]*0.21 -> 139062.46 | L85: =SUM(venta_a_mes3[[#This Row],[IMPORTE NETO]:[EXENTO]]) -> 801264.66
B86: 45103 | C86: 1 | D86: 3 | E86: 140 | F86: 30638318470 | G86: =IFERROR(IF(venta_a_mes3[[#This Row],[CUIT]]="","-",VLOOKUP(venta_a_mes3[[#This Row],[CUIT]],Lista_CUIT[#All],2,0)),"CUIT NO CARGADO") -> DELTA COMPRESION S R L | H86: 454894 | I86: =venta_a_mes3[[#This Row],[IMPORTE NETO]]*0.21 -> 95527.74 | L86: =SUM(venta_a_mes3[[#This Row],[IMPORTE NETO]:[EXENTO]]) -> 550421.74
B87: 45103 | C87: 1 | D87: 3 | E87: 139 | F87: 30638318470 | G87: =IFERROR(IF(venta_a_mes3[[#This Row],[CUIT]]="","-",VLOOKUP(venta_a_mes3[[#This Row],[CUIT]],Lista_CUIT[#All],2,0)),"CUIT NO CARGADO") -> DELTA COMPRESION S R L | H87: 543950 | I87: =venta_a_mes3[[#This Row],[IMPORTE NETO]]*0.21 -> 114229.5 | L87: =SUM(venta_a_mes3[[#This Row],[IMPORTE NETO]:[EXENTO]]) -> 658179.5
B88: 45103 | C88: 2 | D88: 3 | E88: 5 | F88: 30638318470 | G88: =IFERROR(IF(venta_a_mes3[[#This Row],[CUIT]]="","-",VLOOKUP(venta_a_mes3[[#This Row],[CUIT]],Lista_CUIT[#All],2,0)),"CUIT NO CARGADO") -> DELTA COMPRESION S R L | H88: 4306598.9 | I88: =venta_a_mes3[[#This Row],[IMPORTE NETO]]*0.21 -> 904385.77 | L88: =SUM(venta_a_mes3[[#This Row],[IMPORTE NETO]:[EXENTO]]) -> 5210984.7
G89: =IFERROR(IF(venta_a_mes3[[#This Row],[CUIT]]="","-",VLOOKUP(venta_a_mes3[[#This Row],[CUIT]],Lista_CUIT[#All],2,0)),"CUIT NO CARGADO") -> - | I89: =venta_a_mes3[[#This Row],[IMPORTE NETO]]*0.21 -> 0 | L89: =SUM(venta_a_mes3[[#This Row],[IMPORTE NETO]:[EXENTO]]) -> 0
G90: =IFERROR(IF(venta_a_mes3[[#This Row],[CUIT]]="","-",VLOOKUP(venta_a_mes3[[#This Row],[CUIT]],Lista_CUIT[#All],2,0)),"CUIT NO CARGADO") -> - | I90: =venta_a_mes3[[#This Row],[IMPORTE NETO]]*0.21 -> 0 | L90: =SUM(venta_a_mes3[[#This Row],[IMPORTE NETO]:[EXENTO]]) -> 0
B91: Total | H91: =SUBTOTAL(109,venta_a_mes3[IMPORTE NETO]) -> 17707270 | I91: =SUBTOTAL(109,venta_a_mes3[IVA 21%]) -> 1523610.8 | J91: =SUBTOTAL(109,venta_a_mes3[IVA 10,5%]) -> 1097457.9 | K91: =SUBTOTAL(109,venta_a_mes3[EXENTO]) -> 0 | L91: =SUBTOTAL(109,venta_a_mes3[TOTAL]) -> 20328338 | M91: =SUBTOTAL(103,venta_a_mes3[Provincia]) -> 0
B94: VENTAS "B"
B95: FECHA | C95: TIPO | D95: PTO VENTA | E95: Nº FACTURA | F95: CUIT | G95: RAZON SOCIAL | H95: IMPORTE NETO | I95: IVA 21% | J95: IVA 10,5% | K95: EXENTO | L95: TOTAL | M95: Provincia
G96: =IFERROR(IF(ventas_b_mes3[[#This Row],[CUIT]]="","-",VLOOKUP(ventas_b_mes3[[#This Row],[CUIT]],Lista_CUIT[#All],2,0)),"CUIT NO CARGADO") -> - | L96: =SUM(ventas_b_mes3[[#This Row],[IMPORTE NETO]:[EXENTO]]) -> 0
L97: =SUM(ventas_b_mes3[[#This Row],[IMPORTE NETO]:[EXENTO]]) -> 0
L98: =SUM(ventas_b_mes3[[#This Row],[IMPORTE NETO]:[EXENTO]]) -> 0
L99: =SUM(ventas_b_mes3[[#This Row],[IMPORTE NETO]:[EXENTO]]) -> 0
L100: =SUM(ventas_b_mes3[[#This Row],[IMPORTE NETO]:[EXENTO]]) -> 0
L101: =SUM(ventas_b_mes3[[#This Row],[IMPORTE NETO]:[EXENTO]]) -> 0
B102: Total | H102: =SUBTOTAL(109,ventas_b_mes3[IMPORTE NETO]) -> 0 | I102: =SUBTOTAL(109,ventas_b_mes3[IVA 21%]) -> 0 | J102: =SUBTOTAL(109,ventas_b_mes3[IVA 10,5%]) -> 0 | K102: =SUBTOTAL(109,ventas_b_mes3[EXENTO]) -> 0 | L102: =SUBTOTAL(109,ventas_b_mes3[TOTAL]) -> 0 | M102: =SUBTOTAL(103,ventas_b_mes3[Provincia]) -> 0
B105: VENTAS "E"
B106: FECHA | C106: TIPO | D106: PTO VENTA | E106: Nº FACTURA | F106: CUIT | G106: RAZON SOCIAL | H106: USD | I106: TIPO DE CAMBIO2 | J106: TOTAL | K106: Pais
G108: =IFERROR(IF(ventas_b_mes1354[[#This Row],[CUIT]]="","-",VLOOKUP(ventas_b_mes1354[[#This Row],[CUIT]],Lista_CUIT[#All],2,0)),"CUIT NO CARGADO") -> -
B109: Total | H109: =SUBTOTAL(109,ventas_b_mes1354[USD]) -> 0 | I109: =SUBTOTAL(109,ventas_b_mes1354[TIPO DE CAMBIO2]) -> 0 | J109: =SUBTOTAL(109,ventas_b_mes1354[TOTAL]) -> 0 | K109: =SUBTOTAL(103,ventas_b_mes1354[Pais]) -> 0
C113: RETENCIONES
C114: FECHA | D114: COMP Nº | E114: Columna1 | F114: CUIT | G114: RAZON SOCIAL | H114: Ganancias | I114: IVA | J114: SUSS | K114: IIBB BSAS | L114: IIBB CABA
G115: =IFERROR(IF(Retenciones_mes3[[#This Row],[CUIT]]="","-",VLOOKUP(Retenciones_mes3[[#This Row],[CUIT]],Lista_CUIT[#All],2,0)),"CUIT NO CARGADO") -> -
G116: =IFERROR(IF(Retenciones_mes3[[#This Row],[CUIT]]="","-",VLOOKUP(Retenciones_mes3[[#This Row],[CUIT]],Lista_CUIT[#All],2,0)),"CUIT NO CARGADO") -> -
G117: =IFERROR(IF(Retenciones_mes3[[#This Row],[CUIT]]="","-",VLOOKUP(Retenciones_mes3[[#This Row],[CUIT]],Lista_CUIT[#All],2,0)),"CUIT NO CARGADO") -> -
G118: =IFERROR(IF(Retenciones_mes3[[#This Row],[CUIT]]="","-",VLOOKUP(Retenciones_mes3[[#This Row],[CUIT]],Lista_CUIT[#All],2,0)),"CUIT NO CARGADO") -> -
G119: =IFERROR(IF(Retenciones_mes3[[#This Row],[CUIT]]="","-",VLOOKUP(Retenciones_mes3[[#This Row],[CUIT]],Lista_CUIT[#All],2,0)),"CUIT NO CARGADO") -> -

Sheet Jul-23
B1: LIBRO IVA COMPRAS | G1: ='Abr-23'!G1:M1 -> CORITEC S. R. L. | N1: =EDATE('Abr-23'!N1,3) -> 45108
B3: TOTAL COMPRAS | G3: TOTAL CREDITO FISCAL | J3: TOTAL VENTAS NETAS | M3: TOTAL DEBITO FISCAL | P3: RESULTADO
B4: =SUM(compras_mes4[[#Totals],[NETO GRAVADO]])+extracto_banco_mes4[[#Totals],[NETO]] -> 2968818 | G4: =compras_mes4[[#Totals],[IVA 21 %]]+compras_mes4[[#Totals],[IVA 27%]]+compras_mes4[[#Totals],[IVA 10,5%]]+extracto_banco_mes4[[#Totals],[IVA 21%]]+extracto_banco_mes4[[#Totals],[IVA 10,5%]] -> 3820788.2 | J4: =venta_a_mes4[[#Totals],[IMPORTE NETO]]+ventas_b_mes4[[#Totals],[IMPORTE NETO]] -> 19101121 | M4: =venta_a_mes4[[#Totals],[IVA 21%]]+venta_a_mes4[[#Totals],[IVA 10,5%]]+ventas_b_mes4[[#Totals],[IVA 21%]]+ventas_b_mes4[[#Totals],[IVA 10,5%]] -> 2507957.6 | P4: =G4-M4 -> 1312830.5
B8: FECHA | C8: TIPO | D8: PTO VTA | E8: NRO. CPTE | F8: CUIT | G8: RAZON SOCIAL | H8: NETO GRAVADO | I8: IVA 21 % | J8: IVA 27% | K8: IVA 10,5% | L8: PERC. IVA | M8: PERC IIBB BS AS | N8: PERC. IIBB CABA | O8: Otros / No Grav. | P8: TOTAL | Q8: Tipo de Gasto | R8: Provincia
B9: 45108 | C9: 1 | D9: 3 | E9: 661 | F9: 30715402765 | G9: =IFERROR(IF(compras_mes4[[#This Row],[CUIT]]="","-",VLOOKUP(compras_mes4[[#This Row],[CUIT]],Lista_CUIT[#All],2,0)),"CUIT NO CARGADO") -> RIO 265 S.R.L. | H9: 14462.81 | I9: =IF(compras_mes4[[#This Row],[NETO GRAVADO]]="","",compras_mes4[[#This Row],[NETO GRAVADO]]*0.21) -> 3037.1901 | P9: =SUM(compras_mes4[[#This Row],[NETO GRAVADO]:[Otros / No Grav.]]) -> 17500 | Q9: =IFERROR(IF(compras_mes4[[#This Row],[CUIT]]="","-",VLOOKUP(compras_mes4[[#This Row],[CUIT]],Lista_CUIT[#All],3,0)),"CUIT NO CARGADO") -> Gastos Varios | R9: =IFERROR(IF(compras_mes4[[#This Row],[CUIT]]="","-",VLOOKUP(compras_mes4[[#This Row],[CUIT]],Lista_CUIT[#All],4,0)),"CUIT NO CARGADO") -> 0
B10: 45108 | C10: 1 | D10: 3 | E10: 194793 | F10: 30707135596 | G10: =IFERROR(IF(compras_mes4[[#This Row],[CUIT]]="","-",VLOOKUP(compras_mes4[[#This Row],[CUIT]],Lista_CUIT[#All],2,0)),"CUIT NO CARGADO") -> CITILAN ARGENTINA S.A. | H10: 6217.25 | I10: =IF(compras_mes4[[#This Row],[NETO GRAVADO]]="","",compras_mes4[[#This Row],[NETO GRAVADO]]*0.21) -> 1305.6225 | P10: =SUM(compras_mes4[[#This Row],[NETO GRAVADO]:[Otros / No Grav.]]) -> 7522.8725 | Q10: =IFERROR(IF(compras_mes4[[#This Row],[CUIT]]="","-",VLOOKUP(compras_mes4[[#This Row],[CUIT]],Lista_CUIT[#All],3,0)),"CUIT NO CARGADO") -> Servicios Gas, Luz, Etc | R10: =IFERROR(IF(compras_mes4[[#This Row],[CUIT]]="","-",VLOOKUP(compras_mes4[[#This Row],[CUIT]],Lista_CUIT[#All],4,0)),"CUIT NO CARGADO") -> 0
B11: 45110 | C11: 1 | D11: 2 | E11: 2453 | F11: 30709131733 | G11: =IFERROR(IF(compras_mes4[[#This Row],[CUIT]]="","-",VLOOKUP(compras_mes4[[#This Row],[CUIT]],Lista_CUIT[#All],2,0)),"CUIT NO CARGADO") -> DIGAS SRL | H11: 857437 | I11: =IF(compras_mes4[[#This Row],[NETO GRAVADO]]="","",compras_mes4[[#This Row],[NETO GRAVADO]]*0.21) -> 180061.77 | P11: =SUM(compras_mes4[[#This Row],[NETO GRAVADO]:[Otros / No Grav.]]) -> 1037498.8 | Q11: =IFERROR(IF(compras_mes4[[#This Row],[CUIT]]="","-",VLOOKUP(compras_mes4[[#This Row],[CUIT]],Lista_CUIT[#All],3,0)),"CUIT NO CARGADO") -> INSUMO | R11: =IFERROR(IF(compras_mes4[[#This Row],[CUIT]]="","-",VLOOKUP(compras_mes4[[#This Row],[CUIT]],Lista_CUIT[#All],4,0)),"CUIT NO CARGADO") -> 0
B12: 45112 | C12: 1 | D12: 2 | E12: 178 | F12: 20125142851 | G12: =IFERROR(IF(compras_mes4[[#This Row],[CUIT]]="","-",VLOOKUP(compras_mes4[[#This Row],[CUIT]],Lista_CUIT[#All],2,0)),"CUIT NO CARGADO") -> FEDERICI NICOLAS JOSE | H12: 74359 | I12: =IF(compras_mes4[[#This Row],[NETO GRAVADO]]="","",compras_mes4[[#This Row],[NETO GRAVADO]]*0.21) -> 15615.39 | P12: =SUM(compras_mes4[[#This Row],[NETO GRAVADO]:[Otros / No Grav.]]) -> 89974.39 | Q12: =IFERROR(IF(compras_mes4[[#This Row],[CUIT]]="","-",VLOOKUP(compras_mes4[[#This Row],[CUIT]],Lista_CUIT[#All],3,0)),"CUIT NO CARGADO") -> INSUMO | R12: =IFERROR(IF(compras_mes4[[#This Row],[CUIT]]="","-",VLOOKUP(compras_mes4[[#This Row],[CUIT]],Lista_CUIT[#All],4,0)),"CUIT NO CARGADO") -> 0
B13: 45117 | C13: 1 | D13: 2 | E13: 179 | F13: 20125142851 | G13: =IFERROR(IF(compras_mes4[[#This Row],[CUIT]]="","-",VLOOKUP(compras_mes4[[#This Row],[CUIT]],Lista_CUIT[#All],2,0)),"CUIT NO CARGADO") -> FEDERICI NICOLAS JOSE | H13: 55769.25 | I13: =IF(compras_mes4[[#This Row],[NETO GRAVADO]]="","",compras_mes4[[#This Row],[NETO GRAVADO]]*0.21) -> 11711.542 | P13: =SUM(compras_mes4[[#This Row],[NETO GRAVADO]:[Otros / No Grav.]]) -> 67480.792 | Q13: =IFERROR(IF(compras_mes4[[#This Row],[CUIT]]="","-",VLOOKUP(compras_mes4[[#This Row],[CUIT]],Lista_CUIT[#All],3,0)),"CUIT NO CARGADO") -> INSUMO | R13: =IFERROR(IF(compras_mes4[[#This Row],[CUIT]]="","-",VLOOKUP(compras_mes4[[#This Row],[CUIT]],Lista_CUIT[#All],4,0)),"CUIT NO CARGADO") -> 0
B14: 45117 | C14: 1 | D14: 5122 | E14: 14557 | F14: 30695542476 | G14: =IFERROR(IF(compras_mes4[[#This Row],[CUIT]]="","-",VLOOKUP(compras_mes4[[#This Row],[CUIT]],Lista_CUIT[#All],2,0)),"CUIT NO CARGADO") -> PAN AMERICAN ENERGY LLC | H14: 7938.88 | I14: =IF(compras_mes4[[#This Row],[NETO GRAVADO]]="","",compras_mes4[[#This Row],[NETO GRAVADO]]*0.21) -> 1667.1648 | O14: 1499.62 | P14: =SUM(compras_mes4[[#This Row],[NETO GRAVADO]:[Otros / No Grav.]]) -> 11105.665 | Q14: =IFERROR(IF(compras_mes4[[#This Row],[CUIT]]="","-",VLOOKUP(compras_mes4[[#This Row],[CUIT]],Lista_CUIT[#All],3,0)),"CUIT NO CARGADO") -> 0 | R14: =IFERROR(IF(compras_mes4[[#This Row],[CUIT]]="","-",VLOOKUP(compras_mes4[[#This Row],[CUIT]],Lista_CUIT[#All],4,0)),"CUIT NO CARGADO") -> 0
B15: 45118 | C15: 1 | D15: 295 | E15: 2343 | F15: 30709173401 | G15: =IFERROR(IF(compras_mes4[[#This Row],[CUIT]]="","-",VLOOKUP(compras_mes4[[#This Row],[CUIT]],Lista_CUIT[#All],2,0)),"CUIT NO CARGADO") -> NEUMATICOS CORRAL S.A. | H15: 12396.69 | I15: =IF(compras_mes4[[#This Row],[NETO GRAVADO]]="","",compras_mes4[[#This Row],[NETO GRAVADO]]*0.21) -> 2603.3049 | P15: =SUM(compras_mes4[[#This Row],[NETO GRAVADO]:[Otros / No Grav.]]) -> 14999.995 | Q15: =IFERROR(IF(compras_mes4[[#This Row],[CUIT]]="","-",VLOOKUP(compras_mes4[[#This Row],[CUIT]],Lista_CUIT[#All],3,0)),"CUIT NO CARGADO") -> 0 | R15: =IFERROR(IF(compras_mes4[[#This Row],[CUIT]]="","-",VLOOKUP(compras_mes4[[#This Row],[CUIT]],Lista_CUIT[#All],4,0)),"CUIT NO CARGADO") -> 0
B16: 45118 | C16: 1 | D16: 7 | E16: 1514 | F16: 20352108635 | G16: =IFERROR(IF(compras_mes4[[#This Row],[CUIT]]="","-",VLOOKUP(compras_mes4[[#This Row],[CUIT]],Lista_CUIT[#All],2,0)),"CUIT NO CARGADO") -> SOMMARIO TURONI GUSTAVO | H16: 14272.73 | I16: =IF(compras_mes4[[#This Row],[NETO GRAVADO]]="","",compras_mes4[[#This Row],[NETO GRAVADO]]*0.21) -> 2997.2733 | P16: =SUM(compras_mes4[[#This Row],[NETO GRAVADO]:[Otros / No Grav.]]) -> 17270.003 | Q16: =IFERROR(IF(compras_mes4[[#This Row],[CUIT]]="","-",VLOOKUP(compras_mes4[[#This Row],[CUIT]],Lista_CUIT[#All],3,0)),"CUIT NO CARGADO") -> 0 | R16: =IFERROR(IF(compras_mes4[[#This Row],[CUIT]]="","-",VLOOKUP(compras_mes4[[#This Row],[CUIT]],Lista_CUIT[#All],4,0)),"CUIT NO CARGADO") -> 0
B17: 45118 | C17: 1 | D17: 2466 | E17: 531478 | F17: 30678814357 | G17: =IFERROR(IF(compras_mes4[[#This Row],[CUIT]]="","-",VLOOKUP(compras_mes4[[#This Row],[CUIT]],Lista_CUIT[#All],2,0)),"CUIT NO CARGADO") -> TELEFONICA MOVILES ARG | H17: 6358.32 | J17: 1716.75 | L17: 190.75 | O17: 281.65 | P17: =SUM(compras_mes4[[#This Row],[NETO GRAVADO]:[Otros / No Grav.]]) -> 8547.47 | Q17: =IFERROR(IF(compras_mes4[[#This Row],[CUIT]]="","-",VLOOKUP(compras_mes4[[#This Row],[CUIT]],Lista_CUIT[#All],3,0)),"CUIT NO CARGADO") -> SERVICIOS | R17: =IFERROR(IF(compras_mes4[[#This Row],[CUIT]]="","-",VLOOKUP(compras_mes4[[#This Row],[CUIT]],Lista_CUIT[#All],4,0)),"CUIT NO CARGADO") -> 0
B18: 45119 | C18: 1 | D18: 5 | E18: 1588 | F18: 20294907174 | G18: =IFERROR(IF(compras_mes4[[#This Row],[CUIT]]="","-",VLOOKUP(compras_mes4[[#This Row],[CUIT]],Lista_CUIT[#All],2,0)),"CUIT NO CARGADO") -> ORTUÑO ALVAREZ HECTOR MANUEL | H18: 6603.31 | I18: =IF(compras_mes4[[#This Row],[NETO GRAVADO]]="","",compras_mes4[[#This Row],[NETO GRAVADO]]*0.21) -> 1386.6951 | P18: =SUM(compras_mes4[[#This Row],[NETO GRAVADO]:[Otros / No Grav.]]) -> 7990.0051 | Q18: =IFERROR(IF(compras_mes4[[#This Row],[CUIT]]="","-",VLOOKUP(compras_mes4[[#This Row],[CUIT]],Lista_CUIT[#All],3,0)),"CUIT NO CARGADO") -> 0 | R18: =IFERROR(IF(compras_mes4[[#This Row],[CUIT]]="","-",VLOOKUP(compras_mes4[[#This Row],[CUIT]],Lista_CUIT[#All],4,0)),"CUIT NO CARGADO") -> 0
B19: 45119 | C19: 1 | D19: 14 | E19: 98092 | F19: 30516336885 | G19: =IFERROR(IF(compras_mes4[[#This Row],[CUIT]]="","-",VLOOKUP(compras_mes4[[#This Row],[CUIT]],Lista_CUIT[#All],2,0)),"CUIT NO CARGADO") -> STENFAR S. A. U. | H19: 20721.4 | I19: =IF(compras_mes4[[#This Row],[NETO GRAVADO]]="","",compras_mes4[[#This Row],[NETO GRAVADO]]*0.21) -> 4351.494 | L19: 621.64 | N19: 1243.28 | P19: =SUM(compras_mes4[[#This Row],[NETO GRAVADO]:[Otros / No Grav.]]) -> 26937.814 | Q19: =IFERROR(IF(compras_mes4[[#This Row],[CUIT]]="","-",VLOOKUP(compras_mes4[[#This Row],[CUIT]],Lista_CUIT[#All],3,0)),"CUIT NO CARGADO") -> 0 | R19: =IFERROR(IF(compras_mes4[[#This Row],[CUIT]]="","-",VLOOKUP(compras_mes4[[#This Row],[CUIT]],Lista_CUIT[#All],4,0)),"CUIT NO CARGADO") -> 0
