Workbook

Sheet Lista_CUIT
A1: CUIT | B1: RAZON SOCIAL | C1: Tipo de Gasto | D1: PROVINCIA
A2: 34999032089 | B2: GOBIERNO DE LA CIUDAD DE BUENOS AIRES | C2: AGIP | G2: Mercaderia
A3: 30711509859 | B3: HOTELERA NEPTUNO MDP SOCIEDAD ANONIMA | C3: Alojamiento | G3: Servicios Gas, Luz, etc.
A4: 27309896063 | B4: BATTELLINI MARIA SOLEDAD | C4: Alquiler | G4: Gastos catering
A5: 27309896063 | B5: BATTELLINI MARIA SOLEDAD | C5: Alquiler | G5: Combustibe
A6: 20131206144 | B6: CHAMORRO MANUEL | C6: Alquiler | G6: Gastos Varios
A7: 20131206144 | B7: CHAMORRO MANUEL | C7: Alquiler | G7: Gastos seguridad
A8: 20131206144 | B8: CHAMORRO MANUEL | C8: Alquiler | G8: Librería
A9: 20131206144 | B9: CHAMORRO MANUEL | C9: Alquiler | G9: Gastos mantenimiento
A10: 30716010313 | B10: H UNO 1469 S.A. | C10: Alquiler | G10: Gastos comercializacion
A11: 30647082293 | B11: CHARATA SRL | C11: Combustible | G11: Alquiler
A12: 30516186670 | B12: DEHEZA S.A.I.C.F. e I. | C12: Combustible | D12: CABA | G12: Honorarios contables
A13: 30643827197 | B13: HURLINGAS S.RL. | C13: Combustible | G13: Gastos administrativos
A14: 30687310434 | B14: INC SOCIEDAD ANONIMA | C14: Combustible | G14: Seguro
A15: 30687310434 | B15: INC SOCIEDAD ANONIMA | C15: Combustible | G15: Extracto
A16: 30515800219 | B16: INCAT SRL | C16: Combustible | D16: CABA | G16: Flete
A17: 33649669029 | B17: JUAN B JUSTO 1333 | C17: Combustible | G17: Honorarios Legales
A18: 33649669029 | B18: JUAN B JUSTO 1333 SA | C18: Combustible | G18: Insumo
A19: 20217165114 | B19: MARTINO CARLOS ALBERTO | C19: Combustible | G19: Muebles y Utiles
A20: 30685116657 | B20: MIRVAR SA | C20: Combustible | G20: Otros
A21: 33608724279 | B21: NAFPUR SA | C21: Combustible | G21: Telefonia
A22: 30707983732 | B22: NAFPUR XXI SA | C22: Combustible | G22: Alojamiento-Varios
A23: 30678774495 | B23: OPER. DE EST. DE SERV. SA | C23: Combustible
A24: 30546995735 | B24: ORGANIZACION DELASOIE HERMANOS S A | C24: Combustible
A25: 30695542476 | B25: PAN AMERICAN ENERGY LLC | C25: Combustible
A26: 30707841105 | B26: PETRO ARG SRL | C26: Combustible
A27: 30696131003 | B27: Petrolfe S.A. | C27: Combustible
A28: 30574300858 | B28: SHELL SA | C28: Combustible
A29: 30574300858 | B29: SHELL SA | C29: Combustible
A30: 30517264160 | B30: TRIANGLE SCA | C30: Combustible
A31: 30517264160 | B31: TRIANGLE SCA | C31: Combustible
A32: 30546689979 | B32: YPF SA | C32: Combustible
A33: 30546689979 | B33: YPF SA | C33: Combustible
A34: 30708613335 | B34: CASA ELICEIRY S A | C34: Combustible
... A39: 30683553391 | B39: D ERAMO GUSTAVO Y D ERAMO PABLO SOC DE HECHO | C39: Combustible
A40: 30703843618 | B40: SILFA SA | C40: Combustible | D40: BUENOS AIRES
A41: 30695443907 | B41: NAF GAS SA | C41: Combustible
A42: 30653466931 | B42: GNC ESCOBAR SA | C42: Combustible
A43: 30709394912 | B43: KINIEN SA | C43: Combustible
A44: 30715537512 | B44: ESTACION DE SERVICIO ALCOVER SRL | C44: Combustible
A45: 30537781323 | B45: ESTACION DE SERVICIO NORTEÑA SRL | C45: Combustible | D45: CABA
A46: 30662624736 | B46: COMBUSTIBLES MORABITO HNOS SRL | C46: Combustible | D46: BUENOS AIRES
A47: 30698813659 | B47: PUENTE VANGUARDIA SOC ANONIMA | C47: Combustible | D47: BUENOS AIRES
A48: 30701367193 | B48: ESTACION DE SERVICIO CUATRO BOCAS SRL | C48: Combustible | D48: CORRIENTES
A49: 30583747482 | B49: SUPER SEVICIOS OLIVOS SRL | C49: Combustible | D49: BUENOS AIRES
A50: 20130138005 | B50: SILVESTRI SERGIO ALBERTO | C50: Combustible | D50: CABA
A51: 30688774495 | B51: OPERADORA DE ESTAC DE SERVICIOS SA | C51: Combustible | D51: BUENOS AIRES
A52: 30711463514 | B52: GLOBAL OIL S.R.L | C52: Combustible
A53: 30710128584 | B53: JORGE PIRRI Y CUA SRL | C53: Combustible | D53: BUENOS AIRES
A54: 30671637689 | B54: GRUPO NORTE SRL | C54: Combustible
A55: 30594832783 | B55: CHICHIAN SA | C55: Combustible
A56: 30714527300 | B56: BUDAS KINGDOM SRL | C56: Combustible
A57: 30540960085 | B57: ESTACION DE SERVICIO SAN LUIS SRL | C57: Combustible
A58: 30568459500 | B58: ESTACION DE SERVICIO AXION KUKE SRL | C58: Combustible | D58: CABA
A59: 30709474789 | B59: GNC EL TALAR SA | C59: Combustible
A60: 30707918302 | B60: UBR SOCIEDAD ANONIMA | C60: Combustible
A61: 30684988030 | B61: NUEVOS EMPRENDIMIENTOS SRL | C61: Combustible
A62: 30597304281 | B62: NOCEDA SA | C62: Combustible
A63: 30714391344 | B63: FOLGEN SA | C63: Combustible
A64: 30716874601 | B64: BOUVET COMBUSTIBLES SAS | C64: Combustible
A65: 30708046724 | B65: INTEGRAL PACK EXPRESS S.A. | C65: Combustible
A66: 30708224142 | B66: ONSAY BEL SA | C66: Combustible
A67: 30526874249 | B67: FRAVEGA S A C I E I | C67: Gastos Oficina
A68: 30526874249 | B68: FRAVEGA S A C I E I | C68: Gastos Oficina
A69: 30526874249 | B69: FRAVEGA S A C I E I | C69: Gastos Oficina
A70: 30526874249 | B70: FRAVEGA S A C I E I | C70: Gastos Oficina
... A120: 27292471993 | B120: CAEIRO ANA JULIA | C120: Gastos Comercializacion
A121: 30715889486 | B121: EXPOESTETICA | C121: Gastos Comercializacion - Feria | D121: BUENOS AIRES
A122: 30715186256 | B122: FRIGORIFICO ALIMENTIC | C122: Gastos Comercializacion - Feria
A123: 30614617388 | B123: EXPO MADERA DE ALMENDRO JORGE MAGLIO PEDRO MAGLIO GREGORIO | C123: Gastos Comercializacion - Feria
A124: 30695056342 | B124: AVENIDA MAIPU 4199 S C S | C124: Gastos Cosmetica
A125: 30707391983 | B125: NUAGE SYSTEMS S.A | C125: Gastos Oficina
A126: 30707391983 | B126: NUAGE SYSTEMS S.A | C126: Gastos Oficina
A127: 33714232199 | B127: NUAGE SYSTEMS S.A. | C127: Gastos Oficina
A128: 33714232199 | B128: NUAGE SYSTEMS S.A. | C128: Gastos Oficina
A129: 33677414419 | B129: MULTIPOINT SA | C129: Gastos Oficina
A130: 20204428566 | B130: CORANA HERNAN SILVIO | C130: Gastos Oficina
A131: 33708711999 | B131: MARANSI S.A. | C131: Gastos Oficina
A132: 27178797935 | B132: FARFAN MARIA ELSA | C132: Gastos Oficina
A133: 30708349646 | B133: PEM PRODUCTOS ELECTRICOS S.A. | C133: Gastos Oficina
... A194: 33662613199 | B194: D M H S A | C194: Gastos Varios
A195: 20136536320 | B195: FONTENLA ERNESTO MARIO | C195: Gastos Varios | D195: CABA
A196: 30685849751 | B196: DIA ARGENTINA S A | C196: Gastos Varios
A197: 30685849751 | B197: DIA ARGENTINA S A | C197: Gastos Varios
A198: 30578494185 | B198: GUILLERMO DOMIN S.R.L. | C198: Gastos Varios
A199: 20275447057 | B199: HERNAN BERNEY | C199: Gastos Varios
A200: 20134664518 | B200: HOKAMA SERGIO ENRIQUE | C200: Gastos Varios | D200: BUENOS AIRES
A201: 30714730548 | B201: IASSA SA | C201: Gastos Varios
A202: 30712289046 | B202: IMPIERI PIÑEIRO RIZZO Y ASOC SA | C202: Gastos Varios
A203: 30712289046 | B203: IMPIERI PIÑEIRO RIZZO Y ASOC SA | C203: Gastos Varios
A204: 30688241614 | B204: INDUSTRIAS MARTIN S.A. | C204: Gastos Varios
A205: 20226549758 | B205: JANEIRO VERONICA BELEN | C205: Gastos Varios
A206: 20226549758 | B206: JANEIRO VERONICA BELEN | C206: Gastos Varios
A207: 20183380231 | B207: JUAN D NAVARRO | C207: Gastos Varios
A208: 33531122599 | B208: LA CAMIONERA MENDOCINA SRL | C208: Gastos Varios
A209: 30710374801 | B209: LD DISTRIBUIDORA LARREA | C209: Gastos Varios
A210: 20041802082 | B210: LEONARDO TILL | C210: Gastos Varios
A211: 30715723871 | B211: LIBERTECH SRL | C211: Gastos Varios
A212: 20262808557 | B212: LIS GABRIEL HERNAN | C212: Gastos Varios
... A223: 30602422174 | B223: MEGA BABY S.A | C223: Gastos Varios
...

Sheet Ene-25
B1: LIBRO IVA COMPRAS | G1: EUROARGENTINA | N1: 45658
B3: TOTAL COMPRAS | G3: TOTAL CREDITO FISCAL | J3: TOTAL VENTAS NETAS | M3: TOTAL DEBITO FISCAL | P3: RESULTADO
B4: =SUM(compras_mes1[[#Totals],[NETO GRAVADO]])+extracto_banco_mes1[[#Totals],[NETO]] -> 44381077 | G4: =compras_mes1[[#Totals],[IVA 21 %]]+compras_mes1[[#Totals],[IVA 27%]]+compras_mes1[[#Totals],[IVA 10,5%]]+extracto_banco_mes1[[#Totals],[IVA 21%]]+extracto_banco_mes1[[#Totals],[IVA 10,5%]] -> 8974257.9 | J4: =venta_a_mes1[[#Totals],[IMPORTE NETO]]+ventas_b_mes1[[#Totals],[IMPORTE NETO]] -> 0 | M4: =venta_a_mes1[[#Totals],[IVA 21%]]+venta_a_mes1[[#Totals],[IVA 10,5%]]+ventas_b_mes1[[#Totals],[IVA 21%]]+ventas_b_mes1[[#Totals],[IVA 10,5%]] -> 0 | P4: =G4-M4 -> 8974257.9
G6: LAS TIENEN ELLOS Y AFIP | H6: EL RESTO SON TODAS DE AFIP | I6: agregadas a afip
B8: FECHA | C8: TIPO | D8: PTO VTA | E8: NRO. CPTE | F8: CUIT | G8: RAZON SOCIAL | H8: NETO GRAVADO | I8: IVA 21 % | J8: IVA 27% | K8: IVA 10,5% | L8: PERC. IVA | M8: PERC IIBB BS AS | N8: PERC. IIBB CABA | O8: Otros / No Grav. | P8: TOTAL | Q8: Tipo de Gasto | R8: Provincia
B9: 22/01/2025 | C9: 1 | D9: 4 | E9: 370 | F9: 20104345221 | G9: =IFERROR(IF(compras_mes1[[#This Row],[CUIT]]="","-",VLOOKUP(compras_mes1[[#This Row],[CUIT]],Lista_CUIT[#All],2,0)),"CUIT NO CARGADO") -> ARAYA SERGIO ALEJANDRO | H9: 3057.86 | I9: =IF(compras_mes1[[#This Row],[NETO GRAVADO]]="","",compras_mes1[[#This Row],[NETO GRAVADO]]*0.21) -> 642.1506 | P9: =SUM(compras_mes1[[#This Row],[NETO GRAVADO]:[Otros / No Grav.]]) -> 3700.0106 | Q9: =IFERROR(IF(compras_mes1[[#This Row],[CUIT]]="","-",VLOOKUP(compras_mes1[[#This Row],[CUIT]],Lista_CUIT[#All],3,0)),"CUIT NO CARGADO") -> LIBRERÍA | R9: =IFERROR(IF(compras_mes1[[#This Row],[CUIT]]="","-",VLOOKUP(compras_mes1[[#This Row],[CUIT]],Lista_CUIT[#All],4,0)),"CUIT NO CARGADO") -> 0
B10: 23/01/2025 | C10: 1 | D10: 4 | E10: 371 | F10: 20104345221 | G10: =IFERROR(IF(compras_mes1[[#This Row],[CUIT]]="","-",VLOOKUP(compras_mes1[[#This Row],[CUIT]],Lista_CUIT[#All],2,0)),"CUIT NO CARGADO") -> ARAYA SERGIO ALEJANDRO | H10: 11818.19 | I10: =IF(compras_mes1[[#This Row],[NETO GRAVADO]]="","",compras_mes1[[#This Row],[NETO GRAVADO]]*0.21) -> 2481.8199 | P10: =SUM(compras_mes1[[#This Row],[NETO GRAVADO]:[Otros / No Grav.]]) -> 14300.01 | Q10: =IFERROR(IF(compras_mes1[[#This Row],[CUIT]]="","-",VLOOKUP(compras_mes1[[#This Row],[CUIT]],Lista_CUIT[#All],3,0)),"CUIT NO CARGADO") -> LIBRERÍA | R10: =IFERROR(IF(compras_mes1[[#This Row],[CUIT]]="","-",VLOOKUP(compras_mes1[[#This Row],[CUIT]],Lista_CUIT[#All],4,0)),"CUIT NO CARGADO") -> 0
B11: 16/01/2025 | C11: 1 | D11: 50 | E11: 4053001 | F11: 30714112836 | G11: =IFERROR(IF(compras_mes1[[#This Row],[CUIT]]="","-",VLOOKUP(compras_mes1[[#This Row],[CUIT]],Lista_CUIT[#All],2,0)),"CUIT NO CARGADO") -> AUTOPISTAS DE BS AS | H11: 35577.88 | I11: =IF(compras_mes1[[#This Row],[NETO GRAVADO]]="","",compras_mes1[[#This Row],[NETO GRAVADO]]*0.21) -> 7471.3548 | L11: 1067.34 | P11: =SUM(compras_mes1[[#This Row],[NETO GRAVADO]:[Otros / No Grav.]]) -> 44116.575 | Q11: =IFERROR(IF(compras_mes1[[#This Row],[CUIT]]="","-",VLOOKUP(compras_mes1[[#This Row],[CUIT]],Lista_CUIT[#All],3,0)),"CUIT NO CARGADO") -> Peajes | R11: =IFERROR(IF(compras_mes1[[#This Row],[CUIT]]="","-",VLOOKUP(compras_mes1[[#This Row],[CUIT]],Lista_CUIT[#All],4,0)),"CUIT NO CARGADO") -> 0
B12: 31/01/2025 | C12: 1 | D12: 50 | E12: 4093332 | F12: 30714112836 | G12: =IFERROR(IF(compras_mes1[[#This Row],[CUIT]]="","-",VLOOKUP(compras_mes1[[#This Row],[CUIT]],Lista_CUIT[#All],2,0)),"CUIT NO CARGADO") -> AUTOPISTAS DE BS AS | H12: 42783.56 | I12: =IF(compras_mes1[[#This Row],[NETO GRAVADO]]="","",compras_mes1[[#This Row],[NETO GRAVADO]]*0.21) -> 8984.5476 | L12: 1283.51 | P12: =SUM(compras_mes1[[#This Row],[NETO GRAVADO]:[Otros / No Grav.]]) -> 53051.618 | Q12: =IFERROR(IF(compras_mes1[[#This Row],[CUIT]]="","-",VLOOKUP(compras_mes1[[#This Row],[CUIT]],Lista_CUIT[#All],3,0)),"CUIT NO CARGADO") -> Peajes | R12: =IFERROR(IF(compras_mes1[[#This Row],[CUIT]]="","-",VLOOKUP(compras_mes1[[#This Row],[CUIT]],Lista_CUIT[#All],4,0)),"CUIT NO CARGADO") -> 0
B13: 01/01/2025 | C13: 1 | D13: 711 | E13: 6582749 | F13: 30677237119 | G13: =IFERROR(IF(compras_mes1[[#This Row],[CUIT]]="","-",VLOOKUP(compras_mes1[[#This Row],[CUIT]],Lista_CUIT[#All],2,0)),"CUIT NO CARGADO") -> AUTOPISTAS DEL SOL S A | H13: 13461.93 | I13: =IF(compras_mes1[[#This Row],[NETO GRAVADO]]="","",compras_mes1[[#This Row],[NETO GRAVADO]]*0.21) -> 2827.0053 | L13: 403.86 | O13: 403.86 | P13: =SUM(compras_mes1[[#This Row],[NETO GRAVADO]:[Otros / No Grav.]]) -> 17096.655 | Q13: =IFERROR(IF(compras_mes1[[#This Row],[CUIT]]="","-",VLOOKUP(compras_mes1[[#This Row],[CUIT]],Lista_CUIT[#All],3,0)),"CUIT NO CARGADO") -> Peajes | R13: =IFERROR(IF(compras_mes1[[#This Row],[CUIT]]="","-",VLOOKUP(compras_mes1[[#This Row],[CUIT]],Lista_CUIT[#All],4,0)),"CUIT NO CARGADO") -> 0
B14: 16/01/2025 | C14: 1 | D14: 711 | E14: 6641317 | F14: 30677237119 | G14: =IFERROR(IF(compras_mes1[[#This Row],[CUIT]]="","-",VLOOKUP(compras_mes1[[#This Row],[CUIT]],Lista_CUIT[#All],2,0)),"CUIT NO CARGADO") -> AUTOPISTAS DEL SOL S A | H14: 13924.07 | I14: =IF(compras_mes1[[#This Row],[NETO GRAVADO]]="","",compras_mes1[[#This Row],[NETO GRAVADO]]*0.21) -> 2924.0547 | L14: 417.72 | O14: 417.72 | P14: =SUM(compras_mes1[[#This Row],[NETO GRAVADO]:[Otros / No Grav.]]) -> 17683.565 | Q14: =IFERROR(IF(compras_mes1[[#This Row],[CUIT]]="","-",VLOOKUP(compras_mes1[[#This Row],[CUIT]],Lista_CUIT[#All],3,0)),"CUIT NO CARGADO") -> Peajes | R14: =IFERROR(IF(compras_mes1[[#This Row],[CUIT]]="","-",VLOOKUP(compras_mes1[[#This Row],[CUIT]],Lista_CUIT[#All],4,0)),"CUIT NO CARGADO") -> 0
B15: 08/01/2025 | C15: 1 | D15: 5015 | E15: 711560 | F15: 30574876474 | G15: =IFERROR(IF(compras_mes1[[#This Row],[CUIT]]="","-",VLOOKUP(compras_mes1[[#This Row],[CUIT]],Lista_CUIT[#All],2,0)),"CUIT NO CARGADO") -> AUTOPISTAS URBANAS S A | H15: 86388.04 | I15: =IF(compras_mes1[[#This Row],[NETO GRAVADO]]="","",compras_mes1[[#This Row],[NETO GRAVADO]]*0.21) -> 18141.488 | O15: 11230.43 | P15: =SUM(compras_mes1[[#This Row],[NETO GRAVADO]:[Otros / No Grav.]]) -> 115759.96 | Q15: =IFERROR(IF(compras_mes1[[#This Row],[CUIT]]="","-",VLOOKUP(compras_mes1[[#This Row],[CUIT]],Lista_CUIT[#All],3,0)),"CUIT NO CARGADO") -> Peajes | R15: =IFERROR(IF(compras_mes1[[#This Row],[CUIT]]="","-",VLOOKUP(compras_mes1[[#This Row],[CUIT]],Lista_CUIT[#All],4,0)),"CUIT NO CARGADO") -> 0
B16: 15/01/2025 | C16: 1 | D16: 5015 | E16: 714530 | F16: 30574876474 | G16: =IFERROR(IF(compras_mes1[[#This Row],[CUIT]]="","-",VLOOKUP(compras_mes1[[#This Row],[CUIT]],Lista_CUIT[#All],2,0)),"CUIT NO CARGADO") -> AUTOPISTAS URBANAS S A | H16: 70476.38 | I16: =IF(compras_mes1[[#This Row],[NETO GRAVADO]]="","",compras_mes1[[#This Row],[NETO GRAVADO]]*0.21) -> 14800.04 | O16: 9161.91 | P16: =SUM(compras_mes1[[#This Row],[NETO GRAVADO]:[Otros / No Grav.]]) -> 94438.33 | Q16: =IFERROR(IF(compras_mes1[[#This Row],[CUIT]]="","-",VLOOKUP(compras_mes1[[#This Row],[CUIT]],Lista_CUIT[#All],3,0)),"CUIT NO CARGADO") -> Peajes | R16: =IFERROR(IF(compras_mes1[[#This Row],[CUIT]]="","-",VLOOKUP(compras_mes1[[#This Row],[CUIT]],Lista_CUIT[#All],4,0)),"CUIT NO CARGADO") -> 0
B17: 23/01/2025 | C17: 1 | D17: 5015 | E17: 727543 | F17: 30574876474 | G17: =IFERROR(IF(compras_mes1[[#This Row],[CUIT]]="","-",VLOOKUP(compras_mes1[[#This Row],[CUIT]],Lista_CUIT[#All],2,0)),"CUIT NO CARGADO") -> AUTOPISTAS URBANAS S A | H17: 64396.7 | I17: =IF(compras_mes1[[#This Row],[NETO GRAVADO]]="","",compras_mes1[[#This Row],[NETO GRAVADO]]*0.21) -> 13523.307 | O17: 8371.55 | P17: =SUM(compras_mes1[[#This Row],[NETO GRAVADO]:[Otros / No Grav.]]) -> 86291.557 | Q17: =IFERROR(IF(compras_mes1[[#This Row],[CUIT]]="","-",VLOOKUP(compras_mes1[[#This Row],[CUIT]],Lista_CUIT[#All],3,0)),"CUIT NO CARGADO") -> Peajes | R17: =IFERROR(IF(compras_mes1[[#This Row],[CUIT]]="","-",VLOOKUP(compras_mes1[[#This Row],[CUIT]],Lista_CUIT[#All],4,0)),"CUIT NO CARGADO") -> 0
B18: 31/01/2025 | C18: 1 | D18: 5015 | E18: 737142 | F18: 30574876474 | G18: =IFERROR(IF(compras_mes1[[#This Row],[CUIT]]="","-",VLOOKUP(compras_mes1[[#This Row],[CUIT]],Lista_CUIT[#All],2,0)),"CUIT NO CARGADO") -> AUTOPISTAS URBANAS S A | H18: 76599.56 | I18: =IF(compras_mes1[[#This Row],[NETO GRAVADO]]="","",compras_mes1[[#This Row],[NETO GRAVADO]]*0.21) -> 16085.908 | O18: 9957.9 | P18: =SUM(compras_mes1[[#This Row],[NETO GRAVADO]:[Otros / No Grav.]]) -> 102643.37 | Q18: =IFERROR(IF(compras_mes1[[#This Row],[CUIT]]="","-",VLOOKUP(compras_mes1[[#This Row],[CUIT]],Lista_CUIT[#All],3,0)),"CUIT NO CARGADO") -> Peajes | R18: =IFERROR(IF(compras_mes1[[#This Row],[CUIT]]="","-",VLOOKUP(compras_mes1[[#This Row],[CUIT]],Lista_CUIT[#All],4,0)),"CUIT NO CARGADO") -> 0
B19: 08/01/2025 | C19: 1 | D19: 2 | E19: 288 | F19: 27309896063 | G19: =IFERROR(IF(compras_mes1[[#This Row],[CUIT]]="","-",VLOOKUP(compras_mes1[[#This Row],[CUIT]],Lista_CUIT[#All],2,0)),"CUIT NO CARGADO") -> BATTELLINI MARIA SOLEDAD | H19: 550000 | I19: =IF(compras_mes1[[#This Row],[NETO GRAVADO]]="","",compras_mes1[[#This Row],[NETO GRAVADO]]*0.21) -> 115500 | P19: =SUM(compras_mes1[[#This Row],[NETO GRAVADO]:[Otros / No Grav.]]) -> 665500 | Q19: =IFERROR(IF(compras_mes1[[#This Row],[CUIT]]="","-",VLOOKUP(compras_mes1[[#This Row],[CUIT]],Lista_CUIT[#All],3,0)),"CUIT NO CARGADO") -> Alquiler | R19: =IFERROR(IF(compras_mes1[[#This Row],[CUIT]]="","-",VLOOKUP(compras_mes1[[#This Row],[CUIT]],Lista_CUIT[#All],4,0)),"CUIT NO CARGADO") -> 0
B20: 29/01/2025 | C20: 1 | D20: 503 | E20: 1669262 | F20: 30639935872 | G20: =IFERROR(IF(compras_mes1[[#This Row],[CUIT]]="","-",VLOOKUP(compras_mes1[[#This Row],[CUIT]],Lista_CUIT[#All],2,0)),"CUIT NO CARGADO") -> CAMINOS DEL RIO URUGUAY S A DE CONSTRUCCIONES Y CONCESIONES VIALES | H20: 10053.18 | I20: =IF(compras_mes1[[#This Row],[NETO GRAVADO]]="","",compras_mes1[[#This Row],[NETO GRAVADO]]*0.21) -> 2111.1678 | N20: 603.19 | P20: =SUM(compras_mes1[[#This Row],[NETO GRAVADO]:[Otros / No Grav.]]) -> 12767.538 | Q20: =IFERROR(IF(compras_mes1[[#This Row],[CUIT]]="","-",VLOOKUP(compras_mes1[[#This Row],[CUIT]],Lista_CUIT[#All],3,0)),"CUIT NO CARGADO") -> Peajes | R20: =IFERROR(IF(compras_mes1[[#This Row],[CUIT]]="","-",VLOOKUP(compras_mes1[[#This Row],[CUIT]],Lista_CUIT[#All],4,0)),"CUIT NO CARGADO") -> 0
B21: 08/01/2025 | C21: 1 | D21: 4 | E21: 21 | F21: 20262815367 | G21: =IFERROR(IF(compras_mes1[[#This Row],[CUIT]]="","-",VLOOKUP(compras_mes1[[#This Row],[CUIT]],Lista_CUIT[#All],2,0)),"CUIT NO CARGADO") -> CARDARELLO BASAVILBASO FEDERICO JORGE | H21: 16198.35 | I21: =IF(compras_mes1[[#This Row],[NETO GRAVADO]]="","",compras_mes1[[#This Row],[NETO GRAVADO]]*0.21) -> 3401.6535 | P21: =SUM(compras_mes1[[#This Row],[NETO GRAVADO]:[Otros / No Grav.]]) -> 19600.003 | Q21: =IFERROR(IF(compras_mes1[[#This Row],[CUIT]]="","-",VLOOKUP(compras_mes1[[#This Row],[CUIT]],Lista_CUIT[#All],3,0)),"CUIT NO CARGADO") -> Gastos Varios | R21: =IFERROR(IF(compras_mes1[[#This Row],[CUIT]]="","-",VLOOKUP(compras_mes1[[#This Row],[CUIT]],Lista_CUIT[#All],4,0)),"CUIT NO CARGADO") -> 0
B22: 07/01/2025 | C22: 1 | D22: 9 | E22: 10766 | F22: 30709531960 | G22: =IFERROR(IF(compras_mes1[[#This Row],[CUIT]]="","-",VLOOKUP(compras_mes1[[#This Row],[CUIT]],Lista_CUIT[#All],2,0)),"CUIT NO CARGADO") -> CENTRO DE DISTRIBUCION SUR S R L | H22: 29756.6 | I22: =IF(compras_mes1[[#This Row],[NETO GRAVADO]]="","",compras_mes1[[#This Row],[NETO GRAVADO]]*0.21) -> 6248.886 | N22: 1785.4 | P22: =SUM(compras_mes1[[#This Row],[NETO GRAVADO]:[Otros / No Grav.]]) -> 37790.886 | Q22: =IFERROR(IF(compras_mes1[[#This Row],[CUIT]]="","-",VLOOKUP(compras_mes1[[#This Row],[CUIT]],Lista_CUIT[#All],3,0)),"CUIT NO CARGADO") -> Gastos Limpieza | R22: =IFERROR(IF(compras_mes1[[#This Row],[CUIT]]="","-",VLOOKUP(compras_mes1[[#This Row],[CUIT]],Lista_CUIT[#All],4,0)),"CUIT NO CARGADO") -> 0
B23: 02/01/2025 | C23: 1 | D23: 1 | E23: 577 | F23: 20131206144 | G23: =IFERROR(IF(compras_mes1[[#This Row],[CUIT]]="","-",VLOOKUP(compras_mes1[[#This Row],[CUIT]],Lista_CUIT[#All],2,0)),"CUIT NO CARGADO") -> CHAMORRO MANUEL | H23: 1009489 | I23: =IF(compras_mes1[[#This Row],[NETO GRAVADO]]="","",compras_mes1[[#This Row],[NETO GRAVADO]]*0.21) -> 211992.69 | P23: =SUM(compras_mes1[[#This Row],[NETO GRAVADO]:[Otros / No Grav.]]) -> 1221481.7 | Q23: =IFERROR(IF(compras_mes1[[#This Row],[CUIT]]="","-",VLOOKUP(compras_mes1[[#This Row],[CUIT]],Lista_CUIT[#All],3,0)),"CUIT NO CARGADO") -> Alquiler | R23: =IFERROR(IF(compras_mes1[[#This Row],[CUIT]]="","-",VLOOKUP(compras_mes1[[#This Row],[CUIT]],Lista_CUIT[#All],4,0)),"CUIT NO CARGADO") -> 0
B24: 06/01/2025 | C24: 1 | D24: 2 | E24: 83308 | F24: 30715023497 | G24: =IFERROR(IF(compras_mes1[[#This Row],[CUIT]]="","-",VLOOKUP(compras_mes1[[#This Row],[CUIT]],Lista_CUIT[#All],2,0)),"CUIT NO CARGADO") -> EVER SAFE S.R.L. | H24: 26859.5 | I24: =IF(compras_mes1[[#This Row],[NETO GRAVADO]]="","",compras_mes1[[#This Row],[NETO GRAVADO]]*0.21) -> 5640.495 | P24: =SUM(compras_mes1[[#This Row],[NETO GRAVADO]:[Otros / No Grav.]]) -> 32499.995 | Q24: =IFERROR(IF(compras_mes1[[#This Row],[CUIT]]="","-",VLOOKUP(compras_mes1[[#This Row],[CUIT]],Lista_CUIT[#All],3,0)),"CUIT NO CARGADO") -> Gastos Varios | R24: =IFERROR(IF(compras_mes1[[#This Row],[CUIT]]="","-",VLOOKUP(compras_mes1[[#This Row],[CUIT]],Lista_CUIT[#All],4,0)),"CUIT NO CARGADO") -> 0
B25: 15/01/2025 | C25: 1 | D25: 113 | E25: 4023609 | F25: 30577207190 | G25: =IFERROR(IF(compras_mes1[[#This Row],[CUIT]]="","-",VLOOKUP(compras_mes1[[#This Row],[CUIT]],Lista_CUIT[#All],2,0)),"CUIT NO CARGADO") -> COORDINACION ECOLOGICA AREA METROPOLITANA SOCIEDAD DEL ESTADO | H25: 3966.94 | I25: =IF(compras_mes1[[#This Row],[NETO GRAVADO]]="","",compras_mes1[[#This Row],[NETO GRAVADO]]*0.21) -> 833.0574 | L25: 119.01 | P25: =SUM(compras_mes1[[#This Row],[NETO GRAVADO]:[Otros / No Grav.]]) -> 4919.0074 | Q25: =IFERROR(IF(compras_mes1[[#This Row],[CUIT]]="","-",VLOOKUP(compras_mes1[[#This Row],[CUIT]],Lista_CUIT[#All],3,0)),"CUIT NO CARGADO") -> Gastos Limpieza | R25: =IFERROR(IF(compras_mes1[[#This Row],[CUIT]]="","-",VLOOKUP(compras_mes1[[#This Row],[CUIT]],Lista_CUIT[#All],4,0)),"CUIT NO CARGADO") -> 0
B26: 31/01/2025 | C26: 1 | D26: 113 | E26: 4048471 | F26: 30577207190 | G26: =IFERROR(IF(compras_mes1[[#This Row],[CUIT]]="","-",VLOOKUP(compras_mes1[[#This Row],[CUIT]],Lista_CUIT[#All],2,0)),"CUIT NO CARGADO") -> COORDINACION ECOLOGICA AREA METROPOLITANA SOCIEDAD DEL ESTADO | H26: 5960.33 | I26: =IF(compras_mes1[[#This Row],[NETO GRAVADO]]="","",compras_mes1[[#This Row],[NETO GRAVADO]]*0.21) -> 1251.6693 | L26: 178.81 | P26: =SUM(compras_mes1[[#This Row],[NETO GRAVADO]:[Otros / No Grav.]]) -> 7390.8093 | Q26: =IFERROR(IF(compras_mes1[[#This Row],[CUIT]]="","-",VLOOKUP(compras_mes1[[#This Row],[CUIT]],Lista_CUIT[#All],3,0)),"CUIT NO CARGADO") -> Gastos Limpieza | R26: =IFERROR(IF(compras_mes1[[#This Row],[CUIT]]="","-",VLOOKUP(compras_mes1[[#This Row],[CUIT]],Lista_CUIT[#All],4,0)),"CUIT NO CARGADO") -> 0
B27: 07/01/2025 | C27: 1 | D27: 700 | E27: 2181747 | F27: 30715804812 | G27: =IFERROR(IF(compras_mes1[[#This Row],[CUIT]]="","-",VLOOKUP(compras_mes1[[#This Row],[CUIT]],Lista_CUIT[#All],2,0)),"CUIT NO CARGADO") -> CORREDORES VIALES SOCIEDAD ANONIMA | H27: 2703.95 | I27: =IF(compras_mes1[[#This Row],[NETO GRAVADO]]="","",compras_mes1[[#This Row],[NETO GRAVADO]]*0.21) -> 567.8295 | P27: =SUM(compras_mes1[[#This Row],[NETO GRAVADO]:[Otros / No Grav.]]) -> 3271.7795 | Q27: =IFERROR(IF(compras_mes1[[#This Row],[CUIT]]="","-",VLOOKUP(compras_mes1[[#This Row],[CUIT]],Lista_CUIT[#All],3,0)),"CUIT NO CARGADO") -> Peajes | R27: =IFERROR(IF(compras_mes1[[#This Row],[CUIT]]="","-",VLOOKUP(compras_mes1[[#This Row],[CUIT]],Lista_CUIT[#All],4,0)),"CUIT NO CARGADO") -> 0
B28: 14/01/2025 | C28: 1 | D28: 104 | E28: 7758171 | F28: 30715804812 | G28: =IFERROR(IF(compras_mes1[[#This Row],[CUIT]]="","-",VLOOKUP(compras_mes1[[#This Row],[CUIT]],Lista_CUIT[#All],2,0)),"CUIT NO CARGADO") -> CORREDORES VIALES SOCIEDAD ANONIMA | H28: 1039.98 | I28: =IF(compras_mes1[[#This Row],[NETO GRAVADO]]="","",compras_mes1[[#This Row],[NETO GRAVADO]]*0.21) -> 218.3958 | M28: 62.4 | P28: =SUM(compras_mes1[[#This Row],[NETO GRAVADO]:[Otros / No Grav.]]) -> 1320.7758 | Q28: =IFERROR(IF(compras_mes1[[#This Row],[CUIT]]="","-",VLOOKUP(compras_mes1[[#This Row],[CUIT]],Lista_CUIT[#All],3,0)),"CUIT NO CARGADO") -> Peajes | R28: =IFERROR(IF(compras_mes1[[#This Row],[CUIT]]="","-",VLOOKUP(compras_mes1[[#This Row],[CUIT]],Lista_CUIT[#All],4,0)),"CUIT NO CARGADO") -> 0
B29: 21/01/2025 | C29: 1 | D29: 700 | E29: 2215027 | F29: 30715804812 | G29: =IFERROR(IF(compras_mes1[[#This Row],[CUIT]]="","-",VLOOKUP(compras_mes1[[#This Row],[CUIT]],Lista_CUIT[#All],2,0)),"CUIT NO CARGADO") -> CORREDORES VIALES SOCIEDAD ANONIMA | H29: 4575.92 | I29: =IF(compras_mes1[[#This Row],[NETO GRAVADO]]="","",compras_mes1[[#This Row],[NETO GRAVADO]]*0.21) -> 960.9432 | P29: =SUM(compras_mes1[[#This Row],[NETO GRAVADO]:[Otros / No Grav.]]) -> 5536.8632 | Q29: =IFERROR(IF(compras_mes1[[#This Row],[CUIT]]="","-",VLOOKUP(compras_mes1[[#This Row],[CUIT]],Lista_CUIT[#All],3,0)),"CUIT NO CARGADO") -> Peajes | R29: =IFERROR(IF(compras_mes1[[#This Row],[CUIT]]="","-",VLOOKUP(compras_mes1[[#This Row],[CUIT]],Lista_CUIT[#All],4,0)),"CUIT NO CARGADO") -> 0
B30: 09/01/2025 | C30: 1 | D30: 2018 | E30: 5871 | F30: 30548083156 | G30: =IFERROR(IF(compras_mes1[[#This Row],[CUIT]]="","-",VLOOKUP(compras_mes1[[#This Row],[CUIT]],Lista_CUIT[#All],2,0)),"CUIT NO CARGADO") -> COTO CENTRO INTEGRAL DE COMERCIALIZACION SOCIEDAD ANONIMA | H30: 19427.9 | I30: =IF(compras_mes1[[#This Row],[NETO GRAVADO]]="","",compras_mes1[[#This Row],[NETO GRAVADO]]*0.21) -> 4079.859 | O30: 1748.51 | P30: =SUM(compras_mes1[[#This Row],[NETO GRAVADO]:[Otros / No Grav.]]) -> 25256.269 | Q30: =IFERROR(IF(compras_mes1[[#This Row],[CUIT]]="","-",VLOOKUP(compras_mes1[[#This Row],[CUIT]],Lista_CUIT[#All],3,0)),"CUIT NO CARGADO") -> Gastos Varios | R30: =IFERROR(IF(compras_mes1[[#This Row],[CUIT]]="","-",VLOOKUP(compras_mes1[[#This Row],[CUIT]],Lista_CUIT[#All],4,0)),"CUIT NO CARGADO") -> 0
B31: 09/01/2025 | C31: 1 | D31: 2199 | E31: 34414 | F31: 30548083156 | G31: =IFERROR(IF(compras_mes1[[#This Row],[CUIT]]="","-",VLOOKUP(compras_mes1[[#This Row],[CUIT]],Lista_CUIT[#All],2,0)),"CUIT NO CARGADO") -> COTO CENTRO INTEGRAL DE COMERCIALIZACION SOCIEDAD ANONIMA | H31: 59262.1 | I31: =IF(compras_mes1[[#This Row],[NETO GRAVADO]]="","",compras_mes1[[#This Row],[NETO GRAVADO]]*0.21) -> 12445.041 | O31: 5132.13 | P31: =SUM(compras_mes1[[#This Row],[NETO GRAVADO]:[Otros / No Grav.]]) -> 76839.271 | Q31: =IFERROR(IF(compras_mes1[[#This Row],[CUIT]]="","-",VLOOKUP(compras_mes1[[#This Row],[CUIT]],Lista_CUIT[#All],3,0)),"CUIT NO CARGADO") -> Gastos Varios | R31: =IFERROR(IF(compras_mes1[[#This Row],[CUIT]]="","-",VLOOKUP(compras_mes1[[#This Row],[CUIT]],Lista_CUIT[#All],4,0)),"CUIT NO CARGADO") -> 0
B32: 10/01/2025 | C32: 1 | D32: 2188 | E32: 139314 | F32: 30548083156 | G32: =IFERROR(IF(compras_mes1[[#This Row],[CUIT]]="","-",VLOOKUP(compras_mes1[[#This Row],[CUIT]],Lista_CUIT[#All],2,0)),"CUIT NO CARGADO") -> COTO CENTRO INTEGRAL DE COMERCIALIZACION SOCIEDAD ANONIMA | H32: 86331.94 | I32: 15199.6 | K32: 1465.05 | O32: 7390.82 | P32: =SUM(compras_mes1[[#This Row],[NETO GRAVADO]:[Otros / No Grav.]]) -> 110387.41 | Q32: =IFERROR(IF(compras_mes1[[#This Row],[CUIT]]="","-",VLOOKUP(compras_mes1[[#This Row],[CUIT]],Lista_CUIT[#All],3,0)),"CUIT NO CARGADO") -> Gastos Varios | R32: =IFERROR(IF(compras_mes1[[#This Row],[CUIT]]="","-",VLOOKUP(compras_mes1[[#This Row],[CUIT]],Lista_CUIT[#All],4,0)),"CUIT NO CARGADO") -> 0
B33: 11/01/2025 | C33: 1 | D33: 2199 | E33: 34452 | F33: 30548083156 | G33: =IFERROR(IF(compras_mes1[[#This Row],[CUIT]]="","-",VLOOKUP(compras_mes1[[#This Row],[CUIT]],Lista_CUIT[#All],2,0)),"CUIT NO CARGADO") -> COTO CENTRO INTEGRAL DE COMERCIALIZACION SOCIEDAD ANONIMA | H33: 24354.73 | I33: 4770.14 | K33: 172.18 | O33: 2140.63 | P33: =SUM(compras_mes1[[#This Row],[NETO GRAVADO]:[Otros / No Grav.]]) -> 31437.68 | Q33: =IFERROR(IF(compras_mes1[[#This Row],[CUIT]]="","-",VLOOKUP(compras_mes1[[#This Row],[CUIT]],Lista_CUIT[#All],3,0)),"CUIT NO CARGADO") -> Gastos Varios | R33: =IFERROR(IF(compras_mes1[[#This Row],[CUIT]]="","-",VLOOKUP(compras_mes1[[#This Row],[CUIT]],Lista_CUIT[#All],4,0)),"CUIT NO CARGADO") -> 0
B34: 11/01/2025 | C34: 1 | D34: 2084 | E34: 26860 | F34: 30548083156 | G34: =IFERROR(IF(compras_mes1[[#This Row],[CUIT]]="","-",VLOOKUP(compras_mes1[[#This Row],[CUIT]],Lista_CUIT[#All],2,0)),"CUIT NO CARGADO") -> COTO CENTRO INTEGRAL DE COMERCIALIZACION SOCIEDAD ANONIMA | H34: 54278.54 | I34: =IF(compras_mes1[[#This Row],[NETO GRAVADO]]="","",compras_mes1[[#This Row],[NETO GRAVADO]]*0.21) -> 11398.493 | O34: 4753.33 | P34: =SUM(compras_mes1[[#This Row],[NETO GRAVADO]:[Otros / No Grav.]]) -> 70430.363 | Q34: =IFERROR(IF(compras_mes1[[#This Row],[CUIT]]="","-",VLOOKUP(compras_mes1[[#This Row],[CUIT]],Lista_CUIT[#All],3,0)),"CUIT NO CARGADO") -> Gastos Varios | R34: =IFERROR(IF(compras_mes1[[#This Row],[CUIT]]="","-",VLOOKUP(compras_mes1[[#This Row],[CUIT]],Lista_CUIT[#All],4,0)),"CUIT NO CARGADO") -> 0
B35: 17/01/2025 | C35: 1 | D35: 2199 | E35: 34567 | F35: 30548083156 | G35: =IFERROR(IF(compras_mes1[[#This Row],[CUIT]]="","-",VLOOKUP(compras_mes1[[#This Row],[CUIT]],Lista_CUIT[#All],2,0)),"CUIT NO CARGADO") -> COTO CENTRO INTEGRAL DE COMERCIALIZACION SOCIEDAD ANONIMA | H35: 28228.91 | I35: 2484.65 | K35: 1721.71 | O35: 1563.98 | P35: =SUM(compras_mes1[[#This Row],[NETO GRAVADO]:[Otros / No Grav.]]) -> 33999.25 | Q35: =IFERROR(IF(compras_mes1[[#This Row],[CUIT]]="","-",VLOOKUP(compras_mes1[[#This Row],[CUIT]],Lista_CUIT[#All],3,0)),"CUIT NO CARGADO") -> Gastos Varios | R35: =IFERROR(IF(compras_mes1[[#This Row],[CUIT]]="","-",VLOOKUP(compras_mes1[[#This Row],[CUIT]],Lista_CUIT[#All],4,0)),"CUIT NO CARGADO") -> 0
B36: 18/01/2025 | C36: 1 | D36: 2084 | E36: 26973 | F36: 30548083156 | G36: =IFERROR(IF(compras_mes1[[#This Row],[CUIT]]="","-",VLOOKUP(compras_mes1[[#This Row],[CUIT]],Lista_CUIT[#All],2,0)),"CUIT NO CARGADO") -> COTO CENTRO INTEGRAL DE COMERCIALIZACION SOCIEDAD ANONIMA | H36: 26243.84 | I36: =IF(compras_mes1[[#This Row],[NETO GRAVADO]]="","",compras_mes1[[#This Row],[NETO GRAVADO]]*0.21) -> 5511.2064 | O36: 2361.95 | P36: =SUM(compras_mes1[[#This Row],[NETO GRAVADO]:[Otros / No Grav.]]) -> 34116.996 | Q36: =IFERROR(IF(compras_mes1[[#This Row],[CUIT]]="","-",VLOOKUP(compras_mes1[[#This Row],[CUIT]],Lista_CUIT[#All],3,0)),"CUIT NO CARGADO") -> Gastos Varios | R36: =IFERROR(IF(compras_mes1[[#This Row],[CUIT]]="","-",VLOOKUP(compras_mes1[[#This Row],[CUIT]],Lista_CUIT[#All],4,0)),"CUIT NO CARGADO") -> 0
B37: 27/01/2025 | C37: 1 | D37: 2199 | E37: 34760 | F37: 30548083156 | G37: =IFERROR(IF(compras_mes1[[#This Row],[CUIT]]="","-",VLOOKUP(compras_mes1[[#This Row],[CUIT]],Lista_CUIT[#All],2,0)),"CUIT NO CARGADO") -> COTO CENTRO INTEGRAL DE COMERCIALIZACION SOCIEDAD ANONIMA | H37: 76325.89 | I37: 15268.43 | K37: 380 | O37: 6427.39 | P37: =SUM(compras_mes1[[#This Row],[NETO GRAVADO]:[Otros / No Grav.]]) -> 98401.71 | Q37: =IFERROR(IF(compras_mes1[[#This Row],[CUIT]]="","-",VLOOKUP(compras_mes1[[#This Row],[CUIT]],Lista_CUIT[#All],3,0)),"CUIT NO CARGADO") -> Gastos Varios | R37: =IFERROR(IF(compras_mes1[[#This Row],[CUIT]]="","-",VLOOKUP(compras_mes1[[#This Row],[CUIT]],Lista_CUIT[#All],4,0)),"CUIT NO CARGADO") -> 0
B38: 27/01/2025 | C38: 1 | D38: 2199 | E38: 34761 | F38: 30548083156 | G38: =IFERROR(IF(compras_mes1[[#This Row],[CUIT]]="","-",VLOOKUP(compras_mes1[[#This Row],[CUIT]],Lista_CUIT[#All],2,0)),"CUIT NO CARGADO") -> COTO CENTRO INTEGRAL DE COMERCIALIZACION SOCIEDAD ANONIMA | H38: 6292.55 | I38: =IF(compras_mes1[[#This Row],[NETO GRAVADO]]="","",compras_mes1[[#This Row],[NETO GRAVADO]]*0.21) -> 1321.4355 | O38: 566.33 | P38: =SUM(compras_mes1[[#This Row],[NETO GRAVADO]:[Otros / No Grav.]]) -> 8180.3155 | Q38: =IFERROR(IF(compras_mes1[[#This Row],[CUIT]]="","-",VLOOKUP(compras_mes1[[#This Row],[CUIT]],Lista_CUIT[#All],3,0)),"CUIT NO CARGADO") -> Gastos Varios | R38: =IFERROR(IF(compras_mes1[[#This Row],[CUIT]]="","-",VLOOKUP(compras_mes1[[#This Row],[CUIT]],Lista_CUIT[#All],4,0)),"CUIT NO CARGADO") -> 0
B39: 27/01/2025 | C39: 3 | D39: 2199 | E39: 319 | F39: 30548083156 | G39: =IFERROR(IF(compras_mes1[[#This Row],[CUIT]]="","-",VLOOKUP(compras_mes1[[#This Row],[CUIT]],Lista_CUIT[#All],2,0)),"CUIT NO CARGADO") -> COTO CENTRO INTEGRAL DE COMERCIALIZACION SOCIEDAD ANONIMA | H39: -9474.37 | I39: =IF(compras_mes1[[#This Row],[NETO GRAVADO]]="","",compras_mes1[[#This Row],[NETO GRAVADO]]*0.21) -> -1989.6177 | O39: -852.69 | P39: =SUM(compras_mes1[[#This Row],[NETO GRAVADO]:[Otros / No Grav.]]) -> -12316.678 | Q39: =IFERROR(IF(compras_mes1[[#This Row],[CUIT]]="","-",VLOOKUP(compras_mes1[[#This Row],[CUIT]],Lista_CUIT[#All],3,0)),"CUIT NO CARGADO") -> Gastos Varios | R39: =IFERROR(IF(compras_mes1[[#This Row],[CUIT]]="","-",VLOOKUP(compras_mes1[[#This Row],[CUIT]],Lista_CUIT[#All],4,0)),"CUIT NO CARGADO") -> 0
B40: 45670 | C40: 1 | D40: 6 | E40: 2122 | F40: 30718465636 | G40: =IFERROR(IF(compras_mes1[[#This Row],[CUIT]]="","-",VLOOKUP(compras_mes1[[#This Row],[CUIT]],Lista_CUIT[#All],2,0)),"CUIT NO CARGADO") -> MAQUINARIAS BOEDO SRL | H40: 306466.11 | I40: =IF(compras_mes1[[#This Row],[NETO GRAVADO]]="","",compras_mes1[[#This Row],[NETO GRAVADO]]*0.21) -> 64357.883 | P40: =SUM(compras_mes1[[#This Row],[NETO GRAVADO]:[Otros / No Grav.]]) -> 370823.99 | Q40: =IFERROR(IF(compras_mes1[[#This Row],[CUIT]]="","-",VLOOKUP(compras_mes1[[#This Row],[CUIT]],Lista_CUIT[#All],3,0)),"CUIT NO CARGADO") -> Muebles y Utiles | R40: =IFERROR(IF(compras_mes1[[#This Row],[CUIT]]="","-",VLOOKUP(compras_mes1[[#This Row],[CUIT]],Lista_CUIT[#All],4,0)),"CUIT NO CARGADO") -> 0
B41: 02/01/2025 | C41: 1 | D41: 33 | E41: 209 | F41: 30711583927 | G41: =IFERROR(IF(compras_mes1[[#This Row],[CUIT]]="","-",VLOOKUP(compras_mes1[[#This Row],[CUIT]],Lista_CUIT[#All],2,0)),"CUIT NO CARGADO") -> LOVE IN SA | H41: 53719.01 | I41: =IF(compras_mes1[[#This Row],[NETO GRAVADO]]="","",compras_mes1[[#This Row],[NETO GRAVADO]]*0.21) -> 11280.992 | P41: =SUM(compras_mes1[[#This Row],[NETO GRAVADO]:[Otros / No Grav.]]) -> 65000.002 | Q41: =IFERROR(IF(compras_mes1[[#This Row],[CUIT]]="","-",VLOOKUP(compras_mes1[[#This Row],[CUIT]],Lista_CUIT[#All],3,0)),"CUIT NO CARGADO") -> Gastos Varios | R41: =IFERROR(IF(compras_mes1[[#This Row],[CUIT]]="","-",VLOOKUP(compras_mes1[[#This Row],[CUIT]],Lista_CUIT[#All],4,0)),"CUIT NO CARGADO") -> 0
B42: 06/01/2025 | C42: 1 | D42: 4 | E42: 9877 | F42: 20381760317 | G42: =IFERROR(IF(compras_mes1[[#This Row],[CUIT]]="","-",VLOOKUP(compras_mes1[[#This Row],[CUIT]],Lista_CUIT[#All],2,0)),"CUIT NO CARGADO") -> NEASTORE | H42: 9090.08 | I42: =IF(compras_mes1[[#This Row],[NETO GRAVADO]]="","",compras_mes1[[#This Row],[NETO GRAVADO]]*0.21) -> 1908.9168 | P42: =SUM(compras_mes1[[#This Row],[NETO GRAVADO]:[Otros / No Grav.]]) -> 10998.997 | Q42: =IFERROR(IF(compras_mes1[[#This Row],[CUIT]]="","-",VLOOKUP(compras_mes1[[#This Row],[CUIT]],Lista_CUIT[#All],3,0)),"CUIT NO CARGADO") -> Gastos Limpieza | R42: =IFERROR(IF(compras_mes1[[#This Row],[CUIT]]="","-",VLOOKUP(compras_mes1[[#This Row],[CUIT]],Lista_CUIT[#All],4,0)),"CUIT NO CARGADO") -> 0
B43: 06/01/2025 | C43: 1 | D43: 6 | E43: 5881 | F43: 30711431981 | G43: =IFERROR(IF(compras_mes1[[#This Row],[CUIT]]="","-",VLOOKUP(compras_mes1[[#This Row],[CUIT]],Lista_CUIT[#All],2,0)),"CUIT NO CARGADO") -> TANGOID SRL | H43: 52215.45 | I43: =IF(compras_mes1[[#This Row],[NETO GRAVADO]]="","",compras_mes1[[#This Row],[NETO GRAVADO]]*0.21) -> 10965.244 | P43: =SUM(compras_mes1[[#This Row],[NETO GRAVADO]:[Otros / No Grav.]]) -> 63180.694 | Q43: =IFERROR(IF(compras_mes1[[#This Row],[CUIT]]="","-",VLOOKUP(compras_mes1[[#This Row],[CUIT]],Lista_CUIT[#All],3,0)),"CUIT NO CARGADO") -> Gastos Varios | R43: =IFERROR(IF(compras_mes1[[#This Row],[CUIT]]="","-",VLOOKUP(compras_mes1[[#This Row],[CUIT]],Lista_CUIT[#All],4,0)),"CUIT NO CARGADO") -> 0
B44: 06/01/2025 | C44: 1 | D44: 90 | E44: 48142 | F44: 30710852762 | G44: =IFERROR(IF(compras_mes1[[#This Row],[CUIT]]="","-",VLOOKUP(compras_mes1[[#This Row],[CUIT]],Lista_CUIT[#All],2,0)),"CUIT NO CARGADO") -> REBORN SRL | H44: 26076.42 | I44: =IF(compras_mes1[[#This Row],[NETO GRAVADO]]="","",compras_mes1[[#This Row],[NETO GRAVADO]]*0.21) -> 5476.0482 | P44: =SUM(compras_mes1[[#This Row],[NETO GRAVADO]:[Otros / No Grav.]]) -> 31552.468 | Q44: =IFERROR(IF(compras_mes1[[#This Row],[CUIT]]="","-",VLOOKUP(compras_mes1[[#This Row],[CUIT]],Lista_CUIT[#All],3,0)),"CUIT NO CARGADO") -> Gastos Varios | R44: =IFERROR(IF(compras_mes1[[#This Row],[CUIT]]="","-",VLOOKUP(compras_mes1[[#This Row],[CUIT]],Lista_CUIT[#All],4,0)),"CUIT NO CARGADO") -> 0
B45: 07/01/2025 | C45: 1 | D45: 2 | E45: 2136 | F45: 30717961532 | G45: =IFERROR(IF(compras_mes1[[#This Row],[CUIT]]="","-",VLOOKUP(compras_mes1[[#This Row],[CUIT]],Lista_CUIT[#All],2,0)),"CUIT NO CARGADO") -> ABTEC SA | H45: 39718.47 | I45: =IF(compras_mes1[[#This Row],[NETO GRAVADO]]="","",compras_mes1[[#This Row],[NETO GRAVADO]]*0.21) -> 8340.8787 | P45: =SUM(compras_mes1[[#This Row],[NETO GRAVADO]:[Otros / No Grav.]]) -> 48059.349 | Q45: =IFERROR(IF(compras_mes1[[#This Row],[CUIT]]="","-",VLOOKUP(compras_mes1[[#This Row],[CUIT]],Lista_CUIT[#All],3,0)),"CUIT NO CARGADO") -> Gastos Varios | R45: =IFERROR(IF(compras_mes1[[#This Row],[CUIT]]="","-",VLOOKUP(compras_mes1[[#This Row],[CUIT]],Lista_CUIT[#All],4,0)),"CUIT NO CARGADO") -> 0
B46: 09/01/2025 | C46: 1 | D46: 11 | E46: 4901 | F46: 30717214494 | G46: =IFERROR(IF(compras_mes1[[#This Row],[CUIT]]="","-",VLOOKUP(compras_mes1[[#This Row],[CUIT]],Lista_CUIT[#All],2,0)),"CUIT NO CARGADO") -> ONE MEDICAL SRL | H46: 21399.47 | I46: =IF(compras_mes1[[#This Row],[NETO GRAVADO]]="","",compras_mes1[[#This Row],[NETO GRAVADO]]*0.21) -> 4493.8887 | P46: =SUM(compras_mes1[[#This Row],[NETO GRAVADO]:[Otros / No Grav.]]) -> 25893.359 | Q46: =IFERROR(IF(compras_mes1[[#This Row],[CUIT]]="","-",VLOOKUP(compras_mes1[[#This Row],[CUIT]],Lista_CUIT[#All],3,0)),"CUIT NO CARGADO") -> Gastos Limpieza | R46: =IFERROR(IF(compras_mes1[[#This Row],[CUIT]]="","-",VLOOKUP(compras_mes1[[#This Row],[CUIT]],Lista_CUIT[#All],4,0)),"CUIT NO CARGADO") -> 0
B47: 10/01/2025 | C47: 1 | D47: 5 | E47: 28022 | F47: 30715083937 | G47: =IFERROR(IF(compras_mes1[[#This Row],[CUIT]]="","-",VLOOKUP(compras_mes1[[#This Row],[CUIT]],Lista_CUIT[#All],2,0)),"CUIT NO CARGADO") -> MASHARY S.R.L | H47: 43726.51 | I47: =IF(compras_mes1[[#This Row],[NETO GRAVADO]]="","",compras_mes1[[#This Row],[NETO GRAVADO]]*0.21) -> 9182.5671 | P47: =SUM(compras_mes1[[#This Row],[NETO GRAVADO]:[Otros / No Grav.]]) -> 52909.077 | Q47: =IFERROR(IF(compras_mes1[[#This Row],[CUIT]]="","-",VLOOKUP(compras_mes1[[#This Row],[CUIT]],Lista_CUIT[#All],3,0)),"CUIT NO CARGADO") -> Muebles y Utiles | R47: =IFERROR(IF(compras_mes1[[#This Row],[CUIT]]="","-",VLOOKUP(compras_mes1[[#This Row],[CUIT]],Lista_CUIT[#All],4,0)),"CUIT NO CARGADO") -> 0
B48: 11/01/2025 | C48: 1 | D48: 3 | E48: 2646 | F48: 30708393262 | G48: =IFERROR(IF(compras_mes1[[#This Row],[CUIT]]="","-",VLOOKUP(compras_mes1[[#This Row],[CUIT]],Lista_CUIT[#All],2,0)),"CUIT NO CARGADO") -> VIVERO GALANTE BRUNO S.A. | H48: 46697.25 | I48: =IF(compras_mes1[[#This Row],[NETO GRAVADO]]="","",compras_mes1[[#This Row],[NETO GRAVADO]]*0.21) -> 9806.4225 | P48: =SUM(compras_mes1[[#This Row],[NETO GRAVADO]:[Otros / No Grav.]]) -> 56503.673 | Q48: =IFERROR(IF(compras_mes1[[#This Row],[CUIT]]="","-",VLOOKUP(compras_mes1[[#This Row],[CUIT]],Lista_CUIT[#All],3,0)),"CUIT NO CARGADO") -> Gastos Varios | R48: =IFERROR(IF(compras_mes1[[#This Row],[CUIT]]="","-",VLOOKUP(compras_mes1[[#This Row],[CUIT]],Lista_CUIT[#All],4,0)),"CUIT NO CARGADO") -> 0
B49: 13/01/2025 | C49: 1 | D49: 11 | E49: 312 | F49: 30707158952 | G49: =IFERROR(IF(compras_mes1[[#This Row],[CUIT]]="","-",VLOOKUP(compras_mes1[[#This Row],[CUIT]],Lista_CUIT[#All],2,0)),"CUIT NO CARGADO") -> INTERBAT SRL | H49: 109917.36 | I49: =IF(compras_mes1[[#This Row],[NETO GRAVADO]]="","",compras_mes1[[#This Row],[NETO GRAVADO]]*0.21) -> 23082.646 | P49: =SUM(compras_mes1[[#This Row],[NETO GRAVADO]:[Otros / No Grav.]]) -> 133000.01 | Q49: =IFERROR(IF(compras_mes1[[#This Row],[CUIT]]="","-",VLOOKUP(compras_mes1[[#This Row],[CUIT]],Lista_CUIT[#All],3,0)),"CUIT NO CARGADO") -> Gastos Varios | R49: =IFERROR(IF(compras_mes1[[#This Row],[CUIT]]="","-",VLOOKUP(compras_mes1[[#This Row],[CUIT]],Lista_CUIT[#All],4,0)),"CUIT NO CARGADO") -> 0
B50: 14/01/2025 | C50: 1 | D50: 1 | E50: 38349 | F50: 30717334015 | G50: =IFERROR(IF(compras_mes1[[#This Row],[CUIT]]="","-",VLOOKUP(compras_mes1[[#This Row],[CUIT]],Lista_CUIT[#All],2,0)),"CUIT NO CARGADO") -> DIGITAL SALES S.A | H50: 214875.21 | I50: =IF(compras_mes1[[#This Row],[NETO GRAVADO]]="","",compras_mes1[[#This Row],[NETO GRAVADO]]*0.21) -> 45123.794 | P50: =SUM(compras_mes1[[#This Row],[NETO GRAVADO]:[Otros / No Grav.]]) -> 259999 | Q50: =IFERROR(IF(compras_mes1[[#This Row],[CUIT]]="","-",VLOOKUP(compras_mes1[[#This Row],[CUIT]],Lista_CUIT[#All],3,0)),"CUIT NO CARGADO") -> Muebles y Utiles | R50: =IFERROR(IF(compras_mes1[[#This Row],[CUIT]]="","-",VLOOKUP(compras_mes1[[#This Row],[CUIT]],Lista_CUIT[#All],4,0)),"CUIT NO CARGADO") -> 0
B51: 14/01/2025 | C51: 1 | D51: 3 | E51: 3247 | F51: 30682116028 | G51: =IFERROR(IF(compras_mes1[[#This Row],[CUIT]]="","-",VLOOKUP(compras_mes1[[#This Row],[CUIT]],Lista_CUIT[#All],2,0)),"CUIT NO CARGADO") -> BLUE STAR CARGO SRL | H51: 752070 | I51: =IF(compras_mes1[[#This Row],[NETO GRAVADO]]="","",compras_mes1[[#This Row],[NETO GRAVADO]]*0.21) -> 157934.7 | O51: 966400 | P51: =SUM(compras_mes1[[#This Row],[NETO GRAVADO]:[Otros / No Grav.]]) -> 1876404.7 | Q51: =IFERROR(IF(compras_mes1[[#This Row],[CUIT]]="","-",VLOOKUP(compras_mes1[[#This Row],[CUIT]],Lista_CUIT[#All],3,0)),"CUIT NO CARGADO") -> Flete | R51: =IFERROR(IF(compras_mes1[[#This Row],[CUIT]]="","-",VLOOKUP(compras_mes1[[#This Row],[CUIT]],Lista_CUIT[#All],4,0)),"CUIT NO CARGADO") -> 0
B52: 20/01/2025 | C52: 1 | D52: 6 | E52: 698 | F52: 20258099290 | G52: =IFERROR(IF(compras_mes1[[#This Row],[CUIT]]="","-",VLOOKUP(compras_mes1[[#This Row],[CUIT]],Lista_CUIT[#All],2,0)),"CUIT NO CARGADO") -> CENZANO HERNAN | H52: 15537.19 | I52: =IF(compras_mes1[[#This Row],[NETO GRAVADO]]="","",compras_mes1[[#This Row],[NETO GRAVADO]]*0.21) -> 3262.8099 | P52: =SUM(compras_mes1[[#This Row],[NETO GRAVADO]:[Otros / No Grav.]]) -> 18800 | Q52: =IFERROR(IF(compras_mes1[[#This Row],[CUIT]]="","-",VLOOKUP(compras_mes1[[#This Row],[CUIT]],Lista_CUIT[#All],3,0)),"CUIT NO CARGADO") -> Gastos Varios | R52: =IFERROR(IF(compras_mes1[[#This Row],[CUIT]]="","-",VLOOKUP(compras_mes1[[#This Row],[CUIT]],Lista_CUIT[#All],4,0)),"CUIT NO CARGADO") -> 0
B53: 27/01/2025 | C53: 1 | D53: 17 | E53: 2307 | F53: 30686489325 | G53: =IFERROR(IF(compras_mes1[[#This Row],[CUIT]]="","-",VLOOKUP(compras_mes1[[#This Row],[CUIT]],Lista_CUIT[#All],2,0)),"CUIT NO CARGADO") -> ELECTRICIDAD AREV S R L | H53: 12228.36 | I53: =IF(compras_mes1[[#This Row],[NETO GRAVADO]]="","",compras_mes1[[#This Row],[NETO GRAVADO]]*0.21) -> 2567.9556 | N53: 733.7 | P53: =SUM(compras_mes1[[#This Row],[NETO GRAVADO]:[Otros / No Grav.]]) -> 15530.016 | Q53: =IFERROR(IF(compras_mes1[[#This Row],[CUIT]]="","-",VLOOKUP(compras_mes1[[#This Row],[CUIT]],Lista_CUIT[#All],3,0)),"CUIT NO CARGADO") -> Gastos Varios | R53: =IFERROR(IF(compras_mes1[[#This Row],[CUIT]]="","-",VLOOKUP(compras_mes1[[#This Row],[CUIT]],Lista_CUIT[#All],4,0)),"CUIT NO CARGADO") -> 0
B54: 28/01/2025 | C54: 1 | D54: 5 | E54: 19226 | F54: 30716006391 | G54: =IFERROR(IF(compras_mes1[[#This Row],[CUIT]]="","-",VLOOKUP(compras_mes1[[#This Row],[CUIT]],Lista_CUIT[#All],2,0)),"CUIT NO CARGADO") -> ALISSING | H54: 12781.49 | I54: =IF(compras_mes1[[#This Row],[NETO GRAVADO]]="","",compras_mes1[[#This Row],[NETO GRAVADO]]*0.21) -> 2684.1129 | P54: =SUM(compras_mes1[[#This Row],[NETO GRAVADO]:[Otros / No Grav.]]) -> 15465.603 | Q54: =IFERROR(IF(compras_mes1[[#This Row],[CUIT]]="","-",VLOOKUP(compras_mes1[[#This Row],[CUIT]],Lista_CUIT[#All],3,0)),"CUIT NO CARGADO") -> Gastos Varios | R54: =IFERROR(IF(compras_mes1[[#This Row],[CUIT]]="","-",VLOOKUP(compras_mes1[[#This Row],[CUIT]],Lista_CUIT[#All],4,0)),"CUIT NO CARGADO") -> 0
B55: 28/01/2025 | C55: 1 | D55: 5 | E55: 19227 | F55: 30716006391 | G55: =IFERROR(IF(compras_mes1[[#This Row],[CUIT]]="","-",VLOOKUP(compras_mes1[[#This Row],[CUIT]],Lista_CUIT[#All],2,0)),"CUIT NO CARGADO") -> ALISSING | H55: 12781.49 | I55: =IF(compras_mes1[[#This Row],[NETO GRAVADO]]="","",compras_mes1[[#This Row],[NETO GRAVADO]]*0.21) -> 2684.1129 | P55: =SUM(compras_mes1[[#This Row],[NETO GRAVADO]:[Otros / No Grav.]]) -> 15465.603 | Q55: =IFERROR(IF(compras_mes1[[#This Row],[CUIT]]="","-",VLOOKUP(compras_mes1[[#This Row],[CUIT]],Lista_CUIT[#All],3,0)),"CUIT NO CARGADO") -> Gastos Varios | R55: =IFERROR(IF(compras_mes1[[#This Row],[CUIT]]="","-",VLOOKUP(compras_mes1[[#This Row],[CUIT]],Lista_CUIT[#All],4,0)),"CUIT NO CARGADO") -> 0
B56: 28/01/2025 | C56: 1 | D56: 5 | E56: 19233 | F56: 30716006391 | G56: =IFERROR(IF(compras_mes1[[#This Row],[CUIT]]="","-",VLOOKUP(compras_mes1[[#This Row],[CUIT]],Lista_CUIT[#All],2,0)),"CUIT NO CARGADO") -> ALISSING | H56: 12781.49 | I56: =IF(compras_mes1[[#This Row],[NETO GRAVADO]]="","",compras_mes1[[#This Row],[NETO GRAVADO]]*0.21) -> 2684.1129 | P56: =SUM(compras_mes1[[#This Row],[NETO GRAVADO]:[Otros / No Grav.]]) -> 15465.603 | Q56: =IFERROR(IF(compras_mes1[[#This Row],[CUIT]]="","-",VLOOKUP(compras_mes1[[#This Row],[CUIT]],Lista_CUIT[#All],3,0)),"CUIT NO CARGADO") -> Gastos Varios | R56: =IFERROR(IF(compras_mes1[[#This Row],[CUIT]]="","-",VLOOKUP(compras_mes1[[#This Row],[CUIT]],Lista_CUIT[#All],4,0)),"CUIT NO CARGADO") -> 0
B57: 28/01/2025 | C57: 1 | D57: 5 | E57: 19234 | F57: 30716006391 | G57: =IFERROR(IF(compras_mes1[[#This Row],[CUIT]]="","-",VLOOKUP(compras_mes1[[#This Row],[CUIT]],Lista_CUIT[#All],2,0)),"CUIT NO CARGADO") -> ALISSING | H57: 12781.49 | I57: =IF(compras_mes1[[#This Row],[NETO GRAVADO]]="","",compras_mes1[[#This Row],[NETO GRAVADO]]*0.21) -> 2684.1129 | P57: =SUM(compras_mes1[[#This Row],[NETO GRAVADO]:[Otros / No Grav.]]) -> 15465.603 | Q57: =IFERROR(IF(compras_mes1[[#This Row],[CUIT]]="","-",VLOOKUP(compras_mes1[[#This Row],[CUIT]],Lista_CUIT[#All],3,0)),"CUIT NO CARGADO") -> Gastos Varios | R57: =IFERROR(IF(compras_mes1[[#This Row],[CUIT]]="","-",VLOOKUP(compras_mes1[[#This Row],[CUIT]],Lista_CUIT[#All],4,0)),"CUIT NO CARGADO") -> 0
B58: 28/01/2025 | C58: 1 | D58: 5 | E58: 19185 | F58: 30716006391 | G58: =IFERROR(IF(compras_mes1[[#This Row],[CUIT]]="","-",VLOOKUP(compras_mes1[[#This Row],[CUIT]],Lista_CUIT[#All],2,0)),"CUIT NO CARGADO") -> ALISSING | H58: 12781.49 | I58: =IF(compras_mes1[[#This Row],[NETO GRAVADO]]="","",compras_mes1[[#This Row],[NETO GRAVADO]]*0.21) -> 2684.1129 | P58: =SUM(compras_mes1[[#This Row],[NETO GRAVADO]:[Otros / No Grav.]]) -> 15465.603 | Q58: =IFERROR(IF(compras_mes1[[#This Row],[CUIT]]="","-",VLOOKUP(compras_mes1[[#This Row],[CUIT]],Lista_CUIT[#All],3,0)),"CUIT NO CARGADO") -> Gastos Varios | R58: =IFERROR(IF(compras_mes1[[#This Row],[CUIT]]="","-",VLOOKUP(compras_mes1[[#This Row],[CUIT]],Lista_CUIT[#All],4,0)),"CUIT NO CARGADO") -> 0
B59: 28/01/2025 | C59: 1 | D59: 5 | E59: 19186 | F59: 30716006391 | G59: =IFERROR(IF(compras_mes1[[#This Row],[CUIT]]="","-",VLOOKUP(compras_mes1[[#This Row],[CUIT]],Lista_CUIT[#All],2,0)),"CUIT NO CARGADO") -> ALISSING | H59: 25562.97 | I59: =IF(compras_mes1[[#This Row],[NETO GRAVADO]]="","",compras_mes1[[#This Row],[NETO GRAVADO]]*0.21) -> 5368.2237 | P59: =SUM(compras_mes1[[#This Row],[NETO GRAVADO]:[Otros / No Grav.]]) -> 30931.194 | Q59: =IFERROR(IF(compras_mes1[[#This Row],[CUIT]]="","-",VLOOKUP(compras_mes1[[#This Row],[CUIT]],Lista_CUIT[#All],3,0)),"CUIT NO CARGADO") -> Gastos Varios | R59: =IFERROR(IF(compras_mes1[[#This Row],[CUIT]]="","-",VLOOKUP(compras_mes1[[#This Row],[CUIT]],Lista_CUIT[#All],4,0)),"CUIT NO CARGADO") -> 0
B60: 28/01/2025 | C60: 1 | D60: 5 | E60: 19187 | F60: 30716006391 | G60: =IFERROR(IF(compras_mes1[[#This Row],[CUIT]]="","-",VLOOKUP(compras_mes1[[#This Row],[CUIT]],Lista_CUIT[#All],2,0)),"CUIT NO CARGADO") -> ALISSING | H60: 25562.97 | I60: =IF(compras_mes1[[#This Row],[NETO GRAVADO]]="","",compras_mes1[[#This Row],[NETO GRAVADO]]*0.21) -> 5368.2237 | P60: =SUM(compras_mes1[[#This Row],[NETO GRAVADO]:[Otros / No Grav.]]) -> 30931.194 | Q60: =IFERROR(IF(compras_mes1[[#This Row],[CUIT]]="","-",VLOOKUP(compras_mes1[[#This Row],[CUIT]],Lista_CUIT[#All],3,0)),"CUIT NO CARGADO") -> Gastos Varios | R60: =IFERROR(IF(compras_mes1[[#This Row],[CUIT]]="","-",VLOOKUP(compras_mes1[[#This Row],[CUIT]],Lista_CUIT[#All],4,0)),"CUIT NO CARGADO") -> 0
B61: 28/01/2025 | C61: 3 | D61: 5 | E61: 871 | F61: 30716006391 | G61: =IFERROR(IF(compras_mes1[[#This Row],[CUIT]]="","-",VLOOKUP(compras_mes1[[#This Row],[CUIT]],Lista_CUIT[#All],2,0)),"CUIT NO CARGADO") -> ALISSING | H61: -25562.97 | I61: =IF(compras_mes1[[#This Row],[NETO GRAVADO]]="","",compras_mes1[[#This Row],[NETO GRAVADO]]*0.21) -> -5368.2237 | P61: =SUM(compras_mes1[[#This Row],[NETO GRAVADO]:[Otros / No Grav.]]) -> -30931.194 | Q61: =IFERROR(IF(compras_mes1[[#This Row],[CUIT]]="","-",VLOOKUP(compras_mes1[[#This Row],[CUIT]],Lista_CUIT[#All],3,0)),"CUIT NO CARGADO") -> Gastos Varios | R61: =IFERROR(IF(compras_mes1[[#This Row],[CUIT]]="","-",VLOOKUP(compras_mes1[[#This Row],[CUIT]],Lista_CUIT[#All],4,0)),"CUIT NO CARGADO") -> 0
B62: 28/01/2025 | C62: 3 | D62: 5 | E62: 872 | F62: 30716006391 | G62: =IFERROR(IF(compras_mes1[[#This Row],[CUIT]]="","-",VLOOKUP(compras_mes1[[#This Row],[CUIT]],Lista_CUIT[#All],2,0)),"CUIT NO CARGADO") -> ALISSING | H62: -25562.97 | I62: =IF(compras_mes1[[#This Row],[NETO GRAVADO]]="","",compras_mes1[[#This Row],[NETO GRAVADO]]*0.21) -> -5368.2237 | P62: =SUM(compras_mes1[[#This Row],[NETO GRAVADO]:[Otros / No Grav.]]) -> -30931.194 | Q62: =IFERROR(IF(compras_mes1[[#This Row],[CUIT]]="","-",VLOOKUP(compras_mes1[[#This Row],[CUIT]],Lista_CUIT[#All],3,0)),"CUIT NO CARGADO") -> Gastos Varios | R62: =IFERROR(IF(compras_mes1[[#This Row],[CUIT]]="","-",VLOOKUP(compras_mes1[[#This Row],[CUIT]],Lista_CUIT[#All],4,0)),"CUIT NO CARGADO") -> 0
B63: 29/01/2025 | C63: 1 | D63: 5 | E63: 19260 | F63: 30716006391 | G63: =IFERROR(IF(compras_mes1[[#This Row],[CUIT]]="","-",VLOOKUP(compras_mes1[[#This Row],[CUIT]],Lista_CUIT[#All],2,0)),"CUIT NO CARGADO") -> ALISSING | H63: 6390.74 | I63: =IF(compras_mes1[[#This Row],[NETO GRAVADO]]="","",compras_mes1[[#This Row],[NETO GRAVADO]]*0.21) -> 1342.0554 | P63: =SUM(compras_mes1[[#This Row],[NETO GRAVADO]:[Otros / No Grav.]]) -> 7732.7954 | Q63: =IFERROR(IF(compras_mes1[[#This Row],[CUIT]]="","-",VLOOKUP(compras_mes1[[#This Row],[CUIT]],Lista_CUIT[#All],3,0)),"CUIT NO CARGADO") -> Gastos Varios | R63: =IFERROR(IF(compras_mes1[[#This Row],[CUIT]]="","-",VLOOKUP(compras_mes1[[#This Row],[CUIT]],Lista_CUIT[#All],4,0)),"CUIT NO CARGADO") -> 0
B64: 29/01/2025 | C64: 1 | D64: 5 | E64: 19261 | F64: 30716006391 | G64: =IFERROR(IF(compras_mes1[[#This Row],[CUIT]]="","-",VLOOKUP(compras_mes1[[#This Row],[CUIT]],Lista_CUIT[#All],2,0)),"CUIT NO CARGADO") -> ALISSING | H64: 6390.74 | I64: =IF(compras_mes1[[#This Row],[NETO GRAVADO]]="","",compras_mes1[[#This Row],[NETO GRAVADO]]*0.21) -> 1342.0554 | P64: =SUM(compras_mes1[[#This Row],[NETO GRAVADO]:[Otros / No Grav.]]) -> 7732.7954 | Q64: =IFERROR(IF(compras_mes1[[#This Row],[CUIT]]="","-",VLOOKUP(compras_mes1[[#This Row],[CUIT]],Lista_CUIT[#All],3,0)),"CUIT NO CARGADO") -> Gastos Varios | R64: =IFERROR(IF(compras_mes1[[#This Row],[CUIT]]="","-",VLOOKUP(compras_mes1[[#This Row],[CUIT]],Lista_CUIT[#All],4,0)),"CUIT NO CARGADO") -> 0
B65: 29/01/2025 | C65: 1 | D65: 5 | E65: 4153 | F65: 20409938311 | G65: =IFERROR(IF(compras_mes1[[#This Row],[CUIT]]="","-",VLOOKUP(compras_mes1[[#This Row],[CUIT]],Lista_CUIT[#All],2,0)),"CUIT NO CARGADO") -> ROSEMBERG NAHUEL | H65: 49316.28 | I65: =IF(compras_mes1[[#This Row],[NETO GRAVADO]]="","",compras_mes1[[#This Row],[NETO GRAVADO]]*0.21) -> 10356.419 | P65: =SUM(compras_mes1[[#This Row],[NETO GRAVADO]:[Otros / No Grav.]]) -> 59672.699 | Q65: =IFERROR(IF(compras_mes1[[#This Row],[CUIT]]="","-",VLOOKUP(compras_mes1[[#This Row],[CUIT]],Lista_CUIT[#All],3,0)),"CUIT NO CARGADO") -> Gastos Limpieza | R65: =IFERROR(IF(compras_mes1[[#This Row],[CUIT]]="","-",VLOOKUP(compras_mes1[[#This Row],[CUIT]],Lista_CUIT[#All],4,0)),"CUIT NO CARGADO") -> 0
... B72: 03/01/2025 | C72: 1 | D72: 4 | E72: 48501 | F72: 30709863076 | G72: =IFERROR(IF(compras_mes1[[#This Row],[CUIT]]="","-",VLOOKUP(compras_mes1[[#This Row],[CUIT]],Lista_CUIT[#All],2,0)),"CUIT NO CARGADO") -> INDUSTRIAS PLASTICOS SALTA S.R.L. | H72: 42975.21 | I72: =IF(compras_mes1[[#This Row],[NETO GRAVADO]]="","",compras_mes1[[#This Row],[NETO GRAVADO]]*0.21) -> 9024.7941 | P72: =SUM(compras_mes1[[#This Row],[NETO GRAVADO]:[Otros / No Grav.]]) -> 52000.004 | Q72: =IFERROR(IF(compras_mes1[[#This Row],[CUIT]]="","-",VLOOKUP(compras_mes1[[#This Row],[CUIT]],Lista_CUIT[#All],3,0)),"CUIT NO CARGADO") -> Materia Prima | R72: =IFERROR(IF(compras_mes1[[#This Row],[CUIT]]="","-",VLOOKUP(compras_mes1[[#This Row],[CUIT]],Lista_CUIT[#All],4,0)),"CUIT NO CARGADO") -> 0
B73: 10/01/2025 | C73: 1 | D73: 1 | E73: 23 | F73: 30717504824 | G73: =IFERROR(IF(compras_mes1[[#This Row],[CUIT]]="","-",VLOOKUP(compras_mes1[[#This Row],[CUIT]],Lista_CUIT[#All],2,0)),"CUIT NO CARGADO") -> FIDEICOMISO MAMBA | H73: 2673303.1 | K73: =compras_mes1[[#This Row],[NETO GRAVADO]]*0.105 -> 280696.83 | P73: =SUM(compras_mes1[[#This Row],[NETO GRAVADO]:[Otros / No Grav.]]) -> 2954000 | Q73: =IFERROR(IF(compras_mes1[[#This Row],[CUIT]]="","-",VLOOKUP(compras_mes1[[#This Row],[CUIT]],Lista_CUIT[#All],3,0)),"CUIT NO CARGADO") -> MANTENIMIENTO | R73: =IFERROR(IF(compras_mes1[[#This Row],[CUIT]]="","-",VLOOKUP(compras_mes1[[#This Row],[CUIT]],Lista_CUIT[#All],4,0)),"CUIT NO CARGADO") -> 0
B74: 09/01/2025 | C74: 1 | D74: 14 | E74: 15726 | F74: 30715186256 | G74: =IFERROR(IF(compras_mes1[[#This Row],[CUIT]]="","-",VLOOKUP(compras_mes1[[#This Row],[CUIT]],Lista_CUIT[#All],2,0)),"CUIT NO CARGADO") -> FRIGORIFICO ALIMENTIC | H74: 97074.14 | I74: 4246.04 | K74: 8069.77 | P74: =SUM(compras_mes1[[#This Row],[NETO GRAVADO]:[Otros / No Grav.]]) -> 109389.95 | Q74: =IFERROR(IF(compras_mes1[[#This Row],[CUIT]]="","-",VLOOKUP(compras_mes1[[#This Row],[CUIT]],Lista_CUIT[#All],3,0)),"CUIT NO CARGADO") -> Gastos Comercializacion - Feria | R74: =IFERROR(IF(compras_mes1[[#This Row],[CUIT]]="","-",VLOOKUP(compras_mes1[[#This Row],[CUIT]],Lista_CUIT[#All],4,0)),"CUIT NO CARGADO") -> 0
B75: 20/01/2025 | C75: 1 | D75: 4 | E75: 48617 | F75: 30709863076 | G75: =IFERROR(IF(compras_mes1[[#This Row],[CUIT]]="","-",VLOOKUP(compras_mes1[[#This Row],[CUIT]],Lista_CUIT[#All],2,0)),"CUIT NO CARGADO") -> INDUSTRIAS PLASTICOS SALTA S.R.L. | H75: 2264040 | I75: =IF(compras_mes1[[#This Row],[NETO GRAVADO]]="","",compras_mes1[[#This Row],[NETO GRAVADO]]*0.21) -> 475448.4 | P75: =SUM(compras_mes1[[#This Row],[NETO GRAVADO]:[Otros / No Grav.]]) -> 2739488.4 | Q75: =IFERROR(IF(compras_mes1[[#This Row],[CUIT]]="","-",VLOOKUP(compras_mes1[[#This Row],[CUIT]],Lista_CUIT[#All],3,0)),"CUIT NO CARGADO") -> Materia Prima | R75: =IFERROR(IF(compras_mes1[[#This Row],[CUIT]]="","-",VLOOKUP(compras_mes1[[#This Row],[CUIT]],Lista_CUIT[#All],4,0)),"CUIT NO CARGADO") -> 0
B76: 31/01/2025 | C76: 1 | D76: 11 | E76: 1106898 | F76: 33709585229 | G76: =IFERROR(IF(compras_mes1[[#This Row],[CUIT]]="","-",VLOOKUP(compras_mes1[[#This Row],[CUIT]],Lista_CUIT[#All],2,0)),"CUIT NO CARGADO") -> GOOGLE ARGENTINA S.R.L. | H76: 398731.48 | I76: =IF(compras_mes1[[#This Row],[NETO GRAVADO]]="","",compras_mes1[[#This Row],[NETO GRAVADO]]*0.21) -> 83733.611 | N76: 81670.18 | O76: 11961.94 | P76: =SUM(compras_mes1[[#This Row],[NETO GRAVADO]:[Otros / No Grav.]]) -> 576097.21 | Q76: =IFERROR(IF(compras_mes1[[#This Row],[CUIT]]="","-",VLOOKUP(compras_mes1[[#This Row],[CUIT]],Lista_CUIT[#All],3,0)),"CUIT NO CARGADO") -> Gastos Comercializacion | R76: =IFERROR(IF(compras_mes1[[#This Row],[CUIT]]="","-",VLOOKUP(compras_mes1[[#This Row],[CUIT]],Lista_CUIT[#All],4,0)),"CUIT NO CARGADO") -> 0
B77: 31/01/2025 | C77: 3 | D77: 11 | E77: 794471 | F77: 33709585229 | G77: =IFERROR(IF(compras_mes1[[#This Row],[CUIT]]="","-",VLOOKUP(compras_mes1[[#This Row],[CUIT]],Lista_CUIT[#All],2,0)),"CUIT NO CARGADO") -> GOOGLE ARGENTINA S.R.L. | H77: -278.61 | I77: =IF(compras_mes1[[#This Row],[NETO GRAVADO]]="","",compras_mes1[[#This Row],[NETO GRAVADO]]*0.21) -> -58.5081 | N77: -36.84 | P77: =SUM(compras_mes1[[#This Row],[NETO GRAVADO]:[Otros / No Grav.]]) -> -373.9581 | Q77: =IFERROR(IF(compras_mes1[[#This Row],[CUIT]]="","-",VLOOKUP(compras_mes1[[#This Row],[CUIT]],Lista_CUIT[#All],3,0)),"CUIT NO CARGADO") -> Gastos Comercializacion | R77: =IFERROR(IF(compras_mes1[[#This Row],[CUIT]]="","-",VLOOKUP(compras_mes1[[#This Row],[CUIT]],Lista_CUIT[#All],4,0)),"CUIT NO CARGADO") -> 0
B78: 01/01/2025 | C78: 1 | D78: 629 | E78: 5743055 | F78: 30663498513 | G78: =IFERROR(IF(compras_mes1[[#This Row],[CUIT]]="","-",VLOOKUP(compras_mes1[[#This Row],[CUIT]],Lista_CUIT[#All],2,0)),"CUIT NO CARGADO") -> GRUPO CONCES. DEL OESTE SA | H78: 31661.77 | I78: =IF(compras_mes1[[#This Row],[NETO GRAVADO]]="","",compras_mes1[[#This Row],[NETO GRAVADO]]*0.21) -> 6648.9717 | P78: =SUM(compras_mes1[[#This Row],[NETO GRAVADO]:[Otros / No Grav.]]) -> 38310.742 | Q78: =IFERROR(IF(compras_mes1[[#This Row],[CUIT]]="","-",VLOOKUP(compras_mes1[[#This Row],[CUIT]],Lista_CUIT[#All],3,0)),"CUIT NO CARGADO") -> Peajes | R78: =IFERROR(IF(compras_mes1[[#This Row],[CUIT]]="","-",VLOOKUP(compras_mes1[[#This Row],[CUIT]],Lista_CUIT[#All],4,0)),"CUIT NO CARGADO") -> 0
B79: 16/01/2025 | C79: 1 | D79: 629 | E79: 5784055 | F79: 30663498513 | G79: =IFERROR(IF(compras_mes1[[#This Row],[CUIT]]="","-",VLOOKUP(compras_mes1[[#This Row],[CUIT]],Lista_CUIT[#All],2,0)),"CUIT NO CARGADO") -> GRUPO CONCES. DEL OESTE SA | H79: 33741.76 | I79: =IF(compras_mes1[[#This Row],[NETO GRAVADO]]="","",compras_mes1[[#This Row],[NETO GRAVADO]]*0.21) -> 7085.7696 | P79: =SUM(compras_mes1[[#This Row],[NETO GRAVADO]:[Otros / No Grav.]]) -> 40827.53 | Q79: =IFERROR(IF(compras_mes1[[#This Row],[CUIT]]="","-",VLOOKUP(compras_mes1[[#This Row],[CUIT]],Lista_CUIT[#All],3,0)),"CUIT NO CARGADO") -> Peajes | R79: =IFERROR(IF(compras_mes1[[#This Row],[CUIT]]="","-",VLOOKUP(compras_mes1[[#This Row],[CUIT]],Lista_CUIT[#All],4,0)),"CUIT NO CARGADO") -> 0
B80: 02/01/2025 | C80: 1 | D80: 1 | E80: 149 | F80: 30716010313 | G80: =IFERROR(IF(compras_mes1[[#This Row],[CUIT]]="","-",VLOOKUP(compras_mes1[[#This Row],[CUIT]],Lista_CUIT[#All],2,0)),"CUIT NO CARGADO") -> H UNO 1469 S.A. | H80: 500000 | I80: =IF(compras_mes1[[#This Row],[NETO GRAVADO]]="","",compras_mes1[[#This Row],[NETO GRAVADO]]*0.21) -> 105000 | P80: =SUM(compras_mes1[[#This Row],[NETO GRAVADO]:[Otros / No Grav.]]) -> 605000 | Q80: =IFERROR(IF(compras_mes1[[#This Row],[CUIT]]="","-",VLOOKUP(compras_mes1[[#This Row],[CUIT]],Lista_CUIT[#All],3,0)),"CUIT NO CARGADO") -> Alquiler | R80: =IFERROR(IF(compras_mes1[[#This Row],[CUIT]]="","-",VLOOKUP(compras_mes1[[#This Row],[CUIT]],Lista_CUIT[#All],4,0)),"CUIT NO CARGADO") -> 0
B81: 11/01/2025 | C81: 1 | D81: 1005 | E81: 89159 | F81: 20338116978 | G81: =IFERROR(IF(compras_mes1[[#This Row],[CUIT]]="","-",VLOOKUP(compras_mes1[[#This Row],[CUIT]],Lista_CUIT[#All],2,0)),"CUIT NO CARGADO") -> HERBAS ESPINOZA GABRIEL MATIAS | H81: 2892.56 | I81: =IF(compras_mes1[[#This Row],[NETO GRAVADO]]="","",compras_mes1[[#This Row],[NETO GRAVADO]]*0.21) -> 607.4376 | P81: =SUM(compras_mes1[[#This Row],[NETO GRAVADO]:[Otros / No Grav.]]) -> 3499.9976 | Q81: =IFERROR(IF(compras_mes1[[#This Row],[CUIT]]="","-",VLOOKUP(compras_mes1[[#This Row],[CUIT]],Lista_CUIT[#All],3,0)),"CUIT NO CARGADO") -> Gastos Varios | R81: =IFERROR(IF(compras_mes1[[#This Row],[CUIT]]="","-",VLOOKUP(compras_mes1[[#This Row],[CUIT]],Lista_CUIT[#All],4,0)),"CUIT NO CARGADO") -> 0
B82: 16/01/2025 | C82: 1 | D82: 4 | E82: 217 | F82: 27317740196 | G82: =IFERROR(IF(compras_mes1[[#This Row],[CUIT]]="","-",VLOOKUP(compras_mes1[[#This Row],[CUIT]],Lista_CUIT[#All],2,0)),"CUIT NO CARGADO") -> HOKAMA ROMINA PAOLA | H82: 29131.42 | I82: =IF(compras_mes1[[#This Row],[NETO GRAVADO]]="","",compras_mes1[[#This Row],[NETO GRAVADO]]*0.21) -> 6117.5982 | P82: =SUM(compras_mes1[[#This Row],[NETO GRAVADO]:[Otros / No Grav.]]) -> 35249.018 | Q82: =IFERROR(IF(compras_mes1[[#This Row],[CUIT]]="","-",VLOOKUP(compras_mes1[[#This Row],[CUIT]],Lista_CUIT[#All],3,0)),"CUIT NO CARGADO") -> Gastos Varios | R82: =IFERROR(IF(compras_mes1[[#This Row],[CUIT]]="","-",VLOOKUP(compras_mes1[[#This Row],[CUIT]],Lista_CUIT[#All],4,0)),"CUIT NO CARGADO") -> 0
B83: 21/01/2025 | C83: 1 | D83: 4 | E83: 227 | F83: 27317740196 | G83: =IFERROR(IF(compras_mes1[[#This Row],[CUIT]]="","-",VLOOKUP(compras_mes1[[#This Row],[CUIT]],Lista_CUIT[#All],2,0)),"CUIT NO CARGADO") -> HOKAMA ROMINA PAOLA | H83: 40798.33 | I83: =IF(compras_mes1[[#This Row],[NETO GRAVADO]]="","",compras_mes1[[#This Row],[NETO GRAVADO]]*0.21) -> 8567.6493 | P83: =SUM(compras_mes1[[#This Row],[NETO GRAVADO]:[Otros / No Grav.]]) -> 49365.979 | Q83: =IFERROR(IF(compras_mes1[[#This Row],[CUIT]]="","-",VLOOKUP(compras_mes1[[#This Row],[CUIT]],Lista_CUIT[#All],3,0)),"CUIT NO CARGADO") -> Gastos Varios | R83: =IFERROR(IF(compras_mes1[[#This Row],[CUIT]]="","-",VLOOKUP(compras_mes1[[#This Row],[CUIT]],Lista_CUIT[#All],4,0)),"CUIT NO CARGADO") -> 0
B84: 06/01/2025 | C84: 1 | D84: 9 | E84: 10742 | F84: 30709953482 | G84: =IFERROR(IF(compras_mes1[[#This Row],[CUIT]]="","-",VLOOKUP(compras_mes1[[#This Row],[CUIT]],Lista_CUIT[#All],2,0)),"CUIT NO CARGADO") -> HONRE S.A | H84: 29234.02 | I84: =IF(compras_mes1[[#This Row],[NETO GRAVADO]]="","",compras_mes1[[#This Row],[NETO GRAVADO]]*0.21) -> 6139.1442 | P84: =SUM(compras_mes1[[#This Row],[NETO GRAVADO]:[Otros / No Grav.]]) -> 35373.164 | Q84: =IFERROR(IF(compras_mes1[[#This Row],[CUIT]]="","-",VLOOKUP(compras_mes1[[#This Row],[CUIT]],Lista_CUIT[#All],3,0)),"CUIT NO CARGADO") -> Gastos Limpieza | R84: =IFERROR(IF(compras_mes1[[#This Row],[CUIT]]="","-",VLOOKUP(compras_mes1[[#This Row],[CUIT]],Lista_CUIT[#All],4,0)),"CUIT NO CARGADO") -> 0
B85: 06/01/2025 | C85: 1 | D85: 9 | E85: 10743 | F85: 30709953482 | G85: =IFERROR(IF(compras_mes1[[#This Row],[CUIT]]="","-",VLOOKUP(compras_mes1[[#This Row],[CUIT]],Lista_CUIT[#All],2,0)),"CUIT NO CARGADO") -> HONRE S.A | H85: 29234.02 | I85: =IF(compras_mes1[[#This Row],[NETO GRAVADO]]="","",compras_mes1[[#This Row],[NETO GRAVADO]]*0.21) -> 6139.1442 | P85: =SUM(compras_mes1[[#This Row],[NETO GRAVADO]:[Otros / No Grav.]]) -> 35373.164 | Q85: =IFERROR(IF(compras_mes1[[#This Row],[CUIT]]="","-",VLOOKUP(compras_mes1[[#This Row],[CUIT]],Lista_CUIT[#All],3,0)),"CUIT NO CARGADO") -> Gastos Limpieza | R85: =IFERROR(IF(compras_mes1[[#This Row],[CUIT]]="","-",VLOOKUP(compras_mes1[[#This Row],[CUIT]],Lista_CUIT[#All],4,0)),"CUIT NO CARGADO") -> 0
B86: 06/01/2025 | C86: 1 | D86: 9 | E86: 10744 | F86: 30709953482 | G86: =IFERROR(IF(compras_mes1[[#This Row],[CUIT]]="","-",VLOOKUP(compras_mes1[[#This Row],[CUIT]],Lista_CUIT[#All],2,0)),"CUIT NO CARGADO") -> HONRE S.A | H86: 29234.02 | I86: =IF(compras_mes1[[#This Row],[NETO GRAVADO]]="","",compras_mes1[[#This Row],[NETO GRAVADO]]*0.21) -> 6139.1442 | P86: =SUM(compras_mes1[[#This Row],[NETO GRAVADO]:[Otros / No Grav.]]) -> 35373.164 | Q86: =IFERROR(IF(compras_mes1[[#This Row],[CUIT]]="","-",VLOOKUP(compras_mes1[[#This Row],[CUIT]],Lista_CUIT[#All],3,0)),"CUIT NO CARGADO") -> Gastos Limpieza | R86: =IFERROR(IF(compras_mes1[[#This Row],[CUIT]]="","-",VLOOKUP(compras_mes1[[#This Row],[CUIT]],Lista_CUIT[#All],4,0)),"CUIT NO CARGADO") -> 0
B87: 45663 | C87: 1 | D87: 21 | E87: 54464 | F87: 30515800219 | G87: =IFERROR(IF(compras_mes1[[#This Row],[CUIT]]="","-",VLOOKUP(compras_mes1[[#This Row],[CUIT]],Lista_CUIT[#All],2,0)),"CUIT NO CARGADO") -> INCAT SRL | H87: 30599.19 | I87: =IF(compras_mes1[[#This Row],[NETO GRAVADO]]="","",compras_mes1[[#This Row],[NETO GRAVADO]]*0.21) -> 6425.8299 | O87: 15958.08 | P87: =SUM(compras_mes1[[#This Row],[NETO GRAVADO]:[Otros / No Grav.]]) -> 52983.1 | Q87: =IFERROR(IF(compras_mes1[[#This Row],[CUIT]]="","-",VLOOKUP(compras_mes1[[#This Row],[CUIT]],Lista_CUIT[#All],3,0)),"CUIT NO CARGADO") -> Combustible | R87: =IFERROR(IF(compras_mes1[[#This Row],[CUIT]]="","-",VLOOKUP(compras_mes1[[#This Row],[CUIT]],Lista_CUIT[#All],4,0)),"CUIT NO CARGADO") -> CABA
B88: 20/01/2025 | C88: 1 | D88: 4 | E88: 48621 | F88: 30709863076 | G88: =IFERROR(IF(compras_mes1[[#This Row],[CUIT]]="","-",VLOOKUP(compras_mes1[[#This Row],[CUIT]],Lista_CUIT[#All],2,0)),"CUIT NO CARGADO") -> INDUSTRIAS PLASTICOS SALTA S.R.L. | H88: 85950.41 | I88: =IF(compras_mes1[[#This Row],[NETO GRAVADO]]="","",compras_mes1[[#This Row],[NETO GRAVADO]]*0.21) -> 18049.586 | P88: =SUM(compras_mes1[[#This Row],[NETO GRAVADO]:[Otros / No Grav.]]) -> 104000 | Q88: =IFERROR(IF(compras_mes1[[#This Row],[CUIT]]="","-",VLOOKUP(compras_mes1[[#This Row],[CUIT]],Lista_CUIT[#All],3,0)),"CUIT NO CARGADO") -> Materia Prima | R88: =IFERROR(IF(compras_mes1[[#This Row],[CUIT]]="","-",VLOOKUP(compras_mes1[[#This Row],[CUIT]],Lista_CUIT[#All],4,0)),"CUIT NO CARGADO") -> 0
B89: 03/01/2025 | C89: 1 | D89: 4 | E89: 110 | F89: 20308004865 | G89: =IFERROR(IF(compras_mes1[[#This Row],[CUIT]]="","-",VLOOKUP(compras_mes1[[#This Row],[CUIT]],Lista_CUIT[#All],2,0)),"CUIT NO CARGADO") -> VEGA GUSTAVO RAUL | H89: 1487600 | I89: =IF(compras_mes1[[#This Row],[NETO GRAVADO]]="","",compras_mes1[[#This Row],[NETO GRAVADO]]*0.21) -> 312396 | P89: =SUM(compras_mes1[[#This Row],[NETO GRAVADO]:[Otros / No Grav.]]) -> 1799996 | Q89: =IFERROR(IF(compras_mes1[[#This Row],[CUIT]]="","-",VLOOKUP(compras_mes1[[#This Row],[CUIT]],Lista_CUIT[#All],3,0)),"CUIT NO CARGADO") -> Materia Prima | R89: =IFERROR(IF(compras_mes1[[#This Row],[CUIT]]="","-",VLOOKUP(compras_mes1[[#This Row],[CUIT]],Lista_CUIT[#All],4,0)),"CUIT NO CARGADO") -> 0
B90: 09/01/2025 | C90: 1 | D90: 4 | E90: 45645 | F90: 30585948817 | G90: =IFERROR(IF(compras_mes1[[#This Row],[CUIT]]="","-",VLOOKUP(compras_mes1[[#This Row],[CUIT]],Lista_CUIT[#All],2,0)),"CUIT NO CARGADO") -> GLASCAR | H90: 830000 | I90: =IF(compras_mes1[[#This Row],[NETO GRAVADO]]="","",compras_mes1[[#This Row],[NETO GRAVADO]]*0.21) -> 174300 | M90: 49800 | P90: =SUM(compras_mes1[[#This Row],[NETO GRAVADO]:[Otros / No Grav.]]) -> 1054100 | Q90: =IFERROR(IF(compras_mes1[[#This Row],[CUIT]]="","-",VLOOKUP(compras_mes1[[#This Row],[CUIT]],Lista_CUIT[#All],3,0)),"CUIT NO CARGADO") -> Material de Empaque | R90: =IFERROR(IF(compras_mes1[[#This Row],[CUIT]]="","-",VLOOKUP(compras_mes1[[#This Row],[CUIT]],Lista_CUIT[#All],4,0)),"CUIT NO CARGADO") -> 0
B91: 07/01/2025 | C91: 1 | D91: 1674 | E91: 13880 | F91: 30589621499 | G91: =IFERROR(IF(compras_mes1[[#This Row],[CUIT]]="","-",VLOOKUP(compras_mes1[[#This Row],[CUIT]],Lista_CUIT[#All],2,0)),"CUIT NO CARGADO") -> MAKRO SA | H91: 107636.7 | I91: =IF(compras_mes1[[#This Row],[NETO GRAVADO]]="","",compras_mes1[[#This Row],[NETO GRAVADO]]*0.21) -> 22603.707 | L91: 3229.1 | N91: 6458.2 | P91: =SUM(compras_mes1[[#This Row],[NETO GRAVADO]:[Otros / No Grav.]]) -> 139927.71 | Q91: =IFERROR(IF(compras_mes1[[#This Row],[CUIT]]="","-",VLOOKUP(compras_mes1[[#This Row],[CUIT]],Lista_CUIT[#All],3,0)),"CUIT NO CARGADO") -> Gastos Varios | R91: =IFERROR(IF(compras_mes1[[#This Row],[CUIT]]="","-",VLOOKUP(compras_mes1[[#This Row],[CUIT]],Lista_CUIT[#All],4,0)),"CUIT NO CARGADO") -> 0
B92: 30/01/2025 | C92: 1 | D92: 2 | E92: 6382 | F92: 30717403866 | G92: =IFERROR(IF(compras_mes1[[#This Row],[CUIT]]="","-",VLOOKUP(compras_mes1[[#This Row],[CUIT]],Lista_CUIT[#All],2,0)),"CUIT NO CARGADO") -> MCBA S.R.L. | H92: 15709.09 | I92: =IF(compras_mes1[[#This Row],[NETO GRAVADO]]="","",compras_mes1[[#This Row],[NETO GRAVADO]]*0.21) -> 3298.9089 | P92: =SUM(compras_mes1[[#This Row],[NETO GRAVADO]:[Otros / No Grav.]]) -> 19007.999 | Q92: =IFERROR(IF(compras_mes1[[#This Row],[CUIT]]="","-",VLOOKUP(compras_mes1[[#This Row],[CUIT]],Lista_CUIT[#All],3,0)),"CUIT NO CARGADO") -> Gastos Limpieza | R92: =IFERROR(IF(compras_mes1[[#This Row],[CUIT]]="","-",VLOOKUP(compras_mes1[[#This Row],[CUIT]],Lista_CUIT[#All],4,0)),"CUIT NO CARGADO") -> 0
B93: 29/01/2025 | C93: 1 | D93: 27 | E93: 3033116 | F93: 30703088534 | G93: =IFERROR(IF(compras_mes1[[#This Row],[CUIT]]="","-",VLOOKUP(compras_mes1[[#This Row],[CUIT]],Lista_CUIT[#All],2,0)),"CUIT NO CARGADO") -> MERCADO LIBRE SRL | H93: 2435766 | I93: =IF(compras_mes1[[#This Row],[NETO GRAVADO]]="","",compras_mes1[[#This Row],[NETO GRAVADO]]*0.21) -> 511510.87 | L93: 73072.97 | N93: 146145.95 | O93: 24357.66 | P93: =SUM(compras_mes1[[#This Row],[NETO GRAVADO]:[Otros / No Grav.]]) -> 3190853.5 | Q93: =IFERROR(IF(compras_mes1[[#This Row],[CUIT]]="","-",VLOOKUP(compras_mes1[[#This Row],[CUIT]],Lista_CUIT[#All],3,0)),"CUIT NO CARGADO") -> Gastos Varios | R93: =IFERROR(IF(compras_mes1[[#This Row],[CUIT]]="","-",VLOOKUP(compras_mes1[[#This Row],[CUIT]],Lista_CUIT[#All],4,0)),"CUIT NO CARGADO") -> CABA
B94: 45672 | C94: 1 | D94: 64 | E94: 26942640 | F94: 30657863676 | G94: =IFERROR(IF(compras_mes1[[#This Row],[CUIT]]="","-",VLOOKUP(compras_mes1[[#This Row],[CUIT]],Lista_CUIT[#All],2,0)),"CUIT NO CARGADO") -> METROGAS S A | H94: 13359.359 | I94: =IF(compras_mes1[[#This Row],[NETO GRAVADO]]="","",compras_mes1[[#This Row],[NETO GRAVADO]]*0.21) -> 2805.4655 | O94: 22.68 | P94: =SUM(compras_mes1[[#This Row],[NETO GRAVADO]:[Otros / No Grav.]]) -> 16187.505 | Q94: =IFERROR(IF(compras_mes1[[#This Row],[CUIT]]="","-",VLOOKUP(compras_mes1[[#This Row],[CUIT]],Lista_CUIT[#All],3,0)),"CUIT NO CARGADO") -> Servicios Gas, Luz, etc. | R94: =IFERROR(IF(compras_mes1[[#This Row],[CUIT]]="","-",VLOOKUP(compras_mes1[[#This Row],[CUIT]],Lista_CUIT[#All],4,0)),"CUIT NO CARGADO") -> 0
B95: 30/01/2025 | C95: 1 | D95: 4 | E95: 10750 | F95: 30694547903 | G95: =IFERROR(IF(compras_mes1[[#This Row],[CUIT]]="","-",VLOOKUP(compras_mes1[[#This Row],[CUIT]],Lista_CUIT[#All],2,0)),"CUIT NO CARGADO") -> MULTICAJAS S A | H95: 250344 | I95: =IF(compras_mes1[[#This Row],[NETO GRAVADO]]="","",compras_mes1[[#This Row],[NETO GRAVADO]]*0.21) -> 52572.24 | P95: =SUM(compras_mes1[[#This Row],[NETO GRAVADO]:[Otros / No Grav.]]) -> 302916.24 | Q95: =IFERROR(IF(compras_mes1[[#This Row],[CUIT]]="","-",VLOOKUP(compras_mes1[[#This Row],[CUIT]],Lista_CUIT[#All],3,0)),"CUIT NO CARGADO") -> LIBRERÍA | R95: =IFERROR(IF(compras_mes1[[#This Row],[CUIT]]="","-",VLOOKUP(compras_mes1[[#This Row],[CUIT]],Lista_CUIT[#All],4,0)),"CUIT NO CARGADO") -> 0
B96: 14/01/2025 | C96: 1 | D96: 7 | E96: 13674 | F96: 30708017759 | G96: =IFERROR(IF(compras_mes1[[#This Row],[CUIT]]="","-",VLOOKUP(compras_mes1[[#This Row],[CUIT]],Lista_CUIT[#All],2,0)),"CUIT NO CARGADO") -> NEW HIGH PACK SA | H96: 2164393.7 | I96: =IF(compras_mes1[[#This Row],[NETO GRAVADO]]="","",compras_mes1[[#This Row],[NETO GRAVADO]]*0.21) -> 454522.68 | N96: 129863.62 | P96: =SUM(compras_mes1[[#This Row],[NETO GRAVADO]:[Otros / No Grav.]]) -> 2748780 | Q96: =IFERROR(IF(compras_mes1[[#This Row],[CUIT]]="","-",VLOOKUP(compras_mes1[[#This Row],[CUIT]],Lista_CUIT[#All],3,0)),"CUIT NO CARGADO") -> Material de Empaque | R96: =IFERROR(IF(compras_mes1[[#This Row],[CUIT]]="","-",VLOOKUP(compras_mes1[[#This Row],[CUIT]],Lista_CUIT[#All],4,0)),"CUIT NO CARGADO") -> 0
B97: 24/01/2025 | C97: 1 | D97: 7 | E97: 13772 | F97: 30708017759 | G97: =IFERROR(IF(compras_mes1[[#This Row],[CUIT]]="","-",VLOOKUP(compras_mes1[[#This Row],[CUIT]],Lista_CUIT[#All],2,0)),"CUIT NO CARGADO") -> NEW HIGH PACK SA | H97: 1321779.2 | I97: =IF(compras_mes1[[#This Row],[NETO GRAVADO]]="","",compras_mes1[[#This Row],[NETO GRAVADO]]*0.21) -> 277573.63 | N97: 79306.75 | P97: =SUM(compras_mes1[[#This Row],[NETO GRAVADO]:[Otros / No Grav.]]) -> 1678659.6 | Q97: =IFERROR(IF(compras_mes1[[#This Row],[CUIT]]="","-",VLOOKUP(compras_mes1[[#This Row],[CUIT]],Lista_CUIT[#All],3,0)),"CUIT NO CARGADO") -> Material de Empaque | R97: =IFERROR(IF(compras_mes1[[#This Row],[CUIT]]="","-",VLOOKUP(compras_mes1[[#This Row],[CUIT]],Lista_CUIT[#All],4,0)),"CUIT NO CARGADO") -> 0
B98: 03/01/2025 | C98: 3 | D98: 10 | E98: 620 | F98: 30710796838 | G98: =IFERROR(IF(compras_mes1[[#This Row],[CUIT]]="","-",VLOOKUP(compras_mes1[[#This Row],[CUIT]],Lista_CUIT[#All],2,0)),"CUIT NO CARGADO") -> NO BAJAR LOS BRAZOS S.R.L. | H98: -84628.1 | I98: =IF(compras_mes1[[#This Row],[NETO GRAVADO]]="","",compras_mes1[[#This Row],[NETO GRAVADO]]*0.21) -> -17771.901 | P98: =SUM(compras_mes1[[#This Row],[NETO GRAVADO]:[Otros / No Grav.]]) -> -102400 | Q98: =IFERROR(IF(compras_mes1[[#This Row],[CUIT]]="","-",VLOOKUP(compras_mes1[[#This Row],[CUIT]],Lista_CUIT[#All],3,0)),"CUIT NO CARGADO") -> Gastos Limpieza | R98: =IFERROR(IF(compras_mes1[[#This Row],[CUIT]]="","-",VLOOKUP(compras_mes1[[#This Row],[CUIT]],Lista_CUIT[#All],4,0)),"CUIT NO CARGADO") -> 0
B99: 22/01/2025 | C99: 1 | D99: 5 | E99: 3212921 | F99: 30702652975 | G99: =IFERROR(IF(compras_mes1[[#This Row],[CUIT]]="","-",VLOOKUP(compras_mes1[[#This Row],[CUIT]],Lista_CUIT[#All],2,0)),"CUIT NO CARGADO") -> NSS SA | H99: 29946.48 | I99: =IF(compras_mes1[[#This Row],[NETO GRAVADO]]="","",compras_mes1[[#This Row],[NETO GRAVADO]]*0.21) -> 6288.7608 | N99: 1796.79 | P99: =SUM(compras_mes1[[#This Row],[NETO GRAVADO]:[Otros / No Grav.]]) -> 38032.031 | Q99: =IFERROR(IF(compras_mes1[[#This Row],[CUIT]]="","-",VLOOKUP(compras_mes1[[#This Row],[CUIT]],Lista_CUIT[#All],3,0)),"CUIT NO CARGADO") -> Servicios Gas, Luz, etc. | R99: =IFERROR(IF(compras_mes1[[#This Row],[CUIT]]="","-",VLOOKUP(compras_mes1[[#This Row],[CUIT]],Lista_CUIT[#All],4,0)),"CUIT NO CARGADO") -> 0
B100: 07/01/2025 | C100: 1 | D100: 6852 | E100: 28627 | F100: 30678774495 | G100: =IFERROR(IF(compras_mes1[[#This Row],[CUIT]]="","-",VLOOKUP(compras_mes1[[#This Row],[CUIT]],Lista_CUIT[#All],2,0)),"CUIT NO CARGADO") -> OPER. DE EST. DE SERV. SA | H100: 8204.78 | I100: =IF(compras_mes1[[#This Row],[NETO GRAVADO]]="","",compras_mes1[[#This Row],[NETO GRAVADO]]*0.21) -> 1723.0038 | O100: 2072.19 | P100: =SUM(compras_mes1[[#This Row],[NETO GRAVADO]:[Otros / No Grav.]]) -> 11999.974 | Q100: =IFERROR(IF(compras_mes1[[#This Row],[CUIT]]="","-",VLOOKUP(compras_mes1[[#This Row],[CUIT]],Lista_CUIT[#All],3,0)),"CUIT NO CARGADO") -> Combustible | R100: =IFERROR(IF(compras_mes1[[#This Row],[CUIT]]="","-",VLOOKUP(compras_mes1[[#This Row],[CUIT]],Lista_CUIT[#All],4,0)),"CUIT NO CARGADO") -> 0
B101: 14/01/2025 | C101: 1 | D101: 8012 | E101: 35402 | F101: 30678774495 | G101: =IFERROR(IF(compras_mes1[[#This Row],[CUIT]]="","-",VLOOKUP(compras_mes1[[#This Row],[CUIT]],Lista_CUIT[#All],2,0)),"CUIT NO CARGADO") -> OPER. DE EST. DE SERV. SA | H101: 45177.01 | I101: =IF(compras_mes1[[#This Row],[NETO GRAVADO]]="","",compras_mes1[[#This Row],[NETO GRAVADO]]*0.21) -> 9487.1721 | O101: 11505.85 | P101: =SUM(compras_mes1[[#This Row],[NETO GRAVADO]:[Otros / No Grav.]]) -> 66170.032 | Q101: =IFERROR(IF(compras_mes1[[#This Row],[CUIT]]="","-",VLOOKUP(compras_mes1[[#This Row],[CUIT]],Lista_CUIT[#All],3,0)),"CUIT NO CARGADO") -> Combustible | R101: =IFERROR(IF(compras_mes1[[#This Row],[CUIT]]="","-",VLOOKUP(compras_mes1[[#This Row],[CUIT]],Lista_CUIT[#All],4,0)),"CUIT NO CARGADO") -> 0
B102: 31/01/2025 | C102: 1 | D102: 7978 | E102: 22570 | F102: 30678774495 | G102: =IFERROR(IF(compras_mes1[[#This Row],[CUIT]]="","-",VLOOKUP(compras_mes1[[#This Row],[CUIT]],Lista_CUIT[#All],2,0)),"CUIT NO CARGADO") -> OPER. DE EST. DE SERV. SA | H102: 4392.73 | I102: =IF(compras_mes1[[#This Row],[NETO GRAVADO]]="","",compras_mes1[[#This Row],[NETO GRAVADO]]*0.21) -> 922.4733 | P102: =SUM(compras_mes1[[#This Row],[NETO GRAVADO]:[Otros / No Grav.]]) -> 5315.2033 | Q102: =IFERROR(IF(compras_mes1[[#This Row],[CUIT]]="","-",VLOOKUP(compras_mes1[[#This Row],[CUIT]],Lista_CUIT[#All],3,0)),"CUIT NO CARGADO") -> Combustible | R102: =IFERROR(IF(compras_mes1[[#This Row],[CUIT]]="","-",VLOOKUP(compras_mes1[[#This Row],[CUIT]],Lista_CUIT[#All],4,0)),"CUIT NO CARGADO") -> 0
B103: 45661 | C103: 1 | D103: 12 | E103: 56058 | F103: 30696131003 | G103: =IFERROR(IF(compras_mes1[[#This Row],[CUIT]]="","-",VLOOKUP(compras_mes1[[#This Row],[CUIT]],Lista_CUIT[#All],2,0)),"CUIT NO CARGADO") -> Petrolfe S.A. | H103: 126358.14 | I103: =IF(compras_mes1[[#This Row],[NETO GRAVADO]]="","",compras_mes1[[#This Row],[NETO GRAVADO]]*0.21) -> 26535.209 | O103: 45292.02 | P103: =SUM(compras_mes1[[#This Row],[NETO GRAVADO]:[Otros / No Grav.]]) -> 198185.37 | Q103: =IFERROR(IF(compras_mes1[[#This Row],[CUIT]]="","-",VLOOKUP(compras_mes1[[#This Row],[CUIT]],Lista_CUIT[#All],3,0)),"CUIT NO CARGADO") -> Combustible | R103: =IFERROR(IF(compras_mes1[[#This Row],[CUIT]]="","-",VLOOKUP(compras_mes1[[#This Row],[CUIT]],Lista_CUIT[#All],4,0)),"CUIT NO CARGADO") -> 0
B104: 45668 | C104: 1 | D104: 12 | E104: 56442 | F104: 30696131003 | G104: =IFERROR(IF(compras_mes1[[#This Row],[CUIT]]="","-",VLOOKUP(compras_mes1[[#This Row],[CUIT]],Lista_CUIT[#All],2,0)),"CUIT NO CARGADO") -> Petrolfe S.A. | H104: 140113.81 | I104: =IF(compras_mes1[[#This Row],[NETO GRAVADO]]="","",compras_mes1[[#This Row],[NETO GRAVADO]]*0.21) -> 29423.9 | O104: 50222.62 | P104: =SUM(compras_mes1[[#This Row],[NETO GRAVADO]:[Otros / No Grav.]]) -> 219760.33 | Q104: =IFERROR(IF(compras_mes1[[#This Row],[CUIT]]="","-",VLOOKUP(compras_mes1[[#This Row],[CUIT]],Lista_CUIT[#All],3,0)),"CUIT NO CARGADO") -> Combustible | R104: =IFERROR(IF(compras_mes1[[#This Row],[CUIT]]="","-",VLOOKUP(compras_mes1[[#This Row],[CUIT]],Lista_CUIT[#All],4,0)),"CUIT NO CARGADO") -> 0
B105: 45675 | C105: 1 | D105: 12 | E105: 56868 | F105: 30696131003 | G105: =IFERROR(IF(compras_mes1[[#This Row],[CUIT]]="","-",VLOOKUP(compras_mes1[[#This Row],[CUIT]],Lista_CUIT[#All],2,0)),"CUIT NO CARGADO") -> Petrolfe S.A. | H105: 158374.67 | I105: =IF(compras_mes1[[#This Row],[NETO GRAVADO]]="","",compras_mes1[[#This Row],[NETO GRAVADO]]*0.21) -> 33258.681 | O105: 24965.56 | P105: =SUM(compras_mes1[[#This Row],[NETO GRAVADO]:[Otros / No Grav.]]) -> 216598.91 | Q105: =IFERROR(IF(compras_mes1[[#This Row],[CUIT]]="","-",VLOOKUP(compras_mes1[[#This Row],[CUIT]],Lista_CUIT[#All],3,0)),"CUIT NO CARGADO") -> Combustible | R105: =IFERROR(IF(compras_mes1[[#This Row],[CUIT]]="","-",VLOOKUP(compras_mes1[[#This Row],[CUIT]],Lista_CUIT[#All],4,0)),"CUIT NO CARGADO") -> 0
B106: 45682 | C106: 1 | D106: 12 | E106: 57290 | F106: 30696131003 | G106: =IFERROR(IF(compras_mes1[[#This Row],[CUIT]]="","-",VLOOKUP(compras_mes1[[#This Row],[CUIT]],Lista_CUIT[#All],2,0)),"CUIT NO CARGADO") -> Petrolfe S.A. | H106: 106923.25 | I106: =IF(compras_mes1[[#This Row],[NETO GRAVADO]]="","",compras_mes1[[#This Row],[NETO GRAVADO]]*0.21) -> 22453.882 | O106: 19162.87 | P106: =SUM(compras_mes1[[#This Row],[NETO GRAVADO]:[Otros / No Grav.]]) -> 148540 | Q106: =IFERROR(IF(compras_mes1[[#This Row],[CUIT]]="","-",VLOOKUP(compras_mes1[[#This Row],[CUIT]],Lista_CUIT[#All],3,0)),"CUIT NO CARGADO") -> Combustible | R106: =IFERROR(IF(compras_mes1[[#This Row],[CUIT]]="","-",VLOOKUP(compras_mes1[[#This Row],[CUIT]],Lista_CUIT[#All],4,0)),"CUIT NO CARGADO") -> 0
B107: 09/01/2025 | C107: 1 | D107: 336 | E107: 47110 | F107: 30646512952 | G107: =IFERROR(IF(compras_mes1[[#This Row],[CUIT]]="","-",VLOOKUP(compras_mes1[[#This Row],[CUIT]],Lista_CUIT[#All],2,0)),"CUIT NO CARGADO") -> PINTURERIA REX | H107: 487496.2 | I107: =IF(compras_mes1[[#This Row],[NETO GRAVADO]]="","",compras_mes1[[#This Row],[NETO GRAVADO]]*0.21) -> 102374.2 | M107: 29249.77 | P107: =SUM(compras_mes1[[#This Row],[NETO GRAVADO]:[Otros / No Grav.]]) -> 619120.17 | Q107: =IFERROR(IF(compras_mes1[[#This Row],[CUIT]]="","-",VLOOKUP(compras_mes1[[#This Row],[CUIT]],Lista_CUIT[#All],3,0)),"CUIT NO CARGADO") -> Mantenimiento Locales | R107: =IFERROR(IF(compras_mes1[[#This Row],[CUIT]]="","-",VLOOKUP(compras_mes1[[#This Row],[CUIT]],Lista_CUIT[#All],4,0)),"CUIT NO CARGADO") -> 0
B108: 14/01/2025 | C108: 1 | D108: 6 | E108: 3422 | F108: 30574603788 | G108: =IFERROR(IF(compras_mes1[[#This Row],[CUIT]]="","-",VLOOKUP(compras_mes1[[#This Row],[CUIT]],Lista_CUIT[#All],2,0)),"CUIT NO CARGADO") -> CODAC SRL | H108: 2500470 | I108: =IF(compras_mes1[[#This Row],[NETO GRAVADO]]="","",compras_mes1[[#This Row],[NETO GRAVADO]]*0.21) -> 525098.7 | P108: =SUM(compras_mes1[[#This Row],[NETO GRAVADO]:[Otros / No Grav.]]) -> 3025568.7 | Q108: =IFERROR(IF(compras_mes1[[#This Row],[CUIT]]="","-",VLOOKUP(compras_mes1[[#This Row],[CUIT]],Lista_CUIT[#All],3,0)),"CUIT NO CARGADO") -> Productos Venta | R108: =IFERROR(IF(compras_mes1[[#This Row],[CUIT]]="","-",VLOOKUP(compras_mes1[[#This Row],[CUIT]],Lista_CUIT[#All],4,0)),"CUIT NO CARGADO") -> BUENOS AIRES
B109: 03/01/2025 | C109: 1 | D109: 2 | E109: 3933 | F109: 30629863571 | G109: =IFERROR(IF(compras_mes1[[#This Row],[CUIT]]="","-",VLOOKUP(compras_mes1[[#This Row],[CUIT]],Lista_CUIT[#All],2,0)),"CUIT NO CARGADO") -> TECNIMAR S R L | H109: 4572898 | I109: =IF(compras_mes1[[#This Row],[NETO GRAVADO]]="","",compras_mes1[[#This Row],[NETO GRAVADO]]*0.21) -> 960308.59 | P109: =SUM(compras_mes1[[#This Row],[NETO GRAVADO]:[Otros / No Grav.]]) -> 5533206.6 | Q109: =IFERROR(IF(compras_mes1[[#This Row],[CUIT]]="","-",VLOOKUP(compras_mes1[[#This Row],[CUIT]],Lista_CUIT[#All],3,0)),"CUIT NO CARGADO") -> Productos Venta | R109: =IFERROR(IF(compras_mes1[[#This Row],[CUIT]]="","-",VLOOKUP(compras_mes1[[#This Row],[CUIT]],Lista_CUIT[#All],4,0)),"CUIT NO CARGADO") -> 0
...

Sheet Feb-25
B1: LIBRO IVA COMPRAS | G1: ='Ene-25'!G1:M1 -> EUROARGENTINA | N1: =EDATE('Ene-25'!N1,1) -> 45689
B3: TOTAL COMPRAS | G3: TOTAL CREDITO FISCAL | J3: TOTAL VENTAS NETAS | M3: TOTAL DEBITO FISCAL | P3: RESULTADO
B4: =SUM(compras_mes2[[#Totals],[NETO GRAVADO]])+extracto_banco_mes2[[#Totals],[NETO]] -> 42863386 | G4: =compras_mes2[[#Totals],[IVA 21 %]]+compras_mes2[[#Totals],[IVA 27%]]+compras_mes2[[#Totals],[IVA 10,5%]]+extracto_banco_mes2[[#Totals],[IVA 21%]]+extracto_banco_mes2[[#Totals],[IVA 10,5%]] -> 8622566.6 | J4: =venta_a_mes2[[#Totals],[IMPORTE NETO]]+ventas_b_mes2[[#Totals],[IMPORTE NETO]] -> 0 | M4: =venta_a_mes2[[#Totals],[IVA 21%]]+venta_a_mes2[[#Totals],[IVA 10,5%]]+ventas_b_mes2[[#Totals],[IVA 21%]]+ventas_b_mes2[[#Totals],[IVA 10,5%]] -> 0 | P4: =G4-M4 -> 8622566.6
G6: Agregadas a afip
B7: FECHA | C7: TIPO | D7: PTO VTA | E7: NRO. CPTE | F7: CUIT | G7: RAZON SOCIAL | H7: NETO GRAVADO | I7: IVA 21 % | J7: IVA 27% | K7: IVA 10,5% | L7: PERC. IVA | M7: PERC IIBB BS AS | N7: PERC. IIBB CABA | O7: Otros / No Grav. | P7: TOTAL | Q7: Tipo de Gasto | R7: Provincia
B8: 01/02/2025 | C8: 1 | D8: 2084 | E8: 27204 | F8: 30548083156 | G8: =IFERROR(IF(compras_mes2[[#This Row],[CUIT]]="","-",VLOOKUP(compras_mes2[[#This Row],[CUIT]],Lista_CUIT[#All],2,0)),"CUIT NO CARGADO") -> COTO CENTRO INTEGRAL DE COMERCIALIZACION SOCIEDAD ANONIMA | H8: 24264.52 | I8: 2201.38 | K8: 1447.08 | O8: 1150.17 | P8: =SUM(compras_mes2[[#This Row],[NETO GRAVADO]:[Otros / No Grav.]]) -> 29063.15 | Q8: =IFERROR(IF(compras_mes2[[#This Row],[CUIT]]="","-",VLOOKUP(compras_mes2[[#This Row],[CUIT]],Lista_CUIT[#All],3,0)),"CUIT NO CARGADO") -> Gastos Varios | R8: =IFERROR(IF(compras_mes2[[#This Row],[CUIT]]="","-",VLOOKUP(compras_mes2[[#This Row],[CUIT]],Lista_CUIT[#All],4,0)),"CUIT NO CARGADO") -> 0
B9: 01/02/2025 | C9: 1 | D9: 629 | E9: 5823700 | F9: 30663498513 | G9: =IFERROR(IF(compras_mes2[[#This Row],[CUIT]]="","-",VLOOKUP(compras_mes2[[#This Row],[CUIT]],Lista_CUIT[#All],2,0)),"CUIT NO CARGADO") -> GRUPO CONCES. DEL OESTE SA | H9: 27732.84 | I9: =IF(compras_mes2[[#This Row],[NETO GRAVADO]]="","",compras_mes2[[#This Row],[NETO GRAVADO]]*0.21) -> 5823.8964 | P9: =SUM(compras_mes2[[#This Row],[NETO GRAVADO]:[Otros / No Grav.]]) -> 33556.736 | Q9: =IFERROR(IF(compras_mes2[[#This Row],[CUIT]]="","-",VLOOKUP(compras_mes2[[#This Row],[CUIT]],Lista_CUIT[#All],3,0)),"CUIT NO CARGADO") -> Peajes | R9: =IFERROR(IF(compras_mes2[[#This Row],[CUIT]]="","-",VLOOKUP(compras_mes2[[#This Row],[CUIT]],Lista_CUIT[#All],4,0)),"CUIT NO CARGADO") -> 0
B10: 05/02/2025 | C10: 1 | D10: 4 | E10: 3582 | F10: 20132380741 | G10: =IFERROR(IF(compras_mes2[[#This Row],[CUIT]]="","-",VLOOKUP(compras_mes2[[#This Row],[CUIT]],Lista_CUIT[#All],2,0)),"CUIT NO CARGADO") -> GERARDO A.S. LARA | H10: 665000 | I10: =IF(compras_mes2[[#This Row],[NETO GRAVADO]]="","",compras_mes2[[#This Row],[NETO GRAVADO]]*0.21) -> 139650 | O10: 10629.43 | P10: =SUM(compras_mes2[[#This Row],[NETO GRAVADO]:[Otros / No Grav.]]) -> 815279.43 | Q10: =IFERROR(IF(compras_mes2[[#This Row],[CUIT]]="","-",VLOOKUP(compras_mes2[[#This Row],[CUIT]],Lista_CUIT[#All],3,0)),"CUIT NO CARGADO") -> Flete | R10: =IFERROR(IF(compras_mes2[[#This Row],[CUIT]]="","-",VLOOKUP(compras_mes2[[#This Row],[CUIT]],Lista_CUIT[#All],4,0)),"CUIT NO CARGADO") -> 0
B11: 24/02/2025 | C11: 1 | D11: 3 | E11: 83 | F11: 20202970940 | G11: =IFERROR(IF(compras_mes2[[#This Row],[CUIT]]="","-",VLOOKUP(compras_mes2[[#This Row],[CUIT]],Lista_CUIT[#All],2,0)),"CUIT NO CARGADO") -> ALEJANDRO TRAIBER | H11: 2658400 | I11: =IF(compras_mes2[[#This Row],[NETO GRAVADO]]="","",compras_mes2[[#This Row],[NETO GRAVADO]]*0.21) -> 558264 | P11: =SUM(compras_mes2[[#This Row],[NETO GRAVADO]:[Otros / No Grav.]]) -> 3216664 | Q11: =IFERROR(IF(compras_mes2[[#This Row],[CUIT]]="","-",VLOOKUP(compras_mes2[[#This Row],[CUIT]],Lista_CUIT[#All],3,0)),"CUIT NO CARGADO") -> Mercaderia | R11: =IFERROR(IF(compras_mes2[[#This Row],[CUIT]]="","-",VLOOKUP(compras_mes2[[#This Row],[CUIT]],Lista_CUIT[#All],4,0)),"CUIT NO CARGADO") -> 0
B12: 45689 | C12: 1 | D12: 12 | E12: 57783 | F12: 30696131003 | G12: =IFERROR(IF(compras_mes2[[#This Row],[CUIT]]="","-",VLOOKUP(compras_mes2[[#This Row],[CUIT]],Lista_CUIT[#All],2,0)),"CUIT NO CARGADO") -> Petrolfe S.A. | H12: 204168.24 | I12: =IF(compras_mes2[[#This Row],[NETO GRAVADO]]="","",compras_mes2[[#This Row],[NETO GRAVADO]]*0.21) -> 42875.33 | O12: 61551.08 | P12: =SUM(compras_mes2[[#This Row],[NETO GRAVADO]:[Otros / No Grav.]]) -> 308594.65 | Q12: =IFERROR(IF(compras_mes2[[#This Row],[CUIT]]="","-",VLOOKUP(compras_mes2[[#This Row],[CUIT]],Lista_CUIT[#All],3,0)),"CUIT NO CARGADO") -> Combustible | R12: =IFERROR(IF(compras_mes2[[#This Row],[CUIT]]="","-",VLOOKUP(compras_mes2[[#This Row],[CUIT]],Lista_CUIT[#All],4,0)),"CUIT NO CARGADO") -> 0
B13: 02/02/2025 | C13: 1 | D13: 2199 | E13: 34884 | F13: 30548083156 | G13: =IFERROR(IF(compras_mes2[[#This Row],[CUIT]]="","-",VLOOKUP(compras_mes2[[#This Row],[CUIT]],Lista_CUIT[#All],2,0)),"CUIT NO CARGADO") -> COTO CENTRO INTEGRAL DE COMERCIALIZACION SOCIEDAD ANONIMA | H13: 34066.09 | I13: =IF(compras_mes2[[#This Row],[NETO GRAVADO]]="","",compras_mes2[[#This Row],[NETO GRAVADO]]*0.21) -> 7153.8789 | O13: 2927.3 | P13: =SUM(compras_mes2[[#This Row],[NETO GRAVADO]:[Otros / No Grav.]]) -> 44147.269 | Q13: =IFERROR(IF(compras_mes2[[#This Row],[CUIT]]="","-",VLOOKUP(compras_mes2[[#This Row],[CUIT]],Lista_CUIT[#All],3,0)),"CUIT NO CARGADO") -> Gastos Varios | R13: =IFERROR(IF(compras_mes2[[#This Row],[CUIT]]="","-",VLOOKUP(compras_mes2[[#This Row],[CUIT]],Lista_CUIT[#All],4,0)),"CUIT NO CARGADO") -> 0
B14: 03/02/2025 | C14: 1 | D14: 14 | E14: 180510 | F14: 30644997258 | G14: =IFERROR(IF(compras_mes2[[#This Row],[CUIT]]="","-",VLOOKUP(compras_mes2[[#This Row],[CUIT]],Lista_CUIT[#All],2,0)),"CUIT NO CARGADO") -> GEMEZ SA | H14: 950047.5 | I14: =IF(compras_mes2[[#This Row],[NETO GRAVADO]]="","",compras_mes2[[#This Row],[NETO GRAVADO]]*0.21) -> 199509.98 | N14: 57002.85 | P14: =SUM(compras_mes2[[#This Row],[NETO GRAVADO]:[Otros / No Grav.]]) -> 1206560.3 | Q14: =IFERROR(IF(compras_mes2[[#This Row],[CUIT]]="","-",VLOOKUP(compras_mes2[[#This Row],[CUIT]],Lista_CUIT[#All],3,0)),"CUIT NO CARGADO") -> Material de Empaque | R14: =IFERROR(IF(compras_mes2[[#This Row],[CUIT]]="","-",VLOOKUP(compras_mes2[[#This Row],[CUIT]],Lista_CUIT[#All],4,0)),"CUIT NO CARGADO") -> 0
B15: 03/02/2025 | C15: 1 | D15: 3099 | E15: 373747 | F15: 30678814357 | G15: =IFERROR(IF(compras_mes2[[#This Row],[CUIT]]="","-",VLOOKUP(compras_mes2[[#This Row],[CUIT]],Lista_CUIT[#All],2,0)),"CUIT NO CARGADO") -> TELEFONICA MOVILES ARG | H15: 34608 | J15: =compras_mes2[[#This Row],[NETO GRAVADO]]*0.27 -> 9344.16 | L15: 1038.24 | N15: 2076.48 | P15: =SUM(compras_mes2[[#This Row],[NETO GRAVADO]:[Otros / No Grav.]]) -> 47066.88 | Q15: =IFERROR(IF(compras_mes2[[#This Row],[CUIT]]="","-",VLOOKUP(compras_mes2[[#This Row],[CUIT]],Lista_CUIT[#All],3,0)),"CUIT NO CARGADO") -> Servicios Gas, Luz, etc. | R15: =IFERROR(IF(compras_mes2[[#This Row],[CUIT]]="","-",VLOOKUP(compras_mes2[[#This Row],[CUIT]],Lista_CUIT[#All],4,0)),"CUIT NO CARGADO") -> 0
B16: 45691 | C16: 1 | D16: 501 | E16: 42219059 | F16: 30655116512 | G16: =IFERROR(IF(compras_mes2[[#This Row],[CUIT]]="","-",VLOOKUP(compras_mes2[[#This Row],[CUIT]],Lista_CUIT[#All],2,0)),"CUIT NO CARGADO") -> Empresa Distribuidora Sur S.A. | H16: 104119.9 | I16: =IF(compras_mes2[[#This Row],[NETO GRAVADO]]="","",compras_mes2[[#This Row],[NETO GRAVADO]]*0.21) -> 21865.179 | L16: 4164.7998 | O16: 6689.71 | P16: =SUM(compras_mes2[[#This Row],[NETO GRAVADO]:[Otros / No Grav.]]) -> 136839.59 | Q16: =IFERROR(IF(compras_mes2[[#This Row],[CUIT]]="","-",VLOOKUP(compras_mes2[[#This Row],[CUIT]],Lista_CUIT[#All],3,0)),"CUIT NO CARGADO") -> Servicios Gas, Luz, etc. | R16: =IFERROR(IF(compras_mes2[[#This Row],[CUIT]]="","-",VLOOKUP(compras_mes2[[#This Row],[CUIT]],Lista_CUIT[#All],4,0)),"CUIT NO CARGADO") -> 0
B17: 45691 | C17: 1 | D17: 501 | E17: 2027280 | F17: 30655116512 | G17: =IFERROR(IF(compras_mes2[[#This Row],[CUIT]]="","-",VLOOKUP(compras_mes2[[#This Row],[CUIT]],Lista_CUIT[#All],2,0)),"CUIT NO CARGADO") -> Empresa Distribuidora Sur S.A. | H17: 263312.54 | J17: =compras_mes2[[#This Row],[NETO GRAVADO]]*0.27 -> 71094.386 | O17: 16807.24 | P17: =SUM(compras_mes2[[#This Row],[NETO GRAVADO]:[Otros / No Grav.]]) -> 351214.17 | Q17: =IFERROR(IF(compras_mes2[[#This Row],[CUIT]]="","-",VLOOKUP(compras_mes2[[#This Row],[CUIT]],Lista_CUIT[#All],3,0)),"CUIT NO CARGADO") -> Servicios Gas, Luz, etc. | R17: =IFERROR(IF(compras_mes2[[#This Row],[CUIT]]="","-",VLOOKUP(compras_mes2[[#This Row],[CUIT]],Lista_CUIT[#All],4,0)),"CUIT NO CARGADO") -> 0
B18: 45691 | C18: 1 | D18: 501 | E18: 2027281 | F18: 30655116512 | G18: =IFERROR(IF(compras_mes2[[#This Row],[CUIT]]="","-",VLOOKUP(compras_mes2[[#This Row],[CUIT]],Lista_CUIT[#All],2,0)),"CUIT NO CARGADO") -> Empresa Distribuidora Sur S.A. | H18: 100297.29 | J18: =compras_mes2[[#This Row],[NETO GRAVADO]]*0.27 -> 27080.269 | L18: 3008.9199 | O18: 6401.98 | P18: =SUM(compras_mes2[[#This Row],[NETO GRAVADO]:[Otros / No Grav.]]) -> 136788.46 | Q18: =IFERROR(IF(compras_mes2[[#This Row],[CUIT]]="","-",VLOOKUP(compras_mes2[[#This Row],[CUIT]],Lista_CUIT[#All],3,0)),"CUIT NO CARGADO") -> Servicios Gas, Luz, etc. | R18: =IFERROR(IF(compras_mes2[[#This Row],[CUIT]]="","-",VLOOKUP(compras_mes2[[#This Row],[CUIT]],Lista_CUIT[#All],4,0)),"CUIT NO CARGADO") -> 0
B19: 04/02/2025 | C19: 1 | D19: 3 | E19: 29839 | F19: 33707953549 | G19: =IFERROR(IF(compras_mes2[[#This Row],[CUIT]]="","-",VLOOKUP(compras_mes2[[#This Row],[CUIT]],Lista_CUIT[#All],2,0)),"CUIT NO CARGADO") -> TELESMART | H19: 19500 | I19: =IF(compras_mes2[[#This Row],[NETO GRAVADO]]="","",compras_mes2[[#This Row],[NETO GRAVADO]]*0.21) -> 4095 | P19: =SUM(compras_mes2[[#This Row],[NETO GRAVADO]:[Otros / No Grav.]]) -> 23595 | Q19: =IFERROR(IF(compras_mes2[[#This Row],[CUIT]]="","-",VLOOKUP(compras_mes2[[#This Row],[CUIT]],Lista_CUIT[#All],3,0)),"CUIT NO CARGADO") -> Servicios Gas, Luz, etc. | R19: =IFERROR(IF(compras_mes2[[#This Row],[CUIT]]="","-",VLOOKUP(compras_mes2[[#This Row],[CUIT]],Lista_CUIT[#All],4,0)),"CUIT NO CARGADO") -> 0
B20: 04/02/2025 | C20: 1 | D20: 1 | E20: 152 | F20: 30716010313 | G20: =IFERROR(IF(compras_mes2[[#This Row],[CUIT]]="","-",VLOOKUP(compras_mes2[[#This Row],[CUIT]],Lista_CUIT[#All],2,0)),"CUIT NO CARGADO") -> H UNO 1469 S.A. | H20: 500000 | I20: =IF(compras_mes2[[#This Row],[NETO GRAVADO]]="","",compras_mes2[[#This Row],[NETO GRAVADO]]*0.21) -> 105000 | P20: =SUM(compras_mes2[[#This Row],[NETO GRAVADO]:[Otros / No Grav.]]) -> 605000 | Q20: =IFERROR(IF(compras_mes2[[#This Row],[CUIT]]="","-",VLOOKUP(compras_mes2[[#This Row],[CUIT]],Lista_CUIT[#All],3,0)),"CUIT NO CARGADO") -> Alquiler | R20: =IFERROR(IF(compras_mes2[[#This Row],[CUIT]]="","-",VLOOKUP(compras_mes2[[#This Row],[CUIT]],Lista_CUIT[#All],4,0)),"CUIT NO CARGADO") -> 0
B21: 04/02/2025 | C21: 1 | D21: 2 | E21: 293 | F21: 27309896063 | G21: =IFERROR(IF(compras_mes2[[#This Row],[CUIT]]="","-",VLOOKUP(compras_mes2[[#This Row],[CUIT]],Lista_CUIT[#All],2,0)),"CUIT NO CARGADO") -> BATTELLINI MARIA SOLEDAD | H21: 550000 | I21: =IF(compras_mes2[[#This Row],[NETO GRAVADO]]="","",compras_mes2[[#This Row],[NETO GRAVADO]]*0.21) -> 115500 | P21: =SUM(compras_mes2[[#This Row],[NETO GRAVADO]:[Otros / No Grav.]]) -> 665500 | Q21: =IFERROR(IF(compras_mes2[[#This Row],[CUIT]]="","-",VLOOKUP(compras_mes2[[#This Row],[CUIT]],Lista_CUIT[#All],3,0)),"CUIT NO CARGADO") -> Alquiler | R21: =IFERROR(IF(compras_mes2[[#This Row],[CUIT]]="","-",VLOOKUP(compras_mes2[[#This Row],[CUIT]],Lista_CUIT[#All],4,0)),"CUIT NO CARGADO") -> 0
B22: 04/02/2025 | C22: 1 | D22: 1 | E22: 585 | F22: 20131206144 | G22: =IFERROR(IF(compras_mes2[[#This Row],[CUIT]]="","-",VLOOKUP(compras_mes2[[#This Row],[CUIT]],Lista_CUIT[#All],2,0)),"CUIT NO CARGADO") -> CHAMORRO MANUEL | H22: 1009489 | I22: =IF(compras_mes2[[#This Row],[NETO GRAVADO]]="","",compras_mes2[[#This Row],[NETO GRAVADO]]*0.21) -> 211992.69 | P22: =SUM(compras_mes2[[#This Row],[NETO GRAVADO]:[Otros / No Grav.]]) -> 1221481.7 | Q22: =IFERROR(IF(compras_mes2[[#This Row],[CUIT]]="","-",VLOOKUP(compras_mes2[[#This Row],[CUIT]],Lista_CUIT[#All],3,0)),"CUIT NO CARGADO") -> Alquiler | R22: =IFERROR(IF(compras_mes2[[#This Row],[CUIT]]="","-",VLOOKUP(compras_mes2[[#This Row],[CUIT]],Lista_CUIT[#All],4,0)),"CUIT NO CARGADO") -> 0
B23: 45692 | C23: 1 | D23: 26 | E23: 49207834 | F23: 30655116202 | G23: =IFERROR(IF(compras_mes2[[#This Row],[CUIT]]="","-",VLOOKUP(compras_mes2[[#This Row],[CUIT]],Lista_CUIT[#All],2,0)),"CUIT NO CARGADO") -> EDENOR | H23: 67216.672 | J23: =compras_mes2[[#This Row],[NETO GRAVADO]]*0.27 -> 18148.501 | L23: 11527.66 | P23: =SUM(compras_mes2[[#This Row],[NETO GRAVADO]:[Otros / No Grav.]]) -> 96892.833 | Q23: =IFERROR(IF(compras_mes2[[#This Row],[CUIT]]="","-",VLOOKUP(compras_mes2[[#This Row],[CUIT]],Lista_CUIT[#All],3,0)),"CUIT NO CARGADO") -> Servicios Gas, Luz, etc. | R23: =IFERROR(IF(compras_mes2[[#This Row],[CUIT]]="","-",VLOOKUP(compras_mes2[[#This Row],[CUIT]],Lista_CUIT[#All],4,0)),"CUIT NO CARGADO") -> 0
B24: 14/02/2025 | C24: 1 | D24: 8 | E24: 111 | F24: 20330222566 | G24: =IFERROR(IF(compras_mes2[[#This Row],[CUIT]]="","-",VLOOKUP(compras_mes2[[#This Row],[CUIT]],Lista_CUIT[#All],2,0)),"CUIT NO CARGADO") -> TECHSUPPLIES | H24: 93739.67 | I24: =IF(compras_mes2[[#This Row],[NETO GRAVADO]]="","",compras_mes2[[#This Row],[NETO GRAVADO]]*0.21) -> 19685.331 | P24: =SUM(compras_mes2[[#This Row],[NETO GRAVADO]:[Otros / No Grav.]]) -> 113425 | Q24: =IFERROR(IF(compras_mes2[[#This Row],[CUIT]]="","-",VLOOKUP(compras_mes2[[#This Row],[CUIT]],Lista_CUIT[#All],3,0)),"CUIT NO CARGADO") -> Librería | R24: =IFERROR(IF(compras_mes2[[#This Row],[CUIT]]="","-",VLOOKUP(compras_mes2[[#This Row],[CUIT]],Lista_CUIT[#All],4,0)),"CUIT NO CARGADO") -> 0
B25: 05/02/2025 | C25: 1 | D25: 700 | E25: 2249015 | F25: 30715804812 | G25: =IFERROR(IF(compras_mes2[[#This Row],[CUIT]]="","-",VLOOKUP(compras_mes2[[#This Row],[CUIT]],Lista_CUIT[#All],2,0)),"CUIT NO CARGADO") -> CORREDORES VIALES SOCIEDAD ANONIMA | H25: 8111.83 | I25: =IF(compras_mes2[[#This Row],[NETO GRAVADO]]="","",compras_mes2[[#This Row],[NETO GRAVADO]]*0.21) -> 1703.4843 | P25: =SUM(compras_mes2[[#This Row],[NETO GRAVADO]:[Otros / No Grav.]]) -> 9815.3143 | Q25: =IFERROR(IF(compras_mes2[[#This Row],[CUIT]]="","-",VLOOKUP(compras_mes2[[#This Row],[CUIT]],Lista_CUIT[#All],3,0)),"CUIT NO CARGADO") -> Peajes | R25: =IFERROR(IF(compras_mes2[[#This Row],[CUIT]]="","-",VLOOKUP(compras_mes2[[#This Row],[CUIT]],Lista_CUIT[#All],4,0)),"CUIT NO CARGADO") -> 0
B26: 05/02/2025 | C26: 1 | D26: 63 | E26: 3171692 | F26: 30640897267 | G26: =IFERROR(IF(compras_mes2[[#This Row],[CUIT]]="","-",VLOOKUP(compras_mes2[[#This Row],[CUIT]],Lista_CUIT[#All],2,0)),"CUIT NO CARGADO") -> TELECENTRO S.A. | H26: 58457.6 | I26: =IF(compras_mes2[[#This Row],[NETO GRAVADO]]="","",compras_mes2[[#This Row],[NETO GRAVADO]]*0.21) -> 12276.096 | L26: 1753.73 | N26: 3507.46 | P26: =SUM(compras_mes2[[#This Row],[NETO GRAVADO]:[Otros / No Grav.]]) -> 75994.886 | Q26: =IFERROR(IF(compras_mes2[[#This Row],[CUIT]]="","-",VLOOKUP(compras_mes2[[#This Row],[CUIT]],Lista_CUIT[#All],3,0)),"CUIT NO CARGADO") -> Servicios Gas, Luz, etc. | R26: =IFERROR(IF(compras_mes2[[#This Row],[CUIT]]="","-",VLOOKUP(compras_mes2[[#This Row],[CUIT]],Lista_CUIT[#All],4,0)),"CUIT NO CARGADO") -> 0
B27: 05/02/2025 | C27: 1 | D27: 63 | E27: 3172765 | F27: 30640897267 | G27: =IFERROR(IF(compras_mes2[[#This Row],[CUIT]]="","-",VLOOKUP(compras_mes2[[#This Row],[CUIT]],Lista_CUIT[#All],2,0)),"CUIT NO CARGADO") -> TELECENTRO S.A. | H27: 58457.6 | I27: =IF(compras_mes2[[#This Row],[NETO GRAVADO]]="","",compras_mes2[[#This Row],[NETO GRAVADO]]*0.21) -> 12276.096 | L27: 1753.73 | N27: 3507.46 | P27: =SUM(compras_mes2[[#This Row],[NETO GRAVADO]:[Otros / No Grav.]]) -> 75994.886 | Q27: =IFERROR(IF(compras_mes2[[#This Row],[CUIT]]="","-",VLOOKUP(compras_mes2[[#This Row],[CUIT]],Lista_CUIT[#All],3,0)),"CUIT NO CARGADO") -> Servicios Gas, Luz, etc. | R27: =IFERROR(IF(compras_mes2[[#This Row],[CUIT]]="","-",VLOOKUP(compras_mes2[[#This Row],[CUIT]],Lista_CUIT[#All],4,0)),"CUIT NO CARGADO") -> 0
B28: 05/02/2025 | C28: 1 | D28: 1 | E28: 27 | F28: 30717504824 | G28: =IFERROR(IF(compras_mes2[[#This Row],[CUIT]]="","-",VLOOKUP(compras_mes2[[#This Row],[CUIT]],Lista_CUIT[#All],2,0)),"CUIT NO CARGADO") -> FIDEICOMISO MAMBA | H28: 2722715 | K28: =compras_mes2[[#This Row],[NETO GRAVADO]]*0.105 -> 285885.07 | P28: =SUM(compras_mes2[[#This Row],[NETO GRAVADO]:[Otros / No Grav.]]) -> 3008600 | Q28: =IFERROR(IF(compras_mes2[[#This Row],[CUIT]]="","-",VLOOKUP(compras_mes2[[#This Row],[CUIT]],Lista_CUIT[#All],3,0)),"CUIT NO CARGADO") -> MANTENIMIENTO | R28: =IFERROR(IF(compras_mes2[[#This Row],[CUIT]]="","-",VLOOKUP(compras_mes2[[#This Row],[CUIT]],Lista_CUIT[#All],4,0)),"CUIT NO CARGADO") -> 0
B29: 18/02/2025 | C29: 1 | D29: 8 | E29: 3625 | F29: 20348424026 | G29: =IFERROR(IF(compras_mes2[[#This Row],[CUIT]]="","-",VLOOKUP(compras_mes2[[#This Row],[CUIT]],Lista_CUIT[#All],2,0)),"CUIT NO CARGADO") -> ALEXANDER DOUGLAS DROT DE GOURVILLE | H29: 17520.66 | I29: =IF(compras_mes2[[#This Row],[NETO GRAVADO]]="","",compras_mes2[[#This Row],[NETO GRAVADO]]*0.21) -> 3679.3386 | P29: =SUM(compras_mes2[[#This Row],[NETO GRAVADO]:[Otros / No Grav.]]) -> 21199.999 | Q29: =IFERROR(IF(compras_mes2[[#This Row],[CUIT]]="","-",VLOOKUP(compras_mes2[[#This Row],[CUIT]],Lista_CUIT[#All],3,0)),"CUIT NO CARGADO") -> Gastos Limpieza | R29: =IFERROR(IF(compras_mes2[[#This Row],[CUIT]]="","-",VLOOKUP(compras_mes2[[#This Row],[CUIT]],Lista_CUIT[#All],4,0)),"CUIT NO CARGADO") -> 0
B30: 07/02/2025 | C30: 1 | D30: 2 | E30: 2865 | F30: 30715811622 | G30: =IFERROR(IF(compras_mes2[[#This Row],[CUIT]]="","-",VLOOKUP(compras_mes2[[#This Row],[CUIT]],Lista_CUIT[#All],2,0)),"CUIT NO CARGADO") -> VTEC SRL | H30: 732728.94 | I30: =IF(compras_mes2[[#This Row],[NETO GRAVADO]]="","",compras_mes2[[#This Row],[NETO GRAVADO]]*0.21) -> 153873.08 | P30: =SUM(compras_mes2[[#This Row],[NETO GRAVADO]:[Otros / No Grav.]]) -> 886602.02 | Q30: =IFERROR(IF(compras_mes2[[#This Row],[CUIT]]="","-",VLOOKUP(compras_mes2[[#This Row],[CUIT]],Lista_CUIT[#All],3,0)),"CUIT NO CARGADO") -> Productos Venta | R30: =IFERROR(IF(compras_mes2[[#This Row],[CUIT]]="","-",VLOOKUP(compras_mes2[[#This Row],[CUIT]],Lista_CUIT[#All],4,0)),"CUIT NO CARGADO") -> 0
B31: 07/02/2025 | C31: 1 | D31: 5 | E31: 28353 | F31: 20366883879 | G31: =IFERROR(IF(compras_mes2[[#This Row],[CUIT]]="","-",VLOOKUP(compras_mes2[[#This Row],[CUIT]],Lista_CUIT[#All],2,0)),"CUIT NO CARGADO") -> VACCARI DARIO | H31: 105544 | I31: =IF(compras_mes2[[#This Row],[NETO GRAVADO]]="","",compras_mes2[[#This Row],[NETO GRAVADO]]*0.21) -> 22164.24 | P31: =SUM(compras_mes2[[#This Row],[NETO GRAVADO]:[Otros / No Grav.]]) -> 127708.24 | Q31: =IFERROR(IF(compras_mes2[[#This Row],[CUIT]]="","-",VLOOKUP(compras_mes2[[#This Row],[CUIT]],Lista_CUIT[#All],3,0)),"CUIT NO CARGADO") -> Muebles y Utiles | R31: =IFERROR(IF(compras_mes2[[#This Row],[CUIT]]="","-",VLOOKUP(compras_mes2[[#This Row],[CUIT]],Lista_CUIT[#All],4,0)),"CUIT NO CARGADO") -> 0
B32: 07/02/2025 | C32: 1 | D32: 5 | E32: 28354 | F32: 20366883879 | G32: =IFERROR(IF(compras_mes2[[#This Row],[CUIT]]="","-",VLOOKUP(compras_mes2[[#This Row],[CUIT]],Lista_CUIT[#All],2,0)),"CUIT NO CARGADO") -> VACCARI DARIO | H32: 105544 | I32: =IF(compras_mes2[[#This Row],[NETO GRAVADO]]="","",compras_mes2[[#This Row],[NETO GRAVADO]]*0.21) -> 22164.24 | P32: =SUM(compras_mes2[[#This Row],[NETO GRAVADO]:[Otros / No Grav.]]) -> 127708.24 | Q32: =IFERROR(IF(compras_mes2[[#This Row],[CUIT]]="","-",VLOOKUP(compras_mes2[[#This Row],[CUIT]],Lista_CUIT[#All],3,0)),"CUIT NO CARGADO") -> Muebles y Utiles | R32: =IFERROR(IF(compras_mes2[[#This Row],[CUIT]]="","-",VLOOKUP(compras_mes2[[#This Row],[CUIT]],Lista_CUIT[#All],4,0)),"CUIT NO CARGADO") -> 0
B33: 45695 | C33: 1 | D33: 14 | E33: 34417 | F33: 30647082293 | G33: =IFERROR(IF(compras_mes2[[#This Row],[CUIT]]="","-",VLOOKUP(compras_mes2[[#This Row],[CUIT]],Lista_CUIT[#All],2,0)),"CUIT NO CARGADO") -> CHARATA SRL | H33: 52519.1 | I33: =IF(compras_mes2[[#This Row],[NETO GRAVADO]]="","",compras_mes2[[#This Row],[NETO GRAVADO]]*0.21) -> 11029.011 | O33: 14903.82 | P33: =SUM(compras_mes2[[#This Row],[NETO GRAVADO]:[Otros / No Grav.]]) -> 78451.931 | Q33: =IFERROR(IF(compras_mes2[[#This Row],[CUIT]]="","-",VLOOKUP(compras_mes2[[#This Row],[CUIT]],Lista_CUIT[#All],3,0)),"CUIT NO CARGADO") -> Combustible | R33: =IFERROR(IF(compras_mes2[[#This Row],[CUIT]]="","-",VLOOKUP(compras_mes2[[#This Row],[CUIT]],Lista_CUIT[#All],4,0)),"CUIT NO CARGADO") -> 0
B34: 08/02/2025 | C34: 1 | D34: 14 | E34: 16052 | F34: 30715186256 | G34: =IFERROR(IF(compras_mes2[[#This Row],[CUIT]]="","-",VLOOKUP(compras_mes2[[#This Row],[CUIT]],Lista_CUIT[#All],2,0)),"CUIT NO CARGADO") -> FRIGORIFICO ALIMENTIC | H34: 172610.89 | I34: 4142.03 | K34: 16053.13 | P34: =SUM(compras_mes2[[#This Row],[NETO GRAVADO]:[Otros / No Grav.]]) -> 192806.05 | Q34: =IFERROR(IF(compras_mes2[[#This Row],[CUIT]]="","-",VLOOKUP(compras_mes2[[#This Row],[CUIT]],Lista_CUIT[#All],3,0)),"CUIT NO CARGADO") -> Gastos Comercializacion - Feria | R34: =IFERROR(IF(compras_mes2[[#This Row],[CUIT]]="","-",VLOOKUP(compras_mes2[[#This Row],[CUIT]],Lista_CUIT[#All],4,0)),"CUIT NO CARGADO") -> 0
B35: 08/02/2025 | C35: 1 | D35: 2084 | E35: 27310 | F35: 30548083156 | G35: =IFERROR(IF(compras_mes2[[#This Row],[CUIT]]="","-",VLOOKUP(compras_mes2[[#This Row],[CUIT]],Lista_CUIT[#All],2,0)),"CUIT NO CARGADO") -> COTO CENTRO INTEGRAL DE COMERCIALIZACION SOCIEDAD ANONIMA | H35: 51799.27 | I35: 10210.95 | K35: 333.45 | O35: 4289.65 | P35: =SUM(compras_mes2[[#This Row],[NETO GRAVADO]:[Otros / No Grav.]]) -> 66633.32 | Q35: =IFERROR(IF(compras_mes2[[#This Row],[CUIT]]="","-",VLOOKUP(compras_mes2[[#This Row],[CUIT]],Lista_CUIT[#All],3,0)),"CUIT NO CARGADO") -> Gastos Varios | R35: =IFERROR(IF(compras_mes2[[#This Row],[CUIT]]="","-",VLOOKUP(compras_mes2[[#This Row],[CUIT]],Lista_CUIT[#All],4,0)),"CUIT NO CARGADO") -> 0
B36: 08/02/2025 | C36: 1 | D36: 5015 | E36: 745745 | F36: 30574876474 | G36: =IFERROR(IF(compras_mes2[[#This Row],[CUIT]]="","-",VLOOKUP(compras_mes2[[#This Row],[CUIT]],Lista_CUIT[#All],2,0)),"CUIT NO CARGADO") -> AUTOPISTAS URBANAS S A | H36: 45405.7 | I36: =IF(compras_mes2[[#This Row],[NETO GRAVADO]]="","",compras_mes2[[#This Row],[NETO GRAVADO]]*0.21) -> 9535.197 | O36: 5902.74 | P36: =SUM(compras_mes2[[#This Row],[NETO GRAVADO]:[Otros / No Grav.]]) -> 60843.637 | Q36: =IFERROR(IF(compras_mes2[[#This Row],[CUIT]]="","-",VLOOKUP(compras_mes2[[#This Row],[CUIT]],Lista_CUIT[#All],3,0)),"CUIT NO CARGADO") -> Peajes | R36: =IFERROR(IF(compras_mes2[[#This Row],[CUIT]]="","-",VLOOKUP(compras_mes2[[#This Row],[CUIT]],Lista_CUIT[#All],4,0)),"CUIT NO CARGADO") -> 0
B37: 08/02/2025 | C37: 1 | D37: 711 | E37: 6698530 | F37: 30677237119 | G37: =IFERROR(IF(compras_mes2[[#This Row],[CUIT]]="","-",VLOOKUP(compras_mes2[[#This Row],[CUIT]],Lista_CUIT[#All],2,0)),"CUIT NO CARGADO") -> AUTOPISTAS DEL SOL S A | H37: 9186.42 | I37: =IF(compras_mes2[[#This Row],[NETO GRAVADO]]="","",compras_mes2[[#This Row],[NETO GRAVADO]]*0.21) -> 1929.1482 | L37: 275.59 | O37: 275.59 | P37: =SUM(compras_mes2[[#This Row],[NETO GRAVADO]:[Otros / No Grav.]]) -> 11666.748 | Q37: =IFERROR(IF(compras_mes2[[#This Row],[CUIT]]="","-",VLOOKUP(compras_mes2[[#This Row],[CUIT]],Lista_CUIT[#All],3,0)),"CUIT NO CARGADO") -> Peajes | R37: =IFERROR(IF(compras_mes2[[#This Row],[CUIT]]="","-",VLOOKUP(compras_mes2[[#This Row],[CUIT]],Lista_CUIT[#All],4,0)),"CUIT NO CARGADO") -> 0
B38: 45696 | C38: 1 | D38: 12 | E38: 58181 | F38: 30696131003 | G38: =IFERROR(IF(compras_mes2[[#This Row],[CUIT]]="","-",VLOOKUP(compras_mes2[[#This Row],[CUIT]],Lista_CUIT[#All],2,0)),"CUIT NO CARGADO") -> Petrolfe S.A. | H38: 99574.71 | I38: =IF(compras_mes2[[#This Row],[NETO GRAVADO]]="","",compras_mes2[[#This Row],[NETO GRAVADO]]*0.21) -> 20910.689 | O38: 34875.28 | P38: =SUM(compras_mes2[[#This Row],[NETO GRAVADO]:[Otros / No Grav.]]) -> 155360.68 | Q38: =IFERROR(IF(compras_mes2[[#This Row],[CUIT]]="","-",VLOOKUP(compras_mes2[[#This Row],[CUIT]],Lista_CUIT[#All],3,0)),"CUIT NO CARGADO") -> Combustible | R38: =IFERROR(IF(compras_mes2[[#This Row],[CUIT]]="","-",VLOOKUP(compras_mes2[[#This Row],[CUIT]],Lista_CUIT[#All],4,0)),"CUIT NO CARGADO") -> 0
B39: 09/02/2025 | C39: 1 | D39: 2215 | E39: 51306 | F39: 30548083156 | G39: =IFERROR(IF(compras_mes2[[#This Row],[CUIT]]="","-",VLOOKUP(compras_mes2[[#This Row],[CUIT]],Lista_CUIT[#All],2,0)),"CUIT NO CARGADO") -> COTO CENTRO INTEGRAL DE COMERCIALIZACION SOCIEDAD ANONIMA | H39: 94361.53 | I39: 18409.44 | K39: 703.24 | O39: 7951.97 | P39: =SUM(compras_mes2[[#This Row],[NETO GRAVADO]:[Otros / No Grav.]]) -> 121426.18 | Q39: =IFERROR(IF(compras_mes2[[#This Row],[CUIT]]="","-",VLOOKUP(compras_mes2[[#This Row],[CUIT]],Lista_CUIT[#All],3,0)),"CUIT NO CARGADO") -> Gastos Varios | R39: =IFERROR(IF(compras_mes2[[#This Row],[CUIT]]="","-",VLOOKUP(compras_mes2[[#This Row],[CUIT]],Lista_CUIT[#All],4,0)),"CUIT NO CARGADO") -> 0
B40: 09/02/2025 | C40: 1 | D40: 3101 | E40: 264469 | F40: 30678814357 | G40: =IFERROR(IF(compras_mes2[[#This Row],[CUIT]]="","-",VLOOKUP(compras_mes2[[#This Row],[CUIT]],Lista_CUIT[#All],2,0)),"CUIT NO CARGADO") -> TELEFONICA MOVILES ARG | H40: 16370.23 | J40: =compras_mes2[[#This Row],[NETO GRAVADO]]*0.27 -> 4419.9621 | L40: 491.11 | N40: 982.21 | P40: =SUM(compras_mes2[[#This Row],[NETO GRAVADO]:[Otros / No Grav.]]) -> 22263.512 | Q40: =IFERROR(IF(compras_mes2[[#This Row],[CUIT]]="","-",VLOOKUP(compras_mes2[[#This Row],[CUIT]],Lista_CUIT[#All],3,0)),"CUIT NO CARGADO") -> Servicios Gas, Luz, etc. | R40: =IFERROR(IF(compras_mes2[[#This Row],[CUIT]]="","-",VLOOKUP(compras_mes2[[#This Row],[CUIT]],Lista_CUIT[#All],4,0)),"CUIT NO CARGADO") -> 0
B41: 10/02/2025 | C41: 1 | D41: 7 | E41: 13918 | F41: 30708017759 | G41: =IFERROR(IF(compras_mes2[[#This Row],[CUIT]]="","-",VLOOKUP(compras_mes2[[#This Row],[CUIT]],Lista_CUIT[#All],2,0)),"CUIT NO CARGADO") -> NEW HIGH PACK SA | H41: 2846901.6 | I41: =IF(compras_mes2[[#This Row],[NETO GRAVADO]]="","",compras_mes2[[#This Row],[NETO GRAVADO]]*0.21) -> 597849.34 | N41: 170814.1 | P41: =SUM(compras_mes2[[#This Row],[NETO GRAVADO]:[Otros / No Grav.]]) -> 3615565 | Q41: =IFERROR(IF(compras_mes2[[#This Row],[CUIT]]="","-",VLOOKUP(compras_mes2[[#This Row],[CUIT]],Lista_CUIT[#All],3,0)),"CUIT NO CARGADO") -> Material de Empaque | R41: =IFERROR(IF(compras_mes2[[#This Row],[CUIT]]="","-",VLOOKUP(compras_mes2[[#This Row],[CUIT]],Lista_CUIT[#All],4,0)),"CUIT NO CARGADO") -> 0
B42: 10/02/2025 | C42: 1 | D42: 6364 | E42: 8897422 | F42: 30639453738 | G42: =IFERROR(IF(compras_mes2[[#This Row],[CUIT]]="","-",VLOOKUP(compras_mes2[[#This Row],[CUIT]],Lista_CUIT[#All],2,0)),"CUIT NO CARGADO") -> TELECOM ARG SA | H42: 280060.42 | I42: 58596.07 | J42: 278.51 | N42: 15606.86 | O42: 8477.57 | P42: =SUM(compras_mes2[[#This Row],[NETO GRAVADO]:[Otros / No Grav.]]) -> 363019.43 | Q42: =IFERROR(IF(compras_mes2[[#This Row],[CUIT]]="","-",VLOOKUP(compras_mes2[[#This Row],[CUIT]],Lista_CUIT[#All],3,0)),"CUIT NO CARGADO") -> Servicios Gas, Luz, etc. | R42: =IFERROR(IF(compras_mes2[[#This Row],[CUIT]]="","-",VLOOKUP(compras_mes2[[#This Row],[CUIT]],Lista_CUIT[#All],4,0)),"CUIT NO CARGADO") -> 0
B43: 10/02/2025 | C43: 3 | D43: 7 | E43: 1178 | F43: 30708017759 | G43: =IFERROR(IF(compras_mes2[[#This Row],[CUIT]]="","-",VLOOKUP(compras_mes2[[#This Row],[CUIT]],Lista_CUIT[#All],2,0)),"CUIT NO CARGADO") -> NEW HIGH PACK SA | H43: -2164393.7 | I43: =IF(compras_mes2[[#This Row],[NETO GRAVADO]]="","",compras_mes2[[#This Row],[NETO GRAVADO]]*0.21) -> -454522.68 | N43: -129863.62 | P43: =SUM(compras_mes2[[#This Row],[NETO GRAVADO]:[Otros / No Grav.]]) -> -2748780 | Q43: =IFERROR(IF(compras_mes2[[#This Row],[CUIT]]="","-",VLOOKUP(compras_mes2[[#This Row],[CUIT]],Lista_CUIT[#All],3,0)),"CUIT NO CARGADO") -> Material de Empaque | R43: =IFERROR(IF(compras_mes2[[#This Row],[CUIT]]="","-",VLOOKUP(compras_mes2[[#This Row],[CUIT]],Lista_CUIT[#All],4,0)),"CUIT NO CARGADO") -> 0
B44: 45698 | C44: 1 | D44: 106 | E44: 10196672 | F44: 30709565075 | G44: =IFERROR(IF(compras_mes2[[#This Row],[CUIT]]="","-",VLOOKUP(compras_mes2[[#This Row],[CUIT]],Lista_CUIT[#All],2,0)),"CUIT NO CARGADO") -> AYSA S.A | H44: 83566.104 | J44: =compras_mes2[[#This Row],[NETO GRAVADO]]*0.27 -> 22562.848 | L44: 2506.98 | O44: 1495.8398 | P44: =SUM(compras_mes2[[#This Row],[NETO GRAVADO]:[Otros / No Grav.]]) -> 110131.77 | Q44: =IFERROR(IF(compras_mes2[[#This Row],[CUIT]]="","-",VLOOKUP(compras_mes2[[#This Row],[CUIT]],Lista_CUIT[#All],3,0)),"CUIT NO CARGADO") -> Servicios Gas, Luz, etc. | R44: =IFERROR(IF(compras_mes2[[#This Row],[CUIT]]="","-",VLOOKUP(compras_mes2[[#This Row],[CUIT]],Lista_CUIT[#All],4,0)),"CUIT NO CARGADO") -> 0
B45: 45698 | C45: 1 | D45: 110 | E45: 51168570 | F45: 30709565075 | G45: =IFERROR(IF(compras_mes2[[#This Row],[CUIT]]="","-",VLOOKUP(compras_mes2[[#This Row],[CUIT]],Lista_CUIT[#All],2,0)),"CUIT NO CARGADO") -> AYSA S.A | H45: 69409.739 | I45: =IF(compras_mes2[[#This Row],[NETO GRAVADO]]="","",compras_mes2[[#This Row],[NETO GRAVADO]]*0.21) -> 14576.045 | O45: 1242.4301 | P45: =SUM(compras_mes2[[#This Row],[NETO GRAVADO]:[Otros / No Grav.]]) -> 85228.214 | Q45: =IFERROR(IF(compras_mes2[[#This Row],[CUIT]]="","-",VLOOKUP(compras_mes2[[#This Row],[CUIT]],Lista_CUIT[#All],3,0)),"CUIT NO CARGADO") -> Servicios Gas, Luz, etc. | R45: =IFERROR(IF(compras_mes2[[#This Row],[CUIT]]="","-",VLOOKUP(compras_mes2[[#This Row],[CUIT]],Lista_CUIT[#All],4,0)),"CUIT NO CARGADO") -> 0
B46: 45699 | C46: 1 | D46: 1 | E46: 131 | F46: 30718148207 | G46: =IFERROR(IF(compras_mes2[[#This Row],[CUIT]]="","-",VLOOKUP(compras_mes2[[#This Row],[CUIT]],Lista_CUIT[#All],2,0)),"CUIT NO CARGADO") -> VIPA INTERNATIONAL S.R.L. | H46: 1750000 | I46: =IF(compras_mes2[[#This Row],[NETO GRAVADO]]="","",compras_mes2[[#This Row],[NETO GRAVADO]]*0.21) -> 367500 | P46: =SUM(compras_mes2[[#This Row],[NETO GRAVADO]:[Otros / No Grav.]]) -> 2117500 | Q46: =IFERROR(IF(compras_mes2[[#This Row],[CUIT]]="","-",VLOOKUP(compras_mes2[[#This Row],[CUIT]],Lista_CUIT[#All],3,0)),"CUIT NO CARGADO") -> Productos Venta | R46: =IFERROR(IF(compras_mes2[[#This Row],[CUIT]]="","-",VLOOKUP(compras_mes2[[#This Row],[CUIT]],Lista_CUIT[#All],4,0)),"CUIT NO CARGADO") -> 0
B47: 45699 | C47: 1 | D47: 1 | E47: 132 | F47: 30718148207 | G47: =IFERROR(IF(compras_mes2[[#This Row],[CUIT]]="","-",VLOOKUP(compras_mes2[[#This Row],[CUIT]],Lista_CUIT[#All],2,0)),"CUIT NO CARGADO") -> VIPA INTERNATIONAL S.R.L. | H47: 2200000 | I47: =IF(compras_mes2[[#This Row],[NETO GRAVADO]]="","",compras_mes2[[#This Row],[NETO GRAVADO]]*0.21) -> 462000 | P47: =SUM(compras_mes2[[#This Row],[NETO GRAVADO]:[Otros / No Grav.]]) -> 2662000 | Q47: =IFERROR(IF(compras_mes2[[#This Row],[CUIT]]="","-",VLOOKUP(compras_mes2[[#This Row],[CUIT]],Lista_CUIT[#All],3,0)),"CUIT NO CARGADO") -> Productos Venta | R47: =IFERROR(IF(compras_mes2[[#This Row],[CUIT]]="","-",VLOOKUP(compras_mes2[[#This Row],[CUIT]],Lista_CUIT[#All],4,0)),"CUIT NO CARGADO") -> 0
B48: 12/02/2025 | C48: 1 | D48: 3 | E48: 1338 | F48: 20308960782 | G48: =IFERROR(IF(compras_mes2[[#This Row],[CUIT]]="","-",VLOOKUP(compras_mes2[[#This Row],[CUIT]],Lista_CUIT[#All],2,0)),"CUIT NO CARGADO") -> OSSANDON ROBERTO SAUL | H48: 11157.02 | I48: =IF(compras_mes2[[#This Row],[NETO GRAVADO]]="","",compras_mes2[[#This Row],[NETO GRAVADO]]*0.21) -> 2342.9742 | P48: =SUM(compras_mes2[[#This Row],[NETO GRAVADO]:[Otros / No Grav.]]) -> 13499.994 | Q48: =IFERROR(IF(compras_mes2[[#This Row],[CUIT]]="","-",VLOOKUP(compras_mes2[[#This Row],[CUIT]],Lista_CUIT[#All],3,0)),"CUIT NO CARGADO") -> Gastos Limpieza | R48: =IFERROR(IF(compras_mes2[[#This Row],[CUIT]]="","-",VLOOKUP(compras_mes2[[#This Row],[CUIT]],Lista_CUIT[#All],4,0)),"CUIT NO CARGADO") -> 0
B49: 12/02/2025 | C49: 1 | D49: 2 | E49: 2870 | F49: 30715811622 | G49: =IFERROR(IF(compras_mes2[[#This Row],[CUIT]]="","-",VLOOKUP(compras_mes2[[#This Row],[CUIT]],Lista_CUIT[#All],2,0)),"CUIT NO CARGADO") -> VTEC SRL | H49: 688084.96 | I49: =IF(compras_mes2[[#This Row],[NETO GRAVADO]]="","",compras_mes2[[#This Row],[NETO GRAVADO]]*0.21) -> 144497.84 | P49: =SUM(compras_mes2[[#This Row],[NETO GRAVADO]:[Otros / No Grav.]]) -> 832582.8 | Q49: =IFERROR(IF(compras_mes2[[#This Row],[CUIT]]="","-",VLOOKUP(compras_mes2[[#This Row],[CUIT]],Lista_CUIT[#All],3,0)),"CUIT NO CARGADO") -> Productos Venta | R49: =IFERROR(IF(compras_mes2[[#This Row],[CUIT]]="","-",VLOOKUP(compras_mes2[[#This Row],[CUIT]],Lista_CUIT[#All],4,0)),"CUIT NO CARGADO") -> 0
B50: 18/02/2025 | C50: 1 | D50: 8 | E50: 3626 | F50: 20348424026 | G50: =IFERROR(IF(compras_mes2[[#This Row],[CUIT]]="","-",VLOOKUP(compras_mes2[[#This Row],[CUIT]],Lista_CUIT[#All],2,0)),"CUIT NO CARGADO") -> ALEXANDER DOUGLAS DROT DE GOURVILLE | H50: 17520.66 | I50: =IF(compras_mes2[[#This Row],[NETO GRAVADO]]="","",compras_mes2[[#This Row],[NETO GRAVADO]]*0.21) -> 3679.3386 | P50: =SUM(compras_mes2[[#This Row],[NETO GRAVADO]:[Otros / No Grav.]]) -> 21199.999 | Q50: =IFERROR(IF(compras_mes2[[#This Row],[CUIT]]="","-",VLOOKUP(compras_mes2[[#This Row],[CUIT]],Lista_CUIT[#All],3,0)),"CUIT NO CARGADO") -> Gastos Limpieza | R50: =IFERROR(IF(compras_mes2[[#This Row],[CUIT]]="","-",VLOOKUP(compras_mes2[[#This Row],[CUIT]],Lista_CUIT[#All],4,0)),"CUIT NO CARGADO") -> 0
B51: 13/02/2025 | C51: 1 | D51: 5 | E51: 30493 | F51: 30718509552 | G51: =IFERROR(IF(compras_mes2[[#This Row],[CUIT]]="","-",VLOOKUP(compras_mes2[[#This Row],[CUIT]],Lista_CUIT[#All],2,0)),"CUIT NO CARGADO") -> SEDAFE | H51: 32638.02 | I51: =IF(compras_mes2[[#This Row],[NETO GRAVADO]]="","",compras_mes2[[#This Row],[NETO GRAVADO]]*0.21) -> 6853.9842 | P51: =SUM(compras_mes2[[#This Row],[NETO GRAVADO]:[Otros / No Grav.]]) -> 39492.004 | Q51: =IFERROR(IF(compras_mes2[[#This Row],[CUIT]]="","-",VLOOKUP(compras_mes2[[#This Row],[CUIT]],Lista_CUIT[#All],3,0)),"CUIT NO CARGADO") -> Gastos Varios | R51: =IFERROR(IF(compras_mes2[[#This Row],[CUIT]]="","-",VLOOKUP(compras_mes2[[#This Row],[CUIT]],Lista_CUIT[#All],4,0)),"CUIT NO CARGADO") -> 0
B52: 18/02/2025 | C52: 1 | D52: 8 | E52: 3627 | F52: 20348424026 | G52: =IFERROR(IF(compras_mes2[[#This Row],[CUIT]]="","-",VLOOKUP(compras_mes2[[#This Row],[CUIT]],Lista_CUIT[#All],2,0)),"CUIT NO CARGADO") -> ALEXANDER DOUGLAS DROT DE GOURVILLE | H52: 17520.66 | I52: =IF(compras_mes2[[#This Row],[NETO GRAVADO]]="","",compras_mes2[[#This Row],[NETO GRAVADO]]*0.21) -> 3679.3386 | P52: =SUM(compras_mes2[[#This Row],[NETO GRAVADO]:[Otros / No Grav.]]) -> 21199.999 | Q52: =IFERROR(IF(compras_mes2[[#This Row],[CUIT]]="","-",VLOOKUP(compras_mes2[[#This Row],[CUIT]],Lista_CUIT[#All],3,0)),"CUIT NO CARGADO") -> Gastos Limpieza | R52: =IFERROR(IF(compras_mes2[[#This Row],[CUIT]]="","-",VLOOKUP(compras_mes2[[#This Row],[CUIT]],Lista_CUIT[#All],4,0)),"CUIT NO CARGADO") -> 0
B53: 14/02/2025 | C53: 1 | D53: 5722 | E53: 127831 | F53: 30639453738 | G53: =IFERROR(IF(compras_mes2[[#This Row],[CUIT]]="","-",VLOOKUP(compras_mes2[[#This Row],[CUIT]],Lista_CUIT[#All],2,0)),"CUIT NO CARGADO") -> TELECOM ARG SA | H53: 0.01 | I53: =IF(compras_mes2[[#This Row],[NETO GRAVADO]]="","",compras_mes2[[#This Row],[NETO GRAVADO]]*0.21) -> 0.0021 | P53: =SUM(compras_mes2[[#This Row],[NETO GRAVADO]:[Otros / No Grav.]]) -> 0.0121 | Q53: =IFERROR(IF(compras_mes2[[#This Row],[CUIT]]="","-",VLOOKUP(compras_mes2[[#This Row],[CUIT]],Lista_CUIT[#All],3,0)),"CUIT NO CARGADO") -> Servicios Gas, Luz, etc. | R53: =IFERROR(IF(compras_mes2[[#This Row],[CUIT]]="","-",VLOOKUP(compras_mes2[[#This Row],[CUIT]],Lista_CUIT[#All],4,0)),"CUIT NO CARGADO") -> 0
B54: 14/02/2025 | C54: 1 | D54: 3 | E54: 57718 | F54: 20349222923 | G54: =IFERROR(IF(compras_mes2[[#This Row],[CUIT]]="","-",VLOOKUP(compras_mes2[[#This Row],[CUIT]],Lista_CUIT[#All],2,0)),"CUIT NO CARGADO") -> RAUL GUILLERMO RODRIGUEZ | H54: 69020.83 | I54: =IF(compras_mes2[[#This Row],[NETO GRAVADO]]="","",compras_mes2[[#This Row],[NETO GRAVADO]]*0.21) -> 14494.374 | P54: =SUM(compras_mes2[[#This Row],[NETO GRAVADO]:[Otros / No Grav.]]) -> 83515.204 | Q54: =IFERROR(IF(compras_mes2[[#This Row],[CUIT]]="","-",VLOOKUP(compras_mes2[[#This Row],[CUIT]],Lista_CUIT[#All],3,0)),"CUIT NO CARGADO") -> Muebles y Utiles | R54: =IFERROR(IF(compras_mes2[[#This Row],[CUIT]]="","-",VLOOKUP(compras_mes2[[#This Row],[CUIT]],Lista_CUIT[#All],4,0)),"CUIT NO CARGADO") -> 0
B55: 14/02/2025 | C55: 1 | D55: 503 | E55: 1721638 | F55: 30639935872 | G55: =IFERROR(IF(compras_mes2[[#This Row],[CUIT]]="","-",VLOOKUP(compras_mes2[[#This Row],[CUIT]],Lista_CUIT[#All],2,0)),"CUIT NO CARGADO") -> CAMINOS DEL RIO URUGUAY S A DE CONSTRUCCIONES Y CONCESIONES VIALES | H55: 6104.82 | I55: =IF(compras_mes2[[#This Row],[NETO GRAVADO]]="","",compras_mes2[[#This Row],[NETO GRAVADO]]*0.21) -> 1282.0122 | N55: 366.29 | P55: =SUM(compras_mes2[[#This Row],[NETO GRAVADO]:[Otros / No Grav.]]) -> 7753.1222 | Q55: =IFERROR(IF(compras_mes2[[#This Row],[CUIT]]="","-",VLOOKUP(compras_mes2[[#This Row],[CUIT]],Lista_CUIT[#All],3,0)),"CUIT NO CARGADO") -> Peajes | R55: =IFERROR(IF(compras_mes2[[#This Row],[CUIT]]="","-",VLOOKUP(compras_mes2[[#This Row],[CUIT]],Lista_CUIT[#All],4,0)),"CUIT NO CARGADO") -> 0
B56: 19/02/2025 | C56: 1 | D56: 4 | E56: 4320 | F56: 20939155059 | G56: =IFERROR(IF(compras_mes2[[#This Row],[CUIT]]="","-",VLOOKUP(compras_mes2[[#This Row],[CUIT]],Lista_CUIT[#All],2,0)),"CUIT NO CARGADO") -> AGUERA MOLINA JUAN | H56: 65603.38 | I56: =IF(compras_mes2[[#This Row],[NETO GRAVADO]]="","",compras_mes2[[#This Row],[NETO GRAVADO]]*0.21) -> 13776.71 | P56: =SUM(compras_mes2[[#This Row],[NETO GRAVADO]:[Otros / No Grav.]]) -> 79380.09 | Q56: =IFERROR(IF(compras_mes2[[#This Row],[CUIT]]="","-",VLOOKUP(compras_mes2[[#This Row],[CUIT]],Lista_CUIT[#All],3,0)),"CUIT NO CARGADO") -> Gastos mantenimiento | R56: =IFERROR(IF(compras_mes2[[#This Row],[CUIT]]="","-",VLOOKUP(compras_mes2[[#This Row],[CUIT]],Lista_CUIT[#All],4,0)),"CUIT NO CARGADO") -> 0
B57: 14/02/2025 | C57: 1 | D57: 4 | E57: 251 | F57: 27317740196 | G57: =IFERROR(IF(compras_mes2[[#This Row],[CUIT]]="","-",VLOOKUP(compras_mes2[[#This Row],[CUIT]],Lista_CUIT[#All],2,0)),"CUIT NO CARGADO") -> HOKAMA ROMINA PAOLA | H57: 52998.35 | I57: =IF(compras_mes2[[#This Row],[NETO GRAVADO]]="","",compras_mes2[[#This Row],[NETO GRAVADO]]*0.21) -> 11129.653 | P57: =SUM(compras_mes2[[#This Row],[NETO GRAVADO]:[Otros / No Grav.]]) -> 64128.003 | Q57: =IFERROR(IF(compras_mes2[[#This Row],[CUIT]]="","-",VLOOKUP(compras_mes2[[#This Row],[CUIT]],Lista_CUIT[#All],3,0)),"CUIT NO CARGADO") -> Gastos Varios | R57: =IFERROR(IF(compras_mes2[[#This Row],[CUIT]]="","-",VLOOKUP(compras_mes2[[#This Row],[CUIT]],Lista_CUIT[#All],4,0)),"CUIT NO CARGADO") -> 0
B58: 14/02/2025 | C58: 1 | D58: 6852 | E58: 29316 | F58: 30678774495 | G58: =IFERROR(IF(compras_mes2[[#This Row],[CUIT]]="","-",VLOOKUP(compras_mes2[[#This Row],[CUIT]],Lista_CUIT[#All],2,0)),"CUIT NO CARGADO") -> OPER. DE EST. DE SERV. SA | H58: 8936.85 | I58: =IF(compras_mes2[[#This Row],[NETO GRAVADO]]="","",compras_mes2[[#This Row],[NETO GRAVADO]]*0.21) -> 1876.7385 | O58: 2193.39 | P58: =SUM(compras_mes2[[#This Row],[NETO GRAVADO]:[Otros / No Grav.]]) -> 13006.978 | Q58: =IFERROR(IF(compras_mes2[[#This Row],[CUIT]]="","-",VLOOKUP(compras_mes2[[#This Row],[CUIT]],Lista_CUIT[#All],3,0)),"CUIT NO CARGADO") -> Combustible | R58: =IFERROR(IF(compras_mes2[[#This Row],[CUIT]]="","-",VLOOKUP(compras_mes2[[#This Row],[CUIT]],Lista_CUIT[#All],4,0)),"CUIT NO CARGADO") -> 0
B59: 14/02/2025 | C59: 1 | D59: 11 | E59: 82901 | F59: 30534051049 | G59: =IFERROR(IF(compras_mes2[[#This Row],[CUIT]]="","-",VLOOKUP(compras_mes2[[#This Row],[CUIT]],Lista_CUIT[#All],2,0)),"CUIT NO CARGADO") -> PLIN METAL S A | H59: 16452.75 | I59: =IF(compras_mes2[[#This Row],[NETO GRAVADO]]="","",compras_mes2[[#This Row],[NETO GRAVADO]]*0.21) -> 3455.0775 | P59: =SUM(compras_mes2[[#This Row],[NETO GRAVADO]:[Otros / No Grav.]]) -> 19907.827 | Q59: =IFERROR(IF(compras_mes2[[#This Row],[CUIT]]="","-",VLOOKUP(compras_mes2[[#This Row],[CUIT]],Lista_CUIT[#All],3,0)),"CUIT NO CARGADO") -> Materia Prima | R59: =IFERROR(IF(compras_mes2[[#This Row],[CUIT]]="","-",VLOOKUP(compras_mes2[[#This Row],[CUIT]],Lista_CUIT[#All],4,0)),"CUIT NO CARGADO") -> 0
B60: 14/02/2025 | C60: 1 | D60: 50 | E60: 432997 | F60: 30610333822 | G60: =IFERROR(IF(compras_mes2[[#This Row],[CUIT]]="","-",VLOOKUP(compras_mes2[[#This Row],[CUIT]],Lista_CUIT[#All],2,0)),"CUIT NO CARGADO") -> MASIVOS S A | H60: 39190.08 | I60: =IF(compras_mes2[[#This Row],[NETO GRAVADO]]="","",compras_mes2[[#This Row],[NETO GRAVADO]]*0.21) -> 8229.9168 | P60: =SUM(compras_mes2[[#This Row],[NETO GRAVADO]:[Otros / No Grav.]]) -> 47419.997 | Q60: =IFERROR(IF(compras_mes2[[#This Row],[CUIT]]="","-",VLOOKUP(compras_mes2[[#This Row],[CUIT]],Lista_CUIT[#All],3,0)),"CUIT NO CARGADO") -> Gastos Varios | R60: =IFERROR(IF(compras_mes2[[#This Row],[CUIT]]="","-",VLOOKUP(compras_mes2[[#This Row],[CUIT]],Lista_CUIT[#All],4,0)),"CUIT NO CARGADO") -> 0
B61: 45702 | C61: 1 | D61: 9 | E61: 76453 | F61: 30696131003 | G61: =IFERROR(IF(compras_mes2[[#This Row],[CUIT]]="","-",VLOOKUP(compras_mes2[[#This Row],[CUIT]],Lista_CUIT[#All],2,0)),"CUIT NO CARGADO") -> Petrolfe S.A. | H61: 20936.81 | I61: =IF(compras_mes2[[#This Row],[NETO GRAVADO]]="","",compras_mes2[[#This Row],[NETO GRAVADO]]*0.21) -> 4396.7301 | O61: 7332.96 | P61: =SUM(compras_mes2[[#This Row],[NETO GRAVADO]:[Otros / No Grav.]]) -> 32666.5 | Q61: =IFERROR(IF(compras_mes2[[#This Row],[CUIT]]="","-",VLOOKUP(compras_mes2[[#This Row],[CUIT]],Lista_CUIT[#All],3,0)),"CUIT NO CARGADO") -> Combustible | R61: =IFERROR(IF(compras_mes2[[#This Row],[CUIT]]="","-",VLOOKUP(compras_mes2[[#This Row],[CUIT]],Lista_CUIT[#All],4,0)),"CUIT NO CARGADO") -> 0
B62: 45702 | C62: 1 | D62: 2 | E62: 3171692 | F62: 30640897267 | G62: =IFERROR(IF(compras_mes2[[#This Row],[CUIT]]="","-",VLOOKUP(compras_mes2[[#This Row],[CUIT]],Lista_CUIT[#All],2,0)),"CUIT NO CARGADO") -> TELECENTRO S.A. | H62: 58457.601 | I62: =IF(compras_mes2[[#This Row],[NETO GRAVADO]]="","",compras_mes2[[#This Row],[NETO GRAVADO]]*0.21) -> 12276.096 | L62: 3507.46 | N62: 1753.7299 | P62: =SUM(compras_mes2[[#This Row],[NETO GRAVADO]:[Otros / No Grav.]]) -> 75994.887 | Q62: =IFERROR(IF(compras_mes2[[#This Row],[CUIT]]="","-",VLOOKUP(compras_mes2[[#This Row],[CUIT]],Lista_CUIT[#All],3,0)),"CUIT NO CARGADO") -> Servicios Gas, Luz, etc. | R62: =IFERROR(IF(compras_mes2[[#This Row],[CUIT]]="","-",VLOOKUP(compras_mes2[[#This Row],[CUIT]],Lista_CUIT[#All],4,0)),"CUIT NO CARGADO") -> 0
B63: 45702 | C63: 1 | D63: 14 | E63: 19529510 | F63: 30655116202 | G63: =IFERROR(IF(compras_mes2[[#This Row],[CUIT]]="","-",VLOOKUP(compras_mes2[[#This Row],[CUIT]],Lista_CUIT[#All],2,0)),"CUIT NO CARGADO") -> EDENOR | H63: 105336.6 | J63: =compras_mes2[[#This Row],[NETO GRAVADO]]*0.27 -> 28440.883 | L63: 3160.1001 | O63: 6723.6401 | P63: =SUM(compras_mes2[[#This Row],[NETO GRAVADO]:[Otros / No Grav.]]) -> 143661.23 | Q63: =IFERROR(IF(compras_mes2[[#This Row],[CUIT]]="","-",VLOOKUP(compras_mes2[[#This Row],[CUIT]],Lista_CUIT[#All],3,0)),"CUIT NO CARGADO") -> Servicios Gas, Luz, etc. | R63: =IFERROR(IF(compras_mes2[[#This Row],[CUIT]]="","-",VLOOKUP(compras_mes2[[#This Row],[CUIT]],Lista_CUIT[#All],4,0)),"CUIT NO CARGADO") -> 0
B64: 15/02/2025 | C64: 1 | D64: 2084 | E64: 27426 | F64: 30548083156 | G64: =IFERROR(IF(compras_mes2[[#This Row],[CUIT]]="","-",VLOOKUP(compras_mes2[[#This Row],[CUIT]],Lista_CUIT[#All],2,0)),"CUIT NO CARGADO") -> COTO CENTRO INTEGRAL DE COMERCIALIZACION SOCIEDAD ANONIMA | H64: 58798.41 | I64: 7602.67 | K64: 2372.5 | O64: 3597.22 | P64: =SUM(compras_mes2[[#This Row],[NETO GRAVADO]:[Otros / No Grav.]]) -> 72370.8 | Q64: =IFERROR(IF(compras_mes2[[#This Row],[CUIT]]="","-",VLOOKUP(compras_mes2[[#This Row],[CUIT]],Lista_CUIT[#All],3,0)),"CUIT NO CARGADO") -> Gastos Varios | R64: =IFERROR(IF(compras_mes2[[#This Row],[CUIT]]="","-",VLOOKUP(compras_mes2[[#This Row],[CUIT]],Lista_CUIT[#All],4,0)),"CUIT NO CARGADO") -> 0
B65: 15/02/2025 | C65: 1 | D65: 5015 | E65: 748842 | F65: 30574876474 | G65: =IFERROR(IF(compras_mes2[[#This Row],[CUIT]]="","-",VLOOKUP(compras_mes2[[#This Row],[CUIT]],Lista_CUIT[#All],2,0)),"CUIT NO CARGADO") -> AUTOPISTAS URBANAS S A | H65: 41444.34 | I65: =IF(compras_mes2[[#This Row],[NETO GRAVADO]]="","",compras_mes2[[#This Row],[NETO GRAVADO]]*0.21) -> 8703.3114 | O65: 5387.76 | P65: =SUM(compras_mes2[[#This Row],[NETO GRAVADO]:[Otros / No Grav.]]) -> 55535.411 | Q65: =IFERROR(IF(compras_mes2[[#This Row],[CUIT]]="","-",VLOOKUP(compras_mes2[[#This Row],[CUIT]],Lista_CUIT[#All],3,0)),"CUIT NO CARGADO") -> Peajes | R65: =IFERROR(IF(compras_mes2[[#This Row],[CUIT]]="","-",VLOOKUP(compras_mes2[[#This Row],[CUIT]],Lista_CUIT[#All],4,0)),"CUIT NO CARGADO") -> 0
B66: 15/02/2025 | C66: 1 | D66: 103 | E66: 748031 | F66: 30701307115 | G66: =IFERROR(IF(compras_mes2[[#This Row],[CUIT]]="","-",VLOOKUP(compras_mes2[[#This Row],[CUIT]],Lista_CUIT[#All],2,0)),"CUIT NO CARGADO") -> DESPEGAR COM AR SA | H66: 100301 | I66: 2742.43 | K66: 9160.39 | N66: 7112.71 | O66: 12164.03 | P66: =SUM(compras_mes2[[#This Row],[NETO GRAVADO]:[Otros / No Grav.]]) -> 131480.56 | Q66: =IFERROR(IF(compras_mes2[[#This Row],[CUIT]]="","-",VLOOKUP(compras_mes2[[#This Row],[CUIT]],Lista_CUIT[#All],3,0)),"CUIT NO CARGADO") -> Gastos Varios | R66: =IFERROR(IF(compras_mes2[[#This Row],[CUIT]]="","-",VLOOKUP(compras_mes2[[#This Row],[CUIT]],Lista_CUIT[#All],4,0)),"CUIT NO CARGADO") -> 0
B67: 15/02/2025 | C67: 1 | D67: 50 | E67: 4132474 | F67: 30714112836 | G67: =IFERROR(IF(compras_mes2[[#This Row],[CUIT]]="","-",VLOOKUP(compras_mes2[[#This Row],[CUIT]],Lista_CUIT[#All],2,0)),"CUIT NO CARGADO") -> AUTOPISTAS DE BS AS | H67: 36205.91 | I67: =IF(compras_mes2[[#This Row],[NETO GRAVADO]]="","",compras_mes2[[#This Row],[NETO GRAVADO]]*0.21) -> 7603.2411 | L67: 1086.18 | P67: =SUM(compras_mes2[[#This Row],[NETO GRAVADO]:[Otros / No Grav.]]) -> 44895.331 | Q67: =IFERROR(IF(compras_mes2[[#This Row],[CUIT]]="","-",VLOOKUP(compras_mes2[[#This Row],[CUIT]],Lista_CUIT[#All],3,0)),"CUIT NO CARGADO") -> Peajes | R67: =IFERROR(IF(compras_mes2[[#This Row],[CUIT]]="","-",VLOOKUP(compras_mes2[[#This Row],[CUIT]],Lista_CUIT[#All],4,0)),"CUIT NO CARGADO") -> 0
B68: 15/02/2025 | C68: 1 | D68: 113 | E68: 4073690 | F68: 30577207190 | G68: =IFERROR(IF(compras_mes2[[#This Row],[CUIT]]="","-",VLOOKUP(compras_mes2[[#This Row],[CUIT]],Lista_CUIT[#All],2,0)),"CUIT NO CARGADO") -> COORDINACION ECOLOGICA AREA METROPOLITANA SOCIEDAD DEL ESTADO | H68: 3719.01 | I68: =IF(compras_mes2[[#This Row],[NETO GRAVADO]]="","",compras_mes2[[#This Row],[NETO GRAVADO]]*0.21) -> 780.9921 | L68: 111.57 | P68: =SUM(compras_mes2[[#This Row],[NETO GRAVADO]:[Otros / No Grav.]]) -> 4611.5721 | Q68: =IFERROR(IF(compras_mes2[[#This Row],[CUIT]]="","-",VLOOKUP(compras_mes2[[#This Row],[CUIT]],Lista_CUIT[#All],3,0)),"CUIT NO CARGADO") -> Gastos Limpieza | R68: =IFERROR(IF(compras_mes2[[#This Row],[CUIT]]="","-",VLOOKUP(compras_mes2[[#This Row],[CUIT]],Lista_CUIT[#All],4,0)),"CUIT NO CARGADO") -> 0
B69: 15/02/2025 | C69: 1 | D69: 3 | E69: 1965 | F69: 20320262195 | G69: =IFERROR(IF(compras_mes2[[#This Row],[CUIT]]="","-",VLOOKUP(compras_mes2[[#This Row],[CUIT]],Lista_CUIT[#All],2,0)),"CUIT NO CARGADO") -> FRAIRE MARIO ANDRES | H69: 37190.1 | I69: =IF(compras_mes2[[#This Row],[NETO GRAVADO]]="","",compras_mes2[[#This Row],[NETO GRAVADO]]*0.21) -> 7809.921 | P69: =SUM(compras_mes2[[#This Row],[NETO GRAVADO]:[Otros / No Grav.]]) -> 45000.021 | Q69: =IFERROR(IF(compras_mes2[[#This Row],[CUIT]]="","-",VLOOKUP(compras_mes2[[#This Row],[CUIT]],Lista_CUIT[#All],3,0)),"CUIT NO CARGADO") -> Material de Empaque | R69: =IFERROR(IF(compras_mes2[[#This Row],[CUIT]]="","-",VLOOKUP(compras_mes2[[#This Row],[CUIT]],Lista_CUIT[#All],4,0)),"CUIT NO CARGADO") -> 0
B70: 16/02/2025 | C70: 1 | D70: 711 | E70: 6755140 | F70: 30677237119 | G70: =IFERROR(IF(compras_mes2[[#This Row],[CUIT]]="","-",VLOOKUP(compras_mes2[[#This Row],[CUIT]],Lista_CUIT[#All],2,0)),"CUIT NO CARGADO") -> AUTOPISTAS DEL SOL S A | H70: 12999.78 | I70: =IF(compras_mes2[[#This Row],[NETO GRAVADO]]="","",compras_mes2[[#This Row],[NETO GRAVADO]]*0.21) -> 2729.9538 | L70: 389.99 | O70: 389.99 | P70: =SUM(compras_mes2[[#This Row],[NETO GRAVADO]:[Otros / No Grav.]]) -> 16509.714 | Q70: =IFERROR(IF(compras_mes2[[#This Row],[CUIT]]="","-",VLOOKUP(compras_mes2[[#This Row],[CUIT]],Lista_CUIT[#All],3,0)),"CUIT NO CARGADO") -> Peajes | R70: =IFERROR(IF(compras_mes2[[#This Row],[CUIT]]="","-",VLOOKUP(compras_mes2[[#This Row],[CUIT]],Lista_CUIT[#All],4,0)),"CUIT NO CARGADO") -> 0
B71: 16/02/2025 | C71: 1 | D71: 629 | E71: 5863119 | F71: 30663498513 | G71: =IFERROR(IF(compras_mes2[[#This Row],[CUIT]]="","-",VLOOKUP(compras_mes2[[#This Row],[CUIT]],Lista_CUIT[#All],2,0)),"CUIT NO CARGADO") -> GRUPO CONCES. DEL OESTE SA | H71: 17217.59 | I71: =IF(compras_mes2[[#This Row],[NETO GRAVADO]]="","",compras_mes2[[#This Row],[NETO GRAVADO]]*0.21) -> 3615.6939 | P71: =SUM(compras_mes2[[#This Row],[NETO GRAVADO]:[Otros / No Grav.]]) -> 20833.284 | Q71: =IFERROR(IF(compras_mes2[[#This Row],[CUIT]]="","-",VLOOKUP(compras_mes2[[#This Row],[CUIT]],Lista_CUIT[#All],3,0)),"CUIT NO CARGADO") -> Peajes | R71: =IFERROR(IF(compras_mes2[[#This Row],[CUIT]]="","-",VLOOKUP(compras_mes2[[#This Row],[CUIT]],Lista_CUIT[#All],4,0)),"CUIT NO CARGADO") -> 0
B72: 19/02/2025 | C72: 1 | D72: 2 | E72: 275 | F72: 23396559269 | G72: =IFERROR(IF(compras_mes2[[#This Row],[CUIT]]="","-",VLOOKUP(compras_mes2[[#This Row],[CUIT]],Lista_CUIT[#All],2,0)),"CUIT NO CARGADO") -> GODOY MATIAS NICOLAS | H72: 138099.14 | I72: =IF(compras_mes2[[#This Row],[NETO GRAVADO]]="","",compras_mes2[[#This Row],[NETO GRAVADO]]*0.21) -> 29000.819 | P72: =SUM(compras_mes2[[#This Row],[NETO GRAVADO]:[Otros / No Grav.]]) -> 167099.96 | Q72: =IFERROR(IF(compras_mes2[[#This Row],[CUIT]]="","-",VLOOKUP(compras_mes2[[#This Row],[CUIT]],Lista_CUIT[#All],3,0)),"CUIT NO CARGADO") -> Gastos mantenimiento | R72: =IFERROR(IF(compras_mes2[[#This Row],[CUIT]]="","-",VLOOKUP(compras_mes2[[#This Row],[CUIT]],Lista_CUIT[#All],4,0)),"CUIT NO CARGADO") -> 0
B73: 17/02/2025 | C73: 1 | D73: 4 | E73: 48893 | F73: 30709863076 | G73: =IFERROR(IF(compras_mes2[[#This Row],[CUIT]]="","-",VLOOKUP(compras_mes2[[#This Row],[CUIT]],Lista_CUIT[#All],2,0)),"CUIT NO CARGADO") -> INDUSTRIAS PLASTICOS SALTA S.R.L. | H73: 816375 | I73: =IF(compras_mes2[[#This Row],[NETO GRAVADO]]="","",compras_mes2[[#This Row],[NETO GRAVADO]]*0.21) -> 171438.75 | P73: =SUM(compras_mes2[[#This Row],[NETO GRAVADO]:[Otros / No Grav.]]) -> 987813.75 | Q73: =IFERROR(IF(compras_mes2[[#This Row],[CUIT]]="","-",VLOOKUP(compras_mes2[[#This Row],[CUIT]],Lista_CUIT[#All],3,0)),"CUIT NO CARGADO") -> Materia Prima | R73: =IFERROR(IF(compras_mes2[[#This Row],[CUIT]]="","-",VLOOKUP(compras_mes2[[#This Row],[CUIT]],Lista_CUIT[#All],4,0)),"CUIT NO CARGADO") -> 0
B74: 19/02/2025 | C74: 1 | D74: 2 | E74: 274 | F74: 23396559269 | G74: =IFERROR(IF(compras_mes2[[#This Row],[CUIT]]="","-",VLOOKUP(compras_mes2[[#This Row],[CUIT]],Lista_CUIT[#All],2,0)),"CUIT NO CARGADO") -> GODOY MATIAS NICOLAS | H74: 51799.14 | I74: =IF(compras_mes2[[#This Row],[NETO GRAVADO]]="","",compras_mes2[[#This Row],[NETO GRAVADO]]*0.21) -> 10877.819 | P74: =SUM(compras_mes2[[#This Row],[NETO GRAVADO]:[Otros / No Grav.]]) -> 62676.959 | Q74: =IFERROR(IF(compras_mes2[[#This Row],[CUIT]]="","-",VLOOKUP(compras_mes2[[#This Row],[CUIT]],Lista_CUIT[#All],3,0)),"CUIT NO CARGADO") -> Gastos mantenimiento | R74: =IFERROR(IF(compras_mes2[[#This Row],[CUIT]]="","-",VLOOKUP(compras_mes2[[#This Row],[CUIT]],Lista_CUIT[#All],4,0)),"CUIT NO CARGADO") -> 0
B75: 17/02/2025 | C75: 1 | D75: 14 | E75: 63810 | F75: 30711069360 | G75: =IFERROR(IF(compras_mes2[[#This Row],[CUIT]]="","-",VLOOKUP(compras_mes2[[#This Row],[CUIT]],Lista_CUIT[#All],2,0)),"CUIT NO CARGADO") -> BIDCOM SRL | H75: 55655.37 | K75: =compras_mes2[[#This Row],[NETO GRAVADO]]*0.105 -> 5843.8139 | P75: =SUM(compras_mes2[[#This Row],[NETO GRAVADO]:[Otros / No Grav.]]) -> 61499.184 | Q75: =IFERROR(IF(compras_mes2[[#This Row],[CUIT]]="","-",VLOOKUP(compras_mes2[[#This Row],[CUIT]],Lista_CUIT[#All],3,0)),"CUIT NO CARGADO") -> Gastos Varios | R75: =IFERROR(IF(compras_mes2[[#This Row],[CUIT]]="","-",VLOOKUP(compras_mes2[[#This Row],[CUIT]],Lista_CUIT[#All],4,0)),"CUIT NO CARGADO") -> 0
B76: 17/02/2025 | C76: 1 | D76: 14 | E76: 16140 | F76: 30715186256 | G76: =IFERROR(IF(compras_mes2[[#This Row],[CUIT]]="","-",VLOOKUP(compras_mes2[[#This Row],[CUIT]],Lista_CUIT[#All],2,0)),"CUIT NO CARGADO") -> FRIGORIFICO ALIMENTIC | H76: 68355.39 | I76: 5306.41 | K76: 4524.11 | P76: =SUM(compras_mes2[[#This Row],[NETO GRAVADO]:[Otros / No Grav.]]) -> 78185.91 | Q76: =IFERROR(IF(compras_mes2[[#This Row],[CUIT]]="","-",VLOOKUP(compras_mes2[[#This Row],[CUIT]],Lista_CUIT[#All],3,0)),"CUIT NO CARGADO") -> Gastos Comercializacion - Feria | R76: =IFERROR(IF(compras_mes2[[#This Row],[CUIT]]="","-",VLOOKUP(compras_mes2[[#This Row],[CUIT]],Lista_CUIT[#All],4,0)),"CUIT NO CARGADO") -> 0
B77: 17/02/2025 | C77: 1 | D77: 4264 | E77: 4995862 | F77: 30639453738 | G77: =IFERROR(IF(compras_mes2[[#This Row],[CUIT]]="","-",VLOOKUP(compras_mes2[[#This Row],[CUIT]],Lista_CUIT[#All],2,0)),"CUIT NO CARGADO") -> TELECOM ARG SA | H77: 28760 | I77: =IF(compras_mes2[[#This Row],[NETO GRAVADO]]="","",compras_mes2[[#This Row],[NETO GRAVADO]]*0.21) -> 6039.6 | N77: 2588.4 | P77: =SUM(compras_mes2[[#This Row],[NETO GRAVADO]:[Otros / No Grav.]]) -> 37388 | Q77: =IFERROR(IF(compras_mes2[[#This Row],[CUIT]]="","-",VLOOKUP(compras_mes2[[#This Row],[CUIT]],Lista_CUIT[#All],3,0)),"CUIT NO CARGADO") -> Servicios Gas, Luz, etc. | R77: =IFERROR(IF(compras_mes2[[#This Row],[CUIT]]="","-",VLOOKUP(compras_mes2[[#This Row],[CUIT]],Lista_CUIT[#All],4,0)),"CUIT NO CARGADO") -> 0
B78: 17/02/2025 | C78: 1 | D78: 4264 | E78: 4957843 | F78: 30639453738 | G78: =IFERROR(IF(compras_mes2[[#This Row],[CUIT]]="","-",VLOOKUP(compras_mes2[[#This Row],[CUIT]],Lista_CUIT[#All],2,0)),"CUIT NO CARGADO") -> TELECOM ARG SA | H78: 19010 | I78: =IF(compras_mes2[[#This Row],[NETO GRAVADO]]="","",compras_mes2[[#This Row],[NETO GRAVADO]]*0.21) -> 3992.1 | N78: 570.3 | P78: =SUM(compras_mes2[[#This Row],[NETO GRAVADO]:[Otros / No Grav.]]) -> 23572.4 | Q78: =IFERROR(IF(compras_mes2[[#This Row],[CUIT]]="","-",VLOOKUP(compras_mes2[[#This Row],[CUIT]],Lista_CUIT[#All],3,0)),"CUIT NO CARGADO") -> Servicios Gas, Luz, etc. | R78: =IFERROR(IF(compras_mes2[[#This Row],[CUIT]]="","-",VLOOKUP(compras_mes2[[#This Row],[CUIT]],Lista_CUIT[#All],4,0)),"CUIT NO CARGADO") -> 0
B79: 17/02/2025 | C79: 1 | D79: 3 | E79: 10073 | F79: 27412102431 | G79: =IFERROR(IF(compras_mes2[[#This Row],[CUIT]]="","-",VLOOKUP(compras_mes2[[#This Row],[CUIT]],Lista_CUIT[#All],2,0)),"CUIT NO CARGADO") -> ALVEZ ARIANA SOL | H79: 71487.62 | I79: =IF(compras_mes2[[#This Row],[NETO GRAVADO]]="","",compras_mes2[[#This Row],[NETO GRAVADO]]*0.21) -> 15012.4 | P79: =SUM(compras_mes2[[#This Row],[NETO GRAVADO]:[Otros / No Grav.]]) -> 86500.02 | Q79: =IFERROR(IF(compras_mes2[[#This Row],[CUIT]]="","-",VLOOKUP(compras_mes2[[#This Row],[CUIT]],Lista_CUIT[#All],3,0)),"CUIT NO CARGADO") -> Software Mantenimiento | R79: =IFERROR(IF(compras_mes2[[#This Row],[CUIT]]="","-",VLOOKUP(compras_mes2[[#This Row],[CUIT]],Lista_CUIT[#All],4,0)),"CUIT NO CARGADO") -> 0
B80: 17/02/2025 | C80: 1 | D80: 2 | E80: 3961 | F80: 30629863571 | G80: =IFERROR(IF(compras_mes2[[#This Row],[CUIT]]="","-",VLOOKUP(compras_mes2[[#This Row],[CUIT]],Lista_CUIT[#All],2,0)),"CUIT NO CARGADO") -> TECNIMAR S R L | H80: 376793.24 | I80: =IF(compras_mes2[[#This Row],[NETO GRAVADO]]="","",compras_mes2[[#This Row],[NETO GRAVADO]]*0.21) -> 79126.58 | P80: =SUM(compras_mes2[[#This Row],[NETO GRAVADO]:[Otros / No Grav.]]) -> 455919.82 | Q80: =IFERROR(IF(compras_mes2[[#This Row],[CUIT]]="","-",VLOOKUP(compras_mes2[[#This Row],[CUIT]],Lista_CUIT[#All],3,0)),"CUIT NO CARGADO") -> Productos Venta | R80: =IFERROR(IF(compras_mes2[[#This Row],[CUIT]]="","-",VLOOKUP(compras_mes2[[#This Row],[CUIT]],Lista_CUIT[#All],4,0)),"CUIT NO CARGADO") -> 0
B81: 18/02/2025 | C81: 1 | D81: 15 | E81: 90963 | F81: 33708907869 | G81: =IFERROR(IF(compras_mes2[[#This Row],[CUIT]]="","-",VLOOKUP(compras_mes2[[#This Row],[CUIT]],Lista_CUIT[#All],2,0)),"CUIT NO CARGADO") -> SERCAP INSUMOS SRL | H81: 66573.76 | K81: =compras_mes2[[#This Row],[NETO GRAVADO]]*0.105 -> 6990.2448 | P81: =SUM(compras_mes2[[#This Row],[NETO GRAVADO]:[Otros / No Grav.]]) -> 73564.005 | Q81: =IFERROR(IF(compras_mes2[[#This Row],[CUIT]]="","-",VLOOKUP(compras_mes2[[#This Row],[CUIT]],Lista_CUIT[#All],3,0)),"CUIT NO CARGADO") -> Gastos Varios | R81: =IFERROR(IF(compras_mes2[[#This Row],[CUIT]]="","-",VLOOKUP(compras_mes2[[#This Row],[CUIT]],Lista_CUIT[#All],4,0)),"CUIT NO CARGADO") -> 0
B82: 18/02/2025 | C82: 1 | D82: 8 | E82: 2391 | F82: 20277381908 | G82: =IFERROR(IF(compras_mes2[[#This Row],[CUIT]]="","-",VLOOKUP(compras_mes2[[#This Row],[CUIT]],Lista_CUIT[#All],2,0)),"CUIT NO CARGADO") -> ALONSO RODRIGO JAVIER | H82: 59504.13 | I82: =IF(compras_mes2[[#This Row],[NETO GRAVADO]]="","",compras_mes2[[#This Row],[NETO GRAVADO]]*0.21) -> 12495.867 | P82: =SUM(compras_mes2[[#This Row],[NETO GRAVADO]:[Otros / No Grav.]]) -> 71999.997 | Q82: =IFERROR(IF(compras_mes2[[#This Row],[CUIT]]="","-",VLOOKUP(compras_mes2[[#This Row],[CUIT]],Lista_CUIT[#All],3,0)),"CUIT NO CARGADO") -> Gastos Varios | R82: =IFERROR(IF(compras_mes2[[#This Row],[CUIT]]="","-",VLOOKUP(compras_mes2[[#This Row],[CUIT]],Lista_CUIT[#All],4,0)),"CUIT NO CARGADO") -> 0
B83: 19/02/2025 | C83: 1 | D83: 2 | E83: 273 | F83: 23396559269 | G83: =IFERROR(IF(compras_mes2[[#This Row],[CUIT]]="","-",VLOOKUP(compras_mes2[[#This Row],[CUIT]],Lista_CUIT[#All],2,0)),"CUIT NO CARGADO") -> GODOY MATIAS NICOLAS | H83: 51799.14 | I83: =IF(compras_mes2[[#This Row],[NETO GRAVADO]]="","",compras_mes2[[#This Row],[NETO GRAVADO]]*0.21) -> 10877.819 | P83: =SUM(compras_mes2[[#This Row],[NETO GRAVADO]:[Otros / No Grav.]]) -> 62676.959 | Q83: =IFERROR(IF(compras_mes2[[#This Row],[CUIT]]="","-",VLOOKUP(compras_mes2[[#This Row],[CUIT]],Lista_CUIT[#All],3,0)),"CUIT NO CARGADO") -> Gastos mantenimiento | R83: =IFERROR(IF(compras_mes2[[#This Row],[CUIT]]="","-",VLOOKUP(compras_mes2[[#This Row],[CUIT]],Lista_CUIT[#All],4,0)),"CUIT NO CARGADO") -> 0
B84: 19/02/2025 | C84: 3 | D84: 2 | E84: 7 | F84: 23396559269 | G84: =IFERROR(IF(compras_mes2[[#This Row],[CUIT]]="","-",VLOOKUP(compras_mes2[[#This Row],[CUIT]],Lista_CUIT[#All],2,0)),"CUIT NO CARGADO") -> GODOY MATIAS NICOLAS | H84: -51799.14 | I84: =IF(compras_mes2[[#This Row],[NETO GRAVADO]]="","",compras_mes2[[#This Row],[NETO GRAVADO]]*0.21) -> -10877.819 | P84: =SUM(compras_mes2[[#This Row],[NETO GRAVADO]:[Otros / No Grav.]]) -> -62676.959 | Q84: =IFERROR(IF(compras_mes2[[#This Row],[CUIT]]="","-",VLOOKUP(compras_mes2[[#This Row],[CUIT]],Lista_CUIT[#All],3,0)),"CUIT NO CARGADO") -> Gastos mantenimiento | R84: =IFERROR(IF(compras_mes2[[#This Row],[CUIT]]="","-",VLOOKUP(compras_mes2[[#This Row],[CUIT]],Lista_CUIT[#All],4,0)),"CUIT NO CARGADO") -> 0
B85: 19/02/2025 | C85: 3 | D85: 2 | E85: 6 | F85: 23396559269 | G85: =IFERROR(IF(compras_mes2[[#This Row],[CUIT]]="","-",VLOOKUP(compras_mes2[[#This Row],[CUIT]],Lista_CUIT[#All],2,0)),"CUIT NO CARGADO") -> GODOY MATIAS NICOLAS | H85: -51799.14 | I85: =IF(compras_mes2[[#This Row],[NETO GRAVADO]]="","",compras_mes2[[#This Row],[NETO GRAVADO]]*0.21) -> -10877.819 | P85: =SUM(compras_mes2[[#This Row],[NETO GRAVADO]:[Otros / No Grav.]]) -> -62676.959 | Q85: =IFERROR(IF(compras_mes2[[#This Row],[CUIT]]="","-",VLOOKUP(compras_mes2[[#This Row],[CUIT]],Lista_CUIT[#All],3,0)),"CUIT NO CARGADO") -> Gastos mantenimiento | R85: =IFERROR(IF(compras_mes2[[#This Row],[CUIT]]="","-",VLOOKUP(compras_mes2[[#This Row],[CUIT]],Lista_CUIT[#All],4,0)),"CUIT NO CARGADO") -> 0
B86: 18/02/2025 | C86: 1 | D86: 2 | E86: 3962 | F86: 30629863571 | G86: =IFERROR(IF(compras_mes2[[#This Row],[CUIT]]="","-",VLOOKUP(compras_mes2[[#This Row],[CUIT]],Lista_CUIT[#All],2,0)),"CUIT NO CARGADO") -> TECNIMAR S R L | H86: 4091058.7 | I86: =IF(compras_mes2[[#This Row],[NETO GRAVADO]]="","",compras_mes2[[#This Row],[NETO GRAVADO]]*0.21) -> 859122.33 | P86: =SUM(compras_mes2[[#This Row],[NETO GRAVADO]:[Otros / No Grav.]]) -> 4950181 | Q86: =IFERROR(IF(compras_mes2[[#This Row],[CUIT]]="","-",VLOOKUP(compras_mes2[[#This Row],[CUIT]],Lista_CUIT[#All],3,0)),"CUIT NO CARGADO") -> Productos Venta | R86: =IFERROR(IF(compras_mes2[[#This Row],[CUIT]]="","-",VLOOKUP(compras_mes2[[#This Row],[CUIT]],Lista_CUIT[#All],4,0)),"CUIT NO CARGADO") -> 0
B87: 25/02/2025 | C87: 1 | D87: 4 | E87: 97 | F87: 27061895642 | G87: =IFERROR(IF(compras_mes2[[#This Row],[CUIT]]="","-",VLOOKUP(compras_mes2[[#This Row],[CUIT]],Lista_CUIT[#All],2,0)),"CUIT NO CARGADO") -> BUSATTO ELSA MARIA | H87: 30000 | I87: =IF(compras_mes2[[#This Row],[NETO GRAVADO]]="","",compras_mes2[[#This Row],[NETO GRAVADO]]*0.21) -> 6300 | P87: =SUM(compras_mes2[[#This Row],[NETO GRAVADO]:[Otros / No Grav.]]) -> 36300 | Q87: =IFERROR(IF(compras_mes2[[#This Row],[CUIT]]="","-",VLOOKUP(compras_mes2[[#This Row],[CUIT]],Lista_CUIT[#All],3,0)),"CUIT NO CARGADO") -> Gastos seguridad | R87: =IFERROR(IF(compras_mes2[[#This Row],[CUIT]]="","-",VLOOKUP(compras_mes2[[#This Row],[CUIT]],Lista_CUIT[#All],4,0)),"CUIT NO CARGADO") -> 0
B88: 19/02/2025 | C88: 1 | D88: 2188 | E88: 142084 | F88: 30548083156 | G88: =IFERROR(IF(compras_mes2[[#This Row],[CUIT]]="","-",VLOOKUP(compras_mes2[[#This Row],[CUIT]],Lista_CUIT[#All],2,0)),"CUIT NO CARGADO") -> COTO CENTRO INTEGRAL DE COMERCIALIZACION SOCIEDAD ANONIMA | H88: 66983.76 | I88: 12065.51 | K88: 1000.54 | O88: 5235.65 | P88: =SUM(compras_mes2[[#This Row],[NETO GRAVADO]:[Otros / No Grav.]]) -> 85285.46 | Q88: =IFERROR(IF(compras_mes2[[#This Row],[CUIT]]="","-",VLOOKUP(compras_mes2[[#This Row],[CUIT]],Lista_CUIT[#All],3,0)),"CUIT NO CARGADO") -> Gastos Varios | R88: =IFERROR(IF(compras_mes2[[#This Row],[CUIT]]="","-",VLOOKUP(compras_mes2[[#This Row],[CUIT]],Lista_CUIT[#All],4,0)),"CUIT NO CARGADO") -> 0
B89: 19/02/2025 | C89: 1 | D89: 1 | E89: 349 | F89: 27386627695 | G89: =IFERROR(IF(compras_mes2[[#This Row],[CUIT]]="","-",VLOOKUP(compras_mes2[[#This Row],[CUIT]],Lista_CUIT[#All],2,0)),"CUIT NO CARGADO") -> CANAVIDE JIMENA PAOLA | H89: 659073.57 | I89: =IF(compras_mes2[[#This Row],[NETO GRAVADO]]="","",compras_mes2[[#This Row],[NETO GRAVADO]]*0.21) -> 138405.45 | P89: =SUM(compras_mes2[[#This Row],[NETO GRAVADO]:[Otros / No Grav.]]) -> 797479.02 | Q89: =IFERROR(IF(compras_mes2[[#This Row],[CUIT]]="","-",VLOOKUP(compras_mes2[[#This Row],[CUIT]],Lista_CUIT[#All],3,0)),"CUIT NO CARGADO") -> Muebles y Utiles | R89: =IFERROR(IF(compras_mes2[[#This Row],[CUIT]]="","-",VLOOKUP(compras_mes2[[#This Row],[CUIT]],Lista_CUIT[#All],4,0)),"CUIT NO CARGADO") -> 0
B90: 17/02/2025 | C90: 1 | D90: 8 | E90: 30518 | F90: 30542071741 | G90: =IFERROR(IF(compras_mes2[[#This Row],[CUIT]]="","-",VLOOKUP(compras_mes2[[#This Row],[CUIT]],Lista_CUIT[#All],2,0)),"CUIT NO CARGADO") -> VALLS SOCIEDAD ANONIMA | H90: 720358.8 | I90: 36672.04 | K90: 57301.65 | P90: =SUM(compras_mes2[[#This Row],[NETO GRAVADO]:[Otros / No Grav.]]) -> 814332.49 | Q90: =IFERROR(IF(compras_mes2[[#This Row],[CUIT]]="","-",VLOOKUP(compras_mes2[[#This Row],[CUIT]],Lista_CUIT[#All],3,0)),"CUIT NO CARGADO") -> Gastos seguridad | R90: =IFERROR(IF(compras_mes2[[#This Row],[CUIT]]="","-",VLOOKUP(compras_mes2[[#This Row],[CUIT]],Lista_CUIT[#All],4,0)),"CUIT NO CARGADO") -> 0
B91: 28/02/2025 | C91: 1 | D91: 32 | E91: 6228 | F91: 30633413629 | G91: =IFERROR(IF(compras_mes2[[#This Row],[CUIT]]="","-",VLOOKUP(compras_mes2[[#This Row],[CUIT]],Lista_CUIT[#All],2,0)),"CUIT NO CARGADO") -> TRANSPORTE RAOSA SRL | H91: 12186.19 | I91: =IF(compras_mes2[[#This Row],[NETO GRAVADO]]="","",compras_mes2[[#This Row],[NETO GRAVADO]]*0.21) -> 2559.0999 | P91: =SUM(compras_mes2[[#This Row],[NETO GRAVADO]:[Otros / No Grav.]]) -> 14745.29 | Q91: =IFERROR(IF(compras_mes2[[#This Row],[CUIT]]="","-",VLOOKUP(compras_mes2[[#This Row],[CUIT]],Lista_CUIT[#All],3,0)),"CUIT NO CARGADO") -> Flete | R91: =IFERROR(IF(compras_mes2[[#This Row],[CUIT]]="","-",VLOOKUP(compras_mes2[[#This Row],[CUIT]],Lista_CUIT[#All],4,0)),"CUIT NO CARGADO") -> 0
B92: 28/02/2025 | C92: 1 | D92: 5 | E92: 12030 | F92: 30710166834 | G92: =IFERROR(IF(compras_mes2[[#This Row],[CUIT]]="","-",VLOOKUP(compras_mes2[[#This Row],[CUIT]],Lista_CUIT[#All],2,0)),"CUIT NO CARGADO") -> CILUX S.R.L. | H92: 66338.97 | I92: =IF(compras_mes2[[#This Row],[NETO GRAVADO]]="","",compras_mes2[[#This Row],[NETO GRAVADO]]*0.21) -> 13931.184 | P92: =SUM(compras_mes2[[#This Row],[NETO GRAVADO]:[Otros / No Grav.]]) -> 80270.154 | Q92: =IFERROR(IF(compras_mes2[[#This Row],[CUIT]]="","-",VLOOKUP(compras_mes2[[#This Row],[CUIT]],Lista_CUIT[#All],3,0)),"CUIT NO CARGADO") -> Gastos mantenimiento | R92: =IFERROR(IF(compras_mes2[[#This Row],[CUIT]]="","-",VLOOKUP(compras_mes2[[#This Row],[CUIT]],Lista_CUIT[#All],4,0)),"CUIT NO CARGADO") -> 0
B93: 25/02/2025 | C93: 1 | D93: 5 | E93: 23647 | F93: 30710677227 | G93: =IFERROR(IF(compras_mes2[[#This Row],[CUIT]]="","-",VLOOKUP(compras_mes2[[#This Row],[CUIT]],Lista_CUIT[#All],2,0)),"CUIT NO CARGADO") -> CINE 24 SRL | H93: 65452.56 | I93: =IF(compras_mes2[[#This Row],[NETO GRAVADO]]="","",compras_mes2[[#This Row],[NETO GRAVADO]]*0.21) -> 13745.038 | P93: =SUM(compras_mes2[[#This Row],[NETO GRAVADO]:[Otros / No Grav.]]) -> 79197.598 | Q93: =IFERROR(IF(compras_mes2[[#This Row],[CUIT]]="","-",VLOOKUP(compras_mes2[[#This Row],[CUIT]],Lista_CUIT[#All],3,0)),"CUIT NO CARGADO") -> Gastos Limpieza | R93: =IFERROR(IF(compras_mes2[[#This Row],[CUIT]]="","-",VLOOKUP(compras_mes2[[#This Row],[CUIT]],Lista_CUIT[#All],4,0)),"CUIT NO CARGADO") -> 0
B94: 01/02/2025 | C94: 1 | D94: 3 | E94: 340 | F94: 30714239321 | G94: =IFERROR(IF(compras_mes2[[#This Row],[CUIT]]="","-",VLOOKUP(compras_mes2[[#This Row],[CUIT]],Lista_CUIT[#All],2,0)),"CUIT NO CARGADO") -> DINAMANU SRL | H94: 1009489 | I94: =IF(compras_mes2[[#This Row],[NETO GRAVADO]]="","",compras_mes2[[#This Row],[NETO GRAVADO]]*0.21) -> 211992.69 | P94: =SUM(compras_mes2[[#This Row],[NETO GRAVADO]:[Otros / No Grav.]]) -> 1221481.7 | Q94: =IFERROR(IF(compras_mes2[[#This Row],[CUIT]]="","-",VLOOKUP(compras_mes2[[#This Row],[CUIT]],Lista_CUIT[#All],3,0)),"CUIT NO CARGADO") -> Alquiler? | R94: =IFERROR(IF(compras_mes2[[#This Row],[CUIT]]="","-",VLOOKUP(compras_mes2[[#This Row],[CUIT]],Lista_CUIT[#All],4,0)),"CUIT NO CARGADO") -> 0
B95: 01/02/2025 | C95: 3 | D95: 3 | E95: 17 | F95: 30714239321 | G95: =IFERROR(IF(compras_mes2[[#This Row],[CUIT]]="","-",VLOOKUP(compras_mes2[[#This Row],[CUIT]],Lista_CUIT[#All],2,0)),"CUIT NO CARGADO") -> DINAMANU SRL | H95: -1009489 | I95: =IF(compras_mes2[[#This Row],[NETO GRAVADO]]="","",compras_mes2[[#This Row],[NETO GRAVADO]]*0.21) -> -211992.69 | P95: =SUM(compras_mes2[[#This Row],[NETO GRAVADO]:[Otros / No Grav.]]) -> -1221481.7 | Q95: =IFERROR(IF(compras_mes2[[#This Row],[CUIT]]="","-",VLOOKUP(compras_mes2[[#This Row],[CUIT]],Lista_CUIT[#All],3,0)),"CUIT NO CARGADO") -> Alquiler? | R95: =IFERROR(IF(compras_mes2[[#This Row],[CUIT]]="","-",VLOOKUP(compras_mes2[[#This Row],[CUIT]],Lista_CUIT[#All],4,0)),"CUIT NO CARGADO") -> 0
B96: 20/02/2025 | C96: 1 | D96: 700 | E96: 2279499 | F96: 30715804812 | G96: =IFERROR(IF(compras_mes2[[#This Row],[CUIT]]="","-",VLOOKUP(compras_mes2[[#This Row],[CUIT]],Lista_CUIT[#All],2,0)),"CUIT NO CARGADO") -> CORREDORES VIALES SOCIEDAD ANONIMA | H96: 5407.9 | I96: =IF(compras_mes2[[#This Row],[NETO GRAVADO]]="","",compras_mes2[[#This Row],[NETO GRAVADO]]*0.21) -> 1135.659 | P96: =SUM(compras_mes2[[#This Row],[NETO GRAVADO]:[Otros / No Grav.]]) -> 6543.559 | Q96: =IFERROR(IF(compras_mes2[[#This Row],[CUIT]]="","-",VLOOKUP(compras_mes2[[#This Row],[CUIT]],Lista_CUIT[#All],3,0)),"CUIT NO CARGADO") -> Peajes | R96: =IFERROR(IF(compras_mes2[[#This Row],[CUIT]]="","-",VLOOKUP(compras_mes2[[#This Row],[CUIT]],Lista_CUIT[#All],4,0)),"CUIT NO CARGADO") -> 0
B97: 20/02/2025 | C97: 1 | D97: 2 | E97: 3963 | F97: 30629863571 | G97: =IFERROR(IF(compras_mes2[[#This Row],[CUIT]]="","-",VLOOKUP(compras_mes2[[#This Row],[CUIT]],Lista_CUIT[#All],2,0)),"CUIT NO CARGADO") -> TECNIMAR S R L | H97: 1991402.2 | I97: =IF(compras_mes2[[#This Row],[NETO GRAVADO]]="","",compras_mes2[[#This Row],[NETO GRAVADO]]*0.21) -> 418194.47 | P97: =SUM(compras_mes2[[#This Row],[NETO GRAVADO]:[Otros / No Grav.]]) -> 2409596.7 | Q97: =IFERROR(IF(compras_mes2[[#This Row],[CUIT]]="","-",VLOOKUP(compras_mes2[[#This Row],[CUIT]],Lista_CUIT[#All],3,0)),"CUIT NO CARGADO") -> Productos Venta | R97: =IFERROR(IF(compras_mes2[[#This Row],[CUIT]]="","-",VLOOKUP(compras_mes2[[#This Row],[CUIT]],Lista_CUIT[#All],4,0)),"CUIT NO CARGADO") -> 0
B98: 45708 | C98: 1 | D98: 501 | E98: 2137978 | F98: 30655116512 | G98: =IFERROR(IF(compras_mes2[[#This Row],[CUIT]]="","-",VLOOKUP(compras_mes2[[#This Row],[CUIT]],Lista_CUIT[#All],2,0)),"CUIT NO CARGADO") -> Empresa Distribuidora Sur S.A. | H98: 277415.2 | J98: =compras_mes2[[#This Row],[NETO GRAVADO]]*0.27 -> 74902.103 | O98: 16696.38 | P98: =SUM(compras_mes2[[#This Row],[NETO GRAVADO]:[Otros / No Grav.]]) -> 369013.68 | Q98: =IFERROR(IF(compras_mes2[[#This Row],[CUIT]]="","-",VLOOKUP(compras_mes2[[#This Row],[CUIT]],Lista_CUIT[#All],3,0)),"CUIT NO CARGADO") -> Servicios Gas, Luz, etc. | R98: =IFERROR(IF(compras_mes2[[#This Row],[CUIT]]="","-",VLOOKUP(compras_mes2[[#This Row],[CUIT]],Lista_CUIT[#All],4,0)),"CUIT NO CARGADO") -> 0
B99: 45708 | C99: 1 | D99: 501 | E99: 2137979 | F99: 30655116512 | G99: =IFERROR(IF(compras_mes2[[#This Row],[CUIT]]="","-",VLOOKUP(compras_mes2[[#This Row],[CUIT]],Lista_CUIT[#All],2,0)),"CUIT NO CARGADO") -> Empresa Distribuidora Sur S.A. | H99: 105629.4 | J99: =compras_mes2[[#This Row],[NETO GRAVADO]]*0.27 -> 28519.937 | L99: 3168.8799 | O99: 5731.3 | P99: =SUM(compras_mes2[[#This Row],[NETO GRAVADO]:[Otros / No Grav.]]) -> 143049.51 | Q99: =IFERROR(IF(compras_mes2[[#This Row],[CUIT]]="","-",VLOOKUP(compras_mes2[[#This Row],[CUIT]],Lista_CUIT[#All],3,0)),"CUIT NO CARGADO") -> Servicios Gas, Luz, etc. | R99: =IFERROR(IF(compras_mes2[[#This Row],[CUIT]]="","-",VLOOKUP(compras_mes2[[#This Row],[CUIT]],Lista_CUIT[#All],4,0)),"CUIT NO CARGADO") -> 0
B100: 21/02/2025 | C100: 1 | D100: 5 | E100: 3233807 | F100: 30702652975 | G100: =IFERROR(IF(compras_mes2[[#This Row],[CUIT]]="","-",VLOOKUP(compras_mes2[[#This Row],[CUIT]],Lista_CUIT[#All],2,0)),"CUIT NO CARGADO") -> NSS SA | H100: 29946.48 | I100: =IF(compras_mes2[[#This Row],[NETO GRAVADO]]="","",compras_mes2[[#This Row],[NETO GRAVADO]]*0.21) -> 6288.7608 | O100: 1796.79 | P100: =SUM(compras_mes2[[#This Row],[NETO GRAVADO]:[Otros / No Grav.]]) -> 38032.031 | Q100: =IFERROR(IF(compras_mes2[[#This Row],[CUIT]]="","-",VLOOKUP(compras_mes2[[#This Row],[CUIT]],Lista_CUIT[#All],3,0)),"CUIT NO CARGADO") -> Servicios Gas, Luz, etc. | R100: =IFERROR(IF(compras_mes2[[#This Row],[CUIT]]="","-",VLOOKUP(compras_mes2[[#This Row],[CUIT]],Lista_CUIT[#All],4,0)),"CUIT NO CARGADO") -> 0
B101: 21/02/2025 | C101: 1 | D101: 45 | E101: 51 | F101: 30500795804 | G101: =IFERROR(IF(compras_mes2[[#This Row],[CUIT]]="","-",VLOOKUP(compras_mes2[[#This Row],[CUIT]],Lista_CUIT[#All],2,0)),"CUIT NO CARGADO") -> SATURNINO CABEZON S A | H101: 42396.69 | I101: =IF(compras_mes2[[#This Row],[NETO GRAVADO]]="","",compras_mes2[[#This Row],[NETO GRAVADO]]*0.21) -> 8903.3049 | P101: =SUM(compras_mes2[[#This Row],[NETO GRAVADO]:[Otros / No Grav.]]) -> 51299.995 | Q101: =IFERROR(IF(compras_mes2[[#This Row],[CUIT]]="","-",VLOOKUP(compras_mes2[[#This Row],[CUIT]],Lista_CUIT[#All],3,0)),"CUIT NO CARGADO") -> Gastos Varios | R101: =IFERROR(IF(compras_mes2[[#This Row],[CUIT]]="","-",VLOOKUP(compras_mes2[[#This Row],[CUIT]],Lista_CUIT[#All],4,0)),"CUIT NO CARGADO") -> 0
B102: 14/02/2025 | C102: 1 | D102: 15 | E102: 28413 | F102: 30714295957 | G102: =IFERROR(IF(compras_mes2[[#This Row],[CUIT]]="","-",VLOOKUP(compras_mes2[[#This Row],[CUIT]],Lista_CUIT[#All],2,0)),"CUIT NO CARGADO") -> IT BROKERS SA | H102: 70735.54 | I102: =IF(compras_mes2[[#This Row],[NETO GRAVADO]]="","",compras_mes2[[#This Row],[NETO GRAVADO]]*0.21) -> 14854.463 | N102: 4244.13 | P102: =SUM(compras_mes2[[#This Row],[NETO GRAVADO]:[Otros / No Grav.]]) -> 89834.133 | Q102: =IFERROR(IF(compras_mes2[[#This Row],[CUIT]]="","-",VLOOKUP(compras_mes2[[#This Row],[CUIT]],Lista_CUIT[#All],3,0)),"CUIT NO CARGADO") -> Muebles y Utiles | R102: =IFERROR(IF(compras_mes2[[#This Row],[CUIT]]="","-",VLOOKUP(compras_mes2[[#This Row],[CUIT]],Lista_CUIT[#All],4,0)),"CUIT NO CARGADO") -> 0
...

Sheet Mar-25
B1: LIBRO IVA COMPRAS | G1: ='Ene-25'!G1:M1 -> EUROARGENTINA | N1: =EDATE('Ene-25'!N1,2) -> 45717
B3: TOTAL COMPRAS | G3: TOTAL CREDITO FISCAL | J3: TOTAL VENTAS NETAS | M3: TOTAL DEBITO FISCAL | P3: RESULTADO
B4: =SUM(compras_mes3[[#Totals],[NETO GRAVADO]])+extracto_banco_mes3[[#Totals],[NETO]] -> 78599549 | G4: =compras_mes3[[#Totals],[IVA 21 %]]+compras_mes3[[#Totals],[IVA 27%]]+compras_mes3[[#Totals],[IVA 10,5%]]+extracto_banco_mes3[[#Totals],[IVA 21%]]+extracto_banco_mes3[[#Totals],[IVA 10,5%]] -> 16012910 | J4: =venta_a_mes3[[#Totals],[IMPORTE NETO]]+ventas_b_mes3[[#Totals],[IMPORTE NETO]] -> 0 | M4: =venta_a_mes3[[#Totals],[IVA 21%]]+venta_a_mes3[[#Totals],[IVA 10,5%]]+ventas_b_mes3[[#Totals],[IVA 21%]]+ventas_b_mes3[[#Totals],[IVA 10,5%]] -> 0 | P4: =G4-M4 -> 16012910
B8: FECHA | C8: TIPO | D8: PTO VTA | E8: NRO. CPTE | F8: CUIT | G8: RAZON SOCIAL | H8: NETO GRAVADO | I8: IVA 21 % | J8: IVA 27% | K8: IVA 10,5% | L8: PERC. IVA | M8: PERC IIBB BS AS | N8: PERC. IIBB CABA | O8: Otros / No Grav. | P8: TOTAL | Q8: Tipo de Gasto | R8: Provincia
B9: 04/03/2025 | C9: 1 | D9: 8 | E9: 2452 | F9: 20277381908 | G9: =IFERROR(IF(compras_mes3[[#This Row],[CUIT]]="","-",VLOOKUP(compras_mes3[[#This Row],[CUIT]],Lista_CUIT[#All],2,0)),"CUIT NO CARGADO") -> ALONSO RODRIGO JAVIER | H9: 68760.33 | I9: =compras_mes3[[#This Row],[NETO GRAVADO]]*0.21 -> 14439.669 | P9: =SUM(compras_mes3[[#This Row],[NETO GRAVADO]:[Otros / No Grav.]]) -> 83199.999 | Q9: =IFERROR(IF(compras_mes3[[#This Row],[CUIT]]="","-",VLOOKUP(compras_mes3[[#This Row],[CUIT]],Lista_CUIT[#All],3,0)),"CUIT NO CARGADO") -> Gastos Varios | R9: =IFERROR(IF(compras_mes3[[#This Row],[CUIT]]="","-",VLOOKUP(compras_mes3[[#This Row],[CUIT]],Lista_CUIT[#All],4,0)),"CUIT NO CARGADO") -> 0
B10: 13/03/2025 | C10: 1 | D10: 3 | E10: 10154 | F10: 27412102431 | G10: =IFERROR(IF(compras_mes3[[#This Row],[CUIT]]="","-",VLOOKUP(compras_mes3[[#This Row],[CUIT]],Lista_CUIT[#All],2,0)),"CUIT NO CARGADO") -> ALVEZ ARIANA SOL | H10: 89223.14 | I10: =compras_mes3[[#This Row],[NETO GRAVADO]]*0.21 -> 18736.859 | P10: =SUM(compras_mes3[[#This Row],[NETO GRAVADO]:[Otros / No Grav.]]) -> 107960 | Q10: =IFERROR(IF(compras_mes3[[#This Row],[CUIT]]="","-",VLOOKUP(compras_mes3[[#This Row],[CUIT]],Lista_CUIT[#All],3,0)),"CUIT NO CARGADO") -> Software Mantenimiento | R10: =IFERROR(IF(compras_mes3[[#This Row],[CUIT]]="","-",VLOOKUP(compras_mes3[[#This Row],[CUIT]],Lista_CUIT[#All],4,0)),"CUIT NO CARGADO") -> 0
B11: 31/03/2025 | C11: 1 | D11: 50 | E11: 4243302 | F11: 30714112836 | G11: =IFERROR(IF(compras_mes3[[#This Row],[CUIT]]="","-",VLOOKUP(compras_mes3[[#This Row],[CUIT]],Lista_CUIT[#All],2,0)),"CUIT NO CARGADO") -> AUTOPISTAS DE BS AS | H11: 53227.3 | I11: =compras_mes3[[#This Row],[NETO GRAVADO]]*0.21 -> 11177.733 | L11: 1596.82 | P11: =SUM(compras_mes3[[#This Row],[NETO GRAVADO]:[Otros / No Grav.]]) -> 66001.853 | Q11: =IFERROR(IF(compras_mes3[[#This Row],[CUIT]]="","-",VLOOKUP(compras_mes3[[#This Row],[CUIT]],Lista_CUIT[#All],3,0)),"CUIT NO CARGADO") -> Peajes | R11: =IFERROR(IF(compras_mes3[[#This Row],[CUIT]]="","-",VLOOKUP(compras_mes3[[#This Row],[CUIT]],Lista_CUIT[#All],4,0)),"CUIT NO CARGADO") -> 0
B12: 15/03/2025 | C12: 1 | D12: 50 | E12: 4206585 | F12: 30714112836 | G12: =IFERROR(IF(compras_mes3[[#This Row],[CUIT]]="","-",VLOOKUP(compras_mes3[[#This Row],[CUIT]],Lista_CUIT[#All],2,0)),"CUIT NO CARGADO") -> AUTOPISTAS DE BS AS | H12: 39874.78 | I12: =compras_mes3[[#This Row],[NETO GRAVADO]]*0.21 -> 8373.7038 | L12: 1196.24 | P12: =SUM(compras_mes3[[#This Row],[NETO GRAVADO]:[Otros / No Grav.]]) -> 49444.724 | Q12: =IFERROR(IF(compras_mes3[[#This Row],[CUIT]]="","-",VLOOKUP(compras_mes3[[#This Row],[CUIT]],Lista_CUIT[#All],3,0)),"CUIT NO CARGADO") -> Peajes | R12: =IFERROR(IF(compras_mes3[[#This Row],[CUIT]]="","-",VLOOKUP(compras_mes3[[#This Row],[CUIT]],Lista_CUIT[#All],4,0)),"CUIT NO CARGADO") -> 0
B13: 01/03/2025 | C13: 1 | D13: 711 | E13: 6814102 | F13: 30677237119 | G13: =IFERROR(IF(compras_mes3[[#This Row],[CUIT]]="","-",VLOOKUP(compras_mes3[[#This Row],[CUIT]],Lista_CUIT[#All],2,0)),"CUIT NO CARGADO") -> AUTOPISTAS DEL SOL S A | H13: 11208.67 | I13: =compras_mes3[[#This Row],[NETO GRAVADO]]*0.21 -> 2353.8207 | L13: 336.26 | O13: 336.26 | P13: =SUM(compras_mes3[[#This Row],[NETO GRAVADO]:[Otros / No Grav.]]) -> 14235.011 | Q13: =IFERROR(IF(compras_mes3[[#This Row],[CUIT]]="","-",VLOOKUP(compras_mes3[[#This Row],[CUIT]],Lista_CUIT[#All],3,0)),"CUIT NO CARGADO") -> Peajes | R13: =IFERROR(IF(compras_mes3[[#This Row],[CUIT]]="","-",VLOOKUP(compras_mes3[[#This Row],[CUIT]],Lista_CUIT[#All],4,0)),"CUIT NO CARGADO") -> 0
B14: 16/03/2025 | C14: 1 | D14: 711 | E14: 6872526 | F14: 30677237119 | G14: =IFERROR(IF(compras_mes3[[#This Row],[CUIT]]="","-",VLOOKUP(compras_mes3[[#This Row],[CUIT]],Lista_CUIT[#All],2,0)),"CUIT NO CARGADO") -> AUTOPISTAS DEL SOL S A | H14: 10573.09 | I14: =compras_mes3[[#This Row],[NETO GRAVADO]]*0.21 -> 2220.3489 | L14: 317.19 | O14: 317.19 | P14: =SUM(compras_mes3[[#This Row],[NETO GRAVADO]:[Otros / No Grav.]]) -> 13427.819 | Q14: =IFERROR(IF(compras_mes3[[#This Row],[CUIT]]="","-",VLOOKUP(compras_mes3[[#This Row],[CUIT]],Lista_CUIT[#All],3,0)),"CUIT NO CARGADO") -> Peajes | R14: =IFERROR(IF(compras_mes3[[#This Row],[CUIT]]="","-",VLOOKUP(compras_mes3[[#This Row],[CUIT]],Lista_CUIT[#All],4,0)),"CUIT NO CARGADO") -> 0
B15: 31/03/2025 | C15: 1 | D15: 5015 | E15: 802257 | F15: 30574876474 | G15: =IFERROR(IF(compras_mes3[[#This Row],[CUIT]]="","-",VLOOKUP(compras_mes3[[#This Row],[CUIT]],Lista_CUIT[#All],2,0)),"CUIT NO CARGADO") -> AUTOPISTAS URBANAS S A | H15: 132464.07 | I15: =compras_mes3[[#This Row],[NETO GRAVADO]]*0.21 -> 27817.455 | O15: 17220.28 | P15: =SUM(compras_mes3[[#This Row],[NETO GRAVADO]:[Otros / No Grav.]]) -> 177501.8 | Q15: =IFERROR(IF(compras_mes3[[#This Row],[CUIT]]="","-",VLOOKUP(compras_mes3[[#This Row],[CUIT]],Lista_CUIT[#All],3,0)),"CUIT NO CARGADO") -> Peajes | R15: =IFERROR(IF(compras_mes3[[#This Row],[CUIT]]="","-",VLOOKUP(compras_mes3[[#This Row],[CUIT]],Lista_CUIT[#All],4,0)),"CUIT NO CARGADO") -> 0
B16: 15/03/2025 | C16: 1 | D16: 5015 | E16: 782068 | F16: 30574876474 | G16: =IFERROR(IF(compras_mes3[[#This Row],[CUIT]]="","-",VLOOKUP(compras_mes3[[#This Row],[CUIT]],Lista_CUIT[#All],2,0)),"CUIT NO CARGADO") -> AUTOPISTAS URBANAS S A | H16: 114941.7 | I16: =compras_mes3[[#This Row],[NETO GRAVADO]]*0.21 -> 24137.757 | O16: 14942.39 | P16: =SUM(compras_mes3[[#This Row],[NETO GRAVADO]:[Otros / No Grav.]]) -> 154021.85 | Q16: =IFERROR(IF(compras_mes3[[#This Row],[CUIT]]="","-",VLOOKUP(compras_mes3[[#This Row],[CUIT]],Lista_CUIT[#All],3,0)),"CUIT NO CARGADO") -> Peajes | R16: =IFERROR(IF(compras_mes3[[#This Row],[CUIT]]="","-",VLOOKUP(compras_mes3[[#This Row],[CUIT]],Lista_CUIT[#All],4,0)),"CUIT NO CARGADO") -> 0
B17: 23/03/2025 | C17: 1 | D17: 5015 | E17: 795254 | F17: 30574876474 | G17: =IFERROR(IF(compras_mes3[[#This Row],[CUIT]]="","-",VLOOKUP(compras_mes3[[#This Row],[CUIT]],Lista_CUIT[#All],2,0)),"CUIT NO CARGADO") -> AUTOPISTAS URBANAS S A | H17: 85345.81 | I17: =compras_mes3[[#This Row],[NETO GRAVADO]]*0.21 -> 17922.62 | O17: 11095.16 | P17: =SUM(compras_mes3[[#This Row],[NETO GRAVADO]:[Otros / No Grav.]]) -> 114363.59 | Q17: =IFERROR(IF(compras_mes3[[#This Row],[CUIT]]="","-",VLOOKUP(compras_mes3[[#This Row],[CUIT]],Lista_CUIT[#All],3,0)),"CUIT NO CARGADO") -> Peajes | R17: =IFERROR(IF(compras_mes3[[#This Row],[CUIT]]="","-",VLOOKUP(compras_mes3[[#This Row],[CUIT]],Lista_CUIT[#All],4,0)),"CUIT NO CARGADO") -> 0
B18: 08/03/2025 | C18: 1 | D18: 5015 | E18: 779008 | F18: 30574876474 | G18: =IFERROR(IF(compras_mes3[[#This Row],[CUIT]]="","-",VLOOKUP(compras_mes3[[#This Row],[CUIT]],Lista_CUIT[#All],2,0)),"CUIT NO CARGADO") -> AUTOPISTAS URBANAS S A | H18: 64477.81 | I18: =compras_mes3[[#This Row],[NETO GRAVADO]]*0.21 -> 13540.34 | O18: 8382.1 | P18: =SUM(compras_mes3[[#This Row],[NETO GRAVADO]:[Otros / No Grav.]]) -> 86400.25 | Q18: =IFERROR(IF(compras_mes3[[#This Row],[CUIT]]="","-",VLOOKUP(compras_mes3[[#This Row],[CUIT]],Lista_CUIT[#All],3,0)),"CUIT NO CARGADO") -> Peajes | R18: =IFERROR(IF(compras_mes3[[#This Row],[CUIT]]="","-",VLOOKUP(compras_mes3[[#This Row],[CUIT]],Lista_CUIT[#All],4,0)),"CUIT NO CARGADO") -> 0
B19: 25/03/2025 | C19: 1 | D19: 30 | E19: 183850 | F19: 30695056342 | G19: =IFERROR(IF(compras_mes3[[#This Row],[CUIT]]="","-",VLOOKUP(compras_mes3[[#This Row],[CUIT]],Lista_CUIT[#All],2,0)),"CUIT NO CARGADO") -> AVENIDA MAIPU 4199 S C S | H19: 10366.94 | I19: =compras_mes3[[#This Row],[NETO GRAVADO]]*0.21 -> 2177.0574 | P19: =SUM(compras_mes3[[#This Row],[NETO GRAVADO]:[Otros / No Grav.]]) -> 12543.997 | Q19: =IFERROR(IF(compras_mes3[[#This Row],[CUIT]]="","-",VLOOKUP(compras_mes3[[#This Row],[CUIT]],Lista_CUIT[#All],3,0)),"CUIT NO CARGADO") -> Gastos Cosmetica | R19: =IFERROR(IF(compras_mes3[[#This Row],[CUIT]]="","-",VLOOKUP(compras_mes3[[#This Row],[CUIT]],Lista_CUIT[#All],4,0)),"CUIT NO CARGADO") -> 0
B20: 45733 | C20: 1 | D20: 106 | E20: 10303761 | F20: 30709565075 | G20: =IFERROR(IF(compras_mes3[[#This Row],[CUIT]]="","-",VLOOKUP(compras_mes3[[#This Row],[CUIT]],Lista_CUIT[#All],2,0)),"CUIT NO CARGADO") -> AYSA S.A | H20: 85708.685 | J20: =compras_mes3[[#This Row],[NETO GRAVADO]]*0.27 -> 23141.345 | L20: 2571.26 | O20: 1534.1899 | P20: =SUM(compras_mes3[[#This Row],[NETO GRAVADO]:[Otros / No Grav.]]) -> 112955.48 | Q20: =IFERROR(IF(compras_mes3[[#This Row],[CUIT]]="","-",VLOOKUP(compras_mes3[[#This Row],[CUIT]],Lista_CUIT[#All],3,0)),"CUIT NO CARGADO") -> Servicios Gas, Luz, etc. | R20: =IFERROR(IF(compras_mes3[[#This Row],[CUIT]]="","-",VLOOKUP(compras_mes3[[#This Row],[CUIT]],Lista_CUIT[#All],4,0)),"CUIT NO CARGADO") -> 0
B21: 45729 | C21: 1 | D21: 110 | E21: 54731370 | F21: 30709565075 | G21: =IFERROR(IF(compras_mes3[[#This Row],[CUIT]]="","-",VLOOKUP(compras_mes3[[#This Row],[CUIT]],Lista_CUIT[#All],2,0)),"CUIT NO CARGADO") -> AYSA S.A | H21: 32933.557 | I21: =compras_mes3[[#This Row],[NETO GRAVADO]]*0.21 -> 6916.047 | O21: 589.51001 | P21: =SUM(compras_mes3[[#This Row],[NETO GRAVADO]:[Otros / No Grav.]]) -> 40439.114 | Q21: =IFERROR(IF(compras_mes3[[#This Row],[CUIT]]="","-",VLOOKUP(compras_mes3[[#This Row],[CUIT]],Lista_CUIT[#All],3,0)),"CUIT NO CARGADO") -> Servicios Gas, Luz, etc. | R21: =IFERROR(IF(compras_mes3[[#This Row],[CUIT]]="","-",VLOOKUP(compras_mes3[[#This Row],[CUIT]],Lista_CUIT[#All],4,0)),"CUIT NO CARGADO") -> 0
B22: 06/03/2025 | C22: 1 | D22: 2 | E22: 296 | F22: 27309896063 | G22: =IFERROR(IF(compras_mes3[[#This Row],[CUIT]]="","-",VLOOKUP(compras_mes3[[#This Row],[CUIT]],Lista_CUIT[#All],2,0)),"CUIT NO CARGADO") -> BATTELLINI MARIA SOLEDAD | H22: 550000 | I22: =compras_mes3[[#This Row],[NETO GRAVADO]]*0.21 -> 115500 | P22: =SUM(compras_mes3[[#This Row],[NETO GRAVADO]:[Otros / No Grav.]]) -> 665500 | Q22: =IFERROR(IF(compras_mes3[[#This Row],[CUIT]]="","-",VLOOKUP(compras_mes3[[#This Row],[CUIT]],Lista_CUIT[#All],3,0)),"CUIT NO CARGADO") -> Alquiler | R22: =IFERROR(IF(compras_mes3[[#This Row],[CUIT]]="","-",VLOOKUP(compras_mes3[[#This Row],[CUIT]],Lista_CUIT[#All],4,0)),"CUIT NO CARGADO") -> 0
B23: 29/03/2025 | C23: 1 | D23: 503 | E23: 1799272 | F23: 30639935872 | G23: =IFERROR(IF(compras_mes3[[#This Row],[CUIT]]="","-",VLOOKUP(compras_mes3[[#This Row],[CUIT]],Lista_CUIT[#All],2,0)),"CUIT NO CARGADO") -> CAMINOS DEL RIO URUGUAY S A DE CONSTRUCCIONES Y CONCESIONES VIALES | H23: 3471.36 | I23: =compras_mes3[[#This Row],[NETO GRAVADO]]*0.21 -> 728.9856 | N23: 208.28 | P23: =SUM(compras_mes3[[#This Row],[NETO GRAVADO]:[Otros / No Grav.]]) -> 4408.6256 | Q23: =IFERROR(IF(compras_mes3[[#This Row],[CUIT]]="","-",VLOOKUP(compras_mes3[[#This Row],[CUIT]],Lista_CUIT[#All],3,0)),"CUIT NO CARGADO") -> Peajes | R23: =IFERROR(IF(compras_mes3[[#This Row],[CUIT]]="","-",VLOOKUP(compras_mes3[[#This Row],[CUIT]],Lista_CUIT[#All],4,0)),"CUIT NO CARGADO") -> 0
B24: 09/03/2025 | C24: 1 | D24: 4 | E24: 33 | F24: 20262815367 | G24: =IFERROR(IF(compras_mes3[[#This Row],[CUIT]]="","-",VLOOKUP(compras_mes3[[#This Row],[CUIT]],Lista_CUIT[#All],2,0)),"CUIT NO CARGADO") -> CARDARELLO BASAVILBASO FEDERICO JORGE | H24: 13388.43 | I24: =compras_mes3[[#This Row],[NETO GRAVADO]]*0.21 -> 2811.5703 | P24: =SUM(compras_mes3[[#This Row],[NETO GRAVADO]:[Otros / No Grav.]]) -> 16200 | Q24: =IFERROR(IF(compras_mes3[[#This Row],[CUIT]]="","-",VLOOKUP(compras_mes3[[#This Row],[CUIT]],Lista_CUIT[#All],3,0)),"CUIT NO CARGADO") -> Gastos Varios | R24: =IFERROR(IF(compras_mes3[[#This Row],[CUIT]]="","-",VLOOKUP(compras_mes3[[#This Row],[CUIT]],Lista_CUIT[#All],4,0)),"CUIT NO CARGADO") -> 0
B25: 10/03/2025 | C25: 1 | D25: 6 | E25: 7518 | F25: 30717381242 | G25: =IFERROR(IF(compras_mes3[[#This Row],[CUIT]]="","-",VLOOKUP(compras_mes3[[#This Row],[CUIT]],Lista_CUIT[#All],2,0)),"CUIT NO CARGADO") -> CASA MAYO GROUP S.R.L. | H25: 88085.95 | I25: =compras_mes3[[#This Row],[NETO GRAVADO]]*0.21 -> 18498.049 | P25: =SUM(compras_mes3[[#This Row],[NETO GRAVADO]:[Otros / No Grav.]]) -> 106584 | Q25: =IFERROR(IF(compras_mes3[[#This Row],[CUIT]]="","-",VLOOKUP(compras_mes3[[#This Row],[CUIT]],Lista_CUIT[#All],3,0)),"CUIT NO CARGADO") -> Material de Empaque | R25: =IFERROR(IF(compras_mes3[[#This Row],[CUIT]]="","-",VLOOKUP(compras_mes3[[#This Row],[CUIT]],Lista_CUIT[#All],4,0)),"CUIT NO CARGADO") -> 0
B26: 19/03/2025 | C26: 1 | D26: 6 | E26: 7586 | F26: 30717381242 | G26: =IFERROR(IF(compras_mes3[[#This Row],[CUIT]]="","-",VLOOKUP(compras_mes3[[#This Row],[CUIT]],Lista_CUIT[#All],2,0)),"CUIT NO CARGADO") -> CASA MAYO GROUP S.R.L. | H26: 83882.64 | I26: =compras_mes3[[#This Row],[NETO GRAVADO]]*0.21 -> 17615.354 | P26: =SUM(compras_mes3[[#This Row],[NETO GRAVADO]:[Otros / No Grav.]]) -> 101497.99 | Q26: =IFERROR(IF(compras_mes3[[#This Row],[CUIT]]="","-",VLOOKUP(compras_mes3[[#This Row],[CUIT]],Lista_CUIT[#All],3,0)),"CUIT NO CARGADO") -> Material de Empaque | R26: =IFERROR(IF(compras_mes3[[#This Row],[CUIT]]="","-",VLOOKUP(compras_mes3[[#This Row],[CUIT]],Lista_CUIT[#All],4,0)),"CUIT NO CARGADO") -> 0
B27: 15/03/2025 | C27: 1 | D27: 8823 | E27: 7750 | F27: 30590360763 | G27: =IFERROR(IF(compras_mes3[[#This Row],[CUIT]]="","-",VLOOKUP(compras_mes3[[#This Row],[CUIT]],Lista_CUIT[#All],2,0)),"CUIT NO CARGADO") -> CENCOSUD S.A | H27: 5780.99 | I27: =compras_mes3[[#This Row],[NETO GRAVADO]]*0.21 -> 1214.0079 | L27: 173.43 | N27: 346.86 | P27: =SUM(compras_mes3[[#This Row],[NETO GRAVADO]:[Otros / No Grav.]]) -> 7515.2879 | Q27: =IFERROR(IF(compras_mes3[[#This Row],[CUIT]]="","-",VLOOKUP(compras_mes3[[#This Row],[CUIT]],Lista_CUIT[#All],3,0)),"CUIT NO CARGADO") -> Gastos Varios | R27: =IFERROR(IF(compras_mes3[[#This Row],[CUIT]]="","-",VLOOKUP(compras_mes3[[#This Row],[CUIT]],Lista_CUIT[#All],4,0)),"CUIT NO CARGADO") -> 0
B28: 25/03/2025 | C28: 1 | D28: 9 | E28: 2835 | F28: 30715683446 | G28: =IFERROR(IF(compras_mes3[[#This Row],[CUIT]]="","-",VLOOKUP(compras_mes3[[#This Row],[CUIT]],Lista_CUIT[#All],2,0)),"CUIT NO CARGADO") -> CENTRAL MAYORISTA S R L | H28: 4578.33 | I28: =compras_mes3[[#This Row],[NETO GRAVADO]]*0.21 -> 961.4493 | P28: =SUM(compras_mes3[[#This Row],[NETO GRAVADO]:[Otros / No Grav.]]) -> 5539.7793 | Q28: =IFERROR(IF(compras_mes3[[#This Row],[CUIT]]="","-",VLOOKUP(compras_mes3[[#This Row],[CUIT]],Lista_CUIT[#All],3,0)),"CUIT NO CARGADO") -> LIBRERÍA | R28: =IFERROR(IF(compras_mes3[[#This Row],[CUIT]]="","-",VLOOKUP(compras_mes3[[#This Row],[CUIT]],Lista_CUIT[#All],4,0)),"CUIT NO CARGADO") -> 0
B29: 01/03/2025 | C29: 1 | D29: 1 | E29: 594 | F29: 20131206144 | G29: =IFERROR(IF(compras_mes3[[#This Row],[CUIT]]="","-",VLOOKUP(compras_mes3[[#This Row],[CUIT]],Lista_CUIT[#All],2,0)),"CUIT NO CARGADO") -> CHAMORRO MANUEL | H29: 1009489 | I29: =compras_mes3[[#This Row],[NETO GRAVADO]]*0.21 -> 211992.69 | P29: =SUM(compras_mes3[[#This Row],[NETO GRAVADO]:[Otros / No Grav.]]) -> 1221481.7 | Q29: =IFERROR(IF(compras_mes3[[#This Row],[CUIT]]="","-",VLOOKUP(compras_mes3[[#This Row],[CUIT]],Lista_CUIT[#All],3,0)),"CUIT NO CARGADO") -> Alquiler | R29: =IFERROR(IF(compras_mes3[[#This Row],[CUIT]]="","-",VLOOKUP(compras_mes3[[#This Row],[CUIT]],Lista_CUIT[#All],4,0)),"CUIT NO CARGADO") -> 0
B30: 10/03/2025 | C30: 1 | D30: 5 | E30: 14698 | F30: 30717970787 | G30: =IFERROR(IF(compras_mes3[[#This Row],[CUIT]]="","-",VLOOKUP(compras_mes3[[#This Row],[CUIT]],Lista_CUIT[#All],2,0)),"CUIT NO CARGADO") -> CIUDAD DE JUEGOS S. R. L. | H30: 390406.33 | K30: =compras_mes3[[#This Row],[NETO GRAVADO]]*0.105 -> 40992.665 | P30: =SUM(compras_mes3[[#This Row],[NETO GRAVADO]:[Otros / No Grav.]]) -> 431398.99 | Q30: =IFERROR(IF(compras_mes3[[#This Row],[CUIT]]="","-",VLOOKUP(compras_mes3[[#This Row],[CUIT]],Lista_CUIT[#All],3,0)),"CUIT NO CARGADO") -> Gastos Oficina | R30: =IFERROR(IF(compras_mes3[[#This Row],[CUIT]]="","-",VLOOKUP(compras_mes3[[#This Row],[CUIT]],Lista_CUIT[#All],4,0)),"CUIT NO CARGADO") -> 0
B31: 10/03/2025 | C31: 1 | D31: 6 | E31: 3466 | F31: 30574603788 | G31: =IFERROR(IF(compras_mes3[[#This Row],[CUIT]]="","-",VLOOKUP(compras_mes3[[#This Row],[CUIT]],Lista_CUIT[#All],2,0)),"CUIT NO CARGADO") -> CODAC SRL | H31: 2810077 | I31: =compras_mes3[[#This Row],[NETO GRAVADO]]*0.21 -> 590116.17 | P31: =SUM(compras_mes3[[#This Row],[NETO GRAVADO]:[Otros / No Grav.]]) -> 3400193.2 | Q31: =IFERROR(IF(compras_mes3[[#This Row],[CUIT]]="","-",VLOOKUP(compras_mes3[[#This Row],[CUIT]],Lista_CUIT[#All],3,0)),"CUIT NO CARGADO") -> Productos Venta | R31: =IFERROR(IF(compras_mes3[[#This Row],[CUIT]]="","-",VLOOKUP(compras_mes3[[#This Row],[CUIT]],Lista_CUIT[#All],4,0)),"CUIT NO CARGADO") -> BUENOS AIRES
B32: 05/03/2025 | C32: 1 | D32: 6 | E32: 3461 | F32: 30574603788 | G32: =IFERROR(IF(compras_mes3[[#This Row],[CUIT]]="","-",VLOOKUP(compras_mes3[[#This Row],[CUIT]],Lista_CUIT[#All],2,0)),"CUIT NO CARGADO") -> CODAC SRL | H32: 557336 | I32: =compras_mes3[[#This Row],[NETO GRAVADO]]*0.21 -> 117040.56 | P32: =SUM(compras_mes3[[#This Row],[NETO GRAVADO]:[Otros / No Grav.]]) -> 674376.56 | Q32: =IFERROR(IF(compras_mes3[[#This Row],[CUIT]]="","-",VLOOKUP(compras_mes3[[#This Row],[CUIT]],Lista_CUIT[#All],3,0)),"CUIT NO CARGADO") -> Productos Venta | R32: =IFERROR(IF(compras_mes3[[#This Row],[CUIT]]="","-",VLOOKUP(compras_mes3[[#This Row],[CUIT]],Lista_CUIT[#All],4,0)),"CUIT NO CARGADO") -> BUENOS AIRES
B33: 15/03/2025 | C33: 1 | D33: 113 | E33: 4124114 | F33: 30577207190 | G33: =IFERROR(IF(compras_mes3[[#This Row],[CUIT]]="","-",VLOOKUP(compras_mes3[[#This Row],[CUIT]],Lista_CUIT[#All],2,0)),"CUIT NO CARGADO") -> COORDINACION ECOLOGICA AREA METROPOLITANA SOCIEDAD DEL ESTADO | H33: 3719.01 | I33: =compras_mes3[[#This Row],[NETO GRAVADO]]*0.21 -> 780.9921 | L33: 111.57 | P33: =SUM(compras_mes3[[#This Row],[NETO GRAVADO]:[Otros / No Grav.]]) -> 4611.5721 | Q33: =IFERROR(IF(compras_mes3[[#This Row],[CUIT]]="","-",VLOOKUP(compras_mes3[[#This Row],[CUIT]],Lista_CUIT[#All],3,0)),"CUIT NO CARGADO") -> Gastos Limpieza | R33: =IFERROR(IF(compras_mes3[[#This Row],[CUIT]]="","-",VLOOKUP(compras_mes3[[#This Row],[CUIT]],Lista_CUIT[#All],4,0)),"CUIT NO CARGADO") -> 0
B34: 31/03/2025 | C34: 1 | D34: 113 | E34: 4150902 | F34: 30577207190 | G34: =IFERROR(IF(compras_mes3[[#This Row],[CUIT]]="","-",VLOOKUP(compras_mes3[[#This Row],[CUIT]],Lista_CUIT[#All],2,0)),"CUIT NO CARGADO") -> COORDINACION ECOLOGICA AREA METROPOLITANA SOCIEDAD DEL ESTADO | H34: 3719.01 | I34: =compras_mes3[[#This Row],[NETO GRAVADO]]*0.21 -> 780.9921 | L34: 111.57 | P34: =SUM(compras_mes3[[#This Row],[NETO GRAVADO]:[Otros / No Grav.]]) -> 4611.5721 | Q34: =IFERROR(IF(compras_mes3[[#This Row],[CUIT]]="","-",VLOOKUP(compras_mes3[[#This Row],[CUIT]],Lista_CUIT[#All],3,0)),"CUIT NO CARGADO") -> Gastos Limpieza | R34: =IFERROR(IF(compras_mes3[[#This Row],[CUIT]]="","-",VLOOKUP(compras_mes3[[#This Row],[CUIT]],Lista_CUIT[#All],4,0)),"CUIT NO CARGADO") -> 0
B35: 06/03/2025 | C35: 1 | D35: 700 | E35: 2314494 | F35: 30715804812 | G35: =IFERROR(IF(compras_mes3[[#This Row],[CUIT]]="","-",VLOOKUP(compras_mes3[[#This Row],[CUIT]],Lista_CUIT[#All],2,0)),"CUIT NO CARGADO") -> CORREDORES VIALES SOCIEDAD ANONIMA | H35: 5615.9 | I35: =compras_mes3[[#This Row],[NETO GRAVADO]]*0.21 -> 1179.339 | P35: =SUM(compras_mes3[[#This Row],[NETO GRAVADO]:[Otros / No Grav.]]) -> 6795.239 | Q35: =IFERROR(IF(compras_mes3[[#This Row],[CUIT]]="","-",VLOOKUP(compras_mes3[[#This Row],[CUIT]],Lista_CUIT[#All],3,0)),"CUIT NO CARGADO") -> Peajes | R35: =IFERROR(IF(compras_mes3[[#This Row],[CUIT]]="","-",VLOOKUP(compras_mes3[[#This Row],[CUIT]],Lista_CUIT[#All],4,0)),"CUIT NO CARGADO") -> 0
B36: 14/03/2025 | C36: 1 | D36: 104 | E36: 8464148 | F36: 30715804812 | G36: =IFERROR(IF(compras_mes3[[#This Row],[CUIT]]="","-",VLOOKUP(compras_mes3[[#This Row],[CUIT]],Lista_CUIT[#All],2,0)),"CUIT NO CARGADO") -> CORREDORES VIALES SOCIEDAD ANONIMA | H36: 4159.93 | I36: =compras_mes3[[#This Row],[NETO GRAVADO]]*0.21 -> 873.5853 | N36: 249.6 | P36: =SUM(compras_mes3[[#This Row],[NETO GRAVADO]:[Otros / No Grav.]]) -> 5283.1153 | Q36: =IFERROR(IF(compras_mes3[[#This Row],[CUIT]]="","-",VLOOKUP(compras_mes3[[#This Row],[CUIT]],Lista_CUIT[#All],3,0)),"CUIT NO CARGADO") -> Peajes | R36: =IFERROR(IF(compras_mes3[[#This Row],[CUIT]]="","-",VLOOKUP(compras_mes3[[#This Row],[CUIT]],Lista_CUIT[#All],4,0)),"CUIT NO CARGADO") -> 0
B37: 29/03/2025 | C37: 1 | D37: 104 | E37: 8667810 | F37: 30715804812 | G37: =IFERROR(IF(compras_mes3[[#This Row],[CUIT]]="","-",VLOOKUP(compras_mes3[[#This Row],[CUIT]],Lista_CUIT[#All],2,0)),"CUIT NO CARGADO") -> CORREDORES VIALES SOCIEDAD ANONIMA | H37: 2079.97 | I37: =compras_mes3[[#This Row],[NETO GRAVADO]]*0.21 -> 436.7937 | M37: 124.8 | P37: =SUM(compras_mes3[[#This Row],[NETO GRAVADO]:[Otros / No Grav.]]) -> 2641.5637 | Q37: =IFERROR(IF(compras_mes3[[#This Row],[CUIT]]="","-",VLOOKUP(compras_mes3[[#This Row],[CUIT]],Lista_CUIT[#All],3,0)),"CUIT NO CARGADO") -> Peajes | R37: =IFERROR(IF(compras_mes3[[#This Row],[CUIT]]="","-",VLOOKUP(compras_mes3[[#This Row],[CUIT]],Lista_CUIT[#All],4,0)),"CUIT NO CARGADO") -> 0
B38: 21/03/2025 | C38: 1 | D38: 700 | E38: 2342135 | F38: 30715804812 | G38: =IFERROR(IF(compras_mes3[[#This Row],[CUIT]]="","-",VLOOKUP(compras_mes3[[#This Row],[CUIT]],Lista_CUIT[#All],2,0)),"CUIT NO CARGADO") -> CORREDORES VIALES SOCIEDAD ANONIMA | H38: 831.98 | I38: =compras_mes3[[#This Row],[NETO GRAVADO]]*0.21 -> 174.7158 | P38: =SUM(compras_mes3[[#This Row],[NETO GRAVADO]:[Otros / No Grav.]]) -> 1006.6958 | Q38: =IFERROR(IF(compras_mes3[[#This Row],[CUIT]]="","-",VLOOKUP(compras_mes3[[#This Row],[CUIT]],Lista_CUIT[#All],3,0)),"CUIT NO CARGADO") -> Peajes | R38: =IFERROR(IF(compras_mes3[[#This Row],[CUIT]]="","-",VLOOKUP(compras_mes3[[#This Row],[CUIT]],Lista_CUIT[#All],4,0)),"CUIT NO CARGADO") -> 0
B39: 25/03/2025 | C39: 1 | D39: 3034 | E39: 8133093 | F39: 30708574836 | G39: =IFERROR(IF(compras_mes3[[#This Row],[CUIT]]="","-",VLOOKUP(compras_mes3[[#This Row],[CUIT]],Lista_CUIT[#All],2,0)),"CUIT NO CARGADO") -> CORREO OFICIAL DE LA REPUBLICA ARGENTINA SOCIEDAD ANONIMA | H39: 9963.64 | I39: =compras_mes3[[#This Row],[NETO GRAVADO]]*0.21 -> 2092.3644 | P39: =SUM(compras_mes3[[#This Row],[NETO GRAVADO]:[Otros / No Grav.]]) -> 12056.004 | Q39: =IFERROR(IF(compras_mes3[[#This Row],[CUIT]]="","-",VLOOKUP(compras_mes3[[#This Row],[CUIT]],Lista_CUIT[#All],3,0)),"CUIT NO CARGADO") -> MESAJERIA | R39: =IFERROR(IF(compras_mes3[[#This Row],[CUIT]]="","-",VLOOKUP(compras_mes3[[#This Row],[CUIT]],Lista_CUIT[#All],4,0)),"CUIT NO CARGADO") -> 0
B40: 13/03/2025 | C40: 1 | D40: 3034 | E40: 8060702 | F40: 30708574836 | G40: =IFERROR(IF(compras_mes3[[#This Row],[CUIT]]="","-",VLOOKUP(compras_mes3[[#This Row],[CUIT]],Lista_CUIT[#All],2,0)),"CUIT NO CARGADO") -> CORREO OFICIAL DE LA REPUBLICA ARGENTINA SOCIEDAD ANONIMA | H40: 5953.72 | I40: =compras_mes3[[#This Row],[NETO GRAVADO]]*0.21 -> 1250.2812 | P40: =SUM(compras_mes3[[#This Row],[NETO GRAVADO]:[Otros / No Grav.]]) -> 7204.0012 | Q40: =IFERROR(IF(compras_mes3[[#This Row],[CUIT]]="","-",VLOOKUP(compras_mes3[[#This Row],[CUIT]],Lista_CUIT[#All],3,0)),"CUIT NO CARGADO") -> MESAJERIA | R40: =IFERROR(IF(compras_mes3[[#This Row],[CUIT]]="","-",VLOOKUP(compras_mes3[[#This Row],[CUIT]],Lista_CUIT[#All],4,0)),"CUIT NO CARGADO") -> 0
B41: 25/03/2025 | C41: 1 | D41: 3034 | E41: 8133150 | F41: 30708574836 | G41: =IFERROR(IF(compras_mes3[[#This Row],[CUIT]]="","-",VLOOKUP(compras_mes3[[#This Row],[CUIT]],Lista_CUIT[#All],2,0)),"CUIT NO CARGADO") -> CORREO OFICIAL DE LA REPUBLICA ARGENTINA SOCIEDAD ANONIMA | H41: 5953.72 | I41: =compras_mes3[[#This Row],[NETO GRAVADO]]*0.21 -> 1250.2812 | P41: =SUM(compras_mes3[[#This Row],[NETO GRAVADO]:[Otros / No Grav.]]) -> 7204.0012 | Q41: =IFERROR(IF(compras_mes3[[#This Row],[CUIT]]="","-",VLOOKUP(compras_mes3[[#This Row],[CUIT]],Lista_CUIT[#All],3,0)),"CUIT NO CARGADO") -> MESAJERIA | R41: =IFERROR(IF(compras_mes3[[#This Row],[CUIT]]="","-",VLOOKUP(compras_mes3[[#This Row],[CUIT]],Lista_CUIT[#All],4,0)),"CUIT NO CARGADO") -> 0
B42: 28/03/2025 | C42: 1 | D42: 2188 | E42: 144864 | F42: 30548083156 | G42: =IFERROR(IF(compras_mes3[[#This Row],[CUIT]]="","-",VLOOKUP(compras_mes3[[#This Row],[CUIT]],Lista_CUIT[#All],2,0)),"CUIT NO CARGADO") -> COTO CENTRO INTEGRAL DE COMERCIALIZACION SOCIEDAD ANONIMA | H42: 119657.03 | I42: 22180.86 | K42: 1473.56 | O42: 10122.35 | P42: =SUM(compras_mes3[[#This Row],[NETO GRAVADO]:[Otros / No Grav.]]) -> 153433.8 | Q42: =IFERROR(IF(compras_mes3[[#This Row],[CUIT]]="","-",VLOOKUP(compras_mes3[[#This Row],[CUIT]],Lista_CUIT[#All],3,0)),"CUIT NO CARGADO") -> Gastos Varios | R42: =IFERROR(IF(compras_mes3[[#This Row],[CUIT]]="","-",VLOOKUP(compras_mes3[[#This Row],[CUIT]],Lista_CUIT[#All],4,0)),"CUIT NO CARGADO") -> 0
B43: 22/03/2025 | C43: 1 | D43: 2084 | E43: 28101 | F43: 30548083156 | G43: =IFERROR(IF(compras_mes3[[#This Row],[CUIT]]="","-",VLOOKUP(compras_mes3[[#This Row],[CUIT]],Lista_CUIT[#All],2,0)),"CUIT NO CARGADO") -> COTO CENTRO INTEGRAL DE COMERCIALIZACION SOCIEDAD ANONIMA | H43: 107358.91 | I43: 15638.45 | K43: 3453.46 | O43: 7195.54 | P43: =SUM(compras_mes3[[#This Row],[NETO GRAVADO]:[Otros / No Grav.]]) -> 133646.36 | Q43: =IFERROR(IF(compras_mes3[[#This Row],[CUIT]]="","-",VLOOKUP(compras_mes3[[#This Row],[CUIT]],Lista_CUIT[#All],3,0)),"CUIT NO CARGADO") -> Gastos Varios | R43: =IFERROR(IF(compras_mes3[[#This Row],[CUIT]]="","-",VLOOKUP(compras_mes3[[#This Row],[CUIT]],Lista_CUIT[#All],4,0)),"CUIT NO CARGADO") -> 0
B44: 14/03/2025 | C44: 1 | D44: 2188 | E44: 143823 | F44: 30548083156 | G44: =IFERROR(IF(compras_mes3[[#This Row],[CUIT]]="","-",VLOOKUP(compras_mes3[[#This Row],[CUIT]],Lista_CUIT[#All],2,0)),"CUIT NO CARGADO") -> COTO CENTRO INTEGRAL DE COMERCIALIZACION SOCIEDAD ANONIMA | H44: 101850.93 | I44: 14539.58 | K44: 3424.56 | O44: 7390.31 | P44: =SUM(compras_mes3[[#This Row],[NETO GRAVADO]:[Otros / No Grav.]]) -> 127205.38 | Q44: =IFERROR(IF(compras_mes3[[#This Row],[CUIT]]="","-",VLOOKUP(compras_mes3[[#This Row],[CUIT]],Lista_CUIT[#All],3,0)),"CUIT NO CARGADO") -> Gastos Varios | R44: =IFERROR(IF(compras_mes3[[#This Row],[CUIT]]="","-",VLOOKUP(compras_mes3[[#This Row],[CUIT]],Lista_CUIT[#All],4,0)),"CUIT NO CARGADO") -> 0
B45: 01/03/2025 | C45: 1 | D45: 2188 | E45: 142887 | F45: 30548083156 | G45: =IFERROR(IF(compras_mes3[[#This Row],[CUIT]]="","-",VLOOKUP(compras_mes3[[#This Row],[CUIT]],Lista_CUIT[#All],2,0)),"CUIT NO CARGADO") -> COTO CENTRO INTEGRAL DE COMERCIALIZACION SOCIEDAD ANONIMA | H45: 74426.47 | I45: =compras_mes3[[#This Row],[NETO GRAVADO]]*0.21 -> 15629.559 | O45: 6569.46 | P45: =SUM(compras_mes3[[#This Row],[NETO GRAVADO]:[Otros / No Grav.]]) -> 96625.489 | Q45: =IFERROR(IF(compras_mes3[[#This Row],[CUIT]]="","-",VLOOKUP(compras_mes3[[#This Row],[CUIT]],Lista_CUIT[#All],3,0)),"CUIT NO CARGADO") -> Gastos Varios | R45: =IFERROR(IF(compras_mes3[[#This Row],[CUIT]]="","-",VLOOKUP(compras_mes3[[#This Row],[CUIT]],Lista_CUIT[#All],4,0)),"CUIT NO CARGADO") -> 0
B46: 01/03/2025 | C46: 1 | D46: 2084 | E46: 27668 | F46: 30548083156 | G46: =IFERROR(IF(compras_mes3[[#This Row],[CUIT]]="","-",VLOOKUP(compras_mes3[[#This Row],[CUIT]],Lista_CUIT[#All],2,0)),"CUIT NO CARGADO") -> COTO CENTRO INTEGRAL DE COMERCIALIZACION SOCIEDAD ANONIMA | H46: 59617.8 | I46: 6002.99 | K46: 3258.37 | O46: 3038.19 | P46: =SUM(compras_mes3[[#This Row],[NETO GRAVADO]:[Otros / No Grav.]]) -> 71917.35 | Q46: =IFERROR(IF(compras_mes3[[#This Row],[CUIT]]="","-",VLOOKUP(compras_mes3[[#This Row],[CUIT]],Lista_CUIT[#All],3,0)),"CUIT NO CARGADO") -> Gastos Varios | R46: =IFERROR(IF(compras_mes3[[#This Row],[CUIT]]="","-",VLOOKUP(compras_mes3[[#This Row],[CUIT]],Lista_CUIT[#All],4,0)),"CUIT NO CARGADO") -> 0
B47: 07/03/2025 | C47: 1 | D47: 2188 | E47: 143277 | F47: 30548083156 | G47: =IFERROR(IF(compras_mes3[[#This Row],[CUIT]]="","-",VLOOKUP(compras_mes3[[#This Row],[CUIT]],Lista_CUIT[#All],2,0)),"CUIT NO CARGADO") -> COTO CENTRO INTEGRAL DE COMERCIALIZACION SOCIEDAD ANONIMA | H47: 57905.3 | I47: 8934.41 | K47: 1612.85 | O47: 4217.34 | P47: =SUM(compras_mes3[[#This Row],[NETO GRAVADO]:[Otros / No Grav.]]) -> 72669.9 | Q47: =IFERROR(IF(compras_mes3[[#This Row],[CUIT]]="","-",VLOOKUP(compras_mes3[[#This Row],[CUIT]],Lista_CUIT[#All],3,0)),"CUIT NO CARGADO") -> Gastos Varios | R47: =IFERROR(IF(compras_mes3[[#This Row],[CUIT]]="","-",VLOOKUP(compras_mes3[[#This Row],[CUIT]],Lista_CUIT[#All],4,0)),"CUIT NO CARGADO") -> 0
B48: 14/03/2025 | C48: 1 | D48: 2199 | E48: 35682 | F48: 30548083156 | G48: =IFERROR(IF(compras_mes3[[#This Row],[CUIT]]="","-",VLOOKUP(compras_mes3[[#This Row],[CUIT]],Lista_CUIT[#All],2,0)),"CUIT NO CARGADO") -> COTO CENTRO INTEGRAL DE COMERCIALIZACION SOCIEDAD ANONIMA | H48: 50961.13 | I48: 7959.21 | K48: 1371.31 | O48: 2801.21 | P48: =SUM(compras_mes3[[#This Row],[NETO GRAVADO]:[Otros / No Grav.]]) -> 63092.86 | Q48: =IFERROR(IF(compras_mes3[[#This Row],[CUIT]]="","-",VLOOKUP(compras_mes3[[#This Row],[CUIT]],Lista_CUIT[#All],3,0)),"CUIT NO CARGADO") -> Gastos Varios | R48: =IFERROR(IF(compras_mes3[[#This Row],[CUIT]]="","-",VLOOKUP(compras_mes3[[#This Row],[CUIT]],Lista_CUIT[#All],4,0)),"CUIT NO CARGADO") -> 0
B49: 24/03/2025 | C49: 1 | D49: 2215 | E49: 52604 | F49: 30548083156 | G49: =IFERROR(IF(compras_mes3[[#This Row],[CUIT]]="","-",VLOOKUP(compras_mes3[[#This Row],[CUIT]],Lista_CUIT[#All],2,0)),"CUIT NO CARGADO") -> COTO CENTRO INTEGRAL DE COMERCIALIZACION SOCIEDAD ANONIMA | H49: 43963.3 | I49: 7077.89 | K49: 1077.22 | O49: 3758.04 | P49: =SUM(compras_mes3[[#This Row],[NETO GRAVADO]:[Otros / No Grav.]]) -> 55876.45 | Q49: =IFERROR(IF(compras_mes3[[#This Row],[CUIT]]="","-",VLOOKUP(compras_mes3[[#This Row],[CUIT]],Lista_CUIT[#All],3,0)),"CUIT NO CARGADO") -> Gastos Varios | R49: =IFERROR(IF(compras_mes3[[#This Row],[CUIT]]="","-",VLOOKUP(compras_mes3[[#This Row],[CUIT]],Lista_CUIT[#All],4,0)),"CUIT NO CARGADO") -> 0
B50: 11/03/2025 | C50: 1 | D50: 2188 | E50: 143560 | F50: 30548083156 | G50: =IFERROR(IF(compras_mes3[[#This Row],[CUIT]]="","-",VLOOKUP(compras_mes3[[#This Row],[CUIT]],Lista_CUIT[#All],2,0)),"CUIT NO CARGADO") -> COTO CENTRO INTEGRAL DE COMERCIALIZACION SOCIEDAD ANONIMA | H50: 25194.54 | I50: 4955.71 | K50: 167.57 | O50: 2219.63 | P50: =SUM(compras_mes3[[#This Row],[NETO GRAVADO]:[Otros / No Grav.]]) -> 32537.45 | Q50: =IFERROR(IF(compras_mes3[[#This Row],[CUIT]]="","-",VLOOKUP(compras_mes3[[#This Row],[CUIT]],Lista_CUIT[#All],3,0)),"CUIT NO CARGADO") -> Gastos Varios | R50: =IFERROR(IF(compras_mes3[[#This Row],[CUIT]]="","-",VLOOKUP(compras_mes3[[#This Row],[CUIT]],Lista_CUIT[#All],4,0)),"CUIT NO CARGADO") -> 0
B51: 09/03/2025 | C51: 1 | D51: 2084 | E51: 27821 | F51: 30548083156 | G51: =IFERROR(IF(compras_mes3[[#This Row],[CUIT]]="","-",VLOOKUP(compras_mes3[[#This Row],[CUIT]],Lista_CUIT[#All],2,0)),"CUIT NO CARGADO") -> COTO CENTRO INTEGRAL DE COMERCIALIZACION SOCIEDAD ANONIMA | H51: 21951.86 | I51: 2334.7 | K51: 1137.6 | O51: 1306.23 | P51: =SUM(compras_mes3[[#This Row],[NETO GRAVADO]:[Otros / No Grav.]]) -> 26730.39 | Q51: =IFERROR(IF(compras_mes3[[#This Row],[CUIT]]="","-",VLOOKUP(compras_mes3[[#This Row],[CUIT]],Lista_CUIT[#All],3,0)),"CUIT NO CARGADO") -> Gastos Varios | R51: =IFERROR(IF(compras_mes3[[#This Row],[CUIT]]="","-",VLOOKUP(compras_mes3[[#This Row],[CUIT]],Lista_CUIT[#All],4,0)),"CUIT NO CARGADO") -> 0
B52: 20/03/2025 | C52: 1 | D52: 3 | E52: 105 | F52: 20202970940 | G52: =IFERROR(IF(compras_mes3[[#This Row],[CUIT]]="","-",VLOOKUP(compras_mes3[[#This Row],[CUIT]],Lista_CUIT[#All],2,0)),"CUIT NO CARGADO") -> ALEJANDRO TRAIBER | H52: 3000000 | I52: =compras_mes3[[#This Row],[NETO GRAVADO]]*0.21 -> 630000 | P52: =SUM(compras_mes3[[#This Row],[NETO GRAVADO]:[Otros / No Grav.]]) -> 3630000 | Q52: =IFERROR(IF(compras_mes3[[#This Row],[CUIT]]="","-",VLOOKUP(compras_mes3[[#This Row],[CUIT]],Lista_CUIT[#All],3,0)),"CUIT NO CARGADO") -> Mercaderia | R52: =IFERROR(IF(compras_mes3[[#This Row],[CUIT]]="","-",VLOOKUP(compras_mes3[[#This Row],[CUIT]],Lista_CUIT[#All],4,0)),"CUIT NO CARGADO") -> 0
B53: 20/03/2025 | C53: 1 | D53: 3 | E53: 106 | F53: 20202970940 | G53: =IFERROR(IF(compras_mes3[[#This Row],[CUIT]]="","-",VLOOKUP(compras_mes3[[#This Row],[CUIT]],Lista_CUIT[#All],2,0)),"CUIT NO CARGADO") -> ALEJANDRO TRAIBER | H53: 3000000 | I53: =compras_mes3[[#This Row],[NETO GRAVADO]]*0.21 -> 630000 | P53: =SUM(compras_mes3[[#This Row],[NETO GRAVADO]:[Otros / No Grav.]]) -> 3630000 | Q53: =IFERROR(IF(compras_mes3[[#This Row],[CUIT]]="","-",VLOOKUP(compras_mes3[[#This Row],[CUIT]],Lista_CUIT[#All],3,0)),"CUIT NO CARGADO") -> Mercaderia | R53: =IFERROR(IF(compras_mes3[[#This Row],[CUIT]]="","-",VLOOKUP(compras_mes3[[#This Row],[CUIT]],Lista_CUIT[#All],4,0)),"CUIT NO CARGADO") -> 0
B54: 07/03/2025 | C54: 1 | D54: 3 | E54: 91 | F54: 20202970940 | G54: =IFERROR(IF(compras_mes3[[#This Row],[CUIT]]="","-",VLOOKUP(compras_mes3[[#This Row],[CUIT]],Lista_CUIT[#All],2,0)),"CUIT NO CARGADO") -> ALEJANDRO TRAIBER | H54: 2005290 | I54: =compras_mes3[[#This Row],[NETO GRAVADO]]*0.21 -> 421110.9 | P54: =SUM(compras_mes3[[#This Row],[NETO GRAVADO]:[Otros / No Grav.]]) -> 2426400.9 | Q54: =IFERROR(IF(compras_mes3[[#This Row],[CUIT]]="","-",VLOOKUP(compras_mes3[[#This Row],[CUIT]],Lista_CUIT[#All],3,0)),"CUIT NO CARGADO") -> Mercaderia | R54: =IFERROR(IF(compras_mes3[[#This Row],[CUIT]]="","-",VLOOKUP(compras_mes3[[#This Row],[CUIT]],Lista_CUIT[#All],4,0)),"CUIT NO CARGADO") -> 0
B55: 17/03/2025 | C55: 1 | D55: 3 | E55: 5356 | F55: 30716242672 | G55: =IFERROR(IF(compras_mes3[[#This Row],[CUIT]]="","-",VLOOKUP(compras_mes3[[#This Row],[CUIT]],Lista_CUIT[#All],2,0)),"CUIT NO CARGADO") -> Pensagro SRL | H55: 883317.69 | I55: =compras_mes3[[#This Row],[NETO GRAVADO]]*0.21 -> 185496.71 | P55: =SUM(compras_mes3[[#This Row],[NETO GRAVADO]:[Otros / No Grav.]]) -> 1068814.4 | Q55: =IFERROR(IF(compras_mes3[[#This Row],[CUIT]]="","-",VLOOKUP(compras_mes3[[#This Row],[CUIT]],Lista_CUIT[#All],3,0)),"CUIT NO CARGADO") -> Gastos mantenimiento | R55: =IFERROR(IF(compras_mes3[[#This Row],[CUIT]]="","-",VLOOKUP(compras_mes3[[#This Row],[CUIT]],Lista_CUIT[#All],4,0)),"CUIT NO CARGADO") -> 0
B56: 27/03/2025 | C56: 1 | D56: 81 | E56: 302074 | F56: 30546741253 | G56: =IFERROR(IF(compras_mes3[[#This Row],[CUIT]]="","-",VLOOKUP(compras_mes3[[#This Row],[CUIT]],Lista_CUIT[#All],2,0)),"CUIT NO CARGADO") -> OSDE | H56: 582356.56 | K56: =compras_mes3[[#This Row],[NETO GRAVADO]]*0.105 -> 61147.439 | M56: 34941.39 | P56: =SUM(compras_mes3[[#This Row],[NETO GRAVADO]:[Otros / No Grav.]]) -> 678445.39 | Q56: =IFERROR(IF(compras_mes3[[#This Row],[CUIT]]="","-",VLOOKUP(compras_mes3[[#This Row],[CUIT]],Lista_CUIT[#All],3,0)),"CUIT NO CARGADO") -> Prepaga corporativa | R56: =IFERROR(IF(compras_mes3[[#This Row],[CUIT]]="","-",VLOOKUP(compras_mes3[[#This Row],[CUIT]],Lista_CUIT[#All],4,0)),"CUIT NO CARGADO") -> 0
B57: 24/03/2025 | C57: 1 | D57: 2 | E57: 73 | F57: 20353654560 | G57: =IFERROR(IF(compras_mes3[[#This Row],[CUIT]]="","-",VLOOKUP(compras_mes3[[#This Row],[CUIT]],Lista_CUIT[#All],2,0)),"CUIT NO CARGADO") -> CUNIOLI FEDERICO | H57: 495000 | I57: =compras_mes3[[#This Row],[NETO GRAVADO]]*0.21 -> 103950 | P57: =SUM(compras_mes3[[#This Row],[NETO GRAVADO]:[Otros / No Grav.]]) -> 598950 | Q57: =IFERROR(IF(compras_mes3[[#This Row],[CUIT]]="","-",VLOOKUP(compras_mes3[[#This Row],[CUIT]],Lista_CUIT[#All],3,0)),"CUIT NO CARGADO") -> Honorarios Legales | R57: =IFERROR(IF(compras_mes3[[#This Row],[CUIT]]="","-",VLOOKUP(compras_mes3[[#This Row],[CUIT]],Lista_CUIT[#All],4,0)),"CUIT NO CARGADO") -> 0
B58: 12/03/2025 | C58: 1 | D58: 4 | E58: 10845 | F58: 30716627167 | G58: =IFERROR(IF(compras_mes3[[#This Row],[CUIT]]="","-",VLOOKUP(compras_mes3[[#This Row],[CUIT]],Lista_CUIT[#All],2,0)),"CUIT NO CARGADO") -> ZIEL TECHNOLOGY S.A | H58: 267896.69 | I58: =compras_mes3[[#This Row],[NETO GRAVADO]]*0.21 -> 56258.305 | P58: =SUM(compras_mes3[[#This Row],[NETO GRAVADO]:[Otros / No Grav.]]) -> 324154.99 | Q58: =IFERROR(IF(compras_mes3[[#This Row],[CUIT]]="","-",VLOOKUP(compras_mes3[[#This Row],[CUIT]],Lista_CUIT[#All],3,0)),"CUIT NO CARGADO") -> Gastos administrativos | R58: =IFERROR(IF(compras_mes3[[#This Row],[CUIT]]="","-",VLOOKUP(compras_mes3[[#This Row],[CUIT]],Lista_CUIT[#All],4,0)),"CUIT NO CARGADO") -> 0
B59: 28/03/2025 | C59: 1 | D59: 4 | E59: 2394 | F59: 33716767669 | G59: =IFERROR(IF(compras_mes3[[#This Row],[CUIT]]="","-",VLOOKUP(compras_mes3[[#This Row],[CUIT]],Lista_CUIT[#All],2,0)),"CUIT NO CARGADO") -> LIDER ESTANT SRL | H59: 195044.86 | I59: =compras_mes3[[#This Row],[NETO GRAVADO]]*0.21 -> 40959.421 | P59: =SUM(compras_mes3[[#This Row],[NETO GRAVADO]:[Otros / No Grav.]]) -> 236004.28 | Q59: =IFERROR(IF(compras_mes3[[#This Row],[CUIT]]="","-",VLOOKUP(compras_mes3[[#This Row],[CUIT]],Lista_CUIT[#All],3,0)),"CUIT NO CARGADO") -> Muebles y Utiles | R59: =IFERROR(IF(compras_mes3[[#This Row],[CUIT]]="","-",VLOOKUP(compras_mes3[[#This Row],[CUIT]],Lista_CUIT[#All],4,0)),"CUIT NO CARGADO") -> 0
B60: 21/03/2025 | C60: 1 | D60: 12 | E60: 226619 | F60: 30707598936 | G60: =IFERROR(IF(compras_mes3[[#This Row],[CUIT]]="","-",VLOOKUP(compras_mes3[[#This Row],[CUIT]],Lista_CUIT[#All],2,0)),"CUIT NO CARGADO") -> CENTRO-SEC SRL | H60: 190545.96 | I60: =compras_mes3[[#This Row],[NETO GRAVADO]]*0.21 -> 40014.652 | M60: 11432.76 | P60: =SUM(compras_mes3[[#This Row],[NETO GRAVADO]:[Otros / No Grav.]]) -> 241993.37 | Q60: =IFERROR(IF(compras_mes3[[#This Row],[CUIT]]="","-",VLOOKUP(compras_mes3[[#This Row],[CUIT]],Lista_CUIT[#All],3,0)),"CUIT NO CARGADO") -> Gastos Varios | R60: =IFERROR(IF(compras_mes3[[#This Row],[CUIT]]="","-",VLOOKUP(compras_mes3[[#This Row],[CUIT]],Lista_CUIT[#All],4,0)),"CUIT NO CARGADO") -> 0
B61: 03/03/2025 | C61: 1 | D61: 4 | E61: 808 | F61: 30717690075 | G61: =IFERROR(IF(compras_mes3[[#This Row],[CUIT]]="","-",VLOOKUP(compras_mes3[[#This Row],[CUIT]],Lista_CUIT[#All],2,0)),"CUIT NO CARGADO") -> MFK | H61: 162190.08 | I61: =compras_mes3[[#This Row],[NETO GRAVADO]]*0.21 -> 34059.917 | P61: =SUM(compras_mes3[[#This Row],[NETO GRAVADO]:[Otros / No Grav.]]) -> 196250 | Q61: =IFERROR(IF(compras_mes3[[#This Row],[CUIT]]="","-",VLOOKUP(compras_mes3[[#This Row],[CUIT]],Lista_CUIT[#All],3,0)),"CUIT NO CARGADO") -> Gastos Varios | R61: =IFERROR(IF(compras_mes3[[#This Row],[CUIT]]="","-",VLOOKUP(compras_mes3[[#This Row],[CUIT]],Lista_CUIT[#All],4,0)),"CUIT NO CARGADO") -> 0
B62: 06/03/2025 | C62: 1 | D62: 3 | E62: 2728 | F62: 20352040402 | G62: =IFERROR(IF(compras_mes3[[#This Row],[CUIT]]="","-",VLOOKUP(compras_mes3[[#This Row],[CUIT]],Lista_CUIT[#All],2,0)),"CUIT NO CARGADO") -> THE GLOBAL SHINE | H62: 113057.8 | I62: =compras_mes3[[#This Row],[NETO GRAVADO]]*0.21 -> 23742.138 | P62: =SUM(compras_mes3[[#This Row],[NETO GRAVADO]:[Otros / No Grav.]]) -> 136799.94 | Q62: =IFERROR(IF(compras_mes3[[#This Row],[CUIT]]="","-",VLOOKUP(compras_mes3[[#This Row],[CUIT]],Lista_CUIT[#All],3,0)),"CUIT NO CARGADO") -> Muebles y Utiles | R62: =IFERROR(IF(compras_mes3[[#This Row],[CUIT]]="","-",VLOOKUP(compras_mes3[[#This Row],[CUIT]],Lista_CUIT[#All],4,0)),"CUIT NO CARGADO") -> 0
B63: 18/03/2025 | C63: 1 | D63: 6 | E63: 16488 | F63: 30703451310 | G63: =IFERROR(IF(compras_mes3[[#This Row],[CUIT]]="","-",VLOOKUP(compras_mes3[[#This Row],[CUIT]],Lista_CUIT[#All],2,0)),"CUIT NO CARGADO") -> AGROCENTRAL S R L | H63: 94484.32 | I63: =compras_mes3[[#This Row],[NETO GRAVADO]]*0.21 -> 19841.707 | P63: =SUM(compras_mes3[[#This Row],[NETO GRAVADO]:[Otros / No Grav.]]) -> 114326.03 | Q63: =IFERROR(IF(compras_mes3[[#This Row],[CUIT]]="","-",VLOOKUP(compras_mes3[[#This Row],[CUIT]],Lista_CUIT[#All],3,0)),"CUIT NO CARGADO") -> Gastos Varios | R63: =IFERROR(IF(compras_mes3[[#This Row],[CUIT]]="","-",VLOOKUP(compras_mes3[[#This Row],[CUIT]],Lista_CUIT[#All],4,0)),"CUIT NO CARGADO") -> 0
B64: 31/03/2025 | C64: 1 | D64: 7 | E64: 7344 | F64: 27341012525 | G64: =IFERROR(IF(compras_mes3[[#This Row],[CUIT]]="","-",VLOOKUP(compras_mes3[[#This Row],[CUIT]],Lista_CUIT[#All],2,0)),"CUIT NO CARGADO") -> MAGARIÑOS VANESA LORENA | H64: 93933.88 | I64: =compras_mes3[[#This Row],[NETO GRAVADO]]*0.21 -> 19726.115 | P64: =SUM(compras_mes3[[#This Row],[NETO GRAVADO]:[Otros / No Grav.]]) -> 113659.99 | Q64: =IFERROR(IF(compras_mes3[[#This Row],[CUIT]]="","-",VLOOKUP(compras_mes3[[#This Row],[CUIT]],Lista_CUIT[#All],3,0)),"CUIT NO CARGADO") -> Gastos Varios | R64: =IFERROR(IF(compras_mes3[[#This Row],[CUIT]]="","-",VLOOKUP(compras_mes3[[#This Row],[CUIT]],Lista_CUIT[#All],4,0)),"CUIT NO CARGADO") -> 0
B65: 19/03/2025 | C65: 1 | D65: 3 | E65: 20908 | F65: 30717315657 | G65: =IFERROR(IF(compras_mes3[[#This Row],[CUIT]]="","-",VLOOKUP(compras_mes3[[#This Row],[CUIT]],Lista_CUIT[#All],2,0)),"CUIT NO CARGADO") -> Tango Hogar SRL | H65: 58015.64 | I65: =compras_mes3[[#This Row],[NETO GRAVADO]]*0.21 -> 12183.284 | P65: =SUM(compras_mes3[[#This Row],[NETO GRAVADO]:[Otros / No Grav.]]) -> 70198.924 | Q65: =IFERROR(IF(compras_mes3[[#This Row],[CUIT]]="","-",VLOOKUP(compras_mes3[[#This Row],[CUIT]],Lista_CUIT[#All],3,0)),"CUIT NO CARGADO") -> Gastos Varios | R65: =IFERROR(IF(compras_mes3[[#This Row],[CUIT]]="","-",VLOOKUP(compras_mes3[[#This Row],[CUIT]],Lista_CUIT[#All],4,0)),"CUIT NO CARGADO") -> 0
B66: 21/03/2025 | C66: 1 | D66: 2 | E66: 6769 | F66: 20242147341 | G66: =IFERROR(IF(compras_mes3[[#This Row],[CUIT]]="","-",VLOOKUP(compras_mes3[[#This Row],[CUIT]],Lista_CUIT[#All],2,0)),"CUIT NO CARGADO") -> TOSOLINI ANDRES ALCIDES GUSTAVO | H66: 54545.44 | I66: =compras_mes3[[#This Row],[NETO GRAVADO]]*0.21 -> 11454.542 | P66: =SUM(compras_mes3[[#This Row],[NETO GRAVADO]:[Otros / No Grav.]]) -> 65999.982 | Q66: =IFERROR(IF(compras_mes3[[#This Row],[CUIT]]="","-",VLOOKUP(compras_mes3[[#This Row],[CUIT]],Lista_CUIT[#All],3,0)),"CUIT NO CARGADO") -> Honorarios Legales | R66: =IFERROR(IF(compras_mes3[[#This Row],[CUIT]]="","-",VLOOKUP(compras_mes3[[#This Row],[CUIT]],Lista_CUIT[#All],4,0)),"CUIT NO CARGADO") -> 0
B67: 25/03/2025 | C67: 1 | D67: 5 | E67: 200 | F67: 30716502356 | G67: =IFERROR(IF(compras_mes3[[#This Row],[CUIT]]="","-",VLOOKUP(compras_mes3[[#This Row],[CUIT]],Lista_CUIT[#All],2,0)),"CUIT NO CARGADO") -> PUNTOTECH | H67: 45955.66 | K67: =compras_mes3[[#This Row],[NETO GRAVADO]]*0.105 -> 4825.3443 | P67: =SUM(compras_mes3[[#This Row],[NETO GRAVADO]:[Otros / No Grav.]]) -> 50781.004 | Q67: =IFERROR(IF(compras_mes3[[#This Row],[CUIT]]="","-",VLOOKUP(compras_mes3[[#This Row],[CUIT]],Lista_CUIT[#All],3,0)),"CUIT NO CARGADO") -> Muebles y Utiles | R67: =IFERROR(IF(compras_mes3[[#This Row],[CUIT]]="","-",VLOOKUP(compras_mes3[[#This Row],[CUIT]],Lista_CUIT[#All],4,0)),"CUIT NO CARGADO") -> 0
B68: 19/03/2025 | C68: 1 | D68: 7243 | E68: 278 | F68: 33707675069 | G68: =IFERROR(IF(compras_mes3[[#This Row],[CUIT]]="","-",VLOOKUP(compras_mes3[[#This Row],[CUIT]],Lista_CUIT[#All],2,0)),"CUIT NO CARGADO") -> BUS PACK S.A. | H68: 42557.86 | I68: =compras_mes3[[#This Row],[NETO GRAVADO]]*0.21 -> 8937.1506 | P68: =SUM(compras_mes3[[#This Row],[NETO GRAVADO]:[Otros / No Grav.]]) -> 51495.011 | Q68: =IFERROR(IF(compras_mes3[[#This Row],[CUIT]]="","-",VLOOKUP(compras_mes3[[#This Row],[CUIT]],Lista_CUIT[#All],3,0)),"CUIT NO CARGADO") -> Flete | R68: =IFERROR(IF(compras_mes3[[#This Row],[CUIT]]="","-",VLOOKUP(compras_mes3[[#This Row],[CUIT]],Lista_CUIT[#All],4,0)),"CUIT NO CARGADO") -> 0
B69: 18/03/2025 | C69: 1 | D69: 5 | E69: 45264 | F69: 30711549206 | G69: =IFERROR(IF(compras_mes3[[#This Row],[CUIT]]="","-",VLOOKUP(compras_mes3[[#This Row],[CUIT]],Lista_CUIT[#All],2,0)),"CUIT NO CARGADO") -> DDV S.R.L | H69: 40076.4 | I69: =compras_mes3[[#This Row],[NETO GRAVADO]]*0.21 -> 8416.044 | P69: =SUM(compras_mes3[[#This Row],[NETO GRAVADO]:[Otros / No Grav.]]) -> 48492.444 | Q69: =IFERROR(IF(compras_mes3[[#This Row],[CUIT]]="","-",VLOOKUP(compras_mes3[[#This Row],[CUIT]],Lista_CUIT[#All],3,0)),"CUIT NO CARGADO") -> Librería | R69: =IFERROR(IF(compras_mes3[[#This Row],[CUIT]]="","-",VLOOKUP(compras_mes3[[#This Row],[CUIT]],Lista_CUIT[#All],4,0)),"CUIT NO CARGADO") -> 0
B70: 15/03/2025 | C70: 1 | D70: 3 | E70: 2741 | F70: 30708393262 | G70: =IFERROR(IF(compras_mes3[[#This Row],[CUIT]]="","-",VLOOKUP(compras_mes3[[#This Row],[CUIT]],Lista_CUIT[#All],2,0)),"CUIT NO CARGADO") -> VIVERO GALANTE BRUNO S.A. | H70: 38311.25 | I70: =compras_mes3[[#This Row],[NETO GRAVADO]]*0.21 -> 8045.3625 | P70: =SUM(compras_mes3[[#This Row],[NETO GRAVADO]:[Otros / No Grav.]]) -> 46356.613 | Q70: =IFERROR(IF(compras_mes3[[#This Row],[CUIT]]="","-",VLOOKUP(compras_mes3[[#This Row],[CUIT]],Lista_CUIT[#All],3,0)),"CUIT NO CARGADO") -> Gastos Varios | R70: =IFERROR(IF(compras_mes3[[#This Row],[CUIT]]="","-",VLOOKUP(compras_mes3[[#This Row],[CUIT]],Lista_CUIT[#All],4,0)),"CUIT NO CARGADO") -> 0
