Workbook
Name partner_id: Configuracion!$B$332

Sheet Configuracion
F1: CUIT | G1: Cargar sin guiones
F2: RAZON SOCIAL | G2: Maximo 30 caracteres
A3: CUIT | B3: RAZON SOCIAL | C3: DETALLE | F3: DETALLE | G3: Cargar tipo de gasto
A4: 30628205090 | B4: ALBAMIE SA | C4: CLIENTE
A5: 30711678820 | B5: 2PSI INGENIERIA SRL | C5: PROVEEDOR
A6: 33716367539 | B6: 3PI S.A.S. | C6: PROVEEDOR
A7: 30660373108 | B7: ABC SA | C7: VARIOS
A8: 20300210881 | B8: ABOY DIEGO OSCAR | C8: PROVEEDOR
A9: 27229910782 | B9: ABUGAUCH MARIA DE LOS ANGELES | C9: PROVEEDOR
A10: 20242709897 | B10: ABUGAUCH VICTOR HUGO | C10: PROVEEDOR
A11: 20281669053 | B11: ACOSTA JAVIER GUSTAVO | C11: FLETE
A12: 20174240125 | B12: ACOSTA OSCAR ISIDRO | C12: VARIOS
A13: 30641659106 | B13: AGRISOL SA | C13: VARIOS
A14: 33709914109 | B14: ALAN COLLECTION SA | C14: VARIOS
A15: 20267161616 | B15: ALBAJARI DIEGO MARCOS | C15: VARIOS
... A155: 30537679855 | B155: ESTACION LIMA SA | C155: VARIOS
A156: 30-56864959-8 | B156: EXPRESO BISONTE SRL | C156: FLETE
A157: 30708542349 | B157: EXPRESO FORMOSA SRL | C157: FLETE
A158: 30526582884 | B158: EXPRESO MAR DEL PLATA SA | C158: FLETE
A159: 30577744579 | B159: EXPRESO TROLE SRL | C159: FLETE
A160: 30715949292 | B160: EYPAPEL SAS | C160: GASTOS VARIOS
A161: 30715980807 | B161: FABORT SRL | C161: PROVEEDOR
A162: 20359718765 | B162: FAIL ABRAHAM | C162: VARIOS
A163: 30643518364 | B163: FARMACIA DE MEDRANO SCS | C163: PROVEEDOR
A164: 30692138747 | B164: FARMACITY SA | C164: VARIOS
A165: 33712234429 | B165: FEDAGAS SA | C165: VARIOS
A166: 20353576012 | B166: FEDERICO PABLO FEOLA | C166: VARIOS
A167: 20343766441 | B167: FERNANDEZ MAURO | C167: TALLER
A168: 27062343449 | B168: FERREIRA LILIANA INES | C168: FLETE
... A570: 30661273093 | B570: OSETRA | C570: CLIENTE

Sheet Julio 25
A1: ORTOPEDIA GEMINIS S.A. | J1: 45839
A4: LIBRO IVA COMPRAS
A6: FACTURAS A
A7: FECHA | B7: PTO VTA | C7: FAC A | D7: CUIT | E7: RAZON SOCIAL | F7: NETO | G7: IVA 21% | H7: IVA 27% | I7: IVA 10,5% | J7: P IVA | K7: IIBB CF | L7: IIBB BS | M7: NO GRAV | N7: OTROS | O7: TOTAL | P7: DETALLE
E8: =VLOOKUP(D8,Configuracion!$A$4:$C$590,2,FALSE) -> #N/A | G8: =F8*21% -> 0 | O8: =SUM(F8:N8) -> 0 | P8: =VLOOKUP(D8,Configuracion!$A$4:$C$590,3,FALSE) -> #N/A
E9: =VLOOKUP(D9,Configuracion!$A$4:$C$590,2,FALSE) -> #N/A | G9: =F9*21% -> 0 | O9: =SUM(F9:N9) -> 0 | P9: =VLOOKUP(D9,Configuracion!$A$4:$C$590,3,FALSE) -> #N/A
E10: =VLOOKUP(D10,Configuracion!$A$4:$C$590,2,FALSE) -> #N/A | G10: =F10*21% -> 0 | O10: =SUM(F10:N10) -> 0 | P10: =VLOOKUP(D10,Configuracion!$A$4:$C$590,3,FALSE) -> #N/A
E11: =VLOOKUP(D11,Configuracion!$A$4:$C$590,2,FALSE) -> #N/A | G11: =F11*21% -> 0 | O11: =SUM(F11:N11) -> 0 | P11: =VLOOKUP(D11,Configuracion!$A$4:$C$590,3,FALSE) -> #N/A
E12: =VLOOKUP(D12,Configuracion!$A$4:$C$590,2,FALSE) -> #N/A | G12: =F12*21% -> 0 | O12: =SUM(F12:N12) -> 0 | P12: =VLOOKUP(D12,Configuracion!$A$4:$C$590,3,FALSE) -> #N/A
E13: =VLOOKUP(D13,Configuracion!$A$4:$C$590,2,FALSE) -> #N/A | G13: =F13*21% -> 0 | O13: =SUM(F13:N13) -> 0 | P13: =VLOOKUP(D13,Configuracion!$A$4:$C$590,3,FALSE) -> #N/A
E14: =VLOOKUP(D14,Configuracion!$A$4:$C$590,2,FALSE) -> #N/A | G14: =F14*21% -> 0 | O14: =SUM(F14:N14) -> 0 | P14: =VLOOKUP(D14,Configuracion!$A$4:$C$590,3,FALSE) -> #N/A
E15: =VLOOKUP(D15,Configuracion!$A$4:$C$590,2,FALSE) -> #N/A | G15: =F15*21% -> 0 | O15: =SUM(F15:N15) -> 0 | P15: =VLOOKUP(D15,Configuracion!$A$4:$C$590,3,FALSE) -> #N/A
E16: =VLOOKUP(D16,Configuracion!$A$4:$C$590,2,FALSE) -> #N/A | G16: =F16*21% -> 0 | O16: =SUM(F16:N16) -> 0 | P16: =VLOOKUP(D16,Configuracion!$A$4:$C$590,3,FALSE) -> #N/A
E17: =VLOOKUP(D17,Configuracion!$A$4:$C$590,2,FALSE) -> #N/A | G17: =F17*21% -> 0 | O17: =SUM(F17:N17) -> 0 | P17: =VLOOKUP(D17,Configuracion!$A$4:$C$590,3,FALSE) -> #N/A
A18: TOTAL | F18: =SUM(F8:F17) -> 0 | G18: =SUM(G8:G17) -> 0 | H18: =SUM(H8:H17) -> 0 | I18: =SUM(I8:I17) -> 0 | J18: =SUM(J8:J17) -> 0 | K18: =SUM(K8:K17) -> 0 | L18: =SUM(L8:L17) -> 0 | M18: =SUM(M8:M17) -> 0 | ... O18: =SUM(O8:O17) -> 0
F19: IVA | G19: =G18+H18+I18 -> 0
A21: FACTURAS B/C
A22: FECHA | B22: PTO VTA | C22: FAC C | D22: CUIT | E22: RAZON SOCIAL | F22: TOTAL | G22: DETALLE
E23: =VLOOKUP(D23,Configuracion!$A$4:$C$590,2,FALSE) -> #N/A | G23: =VLOOKUP(D23,Configuracion!$A$4:$C$590,3,FALSE) -> #N/A
E24: =VLOOKUP(D24,Configuracion!$A$4:$C$590,2,FALSE) -> #N/A | G24: =VLOOKUP(D24,Configuracion!$A$4:$C$590,3,FALSE) -> #N/A
E25: =VLOOKUP(D25,Configuracion!$A$4:$C$590,2,FALSE) -> #N/A | G25: =VLOOKUP(D25,Configuracion!$A$4:$C$590,3,FALSE) -> #N/A
E26: =VLOOKUP(D26,Configuracion!$A$4:$C$590,2,FALSE) -> #N/A | G26: =VLOOKUP(D26,Configuracion!$A$4:$C$590,3,FALSE) -> #N/A
E27: =VLOOKUP(D27,Configuracion!$A$4:$C$590,2,FALSE) -> #N/A | G27: =VLOOKUP(D27,Configuracion!$A$4:$C$590,3,FALSE) -> #N/A
E28: =VLOOKUP(D28,Configuracion!$A$4:$C$590,2,FALSE) -> #N/A | G28: =VLOOKUP(D28,Configuracion!$A$4:$C$590,3,FALSE) -> #N/A
E29: =VLOOKUP(D29,Configuracion!$A$4:$C$590,2,FALSE) -> #N/A | G29: =VLOOKUP(D29,Configuracion!$A$4:$C$590,3,FALSE) -> #N/A
E30: =VLOOKUP(D30,Configuracion!$A$4:$C$590,2,FALSE) -> #N/A | G30: =VLOOKUP(D30,Configuracion!$A$4:$C$590,3,FALSE) -> #N/A
E31: =VLOOKUP(D31,Configuracion!$A$4:$C$590,2,FALSE) -> #N/A | G31: =VLOOKUP(D31,Configuracion!$A$4:$C$590,3,FALSE) -> #N/A
E32: =VLOOKUP(D32,Configuracion!$A$4:$C$590,2,FALSE) -> #N/A | G32: =VLOOKUP(D32,Configuracion!$A$4:$C$590,3,FALSE) -> #N/A
E33: =VLOOKUP(D33,Configuracion!$A$4:$C$590,2,FALSE) -> #N/A | G33: =VLOOKUP(D33,Configuracion!$A$4:$C$590,3,FALSE) -> #N/A
E34: =VLOOKUP(D34,Configuracion!$A$4:$C$590,2,FALSE) -> #N/A | G34: =VLOOKUP(D34,Configuracion!$A$4:$C$590,3,FALSE) -> #N/A
... E41: =VLOOKUP(D41,Configuracion!$A$4:$C$590,2,FALSE) -> #N/A | G41: =VLOOKUP(D41,Configuracion!$A$4:$C$590,3,FALSE) -> #N/A
A42: TOTAL | F42: =SUM(F23:F41) -> 0
A44: RETENCIONES de IVA solamente
A45: FECHA | B45: COMPROBANTE NRO | D45: CUIT | E45: RAZON SOCIAL | F45: GANANCIAS | G45: IVA | H45: IIBB | I45: SUSS
A46: 45869 | B46: 66528 | D46: 30522428163 | E46: =VLOOKUP(D46,Configuracion!$A$4:$C$590,2,FALSE) -> GALENO ARGENTINA SA | G46: 48359.01
A47: 45869 | B47: 66484 | D47: 30522428163 | E47: =VLOOKUP(D47,Configuracion!$A$4:$C$590,2,FALSE) -> GALENO ARGENTINA SA | G47: 799478.14
D48: 0 | E48: =VLOOKUP(D48,Configuracion!$A$4:$C$590,2,FALSE) -> #N/A
D49: 0 | E49: =VLOOKUP(D49,Configuracion!$A$4:$C$590,2,FALSE) -> #N/A
D50: 0 | E50: =VLOOKUP(D50,Configuracion!$A$4:$C$590,2,FALSE) -> #N/A
D51: 0 | E51: =VLOOKUP(D51,Configuracion!$A$4:$C$590,2,FALSE) -> #N/A
D52: 0 | E52: =VLOOKUP(D52,Configuracion!$A$4:$C$590,2,FALSE) -> #N/A
D53: 0 | E53: =VLOOKUP(D53,Configuracion!$A$4:$C$590,2,FALSE) -> #N/A
D54: 0 | E54: =VLOOKUP(D54,Configuracion!$A$4:$C$590,2,FALSE) -> #N/A
D55: 0 | E55: =VLOOKUP(D55,Configuracion!$A$4:$C$590,2,FALSE) -> #N/A
D56: 0 | E56: =VLOOKUP(D56,Configuracion!$A$4:$C$590,2,FALSE) -> #N/A
D57: 0 | E57: =VLOOKUP(D57,Configuracion!$A$4:$C$590,2,FALSE) -> #N/A
D58: 1 | E58: =VLOOKUP(D58,Configuracion!$A$4:$C$590,2,FALSE) -> #N/A
A59: TOTAL | F59: =SUM(F46:F58) -> 0 | G59: =SUM(G46:G58) -> 847837.15 | H59: =SUM(H46:H58) -> 0 | I59: =SUM(I46:I58) -> 0
A63: LIBRO IVA VENTAS
A65: FACTURA A
A66: FECHA | B66: PTO VTA | C66: NRO FC | D66: CUIT | E66: RAZON SOCIAL | F66: NETO | G66: IVA | H66: NO GRAV. | I66: TOTAL
E67: =VLOOKUP(D67,Configuracion!$A$4:$C$590,2,FALSE) -> #N/A | G67: =F67*0.21 -> 0 | I67: =SUM(F67:H67) -> 0
E68: =VLOOKUP(D68,Configuracion!$A$4:$C$590,2,FALSE) -> #N/A | G68: =F68*0.21 -> 0 | I68: =SUM(F68:H68) -> 0
E69: =VLOOKUP(D69,Configuracion!$A$4:$C$590,2,FALSE) -> #N/A | G69: =F69*0.21 -> 0 | I69: =SUM(F69:H69) -> 0
E70: =VLOOKUP(D70,Configuracion!$A$4:$C$590,2,FALSE) -> #N/A | G70: =F70*0.21 -> 0 | I70: =SUM(F70:H70) -> 0
E71: =VLOOKUP(D71,Configuracion!$A$4:$C$590,2,FALSE) -> #N/A | G71: =F71*0.21 -> 0 | I71: =SUM(F71:H71) -> 0
E72: =VLOOKUP(D72,Configuracion!$A$4:$C$590,2,FALSE) -> #N/A | G72: =F72*0.21 -> 0 | I72: =SUM(F72:H72) -> 0
E73: =VLOOKUP(D73,Configuracion!$A$4:$C$590,2,FALSE) -> #N/A | G73: =F73*0.21 -> 0 | I73: =SUM(F73:H73) -> 0
E74: =VLOOKUP(D74,Configuracion!$A$4:$C$590,2,FALSE) -> #N/A | G74: =F74*0.21 -> 0 | I74: =SUM(F74:H74) -> 0
E75: =VLOOKUP(D75,Configuracion!$A$4:$C$590,2,FALSE) -> #N/A | G75: =F75*0.21 -> 0 | I75: =SUM(F75:H75) -> 0
A76: TOTAL | F76: =SUM(F67:F75) -> 0 | G76: =SUM(G67:G75) -> 0 | I76: =SUM(I67:I75) -> 0
A79: FACTURA B
A80: FECHA | B80: PTO VTA | C80: NRO FC | D80: CUIT | E80: RAZON SOCIAL | F80: NETO | G80: IVA | H80: TOTAL
E81: =VLOOKUP(D81,Configuracion!$A$4:$C$590,2,FALSE) -> #N/A | F81: =H81/1.21 -> 0 | G81: =F81*0.21 -> 0
E82: =VLOOKUP(D82,Configuracion!$A$4:$C$590,2,FALSE) -> #N/A | F82: =H82/1.21 -> 0 | G82: =F82*0.21 -> 0
E83: =VLOOKUP(D83,Configuracion!$A$4:$C$590,2,FALSE) -> #N/A | F83: =H83/1.21 -> 0 | G83: =F83*0.21 -> 0
E84: =VLOOKUP(D84,Configuracion!$A$4:$C$590,2,FALSE) -> #N/A | F84: =H84/1.21 -> 0 | G84: =F84*0.21 -> 0
E85: =VLOOKUP(D85,Configuracion!$A$4:$C$590,2,FALSE) -> #N/A | F85: =H85/1.21 -> 0 | G85: =F85*0.21 -> 0
A86: TOTAL | F86: =SUM(F81:F85) -> 0 | G86: =SUM(G81:G85) -> 0 | H86: =SUM(H81:H85) -> 0

Sheet Calculo IVA
B1: ORTOPEDIA GEMINIS
A2: Calculo Iva | D2: 45809
B4: VENTAS
B5: Neto | C5: Iva | D5: Total
A6: FAC. "A" | B6: =+'Ventas 07'!D4+'Ventas 07'!D5 -> 73784714 | C6: =+B6*0.21 -> 15494790 | D6: =+B6+C6 -> 89279504
A7: FAC. "B" | B7: =+'Ventas 07'!D6+'Ventas 07'!D7+'Ventas 07'!D8 -> 43898013 | C7: =+B7*0.21 -> 9218582.7 | D7: =+B7+C7 -> 53116596
B8: =SUM(B6:B7) -> 1.1768273e+08 | C8: =SUM(C6:C7) -> 24713373 | D8: =SUM(D6:D7) -> 1.423961e+08
B11: COMPRAS
B12: Neto | C12: IVA | D12: Total
A13: Comprobantes / Extractos | B13: =+'Compras 07'!G161+'Compras 07'!H161+'Compras 07'!I161 -> 69769155 | C13: =+'Compras 07'!L161 -> 13591497 | D13: 94654478
B16: =SUM(B13:B15) -> 69769155 | C16: =SUM(C13:C15) -> 13591497 | D16: =SUM(D13:D15) -> 94654478
A19: RETENCIONES | B19: N° Cuit | C19: Importe | D19: Nro. Retencion | E19: Fecha
A20: AFIP - No están informadas las retenciones de IVA en el sistema de AFIP
C35: =+'Julio 25'!G59 -> 847837.15
A37: PERCEPCIONES | B37: N° Cuit | C37: Importe | D37: Nro. Retencion | E37: Fecha
C41: =SUM(C38:C40) -> 0
A43: Total Deducciociones | C43: =+C41+C35 -> 847837.15
C46: (Montos en Positivo)
A47: 1er Saldo Tecnico del Período | C47: =+C8-C16 -> 11121875
A49: Saldo Tecnico de período Anterior (a favor) | D49: (resta en el total)
A51: Saldo Neto Técnico | C51: =+C47-C49 -> 11121875
A55: Saldo L.D. del Período | C55: =+C41+C35 -> 847837.15
A57: Saldo L.D. del Período Anterior
A59: Neto S.L.D | C59: =+C55+C57 -> 847837.15
A62: I V A | C62: =+C51-C59 -> 10274038
A63: NOTA: Sin Tomar posibles Retenciones que se hayan hecho

Sheet afip
A1: Fecha | B1: Tipo | C1: Punto de Venta | D1: Número Desde | E1: Número Hasta | F1: Cód. Autorización | G1: Tipo Doc. Emisor | H1: Nro. Doc. Emisor | I1: Denominación Emisor | J1: Tipo Cambio | K1: Moneda | L1: Imp. Neto Gravado | M1: Imp. Neto No Gravado | N1: Imp. Op. Exentas | O1: Otros Tributos | P1: IVA | Q1: Imp. Total
A2: 01/09/2024 | B2: 1 - Factura A | C2: 2189 | D2: 75919 | F2: 74356447170423 | G2: CUIT | H2: 30548083156 | I2: COTO CENTRO INTEGRAL DE COMERCIALIZACION SOCIEDAD ANONIMA | J2: 1 | K2: $ | L2: 6462.61 | M2: 0 | N2: 0 | O2: 452.38 | P2: 1357.15 | Q2: 8272.14
A3: 02/09/2024 | B3: 1 - Factura A | C3: 500 | D3: 1611886 | F3: 74357098226128 | G3: CUIT | H3: 30654118767 | I3: SOLUCIONES MULTIMEDIA S A | J3: 1 | K3: $ | L3: 89554.36 | M3: 0 | N3: 0 | O3: 0 | P3: 18806.42 | Q3: 112850.92
A4: 02/09/2024 | B4: 1 - Factura A | C4: 1 | D4: 4517 | F4: 74361573927319 | G4: CUIT | H4: 30715141201 | I4: REHAB S.R.L. | J4: 1 | K4: $ | L4: 1216380 | M4: 0 | N4: 0 | O4: 0 | P4: 255439.8 | Q4: 1471819.8
A5: 02/09/2024 | B5: 1 - Factura A | C5: 5 | D5: 158399 | F5: 74363528156508 | G5: CUIT | H5: 30598960093 | I5: SILVESTRIN FABRIS SOC RESP LTDA | J5: 1 | K5: $ | L5: 2376294.2 | M5: 0 | N5: 0 | O5: 0 | P5: 337808.56 | Q5: 2832917.5
A6: 02/09/2024 | B6: 1 - Factura A | C6: 17 | D6: 2245 | F6: 74361547632750 | G6: CUIT | H6: 30711764921 | I6: RELIEF CENTER S.R.L. | J6: 1 | K6: $ | L6: 93973 | M6: 0 | N6: 0 | O6: 0 | P6: 19734.33 | Q6: 113707.33
A7: 02/09/2024 | B7: 1 - Factura A | C7: 3051 | D7: 801967 | F7: 74367703518446 | G7: CUIT | H7: 30678814357 | I7: TELEFONICA MOVILES ARGENTINA SOCIEDAD ANONIMA | J7: 1 | K7: $ | L7: 14407 | M7: 0 | N7: 0 | O7: 0 | P7: 3889.89 | Q7: 20245.61
A8: 02/09/2024 | B8: 1 - Factura A | C8: 2 | D8: 248 | F8: 74363494027429 | G8: CUIT | H8: 27144282383 | I8: SCHEJTER LILA ELISA | J8: 1 | K8: $ | L8: 160000 | M8: 0 | N8: 0 | O8: 0 | P8: 33600 | Q8: 193600
A9: 02/09/2024 | B9: 1 - Factura A | C9: 5 | D9: 102 | F9: 74367559790009 | G9: CUIT | H9: 27329449357 | I9: ANDREANI AGUSTINA SUSANA | J9: 1 | K9: $ | L9: 64100 | M9: 16400 | N9: 0 | O9: 0 | P9: 13461 | Q9: 93961
A10: 02/09/2024 | B10: 11 - Factura C | C10: 3 | D10: 874 | F10: 74363563144286 | G10: CUIT | H10: 20086277523 | I10: BOTINDARI JUAN CARLOS | J10: 1 | K10: $ | O10: 0 | Q10: 275500
A11: 02/09/2024 | B11: 11 - Factura C | C11: 2 | D11: 302 | F11: 74368278674869 | G11: CUIT | H11: 27265832178 | I11: BLASCO MARIA GUADALUPE | J11: 1 | K11: $ | O11: 0 | Q11: 250000
A12: 03/09/2024 | B12: 1 - Factura A | C12: 629 | D12: 5407463 | F12: 34353802937243 | G12: CUIT | H12: 30663498513 | I12: GRUPO CONCESIONARIO DEL OESTE SA | J12: 1 | K12: $ | L12: 2121.64 | M12: 0 | N12: 0 | O12: 0 | P12: 445.54 | Q12: 2673.26
A13: 03/09/2024 | B13: 1 - Factura A | C13: 711 | D13: 6097149 | F13: 34359489663246 | G13: CUIT | H13: 30677237119 | I13: AUTOPISTAS DEL SOL S A | J13: 1 | K13: $ | L13: 7715.05 | M13: 0 | N13: 231.45 | O13: 0 | P13: 1620.16 | Q13: 9952.41
A14: 03/09/2024 | B14: 1 - Factura A | C14: 2635 | D14: 1369 | F14: 34359844249451 | G14: CUIT | H14: 33699685459 | I14: CORREO ANDREANI SA | J14: 1 | K14: $ | L14: 12449.6 | M14: 0 | N14: 0 | O14: 0 | P14: 2614.42 | Q14: 15064.02
A15: 03/09/2024 | B15: 1 - Factura A | C15: 2 | D15: 216 | F15: 74362687536018 | G15: CUIT | H15: 30605344352 | I15: CONSORCIO BARTOLOME MITRE 2466 | J15: 1 | K15: $ | L15: 834000 | M15: 0 | N15: 0 | O15: 0 | P15: 175140 | Q15: 1009140
A16: 04/09/2024 | B16: 1 - Factura A | C16: 17 | D16: 2255 | F16: 74361803741207 | G16: CUIT | H16: 30711764921 | I16: RELIEF CENTER S.R.L. | J16: 1 | K16: $ | L16: 527580 | M16: 0 | N16: 0 | O16: 0 | P16: 110791.8 | Q16: 638371.8
A17: 04/09/2024 | B17: 1 - Factura A | C17: 2 | D17: 50685 | F17: 74365825946417 | G17: CUIT | H17: 30595553535 | I17: RUBRICOM SOCIEDAD ANONIMA | J17: 1 | K17: $ | L17: 4793.39 | M17: 0 | N17: 0 | O17: 0 | P17: 1006.61 | Q17: 5800
A18: 04/09/2024 | B18: 1 - Factura A | C18: 120 | D18: 4949 | F18: 74365804898856 | G18: CUIT | H18: 30587197215 | I18: PANATEL SOCIEDAD ANONIMA | J18: 1 | K18: $ | L18: 68595.04 | M18: 0 | N18: 0 | O18: 0 | P18: 14404.96 | Q18: 86429.75
A19: 04/09/2024 | B19: 1 - Factura A | C19: 7 | D19: 3241 | F19: 74364799883128 | G19: CUIT | H19: 20284183534 | I19: FURLANETTO MARTIN | J19: 1 | K19: $ | L19: 4545.5 | M19: 0 | N19: 0 | O19: 0 | P19: 954.56 | Q19: 5500.06
A20: 04/09/2024 | B20: 1 - Factura A | C20: 120 | D20: 4948 | F20: 74365800262038 | G20: CUIT | H20: 30587197215 | I20: PANATEL SOCIEDAD ANONIMA | J20: 1 | K20: $ | L20: 68595.04 | M20: 0 | N20: 0 | O20: 0 | P20: 14404.96 | Q20: 86429.75
A21: 04/09/2024 | B21: 1 - Factura A | C21: 401 | D21: 66 | F21: 74364797895464 | G21: CUIT | H21: 30716234114 | I21: UZUMAKI S.A.S. | J21: 1305 | K21: USD | L21: 129.3 | M21: 0 | N21: 0 | O21: 0 | P21: 27.15 | Q21: 156.45
A22: 05/09/2024 | B22: 1 - Factura A | C22: 2 | D22: 760 | F22: 74369961703669 | G22: CUIT | H22: 20272865869 | I22: DI FEO MARTIN EZEQUIEL | J22: 1 | K22: $ | L22: 84450 | M22: 0 | N22: 0 | O22: 0 | P22: 17734.5 | Q22: 102184.5
A23: 05/09/2024 | B23: 1 - Factura A | C23: 5 | D23: 5331 | F23: 74363959099503 | G23: CUIT | H23: 30715833243 | I23: BIODINAMICA ASISTENCIA S.R.L. | J23: 1 | K23: $ | L23: 22238.59 | M23: 0 | N23: 0 | O23: 0 | P23: 4670.1 | Q23: 26908.69
... A35: 09/09/2024 | B35: 3 - Nota de Crédito A | C35: 5 | D35: 192 | F35: 74376416376753 | G35: CUIT | H35: 30712187316 | I35: ITALOMED PRODUCTOS SRL | J35: 1 | K35: $ | L35: 293619.94 | M35: 0 | N35: 0 | O35: 0 | P35: 61660.19 | Q35: 355280.13
A36: 09/09/2024 | B36: 11 - Factura C | C36: 1 | D36: 148 | F36: 74370408397319 | G36: CUIT | H36: 27338342840 | I36: CANCINO PAMELA RITA | J36: 1 | K36: $ | O36: 0 | Q36: 276800
A37: 10/09/2024 | B37: 1 - Factura A | C37: 2 | D37: 8403 | F37: 74372567359059 | G37: CUIT | H37: 27363810182 | I37: HECKER LAURA NOEMI | J37: 1 | K37: $ | L37: 3635.54 | M37: 0 | N37: 0 | O37: 0 | P37: 763.46 | Q37: 4399
A38: 10/09/2024 | B38: 1 - Factura A | C38: 5 | D38: 31858 | F38: 74370525870493 | G38: CUIT | H38: 30710804830 | I38: ZG MULTITEC SRL | J38: 1 | K38: $ | L38: 29410.86 | M38: 0 | N38: 0 | O38: 0 | P38: 3088.14 | Q38: 32499
A39: 10/09/2024 | B39: 1 - Factura A | C39: 8 | D39: 1684 | F39: 74371529941038 | G39: CUIT | H39: 30708973501 | I39: ASIAL S.R.L. | J39: 1 | K39: $ | L39: 740255 | M39: 0 | N39: 0 | O39: 0 | P39: 155453.55 | Q39: 895708.55
A40: 10/09/2024 | B40: 1 - Factura A | C40: 3 | D40: 4250 | F40: 74378552751950 | G40: CUIT | H40: 20184052858 | I40: ABOUD PABLO DANIEL | J40: 1 | K40: $ | L40: 16859.48 | M40: 0 | N40: 0 | O40: 0 | P40: 3540.49 | Q40: 20399.95
A41: 10/09/2024 | B41: 11 - Factura C | C41: 3 | D41: 986 | F41: 74379527477577 | G41: CUIT | H41: 20216451679 | I41: VAZQUEZ RICARDO OSCAR | J41: 1 | K41: $ | O41: 0 | Q41: 86000
A42: 11/09/2024 | B42: 1 - Factura A | C42: 1 | D42: 2468 | F42: 74379681409704 | G42: CUIT | H42: 30717179389 | I42: NICOLAS TOBIAS SEQUEIRA Y MARIA GABRIELA RATTNER SOCIEDAD DE LA SECCION IV LGS | J42: 1 | K42: $ | L42: 82644.62 | M42: 0 | N42: 0 | O42: 0 | P42: 17355.37 | Q42: 99999.99
A43: 11/09/2024 | B43: 1 - Factura A | C43: 5 | D43: 3378 | F43: 74379704726153 | G43: CUIT | H43: 30717179389 | I43: NICOLAS TOBIAS SEQUEIRA Y MARIA GABRIELA RATTNER SOCIEDAD DE LA SECCION IV LGS | J43: 1 | K43: $ | L43: 82644.63 | M43: 0 | N43: 0 | O43: 0 | P43: 17355.37 | Q43: 100000
A44: 11/09/2024 | B44: 1 - Factura A | C44: 3 | D44: 7676 | F44: 74379686794320 | G44: CUIT | H44: 33708218699 | I44: MANGGINI PABLO Y MANGGINI ULISES SOC. DE HECHO. | J44: 1 | K44: $ | L44: 15000 | M44: 0 | N44: 0 | O44: 0 | P44: 3150 | Q44: 18150
A45: 11/09/2024 | B45: 11 - Factura C | C45: 1 | D45: 9 | F45: 74373677716509 | G45: CUIT | H45: 20464199633 | I45: OVIEDO JIMENEZ TIZIANO LIONEL | J45: 1 | K45: $ | O45: 0 | Q45: 499950
A46: 12/09/2024 | B46: 1 - Factura A | C46: 2 | D46: 778 | F46: 74379814460759 | G46: CUIT | H46: 20272865869 | I46: DI FEO MARTIN EZEQUIEL | J46: 1 | K46: $ | L46: 128100 | M46: 0 | N46: 0 | O46: 0 | P46: 26901 | Q46: 155001
A47: 12/09/2024 | B47: 1 - Factura A | C47: 4 | D47: 38394 | F47: 74379814609856 | G47: CUIT | H47: 20289111329 | I47: LEDESMA EMILIANO RUBEN | J47: 1 | K47: $ | L47: 585730.8 | M47: 0 | N47: 0 | O47: 0 | P47: 123003.47 | Q47: 708734.27
A48: 12/09/2024 | B48: 1 - Factura A | C48: 5 | D48: 1915 | F48: 74376761404173 | G48: CUIT | H48: 30712187316 | I48: ITALOMED PRODUCTOS SRL | J48: 1 | K48: $ | L48: 254033.05 | M48: 0 | N48: 0 | O48: 0 | P48: 53346.94 | Q48: 307379.99
A49: 12/09/2024 | B49: 1 - Factura A | C49: 5 | D49: 1916 | F49: 74376766353942 | G49: CUIT | H49: 30712187316 | I49: ITALOMED PRODUCTOS SRL | J49: 1 | K49: $ | L49: 472751.65 | M49: 0 | N49: 0 | O49: 0 | P49: 99277.85 | Q49: 572029.5
A50: 13/09/2024 | B50: 1 - Factura A | C50: 1 | D50: 4620 | F50: 74371942773283 | G50: CUIT | H50: 30715141201 | I50: REHAB S.R.L. | J50: 1 | K50: $ | L50: 29295 | M50: 0 | N50: 0 | O50: 0 | P50: 6151.95 | Q50: 35446.95
A51: 13/09/2024 | B51: 1 - Factura A | C51: 5 | D51: 1920 | F51: 74376932362480 | G51: CUIT | H51: 30712187316 | I51: ITALOMED PRODUCTOS SRL | J51: 1 | K51: $ | L51: 34718.6 | M51: 0 | N51: 0 | O51: 0 | P51: 7290.91 | Q51: 42009.51
A52: 13/09/2024 | B52: 1 - Factura A | C52: 2 | D52: 783 | F52: 74379875047216 | G52: CUIT | H52: 20272865869 | I52: DI FEO MARTIN EZEQUIEL | J52: 1 | K52: $ | L52: 9950 | M52: 0 | N52: 0 | O52: 0 | P52: 2089.5 | Q52: 12039.5
A53: 13/09/2024 | B53: 1 - Factura A | C53: 1 | D53: 4613 | F53: 74371932408480 | G53: CUIT | H53: 30715141201 | I53: REHAB S.R.L. | J53: 1 | K53: $ | L53: 3648847.5 | M53: 0 | N53: 0 | O53: 0 | P53: 766257.98 | Q53: 4415105.5
A54: 13/09/2024 | B54: 1 - Factura A | C54: 503 | D54: 1469491 | F54: 74372992481197 | G54: CUIT | H54: 30639935872 | I54: CAMINOS DEL RIO URUGUAY S A DE CONSTRUCCIONES Y CONCESIONES VIALES | J54: 1 | K54: $ | L54: 2934.75 | M54: 0 | N54: 0 | O54: 0 | P54: 616.3 | Q54: 3697.79
A55: 13/09/2024 | B55: 1 - Factura A | C55: 2 | D55: 4940 | F55: 74375873241825 | G55: CUIT | H55: 27117233745 | I55: MANZINI MARTA GRACIELA | J55: 1 | K55: $ | L55: 585519 | M55: 0 | N55: 0 | O55: 0 | P55: 122958.99 | Q55: 708477.99
A56: 13/09/2024 | B56: 1 - Factura A | C56: 3 | D56: 170 | F56: 74383333330765 | G56: CUIT | H56: 20334976433 | I56: NARDOMARINO EZEQUIEL EDUARDO | J56: 1 | K56: $ | L56: 188330 | M56: 0 | N56: 0 | O56: 0 | P56: 39549.3 | Q56: 227879.3
A57: 13/09/2024 | B57: 1 - Factura A | C57: 3 | D57: 171 | F57: 74383357920263 | G57: CUIT | H57: 20334976433 | I57: NARDOMARINO EZEQUIEL EDUARDO | J57: 1 | K57: $ | L57: 153000 | M57: 0 | N57: 0 | O57: 0 | P57: 32130 | Q57: 185130
... A60: 15/09/2024 | B60: 1 - Factura A | C60: 113 | D60: 3802250 | F60: 74380483594334 | G60: CUIT | H60: 30577207190 | I60: COORDINACION ECOLOGICA AREA METROPOLITANA SOCIEDAD DEL ESTADO | J60: 1 | K60: $ | L60: 2975.21 | M60: 0 | N60: 0 | O60: 0 | P60: 624.79 | Q60: 3689.26
A61: 15/09/2024 | B61: 11 - Factura C | C61: 5 | D61: 168 | F61: 74379160231271 | G61: CUIT | H61: 27062343449 | I61: FERREIRA LILIANA INES | J61: 1 | K61: $ | O61: 0 | Q61: 260000
A62: 15/09/2024 | B62: 11 - Factura C | C62: 5 | D62: 169 | F62: 74379160368355 | G62: CUIT | H62: 27062343449 | I62: FERREIRA LILIANA INES | J62: 1 | K62: $ | O62: 0 | Q62: 35000
A63: 16/09/2024 | B63: 1 - Factura A | C63: 5015 | D63: 644558 | F63: 74384236665042 | G63: CUIT | H63: 30574876474 | I63: AUTOPISTAS URBANAS S A | J63: 1 | K63: $ | L63: 12702.19 | M63: 0 | N63: 0 | O63: 0 | P63: 2667.45 | Q63: 17020.92
A64: 16/09/2024 | B64: 1 - Factura A | C64: 6 | D64: 40318 | F64: 74389250556652 | G64: CUIT | H64: 30709459399 | I64: LA JUNIOR S.R.L. | J64: 1 | K64: $ | L64: 11807.44 | M64: 0 | N64: 0 | O64: 0 | P64: 2479.56 | Q64: 14287
A65: 16/09/2024 | B65: 1 - Factura A | C65: 2002 | D65: 72231 | F65: 74385199526054 | G65: CUIT | H65: 30716425165 | I65: MERCADO TOTAL SAS | J65: 1 | K65: $ | L65: 13842.98 | M65: 0 | N65: 0 | O65: 0 | P65: 2907.03 | Q65: 16750
A66: 16/09/2024 | B66: 1 - Factura A | C66: 2 | D66: 249 | F66: 74383195124025 | G66: CUIT | H66: 27144282383 | I66: SCHEJTER LILA ELISA | J66: 1 | K66: $ | L66: 320000 | M66: 0 | N66: 0 | O66: 0 | P66: 67200 | Q66: 387200
A67: 17/09/2024 | B67: 1 - Factura A | C67: 7 | D67: 524 | F67: 74380369713013 | G67: CUIT | H67: 30715630040 | I67: PISOS BODEN S.A. | J67: 1 | K67: $ | L67: 3517469.4 | M67: 0 | N67: 0 | O67: 0 | P67: 738668.58 | Q67: 4256138
A68: 17/09/2024 | B68: 1 - Factura A | C68: 711 | D68: 6155254 | F68: 34379169789485 | G68: CUIT | H68: 30677237119 | I68: AUTOPISTAS DEL SOL S A | J68: 1 | K68: $ | L68: 5515.3 | M68: 0 | N68: 165.46 | O68: 0 | P68: 1158.23 | Q68: 7114.76
A69: 17/09/2024 | B69: 1 - Factura A | C69: 629 | D69: 5447412 | F69: 34373728816629 | G69: CUIT | H69: 30663498513 | I69: GRUPO CONCESIONARIO DEL OESTE SA | J69: 1 | K69: $ | L69: 3440.74 | M69: 0 | N69: 0 | O69: 0 | P69: 722.56 | Q69: 4335.34
A70: 17/09/2024 | B70: 1 - Factura A | C70: 4264 | D70: 4388001 | F70: 74388498673820 | G70: CUIT | H70: 30639453738 | I70: TELECOM ARGENTINA SOCIEDAD ANONIMA | J70: 1 | K70: $ | L70: 24142.14 | M70: 0 | N70: 0 | O70: 0 | P70: 5069.85 | Q70: 30901.93
A71: 17/09/2024 | B71: 11 - Factura C | C71: 1 | D71: 248 | F71: 74395443070489 | G71: CUIT | H71: 27217606255 | I71: SAPUNA MIRIAN KARINA | J71: 1 | K71: $ | O71: 0 | Q71: 50223.03
A72: 17/09/2024 | B72: 11 - Factura C | C72: 1 | D72: 247 | F72: 74395442076201 | G72: CUIT | H72: 27217606255 | I72: SAPUNA MIRIAN KARINA | J72: 1 | K72: $ | O72: 0 | Q72: 56703.42
A73: 18/09/2024 | B73: 1 - Factura A | C73: 2 | D73: 4942 | F73: 74385474906338 | G73: CUIT | H73: 27117233745 | I73: MANZINI MARTA GRACIELA | J73: 1 | K73: $ | L73: 585519 | M73: 0 | N73: 0 | O73: 0 | P73: 122958.99 | Q73: 708477.99
A74: 18/09/2024 | B74: 11 - Factura C | C74: 1 | D74: 70 | F74: 74384470115890 | G74: CUIT | H74: 23281233084 | I74: DRUETTA ANDREA MARIEL | J74: 1 | K74: $ | O74: 0 | Q74: 215000
A75: 18/09/2024 | B75: 11 - Factura C | C75: 1 | D75: 71 | F75: 74384470845746 | G75: CUIT | H75: 23281233084 | I75: DRUETTA ANDREA MARIEL | J75: 1 | K75: $ | O75: 0 | Q75: 215000
A76: 18/09/2024 | B76: 11 - Factura C | C76: 1 | D76: 249 | F76: 74395443331023 | G76: CUIT | H76: 27217606255 | I76: SAPUNA MIRIAN KARINA | J76: 1 | K76: $ | O76: 0 | Q76: 55083.32
A77: 18/09/2024 | B77: 11 - Factura C | C77: 1 | D77: 250 | F77: 74395444517785 | G77: CUIT | H77: 27217606255 | I77: SAPUNA MIRIAN KARINA | J77: 1 | K77: $ | O77: 0 | Q77: 148916.68
A78: 19/09/2024 | B78: 1 - Factura A | C78: 2 | D78: 796 | F78: 74389604255613 | G78: CUIT | H78: 20272865869 | I78: DI FEO MARTIN EZEQUIEL | J78: 1 | K78: $ | L78: 253100 | M78: 0 | N78: 0 | O78: 0 | P78: 53151 | Q78: 306251
A79: 19/09/2024 | B79: 1 - Factura A | C79: 7 | D79: 6066 | F79: 74386569455318 | G79: CUIT | H79: 20131067446 | I79: TRIVEÑO ROMA RAMON | J79: 1 | K79: $ | L79: 278865.6 | M79: 0 | N79: 0 | O79: 0 | P79: 58561.78 | Q79: 337427.38
A80: 19/09/2024 | B80: 1 - Factura A | C80: 11 | D80: 91964 | F80: 74384582154669 | G80: CUIT | H80: 30526582884 | I80: EXPRESO MAR DEL PLATA SOCIEDAD ANONIMA | J80: 1 | K80: $ | L80: 4462.81 | M80: 0 | N80: 0 | O80: 0 | P80: 937.19 | Q80: 5400
A81: 19/09/2024 | B81: 11 - Factura C | C81: 3 | D81: 991 | F81: 74389582435775 | G81: CUIT | H81: 20216451679 | I81: VAZQUEZ RICARDO OSCAR | J81: 1 | K81: $ | O81: 0 | Q81: 160000
A82: 19/09/2024 | B82: 11 - Factura C | C82: 1 | D82: 251 | F82: 74395444759490 | G82: CUIT | H82: 27217606255 | I82: SAPUNA MIRIAN KARINA | J82: 1 | K82: $ | O82: 0 | Q82: 96357.85
A83: 19/09/2024 | B83: 11 - Factura C | C83: 1 | D83: 252 | F83: 74395445013622 | G83: CUIT | H83: 27217606255 | I83: SAPUNA MIRIAN KARINA | J83: 1 | K83: $ | O83: 0 | Q83: 105117.66
A84: 20/09/2024 | B84: 1 - Factura A | C84: 2171 | D84: 6478 | F84: 74386729481785 | G84: CUIT | H84: 30548083156 | I84: COTO CENTRO INTEGRAL DE COMERCIALIZACION SOCIEDAD ANONIMA | J84: 1 | K84: $ | L84: 4109.47 | M84: 0 | N84: 0 | O84: 328.75 | P84: 862.99 | Q84: 5301.21
A85: 20/09/2024 | B85: 1 - Factura A | C85: 17 | D85: 2312 | F85: 74381728297239 | G85: CUIT | H85: 30711764921 | I85: RELIEF CENTER S.R.L. | J85: 1 | K85: $ | L85: 21394 | M85: 0 | N85: 0 | O85: 0 | P85: 4492.74 | Q85: 25886.74
A86: 20/09/2024 | B86: 1 - Factura A | C86: 5 | D86: 3877 | F86: 74380716025151 | G86: CUIT | H86: 20348485580 | I86: NOLASCO ALAN MANUEL | J86: 1 | K86: $ | L86: 29099.82 | M86: 0 | N86: 0 | O86: 0 | P86: 6110.96 | Q86: 35210.78
A87: 20/09/2024 | B87: 1 - Factura A | C87: 5 | D87: 1937 | F87: 74386708279049 | G87: CUIT | H87: 30712187316 | I87: ITALOMED PRODUCTOS SRL | J87: 1 | K87: $ | L87: 213988.29 | M87: 0 | N87: 0 | O87: 0 | P87: 44937.54 | Q87: 258925.83
A88: 20/09/2024 | B88: 1 - Factura A | C88: 2 | D88: 250 | F88: 74383655585682 | G88: CUIT | H88: 27144282383 | I88: SCHEJTER LILA ELISA | J88: 1 | K88: $ | L88: 320000 | M88: 0 | N88: 0 | O88: 0 | P88: 67200 | Q88: 387200
A89: 20/09/2024 | B89: 1 - Factura A | C89: 4 | D89: 136 | F89: 74386719534162 | G89: CUIT | H89: 20317488476 | I89: VILLALBA MIGUEL ANGEL | J89: 1 | K89: $ | L89: 1870000 | M89: 0 | N89: 0 | O89: 0 | P89: 392700 | Q89: 2262700
A90: 20/09/2024 | B90: 11 - Factura C | C90: 1 | D90: 253 | F90: 74395446386733 | G90: CUIT | H90: 27217606255 | I90: SAPUNA MIRIAN KARINA | J90: 1 | K90: $ | O90: 0 | Q90: 87598.05
A91: 21/09/2024 | B91: 11 - Factura C | C91: 1 | D91: 14 | F91: 74395449158811 | G91: CUIT | H91: 27443612705 | I91: MIGOYA MORIONDO MARIA INES | J91: 1 | K91: $ | O91: 0 | Q91: 600000
A92: 23/09/2024 | B92: 1 - Factura A | C92: 5 | D92: 3128526 | F92: 74395012609092 | G92: CUIT | H92: 30702652975 | I92: NSS SA | J92: 1 | K92: $ | L92: 28530.17 | M92: 0 | N92: 0 | O92: 0 | P92: 5991.34 | Q92: 35948.01
A93: 23/09/2024 | B93: 1 - Factura A | C93: 5015 | D93: 648091 | F93: 74394947432580 | G93: CUIT | H93: 30574876474 | I93: AUTOPISTAS URBANAS S A | J93: 1 | K93: $ | L93: 17107.75 | M93: 0 | N93: 0 | O93: 0 | P93: 3592.62 | Q93: 22924.37
A94: 23/09/2024 | B94: 1 - Factura A | C94: 700 | D94: 1936359 | F94: 74392989880786 | G94: CUIT | H94: 30715804812 | I94: CORREDORES VIALES SOCIEDAD ANONIMA | J94: 1 | K94: $ | L94: 6246.93 | M94: 0 | N94: 0 | O94: 0 | P94: 1311.86 | Q94: 7871.14
A95: 23/09/2024 | B95: 1 - Factura A | C95: 700 | D95: 1936360 | F95: 74392989880804 | G95: CUIT | H95: 30715804812 | I95: CORREDORES VIALES SOCIEDAD ANONIMA | J95: 1 | K95: $ | L95: 728.62 | M95: 0 | N95: 0 | O95: 0 | P95: 153.01 | Q95: 881.63
A96: 23/09/2024 | B96: 1 - Factura A | C96: 6 | D96: 85435 | F96: 74394006853805 | G96: CUIT | H96: 30711553564 | I96: SALUDTEX SA | J96: 1 | K96: $ | L96: 999126 | M96: 0 | N96: 0 | O96: 0 | P96: 209816.46 | Q96: 1208942.5
A97: 23/09/2024 | B97: 1 - Factura A | C97: 6 | D97: 54307 | F97: 74398009565100 | G97: CUIT | H97: 30710177658 | I97: TARGET MEDICAL S.A. | J97: 1 | K97: $ | L97: 122080.32 | M97: 0 | N97: 0 | O97: 0 | P97: 25636.86 | Q97: 147717.18
A98: 24/09/2024 | B98: 1 - Factura A | C98: 1055 | D98: 854 | F98: 74391072835510 | G98: CUIT | H98: 30685849751 | I98: DIA ARGENTINA S A | J98: 1 | K98: $ | L98: 6165.28 | M98: 0 | N98: 0 | O98: 0 | P98: 1294.71 | Q98: 7768.25
A99: 24/09/2024 | B99: 1 - Factura A | C99: 2 | D99: 25 | F99: 74395124728024 | G99: CUIT | H99: 27243660535 | I99: BARD MARISA SILVIA | J99: 1 | K99: $ | L99: 360000 | M99: 0 | N99: 0 | O99: 0 | P99: 75600 | Q99: 435600
A100: 25/09/2024 | B100: 1 - Factura A | C100: 6 | D100: 54346 | F100: 74398248406433 | G100: CUIT | H100: 30710177658 | I100: TARGET MEDICAL S.A. | J100: 1 | K100: $ | L100: 356854.44 | M100: 0 | N100: 0 | O100: 0 | P100: 74939.44 | Q100: 431793.88
A101: 25/09/2024 | B101: 1 - Factura A | C101: 4 | D101: 71892 | F101: 74399186438923 | G101: CUIT | H101: 33709738459 | I101: ORTOPEDICOS ALFOLATEX SA | J101: 1 | K101: $ | L101: 655324.52 | M101: 0 | N101: 0 | O101: 0 | P101: 137618.15 | Q101: 792942.67
A102: 25/09/2024 | B102: 1 - Factura A | C102: 4 | D102: 137 | F102: 74396233311030 | G102: CUIT | H102: 20317488476 | I102: VILLALBA MIGUEL ANGEL | J102: 1 | K102: $ | L102: 105000 | M102: 0 | N102: 0 | O102: 0 | P102: 22050 | Q102: 127050
A103: 26/09/2024 | B103: 1 - Factura A | C103: 6 | D103: 54365 | F103: 74398371535029 | G103: CUIT | H103: 30710177658 | I103: TARGET MEDICAL S.A. | J103: 1 | K103: $ | L103: 682125 | M103: 0 | N103: 0 | O103: 0 | P103: 143246.25 | Q103: 825371.25
... A112: 27/09/2024 | B112: 1 - Factura A | C112: 2 | D112: 819 | F112: 74399429730188 | G112: CUIT | H112: 20272865869 | I112: DI FEO MARTIN EZEQUIEL | J112: 1 | K112: $ | L112: 105000 | M112: 0 | N112: 0 | O112: 0 | P112: 22050 | Q112: 127050
A113: 27/09/2024 | B113: 11 - Factura C | C113: 3 | D113: 995 | F113: 74399453320296 | G113: CUIT | H113: 20216451679 | I113: VAZQUEZ RICARDO OSCAR | J113: 1 | K113: $ | O113: 0 | Q113: 160000
A114: 28/09/2024 | B114: 1 - Factura A | C114: 2189 | D114: 77373 | F114: 74396609730132 | G114: CUIT | H114: 30548083156 | I114: COTO CENTRO INTEGRAL DE COMERCIALIZACION SOCIEDAD ANONIMA | J114: 1 | K114: $ | L114: 3905.09 | M114: 0 | N114: 0 | O114: 312.4 | P114: 820.07 | Q114: 5037.56
A115: 28/09/2024 | B115: 1 - Factura A | C115: 2 | D115: 336 | F115: 74409928953266 | G115: CUIT | H115: 27251962559 | I115: CHIARA FLORENCIA | J115: 1 | K115: $ | L115: 42396.71 | M115: 0 | N115: 0 | O115: 0 | P115: 8903.31 | Q115: 51300.01
A116: 29/09/2024 | B116: 1 - Factura A | C116: 25 | D116: 2868796 | F116: 74404735015283 | G116: CUIT | H116: 30703088534 | I116: MERCADOLIBRE S.R.L. | J116: 1 | K116: $ | L116: 37574.04 | M116: 0 | N116: 0 | O116: 3005.92 | P116: 7890.55 | Q116: 48470.51
A117: 30/09/2024 | B117: 1 - Factura A | C117: 6 | D117: 17452146 | F117: 74397511039418 | G117: CUIT | H117: 30620177497 | I117: POSNET SOCIEDAD DE RESPONSABILIDAD LIMITADA | J117: 1 | K117: $ | L117: 0 | M117: 0 | N117: 0 | O117: 0 | P117: 0 | Q117: 0
A118: 30/09/2024 | B118: 1 - Factura A | C118: 6 | D118: 17599524 | F118: 74397542581741 | G118: CUIT | H118: 30620177497 | I118: POSNET SOCIEDAD DE RESPONSABILIDAD LIMITADA | J118: 1 | K118: $ | L118: 26164.14 | M118: 0 | N118: 0 | O118: 0 | P118: 5494.47 | Q118: 33751.74
A119: 30/09/2024 | B119: 1 - Factura A | C119: 5015 | D119: 650706 | F119: 74404997363928 | G119: CUIT | H119: 30574876474 | I119: AUTOPISTAS URBANAS S A | J119: 1 | K119: $ | L119: 24879.27 | M119: 0 | N119: 0 | O119: 0 | P119: 5224.63 | Q119: 33338.2
A120: 30/09/2024 | B120: 1 - Factura A | C120: 20 | D120: 197792 | F120: 74402907225580 | G120: CUIT | H120: 30696850972 | I120: C.P.S. COMUNICACIONES S.A. | J120: 1 | K120: $ | L120: 19732.58 | M120: 0 | N120: 0 | O120: 0 | P120: 5327.8 | Q120: 26047.02
A121: 30/09/2024 | B121: 1 - Factura A | C121: 1 | D121: 591606 | F121: 74409955268089 | G121: CUIT | H121: 33716307749 | I121: VERISURE ARGENTINA MONITOREO DE ALARMAS SA | J121: 1 | K121: $ | L121: 318999 | M121: 0 | N121: 0 | O121: 0 | P121: 66989.79 | Q121: 401938.74
...

Sheet Hoja3
A1: Comprobante no recibido
A4: Fecha | B4: Comprobante | C4: Nombre | D4: Cond. IVA | E4: CUIT o Doc. | F4: Gravado | G4: No Gravado
A5: 02/09/2024 | B5: FA-C 0003-00000874 | C5: BOTINDARI JUAN CARLOS | D5: Responsable Monotributo | E5: 20086277523 | F5: 0 | G5: 275500
A6: 02/09/2024 | B6: 874 | C6: BOTINDARI JUAN CARLOS | E6: 20086277523
A7: 19/09/2024 | B7: FA-A 0007-00006066 | C7: Triveño Roma, Ramon | D7: IVA Responsable Inscripto | E7: 20131067446 | F7: 278865.6 | G7: 0
A8: 19/09/2024 | B8: 6066 | C8: TRIVEÑO ROMA RAMON | E8: 20131067446 | F8: 278865.6 | G8: 0
A9: 10/09/2024 | B9: FA-A 0003-00004250 | C9: Aboud, Pablo Daniel | D9: IVA Responsable Inscripto | E9: 20184052858 | F9: 16859.46 | G9: 0
A10: 30/09/2024 | B10: FA-A 0003-00004276 | C10: Aboud, Pablo Daniel | D10: IVA Responsable Inscripto | E10: 20184052858 | F10: 71074.3 | G10: 0
A11: 10/09/2024 | B11: 4250 | C11: ABOUD PABLO DANIEL | E11: 20184052858 | F11: 16859.48 | G11: 0
A12: 30/09/2024 | B12: 4276 | C12: ABOUD PABLO DANIEL | E12: 20184052858 | F12: 71074.33 | G12: 0
A13: 30/09/2024 | B13: 804 | C13: PAIS HECTOR GUILLERMO | E13: 20214946867 | F13: 37189.24 | G13: 0
A14: 10/09/2024 | B14: FA-C 0003-00000986 | C14: Vazquez, Ricardo Oscar | D14: Responsable Monotributo | E14: 20216451679 | F14: 0 | G14: 86000
A15: 27/09/2024 | B15: FA-C 0003-00000995 | C15: Vazquez, Ricardo Oscar | D15: Responsable Monotributo | E15: 20216451679 | F15: 0 | G15: 160000
A16: 10/09/2024 | B16: 986 | C16: VAZQUEZ RICARDO OSCAR | E16: 20216451679
A17: 19/09/2024 | B17: 991 | C17: VAZQUEZ RICARDO OSCAR | E17: 20216451679
A18: 27/09/2024 | B18: 995 | C18: VAZQUEZ RICARDO OSCAR | E18: 20216451679
A19: 12/09/2024 | B19: FA-A 0002-00000778 | C19: Di Feo, Martin Ezequiel | D19: IVA Responsable Inscripto | E19: 20272865869 | F19: 128100 | G19: 0
A20: 13/09/2024 | B20: FA-A 0002-00000783 | C20: Di Feo, Martin Ezequiel | D20: IVA Responsable Inscripto | E20: 20272865869 | F20: 9950 | G20: 0
A21: 19/09/2024 | B21: FA-A 0002-00000796 | C21: Di Feo, Martin Ezequiel | D21: IVA Responsable Inscripto | E21: 20272865869 | F21: 253100 | G21: 0
A22: 27/09/2024 | B22: FA-A 0002-00000816 | C22: Di Feo, Martin Ezequiel | D22: IVA Responsable Inscripto | E22: 20272865869 | F22: 9800 | G22: 0
A23: 27/09/2024 | B23: FA-A 0002-00000819 | C23: Di Feo, Martin Ezequiel | D23: IVA Responsable Inscripto | E23: 20272865869 | F23: 105000 | G23: 0
A24: 30/09/2024 | B24: FA-A 0002-00000814 | C24: Di Feo, Martin Ezequiel | D24: IVA Responsable Inscripto | E24: 20272865869 | F24: 149150 | G24: 0
A25: 05/09/2024 | B25: 760 | C25: DI FEO MARTIN EZEQUIEL | E25: 20272865869 | F25: 84450 | G25: 0
A26: 12/09/2024 | B26: 778 | C26: DI FEO MARTIN EZEQUIEL | E26: 20272865869 | F26: 128100 | G26: 0
A27: 13/09/2024 | B27: 783 | C27: DI FEO MARTIN EZEQUIEL | E27: 20272865869 | F27: 9950 | G27: 0
A28: 19/09/2024 | B28: 796 | C28: DI FEO MARTIN EZEQUIEL | E28: 20272865869 | F28: 253100 | G28: 0
A29: 26/09/2024 | B29: 814 | C29: DI FEO MARTIN EZEQUIEL | E29: 20272865869 | F29: 149150 | G29: 0
A30: 27/09/2024 | B30: 816 | C30: DI FEO MARTIN EZEQUIEL | E30: 20272865869 | F30: 9800 | G30: 0
A31: 27/09/2024 | B31: 819 | C31: DI FEO MARTIN EZEQUIEL | E31: 20272865869 | F31: 105000 | G31: 0
A32: 04/09/2024 | B32: FA-A 0007-00003241 | C32: Furlanetto, Martin | D32: IVA Responsable Inscripto | E32: 20284183534 | F32: 4545.5 | G32: 0
A33: 26/09/2024 | B33: TF-A0007-00003292 | C33: Furlanetto, Martin | D33: IVA Responsable Inscripto | E33: 20284183534 | F33: 9504.13 | G33: 0
A34: 04/09/2024 | B34: 3241 | C34: FURLANETTO MARTIN | E34: 20284183534 | F34: 4545.5 | G34: 0
A35: 26/09/2024 | B35: 3292 | C35: FURLANETTO MARTIN | E35: 20284183534 | F35: 9504.13 | G35: 0
A36: 12/09/2024 | B36: FA-A 0004-00038394 | C36: Ledesma, Emiliano Ruben | D36: IVA Responsable Inscripto | E36: 20289111329 | F36: 585730.8 | G36: 0
A37: 12/09/2024 | B37: 38394 | C37: LEDESMA EMILIANO RUBEN | E37: 20289111329 | F37: 585730.8 | G37: 0
A38: 20/09/2024 | B38: FA-A 0004-00000136 | C38: Villalba, Miguel Angel | D38: IVA Responsable Inscripto | E38: 20317488476 | F38: 1870000 | G38: 0
A39: 25/09/2024 | B39: FA-A 0004-00000137 | C39: Villalba, Miguel Angel | D39: IVA Responsable Inscripto | E39: 20317488476 | F39: 105000 | G39: 0
A40: 20/09/2024 | B40: 136 | C40: VILLALBA MIGUEL ANGEL | E40: 20317488476 | F40: 1870000 | G40: 0
A41: 25/09/2024 | B41: 137 | C41: VILLALBA MIGUEL ANGEL | E41: 20317488476 | F41: 105000 | G41: 0
A42: 13/09/2024 | B42: NC-A 0003-00000017 | C42: Nardomarino, Ezequiel Eduardo | D42: IVA Responsable Inscripto | E42: 20334976433 | F42: -188330 | G42: 0
A43: 13/09/2024 | B43: FA-A 0003-00000170 | C43: Nardomarino, Ezequiel Eduardo | D43: IVA Responsable Inscripto | E43: 20334976433 | F43: 188330 | G43: 0
A44: 13/09/2024 | B44: FA-A 0003-00000171 | C44: Nardomarino, Ezequiel Eduardo | D44: IVA Responsable Inscripto | E44: 20334976433 | F44: 153000 | G44: 0
A45: 26/09/2024 | B45: FA-A 0003-00000172 | C45: Nardomarino, Ezequiel Eduardo | D45: IVA Responsable Inscripto | E45: 20334976433 | F45: 90000 | G45: 0
A46: 13/09/2024 | B46: 170 | C46: NARDOMARINO EZEQUIEL EDUARDO | E46: 20334976433 | F46: 188330 | G46: 0
A47: 13/09/2024 | B47: 171 | C47: NARDOMARINO EZEQUIEL EDUARDO | E47: 20334976433 | F47: 153000 | G47: 0
A48: 13/09/2024 | B48: 17 | C48: NARDOMARINO EZEQUIEL EDUARDO | E48: 20334976433 | F48: 188330 | G48: 0
A49: 26/09/2024 | B49: 172 | C49: NARDOMARINO EZEQUIEL EDUARDO | E49: 20334976433 | F49: 90000 | G49: 0
A50: 20/09/2024 | B50: FA-A 0005-00003877 | C50: NOLASCO ALAN MANUEL | D50: IVA Responsable Inscripto | E50: 20348485580 | F50: 29099.82 | G50: 0
A51: 20/09/2024 | B51: 3877 | C51: NOLASCO ALAN MANUEL | E51: 20348485580 | F51: 29099.82 | G51: 0
A52: 11/09/2024 | B52: FA-C 0001-00000009 | C52: Oviedo Jimenez, Tiziano Lionel | D52: Responsable Monotributo | E52: 20464199633 | F52: 0 | G52: 499950
A53: 11/09/2024 | B53: 9 | C53: OVIEDO JIMENEZ TIZIANO LIONEL | E53: 20464199633
A54: 26/09/2024 | B54: FA-A 0005-00000032 | C54: MA JUN | D54: IVA Responsable Inscripto | E54: 20929183143 | F54: 50000 | G54: 0
A55: 26/09/2024 | B55: 32 | C55: MA JUN | E55: 20929183143 | F55: 50000 | G55: 0
A56: 18/09/2024 | B56: FA-C 0001-00000070 | C56: Druetta, Andrea Mariel | D56: Responsable Monotributo | E56: 23281233084 | F56: 0 | G56: 215000
A57: 18/09/2024 | B57: FA-C 0001-00000071 | C57: Druetta, Andrea Mariel | D57: Responsable Monotributo | E57: 23281233084 | F57: 0 | G57: 215000
A58: 18/09/2024 | B58: 70 | C58: DRUETTA ANDREA MARIEL | E58: 23281233084
A59: 18/09/2024 | B59: 71 | C59: DRUETTA ANDREA MARIEL | E59: 23281233084
A60: 15/09/2024 | B60: 168 | C60: FERREIRA LILIANA INES | E60: 27062343449
A61: 15/09/2024 | B61: 169 | C61: FERREIRA LILIANA INES | E61: 27062343449
A62: 27/08/2024 | B62: TF-A0005-00002285 | C62: Espada Faraldo, Margarita Mercedes | D62: IVA Responsable Inscripto | E62: 27114789033 | F62: 56363.64 | G62: 0
A63: 28/08/2024 | B63: TF-A0005-00002291 | C63: Espada Faraldo, Margarita Mercedes | D63: IVA Responsable Inscripto | E63: 27114789033 | F63: 10991.74 | G63: 0
A64: 13/09/2024 | B64: FA-A 0002-00004940 | C64: Manzini, Marta Graciela | D64: IVA Responsable Inscripto | E64: 27117233745 | F64: 585519 | G64: 0
A65: 18/09/2024 | B65: FA-A 0002-00004942 | C65: Manzini, Marta Graciela | D65: IVA Responsable Inscripto | E65: 27117233745 | F65: 585519 | G65: 0
A66: 13/09/2024 | B66: 4940 | C66: MANZINI MARTA GRACIELA | E66: 27117233745 | F66: 585519 | G66: 0
A67: 18/09/2024 | B67: 4942 | C67: MANZINI MARTA GRACIELA | E67: 27117233745 | F67: 585519 | G67: 0
A68: 02/09/2024 | B68: FA-A 0002-00000248 | C68: Schejter, Lila Elisa | D68: IVA Responsable Inscripto | E68: 27144282383 | F68: 160000 | G68: 0
A69: 16/09/2024 | B69: FA-A 0002-00000249 | C69: Schejter, Lila Elisa | D69: IVA Responsable Inscripto | E69: 27144282383 | F69: 320000 | G69: 0
A70: 20/09/2024 | B70: FA-A 0002-00000250 | C70: Schejter, Lila Elisa | D70: IVA Responsable Inscripto | E70: 27144282383 | F70: 320000 | G70: 0
A71: 26/09/2024 | B71: FA-A 0002-00000252 | C71: Schejter, Lila Elisa | D71: IVA Responsable Inscripto | E71: 27144282383 | F71: 300000 | G71: 0
A72: 02/09/2024 | B72: 248 | C72: SCHEJTER LILA ELISA | E72: 27144282383 | F72: 160000 | G72: 0
A73: 16/09/2024 | B73: 249 | C73: SCHEJTER LILA ELISA | E73: 27144282383 | F73: 320000 | G73: 0
A74: 20/09/2024 | B74: 250 | C74: SCHEJTER LILA ELISA | E74: 27144282383 | F74: 320000 | G74: 0
A75: 26/09/2024 | B75: 252 | C75: SCHEJTER LILA ELISA | E75: 27144282383 | F75: 300000 | G75: 0
A76: 17/09/2024 | B76: FA-C 0001-00000247 | C76: Sapuna, Mirian Karina | D76: Responsable Monotributo | E76: 27217606255 | F76: 0 | G76: 56703.42
A77: 17/09/2024 | B77: FA-C 0001-00000248 | C77: Sapuna, Mirian Karina | D77: Responsable Monotributo | E77: 27217606255 | F77: 0 | G77: 50223.03
A78: 18/09/2024 | B78: FA-C 0001-00000249 | C78: Sapuna, Mirian Karina | D78: Responsable Monotributo | E78: 27217606255 | F78: 0 | G78: 55083.32
A79: 18/09/2024 | B79: FA-C 0001-00000250 | C79: Sapuna, Mirian Karina | D79: Responsable Monotributo | E79: 27217606255 | F79: 0 | G79: 148916.68
A80: 19/09/2024 | B80: FA-C 0001-00000251 | C80: Sapuna, Mirian Karina | D80: Responsable Monotributo | E80: 27217606255 | F80: 0 | G80: 96357.85
A81: 19/09/2024 | B81: FA-C 0001-00000252 | C81: Sapuna, Mirian Karina | D81: Responsable Monotributo | E81: 27217606255 | F81: 0 | G81: 105117.66
A82: 20/09/2024 | B82: FA-C 0001-00000253 | C82: Sapuna, Mirian Karina | D82: Responsable Monotributo | E82: 27217606255 | F82: 0 | G82: 87598.05
A83: 17/09/2024 | B83: 248 | C83: SAPUNA MIRIAN KARINA | E83: 27217606255
A84: 17/09/2024 | B84: 247 | C84: SAPUNA MIRIAN KARINA | E84: 27217606255
A85: 18/09/2024 | B85: 249 | C85: SAPUNA MIRIAN KARINA | E85: 27217606255
A86: 18/09/2024 | B86: 250 | C86: SAPUNA MIRIAN KARINA | E86: 27217606255
A87: 19/09/2024 | B87: 251 | C87: SAPUNA MIRIAN KARINA | E87: 27217606255
A88: 19/09/2024 | B88: 252 | C88: SAPUNA MIRIAN KARINA | E88: 27217606255
A89: 20/09/2024 | B89: 253 | C89: SAPUNA MIRIAN KARINA | E89: 27217606255
A90: 24/09/2024 | B90: FA-A 0002-00000025 | C90: Bard, Marisa Silvia | D90: IVA Responsable Inscripto | E90: 27243660535 | F90: 360000 | G90: 0
A91: 24/09/2024 | B91: 25 | C91: BARD MARISA SILVIA | E91: 27243660535 | F91: 360000 | G91: 0
A92: 28/09/2024 | B92: 336 | C92: CHIARA FLORENCIA | E92: 27251962559 | F92: 42396.71 | G92: 0
A93: 02/09/2024 | B93: FA-C 0002-00000302 | C93: Blasco, Maria Guadalupe | D93: Responsable Monotributo | E93: 27265832178 | F93: 0 | G93: 250000
A94: 02/09/2024 | B94: 302 | C94: BLASCO MARIA GUADALUPE | E94: 27265832178
A95: 02/09/2024 | B95: FA-A 0005-00000102 | C95: Andreani, Agustina Susana | D95: IVA Responsable Inscripto | E95: 27329449357 | F95: 64100 | G95: 16400
A96: 02/09/2024 | B96: 102 | C96: ANDREANI AGUSTINA SUSANA | E96: 27329449357 | F96: 64100 | G96: 16400
A97: 09/09/2024 | B97: FA-C 0001-00000148 | C97: Cancino, Pamela Rita | D97: Responsable Monotributo | E97: 27338342840 | F97: 0 | G97: 276800
A98: 09/09/2024 | B98: 148 | C98: CANCINO PAMELA RITA | E98: 27338342840
A99: 10/09/2024 | B99: FA-A 0002-00008403 | C99: Hecker, Laura Noemi | D99: IVA Responsable Inscripto | E99: 27363810182 | F99: 3635.54 | G99: 0
A100: 10/09/2024 | B100: 8403 | C100: HECKER LAURA NOEMI | E100: 27363810182 | F100: 3635.54 | G100: 0
A101: 21/09/2024 | B101: FA-C 0001-00000014 | C101: Migoya Moriondo, Maria Ines | D101: Responsable Monotributo | E101: 27443612705 | F101: 0 | G101: 600000
A102: 21/09/2024 | B102: 14 | C102: MIGOYA MORIONDO MARIA INES | E102: 27443612705
...

Sheet Hoja1
A2: Mis Comprobantes Recibidos - CUIT 30710473168
A3: Fecha | B3: Tipo | C3: Punto de Venta | D3: Número Desde | E3: Número Hasta | F3: Cód. Autorización | G3: Tipo Doc. Emisor | H3: Nro. Doc. Emisor | I3: Denominación Emisor | J3: Tipo Cambio | K3: Moneda | L3: Imp. Neto Gravado | M3: Imp. Neto No Gravado | N3: Imp. Op. Exentas | O3: Otros Tributos | P3: IVA | Q3: Imp. Total
A4: 02/12/2024 | B4: 1 - Factura A | C4: 500 | D4: 1655637 | F4: 74487074766855 | G4: CUIT | H4: 30654118767 | I4: SOLUCIONES MULTIMEDIA S A | J4: 1 | K4: $ | L4: 105092.93 | M4: 0 | N4: 0 | O4: 5239.3 | P4: 22069.52 | Q4: 132401.75
A5: 02/12/2024 | B5: 1 - Factura A | C5: 6 | D5: 55227 | F5: 74498346789752 | G5: CUIT | H5: 30710177658 | I5: TARGET MEDICAL S.A. | J5: 1 | K5: $ | L5: 412110 | M5: 0 | N5: 0 | O5: 0 | P5: 86543.1 | Q5: 498653.1
A6: 02/12/2024 | B6: 1 - Factura A | C6: 4 | D6: 38976 | F6: 74499359858810 | G6: CUIT | H6: 20289111329 | I6: LEDESMA EMILIANO RUBEN | J6: 1 | K6: $ | L6: 2174566 | M6: 0 | N6: 0 | O6: 0 | P6: 456658.86 | Q6: 2631224.9
A7: 02/12/2024 | B7: 1 - Factura A | C7: 6 | D7: 55223 | F7: 74498341856485 | G7: CUIT | H7: 30710177658 | I7: TARGET MEDICAL S.A. | J7: 1 | K7: $ | L7: 3760920 | M7: 0 | N7: 0 | O7: 150436.8 | P7: 789793.2 | Q7: 4701150
A8: 02/12/2024 | B8: 1 - Factura A | C8: 711 | D8: 6455819 | F8: 34489322171051 | G8: CUIT | H8: 30677237119 | I8: AUTOPISTAS DEL SOL S A | J8: 1 | K8: $ | L8: 11433.18 | M8: 0 | N8: 343 | O8: 457.33 | P8: 2400.93 | Q8: 14634.44
A9: 02/12/2024 | B9: 1 - Factura A | C9: 101 | D9: 8845 | F9: 74499306271092 | G9: CUIT | H9: 33711430879 | I9: BALANZE S.A. | J9: 1 | K9: $ | L9: 1328291 | M9: 0 | N9: 0 | O9: 0 | P9: 278941.11 | Q9: 1607232.1
A10: 02/12/2024 | B10: 1 - Factura A | C10: 629 | D10: 5656259 | F10: 34483250539705 | G10: CUIT | H10: 30663498513 | I10: GRUPO CONCESIONARIO DEL OESTE SA | J10: 1 | K10: $ | L10: 558.01 | M10: 0 | N10: 0 | O10: 22.32 | P10: 117.18 | Q10: 697.51
A11: 02/12/2024 | B11: 1 - Factura A | C11: 3051 | D11: 844548 | F11: 74497516477337 | G11: CUIT | H11: 30678814357 | I11: TELEFONICA MOVILES ARGENTINA SOCIEDAD ANONIMA | J11: 1 | K11: $ | L11: 53954 | M11: 0 | N11: 0 | O11: 6730.02 | P11: 14567.58 | Q11: 75251.6
A12: 02/12/2024 | B12: 11 - Factura C | C12: 3 | D12: 905 | F12: 74493324806048 | G12: CUIT | H12: 20086277523 | I12: BOTINDARI JUAN CARLOS | J12: 1 | K12: $ | O12: 0 | Q12: 275500
A13: 02/12/2024 | B13: 11 - Factura C | C13: 2 | D13: 319 | F13: 74498730251438 | G13: CUIT | H13: 27265832178 | I13: BLASCO MARIA GUADALUPE | J13: 1 | K13: $ | O13: 0 | Q13: 3200000
A14: 03/12/2024 | B14: 1 - Factura A | C14: 1 | D14: 109430 | F14: 74499429713404 | G14: CUIT | H14: 30714864269 | I14: CONTABILIUM S.A. S. A. | J14: 1 | K14: $ | L14: 139127 | M14: 0 | N14: 0 | O14: 0 | P14: 29216.67 | Q14: 168343.67
A15: 03/12/2024 | B15: 1 - Factura A | C15: 1 | D15: 5589 | F15: 74491435507330 | G15: CUIT | H15: 30715141201 | I15: REHAB S.R.L. | J15: 1 | K15: $ | L15: 139185 | M15: 0 | N15: 0 | O15: 0 | P15: 29228.85 | Q15: 168413.85
A16: 03/12/2024 | B16: 1 - Factura A | C16: 4 | D16: 38981 | F16: 74499427712370 | G16: CUIT | H16: 20289111329 | I16: LEDESMA EMILIANO RUBEN | J16: 1 | K16: $ | L16: 727465.05 | M16: 0 | N16: 0 | O16: 0 | P16: 152767.66 | Q16: 880232.71
A17: 03/12/2024 | B17: 1 - Factura A | C17: 5 | D17: 161604 | F17: 74493439495197 | G17: CUIT | H17: 30598960093 | I17: SILVESTRIN FABRIS SOC RESP LTDA | J17: 1 | K17: $ | L17: 2554513.5 | M17: 0 | N17: 0 | O17: 102180.54 | P17: 536447.84 | Q17: 3193141.9
A18: 03/12/2024 | B18: 1 - Factura A | C18: 2 | D18: 223 | F18: 74492464692349 | G18: CUIT | H18: 30605344352 | I18: CONSORCIO BARTOLOME MITRE 2466 | J18: 1 | K18: $ | L18: 834000 | M18: 0 | N18: 0 | O18: 0 | P18: 175140 | Q18: 1009140
A19: 03/12/2024 | B19: 11 - Factura C | C19: 3 | D19: 61 | F19: 74499463827512 | G19: CUIT | H19: 23163457369 | I19: ASTORGA JORGE DANIEL | J19: 1 | K19: $ | O19: 0 | Q19: 450000
A20: 03/12/2024 | B20: 11 - Factura C | C20: 1 | D20: 162 | F20: 74490436597806 | G20: CUIT | H20: 27338342840 | I20: CANCINO PAMELA RITA | J20: 1 | K20: $ | O20: 0 | Q20: 130800
A21: 04/12/2024 | B21: 1 - Factura A | C21: 4 | D21: 20038 | F21: 74493616266425 | G21: CUIT | H21: 30504854023 | I21: NYLTEF SAICF | J21: 1 | K21: $ | L21: 72100 | M21: 0 | N21: 0 | O21: 2884 | P21: 15141 | Q21: 90125
A22: 04/12/2024 | B22: 1 - Factura A | C22: 7 | D22: 26242 | F22: 74497593058098 | G22: CUIT | H22: 30710951647 | I22: SOLUCIONES TECNOLOGICAS INTEGRALES SRL | J22: 1 | K22: $ | L22: 156102.4 | M22: 0 | N22: 0 | O22: 7805.12 | P22: 16390.75 | Q22: 180298.27
A23: 04/12/2024 | B23: 1 - Factura A | C23: 1 | D23: 666828 | F23: 74499002078073 | G23: CUIT | H23: 33716307749 | I23: VERISURE ARGENTINA MONITOREO DE ALARMAS SA | J23: 1 | K23: $ | L23: 41128 | M23: 0 | N23: 0 | O23: 1645.12 | P23: 8636.88 | Q23: 51410
A24: 04/12/2024 | B24: 1 - Factura A | C24: 4 | D24: 145 | F24: 74496651400602 | G24: CUIT | H24: 20317488476 | I24: VILLALBA MIGUEL ANGEL | J24: 1 | K24: $ | L24: 1155000 | M24: 0 | N24: 0 | O24: 0 | P24: 242550 | Q24: 1397550
A25: 04/12/2024 | B25: 3 - Nota de Crédito A | C25: 4 | D25: 3139 | F25: 74499588156578 | G25: CUIT | H25: 20289111329 | I25: LEDESMA EMILIANO RUBEN | J25: 1 | K25: $ | L25: 727465.05 | M25: 0 | N25: 0 | O25: 0 | P25: 152767.66 | Q25: 880232.71
A26: 05/12/2024 | B26: 1 - Factura A | C26: 7 | D26: 19690 | F26: 74498787252978 | G26: CUIT | H26: 30709214078 | I26: REHAVITA S.A. | J26: 1 | K26: $ | L26: 192492 | M26: 0 | N26: 0 | O26: 0 | P26: 40423.32 | Q26: 232915.32
A27: 05/12/2024 | B27: 1 - Factura A | C27: 2 | D27: 963 | F27: 74499785646902 | G27: CUIT | H27: 20272865869 | I27: DI FEO MARTIN EZEQUIEL | J27: 1 | K27: $ | L27: 93200.04 | M27: 0 | N27: 0 | O27: 0 | P27: 19572.01 | Q27: 112772.05
A28: 05/12/2024 | B28: 1 - Factura A | C28: 2 | D28: 26398 | F28: 74498783507894 | G28: CUIT | H28: 30642604488 | I28: HORIZONTE TRANSPORTES S R L | J28: 1 | K28: $ | L28: 67400 | M28: 0 | N28: 0 | O28: 0 | P28: 14154 | Q28: 81554
A29: 05/12/2024 | B29: 1 - Factura A | C29: 120 | D29: 5406 | F29: 74495750310742 | G29: CUIT | H29: 30587197215 | I29: PANATEL SOCIEDAD ANONIMA | J29: 1 | K29: $ | L29: 95041.32 | M29: 0 | N29: 0 | O29: 3801.65 | P29: 19958.68 | Q29: 118801.65
A30: 05/12/2024 | B30: 1 - Factura A | C30: 2 | D30: 11064 | F30: 74492783832650 | G30: CUIT | H30: 30714331082 | I30: ORTOPEDIA CASA ESCALADA S.R.L. | J30: 1 | K30: $ | L30: 81488.51 | M30: 0 | N30: 0 | O30: 0 | P30: 17112.59 | Q30: 98601.1
A31: 05/12/2024 | B31: 3 - Nota de Crédito A | C31: 7 | D31: 1322 | F31: 74498786515767 | G31: CUIT | H31: 30709214078 | I31: REHAVITA S.A. | J31: 1 | K31: $ | L31: 59820 | M31: 0 | N31: 0 | O31: 0 | P31: 12562.2 | Q31: 72382.2
A32: 05/12/2024 | B32: 11 - Factura C | C32: 1 | D32: 10 | F32: 74493727645078 | G32: CUIT | H32: 27443612713 | I32: MIGOYA MORIONDO SOFIA | J32: 1 | K32: $ | O32: 0 | Q32: 750000
A33: 06/12/2024 | B33: 1 - Factura A | C33: 2189 | D33: 81012 | F33: 74496980568402 | G33: CUIT | H33: 30548083156 | I33: COTO CENTRO INTEGRAL DE COMERCIALIZACION SOCIEDAD ANONIMA | J33: 1 | K33: $ | L33: 7639.42 | M33: 0 | N33: 0 | O33: 534.76 | P33: 1604.28 | Q33: 9778.46
A34: 06/12/2024 | B34: 1 - Factura A | C34: 5 | D34: 2261 | F34: 74498875569162 | G34: CUIT | H34: 20242126158 | I34: IALLONARDO SERGIO ALEJANDRO | J34: 1 | K34: $ | L34: 16470 | M34: 0 | N34: 0 | O34: 0 | P34: 3458.7 | Q34: 19928.7
A35: 06/12/2024 | B35: 1 - Factura A | C35: 7 | D35: 19693 | F35: 74498883622074 | G35: CUIT | H35: 30709214078 | I35: REHAVITA S.A. | J35: 1 | K35: $ | L35: 151800 | M35: 0 | N35: 0 | O35: 0 | P35: 15939 | Q35: 167739
A36: 06/12/2024 | B36: 1 - Factura A | C36: 3 | D36: 197 | F36: 74503230479910 | G36: CUIT | H36: 20334976433 | I36: NARDOMARINO EZEQUIEL EDUARDO | J36: 1 | K36: $ | L36: 947800 | M36: 0 | N36: 0 | O36: 0 | P36: 199038 | Q36: 1146838
A37: 06/12/2024 | B37: 11 - Factura C | C37: 2 | D37: 1 | F37: 74491890516333 | G37: CUIT | H37: 27344304551 | I37: BOCCACCI MARIA FLORENCIA | J37: 1 | K37: $ | O37: 0
A38: 08/12/2024 | B38: 1 - Factura A | C38: 5015 | D38: 673036 | F38: 74494155013792 | G38: CUIT | H38: 30574876474 | I38: AUTOPISTAS URBANAS S A | J38: 1 | K38: $ | L38: 3329.43 | M38: 0 | N38: 0 | O38: 432.82 | P38: 699.17 | Q38: 4461.42
A39: 09/12/2024 | B39: 1 - Factura A | C39: 12 | D39: 40989 | F39: 74504258923570 | G39: CUIT | H39: 30526582884 | I39: EXPRESO MAR DEL PLATA SOCIEDAD ANONIMA | J39: 1 | K39: $ | L39: 96958.68 | M39: 0 | N39: 0 | O39: 0 | P39: 20361.32 | Q39: 117320
A40: 09/12/2024 | B40: 1 - Factura A | C40: 17 | D40: 11167 | F40: 74500215673228 | G40: CUIT | H40: 30661143610 | I40: ORTOPEDIA BERNAT SRL | J40: 1 | K40: $ | L40: 1328690 | M40: 0 | N40: 0 | O40: 53147.6 | P40: 279024.9 | Q40: 1660862.5
A41: 09/12/2024 | B41: 1 - Factura A | C41: 4 | D41: 39047 | F41: 74509213670602 | G41: CUIT | H41: 20289111329 | I41: LEDESMA EMILIANO RUBEN | J41: 1 | K41: $ | L41: 585348.09 | M41: 0 | N41: 0 | O41: 0 | P41: 122923.1 | Q41: 708271.19
A42: 09/12/2024 | B42: 1 - Factura A | C42: 8 | D42: 350 | F42: 74504260222768 | G42: CUIT | H42: 30643518364 | I42: FARMACIA DE MEDRANO 533 SOCIEDAD EN COMANDITA SIMPLE | J42: 1 | K42: $ | L42: 461140 | M42: 0 | N42: 0 | O42: 0 | P42: 96839.4 | Q42: 557979.4
A43: 09/12/2024 | B43: 1 - Factura A | C43: 11 | D43: 1741771 | F43: 74504343694122 | G43: CUIT | H43: 30709776564 | I43: PROSEGUR ACTIVA ARGENTINA SA | J43: 1 | K43: $ | L43: 129241 | M43: 0 | N43: 0 | O43: 5169.64 | P43: 27140.61 | Q43: 161551.27
A44: 09/12/2024 | B44: 1 - Factura A | C44: 700 | D44: 2110090 | F44: 74502327313006 | G44: CUIT | H44: 30715804812 | I44: CORREDORES VIALES SOCIEDAD ANONIMA | J44: 1 | K44: $ | L44: 9672.33 | M44: 0 | N44: 0 | O44: 386.89 | P44: 2031.19 | Q44: 12090.41
A45: 09/12/2024 | B45: 1 - Factura A | C45: 3101 | D45: 220773 | F45: 74507410659421 | G45: CUIT | H45: 30678814357 | I45: TELEFONICA MOVILES ARGENTINA SOCIEDAD ANONIMA | J45: 1 | K45: $ | L45: 75670.63 | M45: 0 | N45: 0 | O45: 5296.95 | P45: 20431.07 | Q45: 101398.65
A46: 09/12/2024 | B46: 1 - Factura A | C46: 5 | D46: 52 | F46: 74502194149412 | G46: CUIT | H46: 30707370552 | I46: RAKE S.A. | J46: 1 | K46: $ | L46: 1050000 | M46: 0 | N46: 0 | O46: 0 | P46: 220500 | Q46: cio
A47: 10/12/2024 | B47: 1 - Factura A | C47: 5 | D47: 2269 | F47: 74508359329607 | G47: CUIT | H47: 20242126158 | I47: IALLONARDO SERGIO ALEJANDRO | J47: 1 | K47: $ | L47: 504360 | M47: 0 | N47: 0 | O47: 0 | P47: 105915.6 | Q47: 610275.6
A48: 10/12/2024 | B48: 1 - Factura A | C48: 7 | D48: 3497 | F48: 74504362927933 | G48: CUIT | H48: 20284183534 | I48: FURLANETTO MARTIN | J48: 1 | K48: $ | L48: 7727.27 | M48: 0 | N48: 0 | O48: 0 | P48: 1622.73 | Q48: 9350
A49: 10/12/2024 | B49: 1 - Factura A | C49: 47 | D49: 30782 | F49: 74507384225200 | G49: CUIT | H49: 30708847247 | I49: EXPRESO LANCIONI S.A. | J49: 1 | K49: $ | L49: 29908.48 | M49: 0 | N49: 0 | O49: 1196.34 | P49: 6280.78 | Q49: 37385.6
A50: 10/12/2024 | B50: 1 - Factura A | C50: 3 | D50: 47165 | F50: 74508408433094 | G50: CUIT | H50: 30711454388 | I50: LIPROT S.R.L. | J50: 1 | K50: $ | L50: 272569.92 | M50: 0 | N50: 0 | O50: 0 | P50: 57239.68 | Q50: 329809.6
A51: 10/12/2024 | B51: 1 - Factura A | C51: 2 | D51: 30 | F51: 74505399555513 | G51: CUIT | H51: 27243660535 | I51: BARD MARISA SILVIA | J51: 1 | K51: $ | L51: 414537 | M51: 0 | N51: 0 | O51: 0 | P51: 87052.77 | Q51: 501589.77
A52: 10/12/2024 | B52: 1 - Factura A | C52: 3 | D52: 8119 | F52: 74509385734160 | G52: CUIT | H52: 33708218699 | I52: MANGGINI PABLO Y MANGGINI ULISES SOC. DE HECHO. | J52: 1 | K52: $ | L52: 19000 | M52: 0 | N52: 0 | O52: 0 | P52: 3990 | Q52: 22990
A53: 12/12/2024 | B53: 11 - Factura C | C53: 1 | D53: 75 | F53: 74504733890547 | G53: CUIT | H53: 23281233084 | I53: DRUETTA ANDREA MARIEL | J53: 1 | K53: $ | O53: 0 | Q53: 240000
A54: 12/12/2024 | B54: 11 - Factura C | C54: 2 | D54: 116 | F54: 74508716353823 | G54: CUIT | H54: 27315710508 | I54: RIVERO GABRIELA ROCIO | J54: 1 | K54: $ | O54: 0 | Q54: 40000
A55: 13/12/2024 | B55: 1 - Factura A | C55: 6938 | D55: 25552 | F55: 74505868756208 | G55: CUIT | H55: 30678774495 | I55: OPERADORA DE ESTACIONES DE SERVICIOS SA | J55: 1 | K55: $ | L55: 36348.74 | M55: 0 | N55: 0 | O55: 9528.05 | P55: 7633.24 | Q55: 53510.03
A56: 13/12/2024 | B56: 1 - Factura A | C56: 1 | D56: 822 | F56: 74500758354097 | G56: CUIT | H56: 30715568760 | I56: ALUFRAME S.R.L | J56: 1 | K56: $ | L56: 336000 | M56: 0 | N56: 0 | O56: 0 | P56: 70560 | Q56: 406560
A57: 13/12/2024 | B57: 1 - Factura A | C57: 8 | D57: 1728 | F57: 74501799554650 | G57: CUIT | H57: 30708973501 | I57: ASIAL S.R.L. | J57: 1 | K57: $ | L57: 728960 | M57: 0 | N57: 0 | O57: 0 | P57: 153081.6 | Q57: 882041.6
A58: 13/12/2024 | B58: 1 - Factura A | C58: 3 | D58: 204 | F58: 74513165157083 | G58: CUIT | H58: 20334976433 | I58: NARDOMARINO EZEQUIEL EDUARDO | J58: 1 | K58: $ | L58: 50000 | M58: 0 | N58: 0 | O58: 0 | P58: 10500 | Q58: 60500
A59: 15/12/2024 | B59: 1 - Factura A | C59: 113 | D59: 3966754 | F59: 74510356402034 | G59: CUIT | H59: 30577207190 | I59: COORDINACION ECOLOGICA AREA METROPOLITANA SOCIEDAD DEL ESTADO | J59: 1 | K59: $ | L59: 991.73 | M59: 0 | N59: 0 | O59: 0 | P59: 208.27 | Q59: 1200
A60: 16/12/2024 | B60: 1 - Factura A | C60: 6 | D60: 1283 | F60: 74513179257709 | G60: CUIT | H60: 20247225243 | I60: VENTO HUGO GABRIEL | J60: 1 | K60: $ | L60: 445238 | M60: 0 | N60: 0 | O60: 0 | P60: 93499.98 | Q60: este
A61: 16/12/2024 | B61: 1 - Factura A | C61: 5 | D61: 161959 | F61: 74513118401565 | G61: CUIT | H61: 30598960093 | I61: SILVESTRIN FABRIS SOC RESP LTDA | J61: 1 | K61: $ | L61: 2662681.5 | M61: 0 | N61: 0 | O61: 106507.26 | P61: 559163.12 | Q61: 3328351.9
A62: 16/12/2024 | B62: 1 - Factura A | C62: 6 | D62: 87588 | F62: 74514172729758 | G62: CUIT | H62: 30711553564 | I62: SALUDTEX SA | J62: 1 | K62: $ | L62: 629391 | M62: 0 | N62: 0 | O62: 0 | P62: 132172.11 | Q62: 761563.11
A63: 16/12/2024 | B63: 1 - Factura A | C63: 5009 | D63: 1102661 | F63: 74514250055586 | G63: CUIT | H63: 30574876474 | I63: AUTOPISTAS URBANAS S A | J63: 1 | K63: $ | L63: 4000.71 | M63: 0 | N63: 0 | O63: 520.09 | P63: 840.15 | Q63: 5360.95
A64: 16/12/2024 | B64: 1 - Factura A | C64: 5015 | D64: 676181 | F64: 74514225222766 | G64: CUIT | H64: 30574876474 | I64: AUTOPISTAS URBANAS S A | J64: 1 | K64: $ | L64: 11734.83 | M64: 0 | N64: 0 | O64: 1525.52 | P64: 2464.3 | Q64: 15724.65
A65: 16/12/2024 | B65: 1 - Factura A | C65: 50 | D65: 3973434 | F65: 74516238472772 | G65: CUIT | H65: 30714112836 | I65: AUTOPISTAS DE BUENOS AIRES (AUBASA) SA S. A. | J65: 1 | K65: $ | L65: 1074.38 | M65: 0 | N65: 0 | O65: 0 | P65: 225.62 | Q65: 1300
A66: 16/12/2024 | B66: 1 - Factura A | C66: 711 | D66: 6515693 | F66: 34509795539939 | G66: CUIT | H66: 30677237119 | I66: AUTOPISTAS DEL SOL S A | J66: 1 | K66: $ | L66: 5715.46 | M66: 0 | N66: 171.46 | O66: 228.62 | P66: 1200.24 | Q66: 7315.78
A67: 16/12/2024 | B67: 1 - Factura A | C67: 629 | D67: 5697193 | F67: 34503377592129 | G67: CUIT | H67: 30663498513 | I67: GRUPO CONCESIONARIO DEL OESTE SA | J67: 1 | K67: $ | L67: 1362.95 | M67: 0 | N67: 0 | O67: 54.52 | P67: 286.22 | Q67: 1703.69
A68: 16/12/2024 | B68: 1 - Factura A | C68: 5 | D68: 35 | F68: 74513130767020 | G68: CUIT | H68: 20929183143 | I68: MA JUN | J68: 1 | K68: $ | L68: 70000 | M68: 0 | N68: 0 | O68: 0 | P68: 14700 | Q68: 84700
A69: 16/12/2024 | B69: 11 - Factura C | C69: 1 | D69: 2 | F69: 74511125686307 | G69: CUIT | H69: 20236043631 | I69: RODRIGUEZ PATRICIO SALVADOR | J69: 1 | K69: $ | O69: 0 | Q69: 500000
A70: 16/12/2024 | B70: 11 - Factura C | C70: 1 | D70: 272 | F70: 74525396385388 | G70: CUIT | H70: 27217606255 | I70: SAPUNA MIRIAN KARINA | J70: 1 | K70: $ | O70: 0 | Q70: 85055.12
A71: 17/12/2024 | B71: 1 - Factura A | C71: 5 | D71: 2299 | F71: 74518259898614 | G71: CUIT | H71: 20242126158 | I71: IALLONARDO SERGIO ALEJANDRO | J71: 1 | K71: $ | L71: 49410 | M71: 0 | N71: 0 | O71: 0 | P71: 10376.1 | Q71: 59786.1
A72: 17/12/2024 | B72: 1 - Factura A | C72: 5 | D72: 1406 | F72: 74515276633327 | G72: CUIT | H72: 27265302225 | I72: PRADO MARISOL | J72: 1 | K72: $ | L72: 750000 | M72: 0 | N72: 0 | O72: 0 | P72: 157500 | Q72: 907500
A73: 17/12/2024 | B73: 11 - Factura C | C73: 1 | D73: 11 | F73: 74528404797484 | G73: CUIT | H73: 27950736858 | I73: VANONI OBANDO ROMY PRISCILLA | J73: 1 | K73: $ | O73: 0 | Q73: 750000
A74: 17/12/2024 | B74: 11 - Factura C | C74: 1 | D74: 273 | F74: 74525396605047 | G74: CUIT | H74: 27217606255 | I74: SAPUNA MIRIAN KARINA | J74: 1 | K74: $ | O74: 0 | Q74: 75334.54
A75: 17/12/2024 | B75: 13 - Nota de Crédito C | C75: 1 | D75: 1 | F75: 74528405372070 | G75: CUIT | H75: 27950736858 | I75: VANONI OBANDO ROMY PRISCILLA | J75: 1 | K75: $ | O75: 0 | Q75: -750000
A76: 18/12/2024 | B76: 1 - Factura A | C76: 2 | D76: 11142 | F76: 74512443644571 | G76: CUIT | H76: 30714331082 | I76: ORTOPEDIA CASA ESCALADA S.R.L. | J76: 1 | K76: $ | L76: 81488.51 | M76: 0 | N76: 0 | O76: 0 | P76: 17112.59 | Q76: 98601.1
A77: 18/12/2024 | B77: 1 - Factura A | C77: 17 | D77: 11263 | F77: 74510456950840 | G77: CUIT | H77: 30661143610 | I77: ORTOPEDIA BERNAT SRL | J77: 1 | K77: $ | L77: 614780 | M77: 0 | N77: 0 | O77: 24591.2 | P77: 129103.8 | Q77: 768475
A78: 18/12/2024 | B78: 1 - Factura A | C78: 114 | D78: 3711 | F78: 74519438888564 | G78: CUIT | H78: 33546505729 | I78: LA UNION SRL | J78: 1 | K78: $ | L78: 9256.2 | M78: 0 | N78: 0 | O78: 0 | P78: 1943.8 | Q78: 11200
A79: 18/12/2024 | B79: 1 - Factura A | C79: 1 | D79: 5748 | F79: 74511457475201 | G79: CUIT | H79: 30715141201 | I79: REHAB S.R.L. | J79: 1 | K79: $ | L79: 166140 | M79: 0 | N79: 0 | O79: 0 | P79: 34889.4 | Q79: 201029.4
A80: 18/12/2024 | B80: 1 - Factura A | C80: 4264 | D80: 4790521 | F80: 74518592669293 | G80: CUIT | H80: 30639453738 | I80: TELECOM ARGENTINA SOCIEDAD ANONIMA | J80: 1 | K80: $ | L80: 26994.42 | M80: 0 | N80: 0 | O80: 2159.55 | P80: 5668.83 | Q80: 34822.8
A81: 18/12/2024 | B81: 3 - Nota de Crédito A | C81: 17 | D81: 701 | F81: 74510526315780 | G81: CUIT | H81: 30661143610 | I81: ORTOPEDIA BERNAT SRL | J81: 1 | K81: $ | L81: -1328690 | M81: 0 | N81: 0 | O81: -53147.6 | P81: -279024.9 | Q81: -1660862.5
A82: 18/12/2024 | B82: 6 - Factura B | C82: 21 | D82: 71212 | F82: 74511506174184 | G82: CUIT | H82: 20166808201 | I82: QUIRINO CARLOS ALBERTO | J82: 1 | K82: $ | L82: 0 | M82: 0 | N82: 0 | O82: 0 | P82: 0 | Q82: 29638.76
A83: 18/12/2024 | B83: 6 - Factura B | C83: 21 | D83: 71213 | F83: 74511506176631 | G83: CUIT | H83: 20166808201 | I83: QUIRINO CARLOS ALBERTO | J83: 1 | K83: $ | L83: 0 | M83: 0 | N83: 0 | O83: 0 | P83: 0 | Q83: 88916.28
A84: 18/12/2024 | B84: 6 - Factura B | C84: 21 | D84: 71214 | F84: 74511506178793 | G84: CUIT | H84: 20166808201 | I84: QUIRINO CARLOS ALBERTO | J84: 1 | K84: $ | L84: 0 | M84: 0 | N84: 0 | O84: 0 | P84: 0 | Q84: 59277.52
A85: 18/12/2024 | B85: 6 - Factura B | C85: 21 | D85: 71215 | F85: 74511506180777 | G85: CUIT | H85: 20166808201 | I85: QUIRINO CARLOS ALBERTO | J85: 1 | K85: $ | L85: 0 | M85: 0 | N85: 0 | O85: 0 | P85: 0 | Q85: 59277.52
A86: 18/12/2024 | B86: 6 - Factura B | C86: 21 | D86: 71217 | F86: 74511506185463 | G86: CUIT | H86: 20166808201 | I86: QUIRINO CARLOS ALBERTO | J86: 1 | K86: $ | L86: 0 | M86: 0 | N86: 0 | O86: 0 | P86: 0 | Q86: 88916.28
A87: 18/12/2024 | B87: 6 - Factura B | C87: 21 | D87: 71218 | F87: 74511506188806 | G87: CUIT | H87: 20166808201 | I87: QUIRINO CARLOS ALBERTO | J87: 1 | K87: $ | L87: 0 | M87: 0 | N87: 0 | O87: 0 | P87: 0 | Q87: 29638.76
A88: 18/12/2024 | B88: 11 - Factura C | C88: 1 | D88: 274 | F88: 74525396786581 | G88: CUIT | H88: 27217606255 | I88: SAPUNA MIRIAN KARINA | J88: 1 | K88: $ | O88: 0 | Q88: 82624.98
A89: 18/12/2024 | B89: 11 - Factura C | C89: 1 | D89: 18 | F89: 74525402646498 | G89: CUIT | H89: 27443612705 | I89: MIGOYA MORIONDO MARIA INES | J89: 1 | K89: $ | O89: 0 | Q89: 900000
A90: 18/12/2024 | B90: 11 - Factura C | C90: 1 | D90: 275 | F90: 74525397105548 | G90: CUIT | H90: 27217606255 | I90: SAPUNA MIRIAN KARINA | J90: 1 | K90: $ | O90: 0 | Q90: 223375.02
A91: 18/12/2024 | B91: 11 - Factura C | C91: 1 | D91: 13 | F91: 74528405922763 | G91: CUIT | H91: 27950736858 | I91: VANONI OBANDO ROMY PRISCILLA | J91: 1 | K91: $ | O91: 0 | Q91: 750000
A92: 18/12/2024 | B92: 11 - Factura C | C92: 1 | D92: 276 | F92: 74525397262422 | G92: CUIT | H92: 27217606255 | I92: SAPUNA MIRIAN KARINA | J92: 1 | K92: $ | O92: 0 | Q92: 144536.78
A93: 18/12/2024 | B93: 13 - Nota de Crédito C | C93: 1 | D93: 2 | F93: 74528569113200 | G93: CUIT | H93: 27950736858 | I93: VANONI OBANDO ROMY PRISCILLA | J93: 1 | K93: $ | O93: 0 | Q93: 750000
A94: 19/12/2024 | B94: 1 - Factura A | C94: 2 | D94: 994 | F94: 74519605939541 | G94: CUIT | H94: 20272865869 | I94: DI FEO MARTIN EZEQUIEL | J94: 1 | K94: $ | L94: 102700 | M94: 0 | N94: 0 | O94: 0 | P94: 21567 | Q94: 124267
A95: 19/12/2024 | B95: 1 - Factura A | C95: 2 | D95: 996 | F95: 74519606038103 | G95: CUIT | H95: 20272865869 | I95: DI FEO MARTIN EZEQUIEL | J95: 1 | K95: $ | L95: 38000 | M95: 0 | N95: 0 | O95: 0 | P95: 7980 | Q95: 45980
A96: 19/12/2024 | B96: 1 - Factura A | C96: 17 | D96: 2569 | F96: 74511564571598 | G96: CUIT | H96: 30711764921 | I96: RELIEF CENTER S.R.L. | J96: 1 | K96: $ | L96: 187885 | M96: 0 | N96: 0 | O96: 0 | P96: 39455.85 | Q96: 227340.85
A97: 19/12/2024 | B97: 1 - Factura A | C97: 2 | D97: 992 | F97: 74519600800067 | G97: CUIT | H97: 20272865869 | I97: DI FEO MARTIN EZEQUIEL | J97: 1 | K97: $ | L97: 172314.47 | M97: 0 | N97: 0 | O97: 0 | P97: 36186.04 | Q97: 208500.51
A98: 19/12/2024 | B98: 11 - Factura C | C98: 1 | D98: 277 | F98: 74525397431861 | G98: CUIT | H98: 27217606255 | I98: SAPUNA MIRIAN KARINA | J98: 1 | K98: $ | O98: 0 | Q98: 157676.49
A99: 20/12/2024 | B99: 1 - Factura A | C99: 11 | D99: 67962 | F99: 74512759148808 | G99: CUIT | H99: 30711091552 | I99: BIGBOX S.A. | J99: 1 | K99: $ | L99: 140909.09 | M99: 0 | N99: 0 | O99: 0 | P99: 29590.91 | Q99: 170500
A100: 20/12/2024 | B100: 1 - Factura A | C100: 2 | D100: 997 | F100: 74519671436659 | G100: CUIT | H100: 20272865869 | I100: DI FEO MARTIN EZEQUIEL | J100: 1 | K100: $ | L100: 13070 | M100: 0 | N100: 0 | O100: 0 | P100: 2744.7 | Q100: 15814.7
A101: 20/12/2024 | B101: 1 - Factura A | C101: 3 | D101: 25 | F101: 74512717044850 | G101: CUIT | H101: 20216164262 | I101: VELEZ ALEJANDRO MARCELO | J101: 1 | K101: $ | L101: 727272.71 | M101: 0 | N101: 0 | O101: 0 | P101: 152727.27 | Q101: 880000
...

Sheet Hoja2

Sheet Comp No Recibidos
A6: Fecha | B6: Tipo | C6: Punto de Venta | D6: NOMBRE | E6: FC Nº | F6: Cód. Autorización | G6: Tipo Doc. Emisor | H6: Nro. Doc. Emisor | I6: Denominación Emisor | J6: Tipo Cambio | K6: Moneda | L6: Imp. Neto Gravado | M6: Imp. Neto No Gravado | N6: Imp. Op. Exentas | O6: Otros Tributos | P6: IVA | Q6: Imp. Total
A7: 01/03/2025 | B7: 1 - Factura A | C7: 1 | D7: CONTABILIUM S.A. S. A. | E7: 116458 | F7: 75099180081192 | G7: CUIT | H7: 30714864269 | I7: CONTABILIUM S.A. S. A. | J7: 1 | K7: $ | L7: 164170 | M7: 0 | N7: 0 | O7: 0 | P7: 34475.7 | Q7: 198645.7
A8: 15/03/2025 | B8: 1 - Factura A | C8: 50 | D8: AUTOPISTAS DE BUENOS AIRES (AUBASA) SA S. A. | E8: 4203840 | F8: 75116065667505 | G8: CUIT | H8: 30714112836 | I8: AUTOPISTAS DE BUENOS AIRES (AUBASA) SA S. A. | J8: 1 | K8: $ | L8: 1322.14 | M8: 0 | N8: 0 | O8: 0 | P8: 277.65 | Q8: 1599.79
A9: 31/03/2025 | B9: 1 - Factura A | C9: 50 | D9: AUTOPISTAS DE BUENOS AIRES (AUBASA) SA S. A. | E9: 4240541 | F9: 75146078835131 | G9: CUIT | H9: 30714112836 | I9: AUTOPISTAS DE BUENOS AIRES (AUBASA) SA S. A. | J9: 1 | K9: $ | L9: 4888.16 | M9: 0 | N9: 0 | O9: 146.64 | P9: 1026.52 | Q9: 6061.32
A10: 02/03/2025 | B10: 1 - Factura A | C10: 3051 | D10: TELEFONICA MOVILES ARGENTINA SOCIEDAD ANONIMA | E10: 885516 | F10: 75097440339951 | G10: CUIT | H10: 30678814357 | I10: TELEFONICA MOVILES ARGENTINA SOCIEDAD ANONIMA | J10: 1 | K10: $ | L10: 65394 | M10: 0 | N10: 0 | O10: 8157 | P10: 17656.38 | Q10: 91207.38
A11: 03/03/2025 | B11: 1 - Factura A | C11: 500 | D11: SOLUCIONES MULTIMEDIA S A | E11: 1694216 | F11: 75097875516122 | G11: CUIT | H11: 30654118767 | I11: SOLUCIONES MULTIMEDIA S A | J11: 1 | K11: $ | L11: 117349.04 | M11: 0 | N11: 0 | O11: 5851.32 | P11: 24643.3 | Q11: 147843.66
A12: 01/03/2025 | B12: 1 - Factura A | C12: 711 | D12: AUTOPISTAS DEL SOL S A | E12: 6809656 | F12: 35089654428747 | G12: CUIT | H12: 30677237119 | I12: AUTOPISTAS DEL SOL S A | J12: 1 | K12: $ | L12: 1155.52 | M12: 0 | N12: 0 | O12: 46.22 | P12: 242.66 | Q12: 1444.4
A13: 03/03/2025 | B13: 11 - Factura C | C13: 2 | D13: BLASCO MARIA GUADALUPE | E13: 338 | F13: 75108573083577 | G13: CUIT | H13: 27265832178 | I13: BLASCO MARIA GUADALUPE | J13: 1 | K13: $ | O13: 0 | Q13: 3200000
A14: 04/03/2025 | B14: 1 - Factura A | C14: 1 | D14: VERISURE ARGENTINA MONITOREO DE ALARMAS SA | E14: 753841 | F14: 75109679292275 | G14: CUIT | H14: 33716307749 | I14: VERISURE ARGENTINA MONITOREO DE ALARMAS SA | J14: 1 | K14: $ | L14: 49498.9 | M14: 0 | N14: 0 | O14: 1979.96 | P14: 10394.77 | Q14: 61873.63
A15: 05/03/2025 | B15: 1 - Factura A | C15: 3 | D15: VELEZ ALEJANDRO MARCELO | E15: 30 | F15: 75102640981500 | G15: CUIT | H15: 20216164262 | I15: VELEZ ALEJANDRO MARCELO | J15: 1 | K15: $ | L15: 1166562 | M15: 0 | N15: 0 | O15: 0 | P15: 244978.02 | Q15: 1411540
A16: 05/03/2025 | B16: 11 - Factura C | C16: 1 | D16: DRUETTA ANDREA MARIEL | E16: 78 | F16: 75104661596492 | G16: CUIT | H16: 23281233084 | I16: DRUETTA ANDREA MARIEL | J16: 1 | K16: $ | O16: 0 | Q16: 270000
A17: 05/03/2025 | B17: 11 - Factura C | C17: 3 | D17: BOTINDARI JUAN CARLOS | E17: 938 | F17: 75103578933928 | G17: CUIT | H17: 20086277523 | I17: BOTINDARI JUAN CARLOS | J17: 1 | K17: $ | O17: 0 | Q17: 275500
A18: 06/03/2025 | B18: 1 - Factura A | C18: 2 | D18: DI FEO MARTIN EZEQUIEL | E18: 1132 | F18: 75109793481045 | G18: CUIT | H18: 20272865869 | I18: DI FEO MARTIN EZEQUIEL | J18: 1 | K18: $ | L18: 155850 | M18: 0 | N18: 0 | O18: 0 | P18: 32728.5 | Q18: 188578.5
A19: 15/03/2025 | B19: 1 - Factura A | C19: 5009 | D19: AUTOPISTAS URBANAS S A | E19: 1272797 | F19: 75114998298974 | G19: CUIT | H19: 30574876474 | I19: AUTOPISTAS URBANAS S A | J19: 1 | K19: $ | L19: 1820.64 | M19: 0 | N19: 0 | O19: 182.06 | P19: 382.33 | Q19: 2385.03
A20: 31/03/2025 | B20: 1 - Factura A | C20: 5009 | D20: AUTOPISTAS URBANAS S A | E20: 1316261 | F20: 75144039185661 | G20: CUIT | H20: 30574876474 | I20: AUTOPISTAS URBANAS S A | J20: 1 | K20: $ | L20: 6798.01 | M20: 0 | N20: 0 | O20: 883.74 | P20: 1427.57 | Q20: 9109.32
A21: 07/03/2025 | B21: 1 - Factura A | C21: 2 | D21: DI FEO MARTIN EZEQUIEL | E21: 1133 | F21: 75109874477776 | G21: CUIT | H21: 20272865869 | I21: DI FEO MARTIN EZEQUIEL | J21: 1 | K21: $ | L21: 39000 | M21: 0 | N21: 0 | O21: 0 | P21: 8190 | Q21: 47190
A22: 07/03/2025 | B22: 1 - Factura A | C22: 2 | D22: DI FEO MARTIN EZEQUIEL | E22: 1135 | F22: 75109882194137 | G22: CUIT | H22: 20272865869 | I22: DI FEO MARTIN EZEQUIEL | J22: 1 | K22: $ | L22: 11006.61 | M22: 0 | N22: 0 | O22: 0 | P22: 2311.39 | Q22: 13318
A23: 07/03/2025 | B23: 1 - Factura A | C23: 5 | D23: SILVESTRIN FABRIS SOC RESP LTDA | E23: 164287 | F23: 75103948936244 | G23: CUIT | H23: 30598960093 | I23: SILVESTRIN FABRIS SOC RESP LTDA | J23: 1 | K23: $ | L23: 2026728 | M23: 0 | N23: 0 | O23: 81069.12 | P23: 425612.89 | Q23: 2533410
A24: 07/03/2025 | B24: 1 - Factura A | C24: 7 | D24: SOUSA ALDERETE ALEJANDRA MABEL | E24: 27 | F24: 75103887647271 | G24: CUIT | H24: 27325223273 | I24: SOUSA ALDERETE ALEJANDRA MABEL | J24: 1 | K24: $ | L24: 1650000 | M24: 0 | N24: 0 | O24: 0 | P24: 346500 | Q24: 1996500
A25: 07/03/2025 | B25: 1 - Factura A | C25: 2 | D25: 46 SPEED S.A. | E25: 487 | F25: 75106908089918 | G25: CUIT | H25: 30711610096 | I25: 46 SPEED S.A. | J25: 1 | K25: $ | L25: 698000 | M25: 0 | N25: 0 | O25: 0 | P25: 146580 | Q25: 844580
A26: 07/03/2025 | B26: 11 - Factura C | C26: 2 | D26: RIVERO GABRIELA ROCIO | E26: 123 | F26: 75108978118375 | G26: CUIT | H26: 27315710508 | I26: RIVERO GABRIELA ROCIO | J26: 1 | K26: $ | O26: 0 | Q26: 43200
A27: 08/03/2025 | B27: 1 - Factura A | C27: 5015 | D27: AUTOPISTAS URBANAS S A | E27: 778963 | F27: 75104071087297 | G27: CUIT | H27: 30574876474 | I27: AUTOPISTAS URBANAS S A | J27: 1 | K27: $ | L27: 13213.87 | M27: 0 | N27: 0 | O27: 1717.79 | P27: 2774.9 | Q27: 17706.56
A28: 31/03/2025 | B28: 1 - Factura A | C28: 5015 | D28: AUTOPISTAS URBANAS S A | E28: 801800 | F28: 75144032396028 | G28: CUIT | H28: 30574876474 | I28: AUTOPISTAS URBANAS S A | J28: 1 | K28: $ | L28: 33681.65 | M28: 0 | N28: 0 | O28: 4378.57 | P28: 7073.11 | Q28: 45133.33
A29: 09/03/2025 | B29: 1 - Factura A | C29: 3101 | D29: TELEFONICA MOVILES ARGENTINA SOCIEDAD ANONIMA | E29: 278864 | F29: 75107271721600 | G29: CUIT | H29: 30678814357 | I29: TELEFONICA MOVILES ARGENTINA SOCIEDAD ANONIMA | J29: 1 | K29: $ | L29: 82083.6 | M29: 0 | N29: 0 | O29: 5745.85 | P29: 22162.57 | Q29: 109992.02
A30: 10/03/2025 | B30: 1 - Factura A | C30: 2002 | D30: MERCADO TOTAL SAS | E30: 79578 | F30: 75105247782031 | G30: CUIT | H30: 30716425165 | I30: MERCADO TOTAL SAS | J30: 1 | K30: $ | L30: 4796.38 | M30: 0 | N30: 0 | O30: 0 | P30: 503.62 | Q30: 5300
A31: 11/03/2025 | B31: 1 - Factura A | C31: 7 | D31: SUPERFOTO S R L | E31: 268472 | F31: 75103434538841 | G31: CUIT | H31: 30708395443 | I31: SUPERFOTO S R L | J31: 1 | K31: $ | L31: 132230.58 | M31: 0 | N31: 0 | O31: 0 | P31: 27768.42 | Q31: 159999
A32: 11/03/2025 | B32: 1 - Factura A | C32: 2 | D32: ORTOPEDIA CASA ESCALADA S.R.L. | E32: 11604 | F32: 75102380894031 | G32: CUIT | H32: 30714331082 | I32: ORTOPEDIA CASA ESCALADA S.R.L. | J32: 1 | K32: $ | L32: 423275.07 | M32: 0 | N32: 0 | O32: 0 | P32: 88887.76 | Q32: 512162.83
A33: 11/03/2025 | B33: 1 - Factura A | C33: 120 | D33: PANATEL SOCIEDAD ANONIMA | E33: 5534 | F33: 75105438448648 | G33: CUIT | H33: 30587197215 | I33: PANATEL SOCIEDAD ANONIMA | J33: 1 | K33: $ | L33: 95041.32 | M33: 0 | N33: 0 | O33: 3801.65 | P33: 19958.68 | Q33: 118801.65
A34: 11/03/2025 | B34: 11 - Factura C | C34: 1 | D34: CHANCO VILLAVICENCIO ERNESTO ANTONIO | E34: 44 | F34: 75107404164811 | G34: CUIT | H34: 20190742297 | I34: CHANCO VILLAVICENCIO ERNESTO ANTONIO | J34: 1 | K34: $ | O34: 0 | Q34: 150000
A35: 11/03/2025 | B35: 11 - Factura C | C35: 1 | D35: MIGOYA MORIONDO SOFIA | E35: 12 | F35: 75103359390490 | G35: CUIT | H35: 27443612713 | I35: MIGOYA MORIONDO SOFIA | J35: 1 | K35: $ | O35: 0 | Q35: 850000
A36: 12/03/2025 | B36: 1 - Factura A | C36: 4 | D36: LEDESMA EMILIANO RUBEN | E36: 39572 | F36: 75119506172639 | G36: CUIT | H36: 20289111329 | I36: LEDESMA EMILIANO RUBEN | J36: 1 | K36: $ | L36: 585348.09 | M36: 0 | N36: 0 | O36: 0 | P36: 122923.1 | Q36: 708271.19
A37: 12/03/2025 | B37: 1 - Factura A | C37: 6 | D37: SALUDTEX SA | E37: 89635 | F37: 75114529251983 | G37: CUIT | H37: 30711553564 | I37: SALUDTEX SA | J37: 1 | K37: $ | L37: 846283.75 | M37: 0 | N37: 0 | O37: 0 | P37: 177719.59 | Q37: 1024003.3
A38: 12/03/2025 | B38: 1 - Factura A | C38: 4 | D38: LEDESMA EMILIANO RUBEN | E38: 39574 | F38: 75119529929350 | G38: CUIT | H38: 20289111329 | I38: LEDESMA EMILIANO RUBEN | J38: 1 | K38: $ | L38: 292865.41 | M38: 0 | N38: 0 | O38: 0 | P38: 61501.73 | Q38: 354367.14
A39: 12/03/2025 | B39: 11 - Factura C | C39: 3 | D39: KLAINER ABEL JAVIER | E39: 2395 | F39: 75111535985217 | G39: CUIT | H39: 20182999661 | I39: KLAINER ABEL JAVIER | J39: 1 | K39: $ | O39: 0 | Q39: 57000
A40: 12/03/2025 | B40: 11 - Factura C | C40: 1 | D40: CANCINO PAMELA RITA | E40: 167 | F40: 75110530978675 | G40: CUIT | H40: 27338342840 | I40: CANCINO PAMELA RITA | J40: 1 | K40: $ | O40: 0 | Q40: 652800
A41: 13/03/2025 | B41: 1 - Factura A | C41: 3 | D41: LIPROT S.R.L. | E41: 48479 | F41: 75118687675469 | G41: CUIT | H41: 30711454388 | I41: LIPROT S.R.L. | J41: 1 | K41: $ | L41: 213732 | M41: 0 | N41: 0 | O41: 0 | P41: 44883.72 | Q41: 258615.72
A42: 13/03/2025 | B42: 1 - Factura A | C42: 3 | D42: LIPROT S.R.L. | E42: 48480 | F42: 75118687920143 | G42: CUIT | H42: 30711454388 | I42: LIPROT S.R.L. | J42: 1 | K42: $ | L42: 137543 | M42: 0 | N42: 0 | O42: 0 | P42: 28884.03 | Q42: 166427.03
A43: 13/03/2025 | B43: 1 - Factura A | C43: 2 | D43: DI FEO MARTIN EZEQUIEL | E43: 1151 | F43: 75119693479565 | G43: CUIT | H43: 20272865869 | I43: DI FEO MARTIN EZEQUIEL | J43: 1 | K43: $ | L43: 87550 | M43: 0 | N43: 0 | O43: 0 | P43: 18385.5 | Q43: 105935.5
A44: 13/03/2025 | B44: 1 - Factura A | C44: 1000 | D44: ITPROUSER S.A. | E44: 215377 | F44: 75113683028005 | G44: CUIT | H44: 30715123483 | I44: ITPROUSER S.A. | J44: 1 | K44: $ | L44: 15170.24 | M44: 0 | N44: 0 | O44: 310.84 | P44: 3185.75 | Q44: 18666.83
A45: 13/03/2025 | B45: 1 - Factura A | C45: 5 | D45: PRADO MARISOL | E45: 1485 | F45: 75115688543714 | G45: CUIT | H45: 27265302225 | I45: PRADO MARISOL | J45: 1 | K45: $ | L45: 800000 | M45: 0 | N45: 0 | O45: 0 | P45: 168000 | Q45: 968000
A46: 13/03/2025 | B46: 1 - Factura A | C46: 3 | D46: MANGGINI PABLO Y MANGGINI ULISES SOC. DE HECHO. | E46: 8664 | F46: 75119677712167 | G46: CUIT | H46: 33708218699 | I46: MANGGINI PABLO Y MANGGINI ULISES SOC. DE HECHO. | J46: 1 | K46: $ | L46: 24000 | M46: 0 | N46: 0 | O46: 0 | P46: 5040 | Q46: 29040
A47: 13/03/2025 | B47: 1 - Factura A | C47: 8 | D47: ASIAL S.R.L. | E47: 1763 | F47: 75111675190378 | G47: CUIT | H47: 30708973501 | I47: ASIAL S.R.L. | J47: 1 | K47: $ | L47: 616271 | M47: 0 | N47: 0 | O47: 0 | P47: 129416.91 | Q47: 745687.91
A48: 13/03/2025 | B48: 11 - Factura C | C48: 5 | D48: FERREIRA LILIANA INES | E48: 176 | F48: 75119666465613 | G48: CUIT | H48: 27062343449 | I48: FERREIRA LILIANA INES | J48: 1 | K48: $ | O48: 0 | Q48: 250000
A49: 13/03/2025 | B49: 11 - Factura C | C49: 5 | D49: FERREIRA LILIANA INES | E49: 177 | F49: 75119666703965 | G49: CUIT | H49: 27062343449 | I49: FERREIRA LILIANA INES | J49: 1 | K49: $ | O49: 0 | Q49: 350000
A50: 14/03/2025 | B50: 1 - Factura A | C50: 1 | D50: REHAB S.R.L. | E50: 6677 | F50: 75111774652240 | G50: CUIT | H50: 30715141201 | I50: REHAB S.R.L. | J50: 1 | K50: $ | L50: 529546.88 | M50: 0 | N50: 0 | O50: 0 | P50: 111204.84 | Q50: 640751.72
A51: 14/03/2025 | B51: 1 - Factura A | C51: 2 | D51: DI FEO MARTIN EZEQUIEL | E51: 1153 | F51: 75119760659695 | G51: CUIT | H51: 20272865869 | I51: DI FEO MARTIN EZEQUIEL | J51: 1 | K51: $ | L51: 180000 | M51: 0 | N51: 0 | O51: 0 | P51: 37800 | Q51: 217800
A52: 14/03/2025 | B52: 1 - Factura A | C52: 503 | D52: CAMINOS DEL RIO URUGUAY S A DE CONSTRUCCIONES Y CONCESIONES VIALES | E52: 1763876 | F52: 75112746806984 | G52: CUIT | H52: 30639935872 | I52: CAMINOS DEL RIO URUGUAY S A DE CONSTRUCCIONES Y CONCESIONES VIALES | J52: 1 | K52: $ | L52: 3471.36 | M52: 0 | N52: 0 | O52: 138.85 | P52: 729 | Q52: 4339.21
A53: 14/03/2025 | B53: 1 - Factura A | C53: 7 | D53: ABRAMOWICZ DEMIAN MARCELO | E53: 4517 | F53: 75119775037250 | G53: CUIT | H53: 20307464269 | I53: ABRAMOWICZ DEMIAN MARCELO | J53: 1 | K53: $ | L53: 8146.58 | M53: 0 | N53: 0 | O53: 0 | P53: 1710.78 | Q53: 9857.36
A54: 03/03/2025 | B54: 1 - Factura A | C54: 2 | D54: CONSORCIO BARTOLOME MITRE 2466 | E54: 231 | F54: 75092415790665 | G54: CUIT | H54: 30605344352 | I54: CONSORCIO BARTOLOME MITRE 2466 | J54: 1 | K54: $ | L54: 1200000 | M54: 0 | N54: 0 | O54: 0 | P54: 252000 | Q54: 1452000
A55: 14/03/2025 | B55: 1 - Factura A | C55: 4 | D55: LEDESMA EMILIANO RUBEN | E55: 39596 | F55: 75119795896075 | G55: CUIT | H55: 20289111329 | I55: LEDESMA EMILIANO RUBEN | J55: 1 | K55: $ | L55: 585348.09 | M55: 0 | N55: 0 | O55: 0 | P55: 122923.1 | Q55: 708271.19
A56: 14/03/2025 | B56: 1 - Factura A | C56: 4 | D56: SHOPNOW S.R.L. | E56: 13184 | F56: 75119804573272 | G56: CUIT | H56: 33711386179 | I56: SHOPNOW S.R.L. | J56: 1 | K56: $ | L56: 192187.6 | M56: 0 | N56: 0 | O56: 0 | P56: 40359.4 | Q56: 232547
A57: 15/03/2025 | B57: 1 - Factura A | C57: 113 | D57: COORDINACION ECOLOGICA AREA METROPOLITANA SOCIEDAD DEL ESTADO | E57: 4122520 | F57: 75110167242664 | G57: CUIT | H57: 30577207190 | I57: COORDINACION ECOLOGICA AREA METROPOLITANA SOCIEDAD DEL ESTADO | J57: 1 | K57: $ | L57: 2479.34 | M57: 0 | N57: 0 | O57: 74.38 | P57: 520.66 | Q57: 3074.38
A58: 14/03/2025 | B58: 1 - Factura A | C58: 3 | D58: LIPROT S.R.L. | E58: 48502 | F58: 75118827918183 | G58: CUIT | H58: 30711454388 | I58: LIPROT S.R.L. | J58: 1 | K58: $ | L58: 42275 | M58: 0 | N58: 0 | O58: 0 | P58: 8877.75 | Q58: 51152.75
A59: 14/03/2025 | B59: 1 - Factura A | C59: 5 | D59: ITALOMED PRODUCTOS SRL | E59: 2281 | F59: 75116802843498 | G59: CUIT | H59: 30712187316 | I59: ITALOMED PRODUCTOS SRL | J59: 1 | K59: $ | L59: 294807.15 | M59: 0 | N59: 0 | O59: 0 | P59: 61909.5 | Q59: 356716.65
A60: 14/03/2025 | B60: 1 - Factura A | C60: 2 | D60: ALCOCER MARIO DANIEL | E60: 2175 | F60: 75112803123104 | G60: CUIT | H60: 20238470502 | I60: ALCOCER MARIO DANIEL | J60: 1 | K60: $ | L60: 2150000 | M60: 0 | N60: 0 | O60: 0 | P60: 451500 | Q60: 2601500
A61: 14/03/2025 | B61: 3 - Nota de Crédito A | C61: 2 | D61: ORTOPEDIA CASA ESCALADA S.R.L. | E61: 476 | F61: 75112768392803 | G61: CUIT | H61: 30714331082 | I61: ORTOPEDIA CASA ESCALADA S.R.L. | J61: 1 | K61: $ | L61: 423275.07 | M61: 0 | N61: 0 | O61: 0 | P61: 88887.76 | Q61: 512162.83
A62: 14/03/2025 | B62: 11 - Factura C | C62: 1 | D62: GUASCH HECTOR RAUL | E62: 15 | F62: 75111831543124 | G62: CUIT | H62: 20311855671 | I62: GUASCH HECTOR RAUL | J62: 1 | K62: $ | O62: 0 | Q62: 110000
A63: 31/03/2025 | B63: 1 - Factura A | C63: 113 | D63: COORDINACION ECOLOGICA AREA METROPOLITANA SOCIEDAD DEL ESTADO | E63: 4149140 | F63: 75140082904765 | G63: CUIT | H63: 30577207190 | I63: COORDINACION ECOLOGICA AREA METROPOLITANA SOCIEDAD DEL ESTADO | J63: 1 | K63: $ | L63: 3719.01 | M63: 0 | N63: 0 | O63: 111.57 | P63: 780.99 | Q63: 4611.57
A64: 15/03/2025 | B64: 1 - Factura A | C64: 5015 | D64: AUTOPISTAS URBANAS S A | E64: 781809 | F64: 75114995550139 | G64: CUIT | H64: 30574876474 | I64: AUTOPISTAS URBANAS S A | J64: 1 | K64: $ | L64: 17603.13 | M64: 0 | N64: 0 | O64: 2288.39 | P64: 3696.64 | Q64: 23588.16
A65: 15/03/2025 | B65: 1 - Factura A | C65: 50 | D65: AUTOPISTAS DE BUENOS AIRES (AUBASA) SA S. A. | E65: 4203839 | F65: 75116065667490 | G65: CUIT | H65: 30714112836 | I65: AUTOPISTAS DE BUENOS AIRES (AUBASA) SA S. A. | J65: 1 | K65: $ | L65: 4495.27 | M65: 0 | N65: 0 | O65: 134.86 | P65: 944 | Q65: 5574.13
A66: 06/03/2025 | B66: 1 - Factura A | C66: 700 | D66: CORREDORES VIALES SOCIEDAD ANONIMA | E66: 2313354 | F66: 75102875466023 | G66: CUIT | H66: 30715804812 | I66: CORREDORES VIALES SOCIEDAD ANONIMA | J66: 1 | K66: $ | L66: 7695.87 | M66: 0 | N66: 0 | O66: 307.83 | P66: 1616.13 | Q66: 9619.83
A67: 06/03/2025 | B67: 1 - Factura A | C67: 700 | D67: CORREDORES VIALES SOCIEDAD ANONIMA | E67: 2313355 | F67: 75102875466036 | G67: CUIT | H67: 30715804812 | I67: CORREDORES VIALES SOCIEDAD ANONIMA | J67: 1 | K67: $ | L67: 9151.84 | M67: 0 | N67: 0 | O67: 366.07 | P67: 1921.88 | Q67: 11439.79
A68: 16/03/2025 | B68: 1 - Factura A | C68: 629 | D68: GRUPO CONCESIONARIO DEL OESTE SA | E68: 5940679 | F68: 35103299105733 | G68: CUIT | H68: 30663498513 | I68: GRUPO CONCESIONARIO DEL OESTE SA | J68: 1 | K68: $ | L68: 3813.27 | M68: 0 | N68: 0 | O68: 152.53 | P68: 800.79 | Q68: 4766.59
A69: 16/03/2025 | B69: 1 - Factura A | C69: 711 | D69: AUTOPISTAS DEL SOL S A | E69: 6867805 | F69: 35109379688279 | G69: CUIT | H69: 30677237119 | I69: AUTOPISTAS DEL SOL S A | J69: 1 | K69: $ | L69: 4448.77 | M69: 0 | N69: 133.46 | O69: 177.95 | P69: 934.23 | Q69: 5694.41
A70: 17/03/2025 | B70: 1 - Factura A | C70: 7 | D70: FURLANETTO MARTIN | E70: 3750 | F70: 75114094443591 | G70: CUIT | H70: 20284183534 | I70: FURLANETTO MARTIN | J70: 1 | K70: $ | L70: 7933.86 | M70: 0 | N70: 0 | O70: 0 | P70: 1666.11 | Q70: 9599.97
A71: 17/03/2025 | B71: 1 - Factura A | C71: 4 | D71: NYLTEF SAICF | E71: 20470 | F71: 75113087434861 | G71: CUIT | H71: 30504854023 | I71: NYLTEF SAICF | J71: 1 | K71: $ | L71: 167552 | M71: 0 | N71: 0 | O71: 6702.08 | P71: 35185.92 | Q71: 209440
A72: 14/03/2025 | B72: 1 - Factura A | C72: 104 | D72: CORREDORES VIALES SOCIEDAD ANONIMA | E72: 8464397 | F72: 75112789139613 | G72: CUIT | H72: 30715804812 | I72: CORREDORES VIALES SOCIEDAD ANONIMA | J72: 1 | K72: $ | L72: 1804.5 | M72: 0 | N72: 0 | O72: 72.18 | P72: 378.95 | Q72: 2255.63
A73: 17/03/2025 | B73: 1 - Factura A | C73: 2 | D73: ORTOPEDIA CASA ESCALADA S.R.L. | E73: 11657 | F73: 75112111811653 | G73: CUIT | H73: 30714331082 | I73: ORTOPEDIA CASA ESCALADA S.R.L. | J73: 1 | K73: $ | L73: 77787.65 | M73: 0 | N73: 0 | O73: 0 | P73: 16335.41 | Q73: 94123.06
A74: 17/03/2025 | B74: 1 - Factura A | C74: 5 | D74: MA JUN | E74: 40 | F74: 75113166622538 | G74: CUIT | H74: 20929183143 | I74: MA JUN | J74: 1 | K74: $ | L74: 70000 | M74: 0 | N74: 0 | O74: 0 | P74: 14700 | Q74: 84700
... A78: 14/03/2025 | B78: 1 - Factura A | C78: 104 | D78: CORREDORES VIALES SOCIEDAD ANONIMA | E78: 8427202 | F78: 75112759496143 | G78: CUIT | H78: 30715804812 | I78: CORREDORES VIALES SOCIEDAD ANONIMA | J78: 1 | K78: $ | L78: 2079.97 | M78: 0 | N78: 0 | O78: 83.2 | P78: 436.79 | Q78: 2599.96
A79: 18/03/2025 | B79: 11 - Factura C | C79: 1 | D79: MIGOYA MORIONDO MARIA INES | E79: 22 | F79: 75115246156824 | G79: CUIT | H79: 27443612705 | I79: MIGOYA MORIONDO MARIA INES | J79: 1 | K79: $ | O79: 0 | Q79: 120000
A80: 18/03/2025 | B80: 11 - Factura C | C80: 1 | D80: GUASCH HECTOR RAUL | E80: 16 | F80: 75111262819399 | G80: CUIT | H80: 20311855671 | I80: GUASCH HECTOR RAUL | J80: 1 | K80: $ | O80: 0 | Q80: 326000
A81: 18/03/2025 | B81: 11 - Factura C | C81: 1 | D81: MIGOYA MORIONDO MARIA INES | E81: 23 | F81: 75135493137375 | G81: CUIT | H81: 27443612705 | I81: MIGOYA MORIONDO MARIA INES | J81: 1 | K81: $ | O81: 0 | Q81: 900000
A82: 19/03/2025 | B82: 1 - Factura A | C82: 6 | D82: TARGET MEDICAL S.A. | E82: 56633 | F82: 75128399589438 | G82: CUIT | H82: 30710177658 | I82: TARGET MEDICAL S.A. | J82: 1 | K82: $ | L82: 658080 | M82: 0 | N82: 0 | O82: 0 | P82: 138196.8 | Q82: 796276.8
A83: 19/03/2025 | B83: 1 - Factura A | C83: 32 | D83: ARMORAUT SA | E83: 14788 | F83: 75126397334504 | G83: CUIT | H83: 30707304886 | I83: ARMORAUT SA | J83: 1 | K83: $ | L83: 284107.44 | M83: 0 | N83: 0 | O83: 11364.3 | P83: 59662.56 | Q83: 355134.3
A84: 19/03/2025 | B84: 1 - Factura A | C84: 15 | D84: COLTEX S R L | E84: 4306 | F84: 75123362523958 | G84: CUIT | H84: 30688140923 | I84: COLTEX S R L | J84: 1 | K84: $ | L84: 528360.28 | M84: 0 | N84: 0 | O84: 0 | P84: 110955.66 | Q84: 639315.94
A85: 19/03/2025 | B85: 1 - Factura A | C85: 4264 | D85: TELECOM ARGENTINA SOCIEDAD ANONIMA | E85: 5198709 | F85: 75128527435454 | G85: CUIT | H85: 30639453738 | I85: TELECOM ARGENTINA SOCIEDAD ANONIMA | J85: 1 | K85: $ | L85: 42961.16 | M85: 0 | N85: 0 | O85: 3007.29 | P85: 9021.84 | Q85: 54990.29
A86: 19/03/2025 | B86: 11 - Factura C | C86: 2 | D86: BOCCACCI MARIA FLORENCIA | E86: 2 | F86: 75121379238304 | G86: CUIT | H86: 27344304551 | I86: BOCCACCI MARIA FLORENCIA | J86: 1 | K86: $ | O86: 0 | Q86: 150000
A87: 29/03/2025 | B87: 1 - Factura A | C87: 104 | D87: CORREDORES VIALES SOCIEDAD ANONIMA | E87: 8683654 | F87: 75132601531264 | G87: CUIT | H87: 30715804812 | I87: CORREDORES VIALES SOCIEDAD ANONIMA | J87: 1 | K87: $ | L87: 1039.98 | M87: 0 | N87: 0 | O87: 41.6 | P87: 218.4 | Q87: 1299.98
A88: 20/03/2025 | B88: 1 - Factura A | C88: 2 | D88: BARD MARISA SILVIA | E88: 35 | F88: 75125607221880 | G88: CUIT | H88: 27243660535 | I88: BARD MARISA SILVIA | J88: 1 | K88: $ | L88: 414537 | M88: 0 | N88: 0 | O88: 0 | P88: 87052.77 | Q88: 501589.77
A89: 21/03/2025 | B89: 1 - Factura A | C89: 13 | D89: N.G.A. SRL | E89: 84832 | F89: 75120667539400 | G89: CUIT | H89: 30709256420 | I89: N.G.A. SRL | J89: 1 | K89: $ | L89: 4485.98 | M89: 0 | N89: 0 | O89: 0 | P89: 942.06 | Q89: 5428.04
A90: 21/03/2025 | B90: 1 - Factura A | C90: 13 | D90: N.G.A. SRL | E90: 84834 | F90: 75120667545713 | G90: CUIT | H90: 30709256420 | I90: N.G.A. SRL | J90: 1 | K90: $ | L90: 4704.55 | M90: 0 | N90: 0 | O90: 0 | P90: 987.96 | Q90: 5692.51
A91: 29/03/2025 | B91: 1 - Factura A | C91: 104 | D91: CORREDORES VIALES SOCIEDAD ANONIMA | E91: 8640520 | F91: 75132585920001 | G91: CUIT | H91: 30715804812 | I91: CORREDORES VIALES SOCIEDAD ANONIMA | J91: 1 | K91: $ | L91: 2079.97 | M91: 0 | N91: 0 | O91: 83.2 | P91: 436.79 | Q91: 2599.96
A92: 21/03/2025 | B92: 1 - Factura A | C92: 40 | D92: BIGBOX S.A. | E92: 1480 | F92: 75122693768828 | G92: CUIT | H92: 30711091552 | I92: BIGBOX S.A. | J92: 1 | K92: $ | L92: 70247.93 | M92: 0 | N92: 0 | O92: 0 | P92: 14752.07 | Q92: 85000
A93: 21/03/2025 | B93: 1 - Factura A | C93: 8 | D93: HONRE S.A | E93: 42491 | F93: 75122657884630 | G93: CUIT | H93: 30709953482 | I93: HONRE S.A | J93: 1 | K93: $ | L93: 1532.24 | M93: 0 | N93: 0 | O93: 0 | P93: 321.77 | Q93: 1854.01
A94: 21/03/2025 | B94: 1 - Factura A | C94: 36 | D94: GOLONOR S.A. | E94: 57200 | F94: 75120646632404 | G94: CUIT | H94: 30714769290 | I94: GOLONOR S.A. | J94: 1 | K94: $ | L94: 6609.92 | M94: 0 | N94: 0 | O94: 0 | P94: 1388.08 | Q94: 7998
A95: 21/03/2025 | B95: 1 - Factura A | C95: 2 | D95: TAP SERVICES S.A. | E95: 56906 | F95: 75122596703405 | G95: CUIT | H95: 30717110052 | I95: TAP SERVICES S.A. | J95: 1 | K95: $ | L95: 4421.49 | M95: 0 | N95: 0 | O95: 0 | P95: 928.51 | Q95: 5350
A96: 21/03/2025 | B96: 1 - Factura A | C96: 10 | D96: ONETO TOMAS AUGUSTO | E96: 32746 | F96: 75126636557223 | G96: CUIT | H96: 20373457796 | I96: ONETO TOMAS AUGUSTO | J96: 1 | K96: $ | L96: 18619.83 | M96: 0 | N96: 0 | O96: 0 | P96: 3910.16 | Q96: 22529.99
A97: 21/03/2025 | B97: 1 - Factura A | C97: 700 | D97: CORREDORES VIALES SOCIEDAD ANONIMA | E97: 2340948 | F97: 75122820196470 | G97: CUIT | H97: 30715804812 | I97: CORREDORES VIALES SOCIEDAD ANONIMA | J97: 1 | K97: $ | L97: 8943.84 | M97: 0 | N97: 0 | O97: 357.75 | P97: 1878.2 | Q97: 11179.79
A98: 21/03/2025 | B98: 1 - Factura A | C98: 700 | D98: CORREDORES VIALES SOCIEDAD ANONIMA | E98: 2340949 | F98: 75122820196556 | G98: CUIT | H98: 30715804812 | I98: CORREDORES VIALES SOCIEDAD ANONIMA | J98: 1 | K98: $ | L98: 831.98 | M98: 0 | N98: 0 | O98: 0 | P98: 174.72 | Q98: 1006.7
... A111: 20/03/2025 | B111: 1 - Factura A | C111: 2 | D111: DI FEO MARTIN EZEQUIEL | E111: 1161 | F111: 75129526301590 | G111: CUIT | H111: 20272865869 | I111: DI FEO MARTIN EZEQUIEL | J111: 1 | K111: $ | L111: 78550 | M111: 0 | N111: 0 | O111: 0 | P111: 16495.5 | Q111: 95045.5
A112: 27/03/2025 | B112: 11 - Factura C | C112: 2 | D112: BOCCACCI MARIA FLORENCIA | E112: 3 | F112: 75131317003394 | G112: CUIT | H112: 27344304551 | I112: BOCCACCI MARIA FLORENCIA | J112: 1 | K112: $ | O112: 0 | Q112: 150000
A113: 29/03/2025 | B113: 1 - Factura A | C113: 10 | D113: LUBRICANTES RUTA DE PASCUET E HIJOS S.R.L | E113: 2722 | F113: 75132564079381 | G113: CUIT | H113: 30716229552 | I113: LUBRICANTES RUTA DE PASCUET E HIJOS S.R.L | J113: 1 | K113: $ | L113: 12396.69 | M113: 0 | N113: 0 | O113: 0 | P113: 2603.31 | Q113: 15000
A114: 21/03/2025 | B114: 1 - Factura A | C114: 36 | D114: GOLONOR S.A. | E114: 57170 | F114: 75120617820543 | G114: CUIT | H114: 30714769290 | I114: GOLONOR S.A. | J114: 1 | K114: $ | L114: 6609.92 | M114: 0 | N114: 0 | O114: 0 | P114: 1388.08 | Q114: 7998
A115: 21/03/2025 | B115: 3 - Nota de Crédito A | C115: 36 | D115: GOLONOR S.A. | E115: 5376 | F115: 75120627279529 | G115: CUIT | H115: 30714769290 | I115: GOLONOR S.A. | J115: 1 | K115: $ | L115: 6609.92 | M115: 0 | N115: 0 | O115: 0 | P115: 1388.08 | Q115: 7998
A116: 29/03/2025 | B116: 1 - Factura A | C116: 24 | D116: MERCADOLIBRE S.R.L. | E116: 3066212 | F116: 75134687151308 | G116: CUIT | H116: 30703088534 | I116: MERCADOLIBRE S.R.L. | J116: 1 | K116: $ | L116: 67805.64 | M116: 0 | N116: 0 | O116: 4746.4 | P116: 14239.18 | Q116: 86791.22
A117: 01/03/2025 | B117: 1 - Factura A | C117: 629 | D117: GRUPO CONCESIONARIO DEL OESTE SA | E117: 5901502 | F117: 35083520478131 | G117: CUIT | H117: 30663498513 | I117: GRUPO CONCESIONARIO DEL OESTE SA | J117: 1 | K117: $ | L117: 1155.52 | M117: 0 | N117: 0 | O117: 46.22 | P117: 242.66 | Q117: 1444.4
A118: 31/03/2025 | B118: 1 - Factura A | C118: 3 | D118: RODRIGUEZ JONATAN | E118: 3364 | F118: 75130837546977 | G118: CUIT | H118: 20320131260 | I118: RODRIGUEZ JONATAN | J118: 1 | K118: $ | L118: 3124.15 | M118: 0 | N118: 0 | O118: 0 | P118: 656.07 | Q118: 3780.22
A119: 31/03/2025 | B119: 1 - Factura A | C119: 17 | D119: ORTOPEDIA BERNAT SRL | E119: 12116 | F119: 75130722989528 | G119: CUIT | H119: 30661143610 | I119: ORTOPEDIA BERNAT SRL | J119: 1 | K119: $ | L119: 1194454.6 | M119: 0 | N119: 0 | O119: 47778.19 | P119: 250835.48 | Q119: 1493068.3
A120: 27/03/2025 | B120: 1 - Factura A | C120: 1 | D120: INFORMATICA BARRACAS SRL | E120: 6469 | F120: 75139349226385 | G120: CUIT | H120: 30715430769 | I120: INFORMATICA BARRACAS SRL | J120: 1 | K120: $ | L120: 20698.67 | M120: 0 | N120: 0 | O120: 0 | P120: 4346.72 | Q120: 25045.41
...

Sheet Hoja5
A2: Fecha | B2: Tipo | C2: Punto de Venta | D2: FACTURA | E2: Número Hasta | F2: Cód. Autorización | G2: Tipo Doc. Emisor | H2: Nro. Doc. Emisor | I2: Denominación Emisor | J2: Tipo Cambio | K2: Moneda | L2: Imp. Neto Gravado | M2: Imp. Neto No Gravado | N2: Imp. Op. Exentas | O2: Otros Tributos | P2: IVA | Q2: Imp. Total
A3: 14/04/2025 | B3: 1 - Factura A | C3: 3 | D3: 40 | F3: 75155469337258 | G3: CUIT | H3: 30716651165 | I3: AMTRASK | J3: 1 | K3: $ | L3: 132230.58 | M3: 0 | N3: 0 | O3: 0 | P3: 27768.42 | Q3: 159999
A4: 30/04/2025 | B4: 1 - Factura A | C4: 50 | D4: 4308216 | F4: 75186472119221 | G4: CUIT | H4: 30714112836 | I4: AUTOPISTAS DE BUENOS AIRES (AUBASA) SA S. A. | J4: 1 | K4: $ | L4: 8566.66 | M4: 0 | N4: 0 | O4: 257 | P4: 1799 | Q4: 10622.66
A5: 01/04/2025 | B5: 1 - Factura A | C5: 711 | D5: 6930599 | F5: 35139646397105 | G5: CUIT | H5: 30677237119 | I5: AUTOPISTAS DEL SOL S A | J5: 1 | K5: $ | L5: 9359.78 | M5: 0 | N5: 280.79 | O5: 374.39 | P5: 1965.56 | Q5: 11980.52
A6: 14/04/2025 | B6: 1 - Factura A | C6: 5009 | D6: 1345646 | F6: 75154574924153 | G6: CUIT | H6: 30574876474 | I6: AUTOPISTAS URBANAS S A | J6: 1 | K6: $ | L6: 3801.48 | M6: 0 | N6: 0 | O6: 494.18 | P6: 798.31 | Q6: 5093.97
A7: 30/04/2025 | B7: 1 - Factura A | C7: 5015 | D7: 832362 | F7: 75184523307368 | G7: CUIT | H7: 30574876474 | I7: AUTOPISTAS URBANAS S A | J7: 1 | K7: $ | L7: 82310.49 | M7: 0 | N7: 0 | O7: 10700.35 | P7: 17285.14 | Q7: 110295.98
A8: 15/04/2025 | B8: 1 - Factura A | C8: 113 | D8: 4177115 | F8: 75160112855057 | G8: CUIT | H8: 30577207190 | I8: COORDINACION ECOLOGICA AREA METROPOLITANA SOCIEDAD DEL ESTADO | J8: 1 | K8: $ | L8: 3719.01 | M8: 0 | N8: 0 | O8: 111.57 | P8: 780.99 | Q8: 4611.57
A9: 30/04/2025 | B9: 1 - Factura A | C9: 113 | D9: 4205467 | F9: 75180616878598 | G9: CUIT | H9: 30577207190 | I9: COORDINACION ECOLOGICA AREA METROPOLITANA SOCIEDAD DEL ESTADO | J9: 1 | K9: $ | L9: 2479.34 | M9: 0 | N9: 0 | O9: 74.38 | P9: 520.66 | Q9: 3074.38
A10: 07/04/2025 | B10: 1 - Factura A | C10: 700 | D10: 2376670 | F10: 75142734003440 | G10: CUIT | H10: 30715804812 | I10: CORREDORES VIALES SOCIEDAD ANONIMA | J10: 1 | K10: $ | L10: 1871.97 | M10: 0 | N10: 0 | O10: 0 | P10: 393.11 | Q10: 2265.08
A11: 22/04/2025 | B11: 1 - Factura A | C11: 700 | D11: 2405995 | F11: 75162438670778 | G11: CUIT | H11: 30715804812 | I11: CORREDORES VIALES SOCIEDAD ANONIMA | J11: 1 | K11: $ | L11: 1663.97 | M11: 0 | N11: 0 | O11: 0 | P11: 349.43 | Q11: 2013.4
A12: 29/04/2025 | B12: 1 - Factura A | C12: 104 | D12: 8983014 | F12: 75172135088830 | G12: CUIT | H12: 30715804812 | I12: CORREDORES VIALES SOCIEDAD ANONIMA | J12: 1 | K12: $ | L12: 2079.97 | M12: 0 | N12: 0 | O12: 83.2 | P12: 436.79 | Q12: 2599.96
A13: 01/04/2025 | B13: 1 - Factura A | C13: 629 | D13: 5982817 | F13: 35133402229824 | G13: CUIT | H13: 30663498513 | I13: GRUPO CONCESIONARIO DEL OESTE SA | J13: 1 | K13: $ | L13: 5662.12 | M13: 0 | N13: 0 | O13: 226.48 | P13: 1189.05 | Q13: 7077.65
A14: 28/04/2025 | B14: 1 - Factura A | C14: 3 | D14: 8212 | F14: 75178083793588 | G14: CUIT | H14: 30710449658 | I14: PORTUMAT S.R.L. | J14: 1 | K14: $ | L14: 260330.52 | M14: 0 | N14: 0 | O14: 0 | P14: 54669.41 | Q14: 314999.93
... A17: 24/04/2025 | B17: 1 - Factura A | C17: 20 | D17: 40132 | F17: 75177648008643 | G17: CUIT | H17: 30717210847 | I17: STENDY | J17: 1 | K17: $ | L17: 7666.11 | M17: 0 | N17: 0 | O17: 0 | P17: 1609.89 | Q17: 9275.99

Sheet Ventas 07
C2: Totales por Tipo de Comprobante - ARCA
D3: Base | E3: IVA | F3: Otros Imp. | G3: Total Compr.
C4: FACTURAS A | D4: 76792881 | E4: =+D4*0.21 -> 16126505 | G4: =SUBTOTAL(9,D4:F4) -> 92919386
C5: NC A | D5: -3008166.8 | E5: =+D5*0.21 -> -631715.04 | G5: =SUBTOTAL(9,D5:F5) -> -3639881.9
C6: FACTURAS B | D6: 44738970 | E6: =+D6*0.21 -> 9395183.7 | G6: =SUBTOTAL(9,D6:F6) -> 54134154
C7: NC B | D7: -3413336 | E7: =+D7*0.21 -> -716800.56 | G7: =SUBTOTAL(9,D7:F7) -> -4130136.6
C8: ND B | D8: 2572378.7 | E8: =+D8*0.21 -> 540199.53 | G8: =SUBTOTAL(9,D8:F8) -> 3112578.2
D9: =SUBTOTAL(9,D4:D8) -> 1.1768273e+08 | E9: =SUBTOTAL(9,E4:E8) -> 24713373 | F9: 0 | G9: =+E9+D9 -> 1.423961e+08 | H9: =+SUBTOTAL(109,H14:H523) -> 1.1749865e+08
A13: Fecha | B13: Razon Social | C13: Cuit | D13: Provincia | E13: Ciudad | F13: Condicion IVA | G13: Nro Factura | H13: Importe Neto Gravado | I13: Importe No Grav | J13: IVA21 | K13: Total IVA | L13: Total Facturado
A14: 14/07/2025 | B14: ROMINA ELIZABETH TOBAR VALDES | C14: 27288300793 | D14: Buenos Aires | E14: BANFIELD | F14: RI | G14: FCA 0005-00000176 | H14: 55289.26 | I14: 0 | J14: 11610.74 | K14: 11610.74 | L14: 66900
A15: 03/07/2025 | B15: GALENO ARGENTINA SA | C15: 30522428163 | D15: Ciudad de Buenos Aires | E15: SIN IDENTIFICAR | F15: RI | G15: FCA 0006-00000617 | H15: 17797801 | I15: 0 | J15: 3737538.2 | K15: 3737538.2 | L15: 21535339
A16: 08/07/2025 | B16: GALENO ARGENTINA SA | C16: 30522428163 | D16: Ciudad de Buenos Aires | E16: SIN IDENTIFICAR | F16: RI | G16: FCA 0006-00000618 | H16: 5842843 | I16: 0 | J16: 1226997 | K16: 1226997 | L16: 7069840
A17: 10/07/2025 | B17: OBRA SOCIAL UNION PERSONAL DE LA UNION DEL PERSONAL CIVIL DE LA NACION | C17: 30683032227 | D17: Ciudad de Buenos Aires | E17: SIN IDENTIFICAR | F17: RI | G17: FCA 0006-00000619 | H17: 4756361.6 | I17: 0 | J17: 998835.94 | K17: 998835.94 | L17: 5755197.5
A18: 11/07/2025 | B18: GALENO ARGENTINA SA | C18: 30522428163 | D18: Ciudad de Buenos Aires | E18: SIN IDENTIFICAR | F18: RI | G18: FCA 0006-00000620 | H18: 3305669.4 | I18: 0 | J18: 694190.58 | K18: 694190.58 | L18: 3999860
A19: 17/07/2025 | B19: AVALIAN SALUD Y BIENESTAR COOPERATIVA LIMITADA | C19: 30604958640 | D19: Ciudad de Buenos Aires | E19: SIN IDENTIFICAR | F19: RI | G19: FCA 0006-00000621 | H19: 8386363.6 | I19: 0 | J19: 1761136.4 | K19: 1761136.4 | L19: 10147500
A20: 18/07/2025 | B20: GALENO ARGENTINA SA | C20: 30522428163 | D20: Ciudad de Buenos Aires | E20: SIN IDENTIFICAR | F20: RI | G20: FCA 0006-00000622 | H20: 9725534.7 | I20: 0 | J20: 2042362.3 | K20: 2042362.3 | L20: 11767897
A21: 29/07/2025 | B21: GALENO ARGENTINA SA | C21: 30522428163 | D21: Ciudad de Buenos Aires | E21: SIN IDENTIFICAR | F21: RI | G21: FCA 0006-00000623 | H21: 11252777 | I21: 0 | J21: 2363083.1 | K21: 2363083.1 | L21: 13615860
A22: 03/07/2025 | B22: GALENO ARGENTINA SA | C22: 30522428163 | D22: Ciudad de Buenos Aires | E22: SIN IDENTIFICAR | F22: RI | G22: FCA 0007-00002578 | H22: 2605258.3 | I22: 0 | J22: 547104.24 | K22: 547104.24 | L22: 3152362.5
A23: 03/07/2025 | B23: GALENO ARGENTINA SA | C23: 30522428163 | D23: Ciudad de Buenos Aires | E23: SIN IDENTIFICAR | F23: RI | G23: FCA 0007-00002579 | H23: 184088.84 | I23: 0 | J23: 38658.66 | K23: 38658.66 | L23: 222747.5
A24: 03/07/2025 | B24: GALENO ARGENTINA SA | C24: 30522428163 | D24: Ciudad de Buenos Aires | E24: SIN IDENTIFICAR | F24: RI | G24: FCA 0007-00002580 | H24: 1305528.7 | I24: 0 | J24: 274161.03 | K24: 274161.03 | L24: 1579689.7
A25: 04/07/2025 | B25: GALENO ARGENTINA SA | C25: 30522428163 | D25: Ciudad de Buenos Aires | E25: SIN IDENTIFICAR | F25: RI | G25: FCA 0007-00002581 | H25: 1338683.3 | I25: 0 | J25: 281123.49 | K25: 281123.49 | L25: 1619806.8
... A80: 30/07/2025 | B80: OBRA SOCIAL DEL PERSONAL DE LAS TELECOMUNICACIONES DE LA REPUBLICA ARGENTINA | C80: 30608716390 | D80: Ciudad de Buenos Aires | E80: SIN IDENTIFICAR | F80: RI | G80: FCA 0007-00002636 | H80: 133214.05 | I80: 0 | J80: 27974.95 | K80: 27974.95 | L80: 161189
A81: 01/07/2025 | B81: DANELLI RAQUEL | D81: Ciudad de Buenos Aires | E81: SIN IDENTIFICAR | F81: CF | G81: FCB 0003-00002891 | H81: 4328134 | J81: 5206.61 | K81: 5206.61 | L81: 30000
A82: 01/07/2025 | B82: . CONSUMIDOR FINAL ANÓNIMO | C82: 111 | D82: Ciudad de Buenos Aires | E82: SIN IDENTIFICAR | F82: CF | G82: FCB 0005-00013625 | H82: 16528.93 | I82: 0 | J82: 3471.07 | K82: 3471.07 | L82: 20000
A83: 01/07/2025 | B83: RAFAEL OSCAR AZNAR | C83: 20124538999 | D83: Ciudad de Buenos Aires | E83: SIN IDENTIFICAR | F83: CF | G83: FCB 0005-00013626 | H83: 170661.16 | I83: 0 | J83: 35838.84 | K83: 35838.84 | L83: 206500
A84: 01/07/2025 | B84: . CONSUMIDOR FINAL ANÓNIMO | C84: 111 | D84: Ciudad de Buenos Aires | E84: SIN IDENTIFICAR | F84: CF | G84: FCB 0005-00013627 | H84: 29752.07 | I84: 0 | J84: 6247.93 | K84: 6247.93 | L84: 36000
A85: 01/07/2025 | B85: . CONSUMIDOR FINAL ANÓNIMO | C85: 111 | D85: Ciudad de Buenos Aires | E85: SIN IDENTIFICAR | F85: CF | G85: FCB 0005-00013628 | H85: 33471.07 | I85: 0 | J85: 7028.93 | K85: 7028.93 | L85: 40500
A86: 01/07/2025 | B86: . CONSUMIDOR FINAL ANÓNIMO | C86: 111 | D86: Ciudad de Buenos Aires | E86: SIN IDENTIFICAR | F86: CF | G86: FCB 0005-00013629 | H86: 18181.82 | I86: 0 | J86: 3818.18 | K86: 3818.18 | L86: 22000
A87: 01/07/2025 | B87: . CONSUMIDOR FINAL ANÓNIMO | C87: 111 | D87: Ciudad de Buenos Aires | E87: SIN IDENTIFICAR | F87: CF | G87: FCB 0005-00013630 | H87: 16528.93 | I87: 0 | J87: 3471.07 | K87: 3471.07 | L87: 20000
A88: 01/07/2025 | B88: . CONSUMIDOR FINAL ANÓNIMO | C88: 111 | D88: Ciudad de Buenos Aires | E88: SIN IDENTIFICAR | F88: CF | G88: FCB 0005-00013631 | H88: 16528.93 | I88: 0 | J88: 3471.07 | K88: 3471.07 | L88: 20000
A89: 01/07/2025 | B89: . CONSUMIDOR FINAL ANÓNIMO | C89: 111 | D89: Ciudad de Buenos Aires | E89: SIN IDENTIFICAR | F89: CF | G89: FCB 0005-00013632 | H89: 36363.64 | I89: 0 | J89: 7636.36 | K89: 7636.36 | L89: 44000
A90: 01/07/2025 | B90: . CONSUMIDOR FINAL ANÓNIMO | C90: 111 | D90: Ciudad de Buenos Aires | E90: SIN IDENTIFICAR | F90: CF | G90: FCB 0005-00013633 | H90: 15702.48 | I90: 0 | J90: 3297.52 | K90: 3297.52 | L90: 19000
A91: 01/07/2025 | B91: . CONSUMIDOR FINAL ANÓNIMO | C91: 111 | D91: Ciudad de Buenos Aires | E91: SIN IDENTIFICAR | F91: CF | G91: FCB 0005-00013634 | H91: 20661.16 | I91: 0 | J91: 4338.84 | K91: 4338.84 | L91: 25000
A92: 01/07/2025 | B92: . CONSUMIDOR FINAL ANÓNIMO | C92: 111 | D92: Ciudad de Buenos Aires | E92: SIN IDENTIFICAR | F92: CF | G92: FCB 0005-00013635 | H92: 24793.39 | I92: 0 | J92: 5206.61 | K92: 5206.61 | L92: 30000
A93: 01/07/2025 | B93: . CONSUMIDOR FINAL ANÓNIMO | C93: 111 | D93: Ciudad de Buenos Aires | E93: SIN IDENTIFICAR | F93: CF | G93: FCB 0005-00013636 | H93: 14876.03 | I93: 0 | J93: 3123.97 | K93: 3123.97 | L93: 18000
... A397: 01/07/2025 | B397: SALLES ANA MARIA | C397: 17814995 | D397: Ciudad de Buenos Aires | E397: SIN IDENTIFICAR | F397: CF | G397: FCB 0007-00006136 | H397: 24793.39 | I397: 0 | J397: 5206.61 | K397: 5206.61 | L397: 30000
A398: 01/07/2025 | B398: VOLPI, ALBERTO JAVIER | D398: Ciudad de Buenos Aires | E398: SIN IDENTIFICAR | F398: CF | G398: FCB 0007-00006137 | H398: 22314.05 | I398: 0 | J398: 4685.95 | K398: 4685.95 | L398: 27000
A399: 01/07/2025 | B399: ARANA, MARCELLA OFELIA | C399: 10138957 | D399: Ciudad de Buenos Aires | E399: SIN IDENTIFICAR | F399: CF | G399: FCB 0007-00006138 | H399: 17355.37 | I399: 0 | J399: 3644.63 | K399: 3644.63 | L399: 21000
A400: 01/07/2025 | B400: NAJUS ANIBAL RUBEN | D400: Buenos Aires | E400: SIN IDENTIFICAR | F400: CF | G400: FCB 0007-00006139 | H400: 21487.6 | I400: 0 | J400: 4512.4 | K400: 4512.4 | L400: 26000
A401: 01/07/2025 | B401: MINERVINI, MARIA DEL CARMEN LILIANA | C401: 12791306 | D401: Buenos Aires | E401: SIN IDENTIFICAR | F401: CF | G401: FCB 0007-00006140 | H401: 28099.17 | I401: 0 | J401: 5900.83 | K401: 5900.83 | L401: 34000
A402: 01/07/2025 | B402: FERRAZIN, CAROLINA ELEONORA INES | C402: 17855620 | D402: Buenos Aires | E402: SIN IDENTIFICAR | F402: CF | G402: FCB 0007-00006141 | H402: 24793.39 | I402: 0 | J402: 5206.61 | K402: 5206.61 | L402: 30000
A403: 01/07/2025 | B403: FERRAZIN, CAROLINA ELEONORA INES | C403: 17855620 | D403: Buenos Aires | E403: SIN IDENTIFICAR | F403: CF | G403: FCB 0007-00006142 | H403: 24793.39 | I403: 0 | J403: 5206.61 | K403: 5206.61 | L403: 30000
A404: 01/07/2025 | B404: MONTI, MARIA PAULA | C404: 24699538 | D404: Buenos Aires | E404: MAR DEL PLATA | F404: CF | G404: FCB 0007-00006143 | H404: 28099.17 | I404: 0 | J404: 5900.83 | K404: 5900.83 | L404: 34000
A405: 01/07/2025 | B405: ENRIQUE LUIS SAGGESE | C405: 4186965 | D405: Buenos Aires | E405: SIN IDENTIFICAR | F405: CF | G405: FCB 0007-00006144 | H405: 132231.4 | I405: 0 | J405: 27768.6 | K405: 27768.6 | L405: 160000
A406: 01/07/2025 | B406: ALEJANDRA SIFFREDI TORRES SANMARCO | C406: 5804480 | D406: Ciudad de Buenos Aires | E406: SIN IDENTIFICAR | F406: CF | G406: FCB 0007-00006145 | H406: 22314.05 | I406: 0 | J406: 4685.95 | K406: 4685.95 | L406: 27000
A407: 01/07/2025 | B407: ROMERO LEONARDO GABRIEL | C407: 20435515 | D407: Buenos Aires | E407: VICTORIA | F407: CF | G407: FCB 0007-00006146 | H407: 181818.18 | I407: 0 | J407: 38181.82 | K407: 38181.82 | L407: 220000
A408: 01/07/2025 | B408: GABRIELA VANINA GALLO | C408: 26542077 | D408: Buenos Aires | E408: SIN IDENTIFICAR | F408: CF | G408: FCB 0007-00006147 | H408: 35537.19 | I408: 0 | J408: 7462.81 | K408: 7462.81 | L408: 43000
A409: 01/07/2025 | B409: KARIVALI DESPINA | C409: 93332052 | D409: Buenos Aires | E409: SIN IDENTIFICAR | F409: CF | G409: FCB 0007-00006148 | H409: 18512.4 | I409: 0 | J409: 3887.6 | K409: 3887.6 | L409: 22400
A410: 03/07/2025 | B410: ROSA GRACIELA DIAZ | C410: 27056711355 | D410: Corrientes | E410: SIN IDENTIFICAR | F410: CF | G410: FCB 0007-00006149 | H410: 289256.2 | I410: 0 | J410: 60743.8 | K410: 60743.8 | L410: 350000
A411: 03/07/2025 | B411: ASOCIACION MUTUAL SANCOR SALUD | C411: 30590354798 | D411: Santa Fe | E411: SUNCHALES | F411: EX | G411: FCB 0007-00006150 | H411: 2033735.3 | I411: 0 | J411: 427084.41 | K411: 427084.41 | L411: 2460819.7
A412: 04/07/2025 | B412: NADINA DEL VALLE VEGA | C412: 20343735643 | D412: Ciudad de Buenos Aires | E412: SIN IDENTIFICAR | F412: CF | G412: FCB 0007-00006151 | H412: 18595.04 | I412: 0 | J412: 3904.96 | K412: 3904.96 | L412: 22500
... A428: 15/07/2025 | B428: PEDRO LUIS REPPETTO | C428: 20403525554 | D428: Buenos Aires | E428: PINAMAR | F428: CF | G428: FCB 0007-00006167 | H428: 18595.04 | I428: 0 | J428: 3904.96 | K428: 3904.96 | L428: 22500
A429: 15/07/2025 | B429: COLUCCIO, MARIANA ISABEL | D429: Buenos Aires | E429: SIN IDENTIFICAR | F429: CF | G429: FCB 0007-00006168 | H429: 33057.85 | I429: 0 | J429: 6942.15 | K429: 6942.15 | L429: 40000
A430: 16/07/2025 | B430: CRISTALDO BRENDA MARIA | C430: 27405431306 | D430: Ciudad de Buenos Aires | E430: SIN IDENTIFICAR | F430: CF | G430: FCB 0007-00006169 | H430: 24793.39 | I430: 0 | J430: 5206.61 | K430: 5206.61 | L430: 30000
A431: 16/07/2025 | B431: CASCO MARTA MARIA | C431: 3791160 | D431: Buenos Aires | E431: RAMOS MEJIA | F431: CF | G431: FCB 0007-00006170 | H431: 5475.21 | I431: 0 | J431: 1149.79 | K431: 1149.79 | L431: 6625
A432: 16/07/2025 | B432: BIANCHI TERESA GERMANA | C432: 2719694 | D432: Buenos Aires | E432: RAMOS MEJIA | F432: CF | G432: FCB 0007-00006171 | H432: 8177.69 | I432: 0 | J432: 1717.31 | K432: 1717.31 | L432: 9895
A433: 16/07/2025 | B433: RUBEN BENJAMIN GOMEZ | C433: 23241341399 | D433: Ciudad de Buenos Aires | E433: SIN IDENTIFICAR | F433: CF | G433: FCB 0007-00006172 | H433: 18595.04 | I433: 0 | J433: 3904.96 | K433: 3904.96 | L433: 22500
A434: 16/07/2025 | B434: ALVAREZ MARTA OLGA | C434: 9955440 | D434: Buenos Aires | E434: RAMOS MEJIA | F434: CF | G434: FCB 0007-00006173 | H434: 8603.31 | I434: 0 | J434: 1806.69 | K434: 1806.69 | L434: 10410
A435: 16/07/2025 | B435: BALMAYOR ISABEL | C435: 3203937 | D435: Ciudad de Buenos Aires | E435: Floresta | F435: CF | G435: FCB 0007-00006174 | H435: 20524.79 | I435: 0 | J435: 4310.21 | K435: 4310.21 | L435: 24835
A436: 16/07/2025 | B436: SOSA MARIA GRACIELA | C436: 2551284 | D436: Buenos Aires | E436: GENERAL RODRIGUEZ | F436: CF | G436: FCB 0007-00006175 | H436: 8603.31 | I436: 0 | J436: 1806.69 | K436: 1806.69 | L436: 10410
A437: 16/07/2025 | B437: RIVERO DE BARBA MARÍA EMILIA | C437: 6091102 | D437: Ciudad de Buenos Aires | E437: SIN IDENTIFICAR | F437: CF | G437: FCB 0007-00006176 | H437: 8793.39 | I437: 0 | J437: 1846.61 | K437: 1846.61 | L437: 10640
A438: 17/07/2025 | B438: RAQUEL DURAÑONA | C438: 4648296 | D438: Buenos Aires | E438: SIN IDENTIFICAR | F438: CF | G438: FCB 0007-00006177 | H438: 28925.62 | I438: 0 | J438: 6074.38 | K438: 6074.38 | L438: 35000
A439: 17/07/2025 | B439: MAIZTEGUI ANDRÉS | C439: 20002428 | D439: Ciudad de Buenos Aires | E439: Recoleta | F439: CF | G439: FCB 0007-00006178 | H439: 17355.37 | I439: 0 | J439: 3644.63 | K439: 3644.63 | L439: 21000
A440: 17/07/2025 | B440: EDUARDO PENJASOFF | C440: 20043010973 | D440: Ciudad de Buenos Aires | E440: SIN IDENTIFICAR | F440: CF | G440: FCB 0007-00006179 | H440: 17355.37 | I440: 0 | J440: 3644.63 | K440: 3644.63 | L440: 21000
A441: 17/07/2025 | B441: PEDROZO PAULA GABRIELA | C441: 29654556 | D441: Ciudad de Buenos Aires | E441: SIN IDENTIFICAR | F441: CF | G441: FCB 0007-00006180 | H441: 46280.99 | I441: 0 | J441: 9719.01 | K441: 9719.01 | L441: 56000
A442: 17/07/2025 | B442: SCHELGEL, LUIS ALBERTO | D442: Buenos Aires | E442: SIN IDENTIFICAR | F442: CF | G442: FCB 0007-00006181 | H442: 47933.88 | I442: 0 | J442: 10066.12 | K442: 10066.12 | L442: 58000
A443: 17/07/2025 | B443: SILVIA MONICA ROJAS | C443: 27141958807 | D443: Ciudad de Buenos Aires | E443: Balvanera | F443: CF | G443: FCB 0007-00006182 | H443: 28099.17 | I443: 0 | J443: 5900.83 | K443: 5900.83 | L443: 34000
A444: 17/07/2025 | B444: AGOSTINO MIRIAM | C444: 17275405 | D444: Buenos Aires | E444: SIN IDENTIFICAR | F444: CF | G444: FCB 0007-00006183 | H444: 43801.65 | I444: 0 | J444: 9198.35 | K444: 9198.35 | L444: 53000
A445: 17/07/2025 | B445: CONEN SILVIA ADELA | C445: 334529 | D445: Ciudad de Buenos Aires | E445: SIN IDENTIFICAR | F445: CF | G445: FCB 0007-00006184 | H445: 32231.4 | I445: 0 | J445: 6768.6 | K445: 6768.6 | L445: 39000
A446: 17/07/2025 | B446: GLADYS SOLER | C446: 27057878539 | D446: Buenos Aires | E446: CIUDAD EVITA | F446: CF | G446: FCB 0007-00006185 | H446: 231404.96 | I446: 0 | J446: 48595.04 | K446: 48595.04 | L446: 280000
A447: 17/07/2025 | B447: Galeno A.R.T. S.A. | C447: 30685228501 | D447: Ciudad de Buenos Aires | E447: SIN IDENTIFICAR | F447: EX | G447: FCB 0007-00006186 | H447: 1175206.6 | I447: 0 | J447: 246793.39 | K447: 246793.39 | L447: 1422000
A448: 17/07/2025 | B448: ASOCIACION MUTUAL SANCOR SALUD | C448: 30590354798 | D448: Santa Fe | E448: SUNCHALES | F448: EX | G448: FCB 0007-00006187 | H448: 83471.07 | I448: 0 | J448: 17528.93 | K448: 17528.93 | L448: 101000
A449: 18/07/2025 | B449: Galeno A.R.T. S.A. | C449: 30685228501 | D449: Ciudad de Buenos Aires | E449: SIN IDENTIFICAR | F449: EX | G449: FCB 0007-00006188 | H449: 3295867.8 | I449: 0 | J449: 692132.23 | K449: 692132.23 | L449: 3988000
A450: 18/07/2025 | B450: ASOCIACION MUTUAL SANCOR SALUD | C450: 30590354798 | D450: Santa Fe | E450: SUNCHALES | F450: EX | G450: FCB 0007-00006189 | H450: 865123.97 | I450: 0 | J450: 181676.03 | K450: 181676.03 | L450: 1046800
A451: 21/07/2025 | B451: OBRA SOCIAL DEL PERSONAL DEL ORGANISMO DE CONTROL EXTERNO | C451: 30657314974 | D451: Ciudad de Buenos Aires | E451: SIN IDENTIFICAR | F451: EX | G451: FCB 0007-00006190 | H451: 926446.28 | I451: 0 | J451: 194553.72 | K451: 194553.72 | L451: 1121000
A452: 21/07/2025 | B452: LIMIA P ROMANO | C452: 27014591813 | D452: Ciudad de Buenos Aires | E452: SIN IDENTIFICAR | F452: CF | G452: FCB 0007-00006191 | H452: 41322.31 | I452: 0 | J452: 8677.69 | K452: 8677.69 | L452: 50000
A453: 21/07/2025 | B453: NICOLINA TASSONE | C453: 27938674375 | D453: Ciudad de Buenos Aires | E453: SIN IDENTIFICAR | F453: CF | G453: FCB 0007-00006192 | H453: 24793.39 | I453: 0 | J453: 5206.61 | K453: 5206.61 | L453: 30000
A454: 22/07/2025 | B454: DANTE ANGEL MIÑO GALVEZ | C454: 20219142308 | D454: Buenos Aires | E454: SIN IDENTIFICAR | F454: CF | G454: FCB 0007-00006193 | H454: 29752.07 | I454: 0 | J454: 6247.93 | K454: 6247.93 | L454: 36000
... A456: 24/07/2025 | B456: GIGAGLIA, MARIA LUCILA | C456: 25315045 | D456: Buenos Aires | E456: BECCAR | F456: CF | G456: FCB 0007-00006195 | H456: 15702.48 | I456: 0 | J456: 3297.52 | K456: 3297.52 | L456: 19000
A457: 24/07/2025 | B457: PASSUELLO, VIVIANA ISABEL | D457: Buenos Aires | E457: SIN IDENTIFICAR | F457: CF | G457: FCB 0007-00006196 | H457: 19834.71 | I457: 0 | J457: 4165.29 | K457: 4165.29 | L457: 24000
A458: 24/07/2025 | B458: PINO, ANA PAULA | C458: 20008996 | D458: Buenos Aires | E458: FLORIDA | F458: CF | G458: FCB 0007-00006197 | H458: 19834.71 | I458: 0 | J458: 4165.29 | K458: 4165.29 | L458: 24000
A459: 24/07/2025 | B459: MAYRA ALEJANDRA SANTIAGO PAREDES | C459: 27959707796 | D459: Ciudad de Buenos Aires | E459: SIN IDENTIFICAR | F459: CF | G459: FCB 0007-00006198 | H459: 24793.39 | I459: 0 | J459: 5206.61 | K459: 5206.61 | L459: 30000
A460: 24/07/2025 | B460: DORFMAN SANDRA | D460: Ciudad de Buenos Aires | E460: SIN IDENTIFICAR | F460: CF | G460: FCB 0007-00006199 | H460: 61983.47 | I460: 0 | J460: 13016.53 | K460: 13016.53 | L460: 75000
A461: 24/07/2025 | B461: JUAN ANTONIO PARRA | C461: 20149320025 | D461: Ciudad de Buenos Aires | E461: SIN IDENTIFICAR | F461: CF | G461: FCB 0007-00006200 | H461: 33057.85 | I461: 0 | J461: 6942.15 | K461: 6942.15 | L461: 40000
A462: 24/07/2025 | B462: BAUAB, CAROLINA | D462: Buenos Aires | E462: SIN IDENTIFICAR | F462: CF | G462: FCB 0007-00006201 | H462: 50413.22 | I462: 0 | J462: 10586.78 | K462: 10586.78 | L462: 61000
A463: 24/07/2025 | B463: GIANLUCA FRASETTE MADIA | C463: 20442617016 | D463: Ciudad de Buenos Aires | E463: SIN IDENTIFICAR | F463: CF | G463: FCB 0007-00006202 | H463: 18595.04 | I463: 0 | J463: 3904.96 | K463: 3904.96 | L463: 22500
A464: 24/07/2025 | B464: JUANA DEL CARMEN VILLAFANE | C464: 27050931094 | D464: Ciudad de Buenos Aires | E464: SIN IDENTIFICAR | F464: CF | G464: FCB 0007-00006203 | H464: 32231.4 | I464: 0 | J464: 6768.6 | K464: 6768.6 | L464: 39000
A465: 24/07/2025 | B465: GLORIA LEONOR ZAMPERETTI | C465: 27044664262 | D465: Ciudad de Buenos Aires | E465: SIN IDENTIFICAR | F465: CF | G465: FCB 0007-00006204 | H465: 18181.82 | I465: 0 | J465: 3818.18 | K465: 3818.18 | L465: 22000
A466: 24/07/2025 | B466: ALEJANDRO CARLOS MIHANOVICH | C466: 20041007266 | D466: Ciudad de Buenos Aires | E466: SIN IDENTIFICAR | F466: CF | G466: FCB 0007-00006205 | H466: 14876.03 | I466: 0 | J466: 3123.97 | K466: 3123.97 | L466: 18000
A467: 24/07/2025 | B467: MORANO, ANDREA NORA | D467: Buenos Aires | E467: SIN IDENTIFICAR | F467: CF | G467: FCB 0007-00006206 | H467: 25214.05 | I467: 0 | J467: 5294.95 | K467: 5294.95 | L467: 30509
A468: 24/07/2025 | B468: SCHELGEL, LUIS ALBERTO | D468: Buenos Aires | E468: SIN IDENTIFICAR | F468: CF | G468: FCB 0007-00006207 | H468: 24793.39 | I468: 0 | J468: 5206.61 | K468: 5206.61 | L468: 30000
A469: 24/07/2025 | B469: RUIZ PAMELA RITA | C469: 26632702 | D469: Ciudad de Buenos Aires | E469: SIN IDENTIFICAR | F469: CF | G469: FCB 0007-00006208 | H469: 24793.39 | I469: 0 | J469: 5206.61 | K469: 5206.61 | L469: 30000
A470: 24/07/2025 | B470: RAMONET JOSÉ IGNACIO | C470: 20349097 | D470: Ciudad de Buenos Aires | E470: SIN IDENTIFICAR | F470: CF | G470: FCB 0007-00006209 | H470: 32231.4 | I470: 0 | J470: 6768.6 | K470: 6768.6 | L470: 39000
A471: 24/07/2025 | B471: CARLOS ANTONIO AGUSTIN COCITO | C471: 20085334647 | D471: Ciudad de Buenos Aires | E471: SIN IDENTIFICAR | F471: CF | G471: FCB 0007-00006210 | H471: 18181.82 | I471: 0 | J471: 3818.18 | K471: 3818.18 | L471: 22000
A472: 24/07/2025 | B472: RODRIGUEZ GRACIELA NOEMI | C472: 14316823 | D472: Ciudad de Buenos Aires | E472: Balvanera | F472: CF | G472: FCB 0007-00006211 | H472: 15702.48 | I472: 0 | J472: 3297.52 | K472: 3297.52 | L472: 19000
A473: 24/07/2025 | B473: CLAVIJO ROQUE | C473: 94433546 | D473: Ciudad de Buenos Aires | E473: SIN IDENTIFICAR | F473: CF | G473: FCB 0007-00006212 | H473: 32231.4 | I473: 0 | J473: 6768.6 | K473: 6768.6 | L473: 39000
A474: 24/07/2025 | B474: SANTA CRUZ ELISA | C474: 16145627 | D474: Buenos Aires | E474: BANFIELD | F474: CF | G474: FCB 0007-00006213 | H474: 17355.37 | I474: 0 | J474: 3644.63 | K474: 3644.63 | L474: 21000
A475: 24/07/2025 | B475: ALEJANDRO JOSE ASCHEMAGER | C475: 20345567217 | D475: Ciudad de Buenos Aires | E475: SIN IDENTIFICAR | F475: CF | G475: FCB 0007-00006214 | H475: 18181.82 | I475: 0 | J475: 3818.18 | K475: 3818.18 | L475: 22000
A476: 24/07/2025 | B476: CORIGLIANO, LORENA ELISA | C476: 25864351 | D476: Buenos Aires | E476: SARANDI | F476: CF | G476: FCB 0007-00006215 | H476: 33057.85 | I476: 0 | J476: 6942.15 | K476: 6942.15 | L476: 40000
A477: 24/07/2025 | B477: MATSUO, MARGARITA NOEMI | C477: 5607654 | D477: Buenos Aires | E477: VILLA ELISA | F477: CF | G477: FCB 0007-00006216 | H477: 28925.62 | I477: 0 | J477: 6074.38 | K477: 6074.38 | L477: 35000
...

Sheet arca 05
A1: Mis Comprobantes Recibidos - CUIT 30710473168
A2: Fecha | B2: Tipo | C2: Punto de Venta | D2: Número Desde | E2: Número Hasta | F2: Cód. Autorización | G2: Tipo Doc. Emisor | H2: Nro. Doc. Emisor | I2: Denominación Emisor | J2: Tipo Cambio | K2: Moneda | L2: Imp. Neto Gravado | M2: Imp. Neto No Gravado | N2: Imp. Op. Exentas | O2: Otros Tributos | P2: IVA | Q2: Imp. Total
A3: 01/05/2025 | B3: 1 - Factura A | C3: 1 | D3: 123356 | F3: 75189399505180 | G3: CUIT | H3: 30714864269 | I3: CONTABILIUM S.A. S. A. | J3: 1 | K3: $ | L3: 164170 | M3: 0 | N3: 0 | O3: 0 | P3: 34475.7 | Q3: 198645.7
A4: 01/05/2025 | B4: 1 - Factura A | C4: 4 | D4: 1518883 | F4: 75184421857692 | G4: CUIT | H4: 30716620634 | I4: FIRST LABEL S.R.L. | J4: 1 | K4: $ | L4: 867767.77 | M4: 0 | N4: 0 | O4: 34710.71 | P4: 182231.23 | Q4: 1084709.7
A5: 31/05/2025 | B5: 1 - Factura A | C5: 50 | D5: 4376000 | E5: ARCA | F5: 75226311242782 | G5: CUIT | H5: 30714112836 | I5: AUTOPISTAS DE BUENOS AIRES (AUBASA) SA S. A. | J5: 1 | K5: $ | L5: 2875.37 | M5: 0 | N5: 0 | O5: 86.26 | P5: 603.83 | Q5: 3565.46
A6: 01/05/2025 | B6: 1 - Factura A | C6: 711 | D6: 7055586 | E6: ARCA | F6: 35179521470241 | G6: CUIT | H6: 30677237119 | I6: AUTOPISTAS DEL SOL S A | J6: 1 | K6: $ | L6: 14559.75 | M6: 0 | N6: 436.79 | O6: 582.39 | P6: 3057.56 | Q6: 18636.49
A7: 01/05/2025 | B7: 11 - Factura C | C7: 4 | D7: 11 | F7: 75183419865716 | G7: CUIT | H7: 20086277523 | I7: BOTINDARI JUAN CARLOS | J7: 1 | K7: $ | O7: 0 | Q7: 290000
A8: 02/05/2025 | B8: 1 - Factura A | C8: 500 | D8: 1723166 | F8: 75177133592830 | G8: CUIT | H8: 30654118767 | I8: SOLUCIONES MULTIMEDIA S A | J8: 1 | K8: $ | L8: 127126.59 | M8: 0 | N8: 0 | O8: 5085.07 | P8: 26696.58 | Q8: 158908.24
A9: 02/05/2025 | B9: 1 - Factura A | C9: 3051 | D9: 911477 | F9: 75187657875181 | G9: CUIT | H9: 30678814357 | I9: TELEFONICA MOVILES ARGENTINA SOCIEDAD ANONIMA | J9: 1 | K9: $ | L9: 88958.37 | M9: 0 | N9: 0 | O9: 10832.74 | P9: 24018.76 | Q9: 123809.87
A10: 02/05/2025 | B10: 1 - Factura A | C10: 2 | D10: 239 | F10: 75182528347539 | G10: CUIT | H10: 30605344352 | I10: CONSORCIO BARTOLOME MITRE 2466 | J10: 1 | K10: $ | L10: 2000000 | M10: 0 | N10: 0 | O10: 0 | P10: 420000 | Q10: 2420000
A11: 03/05/2025 | B11: 1 - Factura A | C11: 1 | D11: 827481 | F11: 75199246715421 | G11: CUIT | H11: 33716307749 | I11: VERISURE ARGENTINA MONITOREO DE ALARMAS SA | J11: 1 | K11: $ | L11: 53953.8 | M11: 0 | N11: 0 | O11: 2158.15 | P11: 11330.3 | Q11: 67442.25
A12: 04/05/2025 | B12: 11 - Factura C | C12: 1 | D12: 24 | F12: 75205029806246 | G12: CUIT | H12: 27443612705 | I12: MIGOYA MORIONDO MARIA INES | J12: 1 | K12: $ | O12: 0 | Q12: 900000
A13: 05/05/2025 | B13: 1 - Factura A | C13: 3 | D13: 37 | F13: 75182868622117 | G13: CUIT | H13: 20216164262 | I13: VELEZ ALEJANDRO MARCELO | J13: 1 | K13: $ | L13: 1500000 | M13: 0 | N13: 0 | O13: 0 | P13: 315000 | Q13: 1815000
A14: 05/05/2025 | B14: 11 - Factura C | C14: 2 | D14: 127 | E14: ARCA | F14: 75188822266811 | G14: CUIT | H14: 27315710508 | I14: RIVERO GABRIELA ROCIO | J14: 1 | K14: $ | O14: 0 | Q14: 48600
A15: 05/05/2025 | B15: 11 - Factura C | C15: 1 | D15: 171 | F15: 75180808654353 | G15: CUIT | H15: 27338342840 | I15: CANCINO PAMELA RITA | J15: 1 | K15: $ | O15: 0 | Q15: 236000
A16: 05/05/2025 | B16: 11 - Factura C | C16: 2 | D16: 351 | F16: 75188019259251 | G16: CUIT | H16: 27265832178 | I16: BLASCO MARIA GUADALUPE | J16: 1 | K16: $ | O16: 0 | Q16: 3200000
A17: 05/05/2025 | B17: 11 - Factura C | C17: 1 | D17: 25 | F17: 75205030188537 | G17: CUIT | H17: 27443612705 | I17: MIGOYA MORIONDO MARIA INES | J17: 1 | K17: $ | O17: 0 | Q17: 900000
A18: 06/05/2025 | B18: 1 - Factura A | C18: 2 | D18: 11968 | F18: 75182968852300 | G18: CUIT | H18: 30714331082 | I18: ORTOPEDIA CASA ESCALADA S.R.L. | J18: 1 | K18: $ | L18: 493491.01 | M18: 0 | N18: 0 | O18: 0 | P18: 103633.11 | Q18: 597124.12
A19: 06/05/2025 | B19: 1 - Factura A | C19: 5 | D19: 1525 | F19: 75185012307446 | G19: CUIT | H19: 27265302225 | I19: PRADO MARISOL | J19: 1 | K19: $ | L19: 3500000 | M19: 0 | N19: 0 | O19: 0 | P19: 735000 | Q19: 4235000
A20: 06/05/2025 | B20: 1 - Factura A | C20: 6 | D20: 57343 | F20: 75188026619178 | G20: CUIT | H20: 30710177658 | I20: TARGET MEDICAL S.A. | J20: 1 | K20: $ | L20: 3155460 | M20: 0 | N20: 0 | O20: 126218.4 | P20: 662646.6 | Q20: 3944325
A21: 06/05/2025 | B21: 1 - Factura A | C21: 120 | D21: 5646 | F21: 75185964379405 | G21: CUIT | H21: 30587197215 | I21: PANATEL SOCIEDAD ANONIMA | J21: 1 | K21: $ | L21: 95041.32 | M21: 0 | N21: 0 | O21: 5702.48 | P21: 19958.68 | Q21: 120702.48
A22: 06/05/2025 | B22: 1 - Factura A | C22: 17 | D22: 12389 | F22: 75180001470373 | G22: CUIT | H22: 30661143610 | I22: ORTOPEDIA BERNAT SRL | J22: 1 | K22: $ | L22: 1154300 | M22: 0 | N22: 0 | O22: 46172 | P22: 242403 | Q22: 1442875
A23: 06/05/2025 | B23: 1 - Factura A | C23: 6 | D23: 50 | F23: 75181011299005 | G23: CUIT | H23: 30716401541 | I23: HIGH MOBILITY S.A.S. | J23: 1 | K23: $ | L23: 3122441 | M23: 0 | N23: 0 | O23: 0 | P23: 655712.61 | Q23: 3778153.6
A24: 06/05/2025 | B24: 11 - Factura C | C24: 2 | D24: 323 | F24: 75182991008641 | G24: CUIT | H24: 20326759792 | I24: VILLALTA MARIANO | J24: 1 | K24: $ | O24: 0 | Q24: 114000
A25: 07/05/2025 | B25: 1 - Factura A | C25: 700 | D25: 2440062 | F25: 75192224513566 | G25: CUIT | H25: 30715804812 | I25: CORREDORES VIALES SOCIEDAD ANONIMA | J25: 1 | K25: $ | L25: 27663.52 | M25: 0 | N25: 0 | O25: 1106.54 | P25: 5809.34 | Q25: 34579.4
A26: 08/05/2025 | B26: 1 - Factura A | C26: 4 | D26: 75883 | F26: 75199233815483 | G26: CUIT | H26: 33709738459 | I26: ORTOPEDICOS ALFOLATEX SA | J26: 1 | K26: $ | L26: 359845.2 | M26: 0 | N26: 0 | O26: 0 | P26: 75567.49 | Q26: 435412.69
A27: 08/05/2025 | B27: 1 - Factura A | C27: 8 | D27: 405 | F27: 75194305707004 | G27: CUIT | H27: 30643518364 | I27: FARMACIA DE MEDRANO 533 SOCIEDAD EN COMANDITA SIMPLE | J27: 1 | K27: $ | L27: 492200 | M27: 0 | N27: 0 | O27: 0 | P27: 103362 | Q27: 595562
A28: 14/05/2025 | B28: 1 - Factura A | C28: 5009 | D28: 1403394 | E28: ARCA | F28: 75204107232683 | G28: CUIT | H28: 30574876474 | I28: AUTOPISTAS URBANAS S A | J28: 1 | K28: $ | L28: 4856.3 | M28: 0 | N28: 0 | O28: 631.32 | P28: 1019.82 | Q28: 6507.44
A29: 09/05/2025 | B29: 1 - Factura A | C29: 2 | D29: 1260 | F29: 75199376111288 | G29: CUIT | H29: 20272865869 | I29: DI FEO MARTIN EZEQUIEL | J29: 1 | K29: $ | L29: 33000 | M29: 0 | N29: 0 | O29: 0 | P29: 6930 | Q29: 39930
A30: 09/05/2025 | B30: 1 - Factura A | C30: 14 | D30: 77344 | F30: 75190446175800 | G30: CUIT | H30: 30711069360 | I30: BIDCOM SRL | J30: 1 | K30: $ | L30: 123966.12 | M30: 0 | N30: 0 | O30: 0 | P30: 26032.89 | Q30: 149999
A31: 09/05/2025 | B31: 1 - Factura A | C31: 8 | D31: 406 | F31: 75194431209519 | G31: CUIT | H31: 30643518364 | I31: FARMACIA DE MEDRANO 533 SOCIEDAD EN COMANDITA SIMPLE | J31: 1 | K31: $ | L31: 76975 | M31: 0 | N31: 0 | O31: 0 | P31: 16164.75 | Q31: 93139.75
A32: 09/05/2025 | B32: 1 - Factura A | C32: 6 | D32: 57397 | F32: 75198419380202 | G32: CUIT | H32: 30710177658 | I32: TARGET MEDICAL S.A. | J32: 1 | K32: $ | L32: 475130.7 | M32: 0 | N32: 0 | O32: 19005.23 | P32: 99777.45 | Q32: 593913.38
A33: 09/05/2025 | B33: 1 - Factura A | C33: 3101 | D33: 300145 | F33: 75197562217991 | G33: CUIT | H33: 30678814357 | I33: TELEFONICA MOVILES ARGENTINA SOCIEDAD ANONIMA | J33: 1 | K33: $ | L33: 66966.83 | M33: 0 | N33: 0 | O33: 4687.67 | P33: 18081.04 | Q33: 89735.54
A34: 09/05/2025 | B34: 1 - Factura A | C34: 2 | D34: 573 | F34: 75196426881343 | G34: CUIT | H34: 30711610096 | I34: 46 SPEED S.A. | J34: 1 | K34: $ | L34: 591900 | M34: 0 | N34: 0 | O34: 0 | P34: 124299 | Q34: 716199
A35: 09/05/2025 | B35: 11 - Factura C | C35: 3 | D35: 2416 | E35: ARCA | F35: 75191428450203 | G35: CUIT | H35: 20182999661 | I35: KLAINER ABEL JAVIER | J35: 1 | K35: $ | O35: 0 | Q35: 5900
A36: 10/05/2025 | B36: 11 - Factura C | C36: 2 | D36: 325 | F36: 75192564951113 | G36: CUIT | H36: 20326759792 | I36: VILLALTA MARIANO | J36: 1 | K36: $ | O36: 0 | Q36: 114000
A37: 12/05/2025 | B37: 1 - Factura A | C37: 3 | D37: 49512 | F37: 75198779526939 | G37: CUIT | H37: 30711454388 | I37: LIPROT S.R.L. | J37: 1 | K37: $ | L37: 221868 | M37: 0 | N37: 0 | O37: 0 | P37: 46592.28 | Q37: 268460.28
A38: 12/05/2025 | B38: 11 - Factura C | C38: 1 | D38: 172 | F38: 75190660006059 | G38: CUIT | H38: 27338342840 | I38: CANCINO PAMELA RITA | J38: 1 | K38: $ | O38: 0 | Q38: 920000
A39: 12/05/2025 | B39: 11 - Factura C | C39: 2 | D39: 326 | F39: 75192720154834 | G39: CUIT | H39: 20326759792 | I39: VILLALTA MARIANO | J39: 1 | K39: $ | O39: 0 | Q39: 106600
A40: 13/05/2025 | B40: 1 - Factura A | C40: 1001 | D40: 546 | F40: 75192851423822 | G40: CUIT | H40: 30707370552 | I40: RAKE S.A. | J40: 1 | K40: $ | L40: 1198760.3 | M40: 0 | N40: 0 | O40: 0 | P40: 251739.67 | Q40: 1450500
A41: 13/05/2025 | B41: 1 - Factura A | C41: 1 | D41: 7227 | F41: 75191838195535 | G41: CUIT | H41: 30715141201 | I41: REHAB S.R.L. | J41: 1 | K41: $ | L41: 420360 | M41: 0 | N41: 0 | O41: 0 | P41: 88275.6 | Q41: 508635.6
A42: 13/05/2025 | B42: 11 - Factura C | C42: 1 | D42: 26 | F42: 75191855887221 | G42: CUIT | H42: 20311855671 | I42: GUASCH HECTOR RAUL | J42: 1 | K42: $ | O42: 0 | Q42: 290000
A43: 13/05/2025 | B43: 11 - Factura C | C43: 1 | D43: 27 | F43: 75191856398056 | G43: CUIT | H43: 20311855671 | I43: GUASCH HECTOR RAUL | J43: 1 | K43: $ | O43: 0 | Q43: 365000
A44: 13/05/2025 | B44: 11 - Factura C | C44: 2 | D44: 4 | F44: 75191879162589 | G44: CUIT | H44: 27344304551 | I44: BOCCACCI MARIA FLORENCIA | J44: 1 | K44: $ | O44: 0 | Q44: 100000
A45: 13/05/2025 | B45: 11 - Factura C | C45: 1 | D45: 25 | F45: 75191855482139 | G45: CUIT | H45: 20311855671 | I45: GUASCH HECTOR RAUL | J45: 1 | K45: $ | O45: 0 | Q45: 290000
A46: 31/05/2025 | B46: 1 - Factura A | C46: 5015 | D46: 873772 | E46: ARCA | F46: 75224271632180 | G46: CUIT | H46: 30574876474 | I46: AUTOPISTAS URBANAS S. A. | J46: 1 | K46: $ | L46: 76172.23 | M46: 0 | N46: 0 | O46: 9902.37 | P46: 15996.1 | Q46: 102070.7
A47: 31/05/2025 | B47: 1 - Factura A | C47: 113 | D47: 4260847 | E47: ARCA | F47: 75220351343855 | G47: CUIT | H47: 30577207190 | I47: COORDINACION ECOLOGICA AREA METROPOLITANA SOCIEDAD DEL ESTADO | J47: 1 | K47: $ | L47: 2479.34 | M47: 0 | N47: 0 | O47: 74.38 | P47: 520.66 | Q47: 3074.38
A48: 14/05/2025 | B48: 1 - Factura A | C48: 6 | D48: 91586 | F48: 75204053253674 | G48: CUIT | H48: 30711553564 | I48: SALUDTEX SA | J48: 1 | K48: $ | L48: 927887 | M48: 0 | N48: 0 | O48: 0 | P48: 194856.27 | Q48: 1122743.3
A49: 14/05/2025 | B49: 1 - Factura A | C49: 5015 | D49: 849565 | F49: 75204098779142 | G49: CUIT | H49: 30574876474 | I49: AUTOPISTAS URBANAS S A | J49: 1 | K49: $ | L49: 42078.11 | M49: 0 | N49: 0 | O49: 5470.14 | P49: 8836.36 | Q49: 56384.61
A50: 14/05/2025 | B50: 1 - Factura A | C50: 104 | D50: 9230267 | E50: ARCA | F50: 75202986644330 | G50: CUIT | H50: 30715804812 | I50: CORREDORES VIALES SOCIEDAD ANONIMA | J50: 1 | K50: $ | L50: 1804.5 | M50: 0 | N50: 0 | O50: 72.18 | P50: 378.95 | Q50: 2255.63
A51: 14/05/2025 | B51: 1 - Factura A | C51: 2 | D51: 168 | F51: 75206036891667 | G51: CUIT | H51: 30718285026 | I51: BLACKLIST S.R.L. | J51: 1 | K51: $ | L51: 23181.14 | M51: 0 | N51: 0 | O51: 0 | P51: 4868.04 | Q51: 28049.16
A52: 15/05/2025 | B52: 1 - Factura A | C52: 2 | D52: 1285 | F52: 75209199741912 | G52: CUIT | H52: 20272865869 | I52: DI FEO MARTIN EZEQUIEL | J52: 1 | K52: $ | L52: 324600 | M52: 0 | N52: 0 | O52: 0 | P52: 68166 | Q52: 392766
A53: 15/05/2025 | B53: 1 - Factura A | C53: 50 | D53: 4341333 | F53: 75206383969125 | G53: CUIT | H53: 30714112836 | I53: AUTOPISTAS DE BUENOS AIRES (AUBASA) SA S. A. | J53: 1 | K53: $ | L53: 2444.07 | M53: 0 | N53: 0 | O53: 73.32 | P53: 513.25 | Q53: 3030.64
A54: 16/05/2025 | B54: 1 - Factura A | C54: 7 | D54: 1577 | F54: 75206316960001 | G54: CUIT | H54: 30712187316 | I54: ITALOMED PRODUCTOS SRL | J54: 1150 | K54: USD | L54: 509.04 | M54: 0 | N54: 0 | O54: 0 | P54: 106.9 | Q54: 615.94
A55: 16/05/2025 | B55: 1 - Factura A | C55: 4 | D55: 1073 | F55: 75203285420000 | G55: CUIT | H55: 30717874133 | I55: GRUPO ORTOPEDIA MODELO 5028 | J55: 1 | K55: $ | L55: 124133.88 | M55: 0 | N55: 0 | O55: 0 | P55: 26068.12 | Q55: 150202
A56: 16/05/2025 | B56: 1 - Factura A | C56: 1 | D56: 7301 | F56: 75201305582767 | G56: CUIT | H56: 30715141201 | I56: REHAB S.R.L. | J56: 1 | K56: $ | L56: 158700 | M56: 0 | N56: 0 | O56: 0 | P56: 33327 | Q56: 192027
A57: 16/05/2025 | B57: 1 - Factura A | C57: 5 | D57: 2421 | F57: 75206316726496 | G57: CUIT | H57: 30712187316 | I57: ITALOMED PRODUCTOS SRL | J57: 1150 | K57: USD | L57: 779.25 | M57: 0 | N57: 0 | O57: 0 | P57: 163.64 | Q57: 942.89
A58: 16/05/2025 | B58: 1 - Factura A | C58: 629 | D58: 6111053 | F58: 35193120201379 | G58: CUIT | H58: 30663498513 | I58: GRUPO CONCESIONARIO DEL OESTE SA | J58: 1 | K58: $ | L58: 2542.18 | M58: 0 | N58: 0 | O58: 101.69 | P58: 533.86 | Q58: 3177.73
A59: 16/05/2025 | B59: 1 - Factura A | C59: 711 | D59: 7116239 | F59: 35199666575201 | G59: CUIT | H59: 30677237119 | I59: AUTOPISTAS DEL SOL S A | J59: 1 | K59: $ | L59: 10053.15 | M59: 0 | N59: 301.59 | O59: 402.13 | P59: 2111.17 | Q59: 12868.04
A60: 19/05/2025 | B60: 1 - Factura A | C60: 44 | D60: 19653 | E60: ARCA | F60: 75207593896654 | G60: CUIT | H60: 30708847247 | I60: EXPRESO LANCIONI S.A. | J60: 1 | K60: $ | L60: 43853.86 | M60: 0 | N60: 0 | O60: 1754.15 | P60: 9209.31 | Q60: 54817.32 | R60: =+L60*0.04 -> 1754.1544
A61: 19/05/2025 | B61: 1 - Factura A | C61: 6 | D61: 57 | F61: 75201584443143 | G61: CUIT | H61: 30716401541 | I61: HIGH MOBILITY S.A.S. | J61: 1 | K61: $ | L61: 1015000 | M61: 0 | N61: 0 | O61: 0 | P61: 213150 | Q61: 1228150
A62: 19/05/2025 | B62: 1 - Factura A | C62: 5 | D62: 48 | F62: 75203668853596 | G62: CUIT | H62: 20929183143 | I62: MA JUN | J62: 1 | K62: $ | L62: 85000 | M62: 0 | N62: 0 | O62: 0 | P62: 17850 | Q62: 102850
A63: 20/05/2025 | B63: 1 - Factura A | C63: 5 | D63: 166975 | F63: 75203702773962 | G63: CUIT | H63: 30598960093 | I63: SILVESTRIN FABRIS SOC RESP LTDA | J63: 1 | K63: $ | L63: 760465.65 | M63: 0 | N63: 0 | O63: 30418.63 | P63: 131577.34 | Q63: 922461.62
A64: 20/05/2025 | B64: 1 - Factura A | C64: 12 | D64: 42634 | F64: 75204734833632 | G64: CUIT | H64: 30526582884 | I64: EXPRESO MAR DEL PLATA SOCIEDAD ANONIMA | J64: 1 | K64: $ | L64: 155355.37 | M64: 0 | N64: 0 | O64: 0 | P64: 32624.63 | Q64: 187980
A65: 20/05/2025 | B65: 11 - Factura C | C65: 1 | D65: 9 | F65: 75201732106411 | G65: CUIT | H65: 27122903201 | I65: ARCE RAQUEL INES | J65: 1 | K65: $ | O65: 0 | Q65: 2000000
A66: 21/05/2025 | B66: 1 - Factura A | C66: 5 | D66: 3300761 | F66: 75215872264683 | G66: CUIT | H66: 30702652975 | I66: NSS SA | J66: 1 | K66: $ | L66: 35660.75 | M66: 0 | N66: 0 | O66: 1426.43 | P66: 7488.76 | Q66: 44575.94
A67: 21/05/2025 | B67: 1 - Factura A | C67: 4264 | D67: 5471712 | F67: 75218986009028 | G67: CUIT | H67: 30639453738 | I67: TELECOM ARGENTINA SOCIEDAD ANONIMA | J67: 1 | K67: $ | L67: 46199.59 | M67: 0 | N67: 0 | O67: 3233.97 | P67: 9701.91 | Q67: 59135.47
A68: 21/05/2025 | B68: 1 - Factura A | C68: 6 | D68: 59 | F68: 75211862068571 | G68: CUIT | H68: 30716401541 | I68: HIGH MOBILITY S.A.S. | J68: 1 | K68: $ | L68: 386280 | M68: 0 | N68: 0 | O68: 0 | P68: 81118.8 | Q68: 467398.8
A69: 21/05/2025 | B69: 11 - Factura C | C69: 1 | D69: 80 | F69: 75214862192180 | G69: CUIT | H69: 23281233084 | I69: DRUETTA ANDREA MARIEL | J69: 1 | K69: $ | O69: 0 | Q69: 300000
A70: 22/05/2025 | B70: 1 - Factura A | C70: 15 | D70: 4537 | F70: 75213952936400 | G70: CUIT | H70: 30688140923 | I70: COLTEX S R L | J70: 1 | K70: $ | L70: 382425.6 | M70: 0 | N70: 0 | O70: 0 | P70: 80309.38 | Q70: 462734.98
A71: 22/05/2025 | B71: 1 - Factura A | C71: 7 | D71: 7572 | E71: ARCA | F71: 75218979071367 | G71: CUIT | H71: 20312058368 | I71: GOTTIG DIEGO GASTON LUJAN | J71: 1 | K71: $ | L71: 49421.49 | M71: 0 | N71: 0 | O71: 0 | P71: 10378.51 | Q71: 59800
A72: 22/05/2025 | B72: 1 - Factura A | C72: 2 | D72: 1304 | F72: 75219997093395 | G72: CUIT | H72: 20272865869 | I72: DI FEO MARTIN EZEQUIEL | J72: 1 | K72: $ | L72: 207100 | M72: 0 | N72: 0 | O72: 0 | P72: 43491 | Q72: 250591
A73: 22/05/2025 | B73: 1 - Factura A | C73: 700 | D73: 2467338 | F73: 75212040906337 | G73: CUIT | H73: 30715804812 | I73: CORREDORES VIALES SOCIEDAD ANONIMA | J73: 1 | K73: $ | L73: 20175.65 | M73: 0 | N73: 0 | O73: 807.02 | P73: 4236.89 | Q73: 25219.56
A74: 14/05/2025 | B74: 1 - Factura A | C74: 104 | D74: 9128311 | E74: ARCA | F74: 75202967142711 | G74: CUIT | H74: 30715804812 | I74: CORREDORES VIALES SOCIEDAD ANONIMA | J74: 1 | K74: $ | L74: 2079.97 | M74: 0 | N74: 0 | O74: 83.2 | P74: 436.79 | Q74: 2599.96
A75: 23/05/2025 | B75: 1 - Factura A | C75: 2 | D75: 12089 | F75: 75212050971859 | G75: CUIT | H75: 30714331082 | I75: ORTOPEDIA CASA ESCALADA S.R.L. | J75: 1 | K75: $ | L75: 1325320.6 | M75: 0 | N75: 0 | O75: 0 | P75: 278317.33 | Q75: 1603638
A76: 23/05/2025 | B76: 1 - Factura A | C76: 2 | D76: 1305 | F76: 75219048529515 | G76: CUIT | H76: 20272865869 | I76: DI FEO MARTIN EZEQUIEL | J76: 1 | K76: $ | L76: 45000 | M76: 0 | N76: 0 | O76: 0 | P76: 9450 | Q76: 54450
A77: 23/05/2025 | B77: 1 - Factura A | C77: 2 | D77: 12090 | F77: 75212051388934 | G77: CUIT | H77: 30714331082 | I77: ORTOPEDIA CASA ESCALADA S.R.L. | J77: 1 | K77: $ | L77: 472360.62 | M77: 0 | N77: 0 | O77: 0 | P77: 99195.73 | Q77: 571556.35
A78: 23/05/2025 | B78: 1 - Factura A | C78: 2 | D78: 12091 | F78: 75212051805898 | G78: CUIT | H78: 30714331082 | I78: ORTOPEDIA CASA ESCALADA S.R.L. | J78: 1 | K78: $ | L78: 579315.54 | M78: 0 | N78: 0 | O78: 0 | P78: 121656.26 | Q78: 700971.8
A79: 23/05/2025 | B79: 1 - Factura A | C79: 210 | D79: 548 | F79: 75212110337517 | G79: CUIT | H79: 30592097482 | I79: ED GAR SOCIEDAD ANONIMA | J79: 1 | K79: $ | L79: 54418.18 | M79: 0 | N79: 0 | O79: 2176.73 | P79: 11427.82 | Q79: 68022.73
A80: 23/05/2025 | B80: 1 - Factura A | C80: 2 | D80: 38 | F80: 75215512508104 | G80: CUIT | H80: 27243660535 | I80: BARD MARISA SILVIA | J80: 1 | K80: $ | L80: 414537 | M80: 0 | N80: 0 | O80: 0 | P80: 87052.77 | Q80: 501589.77
A81: 26/05/2025 | B81: 1 - Factura A | C81: 5 | D81: 3349 | E81: ARCA | F81: 75219386499174 | G81: CUIT | H81: 30518532959 | I81: EGIDIO P HEYD Y CIA SRL | J81: 1 | K81: $ | L81: 33637.02 | M81: 0 | N81: 0 | O81: 0 | P81: 7063.77 | Q81: 40700.79
A82: 26/05/2025 | B82: 3 - Nota de Crédito A | C82: 2 | D82: 496 | F82: 75212349207233 | G82: CUIT | H82: 30714331082 | I82: ORTOPEDIA CASA ESCALADA S.R.L. | J82: 1 | K82: $ | L82: 579315.54 | M82: 0 | N82: 0 | O82: 0 | P82: 121656.26 | Q82: 700971.8
A83: 22/05/2025 | B83: 1 - Factura A | C83: 700 | D83: 2467339 | E83: ARCA | F83: 75212040906340 | G83: CUIT | H83: 30715804812 | I83: CORREDORES VIALES SOCIEDAD ANONIMA | J83: 1 | K83: $ | L83: 1871.97 | M83: 0 | N83: 0 | O83: 0 | P83: 393.11 | Q83: 2265.08
A84: 27/05/2025 | B84: 11 - Factura C | C84: 1 | D84: 28 | F84: 75211527497423 | G84: CUIT | H84: 20311855671 | I84: GUASCH HECTOR RAUL | J84: 1 | K84: $ | O84: 0 | Q84: 145000
A85: 01/05/2025 | B85: 1 - Factura A | C85: 629 | D85: 6069001 | E85: ARCA | F85: 35173338641243 | G85: CUIT | H85: 30663498513 | I85: GRUPO CONCESIONARIO DEL OESTE SA | J85: 1 | K85: $ | L85: 4391.03 | M85: 0 | N85: 0 | O85: 175.64 | P85: 922.12 | Q85: 5488.79
A86: 27/05/2025 | B86: 1 - Factura A | C86: 16 | D86: 386 | E86: ARCA | F86: 75215527916158 | G86: CUIT | H86: 30715626515 | I86: HERRAMIENTAS E INSUMOS S.A. | J86: 1 | K86: $ | L86: 27026.44 | M86: 0 | N86: 0 | O86: 0 | P86: 5675.55 | Q86: 32701.99
A87: 28/05/2025 | B87: 11 - Factura C | C87: 1 | D87: 29 | F87: 75221662372707 | G87: CUIT | H87: 20311855671 | I87: GUASCH HECTOR RAUL | J87: 1 | K87: $ | O87: 0 | Q87: 355000
A88: 08/05/2025 | B88: 11 - Factura C | C88: 1 | D88: 14 | E88: ARCA | F88: 75193233202026 | G88: CUIT | H88: 27443612713 | I88: MIGOYA MORIONDO SOFIA | J88: 1 | K88: $ | O88: 0 | Q88: 850000
A89: 29/05/2025 | B89: 1 - Factura A | C89: 2 | D89: 1315 | F89: 75229781588794 | G89: CUIT | H89: 20272865869 | I89: DI FEO MARTIN EZEQUIEL | J89: 1 | K89: $ | L89: 64550 | M89: 0 | N89: 0 | O89: 0 | P89: 13555.5 | Q89: 78105.5
A90: 29/05/2025 | B90: 1 - Factura A | C90: 73 | D90: 274433 | F90: 75224912928612 | G90: CUIT | H90: 30703088534 | I90: MERCADOLIBRE S.R.L. | J90: 1 | K90: $ | L90: 89907.19 | M90: 0 | N90: 0 | O90: 6293.51 | P90: 18880.51 | Q90: 115081.21
A91: 29/05/2025 | B91: 3 - Nota de Crédito A | C91: 65 | D91: 4961 | F91: 75224925902773 | G91: CUIT | H91: 30703088534 | I91: MERCADOLIBRE S.R.L. | J91: 1 | K91: $ | L91: 1016.53 | M91: 0 | N91: 0 | O91: 30.5 | P91: 213.47 | Q91: 1260.5
A92: 30/05/2025 | B92: 1 - Factura A | C92: 1 | D92: 7503 | F92: 75221887125791 | G92: CUIT | H92: 30715141201 | I92: REHAB S.R.L. | J92: 1 | K92: $ | L92: 61770 | M92: 0 | N92: 0 | O92: 0 | P92: 12971.7 | Q92: 74741.7
A93: 30/05/2025 | B93: 1 - Factura A | C93: 7 | D93: 37 | F93: 75223908075229 | G93: CUIT | H93: 27325223273 | I93: SOUSA ALDERETE ALEJANDRA MABEL | J93: 1 | K93: $ | L93: 1950000 | M93: 0 | N93: 0 | O93: 0 | P93: 409500 | Q93: 2359500
A94: 28/05/2025 | B94: 1 - Factura A | C94: 7 | D94: 1359 | E94: ARCA | F94: 75222633147779 | G94: CUIT | H94: 30677420622 | I94: PAÑALERA NORTE S R L | J94: 1 | K94: $ | L94: 29834.71 | M94: 0 | N94: 0 | O94: 0 | P94: 6265.29 | Q94: 36100
A95: 28/05/2025 | B95: 1 - Factura A | C95: 7 | D95: 1357 | E95: ARCA | F95: 75222621409493 | G95: CUIT | H95: 30677420622 | I95: PAÑALERA NORTE S R L | J95: 1 | K95: $ | L95: 90727.27 | M95: 0 | N95: 0 | O95: 0 | P95: 19052.73 | Q95: 109780
A96: 31/05/2025 | B96: 1 - Factura A | C96: 6 | D96: 19671130 | E96: ARCA | F96: 75227848831450 | G96: CUIT | H96: 30620177497 | I96: POSNET SOCIEDAD DE RESPONSABILIDAD LIMITADA | J96: 1 | K96: $ | L96: 33073.86 | M96: 0 | N96: 0 | O96: 2315.17 | P96: 6945.51 | Q96: 42334.54
A97: 29/05/2025 | B97: 1 - Factura A | C97: 9 | D97: 10088 | E97: ARCA | F97: 75225741025209 | G97: CUIT | H97: 27185947675 | I97: SCHMUKLER SARA ELENA | J97: 1 | K97: $ | L97: 10000.4 | M97: 0 | N97: 0 | O97: 0 | P97: 2100.09 | Q97: 12100.49
H99: ticket | I99: 7
H100: ARCA | I100: 95
H101: CONTABILIUM | I101: =80-7 -> 73
...

Sheet arca
A1: Mis Comprobantes Recibidos - CUIT 30710473168
A2: Fecha | B2: Tipo | C2: Punto de Venta | D2: Número Desde | E2: Número Hasta | F2: Cód. Autorización | G2: Tipo Doc. Emisor | H2: Nro. Doc. Emisor | I2: Denominación Emisor | J2: Tipo Cambio | K2: Moneda | L2: Imp. Neto Gravado | M2: Imp. Neto No Gravado | N2: Imp. Op. Exentas | O2: Otros Tributos | P2: IVA | Q2: Imp. Total | R2: Imp. Total | S2: Imp. Total | T2: Imp. Total | U2: Imp. Total
A3: 13/06/2025 | B3: 1 - Factura A | C3: 3 | D3: 5908 | F3: 75240681441573 | G3: CUIT | H3: 20045368670 | I3: NIEMAND SIMON ALEJANDRO | J3: 1 | K3: $ | L3: 24284.29 | M3: 0 | N3: 0 | O3: 0 | P3: 5099.7 | Q3: 29384
A4: 13/06/2025 | B4: 13/06/2025 | C4: FCA 00003-00005908 | D4: SIMON ALEJANDRO NIEMAND | E4: 20045368670 | F4: RI | G4: 0 | H4: 20045368670 | I4: SIMON ALEJANDRO NIEMAND | J4: 24284.3 | K4: 0 | L4: 0 | M4: 0 | N4: 5099.7 | O4: 0 | P4: 0 | Q4: 0 | R4: 0 | S4: 0 | T4: 0 | U4: 29384
A5: 02/06/2025 | B5: 11 - Factura C | C5: 4 | D5: 21 | F5: 75223226799702 | G5: CUIT | H5: 20086277523 | I5: BOTINDARI JUAN CARLOS | J5: 1 | K5: $ | O5: 0 | Q5: 290000
A6: 02/06/2025 | B6: 02/06/2025 | C6: FCC 00004-00000021 | D6: JUAN CARLOS BOTINDARI | E6: 20086277523 | F6: MO | G6: 0 | H6: 20086277523 | I6: JUAN CARLOS BOTINDARI | J6: 0 | K6: 0 | L6: 0 | M6: 290000 | N6: 0 | O6: 0 | P6: 0 | Q6: 0 | R6: 0 | S6: 0 | T6: 0 | U6: 290000
A7: 23/06/2025 | B7: 1 - Factura A | C7: 4 | D7: 4840 | F7: 75257740618200 | G7: CUIT | H7: 20129871947 | I7: FERNANDEZ CARLOS RODOLFO | J7: 1 | K7: $ | L7: 114724.45 | M7: 0 | N7: 0 | O7: 0 | P7: 24092.13 | Q7: 138816.58
A8: 23/06/2025 | B8: 23/06/2025 | C8: FCA 00004-00004840 | D8: CARLOS RODOLFO FERNANDEZ | E8: 20129871947 | F8: RI | G8: 0 | H8: 20129871947 | I8: CARLOS RODOLFO FERNANDEZ | J8: 114724.45 | K8: 0 | L8: 0 | M8: 0 | N8: 24092.13 | O8: 0 | P8: 0 | Q8: 0 | R8: 0 | S8: 0 | T8: 0 | U8: 138816.58
A9: 09/06/2025 | B9: 1 - Factura A | C9: 4 | D9: 49 | F9: 75246088491040 | G9: CUIT | H9: 20174004146 | I9: NARDOMARINO EDUARDO FRANCISCO | J9: 1 | K9: $ | L9: 210000 | M9: 0 | N9: 0 | O9: 0 | P9: 44100 | Q9: 254100
A10: 19/06/2025 | B10: 1 - Factura A | C10: 3 | D10: 4173 | F10: 75257348383820 | G10: CUIT | H10: 20182721787 | I10: QUIROZ CARLOS DANIEL | J10: 1 | K10: $ | L10: 33057.86 | M10: 0 | N10: 0 | O10: 0 | P10: 6942.15 | Q10: 40000.01
A11: 19/06/2025 | B11: 19/06/2025 | C11: FCA 00003-00004173 | D11: CARLOS DANIEL QUIROZ | E11: 20182721787 | F11: RI | G11: 0 | H11: 20182721787 | I11: CARLOS DANIEL QUIROZ | J11: 33057.86 | K11: 0 | L11: 0 | M11: 0 | N11: 6942.15 | O11: 0 | P11: 0 | Q11: 0 | R11: 0 | S11: 0 | T11: 0 | U11: 40000.01
A12: 02/06/2025 | B12: 1 - Factura A | C12: 6 | D12: 1449 | F12: 75223281664206 | G12: CUIT | H12: 20247225243 | I12: VENTO HUGO GABRIEL | J12: 1 | K12: $ | L12: 140244 | M12: 0 | N12: 0 | O12: 0 | P12: 29451.24 | Q12: 169695.24
A13: 02/06/2025 | B13: 02/06/2025 | C13: FCA 00006-00001449 | D13: HUGO GABRIEL VENTO | E13: 20247225243 | F13: RI | G13: 0 | H13: 20247225243 | I13: HUGO GABRIEL VENTO | J13: 140244 | K13: 0 | L13: 0 | M13: 0 | N13: 29451.24 | O13: 0 | P13: 0 | Q13: 0 | R13: 0 | S13: 0 | T13: 0 | U13: 169695.24
A14: 27/06/2025 | B14: 1 - Factura A | C14: 4 | D14: 473 | F14: 75262216658353 | G14: CUIT | H14: 20253515512 | I14: DELGADO GUSTAVO ADOLFO | J14: 1 | K14: $ | L14: 1487603.3 | M14: 0 | N14: 0 | O14: 0 | P14: 312396.7 | Q14: 1800000
A15: 27/06/2025 | B15: 3 - Nota de Crédito A | C15: 4 | D15: 31 | F15: 75262216836197 | G15: CUIT | H15: 20253515512 | I15: DELGADO GUSTAVO ADOLFO | J15: 1 | K15: $ | L15: 1487603.3 | M15: 0 | N15: 0 | O15: 0 | P15: 312396.7 | Q15: 1800000
A16: 30/06/2025 | B16: 1 - Factura A | C16: 4 | D16: 475 | F16: 75262533948216 | G16: CUIT | H16: 20253515512 | I16: DELGADO GUSTAVO ADOLFO | J16: 1 | K16: $ | L16: 1487603.3 | M16: 0 | N16: 0 | O16: 0 | P16: 312396.7 | Q16: 1800000
A17: 30/06/2025 | B17: 30/06/2025 | C17: FCA 00004-00000475 | D17: GUSTAVO ADOLFO DELGADO | E17: 20253515512 | F17: RI | G17: 0 | H17: 20253515512 | I17: GUSTAVO ADOLFO DELGADO | J17: 1487603.3 | K17: 0 | L17: 0 | M17: 0 | N17: 312396.7 | O17: 0 | P17: 0 | Q17: 0 | R17: 0 | S17: 0 | T17: 0 | U17: 1800000
A18: 27/06/2025 | B18: 3 - Nota de Crédito A | C18: 7 | D18: 1002 | F18: 75263220838146 | G18: CUIT | H18: 20271532483 | I18: RIOS DIEGO MARTIN | J18: 1 | K18: $ | L18: 23299.61 | M18: 0 | N18: 0 | O18: 0 | P18: 4892.92 | Q18: 28192.53
A19: 26/06/2025 | B19: 1 - Factura A | C19: 2 | D19: 1374 | F19: 75269153968000 | G19: CUIT | H19: 20272865869 | I19: DI FEO MARTIN EZEQUIEL | J19: 1 | K19: $ | L19: 40300 | M19: 0 | N19: 0 | O19: 0 | P19: 8463 | Q19: 48763
A20: 18/06/2025 | B20: 1 - Factura A | C20: 2 | D20: 1360 | F20: 75259262153593 | G20: CUIT | H20: 20272865869 | I20: DI FEO MARTIN EZEQUIEL | J20: 1 | K20: $ | L20: 125521.49 | M20: 0 | N20: 0 | O20: 0 | P20: 26359.51 | Q20: 151881
A21: 05/06/2025 | B21: 1 - Factura A | C21: 2 | D21: 1336 | F21: 75239699473466 | G21: CUIT | H21: 20272865869 | I21: DI FEO MARTIN EZEQUIEL | J21: 1 | K21: $ | L21: 209700 | M21: 0 | N21: 0 | O21: 0 | P21: 44037 | Q21: 253737
A22: 12/06/2025 | B22: 1 - Factura A | C22: 2 | D22: 1350 | F22: 75249603550416 | G22: CUIT | H22: 20272865869 | I22: DI FEO MARTIN EZEQUIEL | J22: 1 | K22: $ | L22: 212300 | M22: 0 | N22: 0 | O22: 0 | P22: 44583 | Q22: 256883
A23: 05/06/2025 | B23: 05/06/2025 | C23: FCA 00002-00001336 | D23: MARTIN EZEQUIEL DI FEO | E23: 20272865869 | F23: RI | G23: 0 | H23: 20272865869 | I23: MARTIN EZEQUIEL DI FEO | J23: 209700 | K23: 0 | L23: 0 | M23: 0 | N23: 44037 | O23: 0 | P23: 0 | Q23: 0 | R23: 0 | S23: 0 | T23: 0 | U23: 253737
A24: 12/06/2025 | B24: 12/06/2025 | C24: FCA 00002-00001350 | D24: MARTIN EZEQUIEL DI FEO | E24: 20272865869 | F24: RI | G24: 0 | H24: 20272865869 | I24: MARTIN EZEQUIEL DI FEO | J24: 212300 | K24: 0 | L24: 0 | M24: 0 | N24: 44583 | O24: 0 | P24: 0 | Q24: 0 | R24: 0 | S24: 0 | T24: 0 | U24: 256883
A25: 18/06/2025 | B25: 18/06/2025 | C25: FCA 00002-00001360 | D25: MARTIN EZEQUIEL DI FEO | E25: 20272865869 | F25: RI | G25: 0 | H25: 20272865869 | I25: MARTIN EZEQUIEL DI FEO | J25: 125521 | K25: 0 | L25: 0 | M25: 0 | N25: 26359.41 | O25: 0 | P25: 0 | Q25: 0 | R25: 0 | S25: 0 | T25: 0 | U25: 151880.41
A26: 26/06/2025 | B26: 26/06/2025 | C26: FCA 00002-00001374 | D26: MARTIN EZEQUIEL DI FEO | E26: 20272865869 | F26: RI | G26: 0 | H26: 20272865869 | I26: MARTIN EZEQUIEL DI FEO | J26: 40300 | K26: 0 | L26: 0 | M26: 0 | N26: 8463 | O26: 0 | P26: 0 | Q26: 0 | R26: 0 | S26: 0 | T26: 0 | U26: 48763
A27: 26/06/2025 | B27: 1 - Factura A | C27: 7 | D27: 3973 | F27: 75264115965680 | G27: CUIT | H27: 20284183534 | I27: FURLANETTO MARTIN | J27: 1 | K27: $ | L27: 1900.83 | M27: 0 | N27: 0 | O27: 0 | P27: 399.17 | Q27: 2300
A28: 26/06/2025 | B28: 1 - Factura A | C28: 7 | D28: 3974 | F28: 75264116187002 | G28: CUIT | H28: 20284183534 | I28: FURLANETTO MARTIN | J28: 1 | K28: $ | L28: 2644.63 | M28: 0 | N28: 0 | O28: 0 | P28: 555.37 | Q28: 3200
A29: 27/06/2025 | B29: 1 - Factura A | C29: 5 | D29: 239 | F29: 75262223380402 | G29: CUIT | H29: 20291406212 | I29: BRACHETTA SEBASTIAN NICOLAS | J29: 1 | K29: $ | L29: 1972033.1 | M29: 0 | N29: 0 | O29: 0 | P29: 414126.95 | Q29: 2386160
A30: 27/06/2025 | B30: 27/06/2025 | C30: FCA 00005-00000239 | D30: SEBASTIAN NICOLAS BRACHETTA | E30: 20291406212 | F30: RI | G30: 0 | H30: 20291406212 | I30: SEBASTIAN NICOLAS BRACHETTA | J30: 1972033.1 | K30: 0 | L30: 0 | M30: 0 | N30: 414126.95 | O30: 0 | P30: 0 | Q30: 0 | R30: 0 | S30: 0 | T30: 0 | U30: 2386160
A31: 09/06/2025 | B31: 1 - Factura A | C31: 6 | D31: 1048 | F31: 75239175665017 | G31: CUIT | H31: 20295929309 | I31: ROJAS GULLERMO | J31: 1 | K31: $ | L31: 9979.34 | M31: 0 | N31: 0 | O31: 0 | P31: 2095.66 | Q31: 12075
A32: 09/06/2025 | B32: 09/06/2025 | C32: FCA 00006-00001048 | D32: GULLERMO ROJAS | E32: 20295929309 | F32: RI | G32: 0 | H32: 20295929309 | I32: GULLERMO ROJAS | J32: 9979.34 | K32: 0 | L32: 0 | M32: 0 | N32: 2095.66 | O32: 0 | P32: 0 | Q32: 0 | R32: 0 | S32: 0 | T32: 0 | U32: 12075
A33: 12/06/2025 | B33: 11 - Factura C | C33: 3 | D33: 5 | F33: 75240571600680 | G33: CUIT | H33: 20310489930 | I33: OVIEDO LUIS ALBERTO | J33: 1 | K33: $ | O33: 0 | Q33: 523331
A34: 30/06/2025 | B34: 11 - Factura C | C34: 3 | D34: 6 | F34: 75260584209902 | G34: CUIT | H34: 20310489930 | I34: OVIEDO LUIS ALBERTO | J34: 1 | K34: $ | O34: 0 | Q34: 678731
A35: 12/06/2025 | B35: 12/06/2025 | C35: FCC 00003-00000005 | D35: LUIS ALBERTO OVIEDO | E35: 20310489930 | F35: MO | G35: 0 | H35: 20310489930 | I35: LUIS ALBERTO OVIEDO | J35: 0 | K35: 0 | L35: 0 | M35: 523331 | N35: 0 | O35: 0 | P35: 0 | Q35: 0 | R35: 0 | S35: 0 | T35: 0 | U35: 523331
A36: 30/06/2025 | B36: 30/06/2025 | C36: FCC 00003-00000006 | D36: LUIS ALBERTO OVIEDO | E36: 20310489930 | F36: MO | G36: 0 | H36: 20310489930 | I36: LUIS ALBERTO OVIEDO | J36: 0 | K36: 0 | L36: 0 | M36: 678731 | N36: 0 | O36: 0 | P36: 0 | Q36: 0 | R36: 0 | S36: 0 | T36: 0 | U36: 678731
A37: 11/06/2025 | B37: 11 - Factura C | C37: 1 | D37: 30 | F37: 75241481687452 | G37: CUIT | H37: 20311855671 | I37: GUASCH HECTOR RAUL | J37: 1 | K37: $ | O37: 0 | Q37: 630000
A38: 23/06/2025 | B38: 11 - Factura C | C38: 1 | D38: 31 | F38: 75251746765231 | G38: CUIT | H38: 20311855671 | I38: GUASCH HECTOR RAUL | J38: 1 | K38: $ | O38: 0 | Q38: 350000
A39: 11/06/2025 | B39: 11/06/2025 | C39: FCC 00001-00000030 | D39: HECTOR RAUL GUASCH | E39: 20311855671 | F39: MO | G39: 0 | H39: 20311855671 | I39: HECTOR RAUL GUASCH | J39: 0 | K39: 0 | L39: 0 | M39: 630000 | N39: 0 | O39: 0 | P39: 0 | Q39: 0 | R39: 0 | S39: 0 | T39: 0 | U39: 630000
A40: 23/06/2025 | B40: 24/06/2025 | C40: FCC 00001-00000031 | D40: HECTOR RAUL GUASCH | E40: 20311855671 | F40: MO | G40: 0 | H40: 20311855671 | I40: HECTOR RAUL GUASCH | J40: 0 | K40: 0 | L40: 0 | M40: 350000 | N40: 0 | O40: 0 | P40: 0 | Q40: 0 | R40: 0 | S40: 0 | T40: 0 | U40: 350000
A41: 09/06/2025 | B41: 09/06/2025 | C41: FCA 00004-00000049 | D41: EZEQUIEL EDUARDO NARDOMARINO | E41: 20334976433 | F41: RI | G41: 0 | H41: 20174004146 | I41: NARDOMARINO EDUARDO FRANCISCO | J41: 210000 | K41: 0 | L41: 0 | M41: 0 | N41: 44100 | O41: 0 | P41: 0 | Q41: 0 | R41: 0 | S41: 0 | T41: 0 | U41: 254100
A42: 25/06/2025 | B42: 1 - Factura A | C42: 5 | D42: 55 | F42: 75263064964225 | G42: CUIT | H42: 20929183143 | I42: MA JUN | J42: 1 | K42: $ | L42: 85000 | M42: 0 | N42: 0 | O42: 0 | P42: 17850 | Q42: 102850
A43: 25/06/2025 | B43: 25/06/2025 | C43: FCA 00005-00000055 | D43: JUN MA | E43: 20929183143 | F43: RI | G43: 0 | H43: 20929183143 | I43: JUN MA | J43: 85000 | K43: 0 | L43: 0 | M43: 0 | N43: 17850 | O43: 0 | P43: 0 | Q43: 0 | R43: 0 | S43: 0 | T43: 0 | U43: 102850
A44: 18/06/2025 | B44: 1 - Factura A | C44: 3 | D44: 913 | F44: 75259218311081 | G44: CUIT | H44: 23076996989 | I44: GIULIETTI LUIS ALBERTO | J44: 1 | K44: $ | L44: 10413.24 | M44: 0 | N44: 0 | O44: 0 | P44: 2186.78 | Q44: 12600
A45: 18/06/2025 | B45: 18/06/2025 | C45: FCA 00003-00000913 | D45: LUIS ALBERTO GIULIETTI | E45: 23076996989 | F45: RI | G45: 0 | H45: 23076996989 | I45: LUIS ALBERTO GIULIETTI | J45: 10413.22 | K45: 0 | L45: 0 | M45: 0 | N45: 2186.78 | O45: 0 | P45: 0 | Q45: 0 | R45: 0 | S45: 0 | T45: 0 | U45: 12600
A46: 10/06/2025 | B46: 1 - Factura A | C46: 2 | D46: 26504 | F46: 75239332605962 | G46: CUIT | H46: 23233422029 | I46: SCHULZE RODOLFO ESTEBAN | J46: 1 | K46: $ | L46: 205205.72 | M46: 0 | N46: 0 | O46: 0 | P46: 43093.2 | Q46: 248298.92
A47: 10/06/2025 | B47: 10/06/2025 | C47: FCA 00002-00026504 | D47: RODOLFO ESTEBAN SCHULZE | E47: 23233422029 | F47: RI | G47: 0 | H47: 23233422029 | I47: RODOLFO ESTEBAN SCHULZE | J47: 205205.72 | K47: 0 | L47: 0 | M47: 0 | N47: 43093.2 | O47: 0 | P47: 0 | Q47: 0 | R47: 0 | S47: 0 | T47: 0 | U47: 248298.92
A48: 17/06/2025 | B48: 11 - Factura C | C48: 1 | D48: 81 | F48: 75244165079293 | G48: CUIT | H48: 23281233084 | I48: DRUETTA ANDREA MARIEL | J48: 1 | K48: $ | O48: 0 | Q48: 300000
A49: 17/06/2025 | B49: 17/06/2025 | C49: FCC 00001-00000081 | D49: ANDREA MARIEL DRUETTA | E49: 23281233084 | F49: MO | G49: 0 | H49: 23281233084 | I49: ANDREA MARIEL DRUETTA | J49: 0 | K49: 0 | L49: 0 | M49: 300000 | N49: 0 | O49: 0 | P49: 0 | Q49: 0 | R49: 0 | S49: 0 | T49: 0 | U49: 300000
A50: 04/06/2025 | B50: 1 - Factura A | C50: 2 | D50: 273 | F50: 75233505922163 | G50: CUIT | H50: 27144282383 | I50: SCHEJTER LILA ELISA | J50: 1 | K50: $ | L50: 1020000 | M50: 0 | N50: 0 | O50: 0 | P50: 214200 | Q50: 1234200
A51: 04/06/2025 | B51: 04/06/2025 | C51: FCA 00002-00000273 | D51: SCHEJTER LILA ELISA | E51: 27144282383 | F51: RI | G51: 0 | H51: 27144282383 | I51: SCHEJTER LILA ELISA | J51: 1020000 | K51: 0 | L51: 0 | M51: 0 | N51: 214200 | O51: 0 | P51: 0 | Q51: 0 | R51: 0 | S51: 0 | T51: 0 | U51: 1234200
A52: 25/06/2025 | B52: 1 - Factura A | C52: 2 | D52: 40 | F52: 75265280996941 | G52: CUIT | H52: 27243660535 | I52: BARD MARISA SILVIA | J52: 1 | K52: $ | L52: 414537 | M52: 0 | N52: 0 | O52: 0 | P52: 87052.77 | Q52: 501589.77
A53: 03/06/2025 | B53: 1 - Factura A | C53: 5 | D53: 1555 | F53: 75225445831549 | G53: CUIT | H53: 27265302225 | I53: PRADO MARISOL | J53: 1 | K53: $ | L53: 1200000 | M53: 0 | N53: 0 | O53: 0 | P53: 252000 | Q53: 1452000
A54: 04/06/2025 | B54: 1 - Factura A | C54: 5 | D54: 1557 | F54: 75235533191292 | G54: CUIT | H54: 27265302225 | I54: PRADO MARISOL | J54: 1 | K54: $ | L54: 1500000 | M54: 0 | N54: 0 | O54: 0 | P54: 315000 | Q54: 1815000
A55: 18/06/2025 | B55: 1 - Factura A | C55: 5 | D55: 1569 | F55: 75255228267096 | G55: CUIT | H55: 27265302225 | I55: PRADO MARISOL | J55: 1 | K55: $ | L55: 2500000 | M55: 0 | N55: 0 | O55: 0 | P55: 525000 | Q55: 3025000
A56: 23/06/2025 | B56: 1 - Factura A | C56: 5 | D56: 1572 | F56: 75255731247213 | G56: CUIT | H56: 27265302225 | I56: PRADO MARISOL | J56: 1 | K56: $ | L56: 2500000 | M56: 0 | N56: 0 | O56: 0 | P56: 525000 | Q56: 3025000
A57: 03/06/2025 | B57: 03/06/2025 | C57: FCA 00005-00001555 | D57: MARISOL PRADO | E57: 27265302225 | F57: RI | G57: 0 | H57: 27265302225 | I57: MARISOL PRADO | J57: 1200000 | K57: 0 | L57: 0 | M57: 0 | N57: 252000 | O57: 0 | P57: 0 | Q57: 0 | R57: 0 | S57: 0 | T57: 0 | U57: 1452000
A58: 04/06/2025 | B58: 04/06/2025 | C58: FCA 00005-00001557 | D58: MARISOL PRADO | E58: 27265302225 | F58: RI | G58: 0 | H58: 27265302225 | I58: MARISOL PRADO | J58: 1500000 | K58: 0 | L58: 0 | M58: 0 | N58: 315000 | O58: 0 | P58: 0 | Q58: 0 | R58: 0 | S58: 0 | T58: 0 | U58: 1815000
A59: 18/06/2025 | B59: 18/06/2025 | C59: FCA 00005-00001569 | D59: MARISOL PRADO | E59: 27265302225 | F59: RI | G59: 0 | H59: 27265302225 | I59: MARISOL PRADO | J59: 2500000 | K59: 0 | L59: 0 | M59: 0 | N59: 525000 | O59: 0 | P59: 0 | Q59: 0 | R59: 0 | S59: 0 | T59: 0 | U59: 3025000
A60: 23/06/2025 | B60: 23/06/2025 | C60: FCA 00005-00001572 | D60: MARISOL PRADO | E60: 27265302225 | F60: RI | G60: 0 | H60: 27265302225 | I60: MARISOL PRADO | J60: 2500000 | K60: 0 | L60: 0 | M60: 0 | N60: 525000 | O60: 0 | P60: 0 | Q60: 0 | R60: 0 | S60: 0 | T60: 0 | U60: 3025000
A61: 02/06/2025 | B61: 11 - Factura C | C61: 2 | D61: 357 | F61: 75228233602517 | G61: CUIT | H61: 27265832178 | I61: BLASCO MARIA GUADALUPE | J61: 1 | K61: $ | O61: 0 | Q61: 3200000
A62: 02/06/2025 | B62: 02/06/2025 | C62: FCC 00002-00000357 | D62: MARIA GUADALUPE BLASCO | E62: 27265832178 | F62: MO | G62: 0 | H62: 27265832178 | I62: MARIA GUADALUPE BLASCO | J62: 0 | K62: 0 | L62: 0 | M62: 3200000 | N62: 0 | O62: 0 | P62: 0 | Q62: 0 | R62: 0 | S62: 0 | T62: 0 | U62: 3200000
A63: 23/06/2025 | B63: 1 - Factura A | C63: 16 | D63: 49 | F63: 75253774462485 | G63: CUIT | H63: 27310367813 | I63: LA BRUNA MARIA VIRGINIA | J63: 1 | K63: $ | L63: 152023.28 | M63: 0 | N63: 0 | O63: 0 | P63: 31924.89 | Q63: 183948.17
A64: 05/06/2025 | B64: 11 - Factura C | C64: 2 | D64: 129 | F64: 75238661775227 | G64: CUIT | H64: 27315710508 | I64: RIVERO GABRIELA ROCIO | J64: 1 | K64: $ | O64: 0 | Q64: 48600
A65: 05/06/2025 | B65: 05/06/2025 | C65: FCC 00002-00000129 | D65: GABRIELA ROCIO RIVERO | E65: 27315710508 | F65: MO | G65: 0 | H65: 27315710508 | I65: GABRIELA ROCIO RIVERO | J65: 0 | K65: 0 | L65: 0 | M65: 48600 | N65: 0 | O65: 0 | P65: 0 | Q65: 0 | R65: 0 | S65: 0 | T65: 0 | U65: 48600
A66: 19/06/2025 | B66: 1 - Factura A | C66: 7 | D66: 41 | F66: 75253394208187 | G66: CUIT | H66: 27325223273 | I66: SOUSA ALDERETE ALEJANDRA MABEL | J66: 1 | K66: $ | L66: 1702000 | M66: 0 | N66: 0 | O66: 0 | P66: 357420 | Q66: 2059420
A67: 19/06/2025 | B67: 19/06/2025 | C67: FCA 00007-00000041 | D67: ALEJANDRA MABEL SOUSA ALDERETE | E67: 27325223273 | F67: RI | G67: 0 | H67: 27325223273 | I67: ALEJANDRA MABEL SOUSA ALDERETE | J67: 1702000 | K67: 0 | L67: 0 | M67: 0 | N67: 357420 | O67: 0 | P67: 0 | Q67: 0 | R67: 0 | S67: 0 | T67: 0 | U67: 2059420
A68: 11/06/2025 | B68: 11 - Factura C | C68: 1 | D68: 181 | F68: 75240481952451 | G68: CUIT | H68: 27338342840 | I68: CANCINO PAMELA RITA | J68: 1 | K68: $ | O68: 0 | Q68: 330000
A69: 11/06/2025 | B69: 11/06/2025 | C69: FCC 00001-00000181 | D69: PAMELA RITA CANCINO | E69: 27338342840 | F69: MO | G69: 0 | H69: 27338342840 | I69: PAMELA RITA CANCINO | J69: 0 | K69: 0 | L69: 0 | M69: 330000 | N69: 0 | O69: 0 | P69: 0 | Q69: 0 | R69: 0 | S69: 0 | T69: 0 | U69: 330000
A70: 12/06/2025 | B70: 11 - Factura C | C70: 1 | D70: 26 | F70: 75245530563845 | G70: CUIT | H70: 27443612705 | I70: MIGOYA MORIONDO MARIA INES | J70: 1 | K70: $ | O70: 0 | Q70: 900000
A71: 12/06/2025 | B71: 12/06/2025 | C71: FCC 00001-00000026 | D71: MARIA INES MIGOYA MORIONDO | E71: 27443612705 | F71: MO | G71: 0 | H71: 27443612705 | I71: MARIA INES MIGOYA MORIONDO | J71: 0 | K71: 0 | L71: 0 | M71: 900000 | N71: 0 | O71: 0 | P71: 0 | Q71: 0 | R71: 0 | S71: 0 | T71: 0 | U71: 900000
A72: 03/06/2025 | B72: 11 - Factura C | C72: 1 | D72: 15 | F72: 75223471719934 | G72: CUIT | H72: 27443612713 | I72: MIGOYA MORIONDO SOFIA | J72: 1 | K72: $ | O72: 0 | Q72: 870000
A73: 06/06/2025 | B73: 1 - Factura A | C73: 2036 | D73: 81824 | F73: 75230865461219 | G73: CUIT | H73: 30516186670 | I73: DEHEZA SOCIEDAD ANONIMA INDUSTRIAL COMERCIAL FINANCIERA INMOBILIARIA | J73: 1 | K73: $ | L73: 43366.12 | M73: 0 | N73: 0 | O73: 3035.63 | P73: 9106.88 | Q73: 55508.63
A74: 06/06/2025 | B74: 06/06/2025 | C74: FCA 02036-00081824 | D74: DEHEZA SOCIEDAD ANONIMA INDUSTRIAL COMERCIAL FINANCIERA INMOBILIARIA | E74: 30516186670 | F74: RI | G74: 0 | H74: 30516186670 | I74: DEHEZA SOCIEDAD ANONIMA INDUSTRIAL COMERCIAL FINANCIERA INMOBILIARIA | J74: 43366.12 | K74: 0 | L74: 0 | M74: 0 | N74: 9106.89 | O74: 0 | P74: 0 | Q74: 0 | R74: 0 | S74: 1300.98 | T74: 1734.64 | U74: 55508.63
A75: 02/06/2025 | B75: 1 - Factura A | C75: 11 | D75: 96840 | F75: 75224269050863 | G75: CUIT | H75: 30526582884 | I75: EXPRESO MAR DEL PLATA SOCIEDAD ANONIMA | J75: 1 | K75: $ | L75: 14834.71 | M75: 0 | N75: 0 | O75: 0 | P75: 3115.29 | Q75: 17950
A76: 03/06/2025 | B76: 1 - Factura A | C76: 12 | D76: 42816 | F76: 75224420681440 | G76: CUIT | H76: 30526582884 | I76: EXPRESO MAR DEL PLATA SOCIEDAD ANONIMA | J76: 1 | K76: $ | L76: 48231.4 | M76: 0 | N76: 0 | O76: 0 | P76: 10128.6 | Q76: 58360
A77: 02/06/2025 | B77: 1 - Factura A | C77: 11 | D77: 96841 | F77: 75224269748231 | G77: CUIT | H77: 30526582884 | I77: EXPRESO MAR DEL PLATA SOCIEDAD ANONIMA | J77: 1 | K77: $ | L77: 112520.66 | M77: 0 | N77: 0 | O77: 0 | P77: 23629.34 | Q77: 136150
A78: 02/06/2025 | B78: 02/06/2025 | C78: FCA 00011-00096840 | D78: EXPRESO MAR DEL PLATA SOCIEDAD ANONIMA | E78: 30526582884 | F78: RI | G78: 0 | H78: 30526582884 | I78: EXPRESO MAR DEL PLATA SOCIEDAD ANONIMA | J78: 14834.71 | K78: 0 | L78: 0 | M78: 0 | N78: 3115.29 | O78: 0 | P78: 0 | Q78: 0 | R78: 0 | S78: 0 | T78: 0 | U78: 17950
A79: 02/06/2025 | B79: 02/06/2025 | C79: FCA 00011-00096841 | D79: EXPRESO MAR DEL PLATA SOCIEDAD ANONIMA | E79: 30526582884 | F79: RI | G79: 0 | H79: 30526582884 | I79: EXPRESO MAR DEL PLATA SOCIEDAD ANONIMA | J79: 112520.66 | K79: 0 | L79: 0 | M79: 0 | N79: 23629.34 | O79: 0 | P79: 0 | Q79: 0 | R79: 0 | S79: 0 | T79: 0 | U79: 136150
A80: 03/06/2025 | B80: 03/06/2025 | C80: FCA 00012-00042816 | D80: EXPRESO MAR DEL PLATA SOCIEDAD ANONIMA | E80: 30526582884 | F80: RI | G80: 0 | H80: 30526582884 | I80: EXPRESO MAR DEL PLATA SOCIEDAD ANONIMA | J80: 48231.4 | K80: 0 | L80: 0 | M80: 0 | N80: 10128.59 | O80: 0 | P80: 0 | Q80: 0 | R80: 0 | S80: 0 | T80: 0 | U80: 58359.99
A81: 30/06/2025 | B81: 1 - Factura A | C81: 5015 | D81: 906955 | F81: 75274847526244 | G81: CUIT | H81: 30574876474 | I81: AUTOPISTAS URBANAS S. A. | J81: 1 | K81: $ | L81: 72938.16 | M81: 0 | N81: 0 | O81: 9481.94 | P81: 15316.97 | Q81: 97737.07
A82: 15/06/2025 | B82: 1 - Factura A | C82: 5015 | D82: 889481 | F82: 75244984368791 | G82: CUIT | H82: 30574876474 | I82: AUTOPISTAS URBANAS S. A. | J82: 1 | K82: $ | L82: 80368.61 | M82: 0 | N82: 0 | O82: 10447.89 | P82: 16877.37 | Q82: 107693.87
A83: 15/06/2025 | B83: 15/06/2025 | C83: FCA 05015-00889481 | D83: AUTOPISTAS URBANAS SA | E83: 30574876474 | F83: RI | G83: 0 | H83: 30574876474 | I83: AUTOPISTAS URBANAS SA | J83: 80368.43 | K83: 0 | L83: 0 | M83: 0 | N83: 16877.37 | O83: 2411.05 | P83: 0 | Q83: 0 | R83: 8036.84 | S83: 0 | T83: 0 | U83: 107693.69
A84: 15/06/2025 | B84: 1 - Factura A | C84: 113 | D84: 4288291 | F84: 75250195766310 | G84: CUIT | H84: 30577207190 | I84: COORDINACION ECOLOGICA AREA METROPOLITANA SOCIEDAD DEL ESTADO | J84: 1 | K84: $ | L84: 1487.6 | M84: 0 | N84: 0 | O84: 0 | P84: 312.4 | Q84: 1800
A85: 17/06/2025 | B85: 1 - Factura A | C85: 3 | D85: 54088 | F85: 75249133409515 | G85: CUIT | H85: 30577744579 | I85: EXPRESO TROLE S R L | J85: 1 | K85: $ | L85: 20926.88 | M85: 0 | N85: 0 | O85: 0 | P85: 4394.64 | Q85: 25321.52
A86: 17/06/2025 | B86: 17/06/2025 | C86: FCA 00003-00054088 | D86: EXPRESO TROLE S R L | E86: 30577744579 | F86: RI | G86: 0 | H86: 30577744579 | I86: EXPRESO TROLE S R L | J86: 20926.88 | K86: 0 | L86: 0 | M86: 0 | N86: 4394.64 | O86: 0 | P86: 0 | Q86: 0 | R86: 0 | S86: 0 | T86: 0 | U86: 25321.52
A87: 04/06/2025 | B87: 1 - Factura A | C87: 120 | D87: 5714 | F87: 75235504008979 | G87: CUIT | H87: 30587197215 | I87: PANATEL SOCIEDAD ANONIMA | J87: 1 | K87: $ | L87: 148760.33 | M87: 0 | N87: 0 | O87: 8925.62 | P87: 31239.67 | Q87: 188925.62
A88: 04/06/2025 | B88: 04/06/2025 | C88: FCA 00120-00005714 | D88: PANATEL SOCIEDAD ANONIMA | E88: 30587197215 | F88: RI | G88: 0 | H88: 30587197215 | I88: PANATEL SOCIEDAD ANONIMA | J88: 148760.33 | K88: 0 | L88: 0 | M88: 0 | N88: 31239.67 | O88: 0 | P88: 0 | Q88: 0 | R88: 0 | S88: 0 | T88: 8925.62 | U88: 188925.62
A89: 10/06/2025 | B89: 3 - Nota de Crédito A | C89: 5 | D89: 11109 | F89: 75233279370446 | G89: CUIT | H89: 30598960093 | I89: SILVESTRIN FABRIS SOC RESP LTDA | J89: 1 | K89: $ | L89: 497159.25 | M89: 0 | N89: 0 | O89: 0 | P89: 104403.44 | Q89: 601562.69
A90: 10/06/2025 | B90: 1 - Factura A | C90: 5 | D90: 168011 | F90: 75233328483049 | G90: CUIT | H90: 30598960093 | I90: SILVESTRIN FABRIS SOC RESP LTDA | J90: 1 | K90: $ | L90: 919586.25 | M90: 0 | N90: 0 | O90: 36783.45 | P90: 193113.11 | Q90: 1149482.8
A91: 06/06/2025 | B91: 1 - Factura A | C91: 5 | D91: 167824 | F91: 75233769970561 | G91: CUIT | H91: 30598960093 | I91: SILVESTRIN FABRIS SOC RESP LTDA | J91: 1 | K91: $ | L91: 2043414 | M91: 0 | N91: 0 | O91: 81736.56 | P91: 429116.94 | Q91: 2554267.5
A92: 06/06/2025 | B92: 06/06/2025 | C92: FCA 00005-00167824 | D92: SILVESTRIN FABRIS SOC RESP LTDA | E92: 30598960093 | F92: RI | G92: 0 | H92: 30598960093 | I92: SILVESTRIN FABRIS SOC RESP LTDA | J92: 2043414 | K92: 0 | L92: 0 | M92: 0 | N92: 429116.94 | O92: 0 | P92: 0 | Q92: 0 | R92: 0 | S92: 0 | T92: 81736.56 | U92: 2554267.5
A93: 10/06/2025 | B93: 10/06/2025 | C93: FCA 00005-00168011 | D93: SILVESTRIN FABRIS SOC RESP LTDA | E93: 30598960093 | F93: RI | G93: 0 | H93: 30598960093 | I93: SILVESTRIN FABRIS SOC RESP LTDA | J93: 919586.25 | K93: 0 | L93: 0 | M93: 0 | N93: 193113.11 | O93: 0 | P93: 0 | Q93: 0 | R93: 0 | S93: 0 | T93: 36783.45 | U93: 1149482.8
A94: 10/06/2025 | B94: 10/06/2025 | C94: NCA 00005-00011109 | D94: SILVESTRIN FABRIS SOC RESP LTDA | E94: 30598960093 | F94: RI | G94: 0 | H94: 30598960093 | I94: SILVESTRIN FABRIS SOC RESP LTDA | J94: -497159.25 | K94: 0 | L94: 0 | M94: 0 | N94: -104403.44 | O94: 0 | P94: 0 | Q94: 0 | R94: 0 | S94: 0 | T94: 0 | U94: -601562.69
A95: 02/06/2025 | B95: 1 - Factura A | C95: 2 | D95: 241 | F95: 75222257570701 | G95: CUIT | H95: 30605344352 | I95: CONSORCIO BARTOLOME MITRE 2466 | J95: 1 | K95: $ | L95: 2000000 | M95: 0 | N95: 0 | O95: 0 | P95: 420000 | Q95: 2420000
A96: 02/06/2025 | B96: 02/06/2025 | C96: FCA 00002-00000241 | D96: CONSORCIO BARTOLME MITRE 2466 | E96: 30605344352 | F96: RI | G96: 0 | H96: 30605344352 | I96: CONSORCIO BARTOLME MITRE 2466 | J96: 2000000 | K96: 0 | L96: 0 | M96: 0 | N96: 420000 | O96: 0 | P96: 0 | Q96: 0 | R96: 0 | S96: 0 | T96: 0 | U96: 2420000
A97: 15/06/2025 | B97: 1 - Factura A | C97: 2033 | D97: 84766 | F97: 75249926228757 | G97: CUIT | H97: 30607371799 | I97: AUTOSERVICIO MAYORISTA DIARCO SA | J97: 1 | K97: $ | L97: 285157.29 | M97: 0 | N97: 0 | O97: 31185.04 | P97: 59279.22 | Q97: 375621.55
A98: 15/06/2025 | B98: 15/06/2025 | C98: FCA 02033-00084766 | D98: AUTOSERVICIO MAYORISTA DIARCO SA | E98: 30607371799 | F98: RI | G98: 0 | H98: 30607371799 | I98: AUTOSERVICIO MAYORISTA DIARCO SA | J98: 279406.7 | K98: 0 | L98: 0 | M98: 0 | N98: 59279.22 | O98: 0 | P98: 0 | Q98: 0 | R98: 0 | S98: 8468.46 | T98: 22716.58 | U98: 375621.55
A99: 30/06/2025 | B99: 1 - Factura A | C99: 6 | D99: 19841674 | F99: 75267203549199 | G99: CUIT | H99: 30620177497 | I99: POSNET SOCIEDAD DE RESPONSABILIDAD LIMITADA | J99: 1 | K99: $ | L99: 0 | M99: 0 | N99: 0 | O99: 0 | P99: 0 | Q99: 0
A100: 30/06/2025 | B100: 1 - Factura A | C100: 6 | D100: 19963386 | F100: 75267213449375 | G100: CUIT | H100: 30620177497 | I100: POSNET SOCIEDAD DE RESPONSABILIDAD LIMITADA | J100: 1 | K100: $ | L100: 33999.93 | M100: 0 | N100: 0 | O100: 2380 | P100: 7139.99 | Q100: 43519.92
...

Sheet Compras 07
L1: 45839
C2: AGREGADOS DE AFIP | D2: AGREGADOS A AFIP
A3: Fecha Emision | B3: Fecha Contable | C3: Nro Factura | D3: Razon Social | E3: Cuit | F3: Condicion Iva | G3: Monto Gravado Iva 10,5 | H3: Monto Gravado Iva 21 | I3: Monto Gravado Iva 27 | J3: Monto No Gravado Y Exentos | K3: Monto Gravado Monotributistas | L3: Iva Facturado | M3: Imp Interno | N3: Otros | O3: Percepcion IVA | P3: IIBB | Q3: Total Facturado | R3: Rubro
A4: 14/07/2025 | B4: 14/07/2025 | C4: FCA 00001-00002000 | D4: PAPELERA GEOPEL SRL | E4: 30716815710 | F4: RI | G4: 0 | H4: 17000 | I4: 0 | J4: 0 | K4: 0 | L4: 3570 | M4: 0 | N4: 0 | O4: 0 | P4: 0 | Q4: =SUM(G4:P4) -> 20570 | R4: Bienes
A5: 14/07/2025 | B5: 14/07/2025 | C5: FCA 00001-00003176 | D5: NICOLAS TOBIAS SEQUEIRA Y MARIA GABRIELA RATTNER SOCIEDAD DE LA SECCION IV LGS | E5: 30717179389 | F5: RI | G5: 0 | H5: 49586.78 | I5: 0 | J5: 0 | K5: 0 | L5: 10413.22 | M5: 0 | N5: 0 | O5: 0 | P5: 0 | Q5: =SUM(G5:P5) -> 60000 | R5: Bienes
A6: 10/07/2025 | B6: 10/07/2025 | C6: FCA 00001-00007884 | D6: REHAB SRL | E6: 30715141201 | F6: RI | G6: 0 | H6: 585457.94 | I6: 0 | J6: 0 | K6: 0 | L6: 122946.17 | M6: 0 | N6: 0 | O6: 0 | P6: 0 | Q6: =SUM(G6:P6) -> 708404.11 | R6: Bienes
A7: 10/07/2025 | B7: 10/07/2025 | C7: FCA 00001-00007885 | D7: REHAB SRL | E7: 30715141201 | F7: RI | G7: 0 | H7: 330547.5 | I7: 0 | J7: 0 | K7: 0 | L7: 69414.98 | M7: 0 | N7: 0 | O7: 0 | P7: 0 | Q7: =SUM(G7:P7) -> 399962.48 | R7: Bienes
A8: 24/07/2025 | B8: 24/07/2025 | C8: FCA 00001-00008066 | D8: REHAB SRL | E8: 30715141201 | F8: RI | G8: 0 | H8: 2167818.8 | I8: 0 | J8: 0 | K8: 0 | L8: 455241.94 | M8: 0 | N8: 0 | O8: 0 | P8: 0 | Q8: =SUM(G8:P8) -> 2623060.7 | R8: Bienes
A9: 24/07/2025 | B9: 24/07/2025 | C9: FCA 00001-00008067 | D9: REHAB SRL | E9: 30715141201 | F9: RI | G9: 0 | H9: 3308625 | I9: 0 | J9: 0 | K9: 0 | L9: 694811.25 | M9: 0 | N9: 0 | O9: 0 | P9: 0 | Q9: =SUM(G9:P9) -> 4003436.2 | R9: Bienes
A10: 24/07/2025 | B10: 24/07/2025 | C10: FCA 00001-00008069 | D10: REHAB SRL | E10: 30715141201 | F10: RI | G10: 0 | H10: 810267.77 | I10: 0 | J10: 0 | K10: 0 | L10: 170156.23 | M10: 0 | N10: 0 | O10: 0 | P10: 0 | Q10: =SUM(G10:P10) -> 980424 | R10: Bienes
A11: 25/07/2025 | B11: 25/07/2025 | C11: FCA 00001-00008083 | D11: REHAB SRL | E11: 30715141201 | F11: RI | G11: 0 | H11: 857756.25 | I11: 0 | J11: 0 | K11: 0 | L11: 180128.81 | M11: 0 | N11: 0 | O11: 0 | P11: 0 | Q11: =SUM(G11:P11) -> 1037885.1 | R11: Bienes
A12: 02/07/2025 | B12: 02/07/2025 | C12: FCA 00002-00000643 | D12: 46 SPEED S.A. | E12: 30711610096 | F12: RI | G12: 0 | H12: 591900 | I12: 0 | J12: 0 | K12: 0 | L12: 124299 | M12: 0 | N12: 0 | O12: 0 | P12: 0 | Q12: =SUM(G12:P12) -> 716199 | R12: Bienes
A13: 03/07/2025 | B13: 03/07/2025 | C13: FCA 00002-00001390 | D13: MARTIN EZEQUIEL DI FEO | E13: 20272865869 | F13: RI | G13: 0 | H13: 251308.26 | I13: 0 | J13: 0 | K13: 0 | L13: 52774.73 | M13: 0 | N13: 0 | O13: 0 | P13: 0 | Q13: =SUM(G13:P13) -> 304082.99 | R13: Bienes
A14: 10/07/2025 | B14: 10/07/2025 | C14: FCA 00002-00001403 | D14: MARTIN EZEQUIEL DI FEO | E14: 20272865869 | F14: RI | G14: 0 | H14: 136600 | I14: 0 | J14: 0 | K14: 0 | L14: 28686 | M14: 0 | N14: 0 | O14: 0 | P14: 0 | Q14: =SUM(G14:P14) -> 165286 | R14: Bienes
A15: 21/07/2025 | B15: 21/07/2025 | C15: FCA 00002-00001421 | D15: MARTIN EZEQUIEL DI FEO | E15: 20272865869 | F15: RI | G15: 0 | H15: 299000 | I15: 0 | J15: 0 | K15: 0 | L15: 62790 | M15: 0 | N15: 0 | O15: 0 | P15: 0 | Q15: =SUM(G15:P15) -> 361790 | R15: Bienes
... A80: 29/07/2025 | B80: 29/07/2025 | C80: FCA 00104-09989160 | D80: CORREDORES VIALES SA | E80: 30715804812 | F80: RI | G80: 0 | H80: 1039.98 | I80: 0 | J80: 0 | K80: 0 | L80: 218.4 | M80: 0 | N80: 0 | O80: 41.6 | P80: 0 | Q80: =SUM(G80:P80) -> 1299.98 | R80: Bienes
A81: 45839 | B81: 21/07/2025 | C81: FCA 00500-01752314 | D81: SOLUCIONES MULTIMEDIA SA | E81: 30654118767 | F81: RI | G81: 0 | H81: 134425.88 | I81: 0 | J81: 0 | K81: 0 | L81: 28229.43 | M81: 0 | N81: 0 | O81: 0 | P81: 5377.04 | Q81: =SUM(G81:P81) -> 168032.35 | R81: Bienes
A82: 08/07/2025 | B82: 08/07/2025 | C82: FCA 00700-02564759 | D82: CORREDORES VIALES SA | E82: 30715804812 | F82: RI | G82: 0 | H82: 19343.65 | I82: 0 | J82: 0 | K82: 0 | L82: 4062.17 | M82: 0 | N82: 0 | O82: 0 | P82: 773.74 | Q82: =SUM(G82:P82) -> 24179.56 | R82: Bienes
A83: 22/07/2025 | B83: 22/07/2025 | C83: FCA 00700-02588871 | D83: CORREDORES VIALES SA | E83: 30715804812 | F83: RI | G83: 0 | H83: 17471.67 | I83: 0 | J83: 0 | K83: 0 | L83: 3669.05 | M83: 0 | N83: 0 | O83: 0 | P83: 698.86 | Q83: =SUM(G83:P83) -> 21839.58 | R83: Bienes
A84: 22/07/2025 | B84: 22/07/2025 | C84: FCA 00700-02588872 | D84: CORREDORES VIALES SA | E84: 30715804812 | F84: RI | G84: 0 | H84: 831.98 | I84: 0 | J84: 0 | K84: 0 | L84: 174.72 | M84: 0 | N84: 0 | O84: 0 | P84: 0 | Q84: =SUM(G84:P84) -> 1006.7 | R84: Bienes
A85: 10/07/2025 | B85: 10/07/2025 | C85: FCA 01002-00025719 | D85: IMPIERI, PI„EIRO, RIZZO Y A SA | E85: 30712289046 | F85: RI | G85: 0 | H85: 36641.54 | I85: 0 | J85: 5663.81 | K85: 0 | L85: 7694.72 | M85: 0 | N85: 0 | O85: 0 | P85: 0 | Q85: =SUM(G85:P85) -> 50000.07 | R85: Bienes
A86: 09/07/2025 | B86: 09/07/2025 | C86: FCA 09058-00038326 | D86: OPERADORA DE ESTACIONES DE SERVICIOS SA | E86: 30678774495 | F86: RI | G86: 0 | H86: 17506.57 | I86: 0 | J86: 5835.07 | K86: 0 | L86: 3676.38 | M86: 0 | N86: 0 | O86: 0 | P86: 0 | Q86: =SUM(G86:P86) -> 27018.02 | R86: Bienes
A87: 10/07/2025 | B87: 10/07/2025 | C87: FCC 00001-00000011 | D87: RAQUEL INES ARCE | E87: 27122903201 | F87: MO | G87: 0 | H87: 0 | I87: 0 | J87: 0 | K87: 980000 | L87: 0 | M87: 0 | N87: 0 | O87: 0 | P87: 0 | Q87: =SUM(G87:P87) -> 980000 | R87: Honorarios Arquitecta
A88: 07/07/2025 | B88: 07/07/2025 | C88: FCC 00001-00000016 | D88: SOFIA MIGOYA MORIONDO | E88: 27443612713 | F88: MO | G88: 0 | H88: 0 | I88: 0 | J88: 0 | K88: 870000 | L88: 0 | M88: 0 | N88: 0 | O88: 0 | P88: 0 | Q88: =SUM(G88:P88) -> 870000 | R88: Gtos Administrativos
A89: 06/07/2025 | B89: 06/07/2025 | C89: FCC 00001-00000035 | D89: HECTOR RAUL GUASCH | E89: 20311855671 | F89: MO | G89: 0 | H89: 0 | I89: 0 | J89: 0 | K89: 530000 | L89: 0 | M89: 0 | N89: 0 | O89: 0 | P89: 0 | Q89: =SUM(G89:P89) -> 530000 | R89: Serv Electricos
A90: 11/07/2025 | B90: 11/07/2025 | C90: FCC 00001-00000036 | D90: HECTOR RAUL GUASCH | E90: 20311855671 | F90: MO | G90: 0 | H90: 0 | I90: 0 | J90: 0 | K90: 145000 | L90: 0 | M90: 0 | N90: 0 | O90: 0 | P90: 0 | Q90: =SUM(G90:P90) -> 145000 | R90: Serv Electricos
A91: 11/07/2025 | B91: 11/07/2025 | C91: FCC 00001-00000037 | D91: HECTOR RAUL GUASCH | E91: 20311855671 | F91: MO | G91: 0 | H91: 0 | I91: 0 | J91: 0 | K91: 385000 | L91: 0 | M91: 0 | N91: 0 | O91: 0 | P91: 0 | Q91: =SUM(G91:P91) -> 385000 | R91: Serv Electricos
A92: 10/07/2025 | B92: 10/07/2025 | C92: FCC 00001-00000046 | D92: DILVER ALEX ISNADO IGNACIO | E92: 20944494236 | F92: MO | G92: 0 | H92: 0 | I92: 0 | J92: 0 | K92: 246650 | L92: 0 | M92: 0 | N92: 0 | O92: 0 | P92: 0 | Q92: =SUM(G92:P92) -> 246650 | R92: Bienes
A93: 22/07/2025 | B93: 22/07/2025 | C93: FCC 00001-00000182 | D93: PAMELA RITA CANCINO | E93: 27338342840 | F93: MO | G93: 0 | H93: 0 | I93: 0 | J93: 0 | K93: 610000 | L93: 0 | M93: 0 | N93: 0 | O93: 0 | P93: 0 | Q93: =SUM(G93:P93) -> 610000 | R93: Servicios Medicos
... A142: 31/07/2025 | B142: 31/07/2025 | C142: FCA 05015-00941676 | D142: AUTOPISTAS URBANAS SA | E142: 30574876474 | F142: RI | G142: 0 | H142: 97035.27 | I142: 0 | J142: 0 | K142: 0 | L142: 20377.41 | M142: 12614.54 | N142: 0 | O142: 0 | P142: 0 | Q142: =SUM(G142:P142) -> 130027.22 | R142: Servicios
A143: 11/07/2025 | B143: 11/07/2025 | C143: FCC 00001-00000001 | D143: PAULA CIVALE | E143: 27380284052 | F143: MO | G143: 0 | H143: 0 | I143: 0 | J143: 0 | K143: 260000 | L143: 0 | M143: 0 | N143: 0 | O143: 0 | P143: 0 | Q143: =SUM(G143:P143) -> 260000 | R143: Servicios
A144: 16/07/2025 | B144: 16/07/2025 | C144: FCC 00001-00000082 | D144: ANDREA MARIEL DRUETTA | E144: 23281233084 | F144: MO | G144: 0 | H144: 0 | I144: 0 | J144: 0 | K144: 300000 | L144: 0 | M144: 0 | N144: 0 | O144: 0 | P144: 0 | Q144: =SUM(G144:P144) -> 300000 | R144: Servicios
A145: 03/07/2025 | B145: 03/07/2025 | C145: FCC 00002-00000005 | D145: MARIA FLORENCIA BOCCACCI | E145: 27344304551 | F145: MO | G145: 0 | H145: 0 | I145: 0 | J145: 0 | K145: 100000 | L145: 0 | M145: 0 | N145: 0 | O145: 0 | P145: 0 | Q145: =SUM(G145:P145) -> 100000 | R145: Servicios
A146: 03/07/2025 | B146: 03/07/2025 | C146: FCC 00002-00000006 | D146: MARIA FLORENCIA BOCCACCI | E146: 27344304551 | F146: MO | G146: 0 | H146: 0 | I146: 0 | J146: 0 | K146: 800000 | L146: 0 | M146: 0 | N146: 0 | O146: 0 | P146: 0 | Q146: =SUM(G146:P146) -> 800000 | R146: Servicios
A147: 30/07/2025 | B147: 30/07/2025 | C147: FCC 00002-00000007 | D147: MARIA FLORENCIA BOCCACCI | E147: 27344304551 | F147: MO | G147: 0 | H147: 0 | I147: 0 | J147: 0 | K147: 800000 | L147: 0 | M147: 0 | N147: 0 | O147: 0 | P147: 0 | Q147: =SUM(G147:P147) -> 800000 | R147: Servicios
A148: 10/07/2025 | B148: 10/07/2025 | C148: FCC 00002-00000132 | D148: GABRIELA ROCIO RIVERO | E148: 27315710508 | F148: MO | G148: 0 | H148: 0 | I148: 0 | J148: 0 | K148: 48600 | L148: 0 | M148: 0 | N148: 0 | O148: 0 | P148: 0 | Q148: =SUM(G148:P148) -> 48600 | R148: Servicios
A149: 07/07/2025 | B149: 07/07/2025 | C149: FCC 00002-00000364 | D149: MARIA GUADALUPE BLASCO | E149: 27265832178 | F149: MO | G149: 0 | H149: 0 | I149: 0 | J149: 0 | K149: 3200000 | L149: 0 | M149: 0 | N149: 0 | O149: 0 | P149: 0 | Q149: =SUM(G149:P149) -> 3200000 | R149: Servicios
A150: 30/07/2025 | C150: FCA 00004-0000086 | D150: NARDOMARINO EDUARDO FRANCISCO | E150: 20174004146 | H150: 84000 | L150: 17640 | Q150: =SUM(G150:P150) -> 101640
A151: 30/07/2025 | C151: FCA 00004-0000087 | D151: NARDOMARINO EDUARDO FRANCISCO | E151: 20174004146 | H151: 154000 | L151: 32340 | Q151: =SUM(G151:P151) -> 186340
A152: 31/07/2025 | C152: FCA 00006-20103913 | D152: POSNET SOCIEDAD DE RESPONSABILIDAD LIMITADA | E152: 30620177497 | H152: - | L152: - | Q152: =SUM(G152:P152) -> 0
A153: 45869 | C153: FCA 00126-0055744 | D153: COORDINACION ECOLOGICA AREA METROPOLITANA SOCIEDAD DEL ESTADO | E153: 30577207190 | H153: 1487.6 | L153: 312.4 | Q153: =SUM(G153:P153) -> 1800
A154: 45869 | C154: FCA 00126-0055745 | D154: COORDINACION ECOLOGICA AREA METROPOLITANA SOCIEDAD DEL ESTADO | E154: 30577207190 | H154: 1487.6 | L154: 312.4 | Q154: =SUM(G154:P154) -> 1800
A155: 19/07/2025 | C155: FCA 00006-0022777 | D155: SOMOS ENERGIA S.A. | E155: 33715594949 | H155: 36846.52 | L155: 7737.77 | Q155: 49999.96
A156: 20/07/2025 | C156: FCA 00126-0055747 | D156: SOMOS ENERGIA S.A. | E156: 33715594949 | H156: 27679.81 | L156: 5812.76 | Q156: 37560.94
A157: 45858 | C157: FCA 00012-00008861 | D157: COREY SOCIEDAD ANONIMA | E157: 30688460644 | H157: 39599.57 | L157: 8315.91 | O157: 532.3 | P157: 10590.2 | Q157: 59038
A158: 15/07/2025 | C158: FCA 00008-00015537 | D158: SOMOS ENERGIA S.A. | E158: 33715594949 | H158: 22387.24 | L158: 4701.32 | Q158: 30378.99
A159: 45868 | B159: 45868 | C159: IVA S/ EXTRACTOS | D159: Banco Credicoop | H159: =L159*100/21 -> 53595.571 | L159: =1245+10010.07 -> 11255.07 | Q159: =SUM(G159:P159) -> 64850.641
A160: 45868 | B160: 45868 | C160: IVA S/ EXTRACTOS | D160: Banco Patagonia | H160: =L160*100/21 -> 40275 | L160: =7407.75+1050 -> 8457.75 | Q160: =SUM(G160:P160) -> 48732.75
G161: =SUM(G4:G160) -> 10196998 | H161: =SUM(H4:H160) -> 59394500 | I161: =SUM(I4:I160) -> 177657.45 | J161: =SUM(J4:J160) -> 50481.88 | K161: =SUM(K4:K160) -> 11265250 | L161: =SUM(L4:L160) -> 13591497 | M161: =SUM(M4:M160) -> 44190.12 | N161: =SUM(N4:N160) -> 2994.71 | ... Q161: =SUM(Q4:Q160) -> 95284001
I165: IVA 21 | J165: IVA 27 | K165: IVA 10,5
H166: NETO | I166: 59394500 | J166: 177657.45 | K166: 10196998
H167: IVA | I167: =I166*0.21 -> 12472845 | J167: =J166*0.27 -> 47967.512 | K167: =K166*0.105 -> 1070684.8
H168: TOTAL NETO | I168: =SUM(I166:K166) -> 69769155
H169: TOTAL IVA | I169: =SUM(I167:K167) -> 13591497

Sheet ARCA07
A1: Fecha | B1: Tipo | C1: Punto de Venta | D1: Número Desde | E1: Número Hasta | F1: Cód. Autorización | G1: Tipo Doc. Emisor | H1: Nro. Doc. Emisor | I1: Denominación Emisor | J1: Tipo Cambio | K1: Moneda | L1: Imp. Neto Gravado | M1: Imp. Neto No Gravado | N1: Imp. Op. Exentas | O1: Otros Tributos | P1: IVA | Q1: Imp. Total
A2: 01/07/2025 | B2: 1 - Factura A | C2: 500 | D2: 1752314 | F2: 75267396210618 | G2: CUIT | H2: 30654118767 | I2: SOLUCIONES MULTIMEDIA S A | J2: 1 | K2: $ | L2: 134425.88 | M2: 0 | N2: 0 | O2: 5377.04 | P2: 28229.43 | Q2: 168032.35
A3: 01/07/2025 | B3: 1 - Factura A | C3: 2 | D3: 26610 | F3: 75269789142609 | G3: CUIT | H3: 23233422029 | I3: SCHULZE RODOLFO ESTEBAN | J3: 1 | K3: $ | L3: 243548.67 | M3: 0 | N3: 0 | O3: 0 | P3: 51145.22 | Q3: 294693.89
A4: 01/07/2025 | B4: 1 - Factura A | C4: 1 | D4: 131016 | F4: 75269757212969 | G4: CUIT | H4: 30714864269 | I4: CONTABILIUM S.A. S. A. | J4: 1 | K4: $ | L4: 184800 | M4: 0 | N4: 0 | O4: 0 | P4: 38808 | Q4: 223608
A5: 01/07/2025 | B5: 1 - Factura A | C5: 711 | D5: 7299752 | F5: 35269945169622 | G5: CUIT | H5: 30677237119 | I5: AUTOPISTAS DEL SOL S A | J5: 1 | K5: $ | L5: 5893.17 | M5: 0 | N5: 176.8 | O5: 235.73 | P5: 1237.57 | Q5: 7543.27
A6: 01/07/2025 | B6: 1 - Factura A | C6: 629 | D6: 6239427 | F6: 35263170451766 | G6: CUIT | H6: 30663498513 | I6: GRUPO CONCESIONARIO DEL OESTE SA | J6: 1 | K6: $ | L6: 1155.52 | M6: 0 | N6: 0 | O6: 46.22 | P6: 242.66 | Q6: 1444.4
A7: 01/07/2025 | B7: 1 - Factura A | C7: 2 | D7: 243 | F7: 75262762655199 | G7: CUIT | H7: 30605344352 | I7: CONSORCIO BARTOLOME MITRE 2466 | J7: 1 | K7: $ | L7: 2000000 | M7: 0 | N7: 0 | O7: 0 | P7: 420000 | Q7: 2420000
A8: 01/07/2025 | B8: 2 - Nota de Débito A | C8: 1 | D8: 23 | F8: 75261735325770 | G8: CUIT | H8: 30715141201 | I8: REHAB S.R.L. | J8: 1 | K8: $ | L8: 0 | M8: 3783 | N8: 0 | O8: 0 | P8: 0 | Q8: 3783
A9: 02/07/2025 | B9: 1 - Factura A | C9: 120 | D9: 5750 | F9: 75275918730502 | G9: CUIT | H9: 30587197215 | I9: PANATEL SOCIEDAD ANONIMA | J9: 1 | K9: $ | L9: 148760.33 | M9: 0 | N9: 0 | O9: 8925.62 | P9: 31239.67 | Q9: 188925.62
A10: 02/07/2025 | B10: 1 - Factura A | C10: 1 | D10: 131488 | F10: 75279878826181 | G10: CUIT | H10: 30714864269 | I10: CONTABILIUM S.A. S. A. | J10: 1 | K10: $ | L10: 184800 | M10: 0 | N10: 0 | O10: 0 | P10: 38808 | Q10: 223608
A11: 02/07/2025 | B11: 1 - Factura A | C11: 3051 | D11: 937439 | F11: 75277185042295 | G11: CUIT | H11: 30678814357 | I11: TELEFONICA MOVILES ARGENTINA SOCIEDAD ANONIMA | J11: 1 | K11: $ | L11: 83974.87 | M11: 0 | N11: 0 | O11: 10324.14 | P11: 22673.21 | Q11: 116972.22
A12: 02/07/2025 | B12: 1 - Factura A | C12: 2 | D12: 643 | F12: 75276934618608 | G12: CUIT | H12: 30711610096 | I12: 46 SPEED S.A. | J12: 1 | K12: $ | L12: 591900 | M12: 0 | N12: 0 | O12: 0 | P12: 124299 | Q12: 716199
A13: 02/07/2025 | B13: 11 - Factura C | C13: 4 | D13: 31 | F13: 75273871704348 | G13: CUIT | H13: 20086277523 | I13: BOTINDARI JUAN CARLOS | J13: 1 | K13: $ | O13: 0 | Q13: 290000
A14: 03/07/2025 | B14: 1 - Factura A | C14: 2 | D14: 1390 | F14: 75279063278113 | G14: CUIT | H14: 20272865869 | I14: DI FEO MARTIN EZEQUIEL | J14: 1 | K14: $ | L14: 251308.26 | M14: 0 | N14: 0 | O14: 0 | P14: 52774.73 | Q14: 304082.99
A15: 03/07/2025 | B15: 1 - Factura A | C15: 6 | D15: 58183 | F15: 75278069533021 | G15: CUIT | H15: 30710177658 | I15: TARGET MEDICAL S.A. | J15: 1 | K15: $ | L15: 987480 | M15: 0 | N15: 0 | O15: 0 | P15: 103685.4 | Q15: 1091165.4
A16: 03/07/2025 | B16: 1 - Factura A | C16: 1 | D16: 921255 | F16: 75289907062304 | G16: CUIT | H16: 33716307749 | I16: VERISURE ARGENTINA MONITOREO DE ALARMAS SA | J16: 1 | K16: $ | L16: 58270.1 | M16: 0 | N16: 0 | O16: 2330.8 | P16: 12236.72 | Q16: 72837.62
A17: 03/07/2025 | B17: 11 - Factura C | C17: 2 | D17: 5 | F17: 75271097510744 | G17: CUIT | H17: 27344304551 | I17: BOCCACCI MARIA FLORENCIA | J17: 1 | K17: $ | O17: 0 | Q17: 100000
A18: 03/07/2025 | B18: 11 - Factura C | C18: 2 | D18: 6 | F18: 75271099549061 | G18: CUIT | H18: 27344304551 | I18: BOCCACCI MARIA FLORENCIA | J18: 1 | K18: $ | O18: 0 | Q18: 800000
A19: 04/07/2025 | B19: 1 - Factura A | C19: 2 | D19: 57727 | F19: 75279202091636 | G19: CUIT | H19: 30707986189 | I19: CIERRES ABROJO & HERRAJES SRL | J19: 1 | K19: $ | L19: 83470.41 | M19: 0 | N19: 0 | O19: 0 | P19: 17528.79 | Q19: 100999.2
A20: 05/07/2025 | B20: 1 - Factura A | C20: 2019 | D20: 293272 | F20: 75270339957195 | G20: CUIT | H20: 30516186670 | I20: DEHEZA SOCIEDAD ANONIMA INDUSTRIAL COMERCIAL FINANCIERA INMOBILIARIA | J20: 1 | K20: $ | L20: 47029.37 | M20: 0 | N20: 0 | O20: 15254.6 | P20: 9876.17 | Q20: 72160.13
A21: 06/07/2025 | B21: 11 - Factura C | C21: 1 | D21: 35 | F21: 75271471481833 | G21: CUIT | H21: 20311855671 | I21: GUASCH HECTOR RAUL | J21: 1 | K21: $ | O21: 0 | Q21: 530000
A22: 07/07/2025 | B22: 1 - Factura A | C22: 5 | D22: 169275 | F22: 75273545479476 | G22: CUIT | H22: 30598960093 | I22: SILVESTRIN FABRIS SOC RESP LTDA | J22: 1 | K22: $ | L22: 1332362.9 | M22: 0 | N22: 0 | O22: 53294.52 | P22: 279796.21 | Q22: 1665453.6
A23: 07/07/2025 | B23: 1 - Factura A | C23: 2 | D23: 12343 | F23: 75272513361868 | G23: CUIT | H23: 30714331082 | I23: ORTOPEDIA CASA ESCALADA S.R.L. | J23: 1 | K23: $ | L23: 3407765.5 | M23: 0 | N23: 0 | O23: 0 | P23: 715630.76 | Q23: 4123396.3
A24: 07/07/2025 | B24: 1 - Factura A | C24: 8 | D24: 29773 | F24: 35264802817813 | G24: CUIT | H24: 30708795174 | I24: LUTAC SA | J24: 1 | K24: $ | L24: 29322.72 | M24: 0 | N24: 0 | O24: 4519.51 | P24: 6157.77 | Q24: 40000
A25: 07/07/2025 | B25: 11 - Factura C | C25: 1 | D25: 16 | F25: 75273569271318 | G25: CUIT | H25: 27443612713 | I25: MIGOYA MORIONDO SOFIA | J25: 1 | K25: $ | O25: 0 | Q25: 870000
A26: 07/07/2025 | B26: 11 - Factura C | C26: 2 | D26: 364 | F26: 75278580885457 | G26: CUIT | H26: 27265832178 | I26: BLASCO MARIA GUADALUPE | J26: 1 | K26: $ | O26: 0 | Q26: 3200000
A27: 08/07/2025 | B27: 1 - Factura A | C27: 6 | D27: 58255 | F27: 75278695418133 | G27: CUIT | H27: 30710177658 | I27: TARGET MEDICAL S.A. | J27: 1 | K27: $ | L27: 1974960 | M27: 0 | N27: 0 | O27: 0 | P27: 207370.8 | Q27: 2182330.8
A28: 08/07/2025 | B28: 1 - Factura A | C28: 8 | D28: 435 | F28: 75274675249569 | G28: CUIT | H28: 30643518364 | I28: FARMACIA DE MEDRANO 533 SOCIEDAD EN COMANDITA SIMPLE | J28: 1 | K28: $ | L28: 813981.5 | M28: 0 | N28: 0 | O28: 0 | P28: 170936.12 | Q28: 984917.62
A29: 08/07/2025 | B29: 1 - Factura A | C29: 8 | D29: 436 | F29: 75274691037647 | G29: CUIT | H29: 30643518364 | I29: FARMACIA DE MEDRANO 533 SOCIEDAD EN COMANDITA SIMPLE | J29: 1 | K29: $ | L29: 207100 | M29: 0 | N29: 0 | O29: 0 | P29: 43491 | Q29: 250591
A30: 08/07/2025 | B30: 1 - Factura A | C30: 700 | D30: 2564759 | F30: 75282904450798 | G30: CUIT | H30: 30715804812 | I30: CORREDORES VIALES SOCIEDAD ANONIMA | J30: 1 | K30: $ | L30: 19343.65 | M30: 0 | N30: 0 | O30: 773.74 | P30: 4062.17 | Q30: 24179.56
A31: 08/07/2025 | B31: 1 - Factura A | C31: 7 | D31: 45 | F31: 75273724843523 | G31: CUIT | H31: 27325223273 | I31: SOUSA ALDERETE ALEJANDRA MABEL | J31: 1 | K31: $ | L31: 1506000 | M31: 0 | N31: 0 | O31: 0 | P31: 316260 | Q31: 1822260
A32: 08/07/2025 | B32: 1 - Factura A | C32: 4 | D32: 164 | F32: 75276676679178 | G32: CUIT | H32: 20317488476 | I32: VILLALBA MIGUEL ANGEL | J32: 1 | K32: $ | L32: 300000 | M32: 0 | N32: 0 | O32: 0 | P32: 63000 | Q32: 363000
A33: 08/07/2025 | B33: 11 - Factura C | C33: 1 | D33: 27 | F33: 75275690059142 | G33: CUIT | H33: 27443612705 | I33: MIGOYA MORIONDO MARIA INES | J33: 1 | K33: $ | O33: 0 | Q33: 900000
A34: 09/07/2025 | B34: 1 - Factura A | C34: 9058 | D34: 38326 | F34: 75285829166110 | G34: CUIT | H34: 30678774495 | I34: OPERADORA DE ESTACIONES DE SERVICIOS SA | J34: 1 | K34: $ | L34: 17506.56 | M34: 0 | N34: 0 | O34: 5835.07 | P34: 3676.38 | Q34: 27018.01
A35: 09/07/2025 | B35: 1 - Factura A | C35: 3101 | D35: 347323 | F35: 75287964429683 | G35: CUIT | H35: 30678814357 | I35: TELEFONICA MOVILES ARGENTINA SOCIEDAD ANONIMA | J35: 1 | K35: $ | L35: 93682.58 | M35: 0 | N35: 0 | O35: 6557.78 | P35: 25294.3 | Q35: 125534.66
A36: 10/07/2025 | B36: 1 - Factura A | C36: 4 | D36: 4861 | F36: 75287928028324 | G36: CUIT | H36: 20129871947 | I36: FERNANDEZ CARLOS RODOLFO | J36: 1 | K36: $ | L36: 118166.18 | M36: 0 | N36: 0 | O36: 0 | P36: 24814.9 | Q36: 142981.08
A37: 10/07/2025 | B37: 1 - Factura A | C37: 8 | D37: 437 | F37: 75284896364027 | G37: CUIT | H37: 30643518364 | I37: FARMACIA DE MEDRANO 533 SOCIEDAD EN COMANDITA SIMPLE | J37: 1 | K37: $ | L37: 73091.5 | M37: 0 | N37: 0 | O37: 0 | P37: 15349.22 | Q37: 88440.72
A38: 10/07/2025 | B38: 1 - Factura A | C38: 2 | D38: 1403 | F38: 75289957350180 | G38: CUIT | H38: 20272865869 | I38: DI FEO MARTIN EZEQUIEL | J38: 1 | K38: $ | L38: 136600 | M38: 0 | N38: 0 | O38: 0 | P38: 28686 | Q38: 165286
A39: 10/07/2025 | B39: 1 - Factura A | C39: 1 | D39: 7885 | F39: 75281891194235 | G39: CUIT | H39: 30715141201 | I39: REHAB S.R.L. | J39: 1 | K39: $ | L39: 330547.5 | M39: 0 | N39: 0 | O39: 0 | P39: 69414.98 | Q39: 399962.48
A40: 10/07/2025 | B40: 1 - Factura A | C40: 1 | D40: 7884 | F40: 75281887042944 | G40: CUIT | H40: 30715141201 | I40: REHAB S.R.L. | J40: 1 | K40: $ | L40: 585457.94 | M40: 0 | N40: 0 | O40: 0 | P40: 122946.17 | Q40: 708404.11
A41: 10/07/2025 | B41: 1 - Factura A | C41: 1002 | D41: 25719 | F41: 75286881468498 | G41: CUIT | H41: 30712289046 | I41: IMPIERI, PIÑEIRO, RIZZO Y ASOC S.A. | J41: 1 | K41: $ | L41: 36641.54 | M41: 0 | N41: 0 | O41: 5663.81 | P41: 7694.72 | Q41: 50000.07
A42: 10/07/2025 | B42: 1 - Factura A | C42: 6 | D42: 1524 | F42: 75283927592114 | G42: CUIT | H42: 20247225243 | I42: VENTO HUGO GABRIEL | J42: 1 | K42: $ | L42: 55388 | M42: 0 | N42: 0 | O42: 0 | P42: 11631.48 | Q42: 67019.48
A43: 10/07/2025 | B43: 1 - Factura A | C43: 3 | D43: 242 | F43: 75284928269864 | G43: CUIT | H43: 20134815494 | I43: SUCESION DE MORANT EDUARDO ENRIQUE | J43: 1 | K43: $ | L43: 39669.62 | M43: 0 | N43: 0 | O43: 0 | P43: 8330.62 | Q43: 48000.22
A44: 10/07/2025 | B44: 11 - Factura C | C44: 1 | D44: 11 | F44: 75281890285302 | G44: CUIT | H44: 27122903201 | I44: ARCE RAQUEL INES | J44: 1 | K44: $ | O44: 0 | Q44: 980000
A45: 10/07/2025 | B45: 11 - Factura C | C45: 1 | D45: 46 | F45: 75286914916367 | G45: CUIT | H45: 20944494236 | I45: ISNADO IGNACIO DILVER ALEX | J45: 1 | K45: $ | O45: 0 | Q45: 246650
A46: 10/07/2025 | B46: 11 - Factura C | C46: 2 | D46: 132 | F46: 75288915321195 | G46: CUIT | H46: 27315710508 | I46: RIVERO GABRIELA ROCIO | J46: 1 | K46: $ | O46: 0 | Q46: 48600
A47: 11/07/2025 | B47: 1 - Factura A | C47: 3 | D47: 54323 | F47: 75289070301081 | G47: CUIT | H47: 30577744579 | I47: EXPRESO TROLE S R L | J47: 1 | K47: $ | L47: 89173 | M47: 0 | N47: 0 | O47: 0 | P47: 18726.33 | Q47: 107899.33
A48: 11/07/2025 | B48: 1 - Factura A | C48: 5 | D48: 1584 | F48: 75285017141445 | G48: CUIT | H48: 27265302225 | I48: PRADO MARISOL | J48: 1 | K48: $ | L48: 800000 | M48: 0 | N48: 0 | O48: 0 | P48: 168000 | Q48: 968000
A49: 11/07/2025 | B49: 1 - Factura A | C49: 5 | D49: 169488 | F49: 75283097656552 | G49: CUIT | H49: 30598960093 | I49: SILVESTRIN FABRIS SOC RESP LTDA | J49: 1 | K49: $ | L49: 367834.5 | M49: 0 | N49: 0 | O49: 14713.38 | P49: 77245.24 | Q49: 459793.12
A50: 11/07/2025 | B50: 1 - Factura A | C50: 7 | D50: 1650 | F50: 75286083812521 | G50: CUIT | H50: 30712187316 | I50: ITALOMED PRODUCTOS SRL | J50: 1275 | K50: USD | L50: 298.78 | M50: 0 | N50: 0 | O50: 0 | P50: 62.74 | Q50: 361.52
A51: 11/07/2025 | B51: 1 - Factura A | C51: 5 | D51: 2548 | F51: 75286084086521 | G51: CUIT | H51: 30712187316 | I51: ITALOMED PRODUCTOS SRL | J51: 1275 | K51: USD | L51: 519.5 | M51: 0 | N51: 0 | O51: 0 | P51: 109.1 | Q51: 628.6
A52: 11/07/2025 | B52: 1 - Factura A | C52: 2 | D52: 5703 | F52: 75281958024814 | G52: CUIT | H52: 24253769951 | I52: VIDAL LEONARDO JAVIER | J52: 1 | K52: $ | L52: 395449 | M52: 0 | N52: 0 | O52: 0 | P52: 83044.29 | Q52: 478493.29
A53: 11/07/2025 | B53: 1 - Factura A | C53: 4 | D53: 68 | F53: 75296643585652 | G53: CUIT | H53: 20174004146 | I53: NARDOMARINO EDUARDO FRANCISCO | J53: 1 | K53: $ | L53: 238000 | M53: 0 | N53: 0 | O53: 0 | P53: 49980 | Q53: 287980
A54: 11/07/2025 | B54: 11 - Factura C | C54: 1 | D54: 1 | F54: 75282067165705 | G54: CUIT | H54: 27380284052 | I54: CIVALE PAULA | J54: 1 | K54: $ | O54: 0 | Q54: 260000
A55: 11/07/2025 | B55: 11 - Factura C | C55: 1 | D55: 36 | F55: 75281095139501 | G55: CUIT | H55: 20311855671 | I55: GUASCH HECTOR RAUL | J55: 1 | K55: $ | O55: 0 | Q55: 145000
A56: 11/07/2025 | B56: 11 - Factura C | C56: 1 | D56: 37 | F56: 75281095568471 | G56: CUIT | H56: 20311855671 | I56: GUASCH HECTOR RAUL | J56: 1 | K56: $ | O56: 0 | Q56: 385000
A57: 12/07/2025 | B57: 1 - Factura A | C57: 7 | D57: 593 | F57: 75287196809562 | G57: CUIT | H57: 30717409007 | I57: GUPARO S.R.L. | J57: 1 | K57: $ | L57: 128016.53 | M57: 0 | N57: 0 | O57: 0 | P57: 26883.47 | Q57: 154900
A58: 14/07/2025 | B58: 1 - Factura A | C58: 1001 | D58: 561 | F58: 75282417156123 | G58: CUIT | H58: 30707370552 | I58: RAKE S.A. | J58: 1 | K58: $ | L58: 2397520.7 | M58: 0 | N58: 0 | O58: 0 | P58: 503479.34 | Q58: 2901000
A59: 14/07/2025 | B59: 1 - Factura A | C59: 1 | D59: 3176 | F59: 75289410189365 | G59: CUIT | H59: 30717179389 | I59: NICOLAS TOBIAS SEQUEIRA Y MARIA GABRIELA RATTNER SOCIEDAD DE LA SECCION IV LGS | J59: 1 | K59: $ | L59: 49586.78 | M59: 0 | N59: 0 | O59: 0 | P59: 10413.22 | Q59: 60000
A60: 14/07/2025 | B60: 1 - Factura A | C60: 104 | D60: 9850740 | F60: 75282468723721 | G60: CUIT | H60: 30715804812 | I60: CORREDORES VIALES SOCIEDAD ANONIMA | J60: 1 | K60: $ | L60: 1039.98 | M60: 0 | N60: 0 | O60: 41.6 | P60: 218.4 | Q60: 1299.98
A61: 14/07/2025 | B61: 1 - Factura A | C61: 2 | D61: 12376 | F61: 75282386967814 | G61: CUIT | H61: 30714331082 | I61: ORTOPEDIA CASA ESCALADA S.R.L. | J61: 1 | K61: $ | L61: 2929735.2 | M61: 0 | N61: 0 | O61: 0 | P61: 615244.4 | Q61: 3544979.6
A62: 14/07/2025 | B62: 1 - Factura A | C62: 5 | D62: 3035 | F62: 75287370223999 | G62: CUIT | H62: 30707267077 | I62: BARBARO SOCIEDAD COLECTIVA | J62: 1 | K62: $ | L62: 1560000 | M62: 0 | N62: 0 | O62: 0 | P62: 327600 | Q62: 1887600
A63: 14/07/2025 | B63: 1 - Factura A | C63: 4 | D63: 69 | F63: 75296643916024 | G63: CUIT | H63: 20174004146 | I63: NARDOMARINO EDUARDO FRANCISCO | J63: 1 | K63: $ | L63: 196000 | M63: 0 | N63: 0 | O63: 0 | P63: 41160 | Q63: 237160
A64: 15/07/2025 | B64: 1 - Factura A | C64: 7 | D64: 21690 | F64: 75288535082697 | G64: CUIT | H64: 30709214078 | I64: REHAVITA S.A. | J64: 1 | K64: $ | L64: 607200 | M64: 0 | N64: 0 | O64: 0 | P64: 63756 | Q64: 670956
A65: 15/07/2025 | B65: 1 - Factura A | C65: 5015 | D65: 923924 | F65: 75294616216653 | G65: CUIT | H65: 30574876474 | I65: AUTOPISTAS URBANAS S. A. | J65: 1 | K65: $ | L65: 38953.67 | M65: 0 | N65: 0 | O65: 5063.95 | P65: 8180.24 | Q65: 52197.86
A66: 15/07/2025 | B66: 1 - Factura A | C66: 50 | D66: 4470356 | F66: 75296710412466 | G66: CUIT | H66: 30714112836 | I66: AUTOPISTAS DE BUENOS AIRES (AUBASA) SA S. A. | J66: 1 | K66: $ | L66: 4153.52 | M66: 0 | N66: 0 | O66: 124.61 | P66: 872.24 | Q66: 5150.37
A67: 15/07/2025 | B67: 1 - Factura A | C67: 4 | D67: 70 | F67: 75296644278283 | G67: CUIT | H67: 20174004146 | I67: NARDOMARINO EDUARDO FRANCISCO | J67: 1 | K67: $ | L67: 308000 | M67: 0 | N67: 0 | O67: 0 | P67: 64680 | Q67: 372680
A68: 15/07/2025 | B68: 11 - Factura C | C68: 4 | D68: 41 | F68: 75283527623181 | G68: CUIT | H68: 20086277523 | I68: BOTINDARI JUAN CARLOS | J68: 1 | K68: $ | O68: 0 | Q68: 800000
A69: 16/07/2025 | B69: 1 - Factura A | C69: 3 | D69: 3216303 | F69: 75299680815470 | G69: CUIT | H69: 30712019359 | I69: LINKEDSTORE ARGENTINA S.R.L. | J69: 1 | K69: $ | L69: 16528.1 | M69: 0 | N69: 0 | O69: 661.13 | P69: 3470.9 | Q69: 20660.13
A70: 16/07/2025 | B70: 1 - Factura A | C70: 5 | D70: 169710 | F70: 75293630628110 | G70: CUIT | H70: 30598960093 | I70: SILVESTRIN FABRIS SOC RESP LTDA | J70: 1 | K70: $ | L70: 3068718.8 | M70: 0 | N70: 0 | O70: 122748.75 | P70: 644430.93 | Q70: 3835898.4
A71: 16/07/2025 | B71: 1 - Factura A | C71: 2 | D71: 12394 | F71: 75292643228832 | G71: CUIT | H71: 30714331082 | I71: ORTOPEDIA CASA ESCALADA S.R.L. | J71: 1 | K71: $ | L71: 515221.38 | M71: 0 | N71: 0 | O71: 0 | P71: 54098.24 | Q71: 569319.62
A72: 16/07/2025 | B72: 1 - Factura A | C72: 2 | D72: 7912 | F72: 75297651523996 | G72: CUIT | H72: 30694549817 | I72: DISEÑOS JERY S R L | J72: 1 | K72: $ | L72: 458553.2 | M72: 0 | N72: 0 | O72: 0 | P72: 96296.17 | Q72: 554849.37
A73: 16/07/2025 | B73: 1 - Factura A | C73: 629 | D73: 6280002 | F73: 35283426391697 | G73: CUIT | H73: 30663498513 | I73: GRUPO CONCESIONARIO DEL OESTE SA | J73: 1 | K73: $ | L73: 1155.52 | M73: 0 | N73: 0 | O73: 46.22 | P73: 242.66 | Q73: 1444.4
A74: 16/07/2025 | B74: 1 - Factura A | C74: 711 | D74: 7358779 | F74: 35289849042259 | G74: CUIT | H74: 30677237119 | I74: AUTOPISTAS DEL SOL S A | J74: 1 | K74: $ | L74: 4391.03 | M74: 0 | N74: 131.73 | O74: 175.64 | P74: 922.12 | Q74: 5620.52
A75: 16/07/2025 | B75: 1 - Factura A | C75: 8 | D75: 1832 | F75: 75291689005125 | G75: CUIT | H75: 30708973501 | I75: ASIAL S.R.L. | J75: 1 | K75: $ | L75: 453718 | M75: 0 | N75: 0 | O75: 0 | P75: 95280.78 | Q75: 548998.78
A76: 16/07/2025 | B76: 1 - Factura A | C76: 3 | D76: 6886 | F76: 75299664615823 | G76: CUIT | H76: 30707042679 | I76: MEDICAL FOAM S.R.L. | J76: 1 | K76: $ | L76: 1080000 | M76: 0 | N76: 0 | O76: 0 | P76: 226800 | Q76: 1306800
A77: 16/07/2025 | B77: 11 - Factura C | C77: 1 | D77: 82 | F77: 75294660977647 | G77: CUIT | H77: 23281233084 | I77: DRUETTA ANDREA MARIEL | J77: 1 | K77: $ | O77: 0 | Q77: 300000
A78: 17/07/2025 | B78: 1 - Factura A | C78: 43 | D78: 1186 | F78: 75292764466585 | G78: CUIT | H78: 30516199292 | I78: S V A SACIFI | J78: 1 | K78: $ | L78: 1159191.5 | M78: 0 | N78: 0 | O78: 46367.66 | P78: 243430.22 | Q78: 1448989.4
A79: 17/07/2025 | B79: 1 - Factura A | C79: 2 | D79: 1421 | F79: 75299818959547 | G79: CUIT | H79: 20272865869 | I79: DI FEO MARTIN EZEQUIEL | J79: 1 | K79: $ | L79: 299000 | M79: 0 | N79: 0 | O79: 0 | P79: 62790 | Q79: 361790
A80: 17/07/2025 | B80: 1 - Factura A | C80: 2 | D80: 12406 | F80: 75292799242028 | G80: CUIT | H80: 30714331082 | I80: ORTOPEDIA CASA ESCALADA S.R.L. | J80: 1 | K80: $ | L80: 917813.57 | M80: 0 | N80: 0 | O80: 0 | P80: 96370.42 | Q80: 1014184
A81: 17/07/2025 | B81: 1 - Factura A | C81: 4264 | D81: 5745961 | F81: 75298957750230 | G81: CUIT | H81: 30639453738 | I81: TELECOM ARGENTINA SOCIEDAD ANONIMA | J81: 1 | K81: $ | L81: 48761.16 | M81: 0 | N81: 0 | O81: 3413.28 | P81: 10239.84 | Q81: 62414.28
A82: 17/07/2025 | B82: 1 - Factura A | C82: 4 | D82: 72 | F82: 75296256891743 | G82: CUIT | H82: 20174004146 | I82: NARDOMARINO EDUARDO FRANCISCO | J82: 1 | K82: $ | L82: 224000 | M82: 0 | N82: 0 | O82: 0 | P82: 47040 | Q82: 271040
A83: 18/07/2025 | B83: 1 - Factura A | C83: 4 | D83: 40607 | F83: 75299936001695 | G83: CUIT | H83: 20289111329 | I83: LEDESMA EMILIANO RUBEN | J83: 1 | K83: $ | L83: 520168.01 | M83: 0 | N83: 0 | O83: 0 | P83: 109235.28 | Q83: 629403.29
A84: 18/07/2025 | B84: 1 - Factura A | C84: 15 | D84: 59174 | F84: 75292904479322 | G84: CUIT | H84: 30586185922 | I84: GRUPO CANFEMA S.R.L | J84: 1 | K84: $ | L84: 63341.31 | M84: 0 | N84: 0 | O84: 0 | P84: 13301.68 | Q84: 76642.99
A85: 18/07/2025 | B85: 1 - Factura A | C85: 4 | D85: 7406 | F85: 75292897237030 | G85: CUIT | H85: 20183882512 | I85: MASTROPASQUA CLAUDIO OMAR | J85: 1 | K85: $ | L85: 120000 | M85: 0 | N85: 0 | O85: 0 | P85: 25200 | Q85: 145200
A86: 18/07/2025 | B86: 1 - Factura A | C86: 3 | D86: 9379 | F86: 75299929932405 | G86: CUIT | H86: 33708218699 | I86: MANGGINI PABLO Y MANGGINI ULISES SOC. DE HECHO. | J86: 1 | K86: $ | L86: 30000 | M86: 0 | N86: 0 | O86: 0 | P86: 6300 | Q86: 36300
A87: 18/07/2025 | B87: 1 - Factura A | C87: 5 | D87: 56 | F87: 75293891442678 | G87: CUIT | H87: 20929183143 | I87: MA JUN | J87: 1 | K87: $ | L87: 85000 | M87: 0 | N87: 0 | O87: 0 | P87: 17850 | Q87: 102850
A88: 18/07/2025 | B88: 1 - Factura A | C88: 4 | D88: 73 | F88: 75296257227543 | G88: CUIT | H88: 20174004146 | I88: NARDOMARINO EDUARDO FRANCISCO | J88: 1 | K88: $ | L88: 320000 | M88: 0 | N88: 0 | O88: 0 | P88: 67200 | Q88: 387200
A89: 21/07/2025 | B89: 1 - Factura A | C89: 5 | D89: 3341107 | F89: 75295267128361 | G89: CUIT | H89: 30702652975 | I89: NSS SA | J89: 1 | K89: $ | L89: 35660.75 | M89: 0 | N89: 0 | O89: 1426.43 | P89: 7488.76 | Q89: 44575.94
... A94: 22/07/2025 | B94: 1 - Factura A | C94: 700 | D94: 2588872 | F94: 75302454099142 | G94: CUIT | H94: 30715804812 | I94: CORREDORES VIALES SOCIEDAD ANONIMA | J94: 1 | K94: $ | L94: 831.98 | M94: 0 | N94: 0 | O94: 0 | P94: 174.72 | Q94: 1006.7
A95: 22/07/2025 | B95: 11 - Factura C | C95: 1 | D95: 182 | F95: 75290422075322 | G95: CUIT | H95: 27338342840 | I95: CANCINO PAMELA RITA | J95: 1 | K95: $ | O95: 0 | Q95: 610000
A96: 23/07/2025 | B96: 1 - Factura A | C96: 32 | D96: 166389 | F96: 75307501191061 | G96: CUIT | H96: 30708847247 | I96: EXPRESO LANCIONI S.A. | J96: 1 | K96: $ | L96: 45513.95 | M96: 0 | N96: 0 | O96: 1820.56 | P96: 9557.93 | Q96: 56892.44
