Workbook
Name partner_id: Configuracion!$B$332

Sheet Configuracion
F1: CUIT | G1: Cargar sin guiones
F2: RAZON SOCIAL | G2: Maximo 30 caracteres
A3: CUIT | B3: RAZON SOCIAL | C3: DETALLE | F3: DETALLE | G3: Cargar tipo de gasto
A4: 30628205090 | B4: ALBAMIE SA | C4: CLIENTE
A5: 30711678820 | B5: 2PSI INGENIERIA SRL | C5: PROVEEDOR
A6: 33716367539 | B6: 3PI S.A.S. | C6: PROVEEDOR
A7: 30660373108 | B7: ABC SA | C7: VARIOS
A8: 20300210881 | B8: ABOY DIEGO OSCAR | C8: PROVEEDOR
A9: 27229910782 | B9: ABUGAUCH MARIA DE LOS ANGELES | C9: PROVEEDOR
A10: 20242709897 | B10: ABUGAUCH VICTOR HUGO | C10: PROVEEDOR
A11: 20281669053 | B11: ACOSTA JAVIER GUSTAVO | C11: FLETE
A12: 20174240125 | B12: ACOSTA OSCAR ISIDRO | C12: VARIOS
A13: 30641659106 | B13: AGRISOL SA | C13: VARIOS
A14: 33709914109 | B14: ALAN COLLECTION SA | C14: VARIOS
A15: 20267161616 | B15: ALBAJARI DIEGO MARCOS | C15: VARIOS
... A155: 30537679855 | B155: ESTACION LIMA SA | C155: VARIOS
A156: 30-56864959-8 | B156: EXPRESO BISONTE SRL | C156: FLETE
A157: 30708542349 | B157: EXPRESO FORMOSA SRL | C157: FLETE
A158: 30526582884 | B158: EXPRESO MAR DEL PLATA SA | C158: FLETE
A159: 30577744579 | B159: EXPRESO TROLE SRL | C159: FLETE
A160: 30715949292 | B160: EYPAPEL SAS | C160: GASTOS VARIOS
A161: 30715980807 | B161: FABORT SRL | C161: PROVEEDOR
A162: 20359718765 | B162: FAIL ABRAHAM | C162: VARIOS
A163: 30643518364 | B163: FARMACIA DE MEDRANO SCS | C163: PROVEEDOR
A164: 30692138747 | B164: FARMACITY SA | C164: VARIOS
A165: 33712234429 | B165: FEDAGAS SA | C165: VARIOS
A166: 20353576012 | B166: FEDERICO PABLO FEOLA | C166: VARIOS
A167: 20343766441 | B167: FERNANDEZ MAURO | C167: TALLER
A168: 27062343449 | B168: FERREIRA LILIANA INES | C168: FLETE
... A570: 30661273093 | B570: OSETRA | C570: CLIENTE

Sheet Noviembre 25
A1: ORTOPEDIA GEMINIS S.A. | J1: 45962
A4: LIBRO IVA COMPRAS
A6: FACTURAS A
A7: FECHA | B7: PTO VTA | C7: FAC A | D7: CUIT | E7: RAZON SOCIAL | F7: NETO | G7: IVA 21% | H7: IVA 27% | I7: IVA 10,5% | J7: P IVA | K7: IIBB CF | L7: IIBB BS | M7: NO GRAV | N7: OTROS | O7: TOTAL | P7: DETALLE
E8: =VLOOKUP(D8,Configuracion!$A$4:$C$590,2,FALSE()) -> #N/A | G8: =F8*21% -> 0 | O8: =SUM(F8:N8) -> 0 | P8: =VLOOKUP(D8,Configuracion!$A$4:$C$590,3,FALSE()) -> #N/A
E9: =VLOOKUP(D9,Configuracion!$A$4:$C$590,2,FALSE()) -> #N/A | G9: =F9*21% -> 0 | O9: =SUM(F9:N9) -> 0 | P9: =VLOOKUP(D9,Configuracion!$A$4:$C$590,3,FALSE()) -> #N/A
E10: =VLOOKUP(D10,Configuracion!$A$4:$C$590,2,FALSE()) -> #N/A | G10: =F10*21% -> 0 | O10: =SUM(F10:N10) -> 0 | P10: =VLOOKUP(D10,Configuracion!$A$4:$C$590,3,FALSE()) -> #N/A
E11: =VLOOKUP(D11,Configuracion!$A$4:$C$590,2,FALSE()) -> #N/A | G11: =F11*21% -> 0 | O11: =SUM(F11:N11) -> 0 | P11: =VLOOKUP(D11,Configuracion!$A$4:$C$590,3,FALSE()) -> #N/A
E12: =VLOOKUP(D12,Configuracion!$A$4:$C$590,2,FALSE()) -> #N/A | G12: =F12*21% -> 0 | O12: =SUM(F12:N12) -> 0 | P12: =VLOOKUP(D12,Configuracion!$A$4:$C$590,3,FALSE()) -> #N/A
E13: =VLOOKUP(D13,Configuracion!$A$4:$C$590,2,FALSE()) -> #N/A | G13: =F13*21% -> 0 | O13: =SUM(F13:N13) -> 0 | P13: =VLOOKUP(D13,Configuracion!$A$4:$C$590,3,FALSE()) -> #N/A
E14: =VLOOKUP(D14,Configuracion!$A$4:$C$590,2,FALSE()) -> #N/A | G14: =F14*21% -> 0 | O14: =SUM(F14:N14) -> 0 | P14: =VLOOKUP(D14,Configuracion!$A$4:$C$590,3,FALSE()) -> #N/A
E15: =VLOOKUP(D15,Configuracion!$A$4:$C$590,2,FALSE()) -> #N/A | G15: =F15*21% -> 0 | O15: =SUM(F15:N15) -> 0 | P15: =VLOOKUP(D15,Configuracion!$A$4:$C$590,3,FALSE()) -> #N/A
E16: =VLOOKUP(D16,Configuracion!$A$4:$C$590,2,FALSE()) -> #N/A | G16: =F16*21% -> 0 | O16: =SUM(F16:N16) -> 0 | P16: =VLOOKUP(D16,Configuracion!$A$4:$C$590,3,FALSE()) -> #N/A
E17: =VLOOKUP(D17,Configuracion!$A$4:$C$590,2,FALSE()) -> #N/A | G17: =F17*21% -> 0 | O17: =SUM(F17:N17) -> 0 | P17: =VLOOKUP(D17,Configuracion!$A$4:$C$590,3,FALSE()) -> #N/A
A18: TOTAL | F18: =SUM(F8:F17) -> 0 | G18: =SUM(G8:G17) -> 0 | H18: =SUM(H8:H17) -> 0 | I18: =SUM(I8:I17) -> 0 | J18: =SUM(J8:J17) -> 0 | K18: =SUM(K8:K17) -> 0 | L18: =SUM(L8:L17) -> 0 | M18: =SUM(M8:M17) -> 0 | ... O18: =SUM(O8:O17) -> 0
F19: IVA | G19: =G18+H18+I18 -> 0
A21: FACTURAS B/C
A22: FECHA | B22: PTO VTA | C22: FAC C | D22: CUIT | E22: RAZON SOCIAL | F22: TOTAL | G22: DETALLE
E23: =VLOOKUP(D23,Configuracion!$A$4:$C$590,2,FALSE()) -> #N/A | G23: =VLOOKUP(D23,Configuracion!$A$4:$C$590,3,FALSE()) -> #N/A
E24: =VLOOKUP(D24,Configuracion!$A$4:$C$590,2,FALSE()) -> #N/A | G24: =VLOOKUP(D24,Configuracion!$A$4:$C$590,3,FALSE()) -> #N/A
E25: =VLOOKUP(D25,Configuracion!$A$4:$C$590,2,FALSE()) -> #N/A | G25: =VLOOKUP(D25,Configuracion!$A$4:$C$590,3,FALSE()) -> #N/A
E26: =VLOOKUP(D26,Configuracion!$A$4:$C$590,2,FALSE()) -> #N/A | G26: =VLOOKUP(D26,Configuracion!$A$4:$C$590,3,FALSE()) -> #N/A
E27: =VLOOKUP(D27,Configuracion!$A$4:$C$590,2,FALSE()) -> #N/A | G27: =VLOOKUP(D27,Configuracion!$A$4:$C$590,3,FALSE()) -> #N/A
E28: =VLOOKUP(D28,Configuracion!$A$4:$C$590,2,FALSE()) -> #N/A | G28: =VLOOKUP(D28,Configuracion!$A$4:$C$590,3,FALSE()) -> #N/A
E29: =VLOOKUP(D29,Configuracion!$A$4:$C$590,2,FALSE()) -> #N/A | G29: =VLOOKUP(D29,Configuracion!$A$4:$C$590,3,FALSE()) -> #N/A
E30: =VLOOKUP(D30,Configuracion!$A$4:$C$590,2,FALSE()) -> #N/A | G30: =VLOOKUP(D30,Configuracion!$A$4:$C$590,3,FALSE()) -> #N/A
E31: =VLOOKUP(D31,Configuracion!$A$4:$C$590,2,FALSE()) -> #N/A | G31: =VLOOKUP(D31,Configuracion!$A$4:$C$590,3,FALSE()) -> #N/A
E32: =VLOOKUP(D32,Configuracion!$A$4:$C$590,2,FALSE()) -> #N/A | G32: =VLOOKUP(D32,Configuracion!$A$4:$C$590,3,FALSE()) -> #N/A
E33: =VLOOKUP(D33,Configuracion!$A$4:$C$590,2,FALSE()) -> #N/A | G33: =VLOOKUP(D33,Configuracion!$A$4:$C$590,3,FALSE()) -> #N/A
E34: =VLOOKUP(D34,Configuracion!$A$4:$C$590,2,FALSE()) -> #N/A | G34: =VLOOKUP(D34,Configuracion!$A$4:$C$590,3,FALSE()) -> #N/A
... E41: =VLOOKUP(D41,Configuracion!$A$4:$C$590,2,FALSE()) -> #N/A | G41: =VLOOKUP(D41,Configuracion!$A$4:$C$590,3,FALSE()) -> #N/A
A42: TOTAL | F42: =SUM(F23:F41) -> 0
A44: RETENCIONES
A45: FECHA | B45: COMPROBANTE NRO | D45: CUIT | E45: RAZON SOCIAL | F45: GANANCIAS | G45: IVA | H45: IIBB | I45: SUSS
A46: 45964 | B46: 0000-2025-096416 | D46: 30522428163 | E46: =VLOOKUP(D46,Configuracion!$A$4:$C$590,2,FALSE()) -> GALENO ARGENTINA SA | F46: 258825.79 | G46: 2764710.7 | H46: 13165289 | I46: 131652.89
A47: 45986 | B47: 0000-2025-104354 | D47: 30522428163 | E47: =VLOOKUP(D47,Configuracion!$A$4:$C$590,2,FALSE()) -> GALENO ARGENTINA SA | F47: 597286.55 | G47: 6354868.2 | H47: 298643.41 | I47: 302612.77
A48: 45986 | B48: 0000-2025-104356 | D48: 30522428163 | E48: =VLOOKUP(D48,Configuracion!$A$4:$C$590,2,FALSE()) -> GALENO ARGENTINA SA | F48: 581321.62 | G48: 6159811.9 | H48: 29067301 | I48: 293324.38
A49: 45986 | B49: 0000-2025-104358 | D49: 30522428163 | E49: =VLOOKUP(D49,Configuracion!$A$4:$C$590,2,FALSE()) -> GALENO ARGENTINA SA | F49: 68041.69 | G49: 714563.01 | H49: 34026.81 | I49: 34026.81
A50: 45964 | B50: 0001-2025-00001837 | D50: 30710538014 | E50: =VLOOKUP(D50,Configuracion!$A$4:$C$590,2,FALSE()) -> HC HOMECARE INT DOM SA | F50: 7191.44 | H50: 14935.98
A51: 45964 | B51: 0001-2025-00001837 | D51: 30710538014 | E51: =VLOOKUP(D51,Configuracion!$A$4:$C$590,2,FALSE()) -> HC HOMECARE INT DOM SA | H51: 10668.55
A52: 45974 | B52: 1-11122 | D52: 30608716390 | E52: =VLOOKUP(D52,Configuracion!$A$4:$C$590,2,FALSE()) -> OSTEL | F52: 4493.15
A53: 45981 | B53: 250300005278 | D53: 30999077508 | E53: =VLOOKUP(D53,Configuracion!$A$4:$C$590,2,FALSE()) -> IPROSS | H53: 719325
A54: 45986 | B54: 0001-2025-202795 | D54: 30590354798 | E54: =VLOOKUP(D54,Configuracion!$A$4:$C$590,2,FALSE()) -> ASOCIACION MUTUAL SANCOR SALUD | F54: 43126.03
A55: 45986 | B55: 0001-00145571 | D55: 30590354798 | E55: =VLOOKUP(D55,Configuracion!$A$4:$C$590,2,FALSE()) -> ASOCIACION MUTUAL SANCOR SALUD | H55: 59507.53
A56: 45967 | B56: 0000-2025-099171 | D56: 30522428163 | E56: =VLOOKUP(D56,Configuracion!$A$4:$C$590,2,FALSE()) -> GALENO ARGENTINA SA | F56: 71457.51 | G56: 770646.17 | H56: 35728.76 | I56: 36697.44
A57: 45988 | B57: 0000-2025-105194 | D57: 30522428163 | E57: =VLOOKUP(D57,Configuracion!$A$4:$C$590,2,FALSE()) -> GALENO ARGENTINA SA | F57: 49338.84 | G57: 518057.85 | H57: 24669.42 | I57: 24669.42
A58: 45973 | B58: 0000-2025-177083 | D58: 30500053522 | E58: =VLOOKUP(D58,Configuracion!$A$4:$C$590,2,FALSE()) -> OBRA SOCIAL DE LA ACTIVIDAD DE SEGUROS, REASEGUROS, CAPITALIZACION Y AHORRO Y PRESTAMO PARA LA VIVIENDA | F58: 1139.83 | H58: 2809.92
A59: 45988 | B59: 0001-2025-203275 | D59: 30590354798 | E59: =VLOOKUP(D59,Configuracion!$A$4:$C$590,2,FALSE()) -> ASOCIACION MUTUAL SANCOR SALUD | F59: 2277.85
A60: 45988 | B60: 1001-45722 | D60: 30590354798 | E60: =VLOOKUP(D60,Configuracion!$A$4:$C$590,2,FALSE()) -> ASOCIACION MUTUAL SANCOR SALUD | H60: 2847.31
A61: 45986 | B61: 0001-00026806 | D61: 30712136754 | E61: =VLOOKUP(D61,Configuracion!$A$4:$C$590,2,FALSE()) -> RSC SA | F61: 2389.1 | H61: 12020.92
A62: 45986 | B62: 0001-00026233 | D62: 30606274161 | E62: =VLOOKUP(D62,Configuracion!$A$4:$C$590,2,FALSE()) -> EGESAC SA | F62: 18679.78 | H62: 40529.61
A63: 45987 | B63: 0001-0008311 | D63: 30712529721 | E63: =VLOOKUP(D63,Configuracion!$A$4:$C$590,2,FALSE()) -> SC PILAR SA | H63: 4616.05
E64: =VLOOKUP(D64,Configuracion!$A$4:$C$590,2,FALSE()) -> #N/A
E65: =VLOOKUP(D65,Configuracion!$A$4:$C$590,2,FALSE()) -> #N/A
E66: =VLOOKUP(D66,Configuracion!$A$4:$C$590,2,FALSE()) -> #N/A
E67: =VLOOKUP(D67,Configuracion!$A$4:$C$590,2,FALSE()) -> #N/A
E68: =VLOOKUP(D68,Configuracion!$A$4:$C$590,2,FALSE()) -> #N/A
E69: =VLOOKUP(D69,Configuracion!$A$4:$C$590,2,FALSE()) -> #N/A
E70: =VLOOKUP(D70,Configuracion!$A$4:$C$590,2,FALSE()) -> #N/A
E71: =VLOOKUP(D71,Configuracion!$A$4:$C$590,2,FALSE()) -> #N/A
E72: =VLOOKUP(D72,Configuracion!$A$4:$C$590,2,FALSE()) -> #N/A
E73: =VLOOKUP(D73,Configuracion!$A$4:$C$590,2,FALSE()) -> #N/A
E74: =VLOOKUP(D74,Configuracion!$A$4:$C$590,2,FALSE()) -> #N/A
E75: =VLOOKUP(D75,Configuracion!$A$4:$C$590,2,FALSE()) -> #N/A
... E77: =VLOOKUP(D77,Configuracion!$A$4:$C$590,2,FALSE()) -> #N/A
A78: TOTAL | F78: =SUM(F46:F77) -> 1705569.2 | G78: =SUM(G46:G77) -> 17282658 | H78: =SUM(H46:H77) -> 43492920 | I78: =SUM(I46:I77) -> 822983.71
A82: LIBRO IVA VENTAS
A84: FACTURA A
A85: FECHA | B85: PTO VTA | C85: NRO FC | D85: CUIT | E85: RAZON SOCIAL | F85: NETO | G85: IVA | H85: NO GRAV. | I85: TOTAL
E86: =VLOOKUP(D86,Configuracion!$A$4:$C$590,2,FALSE()) -> #N/A | G86: =F86*0.21 -> 0 | I86: =SUM(F86:H86) -> 0
E87: =VLOOKUP(D87,Configuracion!$A$4:$C$590,2,FALSE()) -> #N/A | G87: =F87*0.21 -> 0 | I87: =SUM(F87:H87) -> 0
E88: =VLOOKUP(D88,Configuracion!$A$4:$C$590,2,FALSE()) -> #N/A | G88: =F88*0.21 -> 0 | I88: =SUM(F88:H88) -> 0
E89: =VLOOKUP(D89,Configuracion!$A$4:$C$590,2,FALSE()) -> #N/A | G89: =F89*0.21 -> 0 | I89: =SUM(F89:H89) -> 0
E90: =VLOOKUP(D90,Configuracion!$A$4:$C$590,2,FALSE()) -> #N/A | G90: =F90*0.21 -> 0 | I90: =SUM(F90:H90) -> 0
E91: =VLOOKUP(D91,Configuracion!$A$4:$C$590,2,FALSE()) -> #N/A | G91: =F91*0.21 -> 0 | I91: =SUM(F91:H91) -> 0
E92: =VLOOKUP(D92,Configuracion!$A$4:$C$590,2,FALSE()) -> #N/A | G92: =F92*0.21 -> 0 | I92: =SUM(F92:H92) -> 0
E93: =VLOOKUP(D93,Configuracion!$A$4:$C$590,2,FALSE()) -> #N/A | G93: =F93*0.21 -> 0 | I93: =SUM(F93:H93) -> 0
E94: =VLOOKUP(D94,Configuracion!$A$4:$C$590,2,FALSE()) -> #N/A | G94: =F94*0.21 -> 0 | I94: =SUM(F94:H94) -> 0
A95: TOTAL | F95: =SUM(F86:F94) -> 0 | G95: =SUM(G86:G94) -> 0 | I95: =SUM(I86:I94) -> 0
A98: FACTURA B
A99: FECHA | B99: PTO VTA | C99: NRO FC | D99: CUIT | E99: RAZON SOCIAL | F99: NETO | G99: IVA | H99: TOTAL
E100: =VLOOKUP(D100,Configuracion!$A$4:$C$590,2,FALSE()) -> #N/A | F100: =H100/1.21 -> 0 | G100: =F100*0.21 -> 0
E101: =VLOOKUP(D101,Configuracion!$A$4:$C$590,2,FALSE()) -> #N/A | F101: =H101/1.21 -> 0 | G101: =F101*0.21 -> 0
E102: =VLOOKUP(D102,Configuracion!$A$4:$C$590,2,FALSE()) -> #N/A | F102: =H102/1.21 -> 0 | G102: =F102*0.21 -> 0
E103: =VLOOKUP(D103,Configuracion!$A$4:$C$590,2,FALSE()) -> #N/A | F103: =H103/1.21 -> 0 | G103: =F103*0.21 -> 0
E104: =VLOOKUP(D104,Configuracion!$A$4:$C$590,2,FALSE()) -> #N/A | F104: =H104/1.21 -> 0 | G104: =F104*0.21 -> 0
A105: TOTAL | F105: =SUM(F100:F104) -> 0 | G105: =SUM(G100:G104) -> 0 | H105: =SUM(H100:H104) -> 0

Sheet Calculo IVA
B1: ORTOPEDIA GEMINIS
A2: Calculo Iva | D2: 45962
B4: VENTAS
B5: Neto | C5: Iva | D5: Total
A6: FAC. "A" | B6: =+'Ventas 11'!D4+'Ventas 11'!D5 -> 29668385 | C6: =+B6*0.21 -> 6230360.8 | D6: =+B6+C6 -> 35898745
A7: FAC. "B" | B7: =+'Ventas 11'!D6+'Ventas 11'!D7+'Ventas 11'!D8 -> 19371243 | C7: =+B7*0.21 -> 4067961 | D7: =+B7+C7 -> 23439204
B8: =SUM(B6:B7) -> 49039627 | C8: =SUM(C6:C7) -> 10298322 | D8: =SUM(D6:D7) -> 59337949
B11: COMPRAS
B12: Neto | C12: IVA | D12: Total
A13: Comprobantes / Extractos | B13: =+'Compras 11'!I148+'Compras 11'!J148+'Compras 11'!K148 -> 36735777 | C13: =+'Compras 11'!N148 -> 7503645.2 | D13: 58925894
B16: =SUM(B13:B15) -> 36735777 | C16: =SUM(C13:C15) -> 7503645.2 | D16: =SUM(D13:D15) -> 58925894
A19: RETENCIONES | B19: N° Cuit | C19: Importe | D19: Nro. Retencion | E19: Fecha
A20: AFIP - No están informadas las retenciones de IVA en el sistema de AFIP
C35: =+'Noviembre 25'!G78 -> 17282658
A37: PERCEPCIONES | B37: N° Cuit | C37: Importe | D37: Nro. Retencion | E37: Fecha
C41: =SUM(C38:C40) -> 0
A43: Total Deducciociones | C43: =+C41+C35 -> 17282658
C46: (Montos en Positivo)
A47: 1er Saldo Tecnico del Período | C47: =+C8-C16 -> 2794676.6
A49: Saldo Tecnico de período Anterior (a favor) | D49: (resta en el total)
A51: Saldo Neto Técnico | C51: =+C47-C49 -> 2794676.6
A55: Saldo L.D. del Período | C55: =+C41+C35 -> 17282658
A57: Saldo L.D. del Período Anterior
A59: Neto S.L.D | C59: =+C55+C57 -> 17282658
A62: I V A | C62: =+C51-C59 -> -14487981
A63: NOTA: Sin Tomar posibles Retenciones que se hayan hecho

Sheet Ventas 11
C2: Totales por Tipo de Comprobante - ARCA
D3: Base | E3: IVA | F3: Otros Imp. | G3: Total Compr.
C4: FACTURAS A | D4: 33129236 | E4: =+D4*0.21 -> 6957139.5 | G4: =SUBTOTAL(9,D4:F4) -> 40086375
C5: NC A | D5: -3460851.2 | E5: =+D5*0.21 -> -726778.74 | G5: =SUBTOTAL(9,D5:F5) -> -4187629.9
C6: FACTURAS B | D6: 27411739 | E6: =+D6*0.21 -> 5756465.1 | G6: =SUBTOTAL(9,D6:F6) -> 33168204
C7: NC B | D7: -8040495.9 | E7: =+D7*0.21 -> -1688504.1 | G7: =SUBTOTAL(9,D7:F7) -> -9729000
C8: ND B | E8: =+D8*0.21 -> 0 | G8: =SUBTOTAL(9,D8:F8) -> 0
D9: =SUBTOTAL(9,D4:D8) -> 49039627 | E9: =SUBTOTAL(9,E4:E8) -> 10298322 | F9: 0 | G9: =+E9+D9 -> 59337949 | H9: =+SUBTOTAL(109,H12:H431) -> 49039628
A11: Fecha | B11: Razon Social | C11: Cuit | D11: Provincia | E11: Ciudad | F11: Condicion IVA | G11: Nro Factura | H11: Importe Neto Gravado | I11: Importe No Grav | J11: IVA2 | K11: IVA5 | L11: IVA10 | M11: IVA21 | N11: IVA27 | O11: IIBB | P11: Percepcion IVA | Q11: Otros Impuestos | R11: Total IVA | S11: Total Facturado | T11: Observaciones
A12: 11/11/2025 | B12: ALEJANDRO AUGUSTO BALDASSARRE LABARRIERE | C12: 23136532979 | D12: Ciudad de Buenos Aires | E12: SIN IDENTIFICAR | F12: RI | G12: FCA 0005-00000188 | H12: 57851.24 | I12: 0 | J12: 0 | K12: 0 | L12: 0 | M12: 12148.76 | N12: 0 | O12: 0 | P12: 0 | Q12: 0 | R12: 12148.76 | S12: 70000
A13: 20/11/2025 | B13: GALENO ARGENTINA SA | C13: 30522428163 | D13: Ciudad de Buenos Aires | E13: SIN IDENTIFICAR | F13: RI | G13: FCA 0006-00000646 | H13: 4395454.5 | I13: 0 | J13: 0 | K13: 0 | L13: 0 | M13: 923045.45 | N13: 0 | O13: 0 | P13: 0 | Q13: 0 | R13: 923045.45 | S13: 5318500
A14: 25/11/2025 | B14: GALENO ARGENTINA SA | C14: 30522428163 | D14: Ciudad de Buenos Aires | E14: SIN IDENTIFICAR | F14: RI | G14: FCA 0006-00000647 | H14: 6012396.7 | I14: 0 | J14: 0 | K14: 0 | L14: 0 | M14: 1262603.3 | N14: 0 | O14: 0 | P14: 0 | Q14: 0 | R14: 1262603.3 | S14: 7275000
A15: 28/11/2025 | B15: GALENO ARGENTINA SA | C15: 30522428163 | D15: Ciudad de Buenos Aires | E15: SIN IDENTIFICAR | F15: RI | G15: FCA 0006-00000648 | H15: 6472562 | I15: 0 | J15: 0 | K15: 0 | L15: 0 | M15: 1359238 | N15: 0 | O15: 0 | P15: 0 | Q15: 0 | R15: 1359238 | S15: 7831800
A16: 01/11/2025 | B16: OBRA SOCIAL UNION PERSONAL DE LA UNION DEL PERSONAL CIVIL DE LA NACION | C16: 30683032227 | D16: Ciudad de Buenos Aires | E16: SIN IDENTIFICAR | F16: RI | G16: FCA 0007-00002768 | H16: 2681410.3 | I16: 0 | J16: 0 | K16: 0 | L16: 0 | M16: 563096.16 | N16: 0 | O16: 0 | P16: 0 | Q16: 0 | R16: 563096.16 | S16: 3244506.5
A17: 06/11/2025 | B17: GERMAN DARIO RAMOS | C17: 20258280416 | D17: Ciudad de Buenos Aires | E17: SIN IDENTIFICAR | F17: RI | G17: FCA 0007-00002769 | H17: 28925.62 | I17: 0 | J17: 0 | K17: 0 | L17: 0 | M17: 6074.38 | N17: 0 | O17: 0 | P17: 0 | Q17: 0 | R17: 6074.38 | S17: 35000
A18: 11/11/2025 | B18: PAULA ANDREA PIAGGIO | C18: 27182477368 | D18: Ciudad de Buenos Aires | E18: SIN IDENTIFICAR | F18: RI | G18: FCA 0007-00002770 | H18: 29752.07 | I18: 0 | J18: 0 | K18: 0 | L18: 0 | M18: 6247.93 | N18: 0 | O18: 0 | P18: 0 | Q18: 0 | R18: 6247.93 | S18: 36000
A19: 11/11/2025 | B19: AMPARO SALUD S.R.L. | C19: 30715186655 | D19: Ciudad de Buenos Aires | E19: SIN IDENTIFICAR | F19: RI | G19: FCA 0007-00002771 | H19: 419890.91 | I19: 0 | J19: 0 | K19: 0 | L19: 0 | M19: 88177.09 | N19: 0 | O19: 0 | P19: 0 | Q19: 0 | R19: 88177.09 | S19: 508068
A20: 11/11/2025 | B20: HC HOMECARE INTERNACION DOMICILIARIA S.A. | C20: 30710538014 | D20: Buenos Aires | E20: VILLA MARTELLI | F20: RI | G20: FCA 0007-00002772 | H20: 443114.05 | I20: 0 | J20: 0 | K20: 0 | L20: 0 | M20: 93053.95 | N20: 0 | O20: 0 | P20: 0 | Q20: 0 | R20: 93053.95 | S20: 536168
A21: 11/11/2025 | B21: PAULA ANDREA PIAGGIO | C21: 27182477368 | D21: Ciudad de Buenos Aires | E21: SIN IDENTIFICAR | F21: RI | G21: FCA 0007-00002773 | H21: 33884.3 | I21: 0 | J21: 0 | K21: 0 | L21: 0 | M21: 7115.7 | N21: 0 | O21: 0 | P21: 0 | Q21: 0 | R21: 7115.7 | S21: 41000
A22: 11/11/2025 | B22: OBRA SOCIAL DEL PERSONAL DE LAS TELECOMUNICACIONES DE LA REPUBLICA ARGENTINA | C22: 30608716390 | D22: Ciudad de Buenos Aires | E22: SIN IDENTIFICAR | F22: RI | G22: FCA 0007-00002774 | H22: 102500 | I22: 0 | J22: 0 | K22: 0 | L22: 0 | M22: 21525 | N22: 0 | O22: 0 | P22: 0 | Q22: 0 | R22: 21525 | S22: 124025
A23: 11/11/2025 | B23: OBRA SOCIAL DEL PERSONAL DE LAS TELECOMUNICACIONES DE LA REPUBLICA ARGENTINA | C23: 30608716390 | D23: Ciudad de Buenos Aires | F23: RI | G23: FCA 0007-00002775 | H23: 20500 | M23: 4305 | R23: 4305 | S23: 24805
A24: 11/11/2025 | B24: OBRA SOCIAL DEL PERSONAL DE LAS TELECOMUNICACIONES DE LA REPUBLICA ARGENTINA | C24: 30608716390 | D24: Ciudad de Buenos Aires | E24: SIN IDENTIFICAR | F24: RI | G24: FCA 0007-00002776 | H24: 20500 | I24: 0 | J24: 0 | K24: 0 | L24: 0 | M24: 4305 | N24: 0 | O24: 0 | P24: 0 | Q24: 0 | R24: 4305 | S24: 24805
A25: 11/11/2025 | B25: OBRA SOCIAL DEL PERSONAL DE LAS TELECOMUNICACIONES DE LA REPUBLICA ARGENTINA | C25: 30608716390 | D25: Ciudad de Buenos Aires | E25: SIN IDENTIFICAR | F25: RI | G25: FCA 0007-00002777 | H25: 147917.36 | I25: 0 | J25: 0 | K25: 0 | L25: 0 | M25: 31062.64 | N25: 0 | O25: 0 | P25: 0 | Q25: 0 | R25: 31062.64 | S25: 178980
A26: 11/11/2025 | B26: OBRA SOCIAL DEL PERSONAL DE LAS TELECOMUNICACIONES DE LA REPUBLICA ARGENTINA | C26: 30608716390 | D26: Ciudad de Buenos Aires | E26: SIN IDENTIFICAR | F26: RI | G26: FCA 0007-00002778 | H26: 102500 | I26: 0 | J26: 0 | K26: 0 | L26: 0 | M26: 21525 | N26: 0 | O26: 0 | P26: 0 | Q26: 0 | R26: 21525 | S26: 124025
A27: 11/11/2025 | B27: OBRA SOCIAL DEL PERSONAL DE LAS TELECOMUNICACIONES DE LA REPUBLICA ARGENTINA | C27: 30608716390 | D27: Ciudad de Buenos Aires | E27: SIN IDENTIFICAR | F27: RI | G27: FCA 0007-00002779 | H27: 59166.94 | I27: 0 | J27: 0 | K27: 0 | L27: 0 | M27: 12425.06 | N27: 0 | O27: 0 | P27: 0 | Q27: 0 | R27: 12425.06 | S27: 71592
A28: 11/11/2025 | B28: OBRA SOCIAL DEL PERSONAL DE LAS TELECOMUNICACIONES DE LA REPUBLICA ARGENTINA | C28: 30608716390 | D28: Ciudad de Buenos Aires | E28: SIN IDENTIFICAR | F28: RI | G28: FCA 0007-00002780 | H28: 41000 | I28: 0 | J28: 0 | K28: 0 | L28: 0 | M28: 8610 | N28: 0 | O28: 0 | P28: 0 | Q28: 0 | R28: 8610 | S28: 49610
A29: 12/11/2025 | B29: OBRA SOCIAL DEL PERSONAL DE LAS TELECOMUNICACIONES DE LA REPUBLICA ARGENTINA | C29: 30608716390 | D29: Ciudad de Buenos Aires | E29: SIN IDENTIFICAR | F29: RI | G29: FCA 0007-00002781 | H29: 137013.22 | I29: 0 | J29: 0 | K29: 0 | L29: 0 | M29: 28772.78 | N29: 0 | O29: 0 | P29: 0 | Q29: 0 | R29: 28772.78 | S29: 165786
A30: 12/11/2025 | B30: OBRA SOCIAL DEL PERSONAL DE LAS TELECOMUNICACIONES DE LA REPUBLICA ARGENTINA | C30: 30608716390 | D30: Ciudad de Buenos Aires | E30: SIN IDENTIFICAR | F30: RI | G30: FCA 0007-00002782 | H30: 123305.79 | I30: 0 | J30: 0 | K30: 0 | L30: 0 | M30: 25894.21 | N30: 0 | O30: 0 | P30: 0 | Q30: 0 | R30: 25894.21 | S30: 149200
A31: 12/11/2025 | B31: OBRA SOCIAL DEL PERSONAL DE LAS TELECOMUNICACIONES DE LA REPUBLICA ARGENTINA | C31: 30608716390 | D31: Ciudad de Buenos Aires | E31: SIN IDENTIFICAR | F31: RI | G31: FCA 0007-00002783 | H31: 87380.17 | I31: 0 | J31: 0 | K31: 0 | L31: 0 | M31: 18349.83 | N31: 0 | O31: 0 | P31: 0 | Q31: 0 | R31: 18349.83 | S31: 105730
A32: 12/11/2025 | B32: OBRA SOCIAL DEL PERSONAL DE LAS TELECOMUNICACIONES DE LA REPUBLICA ARGENTINA | C32: 30608716390 | D32: Ciudad de Buenos Aires | E32: SIN IDENTIFICAR | F32: RI | G32: FCA 0007-00002784 | H32: 41000 | I32: 0 | J32: 0 | K32: 0 | L32: 0 | M32: 8610 | N32: 0 | O32: 0 | P32: 0 | Q32: 0 | R32: 8610 | S32: 49610
A33: 12/11/2025 | B33: OBRA SOCIAL DEL PERSONAL DE LAS TELECOMUNICACIONES DE LA REPUBLICA ARGENTINA | C33: 30608716390 | D33: Ciudad de Buenos Aires | E33: SIN IDENTIFICAR | F33: RI | G33: FCA 0007-00002785 | H33: 41000 | I33: 0 | J33: 0 | K33: 0 | L33: 0 | M33: 8610 | N33: 0 | O33: 0 | P33: 0 | Q33: 0 | R33: 8610 | S33: 49610
A34: 12/11/2025 | B34: OBRA SOCIAL DEL PERSONAL DE LAS TELECOMUNICACIONES DE LA REPUBLICA ARGENTINA | C34: 30608716390 | D34: Ciudad de Buenos Aires | E34: SIN IDENTIFICAR | F34: RI | G34: FCA 0007-00002786 | H34: 41000 | I34: 0 | J34: 0 | K34: 0 | L34: 0 | M34: 8610 | N34: 0 | O34: 0 | P34: 0 | Q34: 0 | R34: 8610 | S34: 49610
A35: 12/11/2025 | B35: OBRA SOCIAL DEL PERSONAL DE LAS TELECOMUNICACIONES DE LA REPUBLICA ARGENTINA | C35: 30608716390 | D35: Ciudad de Buenos Aires | E35: SIN IDENTIFICAR | F35: RI | G35: FCA 0007-00002787 | H35: 41000 | I35: 0 | J35: 0 | K35: 0 | L35: 0 | M35: 8610 | N35: 0 | O35: 0 | P35: 0 | Q35: 0 | R35: 8610 | S35: 49610
... A324: 05/11/2025 | B324: ALVAREZ MARTA OLGA | C324: 9955440 | D324: Buenos Aires | E324: RAMOS MEJIA | F324: CF | G324: FCB 0007-00006542 | H324: 8603.31 | I324: 0 | J324: 0 | K324: 0 | L324: 0 | M324: 1806.69 | N324: 0 | O324: 0 | P324: 0 | Q324: 0 | R324: 1806.69 | S324: 10410
A325: 05/11/2025 | B325: BAUAB, CAROLINA | D325: Buenos Aires | E325: SIN IDENTIFICAR | F325: CF | G325: FCB 0007-00006543 | H325: 58677.69 | I325: 0 | J325: 0 | K325: 0 | L325: 0 | M325: 12322.31 | N325: 0 | O325: 0 | P325: 0 | Q325: 0 | R325: 12322.31 | S325: 71000
A326: 05/11/2025 | B326: SCHELGEL, LUIS ALBERTO | D326: Buenos Aires | E326: SIN IDENTIFICAR | F326: CF | G326: FCB 0007-00006544 | H326: 39669.42 | I326: 0 | J326: 0 | K326: 0 | L326: 0 | M326: 8330.58 | N326: 0 | O326: 0 | P326: 0 | Q326: 0 | R326: 8330.58 | S326: 48000
A327: 05/11/2025 | B327: SILVIA MONICA ROJAS | C327: 27141958807 | D327: Ciudad de Buenos Aires | E327: BALVANERA | F327: CF | G327: FCB 0007-00006545 | H327: 36363.64 | I327: 0 | J327: 0 | K327: 0 | L327: 0 | M327: 7636.36 | N327: 0 | O327: 0 | P327: 0 | Q327: 0 | R327: 7636.36 | S327: 44000
A328: 05/11/2025 | B328: AGOSTINO MIRIAM | C328: 17275405 | D328: Buenos Aires | E328: SIN IDENTIFICAR | F328: CF | G328: FCB 0007-00006546 | H328: 52066.12 | I328: 0 | J328: 0 | K328: 0 | L328: 0 | M328: 10933.88 | N328: 0 | O328: 0 | P328: 0 | Q328: 0 | R328: 10933.88 | S328: 63000
A329: 05/11/2025 | B329: CONEN SILVIA ADELA | C329: 334529 | D329: Ciudad de Buenos Aires | E329: SIN IDENTIFICAR | F329: CF | G329: FCB 0007-00006547 | H329: 37190.08 | I329: 0 | J329: 0 | K329: 0 | L329: 0 | M329: 7809.92 | N329: 0 | O329: 0 | P329: 0 | Q329: 0 | R329: 7809.92 | S329: 45000
A330: 05/11/2025 | B330: CECILIA DEL PILAR TELLO MARTEL | C330: 27951120370 | D330: Ciudad de Buenos Aires | E330: SIN IDENTIFICAR | F330: CF | G330: FCB 0007-00006548 | H330: 28925.62 | I330: 0 | J330: 0 | K330: 0 | L330: 0 | M330: 6074.38 | N330: 0 | O330: 0 | P330: 0 | Q330: 0 | R330: 6074.38 | S330: 35000
A331: 05/11/2025 | B331: BENEIT MORA YAZMIN | C331: 27460270915 | D331: Ciudad de Buenos Aires | E331: SIN IDENTIFICAR | F331: CF | G331: FCB 0007-00006549 | H331: 28925.62 | I331: 0 | J331: 0 | K331: 0 | L331: 0 | M331: 6074.38 | N331: 0 | O331: 0 | P331: 0 | Q331: 0 | R331: 6074.38 | S331: 35000
A332: 05/11/2025 | B332: GIGAGLIA, MARIA LUCILA | C332: 25315045 | D332: Buenos Aires | E332: BECCAR | F332: CF | G332: FCB 0007-00006550 | H332: 18181.82 | I332: 0 | J332: 0 | K332: 0 | L332: 0 | M332: 3818.18 | N332: 0 | O332: 0 | P332: 0 | Q332: 0 | R332: 3818.18 | S332: 22000
A333: 05/11/2025 | B333: MAIZTEGUI ANDRÉS | C333: 20002428 | D333: Ciudad de Buenos Aires | E333: RECOLETA | F333: CF | G333: FCB 0007-00006551 | H333: 23140.5 | I333: 0 | J333: 0 | K333: 0 | L333: 0 | M333: 4859.5 | N333: 0 | O333: 0 | P333: 0 | Q333: 0 | R333: 4859.5 | S333: 28000
A334: 05/11/2025 | B334: DAVID GUILLERMO GERARDUZZI | C334: 20249957322 | D334: Santa Fe | E334: SANTA FE | F334: CF | G334: FCB 0007-00006552 | H334: 21487.6 | I334: 0 | J334: 0 | K334: 0 | L334: 0 | M334: 4512.4 | N334: 0 | O334: 0 | P334: 0 | Q334: 0 | R334: 4512.4 | S334: 26000
A335: 05/11/2025 | B335: BIANCHI TERESA GERMANA | C335: 2719694 | D335: Buenos Aires | E335: RAMOS MEJIA | F335: CF | G335: FCB 0007-00006553 | H335: 8177.69 | I335: 0 | J335: 0 | K335: 0 | L335: 0 | M335: 1717.31 | N335: 0 | O335: 0 | P335: 0 | Q335: 0 | R335: 1717.31 | S335: 9895
A336: 05/11/2025 | B336: EDUARDO PENJASOFF | C336: 20043010973 | D336: Ciudad de Buenos Aires | E336: SIN IDENTIFICAR | F336: CF | G336: FCB 0007-00006554 | H336: 17355.37 | I336: 0 | J336: 0 | K336: 0 | L336: 0 | M336: 3644.63 | N336: 0 | O336: 0 | P336: 0 | Q336: 0 | R336: 3644.63 | S336: 21000
A337: 05/11/2025 | B337: SCHELGEL, LUIS ALBERTO | D337: Buenos Aires | E337: SIN IDENTIFICAR | F337: CF | G337: FCB 0007-00006555 | H337: 37190.08 | I337: 0 | J337: 0 | K337: 0 | L337: 0 | M337: 7809.92 | N337: 0 | O337: 0 | P337: 0 | Q337: 0 | R337: 7809.92 | S337: 45000
A338: 05/11/2025 | B338: SOSA MARIA GRACIELA | C338: 2551284 | D338: Buenos Aires | E338: GENERAL RODRIGUEZ | F338: CF | G338: FCB 0007-00006556 | H338: 8603.31 | I338: 0 | J338: 0 | K338: 0 | L338: 0 | M338: 1806.69 | N338: 0 | O338: 0 | P338: 0 | Q338: 0 | R338: 1806.69 | S338: 10410
A339: 05/11/2025 | B339: YOANA ELIZABETH CARDENAS | C339: 27340248231 | D339: Ciudad de Buenos Aires | E339: SIN IDENTIFICAR | F339: CF | G339: FCB 0007-00006557 | H339: 79338.84 | I339: 0 | J339: 0 | K339: 0 | L339: 0 | M339: 16661.16 | N339: 0 | O339: 0 | P339: 0 | Q339: 0 | R339: 16661.16 | S339: 96000
A340: 05/11/2025 | B340: CLAVIJO ROQUE | C340: 94433546 | D340: Ciudad de Buenos Aires | E340: SIN IDENTIFICAR | F340: CF | G340: FCB 0007-00006558 | H340: 37190.08 | I340: 0 | J340: 0 | K340: 0 | L340: 0 | M340: 7809.92 | N340: 0 | O340: 0 | P340: 0 | Q340: 0 | R340: 7809.92 | S340: 45000
A341: 05/11/2025 | B341: CHINA NORMA NANCY | C341: 21584499 | D341: Ciudad de Buenos Aires | E341: SIN IDENTIFICAR | F341: CF | G341: FCB 0007-00006559 | H341: 61983.47 | I341: 0 | J341: 0 | K341: 0 | L341: 0 | M341: 13016.53 | N341: 0 | O341: 0 | P341: 0 | Q341: 0 | R341: 13016.53 | S341: 75000
A342: 05/11/2025 | B342: AYELEN LUCIA ROLDAN | C342: 27337476398 | D342: Ciudad de Buenos Aires | E342: SIN IDENTIFICAR | F342: CF | G342: FCB 0007-00006560 | H342: 21487.6 | I342: 0 | J342: 0 | K342: 0 | L342: 0 | M342: 4512.4 | N342: 0 | O342: 0 | P342: 0 | Q342: 0 | R342: 4512.4 | S342: 26000
A343: 05/11/2025 | B343: ROMERO ADRIANA DEL CARMEN | C343: 27244220709 | D343: Ciudad de Buenos Aires | E343: SIN IDENTIFICAR | F343: CF | G343: FCB 0007-00006561 | H343: 28925.62 | I343: 0 | J343: 0 | K343: 0 | L343: 0 | M343: 6074.38 | N343: 0 | O343: 0 | P343: 0 | Q343: 0 | R343: 6074.38 | S343: 35000
A344: 05/11/2025 | B344: MARCELO ALEJANDRO ESCALANTE | C344: 20186499019 | D344: Ciudad de Buenos Aires | E344: SIN IDENTIFICAR | F344: CF | G344: FCB 0007-00006562 | H344: 28925.62 | I344: 0 | J344: 0 | K344: 0 | L344: 0 | M344: 6074.38 | N344: 0 | O344: 0 | P344: 0 | Q344: 0 | R344: 6074.38 | S344: 35000
A345: 06/11/2025 | B345: SANTA CRUZ ELISA | C345: 16145627 | D345: Buenos Aires | E345: BANFIELD | F345: CF | G345: FCB 0007-00006563 | H345: 12396.69 | I345: 0 | J345: 0 | K345: 0 | L345: 0 | M345: 2603.31 | N345: 0 | O345: 0 | P345: 0 | Q345: 0 | R345: 2603.31 | S345: 15000
A346: 06/11/2025 | B346: CORIGLIANO, LORENA ELISA | C346: 25864351 | D346: Buenos Aires | E346: SARANDI | F346: CF | G346: FCB 0007-00006564 | H346: 39669.42 | I346: 0 | J346: 0 | K346: 0 | L346: 0 | M346: 8330.58 | N346: 0 | O346: 0 | P346: 0 | Q346: 0 | R346: 8330.58 | S346: 48000
A347: 06/11/2025 | B347: GONZALEZ NATALIA JUDITH | C347: 23767069 | D347: Ciudad de Buenos Aires | E347: RETIRO | F347: CF | G347: FCB 0007-00006565 | H347: 14876.03 | I347: 0 | J347: 0 | K347: 0 | L347: 0 | M347: 3123.97 | N347: 0 | O347: 0 | P347: 0 | Q347: 0 | R347: 3123.97 | S347: 18000
A348: 06/11/2025 | B348: BALDANTONI JORGE RUBEN | C348: 17486158 | D348: Ciudad de Buenos Aires | E348: SIN IDENTIFICAR | F348: CF | G348: FCB 0007-00006566 | H348: 28925.62 | I348: 0 | J348: 0 | K348: 0 | L348: 0 | M348: 6074.38 | N348: 0 | O348: 0 | P348: 0 | Q348: 0 | R348: 6074.38 | S348: 35000
A349: 06/11/2025 | B349: MARCELLI DE SACRISTAN ELBA JOSEFINA | C349: 0533257 | D349: Ciudad de Buenos Aires | E349: FLORESTA | F349: CF | G349: FCB 0007-00006567 | H349: 9595.04 | I349: 0 | J349: 0 | K349: 0 | L349: 0 | M349: 2014.96 | N349: 0 | O349: 0 | P349: 0 | Q349: 0 | R349: 2014.96 | S349: 11610
... A353: 07/11/2025 | B353: FIORE MARIA ROSA | C353: 20127926116 | D353: Ciudad de Buenos Aires | E353: SIN IDENTIFICAR | F353: CF | G353: FCB 0007-00006571 | H353: 28925.62 | I353: 0 | J353: 0 | K353: 0 | L353: 0 | M353: 6074.38 | N353: 0 | O353: 0 | P353: 0 | Q353: 0 | R353: 6074.38 | S353: 35000
A354: 07/11/2025 | B354: DANELLI, RAQUEL | D354: Buenos Aires | E354: ITUZAINGO | F354: CF | G354: FCB 0007-00006572 | H354: 28925.62 | I354: 0 | J354: 0 | K354: 0 | L354: 0 | M354: 6074.38 | N354: 0 | O354: 0 | P354: 0 | Q354: 0 | R354: 6074.38 | S354: 35000
A355: 07/11/2025 | B355: ENRIQUE LUIS SAGGESE | C355: 4186965 | D355: Buenos Aires | E355: SIN IDENTIFICAR | F355: CF | G355: FCB 0007-00006573 | H355: 99173.55 | I355: 0 | J355: 0 | K355: 0 | L355: 0 | M355: 20826.45 | N355: 0 | O355: 0 | P355: 0 | Q355: 0 | R355: 20826.45 | S355: 120000
A356: 10/11/2025 | B356: VALENTINA DEL BARRIO | C356: 27473795790 | D356: Ciudad de Buenos Aires | E356: SIN IDENTIFICAR | F356: CF | G356: FCB 0007-00006574 | H356: 21487.6 | I356: 0 | J356: 0 | K356: 0 | L356: 0 | M356: 4512.4 | N356: 0 | O356: 0 | P356: 0 | Q356: 0 | R356: 4512.4 | S356: 26000
A357: 10/11/2025 | B357: SCHELGEL, LUIS ALBERTO | D357: Buenos Aires | E357: SIN IDENTIFICAR | F357: CF | G357: FCB 0007-00006575 | H357: 17355.37 | I357: 0 | J357: 0 | K357: 0 | L357: 0 | M357: 3644.63 | N357: 0 | O357: 0 | P357: 0 | Q357: 0 | R357: 3644.63 | S357: 21000
A358: 10/11/2025 | B358: PINO, ANA PAULA | C358: 20008996 | D358: Buenos Aires | E358: FLORIDA | F358: CF | G358: FCB 0007-00006576 | H358: 28099.17 | I358: 0 | J358: 0 | K358: 0 | L358: 0 | M358: 5900.83 | N358: 0 | O358: 0 | P358: 0 | Q358: 0 | R358: 5900.83 | S358: 34000
A359: 10/11/2025 | B359: SILVINA ALEJANDRA PEZZANO DE LUCA | C359: 27205676800 | D359: Ciudad de Buenos Aires | E359: SIN IDENTIFICAR | F359: CF | G359: FCB 0007-00006577 | H359: 28925.62 | I359: 0 | J359: 0 | K359: 0 | L359: 0 | M359: 6074.38 | N359: 0 | O359: 0 | P359: 0 | Q359: 0 | R359: 6074.38 | S359: 35000
A360: 10/11/2025 | B360: DORFMAN SANDRA | D360: Ciudad de Buenos Aires | E360: SIN IDENTIFICAR | F360: CF | G360: FCB 0007-00006578 | H360: 61983.47 | I360: 0 | J360: 0 | K360: 0 | L360: 0 | M360: 13016.53 | N360: 0 | O360: 0 | P360: 0 | Q360: 0 | R360: 13016.53 | S360: 75000
A361: 10/11/2025 | B361: ERICK SAMIR FERNANDEZ RODRIGUEZ | C361: 20940555516 | D361: Ciudad de Buenos Aires | E361: SIN IDENTIFICAR | F361: CF | G361: FCB 0007-00006579 | H361: 18181.82 | I361: 0 | J361: 0 | K361: 0 | L361: 0 | M361: 3818.18 | N361: 0 | O361: 0 | P361: 0 | Q361: 0 | R361: 3818.18 | S361: 22000
A362: 10/11/2025 | B362: SOSA MARIA GRACIELA | C362: 2551284 | D362: Buenos Aires | E362: GENERAL RODRIGUEZ | F362: CF | G362: FCB 0007-00006580 | H362: 8603.31 | I362: 0 | J362: 0 | K362: 0 | L362: 0 | M362: 1806.69 | N362: 0 | O362: 0 | P362: 0 | Q362: 0 | R362: 1806.69 | S362: 10410
A363: 10/11/2025 | B363: ENRIQUE LUIS SAGGESE | C363: 4186965 | D363: Buenos Aires | E363: SIN IDENTIFICAR | F363: CF | G363: FCB 0007-00006581 | H363: 99173.55 | I363: 0 | J363: 0 | K363: 0 | L363: 0 | M363: 20826.45 | N363: 0 | O363: 0 | P363: 0 | Q363: 0 | R363: 20826.45 | S363: 120000
A364: 10/11/2025 | B364: DESALVO MIGUEL ANGEL | C364: 24448662 | D364: Buenos Aires | E364: RAMOS MEJIA | F364: CF | G364: FCB 0007-00006582 | H364: 24793.39 | I364: 0 | J364: 0 | K364: 0 | L364: 0 | M364: 5206.61 | N364: 0 | O364: 0 | P364: 0 | Q364: 0 | R364: 5206.61 | S364: 30000
A365: 10/11/2025 | B365: GABRIELA VANINA GALLO | C365: 26542077 | D365: Buenos Aires | E365: SIN IDENTIFICAR | F365: CF | G365: FCB 0007-00006583 | H365: 35537.19 | I365: 0 | J365: 0 | K365: 0 | L365: 0 | M365: 7462.81 | N365: 0 | O365: 0 | P365: 0 | Q365: 0 | R365: 7462.81 | S365: 43000
A366: 10/11/2025 | B366: ARANA, MARCELLA OFELIA | C366: 10138957 | D366: Ciudad de Buenos Aires | E366: SIN IDENTIFICAR | F366: CF | G366: FCB 0007-00006584 | H366: 20661.16 | I366: 0 | J366: 0 | K366: 0 | L366: 0 | M366: 4338.84 | N366: 0 | O366: 0 | P366: 0 | Q366: 0 | R366: 4338.84 | S366: 25000
A367: 10/11/2025 | B367: MINERVINI, MARIA DEL CARMEN LILIANA | C367: 12791306 | D367: Buenos Aires | E367: SIN IDENTIFICAR | F367: CF | G367: FCB 0007-00006585 | H367: 33057.85 | I367: 0 | J367: 0 | K367: 0 | L367: 0 | M367: 6942.15 | N367: 0 | O367: 0 | P367: 0 | Q367: 0 | R367: 6942.15 | S367: 40000
A368: 10/11/2025 | B368: MONTI, MARIA PAULA | C368: 24699538 | D368: Buenos Aires | E368: MAR DEL PLATA | F368: CF | G368: FCB 0007-00006586 | H368: 33057.85 | I368: 0 | J368: 0 | K368: 0 | L368: 0 | M368: 6942.15 | N368: 0 | O368: 0 | P368: 0 | Q368: 0 | R368: 6942.15 | S368: 40000
A369: 11/11/2025 | B369: ALCIDES BENITO CASELLA | C369: 20041052415 | D369: Ciudad de Buenos Aires | E369: SIN IDENTIFICAR | F369: CF | G369: FCB 0007-00006587 | H369: 18181.82 | I369: 0 | J369: 0 | K369: 0 | L369: 0 | M369: 3818.18 | N369: 0 | O369: 0 | P369: 0 | Q369: 0 | R369: 3818.18 | S369: 22000
A370: 11/11/2025 | B370: OBRA SOCIAL DE LOS TRABAJADORES DE LA INDUSTRIA DEL GAS | C370: 30658137642 | D370: Ciudad de Buenos Aires | E370: SIN IDENTIFICAR | F370: EX | G370: FCB 0007-00006588 | H370: 701428.84 | I370: 0 | J370: 0 | K370: 0 | L370: 0 | M370: 147300.06 | N370: 0 | O370: 0 | P370: 0 | Q370: 0 | R370: 147300.06 | S370: 848728.9
A371: 11/11/2025 | B371: Obra Social Del Personal De La Industria Del Plastico | C371: 30571766287 | D371: Ciudad de Buenos Aires | E371: SIN IDENTIFICAR | F371: EX | G371: FCB 0007-00006589 | H371: 159126.45 | I371: 0 | J371: 0 | K371: 0 | L371: 0 | M371: 33416.55 | N371: 0 | O371: 0 | P371: 0 | Q371: 0 | R371: 33416.55 | S371: 192543
A372: 11/11/2025 | B372: OBRA SOCIAL DE LOS TRABAJADORES DE LA INDUSTRIA DEL GAS | C372: 30658137642 | D372: Ciudad de Buenos Aires | E372: SIN IDENTIFICAR | F372: EX | G372: FCB 0007-00006590 | H372: 81571.9 | I372: 0 | J372: 0 | K372: 0 | L372: 0 | M372: 17130.1 | N372: 0 | O372: 0 | P372: 0 | Q372: 0 | R372: 17130.1 | S372: 98702
... A390: 18/11/2025 | B390: EDUARDO PENJASOFF | C390: 20043010973 | D390: Ciudad de Buenos Aires | E390: SIN IDENTIFICAR | F390: CF | G390: FCB 0007-00006608 | H390: 17355.37 | I390: 0 | J390: 0 | K390: 0 | L390: 0 | M390: 3644.63 | N390: 0 | O390: 0 | P390: 0 | Q390: 0 | R390: 3644.63 | S390: 21000
A391: 18/11/2025 | B391: SCHELGEL, LUIS ALBERTO | D391: Buenos Aires | E391: SIN IDENTIFICAR | F391: CF | G391: FCB 0007-00006609 | H391: 37190.08 | I391: 0 | J391: 0 | K391: 0 | L391: 0 | M391: 7809.92 | N391: 0 | O391: 0 | P391: 0 | Q391: 0 | R391: 7809.92 | S391: 45000
A392: 18/11/2025 | B392: CHINA NORMA NANCY | C392: 21584499 | D392: Ciudad de Buenos Aires | E392: SIN IDENTIFICAR | F392: CF | G392: FCB 0007-00006610 | H392: 61983.47 | I392: 0 | J392: 0 | K392: 0 | L392: 0 | M392: 13016.53 | N392: 0 | O392: 0 | P392: 0 | Q392: 0 | R392: 13016.53 | S392: 75000
A393: 18/11/2025 | B393: CLAVIJO ROQUE | C393: 94433546 | D393: Ciudad de Buenos Aires | E393: SIN IDENTIFICAR | F393: CF | G393: FCB 0007-00006611 | H393: 37190.08 | I393: 0 | J393: 0 | K393: 0 | L393: 0 | M393: 7809.92 | N393: 0 | O393: 0 | P393: 0 | Q393: 0 | R393: 7809.92 | S393: 45000
A394: 19/11/2025 | B394: INSTITUTO PROVINCIAL DEL SEGURO DE SALUD I PRO S S | C394: 30999077508 | D394: Rio Negro | E394: VIEDMA | F394: EX | G394: FCB 0007-00006612 | H394: 11889669 | I394: 0 | J394: 0 | K394: 0 | L394: 0 | M394: 2496830.6 | N394: 0 | O394: 0 | P394: 0 | Q394: 0 | R394: 2496830.6 | S394: 14386500
A395: 19/11/2025 | B395: OBRA SOCIAL DEL PERSONAL DEL ORGANISMO DE CONTROL EXTERNO | C395: 30657314974 | D395: Ciudad de Buenos Aires | E395: SIN IDENTIFICAR | F395: EX | G395: FCB 0007-00006613 | H395: 1900826.4 | I395: 0 | J395: 0 | K395: 0 | L395: 0 | M395: 399173.55 | N395: 0 | O395: 0 | P395: 0 | Q395: 0 | R395: 399173.55 | S395: 2300000
A396: 20/11/2025 | B396: Galeno A.R.T. S.A. | C396: 30685228501 | D396: Ciudad de Buenos Aires | E396: SIN IDENTIFICAR | F396: EX | G396: FCB 0007-00006614 | H396: 76033.06 | I396: 0 | J396: 0 | K396: 0 | L396: 0 | M396: 15966.94 | N396: 0 | O396: 0 | P396: 0 | Q396: 0 | R396: 15966.94 | S396: 92000
A397: 20/11/2025 | B397: JULIO CESAR ALDREY | C397: 20045476333 | D397: Ciudad de Buenos Aires | E397: SIN IDENTIFICAR | F397: CF | G397: FCB 0007-00006615 | H397: 18181.82 | I397: 0 | J397: 0 | K397: 0 | L397: 0 | M397: 3818.18 | N397: 0 | O397: 0 | P397: 0 | Q397: 0 | R397: 3818.18 | S397: 22000
A398: 20/11/2025 | B398: CALLE SEGUNDO MARIA DEL CARMEN | C398: 27941648989 | D398: Ciudad de Buenos Aires | E398: SIN IDENTIFICAR | F398: CF | G398: FCB 0007-00006616 | H398: 21487.6 | I398: 0 | J398: 0 | K398: 0 | L398: 0 | M398: 4512.4 | N398: 0 | O398: 0 | P398: 0 | Q398: 0 | R398: 4512.4 | S398: 26000
A399: 20/11/2025 | B399: SALLES ANA MARIA | C399: 17814995 | D399: Ciudad de Buenos Aires | E399: SIN IDENTIFICAR | F399: CF | G399: FCB 0007-00006617 | H399: 24793.39 | I399: 0 | J399: 0 | K399: 0 | L399: 0 | M399: 5206.61 | N399: 0 | O399: 0 | P399: 0 | Q399: 0 | R399: 5206.61 | S399: 30000
A400: 20/11/2025 | B400: MONTI, MARIA PAULA | C400: 24699538 | D400: Buenos Aires | E400: MAR DEL PLATA | F400: CF | G400: FCB 0007-00006618 | H400: 33057.85 | I400: 0 | J400: 0 | K400: 0 | L400: 0 | M400: 6942.15 | N400: 0 | O400: 0 | P400: 0 | Q400: 0 | R400: 6942.15 | S400: 40000
A401: 20/11/2025 | B401: ARANA, MARCELLA OFELIA | C401: 10138957 | D401: Ciudad de Buenos Aires | E401: SIN IDENTIFICAR | F401: CF | G401: FCB 0007-00006619 | H401: 20661.16 | I401: 0 | J401: 0 | K401: 0 | L401: 0 | M401: 4338.84 | N401: 0 | O401: 0 | P401: 0 | Q401: 0 | R401: 4338.84 | S401: 25000
A402: 20/11/2025 | B402: NAJUS ANIBAL RUBEN | D402: Buenos Aires | E402: SIN IDENTIFICAR | F402: CF | G402: FCB 0007-00006620 | H402: 21487.6 | I402: 0 | J402: 0 | K402: 0 | L402: 0 | M402: 4512.4 | N402: 0 | O402: 0 | P402: 0 | Q402: 0 | R402: 4512.4 | S402: 26000
A403: 20/11/2025 | B403: MINERVINI, MARIA DEL CARMEN LILIANA | C403: 12791306 | D403: Buenos Aires | E403: SIN IDENTIFICAR | F403: CF | G403: FCB 0007-00006621 | H403: 33057.85 | I403: 0 | J403: 0 | K403: 0 | L403: 0 | M403: 6942.15 | N403: 0 | O403: 0 | P403: 0 | Q403: 0 | R403: 6942.15 | S403: 40000
A404: 20/11/2025 | B404: GABRIELA TERESA FOLGUEIRAS | C404: 27167647419 | D404: Ciudad de Buenos Aires | E404: SIN IDENTIFICAR | F404: CF | G404: FCB 0007-00006622 | H404: 20661.16 | I404: 0 | J404: 0 | K404: 0 | L404: 0 | M404: 4338.84 | N404: 0 | O404: 0 | P404: 0 | Q404: 0 | R404: 4338.84 | S404: 25000
A405: 25/11/2025 | B405: GONZALEZ NATALIA JUDITH | C405: 23767069 | D405: Ciudad de Buenos Aires | E405: RETIRO | F405: CF | G405: FCB 0007-00006623 | H405: 14876.03 | I405: 0 | J405: 0 | K405: 0 | L405: 0 | M405: 3123.97 | N405: 0 | O405: 0 | P405: 0 | Q405: 0 | R405: 3123.97 | S405: 18000
A406: 25/11/2025 | B406: BALDANTONI JORGE RUBEN | C406: 17486158 | D406: Ciudad de Buenos Aires | E406: SIN IDENTIFICAR | F406: CF | G406: FCB 0007-00006624 | H406: 28925.62 | I406: 0 | J406: 0 | K406: 0 | L406: 0 | M406: 6074.38 | N406: 0 | O406: 0 | P406: 0 | Q406: 0 | R406: 6074.38 | S406: 35000
A407: 25/11/2025 | B407: MARCELLI DE SACRISTAN ELBA JOSEFINA | C407: 0533257 | D407: Ciudad de Buenos Aires | E407: FLORESTA | F407: CF | G407: FCB 0007-00006625 | H407: 9595.04 | I407: 0 | J407: 0 | K407: 0 | L407: 0 | M407: 2014.96 | N407: 0 | O407: 0 | P407: 0 | Q407: 0 | R407: 2014.96 | S407: 11610
A408: 25/11/2025 | B408: CONSTANZO DE DEL CASTILLO NORMA | C408: 026282 | D408: Ciudad de Buenos Aires | E408: FLORESTA | F408: CF | G408: FCB 0007-00006626 | H408: 8177.69 | I408: 0 | J408: 0 | K408: 0 | L408: 0 | M408: 1717.31 | N408: 0 | O408: 0 | P408: 0 | Q408: 0 | R408: 1717.31 | S408: 9895
A409: 25/11/2025 | B409: CARLOS GABRIEL CANEPA | C409: 20183944356 | D409: Ciudad de Buenos Aires | E409: SIN IDENTIFICAR | F409: CF | G409: FCB 0007-00006627 | H409: 58677.69 | I409: 0 | J409: 0 | K409: 0 | L409: 0 | M409: 12322.31 | N409: 0 | O409: 0 | P409: 0 | Q409: 0 | R409: 12322.31 | S409: 71000
A410: 25/11/2025 | B410: PABLO ROBERTO LAFARGUE | C410: 20124382867 | D410: Ciudad de Buenos Aires | E410: SIN IDENTIFICAR | F410: CF | G410: FCB 0007-00006628 | H410: 28925.62 | I410: 0 | J410: 0 | K410: 0 | L410: 0 | M410: 6074.38 | N410: 0 | O410: 0 | P410: 0 | Q410: 0 | R410: 6074.38 | S410: 35000
...

Sheet Compras 11
A1: Fecha Emision | B1: Fecha Contable | C1: Nro Factura | D1: Razon Social | E1: Cuit | F1: Condicion Iva | G1: Monto Gravado Iva 2 | H1: Monto Gravado Iva 5 | I1: Monto Gravado Iva 10,5 | J1: Monto Gravado Iva 21 | K1: Monto Gravado Iva 27 | L1: Monto No Gravado Y Exentos | M1: Monto Gravado Monotributistas | N1: Iva Facturado | O1: Imp Interno | P1: Imp Municipal | Q1: Imp Nacional | R1: Otros | S1: Percepcion IVA | T1: IIBB | U1: Total Facturado | V1: Rubro | W1: Cod Fa | X1: COMPR.
A2: 19/11/2025 | B2: 19/11/2025 | C2: FCA 00001-00009484 | D2: REHAB SRL | E2: 30715141201 | F2: RI | G2: 0 | H2: 0 | I2: 0 | J2: 300318.75 | K2: 0 | L2: 0 | M2: 0 | N2: 63066.94 | O2: 0 | P2: 0 | Q2: 0 | R2: 0 | S2: 0 | T2: 0 | U2: =SUM(G2:T2) -> 363385.69 | V2: Bienes | W2: Buenos Aires
A3: 01/11/2025 | B3: 01/11/2025 | C3: FCA 00001-00143079 | D3: CONTABILIUM SA | E3: 30714864269 | F3: RI | G3: 0 | H3: 0 | I3: 0 | J3: 184800 | K3: 0 | L3: 0 | M3: 0 | N3: 38808 | O3: 0 | P3: 0 | Q3: 0 | R3: 0 | S3: 0 | T3: 0 | U3: =SUM(G3:T3) -> 223608 | V3: Servicios | W3: Ciudad de Buenos Aires
A4: 03/11/2025 | B4: 03/11/2025 | C4: FCA 00001-01071638 | D4: VERISURE ARGENTINA MONITOREO DE ALARMAS SA | E4: 33716307749 | F4: RI | G4: 0 | H4: 0 | I4: 0 | J4: 62349.01 | K4: 0 | L4: 0 | M4: 0 | N4: 13093.29 | O4: 0 | P4: 0 | Q4: 0 | R4: 2493.96 | S4: 0 | T4: 0 | U4: =SUM(G4:T4) -> 77936.26 | V4: Servicios | W4: Ciudad de Buenos Aires | X4: Sin comprobante
A5: 27/11/2025 | B5: 27/11/2025 | C5: FCA 00002-00000053 | D5: BARD MARISA SILVIA | E5: 27243660535 | F5: RI | G5: 0 | H5: 0 | I5: 0 | J5: 489161.16 | K5: 0 | L5: 0 | M5: 0 | N5: 102723.84 | O5: 0 | P5: 0 | Q5: 0 | R5: 0 | S5: 0 | T5: 0 | U5: =SUM(G5:T5) -> 591885 | V5: Locaciones | W5: Buenos Aires
A6: 03/11/2025 | B6: 03/11/2025 | C6: FCA 00002-00000254 | D6: CONSORCIO BARTOLME MITRE 2466 | E6: 30605344352 | F6: RI | G6: 0 | H6: 0 | I6: 0 | J6: 2160580 | K6: 0 | L6: 0 | M6: 0 | N6: 453721.8 | O6: 0 | P6: 0 | Q6: 0 | R6: 0 | S6: 0 | T6: 0 | U6: =SUM(G6:T6) -> 2614301.8 | V6: Servicios | W6: Buenos Aires
A7: 06/11/2025 | B7: 14/11/2025 | C7: FCA 00002-00000289 | D7: SCHEJTER LILA ELISA | E7: 27144282383 | F7: RI | G7: 0 | H7: 0 | I7: 0 | J7: 70000 | K7: 0 | L7: 0 | M7: 0 | N7: 14700 | O7: 0 | P7: 0 | Q7: 0 | R7: 0 | S7: 0 | T7: 0 | U7: =SUM(G7:T7) -> 84700 | V7: Servicios | W7: Buenos Aires
A8: 06/11/2025 | B8: 06/11/2025 | C8: FCA 00002-00001649 | D8: MARTIN EZEQUIEL DI FEO | E8: 20272865869 | F8: RI | G8: 0 | H8: 0 | I8: 0 | J8: 109300 | K8: 0 | L8: 0 | M8: 0 | N8: 22953 | O8: 0 | P8: 0 | Q8: 0 | R8: 0 | S8: 0 | T8: 0 | U8: =SUM(G8:T8) -> 132253 | V8: Bienes | W8: Buenos Aires
A9: 12/11/2025 | B9: 12/11/2025 | C9: FCA 00002-00001667 | D9: MARTIN EZEQUIEL DI FEO | E9: 20272865869 | F9: RI | G9: 0 | H9: 0 | I9: 0 | J9: 126400 | K9: 0 | L9: 0 | M9: 0 | N9: 26544 | O9: 0 | P9: 0 | Q9: 0 | R9: 0 | S9: 0 | T9: 0 | U9: =SUM(G9:T9) -> 152944 | V9: Bienes | W9: Buenos Aires
A10: 14/11/2025 | B10: 14/11/2025 | C10: FCA 00002-00001673 | D10: MARTIN EZEQUIEL DI FEO | E10: 20272865869 | F10: RI | G10: 0 | H10: 0 | I10: 0 | J10: 19500 | K10: 0 | L10: 0 | M10: 0 | N10: 4095 | O10: 0 | P10: 0 | Q10: 0 | R10: 0 | S10: 0 | T10: 0 | U10: =SUM(G10:T10) -> 23595 | V10: Bienes | W10: Buenos Aires | X10: Sin comprobante
A11: 19/11/2025 | B11: 19/11/2025 | C11: FCA 00002-00001686 | D11: MARTIN EZEQUIEL DI FEO | E11: 20272865869 | F11: RI | G11: 0 | H11: 0 | I11: 0 | J11: 150700 | K11: 0 | L11: 0 | M11: 0 | N11: 31647 | O11: 0 | P11: 0 | Q11: 0 | R11: 0 | S11: 0 | T11: 0 | U11: =SUM(G11:T11) -> 182347 | V11: Bienes | W11: Buenos Aires
A12: 20/11/2025 | B12: 20/11/2025 | C12: FCA 00002-00001687 | D12: MARTIN EZEQUIEL DI FEO | E12: 20272865869 | F12: RI | G12: 0 | H12: 0 | I12: 0 | J12: 15700 | K12: 0 | L12: 0 | M12: 0 | N12: 3297 | O12: 0 | P12: 0 | Q12: 0 | R12: 0 | S12: 0 | T12: 0 | U12: =SUM(G12:T12) -> 18997 | V12: Bienes | W12: Buenos Aires
A13: 28/11/2025 | B13: 28/11/2025 | C13: FCA 00002-00001697 | D13: MARTIN EZEQUIEL DI FEO | E13: 20272865869 | F13: RI | G13: 0 | H13: 0 | I13: 0 | J13: 131009.09 | K13: 0 | L13: 0 | M13: 0 | N13: 27511.91 | O13: 0 | P13: 0 | Q13: 0 | R13: 0 | S13: 0 | T13: 0 | U13: =SUM(G13:T13) -> 158521 | V13: Bienes | W13: Buenos Aires
A14: 13/11/2025 | B14: 13/11/2025 | C14: FCA 00002-00005595 | D14: CIEN POR CIENTO FOLLETOS SRL | E14: 30718329805 | F14: RI | G14: 0 | H14: 0 | I14: 0 | J14: 73057.85 | K14: 0 | L14: 0 | M14: 0 | N14: 15342.15 | O14: 0 | P14: 0 | Q14: 0 | R14: 0 | S14: 0 | T14: 0 | U14: =SUM(G14:T14) -> 88400 | W14: Ciudad de Buenos Aires
A15: 18/11/2025 | B15: 18/11/2025 | C15: FCA 00002-00005665 | D15: CIEN POR CIENTO FOLLETOS SRL | E15: 30718329805 | F15: RI | G15: 0 | H15: 0 | I15: 0 | J15: 73057.85 | K15: 0 | L15: 0 | M15: 0 | N15: 15342.15 | O15: 0 | P15: 0 | Q15: 0 | R15: 0 | S15: 0 | T15: 0 | U15: =SUM(G15:T15) -> 88400 | W15: Ciudad de Buenos Aires | X15: Sin comprobante
A16: 03/11/2025 | B16: 14/11/2025 | C16: FCA 00002-00006005 | D16: LEONARDO JAVIER VIDAL | E16: 24253769951 | F16: RI | G16: 0 | H16: 0 | I16: 0 | J16: 315957 | K16: 0 | L16: 0 | M16: 0 | N16: 66350.97 | O16: 0 | P16: 0 | Q16: 0 | R16: 0 | S16: 0 | T16: 0 | U16: =SUM(G16:T16) -> 382307.97 | V16: Bienes | W16: Buenos Aires
A17: 11/11/2025 | B17: 11/11/2025 | C17: FCA 00002-00007991 | D17: DISEÑOS JERY S R L | E17: 30694549817 | F17: RI | G17: 0 | H17: 0 | I17: 0 | J17: 193893 | K17: 0 | L17: 0 | M17: 0 | N17: 40717.53 | O17: 0 | P17: 0 | Q17: 0 | R17: 0 | S17: 0 | T17: 0 | U17: =SUM(G17:T17) -> 234610.53 | V17: Bienes | W17: Ciudad de Buenos Aires | X17: Sin comprobante
A18: 12/11/2025 | B18: 12/11/2025 | C18: FCA 00002-00010010 | D18: MANGGINI PABLO Y M ULISES SH | E18: 33708218699 | F18: RI | G18: 0 | H18: 0 | I18: 0 | J18: 90000 | K18: 0 | L18: 0 | M18: 0 | N18: 18900 | O18: 0 | P18: 0 | Q18: 0 | R18: 0 | S18: 0 | T18: 0 | U18: =SUM(G18:T18) -> 108900 | V18: Locaciones | W18: Buenos Aires
A19: 29/11/2025 | B19: 29/11/2025 | C19: FCA 00002-00474231 | D19: MERCADOLIBRE S.R.L. | E19: 30703088534 | F19: RI | G19: 0 | H19: 0 | I19: 0 | J19: 147998.62 | K19: 0 | L19: 0 | M19: 0 | N19: 31079.71 | O19: 5919.94 | P19: 0 | Q19: 0 | R19: 0 | S19: 4439.96 | T19: 0 | U19: =SUM(G19:T19) -> 189438.23 | V19: Servicios | W19: Ciudad de Buenos Aires
A20: 17/11/2025 | B20: 17/11/2025 | C20: FCA 00003-00010027 | D20: MANGGINI PABLO Y M ULISES SH | E20: 33708218699 | F20: RI | G20: 0 | H20: 0 | I20: 0 | J20: 45000 | K20: 0 | L20: 0 | M20: 0 | N20: 9450 | O20: 0 | P20: 0 | Q20: 0 | R20: 0 | S20: 0 | T20: 0 | U20: =SUM(G20:T20) -> 54450 | V20: Locaciones | W20: Buenos Aires
A21: 04/11/2025 | B21: 04/11/2025 | C21: FCA 00003-00055382 | D21: EXPRESO TROLE S R L | E21: 30577744579 | F21: RI | G21: 0 | H21: 0 | I21: 0 | J21: 130554.62 | K21: 0 | L21: 0 | M21: 0 | N21: 27416.47 | O21: 0 | P21: 0 | Q21: 0 | R21: 0 | S21: 0 | T21: 0 | U21: =SUM(G21:T21) -> 157971.09 | V21: Servicios | W21: Ciudad de Buenos Aires
A22: 07/11/2025 | B22: 07/11/2025 | C22: FCA 00003-00057712 | D22: LIPROT S.R.L. | E22: 30711454388 | F22: RI | G22: 0 | H22: 0 | I22: 0 | J22: 197766 | K22: 0 | L22: 0 | M22: 0 | N22: 41530.86 | O22: 0 | P22: 0 | Q22: 0 | R22: 0 | S22: 0 | T22: 0 | U22: =SUM(G22:T22) -> 239296.86 | V22: Bienes | W22: Buenos Aires
A23: 17/11/2025 | B23: 17/11/2025 | C23: FCA 00003-03596545 | D23: LINKEDSTORE ARGENTINA S.R.L. | E23: 30712019359 | F23: RI | G23: 0 | H23: 0 | I23: 0 | J23: 17767.77 | K23: 0 | L23: 0 | M23: 0 | N23: 3731.23 | O23: 0 | P23: 0 | Q23: 0 | R23: 710.72 | S23: 0 | T23: 0 | U23: =SUM(G23:T23) -> 22209.72 | V23: Servicios | W23: Ciudad de Buenos Aires | X23: Sin comprobante
A24: 05/11/2025 | B24: 05/11/2025 | C24: FCA 00004-00000138 | D24: EDUARDO FRANCISCO NARDOMARINO | E24: 20174004146 | F24: RI | G24: 0 | H24: 0 | I24: 0 | J24: 270000 | K24: 0 | L24: 0 | M24: 0 | N24: 56700 | O24: 0 | P24: 0 | Q24: 0 | R24: 0 | S24: 0 | T24: 0 | U24: =SUM(G24:T24) -> 326700 | V24: Servicios | W24: Ciudad de Buenos Aires
A25: 17/11/2025 | B25: 17/11/2025 | C25: FCA 00004-00000141 | D25: EDUARDO FRANCISCO NARDOMARINO | E25: 20174004146 | F25: RI | G25: 0 | H25: 0 | I25: 0 | J25: 280000 | K25: 0 | L25: 0 | M25: 0 | N25: 58800 | O25: 0 | P25: 0 | Q25: 0 | R25: 0 | S25: 0 | T25: 0 | U25: =SUM(G25:T25) -> 338800 | V25: Servicios | W25: Ciudad de Buenos Aires
A26: 18/11/2025 | B26: 18/11/2025 | C26: FCA 00004-00000142 | D26: EDUARDO FRANCISCO NARDOMARINO | E26: 20174004146 | F26: RI | G26: 0 | H26: 0 | I26: 0 | J26: 332500 | K26: 0 | L26: 0 | M26: 0 | N26: 69825 | O26: 0 | P26: 0 | Q26: 0 | R26: 0 | S26: 0 | T26: 0 | U26: =SUM(G26:T26) -> 402325 | V26: Servicios | W26: Ciudad de Buenos Aires
A27: 20/11/2025 | B27: 20/11/2025 | C27: FCA 00004-00000143 | D27: EDUARDO FRANCISCO NARDOMARINO | E27: 20174004146 | F27: RI | G27: 0 | H27: 0 | I27: 0 | J27: 262500 | K27: 0 | L27: 0 | M27: 0 | N27: 55125 | O27: 0 | P27: 0 | Q27: 0 | R27: 0 | S27: 0 | T27: 0 | U27: =SUM(G27:T27) -> 317625 | V27: Servicios | W27: Ciudad de Buenos Aires
A28: 20/11/2025 | B28: 20/11/2025 | C28: FCA 00004-00000179 | D28: VILLALBA MIGUEL ANGEL | E28: 20317488476 | F28: RI | G28: 0 | H28: 0 | I28: 0 | J28: 900000 | K28: 0 | L28: 0 | M28: 0 | N28: 189000 | O28: 0 | P28: 0 | Q28: 0 | R28: 0 | S28: 0 | T28: 0 | U28: =SUM(G28:T28) -> 1089000 | V28: Bienes de uso | W28: Buenos Aires
A29: 06/11/2025 | B29: 06/11/2025 | C29: FCA 00004-00016201 | D29: TRINIDAD INSUMOS S.R.L. | E29: 30712305513 | F29: RI | G29: 0 | H29: 0 | I29: 0 | J29: 1084000 | K29: 0 | L29: 0 | M29: 0 | N29: 227640 | O29: 0 | P29: 0 | Q29: 0 | R29: 0 | S29: 0 | T29: 0 | U29: =SUM(G29:T29) -> 1311640 | V29: Bienes | W29: Buenos Aires
A30: 14/11/2025 | B30: 14/11/2025 | C30: FCA 00004-00016244 | D30: TRINIDAD INSUMOS S.R.L. | E30: 30712305513 | F30: RI | G30: 0 | H30: 0 | I30: 1863000 | J30: 117800 | K30: 0 | L30: 0 | M30: 0 | N30: 220353 | O30: 0 | P30: 0 | Q30: 0 | R30: 0 | S30: 0 | T30: 0 | U30: =SUM(G30:T30) -> 2201153 | V30: Bienes | W30: Buenos Aires
A31: 03/11/2025 | B31: 03/11/2025 | C31: FCA 00004-00041612 | D31: EMILIANO RUBEN LEDESMA | E31: 20289111329 | F31: RI | G31: 0 | H31: 0 | I31: 0 | J31: 1704476.6 | K31: 0 | L31: 0 | M31: 0 | N31: 357940.09 | O31: 0 | P31: 0 | Q31: 0 | R31: 0 | S31: 0 | T31: 0 | U31: =SUM(G31:T31) -> 2062416.7 | V31: Bienes | W31: Buenos Aires
A32: 28/11/2025 | B32: 28/11/2025 | C32: FCA 00004-00041808 | D32: EMILIANO RUBEN LEDESMA | E32: 20289111329 | F32: RI | G32: 0 | H32: 0 | I32: 0 | J32: 60480 | K32: 0 | L32: 0 | M32: 0 | N32: 12700.8 | O32: 0 | P32: 0 | Q32: 0 | R32: 0 | S32: 0 | T32: 0 | U32: =SUM(G32:T32) -> 73180.8 | V32: Bienes | W32: Buenos Aires
A33: 18/11/2025 | B33: 18/11/2025 | C33: FCA 00005-00000068 | D33: JUN MA | E33: 20929183143 | F33: RI | G33: 0 | H33: 0 | I33: 0 | J33: 110000 | K33: 0 | L33: 0 | M33: 0 | N33: 23100 | O33: 0 | P33: 0 | Q33: 0 | R33: 0 | S33: 0 | T33: 0 | U33: =SUM(G33:T33) -> 133100 | V33: Servicios | W33: Ciudad de Buenos Aires
A34: 12/11/2025 | B34: 12/11/2025 | C34: FCA 00005-00001096 | D34: BM MEDICINE SRL | E34: 30712155945 | F34: RI | G34: 0 | H34: 0 | I34: 0 | J34: 783510 | K34: 0 | L34: 0 | M34: 0 | N34: 164537.1 | O34: 0 | P34: 0 | Q34: 0 | R34: 0 | S34: 0 | T34: 0 | U34: =SUM(G34:T34) -> 948047.1 | V34: Bienes | W34: Ciudad de Buenos Aires
A35: 19/11/2025 | B35: 19/11/2025 | C35: FCA 00005-00001105 | D35: BM MEDICINE SRL | E35: 30712155945 | F35: RI | G35: 0 | H35: 0 | I35: 0 | J35: 682110 | K35: 0 | L35: 0 | M35: 0 | N35: 143243.1 | O35: 0 | P35: 0 | Q35: 0 | R35: 0 | S35: 0 | T35: 0 | U35: =SUM(G35:T35) -> 825353.1 | V35: Bienes | W35: Ciudad de Buenos Aires
... A43: 25/11/2025 | B43: 25/11/2025 | C43: FCA 00006-00001684 | D43: HUGO GABRIEL VENTO | E43: 20247225243 | F43: RI | G43: 0 | H43: 0 | I43: 0 | J43: 140932 | K43: 0 | L43: 0 | M43: 0 | N43: 29595.72 | O43: 0 | P43: 0 | Q43: 0 | R43: 0 | S43: 0 | T43: 0 | U43: =SUM(G43:T43) -> 170527.72 | V43: Bienes | W43: Ciudad de Buenos Aires
A44: 11/11/2025 | B44: 11/11/2025 | C44: FCA 00006-00002160 | D44: PAPELERA GEOPEL SRL | E44: 30716815710 | F44: RI | G44: 0 | H44: 0 | I44: 0 | J44: 26200 | K44: 0 | L44: 0 | M44: 0 | N44: 5502 | O44: 0 | P44: 0 | Q44: 0 | R44: 0 | S44: 0 | T44: 0 | U44: =SUM(G44:T44) -> 31702 | V44: Bienes | W44: 81
A45: 14/11/2025 | B45: 14/11/2025 | C45: FCA 00006-00002163 | D45: PAPELERA GEOPEL SRL | E45: 30716815710 | F45: RI | G45: 0 | H45: 0 | I45: 0 | J45: 17000 | K45: 0 | L45: 0 | M45: 0 | N45: 3570 | O45: 0 | P45: 0 | Q45: 0 | R45: 0 | S45: 0 | T45: 0 | U45: =SUM(G45:T45) -> 20570 | V45: Bienes | W45: 81
A46: 28/11/2025 | B46: 28/11/2025 | C46: FCA 00006-00002177 | D46: PAPELERA GEOPEL SRL | E46: 30716815710 | F46: RI | G46: 0 | H46: 0 | I46: 0 | J46: 14000 | K46: 0 | L46: 0 | M46: 0 | N46: 2940 | O46: 0 | P46: 0 | Q46: 0 | R46: 0 | S46: 0 | T46: 0 | U46: =SUM(G46:T46) -> 16940 | V46: Bienes | W46: 81
A47: 01/11/2025 | B47: 01/11/2025 | C47: FCA 00006-00023963 | D47: SOMOS ENERGIA SA | E47: 33715594949 | F47: RI | G47: 0 | H47: 0 | I47: 0 | J47: 20749.09 | K47: 0 | L47: 0 | M47: 0 | N47: 4357.31 | O47: 3489.83 | P47: 0 | Q47: 0 | R47: 397.76 | S47: 0 | T47: 0 | U47: =SUM(G47:T47) -> 28993.99 | V47: Servicios | W47: 81
A48: 05/11/2025 | B48: 05/11/2025 | C48: FCA 00006-00023998 | D48: SOMOS ENERGIA SA | E48: 33715594949 | F48: RI | G48: 0 | H48: 0 | I48: 0 | J48: 73327.4 | K48: 0 | L48: 0 | M48: 0 | N48: 15398.75 | O48: 10121.3 | P48: 0 | Q48: 0 | R48: 1153.59 | S48: 0 | T48: 0 | U48: =SUM(G48:T48) -> 100001.04 | V48: Servicios | W48: 81
A49: 28/11/2025 | B49: 28/11/2025 | C49: FCA 00006-00059851 | D49: TARGET MEDICAL SA | E49: 30710177658 | F49: RI | G49: 0 | H49: 0 | I49: 0 | J49: 2392500 | K49: 0 | L49: 0 | M49: 0 | N49: 502425 | O49: 0 | P49: 0 | Q49: 0 | S49: 0 | T49: 95700 | U49: =SUM(G49:T49) -> 2990625 | V49: Bienes | W49: Ciudad de Buenos Aires
A50: 10/11/2025 | B50: 10/11/2025 | C50: FCA 00006-00097911 | D50: SALUDTEX SA | E50: 30711553564 | F50: RI | G50: 0 | H50: 0 | I50: 0 | J50: 1026246 | K50: 0 | L50: 0 | M50: 0 | N50: 215511.66 | O50: 0 | P50: 0 | Q50: 0 | R50: 0 | S50: 0 | T50: 0 | U50: =SUM(G50:T50) -> 1241757.7 | V50: Bienes | W50: Buenos Aires
A51: 10/11/2025 | B51: 10/11/2025 | C51: FCA 00006-00097918 | D51: SALUDTEX SA | E51: 30711553564 | F51: RI | G51: 0 | H51: 0 | I51: 0 | J51: 142068 | K51: 0 | L51: 0 | M51: 0 | N51: 29834.28 | O51: 0 | P51: 0 | Q51: 0 | R51: 0 | S51: 0 | T51: 0 | U51: =SUM(G51:T51) -> 171902.28 | V51: Bienes | W51: Buenos Aires
A52: 14/11/2025 | B52: 14/11/2025 | C52: FCA 00006-00098089 | D52: SALUDTEX SA | E52: 30711553564 | F52: RI | G52: 0 | H52: 0 | I52: 0 | J52: 89188 | K52: 0 | L52: 0 | M52: 0 | N52: 18729.48 | O52: 0 | P52: 0 | Q52: 0 | R52: 0 | S52: 0 | T52: 0 | U52: =SUM(G52:T52) -> 107917.48 | V52: Bienes | W52: Buenos Aires
A53: 17/11/2025 | B53: 17/11/2025 | C53: FCA 00006-00098164 | D53: SALUDTEX SA | E53: 30711553564 | F53: RI | G53: 0 | H53: 0 | I53: 0 | J53: 332368 | K53: 0 | L53: 0 | M53: 0 | N53: 69797.28 | O53: 0 | P53: 0 | Q53: 0 | R53: 0 | S53: 0 | T53: 0 | U53: =SUM(G53:T53) -> 402165.28 | V53: Bienes | W53: Buenos Aires
A54: 17/11/2025 | B54: 17/11/2025 | C54: FCA 00006-00098186 | D54: SALUDTEX SA | E54: 30711553564 | F54: RI | G54: 0 | H54: 0 | I54: 0 | J54: 137991 | K54: 0 | L54: 0 | M54: 0 | N54: 28978.11 | O54: 0 | P54: 0 | Q54: 0 | R54: 0 | S54: 0 | T54: 0 | U54: =SUM(G54:T54) -> 166969.11 | V54: Bienes | W54: Buenos Aires
A55: 05/11/2025 | B55: 05/11/2025 | C55: FCA 00007-00000057 | D55: ALEJANDRA MABEL SOUSA ALDERETE | E55: 27325223273 | F55: RI | G55: 0 | H55: 0 | I55: 0 | J55: 700000 | K55: 0 | L55: 0 | M55: 0 | N55: 147000 | O55: 0 | P55: 0 | Q55: 0 | R55: 0 | S55: 0 | T55: 0 | U55: =SUM(G55:T55) -> 847000 | V55: Bienes | W55: Ciudad de Buenos Aires
A56: 26/11/2025 | B56: 26/11/2025 | C56: FCA 00007-00023053 | D56: REHAVITA S.A. | E56: 30709214078 | F56: RI | G56: 0 | H56: 0 | I56: 386400 | J56: 0 | K56: 0 | L56: 0 | M56: 0 | N56: 40572 | O56: 0 | P56: 0 | Q56: 0 | R56: 0 | S56: 0 | T56: 0 | U56: =SUM(G56:T56) -> 426972 | V56: Bienes | W56: Ciudad de Buenos Aires
A57: 18/11/2025 | B57: 18/11/2025 | C57: FCA 00007-00036827 | D57: KASAMI S.A. | E57: 30716661519 | F57: RI | G57: 0 | H57: 0 | I57: 0 | J57: 20429.76 | K57: 0 | L57: 0 | M57: 0 | N57: 4290.25 | O57: 0 | P57: 0 | Q57: 0 | R57: 0 | S57: 0 | T57: 0 | U57: =SUM(G57:T57) -> 24720.01 | W57: Ciudad de Buenos Aires
A58: 05/11/2025 | B58: 05/11/2025 | C58: FCA 00008-00001884 | D58: ASIAL SRL | E58: 30708973501 | F58: RI | G58: 0 | H58: 0 | I58: 0 | J58: 521936 | K58: 0 | L58: 0 | M58: 0 | N58: 109606.56 | O58: 0 | P58: 0 | Q58: 0 | R58: 0 | S58: 0 | T58: 0 | U58: =SUM(G58:T58) -> 631542.56 | V58: Bienes | W58: Buenos Aires
A59: 10/11/2025 | B59: 10/11/2025 | C59: FCA 00008-00016555 | D59: SOMOS ENERGIA SA | E59: 33715594949 | F59: RI | G59: 0 | H59: 0 | I59: 0 | J59: 64264.47 | K59: 0 | L59: 0 | M59: 0 | N59: 13495.54 | O59: 0 | P59: 0 | Q59: 0 | R59: 9837.96 | S59: 0 | T59: 0 | U59: =SUM(G59:T59) -> 87597.97 | V59: Servicios | W59: 81
A60: 13/11/2025 | B60: 13/11/2025 | C60: FCA 00008-00016593 | D60: SOMOS ENERGIA SA | E60: 33715594949 | F60: RI | G60: 0 | H60: 0 | I60: 0 | J60: 29354.14 | K60: 0 | L60: 0 | M60: 0 | N60: 6164.37 | O60: 0 | P60: 0 | Q60: 0 | R60: 4482.44 | S60: 0 | T60: 0 | U60: =SUM(G60:T60) -> 40000.95 | V60: Servicios | W60: 81
A61: 22/11/2025 | B61: 22/11/2025 | C61: FCA 00008-00016657 | D61: SOMOS ENERGIA SA | E61: 33715594949 | F61: RI | G61: 0 | H61: 0 | I61: 0 | J61: 13927.91 | K61: 0 | L61: 0 | M61: 0 | N61: 2924.86 | O61: 0 | P61: 0 | Q61: 0 | R61: 2057.28 | S61: 0 | T61: 0 | U61: =SUM(G61:T61) -> 18910.05 | V61: Servicios | W61: 81
A62: 24/11/2025 | B62: 24/11/2025 | C62: FCA 00008-00016674 | D62: SOMOS ENERGIA SA | E62: 33715594949 | F62: RI | G62: 0 | H62: 0 | I62: 0 | J62: 73663.81 | K62: 0 | L62: 0 | M62: 0 | N62: 15469.4 | O62: 9767.53 | P62: 0 | Q62: 0 | R62: 1113.27 | S62: 0 | T62: 0 | U62: =SUM(G62:T62) -> 100014.01 | V62: Servicios | W62: 81
A63: 11/11/2025 | B63: 11/11/2025 | C63: FCA 00009-00001686 | D63: SERGIO ALEJANDRO IALLONARDO | E63: 20242126158 | F63: RI | G63: 0 | H63: 0 | I63: 0 | J63: 140000 | K63: 0 | L63: 0 | M63: 0 | N63: 29400 | O63: 0 | P63: 0 | Q63: 0 | R63: 0 | S63: 0 | T63: 0 | U63: =SUM(G63:T63) -> 169400 | V63: Bienes | W63: Buenos Aires
A64: 26/11/2025 | B64: 26/11/2025 | C64: FCA 00010-00000001 | D64: SOMOS ENERGIA SA | E64: 33715594949 | F64: RI | G64: 0 | H64: 0 | I64: 0 | J64: 47819.03 | K64: 0 | L64: 0 | M64: 0 | N64: 10042 | O64: 731 | P64: 0 | Q64: 0 | R64: 6408 | S64: 0 | T64: 0 | U64: =SUM(G64:T64) -> 65000.03 | V64: Servicios | W64: 81
A65: 19/11/2025 | B65: 19/11/2025 | C65: FCA 00010-00014484 | D65: GNC MONTE GRANDE S.R.L. | E65: 30709208221 | F65: RI | G65: 0 | H65: 0 | I65: 0 | J65: 43967.06 | K65: 0 | L65: 0 | M65: 0 | N65: 9233.08 | O65: 6104.09 | P65: 0 | Q65: 0 | R65: 695.77 | S65: 0 | T65: 0 | U65: =SUM(G65:T65) -> 60000 | V65: Servicios | W65: 81
A66: 10/11/2025 | B66: 10/11/2025 | C66: FCA 00011-00000142 | D66: DIMITRI CARLOS DANIEL LOPEZ | E66: 20327047354 | F66: RI | G66: 0 | H66: 0 | I66: 0 | J66: 37190.09 | K66: 0 | L66: 0 | M66: 0 | N66: 7809.92 | O66: 0 | P66: 0 | Q66: 0 | R66: 0 | S66: 0 | T66: 0 | U66: =SUM(G66:T66) -> 45000.01 | W66: Ciudad de Buenos Aires | X66: Sin comprobante
A67: 25/11/2025 | B67: 25/11/2025 | C67: FCA 00011-00082065 | D67: BIGBOX S.A. | E67: 30711091552 | F67: RI | G67: 0 | H67: 0 | I67: 0 | J67: 164462.81 | K67: 0 | L67: 0 | M67: 0 | N67: 34537.19 | O67: 0 | P67: 0 | Q67: 0 | R67: 0 | S67: 0 | T67: 0 | U67: =SUM(G67:T67) -> 199000 | V67: Bienes | W67: Ciudad de Buenos Aires | X67: Sin comprobante
A68: 29/11/2025 | B68: 29/11/2025 | C68: FCA 00011-00082421 | D68: BIGBOX S.A. | E68: 30711091552 | F68: RI | G68: 0 | H68: 0 | I68: 0 | J68: 76859.51 | K68: 0 | L68: 0 | M68: 0 | N68: 16140.5 | O68: 0 | P68: 0 | Q68: 0 | R68: 0 | S68: 0 | T68: 0 | U68: =SUM(G68:T68) -> 93000.01 | V68: Bienes | W68: Ciudad de Buenos Aires
A69: 13/11/2025 | B69: 13/11/2025 | C69: FCA 00017-00003517 | D69: RELIEF CENTER S.R.L. | E69: 30711764921 | F69: RI | G69: 0 | H69: 0 | I69: 0 | J69: 522689 | K69: 0 | L69: 0 | M69: 0 | N69: 109764.69 | O69: 0 | P69: 0 | Q69: 0 | R69: 0 | S69: 0 | T69: 0 | U69: =SUM(G69:T69) -> 632453.69 | V69: Bienes | W69: Ciudad de Buenos Aires
A70: 18/11/2025 | B70: 18/11/2025 | C70: FCA 00017-00003525 | D70: RELIEF CENTER S.R.L. | E70: 30711764921 | F70: RI | G70: 0 | H70: 0 | I70: 0 | J70: 253566 | K70: 0 | L70: 0 | M70: 0 | N70: 53248.86 | O70: 0 | P70: 0 | Q70: 0 | R70: 0 | S70: 0 | T70: 0 | U70: =SUM(G70:T70) -> 306814.86 | V70: Bienes | W70: Ciudad de Buenos Aires
A71: 27/11/2025 | B71: 27/11/2025 | C71: FCA 00017-00003552 | D71: RELIEF CENTER S.R.L. | E71: 30711764921 | F71: RI | G71: 0 | H71: 0 | I71: 0 | J71: 218234 | K71: 0 | L71: 0 | M71: 0 | N71: 45829.14 | O71: 0 | P71: 0 | Q71: 0 | R71: 0 | S71: 0 | T71: 0 | U71: =SUM(G71:T71) -> 264063.14 | V71: Bienes | W71: Ciudad de Buenos Aires
A72: 27/11/2025 | B72: 27/11/2025 | C72: FCA 00020-00000089 | D72: COMPAÑIA DE PAPELES S.A. | E72: 30707597956 | F72: RI | G72: 0 | H72: 0 | I72: 0 | J72: 14399.1 | K72: 0 | L72: 0 | M72: 0 | N72: 3023.81 | O72: 0 | P72: 0 | Q72: 0 | R72: 0 | S72: 0 | T72: 0 | U72: =SUM(G72:T72) -> 17422.91 | W72: Ciudad de Buenos Aires
A73: 26/11/2025 | B73: 26/11/2025 | C73: FCA 00024-00004197 | D73: LOGISTICA PATRICIOS SA | E73: 30709879258 | F73: RI | G73: 0 | H73: 0 | I73: 0 | J73: 51500 | K73: 0 | L73: 0 | M73: 0 | N73: 10815 | O73: 0 | P73: 0 | Q73: 0 | R73: 0 | S73: 0 | T73: 0 | U73: =SUM(G73:T73) -> 62315 | V73: Servicios | W73: Ciudad de Buenos Aires
A74: 18/11/2025 | B74: 18/11/2025 | C74: FCA 00031-00079625 | D74: GIFEL S.R.L. | E74: 30715209833 | F74: RI | G74: 0 | H74: 0 | I74: 0 | J74: 15810.74 | K74: 0 | L74: 0 | M74: 0 | N74: 3320.26 | O74: 0 | P74: 0 | Q74: 0 | R74: 370.91 | S74: 0 | T74: 0 | U74: =SUM(G74:T74) -> 19501.91 | W74: Ciudad de Buenos Aires
A75: 20/11/2025 | B75: 20/11/2025 | C75: FCA 00031-00079735 | D75: GIFEL S.R.L. | E75: 30715209833 | F75: RI | G75: 0 | H75: 0 | I75: 0 | J75: 15810.74 | K75: 0 | L75: 0 | M75: 0 | N75: 3320.26 | O75: 0 | P75: 0 | Q75: 0 | R75: 370.91 | S75: 0 | T75: 0 | U75: =SUM(G75:T75) -> 19501.91 | W75: Ciudad de Buenos Aires
A76: 13/11/2025 | B76: 13/11/2025 | C76: FCA 00032-00173281 | D76: EXPRESO LANCIONI SA | E76: 30708847247 | F76: RI | G76: 0 | H76: 0 | I76: 0 | J76: 85233.81 | K76: 0 | L76: 0 | M76: 0 | N76: 17899.1 | O76: 0 | P76: 0 | Q76: 0 | R76: 3409.35 | S76: 0 | T76: 0 | U76: =SUM(G76:T76) -> 106542.26 | V76: Servicios | W76: Buenos Aires
A77: 15/11/2025 | B77: 15/11/2025 | C77: FCA 00050-04739926 | D77: AUTOPISTAS DE BUENOS AIRES (AUBASA) SA | E77: 30714112836 | F77: RI | G77: 0 | H77: 0 | I77: 0 | J77: 2783.03 | K77: 0 | L77: 0 | M77: 0 | N77: 584.44 | O77: 0 | P77: 0 | Q77: 0 | R77: 83.49 | S77: 0 | T77: 0 | U77: =SUM(G77:T77) -> 3450.96 | V77: Servicios | W77: Buenos Aires
A78: 30/11/2025 | B78: 30/11/2025 | C78: FCA 00050-04777596 | D78: AUTOPISTAS DE BUENOS AIRES (AUBASA) SA | E78: 30714112836 | F78: RI | G78: 0 | H78: 0 | I78: 0 | J78: 16383.12 | K78: 0 | L78: 0 | M78: 0 | N78: 3440.46 | O78: 0 | P78: 0 | Q78: 0 | R78: 491.49 | S78: 0 | T78: 0 | U78: =SUM(G78:T78) -> 20315.07 | V78: Servicios | W78: Buenos Aires | X78: Sin comprobante
A79: 28/11/2025 | B79: 28/11/2025 | C79: FCA 00064-00005568 | D79: D ARC LIBERTADOR SOCIEDAD ANONIMA | E79: 30597228984 | F79: RI | G79: 0 | H79: 0 | I79: 0 | J79: 414942.36 | K79: 0 | L79: 0 | M79: 0 | N79: 87137.9 | O79: 0 | P79: 0 | Q79: 0 | R79: 0 | S79: 0 | T79: 0 | U79: =SUM(G79:T79) -> 502080.26 | W79: Ciudad de Buenos Aires
A80: 05/11/2025 | B80: 05/11/2025 | C80: FCA 00101-00009480 | D80: BALANZE S.A. | E80: 33711430879 | F80: RI | G80: 0 | H80: 0 | I80: 0 | J80: 1566000 | K80: 0 | L80: 0 | M80: 0 | N80: 328860 | O80: 0 | P80: 0 | Q80: 0 | R80: 0 | S80: 0 | T80: 0 | U80: =SUM(G80:T80) -> 1894860 | V80: Bienes | W80: Ciudad de Buenos Aires
A81: 14/11/2025 | B81: 14/11/2025 | C81: FCA 00104-11245066 | D81: CORREDORES VIALES SA | E81: 30715804812 | F81: RI | G81: 0 | H81: 0 | I81: 0 | J81: 2079.97 | K81: 0 | L81: 0 | M81: 0 | N81: 436.79 | O81: 0 | P81: 0 | Q81: 0 | R81: 83.2 | S81: 0 | T81: 0 | U81: =SUM(G81:T81) -> 2599.96 | V81: Bienes | W81: Buenos Aires | X81: Sin comprobante
A82: 15/11/2025 | B82: 15/11/2025 | C82: FCA 00104-12280276 | D82: CORREDORES VIALES SA | E82: 30715804812 | F82: RI | G82: 0 | H82: 0 | I82: 0 | J82: 2079.97 | K82: 0 | L82: 0 | M82: 0 | N82: 436.79 | O82: 0 | P82: 0 | Q82: 0 | R82: 83.2 | S82: 0 | T82: 0 | U82: =SUM(G82:T82) -> 2599.96 | V82: Bienes | W82: Buenos Aires | X82: Sin comprobante
A83: 04/11/2025 | B83: 04/11/2025 | C83: FCA 00120-00006008 | D83: PANATEL SOCIEDAD ANONIMA | E83: 30587197215 | F83: RI | G83: 0 | H83: 0 | I83: 0 | J83: 148760.33 | K83: 0 | L83: 0 | M83: 0 | N83: 31239.67 | O83: 0 | P83: 0 | Q83: 0 | R83: 0 | S83: 0 | T83: 5950.41 | U83: =SUM(G83:T83) -> 185950.41 | V83: Servicios | W83: Buenos Aires
A84: 15/11/2025 | B84: 15/11/2025 | C84: FCA 00126-00254459 | D84: COORDINACION ECOLOGICA AREA METROPOLITANA SOCIEDAD DEL ESTADO | E84: 30577207190 | F84: RI | G84: 0 | H84: 0 | I84: 0 | J84: 1487.6 | K84: 0 | L84: 0 | M84: 0 | N84: 312.4 | O84: 0 | P84: 0 | Q84: 0 | R84: 0 | S84: 0 | T84: 0 | U84: =SUM(G84:T84) -> 1800 | V84: Bienes | W84: Buenos Aires | X84: Sin comprobante
A85: 30/11/2025 | B85: 30/11/2025 | C85: FCA 00126-00283594 | D85: COORDINACION ECOLOGICA AREA METROPOLITANA SOCIEDAD DEL ESTADO | E85: 30577207190 | F85: RI | G85: 0 | H85: 0 | I85: 0 | J85: 1487.6 | K85: 0 | L85: 0 | M85: 0 | N85: 312.4 | O85: 0 | P85: 0 | Q85: 0 | R85: 0 | S85: 0 | T85: 0 | U85: =SUM(G85:T85) -> 1800 | V85: Bienes | W85: Buenos Aires | X85: Sin comprobante
A86: 27/11/2025 | B86: 27/11/2025 | C86: FCA 00210-00003912 | D86: ED GAR SOCIEDAD ANONIMA | E86: 30592097482 | F86: RI | G86: 0 | H86: 0 | I86: 0 | J86: 0 | K86: 0 | L86: 30603.01 | M86: 0 | N86: 0 | O86: 0 | P86: 0 | Q86: 0 | R86: 0 | S86: 0 | T86: 0 | U86: =SUM(G86:T86) -> 30603.01 | V86: Bienes | W86: Buenos Aires | X86: Sin comprobante
A87: 01/11/2025 | B87: 01/11/2025 | C87: FCA 00500-01805067 | D87: SOLUCIONES MULTIMEDIA SA | E87: 30654118767 | F87: RI | G87: 0 | H87: 0 | I87: 0 | J87: 172538.09 | K87: 0 | L87: 0 | M87: 0 | N87: 36233 | O87: 0 | P87: 0 | Q87: 0 | R87: 0 | S87: 0 | T87: 6901.52 | U87: =SUM(G87:T87) -> 215672.61 | V87: Bienes | W87: Buenos Aires
A88: 01/11/2025 | B88: 26/11/2025 | C88: FCA 00629-06582507 | D88: GRUPO CONC.DEL OESTE SA | E88: 30663498513 | F88: RI | G88: 0 | H88: 0 | I88: 0 | J88: 7973.16 | K88: 0 | L88: 0 | M88: 0 | N88: 1674.36 | O88: 0 | P88: 0 | Q88: 0 | R88: 0 | S88: 0 | T88: 318.93 | U88: =SUM(G88:T88) -> 9966.45 | V88: Servicios | W88: Buenos Aires
A89: 06/11/2025 | B89: 06/11/2025 | C89: FCA 00700-02826739 | D89: CORREDORES VIALES SA | E89: 30715804812 | F89: RI | G89: 0 | H89: 0 | I89: 0 | J89: 7695.87 | K89: 0 | L89: 0 | M89: 0 | N89: 1616.13 | O89: 0 | P89: 0 | Q89: 0 | R89: 0 | S89: 0 | T89: 307.83 | U89: =SUM(G89:T89) -> 9619.83 | V89: Bienes | W89: Buenos Aires
A90: 24/11/2025 | B90: 24/11/2025 | C90: FCA 00700-02858327 | D90: CORREDORES VIALES SA | E90: 30715804812 | F90: RI | G90: 0 | H90: 0 | I90: 0 | J90: 7071.89 | K90: 0 | L90: 0 | M90: 0 | N90: 1485.1 | O90: 0 | P90: 0 | Q90: 0 | R90: 0 | S90: 0 | T90: 282.87 | U90: =SUM(G90:T90) -> 8839.86 | V90: Bienes | W90: Buenos Aires
A91: 01/11/2025 | B91: 26/11/2025 | C91: FCA 00711-07793985 | D91: AUTOPISTAS DEL SOL SA | E91: 30677237119 | F91: RI | G91: 0 | H91: 0 | I91: 0 | J91: 4159.89 | K91: 0 | L91: 0 | M91: 0 | N91: 873.58 | O91: 0 | P91: 0 | Q91: 0 | R91: 124.8 | S91: 0 | T91: 166.4 | U91: =SUM(G91:T91) -> 5324.67 | V91: Servicios | W91: Buenos Aires
A92: 16/11/2025 | B92: 16/11/2025 | C92: FCA 00711-07857310 | D92: AUTOPISTAS DEL SOL SA | E92: 30677237119 | F92: RI | G92: 0 | H92: 0 | I92: 0 | J92: 7510.97 | K92: 0 | L92: 0 | M92: 0 | N92: 1577.3 | O92: 0 | P92: 0 | Q92: 0 | R92: 0 | S92: 225.33 | T92: 300.44 | U92: =SUM(G92:T92) -> 9614.04 | V92: Servicios | W92: Buenos Aires
A93: 19/11/2025 | B93: 19/11/2025 | C93: FCA 01001-00000604 | D93: RAKE S.A. | E93: 30707370552 | F93: RI | G93: 0 | H93: 0 | I93: 0 | J93: 1623645.4 | K93: 0 | L93: 0 | M93: 0 | N93: 340965.54 | O93: 0 | P93: 0 | Q93: 0 | R93: 0 | S93: 0 | T93: 0 | U93: =SUM(G93:T93) -> 1964611 | V93: Locaciones | W93: Ciudad de Buenos Aires
A94: 11/11/2025 | B94: 11/11/2025 | C94: FCA 01054-00000391 | D94: DIA ARGENTINA S A | E94: 30685849751 | F94: RI | G94: 0 | H94: 0 | I94: 3248.87 | J94: 2462.81 | K94: 0 | L94: 0 | M94: 0 | N94: 858.32 | O94: 0 | P94: 0 | Q94: 0 | R94: 342.7 | S94: 0 | T94: 0 | U94: =SUM(G94:T94) -> 6912.7 | V94: Bienes | W94: Ciudad de Buenos Aires
A95: 14/11/2025 | B95: 14/11/2025 | C95: FCA 01054-00000393 | D95: DIA ARGENTINA S A | E95: 30685849751 | F95: RI | G95: 0 | H95: 0 | I95: 0 | J95: 4223.14 | K95: 0 | L95: 0 | M95: 0 | N95: 886.86 | O95: 0 | P95: 0 | Q95: 0 | R95: 168.93 | S95: 0 | T95: 0 | U95: =SUM(G95:T95) -> 5278.93 | V95: Bienes | W95: Ciudad de Buenos Aires
A96: 17/11/2025 | B96: 17/11/2025 | C96: FCA 01054-00000396 | D96: DIA ARGENTINA S A | E96: 30685849751 | F96: RI | G96: 0 | H96: 0 | I96: 3248.87 | J96: 8449.59 | K96: 0 | L96: 0 | M96: 0 | N96: 2115.54 | O96: 0 | P96: 0 | Q96: 0 | R96: 467.94 | S96: 0 | T96: 0 | U96: =SUM(G96:T96) -> 14281.94 | V96: Bienes | W96: Ciudad de Buenos Aires
A97: 19/11/2025 | B97: 19/11/2025 | C97: FCA 01054-00000398 | D97: DIA ARGENTINA S A | E97: 30685849751 | F97: RI | G97: 0 | H97: 0 | I97: 0 | J97: 5304.97 | K97: 0 | L97: 0 | M97: 0 | N97: 1114.04 | O97: 0 | P97: 0 | Q97: 0 | R97: 212.2 | S97: 0 | T97: 0 | U97: =SUM(G97:T97) -> 6631.21 | V97: Bienes | W97: Ciudad de Buenos Aires
A98: 20/11/2025 | B98: 20/11/2025 | C98: FCA 01054-00000404 | D98: DIA ARGENTINA S A | E98: 30685849751 | F98: RI | G98: 0 | H98: 0 | I98: 0 | J98: 7892.56 | K98: 0 | L98: 0 | M98: 0 | N98: 1657.44 | O98: 0 | P98: 0 | Q98: 0 | R98: 315.7 | S98: 0 | T98: 0 | U98: =SUM(G98:T98) -> 9865.7 | V98: Bienes | W98: Ciudad de Buenos Aires
... A103: 21/11/2025 | B103: 21/11/2025 | C103: FCA 02168-00025475 | D103: COTO CICSA | E103: 30548083156 | F103: RI | G103: 0 | H103: 0 | I103: 37101.25 | J103: 2426.52 | K103: 0 | L103: 0 | M103: 0 | N103: 4405.2 | O103: 72.8 | P103: 0 | Q103: 0 | R103: 556.52 | S103: 305.3 | T103: 0 | U103: =SUM(G103:T103) -> 44867.59 | V103: Bienes | W103: Buenos Aires
A104: 10/11/2025 | B104: 10/11/2025 | C104: FCA 02399-00085991 | D104: CORREO OFICIAL DE LA REPUBLICA ARGENTINA SOCIEDAD ANONIMA | E104: 30708574836 | F104: RI | G104: 0 | H104: 0 | I104: 0 | J104: 0 | K104: 0 | L104: 20900 | M104: 0 | N104: 0 | O104: 0 | P104: 0 | Q104: 0 | R104: 0 | S104: 0 | T104: 0 | U104: =SUM(G104:T104) -> 20900 | V104: Servicios | W104: 81
A105: 26/11/2025 | B105: 26/11/2025 | C105: FCA 02399-00086058 | D105: CORREO OFICIAL DE LA REPUBLICA ARGENTINA SOCIEDAD ANONIMA | E105: 30708574836 | F105: RI | G105: 0 | H105: 0 | I105: 0 | J105: 0 | K105: 0 | L105: 35800 | M105: 0 | N105: 0 | O105: 0 | P105: 0 | Q105: 0 | R105: 0 | S105: 0 | T105: 0 | U105: =SUM(G105:T105) -> 35800 | V105: Servicios | W105: 81
A106: 25/11/2025 | B106: 25/11/2025 | C106: FCA 02399-00086090 | D106: CORREO OFICIAL DE LA REPUBLICA ARGENTINA SOCIEDAD ANONIMA | E106: 30708574836 | F106: RI | G106: 0 | H106: 0 | I106: 0 | J106: 0 | K106: 0 | L106: 25400 | M106: 0 | N106: 0 | O106: 0 | P106: 0 | Q106: 0 | R106: 0 | S106: 0 | T106: 0 | U106: =SUM(G106:T106) -> 25400 | V106: Servicios | W106: 81
A107: 10/11/2025 | B107: 10/11/2025 | C107: FCA 02434-00080459 | D107: CORREO OFICIAL DE LA REPUBLICA ARGENTINA SOCIEDAD ANONIMA | E107: 30708574836 | F107: RI | G107: 0 | H107: 0 | I107: 0 | J107: 0 | K107: 0 | L107: 19950 | M107: 0 | N107: 0 | O107: 0 | P107: 0 | Q107: 0 | R107: 0 | S107: 0 | T107: 0 | U107: =SUM(G107:T107) -> 19950 | V107: Servicios | W107: 81
A108: 13/11/2025 | B108: 13/11/2025 | C108: FCA 02434-00080482 | D108: CORREO OFICIAL DE LA REPUBLICA ARGENTINA SOCIEDAD ANONIMA | E108: 30708574836 | F108: RI | G108: 0 | H108: 0 | I108: 0 | J108: 0 | K108: 0 | L108: 19950 | M108: 0 | N108: 0 | O108: 0 | P108: 0 | Q108: 0 | R108: 0 | S108: 0 | T108: 0 | U108: =SUM(G108:T108) -> 19950 | V108: Servicios | W108: 81
A109: 02/11/2025 | B109: 19/11/2025 | C109: FCA 03051-00999290 | D109: TELEFONICA MOVILES ARG SA | E109: 30678814357 | F109: RI | G109: 0 | H109: 0 | I109: 0 | J109: 0 | K109: 60327 | L109: 0 | M109: 0 | N109: 16288.29 | O109: 3174.07 | P109: 0 | Q109: 0 | R109: 0 | S109: 4349.89 | T109: 0 | U109: =SUM(G109:T109) -> 84139.25 | V109: Servicios | W109: Buenos Aires
A110: 09/11/2025 | B110: 09/11/2025 | C110: FCA 03101-00407272 | D110: TELEFONICA MOVILES ARG SA | E110: 30678814357 | F110: RI | G110: 0 | H110: 0 | I110: 0 | J110: 0 | K110: 70275.86 | L110: 0 | M110: 0 | N110: 18974.48 | O110: 0 | P110: 0 | Q110: 0 | R110: 0 | S110: 2108.28 | T110: 2811.03 | U110: =SUM(G110:T110) -> 94169.65 | V110: Servicios | W110: Buenos Aires
A111: 28/11/2025 | B111: 28/11/2025 | C111: FCA 03950-05597068 | D111: TELECOM ARGENTINA SA | E111: 30639453738 | F111: RI | G111: 0 | H111: 0 | I111: 0 | J111: 52988.43 | K111: 0 | L111: 0 | M111: 0 | N111: 11127.57 | O111: 0 | P111: 0 | Q111: 0 | R111: 0 | S111: 1589.66 | T111: 2119.54 | U111: =SUM(G111:T111) -> 67825.2 | V111: Servicios | W111: Buenos Aires
...

Sheet arcasss
B2: PEAJES | H2: FA-A | I2: 118
B3: ok contabil | H3: NC-A | I3: 8 | L3: 8
H4: FA-C | I4: 25 | L4: 25
H5: NC-C | I5: 2 | L5: 2
H6: TOTAL COMP | I6: =SUBTOTAL(9,I2:I5) -> 153
H7: total contabilium | I7: 149
A9: Fecha | B9: Tipo | C9: Punto de Venta | D9: Número Desde | E9: Número Hasta | F9: Cód. Autorización | G9: Tipo Doc. Emisor | H9: Nro. Doc. Emisor | I9: Denominación Emisor | J9: Tipo Doc. Receptor | K9: Nro. Doc. Receptor | L9: Tipo Cambio | M9: Moneda | N9: Neto Grav. IVA 0% | O9: IVA 2,5% | P9: Neto Grav. IVA 2,5% | Q9: IVA 5% | R9: Neto Grav. IVA 5% | S9: IVA 10,5% | T9: Neto Grav. IVA 10,5% | U9: IVA 21% | V9: Neto Grav. IVA 21% | W9: IVA 27% | X9: Neto Grav. IVA 27% | Y9: Neto Gravado Total | Z9: Neto No Gravado | AA9: Op. Exentas | AB9: Otros Tributos | AC9: Total IVA | AD9: Imp. Total | AE9: comp
A10: 01/10/2025 | B10: 1 - Factura A | C10: 500 | D10: 1791477 | E10: 1791477 | F10: 75397766663182 | G10: CUIT | H10: 30654118767 | I10: SOLUCIONES MULTIMEDIA S A | J10: CUIT | K10: 30710473168 | L10: 1 | M10: $ | U10: 34781 | V10: 165623.79 | Y10: 165623.79 | Z10: 0 | AA10: 0 | AB10: 6624.95 | AC10: 34781 | AD10: 207029.74
A11: 01/10/2025 | B11: 1 - Factura A | C11: 2059 | D11: 34131 | E11: 34131 | F11: 75406205517570 | G11: CUIT | H11: 30548083156 | I11: COTO CENTRO INTEGRAL DE COMERCIALIZACION SOCIEDAD ANONIMA | J11: CUIT | K11: 30710473168 | L11: 1 | M11: $ | U11: 1150.88 | V11: 5480.36 | Y11: 5480.36 | Z11: 0 | AA11: 0 | AB11: 383.62 | AC11: 1150.88 | AD11: 7014.86
A12: 01/10/2025 | B12: 1 - Factura A | C12: 5 | D12: 1679 | E12: 1679 | F12: 75405209208340 | G12: CUIT | H12: 27265302225 | I12: PRADO MARISOL | J12: CUIT | K12: 30710473168 | L12: 1 | M12: $ | U12: 26250 | V12: 125000 | Y12: 125000 | Z12: 0 | AA12: 0 | AB12: 0 | AC12: 26250 | AD12: 151250
A13: 01/10/2025 | B13: 1 - Factura A | C13: 1 | D13: 140551 | E13: 140551 | F13: 75409140621749 | G13: CUIT | H13: 30714864269 | I13: CONTABILIUM S.A. S. A. | J13: CUIT | K13: 30710473168 | L13: 1 | M13: $ | U13: 38808 | V13: 184800 | Y13: 184800 | Z13: 0 | AA13: 0 | AB13: 0 | AC13: 38808 | AD13: 223608
A14: 01/10/2025 | B14: 1 - Factura A | C14: 5 | D14: 1680 | E14: 1680 | F14: 75405214018996 | G14: CUIT | H14: 27265302225 | I14: PRADO MARISOL | J14: CUIT | K14: 30710473168 | L14: 1 | M14: $ | U14: 294000 | V14: 1400000 | Y14: 1400000 | Z14: 0 | AA14: 0 | AB14: 0 | AC14: 294000 | AD14: 1694000
A15: 01/10/2025 | B15: 1 - Factura A | C15: 5 | D15: 1676 | E15: 1676 | F15: 75405186336334 | G15: CUIT | H15: 27265302225 | I15: PRADO MARISOL | J15: CUIT | K15: 30710473168 | L15: 1 | M15: $ | U15: 525000 | V15: 2500000 | Y15: 2500000 | Z15: 0 | AA15: 0 | AB15: 0 | AC15: 525000 | AD15: 3025000
A16: 01/10/2025 | B16: 1 - Factura A | C16: 6 | D16: 96490 | E16: 96490 | F16: 75404218156994 | G16: CUIT | H16: 30711553564 | I16: SALUDTEX SA | J16: CUIT | K16: 30710473168 | L16: 1 | M16: $ | U16: 279778.59 | V16: 1332279 | Y16: 1332279 | Z16: 0 | AA16: 0 | AB16: 0 | AC16: 279778.59 | AD16: 1612057.6
A17: 01/10/2025 | B17: 1 - Factura A | C17: 6 | D17: 96491 | E17: 96491 | F17: 75404218271756 | G17: CUIT | H17: 30711553564 | I17: SALUDTEX SA | J17: CUIT | K17: 30710473168 | L17: 1 | M17: $ | U17: 147536.55 | V17: 702555 | Y17: 702555 | Z17: 0 | AA17: 0 | AB17: 0 | AC17: 147536.55 | AD17: 850091.55
A18: 01/10/2025 | B18: 1 - Factura A | C18: 6 | D18: 96492 | E18: 96492 | F18: 75404218424004 | G18: CUIT | H18: 30711553564 | I18: SALUDTEX SA | J18: CUIT | K18: 30710473168 | L18: 1 | M18: $ | U18: 6460.65 | V18: 30765 | Y18: 30765 | Z18: 0 | AA18: 0 | AB18: 0 | AC18: 6460.65 | AD18: 37225.65
A19: 15/10/2025 | B19: 1 - Factura A | C19: 50 | D19: 4670040 | E19: 4670040 | F19: 75426230181879 | G19: CUIT | H19: 30714112836 | I19: AUTOPISTAS DE BUENOS AIRES (AUBASA) SA S. A. | J19: CUIT | K19: 30710473168 | L19: 1 | M19: $ | U19: 1031.36 | V19: 4911.22 | Y19: 4911.22 | Z19: 0 | AA19: 0 | AB19: 147.34 | AC19: 1031.36 | AD19: 6089.92
A20: 31/10/2025 | B20: 1 - Factura A | C20: 50 | D20: 4706524 | E20: 4706524 | F20: 75446229190253 | G20: CUIT | H20: 30714112836 | I20: AUTOPISTAS DE BUENOS AIRES (AUBASA) SA S. A. | J20: CUIT | K20: 30710473168 | L20: 1 | M20: $ | U20: 343.78 | V20: 1637.07 | Y20: 1637.07 | Z20: 0 | AA20: 0 | AB20: 0 | AC20: 343.78 | AD20: 1980.85 | AE20: sin comp
A21: 01/10/2025 | B21: 1 - Factura A | C21: 2 | D21: 252 | E21: 252 | F21: 75402211250599 | G21: CUIT | H21: 30605344352 | I21: CONSORCIO BARTOLOME MITRE 2466 | J21: CUIT | K21: 30710473168 | L21: 1 | M21: $ | U21: 453722.01 | V21: 2160581 | Y21: 2160581 | Z21: 0 | AA21: 0 | AB21: 0 | AC21: 453722.01 | AD21: 2614303
A22: 01/10/2025 | B22: 3 - Nota de Crédito A | C22: 5 | D22: 131 | E22: 131 | F22: 75405208440708 | G22: CUIT | H22: 27265302225 | I22: PRADO MARISOL | J22: CUIT | K22: 30710473168 | L22: 1 | M22: $ | U22: 525000 | V22: 2500000 | Y22: 2500000 | Z22: 0 | AA22: 0 | AB22: 0 | AC22: 525000 | AD22: 3025000
A23: 01/10/2025 | B23: 3 - Nota de Crédito A | C23: 6 | D23: 13998 | E23: 13998 | F23: 75404232088366 | G23: CUIT | H23: 30711553564 | I23: SALUDTEX SA | J23: CUIT | K23: 30710473168 | L23: 1 | M23: $ | U23: 28978.11 | V23: 137991 | Y23: 137991 | Z23: 0 | AA23: 0 | AB23: 0 | AC23: 28978.11 | AD23: 166969.11
A24: 01/10/2025 | B24: 11 - Factura C | C24: 4 | D24: 67 | E24: 67 | F24: 75403183061118 | G24: CUIT | H24: 20086277523 | I24: GUASCH HECTOR RAUL | J24: CUIT | K24: 30710473168 | L24: 1 | M24: $ | AB24: 0 | AD24: 300000
A25: 01/10/2025 | B25: 11 - Factura C | C25: 4 | D25: 66 | E25: 66 | F25: 75403179949716 | G25: CUIT | H25: 20086277523 | I25: BOTINDARI JUAN CARLOS | J25: CUIT | K25: 30710473168 | L25: 1 | M25: $ | AB25: 0 | AD25: 300000
A26: 01/10/2025 | B26: 13 - Nota de Crédito C | C26: 4 | D26: 2 | E26: 2 | F26: 75403184483403 | G26: CUIT | H26: 20086277523 | I26: BOTINDARI JUAN CARLOS | J26: CUIT | K26: 30710473168 | L26: 1 | M26: $ | AB26: 0 | AD26: 300000
A27: 02/10/2025 | B27: 1 - Factura A | C27: 3051 | D27: 982461 | E27: 982461 | F27: 75407377852221 | G27: CUIT | H27: 30678814357 | I27: TELEFONICA MOVILES ARGENTINA SOCIEDAD ANONIMA | J27: CUIT | K27: 30710473168 | L27: 1 | M27: $ | W27: 15634.89 | X27: 57907 | Y27: 57907 | Z27: 0 | AA27: 0 | AB27: 7223.1 | AC27: 15634.89 | AD27: 80764.99
A28: 02/10/2025 | B28: 1 - Factura A | C28: 8 | D28: 476 | E28: 476 | F28: 75404371927575 | G28: CUIT | H28: 30643518364 | I28: FARMACIA DE MEDRANO 533 SOCIEDAD EN COMANDITA SIMPLE | J28: CUIT | K28: 30710473168 | L28: 1 | M28: $ | U28: 18637.5 | V28: 88750 | Y28: 88750 | Z28: 0 | AA28: 0 | AB28: 0 | AC28: 18637.5 | AD28: 107387.5
A29: 02/10/2025 | B29: 1 - Factura A | C29: 2 | D29: 1576 | E29: 1576 | F29: 75409356956133 | G29: CUIT | H29: 20272865869 | I29: DI FEO MARTIN EZEQUIEL | J29: CUIT | K29: 30710473168 | L29: 1 | M29: $ | U29: 14574 | V29: 69400 | Y29: 69400 | Z29: 0 | AA29: 0 | AB29: 0 | AC29: 14574 | AD29: 83974
A30: 02/10/2025 | B30: 1 - Factura A | C30: 17 | D30: 13744 | E30: 13744 | F30: 75400375536461 | G30: CUIT | H30: 30661143610 | I30: ORTOPEDIA BERNAT SRL | J30: CUIT | K30: 30710473168 | L30: 1 | M30: $ | U30: 21588 | V30: 102800 | Y30: 102800 | Z30: 0 | AA30: 0 | AB30: 4112 | AC30: 21588 | AD30: 128500
A31: 02/10/2025 | B31: 1 - Factura A | C31: 4 | D31: 19861 | E31: 19861 | F31: 75403288996009 | G31: CUIT | H31: 30714440183 | I31: INDUSTRIAS FERNANDEZ GARRIDO SA | J31: CUIT | K31: 30710473168 | L31: 1 | M31: $ | U31: 5684.76 | V31: 27070.3 | Y31: 27070.3 | Z31: 0 | AA31: 0 | AB31: 0 | AC31: 5684.76 | AD31: 32755.06
A32: 02/10/2025 | B32: 1 - Factura A | C32: 1 | D32: 1031096 | E32: 1031096 | F32: 75419072334708 | G32: CUIT | H32: 33716307749 | I32: VERISURE ARGENTINA MONITOREO DE ALARMAS SA | J32: CUIT | K32: 30710473168 | L32: 1 | M32: $ | U32: 13093.29 | V32: 62349.01 | Y32: 62349.01 | Z32: 0 | AA32: 0 | AB32: 2493.96 | AC32: 13093.29 | AD32: 77936.26
A33: 02/10/2025 | B33: 1 - Factura A | C33: 7 | D33: 55 | E33: 55 | F33: 75403337698338 | G33: CUIT | H33: 27325223273 | I33: SOUSA ALDERETE ALEJANDRA MABEL | J33: CUIT | K33: 30710473168 | L33: 1 | M33: $ | U33: 462000 | V33: 2200000 | Y33: 2200000 | Z33: 0 | AA33: 0 | AB33: 0 | AC33: 462000 | AD33: 2662000
A34: 02/10/2025 | B34: 11 - Factura C | C34: 1 | D34: 43 | E34: 43 | F34: 75401342703675 | G34: CUIT | H34: 20311855671 | I34: GUASCH HECTOR RAUL | J34: CUIT | K34: 30710473168 | L34: 1 | M34: $ | AB34: 0 | AD34: 290000
A35: 03/10/2025 | B35: 1 - Factura A | C35: 2 | D35: 1582 | E35: 1582 | F35: 75409440515122 | G35: CUIT | H35: 20272865869 | I35: DI FEO MARTIN EZEQUIEL | J35: CUIT | K35: 30710473168 | L35: 1 | M35: $ | U35: 64932 | V35: 309200 | Y35: 309200 | Z35: 0 | AA35: 0 | AB35: 0 | AC35: 64932 | AD35: 374132
A36: 03/10/2025 | B36: 1 - Factura A | C36: 26 | D36: 215680 | E36: 215680 | F36: 75407512016610 | G36: CUIT | H36: 30708847247 | I36: EXPRESO LANCIONI S.A. | J36: CUIT | K36: 30710473168 | L36: 1 | M36: $ | U36: 15703.62 | V36: 74779.14 | Y36: 74779.14 | Z36: 0 | AA36: 0 | AB36: 2991.17 | AC36: 15703.62 | AD36: 93473.93
A37: 03/10/2025 | B37: 1 - Factura A | C37: 5 | D37: 1682 | E37: 1682 | F37: 75405522210939 | G37: CUIT | H37: 27265302225 | I37: PRADO MARISOL | J37: CUIT | K37: 30710473168 | L37: 1 | M37: $ | U37: 262500 | V37: 1250000 | Y37: 1250000 | Z37: 0 | AA37: 0 | AB37: 0 | AC37: 262500 | AD37: 1512500
A38: 03/10/2025 | B38: 1 - Factura A | C38: 1054 | D38: 381 | E38: 381 | F38: 75401449551620 | G38: CUIT | H38: 30685849751 | I38: DIA ARGENTINA S A | J38: CUIT | K38: 30710473168 | L38: 1 | M38: $ | U38: 1133.31 | V38: 5396.69 | Y38: 5396.69 | Z38: 0 | AA38: 0 | AB38: 215.87 | AC38: 1133.31 | AD38: 6745.87
A39: 03/10/2025 | B39: 1 - Factura A | C39: 3 | D39: 930 | E39: 930 | F39: 75409454635742 | G39: CUIT | H39: 23076996989 | I39: GIULIETTI LUIS ALBERTO | J39: CUIT | K39: 30710473168 | L39: 1 | M39: $ | U39: 2776.86 | V39: 13223.14 | Y39: 13223.14 | Z39: 0 | AA39: 0 | AB39: 0 | AC39: 2776.86 | AD39: 16000
A40: 03/10/2025 | B40: 3 - Nota de Crédito A | C40: 5 | D40: 132 | E40: 132 | F40: 75405520316587 | G40: CUIT | H40: 27265302225 | I40: PRADO MARISOL | J40: CUIT | K40: 30710473168 | L40: 1 | M40: $ | U40: 26250 | V40: 125000 | Y40: 125000 | Z40: 0 | AA40: 0 | AB40: 0 | AC40: 26250 | AD40: 151250
A41: 03/10/2025 | B41: 11 - Factura C | C41: 2 | D41: 634 | E41: 634 | F41: 75407495074987 | G41: CUIT | H41: 20247881957 | I41: CAMPA DANIEL JORGE | J41: CUIT | K41: 30710473168 | L41: 1 | M41: $ | AB41: 0 | AD41: 13400
A42: 04/10/2025 | B42: 11 - Factura C | C42: 2 | D42: 138 | E42: 138 | F42: 75408636655570 | G42: CUIT | H42: 27315710508 | I42: RIVERO GABRIELA ROCIO | J42: CUIT | K42: 30710473168 | L42: 1 | M42: $ | AB42: 0 | AD42: 51030
A43: 06/10/2025 | B43: 1 - Factura A | C43: 17 | D43: 3413 | E43: 3413 | F43: 75401861436133 | G43: CUIT | H43: 30711764921 | I43: RELIEF CENTER S.R.L. | J43: CUIT | K43: 30710473168 | L43: 1 | M43: $ | U43: 44110.71 | V43: 210051 | Y43: 210051 | Z43: 0 | AA43: 0 | AB43: 0 | AC43: 44110.71 | AD43: 254161.71
A44: 06/10/2025 | B44: 1 - Factura A | C44: 120 | D44: 5947 | E44: 5947 | F44: 75405819860121 | G44: CUIT | H44: 30587197215 | I44: PANATEL SOCIEDAD ANONIMA | J44: CUIT | K44: 30710473168 | L44: 1 | M44: $ | U44: 31239.67 | V44: 148760.33 | Y44: 148760.33 | Z44: 0 | AA44: 0 | AB44: 5950.41 | AC44: 31239.67 | AD44: 185950.41
A45: 06/10/2025 | B45: 11 - Factura C | C45: 2 | D45: 380 | E45: 380 | F45: 75418135005567 | G45: CUIT | H45: 27265832178 | I45: BLASCO MARIA GUADALUPE | J45: CUIT | K45: 30710473168 | L45: 1 | M45: $ | AB45: 0 | AD45: 3200000
A46: 07/10/2025 | B46: 1 - Factura A | C46: 15 | D46: 5031 | E46: 5031 | F46: 75403963974821 | G46: CUIT | H46: 30688140923 | I46: COLTEX S R L | J46: CUIT | K46: 30710473168 | L46: 1 | M46: $ | U46: 26619.92 | V46: 126761.5 | Y46: 126761.5 | Z46: 0 | AA46: 0 | AB46: 0 | AC46: 26619.92 | AD46: 153381.42
A47: 07/10/2025 | B47: 1 - Factura A | C47: 3 | D47: 3479058 | E47: 3479058 | F47: 75409982100194 | G47: CUIT | H47: 30712019359 | I47: LINKEDSTORE ARGENTINA S.R.L. | J47: CUIT | K47: 30710473168 | L47: 1 | M47: $ | U47: 3731.23 | V47: 17767.77 | Y47: 17767.77 | Z47: 0 | AB47: 710.72 | AC47: 3731.23 | AD47: 22209.72 | AE47: sin comp
A48: 07/10/2025 | B48: 1 - Factura A | C48: 6 | D48: 3443 | E48: 3443 | F48: 75404953036460 | G48: CUIT | H48: 30715775014 | I48: GRUPO MAXIMUS S.R.L. | J48: CUIT | K48: 30710473168 | L48: 1 | M48: $ | S48: 4028.96 | T48: 38371.04 | Y48: 38371.04 | Z48: 0 | AA48: 0 | AB48: 1534.84 | AC48: 4028.96 | AD48: 43934.84
A49: 07/10/2025 | B49: 11 - Factura C | C49: 1 | D49: 5 | E49: 5 | F49: 75402996095252 | G49: CUIT | H49: 27380284052 | I49: CIVALE PAULA | J49: CUIT | K49: 30710473168 | L49: 1 | M49: $ | AB49: 0 | AD49: 4365000
A50: 07/10/2025 | B50: 11 - Factura C | C50: 1 | D50: 19 | E50: 19 | F50: 75403997414283 | G50: CUIT | H50: 27443612713 | I50: MIGOYA MORIONDO SOFIA | J50: CUIT | K50: 30710473168 | L50: 1 | M50: $ | AB50: 0 | AD50: 870000
A51: 08/10/2025 | B51: 1 - Factura A | C51: 5 | D51: 1694 | E51: 1694 | F51: 75415156068683 | G51: CUIT | H51: 27265302225 | I51: PRADO MARISOL | J51: CUIT | K51: 30710473168 | L51: 1 | M51: $ | U51: 294000 | V51: 1400000 | Y51: 1400000 | Z51: 0 | AA51: 0 | AB51: 0 | AC51: 294000 | AD51: 1694000
A52: 08/10/2025 | B52: 1 - Factura A | C52: 9 | D52: 23056 | E52: 23056 | F52: 75412180556662 | G52: CUIT | H52: 20207044262 | I52: GARCIA HORACIO FERNANDO | J52: CUIT | K52: 30710473168 | L52: 1 | M52: $ | U52: 4915.21 | V52: 23405.78 | Y52: 23405.78 | Z52: 0 | AA52: 0 | AB52: 0 | AC52: 4915.21 | AD52: 28320.99
A53: 08/10/2025 | B53: 1 - Factura A | C53: 2 | D53: 1598 | E53: 1598 | F53: 75419162856166 | G53: CUIT | H53: 20272865869 | I53: DI FEO MARTIN EZEQUIEL | J53: CUIT | K53: 30710473168 | L53: 1 | M53: $ | U53: 14007 | V53: 66700 | Y53: 66700 | Z53: 0 | AA53: 0 | AB53: 0 | AC53: 14007 | AD53: 80707
A54: 08/10/2025 | B54: 1 - Factura A | C54: 1055 | D54: 908 | E54: 908 | F54: 75411108275705 | G54: CUIT | H54: 30685849751 | I54: DIA ARGENTINA S A | J54: CUIT | K54: 30710473168 | L54: 1 | M54: $ | U54: 1135.56 | V54: 5407.44 | Y54: 5407.44 | Z54: 0 | AA54: 0 | AB54: 216.3 | AC54: 1135.56 | AD54: 6759.3
A55: 01/10/2025 | B55: 1 - Factura A | C55: 711 | D55: 7668587 | E55: 7668587 | F55: 35399087215211 | G55: CUIT | H55: 30677237119 | I55: AUTOPISTAS DEL SOL S A | J55: CUIT | K55: 30710473168 | L55: 1 | M55: $ | U55: 1941.32 | V55: 9244.34 | Y55: 9244.34 | Z55: 0 | AA55: 277.33 | AB55: 369.77 | AC55: 1941.32 | AD55: 11832.76
A56: 08/10/2025 | B56: 1 - Factura A | C56: 7 | D56: 56 | E56: 56 | F56: 75413107535128 | G56: CUIT | H56: 27325223273 | I56: SOUSA ALDERETE ALEJANDRA MABEL | J56: CUIT | K56: 30710473168 | L56: 1 | M56: $ | U56: 273000 | V56: 1300000 | Y56: 1300000 | Z56: 0 | AA56: 0 | AB56: 0 | AC56: 273000 | AD56: 1573000
A57: 09/10/2025 | B57: 1 - Factura A | C57: 1055 | D57: 910 | E57: 910 | F57: 75411242633841 | G57: CUIT | H57: 30685849751 | I57: DIA ARGENTINA S A | J57: CUIT | K57: 30710473168 | L57: 1 | M57: $ | U57: 343.64 | V57: 1636.36 | Y57: 1636.36 | Z57: 0 | AA57: 0 | AB57: 0 | AC57: 343.64 | AD57: 1980
A58: 09/10/2025 | B58: 1 - Factura A | C58: 3101 | D58: 390491 | E58: 390491 | F58: 75417293327196 | G58: CUIT | H58: 30678814357 | I58: TELEFONICA MOVILES ARGENTINA SOCIEDAD ANONIMA | J58: CUIT | K58: 30710473168 | L58: 1 | M58: $ | W58: 16530.15 | X58: 61222.8 | Y58: 61222.8 | Z58: 0 | AA58: 0 | AB58: 4285.59 | AC58: 16530.15 | AD58: 82038.54
A59: 09/10/2025 | B59: 1 - Factura A | C59: 2 | D59: 8600 | E59: 8600 | F59: 75418292258895 | G59: CUIT | H59: 30643862928 | I59: OUTLANDISH S R L | J59: CUIT | K59: 30710473168 | L59: 1 | M59: $ | U59: 61923.97 | V59: 294876.03 | Y59: 294876.03 | Z59: 0 | AA59: 0 | AB59: 0 | AC59: 61923.97 | AD59: 356800
A60: 09/10/2025 | B60: 1 - Factura A | C60: 700 | D60: 2758592 | E60: 2758592 | F60: 75412448694790 | G60: CUIT | H60: 30715804812 | I60: CORREDORES VIALES SOCIEDAD ANONIMA | J60: CUIT | K60: 30710473168 | L60: 1 | M60: $ | U60: 2620.76 | V60: 12479.78 | Y60: 12479.78 | Z60: 0 | AA60: 0 | AB60: 499.19 | AC60: 2620.76 | AD60: 15599.73
A61: 09/10/2025 | B61: 1 - Factura A | C61: 6 | D61: 123 | E61: 123 | F61: 75416306146099 | G61: CUIT | H61: 30711610096 | I61: 46 SPEED S.A. | J61: CUIT | K61: 30710473168 | L61: 1 | M61: $ | U61: 181780.2 | V61: 865620 | Y61: 865620 | Z61: 0 | AA61: 0 | AB61: 0 | AC61: 181780.2 | AD61: 1047400.2
A62: 09/10/2025 | B62: 1 - Factura A | C62: 6 | D62: 121 | E62: 121 | F62: 75416296869603 | G62: CUIT | H62: 30711610096 | I62: 46 SPEED S.A. | J62: CUIT | K62: 30710473168 | L62: 1 | M62: $ | U62: 181780.2 | V62: 865620 | Y62: 865620 | Z62: 0 | AA62: 0 | AB62: 0 | AC62: 181780.2 | AD62: 1047400.2
A63: 09/10/2025 | B63: 3 - Nota de Crédito A | C63: 2 | D63: 101 | E63: 101 | F63: 75419233862932 | G63: CUIT | H63: 20272865869 | I63: DI FEO MARTIN EZEQUIEL | J63: CUIT | K63: 30710473168 | L63: 1 | M63: $ | U63: 2793 | V63: 13300 | Y63: 13300 | Z63: 0 | AA63: 0 | AB63: 0 | AC63: 2793 | AD63: 16093
A64: 09/10/2025 | B64: 11 - Factura C | C64: 1 | D64: 30 | E64: 30 | F64: 75415290283482 | G64: CUIT | H64: 27443612705 | I64: MIGOYA MORIONDO MARIA INES | J64: CUIT | K64: 30710473168 | L64: 1 | M64: $ | AB64: 0 | AD64: 900000
A65: 13/10/2025 | B65: 1 - Factura A | C65: 8 | D65: 2509 | E65: 2509 | F65: 75419789475716 | G65: CUIT | H65: 23288035059 | I65: MENDIZABAL RAUL EUGENIO | J65: CUIT | K65: 30710473168 | L65: 1 | M65: $ | U65: 1969.83 | V65: 9380.17 | Y65: 9380.17 | Z65: 0 | AA65: 0 | AB65: 0 | AC65: 1969.83 | AD65: 11350
A66: 13/10/2025 | B66: 1 - Factura A | C66: 2 | D66: 6499 | E66: 6499 | F66: 75417753007542 | G66: CUIT | H66: 20263170017 | I66: ESPERANZA MIGUEL ANGEL | J66: CUIT | K66: 30710473168 | L66: 1 | M66: $ | U66: 3642.89 | V66: 17347.11 | Y66: 17347.11 | Z66: 0 | AA66: 0 | AB66: 0 | AC66: 3642.89 | AD66: 20990 | AE66: sin comp
A67: 13/10/2025 | B67: 1 - Factura A | C67: 3 | D67: 149 | E67: 149 | F67: 75412711422997 | G67: CUIT | H67: 27160577652 | I67: IZQUIERDO MONICA BEATRIZ | J67: CUIT | K67: 30710473168 | L67: 1 | M67: $ | U67: 31433.01 | V67: 149681 | Y67: 149681 | Z67: 0 | AA67: 0 | AB67: 0 | AC67: 31433.01 | AD67: 181114.01 | AE67: sin comp
A68: 14/10/2025 | B68: 1 - Factura A | C68: 2 | D68: 12960 | E68: 12960 | F68: 75412840648970 | G68: CUIT | H68: 30714331082 | I68: ORTOPEDIA CASA ESCALADA S.R.L. | J68: CUIT | K68: 30710473168 | L68: 1 | M68: $ | U68: 9693.43 | V68: 46159.19 | Y68: 46159.19 | Z68: 0 | AA68: 0 | AB68: 0 | AC68: 9693.43 | AD68: 55852.62
A69: 14/10/2025 | B69: 1 - Factura A | C69: 104 | D69: 10864512 | E69: 10864512 | F69: 75412938430375 | G69: CUIT | H69: 30715804812 | I69: CORREDORES VIALES SOCIEDAD ANONIMA | J69: CUIT | K69: 30710473168 | L69: 1 | M69: $ | U69: 873.58 | V69: 4159.94 | Y69: 4159.94 | Z69: 0 | AA69: 0 | AB69: 166.4 | AC69: 873.58 | AD69: 5199.92 | AE69: sin comp
A70: 14/10/2025 | B70: 1 - Factura A | C70: 5 | D70: 6507 | E70: 6507 | F70: 75413860583282 | G70: CUIT | H70: 30715833243 | I70: BIODINAMICA ASISTENCIA S. R. L. | J70: CUIT | K70: 30710473168 | L70: 1 | M70: $ | U70: 79385.25 | V70: 378025 | Y70: 378025 | Z70: 0 | AA70: 0 | AB70: 0 | AC70: 79385.25 | AD70: 457410.25
A71: 14/10/2025 | B71: 1 - Factura A | C71: 7 | D71: 22647 | E71: 22647 | F71: 75418838773231 | G71: CUIT | H71: 30709214078 | I71: REHAVITA S.A. | J71: CUIT | K71: 30710473168 | L71: 1 | M71: $ | S71: 33133.8 | T71: 315560 | Y71: 315560 | Z71: 0 | AA71: 0 | AB71: 0 | AC71: 33133.8 | AD71: 348693.8
A72: 14/10/2025 | B72: 1 - Factura A | C72: 2059 | D72: 34334 | E72: 34334 | F72: 75416897570101 | G72: CUIT | H72: 30548083156 | I72: COTO CENTRO INTEGRAL DE COMERCIALIZACION SOCIEDAD ANONIMA | J72: CUIT | K72: 30710473168 | L72: 1 | M72: $ | U72: 2506.03 | V72: 11933.46 | Y72: 11933.46 | Z72: 0 | AA72: 0 | AB72: 835.34 | AC72: 2506.03 | AD72: 15274.83
A73: 14/10/2025 | B73: 1 - Factura A | C73: 5 | D73: 6509 | E73: 6509 | F73: 75413867140825 | G73: CUIT | H73: 30715833243 | I73: BIODINAMICA ASISTENCIA S. R. L. | J73: CUIT | K73: 30710473168 | L73: 1 | M73: $ | U73: 24195.15 | V73: 115215 | Y73: 115215 | Z73: 0 | AA73: 0 | AB73: 0 | AC73: 24195.15 | AD73: 139410.15
A74: 14/10/2025 | B74: 1 - Factura A | C74: 104 | D74: 10907502 | E74: 10907502 | F74: 75412951609330 | G74: CUIT | H74: 30715804812 | I74: CORREDORES VIALES SOCIEDAD ANONIMA | J74: CUIT | K74: 30710473168 | L74: 1 | M74: $ | U74: 436.79 | V74: 2079.97 | Y74: 2079.97 | Z74: 0 | AA74: 0 | AB74: 83.2 | AC74: 436.79 | AD74: 2599.96 | AE74: sin comp
A75: 14/10/2025 | B75: 1 - Factura A | C75: 6 | D75: 59344 | E75: 59344 | F75: 75418898964636 | G75: CUIT | H75: 30710177658 | I75: TARGET MEDICAL S.A. | J75: CUIT | K75: 30710473168 | L75: 1 | M75: $ | U75: 174709.92 | V75: 831952 | Y75: 831952 | Z75: 0 | AA75: 0 | AB75: 33278.08 | AC75: 174709.92 | AD75: 1039940
A76: 14/10/2025 | B76: 11 - Factura C | C76: 1 | D76: 1 | E76: 1 | F76: 75410883457213 | G76: CUIT | H76: 20421434450 | I76: GALTIERI WALTER QUIMEY | J76: CUIT | K76: 30710473168 | L76: 1 | M76: $ | AB76: 0 | AD76: 260000
A77: 15/10/2025 | B77: 1 - Factura A | C77: 5 | D77: 6522 | E77: 6522 | F77: 75423002311217 | G77: CUIT | H77: 30715833243 | I77: BIODINAMICA ASISTENCIA S. R. L. | J77: CUIT | K77: 30710473168 | L77: 1 | M77: $ | U77: 21621.6 | V77: 102960 | Y77: 102960 | Z77: 0 | AA77: 0 | AB77: 0 | AC77: 21621.6 | AD77: 124581.6
A78: 15/10/2025 | B78: 1 - Factura A | C78: 5 | D78: 6523 | E78: 6523 | F78: 75423008286348 | G78: CUIT | H78: 30715833243 | I78: BIODINAMICA ASISTENCIA S. R. L. | J78: CUIT | K78: 30710473168 | L78: 1 | M78: $ | U78: 7068.76 | V78: 33660.78 | Y78: 33660.78 | Z78: 0 | AA78: 0 | AB78: 0 | AC78: 7068.76 | AD78: 40729.54
A79: 15/10/2025 | B79: 1 - Factura A | C79: 2031 | D79: 230808 | E79: 230808 | F79: 75420966246058 | G79: CUIT | H79: 30516186670 | I79: DEHEZA SOCIEDAD ANONIMA INDUSTRIAL COMERCIAL FINANCIERA INMOBILIARIA | J79: CUIT | K79: 30710473168 | L79: 1 | M79: $ | U79: 10759.37 | V79: 51235.1 | Y79: 51235.1 | Z79: 0 | AA79: 0 | AB79: 16073.15 | AC79: 10759.37 | AD79: 78067.62
A80: 15/10/2025 | B80: 1 - Factura A | C80: 7 | D80: 22677 | E80: 22677 | F80: 75428036459085 | G80: CUIT | H80: 30709214078 | I80: REHAVITA S.A. | J80: CUIT | K80: 30710473168 | L80: 1 | M80: $ | S80: 91963.2 | T80: 875840 | Y80: 875840 | Z80: 0 | AA80: 0 | AB80: 0 | AC80: 91963.2 | AD80: 967803.2
A81: 16/10/2025 | B81: 1 - Factura A | C81: 711 | D81: 7729611 | E81: 7729611 | F81: 35419067819498 | G81: CUIT | H81: 30677237119 | I81: AUTOPISTAS DEL SOL S A | J81: CUIT | K81: 30710473168 | L81: 1 | M81: $ | U81: 1286.11 | V81: 6124.31 | Y81: 6124.31 | Z81: 0 | AA81: 183.73 | AB81: 244.97 | AC81: 1286.11 | AD81: 7839.12
A82: 08/10/2025 | B82: 1 - Factura A | C82: 5015 | D82: 1018189 | E82: 1018189 | F82: 75414111787024 | G82: CUIT | H82: 30574876474 | I82: AUTOPISTAS URBANAS S. A. | J82: CUIT | K82: 30710473168 | L82: 1 | M82: $ | N82: 0.2 | U82: 7536.02 | V82: 35885.79 | Y82: 35885.99 | Z82: 0 | AA82: 0 | AB82: 4665.16 | AC82: 7536.02 | AD82: 48087.17
A83: 15/10/2025 | B83: 1 - Factura A | C83: 5015 | D83: 1027855 | E83: 1027855 | F83: 75424112493005 | G83: CUIT | H83: 30574876474 | I83: AUTOPISTAS URBANAS S. A. | J83: CUIT | K83: 30710473168 | L83: 1 | M83: $ | N83: 0.09 | U83: 3922.3 | V83: 18677.6 | Y83: 18677.69 | Z83: 0 | AA83: 0 | AB83: 2428.09 | AC83: 3922.3 | AD83: 25028.08
A84: 15/10/2025 | B84: 1 - Factura A | C84: 6 | D84: 127 | E84: 127 | F84: 75426020272672 | G84: CUIT | H84: 30711610096 | I84: 46 SPEED S.A. | J84: CUIT | K84: 30710473168 | L84: 1 | M84: $ | U84: 151200 | V84: 720000 | Y84: 720000 | Z84: 0 | AA84: 0 | AB84: 0 | AC84: 151200 | AD84: 871200
A85: 15/10/2025 | B85: 1 - Factura A | C85: 3 | D85: 7009 | E85: 7009 | F85: 75429006101848 | G85: CUIT | H85: 30707042679 | I85: MEDICAL FOAM S.R.L. | J85: CUIT | K85: 30710473168 | L85: 1 | M85: $ | U85: 336126.84 | V85: 1600604 | Y85: 1600604 | Z85: 0 | AA85: 0 | AB85: 0 | AC85: 336126.84 | AD85: 1936730.8
A86: 15/10/2025 | B86: 1 - Factura A | C86: 4 | D86: 555 | E86: 555 | F86: 75425969134392 | G86: CUIT | H86: 20379223185 | I86: AYALA MAURICIO JUAN JOSE | J86: CUIT | K86: 30710473168 | L86: 1 | M86: $ | U86: 41892.9 | V86: 199490 | Y86: 199490 | Z86: 0 | AA86: 0 | AB86: 0 | AC86: 41892.9 | AD86: 241382.9
A87: 16/10/2025 | B87: 1 - Factura A | C87: 2 | D87: 1613 | E87: 1613 | F87: 75429183332107 | G87: CUIT | H87: 20272865869 | I87: DI FEO MARTIN EZEQUIEL | J87: CUIT | K87: 30710473168 | L87: 1 | M87: $ | U87: 32592 | V87: 155200 | Y87: 155200 | Z87: 0 | AA87: 0 | AB87: 0 | AC87: 32592 | AD87: 187792
A88: 16/10/2025 | B88: 1 - Factura A | C88: 5 | D88: 6531 | E88: 6531 | F88: 75423125367040 | G88: CUIT | H88: 30715833243 | I88: BIODINAMICA ASISTENCIA S. R. L. | J88: CUIT | K88: 30710473168 | L88: 1 | M88: $ | U88: 90768.51 | V88: 432231 | Y88: 432231 | Z88: 0 | AA88: 0 | AB88: 0 | AC88: 90768.51 | AD88: 522999.51
A89: 23/10/2025 | B89: 1 - Factura A | C89: 5015 | D89: 1036311 | E89: 1036311 | F89: 75434997968381 | G89: CUIT | H89: 30574876474 | I89: AUTOPISTAS URBANAS S. A. | J89: CUIT | K89: 30710473168 | L89: 1 | M89: $ | N89: 0.22 | U89: 7513.12 | V89: 35776.78 | Y89: 35777 | Z89: 0 | AA89: 0 | AB89: 4650.99 | AC89: 7513.12 | AD89: 47941.11
A90: 31/10/2025 | B90: 1 - Factura A | C90: 5009 | D90: 1680484 | E90: 1680484 | F90: 75444155618397 | G90: CUIT | H90: 30574876474 | I90: AUTOPISTAS URBANAS S. A. | J90: CUIT | K90: 30710473168 | L90: 1 | M90: $ | N90: 0.03 | U90: 1237.13 | V90: 5891.09 | Y90: 5891.12 | Z90: 0 | AA90: =+V90*0.04 -> 235.6436 | AB90: 765.84 | AC90: 1237.13 | AD90: 7894.09 | AE90: sin comp
A91: 16/10/2025 | B91: 11 - Factura C | C91: 2 | D91: 651 | E91: 651 | F91: 75427155899920 | G91: CUIT | H91: 20247881957 | I91: CAMPA DANIEL JORGE | J91: CUIT | K91: 30710473168 | L91: 1 | M91: $ | AB91: 0 | AD91: 21300
A92: 16/10/2025 | B92: 11 - Factura C | C92: 1 | D92: 44 | E92: 44 | F92: 75421150383363 | G92: CUIT | H92: 20311855671 | I92: GUASCH HECTOR RAUL | J92: CUIT | K92: 30710473168 | L92: 1 | M92: $ | AB92: 0 | AD92: 557300
A93: 16/10/2025 | B93: 11 - Factura C | C93: 5 | D93: 183 | E93: 183 | F93: 75429173819933 | G93: CUIT | H93: 27062343449 | I93: FERREIRA LILIANA INES | J93: CUIT | K93: 30710473168 | L93: 1 | M93: $ | AB93: 0 | AD93: 600000
A94: 16/10/2025 | B94: 11 - Factura C | C94: 3 | D94: 12 | E94: 12 | F94: 75420162876634 | G94: CUIT | H94: 20310489930 | I94: OVIEDO LUIS ALBERTO | J94: CUIT | K94: 30710473168 | L94: 1 | M94: $ | AB94: 0 | AD94: 922580
A95: 16/10/2025 | B95: 11 - Factura C | C95: 5 | D95: 184 | E95: 184 | F95: 75429173906219 | G95: CUIT | H95: 27062343449 | I95: FERREIRA LILIANA INES | J95: CUIT | K95: 30710473168 | L95: 1 | M95: $ | AB95: 0 | AD95: 700000
A96: 17/10/2025 | B96: 1 - Factura A | C96: 4 | D96: 88963 | E96: 88963 | F96: 75426318002119 | G96: CUIT | H96: 30714749206 | I96: EBOX S.A. | J96: CUIT | K96: 30710473168 | L96: 1 | M96: $ | S96: 24325.7 | T96: 231673.3 | U96: 355.17 | V96: 1691.3 | Y96: 233364.6 | Z96: 0 | AA96: 0 | AB96: 0 | AC96: 24680.87 | AD96: 258045.47 | AE96: sin comp
A97: 17/10/2025 | B97: 1 - Factura A | C97: 1055 | D97: 918 | E97: 918 | F97: 75421304979446 | G97: CUIT | H97: 30685849751 | I97: DIA ARGENTINA S A | J97: CUIT | K97: 30710473168 | L97: 1 | M97: $ | U97: 343.64 | V97: 1636.36 | Y97: 1636.36 | Z97: 0 | AA97: 0 | AB97: 0 | AC97: 343.64 | AD97: 1980
A98: 17/10/2025 | B98: 3 - Nota de Crédito A | C98: 3 | D98: 503 | E98: 503 | F98: 75429317561410 | G98: CUIT | H98: 30707042679 | I98: MEDICAL FOAM S.R.L. | J98: CUIT | K98: 30710473168 | L98: 1 | M98: $ | U98: 336126.84 | V98: 1600604 | Y98: 1600604 | Z98: 0 | AA98: 0 | AB98: 0 | AC98: 336126.84 | AD98: 1936730.8
A99: 17/10/2025 | B99: 11 - Factura C | C99: 3 | D99: 13 | E99: 13 | F99: 75420308126642 | G99: CUIT | H99: 20310489930 | I99: OVIEDO LUIS ALBERTO | J99: CUIT | K99: 30710473168 | L99: 1 | M99: $ | AB99: 0 | AD99: 500000
A100: 20/10/2025 | B100: 1 - Factura A | C100: 5 | D100: 67 | E100: 67 | F100: 75423624068395 | G100: CUIT | H100: 20929183143 | I100: MA JUN | J100: CUIT | K100: 30710473168 | L100: 1 | M100: $ | U100: 23100 | V100: 110000 | Y100: 110000 | Z100: 0 | AA100: 0 | AB100: 0 | AC100: 23100 | AD100: 133100
A101: 20/10/2025 | B101: 11 - Factura C | C101: 2 | D101: 14 | E101: 14 | F101: 75421570215782 | G101: CUIT | H101: 27344304551 | I101: BOCCACCI MARIA FLORENCIA | J101: CUIT | K101: 30710473168 | L101: 1 | M101: $ | AB101: 0 | AD101: 600000
A102: 20/10/2025 | B102: 11 - Factura C | C102: 2001 | D102: 971 | E102: 971 | F102: 75428615213447 | G102: CUIT | H102: 27167641798 | I102: STEINER FLAVIA ADRIANA | J102: CUIT | K102: 30710473168 | L102: 1 | M102: $ | AB102: 0 | AD102: 170000
...

Sheet Hoja7
A2: Fecha | B2: Tipo | C2: Punto de Venta | D2: Número Desde | E2: Denominación Emisor | F2: CUIT EMISOR | H2: Tipo Doc. Emisor | I2: Nro. Doc. Emisor | K2: Tipo Doc. Receptor | L2: Nro. Doc. Receptor | M2: Tipo Cambio | N2: IVA 10,5% | O2: Neto Grav. IVA 10,5% | P2: IVA 21% | Q2: Neto Grav. IVA 21% | R2: IVA 27% | S2: Neto Grav. IVA 27% | T2: Neto Gravado Total | U2: Neto No Gravado | V2: Op. Exentas | W2: Otros Tributos | X2: Total IVA | Y2: Imp. Total
A3: 03/11/2025 | B3: 11 - Factura C | C3: 4 | D3: 80 | E3: BOTINDARI JUAN CARLOS | F3: 20086277523 | H3: CUIT | I3: 20086277523 | K3: CUIT | L3: 30710473168 | M3: 1 | W3: 0 | Y3: 300000
A4: 03/11/2025 | B4: 03/11/2025 | C4: 03/11/2025 | D4: FCC 00004-00000080 | E4: JUAN CARLOS BOTINDARI | F4: 20086277523 | G4: MO | H4: 0 | I4: 0 | J4: 0 | K4: 0 | L4: 0 | M4: 0 | N4: 300000 | O4: 0 | P4: 0 | Q4: 0 | R4: 0 | S4: 0 | T4: 0 | U4: 0 | V4: 300000 | W4: Bienes | Y4: 300000
A5: 05/11/2025 | B5: 1 - Factura A | C5: 4 | D5: 138 | E5: NARDOMARINO EDUARDO FRANCISCO | F5: 20174004146 | H5: CUIT | I5: 20174004146 | K5: CUIT | L5: 30710473168 | M5: 1 | P5: 56700 | Q5: 270000 | T5: 270000 | U5: 0 | V5: 0 | W5: 0 | X5: 56700 | Y5: 326700
A6: 17/11/2025 | B6: 1 - Factura A | C6: 4 | D6: 141 | E6: NARDOMARINO EDUARDO FRANCISCO | F6: 20174004146 | H6: CUIT | I6: 20174004146 | K6: CUIT | L6: 30710473168 | M6: 1 | P6: 58800 | Q6: 280000 | T6: 280000 | U6: 0 | V6: 0 | W6: 0 | X6: 58800 | Y6: 338800
A7: 18/11/2025 | B7: 1 - Factura A | C7: 4 | D7: 142 | E7: NARDOMARINO EDUARDO FRANCISCO | F7: 20174004146 | H7: CUIT | I7: 20174004146 | K7: CUIT | L7: 30710473168 | M7: 1 | P7: 69825 | Q7: 332500 | T7: 332500 | U7: 0 | V7: 0 | W7: 0 | X7: 69825 | Y7: 402325
A8: 20/11/2025 | B8: 1 - Factura A | C8: 4 | D8: 143 | E8: NARDOMARINO EDUARDO FRANCISCO | F8: 20174004146 | H8: CUIT | I8: 20174004146 | K8: CUIT | L8: 30710473168 | M8: 1 | P8: 55125 | Q8: 262500 | T8: 262500 | U8: 0 | V8: 0 | W8: 0 | X8: 55125 | Y8: 317625
A9: 05/11/2025 | B9: 05/11/2025 | C9: 05/11/2025 | D9: FCA 00004-00000138 | E9: EDUARDO FRANCISCO NARDOMARINO | F9: 20174004146 | G9: RI | H9: 0 | I9: 0 | J9: 0 | K9: 270000 | L9: 0 | M9: 0 | N9: 0 | O9: 56700 | P9: 0 | Q9: 0 | R9: 0 | S9: 0 | T9: 0 | U9: 0 | V9: 326700 | W9: Servicios | Y9: 326700
A10: 27/11/2025 | B10: 11 - Factura C | C10: 9 | D10: 197 | E10: CORRAO HECTOR RUBEN | F10: 20233248283 | H10: CUIT | I10: 20233248283 | K10: CUIT | L10: 30710473168 | M10: 1 | W10: 0 | Y10: 525000
A11: 27/11/2025 | B11: 27/11/2025 | C11: 27/11/2025 | D11: FCC 00009-00000197 | E11: HECTOR RUBEN CORRAO | F11: 20233248283 | G11: MO | H11: 0 | I11: 0 | J11: 0 | K11: 0 | L11: 0 | M11: 0 | N11: 525000 | O11: 0 | P11: 0 | Q11: 0 | R11: 0 | S11: 0 | T11: 0 | U11: 0 | V11: 525000 | Y11: 525000
A12: 11/11/2025 | B12: 1 - Factura A | C12: 9 | D12: 1686 | E12: IALLONARDO SERGIO ALEJANDRO | F12: 20242126158 | H12: CUIT | I12: 20242126158 | K12: CUIT | L12: 30710473168 | M12: 1 | P12: 29400 | Q12: 140000 | T12: 140000 | U12: 0 | V12: 0 | W12: 0 | X12: 29400 | Y12: 169400
A13: 11/11/2025 | B13: 11/11/2025 | C13: 11/11/2025 | D13: FCA 00009-00001686 | E13: SERGIO ALEJANDRO IALLONARDO | F13: 20242126158 | G13: RI | H13: 0 | I13: 0 | J13: 0 | K13: 140000 | L13: 0 | M13: 0 | N13: 0 | O13: 29400 | P13: 0 | Q13: 0 | R13: 0 | S13: 0 | T13: 0 | U13: 0 | V13: 169400 | W13: Bienes | Y13: 169400
A14: 13/11/2025 | B14: 1 - Factura A | C14: 6 | D14: 1672 | E14: VENTO HUGO GABRIEL | F14: 20247225243 | H14: CUIT | I14: 20247225243 | K14: CUIT | L14: 30710473168 | M14: 1 | P14: 34216.14 | Q14: 162934 | T14: 162934 | U14: 0 | V14: 0 | W14: 0 | X14: 34216.14 | Y14: 197150.14
A15: 21/11/2025 | B15: 1 - Factura A | C15: 6 | D15: 1679 | E15: VENTO HUGO GABRIEL | F15: 20247225243 | H15: CUIT | I15: 20247225243 | K15: CUIT | L15: 30710473168 | M15: 1 | P15: 17507.28 | Q15: 83368 | T15: 83368 | U15: 0 | V15: 0 | W15: 0 | X15: 17507.28 | Y15: 100875.28
A16: 25/11/2025 | B16: 1 - Factura A | C16: 6 | D16: 1684 | E16: VENTO HUGO GABRIEL | F16: 20247225243 | H16: CUIT | I16: 20247225243 | K16: CUIT | L16: 30710473168 | M16: 1 | P16: 29595.72 | Q16: 140932 | T16: 140932 | U16: 0 | V16: 0 | W16: 0 | X16: 29595.72 | Y16: 170527.72
A17: 13/11/2025 | B17: 13/11/2025 | C17: 45974 | D17: FCA 00006-00001672 | E17: HUGO GABRIEL VENTO | F17: 20247225243 | G17: RI | H17: 0 | I17: 0 | J17: 0 | K17: 162934 | L17: 0 | M17: 0 | N17: 0 | O17: 34216.14 | P17: 0 | Q17: 0 | R17: 0 | S17: 0 | T17: 0 | U17: 0 | V17: 197150.14 | W17: Bienes | Y17: 197150.14
A18: 25/11/2025 | B18: 25/11/2025 | C18: 45986 | D18: FCA 00006-00001684 | E18: HUGO GABRIEL VENTO | F18: 20247225243 | G18: RI | H18: 0 | I18: 0 | J18: 0 | K18: 140932 | L18: 0 | M18: 0 | N18: 0 | O18: 29595.72 | P18: 0 | Q18: 0 | R18: 0 | S18: 0 | T18: 0 | U18: 0 | V18: 170527.72 | W18: Bienes | Y18: 170527.72
A19: 21/11/2025 | B19: 21/11/2025 | C19: 45982 | D19: FCA 00006-00001679 | E19: HUGO GABRIEL VENTO | F19: 20247225243 | G19: RI | H19: 0 | I19: 0 | J19: 0 | K19: 83368 | L19: 0 | M19: 0 | N19: 0 | O19: 17507.28 | P19: 0 | Q19: 0 | R19: 0 | S19: 0 | T19: 0 | U19: 0 | V19: 100875.28 | W19: Bienes | Y19: 100875.28
A20: 10/11/2025 | B20: 11 - Factura C | C20: 2 | D20: 706 | E20: CAMPA DANIEL JORGE | F20: 20247881957 | H20: CUIT | I20: 20247881957 | K20: CUIT | L20: 30710473168 | M20: 1 | W20: 0 | Y20: 9700
A21: 27/11/2025 | B21: 11 - Factura C | C21: 2 | D21: 751 | E21: CAMPA DANIEL JORGE | F21: 20247881957 | H21: CUIT | I21: 20247881957 | K21: CUIT | L21: 30710473168 | M21: 1 | W21: 0 | Y21: 8500
A22: 10/11/2025 | B22: 10/11/2025 | C22: 10/11/2025 | D22: FCC 00002-00000706 | E22: DANIEL JORGE CAMPA | F22: 20247881957 | G22: MO | H22: 0 | I22: 0 | J22: 0 | K22: 0 | L22: 0 | M22: 0 | N22: 9700 | O22: 0 | P22: 0 | Q22: 0 | R22: 0 | S22: 0 | T22: 0 | U22: 0 | V22: 9700 | W22: Bienes | Y22: 9700
A23: 27/11/2025 | B23: 27/11/2025 | C23: 27/11/2025 | D23: FCC 00002-00000751 | E23: DANIEL JORGE CAMPA | F23: 20247881957 | G23: MO | H23: 0 | I23: 0 | J23: 0 | K23: 0 | L23: 0 | M23: 0 | N23: 8500 | O23: 0 | P23: 0 | Q23: 0 | R23: 0 | S23: 0 | T23: 0 | U23: 0 | V23: 8500 | W23: Bienes | Y23: 8500
A24: 06/11/2025 | B24: 1 - Factura A | C24: 2 | D24: 1649 | E24: DI FEO MARTIN EZEQUIEL | F24: 20272865869 | H24: CUIT | I24: 20272865869 | K24: CUIT | L24: 30710473168 | M24: 1 | P24: 22953 | Q24: 109300 | T24: 109300 | U24: 0 | V24: 0 | W24: 0 | X24: 22953 | Y24: 132253
A25: 12/11/2025 | B25: 1 - Factura A | C25: 2 | D25: 1667 | E25: DI FEO MARTIN EZEQUIEL | F25: 20272865869 | H25: CUIT | I25: 20272865869 | K25: CUIT | L25: 30710473168 | M25: 1 | P25: 26544 | Q25: 126400 | T25: 126400 | U25: 0 | V25: 0 | W25: 0 | X25: 26544 | Y25: 152944
A26: 14/11/2025 | B26: 1 - Factura A | C26: 2 | D26: 1673 | E26: DI FEO MARTIN EZEQUIEL | F26: 20272865869 | H26: CUIT | I26: 20272865869 | K26: CUIT | L26: 30710473168 | M26: 1 | P26: 4095 | Q26: 19500 | T26: 19500 | U26: 0 | V26: 0 | W26: 0 | X26: 4095 | Y26: 23595
A27: 14/11/2025 | B27: 14/11/2025 | C27: FCA 00002-00001673 | E27: DI FEO MARTIN EZEQUIEL | F27: 20272865869 | G27: 0 | H27: 0 | I27: 0 | J27: 19500 | K27: 0 | L27: 0 | M27: 0 | N27: 4095 | O27: 0 | P27: 0 | Q27: 0 | R27: 0 | S27: 0 | T27: 0 | U27: 23595 | V27: Bienes | W27: Buenos Aires | X27: Sin comprobante | Y27: 23595 | Z27: Sin comprobante
A28: 19/11/2025 | B28: 1 - Factura A | C28: 2 | D28: 1686 | E28: DI FEO MARTIN EZEQUIEL | F28: 20272865869 | H28: CUIT | I28: 20272865869 | K28: CUIT | L28: 30710473168 | M28: 1 | P28: 31647 | Q28: 150700 | T28: 150700 | U28: 0 | V28: 0 | W28: 0 | X28: 31647 | Y28: 182347
A29: 20/11/2025 | B29: 1 - Factura A | C29: 2 | D29: 1687 | E29: DI FEO MARTIN EZEQUIEL | F29: 20272865869 | H29: CUIT | I29: 20272865869 | K29: CUIT | L29: 30710473168 | M29: 1 | P29: 3297 | Q29: 15700 | T29: 15700 | U29: 0 | V29: 0 | W29: 0 | X29: 3297 | Y29: 18997
A30: 28/11/2025 | B30: 1 - Factura A | C30: 2 | D30: 1697 | E30: DI FEO MARTIN EZEQUIEL | F30: 20272865869 | H30: CUIT | I30: 20272865869 | K30: CUIT | L30: 30710473168 | M30: 1 | P30: 27511.91 | Q30: 131009.09 | T30: 131009.09 | U30: 0 | V30: 0 | W30: 0 | X30: 27511.91 | Y30: 158521
A31: 06/11/2025 | B31: 06/11/2025 | C31: 06/11/2025 | D31: FCA 00002-00001649 | E31: MARTIN EZEQUIEL DI FEO | F31: 20272865869 | G31: RI | H31: 0 | I31: 0 | J31: 0 | K31: 109300 | L31: 0 | M31: 0 | N31: 0 | O31: 22953 | P31: 0 | Q31: 0 | R31: 0 | S31: 0 | T31: 0 | U31: 0 | V31: 132253 | W31: Bienes | Y31: 132253
A32: 12/11/2025 | B32: 12/11/2025 | C32: 12/11/2025 | D32: FCA 00002-00001667 | E32: MARTIN EZEQUIEL DI FEO | F32: 20272865869 | G32: RI | H32: 0 | I32: 0 | J32: 0 | K32: 126400 | L32: 0 | M32: 0 | N32: 0 | O32: 26544 | P32: 0 | Q32: 0 | R32: 0 | S32: 0 | T32: 0 | U32: 0 | V32: 152944 | W32: Bienes | Y32: 152944
A33: 20/11/2025 | B33: 20/11/2025 | C33: 45981 | D33: FCA 00002-00001687 | E33: MARTIN EZEQUIEL DI FEO | F33: 20272865869 | G33: RI | H33: 0 | I33: 0 | J33: 0 | K33: 15700 | L33: 0 | M33: 0 | N33: 0 | O33: 3297 | P33: 0 | Q33: 0 | R33: 0 | S33: 0 | T33: 0 | U33: 0 | V33: 18997 | W33: Bienes | Y33: 18997
A34: 19/11/2025 | B34: 19/11/2025 | C34: 45980 | D34: FCA 00002-00001686 | E34: MARTIN EZEQUIEL DI FEO | F34: 20272865869 | G34: RI | H34: 0 | I34: 0 | J34: 0 | K34: 150700 | L34: 0 | M34: 0 | N34: 0 | O34: 31647 | P34: 0 | Q34: 0 | R34: 0 | S34: 0 | T34: 0 | U34: 0 | V34: 182347 | W34: Bienes | Y34: 182347
A35: 28/11/2025 | B35: 28/11/2025 | C35: 28/11/2025 | D35: FCA 00002-00001697 | E35: MARTIN EZEQUIEL DI FEO | F35: 20272865869 | G35: RI | H35: 0 | I35: 0 | J35: 0 | K35: 131009.09 | L35: 0 | M35: 0 | N35: 0 | O35: 27511.91 | P35: 0 | Q35: 0 | R35: 0 | S35: 0 | T35: 0 | U35: 0 | V35: 158521 | W35: Bienes | Y35: 158521
A36: 03/11/2025 | B36: 1 - Factura A | C36: 4 | D36: 41612 | E36: LEDESMA EMILIANO RUBEN | F36: 20289111329 | H36: CUIT | I36: 20289111329 | K36: CUIT | L36: 30710473168 | M36: 1 | P36: 357940.09 | Q36: 1704476.6 | T36: 1704476.6 | U36: 0 | V36: 0 | W36: 0 | X36: 357940.09 | Y36: 2062416.7
A37: 28/11/2025 | B37: 1 - Factura A | C37: 4 | D37: 41808 | E37: LEDESMA EMILIANO RUBEN | F37: 20289111329 | H37: CUIT | I37: 20289111329 | K37: CUIT | L37: 30710473168 | M37: 1 | P37: 12700.8 | Q37: 60480 | T37: 60480 | U37: 0 | V37: 0 | W37: 0 | X37: 12700.8 | Y37: 73180.8
A38: 03/11/2025 | B38: 03/11/2025 | C38: 14/11/2025 | D38: FCA 00004-00041612 | E38: EMILIANO RUBEN LEDESMA | F38: 20289111329 | G38: RI | H38: 0 | I38: 0 | J38: 0 | K38: 1704476.6 | L38: 0 | M38: 0 | N38: 0 | O38: 357940.09 | P38: 0 | Q38: 0 | R38: 0 | S38: 0 | T38: 0 | U38: 0 | V38: 2062416.7 | W38: Bienes | Y38: 2062416.7
A39: 28/11/2025 | B39: 28/11/2025 | C39: 28/11/2025 | D39: FCA 00004-00041808 | E39: EMILIANO RUBEN LEDESMA | F39: 20289111329 | G39: RI | H39: 0 | I39: 0 | J39: 0 | K39: 60480 | L39: 0 | M39: 0 | N39: 0 | O39: 12700.8 | P39: 0 | Q39: 0 | R39: 0 | S39: 0 | T39: 0 | U39: 0 | V39: 73180.8 | W39: Bienes | Y39: 73180.8
A40: 13/11/2025 | B40: 11 - Factura C | C40: 3 | D40: 15 | E40: OVIEDO LUIS ALBERTO | F40: 20310489930 | H40: CUIT | I40: 20310489930 | K40: CUIT | L40: 30710473168 | M40: 1 | W40: 0 | Y40: 540580
A41: 28/11/2025 | B41: 11 - Factura C | C41: 3 | D41: 16 | E41: OVIEDO LUIS ALBERTO | F41: 20310489930 | H41: CUIT | I41: 20310489930 | K41: CUIT | L41: 30710473168 | M41: 1 | W41: 0 | Y41: 383580
A42: 13/11/2025 | B42: 13/11/2025 | C42: 13/11/2025 | D42: FCC 00003-00000015 | E42: LUIS ALBERTO OVIEDO | F42: 20310489930 | G42: MO | H42: 0 | I42: 0 | J42: 0 | K42: 0 | L42: 0 | M42: 0 | N42: 540580 | O42: 0 | P42: 0 | Q42: 0 | R42: 0 | S42: 0 | T42: 0 | U42: 0 | V42: 540580 | W42: Bienes | Y42: 540580
A43: 45989 | B43: 45989 | C43: 45989 | D43: FCC 00002-00000016 | E43: LUIS ALBERTO OVIEDO | F43: 20310489930 | G43: MO | H43: 0 | I43: 0 | J43: 0 | K43: 0 | L43: 0 | M43: 0 | N43: 383580 | O43: 0 | P43: 0 | Q43: 0 | R43: 0 | S43: 0 | T43: 0 | U43: 0 | V43: 383580 | W43: Bienes | Y43: 383580
A44: 20/11/2025 | B44: 1 - Factura A | C44: 4 | D44: 179 | E44: VILLALBA MIGUEL ANGEL | F44: 20317488476 | H44: CUIT | I44: 20317488476 | K44: CUIT | L44: 30710473168 | M44: 1 | P44: 189000 | Q44: 900000 | T44: 900000 | U44: 0 | V44: 0 | W44: 0 | X44: 189000 | Y44: 1089000
A45: 20/11/2025 | B45: 20/11/2025 | C45: 20/11/2025 | D45: FCA 00004-00000179 | E45: VILLALBA MIGUEL ANGEL | F45: 20317488476 | G45: RI | H45: 0 | I45: 0 | J45: 0 | K45: 900000 | L45: 0 | M45: 0 | N45: 0 | O45: 189000 | P45: 0 | Q45: 0 | R45: 0 | S45: 0 | T45: 0 | U45: 0 | V45: 1089000 | W45: Bienes de uso | Y45: 1089000
A46: 10/11/2025 | B46: 1 - Factura A | C46: 11 | D46: 142 | E46: LOPEZ DIMITRI CARLOS DANIEL | F46: 20327047354 | H46: CUIT | I46: 20327047354 | K46: CUIT | L46: 30710473168 | M46: 1 | P46: 7809.91 | Q46: 37190.09 | T46: 37190.09 | U46: 0 | V46: 0 | W46: 0 | X46: 7809.91 | Y46: 45000
A47: 45971 | B47: 45971 | C47: 45971 | D47: FCA 00011-00000142 | E47: DIMITRI CARLOS DANIEL LOPEZ | F47: 20327047354 | G47: RI | H47: 0 | I47: 0 | J47: 0 | K47: 37190.09 | L47: 0 | M47: 0 | N47: 0 | O47: 7809.92 | P47: 0 | Q47: 0 | R47: 0 | S47: 0 | T47: 0 | U47: 0 | V47: 45000.01 | Y47: 45000.01
A48: 17/11/2025 | B48: 17/11/2025 | C48: 45978 | D48: FCA 00004-00000141 | E48: NARDOMARINO EDUARDO FRANCISCO | F48: 20174004146 | G48: RI | H48: 0 | I48: 0 | J48: 0 | K48: 280000 | L48: 0 | M48: 0 | N48: 0 | O48: 58800 | P48: 0 | Q48: 0 | R48: 0 | S48: 0 | T48: 0 | U48: 0 | V48: 338800 | W48: Servicios | Y48: 338800
A49: 20/11/2025 | B49: 20/11/2025 | C49: 45981 | D49: FCA 00004-00000143 | E49: NARDOMARINO EDUARDO FRANCISCO | F49: 20174004146 | G49: RI | H49: 0 | I49: 0 | J49: 0 | K49: 262500 | L49: 0 | M49: 0 | N49: 0 | O49: 55125 | P49: 0 | Q49: 0 | R49: 0 | S49: 0 | T49: 0 | U49: 0 | V49: 317625 | W49: Servicios | Y49: 317625
A50: 18/11/2025 | B50: 18/11/2025 | C50: 45979 | D50: FCA 00004-00000142 | E50: NARDOMARINO EDUARDO FRANCISCO | F50: 20174004146 | G50: RI | H50: 0 | I50: 0 | J50: 0 | K50: 332500 | L50: 0 | M50: 0 | N50: 0 | O50: 69825 | P50: 0 | Q50: 0 | R50: 0 | S50: 0 | T50: 0 | U50: 0 | V50: 402325 | W50: Servicios | Y50: 402325
A51: 28/11/2025 | B51: 11 - Factura C | C51: 1 | D51: 2 | E51: GALTIERI WALTER QUIMEY | F51: 20421434450 | H51: CUIT | I51: 20421434450 | K51: CUIT | L51: 30710473168 | M51: 1 | W51: 0 | Y51: 260000
A52: 28/11/2025 | B52: 28/11/2025 | C52: 28/11/2025 | D52: FCC 00001-00000002 | E52: WALTER QUIMEY GALTIERI | F52: 20421434450 | G52: MO | H52: 0 | I52: 0 | J52: 0 | K52: 0 | L52: 0 | M52: 0 | N52: 260000 | O52: 0 | P52: 0 | Q52: 0 | R52: 0 | S52: 0 | T52: 0 | U52: 0 | V52: 260000 | W52: Servicios | Y52: 260000
A53: 18/11/2025 | B53: 1 - Factura A | C53: 5 | D53: 68 | E53: MA JUN | F53: 20929183143 | H53: CUIT | I53: 20929183143 | K53: CUIT | L53: 30710473168 | M53: 1 | P53: 23100 | Q53: 110000 | T53: 110000 | U53: 0 | V53: 0 | W53: 0 | X53: 23100 | Y53: 133100
A54: 18/11/2025 | B54: 18/11/2025 | C54: 45979 | D54: FCA 00005-00000068 | E54: JUN MA | F54: 20929183143 | G54: RI | H54: 0 | I54: 0 | J54: 0 | K54: 110000 | L54: 0 | M54: 0 | N54: 0 | O54: 23100 | P54: 0 | Q54: 0 | R54: 0 | S54: 0 | T54: 0 | U54: 0 | V54: 133100 | W54: Servicios | Y54: 133100
A55: 14/11/2025 | B55: 11 - Factura C | C55: 1 | D55: 87 | E55: DRUETTA ANDREA MARIEL | F55: 23281233084 | H55: CUIT | I55: 23281233084 | K55: CUIT | L55: 30710473168 | M55: 1 | W55: 0 | Y55: 300000
A56: 14/11/2025 | B56: 14/11/2025 | C56: 14/11/2025 | D56: FCC 00001-00000087 | E56: ANDREA MARIEL DRUETTA | F56: 23281233084 | G56: MO | H56: 0 | I56: 0 | J56: 0 | K56: 0 | L56: 0 | M56: 0 | N56: 300000 | O56: 0 | P56: 0 | Q56: 0 | R56: 0 | S56: 0 | T56: 0 | U56: 0 | V56: 300000 | W56: Servicios | Y56: 300000
A57: 03/11/2025 | B57: 1 - Factura A | C57: 2 | D57: 6005 | E57: VIDAL LEONARDO JAVIER | F57: 24253769951 | H57: CUIT | I57: 24253769951 | K57: CUIT | L57: 30710473168 | M57: 1 | P57: 66350.97 | Q57: 315957 | T57: 315957 | U57: 0 | V57: 0 | W57: 0 | X57: 66350.97 | Y57: 382307.97
A58: 03/11/2025 | B58: 03/11/2025 | C58: 14/11/2025 | D58: FCA 00002-00006005 | E58: LEONARDO JAVIER VIDAL | F58: 24253769951 | G58: RI | H58: 0 | I58: 0 | J58: 0 | K58: 315957 | L58: 0 | M58: 0 | N58: 0 | O58: 66350.97 | P58: 0 | Q58: 0 | R58: 0 | S58: 0 | T58: 0 | U58: 0 | V58: 382307.97 | W58: Bienes | Y58: 382307.97
A59: 06/11/2025 | B59: 1 - Factura A | C59: 2 | D59: 289 | E59: SCHEJTER LILA ELISA | F59: 27144282383 | H59: CUIT | I59: 27144282383 | K59: CUIT | L59: 30710473168 | M59: 1 | P59: 14700 | Q59: 70000 | T59: 70000 | U59: 0 | V59: 0 | W59: 0 | X59: 14700 | Y59: 84700
A60: 06/11/2025 | B60: 06/11/2025 | C60: 45967 | D60: FCA 00002-00000289 | E60: SCHEJTER LILA ELISA | F60: 27144282383 | G60: RI | H60: 0 | I60: 0 | J60: 0 | K60: 70000 | L60: 0 | M60: 0 | N60: 0 | O60: 14700 | P60: 0 | Q60: 0 | R60: 0 | S60: 0 | T60: 0 | U60: 0 | V60: 84700 | W60: Servicios | Y60: 84700
A61: 27/11/2025 | B61: 1 - Factura A | C61: 2 | D61: 53 | E61: BARD MARISA SILVIA | F61: 27243660535 | H61: CUIT | I61: 27243660535 | K61: CUIT | L61: 30710473168 | M61: 1 | P61: 102723.84 | Q61: 489161.14 | T61: 489161.14 | U61: 0 | V61: 0 | W61: 0 | X61: 102723.84 | Y61: 591885
A62: 27/11/2025 | B62: 27/11/2025 | C62: 27/11/2025 | D62: FCA 00002-00000053 | E62: BARD MARISA SILVIA | F62: 27243660535 | G62: RI | H62: 0 | I62: 0 | J62: 0 | K62: 489161.16 | L62: 0 | M62: 0 | N62: 0 | O62: 102723.84 | P62: 0 | Q62: 0 | R62: 0 | S62: 0 | T62: 0 | U62: 0 | V62: 591885 | W62: Locaciones | Y62: 591885
A63: 03/11/2025 | B63: 1 - Factura A | C63: 5 | D63: 1705 | E63: PRADO MARISOL | F63: 27265302225 | H63: CUIT | I63: 27265302225 | K63: CUIT | L63: 30710473168 | M63: 1 | P63: 378000 | Q63: 1800000 | T63: 1800000 | U63: 0 | V63: 0 | W63: 0 | X63: 378000 | Y63: 2178000
A64: 03/11/2025 | B64: 03/11/2025 | C64: 03/11/2025 | D64: FCA 00005-00001705 | E64: MARISOL PRADO | F64: 27265302225 | G64: RI | H64: 0 | I64: 0 | J64: 0 | K64: 1800000 | L64: 0 | M64: 0 | N64: 0 | O64: 378000 | P64: 0 | Q64: 0 | R64: 0 | S64: 0 | T64: 0 | U64: 0 | V64: 2178000 | W64: Bienes | Y64: 2178000
A65: 07/11/2025 | B65: 11 - Factura C | C65: 2 | D65: 384 | E65: BLASCO MARIA GUADALUPE | F65: 27265832178 | H65: CUIT | I65: 27265832178 | K65: CUIT | L65: 30710473168 | M65: 1 | W65: 0 | Y65: 3200000
A66: 07/11/2025 | B66: 07/11/2025 | C66: 07/11/2025 | D66: FCC 00002-00000384 | E66: MARIA GUADALUPE BLASCO | F66: 27265832178 | G66: MO | H66: 0 | I66: 0 | J66: 0 | K66: 0 | L66: 0 | M66: 0 | N66: 320000 | O66: 0 | P66: 0 | Q66: 0 | R66: 0 | S66: 0 | T66: 0 | U66: 0 | V66: 320000 | W66: Servicios | Y66: 320000
A67: 06/11/2025 | B67: 11 - Factura C | C67: 2 | D67: 140 | E67: RIVERO GABRIELA ROCIO | F67: 27315710508 | H67: CUIT | I67: 27315710508 | K67: CUIT | L67: 30710473168 | M67: 1 | W67: 0 | Y67: 60000
A68: 06/11/2025 | B68: 06/11/2025 | C68: 06/11/2025 | D68: FCC 00002-00000140 | E68: GABRIELA ROCIO RIVERO | F68: 27315710508 | G68: MO | H68: 0 | I68: 0 | J68: 0 | K68: 0 | L68: 0 | M68: 0 | N68: 60000 | O68: 0 | P68: 0 | Q68: 0 | R68: 0 | S68: 0 | T68: 0 | U68: 0 | V68: 60000 | W68: Servicios | Y68: 60000
A69: 05/11/2025 | B69: 1 - Factura A | C69: 7 | D69: 57 | E69: SOUSA ALDERETE ALEJANDRA MABEL | F69: 27325223273 | H69: CUIT | I69: 27325223273 | K69: CUIT | L69: 30710473168 | M69: 1 | P69: 147000 | Q69: 700000 | T69: 700000 | U69: 0 | V69: 0 | W69: 0 | X69: 147000 | Y69: 847000
A70: 28/11/2025 | B70: 3 - Nota de Crédito A | C70: 7 | D70: 7 | E70: SOUSA ALDERETE ALEJANDRA MABEL | F70: 27325223273 | H70: CUIT | I70: 27325223273 | K70: CUIT | L70: 30710473168 | M70: 1 | P70: 273000 | Q70: 1300000 | T70: 1300000 | U70: 0 | V70: 0 | W70: 0 | X70: 273000 | Y70: 1573000
A71: 05/11/2025 | B71: 05/11/2025 | C71: 45966 | D71: FCA 00007-00000057 | E71: ALEJANDRA MABEL SOUSA ALDERETE | F71: 27325223273 | G71: RI | H71: 0 | I71: 0 | J71: 0 | K71: 700000 | L71: 0 | M71: 0 | N71: 0 | O71: 147000 | P71: 0 | Q71: 0 | R71: 0 | S71: 0 | T71: 0 | U71: 0 | V71: 847000 | W71: Bienes | Y71: 847000
A72: 45989 | B72: 45989 | C72: 45989 | D72: NCA 00007-00000007 | E72: ALEJANDRA MABEL SOUSA ALDERETE | F72: 27325223273 | G72: RI | H72: 0 | I72: 0 | J72: 0 | K72: -130000 | L72: 0 | M72: 0 | N72: 0 | O72: -27300 | P72: 0 | Q72: 0 | R72: 0 | S72: 0 | T72: 0 | U72: 0 | V72: -157300 | W72: Bienes | Y72: -157300
A73: 03/11/2025 | B73: 11 - Factura C | C73: 1 | D73: 196 | E73: CANCINO PAMELA RITA | F73: 27338342840 | H73: CUIT | I73: 27338342840 | K73: CUIT | L73: 30710473168 | M73: 1 | W73: 0 | Y73: 165000
A74: 03/11/2025 | B74: 03/11/2025 | C74: 03/11/2025 | D74: FCC 00001-00000196 | E74: PAMELA RITA CANCINO | F74: 27338342840 | G74: MO | H74: 0 | I74: 0 | J74: 0 | K74: 0 | L74: 0 | M74: 0 | N74: 165000 | O74: 0 | P74: 0 | Q74: 0 | R74: 0 | S74: 0 | T74: 0 | U74: 0 | V74: 165000 | W74: Bienes | Y74: 165000
A75: 28/11/2025 | B75: 11 - Factura C | C75: 2 | D75: 17 | E75: BOCCACCI MARIA FLORENCIA | F75: 27344304551 | H75: CUIT | I75: 27344304551 | K75: CUIT | L75: 30710473168 | M75: 1 | W75: 0 | Y75: 850000
A76: 28/11/2025 | B76: 28/11/2025 | C76: 28/11/2025 | D76: FCC 00002-00000017 | E76: MARIA FLORENCIA BOCCACCI | F76: 27344304551 | G76: MO | H76: 0 | I76: 0 | J76: 0 | K76: 0 | L76: 0 | M76: 0 | N76: 850000 | O76: 0 | P76: 0 | Q76: 0 | R76: 0 | S76: 0 | T76: 0 | U76: 0 | V76: 850000 | W76: Servicios | Y76: 850000
A77: 03/11/2025 | B77: 11 - Factura C | C77: 1 | D77: 6 | E77: CIVALE PAULA | F77: 27380284052 | H77: CUIT | I77: 27380284052 | K77: CUIT | L77: 30710473168 | M77: 1 | W77: 0 | Y77: 4335000
A78: 03/11/2025 | B78: 03/11/2025 | C78: 03/11/2025 | D78: FCC 00001-00000006 | E78: PAULA CIVALE | F78: 27380284052 | G78: MO | H78: 0 | I78: 0 | J78: 0 | K78: 0 | L78: 0 | M78: 0 | N78: 4335000 | O78: 0 | P78: 0 | Q78: 0 | R78: 0 | S78: 0 | T78: 0 | U78: 0 | V78: 4335000 | W78: Servicios | Y78: 4335000
A79: 14/11/2025 | B79: 11 - Factura C | C79: 1 | D79: 31 | E79: MIGOYA MORIONDO MARIA INES | F79: 27443612705 | H79: CUIT | I79: 27443612705 | K79: CUIT | L79: 30710473168 | M79: 1 | W79: 0 | Y79: 900000
A80: 14/11/2025 | B80: 14/11/2025 | C80: 19/11/2025 | D80: FCC 00001-00000031 | E80: MARIA INES MIGOYA MORIONDO | F80: 27443612705 | G80: MO | H80: 0 | I80: 0 | J80: 0 | K80: 0 | L80: 0 | M80: 0 | N80: 900000 | O80: 0 | P80: 0 | Q80: 0 | R80: 0 | S80: 0 | T80: 0 | U80: 0 | V80: 900000 | W80: Locaciones | Y80: 900000
A81: 03/11/2025 | B81: 11 - Factura C | C81: 1 | D81: 20 | E81: MIGOYA MORIONDO SOFIA | F81: 27443612713 | H81: CUIT | I81: 27443612713 | K81: CUIT | L81: 30710473168 | M81: 1 | W81: 0 | Y81: 870000
A82: 03/11/2025 | B82: 03/11/2025 | C82: 14/11/2025 | D82: FCC 00001-00000020 | E82: SOFIA MIGOYA MORIONDO | F82: 27443612713 | G82: MO | H82: 0 | I82: 0 | J82: 0 | K82: 0 | L82: 0 | M82: 0 | N82: 870000 | O82: 0 | P82: 0 | Q82: 0 | R82: 0 | S82: 0 | T82: 0 | U82: 0 | V82: 870000 | W82: Bienes | Y82: 870000
A83: 05/11/2025 | B83: 11 - Factura C | C83: 1 | D83: 7 | E83: OPORTO ZELAYA ANA CECILIA | F83: 27955236861 | H83: CUIT | I83: 27955236861 | K83: CUIT | L83: 30710473168 | M83: 1 | W83: 0 | Y83: 100000
A84: 05/11/2025 | B84: 05/11/2025 | C84: 45966 | D84: FCC 00001-00000007 | E84: ANA CECILIA OPORTO ZELAYA | F84: 27955236861 | G84: MO | H84: 0 | I84: 0 | J84: 0 | K84: 0 | L84: 0 | M84: 0 | N84: 100000 | O84: 0 | P84: 0 | Q84: 0 | R84: 0 | S84: 0 | T84: 0 | U84: 0 | V84: 100000 | Y84: 100000
A85: 04/11/2025 | B85: 1 - Factura A | C85: 2031 | D85: 233913 | E85: DEHEZA SOCIEDAD ANONIMA INDUSTRIAL COMERCIAL FINANCIERA INMOBILIARIA | F85: 30516186670 | H85: CUIT | I85: 30516186670 | K85: CUIT | L85: 30710473168 | M85: 1 | P85: 7036.67 | Q85: 33507.94 | T85: 33507.94 | U85: 0 | V85: 0 | W85: 10845.42 | X85: 7036.67 | Y85: 51390.02
A86: 08/11/2025 | B86: 1 - Factura A | C86: 2049 | D86: 771 | E86: DEHEZA SOCIEDAD ANONIMA INDUSTRIAL COMERCIAL FINANCIERA INMOBILIARIA | F86: 30516186670 | H86: CUIT | I86: 30516186670 | K86: CUIT | L86: 30710473168 | M86: 1 | P86: 10846.1 | Q86: 51648.07 | T86: 51648.07 | U86: 0 | V86: 0 | W86: 16615.74 | X86: 10846.1 | Y86: 79109.91
A87: 04/11/2025 | B87: 04/11/2025 | D87: FCA 02031-00233913 | E87: DEHEZA SOCIEDAD ANONIMA INDUSTRIAL COMERCIAL FINANCIERA INMOBILIARIA | F87: 30516186670 | G87: RI | H87: 0 | I87: 0 | J87: 0 | K87: 33507.94 | L87: 0 | M87: 0 | N87: 0 | O87: 7036.67 | P87: 1005.24 | Q87: 0 | R87: 471.75 | S87: 7701.19 | T87: 1667.24 | U87: 0 | V87: 51390.03 | W87: Servicios | X87: Ciudad de Buenos Aires | Y87: 51390.03
A88: 08/11/2025 | B88: 08/11/2025 | D88: FCA 02049-00000771 | E88: DEHEZA SOCIEDAD ANONIMA INDUSTRIAL COMERCIAL FINANCIERA INMOBILIARIA | F88: 30516186670 | G88: RI | H88: 0 | I88: 0 | J88: 0 | K88: 51648.07 | L88: 0 | M88: 0 | N88: 0 | O88: 10846.09 | P88: 721.54 | Q88: 0 | R88: 0 | S88: 11778.83 | T88: 4115.38 | U88: 0 | V88: 79109.91 | W88: Servicios | X88: Ciudad de Buenos Aires | Y88: 79109.91
A89: 09/11/2025 | B89: 1 - Factura A | C89: 2168 | D89: 25353 | E89: COTO CENTRO INTEGRAL DE COMERCIALIZACION SOCIEDAD ANONIMA | F89: 30548083156 | H89: CUIT | I89: 30548083156 | K89: CUIT | L89: 30710473168 | M89: 1 | N89: 2264.91 | O89: 21570.59 | P89: 4793.22 | Q89: 22824.88 | T89: 44395.47 | U89: 0 | V89: 0 | W89: 2268.08 | X89: 7058.13 | Y89: 53721.68
A90: 21/11/2025 | B90: 1 - Factura A | C90: 2168 | D90: 25475 | E90: COTO CENTRO INTEGRAL DE COMERCIALIZACION SOCIEDAD ANONIMA | F90: 30548083156 | H90: CUIT | I90: 30548083156 | K90: CUIT | L90: 30710473168 | M90: 1 | N90: 3895.63 | O90: 37101.25 | P90: 509.57 | Q90: 2426.52 | T90: 39527.77 | U90: 0 | V90: 0 | W90: 934.62 | X90: 4405.2 | Y90: 44867.59
A91: 09/11/2025 | B91: 09/11/2025 | C91: 10/11/2025 | D91: FCA 02168-00025353 | E91: COTO CICSA | F91: 30548083156 | G91: RI | H91: 0 | I91: 0 | J91: 0 | K91: 44395.47 | L91: 0 | M91: 0 | N91: 0 | O91: 9323.05 | P91: 0 | Q91: 0 | R91: 0 | S91: 0 | T91: 0 | U91: 0 | V91: 53718.52 | W91: Bienes | Y91: 53718.52
A92: 21/11/2025 | B92: 21/11/2025 | C92: 45982 | D92: FCA 02168-00025475 | E92: COTO CICSA | F92: 30548083156 | G92: RI | H92: 0 | I92: 0 | J92: 37101.25 | K92: 2426.52 | L92: 0 | M92: 0 | N92: 0 | O92: 4405.2 | P92: 72.8 | Q92: 0 | R92: 0 | S92: 556.52 | T92: 305.3 | U92: 0 | V92: 44867.59 | W92: Bienes | Y92: 44867.59
A93: 08/11/2025 | B93: 1 - Factura A | C93: 5015 | D93: 1054172 | E93: AUTOPISTAS URBANAS S. A. | F93: 30574876474 | H93: CUIT | I93: 30574876474 | K93: CUIT | L93: 30710473168 | M93: 1 | P93: 3538.07 | Q93: 16847.96 | T93: 16848.02 | U93: 0 | V93: 0 | W93: 2190.23 | X93: 3538.07 | Y93: 22576.32
A94: 16/11/2025 | B94: 1 - Factura A | C94: 5015 | D94: 1069226 | E94: AUTOPISTAS URBANAS S. A. | F94: 30574876474 | H94: CUIT | I94: 30574876474 | K94: CUIT | L94: 30710473168 | M94: 1 | P94: 4396.45 | Q94: 20935.48 | T94: 20935.54 | U94: 0 | V94: 0 | W94: 2721.61 | X94: 4396.45 | Y94: 28053.6
A95: 23/11/2025 | B95: 1 - Factura A | C95: 5015 | D95: 1071690 | E95: AUTOPISTAS URBANAS S. A. | F95: 30574876474 | H95: CUIT | I95: 30574876474 | K95: CUIT | L95: 30710473168 | M95: 1 | P95: 2835.9 | Q95: 13504.27 | T95: 13504.31 | U95: 0 | V95: 0 | W95: 1755.56 | X95: 2835.9 | Y95: 18095.77
A96: 30/11/2025 | B96: 1 - Factura A | C96: 5009 | D96: 1726652 | E96: AUTOPISTAS URBANAS S. A. | F96: 30574876474 | H96: CUIT | I96: 30574876474 | K96: CUIT | L96: 30710473168 | M96: 1 | P96: 1500.95 | Q96: 7147.39 | T96: 7147.41 | U96: 0 | V96: 0 | W96: 929.16 | X96: 1500.95 | Y96: 9577.52
A97: 30/11/2025 | B97: 1 - Factura A | C97: 5015 | D97: 1087035 | E97: AUTOPISTAS URBANAS S. A. | F97: 30574876474 | H97: CUIT | I97: 30574876474 | K97: CUIT | L97: 30710473168 | M97: 1 | P97: 2788.62 | Q97: 13279.13 | T97: 13279.17 | U97: 0 | V97: 0 | W97: 1726.28 | X97: 2788.62 | Y97: 17794.07
A98: 45991 | B98: 45991 | C98: 45991 | D98: FCA 05009-01726652 | E98: AUTOPISTAS URBANAS SA | F98: 30574876474 | G98: RI | H98: 0 | I98: 0 | J98: 0 | K98: 7147.41 | L98: 0 | M98: 0 | N98: 0 | O98: 1500.96 | P98: 0 | Q98: 0 | R98: 0 | S98: 929.16 | T98: 0 | U98: 0 | V98: 9577.53 | W98: Servicios | Y98: 9577.53
A99: 45991 | B99: 45991 | C99: 45991 | D99: FCA 05015-00108735 | E99: AUTOPISTAS URBANAS SA | F99: 30574876474 | G99: RI | H99: 0 | I99: 0 | J99: 0 | K99: 13279.17 | L99: 0 | M99: 0 | N99: 0 | O99: 2788.63 | P99: 0 | Q99: 0 | R99: 0 | S99: 1726.28 | T99: 0 | U99: 0 | V99: 17794.08 | W99: Servicios | Y99: 17794.08
A100: 08/11/2025 | B100: 08/11/2025 | C100: 45969 | D100: FCA 05015-01054172 | E100: AUTOPISTAS URBANAS SA | F100: 30574876474 | G100: RI | H100: 0 | I100: 0 | J100: 0 | K100: 16847.96 | L100: 0 | M100: 0 | N100: 0 | O100: 3538.07 | P100: 0 | Q100: 0 | R100: 0 | S100: 1684.79 | T100: 505.44 | U100: 0 | V100: 22576.26 | W100: Servicios | Y100: 22576.26
A101: 23/11/2025 | B101: 23/11/2025 | C101: 45984 | D101: FCA 05015-01071690 | E101: AUTOPISTAS URBANAS SA | F101: 30574876474 | G101: RI | H101: 0 | I101: 0 | J101: 0 | K101: 13504.27 | L101: 0 | M101: 0 | N101: 0 | O101: 2835.9 | P101: 0 | Q101: 0 | R101: 0 | S101: 1350.43 | T101: 405.13 | U101: 0 | V101: 18095.73 | W101: Servicios | Y101: 18095.73
...
