Workbook

Sheet Lista_CUIT
A1: CUIT | B1: RAZON SOCIAL | C1: Tipo de Gasto | D1: PROVINCIA
A2: 20174004146 | B2: EDUEARDO FRANCISCO NARDOMARINO | C2: FLETE | G2: Mercaderia
A3: 30708555548 | B3: AGH S.A | C3: Insumo | G3: Servicios Gas, Luz, etc.
A4: 20270821 | B4: AGOSTINO, ANA CAROLINA | G4: Gastos catering
A5: 30641659106 | B5: AGRISOL SA | C5: INSUMO | G5: Combustibe
A6: 30709565075 | B6: AGUA Y SANEAMIENTOS ARG SA | C6: SERVICIOS | G6: Gastos Varios
A7: 18149370 | B7: AGÜERO, PATRICIA ALEJANDRA | G7: Gastos seguridad
A8: 20273107526 | B8: AGUERRIDO NAZARENO ISMAEL | G8: Librería
A9: 4399520 | B9: Aguiar Elvira | G9: Gastos mantenimiento
A10: 18139117 | B10: Aguilar Omar Adolfo | G10: Gastos comercializacion
A11: 8208160 | B11: Aguirre Diego | G11: Alquiler
A12: 29803614 | B12: Aguirre Rodrigo | G12: Honorarios contables
A13: 33109633 | B13: AGUIRRE SERGIO SEBASTIAN | G13: Gastos administrativos
A14: 7419183 | B14: AISEMBERG FREDY | G14: Seguro
A15: 30500229973 | B15: AKIAN GRAFICA EDITORA SA | C15: Insumo | G15: Extracto
A16: 33709914109 | B16: ALAN COLLECTION SA | C16: MERCADERIA | G16: Flete
A17: 30710799241 | B17: ALANAR S.R.L. | G17: Honorarios Legales
A18: 20469052 | B18: ALARCON CAPRA, KARINA ANDREA | G18: Insumo
A19: 20267161616 | B19: ALBAJARI DIEGO MARCOS | C19: Gastos Varios | G19: Muebles y Utiles
A20: 30628205090 | B20: ALBAMIE SA | C20: CLIENTE | G20: Otros
A21: 30628205090 | B21: ALBAMIE SA | C21: CLIENTE | G21: Telefonia
A22: 7375725 | B22: ALBANESE, ARTURO ANTONIO | G22: Alojamiento-Varios
A23: 4049033 | B23: Aldazabal Martin Claudio
A24: 10121438 | B24: ALDO SODANO
A25: 5804480 | B25: ALEJANDRA SIFFREDI TORRES SANMARCO
A26: 35376990 | B26: ALEJANDRO DANIEL TORRES
A27: 20236101127 | B27: ALEJANDRO DARIO LOPEZ
A28: 20291929126 | B28: ALEJANDRO MIGUEL DAUBLER
A29: 26472781 | B29: ALEJANDRO, ULISES ISAAC
A30: 30645337979 | B30: ALEXANDER FLEMING SA
A31: 30709604887 | B31: ALFABIS SRL. | C31: Mantenimiento
A32: 4171382 | B32: Alfano Alberico Alejandro
A33: 30711573999 | B33: Alfar Construcciones SA
A34: 20083925680 | B34: ALFREDO DANIEL FERNANDEZ | C34: Gastos Varios
A35: 30656038752 | B35: ALFREDO OMAR POTENZA SRL | C35: INSUMO
A36: 30504563894 | B36: ALI HERMANOS SRL | C36: Insumo
A37: 3751602 | B37: Alicia Lemma
A38: 30602699826 | B38: ALKO SRL
A39: 30715190385 | B39: ALL FEDERAL SA.
A40: 28735023 | B40: ALLARIO, MARTIN EMANUEL
A41: 30716375176 | B41: ALO FER S.A. | C41: INSUMO
A42: 22480839 | B42: ALONSO CLAUDIA MARCELA
A43: 12961417 | B43: ALONSO DE LARA JOSE LUIS
A44: 7768190 | B44: ALONSO FERNANDO LUIS
A45: 30710406037 | B45: ALSINA MARCELO DANIEL SH | C45: PROVEEDOR
A46: 30715678310 | B46: ALTO CALABRIA S.R.L. | C46: COMIDA
A47: 23945042079 | B47: ALVARENGA VILLAR LUIS F | C47: Gastos Varios
A48: 32576384 | B48: ALVAREZ CAROLINA
A49: 32576384 | B49: ALVAREZ CAROLINA
A50: 29871464 | B50: Alvarez Danisa Tatiana
A51: 37433123 | B51: ALVAREZ FIGUEIRA, JHONATAN EMANUEL
A52: 92382512 | B52: ALVAREZ HERRERA ROSA DE LOURDES
A53: 20040616498 | B53: ALVAREZ MARCELINO
A54: 95896286 | B54: ALVAREZ PIMIENTO DAVID
A55: 30710587147 | B55: AMAKOR SA | C55: SERVICIOS
A56: 2383098 | B56: Amalia Mazón Torrijos
A57: 27066271728 | B57: AMENDOLARO MARIA
A58: 27101205733 | B58: AMERELLI MIRTA SUSANA | C58: INSUMO
A59: 27101205733 | B59: AMERELLI MIRTA SUSANA | C59: INSUMO
A60: 30574816870 | B60: AMERICAN EXPRESS ARG SA | C60: EXTRACTO
A61: 8076660 | B61: AMERICO PIANELLI
A62: 6421312 | B62: AMOROS, MONICA DELIA
A63: 30715186655 | B63: Amparo Salud S.R.L.
A64: 30663288497 | B64: AMX ARG SA | C64: SERVICIOS DE INTERNET
A65: 27108310559 | B65: ANA MARIA VALDEZ
A66: 93298160 | B66: ANA NOGA
A67: 30502375535 | B67: ANAVI S.C.A.
A68: 30709251739 | B68: ANDES LINEAS AEREAS SA
A69: 5614493 | B69: Andrade Mesquita Jose
A70: 30710986416 | B70: ANDREES PAPAZIAN Y A.PAPAZIAN SH | C70: INSUMOS
A71: 30710986416 | B71: ANDREES PAPAZIAN Y A.PAPAZIAN SH | C71: INSUMOS
A72: 33878883 | B72: ANDRES RAMON GALEANO
A73: 13223046 | B73: Angelini, Maria Concepcion
A74: 92207472 | B74: ANITA ZULMA PACHECO
A75: 30709948667 | B75: ANTAGGER SRL | C75: INSUMO
A76: 30683702060 | B76: ANTARES INDUST. ORTOP SA | C76: INSUMO
A77: 30715985124 | B77: ANTOLFO S.R.L.
A78: 30691054833 | B78: Apresa Asistencia Y Prestaciones De Salud Sa
A79: 30712000372 | B79: AQUÍ MERCEDES SRL | C79: INSUMO
A80: 30711492409 | B80: AQUINO EDUARDO Y RODRIGUEZ FRANCISCO SOCIEDAD DE HECHO | C80: MERCADERIA
A81: 30714741167 | B81: ARALIMP S.R.L.
A82: 10138957 | B82: ARANA, MARCELLA OFELIA
A83: 20927832136 | B83: ARANCIBIA IBACETA CIPRIANO | C83: Gastos Varios
A84: 37834370 | B84: ARCE BARBARA NOEMI
A85: 5427278 | B85: ARCUSIN BERTA
A86: 27135302835 | B86: ARENAS MONICA MARIEL
A87: 27276671109 | B87: AREVALO LORENA ELIZABETH | C87: Insumo
A88: 30647539226 | B88: ARGENDIVE S.R.L. | C88: INSUMO
A89: 30711597499 | B89: ARGENVODA SA
A90: 30600907553 | B90: ARMAGALLI SA | C90: Gastos Varios
A91: 30709585262 | B91: ARMY TECHNOLOGIES S.A. | C91: Mantenimiento
A92: 27046072060 | B92: Arraztoa, Lili Perla
A93: 30614941509 | B93: ARREDO
A94: 20087048471 | B94: ARRIGO RAUL AGUSTIN
A95: 37004257 | B95: Arroyo Sosa Sandra Rocio
A96: 30560443648 | B96: ARSA ELECTRICIDAD SRL
A97: 30708547790 | B97: ARTELEC ARGENTINA SRL
A98: 30711624402 | B98: ARTES REGIONALES SRL
A99: 30715290835 | B99: ARTYLUZ SRL | C99: Mantenimiento
A100: 20045180620 | B100: ARUGUETE ENRIQUE JORGE | C100: Gastos Varios
...

Sheet Ene-25
B1: LIBRO IVA COMPRAS | G1: ORTOPEDIA GEMINIS S.A. | N1: 45658
B3: TOTAL COMPRAS NETAS | G3: TOTAL CREDITO FISCAL | J3: TOTAL VENTAS NETAS | M3: TOTAL DEBITO FISCAL | P3: RESULTADO
B4: =SUM(compras_mes1[[#Totals],[NETO GRAVADO]])+extracto_banco_mes1[[#Totals],[NETO]] -> 38722844 | G4: =compras_mes1[[#Totals],[IVA 21 %]]+compras_mes1[[#Totals],[IVA 27%]]+compras_mes1[[#Totals],[IVA 10,5%]]+I133 -> 8069136 | J4: =venta_a_mes1[[#Totals],[IMPORTE NETO]]+ventas_b_mes1[[#Totals],[IMPORTE NETO]] -> 0 | M4: =venta_a_mes1[[#Totals],[IVA 21%]]+venta_a_mes1[[#Totals],[IVA 10,5%]]+ventas_b_mes1[[#Totals],[IVA 21%]]+ventas_b_mes1[[#Totals],[IVA 10,5%]] -> 0 | P4: =G4-M4 -> 8069136
B8: FECHA | C8: TIPO | D8: PTO VTA | E8: NRO. CPTE | F8: CUIT | G8: RAZON SOCIAL | H8: NETO GRAVADO | I8: IVA 21 % | J8: IVA 27% | K8: IVA 10,5% | L8: PERC. IVA | M8: PERC IIBB BS AS | N8: PERC. IIBB CABA | O8: Otros / No Grav. | P8: TOTAL | Q8: Tipo de Gasto | R8: Provincia
B9: 45658 | C9: 1 | D9: 711 | E9: 6577836 | F9: 30677237119 | G9: =IFERROR(IF(compras_mes1[[#This Row],[CUIT]]="","-",VLOOKUP(compras_mes1[[#This Row],[CUIT]],Lista_CUIT[#All],2,0)),"CUIT NO CARGADO") -> AUTOPISTAS DEL SOL SA | H9: 10053.15 | I9: =IF(compras_mes1[[#This Row],[NETO GRAVADO]]="","",compras_mes1[[#This Row],[NETO GRAVADO]]*0.21) -> 2111.1615 | O9: 301.59 | P9: =SUM(compras_mes1[[#This Row],[NETO GRAVADO]:[Otros / No Grav.]]) -> 12465.901 | Q9: =IFERROR(IF(compras_mes1[[#This Row],[CUIT]]="","-",VLOOKUP(compras_mes1[[#This Row],[CUIT]],Lista_CUIT[#All],3,0)),"CUIT NO CARGADO") -> Autopista | R9: =IFERROR(IF(compras_mes1[[#This Row],[CUIT]]="","-",VLOOKUP(compras_mes1[[#This Row],[CUIT]],Lista_CUIT[#All],4,0)),"CUIT NO CARGADO") -> 0
B10: 45658 | C10: 1 | D10: 629 | E10: 5740876 | F10: 30663498513 | G10: =IFERROR(IF(compras_mes1[[#This Row],[CUIT]]="","-",VLOOKUP(compras_mes1[[#This Row],[CUIT]],Lista_CUIT[#All],2,0)),"CUIT NO CARGADO") -> GRUPO CONCES. DEL OESTE SA | H10: 4968.79 | I10: =IF(compras_mes1[[#This Row],[NETO GRAVADO]]="","",compras_mes1[[#This Row],[NETO GRAVADO]]*0.21) -> 1043.4459 | P10: =SUM(compras_mes1[[#This Row],[NETO GRAVADO]:[Otros / No Grav.]]) -> 6012.2359 | Q10: =IFERROR(IF(compras_mes1[[#This Row],[CUIT]]="","-",VLOOKUP(compras_mes1[[#This Row],[CUIT]],Lista_CUIT[#All],3,0)),"CUIT NO CARGADO") -> Autopista | R10: =IFERROR(IF(compras_mes1[[#This Row],[CUIT]]="","-",VLOOKUP(compras_mes1[[#This Row],[CUIT]],Lista_CUIT[#All],4,0)),"CUIT NO CARGADO") -> 0
B11: 45659 | C11: 1 | D11: 500 | E11: 1671509 | F11: 30654118767 | G11: =IFERROR(IF(compras_mes1[[#This Row],[CUIT]]="","-",VLOOKUP(compras_mes1[[#This Row],[CUIT]],Lista_CUIT[#All],2,0)),"CUIT NO CARGADO") -> SOLUCIONES MULTIMEDIA SA | H11: 109168.92 | I11: =IF(compras_mes1[[#This Row],[NETO GRAVADO]]="","",compras_mes1[[#This Row],[NETO GRAVADO]]*0.21) -> 22925.473 | P11: =SUM(compras_mes1[[#This Row],[NETO GRAVADO]:[Otros / No Grav.]]) -> 132094.39 | Q11: =IFERROR(IF(compras_mes1[[#This Row],[CUIT]]="","-",VLOOKUP(compras_mes1[[#This Row],[CUIT]],Lista_CUIT[#All],3,0)),"CUIT NO CARGADO") -> gastos varios | R11: =IFERROR(IF(compras_mes1[[#This Row],[CUIT]]="","-",VLOOKUP(compras_mes1[[#This Row],[CUIT]],Lista_CUIT[#All],4,0)),"CUIT NO CARGADO") -> 0
B12: 45659 | C12: 1 | D12: 3 | E12: 4390 | F12: 20184052858 | G12: =IFERROR(IF(compras_mes1[[#This Row],[CUIT]]="","-",VLOOKUP(compras_mes1[[#This Row],[CUIT]],Lista_CUIT[#All],2,0)),"CUIT NO CARGADO") -> ABOUD PABLO DANIEL | H12: 54214.86 | I12: =IF(compras_mes1[[#This Row],[NETO GRAVADO]]="","",compras_mes1[[#This Row],[NETO GRAVADO]]*0.21) -> 11385.121 | P12: =SUM(compras_mes1[[#This Row],[NETO GRAVADO]:[Otros / No Grav.]]) -> 65599.981 | Q12: =IFERROR(IF(compras_mes1[[#This Row],[CUIT]]="","-",VLOOKUP(compras_mes1[[#This Row],[CUIT]],Lista_CUIT[#All],3,0)),"CUIT NO CARGADO") -> Gastos Varios | R12: =IFERROR(IF(compras_mes1[[#This Row],[CUIT]]="","-",VLOOKUP(compras_mes1[[#This Row],[CUIT]],Lista_CUIT[#All],4,0)),"CUIT NO CARGADO") -> 0
B13: 45659 | C13: 1 | D13: 2 | E13: 1026 | F13: 20272865869 | G13: =IFERROR(IF(compras_mes1[[#This Row],[CUIT]]="","-",VLOOKUP(compras_mes1[[#This Row],[CUIT]],Lista_CUIT[#All],2,0)),"CUIT NO CARGADO") -> DI FEO MARTIN EZEQUIEL | H13: 47550 | I13: =IF(compras_mes1[[#This Row],[NETO GRAVADO]]="","",compras_mes1[[#This Row],[NETO GRAVADO]]*0.21) -> 9985.5 | P13: =SUM(compras_mes1[[#This Row],[NETO GRAVADO]:[Otros / No Grav.]]) -> 57535.5 | Q13: =IFERROR(IF(compras_mes1[[#This Row],[CUIT]]="","-",VLOOKUP(compras_mes1[[#This Row],[CUIT]],Lista_CUIT[#All],3,0)),"CUIT NO CARGADO") -> INSUMOS | R13: =IFERROR(IF(compras_mes1[[#This Row],[CUIT]]="","-",VLOOKUP(compras_mes1[[#This Row],[CUIT]],Lista_CUIT[#All],4,0)),"CUIT NO CARGADO") -> 0
B14: 45659 | C14: 1 | D14: 13 | E14: 955 | F14: 30714201286 | G14: =IFERROR(IF(compras_mes1[[#This Row],[CUIT]]="","-",VLOOKUP(compras_mes1[[#This Row],[CUIT]],Lista_CUIT[#All],2,0)),"CUIT NO CARGADO") -> T.I.M. TIME IS MONEY S.R.L. | H14: 125000 | I14: =IF(compras_mes1[[#This Row],[NETO GRAVADO]]="","",compras_mes1[[#This Row],[NETO GRAVADO]]*0.21) -> 26250 | P14: =SUM(compras_mes1[[#This Row],[NETO GRAVADO]:[Otros / No Grav.]]) -> 151250 | Q14: =IFERROR(IF(compras_mes1[[#This Row],[CUIT]]="","-",VLOOKUP(compras_mes1[[#This Row],[CUIT]],Lista_CUIT[#All],3,0)),"CUIT NO CARGADO") -> textil | R14: =IFERROR(IF(compras_mes1[[#This Row],[CUIT]]="","-",VLOOKUP(compras_mes1[[#This Row],[CUIT]],Lista_CUIT[#All],4,0)),"CUIT NO CARGADO") -> 0
B15: 45659 | C15: 1 | D15: 3051 | E15: 856129 | F15: 30678814357 | G15: =IFERROR(IF(compras_mes1[[#This Row],[CUIT]]="","-",VLOOKUP(compras_mes1[[#This Row],[CUIT]],Lista_CUIT[#All],2,0)),"CUIT NO CARGADO") -> TELEFONICA MOVILES ARG SA | H15: 58294 | J15: =compras_mes1[[#This Row],[NETO GRAVADO]]*27/100 -> 15739.38 | P15: =SUM(compras_mes1[[#This Row],[NETO GRAVADO]:[Otros / No Grav.]]) -> 74033.38 | Q15: =IFERROR(IF(compras_mes1[[#This Row],[CUIT]]="","-",VLOOKUP(compras_mes1[[#This Row],[CUIT]],Lista_CUIT[#All],3,0)),"CUIT NO CARGADO") -> SERVICIO | R15: =IFERROR(IF(compras_mes1[[#This Row],[CUIT]]="","-",VLOOKUP(compras_mes1[[#This Row],[CUIT]],Lista_CUIT[#All],4,0)),"CUIT NO CARGADO") -> 0
B16: 45660 | C16: 1 | D16: 120 | E16: 5451 | F16: 30587197215 | G16: =IFERROR(IF(compras_mes1[[#This Row],[CUIT]]="","-",VLOOKUP(compras_mes1[[#This Row],[CUIT]],Lista_CUIT[#All],2,0)),"CUIT NO CARGADO") -> PANATEL SOCIEDAD ANONIMA | H16: 95041.32 | I16: =IF(compras_mes1[[#This Row],[NETO GRAVADO]]="","",compras_mes1[[#This Row],[NETO GRAVADO]]*0.21) -> 19958.677 | P16: =SUM(compras_mes1[[#This Row],[NETO GRAVADO]:[Otros / No Grav.]]) -> 115000 | Q16: =IFERROR(IF(compras_mes1[[#This Row],[CUIT]]="","-",VLOOKUP(compras_mes1[[#This Row],[CUIT]],Lista_CUIT[#All],3,0)),"CUIT NO CARGADO") -> SERVICIOS DE ALOJAMIENTO EN HOTELES | R16: =IFERROR(IF(compras_mes1[[#This Row],[CUIT]]="","-",VLOOKUP(compras_mes1[[#This Row],[CUIT]],Lista_CUIT[#All],4,0)),"CUIT NO CARGADO") -> 0
B17: 45660 | C17: 1 | D17: 1 | E17: 711934 | F17: 33716307749 | G17: =IFERROR(IF(compras_mes1[[#This Row],[CUIT]]="","-",VLOOKUP(compras_mes1[[#This Row],[CUIT]],Lista_CUIT[#All],2,0)),"CUIT NO CARGADO") -> VERISURE ARGENTINA MONITOREO DE ALARMAS SA | H17: 49498.9 | I17: =IF(compras_mes1[[#This Row],[NETO GRAVADO]]="","",compras_mes1[[#This Row],[NETO GRAVADO]]*0.21) -> 10394.769 | P17: =SUM(compras_mes1[[#This Row],[NETO GRAVADO]:[Otros / No Grav.]]) -> 59893.669 | Q17: =IFERROR(IF(compras_mes1[[#This Row],[CUIT]]="","-",VLOOKUP(compras_mes1[[#This Row],[CUIT]],Lista_CUIT[#All],3,0)),"CUIT NO CARGADO") -> Serv. Seguridad | R17: =IFERROR(IF(compras_mes1[[#This Row],[CUIT]]="","-",VLOOKUP(compras_mes1[[#This Row],[CUIT]],Lista_CUIT[#All],4,0)),"CUIT NO CARGADO") -> 0
B18: 45660 | C18: 1 | D18: 7 | E18: 3573 | F18: 20284183534 | G18: =IFERROR(IF(compras_mes1[[#This Row],[CUIT]]="","-",VLOOKUP(compras_mes1[[#This Row],[CUIT]],Lista_CUIT[#All],2,0)),"CUIT NO CARGADO") -> FURLANETTO MARTIN | H18: 9256.19 | I18: =IF(compras_mes1[[#This Row],[NETO GRAVADO]]="","",compras_mes1[[#This Row],[NETO GRAVADO]]*0.21) -> 1943.7999 | P18: =SUM(compras_mes1[[#This Row],[NETO GRAVADO]:[Otros / No Grav.]]) -> 11199.99 | Q18: =IFERROR(IF(compras_mes1[[#This Row],[CUIT]]="","-",VLOOKUP(compras_mes1[[#This Row],[CUIT]],Lista_CUIT[#All],3,0)),"CUIT NO CARGADO") -> gastos varios | R18: =IFERROR(IF(compras_mes1[[#This Row],[CUIT]]="","-",VLOOKUP(compras_mes1[[#This Row],[CUIT]],Lista_CUIT[#All],4,0)),"CUIT NO CARGADO") -> 0
B19: 45663 | C19: 1 | D19: 5 | E19: 1419 | F19: 27265302225 | G19: =IFERROR(IF(compras_mes1[[#This Row],[CUIT]]="","-",VLOOKUP(compras_mes1[[#This Row],[CUIT]],Lista_CUIT[#All],2,0)),"CUIT NO CARGADO") -> PRADO MARISOL | H19: 2100000 | I19: =IF(compras_mes1[[#This Row],[NETO GRAVADO]]="","",compras_mes1[[#This Row],[NETO GRAVADO]]*0.21) -> 441000 | P19: =SUM(compras_mes1[[#This Row],[NETO GRAVADO]:[Otros / No Grav.]]) -> 2541000 | Q19: =IFERROR(IF(compras_mes1[[#This Row],[CUIT]]="","-",VLOOKUP(compras_mes1[[#This Row],[CUIT]],Lista_CUIT[#All],3,0)),"CUIT NO CARGADO") -> INSUMO | R19: =IFERROR(IF(compras_mes1[[#This Row],[CUIT]]="","-",VLOOKUP(compras_mes1[[#This Row],[CUIT]],Lista_CUIT[#All],4,0)),"CUIT NO CARGADO") -> 0
B20: 45663 | C20: 1 | D20: 1 | E20: 112052 | F20: 30714864269 | G20: =IFERROR(IF(compras_mes1[[#This Row],[CUIT]]="","-",VLOOKUP(compras_mes1[[#This Row],[CUIT]],Lista_CUIT[#All],2,0)),"CUIT NO CARGADO") -> CONTABILIUM S.A. S. A. | H20: 139127 | I20: =IF(compras_mes1[[#This Row],[NETO GRAVADO]]="","",compras_mes1[[#This Row],[NETO GRAVADO]]*0.21) -> 29216.67 | P20: =SUM(compras_mes1[[#This Row],[NETO GRAVADO]:[Otros / No Grav.]]) -> 168343.67 | Q20: =IFERROR(IF(compras_mes1[[#This Row],[CUIT]]="","-",VLOOKUP(compras_mes1[[#This Row],[CUIT]],Lista_CUIT[#All],3,0)),"CUIT NO CARGADO") -> USUARIO CONTABLE | R20: =IFERROR(IF(compras_mes1[[#This Row],[CUIT]]="","-",VLOOKUP(compras_mes1[[#This Row],[CUIT]],Lista_CUIT[#All],4,0)),"CUIT NO CARGADO") -> 0
B21: 45663 | C21: 1 | D21: 1 | E21: 112096 | F21: 30714864269 | G21: =IFERROR(IF(compras_mes1[[#This Row],[CUIT]]="","-",VLOOKUP(compras_mes1[[#This Row],[CUIT]],Lista_CUIT[#All],2,0)),"CUIT NO CARGADO") -> CONTABILIUM S.A. S. A. | H21: 139127 | I21: =IF(compras_mes1[[#This Row],[NETO GRAVADO]]="","",compras_mes1[[#This Row],[NETO GRAVADO]]*0.21) -> 29216.67 | P21: =SUM(compras_mes1[[#This Row],[NETO GRAVADO]:[Otros / No Grav.]]) -> 168343.67 | Q21: =IFERROR(IF(compras_mes1[[#This Row],[CUIT]]="","-",VLOOKUP(compras_mes1[[#This Row],[CUIT]],Lista_CUIT[#All],3,0)),"CUIT NO CARGADO") -> USUARIO CONTABLE | R21: =IFERROR(IF(compras_mes1[[#This Row],[CUIT]]="","-",VLOOKUP(compras_mes1[[#This Row],[CUIT]],Lista_CUIT[#All],4,0)),"CUIT NO CARGADO") -> 0
B22: 45663 | C22: 1 | D22: 6 | E22: 87976 | F22: 30711553564 | G22: =IFERROR(IF(compras_mes1[[#This Row],[CUIT]]="","-",VLOOKUP(compras_mes1[[#This Row],[CUIT]],Lista_CUIT[#All],2,0)),"CUIT NO CARGADO") -> SALUD TEX S.A | H22: 72248 | I22: =IF(compras_mes1[[#This Row],[NETO GRAVADO]]="","",compras_mes1[[#This Row],[NETO GRAVADO]]*0.21) -> 15172.08 | P22: =SUM(compras_mes1[[#This Row],[NETO GRAVADO]:[Otros / No Grav.]]) -> 87420.08 | Q22: =IFERROR(IF(compras_mes1[[#This Row],[CUIT]]="","-",VLOOKUP(compras_mes1[[#This Row],[CUIT]],Lista_CUIT[#All],3,0)),"CUIT NO CARGADO") -> INSUMO | R22: =IFERROR(IF(compras_mes1[[#This Row],[CUIT]]="","-",VLOOKUP(compras_mes1[[#This Row],[CUIT]],Lista_CUIT[#All],4,0)),"CUIT NO CARGADO") -> 0
B23: 45663 | C23: 1 | D23: 5 | E23: 162444 | F23: 30598960093 | G23: =IFERROR(IF(compras_mes1[[#This Row],[CUIT]]="","-",VLOOKUP(compras_mes1[[#This Row],[CUIT]],Lista_CUIT[#All],2,0)),"CUIT NO CARGADO") -> SILVESTRIN FABRIS SRL | H23: 4386223.5 | I23: =IF(compras_mes1[[#This Row],[NETO GRAVADO]]="","",compras_mes1[[#This Row],[NETO GRAVADO]]*0.21) -> 921106.93 | P23: =SUM(compras_mes1[[#This Row],[NETO GRAVADO]:[Otros / No Grav.]]) -> 5307330.4 | Q23: =IFERROR(IF(compras_mes1[[#This Row],[CUIT]]="","-",VLOOKUP(compras_mes1[[#This Row],[CUIT]],Lista_CUIT[#All],3,0)),"CUIT NO CARGADO") -> INSUMO | R23: =IFERROR(IF(compras_mes1[[#This Row],[CUIT]]="","-",VLOOKUP(compras_mes1[[#This Row],[CUIT]],Lista_CUIT[#All],4,0)),"CUIT NO CARGADO") -> 0
B24: 45663 | C24: 1 | D24: 11 | E24: 69639 | F24: 30711091552 | G24: =IFERROR(IF(compras_mes1[[#This Row],[CUIT]]="","-",VLOOKUP(compras_mes1[[#This Row],[CUIT]],Lista_CUIT[#All],2,0)),"CUIT NO CARGADO") -> BIGBOX S.A. | H24: 30578.51 | I24: =IF(compras_mes1[[#This Row],[NETO GRAVADO]]="","",compras_mes1[[#This Row],[NETO GRAVADO]]*0.21) -> 6421.4871 | P24: =SUM(compras_mes1[[#This Row],[NETO GRAVADO]:[Otros / No Grav.]]) -> 36999.997 | Q24: =IFERROR(IF(compras_mes1[[#This Row],[CUIT]]="","-",VLOOKUP(compras_mes1[[#This Row],[CUIT]],Lista_CUIT[#All],3,0)),"CUIT NO CARGADO") -> INSUMO | R24: =IFERROR(IF(compras_mes1[[#This Row],[CUIT]]="","-",VLOOKUP(compras_mes1[[#This Row],[CUIT]],Lista_CUIT[#All],4,0)),"CUIT NO CARGADO") -> 0
B25: 45664 | C25: 1 | D25: 700 | E25: 2180405 | F25: 30715804812 | G25: =IFERROR(IF(compras_mes1[[#This Row],[CUIT]]="","-",VLOOKUP(compras_mes1[[#This Row],[CUIT]],Lista_CUIT[#All],2,0)),"CUIT NO CARGADO") -> CORREDORES VIALES SOCIEDAD ANONIMA | H25: 8735.85 | I25: =IF(compras_mes1[[#This Row],[NETO GRAVADO]]="","",compras_mes1[[#This Row],[NETO GRAVADO]]*0.21) -> 1834.5285 | P25: =SUM(compras_mes1[[#This Row],[NETO GRAVADO]:[Otros / No Grav.]]) -> 10570.379 | Q25: =IFERROR(IF(compras_mes1[[#This Row],[CUIT]]="","-",VLOOKUP(compras_mes1[[#This Row],[CUIT]],Lista_CUIT[#All],3,0)),"CUIT NO CARGADO") -> Autopista | R25: =IFERROR(IF(compras_mes1[[#This Row],[CUIT]]="","-",VLOOKUP(compras_mes1[[#This Row],[CUIT]],Lista_CUIT[#All],4,0)),"CUIT NO CARGADO") -> 0
B26: 45664 | C26: 1 | D26: 2 | E26: 25726 | F26: 23233422029 | G26: =IFERROR(IF(compras_mes1[[#This Row],[CUIT]]="","-",VLOOKUP(compras_mes1[[#This Row],[CUIT]],Lista_CUIT[#All],2,0)),"CUIT NO CARGADO") -> RODOLFO SCHULZE | H26: 272814.48 | I26: =IF(compras_mes1[[#This Row],[NETO GRAVADO]]="","",compras_mes1[[#This Row],[NETO GRAVADO]]*0.21) -> 57291.041 | P26: =SUM(compras_mes1[[#This Row],[NETO GRAVADO]:[Otros / No Grav.]]) -> 330105.52 | Q26: =IFERROR(IF(compras_mes1[[#This Row],[CUIT]]="","-",VLOOKUP(compras_mes1[[#This Row],[CUIT]],Lista_CUIT[#All],3,0)),"CUIT NO CARGADO") -> INSUMO | R26: =IFERROR(IF(compras_mes1[[#This Row],[CUIT]]="","-",VLOOKUP(compras_mes1[[#This Row],[CUIT]],Lista_CUIT[#All],4,0)),"CUIT NO CARGADO") -> 0
B27: 45664 | C27: 1 | D27: 4 | E27: 1280 | F27: 27148854764 | G27: =IFERROR(IF(compras_mes1[[#This Row],[CUIT]]="","-",VLOOKUP(compras_mes1[[#This Row],[CUIT]],Lista_CUIT[#All],2,0)),"CUIT NO CARGADO") -> PAZ CLAUDIA SILVIA | H27: 12452.89 | I27: =IF(compras_mes1[[#This Row],[NETO GRAVADO]]="","",compras_mes1[[#This Row],[NETO GRAVADO]]*0.21) -> 2615.1069 | P27: =SUM(compras_mes1[[#This Row],[NETO GRAVADO]:[Otros / No Grav.]]) -> 15067.997 | Q27: =IFERROR(IF(compras_mes1[[#This Row],[CUIT]]="","-",VLOOKUP(compras_mes1[[#This Row],[CUIT]],Lista_CUIT[#All],3,0)),"CUIT NO CARGADO") -> Gastos Varios | R27: =IFERROR(IF(compras_mes1[[#This Row],[CUIT]]="","-",VLOOKUP(compras_mes1[[#This Row],[CUIT]],Lista_CUIT[#All],4,0)),"CUIT NO CARGADO") -> 0
... B33: 45665 | C33: 1 | D33: 12 | E33: 1811132 | F33: 30709776564 | G33: =IFERROR(IF(compras_mes1[[#This Row],[CUIT]]="","-",VLOOKUP(compras_mes1[[#This Row],[CUIT]],Lista_CUIT[#All],2,0)),"CUIT NO CARGADO") -> PROSEGUR ACTIVA ARG SA | H33: 129241 | I33: =IF(compras_mes1[[#This Row],[NETO GRAVADO]]="","",compras_mes1[[#This Row],[NETO GRAVADO]]*0.21) -> 27140.61 | P33: =SUM(compras_mes1[[#This Row],[NETO GRAVADO]:[Otros / No Grav.]]) -> 156381.61 | Q33: =IFERROR(IF(compras_mes1[[#This Row],[CUIT]]="","-",VLOOKUP(compras_mes1[[#This Row],[CUIT]],Lista_CUIT[#All],3,0)),"CUIT NO CARGADO") -> ALARMA SEGURIDAD | R33: =IFERROR(IF(compras_mes1[[#This Row],[CUIT]]="","-",VLOOKUP(compras_mes1[[#This Row],[CUIT]],Lista_CUIT[#All],4,0)),"CUIT NO CARGADO") -> 0
B34: 45666 | C34: 1 | D34: 3101 | E34: 235363 | F34: 30678814357 | G34: =IFERROR(IF(compras_mes1[[#This Row],[CUIT]]="","-",VLOOKUP(compras_mes1[[#This Row],[CUIT]],Lista_CUIT[#All],2,0)),"CUIT NO CARGADO") -> TELEFONICA MOVILES ARG SA | H34: 73526.55 | J34: =compras_mes1[[#This Row],[NETO GRAVADO]]*27/100 -> 19852.168 | P34: =SUM(compras_mes1[[#This Row],[NETO GRAVADO]:[Otros / No Grav.]]) -> 93378.719 | Q34: =IFERROR(IF(compras_mes1[[#This Row],[CUIT]]="","-",VLOOKUP(compras_mes1[[#This Row],[CUIT]],Lista_CUIT[#All],3,0)),"CUIT NO CARGADO") -> SERVICIO | R34: =IFERROR(IF(compras_mes1[[#This Row],[CUIT]]="","-",VLOOKUP(compras_mes1[[#This Row],[CUIT]],Lista_CUIT[#All],4,0)),"CUIT NO CARGADO") -> 0
B35: 45666 | C35: 1 | D35: 2 | E35: 1041 | F35: 20272865869 | G35: =IFERROR(IF(compras_mes1[[#This Row],[CUIT]]="","-",VLOOKUP(compras_mes1[[#This Row],[CUIT]],Lista_CUIT[#All],2,0)),"CUIT NO CARGADO") -> DI FEO MARTIN EZEQUIEL | H35: 24220 | I35: =IF(compras_mes1[[#This Row],[NETO GRAVADO]]="","",compras_mes1[[#This Row],[NETO GRAVADO]]*0.21) -> 5086.2 | P35: =SUM(compras_mes1[[#This Row],[NETO GRAVADO]:[Otros / No Grav.]]) -> 29306.2 | Q35: =IFERROR(IF(compras_mes1[[#This Row],[CUIT]]="","-",VLOOKUP(compras_mes1[[#This Row],[CUIT]],Lista_CUIT[#All],3,0)),"CUIT NO CARGADO") -> INSUMOS | R35: =IFERROR(IF(compras_mes1[[#This Row],[CUIT]]="","-",VLOOKUP(compras_mes1[[#This Row],[CUIT]],Lista_CUIT[#All],4,0)),"CUIT NO CARGADO") -> 0
B36: 45666 | C36: 1 | D36: 7 | E36: 19904 | F36: 30709214078 | G36: =IFERROR(IF(compras_mes1[[#This Row],[CUIT]]="","-",VLOOKUP(compras_mes1[[#This Row],[CUIT]],Lista_CUIT[#All],2,0)),"CUIT NO CARGADO") -> REHAVITA S.A | H36: 96246 | I36: =IF(compras_mes1[[#This Row],[NETO GRAVADO]]="","",compras_mes1[[#This Row],[NETO GRAVADO]]*0.21) -> 20211.66 | P36: =SUM(compras_mes1[[#This Row],[NETO GRAVADO]:[Otros / No Grav.]]) -> 116457.66 | Q36: =IFERROR(IF(compras_mes1[[#This Row],[CUIT]]="","-",VLOOKUP(compras_mes1[[#This Row],[CUIT]],Lista_CUIT[#All],3,0)),"CUIT NO CARGADO") -> INSUMO | R36: =IFERROR(IF(compras_mes1[[#This Row],[CUIT]]="","-",VLOOKUP(compras_mes1[[#This Row],[CUIT]],Lista_CUIT[#All],4,0)),"CUIT NO CARGADO") -> 0
B37: 45667 | C37: 1 | D37: 2 | E37: 226 | F37: 30605344352 | G37: =IFERROR(IF(compras_mes1[[#This Row],[CUIT]]="","-",VLOOKUP(compras_mes1[[#This Row],[CUIT]],Lista_CUIT[#All],2,0)),"CUIT NO CARGADO") -> CONSORCIO BARTOLME MITRE 2466 | H37: 1200000 | I37: =IF(compras_mes1[[#This Row],[NETO GRAVADO]]="","",compras_mes1[[#This Row],[NETO GRAVADO]]*0.21) -> 252000 | P37: =SUM(compras_mes1[[#This Row],[NETO GRAVADO]:[Otros / No Grav.]]) -> 1452000 | Q37: =IFERROR(IF(compras_mes1[[#This Row],[CUIT]]="","-",VLOOKUP(compras_mes1[[#This Row],[CUIT]],Lista_CUIT[#All],3,0)),"CUIT NO CARGADO") -> ALQUILER LOCAL | R37: =IFERROR(IF(compras_mes1[[#This Row],[CUIT]]="","-",VLOOKUP(compras_mes1[[#This Row],[CUIT]],Lista_CUIT[#All],4,0)),"CUIT NO CARGADO") -> 0
B38: 45667 | C38: 1 | D38: 6 | E38: 55729 | F38: 30710177658 | G38: =IFERROR(IF(compras_mes1[[#This Row],[CUIT]]="","-",VLOOKUP(compras_mes1[[#This Row],[CUIT]],Lista_CUIT[#All],2,0)),"CUIT NO CARGADO") -> TARGET MEDICAL SA | H38: 904195.2 | I38: =IF(compras_mes1[[#This Row],[NETO GRAVADO]]="","",compras_mes1[[#This Row],[NETO GRAVADO]]*0.21) -> 189880.99 | P38: =SUM(compras_mes1[[#This Row],[NETO GRAVADO]:[Otros / No Grav.]]) -> 1094076.2 | Q38: =IFERROR(IF(compras_mes1[[#This Row],[CUIT]]="","-",VLOOKUP(compras_mes1[[#This Row],[CUIT]],Lista_CUIT[#All],3,0)),"CUIT NO CARGADO") -> INSUMO | R38: =IFERROR(IF(compras_mes1[[#This Row],[CUIT]]="","-",VLOOKUP(compras_mes1[[#This Row],[CUIT]],Lista_CUIT[#All],4,0)),"CUIT NO CARGADO") -> 0
B39: 45667 | C39: 1 | D39: 2 | E39: 2471 | F39: 33713192509 | G39: =IFERROR(IF(compras_mes1[[#This Row],[CUIT]]="","-",VLOOKUP(compras_mes1[[#This Row],[CUIT]],Lista_CUIT[#All],2,0)),"CUIT NO CARGADO") -> TAIKUE SA | H39: 104958.68 | I39: =IF(compras_mes1[[#This Row],[NETO GRAVADO]]="","",compras_mes1[[#This Row],[NETO GRAVADO]]*0.21) -> 22041.323 | P39: =SUM(compras_mes1[[#This Row],[NETO GRAVADO]:[Otros / No Grav.]]) -> 127000 | Q39: =IFERROR(IF(compras_mes1[[#This Row],[CUIT]]="","-",VLOOKUP(compras_mes1[[#This Row],[CUIT]],Lista_CUIT[#All],3,0)),"CUIT NO CARGADO") -> Mantenimiento | R39: =IFERROR(IF(compras_mes1[[#This Row],[CUIT]]="","-",VLOOKUP(compras_mes1[[#This Row],[CUIT]],Lista_CUIT[#All],4,0)),"CUIT NO CARGADO") -> 0
B40: 45667 | C40: 1 | D40: 4 | E40: 148 | F40: 20317488476 | G40: =IFERROR(IF(compras_mes1[[#This Row],[CUIT]]="","-",VLOOKUP(compras_mes1[[#This Row],[CUIT]],Lista_CUIT[#All],2,0)),"CUIT NO CARGADO") -> MIGUEL ANGEL VILLALBA | H40: 500000 | I40: =IF(compras_mes1[[#This Row],[NETO GRAVADO]]="","",compras_mes1[[#This Row],[NETO GRAVADO]]*0.21) -> 105000 | P40: =SUM(compras_mes1[[#This Row],[NETO GRAVADO]:[Otros / No Grav.]]) -> 605000 | Q40: BIEN DE USO | R40: =IFERROR(IF(compras_mes1[[#This Row],[CUIT]]="","-",VLOOKUP(compras_mes1[[#This Row],[CUIT]],Lista_CUIT[#All],4,0)),"CUIT NO CARGADO") -> 0
B41: 45667 | C41: 1 | D41: 4 | E41: 1291 | F41: 20202500138 | G41: =IFERROR(IF(compras_mes1[[#This Row],[CUIT]]="","-",VLOOKUP(compras_mes1[[#This Row],[CUIT]],Lista_CUIT[#All],2,0)),"CUIT NO CARGADO") -> RAMBAUD DIEGO GABRIEL | H41: 39457.01 | K41: =compras_mes1[[#This Row],[NETO GRAVADO]]*10.5/100 -> 4142.9861 | P41: =SUM(compras_mes1[[#This Row],[NETO GRAVADO]:[Otros / No Grav.]]) -> 43599.996 | Q41: =IFERROR(IF(compras_mes1[[#This Row],[CUIT]]="","-",VLOOKUP(compras_mes1[[#This Row],[CUIT]],Lista_CUIT[#All],3,0)),"CUIT NO CARGADO") -> GASTOS VARIOS | R41: =IFERROR(IF(compras_mes1[[#This Row],[CUIT]]="","-",VLOOKUP(compras_mes1[[#This Row],[CUIT]],Lista_CUIT[#All],4,0)),"CUIT NO CARGADO") -> 0
B42: 45667 | C42: 1 | D42: 16 | E42: 32 | F42: 27310367813 | G42: =IFERROR(IF(compras_mes1[[#This Row],[CUIT]]="","-",VLOOKUP(compras_mes1[[#This Row],[CUIT]],Lista_CUIT[#All],2,0)),"CUIT NO CARGADO") -> LA BRUNA MARIA VIRGINIA | H42: 133471.07 | I42: =IF(compras_mes1[[#This Row],[NETO GRAVADO]]="","",compras_mes1[[#This Row],[NETO GRAVADO]]*0.21) -> 28028.925 | P42: =SUM(compras_mes1[[#This Row],[NETO GRAVADO]:[Otros / No Grav.]]) -> 161499.99 | Q42: =IFERROR(IF(compras_mes1[[#This Row],[CUIT]]="","-",VLOOKUP(compras_mes1[[#This Row],[CUIT]],Lista_CUIT[#All],3,0)),"CUIT NO CARGADO") -> Hon. Juridicos | R42: =IFERROR(IF(compras_mes1[[#This Row],[CUIT]]="","-",VLOOKUP(compras_mes1[[#This Row],[CUIT]],Lista_CUIT[#All],4,0)),"CUIT NO CARGADO") -> 0
B43: 45668 | C43: 1 | D43: 2 | E43: 227 | F43: 30605344352 | G43: =IFERROR(IF(compras_mes1[[#This Row],[CUIT]]="","-",VLOOKUP(compras_mes1[[#This Row],[CUIT]],Lista_CUIT[#All],2,0)),"CUIT NO CARGADO") -> CONSORCIO BARTOLME MITRE 2466 | H43: 366000 | I43: =IF(compras_mes1[[#This Row],[NETO GRAVADO]]="","",compras_mes1[[#This Row],[NETO GRAVADO]]*0.21) -> 76860 | P43: =SUM(compras_mes1[[#This Row],[NETO GRAVADO]:[Otros / No Grav.]]) -> 442860 | Q43: =IFERROR(IF(compras_mes1[[#This Row],[CUIT]]="","-",VLOOKUP(compras_mes1[[#This Row],[CUIT]],Lista_CUIT[#All],3,0)),"CUIT NO CARGADO") -> ALQUILER LOCAL | R43: =IFERROR(IF(compras_mes1[[#This Row],[CUIT]]="","-",VLOOKUP(compras_mes1[[#This Row],[CUIT]],Lista_CUIT[#All],4,0)),"CUIT NO CARGADO") -> 0
B44: 45669 | C44: 1 | D44: 2189 | E44: 83402 | F44: 30548083156 | G44: =IFERROR(IF(compras_mes1[[#This Row],[CUIT]]="","-",VLOOKUP(compras_mes1[[#This Row],[CUIT]],Lista_CUIT[#All],2,0)),"CUIT NO CARGADO") -> COTO CICSA | H44: 9135.66 | I44: =IF(compras_mes1[[#This Row],[NETO GRAVADO]]="","",compras_mes1[[#This Row],[NETO GRAVADO]]*0.21) -> 1918.4886 | P44: =SUM(compras_mes1[[#This Row],[NETO GRAVADO]:[Otros / No Grav.]]) -> 11054.149 | Q44: =IFERROR(IF(compras_mes1[[#This Row],[CUIT]]="","-",VLOOKUP(compras_mes1[[#This Row],[CUIT]],Lista_CUIT[#All],3,0)),"CUIT NO CARGADO") -> Gastos Varios | R44: =IFERROR(IF(compras_mes1[[#This Row],[CUIT]]="","-",VLOOKUP(compras_mes1[[#This Row],[CUIT]],Lista_CUIT[#All],4,0)),"CUIT NO CARGADO") -> 0
B45: 45671 | C45: 1 | D45: 104 | E45: 7892105 | F45: 30715804812 | G45: =IFERROR(IF(compras_mes1[[#This Row],[CUIT]]="","-",VLOOKUP(compras_mes1[[#This Row],[CUIT]],Lista_CUIT[#All],2,0)),"CUIT NO CARGADO") -> CORREDORES VIALES SOCIEDAD ANONIMA | H45: 1039.98 | I45: =IF(compras_mes1[[#This Row],[NETO GRAVADO]]="","",compras_mes1[[#This Row],[NETO GRAVADO]]*0.21) -> 218.3958 | P45: =SUM(compras_mes1[[#This Row],[NETO GRAVADO]:[Otros / No Grav.]]) -> 1258.3758 | Q45: =IFERROR(IF(compras_mes1[[#This Row],[CUIT]]="","-",VLOOKUP(compras_mes1[[#This Row],[CUIT]],Lista_CUIT[#All],3,0)),"CUIT NO CARGADO") -> Autopista | R45: =IFERROR(IF(compras_mes1[[#This Row],[CUIT]]="","-",VLOOKUP(compras_mes1[[#This Row],[CUIT]],Lista_CUIT[#All],4,0)),"CUIT NO CARGADO") -> 0
B46: 45671 | C46: 1 | D46: 101 | E46: 8931 | F46: 33711430879 | G46: =IFERROR(IF(compras_mes1[[#This Row],[CUIT]]="","-",VLOOKUP(compras_mes1[[#This Row],[CUIT]],Lista_CUIT[#All],2,0)),"CUIT NO CARGADO") -> BALANZE S.A. | H46: 130000 | I46: =IF(compras_mes1[[#This Row],[NETO GRAVADO]]="","",compras_mes1[[#This Row],[NETO GRAVADO]]*0.21) -> 27300 | P46: =SUM(compras_mes1[[#This Row],[NETO GRAVADO]:[Otros / No Grav.]]) -> 157300 | Q46: =IFERROR(IF(compras_mes1[[#This Row],[CUIT]]="","-",VLOOKUP(compras_mes1[[#This Row],[CUIT]],Lista_CUIT[#All],3,0)),"CUIT NO CARGADO") -> INSUMO | R46: =IFERROR(IF(compras_mes1[[#This Row],[CUIT]]="","-",VLOOKUP(compras_mes1[[#This Row],[CUIT]],Lista_CUIT[#All],4,0)),"CUIT NO CARGADO") -> 0
B47: 45672 | C47: 1 | D47: 5015 | E47: 714288 | F47: 30574876474 | G47: =IFERROR(IF(compras_mes1[[#This Row],[CUIT]]="","-",VLOOKUP(compras_mes1[[#This Row],[CUIT]],Lista_CUIT[#All],2,0)),"CUIT NO CARGADO") -> AUTOP. URBANAS SA | H47: 11727.02 | I47: =IF(compras_mes1[[#This Row],[NETO GRAVADO]]="","",compras_mes1[[#This Row],[NETO GRAVADO]]*0.21) -> 2462.6742 | P47: =SUM(compras_mes1[[#This Row],[NETO GRAVADO]:[Otros / No Grav.]]) -> 14189.694 | Q47: =IFERROR(IF(compras_mes1[[#This Row],[CUIT]]="","-",VLOOKUP(compras_mes1[[#This Row],[CUIT]],Lista_CUIT[#All],3,0)),"CUIT NO CARGADO") -> PEAJE | R47: =IFERROR(IF(compras_mes1[[#This Row],[CUIT]]="","-",VLOOKUP(compras_mes1[[#This Row],[CUIT]],Lista_CUIT[#All],4,0)),"CUIT NO CARGADO") -> 0
B48: 45672 | C48: 1 | D48: 113 | E48: 4022341 | F48: 30577207190 | G48: =IFERROR(IF(compras_mes1[[#This Row],[CUIT]]="","-",VLOOKUP(compras_mes1[[#This Row],[CUIT]],Lista_CUIT[#All],2,0)),"CUIT NO CARGADO") -> COORDINACION ECOLOGICA AREA METROPOLITANA SOCIEDAD DEL ESTADO | H48: 5960.33 | I48: =IF(compras_mes1[[#This Row],[NETO GRAVADO]]="","",compras_mes1[[#This Row],[NETO GRAVADO]]*0.21) -> 1251.6693 | P48: =SUM(compras_mes1[[#This Row],[NETO GRAVADO]:[Otros / No Grav.]]) -> 7211.9993 | Q48: =IFERROR(IF(compras_mes1[[#This Row],[CUIT]]="","-",VLOOKUP(compras_mes1[[#This Row],[CUIT]],Lista_CUIT[#All],3,0)),"CUIT NO CARGADO") -> gastos varios | R48: =IFERROR(IF(compras_mes1[[#This Row],[CUIT]]="","-",VLOOKUP(compras_mes1[[#This Row],[CUIT]],Lista_CUIT[#All],4,0)),"CUIT NO CARGADO") -> 0
B49: 45672 | C49: 1 | D49: 5009 | E49: 1166794 | F49: 30574876474 | G49: =IFERROR(IF(compras_mes1[[#This Row],[CUIT]]="","-",VLOOKUP(compras_mes1[[#This Row],[CUIT]],Lista_CUIT[#All],2,0)),"CUIT NO CARGADO") -> AUTOP. URBANAS SA | H49: 1655.12 | I49: =IF(compras_mes1[[#This Row],[NETO GRAVADO]]="","",compras_mes1[[#This Row],[NETO GRAVADO]]*0.21) -> 347.5752 | P49: =SUM(compras_mes1[[#This Row],[NETO GRAVADO]:[Otros / No Grav.]]) -> 2002.6952 | Q49: =IFERROR(IF(compras_mes1[[#This Row],[CUIT]]="","-",VLOOKUP(compras_mes1[[#This Row],[CUIT]],Lista_CUIT[#All],3,0)),"CUIT NO CARGADO") -> PEAJE | R49: =IFERROR(IF(compras_mes1[[#This Row],[CUIT]]="","-",VLOOKUP(compras_mes1[[#This Row],[CUIT]],Lista_CUIT[#All],4,0)),"CUIT NO CARGADO") -> 0
B50: 45673 | C50: 1 | D50: 2007 | E50: 39777 | F50: 30516186670 | G50: =IFERROR(IF(compras_mes1[[#This Row],[CUIT]]="","-",VLOOKUP(compras_mes1[[#This Row],[CUIT]],Lista_CUIT[#All],2,0)),"CUIT NO CARGADO") -> DEHEZA SAICF E I | H50: 37022.31 | I50: =IF(compras_mes1[[#This Row],[NETO GRAVADO]]="","",compras_mes1[[#This Row],[NETO GRAVADO]]*0.21) -> 7774.6851 | P50: =SUM(compras_mes1[[#This Row],[NETO GRAVADO]:[Otros / No Grav.]]) -> 44796.995 | Q50: =IFERROR(IF(compras_mes1[[#This Row],[CUIT]]="","-",VLOOKUP(compras_mes1[[#This Row],[CUIT]],Lista_CUIT[#All],3,0)),"CUIT NO CARGADO") -> COMBUSTIBLE | R50: =IFERROR(IF(compras_mes1[[#This Row],[CUIT]]="","-",VLOOKUP(compras_mes1[[#This Row],[CUIT]],Lista_CUIT[#All],4,0)),"CUIT NO CARGADO") -> 0
B51: 45673 | C51: 1 | D51: 6 | E51: 55806 | F51: 30710177658 | G51: =IFERROR(IF(compras_mes1[[#This Row],[CUIT]]="","-",VLOOKUP(compras_mes1[[#This Row],[CUIT]],Lista_CUIT[#All],2,0)),"CUIT NO CARGADO") -> TARGET MEDICAL SA | H51: 261124 | I51: =IF(compras_mes1[[#This Row],[NETO GRAVADO]]="","",compras_mes1[[#This Row],[NETO GRAVADO]]*0.21) -> 54836.04 | P51: =SUM(compras_mes1[[#This Row],[NETO GRAVADO]:[Otros / No Grav.]]) -> 315960.04 | Q51: =IFERROR(IF(compras_mes1[[#This Row],[CUIT]]="","-",VLOOKUP(compras_mes1[[#This Row],[CUIT]],Lista_CUIT[#All],3,0)),"CUIT NO CARGADO") -> INSUMO | R51: =IFERROR(IF(compras_mes1[[#This Row],[CUIT]]="","-",VLOOKUP(compras_mes1[[#This Row],[CUIT]],Lista_CUIT[#All],4,0)),"CUIT NO CARGADO") -> 0
B52: 45673 | C52: 1 | D52: 6 | E52: 55814 | F52: 30710177658 | G52: =IFERROR(IF(compras_mes1[[#This Row],[CUIT]]="","-",VLOOKUP(compras_mes1[[#This Row],[CUIT]],Lista_CUIT[#All],2,0)),"CUIT NO CARGADO") -> TARGET MEDICAL SA | H52: 46510 | I52: =IF(compras_mes1[[#This Row],[NETO GRAVADO]]="","",compras_mes1[[#This Row],[NETO GRAVADO]]*0.21) -> 9767.1 | P52: =SUM(compras_mes1[[#This Row],[NETO GRAVADO]:[Otros / No Grav.]]) -> 56277.1 | Q52: =IFERROR(IF(compras_mes1[[#This Row],[CUIT]]="","-",VLOOKUP(compras_mes1[[#This Row],[CUIT]],Lista_CUIT[#All],3,0)),"CUIT NO CARGADO") -> INSUMO | R52: =IFERROR(IF(compras_mes1[[#This Row],[CUIT]]="","-",VLOOKUP(compras_mes1[[#This Row],[CUIT]],Lista_CUIT[#All],4,0)),"CUIT NO CARGADO") -> 0
B53: 45673 | C53: 1 | D53: 629 | E53: 5782099 | F53: 30663498513 | G53: =IFERROR(IF(compras_mes1[[#This Row],[CUIT]]="","-",VLOOKUP(compras_mes1[[#This Row],[CUIT]],Lista_CUIT[#All],2,0)),"CUIT NO CARGADO") -> GRUPO CONCES. DEL OESTE SA | H53: 3928.84 | I53: =IF(compras_mes1[[#This Row],[NETO GRAVADO]]="","",compras_mes1[[#This Row],[NETO GRAVADO]]*0.21) -> 825.0564 | P53: =SUM(compras_mes1[[#This Row],[NETO GRAVADO]:[Otros / No Grav.]]) -> 4753.8964 | Q53: =IFERROR(IF(compras_mes1[[#This Row],[CUIT]]="","-",VLOOKUP(compras_mes1[[#This Row],[CUIT]],Lista_CUIT[#All],3,0)),"CUIT NO CARGADO") -> Autopista | R53: =IFERROR(IF(compras_mes1[[#This Row],[CUIT]]="","-",VLOOKUP(compras_mes1[[#This Row],[CUIT]],Lista_CUIT[#All],4,0)),"CUIT NO CARGADO") -> 0
... B90: 45684 | C90: 1 | D90: 13 | E90: 3295 | F90: 20119743959 | G90: =IFERROR(IF(compras_mes1[[#This Row],[CUIT]]="","-",VLOOKUP(compras_mes1[[#This Row],[CUIT]],Lista_CUIT[#All],2,0)),"CUIT NO CARGADO") -> BENNUN FERNANDO RUBEN | H90: 750000 | I90: =IF(compras_mes1[[#This Row],[NETO GRAVADO]]="","",compras_mes1[[#This Row],[NETO GRAVADO]]*0.21) -> 157500 | P90: =SUM(compras_mes1[[#This Row],[NETO GRAVADO]:[Otros / No Grav.]]) -> 907500 | Q90: =IFERROR(IF(compras_mes1[[#This Row],[CUIT]]="","-",VLOOKUP(compras_mes1[[#This Row],[CUIT]],Lista_CUIT[#All],3,0)),"CUIT NO CARGADO") -> PROVEEDOR | R90: =IFERROR(IF(compras_mes1[[#This Row],[CUIT]]="","-",VLOOKUP(compras_mes1[[#This Row],[CUIT]],Lista_CUIT[#All],4,0)),"CUIT NO CARGADO") -> 0
B91: 45684 | C91: 1 | D91: 4 | E91: 150 | F91: 20317488476 | G91: =IFERROR(IF(compras_mes1[[#This Row],[CUIT]]="","-",VLOOKUP(compras_mes1[[#This Row],[CUIT]],Lista_CUIT[#All],2,0)),"CUIT NO CARGADO") -> MIGUEL ANGEL VILLALBA | H91: 1155000 | I91: =IF(compras_mes1[[#This Row],[NETO GRAVADO]]="","",compras_mes1[[#This Row],[NETO GRAVADO]]*0.21) -> 242550 | P91: =SUM(compras_mes1[[#This Row],[NETO GRAVADO]:[Otros / No Grav.]]) -> 1397550 | Q91: BIEN DE USO | R91: =IFERROR(IF(compras_mes1[[#This Row],[CUIT]]="","-",VLOOKUP(compras_mes1[[#This Row],[CUIT]],Lista_CUIT[#All],4,0)),"CUIT NO CARGADO") -> 0
B92: 45685 | C92: 1 | D92: 7 | E92: 20115 | F92: 30709214078 | G92: =IFERROR(IF(compras_mes1[[#This Row],[CUIT]]="","-",VLOOKUP(compras_mes1[[#This Row],[CUIT]],Lista_CUIT[#All],2,0)),"CUIT NO CARGADO") -> REHAVITA S.A | H92: 632500 | K92: =compras_mes1[[#This Row],[NETO GRAVADO]]*10.5/100 -> 66412.5 | P92: =SUM(compras_mes1[[#This Row],[NETO GRAVADO]:[Otros / No Grav.]]) -> 698912.5 | Q92: =IFERROR(IF(compras_mes1[[#This Row],[CUIT]]="","-",VLOOKUP(compras_mes1[[#This Row],[CUIT]],Lista_CUIT[#All],3,0)),"CUIT NO CARGADO") -> INSUMO | R92: =IFERROR(IF(compras_mes1[[#This Row],[CUIT]]="","-",VLOOKUP(compras_mes1[[#This Row],[CUIT]],Lista_CUIT[#All],4,0)),"CUIT NO CARGADO") -> 0
B93: 45685 | C93: 1 | D93: 2 | E93: 32 | F93: 27243660535 | G93: =IFERROR(IF(compras_mes1[[#This Row],[CUIT]]="","-",VLOOKUP(compras_mes1[[#This Row],[CUIT]],Lista_CUIT[#All],2,0)),"CUIT NO CARGADO") -> BARD MARISA SILVIA | H93: 414537 | I93: =IF(compras_mes1[[#This Row],[NETO GRAVADO]]="","",compras_mes1[[#This Row],[NETO GRAVADO]]*0.21) -> 87052.77 | P93: =SUM(compras_mes1[[#This Row],[NETO GRAVADO]:[Otros / No Grav.]]) -> 501589.77 | Q93: =IFERROR(IF(compras_mes1[[#This Row],[CUIT]]="","-",VLOOKUP(compras_mes1[[#This Row],[CUIT]],Lista_CUIT[#All],3,0)),"CUIT NO CARGADO") -> Insumos | R93: =IFERROR(IF(compras_mes1[[#This Row],[CUIT]]="","-",VLOOKUP(compras_mes1[[#This Row],[CUIT]],Lista_CUIT[#All],4,0)),"CUIT NO CARGADO") -> 0
B94: 45685 | C94: 1 | D94: 6 | E94: 55956 | F94: 30710177658 | G94: =IFERROR(IF(compras_mes1[[#This Row],[CUIT]]="","-",VLOOKUP(compras_mes1[[#This Row],[CUIT]],Lista_CUIT[#All],2,0)),"CUIT NO CARGADO") -> TARGET MEDICAL SA | H94: 1488106.7 | I94: =IF(compras_mes1[[#This Row],[NETO GRAVADO]]="","",compras_mes1[[#This Row],[NETO GRAVADO]]*0.21) -> 312502.41 | P94: =SUM(compras_mes1[[#This Row],[NETO GRAVADO]:[Otros / No Grav.]]) -> 1800609.1 | Q94: =IFERROR(IF(compras_mes1[[#This Row],[CUIT]]="","-",VLOOKUP(compras_mes1[[#This Row],[CUIT]],Lista_CUIT[#All],3,0)),"CUIT NO CARGADO") -> INSUMO | R94: =IFERROR(IF(compras_mes1[[#This Row],[CUIT]]="","-",VLOOKUP(compras_mes1[[#This Row],[CUIT]],Lista_CUIT[#All],4,0)),"CUIT NO CARGADO") -> 0
B95: 45686 | C95: 1 | D95: 12 | E95: 3334726 | F95: 30703088534 | G95: =IFERROR(IF(compras_mes1[[#This Row],[CUIT]]="","-",VLOOKUP(compras_mes1[[#This Row],[CUIT]],Lista_CUIT[#All],2,0)),"CUIT NO CARGADO") -> MERCADO LIBRE SRL | H95: 50228.69 | I95: =IF(compras_mes1[[#This Row],[NETO GRAVADO]]="","",compras_mes1[[#This Row],[NETO GRAVADO]]*0.21) -> 10548.025 | P95: =SUM(compras_mes1[[#This Row],[NETO GRAVADO]:[Otros / No Grav.]]) -> 60776.715 | Q95: =IFERROR(IF(compras_mes1[[#This Row],[CUIT]]="","-",VLOOKUP(compras_mes1[[#This Row],[CUIT]],Lista_CUIT[#All],3,0)),"CUIT NO CARGADO") -> PLATAFORMA ONLINE | R95: =IFERROR(IF(compras_mes1[[#This Row],[CUIT]]="","-",VLOOKUP(compras_mes1[[#This Row],[CUIT]],Lista_CUIT[#All],4,0)),"CUIT NO CARGADO") -> 0
B96: 45686 | C96: 1 | D96: 3 | E96: 230 | F96: 20334976433 | G96: =IFERROR(IF(compras_mes1[[#This Row],[CUIT]]="","-",VLOOKUP(compras_mes1[[#This Row],[CUIT]],Lista_CUIT[#All],2,0)),"CUIT NO CARGADO") -> NARDOMARINO EZEQUIEL EDUARDO | H96: 130000 | I96: =IF(compras_mes1[[#This Row],[NETO GRAVADO]]="","",compras_mes1[[#This Row],[NETO GRAVADO]]*0.21) -> 27300 | P96: =SUM(compras_mes1[[#This Row],[NETO GRAVADO]:[Otros / No Grav.]]) -> 157300 | Q96: =IFERROR(IF(compras_mes1[[#This Row],[CUIT]]="","-",VLOOKUP(compras_mes1[[#This Row],[CUIT]],Lista_CUIT[#All],3,0)),"CUIT NO CARGADO") -> FLETE | R96: =IFERROR(IF(compras_mes1[[#This Row],[CUIT]]="","-",VLOOKUP(compras_mes1[[#This Row],[CUIT]],Lista_CUIT[#All],4,0)),"CUIT NO CARGADO") -> 0
B97: 45686 | C97: 1 | D97: 3 | E97: 231 | F97: 20334976433 | G97: =IFERROR(IF(compras_mes1[[#This Row],[CUIT]]="","-",VLOOKUP(compras_mes1[[#This Row],[CUIT]],Lista_CUIT[#All],2,0)),"CUIT NO CARGADO") -> NARDOMARINO EZEQUIEL EDUARDO | H97: 180000 | I97: =IF(compras_mes1[[#This Row],[NETO GRAVADO]]="","",compras_mes1[[#This Row],[NETO GRAVADO]]*0.21) -> 37800 | P97: =SUM(compras_mes1[[#This Row],[NETO GRAVADO]:[Otros / No Grav.]]) -> 217800 | Q97: =IFERROR(IF(compras_mes1[[#This Row],[CUIT]]="","-",VLOOKUP(compras_mes1[[#This Row],[CUIT]],Lista_CUIT[#All],3,0)),"CUIT NO CARGADO") -> FLETE | R97: =IFERROR(IF(compras_mes1[[#This Row],[CUIT]]="","-",VLOOKUP(compras_mes1[[#This Row],[CUIT]],Lista_CUIT[#All],4,0)),"CUIT NO CARGADO") -> 0
B98: 45686 | C98: 1 | D98: 3 | E98: 232 | F98: 20334976433 | G98: =IFERROR(IF(compras_mes1[[#This Row],[CUIT]]="","-",VLOOKUP(compras_mes1[[#This Row],[CUIT]],Lista_CUIT[#All],2,0)),"CUIT NO CARGADO") -> NARDOMARINO EZEQUIEL EDUARDO | H98: 180000 | I98: =IF(compras_mes1[[#This Row],[NETO GRAVADO]]="","",compras_mes1[[#This Row],[NETO GRAVADO]]*0.21) -> 37800 | P98: =SUM(compras_mes1[[#This Row],[NETO GRAVADO]:[Otros / No Grav.]]) -> 217800 | Q98: =IFERROR(IF(compras_mes1[[#This Row],[CUIT]]="","-",VLOOKUP(compras_mes1[[#This Row],[CUIT]],Lista_CUIT[#All],3,0)),"CUIT NO CARGADO") -> FLETE | R98: =IFERROR(IF(compras_mes1[[#This Row],[CUIT]]="","-",VLOOKUP(compras_mes1[[#This Row],[CUIT]],Lista_CUIT[#All],4,0)),"CUIT NO CARGADO") -> 0
B99: 45687 | C99: 1 | D99: 1 | E99: 710 | F99: 30715613952 | G99: =IFERROR(IF(compras_mes1[[#This Row],[CUIT]]="","-",VLOOKUP(compras_mes1[[#This Row],[CUIT]],Lista_CUIT[#All],2,0)),"CUIT NO CARGADO") -> LAVALLETEXTIL SA | H99: 120000 | I99: =IF(compras_mes1[[#This Row],[NETO GRAVADO]]="","",compras_mes1[[#This Row],[NETO GRAVADO]]*0.21) -> 25200 | P99: =SUM(compras_mes1[[#This Row],[NETO GRAVADO]:[Otros / No Grav.]]) -> 145200 | Q99: =IFERROR(IF(compras_mes1[[#This Row],[CUIT]]="","-",VLOOKUP(compras_mes1[[#This Row],[CUIT]],Lista_CUIT[#All],3,0)),"CUIT NO CARGADO") -> textil | R99: =IFERROR(IF(compras_mes1[[#This Row],[CUIT]]="","-",VLOOKUP(compras_mes1[[#This Row],[CUIT]],Lista_CUIT[#All],4,0)),"CUIT NO CARGADO") -> 0
B100: 45687 | C100: 1 | D100: 17 | E100: 2653 | F100: 30711764921 | G100: =IFERROR(IF(compras_mes1[[#This Row],[CUIT]]="","-",VLOOKUP(compras_mes1[[#This Row],[CUIT]],Lista_CUIT[#All],2,0)),"CUIT NO CARGADO") -> RELIEF CENTER SRL | H100: 88640 | I100: =IF(compras_mes1[[#This Row],[NETO GRAVADO]]="","",compras_mes1[[#This Row],[NETO GRAVADO]]*0.21) -> 18614.4 | P100: =SUM(compras_mes1[[#This Row],[NETO GRAVADO]:[Otros / No Grav.]]) -> 107254.4 | Q100: =IFERROR(IF(compras_mes1[[#This Row],[CUIT]]="","-",VLOOKUP(compras_mes1[[#This Row],[CUIT]],Lista_CUIT[#All],3,0)),"CUIT NO CARGADO") -> INSUMO | R100: =IFERROR(IF(compras_mes1[[#This Row],[CUIT]]="","-",VLOOKUP(compras_mes1[[#This Row],[CUIT]],Lista_CUIT[#All],4,0)),"CUIT NO CARGADO") -> 0
B101: 45687 | C101: 1 | D101: 7 | E101: 19 | F101: 27325223273 | G101: =IFERROR(IF(compras_mes1[[#This Row],[CUIT]]="","-",VLOOKUP(compras_mes1[[#This Row],[CUIT]],Lista_CUIT[#All],2,0)),"CUIT NO CARGADO") -> SOUSA ALDERETE ALEJANDRA MABEL | H101: 49000 | I101: =IF(compras_mes1[[#This Row],[NETO GRAVADO]]="","",compras_mes1[[#This Row],[NETO GRAVADO]]*0.21) -> 10290 | P101: =SUM(compras_mes1[[#This Row],[NETO GRAVADO]:[Otros / No Grav.]]) -> 59290 | Q101: =IFERROR(IF(compras_mes1[[#This Row],[CUIT]]="","-",VLOOKUP(compras_mes1[[#This Row],[CUIT]],Lista_CUIT[#All],3,0)),"CUIT NO CARGADO") -> Insumos | R101: =IFERROR(IF(compras_mes1[[#This Row],[CUIT]]="","-",VLOOKUP(compras_mes1[[#This Row],[CUIT]],Lista_CUIT[#All],4,0)),"CUIT NO CARGADO") -> 0
B102: 45687 | C102: 1 | D102: 2 | E102: 11374 | F102: 30714331082 | G102: =IFERROR(IF(compras_mes1[[#This Row],[CUIT]]="","-",VLOOKUP(compras_mes1[[#This Row],[CUIT]],Lista_CUIT[#All],2,0)),"CUIT NO CARGADO") -> ORTOPEDIA CASA ESCALADA SRL | H102: 482335.25 | I102: =IF(compras_mes1[[#This Row],[NETO GRAVADO]]="","",compras_mes1[[#This Row],[NETO GRAVADO]]*0.21) -> 101290.4 | P102: =SUM(compras_mes1[[#This Row],[NETO GRAVADO]:[Otros / No Grav.]]) -> 583625.65 | Q102: =IFERROR(IF(compras_mes1[[#This Row],[CUIT]]="","-",VLOOKUP(compras_mes1[[#This Row],[CUIT]],Lista_CUIT[#All],3,0)),"CUIT NO CARGADO") -> INSUMO | R102: =IFERROR(IF(compras_mes1[[#This Row],[CUIT]]="","-",VLOOKUP(compras_mes1[[#This Row],[CUIT]],Lista_CUIT[#All],4,0)),"CUIT NO CARGADO") -> 0
B103: 45688 | C103: 1 | D103: 6 | E103: 18499902 | F103: 30620177497 | G103: =IFERROR(IF(compras_mes1[[#This Row],[CUIT]]="","-",VLOOKUP(compras_mes1[[#This Row],[CUIT]],Lista_CUIT[#All],2,0)),"CUIT NO CARGADO") -> POSNET SOCIEDAD DE RESPONSABILIDAD LIMITADA | H103: 0 | I103: =IF(compras_mes1[[#This Row],[NETO GRAVADO]]="","",compras_mes1[[#This Row],[NETO GRAVADO]]*0.21) -> 0 | P103: =SUM(compras_mes1[[#This Row],[NETO GRAVADO]:[Otros / No Grav.]]) -> 0 | Q103: =IFERROR(IF(compras_mes1[[#This Row],[CUIT]]="","-",VLOOKUP(compras_mes1[[#This Row],[CUIT]],Lista_CUIT[#All],3,0)),"CUIT NO CARGADO") -> Gastos Varios | R103: =IFERROR(IF(compras_mes1[[#This Row],[CUIT]]="","-",VLOOKUP(compras_mes1[[#This Row],[CUIT]],Lista_CUIT[#All],4,0)),"CUIT NO CARGADO") -> 0
B104: 45688 | C104: 1 | D104: 5015 | E104: 736663 | F104: 30574876474 | G104: =IFERROR(IF(compras_mes1[[#This Row],[CUIT]]="","-",VLOOKUP(compras_mes1[[#This Row],[CUIT]],Lista_CUIT[#All],2,0)),"CUIT NO CARGADO") -> AUTOP. URBANAS SA | H104: 6078.1 | I104: =IF(compras_mes1[[#This Row],[NETO GRAVADO]]="","",compras_mes1[[#This Row],[NETO GRAVADO]]*0.21) -> 1276.401 | P104: =SUM(compras_mes1[[#This Row],[NETO GRAVADO]:[Otros / No Grav.]]) -> 7354.501 | Q104: =IFERROR(IF(compras_mes1[[#This Row],[CUIT]]="","-",VLOOKUP(compras_mes1[[#This Row],[CUIT]],Lista_CUIT[#All],3,0)),"CUIT NO CARGADO") -> PEAJE | R104: =IFERROR(IF(compras_mes1[[#This Row],[CUIT]]="","-",VLOOKUP(compras_mes1[[#This Row],[CUIT]],Lista_CUIT[#All],4,0)),"CUIT NO CARGADO") -> 0
... B118: 45680 | C118: 1 | D118: 49 | E118: 3560 | F118: 30708560568 | G118: =IFERROR(IF(compras_mes1[[#This Row],[CUIT]]="","-",VLOOKUP(compras_mes1[[#This Row],[CUIT]],Lista_CUIT[#All],2,0)),"CUIT NO CARGADO") -> PINTURERIAS MINUTO SRL | H118: 11404.38 | I118: =IF(compras_mes1[[#This Row],[NETO GRAVADO]]="","",compras_mes1[[#This Row],[NETO GRAVADO]]*0.21) -> 2394.9198 | P118: =SUM(compras_mes1[[#This Row],[NETO GRAVADO]:[Otros / No Grav.]]) -> 13799.3 | Q118: =IFERROR(IF(compras_mes1[[#This Row],[CUIT]]="","-",VLOOKUP(compras_mes1[[#This Row],[CUIT]],Lista_CUIT[#All],3,0)),"CUIT NO CARGADO") -> Gastos Varios | R118: =IFERROR(IF(compras_mes1[[#This Row],[CUIT]]="","-",VLOOKUP(compras_mes1[[#This Row],[CUIT]],Lista_CUIT[#All],4,0)),"CUIT NO CARGADO") -> 0
B119: 45670 | C119: 1 | D119: 100 | E119: 227194 | F119: 30537679855 | G119: =IFERROR(IF(compras_mes1[[#This Row],[CUIT]]="","-",VLOOKUP(compras_mes1[[#This Row],[CUIT]],Lista_CUIT[#All],2,0)),"CUIT NO CARGADO") -> ESTACION LIMA SA | H119: 80650.16 | I119: =IF(compras_mes1[[#This Row],[NETO GRAVADO]]="","",compras_mes1[[#This Row],[NETO GRAVADO]]*0.21) -> 16936.534 | N119: 2761.72 | O119: =1167.14+10239.97 -> 11407.11 | P119: =SUM(compras_mes1[[#This Row],[NETO GRAVADO]:[Otros / No Grav.]]) -> 111755.52 | Q119: =IFERROR(IF(compras_mes1[[#This Row],[CUIT]]="","-",VLOOKUP(compras_mes1[[#This Row],[CUIT]],Lista_CUIT[#All],3,0)),"CUIT NO CARGADO") -> MERCADERIA | R119: =IFERROR(IF(compras_mes1[[#This Row],[CUIT]]="","-",VLOOKUP(compras_mes1[[#This Row],[CUIT]],Lista_CUIT[#All],4,0)),"CUIT NO CARGADO") -> 0
B120: 45667 | C120: 1 | D120: 14 | E120: 35834 | F120: 30600981486 | G120: =IFERROR(IF(compras_mes1[[#This Row],[CUIT]]="","-",VLOOKUP(compras_mes1[[#This Row],[CUIT]],Lista_CUIT[#All],2,0)),"CUIT NO CARGADO") -> EXPRESO LO BRUNO S A | H120: 22873.73 | I120: =IF(compras_mes1[[#This Row],[NETO GRAVADO]]="","",compras_mes1[[#This Row],[NETO GRAVADO]]*0.21) -> 4803.4833 | P120: =SUM(compras_mes1[[#This Row],[NETO GRAVADO]:[Otros / No Grav.]]) -> 27677.213 | Q120: =IFERROR(IF(compras_mes1[[#This Row],[CUIT]]="","-",VLOOKUP(compras_mes1[[#This Row],[CUIT]],Lista_CUIT[#All],3,0)),"CUIT NO CARGADO") -> Insumos | R120: =IFERROR(IF(compras_mes1[[#This Row],[CUIT]]="","-",VLOOKUP(compras_mes1[[#This Row],[CUIT]],Lista_CUIT[#All],4,0)),"CUIT NO CARGADO") -> 0
G121: =IFERROR(IF(compras_mes1[[#This Row],[CUIT]]="","-",VLOOKUP(compras_mes1[[#This Row],[CUIT]],Lista_CUIT[#All],2,0)),"CUIT NO CARGADO") -> - | I121: =IF(compras_mes1[[#This Row],[NETO GRAVADO]]="","",compras_mes1[[#This Row],[NETO GRAVADO]]*0.21) | P121: =SUM(compras_mes1[[#This Row],[NETO GRAVADO]:[Otros / No Grav.]]) -> 0 | Q121: =IFERROR(IF(compras_mes1[[#This Row],[CUIT]]="","-",VLOOKUP(compras_mes1[[#This Row],[CUIT]],Lista_CUIT[#All],3,0)),"CUIT NO CARGADO") -> - | R121: =IFERROR(IF(compras_mes1[[#This Row],[CUIT]]="","-",VLOOKUP(compras_mes1[[#This Row],[CUIT]],Lista_CUIT[#All],4,0)),"CUIT NO CARGADO") -> -
B122: Total | H122: =SUBTOTAL(109,compras_mes1[NETO GRAVADO]) -> 38655217 | I122: =SUBTOTAL(109,compras_mes1[IVA 21 %]) -> 7948802.2 | J122: =SUBTOTAL(109,compras_mes1[IVA 27%]) -> 35591.548 | K122: =SUBTOTAL(109,compras_mes1[IVA 10,5%]) -> 70555.486 | L122: =SUBTOTAL(109,compras_mes1[PERC. IVA]) -> 0 | M122: =SUBTOTAL(109,compras_mes1[PERC IIBB BS AS]) -> 0 | N122: =SUBTOTAL(109,compras_mes1[PERC. IIBB CABA]) -> 2761.72 | O122: =SUBTOTAL(109,compras_mes1[Otros / No Grav.]) -> 11708.7 | P122: =SUBTOTAL(109,compras_mes1[TOTAL]) -> 46724636
D127: LIQUIDACION EXTRACTOS BANCARIOS-TARJETAS
D128: FECHA | E128: NRO CPTE | F128: BANCO | G128: NETO | H128: IVA 21% | I128: IVA 10,5% | J128: RET IIBB CABA | K128: PERC IVA | L128: PERC IIBB
D129: 45688 | E129: 31202501 | F129: CREDICOOP | G129: 37385 | H129: =extracto_banco_mes1[[#This Row],[NETO]]*0.21 -> 7850.85 | K129: 810 | L129: 1000
D130: 45688 | E130: 31012025 | F130: PATAGONIA | G130: 30242.19 | H130: 6321 | I130: 14.93 | K130: 900 | L130: 1200
H131: =extracto_banco_mes1[[#This Row],[NETO]]*0.21 -> 0
D132: Total | G132: =SUBTOTAL(109,extracto_banco_mes1[NETO]) -> 67627.19 | H132: =SUBTOTAL(109,extracto_banco_mes1[IVA 21%]) -> 14171.85 | I132: =SUBTOTAL(109,extracto_banco_mes1[IVA 10,5%]) -> 14.93 | J132: =SUBTOTAL(109,extracto_banco_mes1[RET IIBB CABA]) -> 0 | K132: =SUBTOTAL(109,extracto_banco_mes1[PERC IVA]) -> 1710 | L132: =SUBTOTAL(109,extracto_banco_mes1[PERC IIBB]) -> 2200
H133: TOTAL: | I133: =SUM(extracto_banco_mes1[[#Totals],[IVA 21%]:[IVA 10,5%]]) -> 14186.78 | J133: > ya esta sumado al total
D136: FACTURAS C
D137: FECHA | E137: PTO VTA | F137: FC Nº | G137: CUIT | H137: RAZON SOCIAL | I137: TOTAL | J137: TIPO DE GASTO | K137: Provincia
G138: 20311855671 | H138: =IFERROR(IF(factura_c_mes1[[#This Row],[CUIT]]="","-",VLOOKUP(factura_c_mes1[[#This Row],[CUIT]],Lista_CUIT[#All],2,0)),"CUIT NO CARGADO") -> GUASCH HECTOR RAUL | I138: 160000 | J138: =IFERROR(IF(factura_c_mes1[[#This Row],[CUIT]]="","-",VLOOKUP(factura_c_mes1[[#This Row],[CUIT]],Lista_CUIT[#All],3,0)),"CUIT NO CARGADO") -> Insumos | K138: =IFERROR(IF(factura_c_mes1[[#This Row],[CUIT]]="","-",VLOOKUP(factura_c_mes1[[#This Row],[CUIT]],Lista_CUIT[#All],4,0)),"CUIT NO CARGADO") -> 0
G139: 23281233084 | H139: =IFERROR(IF(factura_c_mes1[[#This Row],[CUIT]]="","-",VLOOKUP(factura_c_mes1[[#This Row],[CUIT]],Lista_CUIT[#All],2,0)),"CUIT NO CARGADO") -> DRUETTA ANDREA MARIEL | I139: 240000 | J139: =IFERROR(IF(factura_c_mes1[[#This Row],[CUIT]]="","-",VLOOKUP(factura_c_mes1[[#This Row],[CUIT]],Lista_CUIT[#All],3,0)),"CUIT NO CARGADO") -> TECNICO | K139: =IFERROR(IF(factura_c_mes1[[#This Row],[CUIT]]="","-",VLOOKUP(factura_c_mes1[[#This Row],[CUIT]],Lista_CUIT[#All],4,0)),"CUIT NO CARGADO") -> 0
G140: 27338342840 | H140: =IFERROR(IF(factura_c_mes1[[#This Row],[CUIT]]="","-",VLOOKUP(factura_c_mes1[[#This Row],[CUIT]],Lista_CUIT[#All],2,0)),"CUIT NO CARGADO") -> CANCINO PAMELA RITA | I140: 115000 | J140: =IFERROR(IF(factura_c_mes1[[#This Row],[CUIT]]="","-",VLOOKUP(factura_c_mes1[[#This Row],[CUIT]],Lista_CUIT[#All],3,0)),"CUIT NO CARGADO") -> PROVEEDOR | K140: =IFERROR(IF(factura_c_mes1[[#This Row],[CUIT]]="","-",VLOOKUP(factura_c_mes1[[#This Row],[CUIT]],Lista_CUIT[#All],4,0)),"CUIT NO CARGADO") -> 0
G141: 27217606255 | H141: =IFERROR(IF(factura_c_mes1[[#This Row],[CUIT]]="","-",VLOOKUP(factura_c_mes1[[#This Row],[CUIT]],Lista_CUIT[#All],2,0)),"CUIT NO CARGADO") -> SAPUNA MARIAN KARINA | I141: 85055.12 | J141: =IFERROR(IF(factura_c_mes1[[#This Row],[CUIT]]="","-",VLOOKUP(factura_c_mes1[[#This Row],[CUIT]],Lista_CUIT[#All],3,0)),"CUIT NO CARGADO") -> PROVEEDOR | K141: =IFERROR(IF(factura_c_mes1[[#This Row],[CUIT]]="","-",VLOOKUP(factura_c_mes1[[#This Row],[CUIT]],Lista_CUIT[#All],4,0)),"CUIT NO CARGADO") -> 0
G142: 27217606255 | H142: =IFERROR(IF(factura_c_mes1[[#This Row],[CUIT]]="","-",VLOOKUP(factura_c_mes1[[#This Row],[CUIT]],Lista_CUIT[#All],2,0)),"CUIT NO CARGADO") -> SAPUNA MARIAN KARINA | I142: 75334.54 | J142: =IFERROR(IF(factura_c_mes1[[#This Row],[CUIT]]="","-",VLOOKUP(factura_c_mes1[[#This Row],[CUIT]],Lista_CUIT[#All],3,0)),"CUIT NO CARGADO") -> PROVEEDOR | K142: =IFERROR(IF(factura_c_mes1[[#This Row],[CUIT]]="","-",VLOOKUP(factura_c_mes1[[#This Row],[CUIT]],Lista_CUIT[#All],4,0)),"CUIT NO CARGADO") -> 0
G143: 27217606255 | H143: =IFERROR(IF(factura_c_mes1[[#This Row],[CUIT]]="","-",VLOOKUP(factura_c_mes1[[#This Row],[CUIT]],Lista_CUIT[#All],2,0)),"CUIT NO CARGADO") -> SAPUNA MARIAN KARINA | I143: 82624.98 | J143: =IFERROR(IF(factura_c_mes1[[#This Row],[CUIT]]="","-",VLOOKUP(factura_c_mes1[[#This Row],[CUIT]],Lista_CUIT[#All],3,0)),"CUIT NO CARGADO") -> PROVEEDOR | K143: =IFERROR(IF(factura_c_mes1[[#This Row],[CUIT]]="","-",VLOOKUP(factura_c_mes1[[#This Row],[CUIT]],Lista_CUIT[#All],4,0)),"CUIT NO CARGADO") -> 0
G144: 27217606255 | H144: =IFERROR(IF(factura_c_mes1[[#This Row],[CUIT]]="","-",VLOOKUP(factura_c_mes1[[#This Row],[CUIT]],Lista_CUIT[#All],2,0)),"CUIT NO CARGADO") -> SAPUNA MARIAN KARINA | I144: 223375.02 | J144: =IFERROR(IF(factura_c_mes1[[#This Row],[CUIT]]="","-",VLOOKUP(factura_c_mes1[[#This Row],[CUIT]],Lista_CUIT[#All],3,0)),"CUIT NO CARGADO") -> PROVEEDOR | K144: =IFERROR(IF(factura_c_mes1[[#This Row],[CUIT]]="","-",VLOOKUP(factura_c_mes1[[#This Row],[CUIT]],Lista_CUIT[#All],4,0)),"CUIT NO CARGADO") -> 0
G145: 27217606255 | H145: =IFERROR(IF(factura_c_mes1[[#This Row],[CUIT]]="","-",VLOOKUP(factura_c_mes1[[#This Row],[CUIT]],Lista_CUIT[#All],2,0)),"CUIT NO CARGADO") -> SAPUNA MARIAN KARINA | I145: 144536.78 | J145: =IFERROR(IF(factura_c_mes1[[#This Row],[CUIT]]="","-",VLOOKUP(factura_c_mes1[[#This Row],[CUIT]],Lista_CUIT[#All],3,0)),"CUIT NO CARGADO") -> PROVEEDOR | K145: =IFERROR(IF(factura_c_mes1[[#This Row],[CUIT]]="","-",VLOOKUP(factura_c_mes1[[#This Row],[CUIT]],Lista_CUIT[#All],4,0)),"CUIT NO CARGADO") -> 0
G146: 27217606255 | H146: =IFERROR(IF(factura_c_mes1[[#This Row],[CUIT]]="","-",VLOOKUP(factura_c_mes1[[#This Row],[CUIT]],Lista_CUIT[#All],2,0)),"CUIT NO CARGADO") -> SAPUNA MARIAN KARINA | I146: 157676.49 | J146: =IFERROR(IF(factura_c_mes1[[#This Row],[CUIT]]="","-",VLOOKUP(factura_c_mes1[[#This Row],[CUIT]],Lista_CUIT[#All],3,0)),"CUIT NO CARGADO") -> PROVEEDOR | K146: =IFERROR(IF(factura_c_mes1[[#This Row],[CUIT]]="","-",VLOOKUP(factura_c_mes1[[#This Row],[CUIT]],Lista_CUIT[#All],4,0)),"CUIT NO CARGADO") -> 0
G147: 27217606255 | H147: =IFERROR(IF(factura_c_mes1[[#This Row],[CUIT]]="","-",VLOOKUP(factura_c_mes1[[#This Row],[CUIT]],Lista_CUIT[#All],2,0)),"CUIT NO CARGADO") -> SAPUNA MARIAN KARINA | I147: 131397.07 | J147: =IFERROR(IF(factura_c_mes1[[#This Row],[CUIT]]="","-",VLOOKUP(factura_c_mes1[[#This Row],[CUIT]],Lista_CUIT[#All],3,0)),"CUIT NO CARGADO") -> PROVEEDOR | K147: =IFERROR(IF(factura_c_mes1[[#This Row],[CUIT]]="","-",VLOOKUP(factura_c_mes1[[#This Row],[CUIT]],Lista_CUIT[#All],4,0)),"CUIT NO CARGADO") -> 0
G148: 27315710508 | H148: =IFERROR(IF(factura_c_mes1[[#This Row],[CUIT]]="","-",VLOOKUP(factura_c_mes1[[#This Row],[CUIT]],Lista_CUIT[#All],2,0)),"CUIT NO CARGADO") -> RIVERO GABRIELA ROCIO | I148: 40000 | J148: =IFERROR(IF(factura_c_mes1[[#This Row],[CUIT]]="","-",VLOOKUP(factura_c_mes1[[#This Row],[CUIT]],Lista_CUIT[#All],3,0)),"CUIT NO CARGADO") -> Serv. Informaticos | K148: =IFERROR(IF(factura_c_mes1[[#This Row],[CUIT]]="","-",VLOOKUP(factura_c_mes1[[#This Row],[CUIT]],Lista_CUIT[#All],4,0)),"CUIT NO CARGADO") -> 0
G149: 27265832178 | H149: =IFERROR(IF(factura_c_mes1[[#This Row],[CUIT]]="","-",VLOOKUP(factura_c_mes1[[#This Row],[CUIT]],Lista_CUIT[#All],2,0)),"CUIT NO CARGADO") -> BLASCO MARIA GUADALUPE | I149: 3200000 | J149: =IFERROR(IF(factura_c_mes1[[#This Row],[CUIT]]="","-",VLOOKUP(factura_c_mes1[[#This Row],[CUIT]],Lista_CUIT[#All],3,0)),"CUIT NO CARGADO") -> PROVEEDOR | K149: =IFERROR(IF(factura_c_mes1[[#This Row],[CUIT]]="","-",VLOOKUP(factura_c_mes1[[#This Row],[CUIT]],Lista_CUIT[#All],4,0)),"CUIT NO CARGADO") -> 0
... G153: 27062343449 | H153: =IFERROR(IF(factura_c_mes1[[#This Row],[CUIT]]="","-",VLOOKUP(factura_c_mes1[[#This Row],[CUIT]],Lista_CUIT[#All],2,0)),"CUIT NO CARGADO") -> FERREIRS LILISNS INES | I153: 350000 | J153: =IFERROR(IF(factura_c_mes1[[#This Row],[CUIT]]="","-",VLOOKUP(factura_c_mes1[[#This Row],[CUIT]],Lista_CUIT[#All],3,0)),"CUIT NO CARGADO") -> FLETE | K153: =IFERROR(IF(factura_c_mes1[[#This Row],[CUIT]]="","-",VLOOKUP(factura_c_mes1[[#This Row],[CUIT]],Lista_CUIT[#All],4,0)),"CUIT NO CARGADO") -> 0
H154: =IFERROR(IF(factura_c_mes1[[#This Row],[CUIT]]="","-",VLOOKUP(factura_c_mes1[[#This Row],[CUIT]],Lista_CUIT[#All],2,0)),"CUIT NO CARGADO") -> - | J154: =IFERROR(IF(factura_c_mes1[[#This Row],[CUIT]]="","-",VLOOKUP(factura_c_mes1[[#This Row],[CUIT]],Lista_CUIT[#All],3,0)),"CUIT NO CARGADO") -> - | K154: =IFERROR(IF(factura_c_mes1[[#This Row],[CUIT]]="","-",VLOOKUP(factura_c_mes1[[#This Row],[CUIT]],Lista_CUIT[#All],4,0)),"CUIT NO CARGADO") -> -
H155: =IFERROR(IF(factura_c_mes1[[#This Row],[CUIT]]="","-",VLOOKUP(factura_c_mes1[[#This Row],[CUIT]],Lista_CUIT[#All],2,0)),"CUIT NO CARGADO") -> - | J155: =IFERROR(IF(factura_c_mes1[[#This Row],[CUIT]]="","-",VLOOKUP(factura_c_mes1[[#This Row],[CUIT]],Lista_CUIT[#All],3,0)),"CUIT NO CARGADO") -> - | K155: =IFERROR(IF(factura_c_mes1[[#This Row],[CUIT]]="","-",VLOOKUP(factura_c_mes1[[#This Row],[CUIT]],Lista_CUIT[#All],4,0)),"CUIT NO CARGADO") -> -
H156: =IFERROR(IF(factura_c_mes1[[#This Row],[CUIT]]="","-",VLOOKUP(factura_c_mes1[[#This Row],[CUIT]],Lista_CUIT[#All],2,0)),"CUIT NO CARGADO") -> - | J156: =IFERROR(IF(factura_c_mes1[[#This Row],[CUIT]]="","-",VLOOKUP(factura_c_mes1[[#This Row],[CUIT]],Lista_CUIT[#All],3,0)),"CUIT NO CARGADO") -> - | K156: =IFERROR(IF(factura_c_mes1[[#This Row],[CUIT]]="","-",VLOOKUP(factura_c_mes1[[#This Row],[CUIT]],Lista_CUIT[#All],4,0)),"CUIT NO CARGADO") -> -
H157: =IFERROR(IF(factura_c_mes1[[#This Row],[CUIT]]="","-",VLOOKUP(factura_c_mes1[[#This Row],[CUIT]],Lista_CUIT[#All],2,0)),"CUIT NO CARGADO") -> - | J157: =IFERROR(IF(factura_c_mes1[[#This Row],[CUIT]]="","-",VLOOKUP(factura_c_mes1[[#This Row],[CUIT]],Lista_CUIT[#All],3,0)),"CUIT NO CARGADO") -> - | K157: =IFERROR(IF(factura_c_mes1[[#This Row],[CUIT]]="","-",VLOOKUP(factura_c_mes1[[#This Row],[CUIT]],Lista_CUIT[#All],4,0)),"CUIT NO CARGADO") -> -
H158: =IFERROR(IF(factura_c_mes1[[#This Row],[CUIT]]="","-",VLOOKUP(factura_c_mes1[[#This Row],[CUIT]],Lista_CUIT[#All],2,0)),"CUIT NO CARGADO") -> - | J158: =IFERROR(IF(factura_c_mes1[[#This Row],[CUIT]]="","-",VLOOKUP(factura_c_mes1[[#This Row],[CUIT]],Lista_CUIT[#All],3,0)),"CUIT NO CARGADO") -> - | K158: =IFERROR(IF(factura_c_mes1[[#This Row],[CUIT]]="","-",VLOOKUP(factura_c_mes1[[#This Row],[CUIT]],Lista_CUIT[#All],4,0)),"CUIT NO CARGADO") -> -
H159: =IFERROR(IF(factura_c_mes1[[#This Row],[CUIT]]="","-",VLOOKUP(factura_c_mes1[[#This Row],[CUIT]],Lista_CUIT[#All],2,0)),"CUIT NO CARGADO") -> - | J159: =IFERROR(IF(factura_c_mes1[[#This Row],[CUIT]]="","-",VLOOKUP(factura_c_mes1[[#This Row],[CUIT]],Lista_CUIT[#All],3,0)),"CUIT NO CARGADO") -> - | K159: =IFERROR(IF(factura_c_mes1[[#This Row],[CUIT]]="","-",VLOOKUP(factura_c_mes1[[#This Row],[CUIT]],Lista_CUIT[#All],4,0)),"CUIT NO CARGADO") -> -
H160: =IFERROR(IF(factura_c_mes1[[#This Row],[CUIT]]="","-",VLOOKUP(factura_c_mes1[[#This Row],[CUIT]],Lista_CUIT[#All],2,0)),"CUIT NO CARGADO") -> - | J160: =IFERROR(IF(factura_c_mes1[[#This Row],[CUIT]]="","-",VLOOKUP(factura_c_mes1[[#This Row],[CUIT]],Lista_CUIT[#All],3,0)),"CUIT NO CARGADO") -> - | K160: =IFERROR(IF(factura_c_mes1[[#This Row],[CUIT]]="","-",VLOOKUP(factura_c_mes1[[#This Row],[CUIT]],Lista_CUIT[#All],4,0)),"CUIT NO CARGADO") -> -
H161: =IFERROR(IF(factura_c_mes1[[#This Row],[CUIT]]="","-",VLOOKUP(factura_c_mes1[[#This Row],[CUIT]],Lista_CUIT[#All],2,0)),"CUIT NO CARGADO") -> - | J161: =IFERROR(IF(factura_c_mes1[[#This Row],[CUIT]]="","-",VLOOKUP(factura_c_mes1[[#This Row],[CUIT]],Lista_CUIT[#All],3,0)),"CUIT NO CARGADO") -> - | K161: =IFERROR(IF(factura_c_mes1[[#This Row],[CUIT]]="","-",VLOOKUP(factura_c_mes1[[#This Row],[CUIT]],Lista_CUIT[#All],4,0)),"CUIT NO CARGADO") -> -
H162: =IFERROR(IF(factura_c_mes1[[#This Row],[CUIT]]="","-",VLOOKUP(factura_c_mes1[[#This Row],[CUIT]],Lista_CUIT[#All],2,0)),"CUIT NO CARGADO") -> - | J162: =IFERROR(IF(factura_c_mes1[[#This Row],[CUIT]]="","-",VLOOKUP(factura_c_mes1[[#This Row],[CUIT]],Lista_CUIT[#All],3,0)),"CUIT NO CARGADO") -> - | K162: =IFERROR(IF(factura_c_mes1[[#This Row],[CUIT]]="","-",VLOOKUP(factura_c_mes1[[#This Row],[CUIT]],Lista_CUIT[#All],4,0)),"CUIT NO CARGADO") -> -
H163: =IFERROR(IF(factura_c_mes1[[#This Row],[CUIT]]="","-",VLOOKUP(factura_c_mes1[[#This Row],[CUIT]],Lista_CUIT[#All],2,0)),"CUIT NO CARGADO") -> - | J163: =IFERROR(IF(factura_c_mes1[[#This Row],[CUIT]]="","-",VLOOKUP(factura_c_mes1[[#This Row],[CUIT]],Lista_CUIT[#All],3,0)),"CUIT NO CARGADO") -> - | K163: =IFERROR(IF(factura_c_mes1[[#This Row],[CUIT]]="","-",VLOOKUP(factura_c_mes1[[#This Row],[CUIT]],Lista_CUIT[#All],4,0)),"CUIT NO CARGADO") -> -
H164: =IFERROR(IF(factura_c_mes1[[#This Row],[CUIT]]="","-",VLOOKUP(factura_c_mes1[[#This Row],[CUIT]],Lista_CUIT[#All],2,0)),"CUIT NO CARGADO") -> - | J164: =IFERROR(IF(factura_c_mes1[[#This Row],[CUIT]]="","-",VLOOKUP(factura_c_mes1[[#This Row],[CUIT]],Lista_CUIT[#All],3,0)),"CUIT NO CARGADO") -> - | K164: =IFERROR(IF(factura_c_mes1[[#This Row],[CUIT]]="","-",VLOOKUP(factura_c_mes1[[#This Row],[CUIT]],Lista_CUIT[#All],4,0)),"CUIT NO CARGADO") -> -
H165: =IFERROR(IF(factura_c_mes1[[#This Row],[CUIT]]="","-",VLOOKUP(factura_c_mes1[[#This Row],[CUIT]],Lista_CUIT[#All],2,0)),"CUIT NO CARGADO") -> - | J165: =IFERROR(IF(factura_c_mes1[[#This Row],[CUIT]]="","-",VLOOKUP(factura_c_mes1[[#This Row],[CUIT]],Lista_CUIT[#All],3,0)),"CUIT NO CARGADO") -> - | K165: =IFERROR(IF(factura_c_mes1[[#This Row],[CUIT]]="","-",VLOOKUP(factura_c_mes1[[#This Row],[CUIT]],Lista_CUIT[#All],4,0)),"CUIT NO CARGADO") -> -
... H170: =IFERROR(IF(factura_c_mes1[[#This Row],[CUIT]]="","-",VLOOKUP(factura_c_mes1[[#This Row],[CUIT]],Lista_CUIT[#All],2,0)),"CUIT NO CARGADO") -> - | J170: =IFERROR(IF(factura_c_mes1[[#This Row],[CUIT]]="","-",VLOOKUP(factura_c_mes1[[#This Row],[CUIT]],Lista_CUIT[#All],3,0)),"CUIT NO CARGADO") -> - | K170: =IFERROR(IF(factura_c_mes1[[#This Row],[CUIT]]="","-",VLOOKUP(factura_c_mes1[[#This Row],[CUIT]],Lista_CUIT[#All],4,0)),"CUIT NO CARGADO") -> -
D171: Total | I171: =SUBTOTAL(109,factura_c_mes1[TOTAL]) -> 5641000
...

Sheet Feb-25
B1: LIBRO IVA COMPRAS | G1: ='Ene-25'!G1:M1 -> ORTOPEDIA GEMINIS S.A. | N1: =EDATE('Ene-25'!N1,1) -> 45689
B3: TOTAL COMPRAS | G3: TOTAL CREDITO FISCAL | J3: TOTAL VENTAS NETAS | M3: TOTAL DEBITO FISCAL | P3: RESULTADO
B4: =SUM(compras_mes2[[#Totals],[NETO GRAVADO]])+extracto_banco_mes2[[#Totals],[NETO]] -> 26792809 | G4: =compras_mes2[[#Totals],[IVA 21 %]]+compras_mes2[[#Totals],[IVA 27%]]+compras_mes2[[#Totals],[IVA 10,5%]]+extracto_banco_mes2[[#Totals],[IVA 21%]]+extracto_banco_mes2[[#Totals],[IVA 10,5%]] -> 5467560.1 | J4: =venta_a_mes2[[#Totals],[IMPORTE NETO]]+ventas_b_mes2[[#Totals],[IMPORTE NETO]] -> 0 | M4: =venta_a_mes2[[#Totals],[IVA 21%]]+venta_a_mes2[[#Totals],[IVA 10,5%]]+ventas_b_mes2[[#Totals],[IVA 21%]]+ventas_b_mes2[[#Totals],[IVA 10,5%]] -> 0 | P4: =G4-M4 -> 5467560.1
B8: FECHA | C8: TIPO | D8: PTO VTA | E8: NRO. CPTE | F8: CUIT | G8: RAZON SOCIAL | H8: NETO GRAVADO | I8: IVA 21 % | J8: IVA 27% | K8: IVA 10,5% | L8: PERC. IVA | M8: PERC IIBB BS AS | N8: PERC. IIBB CABA | O8: Otros / No Grav. | P8: TOTAL | Q8: Tipo de Gasto | R8: Provincia
B9: 45689 | C9: 1 | D9: 629 | E9: 5821744 | F9: 30663498513 | G9: =IFERROR(IF(compras_mes2[[#This Row],[CUIT]]="","-",VLOOKUP(compras_mes2[[#This Row],[CUIT]],Lista_CUIT[#All],2,0)),"CUIT NO CARGADO") -> GRUPO CONCES. DEL OESTE SA | H9: 577.76 | I9: =IF(compras_mes2[[#This Row],[NETO GRAVADO]]="","",compras_mes2[[#This Row],[NETO GRAVADO]]*0.21) -> 121.3296 | P9: =SUM(compras_mes2[[#This Row],[NETO GRAVADO]:[Otros / No Grav.]]) -> 699.0896 | Q9: =IFERROR(IF(compras_mes2[[#This Row],[CUIT]]="","-",VLOOKUP(compras_mes2[[#This Row],[CUIT]],Lista_CUIT[#All],3,0)),"CUIT NO CARGADO") -> Autopista | R9: =IFERROR(IF(compras_mes2[[#This Row],[CUIT]]="","-",VLOOKUP(compras_mes2[[#This Row],[CUIT]],Lista_CUIT[#All],4,0)),"CUIT NO CARGADO") -> 0 | S9: 72378.33
B10: 45690 | C10: 1 | D10: 2031 | E10: 194172 | F10: 30516186670 | G10: =IFERROR(IF(compras_mes2[[#This Row],[CUIT]]="","-",VLOOKUP(compras_mes2[[#This Row],[CUIT]],Lista_CUIT[#All],2,0)),"CUIT NO CARGADO") -> DEHEZA SAICF E I | H10: 41633.14 | I10: =IF(compras_mes2[[#This Row],[NETO GRAVADO]]="","",compras_mes2[[#This Row],[NETO GRAVADO]]*0.21) -> 8742.9594 | P10: =SUM(compras_mes2[[#This Row],[NETO GRAVADO]:[Otros / No Grav.]]) -> 50376.099 | Q10: =IFERROR(IF(compras_mes2[[#This Row],[CUIT]]="","-",VLOOKUP(compras_mes2[[#This Row],[CUIT]],Lista_CUIT[#All],3,0)),"CUIT NO CARGADO") -> COMBUSTIBLE | R10: =IFERROR(IF(compras_mes2[[#This Row],[CUIT]]="","-",VLOOKUP(compras_mes2[[#This Row],[CUIT]],Lista_CUIT[#All],4,0)),"CUIT NO CARGADO") -> 0 | S10: 210479.5
B11: 45690 | C11: 1 | D11: 3051 | E11: 876626 | F11: 30678814357 | G11: =IFERROR(IF(compras_mes2[[#This Row],[CUIT]]="","-",VLOOKUP(compras_mes2[[#This Row],[CUIT]],Lista_CUIT[#All],2,0)),"CUIT NO CARGADO") -> TELEFONICA MOVILES ARG SA | H11: 76614.82 | J11: =compras_mes2[[#This Row],[NETO GRAVADO]]*27/100 -> 20686.001 | P11: =SUM(compras_mes2[[#This Row],[NETO GRAVADO]:[Otros / No Grav.]]) -> 97300.821 | Q11: =IFERROR(IF(compras_mes2[[#This Row],[CUIT]]="","-",VLOOKUP(compras_mes2[[#This Row],[CUIT]],Lista_CUIT[#All],3,0)),"CUIT NO CARGADO") -> SERVICIO | R11: =IFERROR(IF(compras_mes2[[#This Row],[CUIT]]="","-",VLOOKUP(compras_mes2[[#This Row],[CUIT]],Lista_CUIT[#All],4,0)),"CUIT NO CARGADO") -> 0 | S11: 23923.11
B12: 45691 | C12: 1 | D12: 7 | E12: 3876 | F12: 20347228002 | G12: =IFERROR(IF(compras_mes2[[#This Row],[CUIT]]="","-",VLOOKUP(compras_mes2[[#This Row],[CUIT]],Lista_CUIT[#All],2,0)),"CUIT NO CARGADO") -> MATIAS EZEQUIEL ROMANO | H12: 81817.36 | I12: =IF(compras_mes2[[#This Row],[NETO GRAVADO]]="","",compras_mes2[[#This Row],[NETO GRAVADO]]*0.21) -> 17181.646 | P12: =SUM(compras_mes2[[#This Row],[NETO GRAVADO]:[Otros / No Grav.]]) -> 98999.006 | Q12: =IFERROR(IF(compras_mes2[[#This Row],[CUIT]]="","-",VLOOKUP(compras_mes2[[#This Row],[CUIT]],Lista_CUIT[#All],3,0)),"CUIT NO CARGADO") -> INSUMO | R12: =IFERROR(IF(compras_mes2[[#This Row],[CUIT]]="","-",VLOOKUP(compras_mes2[[#This Row],[CUIT]],Lista_CUIT[#All],4,0)),"CUIT NO CARGADO") -> 0 | S12: 48658.91
B13: 45691 | C13: 1 | D13: 2 | E13: 229 | F13: 30605344352 | G13: =IFERROR(IF(compras_mes2[[#This Row],[CUIT]]="","-",VLOOKUP(compras_mes2[[#This Row],[CUIT]],Lista_CUIT[#All],2,0)),"CUIT NO CARGADO") -> CONSORCIO BARTOLME MITRE 2466 | H13: 1200000 | I13: =IF(compras_mes2[[#This Row],[NETO GRAVADO]]="","",compras_mes2[[#This Row],[NETO GRAVADO]]*0.21) -> 252000 | P13: =SUM(compras_mes2[[#This Row],[NETO GRAVADO]:[Otros / No Grav.]]) -> 1452000 | Q13: =IFERROR(IF(compras_mes2[[#This Row],[CUIT]]="","-",VLOOKUP(compras_mes2[[#This Row],[CUIT]],Lista_CUIT[#All],3,0)),"CUIT NO CARGADO") -> ALQUILER LOCAL | R13: =IFERROR(IF(compras_mes2[[#This Row],[CUIT]]="","-",VLOOKUP(compras_mes2[[#This Row],[CUIT]],Lista_CUIT[#All],4,0)),"CUIT NO CARGADO") -> 0 | S13: 182956.36
B14: 45691 | C14: 1 | D14: 5 | E14: 1438 | F14: 27265302225 | G14: =IFERROR(IF(compras_mes2[[#This Row],[CUIT]]="","-",VLOOKUP(compras_mes2[[#This Row],[CUIT]],Lista_CUIT[#All],2,0)),"CUIT NO CARGADO") -> PRADO MARISOL | H14: 1200000 | I14: =IF(compras_mes2[[#This Row],[NETO GRAVADO]]="","",compras_mes2[[#This Row],[NETO GRAVADO]]*0.21) -> 252000 | P14: =SUM(compras_mes2[[#This Row],[NETO GRAVADO]:[Otros / No Grav.]]) -> 1452000 | Q14: =IFERROR(IF(compras_mes2[[#This Row],[CUIT]]="","-",VLOOKUP(compras_mes2[[#This Row],[CUIT]],Lista_CUIT[#All],3,0)),"CUIT NO CARGADO") -> INSUMO | R14: =IFERROR(IF(compras_mes2[[#This Row],[CUIT]]="","-",VLOOKUP(compras_mes2[[#This Row],[CUIT]],Lista_CUIT[#All],4,0)),"CUIT NO CARGADO") -> 0 | S14: 695750
B15: 45691 | C15: 1 | D15: 23 | E15: 7614 | F15: 30711776040 | G15: =IFERROR(IF(compras_mes2[[#This Row],[CUIT]]="","-",VLOOKUP(compras_mes2[[#This Row],[CUIT]],Lista_CUIT[#All],2,0)),"CUIT NO CARGADO") -> EXPRESO BICENTENARIO S.R.L | H15: 19433 | I15: =IF(compras_mes2[[#This Row],[NETO GRAVADO]]="","",compras_mes2[[#This Row],[NETO GRAVADO]]*0.21) -> 4080.93 | P15: =SUM(compras_mes2[[#This Row],[NETO GRAVADO]:[Otros / No Grav.]]) -> 23513.93 | Q15: =IFERROR(IF(compras_mes2[[#This Row],[CUIT]]="","-",VLOOKUP(compras_mes2[[#This Row],[CUIT]],Lista_CUIT[#All],3,0)),"CUIT NO CARGADO") -> Servicio Transporte | R15: =IFERROR(IF(compras_mes2[[#This Row],[CUIT]]="","-",VLOOKUP(compras_mes2[[#This Row],[CUIT]],Lista_CUIT[#All],4,0)),"CUIT NO CARGADO") -> 0 | S15: 696359.88
B16: 45691 | C16: 1 | D16: 500 | E16: 1681453 | F16: 30654118767 | G16: =IFERROR(IF(compras_mes2[[#This Row],[CUIT]]="","-",VLOOKUP(compras_mes2[[#This Row],[CUIT]],Lista_CUIT[#All],2,0)),"CUIT NO CARGADO") -> SOLUCIONES MULTIMEDIA SA | H16: 113718.7 | I16: =IF(compras_mes2[[#This Row],[NETO GRAVADO]]="","",compras_mes2[[#This Row],[NETO GRAVADO]]*0.21) -> 23880.927 | P16: =SUM(compras_mes2[[#This Row],[NETO GRAVADO]:[Otros / No Grav.]]) -> 137599.63 | Q16: =IFERROR(IF(compras_mes2[[#This Row],[CUIT]]="","-",VLOOKUP(compras_mes2[[#This Row],[CUIT]],Lista_CUIT[#All],3,0)),"CUIT NO CARGADO") -> gastos varios | R16: =IFERROR(IF(compras_mes2[[#This Row],[CUIT]]="","-",VLOOKUP(compras_mes2[[#This Row],[CUIT]],Lista_CUIT[#All],4,0)),"CUIT NO CARGADO") -> 0 | S16: 357748.6
B17: 45691 | C17: 1 | D17: 1 | E17: 722566 | F17: 33716307749 | G17: =IFERROR(IF(compras_mes2[[#This Row],[CUIT]]="","-",VLOOKUP(compras_mes2[[#This Row],[CUIT]],Lista_CUIT[#All],2,0)),"CUIT NO CARGADO") -> VERISURE ARGENTINA MONITOREO DE ALARMAS SA | H17: 49498.9 | I17: =IF(compras_mes2[[#This Row],[NETO GRAVADO]]="","",compras_mes2[[#This Row],[NETO GRAVADO]]*0.21) -> 10394.769 | P17: =SUM(compras_mes2[[#This Row],[NETO GRAVADO]:[Otros / No Grav.]]) -> 59893.669 | Q17: =IFERROR(IF(compras_mes2[[#This Row],[CUIT]]="","-",VLOOKUP(compras_mes2[[#This Row],[CUIT]],Lista_CUIT[#All],3,0)),"CUIT NO CARGADO") -> Serv. Seguridad | R17: =IFERROR(IF(compras_mes2[[#This Row],[CUIT]]="","-",VLOOKUP(compras_mes2[[#This Row],[CUIT]],Lista_CUIT[#All],4,0)),"CUIT NO CARGADO") -> 0 | S17: 1200000
B18: 45692 | C18: 1 | D18: 7 | E18: 1465 | F18: 30712187316 | G18: =IFERROR(IF(compras_mes2[[#This Row],[CUIT]]="","-",VLOOKUP(compras_mes2[[#This Row],[CUIT]],Lista_CUIT[#All],2,0)),"CUIT NO CARGADO") -> ITALOMED PRODUCTOS SRL | H18: 355547.74 | I18: =IF(compras_mes2[[#This Row],[NETO GRAVADO]]="","",compras_mes2[[#This Row],[NETO GRAVADO]]*0.21) -> 74665.025 | P18: =SUM(compras_mes2[[#This Row],[NETO GRAVADO]:[Otros / No Grav.]]) -> 430212.77 | Q18: =IFERROR(IF(compras_mes2[[#This Row],[CUIT]]="","-",VLOOKUP(compras_mes2[[#This Row],[CUIT]],Lista_CUIT[#All],3,0)),"CUIT NO CARGADO") -> INSUMO | R18: =IFERROR(IF(compras_mes2[[#This Row],[CUIT]]="","-",VLOOKUP(compras_mes2[[#This Row],[CUIT]],Lista_CUIT[#All],4,0)),"CUIT NO CARGADO") -> 0 | S18: 23837
B19: 45692 | C19: 1 | D19: 17 | E19: 11625 | F19: 30661143610 | G19: =IFERROR(IF(compras_mes2[[#This Row],[CUIT]]="","-",VLOOKUP(compras_mes2[[#This Row],[CUIT]],Lista_CUIT[#All],2,0)),"CUIT NO CARGADO") -> ORTOPEDIA BERNAT SRL | H19: 643559.14 | I19: =IF(compras_mes2[[#This Row],[NETO GRAVADO]]="","",compras_mes2[[#This Row],[NETO GRAVADO]]*0.21) -> 135147.42 | P19: =SUM(compras_mes2[[#This Row],[NETO GRAVADO]:[Otros / No Grav.]]) -> 778706.56 | Q19: =IFERROR(IF(compras_mes2[[#This Row],[CUIT]]="","-",VLOOKUP(compras_mes2[[#This Row],[CUIT]],Lista_CUIT[#All],3,0)),"CUIT NO CARGADO") -> INSUMO | R19: =IFERROR(IF(compras_mes2[[#This Row],[CUIT]]="","-",VLOOKUP(compras_mes2[[#This Row],[CUIT]],Lista_CUIT[#All],4,0)),"CUIT NO CARGADO") -> 0 | S19: 1394.63
B20: 45692 | C20: 1 | D20: 5 | E20: 163325 | F20: 30598960093 | G20: =IFERROR(IF(compras_mes2[[#This Row],[CUIT]]="","-",VLOOKUP(compras_mes2[[#This Row],[CUIT]],Lista_CUIT[#All],2,0)),"CUIT NO CARGADO") -> SILVESTRIN FABRIS SRL | H20: 453720 | I20: =IF(compras_mes2[[#This Row],[NETO GRAVADO]]="","",compras_mes2[[#This Row],[NETO GRAVADO]]*0.21) -> 95281.2 | P20: =SUM(compras_mes2[[#This Row],[NETO GRAVADO]:[Otros / No Grav.]]) -> 549001.2 | Q20: =IFERROR(IF(compras_mes2[[#This Row],[CUIT]]="","-",VLOOKUP(compras_mes2[[#This Row],[CUIT]],Lista_CUIT[#All],3,0)),"CUIT NO CARGADO") -> INSUMO | R20: =IFERROR(IF(compras_mes2[[#This Row],[CUIT]]="","-",VLOOKUP(compras_mes2[[#This Row],[CUIT]],Lista_CUIT[#All],4,0)),"CUIT NO CARGADO") -> 0 | S20: 1394.63
B21: 45692 | C21: 1 | D21: 5 | E21: 2205 | F21: 30712187316 | G21: =IFERROR(IF(compras_mes2[[#This Row],[CUIT]]="","-",VLOOKUP(compras_mes2[[#This Row],[CUIT]],Lista_CUIT[#All],2,0)),"CUIT NO CARGADO") -> ITALOMED PRODUCTOS SRL | H21: 219513.44 | I21: =IF(compras_mes2[[#This Row],[NETO GRAVADO]]="","",compras_mes2[[#This Row],[NETO GRAVADO]]*0.21) -> 46097.822 | P21: =SUM(compras_mes2[[#This Row],[NETO GRAVADO]:[Otros / No Grav.]]) -> 265611.26 | Q21: =IFERROR(IF(compras_mes2[[#This Row],[CUIT]]="","-",VLOOKUP(compras_mes2[[#This Row],[CUIT]],Lista_CUIT[#All],3,0)),"CUIT NO CARGADO") -> INSUMO | R21: =IFERROR(IF(compras_mes2[[#This Row],[CUIT]]="","-",VLOOKUP(compras_mes2[[#This Row],[CUIT]],Lista_CUIT[#All],4,0)),"CUIT NO CARGADO") -> 0 | S21: 171435
B22: 45693 | C22: 1 | D22: 700 | E22: 2247740 | F22: 30715804812 | G22: =IFERROR(IF(compras_mes2[[#This Row],[CUIT]]="","-",VLOOKUP(compras_mes2[[#This Row],[CUIT]],Lista_CUIT[#All],2,0)),"CUIT NO CARGADO") -> CORREDORES VIALES SOCIEDAD ANONIMA | H22: 2079.97 | I22: =IF(compras_mes2[[#This Row],[NETO GRAVADO]]="","",compras_mes2[[#This Row],[NETO GRAVADO]]*0.21) -> 436.7937 | P22: =SUM(compras_mes2[[#This Row],[NETO GRAVADO]:[Otros / No Grav.]]) -> 2516.7637 | Q22: =IFERROR(IF(compras_mes2[[#This Row],[CUIT]]="","-",VLOOKUP(compras_mes2[[#This Row],[CUIT]],Lista_CUIT[#All],3,0)),"CUIT NO CARGADO") -> Autopista | R22: =IFERROR(IF(compras_mes2[[#This Row],[CUIT]]="","-",VLOOKUP(compras_mes2[[#This Row],[CUIT]],Lista_CUIT[#All],4,0)),"CUIT NO CARGADO") -> 0 | S22: 481999
B23: 45693 | C23: 1 | D23: 700 | E23: 2247741 | F23: 30715804812 | G23: =IFERROR(IF(compras_mes2[[#This Row],[CUIT]]="","-",VLOOKUP(compras_mes2[[#This Row],[CUIT]],Lista_CUIT[#All],2,0)),"CUIT NO CARGADO") -> CORREDORES VIALES SOCIEDAD ANONIMA | H23: 5407.9 | I23: =IF(compras_mes2[[#This Row],[NETO GRAVADO]]="","",compras_mes2[[#This Row],[NETO GRAVADO]]*0.21) -> 1135.659 | P23: =SUM(compras_mes2[[#This Row],[NETO GRAVADO]:[Otros / No Grav.]]) -> 6543.559 | Q23: =IFERROR(IF(compras_mes2[[#This Row],[CUIT]]="","-",VLOOKUP(compras_mes2[[#This Row],[CUIT]],Lista_CUIT[#All],3,0)),"CUIT NO CARGADO") -> Autopista | R23: =IFERROR(IF(compras_mes2[[#This Row],[CUIT]]="","-",VLOOKUP(compras_mes2[[#This Row],[CUIT]],Lista_CUIT[#All],4,0)),"CUIT NO CARGADO") -> 0 | S23: 116708
... B31: 45696 | C31: 1 | D31: 2019 | E31: 266598 | F31: 30516186670 | G31: =IFERROR(IF(compras_mes2[[#This Row],[CUIT]]="","-",VLOOKUP(compras_mes2[[#This Row],[CUIT]],Lista_CUIT[#All],2,0)),"CUIT NO CARGADO") -> DEHEZA SAICF E I | H31: 40217.66 | I31: =IF(compras_mes2[[#This Row],[NETO GRAVADO]]="","",compras_mes2[[#This Row],[NETO GRAVADO]]*0.21) -> 8445.7086 | P31: =SUM(compras_mes2[[#This Row],[NETO GRAVADO]:[Otros / No Grav.]]) -> 48663.369 | Q31: =IFERROR(IF(compras_mes2[[#This Row],[CUIT]]="","-",VLOOKUP(compras_mes2[[#This Row],[CUIT]],Lista_CUIT[#All],3,0)),"CUIT NO CARGADO") -> COMBUSTIBLE | R31: =IFERROR(IF(compras_mes2[[#This Row],[CUIT]]="","-",VLOOKUP(compras_mes2[[#This Row],[CUIT]],Lista_CUIT[#All],4,0)),"CUIT NO CARGADO") -> 0 | S31: 956080
B32: 45696 | C32: 1 | D32: 711 | E32: 6694090 | F32: 30677237119 | G32: =IFERROR(IF(compras_mes2[[#This Row],[CUIT]]="","-",VLOOKUP(compras_mes2[[#This Row],[CUIT]],Lista_CUIT[#All],2,0)),"CUIT NO CARGADO") -> AUTOPISTAS DEL SOL SA | H32: 5430.98 | I32: =IF(compras_mes2[[#This Row],[NETO GRAVADO]]="","",compras_mes2[[#This Row],[NETO GRAVADO]]*0.21) -> 1140.5058 | O32: 162.93 | P32: =SUM(compras_mes2[[#This Row],[NETO GRAVADO]:[Otros / No Grav.]]) -> 6734.4158 | Q32: =IFERROR(IF(compras_mes2[[#This Row],[CUIT]]="","-",VLOOKUP(compras_mes2[[#This Row],[CUIT]],Lista_CUIT[#All],3,0)),"CUIT NO CARGADO") -> Autopista | R32: =IFERROR(IF(compras_mes2[[#This Row],[CUIT]]="","-",VLOOKUP(compras_mes2[[#This Row],[CUIT]],Lista_CUIT[#All],4,0)),"CUIT NO CARGADO") -> 0 | S32: 413221.08
B33: 45696 | C33: 1 | D33: 5015 | E33: 745697 | F33: 30574876474 | G33: =IFERROR(IF(compras_mes2[[#This Row],[CUIT]]="","-",VLOOKUP(compras_mes2[[#This Row],[CUIT]],Lista_CUIT[#All],2,0)),"CUIT NO CARGADO") -> AUTOP. URBANAS SA | H33: 22267.28 | I33: =IF(compras_mes2[[#This Row],[NETO GRAVADO]]="","",compras_mes2[[#This Row],[NETO GRAVADO]]*0.21) -> 4676.1288 | P33: =SUM(compras_mes2[[#This Row],[NETO GRAVADO]:[Otros / No Grav.]]) -> 26943.409 | Q33: =IFERROR(IF(compras_mes2[[#This Row],[CUIT]]="","-",VLOOKUP(compras_mes2[[#This Row],[CUIT]],Lista_CUIT[#All],3,0)),"CUIT NO CARGADO") -> PEAJE | R33: =IFERROR(IF(compras_mes2[[#This Row],[CUIT]]="","-",VLOOKUP(compras_mes2[[#This Row],[CUIT]],Lista_CUIT[#All],4,0)),"CUIT NO CARGADO") -> 0 | S33: 87109.57
B34: 45697 | C34: 1 | D34: 3101 | E34: 263748 | F34: 30678814357 | G34: =IFERROR(IF(compras_mes2[[#This Row],[CUIT]]="","-",VLOOKUP(compras_mes2[[#This Row],[CUIT]],Lista_CUIT[#All],2,0)),"CUIT NO CARGADO") -> TELEFONICA MOVILES ARG SA | H34: 91600.07 | J34: =compras_mes2[[#This Row],[NETO GRAVADO]]*27/100 -> 24732.019 | P34: =SUM(compras_mes2[[#This Row],[NETO GRAVADO]:[Otros / No Grav.]]) -> 116332.09 | Q34: =IFERROR(IF(compras_mes2[[#This Row],[CUIT]]="","-",VLOOKUP(compras_mes2[[#This Row],[CUIT]],Lista_CUIT[#All],3,0)),"CUIT NO CARGADO") -> SERVICIO | R34: =IFERROR(IF(compras_mes2[[#This Row],[CUIT]]="","-",VLOOKUP(compras_mes2[[#This Row],[CUIT]],Lista_CUIT[#All],4,0)),"CUIT NO CARGADO") -> 0 | S34: 5371.9
B35: 45698 | C35: 1 | D35: 2 | E35: 11420 | F35: 30714331082 | G35: =IFERROR(IF(compras_mes2[[#This Row],[CUIT]]="","-",VLOOKUP(compras_mes2[[#This Row],[CUIT]],Lista_CUIT[#All],2,0)),"CUIT NO CARGADO") -> ORTOPEDIA CASA ESCALADA SRL | H35: 4007577.6 | I35: =IF(compras_mes2[[#This Row],[NETO GRAVADO]]="","",compras_mes2[[#This Row],[NETO GRAVADO]]*0.21) -> 841591.31 | P35: =SUM(compras_mes2[[#This Row],[NETO GRAVADO]:[Otros / No Grav.]]) -> 4849169 | Q35: =IFERROR(IF(compras_mes2[[#This Row],[CUIT]]="","-",VLOOKUP(compras_mes2[[#This Row],[CUIT]],Lista_CUIT[#All],3,0)),"CUIT NO CARGADO") -> INSUMO | R35: =IFERROR(IF(compras_mes2[[#This Row],[CUIT]]="","-",VLOOKUP(compras_mes2[[#This Row],[CUIT]],Lista_CUIT[#All],4,0)),"CUIT NO CARGADO") -> 0 | S35: 6596.25
B36: 45698 | C36: 1 | D36: 2 | E36: 11419 | F36: 30714331082 | G36: =IFERROR(IF(compras_mes2[[#This Row],[CUIT]]="","-",VLOOKUP(compras_mes2[[#This Row],[CUIT]],Lista_CUIT[#All],2,0)),"CUIT NO CARGADO") -> ORTOPEDIA CASA ESCALADA SRL | H36: 465345.68 | K36: =compras_mes2[[#This Row],[NETO GRAVADO]]*10.5/100 -> 48861.296 | P36: =SUM(compras_mes2[[#This Row],[NETO GRAVADO]:[Otros / No Grav.]]) -> 514206.98 | Q36: =IFERROR(IF(compras_mes2[[#This Row],[CUIT]]="","-",VLOOKUP(compras_mes2[[#This Row],[CUIT]],Lista_CUIT[#All],3,0)),"CUIT NO CARGADO") -> INSUMO | R36: =IFERROR(IF(compras_mes2[[#This Row],[CUIT]]="","-",VLOOKUP(compras_mes2[[#This Row],[CUIT]],Lista_CUIT[#All],4,0)),"CUIT NO CARGADO") -> 0 | S36: 22929.5
B37: 45698 | C37: 1 | D37: 6 | E37: 88871 | F37: 30711553564 | G37: =IFERROR(IF(compras_mes2[[#This Row],[CUIT]]="","-",VLOOKUP(compras_mes2[[#This Row],[CUIT]],Lista_CUIT[#All],2,0)),"CUIT NO CARGADO") -> SALUD TEX S.A | H37: 279138.5 | I37: =IF(compras_mes2[[#This Row],[NETO GRAVADO]]="","",compras_mes2[[#This Row],[NETO GRAVADO]]*0.21) -> 58619.085 | P37: =SUM(compras_mes2[[#This Row],[NETO GRAVADO]:[Otros / No Grav.]]) -> 337757.59 | Q37: =IFERROR(IF(compras_mes2[[#This Row],[CUIT]]="","-",VLOOKUP(compras_mes2[[#This Row],[CUIT]],Lista_CUIT[#All],3,0)),"CUIT NO CARGADO") -> INSUMO | R37: =IFERROR(IF(compras_mes2[[#This Row],[CUIT]]="","-",VLOOKUP(compras_mes2[[#This Row],[CUIT]],Lista_CUIT[#All],4,0)),"CUIT NO CARGADO") -> 0 | S37: 285000
B38: 45698 | C38: 1 | D38: 3 | E38: 47974 | F38: 30711454388 | G38: =IFERROR(IF(compras_mes2[[#This Row],[CUIT]]="","-",VLOOKUP(compras_mes2[[#This Row],[CUIT]],Lista_CUIT[#All],2,0)),"CUIT NO CARGADO") -> LIPROT S.R.L. | H38: 163900 | I38: =IF(compras_mes2[[#This Row],[NETO GRAVADO]]="","",compras_mes2[[#This Row],[NETO GRAVADO]]*0.21) -> 34419 | P38: =SUM(compras_mes2[[#This Row],[NETO GRAVADO]:[Otros / No Grav.]]) -> 198319 | Q38: =IFERROR(IF(compras_mes2[[#This Row],[CUIT]]="","-",VLOOKUP(compras_mes2[[#This Row],[CUIT]],Lista_CUIT[#All],3,0)),"CUIT NO CARGADO") -> textil | R38: =IFERROR(IF(compras_mes2[[#This Row],[CUIT]]="","-",VLOOKUP(compras_mes2[[#This Row],[CUIT]],Lista_CUIT[#All],4,0)),"CUIT NO CARGADO") -> 0 | S38: 40214.11
B39: 45699 | C39: 1 | D39: 26 | E39: 203264 | F39: 30708847247 | G39: =IFERROR(IF(compras_mes2[[#This Row],[CUIT]]="","-",VLOOKUP(compras_mes2[[#This Row],[CUIT]],Lista_CUIT[#All],2,0)),"CUIT NO CARGADO") -> TOAGRA SRL | H39: 12815.9 | I39: =IF(compras_mes2[[#This Row],[NETO GRAVADO]]="","",compras_mes2[[#This Row],[NETO GRAVADO]]*0.21) -> 2691.339 | P39: =SUM(compras_mes2[[#This Row],[NETO GRAVADO]:[Otros / No Grav.]]) -> 15507.239 | Q39: =IFERROR(IF(compras_mes2[[#This Row],[CUIT]]="","-",VLOOKUP(compras_mes2[[#This Row],[CUIT]],Lista_CUIT[#All],3,0)),"CUIT NO CARGADO") -> FLETE | R39: =IFERROR(IF(compras_mes2[[#This Row],[CUIT]]="","-",VLOOKUP(compras_mes2[[#This Row],[CUIT]],Lista_CUIT[#All],4,0)),"CUIT NO CARGADO") -> 0 | S39: 34999.98
B40: 45699 | C40: 1 | D40: 1 | E40: 6332 | F40: 30715141201 | G40: =IFERROR(IF(compras_mes2[[#This Row],[CUIT]]="","-",VLOOKUP(compras_mes2[[#This Row],[CUIT]],Lista_CUIT[#All],2,0)),"CUIT NO CARGADO") -> REHAB SRL | H40: 64545 | I40: =IF(compras_mes2[[#This Row],[NETO GRAVADO]]="","",compras_mes2[[#This Row],[NETO GRAVADO]]*0.21) -> 13554.45 | P40: =SUM(compras_mes2[[#This Row],[NETO GRAVADO]:[Otros / No Grav.]]) -> 78099.45 | Q40: =IFERROR(IF(compras_mes2[[#This Row],[CUIT]]="","-",VLOOKUP(compras_mes2[[#This Row],[CUIT]],Lista_CUIT[#All],3,0)),"CUIT NO CARGADO") -> INSUMO | R40: =IFERROR(IF(compras_mes2[[#This Row],[CUIT]]="","-",VLOOKUP(compras_mes2[[#This Row],[CUIT]],Lista_CUIT[#All],4,0)),"CUIT NO CARGADO") -> 0 | S40: 24000
B41: 45699 | C41: 1 | D41: 32 | E41: 156584 | F41: 30708847247 | G41: =IFERROR(IF(compras_mes2[[#This Row],[CUIT]]="","-",VLOOKUP(compras_mes2[[#This Row],[CUIT]],Lista_CUIT[#All],2,0)),"CUIT NO CARGADO") -> TOAGRA SRL | H41: 27257.62 | I41: =IF(compras_mes2[[#This Row],[NETO GRAVADO]]="","",compras_mes2[[#This Row],[NETO GRAVADO]]*0.21) -> 5724.1002 | P41: =SUM(compras_mes2[[#This Row],[NETO GRAVADO]:[Otros / No Grav.]]) -> 32981.72 | Q41: =IFERROR(IF(compras_mes2[[#This Row],[CUIT]]="","-",VLOOKUP(compras_mes2[[#This Row],[CUIT]],Lista_CUIT[#All],3,0)),"CUIT NO CARGADO") -> FLETE | R41: =IFERROR(IF(compras_mes2[[#This Row],[CUIT]]="","-",VLOOKUP(compras_mes2[[#This Row],[CUIT]],Lista_CUIT[#All],4,0)),"CUIT NO CARGADO") -> 0 | S41: 808361.07
B42: 45699 | C42: 1 | D42: 120 | E42: 5506 | F42: 30587197215 | G42: =IFERROR(IF(compras_mes2[[#This Row],[CUIT]]="","-",VLOOKUP(compras_mes2[[#This Row],[CUIT]],Lista_CUIT[#All],2,0)),"CUIT NO CARGADO") -> PANATEL SOCIEDAD ANONIMA | H42: 95041.32 | I42: =IF(compras_mes2[[#This Row],[NETO GRAVADO]]="","",compras_mes2[[#This Row],[NETO GRAVADO]]*0.21) -> 19958.677 | P42: =SUM(compras_mes2[[#This Row],[NETO GRAVADO]:[Otros / No Grav.]]) -> 115000 | Q42: =IFERROR(IF(compras_mes2[[#This Row],[CUIT]]="","-",VLOOKUP(compras_mes2[[#This Row],[CUIT]],Lista_CUIT[#All],3,0)),"CUIT NO CARGADO") -> SERVICIOS DE ALOJAMIENTO EN HOTELES | R42: =IFERROR(IF(compras_mes2[[#This Row],[CUIT]]="","-",VLOOKUP(compras_mes2[[#This Row],[CUIT]],Lista_CUIT[#All],4,0)),"CUIT NO CARGADO") -> 0 | S42: 2834920
B43: 45699 | C43: 1 | D43: 5 | E43: 1460 | F43: 27265302225 | G43: =IFERROR(IF(compras_mes2[[#This Row],[CUIT]]="","-",VLOOKUP(compras_mes2[[#This Row],[CUIT]],Lista_CUIT[#All],2,0)),"CUIT NO CARGADO") -> PRADO MARISOL | H43: 1 | I43: =IF(compras_mes2[[#This Row],[NETO GRAVADO]]="","",compras_mes2[[#This Row],[NETO GRAVADO]]*0.21) -> 0.21 | P43: =SUM(compras_mes2[[#This Row],[NETO GRAVADO]:[Otros / No Grav.]]) -> 1.21 | Q43: =IFERROR(IF(compras_mes2[[#This Row],[CUIT]]="","-",VLOOKUP(compras_mes2[[#This Row],[CUIT]],Lista_CUIT[#All],3,0)),"CUIT NO CARGADO") -> INSUMO | R43: =IFERROR(IF(compras_mes2[[#This Row],[CUIT]]="","-",VLOOKUP(compras_mes2[[#This Row],[CUIT]],Lista_CUIT[#All],4,0)),"CUIT NO CARGADO") -> 0 | S43: 5853.75
B44: 45700 | C44: 1 | D44: 2 | E44: 11442 | F44: 30714331082 | G44: =IFERROR(IF(compras_mes2[[#This Row],[CUIT]]="","-",VLOOKUP(compras_mes2[[#This Row],[CUIT]],Lista_CUIT[#All],2,0)),"CUIT NO CARGADO") -> ORTOPEDIA CASA ESCALADA SRL | H44: 1269066.3 | I44: =IF(compras_mes2[[#This Row],[NETO GRAVADO]]="","",compras_mes2[[#This Row],[NETO GRAVADO]]*0.21) -> 266503.91 | P44: =SUM(compras_mes2[[#This Row],[NETO GRAVADO]:[Otros / No Grav.]]) -> 1535570.2 | Q44: =IFERROR(IF(compras_mes2[[#This Row],[CUIT]]="","-",VLOOKUP(compras_mes2[[#This Row],[CUIT]],Lista_CUIT[#All],3,0)),"CUIT NO CARGADO") -> INSUMO | R44: =IFERROR(IF(compras_mes2[[#This Row],[CUIT]]="","-",VLOOKUP(compras_mes2[[#This Row],[CUIT]],Lista_CUIT[#All],4,0)),"CUIT NO CARGADO") -> 0 | S44: 7290406.4
B45: 45700 | C45: 1 | D45: 5 | E45: 163567 | F45: 30598960093 | G45: =IFERROR(IF(compras_mes2[[#This Row],[CUIT]]="","-",VLOOKUP(compras_mes2[[#This Row],[CUIT]],Lista_CUIT[#All],2,0)),"CUIT NO CARGADO") -> SILVESTRIN FABRIS SRL | H45: 1231762.2 | I45: 25389.88 | K45: 116640.09 | P45: =SUM(compras_mes2[[#This Row],[NETO GRAVADO]:[Otros / No Grav.]]) -> 1373792.2 | Q45: =IFERROR(IF(compras_mes2[[#This Row],[CUIT]]="","-",VLOOKUP(compras_mes2[[#This Row],[CUIT]],Lista_CUIT[#All],3,0)),"CUIT NO CARGADO") -> INSUMO | R45: =IFERROR(IF(compras_mes2[[#This Row],[CUIT]]="","-",VLOOKUP(compras_mes2[[#This Row],[CUIT]],Lista_CUIT[#All],4,0)),"CUIT NO CARGADO") -> 0 | S45: 39750.27
B46: 45700 | C46: 1 | D46: 2 | E46: 11443 | F46: 30714331082 | G46: =IFERROR(IF(compras_mes2[[#This Row],[CUIT]]="","-",VLOOKUP(compras_mes2[[#This Row],[CUIT]],Lista_CUIT[#All],2,0)),"CUIT NO CARGADO") -> ORTOPEDIA CASA ESCALADA SRL | H46: 341383.77 | I46: =IF(compras_mes2[[#This Row],[NETO GRAVADO]]="","",compras_mes2[[#This Row],[NETO GRAVADO]]*0.21) -> 71690.592 | P46: =SUM(compras_mes2[[#This Row],[NETO GRAVADO]:[Otros / No Grav.]]) -> 413074.36 | Q46: =IFERROR(IF(compras_mes2[[#This Row],[CUIT]]="","-",VLOOKUP(compras_mes2[[#This Row],[CUIT]],Lista_CUIT[#All],3,0)),"CUIT NO CARGADO") -> INSUMO | R46: =IFERROR(IF(compras_mes2[[#This Row],[CUIT]]="","-",VLOOKUP(compras_mes2[[#This Row],[CUIT]],Lista_CUIT[#All],4,0)),"CUIT NO CARGADO") -> 0 | S46: 210139.51
B47: 45701 | C47: 1 | D47: 5 | E47: 24333 | F47: 30656038752 | G47: =IFERROR(IF(compras_mes2[[#This Row],[CUIT]]="","-",VLOOKUP(compras_mes2[[#This Row],[CUIT]],Lista_CUIT[#All],2,0)),"CUIT NO CARGADO") -> ALFREDO OMAR POTENZA SRL | H47: 314389.25 | I47: =IF(compras_mes2[[#This Row],[NETO GRAVADO]]="","",compras_mes2[[#This Row],[NETO GRAVADO]]*0.21) -> 66021.742 | P47: =SUM(compras_mes2[[#This Row],[NETO GRAVADO]:[Otros / No Grav.]]) -> 380410.99 | Q47: =IFERROR(IF(compras_mes2[[#This Row],[CUIT]]="","-",VLOOKUP(compras_mes2[[#This Row],[CUIT]],Lista_CUIT[#All],3,0)),"CUIT NO CARGADO") -> INSUMO | R47: =IFERROR(IF(compras_mes2[[#This Row],[CUIT]]="","-",VLOOKUP(compras_mes2[[#This Row],[CUIT]],Lista_CUIT[#All],4,0)),"CUIT NO CARGADO") -> 0 | S47: 130482.28
B48: 45701 | C48: 1 | D48: 2 | E48: 1080 | F48: 20272865869 | G48: =IFERROR(IF(compras_mes2[[#This Row],[CUIT]]="","-",VLOOKUP(compras_mes2[[#This Row],[CUIT]],Lista_CUIT[#All],2,0)),"CUIT NO CARGADO") -> DI FEO MARTIN EZEQUIEL | H48: 397580 | I48: =IF(compras_mes2[[#This Row],[NETO GRAVADO]]="","",compras_mes2[[#This Row],[NETO GRAVADO]]*0.21) -> 83491.8 | P48: =SUM(compras_mes2[[#This Row],[NETO GRAVADO]:[Otros / No Grav.]]) -> 481071.8 | Q48: =IFERROR(IF(compras_mes2[[#This Row],[CUIT]]="","-",VLOOKUP(compras_mes2[[#This Row],[CUIT]],Lista_CUIT[#All],3,0)),"CUIT NO CARGADO") -> INSUMOS | R48: =IFERROR(IF(compras_mes2[[#This Row],[CUIT]]="","-",VLOOKUP(compras_mes2[[#This Row],[CUIT]],Lista_CUIT[#All],4,0)),"CUIT NO CARGADO") -> 0 | S48: 126445
B49: 45702 | C49: 1 | D49: 5 | E49: 2227 | F49: 30712187316 | G49: =IFERROR(IF(compras_mes2[[#This Row],[CUIT]]="","-",VLOOKUP(compras_mes2[[#This Row],[CUIT]],Lista_CUIT[#All],2,0)),"CUIT NO CARGADO") -> ITALOMED PRODUCTOS SRL | H49: 400088.92 | I49: =IF(compras_mes2[[#This Row],[NETO GRAVADO]]="","",compras_mes2[[#This Row],[NETO GRAVADO]]*0.21) -> 84018.673 | P49: =SUM(compras_mes2[[#This Row],[NETO GRAVADO]:[Otros / No Grav.]]) -> 484107.59 | Q49: =IFERROR(IF(compras_mes2[[#This Row],[CUIT]]="","-",VLOOKUP(compras_mes2[[#This Row],[CUIT]],Lista_CUIT[#All],3,0)),"CUIT NO CARGADO") -> INSUMO | R49: =IFERROR(IF(compras_mes2[[#This Row],[CUIT]]="","-",VLOOKUP(compras_mes2[[#This Row],[CUIT]],Lista_CUIT[#All],4,0)),"CUIT NO CARGADO") -> 0 | S49: 44000
B50: 45702 | C50: 1 | D50: 2 | E50: 1083 | F50: 20272865869 | G50: =IFERROR(IF(compras_mes2[[#This Row],[CUIT]]="","-",VLOOKUP(compras_mes2[[#This Row],[CUIT]],Lista_CUIT[#All],2,0)),"CUIT NO CARGADO") -> DI FEO MARTIN EZEQUIEL | H50: 12050 | I50: =IF(compras_mes2[[#This Row],[NETO GRAVADO]]="","",compras_mes2[[#This Row],[NETO GRAVADO]]*0.21) -> 2530.5 | P50: =SUM(compras_mes2[[#This Row],[NETO GRAVADO]:[Otros / No Grav.]]) -> 14580.5 | Q50: =IFERROR(IF(compras_mes2[[#This Row],[CUIT]]="","-",VLOOKUP(compras_mes2[[#This Row],[CUIT]],Lista_CUIT[#All],3,0)),"CUIT NO CARGADO") -> INSUMOS | R50: =IFERROR(IF(compras_mes2[[#This Row],[CUIT]]="","-",VLOOKUP(compras_mes2[[#This Row],[CUIT]],Lista_CUIT[#All],4,0)),"CUIT NO CARGADO") -> 0 | S50: 226834.59
B51: 45702 | C51: 1 | D51: 8 | E51: 369 | F51: 30643518364 | G51: =IFERROR(IF(compras_mes2[[#This Row],[CUIT]]="","-",VLOOKUP(compras_mes2[[#This Row],[CUIT]],Lista_CUIT[#All],2,0)),"CUIT NO CARGADO") -> FARMACIA DE MEDRANO SCS | H51: 390810 | I51: =IF(compras_mes2[[#This Row],[NETO GRAVADO]]="","",compras_mes2[[#This Row],[NETO GRAVADO]]*0.21) -> 82070.1 | P51: =SUM(compras_mes2[[#This Row],[NETO GRAVADO]:[Otros / No Grav.]]) -> 472880.1 | Q51: =IFERROR(IF(compras_mes2[[#This Row],[CUIT]]="","-",VLOOKUP(compras_mes2[[#This Row],[CUIT]],Lista_CUIT[#All],3,0)),"CUIT NO CARGADO") -> INSUMO | R51: =IFERROR(IF(compras_mes2[[#This Row],[CUIT]]="","-",VLOOKUP(compras_mes2[[#This Row],[CUIT]],Lista_CUIT[#All],4,0)),"CUIT NO CARGADO") -> 0 | S51: 115000
B52: 45702 | C52: 1 | D52: 17 | E52: 11738 | F52: 30661143610 | G52: =IFERROR(IF(compras_mes2[[#This Row],[CUIT]]="","-",VLOOKUP(compras_mes2[[#This Row],[CUIT]],Lista_CUIT[#All],2,0)),"CUIT NO CARGADO") -> ORTOPEDIA BERNAT SRL | H52: 609070 | I52: =IF(compras_mes2[[#This Row],[NETO GRAVADO]]="","",compras_mes2[[#This Row],[NETO GRAVADO]]*0.21) -> 127904.7 | P52: =SUM(compras_mes2[[#This Row],[NETO GRAVADO]:[Otros / No Grav.]]) -> 736974.7 | Q52: =IFERROR(IF(compras_mes2[[#This Row],[CUIT]]="","-",VLOOKUP(compras_mes2[[#This Row],[CUIT]],Lista_CUIT[#All],3,0)),"CUIT NO CARGADO") -> INSUMO | R52: =IFERROR(IF(compras_mes2[[#This Row],[CUIT]]="","-",VLOOKUP(compras_mes2[[#This Row],[CUIT]],Lista_CUIT[#All],4,0)),"CUIT NO CARGADO") -> 0 | S52: 12700
B53: 45702 | C53: 1 | D53: 8 | E53: 1749 | F53: 30708973501 | G53: =IFERROR(IF(compras_mes2[[#This Row],[CUIT]]="","-",VLOOKUP(compras_mes2[[#This Row],[CUIT]],Lista_CUIT[#All],2,0)),"CUIT NO CARGADO") -> ASIAL SRL | H53: 490420 | I53: =IF(compras_mes2[[#This Row],[NETO GRAVADO]]="","",compras_mes2[[#This Row],[NETO GRAVADO]]*0.21) -> 102988.2 | P53: =SUM(compras_mes2[[#This Row],[NETO GRAVADO]:[Otros / No Grav.]]) -> 593408.2 | Q53: =IFERROR(IF(compras_mes2[[#This Row],[CUIT]]="","-",VLOOKUP(compras_mes2[[#This Row],[CUIT]],Lista_CUIT[#All],3,0)),"CUIT NO CARGADO") -> INSUMO | R53: =IFERROR(IF(compras_mes2[[#This Row],[CUIT]]="","-",VLOOKUP(compras_mes2[[#This Row],[CUIT]],Lista_CUIT[#All],4,0)),"CUIT NO CARGADO") -> 0 | S53: 6346.25
B54: 45703 | C54: 1 | D54: 5015 | E54: 748565 | F54: 30574876474 | G54: =IFERROR(IF(compras_mes2[[#This Row],[CUIT]]="","-",VLOOKUP(compras_mes2[[#This Row],[CUIT]],Lista_CUIT[#All],2,0)),"CUIT NO CARGADO") -> AUTOP. URBANAS SA | H54: 28143.42 | I54: =IF(compras_mes2[[#This Row],[NETO GRAVADO]]="","",compras_mes2[[#This Row],[NETO GRAVADO]]*0.21) -> 5910.1182 | P54: =SUM(compras_mes2[[#This Row],[NETO GRAVADO]:[Otros / No Grav.]]) -> 34053.538 | Q54: =IFERROR(IF(compras_mes2[[#This Row],[CUIT]]="","-",VLOOKUP(compras_mes2[[#This Row],[CUIT]],Lista_CUIT[#All],3,0)),"CUIT NO CARGADO") -> PEAJE | R54: =IFERROR(IF(compras_mes2[[#This Row],[CUIT]]="","-",VLOOKUP(compras_mes2[[#This Row],[CUIT]],Lista_CUIT[#All],4,0)),"CUIT NO CARGADO") -> 0 | S54: 4038.75
B55: 45703 | C55: 1 | D55: 5009 | E55: 1225857 | F55: 30574876474 | G55: =IFERROR(IF(compras_mes2[[#This Row],[CUIT]]="","-",VLOOKUP(compras_mes2[[#This Row],[CUIT]],Lista_CUIT[#All],2,0)),"CUIT NO CARGADO") -> AUTOP. URBANAS SA | H55: 3310.25 | I55: =IF(compras_mes2[[#This Row],[NETO GRAVADO]]="","",compras_mes2[[#This Row],[NETO GRAVADO]]*0.21) -> 695.1525 | P55: =SUM(compras_mes2[[#This Row],[NETO GRAVADO]:[Otros / No Grav.]]) -> 4005.4025 | Q55: =IFERROR(IF(compras_mes2[[#This Row],[CUIT]]="","-",VLOOKUP(compras_mes2[[#This Row],[CUIT]],Lista_CUIT[#All],3,0)),"CUIT NO CARGADO") -> PEAJE | R55: =IFERROR(IF(compras_mes2[[#This Row],[CUIT]]="","-",VLOOKUP(compras_mes2[[#This Row],[CUIT]],Lista_CUIT[#All],4,0)),"CUIT NO CARGADO") -> 0 | S55: 226834.59
B56: 45703 | C56: 1 | D56: 113 | E56: 4072169 | F56: 30577207190 | G56: =IFERROR(IF(compras_mes2[[#This Row],[CUIT]]="","-",VLOOKUP(compras_mes2[[#This Row],[CUIT]],Lista_CUIT[#All],2,0)),"CUIT NO CARGADO") -> COORDINACION ECOLOGICA AREA METROPOLITANA SOCIEDAD DEL ESTADO | H56: 1239.67 | I56: =IF(compras_mes2[[#This Row],[NETO GRAVADO]]="","",compras_mes2[[#This Row],[NETO GRAVADO]]*0.21) -> 260.3307 | P56: =SUM(compras_mes2[[#This Row],[NETO GRAVADO]:[Otros / No Grav.]]) -> 1500.0007 | Q56: =IFERROR(IF(compras_mes2[[#This Row],[CUIT]]="","-",VLOOKUP(compras_mes2[[#This Row],[CUIT]],Lista_CUIT[#All],3,0)),"CUIT NO CARGADO") -> gastos varios | R56: =IFERROR(IF(compras_mes2[[#This Row],[CUIT]]="","-",VLOOKUP(compras_mes2[[#This Row],[CUIT]],Lista_CUIT[#All],4,0)),"CUIT NO CARGADO") -> 0 | S56: 999000.01
B57: 45704 | C57: 1 | D57: 629 | E57: 5861197 | F57: 30663498513 | G57: =IFERROR(IF(compras_mes2[[#This Row],[CUIT]]="","-",VLOOKUP(compras_mes2[[#This Row],[CUIT]],Lista_CUIT[#All],2,0)),"CUIT NO CARGADO") -> GRUPO CONCES. DEL OESTE SA | H57: 4275.46 | I57: =IF(compras_mes2[[#This Row],[NETO GRAVADO]]="","",compras_mes2[[#This Row],[NETO GRAVADO]]*0.21) -> 897.8466 | P57: =SUM(compras_mes2[[#This Row],[NETO GRAVADO]:[Otros / No Grav.]]) -> 5173.3066 | Q57: =IFERROR(IF(compras_mes2[[#This Row],[CUIT]]="","-",VLOOKUP(compras_mes2[[#This Row],[CUIT]],Lista_CUIT[#All],3,0)),"CUIT NO CARGADO") -> Autopista | R57: =IFERROR(IF(compras_mes2[[#This Row],[CUIT]]="","-",VLOOKUP(compras_mes2[[#This Row],[CUIT]],Lista_CUIT[#All],4,0)),"CUIT NO CARGADO") -> 0 | S57: 4038.75
B58: 45704 | C58: 1 | D58: 711 | E58: 6750565 | F58: 30677237119 | G58: =IFERROR(IF(compras_mes2[[#This Row],[CUIT]]="","-",VLOOKUP(compras_mes2[[#This Row],[CUIT]],Lista_CUIT[#All],2,0)),"CUIT NO CARGADO") -> AUTOPISTAS DEL SOL SA | H58: 9244.25 | I58: =IF(compras_mes2[[#This Row],[NETO GRAVADO]]="","",compras_mes2[[#This Row],[NETO GRAVADO]]*0.21) -> 1941.2925 | O58: 277.33 | P58: =SUM(compras_mes2[[#This Row],[NETO GRAVADO]:[Otros / No Grav.]]) -> 11462.872 | Q58: =IFERROR(IF(compras_mes2[[#This Row],[CUIT]]="","-",VLOOKUP(compras_mes2[[#This Row],[CUIT]],Lista_CUIT[#All],3,0)),"CUIT NO CARGADO") -> Autopista | R58: =IFERROR(IF(compras_mes2[[#This Row],[CUIT]]="","-",VLOOKUP(compras_mes2[[#This Row],[CUIT]],Lista_CUIT[#All],4,0)),"CUIT NO CARGADO") -> 0 | S58: 55478.5
B59: 45705 | C59: 1 | D59: 4264 | E59: 5062414 | F59: 30639453738 | G59: =IFERROR(IF(compras_mes2[[#This Row],[CUIT]]="","-",VLOOKUP(compras_mes2[[#This Row],[CUIT]],Lista_CUIT[#All],2,0)),"CUIT NO CARGADO") -> TELECOM ARGENTINA SA | H59: 41922.94 | I59: =IF(compras_mes2[[#This Row],[NETO GRAVADO]]="","",compras_mes2[[#This Row],[NETO GRAVADO]]*0.21) -> 8803.8174 | P59: =SUM(compras_mes2[[#This Row],[NETO GRAVADO]:[Otros / No Grav.]]) -> 50726.757 | Q59: =IFERROR(IF(compras_mes2[[#This Row],[CUIT]]="","-",VLOOKUP(compras_mes2[[#This Row],[CUIT]],Lista_CUIT[#All],3,0)),"CUIT NO CARGADO") -> SERVICIO | R59: =IFERROR(IF(compras_mes2[[#This Row],[CUIT]]="","-",VLOOKUP(compras_mes2[[#This Row],[CUIT]],Lista_CUIT[#All],4,0)),"CUIT NO CARGADO") -> 0 | S59: 73447
B60: 45705 | C60: 1 | D60: 3 | E60: 28 | F60: 20216164262 | G60: =IFERROR(IF(compras_mes2[[#This Row],[CUIT]]="","-",VLOOKUP(compras_mes2[[#This Row],[CUIT]],Lista_CUIT[#All],2,0)),"CUIT NO CARGADO") -> VELEZ ALEJANDRO MARCELO | H60: 2292990.9 | I60: =IF(compras_mes2[[#This Row],[NETO GRAVADO]]="","",compras_mes2[[#This Row],[NETO GRAVADO]]*0.21) -> 481528.09 | P60: =SUM(compras_mes2[[#This Row],[NETO GRAVADO]:[Otros / No Grav.]]) -> 2774519 | Q60: =IFERROR(IF(compras_mes2[[#This Row],[CUIT]]="","-",VLOOKUP(compras_mes2[[#This Row],[CUIT]],Lista_CUIT[#All],3,0)),"CUIT NO CARGADO") -> Insumos | R60: =IFERROR(IF(compras_mes2[[#This Row],[CUIT]]="","-",VLOOKUP(compras_mes2[[#This Row],[CUIT]],Lista_CUIT[#All],4,0)),"CUIT NO CARGADO") -> 0 | S60: 11000.73
B61: 45706 | C61: 1 | D61: 9 | E61: 6409 | F61: 30693449525 | G61: =IFERROR(IF(compras_mes2[[#This Row],[CUIT]]="","-",VLOOKUP(compras_mes2[[#This Row],[CUIT]],Lista_CUIT[#All],2,0)),"CUIT NO CARGADO") -> PHONEMARK SRL | H61: 74561.98 | I61: =IF(compras_mes2[[#This Row],[NETO GRAVADO]]="","",compras_mes2[[#This Row],[NETO GRAVADO]]*0.21) -> 15658.016 | P61: =SUM(compras_mes2[[#This Row],[NETO GRAVADO]:[Otros / No Grav.]]) -> 90219.996 | Q61: =IFERROR(IF(compras_mes2[[#This Row],[CUIT]]="","-",VLOOKUP(compras_mes2[[#This Row],[CUIT]],Lista_CUIT[#All],3,0)),"CUIT NO CARGADO") -> Gastos Varios | R61: =IFERROR(IF(compras_mes2[[#This Row],[CUIT]]="","-",VLOOKUP(compras_mes2[[#This Row],[CUIT]],Lista_CUIT[#All],4,0)),"CUIT NO CARGADO") -> 0 | S61: 929.75
B62: 45706 | C62: 1 | D62: 4 | E62: 522 | F62: 20379223185 | G62: =IFERROR(IF(compras_mes2[[#This Row],[CUIT]]="","-",VLOOKUP(compras_mes2[[#This Row],[CUIT]],Lista_CUIT[#All],2,0)),"CUIT NO CARGADO") -> AYALA MAURICIO JUAN JOSE | H62: 194285 | I62: =IF(compras_mes2[[#This Row],[NETO GRAVADO]]="","",compras_mes2[[#This Row],[NETO GRAVADO]]*0.21) -> 40799.85 | P62: =SUM(compras_mes2[[#This Row],[NETO GRAVADO]:[Otros / No Grav.]]) -> 235084.85 | Q62: BIEN DE USO | R62: =IFERROR(IF(compras_mes2[[#This Row],[CUIT]]="","-",VLOOKUP(compras_mes2[[#This Row],[CUIT]],Lista_CUIT[#All],4,0)),"CUIT NO CARGADO") -> 0 | S62: 5003766.2
B63: 45707 | C63: 1 | D63: 6 | E63: 1338 | F63: 20247225243 | G63: =IFERROR(IF(compras_mes2[[#This Row],[CUIT]]="","-",VLOOKUP(compras_mes2[[#This Row],[CUIT]],Lista_CUIT[#All],2,0)),"CUIT NO CARGADO") -> VENTO HUGO GABRIEL | H63: 82947 | I63: =IF(compras_mes2[[#This Row],[NETO GRAVADO]]="","",compras_mes2[[#This Row],[NETO GRAVADO]]*0.21) -> 17418.87 | P63: =SUM(compras_mes2[[#This Row],[NETO GRAVADO]:[Otros / No Grav.]]) -> 100365.87 | Q63: =IFERROR(IF(compras_mes2[[#This Row],[CUIT]]="","-",VLOOKUP(compras_mes2[[#This Row],[CUIT]],Lista_CUIT[#All],3,0)),"CUIT NO CARGADO") -> INSUMO | R63: =IFERROR(IF(compras_mes2[[#This Row],[CUIT]]="","-",VLOOKUP(compras_mes2[[#This Row],[CUIT]],Lista_CUIT[#All],4,0)),"CUIT NO CARGADO") -> 0 | S63: 7780.28
B64: 45707 | C64: 1 | D64: 2 | E64: 11517 | F64: 30714331082 | G64: =IFERROR(IF(compras_mes2[[#This Row],[CUIT]]="","-",VLOOKUP(compras_mes2[[#This Row],[CUIT]],Lista_CUIT[#All],2,0)),"CUIT NO CARGADO") -> ORTOPEDIA CASA ESCALADA SRL | H64: 1480976.6 | I64: =IF(compras_mes2[[#This Row],[NETO GRAVADO]]="","",compras_mes2[[#This Row],[NETO GRAVADO]]*0.21) -> 311005.08 | P64: =SUM(compras_mes2[[#This Row],[NETO GRAVADO]:[Otros / No Grav.]]) -> 1791981.7 | Q64: =IFERROR(IF(compras_mes2[[#This Row],[CUIT]]="","-",VLOOKUP(compras_mes2[[#This Row],[CUIT]],Lista_CUIT[#All],3,0)),"CUIT NO CARGADO") -> INSUMO | R64: =IFERROR(IF(compras_mes2[[#This Row],[CUIT]]="","-",VLOOKUP(compras_mes2[[#This Row],[CUIT]],Lista_CUIT[#All],4,0)),"CUIT NO CARGADO") -> 0 | S64: 39600
B65: 45707 | C65: 1 | D65: 3 | E65: 8524 | F65: 33708218699 | G65: =IFERROR(IF(compras_mes2[[#This Row],[CUIT]]="","-",VLOOKUP(compras_mes2[[#This Row],[CUIT]],Lista_CUIT[#All],2,0)),"CUIT NO CARGADO") -> MANGGINI PABLO Y MANGGINI ULISES SOC. DE HECHO. | H65: 24000 | I65: =IF(compras_mes2[[#This Row],[NETO GRAVADO]]="","",compras_mes2[[#This Row],[NETO GRAVADO]]*0.21) -> 5040 | P65: =SUM(compras_mes2[[#This Row],[NETO GRAVADO]:[Otros / No Grav.]]) -> 29040 | Q65: =IFERROR(IF(compras_mes2[[#This Row],[CUIT]]="","-",VLOOKUP(compras_mes2[[#This Row],[CUIT]],Lista_CUIT[#All],3,0)),"CUIT NO CARGADO") -> SERVICIO | R65: =IFERROR(IF(compras_mes2[[#This Row],[CUIT]]="","-",VLOOKUP(compras_mes2[[#This Row],[CUIT]],Lista_CUIT[#All],4,0)),"CUIT NO CARGADO") -> 0 | S65: 1892885.6
B66: 45708 | C66: 1 | D66: 2 | E66: 1100 | F66: 20272865869 | G66: =IFERROR(IF(compras_mes2[[#This Row],[CUIT]]="","-",VLOOKUP(compras_mes2[[#This Row],[CUIT]],Lista_CUIT[#All],2,0)),"CUIT NO CARGADO") -> DI FEO MARTIN EZEQUIEL | H66: 147019.5 | I66: =IF(compras_mes2[[#This Row],[NETO GRAVADO]]="","",compras_mes2[[#This Row],[NETO GRAVADO]]*0.21) -> 30874.095 | P66: =SUM(compras_mes2[[#This Row],[NETO GRAVADO]:[Otros / No Grav.]]) -> 177893.6 | Q66: =IFERROR(IF(compras_mes2[[#This Row],[CUIT]]="","-",VLOOKUP(compras_mes2[[#This Row],[CUIT]],Lista_CUIT[#All],3,0)),"CUIT NO CARGADO") -> INSUMOS | R66: =IFERROR(IF(compras_mes2[[#This Row],[CUIT]]="","-",VLOOKUP(compras_mes2[[#This Row],[CUIT]],Lista_CUIT[#All],4,0)),"CUIT NO CARGADO") -> 0 | S66: 27000
B67: 45708 | C67: 1 | D67: 5 | E67: 39 | F67: 20929183143 | G67: =IFERROR(IF(compras_mes2[[#This Row],[CUIT]]="","-",VLOOKUP(compras_mes2[[#This Row],[CUIT]],Lista_CUIT[#All],2,0)),"CUIT NO CARGADO") -> MA JUN | H67: 70000 | I67: =IF(compras_mes2[[#This Row],[NETO GRAVADO]]="","",compras_mes2[[#This Row],[NETO GRAVADO]]*0.21) -> 14700 | P67: =SUM(compras_mes2[[#This Row],[NETO GRAVADO]:[Otros / No Grav.]]) -> 84700 | Q67: =IFERROR(IF(compras_mes2[[#This Row],[CUIT]]="","-",VLOOKUP(compras_mes2[[#This Row],[CUIT]],Lista_CUIT[#All],3,0)),"CUIT NO CARGADO") -> Gastos Varios | R67: =IFERROR(IF(compras_mes2[[#This Row],[CUIT]]="","-",VLOOKUP(compras_mes2[[#This Row],[CUIT]],Lista_CUIT[#All],4,0)),"CUIT NO CARGADO") -> 0 | S67: 115198.82
B68: 45708 | C68: 1 | D68: 700 | E68: 2278248 | F68: 30715804812 | G68: =IFERROR(IF(compras_mes2[[#This Row],[CUIT]]="","-",VLOOKUP(compras_mes2[[#This Row],[CUIT]],Lista_CUIT[#All],2,0)),"CUIT NO CARGADO") -> CORREDORES VIALES SOCIEDAD ANONIMA | H68: 9775.84 | I68: =IF(compras_mes2[[#This Row],[NETO GRAVADO]]="","",compras_mes2[[#This Row],[NETO GRAVADO]]*0.21) -> 2052.9264 | P68: =SUM(compras_mes2[[#This Row],[NETO GRAVADO]:[Otros / No Grav.]]) -> 11828.766 | Q68: =IFERROR(IF(compras_mes2[[#This Row],[CUIT]]="","-",VLOOKUP(compras_mes2[[#This Row],[CUIT]],Lista_CUIT[#All],3,0)),"CUIT NO CARGADO") -> Autopista | R68: =IFERROR(IF(compras_mes2[[#This Row],[CUIT]]="","-",VLOOKUP(compras_mes2[[#This Row],[CUIT]],Lista_CUIT[#All],4,0)),"CUIT NO CARGADO") -> 0 | S68: 1015795
B69: 45708 | C69: 1 | D69: 700 | E69: 2278249 | F69: 30715804812 | G69: =IFERROR(IF(compras_mes2[[#This Row],[CUIT]]="","-",VLOOKUP(compras_mes2[[#This Row],[CUIT]],Lista_CUIT[#All],2,0)),"CUIT NO CARGADO") -> CORREDORES VIALES SOCIEDAD ANONIMA | H69: 2495.95 | I69: =IF(compras_mes2[[#This Row],[NETO GRAVADO]]="","",compras_mes2[[#This Row],[NETO GRAVADO]]*0.21) -> 524.1495 | P69: =SUM(compras_mes2[[#This Row],[NETO GRAVADO]:[Otros / No Grav.]]) -> 3020.0995 | Q69: =IFERROR(IF(compras_mes2[[#This Row],[CUIT]]="","-",VLOOKUP(compras_mes2[[#This Row],[CUIT]],Lista_CUIT[#All],3,0)),"CUIT NO CARGADO") -> Autopista | R69: =IFERROR(IF(compras_mes2[[#This Row],[CUIT]]="","-",VLOOKUP(compras_mes2[[#This Row],[CUIT]],Lista_CUIT[#All],4,0)),"CUIT NO CARGADO") -> 0 | S69: 1084.71
B70: 45709 | C70: 1 | D70: 6 | E70: 56322 | F70: 30710177658 | G70: =IFERROR(IF(compras_mes2[[#This Row],[CUIT]]="","-",VLOOKUP(compras_mes2[[#This Row],[CUIT]],Lista_CUIT[#All],2,0)),"CUIT NO CARGADO") -> TARGET MEDICAL SA | H70: 145850 | I70: =IF(compras_mes2[[#This Row],[NETO GRAVADO]]="","",compras_mes2[[#This Row],[NETO GRAVADO]]*0.21) -> 30628.5 | P70: =SUM(compras_mes2[[#This Row],[NETO GRAVADO]:[Otros / No Grav.]]) -> 176478.5 | Q70: =IFERROR(IF(compras_mes2[[#This Row],[CUIT]]="","-",VLOOKUP(compras_mes2[[#This Row],[CUIT]],Lista_CUIT[#All],3,0)),"CUIT NO CARGADO") -> INSUMO | R70: =IFERROR(IF(compras_mes2[[#This Row],[CUIT]]="","-",VLOOKUP(compras_mes2[[#This Row],[CUIT]],Lista_CUIT[#All],4,0)),"CUIT NO CARGADO") -> 0 | S70: 40310.46
B71: 45709 | C71: 1 | D71: 5 | E71: 3237037 | F71: 30702652975 | G71: =IFERROR(IF(compras_mes2[[#This Row],[CUIT]]="","-",VLOOKUP(compras_mes2[[#This Row],[CUIT]],Lista_CUIT[#All],2,0)),"CUIT NO CARGADO") -> NSS SA | H71: 28528.6 | I71: =IF(compras_mes2[[#This Row],[NETO GRAVADO]]="","",compras_mes2[[#This Row],[NETO GRAVADO]]*0.21) -> 5991.006 | P71: =SUM(compras_mes2[[#This Row],[NETO GRAVADO]:[Otros / No Grav.]]) -> 34519.606 | Q71: =IFERROR(IF(compras_mes2[[#This Row],[CUIT]]="","-",VLOOKUP(compras_mes2[[#This Row],[CUIT]],Lista_CUIT[#All],3,0)),"CUIT NO CARGADO") -> SERVICIOS | R71: =IFERROR(IF(compras_mes2[[#This Row],[CUIT]]="","-",VLOOKUP(compras_mes2[[#This Row],[CUIT]],Lista_CUIT[#All],4,0)),"CUIT NO CARGADO") -> 0 | S71: 16214.09
B72: 45709 | C72: 1 | D72: 2 | E72: 56296 | F72: 30707986189 | G72: =IFERROR(IF(compras_mes2[[#This Row],[CUIT]]="","-",VLOOKUP(compras_mes2[[#This Row],[CUIT]],Lista_CUIT[#All],2,0)),"CUIT NO CARGADO") -> CIERRER, ABROJO & HERRAJES SRL | H72: 294011.7 | I72: =IF(compras_mes2[[#This Row],[NETO GRAVADO]]="","",compras_mes2[[#This Row],[NETO GRAVADO]]*0.21) -> 61742.457 | P72: =SUM(compras_mes2[[#This Row],[NETO GRAVADO]:[Otros / No Grav.]]) -> 355754.16 | Q72: =IFERROR(IF(compras_mes2[[#This Row],[CUIT]]="","-",VLOOKUP(compras_mes2[[#This Row],[CUIT]],Lista_CUIT[#All],3,0)),"CUIT NO CARGADO") -> INSUMO | R72: =IFERROR(IF(compras_mes2[[#This Row],[CUIT]]="","-",VLOOKUP(compras_mes2[[#This Row],[CUIT]],Lista_CUIT[#All],4,0)),"CUIT NO CARGADO") -> 0 | S72: 840429.7
B73: 45709 | C73: 1 | D73: 4 | E73: 39453 | F73: 20289111329 | G73: =IFERROR(IF(compras_mes2[[#This Row],[CUIT]]="","-",VLOOKUP(compras_mes2[[#This Row],[CUIT]],Lista_CUIT[#All],2,0)),"CUIT NO CARGADO") -> R. N. LEDESMA | H73: 878787.49 | I73: =IF(compras_mes2[[#This Row],[NETO GRAVADO]]="","",compras_mes2[[#This Row],[NETO GRAVADO]]*0.21) -> 184545.37 | P73: =SUM(compras_mes2[[#This Row],[NETO GRAVADO]:[Otros / No Grav.]]) -> 1063332.9 | Q73: =IFERROR(IF(compras_mes2[[#This Row],[CUIT]]="","-",VLOOKUP(compras_mes2[[#This Row],[CUIT]],Lista_CUIT[#All],3,0)),"CUIT NO CARGADO") -> Insumo | R73: =IFERROR(IF(compras_mes2[[#This Row],[CUIT]]="","-",VLOOKUP(compras_mes2[[#This Row],[CUIT]],Lista_CUIT[#All],4,0)),"CUIT NO CARGADO") -> 0 | S73: 11249.99
B74: 45711 | C74: 1 | D74: 5015 | E74: 762285 | F74: 30574876474 | G74: =IFERROR(IF(compras_mes2[[#This Row],[CUIT]]="","-",VLOOKUP(compras_mes2[[#This Row],[CUIT]],Lista_CUIT[#All],2,0)),"CUIT NO CARGADO") -> AUTOP. URBANAS SA | H74: 25893.91 | I74: =IF(compras_mes2[[#This Row],[NETO GRAVADO]]="","",compras_mes2[[#This Row],[NETO GRAVADO]]*0.21) -> 5437.7211 | P74: =SUM(compras_mes2[[#This Row],[NETO GRAVADO]:[Otros / No Grav.]]) -> 31331.631 | Q74: =IFERROR(IF(compras_mes2[[#This Row],[CUIT]]="","-",VLOOKUP(compras_mes2[[#This Row],[CUIT]],Lista_CUIT[#All],3,0)),"CUIT NO CARGADO") -> PEAJE | R74: =IFERROR(IF(compras_mes2[[#This Row],[CUIT]]="","-",VLOOKUP(compras_mes2[[#This Row],[CUIT]],Lista_CUIT[#All],4,0)),"CUIT NO CARGADO") -> 0 | S74: 322089
... B83: 45715 | C83: 1 | D83: 2 | E83: 1112 | F83: 20272865869 | G83: =IFERROR(IF(compras_mes2[[#This Row],[CUIT]]="","-",VLOOKUP(compras_mes2[[#This Row],[CUIT]],Lista_CUIT[#All],2,0)),"CUIT NO CARGADO") -> DI FEO MARTIN EZEQUIEL | H83: 154870 | I83: =IF(compras_mes2[[#This Row],[NETO GRAVADO]]="","",compras_mes2[[#This Row],[NETO GRAVADO]]*0.21) -> 32522.7 | P83: =SUM(compras_mes2[[#This Row],[NETO GRAVADO]:[Otros / No Grav.]]) -> 187392.7 | Q83: =IFERROR(IF(compras_mes2[[#This Row],[CUIT]]="","-",VLOOKUP(compras_mes2[[#This Row],[CUIT]],Lista_CUIT[#All],3,0)),"CUIT NO CARGADO") -> INSUMOS | R83: =IFERROR(IF(compras_mes2[[#This Row],[CUIT]]="","-",VLOOKUP(compras_mes2[[#This Row],[CUIT]],Lista_CUIT[#All],4,0)),"CUIT NO CARGADO") -> 0 | S83: 5938861.1
B84: 45715 | C84: 1 | D84: 10 | E84: 2621 | F84: 30716229552 | G84: =IFERROR(IF(compras_mes2[[#This Row],[CUIT]]="","-",VLOOKUP(compras_mes2[[#This Row],[CUIT]],Lista_CUIT[#All],2,0)),"CUIT NO CARGADO") -> LUBRICANTES RUTA DE P e H SRL | H84: 27272.73 | I84: =IF(compras_mes2[[#This Row],[NETO GRAVADO]]="","",compras_mes2[[#This Row],[NETO GRAVADO]]*0.21) -> 5727.2733 | P84: =SUM(compras_mes2[[#This Row],[NETO GRAVADO]:[Otros / No Grav.]]) -> 33000.003 | Q84: =IFERROR(IF(compras_mes2[[#This Row],[CUIT]]="","-",VLOOKUP(compras_mes2[[#This Row],[CUIT]],Lista_CUIT[#All],3,0)),"CUIT NO CARGADO") -> COMBUSTIBLE | R84: =IFERROR(IF(compras_mes2[[#This Row],[CUIT]]="","-",VLOOKUP(compras_mes2[[#This Row],[CUIT]],Lista_CUIT[#All],4,0)),"CUIT NO CARGADO") -> 0
B85: 45715 | C85: 1 | D85: 6 | E85: 56400 | F85: 30710177658 | G85: =IFERROR(IF(compras_mes2[[#This Row],[CUIT]]="","-",VLOOKUP(compras_mes2[[#This Row],[CUIT]],Lista_CUIT[#All],2,0)),"CUIT NO CARGADO") -> TARGET MEDICAL SA | H85: 74650 | I85: =IF(compras_mes2[[#This Row],[NETO GRAVADO]]="","",compras_mes2[[#This Row],[NETO GRAVADO]]*0.21) -> 15676.5 | P85: =SUM(compras_mes2[[#This Row],[NETO GRAVADO]:[Otros / No Grav.]]) -> 90326.5 | Q85: =IFERROR(IF(compras_mes2[[#This Row],[CUIT]]="","-",VLOOKUP(compras_mes2[[#This Row],[CUIT]],Lista_CUIT[#All],3,0)),"CUIT NO CARGADO") -> INSUMO | R85: =IFERROR(IF(compras_mes2[[#This Row],[CUIT]]="","-",VLOOKUP(compras_mes2[[#This Row],[CUIT]],Lista_CUIT[#All],4,0)),"CUIT NO CARGADO") -> 0
B86: 45716 | C86: 1 | D86: 503 | E86: 1750899 | F86: 30639935872 | G86: =IFERROR(IF(compras_mes2[[#This Row],[CUIT]]="","-",VLOOKUP(compras_mes2[[#This Row],[CUIT]],Lista_CUIT[#All],2,0)),"CUIT NO CARGADO") -> CAMINOS DEL RIO URUGUAY S A DE CONSTRUCCIONES Y CONCESIONES VIALES | H86: 3471.36 | I86: =IF(compras_mes2[[#This Row],[NETO GRAVADO]]="","",compras_mes2[[#This Row],[NETO GRAVADO]]*0.21) -> 728.9856 | P86: =SUM(compras_mes2[[#This Row],[NETO GRAVADO]:[Otros / No Grav.]]) -> 4200.3456 | Q86: =IFERROR(IF(compras_mes2[[#This Row],[CUIT]]="","-",VLOOKUP(compras_mes2[[#This Row],[CUIT]],Lista_CUIT[#All],3,0)),"CUIT NO CARGADO") -> PEAJE | R86: =IFERROR(IF(compras_mes2[[#This Row],[CUIT]]="","-",VLOOKUP(compras_mes2[[#This Row],[CUIT]],Lista_CUIT[#All],4,0)),"CUIT NO CARGADO") -> 0
B87: 45716 | C87: 1 | D87: 50 | E87: 4169073 | F87: 30714112836 | G87: =IFERROR(IF(compras_mes2[[#This Row],[CUIT]]="","-",VLOOKUP(compras_mes2[[#This Row],[CUIT]],Lista_CUIT[#All],2,0)),"CUIT NO CARGADO") -> AUTOPISTAS DE BUENOS AIRES (AUBASA) SA | H87: 1322.14 | I87: =IF(compras_mes2[[#This Row],[NETO GRAVADO]]="","",compras_mes2[[#This Row],[NETO GRAVADO]]*0.21) -> 277.6494 | P87: =SUM(compras_mes2[[#This Row],[NETO GRAVADO]:[Otros / No Grav.]]) -> 1599.7894 | Q87: =IFERROR(IF(compras_mes2[[#This Row],[CUIT]]="","-",VLOOKUP(compras_mes2[[#This Row],[CUIT]],Lista_CUIT[#All],3,0)),"CUIT NO CARGADO") -> Autopista | R87: =IFERROR(IF(compras_mes2[[#This Row],[CUIT]]="","-",VLOOKUP(compras_mes2[[#This Row],[CUIT]],Lista_CUIT[#All],4,0)),"CUIT NO CARGADO") -> 0
B88: 45716 | C88: 1 | D88: 68 | E88: 173796 | F88: 30703088534 | G88: =IFERROR(IF(compras_mes2[[#This Row],[CUIT]]="","-",VLOOKUP(compras_mes2[[#This Row],[CUIT]],Lista_CUIT[#All],2,0)),"CUIT NO CARGADO") -> MERCADO LIBRE SRL | H88: 72653 | I88: =IF(compras_mes2[[#This Row],[NETO GRAVADO]]="","",compras_mes2[[#This Row],[NETO GRAVADO]]*0.21) -> 15257.13 | P88: =SUM(compras_mes2[[#This Row],[NETO GRAVADO]:[Otros / No Grav.]]) -> 87910.13 | Q88: =IFERROR(IF(compras_mes2[[#This Row],[CUIT]]="","-",VLOOKUP(compras_mes2[[#This Row],[CUIT]],Lista_CUIT[#All],3,0)),"CUIT NO CARGADO") -> PLATAFORMA ONLINE | R88: =IFERROR(IF(compras_mes2[[#This Row],[CUIT]]="","-",VLOOKUP(compras_mes2[[#This Row],[CUIT]],Lista_CUIT[#All],4,0)),"CUIT NO CARGADO") -> 0
B89: 45716 | C89: 1 | D89: 104 | E89: 8396216 | F89: 30715804812 | G89: =IFERROR(IF(compras_mes2[[#This Row],[CUIT]]="","-",VLOOKUP(compras_mes2[[#This Row],[CUIT]],Lista_CUIT[#All],2,0)),"CUIT NO CARGADO") -> CORREDORES VIALES SOCIEDAD ANONIMA | H89: 3119.95 | I89: =IF(compras_mes2[[#This Row],[NETO GRAVADO]]="","",compras_mes2[[#This Row],[NETO GRAVADO]]*0.21) -> 655.1895 | P89: =SUM(compras_mes2[[#This Row],[NETO GRAVADO]:[Otros / No Grav.]]) -> 3775.1395 | Q89: =IFERROR(IF(compras_mes2[[#This Row],[CUIT]]="","-",VLOOKUP(compras_mes2[[#This Row],[CUIT]],Lista_CUIT[#All],3,0)),"CUIT NO CARGADO") -> Autopista | R89: =IFERROR(IF(compras_mes2[[#This Row],[CUIT]]="","-",VLOOKUP(compras_mes2[[#This Row],[CUIT]],Lista_CUIT[#All],4,0)),"CUIT NO CARGADO") -> 0
B90: 45716 | C90: 1 | D90: 6 | E90: 18757461 | F90: 30620177497 | G90: =IFERROR(IF(compras_mes2[[#This Row],[CUIT]]="","-",VLOOKUP(compras_mes2[[#This Row],[CUIT]],Lista_CUIT[#All],2,0)),"CUIT NO CARGADO") -> POSNET SOCIEDAD DE RESPONSABILIDAD LIMITADA | H90: 0 | I90: =IF(compras_mes2[[#This Row],[NETO GRAVADO]]="","",compras_mes2[[#This Row],[NETO GRAVADO]]*0.21) -> 0 | P90: =SUM(compras_mes2[[#This Row],[NETO GRAVADO]:[Otros / No Grav.]]) -> 0 | Q90: =IFERROR(IF(compras_mes2[[#This Row],[CUIT]]="","-",VLOOKUP(compras_mes2[[#This Row],[CUIT]],Lista_CUIT[#All],3,0)),"CUIT NO CARGADO") -> Gastos Varios | R90: =IFERROR(IF(compras_mes2[[#This Row],[CUIT]]="","-",VLOOKUP(compras_mes2[[#This Row],[CUIT]],Lista_CUIT[#All],4,0)),"CUIT NO CARGADO") -> 0
B91: 45716 | C91: 1 | D91: 104 | E91: 8381772 | F91: 30715804812 | G91: =IFERROR(IF(compras_mes2[[#This Row],[CUIT]]="","-",VLOOKUP(compras_mes2[[#This Row],[CUIT]],Lista_CUIT[#All],2,0)),"CUIT NO CARGADO") -> CORREDORES VIALES SOCIEDAD ANONIMA | H91: 1804.5 | I91: =IF(compras_mes2[[#This Row],[NETO GRAVADO]]="","",compras_mes2[[#This Row],[NETO GRAVADO]]*0.21) -> 378.945 | P91: =SUM(compras_mes2[[#This Row],[NETO GRAVADO]:[Otros / No Grav.]]) -> 2183.445 | Q91: =IFERROR(IF(compras_mes2[[#This Row],[CUIT]]="","-",VLOOKUP(compras_mes2[[#This Row],[CUIT]],Lista_CUIT[#All],3,0)),"CUIT NO CARGADO") -> Autopista | R91: =IFERROR(IF(compras_mes2[[#This Row],[CUIT]]="","-",VLOOKUP(compras_mes2[[#This Row],[CUIT]],Lista_CUIT[#All],4,0)),"CUIT NO CARGADO") -> 0
B92: 45716 | C92: 1 | D92: 104 | E92: 8363803 | F92: 30715804812 | G92: =IFERROR(IF(compras_mes2[[#This Row],[CUIT]]="","-",VLOOKUP(compras_mes2[[#This Row],[CUIT]],Lista_CUIT[#All],2,0)),"CUIT NO CARGADO") -> CORREDORES VIALES SOCIEDAD ANONIMA | H92: 1039.98 | I92: =IF(compras_mes2[[#This Row],[NETO GRAVADO]]="","",compras_mes2[[#This Row],[NETO GRAVADO]]*0.21) -> 218.3958 | P92: =SUM(compras_mes2[[#This Row],[NETO GRAVADO]:[Otros / No Grav.]]) -> 1258.3758 | Q92: =IFERROR(IF(compras_mes2[[#This Row],[CUIT]]="","-",VLOOKUP(compras_mes2[[#This Row],[CUIT]],Lista_CUIT[#All],3,0)),"CUIT NO CARGADO") -> Autopista | R92: =IFERROR(IF(compras_mes2[[#This Row],[CUIT]]="","-",VLOOKUP(compras_mes2[[#This Row],[CUIT]],Lista_CUIT[#All],4,0)),"CUIT NO CARGADO") -> 0
B93: 45716 | C93: 1 | D93: 6 | E93: 18890384 | F93: 30620177497 | G93: =IFERROR(IF(compras_mes2[[#This Row],[CUIT]]="","-",VLOOKUP(compras_mes2[[#This Row],[CUIT]],Lista_CUIT[#All],2,0)),"CUIT NO CARGADO") -> POSNET SOCIEDAD DE RESPONSABILIDAD LIMITADA | H93: 30475.81 | I93: =IF(compras_mes2[[#This Row],[NETO GRAVADO]]="","",compras_mes2[[#This Row],[NETO GRAVADO]]*0.21) -> 6399.9201 | P93: =SUM(compras_mes2[[#This Row],[NETO GRAVADO]:[Otros / No Grav.]]) -> 36875.73 | Q93: =IFERROR(IF(compras_mes2[[#This Row],[CUIT]]="","-",VLOOKUP(compras_mes2[[#This Row],[CUIT]],Lista_CUIT[#All],3,0)),"CUIT NO CARGADO") -> Gastos Varios | R93: =IFERROR(IF(compras_mes2[[#This Row],[CUIT]]="","-",VLOOKUP(compras_mes2[[#This Row],[CUIT]],Lista_CUIT[#All],4,0)),"CUIT NO CARGADO") -> 0
B94: 45716 | C94: 1 | D94: 2 | E94: 1119 | F94: 20272865869 | G94: =IFERROR(IF(compras_mes2[[#This Row],[CUIT]]="","-",VLOOKUP(compras_mes2[[#This Row],[CUIT]],Lista_CUIT[#All],2,0)),"CUIT NO CARGADO") -> DI FEO MARTIN EZEQUIEL | H94: 188000 | I94: =IF(compras_mes2[[#This Row],[NETO GRAVADO]]="","",compras_mes2[[#This Row],[NETO GRAVADO]]*0.21) -> 39480 | P94: =SUM(compras_mes2[[#This Row],[NETO GRAVADO]:[Otros / No Grav.]]) -> 227480 | Q94: =IFERROR(IF(compras_mes2[[#This Row],[CUIT]]="","-",VLOOKUP(compras_mes2[[#This Row],[CUIT]],Lista_CUIT[#All],3,0)),"CUIT NO CARGADO") -> INSUMOS | R94: =IFERROR(IF(compras_mes2[[#This Row],[CUIT]]="","-",VLOOKUP(compras_mes2[[#This Row],[CUIT]],Lista_CUIT[#All],4,0)),"CUIT NO CARGADO") -> 0
B95: 45716 | C95: 1 | D95: 5009 | E95: 1245733 | F95: 30574876474 | G95: =IFERROR(IF(compras_mes2[[#This Row],[CUIT]]="","-",VLOOKUP(compras_mes2[[#This Row],[CUIT]],Lista_CUIT[#All],2,0)),"CUIT NO CARGADO") -> AUTOP. URBANAS SA | H95: 8801.57 | I95: =IF(compras_mes2[[#This Row],[NETO GRAVADO]]="","",compras_mes2[[#This Row],[NETO GRAVADO]]*0.21) -> 1848.3297 | P95: =SUM(compras_mes2[[#This Row],[NETO GRAVADO]:[Otros / No Grav.]]) -> 10649.9 | Q95: =IFERROR(IF(compras_mes2[[#This Row],[CUIT]]="","-",VLOOKUP(compras_mes2[[#This Row],[CUIT]],Lista_CUIT[#All],3,0)),"CUIT NO CARGADO") -> PEAJE | R95: =IFERROR(IF(compras_mes2[[#This Row],[CUIT]]="","-",VLOOKUP(compras_mes2[[#This Row],[CUIT]],Lista_CUIT[#All],4,0)),"CUIT NO CARGADO") -> 0
... B99: 45693 | C99: 1 | D99: 8 | E99: 14120 | F99: 33715594949 | G99: =IFERROR(IF(compras_mes2[[#This Row],[CUIT]]="","-",VLOOKUP(compras_mes2[[#This Row],[CUIT]],Lista_CUIT[#All],2,0)),"CUIT NO CARGADO") -> SOMOS ENERGIA SA | H99: 44581.24 | I99: =IF(compras_mes2[[#This Row],[NETO GRAVADO]]="","",compras_mes2[[#This Row],[NETO GRAVADO]]*0.21) -> 9362.0604 | P99: =SUM(compras_mes2[[#This Row],[NETO GRAVADO]:[Otros / No Grav.]]) -> 53943.3 | Q99: =IFERROR(IF(compras_mes2[[#This Row],[CUIT]]="","-",VLOOKUP(compras_mes2[[#This Row],[CUIT]],Lista_CUIT[#All],3,0)),"CUIT NO CARGADO") -> COMBUSTIBLE | R99: =IFERROR(IF(compras_mes2[[#This Row],[CUIT]]="","-",VLOOKUP(compras_mes2[[#This Row],[CUIT]],Lista_CUIT[#All],4,0)),"CUIT NO CARGADO") -> 0
B100: 45694 | C100: 1 | D100: 11 | E100: 11388 | F100: 20211408511 | G100: =IFERROR(IF(compras_mes2[[#This Row],[CUIT]]="","-",VLOOKUP(compras_mes2[[#This Row],[CUIT]],Lista_CUIT[#All],2,0)),"CUIT NO CARGADO") -> GABRIEL ALEJANDRO SEGAL | H100: 33535.71 | K100: =compras_mes2[[#This Row],[NETO GRAVADO]]*10.5/100 -> 3521.2495 | P100: =SUM(compras_mes2[[#This Row],[NETO GRAVADO]:[Otros / No Grav.]]) -> 37056.96 | Q100: =IFERROR(IF(compras_mes2[[#This Row],[CUIT]]="","-",VLOOKUP(compras_mes2[[#This Row],[CUIT]],Lista_CUIT[#All],3,0)),"CUIT NO CARGADO") -> Gastos Varios | R100: =IFERROR(IF(compras_mes2[[#This Row],[CUIT]]="","-",VLOOKUP(compras_mes2[[#This Row],[CUIT]],Lista_CUIT[#All],4,0)),"CUIT NO CARGADO") -> 0
B101: 45697 | C101: 1 | D101: 8 | E101: 14152 | F101: 33715594949 | G101: =IFERROR(IF(compras_mes2[[#This Row],[CUIT]]="","-",VLOOKUP(compras_mes2[[#This Row],[CUIT]],Lista_CUIT[#All],2,0)),"CUIT NO CARGADO") -> SOMOS ENERGIA SA | H101: 32287.71 | I101: =IF(compras_mes2[[#This Row],[NETO GRAVADO]]="","",compras_mes2[[#This Row],[NETO GRAVADO]]*0.21) -> 6780.4191 | P101: =SUM(compras_mes2[[#This Row],[NETO GRAVADO]:[Otros / No Grav.]]) -> 39068.129 | Q101: =IFERROR(IF(compras_mes2[[#This Row],[CUIT]]="","-",VLOOKUP(compras_mes2[[#This Row],[CUIT]],Lista_CUIT[#All],3,0)),"CUIT NO CARGADO") -> COMBUSTIBLE | R101: =IFERROR(IF(compras_mes2[[#This Row],[CUIT]]="","-",VLOOKUP(compras_mes2[[#This Row],[CUIT]],Lista_CUIT[#All],4,0)),"CUIT NO CARGADO") -> 0
B102: 45699 | C102: 1 | D102: 8 | E102: 14178 | F102: 33715594949 | G102: =IFERROR(IF(compras_mes2[[#This Row],[CUIT]]="","-",VLOOKUP(compras_mes2[[#This Row],[CUIT]],Lista_CUIT[#All],2,0)),"CUIT NO CARGADO") -> SOMOS ENERGIA SA | H102: 37151 | I102: =IF(compras_mes2[[#This Row],[NETO GRAVADO]]="","",compras_mes2[[#This Row],[NETO GRAVADO]]*0.21) -> 7801.71 | P102: =SUM(compras_mes2[[#This Row],[NETO GRAVADO]:[Otros / No Grav.]]) -> 44952.71 | Q102: =IFERROR(IF(compras_mes2[[#This Row],[CUIT]]="","-",VLOOKUP(compras_mes2[[#This Row],[CUIT]],Lista_CUIT[#All],3,0)),"CUIT NO CARGADO") -> COMBUSTIBLE | R102: =IFERROR(IF(compras_mes2[[#This Row],[CUIT]]="","-",VLOOKUP(compras_mes2[[#This Row],[CUIT]],Lista_CUIT[#All],4,0)),"CUIT NO CARGADO") -> 0
B103: 45705 | C103: 1 | D103: 6 | E103: 1806 | F103: 30716815710 | G103: =IFERROR(IF(compras_mes2[[#This Row],[CUIT]]="","-",VLOOKUP(compras_mes2[[#This Row],[CUIT]],Lista_CUIT[#All],2,0)),"CUIT NO CARGADO") -> PAPELERA GEOPEL SRL | H103: 10250 | I103: =IF(compras_mes2[[#This Row],[NETO GRAVADO]]="","",compras_mes2[[#This Row],[NETO GRAVADO]]*0.21) -> 2152.5 | P103: =SUM(compras_mes2[[#This Row],[NETO GRAVADO]:[Otros / No Grav.]]) -> 12402.5 | Q103: =IFERROR(IF(compras_mes2[[#This Row],[CUIT]]="","-",VLOOKUP(compras_mes2[[#This Row],[CUIT]],Lista_CUIT[#All],3,0)),"CUIT NO CARGADO") -> librería | R103: =IFERROR(IF(compras_mes2[[#This Row],[CUIT]]="","-",VLOOKUP(compras_mes2[[#This Row],[CUIT]],Lista_CUIT[#All],4,0)),"CUIT NO CARGADO") -> 0
B104: 45713 | C104: 2 | D104: 7 | E104: 1 | F104: 27325223273 | G104: =IFERROR(IF(compras_mes2[[#This Row],[CUIT]]="","-",VLOOKUP(compras_mes2[[#This Row],[CUIT]],Lista_CUIT[#All],2,0)),"CUIT NO CARGADO") -> SOUSA ALDERETE ALEJANDRA MABEL | H104: 648800 | I104: =IF(compras_mes2[[#This Row],[NETO GRAVADO]]="","",compras_mes2[[#This Row],[NETO GRAVADO]]*0.21) -> 136248 | P104: =SUM(compras_mes2[[#This Row],[NETO GRAVADO]:[Otros / No Grav.]]) -> 785048 | Q104: =IFERROR(IF(compras_mes2[[#This Row],[CUIT]]="","-",VLOOKUP(compras_mes2[[#This Row],[CUIT]],Lista_CUIT[#All],3,0)),"CUIT NO CARGADO") -> Insumos | R104: =IFERROR(IF(compras_mes2[[#This Row],[CUIT]]="","-",VLOOKUP(compras_mes2[[#This Row],[CUIT]],Lista_CUIT[#All],4,0)),"CUIT NO CARGADO") -> 0
B105: 45695 | C105: 3 | D105: 15 | E105: 175552 | F105: 30709776564 | G105: =IFERROR(IF(compras_mes2[[#This Row],[CUIT]]="","-",VLOOKUP(compras_mes2[[#This Row],[CUIT]],Lista_CUIT[#All],2,0)),"CUIT NO CARGADO") -> PROSEGUR ACTIVA ARG SA | H105: -129241 | I105: =IF(compras_mes2[[#This Row],[NETO GRAVADO]]="","",compras_mes2[[#This Row],[NETO GRAVADO]]*0.21) -> -27140.61 | P105: =SUM(compras_mes2[[#This Row],[NETO GRAVADO]:[Otros / No Grav.]]) -> -156381.61 | Q105: =IFERROR(IF(compras_mes2[[#This Row],[CUIT]]="","-",VLOOKUP(compras_mes2[[#This Row],[CUIT]],Lista_CUIT[#All],3,0)),"CUIT NO CARGADO") -> ALARMA SEGURIDAD | R105: =IFERROR(IF(compras_mes2[[#This Row],[CUIT]]="","-",VLOOKUP(compras_mes2[[#This Row],[CUIT]],Lista_CUIT[#All],4,0)),"CUIT NO CARGADO") -> 0
B106: 45695 | C106: 3 | D106: 15 | E106: 175572 | F106: 30709776564 | G106: =IFERROR(IF(compras_mes2[[#This Row],[CUIT]]="","-",VLOOKUP(compras_mes2[[#This Row],[CUIT]],Lista_CUIT[#All],2,0)),"CUIT NO CARGADO") -> PROSEGUR ACTIVA ARG SA | H106: -129241 | I106: =IF(compras_mes2[[#This Row],[NETO GRAVADO]]="","",compras_mes2[[#This Row],[NETO GRAVADO]]*0.21) -> -27140.61 | P106: =SUM(compras_mes2[[#This Row],[NETO GRAVADO]:[Otros / No Grav.]]) -> -156381.61 | Q106: =IFERROR(IF(compras_mes2[[#This Row],[CUIT]]="","-",VLOOKUP(compras_mes2[[#This Row],[CUIT]],Lista_CUIT[#All],3,0)),"CUIT NO CARGADO") -> ALARMA SEGURIDAD | R106: =IFERROR(IF(compras_mes2[[#This Row],[CUIT]]="","-",VLOOKUP(compras_mes2[[#This Row],[CUIT]],Lista_CUIT[#All],4,0)),"CUIT NO CARGADO") -> 0
B107: 45695 | C107: 3 | D107: 15 | E107: 175574 | F107: 30709776564 | G107: =IFERROR(IF(compras_mes2[[#This Row],[CUIT]]="","-",VLOOKUP(compras_mes2[[#This Row],[CUIT]],Lista_CUIT[#All],2,0)),"CUIT NO CARGADO") -> PROSEGUR ACTIVA ARG SA | H107: -129241 | I107: =IF(compras_mes2[[#This Row],[NETO GRAVADO]]="","",compras_mes2[[#This Row],[NETO GRAVADO]]*0.21) -> -27140.61 | P107: =SUM(compras_mes2[[#This Row],[NETO GRAVADO]:[Otros / No Grav.]]) -> -156381.61 | Q107: =IFERROR(IF(compras_mes2[[#This Row],[CUIT]]="","-",VLOOKUP(compras_mes2[[#This Row],[CUIT]],Lista_CUIT[#All],3,0)),"CUIT NO CARGADO") -> ALARMA SEGURIDAD | R107: =IFERROR(IF(compras_mes2[[#This Row],[CUIT]]="","-",VLOOKUP(compras_mes2[[#This Row],[CUIT]],Lista_CUIT[#All],4,0)),"CUIT NO CARGADO") -> 0
B108: 45695 | C108: 3 | D108: 15 | E108: 175677 | F108: 30709776564 | G108: =IFERROR(IF(compras_mes2[[#This Row],[CUIT]]="","-",VLOOKUP(compras_mes2[[#This Row],[CUIT]],Lista_CUIT[#All],2,0)),"CUIT NO CARGADO") -> PROSEGUR ACTIVA ARG SA | H108: -129241 | I108: =IF(compras_mes2[[#This Row],[NETO GRAVADO]]="","",compras_mes2[[#This Row],[NETO GRAVADO]]*0.21) -> -27140.61 | P108: =SUM(compras_mes2[[#This Row],[NETO GRAVADO]:[Otros / No Grav.]]) -> -156381.61 | Q108: =IFERROR(IF(compras_mes2[[#This Row],[CUIT]]="","-",VLOOKUP(compras_mes2[[#This Row],[CUIT]],Lista_CUIT[#All],3,0)),"CUIT NO CARGADO") -> ALARMA SEGURIDAD | R108: =IFERROR(IF(compras_mes2[[#This Row],[CUIT]]="","-",VLOOKUP(compras_mes2[[#This Row],[CUIT]],Lista_CUIT[#All],4,0)),"CUIT NO CARGADO") -> 0
B109: 45708 | C109: 3 | D109: 4 | E109: 950 | F109: 30504854023 | G109: =IFERROR(IF(compras_mes2[[#This Row],[CUIT]]="","-",VLOOKUP(compras_mes2[[#This Row],[CUIT]],Lista_CUIT[#All],2,0)),"CUIT NO CARGADO") -> NYLTEF SAICFI | H109: -75232.5 | I109: =IF(compras_mes2[[#This Row],[NETO GRAVADO]]="","",compras_mes2[[#This Row],[NETO GRAVADO]]*0.21) -> -15798.825 | P109: =SUM(compras_mes2[[#This Row],[NETO GRAVADO]:[Otros / No Grav.]]) -> -91031.325 | Q109: =IFERROR(IF(compras_mes2[[#This Row],[CUIT]]="","-",VLOOKUP(compras_mes2[[#This Row],[CUIT]],Lista_CUIT[#All],3,0)),"CUIT NO CARGADO") -> INSUMO | R109: =IFERROR(IF(compras_mes2[[#This Row],[CUIT]]="","-",VLOOKUP(compras_mes2[[#This Row],[CUIT]],Lista_CUIT[#All],4,0)),"CUIT NO CARGADO") -> 0
B110: 45713 | C110: 3 | D110: 7 | E110: 2 | F110: 27325223273 | G110: =IFERROR(IF(compras_mes2[[#This Row],[CUIT]]="","-",VLOOKUP(compras_mes2[[#This Row],[CUIT]],Lista_CUIT[#All],2,0)),"CUIT NO CARGADO") -> SOUSA ALDERETE ALEJANDRA MABEL | H110: -648800 | I110: =IF(compras_mes2[[#This Row],[NETO GRAVADO]]="","",compras_mes2[[#This Row],[NETO GRAVADO]]*0.21) -> -136248 | P110: =SUM(compras_mes2[[#This Row],[NETO GRAVADO]:[Otros / No Grav.]]) -> -785048 | Q110: =IFERROR(IF(compras_mes2[[#This Row],[CUIT]]="","-",VLOOKUP(compras_mes2[[#This Row],[CUIT]],Lista_CUIT[#All],3,0)),"CUIT NO CARGADO") -> Insumos | R110: =IFERROR(IF(compras_mes2[[#This Row],[CUIT]]="","-",VLOOKUP(compras_mes2[[#This Row],[CUIT]],Lista_CUIT[#All],4,0)),"CUIT NO CARGADO") -> 0
B111: 45713 | C111: 3 | D111: 7 | E111: 3 | F111: 27325223273 | G111: =IFERROR(IF(compras_mes2[[#This Row],[CUIT]]="","-",VLOOKUP(compras_mes2[[#This Row],[CUIT]],Lista_CUIT[#All],2,0)),"CUIT NO CARGADO") -> SOUSA ALDERETE ALEJANDRA MABEL | H111: -648800 | I111: =IF(compras_mes2[[#This Row],[NETO GRAVADO]]="","",compras_mes2[[#This Row],[NETO GRAVADO]]*0.21) -> -136248 | P111: =SUM(compras_mes2[[#This Row],[NETO GRAVADO]:[Otros / No Grav.]]) -> -785048 | Q111: =IFERROR(IF(compras_mes2[[#This Row],[CUIT]]="","-",VLOOKUP(compras_mes2[[#This Row],[CUIT]],Lista_CUIT[#All],3,0)),"CUIT NO CARGADO") -> Insumos | R111: =IFERROR(IF(compras_mes2[[#This Row],[CUIT]]="","-",VLOOKUP(compras_mes2[[#This Row],[CUIT]],Lista_CUIT[#All],4,0)),"CUIT NO CARGADO") -> 0
B112: 45716 | C112: 3 | D112: 12 | E112: 155098 | F112: 30703088534 | G112: =IFERROR(IF(compras_mes2[[#This Row],[CUIT]]="","-",VLOOKUP(compras_mes2[[#This Row],[CUIT]],Lista_CUIT[#All],2,0)),"CUIT NO CARGADO") -> MERCADO LIBRE SRL | H112: -711.57 | I112: =IF(compras_mes2[[#This Row],[NETO GRAVADO]]="","",compras_mes2[[#This Row],[NETO GRAVADO]]*0.21) -> -149.4297 | P112: =SUM(compras_mes2[[#This Row],[NETO GRAVADO]:[Otros / No Grav.]]) -> -860.9997 | Q112: =IFERROR(IF(compras_mes2[[#This Row],[CUIT]]="","-",VLOOKUP(compras_mes2[[#This Row],[CUIT]],Lista_CUIT[#All],3,0)),"CUIT NO CARGADO") -> PLATAFORMA ONLINE | R112: =IFERROR(IF(compras_mes2[[#This Row],[CUIT]]="","-",VLOOKUP(compras_mes2[[#This Row],[CUIT]],Lista_CUIT[#All],4,0)),"CUIT NO CARGADO") -> 0
B113: 45716 | C113: 3 | D113: 74 | E113: 3384 | F113: 30703088534 | G113: =IFERROR(IF(compras_mes2[[#This Row],[CUIT]]="","-",VLOOKUP(compras_mes2[[#This Row],[CUIT]],Lista_CUIT[#All],2,0)),"CUIT NO CARGADO") -> MERCADO LIBRE SRL | H113: -711.57 | I113: =IF(compras_mes2[[#This Row],[NETO GRAVADO]]="","",compras_mes2[[#This Row],[NETO GRAVADO]]*0.21) -> -149.4297 | P113: =SUM(compras_mes2[[#This Row],[NETO GRAVADO]:[Otros / No Grav.]]) -> -860.9997 | Q113: =IFERROR(IF(compras_mes2[[#This Row],[CUIT]]="","-",VLOOKUP(compras_mes2[[#This Row],[CUIT]],Lista_CUIT[#All],3,0)),"CUIT NO CARGADO") -> PLATAFORMA ONLINE | R113: =IFERROR(IF(compras_mes2[[#This Row],[CUIT]]="","-",VLOOKUP(compras_mes2[[#This Row],[CUIT]],Lista_CUIT[#All],4,0)),"CUIT NO CARGADO") -> 0
B114: 45693 | C114: 1 | D114: 6 | E114: 11377 | F114: 30707988378 | G114: =IFERROR(IF(compras_mes2[[#This Row],[CUIT]]="","-",VLOOKUP(compras_mes2[[#This Row],[CUIT]],Lista_CUIT[#All],2,0)),"CUIT NO CARGADO") -> CARMAS COMPOSITES S.R.L. | H114: =356.13*1075 -> 382839.75 | I114: =IF(compras_mes2[[#This Row],[NETO GRAVADO]]="","",compras_mes2[[#This Row],[NETO GRAVADO]]*0.21) -> 80396.348 | P114: =SUM(compras_mes2[[#This Row],[NETO GRAVADO]:[Otros / No Grav.]]) -> 463236.1 | Q114: =IFERROR(IF(compras_mes2[[#This Row],[CUIT]]="","-",VLOOKUP(compras_mes2[[#This Row],[CUIT]],Lista_CUIT[#All],3,0)),"CUIT NO CARGADO") -> Mantenimiento | R114: =IFERROR(IF(compras_mes2[[#This Row],[CUIT]]="","-",VLOOKUP(compras_mes2[[#This Row],[CUIT]],Lista_CUIT[#All],4,0)),"CUIT NO CARGADO") -> 0
B115: 45702 | C115: 1 | D115: 13 | E115: 1932 | F115: 33709914109 | G115: =IFERROR(IF(compras_mes2[[#This Row],[CUIT]]="","-",VLOOKUP(compras_mes2[[#This Row],[CUIT]],Lista_CUIT[#All],2,0)),"CUIT NO CARGADO") -> ALAN COLLECTION SA | H115: 2066.12 | I115: =IF(compras_mes2[[#This Row],[NETO GRAVADO]]="","",compras_mes2[[#This Row],[NETO GRAVADO]]*0.21) -> 433.8852 | P115: =SUM(compras_mes2[[#This Row],[NETO GRAVADO]:[Otros / No Grav.]]) -> 2500.0052 | Q115: =IFERROR(IF(compras_mes2[[#This Row],[CUIT]]="","-",VLOOKUP(compras_mes2[[#This Row],[CUIT]],Lista_CUIT[#All],3,0)),"CUIT NO CARGADO") -> MERCADERIA | R115: =IFERROR(IF(compras_mes2[[#This Row],[CUIT]]="","-",VLOOKUP(compras_mes2[[#This Row],[CUIT]],Lista_CUIT[#All],4,0)),"CUIT NO CARGADO") -> 0
B116: 45705 | C116: 1 | D116: 10 | E116: 11470 | F116: 30709208221 | G116: =IFERROR(IF(compras_mes2[[#This Row],[CUIT]]="","-",VLOOKUP(compras_mes2[[#This Row],[CUIT]],Lista_CUIT[#All],2,0)),"CUIT NO CARGADO") -> GNC MONTE GRANDE SRL | H116: 51565.9 | I116: =IF(compras_mes2[[#This Row],[NETO GRAVADO]]="","",compras_mes2[[#This Row],[NETO GRAVADO]]*0.21) -> 10828.839 | O116: 7605.15 | P116: =SUM(compras_mes2[[#This Row],[NETO GRAVADO]:[Otros / No Grav.]]) -> 69999.889 | Q116: =IFERROR(IF(compras_mes2[[#This Row],[CUIT]]="","-",VLOOKUP(compras_mes2[[#This Row],[CUIT]],Lista_CUIT[#All],3,0)),"CUIT NO CARGADO") -> COMBUSTIBLE | R116: =IFERROR(IF(compras_mes2[[#This Row],[CUIT]]="","-",VLOOKUP(compras_mes2[[#This Row],[CUIT]],Lista_CUIT[#All],4,0)),"CUIT NO CARGADO") -> 0
B117: 45708 | C117: 1 | D117: 6 | E117: 21245 | F117: 33715594949 | G117: =IFERROR(IF(compras_mes2[[#This Row],[CUIT]]="","-",VLOOKUP(compras_mes2[[#This Row],[CUIT]],Lista_CUIT[#All],2,0)),"CUIT NO CARGADO") -> SOMOS ENERGIA SA | H117: 68875.76 | I117: =IF(compras_mes2[[#This Row],[NETO GRAVADO]]="","",compras_mes2[[#This Row],[NETO GRAVADO]]*0.21) -> 14463.91 | O117: 9357.31 | P117: =SUM(compras_mes2[[#This Row],[NETO GRAVADO]:[Otros / No Grav.]]) -> 92696.98 | Q117: =IFERROR(IF(compras_mes2[[#This Row],[CUIT]]="","-",VLOOKUP(compras_mes2[[#This Row],[CUIT]],Lista_CUIT[#All],3,0)),"CUIT NO CARGADO") -> COMBUSTIBLE | R117: =IFERROR(IF(compras_mes2[[#This Row],[CUIT]]="","-",VLOOKUP(compras_mes2[[#This Row],[CUIT]],Lista_CUIT[#All],4,0)),"CUIT NO CARGADO") -> 0
B118: 45715 | C118: 1 | D118: 6 | E118: 1816 | F118: 30716815710 | G118: =IFERROR(IF(compras_mes2[[#This Row],[CUIT]]="","-",VLOOKUP(compras_mes2[[#This Row],[CUIT]],Lista_CUIT[#All],2,0)),"CUIT NO CARGADO") -> PAPELERA GEOPEL SRL | H118: 15000 | I118: =IF(compras_mes2[[#This Row],[NETO GRAVADO]]="","",compras_mes2[[#This Row],[NETO GRAVADO]]*0.21) -> 3150 | P118: =SUM(compras_mes2[[#This Row],[NETO GRAVADO]:[Otros / No Grav.]]) -> 18150 | Q118: =IFERROR(IF(compras_mes2[[#This Row],[CUIT]]="","-",VLOOKUP(compras_mes2[[#This Row],[CUIT]],Lista_CUIT[#All],3,0)),"CUIT NO CARGADO") -> librería | R118: =IFERROR(IF(compras_mes2[[#This Row],[CUIT]]="","-",VLOOKUP(compras_mes2[[#This Row],[CUIT]],Lista_CUIT[#All],4,0)),"CUIT NO CARGADO") -> 0
G119: =IFERROR(IF(compras_mes2[[#This Row],[CUIT]]="","-",VLOOKUP(compras_mes2[[#This Row],[CUIT]],Lista_CUIT[#All],2,0)),"CUIT NO CARGADO") -> - | P119: =SUM(compras_mes2[[#This Row],[NETO GRAVADO]:[Otros / No Grav.]]) -> 0 | Q119: =IFERROR(IF(compras_mes2[[#This Row],[CUIT]]="","-",VLOOKUP(compras_mes2[[#This Row],[CUIT]],Lista_CUIT[#All],3,0)),"CUIT NO CARGADO") -> - | R119: =IFERROR(IF(compras_mes2[[#This Row],[CUIT]]="","-",VLOOKUP(compras_mes2[[#This Row],[CUIT]],Lista_CUIT[#All],4,0)),"CUIT NO CARGADO") -> -
G120: =IFERROR(IF(compras_mes2[[#This Row],[CUIT]]="","-",VLOOKUP(compras_mes2[[#This Row],[CUIT]],Lista_CUIT[#All],2,0)),"CUIT NO CARGADO") -> - | I120: =IF(compras_mes2[[#This Row],[NETO GRAVADO]]="","",compras_mes2[[#This Row],[NETO GRAVADO]]*0.21) | P120: =SUM(compras_mes2[[#This Row],[NETO GRAVADO]:[Otros / No Grav.]]) -> 0 | Q120: =IFERROR(IF(compras_mes2[[#This Row],[CUIT]]="","-",VLOOKUP(compras_mes2[[#This Row],[CUIT]],Lista_CUIT[#All],3,0)),"CUIT NO CARGADO") -> - | R120: =IFERROR(IF(compras_mes2[[#This Row],[CUIT]]="","-",VLOOKUP(compras_mes2[[#This Row],[CUIT]],Lista_CUIT[#All],4,0)),"CUIT NO CARGADO") -> -
B121: Total | H121: =SUBTOTAL(109,compras_mes2[NETO GRAVADO]) -> 26725599 | I121: =SUBTOTAL(109,compras_mes2[IVA 21 %]) -> 5239005.3 | J121: =SUBTOTAL(109,compras_mes2[IVA 27%]) -> 45418.02 | K121: =SUBTOTAL(109,compras_mes2[IVA 10,5%]) -> 169022.64 | L121: =SUBTOTAL(109,compras_mes2[PERC. IVA]) -> 0 | M121: =SUBTOTAL(109,compras_mes2[PERC IIBB BS AS]) -> 0 | N121: =SUBTOTAL(109,compras_mes2[PERC. IIBB CABA]) -> 0 | O121: =SUBTOTAL(109,compras_mes2[Otros / No Grav.]) -> 17402.72 | P121: =SUBTOTAL(109,compras_mes2[TOTAL]) -> 32196447
I123: 142029.97
...

Sheet Mar-25
B1: LIBRO IVA COMPRAS | G1: ='Ene-25'!G1:M1 -> ORTOPEDIA GEMINIS S.A. | N1: =EDATE('Ene-25'!N1,2) -> 45717
B3: TOTAL COMPRAS | G3: TOTAL CREDITO FISCAL | J3: TOTAL VENTAS NETAS | M3: TOTAL DEBITO FISCAL | P3: RESULTADO
B4: =SUM(compras_mes3[[#Totals],[NETO GRAVADO]])+extracto_banco_mes3[[#Totals],[NETO]]+O72 -> 22713890 | G4: =compras_mes3[[#Totals],[IVA 21 %]]+compras_mes3[[#Totals],[IVA 27%]]+compras_mes3[[#Totals],[IVA 10,5%]]+extracto_banco_mes3[[#Totals],[IVA 21%]]+extracto_banco_mes3[[#Totals],[IVA 10,5%]] -> 4741924.9 | J4: =venta_a_mes3[[#Totals],[IMPORTE NETO]]+ventas_b_mes3[[#Totals],[IMPORTE NETO]] -> 0 | M4: =venta_a_mes3[[#Totals],[IVA 21%]]+venta_a_mes3[[#Totals],[IVA 10,5%]]+ventas_b_mes3[[#Totals],[IVA 21%]]+ventas_b_mes3[[#Totals],[IVA 10,5%]] -> 0 | P4: =G4-M4 -> 4741924.9
B8: FECHA | C8: TIPO | D8: PTO VTA | E8: NRO. CPTE | F8: CUIT | G8: RAZON SOCIAL | H8: NETO GRAVADO | I8: IVA 21 % | J8: IVA 27% | K8: IVA 10,5% | L8: PERC. IVA | M8: PERC IIBB BS AS | N8: PERC. IIBB CABA | O8: Otros / No Grav. | P8: TOTAL | Q8: Tipo de Gasto | R8: Provincia
B9: 45718 | C9: 1 | D9: 3051 | E9: 885516 | F9: 30678814357 | G9: =IFERROR(IF(compras_mes3[[#This Row],[CUIT]]="","-",VLOOKUP(compras_mes3[[#This Row],[CUIT]],Lista_CUIT[#All],2,0)),"CUIT NO CARGADO") -> TELEFONICA MOVILES ARG SA | H9: 65394 | J9: =compras_mes3[[#This Row],[NETO GRAVADO]]*27/100 -> 17656.38 | P9: =SUM(compras_mes3[[#This Row],[NETO GRAVADO]:[Otros / No Grav.]]) -> 83050.38 | Q9: =IFERROR(IF(compras_mes3[[#This Row],[CUIT]]="","-",VLOOKUP(compras_mes3[[#This Row],[CUIT]],Lista_CUIT[#All],3,0)),"CUIT NO CARGADO") -> SERVICIO | R9: =IFERROR(IF(compras_mes3[[#This Row],[CUIT]]="","-",VLOOKUP(compras_mes3[[#This Row],[CUIT]],Lista_CUIT[#All],4,0)),"CUIT NO CARGADO") -> 0
B10: 45720 | C10: 1 | D10: 1 | E10: 753841 | F10: 33716307749 | G10: =IFERROR(IF(compras_mes3[[#This Row],[CUIT]]="","-",VLOOKUP(compras_mes3[[#This Row],[CUIT]],Lista_CUIT[#All],2,0)),"CUIT NO CARGADO") -> VERISURE ARGENTINA MONITOREO DE ALARMAS SA | H10: 49498.9 | I10: =IF(compras_mes3[[#This Row],[NETO GRAVADO]]="","",compras_mes3[[#This Row],[NETO GRAVADO]]*0.21) -> 10394.769 | P10: =SUM(compras_mes3[[#This Row],[NETO GRAVADO]:[Otros / No Grav.]]) -> 59893.669 | Q10: =IFERROR(IF(compras_mes3[[#This Row],[CUIT]]="","-",VLOOKUP(compras_mes3[[#This Row],[CUIT]],Lista_CUIT[#All],3,0)),"CUIT NO CARGADO") -> Serv. Seguridad | R10: =IFERROR(IF(compras_mes3[[#This Row],[CUIT]]="","-",VLOOKUP(compras_mes3[[#This Row],[CUIT]],Lista_CUIT[#All],4,0)),"CUIT NO CARGADO") -> 0
B11: 45726 | C11: 1 | D11: 2002 | E11: 79578 | F11: 30716425165 | G11: =IFERROR(IF(compras_mes3[[#This Row],[CUIT]]="","-",VLOOKUP(compras_mes3[[#This Row],[CUIT]],Lista_CUIT[#All],2,0)),"CUIT NO CARGADO") -> MERCADO TOTAL SAS | H11: 4796.38 | K11: =compras_mes3[[#This Row],[NETO GRAVADO]]*10.5/100 -> 503.6199 | P11: =SUM(compras_mes3[[#This Row],[NETO GRAVADO]:[Otros / No Grav.]]) -> 5299.9999 | Q11: =IFERROR(IF(compras_mes3[[#This Row],[CUIT]]="","-",VLOOKUP(compras_mes3[[#This Row],[CUIT]],Lista_CUIT[#All],3,0)),"CUIT NO CARGADO") -> gastos varios | R11: =IFERROR(IF(compras_mes3[[#This Row],[CUIT]]="","-",VLOOKUP(compras_mes3[[#This Row],[CUIT]],Lista_CUIT[#All],4,0)),"CUIT NO CARGADO") -> 0
B12: 45727 | C12: 1 | D12: 7 | E12: 268472 | F12: 30708395443 | G12: =IFERROR(IF(compras_mes3[[#This Row],[CUIT]]="","-",VLOOKUP(compras_mes3[[#This Row],[CUIT]],Lista_CUIT[#All],2,0)),"CUIT NO CARGADO") -> SUPERFOTO S R L | H12: 132230.58 | I12: =IF(compras_mes3[[#This Row],[NETO GRAVADO]]="","",compras_mes3[[#This Row],[NETO GRAVADO]]*0.21) -> 27768.422 | P12: =SUM(compras_mes3[[#This Row],[NETO GRAVADO]:[Otros / No Grav.]]) -> 159999 | Q12: =IFERROR(IF(compras_mes3[[#This Row],[CUIT]]="","-",VLOOKUP(compras_mes3[[#This Row],[CUIT]],Lista_CUIT[#All],3,0)),"CUIT NO CARGADO") -> Gastos Varios | R12: =IFERROR(IF(compras_mes3[[#This Row],[CUIT]]="","-",VLOOKUP(compras_mes3[[#This Row],[CUIT]],Lista_CUIT[#All],4,0)),"CUIT NO CARGADO") -> 0
B13: 45727 | C13: 1 | D13: 120 | E13: 5534 | F13: 30587197215 | G13: =IFERROR(IF(compras_mes3[[#This Row],[CUIT]]="","-",VLOOKUP(compras_mes3[[#This Row],[CUIT]],Lista_CUIT[#All],2,0)),"CUIT NO CARGADO") -> PANATEL SOCIEDAD ANONIMA | H13: 95041.32 | I13: =IF(compras_mes3[[#This Row],[NETO GRAVADO]]="","",compras_mes3[[#This Row],[NETO GRAVADO]]*0.21) -> 19958.677 | P13: =SUM(compras_mes3[[#This Row],[NETO GRAVADO]:[Otros / No Grav.]]) -> 115000 | Q13: =IFERROR(IF(compras_mes3[[#This Row],[CUIT]]="","-",VLOOKUP(compras_mes3[[#This Row],[CUIT]],Lista_CUIT[#All],3,0)),"CUIT NO CARGADO") -> SERVICIOS DE ALOJAMIENTO EN HOTELES | R13: =IFERROR(IF(compras_mes3[[#This Row],[CUIT]]="","-",VLOOKUP(compras_mes3[[#This Row],[CUIT]],Lista_CUIT[#All],4,0)),"CUIT NO CARGADO") -> 0
B14: 45730 | C14: 1 | D14: 7 | E14: 4517 | F14: 20307464269 | G14: =IFERROR(IF(compras_mes3[[#This Row],[CUIT]]="","-",VLOOKUP(compras_mes3[[#This Row],[CUIT]],Lista_CUIT[#All],2,0)),"CUIT NO CARGADO") -> ABRAMOWICZ DEMIAN MARCELO | H14: 8146.58 | I14: =IF(compras_mes3[[#This Row],[NETO GRAVADO]]="","",compras_mes3[[#This Row],[NETO GRAVADO]]*0.21) -> 1710.7818 | P14: =SUM(compras_mes3[[#This Row],[NETO GRAVADO]:[Otros / No Grav.]]) -> 9857.3618 | Q14: =IFERROR(IF(compras_mes3[[#This Row],[CUIT]]="","-",VLOOKUP(compras_mes3[[#This Row],[CUIT]],Lista_CUIT[#All],3,0)),"CUIT NO CARGADO") -> Gastos Varios | R14: =IFERROR(IF(compras_mes3[[#This Row],[CUIT]]="","-",VLOOKUP(compras_mes3[[#This Row],[CUIT]],Lista_CUIT[#All],4,0)),"CUIT NO CARGADO") -> 0
B15: 45730 | C15: 1 | D15: 4 | E15: 13184 | F15: 33711386179 | G15: =IFERROR(IF(compras_mes3[[#This Row],[CUIT]]="","-",VLOOKUP(compras_mes3[[#This Row],[CUIT]],Lista_CUIT[#All],2,0)),"CUIT NO CARGADO") -> SHOPNOW S.R.L. | H15: 192187.6 | I15: =IF(compras_mes3[[#This Row],[NETO GRAVADO]]="","",compras_mes3[[#This Row],[NETO GRAVADO]]*0.21) -> 40359.396 | P15: =SUM(compras_mes3[[#This Row],[NETO GRAVADO]:[Otros / No Grav.]]) -> 232547 | Q15: =IFERROR(IF(compras_mes3[[#This Row],[CUIT]]="","-",VLOOKUP(compras_mes3[[#This Row],[CUIT]],Lista_CUIT[#All],3,0)),"CUIT NO CARGADO") -> Insumos | R15: =IFERROR(IF(compras_mes3[[#This Row],[CUIT]]="","-",VLOOKUP(compras_mes3[[#This Row],[CUIT]],Lista_CUIT[#All],4,0)),"CUIT NO CARGADO") -> 0
B16: 45730 | C16: 1 | D16: 1 | E16: 6677 | F16: 30715141201 | G16: =IFERROR(IF(compras_mes3[[#This Row],[CUIT]]="","-",VLOOKUP(compras_mes3[[#This Row],[CUIT]],Lista_CUIT[#All],2,0)),"CUIT NO CARGADO") -> REHAB SRL | H16: 529546.88 | I16: =IF(compras_mes3[[#This Row],[NETO GRAVADO]]="","",compras_mes3[[#This Row],[NETO GRAVADO]]*0.21) -> 111204.84 | P16: =SUM(compras_mes3[[#This Row],[NETO GRAVADO]:[Otros / No Grav.]]) -> 640751.72 | Q16: =IFERROR(IF(compras_mes3[[#This Row],[CUIT]]="","-",VLOOKUP(compras_mes3[[#This Row],[CUIT]],Lista_CUIT[#All],3,0)),"CUIT NO CARGADO") -> INSUMO | R16: =IFERROR(IF(compras_mes3[[#This Row],[CUIT]]="","-",VLOOKUP(compras_mes3[[#This Row],[CUIT]],Lista_CUIT[#All],4,0)),"CUIT NO CARGADO") -> 0
B17: 45733 | C17: 1 | D17: 7 | E17: 3750 | F17: 20284183534 | G17: =IFERROR(IF(compras_mes3[[#This Row],[CUIT]]="","-",VLOOKUP(compras_mes3[[#This Row],[CUIT]],Lista_CUIT[#All],2,0)),"CUIT NO CARGADO") -> FURLANETTO MARTIN | H17: 7933.86 | I17: =IF(compras_mes3[[#This Row],[NETO GRAVADO]]="","",compras_mes3[[#This Row],[NETO GRAVADO]]*0.21) -> 1666.1106 | P17: =SUM(compras_mes3[[#This Row],[NETO GRAVADO]:[Otros / No Grav.]]) -> 9599.9706 | Q17: =IFERROR(IF(compras_mes3[[#This Row],[CUIT]]="","-",VLOOKUP(compras_mes3[[#This Row],[CUIT]],Lista_CUIT[#All],3,0)),"CUIT NO CARGADO") -> gastos varios | R17: =IFERROR(IF(compras_mes3[[#This Row],[CUIT]]="","-",VLOOKUP(compras_mes3[[#This Row],[CUIT]],Lista_CUIT[#All],4,0)),"CUIT NO CARGADO") -> 0
B18: 45734 | C18: 1 | D18: 13 | E18: 7271 | F18: 27256759646 | G18: =IFERROR(IF(compras_mes3[[#This Row],[CUIT]]="","-",VLOOKUP(compras_mes3[[#This Row],[CUIT]],Lista_CUIT[#All],2,0)),"CUIT NO CARGADO") -> ORTOPEDIA Y CIRUGIA MODELO | H18: 43899.17 | I18: =IF(compras_mes3[[#This Row],[NETO GRAVADO]]="","",compras_mes3[[#This Row],[NETO GRAVADO]]*0.21) -> 9218.8257 | P18: =SUM(compras_mes3[[#This Row],[NETO GRAVADO]:[Otros / No Grav.]]) -> 53117.996 | Q18: =IFERROR(IF(compras_mes3[[#This Row],[CUIT]]="","-",VLOOKUP(compras_mes3[[#This Row],[CUIT]],Lista_CUIT[#All],3,0)),"CUIT NO CARGADO") -> INSUMO | R18: =IFERROR(IF(compras_mes3[[#This Row],[CUIT]]="","-",VLOOKUP(compras_mes3[[#This Row],[CUIT]],Lista_CUIT[#All],4,0)),"CUIT NO CARGADO") -> 0
B19: 45735 | C19: 1 | D19: 32 | E19: 14788 | F19: 30707304886 | G19: =IFERROR(IF(compras_mes3[[#This Row],[CUIT]]="","-",VLOOKUP(compras_mes3[[#This Row],[CUIT]],Lista_CUIT[#All],2,0)),"CUIT NO CARGADO") -> ARMORAUT SA | H19: 284107.44 | I19: =IF(compras_mes3[[#This Row],[NETO GRAVADO]]="","",compras_mes3[[#This Row],[NETO GRAVADO]]*0.21) -> 59662.562 | P19: =SUM(compras_mes3[[#This Row],[NETO GRAVADO]:[Otros / No Grav.]]) -> 343770 | Q19: =IFERROR(IF(compras_mes3[[#This Row],[CUIT]]="","-",VLOOKUP(compras_mes3[[#This Row],[CUIT]],Lista_CUIT[#All],3,0)),"CUIT NO CARGADO") -> Mantenimiento | R19: =IFERROR(IF(compras_mes3[[#This Row],[CUIT]]="","-",VLOOKUP(compras_mes3[[#This Row],[CUIT]],Lista_CUIT[#All],4,0)),"CUIT NO CARGADO") -> 0
B20: 45737 | C20: 1 | D20: 2 | E20: 56906 | F20: 30717110052 | G20: =IFERROR(IF(compras_mes3[[#This Row],[CUIT]]="","-",VLOOKUP(compras_mes3[[#This Row],[CUIT]],Lista_CUIT[#All],2,0)),"CUIT NO CARGADO") -> TAP SERVICES S.A. | H20: 4421.49 | I20: =IF(compras_mes3[[#This Row],[NETO GRAVADO]]="","",compras_mes3[[#This Row],[NETO GRAVADO]]*0.21) -> 928.5129 | P20: =SUM(compras_mes3[[#This Row],[NETO GRAVADO]:[Otros / No Grav.]]) -> 5350.0029 | Q20: =IFERROR(IF(compras_mes3[[#This Row],[CUIT]]="","-",VLOOKUP(compras_mes3[[#This Row],[CUIT]],Lista_CUIT[#All],3,0)),"CUIT NO CARGADO") -> Bienes | R20: =IFERROR(IF(compras_mes3[[#This Row],[CUIT]]="","-",VLOOKUP(compras_mes3[[#This Row],[CUIT]],Lista_CUIT[#All],4,0)),"CUIT NO CARGADO") -> 0
B21: 45737 | C21: 1 | D21: 700 | E21: 2340949 | F21: 30715804812 | G21: =IFERROR(IF(compras_mes3[[#This Row],[CUIT]]="","-",VLOOKUP(compras_mes3[[#This Row],[CUIT]],Lista_CUIT[#All],2,0)),"CUIT NO CARGADO") -> CORREDORES VIALES SOCIEDAD ANONIMA | H21: 831.98 | I21: =IF(compras_mes3[[#This Row],[NETO GRAVADO]]="","",compras_mes3[[#This Row],[NETO GRAVADO]]*0.21) -> 174.7158 | P21: =SUM(compras_mes3[[#This Row],[NETO GRAVADO]:[Otros / No Grav.]]) -> 1006.6958 | Q21: =IFERROR(IF(compras_mes3[[#This Row],[CUIT]]="","-",VLOOKUP(compras_mes3[[#This Row],[CUIT]],Lista_CUIT[#All],3,0)),"CUIT NO CARGADO") -> Autopista | R21: =IFERROR(IF(compras_mes3[[#This Row],[CUIT]]="","-",VLOOKUP(compras_mes3[[#This Row],[CUIT]],Lista_CUIT[#All],4,0)),"CUIT NO CARGADO") -> 0
B22: 45743 | C22: 1 | D22: 6 | E22: 1851 | F22: 30716815710 | G22: =IFERROR(IF(compras_mes3[[#This Row],[CUIT]]="","-",VLOOKUP(compras_mes3[[#This Row],[CUIT]],Lista_CUIT[#All],2,0)),"CUIT NO CARGADO") -> PAPELERA GEOPEL SRL | H22: 17000 | I22: =IF(compras_mes3[[#This Row],[NETO GRAVADO]]="","",compras_mes3[[#This Row],[NETO GRAVADO]]*0.21) -> 3570 | P22: =SUM(compras_mes3[[#This Row],[NETO GRAVADO]:[Otros / No Grav.]]) -> 20570 | Q22: =IFERROR(IF(compras_mes3[[#This Row],[CUIT]]="","-",VLOOKUP(compras_mes3[[#This Row],[CUIT]],Lista_CUIT[#All],3,0)),"CUIT NO CARGADO") -> librería | R22: =IFERROR(IF(compras_mes3[[#This Row],[CUIT]]="","-",VLOOKUP(compras_mes3[[#This Row],[CUIT]],Lista_CUIT[#All],4,0)),"CUIT NO CARGADO") -> 0
B23: 45742 | C23: 1 | D23: 6 | E23: 11449 | F23: 30707988378 | G23: =IFERROR(IF(compras_mes3[[#This Row],[CUIT]]="","-",VLOOKUP(compras_mes3[[#This Row],[CUIT]],Lista_CUIT[#All],2,0)),"CUIT NO CARGADO") -> CARMAS COMPOSITES S.R.L. | H23: =224.7*1091.5 -> 245260.05 | I23: =IF(compras_mes3[[#This Row],[NETO GRAVADO]]="","",compras_mes3[[#This Row],[NETO GRAVADO]]*0.21) -> 51504.61 | P23: =SUM(compras_mes3[[#This Row],[NETO GRAVADO]:[Otros / No Grav.]]) -> 296764.66 | Q23: =IFERROR(IF(compras_mes3[[#This Row],[CUIT]]="","-",VLOOKUP(compras_mes3[[#This Row],[CUIT]],Lista_CUIT[#All],3,0)),"CUIT NO CARGADO") -> Mantenimiento | R23: =IFERROR(IF(compras_mes3[[#This Row],[CUIT]]="","-",VLOOKUP(compras_mes3[[#This Row],[CUIT]],Lista_CUIT[#All],4,0)),"CUIT NO CARGADO") -> 0
B24: 45714 | C24: 1 | D24: 6 | E24: 21293 | F24: 33715594949 | G24: =IFERROR(IF(compras_mes3[[#This Row],[CUIT]]="","-",VLOOKUP(compras_mes3[[#This Row],[CUIT]],Lista_CUIT[#All],2,0)),"CUIT NO CARGADO") -> SOMOS ENERGIA SA | H24: 63156.77 | I24: =IF(compras_mes3[[#This Row],[NETO GRAVADO]]="","",compras_mes3[[#This Row],[NETO GRAVADO]]*0.21) -> 13262.922 | O24: 8580.35 | P24: =SUM(compras_mes3[[#This Row],[NETO GRAVADO]:[Otros / No Grav.]]) -> 85000.042 | Q24: =IFERROR(IF(compras_mes3[[#This Row],[CUIT]]="","-",VLOOKUP(compras_mes3[[#This Row],[CUIT]],Lista_CUIT[#All],3,0)),"CUIT NO CARGADO") -> COMBUSTIBLE | R24: =IFERROR(IF(compras_mes3[[#This Row],[CUIT]]="","-",VLOOKUP(compras_mes3[[#This Row],[CUIT]],Lista_CUIT[#All],4,0)),"CUIT NO CARGADO") -> 0
B25: 45727 | C25: 1 | D25: 8 | E25: 14425 | F25: 33715594949 | G25: =IFERROR(IF(compras_mes3[[#This Row],[CUIT]]="","-",VLOOKUP(compras_mes3[[#This Row],[CUIT]],Lista_CUIT[#All],2,0)),"CUIT NO CARGADO") -> SOMOS ENERGIA SA | H25: 20948.88 | I25: =IF(compras_mes3[[#This Row],[NETO GRAVADO]]="","",compras_mes3[[#This Row],[NETO GRAVADO]]*0.21) -> 4399.2648 | O25: 5651.9 | P25: =SUM(compras_mes3[[#This Row],[NETO GRAVADO]:[Otros / No Grav.]]) -> 31000.045 | Q25: =IFERROR(IF(compras_mes3[[#This Row],[CUIT]]="","-",VLOOKUP(compras_mes3[[#This Row],[CUIT]],Lista_CUIT[#All],3,0)),"CUIT NO CARGADO") -> COMBUSTIBLE | R25: =IFERROR(IF(compras_mes3[[#This Row],[CUIT]]="","-",VLOOKUP(compras_mes3[[#This Row],[CUIT]],Lista_CUIT[#All],4,0)),"CUIT NO CARGADO") -> 0
B26: 45743 | C26: 1 | D26: 8 | E26: 14585 | F26: 33715594949 | G26: =IFERROR(IF(compras_mes3[[#This Row],[CUIT]]="","-",VLOOKUP(compras_mes3[[#This Row],[CUIT]],Lista_CUIT[#All],2,0)),"CUIT NO CARGADO") -> SOMOS ENERGIA SA | H26: 37115.45 | I26: =IF(compras_mes3[[#This Row],[NETO GRAVADO]]="","",compras_mes3[[#This Row],[NETO GRAVADO]]*0.21) -> 7794.2445 | O26: 5091.34 | P26: =SUM(compras_mes3[[#This Row],[NETO GRAVADO]:[Otros / No Grav.]]) -> 50001.034 | Q26: =IFERROR(IF(compras_mes3[[#This Row],[CUIT]]="","-",VLOOKUP(compras_mes3[[#This Row],[CUIT]],Lista_CUIT[#All],3,0)),"CUIT NO CARGADO") -> COMBUSTIBLE | R26: =IFERROR(IF(compras_mes3[[#This Row],[CUIT]]="","-",VLOOKUP(compras_mes3[[#This Row],[CUIT]],Lista_CUIT[#All],4,0)),"CUIT NO CARGADO") -> 0
B27: 45735 | C27: 1 | D27: 10 | E27: 11795 | F27: 30709208221 | G27: =IFERROR(IF(compras_mes3[[#This Row],[CUIT]]="","-",VLOOKUP(compras_mes3[[#This Row],[CUIT]],Lista_CUIT[#All],2,0)),"CUIT NO CARGADO") -> GNC MONTE GRANDE SRL | H27: 51867.12 | I27: =IF(compras_mes3[[#This Row],[NETO GRAVADO]]="","",compras_mes3[[#This Row],[NETO GRAVADO]]*0.21) -> 10892.095 | O27: 7240.83 | P27: =SUM(compras_mes3[[#This Row],[NETO GRAVADO]:[Otros / No Grav.]]) -> 70000.045 | Q27: =IFERROR(IF(compras_mes3[[#This Row],[CUIT]]="","-",VLOOKUP(compras_mes3[[#This Row],[CUIT]],Lista_CUIT[#All],3,0)),"CUIT NO CARGADO") -> COMBUSTIBLE | R27: =IFERROR(IF(compras_mes3[[#This Row],[CUIT]]="","-",VLOOKUP(compras_mes3[[#This Row],[CUIT]],Lista_CUIT[#All],4,0)),"CUIT NO CARGADO") -> 0
B28: 45730 | C28: 1 | D28: 7 | E28: 5105 | F28: 30709904872 | G28: =IFERROR(IF(compras_mes3[[#This Row],[CUIT]]="","-",VLOOKUP(compras_mes3[[#This Row],[CUIT]],Lista_CUIT[#All],2,0)),"CUIT NO CARGADO") -> LOGISTICA DE LA COSTA SA | H28: 65800 | I28: =IF(compras_mes3[[#This Row],[NETO GRAVADO]]="","",compras_mes3[[#This Row],[NETO GRAVADO]]*0.21) -> 13818 | P28: =SUM(compras_mes3[[#This Row],[NETO GRAVADO]:[Otros / No Grav.]]) -> 79618 | Q28: =IFERROR(IF(compras_mes3[[#This Row],[CUIT]]="","-",VLOOKUP(compras_mes3[[#This Row],[CUIT]],Lista_CUIT[#All],3,0)),"CUIT NO CARGADO") -> Flete | R28: =IFERROR(IF(compras_mes3[[#This Row],[CUIT]]="","-",VLOOKUP(compras_mes3[[#This Row],[CUIT]],Lista_CUIT[#All],4,0)),"CUIT NO CARGADO") -> 0
B29: 45721 | C29: 1 | D29: 2399 | E29: 84206 | F29: 30708574836 | G29: =IFERROR(IF(compras_mes3[[#This Row],[CUIT]]="","-",VLOOKUP(compras_mes3[[#This Row],[CUIT]],Lista_CUIT[#All],2,0)),"CUIT NO CARGADO") -> CORREO OFICIAL DE LA REPUBLICA ARGENTINA SOCIEDAD ANONIMA | H29: 21100 | P29: =SUM(compras_mes3[[#This Row],[NETO GRAVADO]:[Otros / No Grav.]]) -> 21100 | Q29: =IFERROR(IF(compras_mes3[[#This Row],[CUIT]]="","-",VLOOKUP(compras_mes3[[#This Row],[CUIT]],Lista_CUIT[#All],3,0)),"CUIT NO CARGADO") -> Gastos Varios | R29: =IFERROR(IF(compras_mes3[[#This Row],[CUIT]]="","-",VLOOKUP(compras_mes3[[#This Row],[CUIT]],Lista_CUIT[#All],4,0)),"CUIT NO CARGADO") -> 0
B30: 45717 | C30: 1 | D30: 629 | E30: 5901502 | F30: 30663498513 | G30: =IFERROR(IF(compras_mes3[[#This Row],[CUIT]]="","-",VLOOKUP(compras_mes3[[#This Row],[CUIT]],Lista_CUIT[#All],2,0)),"CUIT NO CARGADO") -> GRUPO CONCES. DEL OESTE SA | H30: 1155.52 | I30: =IF(compras_mes3[[#This Row],[NETO GRAVADO]]="","",compras_mes3[[#This Row],[NETO GRAVADO]]*0.21) -> 242.6592 | P30: =SUM(compras_mes3[[#This Row],[NETO GRAVADO]:[Otros / No Grav.]]) -> 1398.1792 | Q30: =IFERROR(IF(compras_mes3[[#This Row],[CUIT]]="","-",VLOOKUP(compras_mes3[[#This Row],[CUIT]],Lista_CUIT[#All],3,0)),"CUIT NO CARGADO") -> Autopista | R30: =IFERROR(IF(compras_mes3[[#This Row],[CUIT]]="","-",VLOOKUP(compras_mes3[[#This Row],[CUIT]],Lista_CUIT[#All],4,0)),"CUIT NO CARGADO") -> 0
B31: 45717 | C31: 1 | D31: 1 | E31: 116458 | F31: 30714864269 | G31: =IFERROR(IF(compras_mes3[[#This Row],[CUIT]]="","-",VLOOKUP(compras_mes3[[#This Row],[CUIT]],Lista_CUIT[#All],2,0)),"CUIT NO CARGADO") -> CONTABILIUM S.A. S. A. | H31: 164170 | I31: =IF(compras_mes3[[#This Row],[NETO GRAVADO]]="","",compras_mes3[[#This Row],[NETO GRAVADO]]*0.21) -> 34475.7 | P31: =SUM(compras_mes3[[#This Row],[NETO GRAVADO]:[Otros / No Grav.]]) -> 198645.7 | Q31: =IFERROR(IF(compras_mes3[[#This Row],[CUIT]]="","-",VLOOKUP(compras_mes3[[#This Row],[CUIT]],Lista_CUIT[#All],3,0)),"CUIT NO CARGADO") -> USUARIO CONTABLE | R31: =IFERROR(IF(compras_mes3[[#This Row],[CUIT]]="","-",VLOOKUP(compras_mes3[[#This Row],[CUIT]],Lista_CUIT[#All],4,0)),"CUIT NO CARGADO") -> 0
B32: 45717 | C32: 1 | D32: 711 | E32: 6809656 | F32: 30677237119 | G32: =IFERROR(IF(compras_mes3[[#This Row],[CUIT]]="","-",VLOOKUP(compras_mes3[[#This Row],[CUIT]],Lista_CUIT[#All],2,0)),"CUIT NO CARGADO") -> AUTOPISTAS DEL SOL SA | H32: 1155.52 | I32: =IF(compras_mes3[[#This Row],[NETO GRAVADO]]="","",compras_mes3[[#This Row],[NETO GRAVADO]]*0.21) -> 242.6592 | P32: =SUM(compras_mes3[[#This Row],[NETO GRAVADO]:[Otros / No Grav.]]) -> 1398.1792 | Q32: =IFERROR(IF(compras_mes3[[#This Row],[CUIT]]="","-",VLOOKUP(compras_mes3[[#This Row],[CUIT]],Lista_CUIT[#All],3,0)),"CUIT NO CARGADO") -> Autopista | R32: =IFERROR(IF(compras_mes3[[#This Row],[CUIT]]="","-",VLOOKUP(compras_mes3[[#This Row],[CUIT]],Lista_CUIT[#All],4,0)),"CUIT NO CARGADO") -> 0
B33: 45719 | C33: 1 | D33: 2 | E33: 231 | F33: 30605344352 | G33: =IFERROR(IF(compras_mes3[[#This Row],[CUIT]]="","-",VLOOKUP(compras_mes3[[#This Row],[CUIT]],Lista_CUIT[#All],2,0)),"CUIT NO CARGADO") -> CONSORCIO BARTOLME MITRE 2466 | H33: 1200000 | I33: =IF(compras_mes3[[#This Row],[NETO GRAVADO]]="","",compras_mes3[[#This Row],[NETO GRAVADO]]*0.21) -> 252000 | P33: =SUM(compras_mes3[[#This Row],[NETO GRAVADO]:[Otros / No Grav.]]) -> 1452000 | Q33: =IFERROR(IF(compras_mes3[[#This Row],[CUIT]]="","-",VLOOKUP(compras_mes3[[#This Row],[CUIT]],Lista_CUIT[#All],3,0)),"CUIT NO CARGADO") -> ALQUILER LOCAL | R33: =IFERROR(IF(compras_mes3[[#This Row],[CUIT]]="","-",VLOOKUP(compras_mes3[[#This Row],[CUIT]],Lista_CUIT[#All],4,0)),"CUIT NO CARGADO") -> 0
B34: 45719 | C34: 1 | D34: 500 | E34: 1694216 | F34: 30654118767 | G34: =IFERROR(IF(compras_mes3[[#This Row],[CUIT]]="","-",VLOOKUP(compras_mes3[[#This Row],[CUIT]],Lista_CUIT[#All],2,0)),"CUIT NO CARGADO") -> SOLUCIONES MULTIMEDIA SA | H34: 117349.04 | I34: =IF(compras_mes3[[#This Row],[NETO GRAVADO]]="","",compras_mes3[[#This Row],[NETO GRAVADO]]*0.21) -> 24643.298 | P34: =SUM(compras_mes3[[#This Row],[NETO GRAVADO]:[Otros / No Grav.]]) -> 141992.34 | Q34: =IFERROR(IF(compras_mes3[[#This Row],[CUIT]]="","-",VLOOKUP(compras_mes3[[#This Row],[CUIT]],Lista_CUIT[#All],3,0)),"CUIT NO CARGADO") -> gastos varios | R34: =IFERROR(IF(compras_mes3[[#This Row],[CUIT]]="","-",VLOOKUP(compras_mes3[[#This Row],[CUIT]],Lista_CUIT[#All],4,0)),"CUIT NO CARGADO") -> 0
B35: 45721 | C35: 1 | D35: 3 | E35: 30 | F35: 20216164262 | G35: =IFERROR(IF(compras_mes3[[#This Row],[CUIT]]="","-",VLOOKUP(compras_mes3[[#This Row],[CUIT]],Lista_CUIT[#All],2,0)),"CUIT NO CARGADO") -> VELEZ ALEJANDRO MARCELO | H35: 1166562 | I35: =IF(compras_mes3[[#This Row],[NETO GRAVADO]]="","",compras_mes3[[#This Row],[NETO GRAVADO]]*0.21) -> 244978.02 | P35: =SUM(compras_mes3[[#This Row],[NETO GRAVADO]:[Otros / No Grav.]]) -> 1411540 | Q35: =IFERROR(IF(compras_mes3[[#This Row],[CUIT]]="","-",VLOOKUP(compras_mes3[[#This Row],[CUIT]],Lista_CUIT[#All],3,0)),"CUIT NO CARGADO") -> Insumos | R35: =IFERROR(IF(compras_mes3[[#This Row],[CUIT]]="","-",VLOOKUP(compras_mes3[[#This Row],[CUIT]],Lista_CUIT[#All],4,0)),"CUIT NO CARGADO") -> 0
B36: 45722 | C36: 1 | D36: 2 | E36: 1132 | F36: 20272865869 | G36: =IFERROR(IF(compras_mes3[[#This Row],[CUIT]]="","-",VLOOKUP(compras_mes3[[#This Row],[CUIT]],Lista_CUIT[#All],2,0)),"CUIT NO CARGADO") -> DI FEO MARTIN EZEQUIEL | H36: 155850 | I36: =IF(compras_mes3[[#This Row],[NETO GRAVADO]]="","",compras_mes3[[#This Row],[NETO GRAVADO]]*0.21) -> 32728.5 | P36: =SUM(compras_mes3[[#This Row],[NETO GRAVADO]:[Otros / No Grav.]]) -> 188578.5 | Q36: =IFERROR(IF(compras_mes3[[#This Row],[CUIT]]="","-",VLOOKUP(compras_mes3[[#This Row],[CUIT]],Lista_CUIT[#All],3,0)),"CUIT NO CARGADO") -> INSUMOS | R36: =IFERROR(IF(compras_mes3[[#This Row],[CUIT]]="","-",VLOOKUP(compras_mes3[[#This Row],[CUIT]],Lista_CUIT[#All],4,0)),"CUIT NO CARGADO") -> 0
B37: 45722 | C37: 1 | D37: 700 | E37: 2313354 | F37: 30715804812 | G37: =IFERROR(IF(compras_mes3[[#This Row],[CUIT]]="","-",VLOOKUP(compras_mes3[[#This Row],[CUIT]],Lista_CUIT[#All],2,0)),"CUIT NO CARGADO") -> CORREDORES VIALES SOCIEDAD ANONIMA | H37: 7695.87 | I37: =IF(compras_mes3[[#This Row],[NETO GRAVADO]]="","",compras_mes3[[#This Row],[NETO GRAVADO]]*0.21) -> 1616.1327 | P37: =SUM(compras_mes3[[#This Row],[NETO GRAVADO]:[Otros / No Grav.]]) -> 9312.0027 | Q37: =IFERROR(IF(compras_mes3[[#This Row],[CUIT]]="","-",VLOOKUP(compras_mes3[[#This Row],[CUIT]],Lista_CUIT[#All],3,0)),"CUIT NO CARGADO") -> Autopista | R37: =IFERROR(IF(compras_mes3[[#This Row],[CUIT]]="","-",VLOOKUP(compras_mes3[[#This Row],[CUIT]],Lista_CUIT[#All],4,0)),"CUIT NO CARGADO") -> 0
B38: 45722 | C38: 1 | D38: 700 | E38: 2313355 | F38: 30715804812 | G38: =IFERROR(IF(compras_mes3[[#This Row],[CUIT]]="","-",VLOOKUP(compras_mes3[[#This Row],[CUIT]],Lista_CUIT[#All],2,0)),"CUIT NO CARGADO") -> CORREDORES VIALES SOCIEDAD ANONIMA | H38: 9151.84 | I38: =IF(compras_mes3[[#This Row],[NETO GRAVADO]]="","",compras_mes3[[#This Row],[NETO GRAVADO]]*0.21) -> 1921.8864 | P38: =SUM(compras_mes3[[#This Row],[NETO GRAVADO]:[Otros / No Grav.]]) -> 11073.726 | Q38: =IFERROR(IF(compras_mes3[[#This Row],[CUIT]]="","-",VLOOKUP(compras_mes3[[#This Row],[CUIT]],Lista_CUIT[#All],3,0)),"CUIT NO CARGADO") -> Autopista | R38: =IFERROR(IF(compras_mes3[[#This Row],[CUIT]]="","-",VLOOKUP(compras_mes3[[#This Row],[CUIT]],Lista_CUIT[#All],4,0)),"CUIT NO CARGADO") -> 0
B39: 45723 | C39: 1 | D39: 2 | E39: 1133 | F39: 20272865869 | G39: =IFERROR(IF(compras_mes3[[#This Row],[CUIT]]="","-",VLOOKUP(compras_mes3[[#This Row],[CUIT]],Lista_CUIT[#All],2,0)),"CUIT NO CARGADO") -> DI FEO MARTIN EZEQUIEL | H39: 39000 | I39: =IF(compras_mes3[[#This Row],[NETO GRAVADO]]="","",compras_mes3[[#This Row],[NETO GRAVADO]]*0.21) -> 8190 | P39: =SUM(compras_mes3[[#This Row],[NETO GRAVADO]:[Otros / No Grav.]]) -> 47190 | Q39: =IFERROR(IF(compras_mes3[[#This Row],[CUIT]]="","-",VLOOKUP(compras_mes3[[#This Row],[CUIT]],Lista_CUIT[#All],3,0)),"CUIT NO CARGADO") -> INSUMOS | R39: =IFERROR(IF(compras_mes3[[#This Row],[CUIT]]="","-",VLOOKUP(compras_mes3[[#This Row],[CUIT]],Lista_CUIT[#All],4,0)),"CUIT NO CARGADO") -> 0
B40: 45723 | C40: 1 | D40: 7 | E40: 27 | F40: 27325223273 | G40: =IFERROR(IF(compras_mes3[[#This Row],[CUIT]]="","-",VLOOKUP(compras_mes3[[#This Row],[CUIT]],Lista_CUIT[#All],2,0)),"CUIT NO CARGADO") -> SOUSA ALDERETE ALEJANDRA MABEL | H40: 1650000 | I40: =IF(compras_mes3[[#This Row],[NETO GRAVADO]]="","",compras_mes3[[#This Row],[NETO GRAVADO]]*0.21) -> 346500 | P40: =SUM(compras_mes3[[#This Row],[NETO GRAVADO]:[Otros / No Grav.]]) -> 1996500 | Q40: =IFERROR(IF(compras_mes3[[#This Row],[CUIT]]="","-",VLOOKUP(compras_mes3[[#This Row],[CUIT]],Lista_CUIT[#All],3,0)),"CUIT NO CARGADO") -> Insumos | R40: =IFERROR(IF(compras_mes3[[#This Row],[CUIT]]="","-",VLOOKUP(compras_mes3[[#This Row],[CUIT]],Lista_CUIT[#All],4,0)),"CUIT NO CARGADO") -> 0
B41: 45723 | C41: 1 | D41: 2 | E41: 487 | F41: 30711610096 | G41: =IFERROR(IF(compras_mes3[[#This Row],[CUIT]]="","-",VLOOKUP(compras_mes3[[#This Row],[CUIT]],Lista_CUIT[#All],2,0)),"CUIT NO CARGADO") -> 46 SPEED S.A. | H41: 698000 | I41: =IF(compras_mes3[[#This Row],[NETO GRAVADO]]="","",compras_mes3[[#This Row],[NETO GRAVADO]]*0.21) -> 146580 | P41: =SUM(compras_mes3[[#This Row],[NETO GRAVADO]:[Otros / No Grav.]]) -> 844580 | Q41: =IFERROR(IF(compras_mes3[[#This Row],[CUIT]]="","-",VLOOKUP(compras_mes3[[#This Row],[CUIT]],Lista_CUIT[#All],3,0)),"CUIT NO CARGADO") -> Insumos | R41: =IFERROR(IF(compras_mes3[[#This Row],[CUIT]]="","-",VLOOKUP(compras_mes3[[#This Row],[CUIT]],Lista_CUIT[#All],4,0)),"CUIT NO CARGADO") -> 0
... B44: 45724 | C44: 1 | D44: 5015 | E44: 778963 | F44: 30574876474 | G44: =IFERROR(IF(compras_mes3[[#This Row],[CUIT]]="","-",VLOOKUP(compras_mes3[[#This Row],[CUIT]],Lista_CUIT[#All],2,0)),"CUIT NO CARGADO") -> AUTOP. URBANAS SA | H44: 13213.87 | I44: =IF(compras_mes3[[#This Row],[NETO GRAVADO]]="","",compras_mes3[[#This Row],[NETO GRAVADO]]*0.21) -> 2774.9127 | P44: =SUM(compras_mes3[[#This Row],[NETO GRAVADO]:[Otros / No Grav.]]) -> 15988.783 | Q44: =IFERROR(IF(compras_mes3[[#This Row],[CUIT]]="","-",VLOOKUP(compras_mes3[[#This Row],[CUIT]],Lista_CUIT[#All],3,0)),"CUIT NO CARGADO") -> PEAJE | R44: =IFERROR(IF(compras_mes3[[#This Row],[CUIT]]="","-",VLOOKUP(compras_mes3[[#This Row],[CUIT]],Lista_CUIT[#All],4,0)),"CUIT NO CARGADO") -> 0
B45: 45725 | C45: 1 | D45: 3101 | E45: 278864 | F45: 30678814357 | G45: =IFERROR(IF(compras_mes3[[#This Row],[CUIT]]="","-",VLOOKUP(compras_mes3[[#This Row],[CUIT]],Lista_CUIT[#All],2,0)),"CUIT NO CARGADO") -> TELEFONICA MOVILES ARG SA | H45: 82083.6 | J45: =compras_mes3[[#This Row],[NETO GRAVADO]]*27/100 -> 22162.572 | P45: =SUM(compras_mes3[[#This Row],[NETO GRAVADO]:[Otros / No Grav.]]) -> 104246.17 | Q45: =IFERROR(IF(compras_mes3[[#This Row],[CUIT]]="","-",VLOOKUP(compras_mes3[[#This Row],[CUIT]],Lista_CUIT[#All],3,0)),"CUIT NO CARGADO") -> SERVICIO | R45: =IFERROR(IF(compras_mes3[[#This Row],[CUIT]]="","-",VLOOKUP(compras_mes3[[#This Row],[CUIT]],Lista_CUIT[#All],4,0)),"CUIT NO CARGADO") -> 0
B46: 45725 | C46: 1 | D46: 2189 | E46: 86551 | F46: 30548083156 | G46: =IFERROR(IF(compras_mes3[[#This Row],[CUIT]]="","-",VLOOKUP(compras_mes3[[#This Row],[CUIT]],Lista_CUIT[#All],2,0)),"CUIT NO CARGADO") -> COTO CICSA | H46: 7295.47 | I46: =IF(compras_mes3[[#This Row],[NETO GRAVADO]]="","",compras_mes3[[#This Row],[NETO GRAVADO]]*0.21) -> 1532.0487 | P46: =SUM(compras_mes3[[#This Row],[NETO GRAVADO]:[Otros / No Grav.]]) -> 8827.5187 | Q46: =IFERROR(IF(compras_mes3[[#This Row],[CUIT]]="","-",VLOOKUP(compras_mes3[[#This Row],[CUIT]],Lista_CUIT[#All],3,0)),"CUIT NO CARGADO") -> Gastos Varios | R46: =IFERROR(IF(compras_mes3[[#This Row],[CUIT]]="","-",VLOOKUP(compras_mes3[[#This Row],[CUIT]],Lista_CUIT[#All],4,0)),"CUIT NO CARGADO") -> 0
B47: 45727 | C47: 1 | D47: 2 | E47: 11604 | F47: 30714331082 | G47: =IFERROR(IF(compras_mes3[[#This Row],[CUIT]]="","-",VLOOKUP(compras_mes3[[#This Row],[CUIT]],Lista_CUIT[#All],2,0)),"CUIT NO CARGADO") -> ORTOPEDIA CASA ESCALADA SRL | H47: 423275.07 | I47: =IF(compras_mes3[[#This Row],[NETO GRAVADO]]="","",compras_mes3[[#This Row],[NETO GRAVADO]]*0.21) -> 88887.765 | P47: =SUM(compras_mes3[[#This Row],[NETO GRAVADO]:[Otros / No Grav.]]) -> 512162.83 | Q47: =IFERROR(IF(compras_mes3[[#This Row],[CUIT]]="","-",VLOOKUP(compras_mes3[[#This Row],[CUIT]],Lista_CUIT[#All],3,0)),"CUIT NO CARGADO") -> INSUMO | R47: =IFERROR(IF(compras_mes3[[#This Row],[CUIT]]="","-",VLOOKUP(compras_mes3[[#This Row],[CUIT]],Lista_CUIT[#All],4,0)),"CUIT NO CARGADO") -> 0
B48: 45728 | C48: 1 | D48: 4 | E48: 39574 | F48: 20289111329 | G48: =IFERROR(IF(compras_mes3[[#This Row],[CUIT]]="","-",VLOOKUP(compras_mes3[[#This Row],[CUIT]],Lista_CUIT[#All],2,0)),"CUIT NO CARGADO") -> R. N. LEDESMA | H48: 292865.41 | I48: =IF(compras_mes3[[#This Row],[NETO GRAVADO]]="","",compras_mes3[[#This Row],[NETO GRAVADO]]*0.21) -> 61501.736 | P48: =SUM(compras_mes3[[#This Row],[NETO GRAVADO]:[Otros / No Grav.]]) -> 354367.15 | Q48: =IFERROR(IF(compras_mes3[[#This Row],[CUIT]]="","-",VLOOKUP(compras_mes3[[#This Row],[CUIT]],Lista_CUIT[#All],3,0)),"CUIT NO CARGADO") -> Insumo | R48: =IFERROR(IF(compras_mes3[[#This Row],[CUIT]]="","-",VLOOKUP(compras_mes3[[#This Row],[CUIT]],Lista_CUIT[#All],4,0)),"CUIT NO CARGADO") -> 0
B49: 45728 | C49: 1 | D49: 4 | E49: 39572 | F49: 20289111329 | G49: =IFERROR(IF(compras_mes3[[#This Row],[CUIT]]="","-",VLOOKUP(compras_mes3[[#This Row],[CUIT]],Lista_CUIT[#All],2,0)),"CUIT NO CARGADO") -> R. N. LEDESMA | H49: 585348.09 | I49: =IF(compras_mes3[[#This Row],[NETO GRAVADO]]="","",compras_mes3[[#This Row],[NETO GRAVADO]]*0.21) -> 122923.1 | P49: =SUM(compras_mes3[[#This Row],[NETO GRAVADO]:[Otros / No Grav.]]) -> 708271.19 | Q49: =IFERROR(IF(compras_mes3[[#This Row],[CUIT]]="","-",VLOOKUP(compras_mes3[[#This Row],[CUIT]],Lista_CUIT[#All],3,0)),"CUIT NO CARGADO") -> Insumo | R49: =IFERROR(IF(compras_mes3[[#This Row],[CUIT]]="","-",VLOOKUP(compras_mes3[[#This Row],[CUIT]],Lista_CUIT[#All],4,0)),"CUIT NO CARGADO") -> 0
B50: 45728 | C50: 1 | D50: 6 | E50: 89635 | F50: 30711553564 | G50: =IFERROR(IF(compras_mes3[[#This Row],[CUIT]]="","-",VLOOKUP(compras_mes3[[#This Row],[CUIT]],Lista_CUIT[#All],2,0)),"CUIT NO CARGADO") -> SALUD TEX S.A | H50: 846283.75 | I50: =IF(compras_mes3[[#This Row],[NETO GRAVADO]]="","",compras_mes3[[#This Row],[NETO GRAVADO]]*0.21) -> 177719.59 | P50: =SUM(compras_mes3[[#This Row],[NETO GRAVADO]:[Otros / No Grav.]]) -> 1024003.3 | Q50: =IFERROR(IF(compras_mes3[[#This Row],[CUIT]]="","-",VLOOKUP(compras_mes3[[#This Row],[CUIT]],Lista_CUIT[#All],3,0)),"CUIT NO CARGADO") -> INSUMO | R50: =IFERROR(IF(compras_mes3[[#This Row],[CUIT]]="","-",VLOOKUP(compras_mes3[[#This Row],[CUIT]],Lista_CUIT[#All],4,0)),"CUIT NO CARGADO") -> 0
B51: 45729 | C51: 1 | D51: 5 | E51: 1485 | F51: 27265302225 | G51: =IFERROR(IF(compras_mes3[[#This Row],[CUIT]]="","-",VLOOKUP(compras_mes3[[#This Row],[CUIT]],Lista_CUIT[#All],2,0)),"CUIT NO CARGADO") -> PRADO MARISOL | H51: 800000 | I51: =IF(compras_mes3[[#This Row],[NETO GRAVADO]]="","",compras_mes3[[#This Row],[NETO GRAVADO]]*0.21) -> 168000 | P51: =SUM(compras_mes3[[#This Row],[NETO GRAVADO]:[Otros / No Grav.]]) -> 968000 | Q51: =IFERROR(IF(compras_mes3[[#This Row],[CUIT]]="","-",VLOOKUP(compras_mes3[[#This Row],[CUIT]],Lista_CUIT[#All],3,0)),"CUIT NO CARGADO") -> INSUMO | R51: =IFERROR(IF(compras_mes3[[#This Row],[CUIT]]="","-",VLOOKUP(compras_mes3[[#This Row],[CUIT]],Lista_CUIT[#All],4,0)),"CUIT NO CARGADO") -> 0
B52: 45729 | C52: 1 | D52: 3 | E52: 48480 | F52: 30711454388 | G52: =IFERROR(IF(compras_mes3[[#This Row],[CUIT]]="","-",VLOOKUP(compras_mes3[[#This Row],[CUIT]],Lista_CUIT[#All],2,0)),"CUIT NO CARGADO") -> LIPROT S.R.L. | H52: 137543 | I52: =IF(compras_mes3[[#This Row],[NETO GRAVADO]]="","",compras_mes3[[#This Row],[NETO GRAVADO]]*0.21) -> 28884.03 | P52: =SUM(compras_mes3[[#This Row],[NETO GRAVADO]:[Otros / No Grav.]]) -> 166427.03 | Q52: =IFERROR(IF(compras_mes3[[#This Row],[CUIT]]="","-",VLOOKUP(compras_mes3[[#This Row],[CUIT]],Lista_CUIT[#All],3,0)),"CUIT NO CARGADO") -> textil | R52: =IFERROR(IF(compras_mes3[[#This Row],[CUIT]]="","-",VLOOKUP(compras_mes3[[#This Row],[CUIT]],Lista_CUIT[#All],4,0)),"CUIT NO CARGADO") -> 0
B53: 45729 | C53: 1 | D53: 2 | E53: 1151 | F53: 20272865869 | G53: =IFERROR(IF(compras_mes3[[#This Row],[CUIT]]="","-",VLOOKUP(compras_mes3[[#This Row],[CUIT]],Lista_CUIT[#All],2,0)),"CUIT NO CARGADO") -> DI FEO MARTIN EZEQUIEL | H53: 87550 | I53: =IF(compras_mes3[[#This Row],[NETO GRAVADO]]="","",compras_mes3[[#This Row],[NETO GRAVADO]]*0.21) -> 18385.5 | P53: =SUM(compras_mes3[[#This Row],[NETO GRAVADO]:[Otros / No Grav.]]) -> 105935.5 | Q53: =IFERROR(IF(compras_mes3[[#This Row],[CUIT]]="","-",VLOOKUP(compras_mes3[[#This Row],[CUIT]],Lista_CUIT[#All],3,0)),"CUIT NO CARGADO") -> INSUMOS | R53: =IFERROR(IF(compras_mes3[[#This Row],[CUIT]]="","-",VLOOKUP(compras_mes3[[#This Row],[CUIT]],Lista_CUIT[#All],4,0)),"CUIT NO CARGADO") -> 0
B54: 45729 | C54: 1 | D54: 3 | E54: 8664 | F54: 33708218699 | G54: =IFERROR(IF(compras_mes3[[#This Row],[CUIT]]="","-",VLOOKUP(compras_mes3[[#This Row],[CUIT]],Lista_CUIT[#All],2,0)),"CUIT NO CARGADO") -> MANGGINI PABLO Y MANGGINI ULISES SOC. DE HECHO. | H54: 24000 | I54: =IF(compras_mes3[[#This Row],[NETO GRAVADO]]="","",compras_mes3[[#This Row],[NETO GRAVADO]]*0.21) -> 5040 | P54: =SUM(compras_mes3[[#This Row],[NETO GRAVADO]:[Otros / No Grav.]]) -> 29040 | Q54: =IFERROR(IF(compras_mes3[[#This Row],[CUIT]]="","-",VLOOKUP(compras_mes3[[#This Row],[CUIT]],Lista_CUIT[#All],3,0)),"CUIT NO CARGADO") -> SERVICIO | R54: =IFERROR(IF(compras_mes3[[#This Row],[CUIT]]="","-",VLOOKUP(compras_mes3[[#This Row],[CUIT]],Lista_CUIT[#All],4,0)),"CUIT NO CARGADO") -> 0
B55: 45729 | C55: 1 | D55: 3 | E55: 48479 | F55: 30711454388 | G55: =IFERROR(IF(compras_mes3[[#This Row],[CUIT]]="","-",VLOOKUP(compras_mes3[[#This Row],[CUIT]],Lista_CUIT[#All],2,0)),"CUIT NO CARGADO") -> LIPROT S.R.L. | H55: 213732 | I55: =IF(compras_mes3[[#This Row],[NETO GRAVADO]]="","",compras_mes3[[#This Row],[NETO GRAVADO]]*0.21) -> 44883.72 | P55: =SUM(compras_mes3[[#This Row],[NETO GRAVADO]:[Otros / No Grav.]]) -> 258615.72 | Q55: =IFERROR(IF(compras_mes3[[#This Row],[CUIT]]="","-",VLOOKUP(compras_mes3[[#This Row],[CUIT]],Lista_CUIT[#All],3,0)),"CUIT NO CARGADO") -> textil | R55: =IFERROR(IF(compras_mes3[[#This Row],[CUIT]]="","-",VLOOKUP(compras_mes3[[#This Row],[CUIT]],Lista_CUIT[#All],4,0)),"CUIT NO CARGADO") -> 0
B56: 45729 | C56: 1 | D56: 1000 | E56: 215377 | F56: 30715123483 | G56: =IFERROR(IF(compras_mes3[[#This Row],[CUIT]]="","-",VLOOKUP(compras_mes3[[#This Row],[CUIT]],Lista_CUIT[#All],2,0)),"CUIT NO CARGADO") -> ITPROUSER SA | H56: 15170.24 | I56: =IF(compras_mes3[[#This Row],[NETO GRAVADO]]="","",compras_mes3[[#This Row],[NETO GRAVADO]]*0.21) -> 3185.7504 | P56: =SUM(compras_mes3[[#This Row],[NETO GRAVADO]:[Otros / No Grav.]]) -> 18355.99 | Q56: =IFERROR(IF(compras_mes3[[#This Row],[CUIT]]="","-",VLOOKUP(compras_mes3[[#This Row],[CUIT]],Lista_CUIT[#All],3,0)),"CUIT NO CARGADO") -> FLETE | R56: =IFERROR(IF(compras_mes3[[#This Row],[CUIT]]="","-",VLOOKUP(compras_mes3[[#This Row],[CUIT]],Lista_CUIT[#All],4,0)),"CUIT NO CARGADO") -> 0
B57: 45729 | C57: 1 | D57: 8 | E57: 1763 | F57: 30708973501 | G57: =IFERROR(IF(compras_mes3[[#This Row],[CUIT]]="","-",VLOOKUP(compras_mes3[[#This Row],[CUIT]],Lista_CUIT[#All],2,0)),"CUIT NO CARGADO") -> ASIAL SRL | H57: 616271 | I57: =IF(compras_mes3[[#This Row],[NETO GRAVADO]]="","",compras_mes3[[#This Row],[NETO GRAVADO]]*0.21) -> 129416.91 | P57: =SUM(compras_mes3[[#This Row],[NETO GRAVADO]:[Otros / No Grav.]]) -> 745687.91 | Q57: =IFERROR(IF(compras_mes3[[#This Row],[CUIT]]="","-",VLOOKUP(compras_mes3[[#This Row],[CUIT]],Lista_CUIT[#All],3,0)),"CUIT NO CARGADO") -> INSUMO | R57: =IFERROR(IF(compras_mes3[[#This Row],[CUIT]]="","-",VLOOKUP(compras_mes3[[#This Row],[CUIT]],Lista_CUIT[#All],4,0)),"CUIT NO CARGADO") -> 0
... B71: 45732 | C71: 1 | D71: 629 | E71: 5940679 | F71: 30663498513 | G71: =IFERROR(IF(compras_mes3[[#This Row],[CUIT]]="","-",VLOOKUP(compras_mes3[[#This Row],[CUIT]],Lista_CUIT[#All],2,0)),"CUIT NO CARGADO") -> GRUPO CONCES. DEL OESTE SA | H71: 3813.27 | I71: =IF(compras_mes3[[#This Row],[NETO GRAVADO]]="","",compras_mes3[[#This Row],[NETO GRAVADO]]*0.21) -> 800.7867 | P71: =SUM(compras_mes3[[#This Row],[NETO GRAVADO]:[Otros / No Grav.]]) -> 4614.0567 | Q71: =IFERROR(IF(compras_mes3[[#This Row],[CUIT]]="","-",VLOOKUP(compras_mes3[[#This Row],[CUIT]],Lista_CUIT[#All],3,0)),"CUIT NO CARGADO") -> Autopista | R71: =IFERROR(IF(compras_mes3[[#This Row],[CUIT]]="","-",VLOOKUP(compras_mes3[[#This Row],[CUIT]],Lista_CUIT[#All],4,0)),"CUIT NO CARGADO") -> 0
B72: 45732 | C72: 1 | D72: 711 | E72: 6867805 | F72: 30677237119 | G72: =IFERROR(IF(compras_mes3[[#This Row],[CUIT]]="","-",VLOOKUP(compras_mes3[[#This Row],[CUIT]],Lista_CUIT[#All],2,0)),"CUIT NO CARGADO") -> AUTOPISTAS DEL SOL SA | H72: 4448.77 | I72: =IF(compras_mes3[[#This Row],[NETO GRAVADO]]="","",compras_mes3[[#This Row],[NETO GRAVADO]]*0.21) -> 934.2417 | L72: 133.46 | O72: 133.46 | P72: =SUM(compras_mes3[[#This Row],[NETO GRAVADO]:[Otros / No Grav.]]) -> 5649.9317 | Q72: =IFERROR(IF(compras_mes3[[#This Row],[CUIT]]="","-",VLOOKUP(compras_mes3[[#This Row],[CUIT]],Lista_CUIT[#All],3,0)),"CUIT NO CARGADO") -> Autopista | R72: =IFERROR(IF(compras_mes3[[#This Row],[CUIT]]="","-",VLOOKUP(compras_mes3[[#This Row],[CUIT]],Lista_CUIT[#All],4,0)),"CUIT NO CARGADO") -> 0
B73: 45733 | C73: 1 | D73: 5 | E73: 40 | F73: 20929183143 | G73: =IFERROR(IF(compras_mes3[[#This Row],[CUIT]]="","-",VLOOKUP(compras_mes3[[#This Row],[CUIT]],Lista_CUIT[#All],2,0)),"CUIT NO CARGADO") -> MA JUN | H73: 70000 | I73: =IF(compras_mes3[[#This Row],[NETO GRAVADO]]="","",compras_mes3[[#This Row],[NETO GRAVADO]]*0.21) -> 14700 | P73: =SUM(compras_mes3[[#This Row],[NETO GRAVADO]:[Otros / No Grav.]]) -> 84700 | Q73: =IFERROR(IF(compras_mes3[[#This Row],[CUIT]]="","-",VLOOKUP(compras_mes3[[#This Row],[CUIT]],Lista_CUIT[#All],3,0)),"CUIT NO CARGADO") -> Gastos Varios | R73: =IFERROR(IF(compras_mes3[[#This Row],[CUIT]]="","-",VLOOKUP(compras_mes3[[#This Row],[CUIT]],Lista_CUIT[#All],4,0)),"CUIT NO CARGADO") -> 0
B74: 45733 | C74: 1 | D74: 7 | E74: 20435 | F74: 30709214078 | G74: =IFERROR(IF(compras_mes3[[#This Row],[CUIT]]="","-",VLOOKUP(compras_mes3[[#This Row],[CUIT]],Lista_CUIT[#All],2,0)),"CUIT NO CARGADO") -> REHAVITA S.A | H74: 250800 | K74: =compras_mes3[[#This Row],[NETO GRAVADO]]*10.5/100 -> 26334 | P74: =SUM(compras_mes3[[#This Row],[NETO GRAVADO]:[Otros / No Grav.]]) -> 277134 | Q74: =IFERROR(IF(compras_mes3[[#This Row],[CUIT]]="","-",VLOOKUP(compras_mes3[[#This Row],[CUIT]],Lista_CUIT[#All],3,0)),"CUIT NO CARGADO") -> INSUMO | R74: =IFERROR(IF(compras_mes3[[#This Row],[CUIT]]="","-",VLOOKUP(compras_mes3[[#This Row],[CUIT]],Lista_CUIT[#All],4,0)),"CUIT NO CARGADO") -> 0
B75: 45733 | C75: 1 | D75: 4 | E75: 20470 | F75: 30504854023 | G75: =IFERROR(IF(compras_mes3[[#This Row],[CUIT]]="","-",VLOOKUP(compras_mes3[[#This Row],[CUIT]],Lista_CUIT[#All],2,0)),"CUIT NO CARGADO") -> NYLTEF SAICFI | H75: 167552 | I75: =IF(compras_mes3[[#This Row],[NETO GRAVADO]]="","",compras_mes3[[#This Row],[NETO GRAVADO]]*0.21) -> 35185.92 | P75: =SUM(compras_mes3[[#This Row],[NETO GRAVADO]:[Otros / No Grav.]]) -> 202737.92 | Q75: =IFERROR(IF(compras_mes3[[#This Row],[CUIT]]="","-",VLOOKUP(compras_mes3[[#This Row],[CUIT]],Lista_CUIT[#All],3,0)),"CUIT NO CARGADO") -> INSUMO | R75: =IFERROR(IF(compras_mes3[[#This Row],[CUIT]]="","-",VLOOKUP(compras_mes3[[#This Row],[CUIT]],Lista_CUIT[#All],4,0)),"CUIT NO CARGADO") -> 0
B76: 45733 | C76: 1 | D76: 2 | E76: 11657 | F76: 30714331082 | G76: =IFERROR(IF(compras_mes3[[#This Row],[CUIT]]="","-",VLOOKUP(compras_mes3[[#This Row],[CUIT]],Lista_CUIT[#All],2,0)),"CUIT NO CARGADO") -> ORTOPEDIA CASA ESCALADA SRL | H76: 77787.65 | I76: =IF(compras_mes3[[#This Row],[NETO GRAVADO]]="","",compras_mes3[[#This Row],[NETO GRAVADO]]*0.21) -> 16335.406 | P76: =SUM(compras_mes3[[#This Row],[NETO GRAVADO]:[Otros / No Grav.]]) -> 94123.056 | Q76: =IFERROR(IF(compras_mes3[[#This Row],[CUIT]]="","-",VLOOKUP(compras_mes3[[#This Row],[CUIT]],Lista_CUIT[#All],3,0)),"CUIT NO CARGADO") -> INSUMO | R76: =IFERROR(IF(compras_mes3[[#This Row],[CUIT]]="","-",VLOOKUP(compras_mes3[[#This Row],[CUIT]],Lista_CUIT[#All],4,0)),"CUIT NO CARGADO") -> 0
B77: 45734 | C77: 1 | D77: 1001 | E77: 523 | F77: 30707370552 | G77: =IFERROR(IF(compras_mes3[[#This Row],[CUIT]]="","-",VLOOKUP(compras_mes3[[#This Row],[CUIT]],Lista_CUIT[#All],2,0)),"CUIT NO CARGADO") -> RAKE SA | H77: 1198760.3 | I77: =IF(compras_mes3[[#This Row],[NETO GRAVADO]]="","",compras_mes3[[#This Row],[NETO GRAVADO]]*0.21) -> 251739.67 | P77: =SUM(compras_mes3[[#This Row],[NETO GRAVADO]:[Otros / No Grav.]]) -> 1450500 | Q77: =IFERROR(IF(compras_mes3[[#This Row],[CUIT]]="","-",VLOOKUP(compras_mes3[[#This Row],[CUIT]],Lista_CUIT[#All],3,0)),"CUIT NO CARGADO") -> GASTOS VARIOS | R77: =IFERROR(IF(compras_mes3[[#This Row],[CUIT]]="","-",VLOOKUP(compras_mes3[[#This Row],[CUIT]],Lista_CUIT[#All],4,0)),"CUIT NO CARGADO") -> 0
B78: 45734 | C78: 1 | D78: 7 | E78: 20461 | F78: 30709214078 | G78: =IFERROR(IF(compras_mes3[[#This Row],[CUIT]]="","-",VLOOKUP(compras_mes3[[#This Row],[CUIT]],Lista_CUIT[#All],2,0)),"CUIT NO CARGADO") -> REHAVITA S.A | H78: 303600 | K78: =compras_mes3[[#This Row],[NETO GRAVADO]]*10.5/100 -> 31878 | P78: =SUM(compras_mes3[[#This Row],[NETO GRAVADO]:[Otros / No Grav.]]) -> 335478 | Q78: =IFERROR(IF(compras_mes3[[#This Row],[CUIT]]="","-",VLOOKUP(compras_mes3[[#This Row],[CUIT]],Lista_CUIT[#All],3,0)),"CUIT NO CARGADO") -> INSUMO | R78: =IFERROR(IF(compras_mes3[[#This Row],[CUIT]]="","-",VLOOKUP(compras_mes3[[#This Row],[CUIT]],Lista_CUIT[#All],4,0)),"CUIT NO CARGADO") -> 0
B79: 45735 | C79: 1 | D79: 15 | E79: 4306 | F79: 30688140923 | G79: =IFERROR(IF(compras_mes3[[#This Row],[CUIT]]="","-",VLOOKUP(compras_mes3[[#This Row],[CUIT]],Lista_CUIT[#All],2,0)),"CUIT NO CARGADO") -> COLTEX SRL | H79: 528360.28 | I79: =IF(compras_mes3[[#This Row],[NETO GRAVADO]]="","",compras_mes3[[#This Row],[NETO GRAVADO]]*0.21) -> 110955.66 | P79: =SUM(compras_mes3[[#This Row],[NETO GRAVADO]:[Otros / No Grav.]]) -> 639315.94 | Q79: =IFERROR(IF(compras_mes3[[#This Row],[CUIT]]="","-",VLOOKUP(compras_mes3[[#This Row],[CUIT]],Lista_CUIT[#All],3,0)),"CUIT NO CARGADO") -> INSUMO | R79: =IFERROR(IF(compras_mes3[[#This Row],[CUIT]]="","-",VLOOKUP(compras_mes3[[#This Row],[CUIT]],Lista_CUIT[#All],4,0)),"CUIT NO CARGADO") -> 0
B80: 45735 | C80: 1 | D80: 4264 | E80: 5198709 | F80: 30639453738 | G80: =IFERROR(IF(compras_mes3[[#This Row],[CUIT]]="","-",VLOOKUP(compras_mes3[[#This Row],[CUIT]],Lista_CUIT[#All],2,0)),"CUIT NO CARGADO") -> TELECOM ARGENTINA SA | H80: 42961.16 | I80: =IF(compras_mes3[[#This Row],[NETO GRAVADO]]="","",compras_mes3[[#This Row],[NETO GRAVADO]]*0.21) -> 9021.8436 | P80: =SUM(compras_mes3[[#This Row],[NETO GRAVADO]:[Otros / No Grav.]]) -> 51983.004 | Q80: =IFERROR(IF(compras_mes3[[#This Row],[CUIT]]="","-",VLOOKUP(compras_mes3[[#This Row],[CUIT]],Lista_CUIT[#All],3,0)),"CUIT NO CARGADO") -> SERVICIO | R80: =IFERROR(IF(compras_mes3[[#This Row],[CUIT]]="","-",VLOOKUP(compras_mes3[[#This Row],[CUIT]],Lista_CUIT[#All],4,0)),"CUIT NO CARGADO") -> 0
B81: 45735 | C81: 1 | D81: 6 | E81: 56633 | F81: 30710177658 | G81: =IFERROR(IF(compras_mes3[[#This Row],[CUIT]]="","-",VLOOKUP(compras_mes3[[#This Row],[CUIT]],Lista_CUIT[#All],2,0)),"CUIT NO CARGADO") -> TARGET MEDICAL SA | H81: 658080 | I81: =IF(compras_mes3[[#This Row],[NETO GRAVADO]]="","",compras_mes3[[#This Row],[NETO GRAVADO]]*0.21) -> 138196.8 | P81: =SUM(compras_mes3[[#This Row],[NETO GRAVADO]:[Otros / No Grav.]]) -> 796276.8 | Q81: =IFERROR(IF(compras_mes3[[#This Row],[CUIT]]="","-",VLOOKUP(compras_mes3[[#This Row],[CUIT]],Lista_CUIT[#All],3,0)),"CUIT NO CARGADO") -> INSUMO | R81: =IFERROR(IF(compras_mes3[[#This Row],[CUIT]]="","-",VLOOKUP(compras_mes3[[#This Row],[CUIT]],Lista_CUIT[#All],4,0)),"CUIT NO CARGADO") -> 0
B82: 45736 | C82: 1 | D82: 2 | E82: 35 | F82: 27243660535 | G82: =IFERROR(IF(compras_mes3[[#This Row],[CUIT]]="","-",VLOOKUP(compras_mes3[[#This Row],[CUIT]],Lista_CUIT[#All],2,0)),"CUIT NO CARGADO") -> BARD MARISA SILVIA | H82: 414537 | I82: =IF(compras_mes3[[#This Row],[NETO GRAVADO]]="","",compras_mes3[[#This Row],[NETO GRAVADO]]*0.21) -> 87052.77 | P82: =SUM(compras_mes3[[#This Row],[NETO GRAVADO]:[Otros / No Grav.]]) -> 501589.77 | Q82: =IFERROR(IF(compras_mes3[[#This Row],[CUIT]]="","-",VLOOKUP(compras_mes3[[#This Row],[CUIT]],Lista_CUIT[#All],3,0)),"CUIT NO CARGADO") -> Insumos | R82: =IFERROR(IF(compras_mes3[[#This Row],[CUIT]]="","-",VLOOKUP(compras_mes3[[#This Row],[CUIT]],Lista_CUIT[#All],4,0)),"CUIT NO CARGADO") -> 0
B83: 45736 | C83: 1 | D83: 2 | E83: 1161 | F83: 20272865869 | G83: =IFERROR(IF(compras_mes3[[#This Row],[CUIT]]="","-",VLOOKUP(compras_mes3[[#This Row],[CUIT]],Lista_CUIT[#All],2,0)),"CUIT NO CARGADO") -> DI FEO MARTIN EZEQUIEL | H83: 78550 | I83: =IF(compras_mes3[[#This Row],[NETO GRAVADO]]="","",compras_mes3[[#This Row],[NETO GRAVADO]]*0.21) -> 16495.5 | P83: =SUM(compras_mes3[[#This Row],[NETO GRAVADO]:[Otros / No Grav.]]) -> 95045.5 | Q83: =IFERROR(IF(compras_mes3[[#This Row],[CUIT]]="","-",VLOOKUP(compras_mes3[[#This Row],[CUIT]],Lista_CUIT[#All],3,0)),"CUIT NO CARGADO") -> INSUMOS | R83: =IFERROR(IF(compras_mes3[[#This Row],[CUIT]]="","-",VLOOKUP(compras_mes3[[#This Row],[CUIT]],Lista_CUIT[#All],4,0)),"CUIT NO CARGADO") -> 0
B84: 45737 | C84: 1 | D84: 10 | E84: 32746 | F84: 20373457796 | G84: =IFERROR(IF(compras_mes3[[#This Row],[CUIT]]="","-",VLOOKUP(compras_mes3[[#This Row],[CUIT]],Lista_CUIT[#All],2,0)),"CUIT NO CARGADO") -> ONETO TOMAS AUGUSTO | H84: 18619.83 | I84: =IF(compras_mes3[[#This Row],[NETO GRAVADO]]="","",compras_mes3[[#This Row],[NETO GRAVADO]]*0.21) -> 3910.1643 | P84: =SUM(compras_mes3[[#This Row],[NETO GRAVADO]:[Otros / No Grav.]]) -> 22529.994 | Q84: =IFERROR(IF(compras_mes3[[#This Row],[CUIT]]="","-",VLOOKUP(compras_mes3[[#This Row],[CUIT]],Lista_CUIT[#All],3,0)),"CUIT NO CARGADO") -> Papeleria | R84: =IFERROR(IF(compras_mes3[[#This Row],[CUIT]]="","-",VLOOKUP(compras_mes3[[#This Row],[CUIT]],Lista_CUIT[#All],4,0)),"CUIT NO CARGADO") -> 0
B85: 45737 | C85: 1 | D85: 13 | E85: 84834 | F85: 30709256420 | G85: =IFERROR(IF(compras_mes3[[#This Row],[CUIT]]="","-",VLOOKUP(compras_mes3[[#This Row],[CUIT]],Lista_CUIT[#All],2,0)),"CUIT NO CARGADO") -> N.G.A. SRL | H85: 4704.55 | I85: =IF(compras_mes3[[#This Row],[NETO GRAVADO]]="","",compras_mes3[[#This Row],[NETO GRAVADO]]*0.21) -> 987.9555 | P85: =SUM(compras_mes3[[#This Row],[NETO GRAVADO]:[Otros / No Grav.]]) -> 5692.5055 | Q85: =IFERROR(IF(compras_mes3[[#This Row],[CUIT]]="","-",VLOOKUP(compras_mes3[[#This Row],[CUIT]],Lista_CUIT[#All],3,0)),"CUIT NO CARGADO") -> Gastos Varios | R85: =IFERROR(IF(compras_mes3[[#This Row],[CUIT]]="","-",VLOOKUP(compras_mes3[[#This Row],[CUIT]],Lista_CUIT[#All],4,0)),"CUIT NO CARGADO") -> 0
B86: 45737 | C86: 1 | D86: 13 | E86: 84832 | F86: 30709256420 | G86: =IFERROR(IF(compras_mes3[[#This Row],[CUIT]]="","-",VLOOKUP(compras_mes3[[#This Row],[CUIT]],Lista_CUIT[#All],2,0)),"CUIT NO CARGADO") -> N.G.A. SRL | H86: 4485.98 | I86: =IF(compras_mes3[[#This Row],[NETO GRAVADO]]="","",compras_mes3[[#This Row],[NETO GRAVADO]]*0.21) -> 942.0558 | P86: =SUM(compras_mes3[[#This Row],[NETO GRAVADO]:[Otros / No Grav.]]) -> 5428.0358 | Q86: =IFERROR(IF(compras_mes3[[#This Row],[CUIT]]="","-",VLOOKUP(compras_mes3[[#This Row],[CUIT]],Lista_CUIT[#All],3,0)),"CUIT NO CARGADO") -> Gastos Varios | R86: =IFERROR(IF(compras_mes3[[#This Row],[CUIT]]="","-",VLOOKUP(compras_mes3[[#This Row],[CUIT]],Lista_CUIT[#All],4,0)),"CUIT NO CARGADO") -> 0
B87: 45737 | C87: 1 | D87: 40 | E87: 1480 | F87: 30711091552 | G87: =IFERROR(IF(compras_mes3[[#This Row],[CUIT]]="","-",VLOOKUP(compras_mes3[[#This Row],[CUIT]],Lista_CUIT[#All],2,0)),"CUIT NO CARGADO") -> BIGBOX S.A. | H87: 70247.93 | I87: =IF(compras_mes3[[#This Row],[NETO GRAVADO]]="","",compras_mes3[[#This Row],[NETO GRAVADO]]*0.21) -> 14752.065 | P87: =SUM(compras_mes3[[#This Row],[NETO GRAVADO]:[Otros / No Grav.]]) -> 84999.995 | Q87: =IFERROR(IF(compras_mes3[[#This Row],[CUIT]]="","-",VLOOKUP(compras_mes3[[#This Row],[CUIT]],Lista_CUIT[#All],3,0)),"CUIT NO CARGADO") -> INSUMO | R87: =IFERROR(IF(compras_mes3[[#This Row],[CUIT]]="","-",VLOOKUP(compras_mes3[[#This Row],[CUIT]],Lista_CUIT[#All],4,0)),"CUIT NO CARGADO") -> 0
B88: 45737 | C88: 1 | D88: 8 | E88: 42491 | F88: 30709953482 | G88: =IFERROR(IF(compras_mes3[[#This Row],[CUIT]]="","-",VLOOKUP(compras_mes3[[#This Row],[CUIT]],Lista_CUIT[#All],2,0)),"CUIT NO CARGADO") -> HONRE SA | H88: 1532.24 | I88: =IF(compras_mes3[[#This Row],[NETO GRAVADO]]="","",compras_mes3[[#This Row],[NETO GRAVADO]]*0.21) -> 321.7704 | P88: =SUM(compras_mes3[[#This Row],[NETO GRAVADO]:[Otros / No Grav.]]) -> 1854.0104 | Q88: =IFERROR(IF(compras_mes3[[#This Row],[CUIT]]="","-",VLOOKUP(compras_mes3[[#This Row],[CUIT]],Lista_CUIT[#All],3,0)),"CUIT NO CARGADO") -> Gastos Varios | R88: =IFERROR(IF(compras_mes3[[#This Row],[CUIT]]="","-",VLOOKUP(compras_mes3[[#This Row],[CUIT]],Lista_CUIT[#All],4,0)),"CUIT NO CARGADO") -> 0
B89: 45737 | C89: 1 | D89: 700 | E89: 2340948 | F89: 30715804812 | G89: =IFERROR(IF(compras_mes3[[#This Row],[CUIT]]="","-",VLOOKUP(compras_mes3[[#This Row],[CUIT]],Lista_CUIT[#All],2,0)),"CUIT NO CARGADO") -> CORREDORES VIALES SOCIEDAD ANONIMA | H89: 8943.84 | I89: =IF(compras_mes3[[#This Row],[NETO GRAVADO]]="","",compras_mes3[[#This Row],[NETO GRAVADO]]*0.21) -> 1878.2064 | P89: =SUM(compras_mes3[[#This Row],[NETO GRAVADO]:[Otros / No Grav.]]) -> 10822.046 | Q89: =IFERROR(IF(compras_mes3[[#This Row],[CUIT]]="","-",VLOOKUP(compras_mes3[[#This Row],[CUIT]],Lista_CUIT[#All],3,0)),"CUIT NO CARGADO") -> Autopista | R89: =IFERROR(IF(compras_mes3[[#This Row],[CUIT]]="","-",VLOOKUP(compras_mes3[[#This Row],[CUIT]],Lista_CUIT[#All],4,0)),"CUIT NO CARGADO") -> 0
B90: 45737 | C90: 1 | D90: 36 | E90: 57170 | F90: 30714769290 | G90: =IFERROR(IF(compras_mes3[[#This Row],[CUIT]]="","-",VLOOKUP(compras_mes3[[#This Row],[CUIT]],Lista_CUIT[#All],2,0)),"CUIT NO CARGADO") -> GOLONOR SA | H90: 6609.92 | I90: =IF(compras_mes3[[#This Row],[NETO GRAVADO]]="","",compras_mes3[[#This Row],[NETO GRAVADO]]*0.21) -> 1388.0832 | P90: =SUM(compras_mes3[[#This Row],[NETO GRAVADO]:[Otros / No Grav.]]) -> 7998.0032 | Q90: =IFERROR(IF(compras_mes3[[#This Row],[CUIT]]="","-",VLOOKUP(compras_mes3[[#This Row],[CUIT]],Lista_CUIT[#All],3,0)),"CUIT NO CARGADO") -> Gastos Varios | R90: =IFERROR(IF(compras_mes3[[#This Row],[CUIT]]="","-",VLOOKUP(compras_mes3[[#This Row],[CUIT]],Lista_CUIT[#All],4,0)),"CUIT NO CARGADO") -> 0
... B117: 45730 | C117: 3 | D117: 2 | E117: 476 | F117: 30714331082 | G117: =IFERROR(IF(compras_mes3[[#This Row],[CUIT]]="","-",VLOOKUP(compras_mes3[[#This Row],[CUIT]],Lista_CUIT[#All],2,0)),"CUIT NO CARGADO") -> ORTOPEDIA CASA ESCALADA SRL | H117: -423275.07 | I117: =IF(compras_mes3[[#This Row],[NETO GRAVADO]]="","",compras_mes3[[#This Row],[NETO GRAVADO]]*0.21) -> -88887.765 | P117: =SUM(compras_mes3[[#This Row],[NETO GRAVADO]:[Otros / No Grav.]]) -> -512162.83 | Q117: =IFERROR(IF(compras_mes3[[#This Row],[CUIT]]="","-",VLOOKUP(compras_mes3[[#This Row],[CUIT]],Lista_CUIT[#All],3,0)),"CUIT NO CARGADO") -> INSUMO | R117: =IFERROR(IF(compras_mes3[[#This Row],[CUIT]]="","-",VLOOKUP(compras_mes3[[#This Row],[CUIT]],Lista_CUIT[#All],4,0)),"CUIT NO CARGADO") -> 0
B118: 45734 | C118: 3 | D118: 7 | E118: 1375 | F118: 30709214078 | G118: =IFERROR(IF(compras_mes3[[#This Row],[CUIT]]="","-",VLOOKUP(compras_mes3[[#This Row],[CUIT]],Lista_CUIT[#All],2,0)),"CUIT NO CARGADO") -> REHAVITA S.A | H118: -250800 | K118: =compras_mes3[[#This Row],[NETO GRAVADO]]*10.5/100 -> -26334 | P118: =SUM(compras_mes3[[#This Row],[NETO GRAVADO]:[Otros / No Grav.]]) -> -277134 | Q118: =IFERROR(IF(compras_mes3[[#This Row],[CUIT]]="","-",VLOOKUP(compras_mes3[[#This Row],[CUIT]],Lista_CUIT[#All],3,0)),"CUIT NO CARGADO") -> INSUMO | R118: =IFERROR(IF(compras_mes3[[#This Row],[CUIT]]="","-",VLOOKUP(compras_mes3[[#This Row],[CUIT]],Lista_CUIT[#All],4,0)),"CUIT NO CARGADO") -> 0
B119: 45737 | C119: 3 | D119: 36 | E119: 5376 | F119: 30714769290 | G119: =IFERROR(IF(compras_mes3[[#This Row],[CUIT]]="","-",VLOOKUP(compras_mes3[[#This Row],[CUIT]],Lista_CUIT[#All],2,0)),"CUIT NO CARGADO") -> GOLONOR SA | H119: -6609.92 | I119: =IF(compras_mes3[[#This Row],[NETO GRAVADO]]="","",compras_mes3[[#This Row],[NETO GRAVADO]]*0.21) -> -1388.0832 | P119: =SUM(compras_mes3[[#This Row],[NETO GRAVADO]:[Otros / No Grav.]]) -> -7998.0032 | Q119: =IFERROR(IF(compras_mes3[[#This Row],[CUIT]]="","-",VLOOKUP(compras_mes3[[#This Row],[CUIT]],Lista_CUIT[#All],3,0)),"CUIT NO CARGADO") -> Gastos Varios | R119: =IFERROR(IF(compras_mes3[[#This Row],[CUIT]]="","-",VLOOKUP(compras_mes3[[#This Row],[CUIT]],Lista_CUIT[#All],4,0)),"CUIT NO CARGADO") -> 0
B120: Total | H120: =SUBTOTAL(109,compras_mes3[NETO GRAVADO]) -> 22652156 | I120: =SUBTOTAL(109,compras_mes3[IVA 21 %]) -> 4656788.1 | J120: =SUBTOTAL(109,compras_mes3[IVA 27%]) -> 39818.952 | K120: =SUBTOTAL(109,compras_mes3[IVA 10,5%]) -> 32381.62 | L120: =SUBTOTAL(109,compras_mes3[PERC. IVA]) -> 133.46 | M120: =SUBTOTAL(109,compras_mes3[PERC IIBB BS AS]) -> 0 | N120: =SUBTOTAL(109,compras_mes3[PERC. IIBB CABA]) -> 0 | O120: =SUBTOTAL(109,compras_mes3[Otros / No Grav.]) -> 26697.88 | P120: =SUBTOTAL(109,compras_mes3[TOTAL]) -> 27407976
F124: 30500006613
D125: LIQUIDACION EXTRACTOS BANCARIOS-TARJETAS
D126: FECHA | E126: NRO CPTE | F126: BANCO | G126: NETO | H126: IVA 21% | I126: IVA 10,5% | J126: RET IIBB CABA | K126: PERC IVA | L126: PERC IIBB | M126: TOTAL
D127: 45747 | E127: 566718388 | F127: CREDICOOP | G127: 31551 | H127: =extracto_banco_mes3[[#This Row],[NETO]]*0.21 -> 6625.71 | K127: 870 | L127: 1080 | M127: =extracto_banco_mes3[[#This Row],[PERC IIBB]]+extracto_banco_mes3[[#This Row],[PERC IVA]]+extracto_banco_mes3[[#This Row],[NETO]]+extracto_banco_mes3[[#This Row],[IVA 10,5%]]+extracto_banco_mes3[[#This Row],[IVA 21%]] -> 40126.71
D128: 45747 | E128: 119007808 | F128: PATAGONIA | G128: 30050 | H128: =extracto_banco_mes3[[#This Row],[NETO]]*0.21 -> 6310.5 | K128: 900 | L128: 1200 | M128: =extracto_banco_mes3[[#This Row],[PERC IIBB]]+extracto_banco_mes3[[#This Row],[PERC IVA]]+extracto_banco_mes3[[#This Row],[NETO]]+extracto_banco_mes3[[#This Row],[IVA 10,5%]]+extracto_banco_mes3[[#This Row],[IVA 21%]] -> 38460.5
F129: CREDICOOP MAESRTRO | H129: =extracto_banco_mes3[[#This Row],[NETO]]*0.21 -> 0 | M129: =extracto_banco_mes3[[#This Row],[PERC IIBB]]+extracto_banco_mes3[[#This Row],[PERC IVA]]+extracto_banco_mes3[[#This Row],[NETO]]+extracto_banco_mes3[[#This Row],[IVA 10,5%]]+extracto_banco_mes3[[#This Row],[IVA 21%]] -> 0
F130: CREDICOOP MASTER | H130: =extracto_banco_mes3[[#This Row],[NETO]]*0.21 -> 0 | M130: =extracto_banco_mes3[[#This Row],[PERC IIBB]]+extracto_banco_mes3[[#This Row],[PERC IVA]]+extracto_banco_mes3[[#This Row],[NETO]]+extracto_banco_mes3[[#This Row],[IVA 10,5%]]+extracto_banco_mes3[[#This Row],[IVA 21%]] -> 0
D131: Total | G131: =SUBTOTAL(109,extracto_banco_mes3[NETO]) -> 61601 | H131: =SUBTOTAL(109,extracto_banco_mes3[IVA 21%]) -> 12936.21 | I131: =SUBTOTAL(109,extracto_banco_mes3[IVA 10,5%]) -> 0 | J131: =SUBTOTAL(109,extracto_banco_mes3[RET IIBB CABA]) -> 0 | K131: =SUBTOTAL(109,extracto_banco_mes3[PERC IVA]) -> 1770 | L131: =SUBTOTAL(109,extracto_banco_mes3[PERC IIBB]) -> 2280
D134: FACTURAS C
D135: FECHA | E135: PTO VTA | F135: FC Nº | G135: CUIT | H135: RAZON SOCIAL | I135: TOTAL | J135: TIPO DE GASTO | K135: Provincia
D136: 45719 | E136: 2 | F136: 338 | G136: 27265832178 | H136: =IFERROR(IF(factura_c_mes3[[#This Row],[CUIT]]="","-",VLOOKUP(factura_c_mes3[[#This Row],[CUIT]],Lista_CUIT[#All],2,0)),"CUIT NO CARGADO") -> BLASCO MARIA GUADALUPE | I136: 3200000 | J136: =IFERROR(IF(factura_c_mes3[[#This Row],[CUIT]]="","-",VLOOKUP(factura_c_mes3[[#This Row],[CUIT]],Lista_CUIT[#All],3,0)),"CUIT NO CARGADO") -> PROVEEDOR | K136: =IFERROR(IF(factura_c_mes3[[#This Row],[CUIT]]="","-",VLOOKUP(factura_c_mes3[[#This Row],[CUIT]],Lista_CUIT[#All],4,0)),"CUIT NO CARGADO") -> 0
D137: 45721 | E137: 1 | F137: 78 | G137: 23281233084 | H137: =IFERROR(IF(factura_c_mes3[[#This Row],[CUIT]]="","-",VLOOKUP(factura_c_mes3[[#This Row],[CUIT]],Lista_CUIT[#All],2,0)),"CUIT NO CARGADO") -> DRUETTA ANDREA MARIEL | I137: 270000 | J137: =IFERROR(IF(factura_c_mes3[[#This Row],[CUIT]]="","-",VLOOKUP(factura_c_mes3[[#This Row],[CUIT]],Lista_CUIT[#All],3,0)),"CUIT NO CARGADO") -> TECNICO | K137: =IFERROR(IF(factura_c_mes3[[#This Row],[CUIT]]="","-",VLOOKUP(factura_c_mes3[[#This Row],[CUIT]],Lista_CUIT[#All],4,0)),"CUIT NO CARGADO") -> 0
D138: 45721 | E138: 3 | F138: 938 | G138: 20086277523 | H138: =IFERROR(IF(factura_c_mes3[[#This Row],[CUIT]]="","-",VLOOKUP(factura_c_mes3[[#This Row],[CUIT]],Lista_CUIT[#All],2,0)),"CUIT NO CARGADO") -> BOTINDARI JUAN CARLOS | I138: 275500 | J138: =IFERROR(IF(factura_c_mes3[[#This Row],[CUIT]]="","-",VLOOKUP(factura_c_mes3[[#This Row],[CUIT]],Lista_CUIT[#All],3,0)),"CUIT NO CARGADO") -> HONORARIOS | K138: =IFERROR(IF(factura_c_mes3[[#This Row],[CUIT]]="","-",VLOOKUP(factura_c_mes3[[#This Row],[CUIT]],Lista_CUIT[#All],4,0)),"CUIT NO CARGADO") -> 0
D139: 45723 | E139: 2 | F139: 123 | G139: 27315710508 | H139: =IFERROR(IF(factura_c_mes3[[#This Row],[CUIT]]="","-",VLOOKUP(factura_c_mes3[[#This Row],[CUIT]],Lista_CUIT[#All],2,0)),"CUIT NO CARGADO") -> RIVERO GABRIELA ROCIO | I139: 43200 | J139: =IFERROR(IF(factura_c_mes3[[#This Row],[CUIT]]="","-",VLOOKUP(factura_c_mes3[[#This Row],[CUIT]],Lista_CUIT[#All],3,0)),"CUIT NO CARGADO") -> Serv. Informaticos | K139: =IFERROR(IF(factura_c_mes3[[#This Row],[CUIT]]="","-",VLOOKUP(factura_c_mes3[[#This Row],[CUIT]],Lista_CUIT[#All],4,0)),"CUIT NO CARGADO") -> 0
D140: 45727 | E140: 1 | F140: 12 | G140: 27443612713 | H140: =IFERROR(IF(factura_c_mes3[[#This Row],[CUIT]]="","-",VLOOKUP(factura_c_mes3[[#This Row],[CUIT]],Lista_CUIT[#All],2,0)),"CUIT NO CARGADO") -> MIGOYA MORIONDO SOFIA | I140: 850000 | J140: =IFERROR(IF(factura_c_mes3[[#This Row],[CUIT]]="","-",VLOOKUP(factura_c_mes3[[#This Row],[CUIT]],Lista_CUIT[#All],3,0)),"CUIT NO CARGADO") -> GTOS ADMINISTRATIVOS | K140: =IFERROR(IF(factura_c_mes3[[#This Row],[CUIT]]="","-",VLOOKUP(factura_c_mes3[[#This Row],[CUIT]],Lista_CUIT[#All],4,0)),"CUIT NO CARGADO") -> 0
D141: 45727 | E141: 1 | F141: 44 | G141: 20190742297 | H141: =IFERROR(IF(factura_c_mes3[[#This Row],[CUIT]]="","-",VLOOKUP(factura_c_mes3[[#This Row],[CUIT]],Lista_CUIT[#All],2,0)),"CUIT NO CARGADO") -> CHANCO VILLAVICENCIO ERNESTO ANTONIO | I141: 150000 | J141: =IFERROR(IF(factura_c_mes3[[#This Row],[CUIT]]="","-",VLOOKUP(factura_c_mes3[[#This Row],[CUIT]],Lista_CUIT[#All],3,0)),"CUIT NO CARGADO") -> GTOS ADMINISTRATIVOS | K141: =IFERROR(IF(factura_c_mes3[[#This Row],[CUIT]]="","-",VLOOKUP(factura_c_mes3[[#This Row],[CUIT]],Lista_CUIT[#All],4,0)),"CUIT NO CARGADO") -> 0
D142: 45728 | E142: 3 | F142: 2395 | G142: 20182999661 | H142: =IFERROR(IF(factura_c_mes3[[#This Row],[CUIT]]="","-",VLOOKUP(factura_c_mes3[[#This Row],[CUIT]],Lista_CUIT[#All],2,0)),"CUIT NO CARGADO") -> KLAINER ABEL JAVIER | I142: 57000 | J142: =IFERROR(IF(factura_c_mes3[[#This Row],[CUIT]]="","-",VLOOKUP(factura_c_mes3[[#This Row],[CUIT]],Lista_CUIT[#All],3,0)),"CUIT NO CARGADO") -> Gastos Varios | K142: =IFERROR(IF(factura_c_mes3[[#This Row],[CUIT]]="","-",VLOOKUP(factura_c_mes3[[#This Row],[CUIT]],Lista_CUIT[#All],4,0)),"CUIT NO CARGADO") -> 0
D143: 45728 | E143: 1 | F143: 167 | G143: 27338342840 | H143: =IFERROR(IF(factura_c_mes3[[#This Row],[CUIT]]="","-",VLOOKUP(factura_c_mes3[[#This Row],[CUIT]],Lista_CUIT[#All],2,0)),"CUIT NO CARGADO") -> CANCINO PAMELA RITA | I143: 652800 | J143: =IFERROR(IF(factura_c_mes3[[#This Row],[CUIT]]="","-",VLOOKUP(factura_c_mes3[[#This Row],[CUIT]],Lista_CUIT[#All],3,0)),"CUIT NO CARGADO") -> PROVEEDOR | K143: =IFERROR(IF(factura_c_mes3[[#This Row],[CUIT]]="","-",VLOOKUP(factura_c_mes3[[#This Row],[CUIT]],Lista_CUIT[#All],4,0)),"CUIT NO CARGADO") -> 0
D144: 45729 | E144: 5 | F144: 177 | G144: 27062343449 | H144: =IFERROR(IF(factura_c_mes3[[#This Row],[CUIT]]="","-",VLOOKUP(factura_c_mes3[[#This Row],[CUIT]],Lista_CUIT[#All],2,0)),"CUIT NO CARGADO") -> FERREIRS LILISNS INES | I144: 350000 | J144: =IFERROR(IF(factura_c_mes3[[#This Row],[CUIT]]="","-",VLOOKUP(factura_c_mes3[[#This Row],[CUIT]],Lista_CUIT[#All],3,0)),"CUIT NO CARGADO") -> FLETE | K144: =IFERROR(IF(factura_c_mes3[[#This Row],[CUIT]]="","-",VLOOKUP(factura_c_mes3[[#This Row],[CUIT]],Lista_CUIT[#All],4,0)),"CUIT NO CARGADO") -> 0
D145: 45729 | E145: 5 | F145: 176 | G145: 27062343449 | H145: =IFERROR(IF(factura_c_mes3[[#This Row],[CUIT]]="","-",VLOOKUP(factura_c_mes3[[#This Row],[CUIT]],Lista_CUIT[#All],2,0)),"CUIT NO CARGADO") -> FERREIRS LILISNS INES | I145: 250000 | J145: =IFERROR(IF(factura_c_mes3[[#This Row],[CUIT]]="","-",VLOOKUP(factura_c_mes3[[#This Row],[CUIT]],Lista_CUIT[#All],3,0)),"CUIT NO CARGADO") -> FLETE | K145: =IFERROR(IF(factura_c_mes3[[#This Row],[CUIT]]="","-",VLOOKUP(factura_c_mes3[[#This Row],[CUIT]],Lista_CUIT[#All],4,0)),"CUIT NO CARGADO") -> 0
D146: 45730 | E146: 1 | F146: 15 | G146: 20311855671 | H146: =IFERROR(IF(factura_c_mes3[[#This Row],[CUIT]]="","-",VLOOKUP(factura_c_mes3[[#This Row],[CUIT]],Lista_CUIT[#All],2,0)),"CUIT NO CARGADO") -> GUASCH HECTOR RAUL | I146: 110000 | J146: =IFERROR(IF(factura_c_mes3[[#This Row],[CUIT]]="","-",VLOOKUP(factura_c_mes3[[#This Row],[CUIT]],Lista_CUIT[#All],3,0)),"CUIT NO CARGADO") -> Insumos | K146: =IFERROR(IF(factura_c_mes3[[#This Row],[CUIT]]="","-",VLOOKUP(factura_c_mes3[[#This Row],[CUIT]],Lista_CUIT[#All],4,0)),"CUIT NO CARGADO") -> 0
D147: 45734 | E147: 1 | F147: 23 | G147: 27443612705 | H147: =IFERROR(IF(factura_c_mes3[[#This Row],[CUIT]]="","-",VLOOKUP(factura_c_mes3[[#This Row],[CUIT]],Lista_CUIT[#All],2,0)),"CUIT NO CARGADO") -> MIGOYA MORIONDO MARIA INES | I147: 900000 | J147: =IFERROR(IF(factura_c_mes3[[#This Row],[CUIT]]="","-",VLOOKUP(factura_c_mes3[[#This Row],[CUIT]],Lista_CUIT[#All],3,0)),"CUIT NO CARGADO") -> GTOS ADMINISTRATIVOS | K147: =IFERROR(IF(factura_c_mes3[[#This Row],[CUIT]]="","-",VLOOKUP(factura_c_mes3[[#This Row],[CUIT]],Lista_CUIT[#All],4,0)),"CUIT NO CARGADO") -> 0
