Workbook
Name partner_id: Configuracion!$B$332

Sheet Configuracion
F1: CUIT | G1: Cargar sin guiones
F2: RAZON SOCIAL | G2: Maximo 30 caracteres
A3: CUIT | B3: RAZON SOCIAL | C3: DETALLE | F3: DETALLE | G3: Cargar tipo de gasto
A4: 30628205090 | B4: ALBAMIE SA | C4: CLIENTE
A5: 30711678820 | B5: 2PSI INGENIERIA SRL | C5: PROVEEDOR
A6: 33716367539 | B6: 3PI S.A.S. | C6: PROVEEDOR
A7: 30660373108 | B7: ABC SA | C7: VARIOS
A8: 20300210881 | B8: ABOY DIEGO OSCAR | C8: PROVEEDOR
A9: 27229910782 | B9: ABUGAUCH MARIA DE LOS ANGELES | C9: PROVEEDOR
A10: 20242709897 | B10: ABUGAUCH VICTOR HUGO | C10: PROVEEDOR
A11: 20281669053 | B11: ACOSTA JAVIER GUSTAVO | C11: FLETE
A12: 20174240125 | B12: ACOSTA OSCAR ISIDRO | C12: VARIOS
A13: 30641659106 | B13: AGRISOL SA | C13: VARIOS
A14: 33709914109 | B14: ALAN COLLECTION SA | C14: VARIOS
A15: 20267161616 | B15: ALBAJARI DIEGO MARCOS | C15: VARIOS
... A155: 30537679855 | B155: ESTACION LIMA SA | C155: VARIOS
A156: 30-56864959-8 | B156: EXPRESO BISONTE SRL | C156: FLETE
A157: 30708542349 | B157: EXPRESO FORMOSA SRL | C157: FLETE
A158: 30526582884 | B158: EXPRESO MAR DEL PLATA SA | C158: FLETE
A159: 30577744579 | B159: EXPRESO TROLE SRL | C159: FLETE
A160: 30715949292 | B160: EYPAPEL SAS | C160: GASTOS VARIOS
A161: 30715980807 | B161: FABORT SRL | C161: PROVEEDOR
A162: 20359718765 | B162: FAIL ABRAHAM | C162: VARIOS
A163: 30643518364 | B163: FARMACIA DE MEDRANO SCS | C163: PROVEEDOR
A164: 30692138747 | B164: FARMACITY SA | C164: VARIOS
A165: 33712234429 | B165: FEDAGAS SA | C165: VARIOS
A166: 20353576012 | B166: FEDERICO PABLO FEOLA | C166: VARIOS
A167: 20343766441 | B167: FERNANDEZ MAURO | C167: TALLER
A168: 27062343449 | B168: FERREIRA LILIANA INES | C168: FLETE
... A570: 30661273093 | B570: OSETRA | C570: CLIENTE

Sheet Octubre 25
A1: ORTOPEDIA GEMINIS S.A. | J1: 45931
A4: LIBRO IVA COMPRAS
A6: FACTURAS A
A7: FECHA | B7: PTO VTA | C7: FAC A | D7: CUIT | E7: RAZON SOCIAL | F7: NETO | G7: IVA 21% | H7: IVA 27% | I7: IVA 10,5% | J7: P IVA | K7: IIBB CF | L7: IIBB BS | M7: NO GRAV | N7: OTROS | O7: TOTAL | P7: DETALLE
E8: =VLOOKUP(D8,Configuracion!$A$4:$C$590,2,FALSE()) -> #N/A | G8: =F8*21% -> 0 | O8: =SUM(F8:N8) -> 0 | P8: =VLOOKUP(D8,Configuracion!$A$4:$C$590,3,FALSE()) -> #N/A
E9: =VLOOKUP(D9,Configuracion!$A$4:$C$590,2,FALSE()) -> #N/A | G9: =F9*21% -> 0 | O9: =SUM(F9:N9) -> 0 | P9: =VLOOKUP(D9,Configuracion!$A$4:$C$590,3,FALSE()) -> #N/A
E10: =VLOOKUP(D10,Configuracion!$A$4:$C$590,2,FALSE()) -> #N/A | G10: =F10*21% -> 0 | O10: =SUM(F10:N10) -> 0 | P10: =VLOOKUP(D10,Configuracion!$A$4:$C$590,3,FALSE()) -> #N/A
E11: =VLOOKUP(D11,Configuracion!$A$4:$C$590,2,FALSE()) -> #N/A | G11: =F11*21% -> 0 | O11: =SUM(F11:N11) -> 0 | P11: =VLOOKUP(D11,Configuracion!$A$4:$C$590,3,FALSE()) -> #N/A
E12: =VLOOKUP(D12,Configuracion!$A$4:$C$590,2,FALSE()) -> #N/A | G12: =F12*21% -> 0 | O12: =SUM(F12:N12) -> 0 | P12: =VLOOKUP(D12,Configuracion!$A$4:$C$590,3,FALSE()) -> #N/A
E13: =VLOOKUP(D13,Configuracion!$A$4:$C$590,2,FALSE()) -> #N/A | G13: =F13*21% -> 0 | O13: =SUM(F13:N13) -> 0 | P13: =VLOOKUP(D13,Configuracion!$A$4:$C$590,3,FALSE()) -> #N/A
E14: =VLOOKUP(D14,Configuracion!$A$4:$C$590,2,FALSE()) -> #N/A | G14: =F14*21% -> 0 | O14: =SUM(F14:N14) -> 0 | P14: =VLOOKUP(D14,Configuracion!$A$4:$C$590,3,FALSE()) -> #N/A
E15: =VLOOKUP(D15,Configuracion!$A$4:$C$590,2,FALSE()) -> #N/A | G15: =F15*21% -> 0 | O15: =SUM(F15:N15) -> 0 | P15: =VLOOKUP(D15,Configuracion!$A$4:$C$590,3,FALSE()) -> #N/A
E16: =VLOOKUP(D16,Configuracion!$A$4:$C$590,2,FALSE()) -> #N/A | G16: =F16*21% -> 0 | O16: =SUM(F16:N16) -> 0 | P16: =VLOOKUP(D16,Configuracion!$A$4:$C$590,3,FALSE()) -> #N/A
E17: =VLOOKUP(D17,Configuracion!$A$4:$C$590,2,FALSE()) -> #N/A | G17: =F17*21% -> 0 | O17: =SUM(F17:N17) -> 0 | P17: =VLOOKUP(D17,Configuracion!$A$4:$C$590,3,FALSE()) -> #N/A
A18: TOTAL | F18: =SUM(F8:F17) -> 0 | G18: =SUM(G8:G17) -> 0 | H18: =SUM(H8:H17) -> 0 | I18: =SUM(I8:I17) -> 0 | J18: =SUM(J8:J17) -> 0 | K18: =SUM(K8:K17) -> 0 | L18: =SUM(L8:L17) -> 0 | M18: =SUM(M8:M17) -> 0 | ... O18: =SUM(O8:O17) -> 0
F19: IVA | G19: =G18+H18+I18 -> 0
A21: FACTURAS B/C
A22: FECHA | B22: PTO VTA | C22: FAC C | D22: CUIT | E22: RAZON SOCIAL | F22: TOTAL | G22: DETALLE
E23: =VLOOKUP(D23,Configuracion!$A$4:$C$590,2,FALSE()) -> #N/A | G23: =VLOOKUP(D23,Configuracion!$A$4:$C$590,3,FALSE()) -> #N/A
E24: =VLOOKUP(D24,Configuracion!$A$4:$C$590,2,FALSE()) -> #N/A | G24: =VLOOKUP(D24,Configuracion!$A$4:$C$590,3,FALSE()) -> #N/A
E25: =VLOOKUP(D25,Configuracion!$A$4:$C$590,2,FALSE()) -> #N/A | G25: =VLOOKUP(D25,Configuracion!$A$4:$C$590,3,FALSE()) -> #N/A
E26: =VLOOKUP(D26,Configuracion!$A$4:$C$590,2,FALSE()) -> #N/A | G26: =VLOOKUP(D26,Configuracion!$A$4:$C$590,3,FALSE()) -> #N/A
E27: =VLOOKUP(D27,Configuracion!$A$4:$C$590,2,FALSE()) -> #N/A | G27: =VLOOKUP(D27,Configuracion!$A$4:$C$590,3,FALSE()) -> #N/A
E28: =VLOOKUP(D28,Configuracion!$A$4:$C$590,2,FALSE()) -> #N/A | G28: =VLOOKUP(D28,Configuracion!$A$4:$C$590,3,FALSE()) -> #N/A
E29: =VLOOKUP(D29,Configuracion!$A$4:$C$590,2,FALSE()) -> #N/A | G29: =VLOOKUP(D29,Configuracion!$A$4:$C$590,3,FALSE()) -> #N/A
E30: =VLOOKUP(D30,Configuracion!$A$4:$C$590,2,FALSE()) -> #N/A | G30: =VLOOKUP(D30,Configuracion!$A$4:$C$590,3,FALSE()) -> #N/A
E31: =VLOOKUP(D31,Configuracion!$A$4:$C$590,2,FALSE()) -> #N/A | G31: =VLOOKUP(D31,Configuracion!$A$4:$C$590,3,FALSE()) -> #N/A
E32: =VLOOKUP(D32,Configuracion!$A$4:$C$590,2,FALSE()) -> #N/A | G32: =VLOOKUP(D32,Configuracion!$A$4:$C$590,3,FALSE()) -> #N/A
E33: =VLOOKUP(D33,Configuracion!$A$4:$C$590,2,FALSE()) -> #N/A | G33: =VLOOKUP(D33,Configuracion!$A$4:$C$590,3,FALSE()) -> #N/A
E34: =VLOOKUP(D34,Configuracion!$A$4:$C$590,2,FALSE()) -> #N/A | G34: =VLOOKUP(D34,Configuracion!$A$4:$C$590,3,FALSE()) -> #N/A
... E41: =VLOOKUP(D41,Configuracion!$A$4:$C$590,2,FALSE()) -> #N/A | G41: =VLOOKUP(D41,Configuracion!$A$4:$C$590,3,FALSE()) -> #N/A
A42: TOTAL | F42: =SUM(F23:F41) -> 0
A44: RETENCIONES
A45: FECHA | B45: COMPROBANTE NRO | D45: CUIT | E45: RAZON SOCIAL | F45: GANANCIAS | G45: IVA | H45: IIBB | I45: SUSS
A46: 45950 | B46: 92687 | D46: 30522428163 | E46: =VLOOKUP(D46,Configuracion!$A$4:$C$590,2,FALSE()) -> GALENO ARGENTINA SA | G46: 693084.55
E47: =VLOOKUP(D47,Configuracion!$A$4:$C$590,2,FALSE()) -> #N/A
E48: =VLOOKUP(D48,Configuracion!$A$4:$C$590,2,FALSE()) -> #N/A
E49: =VLOOKUP(D49,Configuracion!$A$4:$C$590,2,FALSE()) -> #N/A
E50: =VLOOKUP(D50,Configuracion!$A$4:$C$590,2,FALSE()) -> #N/A
E51: =VLOOKUP(D51,Configuracion!$A$4:$C$590,2,FALSE()) -> #N/A
E52: =VLOOKUP(D52,Configuracion!$A$4:$C$590,2,FALSE()) -> #N/A
E53: =VLOOKUP(D53,Configuracion!$A$4:$C$590,2,FALSE()) -> #N/A
E54: =VLOOKUP(D54,Configuracion!$A$4:$C$590,2,FALSE()) -> #N/A
E55: =VLOOKUP(D55,Configuracion!$A$4:$C$590,2,FALSE()) -> #N/A
E56: =VLOOKUP(D56,Configuracion!$A$4:$C$590,2,FALSE()) -> #N/A
E57: =VLOOKUP(D57,Configuracion!$A$4:$C$590,2,FALSE()) -> #N/A
E58: =VLOOKUP(D58,Configuracion!$A$4:$C$590,2,FALSE()) -> #N/A
... E78: =VLOOKUP(D78,Configuracion!$A$4:$C$590,2,FALSE()) -> #N/A
A79: TOTAL | F79: =SUM(F46:F78) -> 0 | G79: =SUM(G46:G78) -> 693084.55 | H79: =SUM(H46:H78) -> 0 | I79: =SUM(I46:I78) -> 0
A83: LIBRO IVA VENTAS
A85: FACTURA A
A86: FECHA | B86: PTO VTA | C86: NRO FC | D86: CUIT | E86: RAZON SOCIAL | F86: NETO | G86: IVA | H86: NO GRAV. | I86: TOTAL
E87: =VLOOKUP(D87,Configuracion!$A$4:$C$590,2,FALSE()) -> #N/A | G87: =F87*0.21 -> 0 | I87: =SUM(F87:H87) -> 0
E88: =VLOOKUP(D88,Configuracion!$A$4:$C$590,2,FALSE()) -> #N/A | G88: =F88*0.21 -> 0 | I88: =SUM(F88:H88) -> 0
E89: =VLOOKUP(D89,Configuracion!$A$4:$C$590,2,FALSE()) -> #N/A | G89: =F89*0.21 -> 0 | I89: =SUM(F89:H89) -> 0
E90: =VLOOKUP(D90,Configuracion!$A$4:$C$590,2,FALSE()) -> #N/A | G90: =F90*0.21 -> 0 | I90: =SUM(F90:H90) -> 0
E91: =VLOOKUP(D91,Configuracion!$A$4:$C$590,2,FALSE()) -> #N/A | G91: =F91*0.21 -> 0 | I91: =SUM(F91:H91) -> 0
E92: =VLOOKUP(D92,Configuracion!$A$4:$C$590,2,FALSE()) -> #N/A | G92: =F92*0.21 -> 0 | I92: =SUM(F92:H92) -> 0
E93: =VLOOKUP(D93,Configuracion!$A$4:$C$590,2,FALSE()) -> #N/A | G93: =F93*0.21 -> 0 | I93: =SUM(F93:H93) -> 0
E94: =VLOOKUP(D94,Configuracion!$A$4:$C$590,2,FALSE()) -> #N/A | G94: =F94*0.21 -> 0 | I94: =SUM(F94:H94) -> 0
E95: =VLOOKUP(D95,Configuracion!$A$4:$C$590,2,FALSE()) -> #N/A | G95: =F95*0.21 -> 0 | I95: =SUM(F95:H95) -> 0
A96: TOTAL | F96: =SUM(F87:F95) -> 0 | G96: =SUM(G87:G95) -> 0 | I96: =SUM(I87:I95) -> 0
A99: FACTURA B
A100: FECHA | B100: PTO VTA | C100: NRO FC | D100: CUIT | E100: RAZON SOCIAL | F100: NETO | G100: IVA | H100: TOTAL
E101: =VLOOKUP(D101,Configuracion!$A$4:$C$590,2,FALSE()) -> #N/A | F101: =H101/1.21 -> 0 | G101: =F101*0.21 -> 0
E102: =VLOOKUP(D102,Configuracion!$A$4:$C$590,2,FALSE()) -> #N/A | F102: =H102/1.21 -> 0 | G102: =F102*0.21 -> 0
E103: =VLOOKUP(D103,Configuracion!$A$4:$C$590,2,FALSE()) -> #N/A | F103: =H103/1.21 -> 0 | G103: =F103*0.21 -> 0
E104: =VLOOKUP(D104,Configuracion!$A$4:$C$590,2,FALSE()) -> #N/A | F104: =H104/1.21 -> 0 | G104: =F104*0.21 -> 0
E105: =VLOOKUP(D105,Configuracion!$A$4:$C$590,2,FALSE()) -> #N/A | F105: =H105/1.21 -> 0 | G105: =F105*0.21 -> 0
A106: TOTAL | F106: =SUM(F101:F105) -> 0 | G106: =SUM(G101:G105) -> 0 | H106: =SUM(H101:H105) -> 0

Sheet Calculo IVA
B1: ORTOPEDIA GEMINIS
A2: Calculo Iva | D2: 45931
B4: VENTAS
B5: Neto | C5: Iva | D5: Total
A6: FAC. "A" | B6: =+'Ventas 10'!D4+'Ventas 10'!D5 -> 1.3344938e+08 | C6: =+B6*0.21 -> 28024369 | D6: =+B6+C6 -> 1.6147374e+08
A7: FAC. "B" | B7: =+'Ventas 10'!D6+'Ventas 10'!D7+'Ventas 10'!D8 -> 31019426 | C7: =+B7*0.21 -> 6514079.4 | D7: =+B7+C7 -> 37533505
B8: =SUM(B6:B7) -> 1.644688e+08 | C8: =SUM(C6:C7) -> 34538448 | D8: =SUM(D6:D7) -> 1.9900725e+08
B11: COMPRAS
B12: Neto | C12: IVA | D12: Total
A13: Comprobantes / Extractos | B13: =+'Compras 10'!I177+'Compras 10'!J177+'Compras 10'!K177 -> 51535702 | C13: =+'Compras 10'!N177 -> 10623453 | D13: =+'Compras 10'!U177 -> 79402288
B16: =SUM(B13:B15) -> 51535702 | C16: =SUM(C13:C15) -> 10623453 | D16: =SUM(D13:D15) -> 79402288
A19: RETENCIONES | B19: N° Cuit | C19: Importe | D19: Nro. Retencion | E19: Fecha
A20: AFIP - No están informadas las retenciones de IVA en el sistema de AFIP
C35: =+'Octubre 25'!G79 -> 693084.55
A37: PERCEPCIONES | B37: N° Cuit | C37: Importe | D37: Nro. Retencion | E37: Fecha
C41: =SUM(C38:C40) -> 0
A43: Total Deducciociones | C43: =+C41+C35 -> 693084.55
C46: (Montos en Positivo)
A47: 1er Saldo Tecnico del Período | C47: =+C8-C16 -> 23914995
A49: Saldo Tecnico de período Anterior (a favor) | D49: (resta en el total)
A51: Saldo Neto Técnico | C51: =+C47-C49 -> 23914995
A55: Saldo L.D. del Período | C55: =+C41+C35 -> 693084.55
A57: Saldo L.D. del Período Anterior
A59: Neto S.L.D | C59: =+C55+C57 -> 693084.55
A62: I V A | C62: =+C51-C59 -> 23221911
A63: NOTA: Sin Tomar posibles Retenciones que se hayan hecho

Sheet Ventas 10
C2: Totales por Tipo de Comprobante - ARCA
D3: Base | E3: IVA | F3: Otros Imp. | G3: Total Compr.
C4: FACTURAS A | D4: 1.3832638e+08 | E4: =+D4*0.21 -> 29048540 | G4: =SUBTOTAL(9,D4:F4) -> 1.6737492e+08
C5: NC A | D5: -4877007.9 | E5: =+D5*0.21 -> -1024171.7 | G5: =SUBTOTAL(9,D5:F5) -> -5901179.5
C6: FACTURAS B | D6: 35076825 | E6: =+D6*0.21 -> 7366133.2 | G6: =SUBTOTAL(9,D6:F6) -> 42442958
C7: NC B | D7: -4057398.8 | E7: =+D7*0.21 -> -852053.74 | G7: =SUBTOTAL(9,D7:F7) -> -4909452.5
C8: ND B | E8: =+D8*0.21 -> 0 | G8: =SUBTOTAL(9,D8:F8) -> 0
D9: =SUBTOTAL(9,D4:D8) -> 1.644688e+08 | E9: =SUBTOTAL(9,E4:E8) -> 34538448 | F9: 0 | G9: =+E9+D9 -> 1.9900725e+08 | H9: =+SUBTOTAL(109,H12:H466) -> 1.644688e+08
A11: Fecha | B11: Razon Social | C11: Cuit | D11: Provincia | E11: Ciudad | F11: Condicion IVA | G11: Nro Factura | H11: Importe Neto Gravado | I11: Importe No Grav | J11: IVA2 | K11: IVA5 | L11: IVA10 | M11: IVA21 | N11: IVA27 | O11: IIBB | P11: Percepcion IVA | Q11: Otros Impuestos | R11: Total IVA | S11: Total Facturado | T11: Observaciones
A12: 01/10/2025 | B12: Galeno A.R.T. S.A. | C12: 30685228501 | D12: Ciudad de Buenos Aires | E12: SIN IDENTIFICAR | F12: EX | G12: FCB 0007-00006469 | H12: 494958.68 | I12: 0 | J12: 0 | K12: 0 | L12: 0 | M12: 103941.32 | N12: 0 | O12: 0 | P12: 0 | Q12: 0 | R12: 103941.32 | S12: 598900
A13: 01/10/2025 | B13: GIGAGLIA, MARIA LUCILA | C13: 25315045 | D13: Buenos Aires | E13: BECCAR | F13: CF | G13: FCB 0007-00006470 | H13: 18181.82 | I13: 0 | J13: 0 | K13: 0 | L13: 0 | M13: 3818.18 | N13: 0 | O13: 0 | P13: 0 | Q13: 0 | R13: 3818.18 | S13: 22000
A14: 01/10/2025 | B14: MAIZTEGUI ANDRÉS | C14: 20002428 | D14: Ciudad de Buenos Aires | E14: RECOLETA | F14: CF | G14: FCB 0007-00006471 | H14: 23140.5 | I14: 0 | J14: 0 | K14: 0 | L14: 0 | M14: 4859.5 | N14: 0 | O14: 0 | P14: 0 | Q14: 0 | R14: 4859.5 | S14: 28000
A15: 01/10/2025 | B15: AYELEN LUCIA ROLDAN | C15: 27337476398 | D15: Ciudad de Buenos Aires | E15: SIN IDENTIFICAR | F15: CF | G15: FCB 0007-00006472 | H15: 21487.6 | I15: 0 | J15: 0 | K15: 0 | L15: 0 | M15: 4512.4 | N15: 0 | O15: 0 | P15: 0 | Q15: 0 | R15: 4512.4 | S15: 26000
A16: 01/10/2025 | B16: FEDERICO DANTE BARRANCO | C16: 20400911542 | D16: Ciudad de Buenos Aires | E16: SIN IDENTIFICAR | F16: CF | G16: FCB 0005-00014481 | H16: 27272.73 | I16: 0 | J16: 0 | K16: 0 | L16: 0 | M16: 5727.27 | N16: 0 | O16: 0 | P16: 0 | Q16: 0 | R16: 5727.27 | S16: 33000
A17: 01/10/2025 | B17: CISNERO CLARA PATRICIA | C17: 23271414544 | D17: Ciudad de Buenos Aires | E17: SIN IDENTIFICAR | F17: CF | G17: FCB 0007-00006473 | H17: 42148.76 | I17: 0 | J17: 0 | K17: 0 | L17: 0 | M17: 8851.24 | N17: 0 | O17: 0 | P17: 0 | Q17: 0 | R17: 8851.24 | S17: 51000
A18: 01/10/2025 | B18: LAILA IVANA NATUCCE | C18: 27355887206 | D18: Ciudad de Buenos Aires | E18: SIN IDENTIFICAR | F18: CF | G18: FCB 0007-00006474 | H18: 18181.82 | I18: 0 | J18: 0 | K18: 0 | L18: 0 | M18: 3818.18 | N18: 0 | O18: 0 | P18: 0 | Q18: 0 | R18: 3818.18 | S18: 22000
A19: 01/10/2025 | B19: CECILIA DEL PILAR TELLO MARTEL | C19: 27951120370 | D19: Ciudad de Buenos Aires | E19: SIN IDENTIFICAR | F19: CF | G19: FCB 0007-00006475 | H19: 28925.62 | I19: 0 | J19: 0 | K19: 0 | L19: 0 | M19: 6074.38 | N19: 0 | O19: 0 | P19: 0 | Q19: 0 | R19: 6074.38 | S19: 35000
A20: 01/10/2025 | B20: . CONSUMIDOR FINAL ANÓNIMO | C20: 111 | D20: Ciudad de Buenos Aires | E20: SIN IDENTIFICAR | F20: CF | G20: FCB 0005-00014482 | H20: 14214.88 | I20: 0 | J20: 0 | K20: 0 | L20: 0 | M20: 2985.12 | N20: 0 | O20: 0 | P20: 0 | Q20: 0 | R20: 2985.12 | S20: 17200
A21: 01/10/2025 | B21: HC HOMECARE INTERNACION DOMICILIARIA S.A. | C21: 30710538014 | D21: Buenos Aires | E21: VILLA MARTELLI | F21: RI | G21: FCA 0007-00002719 | H21: 434850.24 | I21: 0 | J21: 0 | K21: 0 | L21: 0 | M21: 91318.55 | N21: 0 | O21: 0 | P21: 0 | Q21: 0 | R21: 91318.55 | S21: 526168.79
A22: 01/10/2025 | B22: . CONSUMIDOR FINAL ANÓNIMO | C22: 111 | D22: Ciudad de Buenos Aires | E22: SIN IDENTIFICAR | F22: CF | G22: FCB 0005-00014483 | H22: 26942.15 | I22: 0 | J22: 0 | K22: 0 | L22: 0 | M22: 5657.85 | N22: 0 | O22: 0 | P22: 0 | Q22: 0 | R22: 5657.85 | S22: 32600
A23: 01/10/2025 | B23: . CONSUMIDOR FINAL ANÓNIMO | C23: 111 | D23: Ciudad de Buenos Aires | E23: SIN IDENTIFICAR | F23: CF | G23: FCB 0005-00014484 | H23: 18595.04 | I23: 0 | J23: 0 | K23: 0 | L23: 0 | M23: 3904.96 | N23: 0 | O23: 0 | P23: 0 | Q23: 0 | R23: 3904.96 | S23: 22500
... A123: 07/10/2025 | B123: PINO, ANA PAULA | C123: 20008996 | D123: Buenos Aires | E123: FLORIDA | F123: CF | G123: FCB 0007-00006484 | H123: 28099.17 | I123: 0 | J123: 0 | K123: 0 | L123: 0 | M123: 5900.83 | N123: 0 | O123: 0 | P123: 0 | Q123: 0 | R123: 5900.83 | S123: 34000
A124: 07/10/2025 | B124: SCHELGEL, LUIS ALBERTO | D124: Buenos Aires | E124: SIN IDENTIFICAR | F124: CF | G124: FCB 0007-00006485 | H124: 17355.37 | I124: 0 | J124: 0 | K124: 0 | L124: 0 | M124: 3644.63 | N124: 0 | O124: 0 | P124: 0 | Q124: 0 | R124: 3644.63 | S124: 21000
A125: 07/10/2025 | B125: ANA ESTELA CALVINO | C125: 27144066990 | D125: Ciudad de Buenos Aires | E125: SIN IDENTIFICAR | F125: CF | G125: FCB 0007-00006486 | H125: 28925.62 | I125: 0 | J125: 0 | K125: 0 | L125: 0 | M125: 6074.38 | N125: 0 | O125: 0 | P125: 0 | Q125: 0 | R125: 6074.38 | S125: 35000
A126: 07/10/2025 | B126: ALVAREZ MARTA OLGA | C126: 9955440 | D126: Buenos Aires | E126: RAMOS MEJIA | F126: CF | G126: FCB 0007-00006487 | H126: 8603.31 | I126: 0 | J126: 0 | K126: 0 | L126: 0 | M126: 1806.69 | N126: 0 | O126: 0 | P126: 0 | Q126: 0 | R126: 1806.69 | S126: 10410
A127: 07/10/2025 | B127: FREDA JOHANNA GISE | C127: 27337086301 | D127: Ciudad de Buenos Aires | E127: SIN IDENTIFICAR | F127: CF | G127: FCB 0007-00006488 | H127: 26033.06 | I127: 0 | J127: 0 | K127: 0 | L127: 0 | M127: 5466.94 | N127: 0 | O127: 0 | P127: 0 | Q127: 0 | R127: 5466.94 | S127: 31500
A128: 07/10/2025 | B128: JUAN ANTONIO PARRA | C128: 20149320025 | D128: Ciudad de Buenos Aires | E128: SIN IDENTIFICAR | F128: CF | G128: FCB 0007-00006489 | H128: 39669.42 | I128: 0 | J128: 0 | K128: 0 | L128: 0 | M128: 8330.58 | N128: 0 | O128: 0 | P128: 0 | Q128: 0 | R128: 8330.58 | S128: 48000
A129: 07/10/2025 | B129: BAUAB, CAROLINA | D129: Buenos Aires | E129: SIN IDENTIFICAR | F129: CF | G129: FCB 0007-00006490 | H129: 58677.69 | I129: 0 | J129: 0 | K129: 0 | L129: 0 | M129: 12322.31 | N129: 0 | O129: 0 | P129: 0 | Q129: 0 | R129: 12322.31 | S129: 71000
A130: 07/10/2025 | B130: SCHELGEL, LUIS ALBERTO | D130: Buenos Aires | E130: SIN IDENTIFICAR | F130: CF | G130: FCB 0007-00006491 | H130: 39669.42 | I130: 0 | J130: 0 | K130: 0 | L130: 0 | M130: 8330.58 | N130: 0 | O130: 0 | P130: 0 | Q130: 0 | R130: 8330.58 | S130: 48000
A131: 07/10/2025 | B131: SILVIA MONICA ROJAS | C131: 27141958807 | D131: Ciudad de Buenos Aires | E131: BALVANERA | F131: CF | G131: FCB 0007-00006492 | H131: 36363.64 | I131: 0 | J131: 0 | K131: 0 | L131: 0 | M131: 7636.36 | N131: 0 | O131: 0 | P131: 0 | Q131: 0 | R131: 7636.36 | S131: 44000
A132: 07/10/2025 | B132: AGOSTINO MIRIAM | C132: 17275405 | D132: Buenos Aires | E132: SIN IDENTIFICAR | F132: CF | G132: FCB 0007-00006493 | H132: 52066.12 | I132: 0 | J132: 0 | K132: 0 | L132: 0 | M132: 10933.88 | N132: 0 | O132: 0 | P132: 0 | Q132: 0 | R132: 10933.88 | S132: 63000
A133: 07/10/2025 | B133: CONEN SILVIA ADELA | C133: 334529 | D133: Ciudad de Buenos Aires | E133: SIN IDENTIFICAR | F133: CF | G133: FCB 0007-00006494 | H133: 37190.08 | I133: 0 | J133: 0 | K133: 0 | L133: 0 | M133: 7809.92 | N133: 0 | O133: 0 | P133: 0 | Q133: 0 | R133: 7809.92 | S133: 45000
A134: 07/10/2025 | B134: . CONSUMIDOR FINAL ANÓNIMO | C134: 111 | D134: Ciudad de Buenos Aires | E134: SIN IDENTIFICAR | F134: CF | G134: FCB 0005-00014544 | H134: 23966.94 | I134: 0 | J134: 0 | K134: 0 | L134: 0 | M134: 5033.06 | N134: 0 | O134: 0 | P134: 0 | Q134: 0 | R134: 5033.06 | S134: 29000
A135: 07/10/2025 | B135: . CONSUMIDOR FINAL ANÓNIMO | C135: 111 | D135: Ciudad de Buenos Aires | E135: SIN IDENTIFICAR | F135: CF | G135: FCB 0005-00014545 | H135: 13884.3 | I135: 0 | J135: 0 | K135: 0 | L135: 0 | M135: 2915.7 | N135: 0 | O135: 0 | P135: 0 | Q135: 0 | R135: 2915.7 | S135: 16800
A136: 07/10/2025 | B136: . CONSUMIDOR FINAL ANÓNIMO | C136: 111 | D136: Ciudad de Buenos Aires | E136: SIN IDENTIFICAR | F136: CF | G136: FCB 0005-00014546 | H136: 14380.17 | I136: 0 | J136: 0 | K136: 0 | L136: 0 | M136: 3019.83 | N136: 0 | O136: 0 | P136: 0 | Q136: 0 | R136: 3019.83 | S136: 17400
A137: 07/10/2025 | B137: MIRTA EVANGELINA OJEDA | C137: 27301702367 | D137: Ciudad de Buenos Aires | E137: SIN IDENTIFICAR | F137: CF | G137: FCB 0005-00014547 | H137: 57851.24 | I137: 0 | J137: 0 | K137: 0 | L137: 0 | M137: 12148.76 | N137: 0 | O137: 0 | P137: 0 | Q137: 0 | R137: 12148.76 | S137: 70000
A138: 07/10/2025 | B138: FERRAZIN, CAROLINA ELEONORA INES | C138: 17855620 | D138: Buenos Aires | E138: SIN IDENTIFICAR | F138: CF | G138: FCB 0007-00006495 | H138: 33057.85 | I138: 0 | J138: 0 | K138: 0 | L138: 0 | M138: 6942.15 | N138: 0 | O138: 0 | P138: 0 | Q138: 0 | R138: 6942.15 | S138: 40000
A139: 07/10/2025 | B139: VOLPI, ALBERTO JAVIER | D139: Ciudad de Buenos Aires | E139: SIN IDENTIFICAR | F139: CF | G139: FCB 0007-00006496 | H139: 66115.7 | I139: 0 | J139: 0 | K139: 0 | L139: 0 | M139: 13884.3 | N139: 0 | O139: 0 | P139: 0 | Q139: 0 | R139: 13884.3 | S139: 80000
A140: 07/10/2025 | B140: Herman Patricia | C140: 21645724 | D140: Buenos Aires | E140: PILAR | F140: CF | G140: FCB 0007-00006497 | H140: 45454.55 | I140: 0 | J140: 0 | K140: 0 | L140: 0 | M140: 9545.45 | N140: 0 | O140: 0 | P140: 0 | Q140: 0 | R140: 9545.45 | S140: 55000
A141: 07/10/2025 | B141: . CONSUMIDOR FINAL ANÓNIMO | C141: 111 | D141: Ciudad de Buenos Aires | E141: SIN IDENTIFICAR | F141: CF | G141: FCB 0005-00014548 | H141: 27851.24 | I141: 0 | J141: 0 | K141: 0 | L141: 0 | M141: 5848.76 | N141: 0 | O141: 0 | P141: 0 | Q141: 0 | R141: 5848.76 | S141: 33700
A142: 07/10/2025 | B142: DESALVO MIGUEL ANGEL | C142: 24448662 | D142: Buenos Aires | E142: RAMOS MEJIA | F142: CF | G142: FCB 0007-00006498 | H142: 24793.39 | I142: 0 | J142: 0 | K142: 0 | L142: 0 | M142: 5206.61 | N142: 0 | O142: 0 | P142: 0 | Q142: 0 | R142: 5206.61 | S142: 30000
A143: 07/10/2025 | B143: . CONSUMIDOR FINAL ANÓNIMO | C143: 111 | D143: Ciudad de Buenos Aires | E143: SIN IDENTIFICAR | F143: CF | G143: FCB 0005-00014549 | H143: 28925.62 | I143: 0 | J143: 0 | K143: 0 | L143: 0 | M143: 6074.38 | N143: 0 | O143: 0 | P143: 0 | Q143: 0 | R143: 6074.38 | S143: 35000
A144: 07/10/2025 | B144: ALEJANDRA SIFFREDI TORRES SANMARCO | C144: 5804480 | D144: Ciudad de Buenos Aires | E144: SIN IDENTIFICAR | F144: CF | G144: FCB 0007-00006499 | H144: 29752.07 | I144: 0 | J144: 0 | K144: 0 | L144: 0 | M144: 6247.93 | N144: 0 | O144: 0 | P144: 0 | Q144: 0 | R144: 6247.93 | S144: 36000
A145: 07/10/2025 | B145: . CONSUMIDOR FINAL ANÓNIMO | C145: 111 | D145: Ciudad de Buenos Aires | E145: SIN IDENTIFICAR | F145: CF | G145: FCB 0005-00014550 | H145: 26942.15 | I145: 0 | J145: 0 | K145: 0 | L145: 0 | M145: 5657.85 | N145: 0 | O145: 0 | P145: 0 | Q145: 0 | R145: 5657.85 | S145: 32600
A146: 07/10/2025 | B146: . CONSUMIDOR FINAL ANÓNIMO | C146: 111 | D146: Ciudad de Buenos Aires | E146: SIN IDENTIFICAR | F146: CF | G146: FCB 0005-00014551 | H146: 28925.62 | I146: 0 | J146: 0 | K146: 0 | L146: 0 | M146: 6074.38 | N146: 0 | O146: 0 | P146: 0 | Q146: 0 | R146: 6074.38 | S146: 35000
A147: 07/10/2025 | B147: . CONSUMIDOR FINAL ANÓNIMO | C147: 111 | D147: Ciudad de Buenos Aires | E147: SIN IDENTIFICAR | F147: CF | G147: FCB 0005-00014552 | H147: 41322.31 | I147: 0 | J147: 0 | K147: 0 | L147: 0 | M147: 8677.69 | N147: 0 | O147: 0 | P147: 0 | Q147: 0 | R147: 8677.69 | S147: 50000
A148: 07/10/2025 | B148: . CONSUMIDOR FINAL ANÓNIMO | C148: 111 | D148: Ciudad de Buenos Aires | E148: SIN IDENTIFICAR | F148: CF | G148: FCB 0005-00014553 | H148: 20661.16 | I148: 0 | J148: 0 | K148: 0 | L148: 0 | M148: 4338.84 | N148: 0 | O148: 0 | P148: 0 | Q148: 0 | R148: 4338.84 | S148: 25000
A149: 07/10/2025 | B149: ALEXIA CANDELA VERA | C149: 27415462277 | D149: Ciudad de Buenos Aires | E149: SIN IDENTIFICAR | F149: CF | G149: FCB 0007-00006500 | H149: 21487.6 | I149: 0 | J149: 0 | K149: 0 | L149: 0 | M149: 4512.4 | N149: 0 | O149: 0 | P149: 0 | Q149: 0 | R149: 4512.4 | S149: 26000
A150: 07/10/2025 | B150: . CONSUMIDOR FINAL ANÓNIMO | C150: 111 | D150: Ciudad de Buenos Aires | E150: SIN IDENTIFICAR | F150: CF | G150: FCB 0005-00014554 | H150: 24793.39 | I150: 0 | J150: 0 | K150: 0 | L150: 0 | M150: 5206.61 | N150: 0 | O150: 0 | P150: 0 | Q150: 0 | R150: 5206.61 | S150: 30000
A151: 07/10/2025 | B151: . CONSUMIDOR FINAL ANÓNIMO | C151: 111 | D151: Ciudad de Buenos Aires | E151: SIN IDENTIFICAR | F151: CF | G151: FCB 0005-00014555 | H151: 74380.17 | I151: 0 | J151: 0 | K151: 0 | L151: 0 | M151: 15619.83 | N151: 0 | O151: 0 | P151: 0 | Q151: 0 | R151: 15619.83 | S151: 90000
... A154: 07/10/2025 | B154: . CONSUMIDOR FINAL ANÓNIMO | C154: 111 | D154: Ciudad de Buenos Aires | E154: SIN IDENTIFICAR | F154: CF | G154: FCB 0005-00014558 | H154: 44628.1 | I154: 0 | J154: 0 | K154: 0 | L154: 0 | M154: 9371.9 | N154: 0 | O154: 0 | P154: 0 | Q154: 0 | R154: 9371.9 | S154: 54000
A155: 08/10/2025 | B155: DANELLI, RAQUEL | D155: Buenos Aires | E155: ITUZAINGO | F155: CF | G155: FCB 0007-00006501 | H155: 28925.62 | I155: 0 | J155: 0 | K155: 0 | L155: 0 | M155: 6074.38 | N155: 0 | O155: 0 | P155: 0 | Q155: 0 | R155: 6074.38 | S155: 35000
A156: 08/10/2025 | B156: . CONSUMIDOR FINAL ANÓNIMO | C156: 111 | D156: Ciudad de Buenos Aires | E156: SIN IDENTIFICAR | F156: CF | G156: FCB 0005-00014560 | H156: 9917.36 | I156: 0 | J156: 0 | K156: 0 | L156: 0 | M156: 2082.64 | N156: 0 | O156: 0 | P156: 0 | Q156: 0 | R156: 2082.64 | S156: 12000
A157: 08/10/2025 | B157: . CONSUMIDOR FINAL ANÓNIMO | C157: 111 | D157: Ciudad de Buenos Aires | E157: SIN IDENTIFICAR | F157: CF | G157: FCB 0005-00014561 | H157: 31818.18 | I157: 0 | J157: 0 | K157: 0 | L157: 0 | M157: 6681.82 | N157: 0 | O157: 0 | P157: 0 | Q157: 0 | R157: 6681.82 | S157: 38500
A158: 08/10/2025 | B158: . CONSUMIDOR FINAL ANÓNIMO | C158: 111 | D158: Ciudad de Buenos Aires | E158: SIN IDENTIFICAR | F158: CF | G158: FCB 0005-00014562 | H158: 18595.04 | I158: 0 | J158: 0 | K158: 0 | L158: 0 | M158: 3904.96 | N158: 0 | O158: 0 | P158: 0 | Q158: 0 | R158: 3904.96 | S158: 22500
A159: 08/10/2025 | B159: . CONSUMIDOR FINAL ANÓNIMO | C159: 111 | D159: Ciudad de Buenos Aires | E159: SIN IDENTIFICAR | F159: CF | G159: FCB 0005-00014563 | H159: 57851.24 | I159: 0 | J159: 0 | K159: 0 | L159: 0 | M159: 12148.76 | N159: 0 | O159: 0 | P159: 0 | Q159: 0 | R159: 12148.76 | S159: 70000
A160: 08/10/2025 | B160: . CONSUMIDOR FINAL ANÓNIMO | C160: 111 | D160: Ciudad de Buenos Aires | E160: SIN IDENTIFICAR | F160: CF | G160: FCB 0005-00014564 | H160: 23140.5 | I160: 0 | J160: 0 | K160: 0 | L160: 0 | M160: 4859.5 | N160: 0 | O160: 0 | P160: 0 | Q160: 0 | R160: 4859.5 | S160: 28000
A161: 08/10/2025 | B161: . CONSUMIDOR FINAL ANÓNIMO | C161: 111 | D161: Ciudad de Buenos Aires | E161: SIN IDENTIFICAR | F161: CF | G161: FCB 0005-00014565 | H161: 28925.62 | I161: 0 | J161: 0 | K161: 0 | L161: 0 | M161: 6074.38 | N161: 0 | O161: 0 | P161: 0 | Q161: 0 | R161: 6074.38 | S161: 35000
A162: 08/10/2025 | B162: MAURO SEBASTIAN BELLUCCI | C162: 20304445093 | D162: Buenos Aires | E162: CIUDADELA | F162: CF | G162: FCB 0005-00014566 | H162: 27520.66 | I162: 0 | J162: 0 | K162: 0 | L162: 0 | M162: 5779.34 | N162: 0 | O162: 0 | P162: 0 | Q162: 0 | R162: 5779.34 | S162: 33300
A163: 08/10/2025 | B163: . CONSUMIDOR FINAL ANÓNIMO | C163: 111 | D163: Ciudad de Buenos Aires | E163: SIN IDENTIFICAR | F163: CF | G163: FCB 0005-00014567 | H163: 18595.04 | I163: 0 | J163: 0 | K163: 0 | L163: 0 | M163: 3904.96 | N163: 0 | O163: 0 | P163: 0 | Q163: 0 | R163: 3904.96 | S163: 22500
A164: 08/10/2025 | B164: . CONSUMIDOR FINAL ANÓNIMO | C164: 111 | D164: Ciudad de Buenos Aires | E164: SIN IDENTIFICAR | F164: CF | G164: FCB 0005-00014568 | H164: 14876.03 | I164: 0 | J164: 0 | K164: 0 | L164: 0 | M164: 3123.97 | N164: 0 | O164: 0 | P164: 0 | Q164: 0 | R164: 3123.97 | S164: 18000
A165: 08/10/2025 | B165: . CONSUMIDOR FINAL ANÓNIMO | C165: 111 | D165: Ciudad de Buenos Aires | E165: SIN IDENTIFICAR | F165: CF | G165: FCB 0005-00014569 | H165: 3305.79 | I165: 0 | J165: 0 | K165: 0 | L165: 0 | M165: 694.21 | N165: 0 | O165: 0 | P165: 0 | Q165: 0 | R165: 694.21 | S165: 4000
A166: 08/10/2025 | B166: . CONSUMIDOR FINAL ANÓNIMO | C166: 111 | D166: Ciudad de Buenos Aires | E166: SIN IDENTIFICAR | F166: CF | G166: FCB 0005-00014570 | H166: 16528.93 | I166: 0 | J166: 0 | K166: 0 | L166: 0 | M166: 3471.07 | N166: 0 | O166: 0 | P166: 0 | Q166: 0 | R166: 3471.07 | S166: 20000
A167: 08/10/2025 | B167: . CONSUMIDOR FINAL ANÓNIMO | C167: 111 | D167: Ciudad de Buenos Aires | E167: SIN IDENTIFICAR | F167: CF | G167: FCB 0005-00014571 | H167: 14049.59 | I167: 0 | J167: 0 | K167: 0 | L167: 0 | M167: 2950.41 | N167: 0 | O167: 0 | P167: 0 | Q167: 0 | R167: 2950.41 | S167: 17000
... A207: 13/10/2025 | B207: LEONARDO EZEQUIEL BORDON | C207: 20323111813 | D207: Ciudad de Buenos Aires | E207: SIN IDENTIFICAR | F207: CF | G207: FCB 0007-00006513 | H207: 20661.16 | I207: 0 | J207: 0 | K207: 0 | L207: 0 | M207: 4338.84 | N207: 0 | O207: 0 | P207: 0 | Q207: 0 | R207: 4338.84 | S207: 25000
A208: 13/10/2025 | B208: DORFMAN SANDRA | D208: Ciudad de Buenos Aires | E208: SIN IDENTIFICAR | F208: CF | G208: FCB 0007-00006514 | H208: 61983.47 | I208: 0 | J208: 0 | K208: 0 | L208: 0 | M208: 13016.53 | N208: 0 | O208: 0 | P208: 0 | Q208: 0 | R208: 13016.53 | S208: 75000
A209: 13/10/2025 | B209: SILVINA ALEJANDRA PEZZANO DE LUCA | C209: 27205676800 | D209: Ciudad de Buenos Aires | E209: SIN IDENTIFICAR | F209: CF | G209: FCB 0007-00006515 | H209: 28925.62 | I209: 0 | J209: 0 | K209: 0 | L209: 0 | M209: 6074.38 | N209: 0 | O209: 0 | P209: 0 | Q209: 0 | R209: 6074.38 | S209: 35000
A210: 13/10/2025 | B210: ALDO EUGENIO ARLANDI | C210: 20043763483 | D210: Ciudad de Buenos Aires | E210: SIN IDENTIFICAR | F210: CF | G210: FCB 0007-00006516 | H210: 50413.22 | I210: 0 | J210: 0 | K210: 0 | L210: 0 | M210: 10586.78 | N210: 0 | O210: 0 | P210: 0 | Q210: 0 | R210: 10586.78 | S210: 61000
A211: 13/10/2025 | B211: . CONSUMIDOR FINAL ANÓNIMO | C211: 111 | D211: Ciudad de Buenos Aires | E211: SIN IDENTIFICAR | F211: CF | G211: FCB 0005-00014592 | H211: 94876.03 | I211: 0 | J211: 0 | K211: 0 | L211: 0 | M211: 19923.97 | N211: 0 | O211: 0 | P211: 0 | Q211: 0 | R211: 19923.97 | S211: 114800
A212: 13/10/2025 | B212: . CONSUMIDOR FINAL ANÓNIMO | C212: 111 | D212: Ciudad de Buenos Aires | E212: SIN IDENTIFICAR | F212: CF | G212: FCB 0005-00014593 | H212: 14049.59 | I212: 0 | J212: 0 | K212: 0 | L212: 0 | M212: 2950.41 | N212: 0 | O212: 0 | P212: 0 | Q212: 0 | R212: 2950.41 | S212: 17000
A213: 13/10/2025 | B213: . CONSUMIDOR FINAL ANÓNIMO | C213: 111 | D213: Ciudad de Buenos Aires | E213: SIN IDENTIFICAR | F213: CF | G213: FCB 0005-00014594 | H213: 20413.22 | I213: 0 | J213: 0 | K213: 0 | L213: 0 | M213: 4286.78 | N213: 0 | O213: 0 | P213: 0 | Q213: 0 | R213: 4286.78 | S213: 24700
A214: 13/10/2025 | B214: . CONSUMIDOR FINAL ANÓNIMO | C214: 111 | D214: Ciudad de Buenos Aires | E214: SIN IDENTIFICAR | F214: CF | G214: FCB 0005-00014595 | H214: 28925.62 | I214: 0 | J214: 0 | K214: 0 | L214: 0 | M214: 6074.38 | N214: 0 | O214: 0 | P214: 0 | Q214: 0 | R214: 6074.38 | S214: 35000
A215: 13/10/2025 | B215: . CONSUMIDOR FINAL ANÓNIMO | C215: 111 | D215: Ciudad de Buenos Aires | E215: SIN IDENTIFICAR | F215: CF | G215: FCB 0005-00014596 | H215: 38636.36 | I215: 0 | J215: 0 | K215: 0 | L215: 0 | M215: 8113.64 | N215: 0 | O215: 0 | P215: 0 | Q215: 0 | R215: 8113.64 | S215: 46750
A216: 13/10/2025 | B216: . CONSUMIDOR FINAL ANÓNIMO | C216: 111 | D216: Ciudad de Buenos Aires | E216: SIN IDENTIFICAR | F216: CF | G216: FCB 0005-00014597 | H216: 37024.79 | I216: 0 | J216: 0 | K216: 0 | L216: 0 | M216: 7775.21 | N216: 0 | O216: 0 | P216: 0 | Q216: 0 | R216: 7775.21 | S216: 44800
A217: 13/10/2025 | B217: OBRA SOCIAL DEL PERSONAL DE LAS TELECOMUNICACIONES DE LA REPUBLICA ARGENTINA | C217: 30608716390 | D217: Ciudad de Buenos Aires | E217: SIN IDENTIFICAR | F217: RI | G217: FCA 0007-00002748 | H217: 38636.36 | I217: 0 | J217: 0 | K217: 0 | L217: 0 | M217: 8113.64 | N217: 0 | O217: 0 | P217: 0 | Q217: 0 | R217: 8113.64 | S217: 46750
A218: 13/10/2025 | B218: OBRA SOCIAL DEL PERSONAL DE ESTACIONES DE SERVICIOS GARAGES PLAYAS DE ESTACIONAMIENTO Y LAVADEROS AUTOMATICOS | C218: 30631503280 | D218: Ciudad de Buenos Aires | E218: SIN IDENTIFICAR | F218: EX | G218: FCB 0007-00006517 | H218: 640495.87 | I218: 0 | J218: 0 | K218: 0 | L218: 0 | M218: 134504.13 | N218: 0 | O218: 0 | P218: 0 | Q218: 0 | R218: 134504.13 | S218: 775000
A219: 13/10/2025 | B219: . CONSUMIDOR FINAL ANÓNIMO | C219: 111 | D219: Ciudad de Buenos Aires | E219: SIN IDENTIFICAR | F219: CF | G219: FCB 0005-00014598 | H219: 18595.04 | I219: 0 | J219: 0 | K219: 0 | L219: 0 | M219: 3904.96 | N219: 0 | O219: 0 | P219: 0 | Q219: 0 | R219: 3904.96 | S219: 22500
A220: 13/10/2025 | B220: OBRA SOCIAL UNION PERSONAL DE LA UNION DEL PERSONAL CIVIL DE LA NACION | C220: 30683032227 | D220: Ciudad de Buenos Aires | E220: SIN IDENTIFICAR | F220: RI | G220: FCA 0007-00002749 | H220: 1899173.6 | I220: 0 | J220: 0 | K220: 0 | L220: 0 | M220: 398826.45 | N220: 0 | O220: 0 | P220: 0 | Q220: 0 | R220: 398826.45 | S220: 2298000
... A459: 31/10/2025 | B459: OBRA SOCIAL DEL PERSONAL DE ESTACIONES DE SERVICIOS GARAGES PLAYAS DE ESTACIONAMIENTO Y LAVADEROS AUTOMATICOS | C459: 30631503280 | D459: Ciudad de Buenos Aires | E459: SIN IDENTIFICAR | F459: EX | G459: NCB 0007-00000228 | H459: -3814049.6 | I459: 0 | J459: 0 | K459: 0 | L459: 0 | M459: -800950.41 | N459: 0 | O459: 0 | P459: 0 | Q459: 0 | R459: -800950.41 | S459: -4615000
A460: 31/10/2025 | B460: GALENO ARGENTINA SOCIEDAD ANONIMA | C460: 30522428163 | D460: Ciudad de Buenos Aires | E460: SIN IDENTIFICAR | F460: RI | G460: FCA 0003-00002147 | H460: 226011.71 | I460: 0 | J460: 0 | K460: 0 | L460: 0 | M460: 47462.46 | N460: 0 | O460: 0 | P460: 0 | Q460: 0 | R460: 47462.46 | S460: 273474.16 | T460: Comprobante Emitido por ARCA
A461: 31/10/2025 | B461: OBRA SOCIAL UNION PERSONAL DE LA UNION DEL PERSONAL CIVIL DE LA NACION | C461: 30683032227 | D461: Ciudad de Buenos Aires | E461: SIN IDENTIFICAR | F461: RI | G461: FCA 0003-00002144 | H461: 2681410.3 | I461: 0 | J461: 0 | K461: 0 | L461: 0 | M461: 563096.17 | N461: 0 | O461: 0 | P461: 0 | Q461: 0 | R461: 563096.17 | S461: 3244506.5 | T461: Comprobante Emitido por ARCA
A462: 31/10/2025 | B462: GALENO ARGENTINA SOCIEDAD ANONIMA | C462: 30522428163 | D462: Ciudad de Buenos Aires | E462: SIN IDENTIFICAR | F462: RI | G462: FCA 0003-00002146 | H462: 1930296.4 | I462: 0 | J462: 0 | K462: 0 | L462: 0 | M462: 405362.24 | N462: 0 | O462: 0 | P462: 0 | Q462: 0 | R462: 405362.24 | S462: 2335658.6 | T462: Comprobante Emitido por ARCA
A463: 31/10/2025 | B463: GALENO ARGENTINA SOCIEDAD ANONIMA | C463: 30522428163 | D463: Ciudad de Buenos Aires | E463: SIN IDENTIFICAR | F463: RI | G463: FCA 0003-00002145 | H463: 2886275.8 | I463: 0 | J463: 0 | K463: 0 | L463: 0 | M463: 606117.91 | N463: 0 | O463: 0 | P463: 0 | Q463: 0 | R463: 606117.91 | S463: 3492393.7 | T463: Comprobante Emitido por ARCA
A464: 31/10/2025 | B464: ASOCIACION MUTUAL SANCOR SALUD | C464: 30590354798 | E464: SIN IDENTIFICAR | F464: EX | G464: FCB 0003-00002892 | H464: 2268976.9 | I464: 0 | J464: 0 | K464: 0 | L464: 0 | M464: 476485.14 | N464: 0 | O464: 0 | P464: 0 | Q464: 0 | R464: 476485.14 | S464: 2745462 | T464: Comprobante Emitido por ARCA
A465: 31/10/2025 | B465: GALENO ARGENTINA SOCIEDAD ANONIMA | C465: 30522428163 | D465: Ciudad de Buenos Aires | E465: SIN IDENTIFICAR | F465: RI | G465: FCA 0003-00000022 | H465: 26368794 | I465: 0 | J465: 0 | K465: 0 | L465: 0 | M465: 5537446.8 | N465: 0 | O465: 0 | P465: 0 | Q465: 0 | R465: 5537446.8 | S465: 31906241 | T465: Comprobante Emitido por ARCA
A466: 31/10/2025 | B466: GALENO ARGENTINA SOCIEDAD ANONIMA | C466: 30522428163 | D466: Ciudad de Buenos Aires | E466: SIN IDENTIFICAR | F466: RI | G466: FCA 0003-00000023 | H466: 3503108.5 | I466: 0 | J466: 0 | K466: 0 | L466: 0 | M466: 735652.78 | N466: 0 | O466: 0 | P466: 0 | Q466: 0 | R466: 735652.78 | S466: 4238761.2 | T466: Comprobante Emitido por ARCA

Sheet Compras 10
A1: Fecha Emision | B1: Fecha Contable | C1: Nro Factura | D1: Razon Social | E1: Cuit | F1: Condicion Iva | G1: Monto Gravado Iva 2 | H1: Monto Gravado Iva 5 | I1: Monto Gravado Iva 10,5 | J1: Monto Gravado Iva 21 | K1: Monto Gravado Iva 27 | L1: Monto No Gravado Y Exentos | M1: Monto Gravado Monotributistas | N1: Iva Facturado | O1: Imp Interno | P1: Imp Municipal | Q1: Imp Nacional | R1: Otros | S1: Percepcion IVA | T1: IIBB | U1: Total Facturado | V1: Rubro | W1: Cod Fa
A2: 22/10/2025 | B2: 22/10/2025 | C2: FCA 00001-00000142 | D2: GOU TURISMO EJECUTIVO S.R.L. | E2: 30716046091 | F2: RI | G2: 0 | H2: 0 | I2: 400000 | J2: 0 | K2: 0 | L2: 0 | M2: 0 | N2: 42000 | O2: 0 | P2: 0 | Q2: 0 | R2: 0 | S2: 0 | T2: 0 | U2: 442000 | V2: Servicios
A3: 24/10/2025 | B3: 24/10/2025 | C3: FCA 00001-00009186 | D3: REHAB SRL | E3: 30715141201 | F3: RI | G3: 0 | H3: 0 | I3: 0 | J3: 2411808.8 | K3: 0 | L3: 0 | M3: 0 | N3: 506479.84 | O3: 0 | P3: 0 | Q3: 0 | R3: 0 | S3: 0 | T3: 0 | U3: 2918288.6 | V3: Bienes
A4: 27/10/2025 | B4: 27/10/2025 | C4: FCA 00001-00009201 | D4: REHAB SRL | E4: 30715141201 | F4: RI | G4: 0 | H4: 0 | I4: 0 | J4: 14480734 | K4: 0 | L4: 0 | M4: 0 | N4: 3040954.1 | O4: 0 | P4: 0 | Q4: 0 | R4: 0 | S4: 0 | T4: 0 | U4: 17521688 | V4: Bienes
A5: 28/10/2025 | B5: 28/10/2025 | C5: FCA 00001-00009213 | D5: REHAB SRL | E5: 30715141201 | F5: RI | G5: 0 | H5: 0 | I5: 0 | J5: 1647975 | K5: 0 | L5: 0 | M5: 0 | N5: 346074.75 | O5: 0 | P5: 0 | Q5: 0 | R5: 0 | S5: 0 | T5: 0 | U5: 1994049.8 | V5: Bienes
A6: 28/10/2025 | B6: 28/10/2025 | C6: FCA 00001-00009214 | D6: REHAB SRL | E6: 30715141201 | F6: RI | G6: 0 | H6: 0 | I6: 0 | J6: 206561.25 | K6: 0 | L6: 0 | M6: 0 | N6: 43377.86 | O6: 0 | P6: 0 | Q6: 0 | R6: 0 | S6: 0 | T6: 0 | U6: 249939.11 | V6: Bienes
A7: 01/10/2025 | B7: 01/10/2025 | C7: FCA 00001-00140551 | D7: CONTABILIUM SA | E7: 30714864269 | F7: RI | G7: 0 | H7: 0 | I7: 0 | J7: 184800 | K7: 0 | L7: 0 | M7: 0 | N7: 38808 | O7: 0 | P7: 0 | Q7: 0 | R7: 0 | S7: 0 | T7: 0 | U7: 223608 | V7: Servicios
A8: 01/10/2025 | B8: 08/10/2025 | C8: FCA 00001-01031096 | D8: VERISURE ARGENTINA MONITOREO DE ALARMAS SA | E8: 33716307749 | F8: RI | G8: 0 | H8: 0 | I8: 0 | J8: 62349.01 | K8: 0 | L8: 0 | M8: 0 | N8: 13093.29 | O8: 0 | P8: 0 | Q8: 0 | R8: 2493.96 | S8: 0 | T8: 0 | U8: 77936.26 | V8: Servicios
A9: 29/10/2025 | B9: 29/10/2025 | C9: FCA 00002-00000049 | D9: BARD MARISA SILVIA | E9: 27243660535 | F9: RI | G9: 0 | H9: 0 | I9: 0 | J9: 474914.87 | K9: 0 | L9: 0 | M9: 0 | N9: 99732.12 | O9: 0 | P9: 0 | Q9: 0 | R9: 0 | S9: 0 | T9: 0 | U9: 574646.99 | V9: Locaciones
A10: 29/10/2025 | B10: 29/10/2025 | C10: FCA 00002-00000050 | D10: BARD MARISA SILVIA | E10: 27243660535 | F10: RI | G10: 0 | H10: 0 | I10: 0 | J10: 474914.87 | K10: 0 | L10: 0 | M10: 0 | N10: 99732.12 | O10: 0 | P10: 0 | Q10: 0 | R10: 0 | S10: 0 | T10: 0 | U10: 574646.99 | V10: Locaciones
A11: 28/10/2025 | B11: 28/10/2025 | C11: FCA 00002-00000141 | D11: WILSON GUSTAVO UBALDO AQUINO | E11: 20276761111 | F11: RI | G11: 0 | H11: 0 | I11: 0 | J11: 49950 | K11: 0 | L11: 0 | M11: 0 | N11: 10489.5 | O11: 0 | P11: 0 | Q11: 0 | R11: 0 | S11: 0 | T11: 0 | U11: 60439.5 | V11: Bienes
A12: 01/10/2025 | B12: 07/10/2025 | C12: FCA 00002-00000252 | D12: CONSORCIO BARTOLME MITRE 2466 | E12: 30605344352 | F12: RI | G12: 0 | H12: 0 | I12: 0 | J12: 2160581 | K12: 0 | L12: 0 | M12: 0 | N12: 453722.01 | O12: 0 | P12: 0 | Q12: 0 | R12: 0 | S12: 0 | T12: 0 | U12: 2614303 | V12: Servicios
A13: 02/10/2025 | B13: 02/10/2025 | C13: FCA 00002-00001576 | D13: MARTIN EZEQUIEL DI FEO | E13: 20272865869 | F13: RI | G13: 0 | H13: 0 | I13: 0 | J13: 69400 | K13: 0 | L13: 0 | M13: 0 | N13: 14574 | O13: 0 | P13: 0 | Q13: 0 | R13: 0 | S13: 0 | T13: 0 | U13: 83974 | V13: Bienes
... A42: 08/10/2025 | B42: 09/10/2025 | C42: FCA 00005-00001694 | D42: MARISOL PRADO | E42: 27265302225 | F42: RI | G42: 0 | H42: 0 | I42: 0 | J42: 1400000 | K42: 0 | L42: 0 | M42: 0 | N42: 294000 | O42: 0 | P42: 0 | Q42: 0 | R42: 0 | S42: 0 | T42: 0 | U42: 1694000 | V42: Bienes
A43: 21/09/2025 | B43: 20/10/2025 | C43: FCA 00005-00006144 | D43: MONTE DUAL S.R.L. | E43: 33714967989 | F43: RI | G43: 0 | H43: 0 | I43: 0 | J43: 47207.83 | K43: 0 | L43: 0 | M43: 0 | N43: 9913.64 | O43: 11223.05 | P43: 0 | Q43: 0 | R43: 687.49 | S43: 0 | T43: 0 | U43: 69032.01 | V43: Servicios | W43: 81
A44: 14/10/2025 | B44: 14/10/2025 | C44: FCA 00005-00006507 | D44: BIODINAMICA ASISTENCIA S.R.L. | E44: 30715833243 | F44: RI | G44: 0 | H44: 0 | I44: 0 | J44: 378025 | K44: 0 | L44: 0 | M44: 0 | N44: 79385.25 | O44: 0 | P44: 0 | Q44: 0 | R44: 0 | S44: 0 | T44: 0 | U44: 457410.25 | V44: Bienes
A45: 14/10/2025 | B45: 14/10/2025 | C45: FCA 00005-00006509 | D45: BIODINAMICA ASISTENCIA S.R.L. | E45: 30715833243 | F45: RI | G45: 0 | H45: 0 | I45: 0 | J45: 115215 | K45: 0 | L45: 0 | M45: 0 | N45: 24195.15 | O45: 0 | P45: 0 | Q45: 0 | R45: 0 | S45: 0 | T45: 0 | U45: 139410.15 | V45: Bienes
A46: 15/10/2025 | B46: 15/10/2025 | C46: FCA 00005-00006522 | D46: BIODINAMICA ASISTENCIA S.R.L. | E46: 30715833243 | F46: RI | G46: 0 | H46: 0 | I46: 0 | J46: 102960 | K46: 0 | L46: 0 | M46: 0 | N46: 21621.6 | O46: 0 | P46: 0 | Q46: 0 | R46: 0 | S46: 0 | T46: 0 | U46: 124581.6 | V46: Bienes
A47: 15/10/2025 | B47: 15/10/2025 | C47: FCA 00005-00006523 | D47: BIODINAMICA ASISTENCIA S.R.L. | E47: 30715833243 | F47: RI | G47: 0 | H47: 0 | I47: 0 | J47: 33660.78 | K47: 0 | L47: 0 | M47: 0 | N47: 7068.76 | O47: 0 | P47: 0 | Q47: 0 | R47: 0 | S47: 0 | T47: 0 | U47: 40729.54 | V47: Bienes
A48: 16/10/2025 | B48: 16/10/2025 | C48: FCA 00005-00006531 | D48: BIODINAMICA ASISTENCIA S.R.L. | E48: 30715833243 | F48: RI | G48: 0 | H48: 0 | I48: 0 | J48: 432231 | K48: 0 | L48: 0 | M48: 0 | N48: 90768.51 | O48: 0 | P48: 0 | Q48: 0 | R48: 0 | S48: 0 | T48: 0 | U48: 522999.51 | V48: Bienes
A49: 22/10/2025 | B49: 22/10/2025 | C49: FCA 00005-03410705 | D49: NSS SA - IPLAN | E49: 30702652975 | F49: RI | G49: 0 | H49: 0 | I49: 0 | J49: 39734.25 | K49: 0 | L49: 0 | M49: 0 | N49: 8344.19 | O49: 0 | P49: 0 | Q49: 0 | R49: 0 | S49: 0 | T49: 1589.37 | U49: 49667.81 | V49: Servicios
A50: 09/10/2025 | B50: 09/10/2025 | C50: FCA 00006-00000121 | D50: 46 SPEED S.A. | E50: 30711610096 | F50: RI | G50: 0 | H50: 0 | I50: 0 | J50: 865620 | K50: 0 | L50: 0 | M50: 0 | N50: 181780.2 | O50: 0 | P50: 0 | Q50: 0 | R50: 0 | S50: 0 | T50: 0 | U50: 1047400.2 | V50: Bienes
A51: 09/10/2025 | B51: 09/10/2025 | C51: FCA 00006-00000123 | D51: 46 SPEED S.A. | E51: 30711610096 | F51: RI | G51: 0 | H51: 0 | I51: 0 | J51: 865620 | K51: 0 | L51: 0 | M51: 0 | N51: 181780.2 | O51: 0 | P51: 0 | Q51: 0 | R51: 0 | S51: 0 | T51: 0 | U51: 1047400.2 | V51: Bienes
A52: 15/10/2025 | B52: 15/10/2025 | C52: FCA 00006-00000127 | D52: 46 SPEED S.A. | E52: 30711610096 | F52: RI | G52: 0 | H52: 0 | I52: 0 | J52: 720000 | K52: 0 | L52: 0 | M52: 0 | N52: 151200 | O52: 0 | P52: 0 | Q52: 0 | R52: 0 | S52: 0 | T52: 0 | U52: 871200 | V52: Bienes
A53: 08/10/2025 | B53: 08/10/2025 | C53: FCA 00006-00002120 | D53: PAPELERA GEOPEL SRL | E53: 30716815710 | F53: RI | G53: 0 | H53: 0 | I53: 0 | J53: 26800 | K53: 0 | L53: 0 | M53: 0 | N53: 5628 | O53: 0 | P53: 0 | Q53: 0 | R53: 0 | S53: 0 | T53: 0 | U53: 32428 | V53: Bienes
A54: 07/10/2025 | B54: 07/10/2025 | C54: FCA 00006-00003443 | D54: GRUPO MAXIMUS S.R.L. | E54: 30715775014 | F54: RI | G54: 0 | H54: 0 | I54: 38371.04 | J54: 0 | K54: 0 | L54: 0 | M54: 0 | N54: 4028.96 | O54: 0 | P54: 0 | Q54: 0 | R54: 0 | S54: 0 | T54: 1534.84 | U54: 43934.84 | V54: Bienes
A55: 14/10/2025 | B55: 14/10/2025 | C55: FCA 00006-00059344 | D55: TARGET MEDICAL SA | E55: 30710177658 | F55: RI | G55: 0 | H55: 0 | I55: 0 | J55: 831952 | K55: 0 | L55: 0 | M55: 0 | N55: 174709.92 | O55: 0 | P55: 0 | Q55: 0 | R55: 0 | S55: 0 | T55: 33278.08 | U55: 1039940 | V55: Bienes
A56: 31/10/2025 | B56: 31/10/2025 | C56: FCA 00006-00059569 | D56: TARGET MEDICAL SA | E56: 30710177658 | F56: RI | G56: 0 | H56: 0 | I56: 0 | J56: 575200 | K56: 0 | L56: 0 | M56: 0 | N56: =J56*0.21 -> 120792 | O56: 0 | P56: 0 | Q56: 0 | R56: 0 | S56: 0 | T56: 23008 | U56: =SUM(G56:T56) -> 719000 | V56: Bienes
A57: 01/10/2025 | B57: 01/10/2025 | C57: FCA 00006-00096490 | D57: SALUDTEX SA | E57: 30711553564 | F57: RI | G57: 0 | H57: 0 | I57: 0 | J57: 1332279 | K57: 0 | L57: 0 | M57: 0 | N57: 279778.59 | O57: 0 | P57: 0 | Q57: 0 | R57: 0 | S57: 0 | T57: 0 | U57: 1612057.6 | V57: Bienes
A58: 01/10/2025 | B58: 01/10/2025 | C58: FCA 00006-00096491 | D58: SALUDTEX SA | E58: 30711553564 | F58: RI | G58: 0 | H58: 0 | I58: 0 | J58: 702555 | K58: 0 | L58: 0 | M58: 0 | N58: 147536.55 | O58: 0 | P58: 0 | Q58: 0 | R58: 0 | S58: 0 | T58: 0 | U58: 850091.55 | V58: Bienes
A59: 01/10/2025 | B59: 01/10/2025 | C59: FCA 00006-00096492 | D59: SALUDTEX SA | E59: 30711553564 | F59: RI | G59: 0 | H59: 0 | I59: 0 | J59: 30765 | K59: 0 | L59: 0 | M59: 0 | N59: 6460.65 | O59: 0 | P59: 0 | Q59: 0 | R59: 0 | S59: 0 | T59: 0 | U59: 37225.65 | V59: Bienes
A60: 22/10/2025 | B60: 22/10/2025 | C60: FCA 00006-00097166 | D60: SALUDTEX SA | E60: 30711553564 | F60: RI | G60: 0 | H60: 0 | I60: 0 | J60: 355304 | K60: 0 | L60: 0 | M60: 0 | N60: 74613.84 | O60: 0 | P60: 0 | Q60: 0 | R60: 0 | S60: 0 | T60: 0 | U60: 429917.84 | V60: Bienes
A61: 30/10/2025 | B61: 30/10/2025 | C61: FCA 00006-21005478 | D61: POSNET SOCIEDAD DE RESPONSABILIDAD LIMITADA | E61: 30620177497 | F61: RI | G61: 0 | H61: 0 | I61: 0 | J61: 19593.02 | K61: 0 | L61: 0 | M61: 0 | N61: 4114.53 | O61: 0 | P61: 0 | Q61: 0 | R61: 1371.51 | S61: 0 | T61: 0 | U61: 25079.06 | V61: Servicios
A62: 02/10/2025 | B62: 07/10/2025 | C62: FCA 00007-00000055 | D62: ALEJANDRA MABEL SOUSA ALDERETE | E62: 27325223273 | F62: RI | G62: 0 | H62: 0 | I62: 0 | J62: 2200000 | K62: 0 | L62: 0 | M62: 0 | N62: 462000 | O62: 0 | P62: 0 | Q62: 0 | R62: 0 | S62: 0 | T62: 0 | U62: 2662000 | V62: Bienes
A63: 08/10/2025 | B63: 09/10/2025 | C63: FCA 00007-00000056 | D63: ALEJANDRA MABEL SOUSA ALDERETE | E63: 27325223273 | F63: RI | G63: 0 | H63: 0 | I63: 0 | J63: 1300000 | K63: 0 | L63: 0 | M63: 0 | N63: 273000 | O63: 0 | P63: 0 | Q63: 0 | R63: 0 | S63: 0 | T63: 0 | U63: 1573000 | V63: Bienes
A64: 28/10/2025 | B64: 28/10/2025 | C64: FCA 00007-00001773 | D64: ITALOMED PRODUCTOS SRL | E64: 30712187316 | F64: RI | G64: 0 | H64: 0 | I64: 0 | J64: 215832.05 | K64: 0 | L64: 0 | M64: 0 | N64: 45324.73 | O64: 0 | P64: 0 | Q64: 0 | R64: 0 | S64: 0 | T64: 0 | U64: 261156.78 | V64: Bienes
A65: 29/10/2025 | B65: 29/10/2025 | C65: FCA 00007-00001777 | D65: ITALOMED PRODUCTOS SRL | E65: 30712187316 | F65: RI | G65: 0 | H65: 0 | I65: 0 | J65: 199854.05 | K65: 0 | L65: 0 | M65: 0 | N65: 41969.35 | O65: 0 | P65: 0 | Q65: 0 | R65: 0 | S65: 0 | T65: 0 | U65: 241823.4 | V65: Bienes
A66: 23/10/2025 | B66: 23/10/2025 | C66: FCA 00007-00005934 | D66: MATIAS EZEQUIEL ROMANO | E66: 20347228002 | F66: RI | G66: 0 | H66: 0 | I66: 0 | J66: 80594.23 | K66: 0 | L66: 0 | M66: 0 | N66: 16924.79 | O66: 0 | P66: 0 | Q66: 0 | R66: 0 | S66: 0 | T66: 0 | U66: 97519.02 | V66: Bienes
A67: 10/10/2025 | B67: 13/10/2025 | C67: FCA 00007-00022484 | D67: FOURMAX S.R.L. | E67: 30711647135 | F67: RI | G67: 0 | H67: 0 | I67: 0 | J67: 96169.7 | K67: 0 | L67: 0 | M67: 0 | N67: 20195.64 | O67: 0 | P67: 0 | Q67: 0 | R67: 13634.67 | S67: 0 | T67: 0 | U67: 130000.01 | W67: 81
A68: 14/10/2025 | B68: 14/10/2025 | C68: FCA 00007-00022647 | D68: REHAVITA S.A. | E68: 30709214078 | F68: RI | G68: 0 | H68: 0 | I68: 315560 | J68: 0 | K68: 0 | L68: 0 | M68: 0 | N68: 33133.8 | O68: 0 | P68: 0 | Q68: 0 | R68: 0 | S68: 0 | T68: 0 | U68: 348693.8 | V68: Bienes
A69: 15/10/2025 | B69: 15/10/2025 | C69: FCA 00007-00022677 | D69: REHAVITA S.A. | E69: 30709214078 | F69: RI | G69: 0 | H69: 0 | I69: 875840 | J69: 0 | K69: 0 | L69: 0 | M69: 0 | N69: 91963.2 | O69: 0 | P69: 0 | Q69: 0 | R69: 0 | S69: 0 | T69: 0 | U69: 967803.2 | V69: Bienes
A70: 02/10/2025 | B70: 07/10/2025 | C70: FCA 00008-00000476 | D70: FARMACIA DE MEDRANO 533 SOCIEDAD EN COMANDITA SIMPLE | E70: 30643518364 | F70: RI | G70: 0 | H70: 0 | I70: 0 | J70: 88750 | K70: 0 | L70: 0 | M70: 0 | N70: 18637.5 | O70: 0 | P70: 0 | Q70: 0 | R70: 0 | S70: 0 | T70: 0 | U70: 107387.5 | V70: Bienes
A71: 13/10/2025 | B71: 13/10/2025 | C71: FCA 00008-00002509 | D71: RAUL EUGENIO MENDIZABAL | E71: 23288035059 | F71: RI | G71: 0 | H71: 0 | I71: 0 | J71: 9380.17 | K71: 0 | L71: 0 | M71: 0 | N71: 1969.84 | O71: 0 | P71: 0 | Q71: 0 | R71: 0 | S71: 0 | T71: 0 | U71: 11350.01 | V71: Bienes
A72: 02/10/2025 | B72: 02/10/2025 | C72: FCA 00008-00016206 | D72: SOMOS ENERGIA SA | E72: 33715594949 | F72: RI | G72: 0 | H72: 0 | I72: 0 | J72: 73101.04 | K72: 0 | L72: 0 | M72: 0 | N72: 15351.22 | O72: 10377.9 | P72: 0 | Q72: 0 | R72: 1182.84 | S72: 0 | T72: 0 | U72: 100013 | V72: Servicios | W72: 81
A73: 15/10/2025 | B73: 15/10/2025 | C73: FCA 00008-00016335 | D73: SOMOS ENERGIA SA | E73: 33715594949 | F73: RI | G73: 0 | H73: 0 | I73: 0 | J73: 47576.46 | K73: 0 | L73: 0 | M73: 0 | N73: 9991.06 | O73: 6672.07 | P73: 0 | Q73: 0 | R73: 760.46 | S73: 0 | T73: 0 | U73: 65000.05 | V73: Servicios | W73: 81
A74: 18/10/2025 | B74: 18/10/2025 | C74: FCA 00008-00016365 | D74: SOMOS ENERGIA SA | E74: 33715594949 | F74: RI | G74: 0 | H74: 0 | I74: 0 | J74: 43948.61 | K74: 0 | L74: 0 | M74: 0 | N74: 9229.21 | O74: 6124.09 | P74: 0 | Q74: 0 | R74: 698 | S74: 0 | T74: 0 | U74: 59999.91 | V74: Servicios | W74: 81
A75: 26/10/2025 | B75: 26/10/2025 | C75: FCA 00008-00016423 | D75: SOMOS ENERGIA SA | E75: 33715594949 | F75: RI | G75: 0 | H75: 0 | I75: 0 | J75: 13063.72 | K75: 0 | L75: 0 | M75: 0 | N75: 2743.38 | O75: 1820.38 | P75: 0 | Q75: 0 | R75: 207.48 | S75: 0 | T75: 0 | U75: 17834.96 | V75: Servicios | W75: 81
A76: 27/10/2025 | B76: 27/10/2025 | C76: FCA 00008-00016431 | D76: SOMOS ENERGIA SA | E76: 33715594949 | F76: RI | G76: 0 | H76: 0 | I76: 0 | J76: 49810.75 | K76: 0 | L76: 0 | M76: 0 | N76: 10460.26 | O76: 6940.95 | P76: 0 | Q76: 0 | R76: 791.11 | S76: 0 | T76: 0 | U76: 68003.07 | V76: Servicios | W76: 81
A77: 08/10/2025 | B77: 08/10/2025 | C77: FCA 00009-00023056 | D77: HORACIO FERNANDO GARCIA | E77: 20207044262 | F77: RI | G77: 0 | H77: 0 | I77: 0 | J77: 23405.78 | K77: 0 | L77: 0 | M77: 0 | N77: 4915.21 | O77: 0 | P77: 0 | Q77: 0 | R77: 0 | S77: 0 | T77: 0 | U77: 28320.99 | V77: Bienes
A78: 21/10/2025 | B78: 21/10/2025 | C78: FCA 00010-00002818 | D78: QBIKE | E78: 30716886766 | F78: RI | G78: 0 | H78: 0 | I78: 0 | J78: 37776.86 | K78: 0 | L78: 0 | M78: 0 | N78: 7933.14 | O78: 0 | P78: 0 | Q78: 0 | R78: 0 | S78: 0 | T78: 0 | U78: 45710 | V78: Bienes
A79: 06/10/2025 | B79: 06/10/2025 | C79: FCA 00010-00004192 | D79: PLASTICENTRO 11 SOCIEDAD ANONIMA | E79: 30591749656 | F79: RI | G79: 0 | H79: 0 | I79: 0 | J79: 132090 | K79: 0 | L79: 0 | M79: 0 | N79: 27738.9 | O79: 0 | P79: 0 | Q79: 0 | R79: 0 | S79: 0 | T79: 5283.6 | U79: 165112.5 | V79: Bienes | W79: 81
A80: 31/10/2025 | B80: 31/10/2025 | C80: FCA 00011-00000834 | D80: OLGA ESTELA DI SALVI | E80: 27167838001 | F80: RI | G80: 0 | H80: 0 | I80: 0 | J80: 315000 | K80: 0 | L80: 0 | M80: 0 | N80: 66150 | O80: 0 | P80: 0 | Q80: 0 | R80: 0 | S80: 0 | T80: 0 | U80: 381150 | V80: Bienes
A81: 31/10/2025 | B81: 31/10/2025 | C81: FCA 00011-00000835 | D81: OLGA ESTELA DI SALVI | E81: 27167838001 | F81: RI | G81: 0 | H81: 0 | I81: 0 | J81: 357000 | K81: 0 | L81: 0 | M81: 0 | N81: 74970 | O81: 0 | P81: 0 | Q81: 0 | R81: 0 | S81: 0 | T81: 0 | U81: 431970 | V81: Bienes
A82: 29/10/2025 | B82: 29/10/2025 | C82: FCA 00011-04698716 | D82: MERCADOLIBRE S.R.L. | E82: 30703088534 | F82: RI | G82: 0 | H82: 0 | I82: 0 | J82: 83568.6 | K82: 0 | L82: 0 | M82: 0 | N82: 17549.41 | O82: 0 | P82: 0 | Q82: 0 | R82: 0 | S82: 2507.06 | T82: 3342.74 | U82: 106967.81 | V82: Servicios
A83: 07/10/2025 | B83: 07/10/2025 | C83: FCA 00015-00005031 | D83: COLTEX SRL | E83: 30688140923 | F83: RI | G83: 0 | H83: 0 | I83: 0 | J83: 126761.5 | K83: 0 | L83: 0 | M83: 0 | N83: 26619.92 | O83: 0 | P83: 0 | Q83: 0 | R83: 0 | S83: 0 | T83: 0 | U83: 153381.42 | V83: Bienes
A84: 31/10/2025 | B84: 31/10/2025 | C84: FCA 00016-00000064 | D84: MARIA VIRGINIA LA BRUNA | E84: 27310367813 | F84: RI | G84: 0 | H84: 0 | I84: 0 | J84: 190248.57 | K84: 0 | L84: 0 | M84: 0 | N84: 39952.2 | O84: 0 | P84: 0 | Q84: 0 | R84: 0 | S84: 0 | T84: 0 | U84: 230200.77 | V84: Bienes
A85: 06/10/2025 | B85: 07/10/2025 | C85: FCA 00017-00003413 | D85: RELIEF CENTER S.R.L. | E85: 30711764921 | F85: RI | G85: 0 | H85: 0 | I85: 0 | J85: 210051 | K85: 0 | L85: 0 | M85: 0 | N85: 44110.71 | O85: 0 | P85: 0 | Q85: 0 | R85: 0 | S85: 0 | T85: 0 | U85: 254161.71 | V85: Bienes
A86: 02/10/2025 | B86: 07/10/2025 | C86: FCA 00017-00013744 | D86: ORTOPEDIA BERNAT SRL | E86: 30661143610 | F86: RI | G86: 0 | H86: 0 | I86: 0 | J86: 102800 | K86: 0 | L86: 0 | M86: 0 | N86: 21588 | O86: 0 | P86: 0 | Q86: 0 | R86: 4112 | S86: 0 | T86: 0 | U86: 128500 | V86: Bienes
A87: 22/10/2025 | B87: 22/10/2025 | C87: FCA 00023-00008977 | D87: LIBRERIA PELUFFO SRL | E87: 30679067431 | F87: RI | G87: 0 | H87: 0 | I87: 0 | J87: 27267.36 | K87: 0 | L87: 0 | M87: 0 | N87: 5726.15 | O87: 0 | P87: 0 | Q87: 0 | R87: 0 | S87: 0 | T87: 0 | U87: 32993.51 | V87: Bienes
A88: 03/10/2025 | B88: 07/10/2025 | C88: FCA 00026-00215680 | D88: EXPRESO LANCIONI SA | E88: 30708847247 | F88: RI | G88: 0 | H88: 0 | I88: 0 | J88: 74779.13 | K88: 0 | L88: 0 | M88: 0 | N88: 15703.62 | O88: 0 | P88: 0 | Q88: 0 | R88: 2991.17 | S88: 0 | T88: 0 | U88: 93473.92 | V88: Servicios
A89: 15/10/2025 | B89: 15/10/2025 | C89: FCA 00050-04670040 | D89: AUTOPISTAS DE BUENOS AIRES (AUBASA) SA | E89: 30714112836 | F89: RI | G89: 0 | H89: 0 | I89: 0 | J89: 4911.22 | K89: 0 | L89: 0 | M89: 0 | N89: 1031.36 | O89: 0 | P89: 0 | Q89: 0 | R89: 0 | S89: 147.34 | T89: 0 | U89: 6089.92 | V89: Servicios
A90: 31/10/2025 | B90: 31/10/2025 | C90: FCA 00050-04706524 | D90: AUTOPISTAS DE BUENOS AIRES (AUBASA) SA | E90: 30714112836 | F90: RI | G90: 0 | H90: 0 | I90: 0 | J90: 1637.07 | K90: 0 | L90: 0 | M90: 0 | N90: 343.78 | O90: 0 | P90: 0 | Q90: 0 | R90: 0 | S90: 0 | T90: 0 | U90: 1980.85 | V90: Servicios
A91: 29/10/2025 | B91: 29/10/2025 | C91: FCA 00066-00440765 | D91: MERCADOLIBRE S.R.L. | E91: 30703088534 | F91: RI | G91: 0 | H91: 0 | I91: 0 | J91: 140500.92 | K91: 0 | L91: 0 | M91: 0 | N91: 29505.19 | O91: 0 | P91: 0 | Q91: 0 | R91: 0 | S91: 4215.03 | T91: 5620.03 | U91: 179841.17 | V91: Servicios
... A121: 21/10/2025 | B121: 21/10/2025 | C121: FCA 02168-00025156 | D121: COTO CICSA | E121: 30548083156 | F121: RI | G121: 0 | H121: 0 | I121: 42691.29 | J121: 2169.42 | K121: 0 | L121: 0 | M121: 0 | N121: 4938.16 | O121: 0 | P121: 0 | Q121: 0 | R121: 0 | S121: 676.81 | T121: 354.73 | U121: 50830.41 | V121: Bienes
A122: 15/10/2025 | B122: 15/10/2025 | C122: FCA 02399-00085833 | D122: CORREO OFICIAL DE LA REPUBLICA ARGENTINA SOCIEDAD ANONIMA | E122: 30708574836 | F122: RI | G122: 0 | H122: 0 | I122: 0 | J122: 0 | K122: 0 | L122: 17400 | M122: 0 | N122: 0 | O122: 0 | P122: 0 | Q122: 0 | R122: 0 | S122: 0 | T122: 0 | U122: 17400 | V122: Servicios | W122: 81
A123: 30/10/2025 | B123: 30/10/2025 | C123: FCA 02399-00085929 | D123: CORREO OFICIAL DE LA REPUBLICA ARGENTINA SOCIEDAD ANONIMA | E123: 30708574836 | F123: RI | G123: 0 | H123: 0 | I123: 0 | J123: 0 | K123: 0 | L123: 19900 | M123: 0 | N123: 0 | O123: 0 | P123: 0 | Q123: 0 | R123: 0 | S123: 0 | T123: 0 | U123: 19900 | V123: Servicios | W123: 81
A124: 20/10/2025 | B124: 20/10/2025 | C124: FCA 02434-00080327 | D124: CORREO OFICIAL DE LA REPUBLICA ARGENTINA SOCIEDAD ANONIMA | E124: 30708574836 | F124: RI | G124: 0 | H124: 0 | I124: 0 | J124: 0 | K124: 0 | L124: 18950 | M124: 0 | N124: 0 | O124: 0 | P124: 0 | Q124: 0 | R124: 0 | S124: 0 | T124: 0 | U124: 18950 | V124: Servicios | W124: 81
A125: 02/10/2025 | B125: 07/10/2025 | C125: FCA 03051-00982461 | D125: TELEFONICA MOVILES ARG SA | E125: 30678814357 | F125: RI | G125: 0 | H125: 0 | I125: 0 | J125: 0 | K125: 57907 | L125: 0 | M125: 0 | N125: 15634.89 | O125: 3047.7 | P125: 0 | Q125: 0 | R125: 0 | S125: 1737.21 | T125: 2438.19 | U125: 80764.99 | V125: Servicios
A126: 09/10/2025 | B126: 09/10/2025 | C126: FCA 03101-00390491 | D126: TELEFONICA MOVILES ARG SA | E126: 30678814357 | F126: RI | G126: 0 | H126: 0 | I126: 0 | J126: 0 | K126: 61222.8 | L126: 0 | M126: 0 | N126: 16530.16 | O126: 0 | P126: 0 | Q126: 0 | R126: 0 | S126: 1836.68 | T126: 2448.91 | U126: 82038.55 | V126: Servicios
A127: 28/10/2025 | B127: 28/10/2025 | C127: FCA 03950-05311093 | D127: TELECOM ARGENTINA SA | E127: 30639453738 | F127: RI | G127: 0 | H127: 0 | I127: 0 | J127: 46766.15 | K127: 0 | L127: 0 | M127: 0 | N127: 9820.89 | O127: 0 | P127: 0 | Q127: 0 | R127: 0 | S127: 1402.98 | T127: 1870.65 | U127: 59860.67 | V127: Servicios
A128: 31/10/2025 | B128: 31/10/2025 | C128: FCA 05009-01680484 | D128: AUTOPISTAS URBANAS SA | E128: 30574876474 | F128: RI | G128: 0 | H128: 0 | I128: 0 | J128: 5891.09 | K128: 0 | L128: 0 | M128: 0 | N128: 1237.13 | O128: 0 | P128: 0 | Q128: 0 | R128: 765.84 | S128: 0 | T128: 0 | U128: 7894.06 | V128: Servicios
A129: 08/10/2025 | B129: 08/10/2025 | C129: FCA 05015-01018189 | D129: AUTOPISTAS URBANAS SA | E129: 30574876474 | F129: RI | G129: 0 | H129: 0 | I129: 0 | J129: 35885.79 | K129: 0 | L129: 0.2 | M129: 0 | N129: 7536.02 | O129: 3588.59 | P129: 0 | Q129: 0 | R129: 1076.57 | S129: 0 | T129: 0 | U129: 48087.17 | V129: Servicios
A130: 29/10/2025 | B130: 29/10/2025 | C130: FCA 05015-01027855 | D130: AUTOPISTAS URBANAS SA | E130: 30574876474 | F130: RI | G130: 0 | H130: 0 | I130: 0 | J130: 18677.6 | K130: 0 | L130: 0.09 | M130: 0 | N130: 3922.3 | O130: 1867.76 | P130: 0 | Q130: 0 | R130: 560.33 | S130: 0 | T130: 0 | U130: 25028.08 | V130: Servicios
A131: 23/10/2025 | B131: 23/10/2025 | C131: FCA 05015-01036311 | D131: AUTOPISTAS URBANAS SA | E131: 30574876474 | F131: RI | G131: 0 | H131: 0 | I131: 0 | J131: 35776.78 | K131: 0 | L131: 0.22 | M131: 0 | N131: 7513.12 | O131: 3577.69 | P131: 0 | Q131: 0 | R131: 1073.3 | S131: 0 | T131: 0 | U131: 47941.11 | V131: Servicios
A132: 31/10/2025 | B132: 31/10/2025 | C132: FCA 05015-01051683 | D132: AUTOPISTAS URBANAS SA | E132: 30574876474 | F132: RI | G132: 0 | H132: 0 | I132: 0 | J132: 9832.17 | K132: 0 | L132: 0 | M132: 0 | N132: 2064.76 | O132: 0 | P132: 0 | Q132: 0 | R132: 1278.19 | S132: 0 | T132: 0 | U132: 13175.12 | V132: Servicios
A133: 09/10/2025 | B133: 09/10/2025 | C133: FCA 09238-00000711 | D133: VIA BARILOCHE SOCIEDAD ANONIMA | E133: 30643922157 | F133: RI | G133: 0 | H133: 0 | I133: 0 | J133: 29752.07 | K133: 0 | L133: 0 | M133: 0 | N133: 6247.93 | O133: 0 | P133: 0 | Q133: 0 | R133: 0 | S133: 0 | T133: 0 | U133: 36000 | V133: Servicios
A134: 20/10/2025 | B134: 20/10/2025 | C134: FCA 09426-00003532 | D134: VIA BARILOCHE SOCIEDAD ANONIMA | E134: 30643922157 | F134: RI | G134: 0 | H134: 0 | I134: 0 | J134: 19008.27 | K134: 0 | L134: 0 | M134: 0 | N134: 3991.74 | O134: 0 | P134: 0 | Q134: 0 | R134: 0 | S134: 0 | T134: 0 | U134: 23000.01 | V134: Servicios
A135: 14/10/2025 | B135: 14/10/2025 | C135: FCC 00001-00000001 | D135: WALTER QUIMEY GALTIERI | E135: 20421434450 | F135: MO | G135: 0 | H135: 0 | I135: 0 | J135: 0 | K135: 0 | L135: 0 | M135: 260000 | N135: 0 | O135: 0 | P135: 0 | Q135: 0 | R135: 0 | S135: 0 | T135: 0 | U135: 260000 | V135: Servicios
A136: 07/10/2025 | B136: 09/10/2025 | C136: FCC 00001-00000005 | D136: PAULA CIVALE | E136: 27380284052 | F136: MO | G136: 0 | H136: 0 | I136: 0 | J136: 0 | K136: 0 | L136: 0 | M136: 4365000 | N136: 0 | O136: 0 | P136: 0 | Q136: 0 | R136: 0 | S136: 0 | T136: 0 | U136: 4365000 | V136: Servicios
... A150: 06/10/2025 | B150: 09/10/2025 | C150: FCC 00002-00000380 | D150: MARIA GUADALUPE BLASCO | E150: 27265832178 | F150: MO | G150: 0 | H150: 0 | I150: 0 | J150: 0 | K150: 0 | L150: 0 | M150: 3200000 | N150: 0 | O150: 0 | P150: 0 | Q150: 0 | R150: 0 | S150: 0 | T150: 0 | U150: 3200000 | V150: Servicios
A151: 03/10/2025 | B151: 07/10/2025 | C151: FCC 00002-00000634 | D151: DANIEL JORGE CAMPA | E151: 20247881957 | F151: MO | G151: 0 | H151: 0 | I151: 0 | J151: 0 | K151: 0 | L151: 0 | M151: 13400 | N151: 0 | O151: 0 | P151: 0 | Q151: 0 | R151: 0 | S151: 0 | T151: 0 | U151: 13400
A152: 16/10/2025 | B152: 16/10/2025 | C152: FCC 00002-00000651 | D152: DANIEL JORGE CAMPA | E152: 20247881957 | F152: MO | G152: 0 | H152: 0 | I152: 0 | J152: 0 | K152: 0 | L152: 0 | M152: 21300 | N152: 0 | O152: 0 | P152: 0 | Q152: 0 | R152: 0 | S152: 0 | T152: 0 | U152: 21300 | V152: Bienes
A153: 16/10/2025 | B153: 16/10/2025 | C153: FCC 00003-00000012 | D153: LUIS ALBERTO OVIEDO | E153: 20310489930 | F153: MO | G153: 0 | H153: 0 | I153: 0 | J153: 0 | K153: 0 | L153: 0 | M153: 922580 | N153: 0 | O153: 0 | P153: 0 | Q153: 0 | R153: 0 | S153: 0 | T153: 0 | U153: 922580 | V153: Bienes
A154: 17/10/2025 | B154: 17/10/2025 | C154: FCC 00003-00000013 | D154: LUIS ALBERTO OVIEDO | E154: 20310489930 | F154: MO | G154: 0 | H154: 0 | I154: 0 | J154: 0 | K154: 0 | L154: 0 | M154: 500000 | N154: 0 | O154: 0 | P154: 0 | Q154: 0 | R154: 0 | S154: 0 | T154: 0 | U154: 500000 | V154: Bienes
A155: 01/10/2025 | B155: 07/10/2025 | C155: FCC 00004-00000066 | D155: JUAN CARLOS BOTINDARI | E155: 20086277523 | F155: MO | G155: 0 | H155: 0 | I155: 0 | J155: 0 | K155: 0 | L155: 0 | M155: 300000 | N155: 0 | O155: 0 | P155: 0 | Q155: 0 | R155: 0 | S155: 0 | T155: 0 | U155: 300000 | V155: Bienes
A156: 01/10/2025 | B156: 07/10/2025 | C156: FCC 00004-00000067 | D156: JUAN CARLOS BOTINDARI | E156: 20086277523 | F156: MO | G156: 0 | H156: 0 | I156: 0 | J156: 0 | K156: 0 | L156: 0 | M156: 300000 | N156: 0 | O156: 0 | P156: 0 | Q156: 0 | R156: 0 | S156: 0 | T156: 0 | U156: 300000 | V156: Bienes
A157: 16/10/2025 | B157: 16/10/2025 | C157: FCC 00005-00000183 | D157: LILIANA INES FERREIRA | E157: 27062343449 | F157: MO | G157: 0 | H157: 0 | I157: 0 | J157: 0 | K157: 0 | L157: 0 | M157: 600000 | N157: 0 | O157: 0 | P157: 0 | Q157: 0 | R157: 0 | S157: 0 | T157: 0 | U157: 600000 | V157: Locaciones
A158: 16/10/2025 | B158: 16/10/2025 | C158: FCC 00005-00000184 | D158: LILIANA INES FERREIRA | E158: 27062343449 | F158: MO | G158: 0 | H158: 0 | I158: 0 | J158: 0 | K158: 0 | L158: 0 | M158: 700000 | N158: 0 | O158: 0 | P158: 0 | Q158: 0 | R158: 0 | S158: 0 | T158: 0 | U158: 700000 | V158: Locaciones
A159: 20/10/2025 | B159: 20/10/2025 | C159: FCC 02001-00000971 | D159: FLAVIA ADRIANA STEINER | E159: 27167641798 | F159: MO | G159: 0 | H159: 0 | I159: 0 | J159: 0 | K159: 0 | L159: 0 | M159: 170000 | N159: 0 | O159: 0 | P159: 0 | Q159: 0 | R159: 0 | S159: 0 | T159: 0 | U159: 170000 | V159: Bienes
A160: 45930 | B160: 45930 | C160: IVA S/ EXTRACTOS | D160: Banco Credicoop | J160: =N160*100/21 -> 59218.286 | N160: =1410+11025.84 -> 12435.84 | U160: =SUM(J160:T160) -> 71654.126
A161: 45930 | B161: 45930 | C161: IVA S/ EXTRACTOS | D161: Banco Patagonia | J161: =N161*100/21 -> 41775 | N161: =7722.75+1050 -> 8772.75 | U161: =SUM(J161:T161) -> 50547.75
A162: 29/10/2025 | B162: 29/10/2025 | C162: NCA 00002-00000002 | D162: BARD MARISA SILVIA | E162: 27243660535 | F162: RI | G162: 0 | H162: 0 | I162: 0 | J162: -474914.86 | K162: 0 | L162: 0 | M162: 0 | N162: -99732.12 | O162: 0 | P162: 0 | Q162: 0 | R162: 0 | S162: 0 | T162: 0 | U162: -574646.98 | V162: Locaciones
A163: 09/10/2025 | B163: 09/10/2025 | C163: NCA 00002-00000101 | D163: MARTIN EZEQUIEL DI FEO | E163: 20272865869 | F163: RI | G163: 0 | H163: 0 | I163: 0 | J163: -13300 | K163: 0 | L163: 0 | M163: 0 | N163: -2793 | O163: 0 | P163: 0 | Q163: 0 | R163: 0 | S163: 0 | T163: 0 | U163: -16093 | V163: Bienes
A164: 17/10/2025 | B164: 17/10/2025 | C164: NCA 00003-00000503 | D164: MEDICAL FOAM S.R.L. | E164: 30707042679 | F164: RI | G164: 0 | H164: 0 | I164: 0 | J164: -1600604 | K164: 0 | L164: 0 | M164: 0 | N164: -336126.84 | O164: 0 | P164: 0 | Q164: 0 | R164: 0 | S164: 0 | T164: 0 | U164: -1936730.8 | V164: Bienes
A165: 01/10/2025 | B165: 01/10/2025 | C165: NCA 00005-00000131 | D165: MARISOL PRADO | E165: 27265302225 | F165: RI | G165: 0 | H165: 0 | I165: 0 | J165: -2500000 | K165: 0 | L165: 0 | M165: 0 | N165: -525000 | O165: 0 | P165: 0 | Q165: 0 | R165: 0 | S165: 0 | T165: 0 | U165: -3025000 | V165: Bienes
A166: 03/10/2025 | B166: 03/10/2025 | C166: NCA 00005-00000132 | D166: MARISOL PRADO | E166: 27265302225 | F166: RI | G166: 0 | H166: 0 | I166: 0 | J166: -125000 | K166: 0 | L166: 0 | M166: 0 | N166: -26250 | O166: 0 | P166: 0 | Q166: 0 | R166: 0 | S166: 0 | T166: 0 | U166: -151250 | V166: Bienes
A167: 01/10/2025 | B167: 01/10/2025 | C167: NCA 00006-00013998 | D167: SALUDTEX SA | E167: 30711553564 | F167: RI | G167: 0 | H167: 0 | I167: 0 | J167: -137991 | K167: 0 | L167: 0 | M167: 0 | N167: -28978.11 | O167: 0 | P167: 0 | Q167: 0 | R167: 0 | S167: 0 | T167: 0 | U167: -166969.11 | V167: Bienes
A168: 29/10/2025 | B168: 29/10/2025 | C168: NCA 00028-00109556 | D168: MERCADOLIBRE S.R.L. | E168: 30703088534 | F168: RI | G168: 0 | H168: 0 | I168: 0 | J168: -1626.45 | K168: 0 | L168: 0 | M168: 0 | N168: -341.55 | O168: 0 | P168: 0 | Q168: 0 | R168: 0 | S168: -48.79 | T168: 0 | U168: -2016.79 | V168: Servicios
A169: 31/10/2025 | B169: 31/10/2025 | C169: NCA 00033-00000033 | D169: OLGA ESTELA DI SALVI | E169: 27167838001 | F169: RI | G169: 0 | H169: 0 | I169: 0 | J169: -315000 | K169: 0 | L169: 0 | M169: 0 | N169: -66150 | O169: 0 | P169: 0 | Q169: 0 | R169: 0 | S169: 0 | T169: 0 | U169: -381150 | V169: Bienes
A170: 45960 | C170: NCA 00006-20898297 | D170: POSNET SOCIEDAD DE RESPONSABILIDAD LIMITADA | E170: 30620177497 | J170: 0 | M170: 0 | U170: 0
...

Sheet arcasss
B2: PEAJES | H2: FA-A | I2: 118
B3: ok contabil | H3: NC-A | I3: 8 | L3: 8
H4: FA-C | I4: 25 | L4: 25
H5: NC-C | I5: 2 | L5: 2
H6: TOTAL COMP | I6: =SUBTOTAL(9,I2:I5) -> 153
H7: total contabilium | I7: 149
A9: Fecha | B9: Tipo | C9: Punto de Venta | D9: Número Desde | E9: Número Hasta | F9: Cód. Autorización | G9: Tipo Doc. Emisor | H9: Nro. Doc. Emisor | I9: Denominación Emisor | J9: Tipo Doc. Receptor | K9: Nro. Doc. Receptor | L9: Tipo Cambio | M9: Moneda | N9: Neto Grav. IVA 0% | O9: IVA 2,5% | P9: Neto Grav. IVA 2,5% | Q9: IVA 5% | R9: Neto Grav. IVA 5% | S9: IVA 10,5% | T9: Neto Grav. IVA 10,5% | U9: IVA 21% | V9: Neto Grav. IVA 21% | W9: IVA 27% | X9: Neto Grav. IVA 27% | Y9: Neto Gravado Total | Z9: Neto No Gravado | AA9: Op. Exentas | AB9: Otros Tributos | AC9: Total IVA | AD9: Imp. Total | AE9: comp
A10: 01/10/2025 | B10: 1 - Factura A | C10: 500 | D10: 1791477 | E10: 1791477 | F10: 75397766663182 | G10: CUIT | H10: 30654118767 | I10: SOLUCIONES MULTIMEDIA S A | J10: CUIT | K10: 30710473168 | L10: 1 | M10: $ | U10: 34781 | V10: 165623.79 | Y10: 165623.79 | Z10: 0 | AA10: 0 | AB10: 6624.95 | AC10: 34781 | AD10: 207029.74
A11: 01/10/2025 | B11: 1 - Factura A | C11: 2059 | D11: 34131 | E11: 34131 | F11: 75406205517570 | G11: CUIT | H11: 30548083156 | I11: COTO CENTRO INTEGRAL DE COMERCIALIZACION SOCIEDAD ANONIMA | J11: CUIT | K11: 30710473168 | L11: 1 | M11: $ | U11: 1150.88 | V11: 5480.36 | Y11: 5480.36 | Z11: 0 | AA11: 0 | AB11: 383.62 | AC11: 1150.88 | AD11: 7014.86
A12: 01/10/2025 | B12: 1 - Factura A | C12: 5 | D12: 1679 | E12: 1679 | F12: 75405209208340 | G12: CUIT | H12: 27265302225 | I12: PRADO MARISOL | J12: CUIT | K12: 30710473168 | L12: 1 | M12: $ | U12: 26250 | V12: 125000 | Y12: 125000 | Z12: 0 | AA12: 0 | AB12: 0 | AC12: 26250 | AD12: 151250
A13: 01/10/2025 | B13: 1 - Factura A | C13: 1 | D13: 140551 | E13: 140551 | F13: 75409140621749 | G13: CUIT | H13: 30714864269 | I13: CONTABILIUM S.A. S. A. | J13: CUIT | K13: 30710473168 | L13: 1 | M13: $ | U13: 38808 | V13: 184800 | Y13: 184800 | Z13: 0 | AA13: 0 | AB13: 0 | AC13: 38808 | AD13: 223608
A14: 01/10/2025 | B14: 1 - Factura A | C14: 5 | D14: 1680 | E14: 1680 | F14: 75405214018996 | G14: CUIT | H14: 27265302225 | I14: PRADO MARISOL | J14: CUIT | K14: 30710473168 | L14: 1 | M14: $ | U14: 294000 | V14: 1400000 | Y14: 1400000 | Z14: 0 | AA14: 0 | AB14: 0 | AC14: 294000 | AD14: 1694000
A15: 01/10/2025 | B15: 1 - Factura A | C15: 5 | D15: 1676 | E15: 1676 | F15: 75405186336334 | G15: CUIT | H15: 27265302225 | I15: PRADO MARISOL | J15: CUIT | K15: 30710473168 | L15: 1 | M15: $ | U15: 525000 | V15: 2500000 | Y15: 2500000 | Z15: 0 | AA15: 0 | AB15: 0 | AC15: 525000 | AD15: 3025000
A16: 01/10/2025 | B16: 1 - Factura A | C16: 6 | D16: 96490 | E16: 96490 | F16: 75404218156994 | G16: CUIT | H16: 30711553564 | I16: SALUDTEX SA | J16: CUIT | K16: 30710473168 | L16: 1 | M16: $ | U16: 279778.59 | V16: 1332279 | Y16: 1332279 | Z16: 0 | AA16: 0 | AB16: 0 | AC16: 279778.59 | AD16: 1612057.6
A17: 01/10/2025 | B17: 1 - Factura A | C17: 6 | D17: 96491 | E17: 96491 | F17: 75404218271756 | G17: CUIT | H17: 30711553564 | I17: SALUDTEX SA | J17: CUIT | K17: 30710473168 | L17: 1 | M17: $ | U17: 147536.55 | V17: 702555 | Y17: 702555 | Z17: 0 | AA17: 0 | AB17: 0 | AC17: 147536.55 | AD17: 850091.55
A18: 01/10/2025 | B18: 1 - Factura A | C18: 6 | D18: 96492 | E18: 96492 | F18: 75404218424004 | G18: CUIT | H18: 30711553564 | I18: SALUDTEX SA | J18: CUIT | K18: 30710473168 | L18: 1 | M18: $ | U18: 6460.65 | V18: 30765 | Y18: 30765 | Z18: 0 | AA18: 0 | AB18: 0 | AC18: 6460.65 | AD18: 37225.65
A19: 15/10/2025 | B19: 1 - Factura A | C19: 50 | D19: 4670040 | E19: 4670040 | F19: 75426230181879 | G19: CUIT | H19: 30714112836 | I19: AUTOPISTAS DE BUENOS AIRES (AUBASA) SA S. A. | J19: CUIT | K19: 30710473168 | L19: 1 | M19: $ | U19: 1031.36 | V19: 4911.22 | Y19: 4911.22 | Z19: 0 | AA19: 0 | AB19: 147.34 | AC19: 1031.36 | AD19: 6089.92
A20: 31/10/2025 | B20: 1 - Factura A | C20: 50 | D20: 4706524 | E20: 4706524 | F20: 75446229190253 | G20: CUIT | H20: 30714112836 | I20: AUTOPISTAS DE BUENOS AIRES (AUBASA) SA S. A. | J20: CUIT | K20: 30710473168 | L20: 1 | M20: $ | U20: 343.78 | V20: 1637.07 | Y20: 1637.07 | Z20: 0 | AA20: 0 | AB20: 0 | AC20: 343.78 | AD20: 1980.85 | AE20: sin comp
A21: 01/10/2025 | B21: 1 - Factura A | C21: 2 | D21: 252 | E21: 252 | F21: 75402211250599 | G21: CUIT | H21: 30605344352 | I21: CONSORCIO BARTOLOME MITRE 2466 | J21: CUIT | K21: 30710473168 | L21: 1 | M21: $ | U21: 453722.01 | V21: 2160581 | Y21: 2160581 | Z21: 0 | AA21: 0 | AB21: 0 | AC21: 453722.01 | AD21: 2614303
A22: 01/10/2025 | B22: 3 - Nota de Crédito A | C22: 5 | D22: 131 | E22: 131 | F22: 75405208440708 | G22: CUIT | H22: 27265302225 | I22: PRADO MARISOL | J22: CUIT | K22: 30710473168 | L22: 1 | M22: $ | U22: 525000 | V22: 2500000 | Y22: 2500000 | Z22: 0 | AA22: 0 | AB22: 0 | AC22: 525000 | AD22: 3025000
A23: 01/10/2025 | B23: 3 - Nota de Crédito A | C23: 6 | D23: 13998 | E23: 13998 | F23: 75404232088366 | G23: CUIT | H23: 30711553564 | I23: SALUDTEX SA | J23: CUIT | K23: 30710473168 | L23: 1 | M23: $ | U23: 28978.11 | V23: 137991 | Y23: 137991 | Z23: 0 | AA23: 0 | AB23: 0 | AC23: 28978.11 | AD23: 166969.11
A24: 01/10/2025 | B24: 11 - Factura C | C24: 4 | D24: 67 | E24: 67 | F24: 75403183061118 | G24: CUIT | H24: 20086277523 | I24: GUASCH HECTOR RAUL | J24: CUIT | K24: 30710473168 | L24: 1 | M24: $ | AB24: 0 | AD24: 300000
A25: 01/10/2025 | B25: 11 - Factura C | C25: 4 | D25: 66 | E25: 66 | F25: 75403179949716 | G25: CUIT | H25: 20086277523 | I25: BOTINDARI JUAN CARLOS | J25: CUIT | K25: 30710473168 | L25: 1 | M25: $ | AB25: 0 | AD25: 300000
A26: 01/10/2025 | B26: 13 - Nota de Crédito C | C26: 4 | D26: 2 | E26: 2 | F26: 75403184483403 | G26: CUIT | H26: 20086277523 | I26: BOTINDARI JUAN CARLOS | J26: CUIT | K26: 30710473168 | L26: 1 | M26: $ | AB26: 0 | AD26: 300000
A27: 02/10/2025 | B27: 1 - Factura A | C27: 3051 | D27: 982461 | E27: 982461 | F27: 75407377852221 | G27: CUIT | H27: 30678814357 | I27: TELEFONICA MOVILES ARGENTINA SOCIEDAD ANONIMA | J27: CUIT | K27: 30710473168 | L27: 1 | M27: $ | W27: 15634.89 | X27: 57907 | Y27: 57907 | Z27: 0 | AA27: 0 | AB27: 7223.1 | AC27: 15634.89 | AD27: 80764.99
A28: 02/10/2025 | B28: 1 - Factura A | C28: 8 | D28: 476 | E28: 476 | F28: 75404371927575 | G28: CUIT | H28: 30643518364 | I28: FARMACIA DE MEDRANO 533 SOCIEDAD EN COMANDITA SIMPLE | J28: CUIT | K28: 30710473168 | L28: 1 | M28: $ | U28: 18637.5 | V28: 88750 | Y28: 88750 | Z28: 0 | AA28: 0 | AB28: 0 | AC28: 18637.5 | AD28: 107387.5
A29: 02/10/2025 | B29: 1 - Factura A | C29: 2 | D29: 1576 | E29: 1576 | F29: 75409356956133 | G29: CUIT | H29: 20272865869 | I29: DI FEO MARTIN EZEQUIEL | J29: CUIT | K29: 30710473168 | L29: 1 | M29: $ | U29: 14574 | V29: 69400 | Y29: 69400 | Z29: 0 | AA29: 0 | AB29: 0 | AC29: 14574 | AD29: 83974
A30: 02/10/2025 | B30: 1 - Factura A | C30: 17 | D30: 13744 | E30: 13744 | F30: 75400375536461 | G30: CUIT | H30: 30661143610 | I30: ORTOPEDIA BERNAT SRL | J30: CUIT | K30: 30710473168 | L30: 1 | M30: $ | U30: 21588 | V30: 102800 | Y30: 102800 | Z30: 0 | AA30: 0 | AB30: 4112 | AC30: 21588 | AD30: 128500
A31: 02/10/2025 | B31: 1 - Factura A | C31: 4 | D31: 19861 | E31: 19861 | F31: 75403288996009 | G31: CUIT | H31: 30714440183 | I31: INDUSTRIAS FERNANDEZ GARRIDO SA | J31: CUIT | K31: 30710473168 | L31: 1 | M31: $ | U31: 5684.76 | V31: 27070.3 | Y31: 27070.3 | Z31: 0 | AA31: 0 | AB31: 0 | AC31: 5684.76 | AD31: 32755.06
A32: 02/10/2025 | B32: 1 - Factura A | C32: 1 | D32: 1031096 | E32: 1031096 | F32: 75419072334708 | G32: CUIT | H32: 33716307749 | I32: VERISURE ARGENTINA MONITOREO DE ALARMAS SA | J32: CUIT | K32: 30710473168 | L32: 1 | M32: $ | U32: 13093.29 | V32: 62349.01 | Y32: 62349.01 | Z32: 0 | AA32: 0 | AB32: 2493.96 | AC32: 13093.29 | AD32: 77936.26
A33: 02/10/2025 | B33: 1 - Factura A | C33: 7 | D33: 55 | E33: 55 | F33: 75403337698338 | G33: CUIT | H33: 27325223273 | I33: SOUSA ALDERETE ALEJANDRA MABEL | J33: CUIT | K33: 30710473168 | L33: 1 | M33: $ | U33: 462000 | V33: 2200000 | Y33: 2200000 | Z33: 0 | AA33: 0 | AB33: 0 | AC33: 462000 | AD33: 2662000
A34: 02/10/2025 | B34: 11 - Factura C | C34: 1 | D34: 43 | E34: 43 | F34: 75401342703675 | G34: CUIT | H34: 20311855671 | I34: GUASCH HECTOR RAUL | J34: CUIT | K34: 30710473168 | L34: 1 | M34: $ | AB34: 0 | AD34: 290000
A35: 03/10/2025 | B35: 1 - Factura A | C35: 2 | D35: 1582 | E35: 1582 | F35: 75409440515122 | G35: CUIT | H35: 20272865869 | I35: DI FEO MARTIN EZEQUIEL | J35: CUIT | K35: 30710473168 | L35: 1 | M35: $ | U35: 64932 | V35: 309200 | Y35: 309200 | Z35: 0 | AA35: 0 | AB35: 0 | AC35: 64932 | AD35: 374132
A36: 03/10/2025 | B36: 1 - Factura A | C36: 26 | D36: 215680 | E36: 215680 | F36: 75407512016610 | G36: CUIT | H36: 30708847247 | I36: EXPRESO LANCIONI S.A. | J36: CUIT | K36: 30710473168 | L36: 1 | M36: $ | U36: 15703.62 | V36: 74779.14 | Y36: 74779.14 | Z36: 0 | AA36: 0 | AB36: 2991.17 | AC36: 15703.62 | AD36: 93473.93
A37: 03/10/2025 | B37: 1 - Factura A | C37: 5 | D37: 1682 | E37: 1682 | F37: 75405522210939 | G37: CUIT | H37: 27265302225 | I37: PRADO MARISOL | J37: CUIT | K37: 30710473168 | L37: 1 | M37: $ | U37: 262500 | V37: 1250000 | Y37: 1250000 | Z37: 0 | AA37: 0 | AB37: 0 | AC37: 262500 | AD37: 1512500
A38: 03/10/2025 | B38: 1 - Factura A | C38: 1054 | D38: 381 | E38: 381 | F38: 75401449551620 | G38: CUIT | H38: 30685849751 | I38: DIA ARGENTINA S A | J38: CUIT | K38: 30710473168 | L38: 1 | M38: $ | U38: 1133.31 | V38: 5396.69 | Y38: 5396.69 | Z38: 0 | AA38: 0 | AB38: 215.87 | AC38: 1133.31 | AD38: 6745.87
A39: 03/10/2025 | B39: 1 - Factura A | C39: 3 | D39: 930 | E39: 930 | F39: 75409454635742 | G39: CUIT | H39: 23076996989 | I39: GIULIETTI LUIS ALBERTO | J39: CUIT | K39: 30710473168 | L39: 1 | M39: $ | U39: 2776.86 | V39: 13223.14 | Y39: 13223.14 | Z39: 0 | AA39: 0 | AB39: 0 | AC39: 2776.86 | AD39: 16000
A40: 03/10/2025 | B40: 3 - Nota de Crédito A | C40: 5 | D40: 132 | E40: 132 | F40: 75405520316587 | G40: CUIT | H40: 27265302225 | I40: PRADO MARISOL | J40: CUIT | K40: 30710473168 | L40: 1 | M40: $ | U40: 26250 | V40: 125000 | Y40: 125000 | Z40: 0 | AA40: 0 | AB40: 0 | AC40: 26250 | AD40: 151250
A41: 03/10/2025 | B41: 11 - Factura C | C41: 2 | D41: 634 | E41: 634 | F41: 75407495074987 | G41: CUIT | H41: 20247881957 | I41: CAMPA DANIEL JORGE | J41: CUIT | K41: 30710473168 | L41: 1 | M41: $ | AB41: 0 | AD41: 13400
A42: 04/10/2025 | B42: 11 - Factura C | C42: 2 | D42: 138 | E42: 138 | F42: 75408636655570 | G42: CUIT | H42: 27315710508 | I42: RIVERO GABRIELA ROCIO | J42: CUIT | K42: 30710473168 | L42: 1 | M42: $ | AB42: 0 | AD42: 51030
A43: 06/10/2025 | B43: 1 - Factura A | C43: 17 | D43: 3413 | E43: 3413 | F43: 75401861436133 | G43: CUIT | H43: 30711764921 | I43: RELIEF CENTER S.R.L. | J43: CUIT | K43: 30710473168 | L43: 1 | M43: $ | U43: 44110.71 | V43: 210051 | Y43: 210051 | Z43: 0 | AA43: 0 | AB43: 0 | AC43: 44110.71 | AD43: 254161.71
A44: 06/10/2025 | B44: 1 - Factura A | C44: 120 | D44: 5947 | E44: 5947 | F44: 75405819860121 | G44: CUIT | H44: 30587197215 | I44: PANATEL SOCIEDAD ANONIMA | J44: CUIT | K44: 30710473168 | L44: 1 | M44: $ | U44: 31239.67 | V44: 148760.33 | Y44: 148760.33 | Z44: 0 | AA44: 0 | AB44: 5950.41 | AC44: 31239.67 | AD44: 185950.41
A45: 06/10/2025 | B45: 11 - Factura C | C45: 2 | D45: 380 | E45: 380 | F45: 75418135005567 | G45: CUIT | H45: 27265832178 | I45: BLASCO MARIA GUADALUPE | J45: CUIT | K45: 30710473168 | L45: 1 | M45: $ | AB45: 0 | AD45: 3200000
A46: 07/10/2025 | B46: 1 - Factura A | C46: 15 | D46: 5031 | E46: 5031 | F46: 75403963974821 | G46: CUIT | H46: 30688140923 | I46: COLTEX S R L | J46: CUIT | K46: 30710473168 | L46: 1 | M46: $ | U46: 26619.92 | V46: 126761.5 | Y46: 126761.5 | Z46: 0 | AA46: 0 | AB46: 0 | AC46: 26619.92 | AD46: 153381.42
A47: 07/10/2025 | B47: 1 - Factura A | C47: 3 | D47: 3479058 | E47: 3479058 | F47: 75409982100194 | G47: CUIT | H47: 30712019359 | I47: LINKEDSTORE ARGENTINA S.R.L. | J47: CUIT | K47: 30710473168 | L47: 1 | M47: $ | U47: 3731.23 | V47: 17767.77 | Y47: 17767.77 | Z47: 0 | AB47: 710.72 | AC47: 3731.23 | AD47: 22209.72 | AE47: sin comp
A48: 07/10/2025 | B48: 1 - Factura A | C48: 6 | D48: 3443 | E48: 3443 | F48: 75404953036460 | G48: CUIT | H48: 30715775014 | I48: GRUPO MAXIMUS S.R.L. | J48: CUIT | K48: 30710473168 | L48: 1 | M48: $ | S48: 4028.96 | T48: 38371.04 | Y48: 38371.04 | Z48: 0 | AA48: 0 | AB48: 1534.84 | AC48: 4028.96 | AD48: 43934.84
A49: 07/10/2025 | B49: 11 - Factura C | C49: 1 | D49: 5 | E49: 5 | F49: 75402996095252 | G49: CUIT | H49: 27380284052 | I49: CIVALE PAULA | J49: CUIT | K49: 30710473168 | L49: 1 | M49: $ | AB49: 0 | AD49: 4365000
A50: 07/10/2025 | B50: 11 - Factura C | C50: 1 | D50: 19 | E50: 19 | F50: 75403997414283 | G50: CUIT | H50: 27443612713 | I50: MIGOYA MORIONDO SOFIA | J50: CUIT | K50: 30710473168 | L50: 1 | M50: $ | AB50: 0 | AD50: 870000
A51: 08/10/2025 | B51: 1 - Factura A | C51: 5 | D51: 1694 | E51: 1694 | F51: 75415156068683 | G51: CUIT | H51: 27265302225 | I51: PRADO MARISOL | J51: CUIT | K51: 30710473168 | L51: 1 | M51: $ | U51: 294000 | V51: 1400000 | Y51: 1400000 | Z51: 0 | AA51: 0 | AB51: 0 | AC51: 294000 | AD51: 1694000
A52: 08/10/2025 | B52: 1 - Factura A | C52: 9 | D52: 23056 | E52: 23056 | F52: 75412180556662 | G52: CUIT | H52: 20207044262 | I52: GARCIA HORACIO FERNANDO | J52: CUIT | K52: 30710473168 | L52: 1 | M52: $ | U52: 4915.21 | V52: 23405.78 | Y52: 23405.78 | Z52: 0 | AA52: 0 | AB52: 0 | AC52: 4915.21 | AD52: 28320.99
A53: 08/10/2025 | B53: 1 - Factura A | C53: 2 | D53: 1598 | E53: 1598 | F53: 75419162856166 | G53: CUIT | H53: 20272865869 | I53: DI FEO MARTIN EZEQUIEL | J53: CUIT | K53: 30710473168 | L53: 1 | M53: $ | U53: 14007 | V53: 66700 | Y53: 66700 | Z53: 0 | AA53: 0 | AB53: 0 | AC53: 14007 | AD53: 80707
A54: 08/10/2025 | B54: 1 - Factura A | C54: 1055 | D54: 908 | E54: 908 | F54: 75411108275705 | G54: CUIT | H54: 30685849751 | I54: DIA ARGENTINA S A | J54: CUIT | K54: 30710473168 | L54: 1 | M54: $ | U54: 1135.56 | V54: 5407.44 | Y54: 5407.44 | Z54: 0 | AA54: 0 | AB54: 216.3 | AC54: 1135.56 | AD54: 6759.3
A55: 01/10/2025 | B55: 1 - Factura A | C55: 711 | D55: 7668587 | E55: 7668587 | F55: 35399087215211 | G55: CUIT | H55: 30677237119 | I55: AUTOPISTAS DEL SOL S A | J55: CUIT | K55: 30710473168 | L55: 1 | M55: $ | U55: 1941.32 | V55: 9244.34 | Y55: 9244.34 | Z55: 0 | AA55: 277.33 | AB55: 369.77 | AC55: 1941.32 | AD55: 11832.76
A56: 08/10/2025 | B56: 1 - Factura A | C56: 7 | D56: 56 | E56: 56 | F56: 75413107535128 | G56: CUIT | H56: 27325223273 | I56: SOUSA ALDERETE ALEJANDRA MABEL | J56: CUIT | K56: 30710473168 | L56: 1 | M56: $ | U56: 273000 | V56: 1300000 | Y56: 1300000 | Z56: 0 | AA56: 0 | AB56: 0 | AC56: 273000 | AD56: 1573000
A57: 09/10/2025 | B57: 1 - Factura A | C57: 1055 | D57: 910 | E57: 910 | F57: 75411242633841 | G57: CUIT | H57: 30685849751 | I57: DIA ARGENTINA S A | J57: CUIT | K57: 30710473168 | L57: 1 | M57: $ | U57: 343.64 | V57: 1636.36 | Y57: 1636.36 | Z57: 0 | AA57: 0 | AB57: 0 | AC57: 343.64 | AD57: 1980
A58: 09/10/2025 | B58: 1 - Factura A | C58: 3101 | D58: 390491 | E58: 390491 | F58: 75417293327196 | G58: CUIT | H58: 30678814357 | I58: TELEFONICA MOVILES ARGENTINA SOCIEDAD ANONIMA | J58: CUIT | K58: 30710473168 | L58: 1 | M58: $ | W58: 16530.15 | X58: 61222.8 | Y58: 61222.8 | Z58: 0 | AA58: 0 | AB58: 4285.59 | AC58: 16530.15 | AD58: 82038.54
A59: 09/10/2025 | B59: 1 - Factura A | C59: 2 | D59: 8600 | E59: 8600 | F59: 75418292258895 | G59: CUIT | H59: 30643862928 | I59: OUTLANDISH S R L | J59: CUIT | K59: 30710473168 | L59: 1 | M59: $ | U59: 61923.97 | V59: 294876.03 | Y59: 294876.03 | Z59: 0 | AA59: 0 | AB59: 0 | AC59: 61923.97 | AD59: 356800
A60: 09/10/2025 | B60: 1 - Factura A | C60: 700 | D60: 2758592 | E60: 2758592 | F60: 75412448694790 | G60: CUIT | H60: 30715804812 | I60: CORREDORES VIALES SOCIEDAD ANONIMA | J60: CUIT | K60: 30710473168 | L60: 1 | M60: $ | U60: 2620.76 | V60: 12479.78 | Y60: 12479.78 | Z60: 0 | AA60: 0 | AB60: 499.19 | AC60: 2620.76 | AD60: 15599.73
A61: 09/10/2025 | B61: 1 - Factura A | C61: 6 | D61: 123 | E61: 123 | F61: 75416306146099 | G61: CUIT | H61: 30711610096 | I61: 46 SPEED S.A. | J61: CUIT | K61: 30710473168 | L61: 1 | M61: $ | U61: 181780.2 | V61: 865620 | Y61: 865620 | Z61: 0 | AA61: 0 | AB61: 0 | AC61: 181780.2 | AD61: 1047400.2
A62: 09/10/2025 | B62: 1 - Factura A | C62: 6 | D62: 121 | E62: 121 | F62: 75416296869603 | G62: CUIT | H62: 30711610096 | I62: 46 SPEED S.A. | J62: CUIT | K62: 30710473168 | L62: 1 | M62: $ | U62: 181780.2 | V62: 865620 | Y62: 865620 | Z62: 0 | AA62: 0 | AB62: 0 | AC62: 181780.2 | AD62: 1047400.2
A63: 09/10/2025 | B63: 3 - Nota de Crédito A | C63: 2 | D63: 101 | E63: 101 | F63: 75419233862932 | G63: CUIT | H63: 20272865869 | I63: DI FEO MARTIN EZEQUIEL | J63: CUIT | K63: 30710473168 | L63: 1 | M63: $ | U63: 2793 | V63: 13300 | Y63: 13300 | Z63: 0 | AA63: 0 | AB63: 0 | AC63: 2793 | AD63: 16093
A64: 09/10/2025 | B64: 11 - Factura C | C64: 1 | D64: 30 | E64: 30 | F64: 75415290283482 | G64: CUIT | H64: 27443612705 | I64: MIGOYA MORIONDO MARIA INES | J64: CUIT | K64: 30710473168 | L64: 1 | M64: $ | AB64: 0 | AD64: 900000
A65: 13/10/2025 | B65: 1 - Factura A | C65: 8 | D65: 2509 | E65: 2509 | F65: 75419789475716 | G65: CUIT | H65: 23288035059 | I65: MENDIZABAL RAUL EUGENIO | J65: CUIT | K65: 30710473168 | L65: 1 | M65: $ | U65: 1969.83 | V65: 9380.17 | Y65: 9380.17 | Z65: 0 | AA65: 0 | AB65: 0 | AC65: 1969.83 | AD65: 11350
A66: 13/10/2025 | B66: 1 - Factura A | C66: 2 | D66: 6499 | E66: 6499 | F66: 75417753007542 | G66: CUIT | H66: 20263170017 | I66: ESPERANZA MIGUEL ANGEL | J66: CUIT | K66: 30710473168 | L66: 1 | M66: $ | U66: 3642.89 | V66: 17347.11 | Y66: 17347.11 | Z66: 0 | AA66: 0 | AB66: 0 | AC66: 3642.89 | AD66: 20990 | AE66: sin comp
A67: 13/10/2025 | B67: 1 - Factura A | C67: 3 | D67: 149 | E67: 149 | F67: 75412711422997 | G67: CUIT | H67: 27160577652 | I67: IZQUIERDO MONICA BEATRIZ | J67: CUIT | K67: 30710473168 | L67: 1 | M67: $ | U67: 31433.01 | V67: 149681 | Y67: 149681 | Z67: 0 | AA67: 0 | AB67: 0 | AC67: 31433.01 | AD67: 181114.01 | AE67: sin comp
A68: 14/10/2025 | B68: 1 - Factura A | C68: 2 | D68: 12960 | E68: 12960 | F68: 75412840648970 | G68: CUIT | H68: 30714331082 | I68: ORTOPEDIA CASA ESCALADA S.R.L. | J68: CUIT | K68: 30710473168 | L68: 1 | M68: $ | U68: 9693.43 | V68: 46159.19 | Y68: 46159.19 | Z68: 0 | AA68: 0 | AB68: 0 | AC68: 9693.43 | AD68: 55852.62
A69: 14/10/2025 | B69: 1 - Factura A | C69: 104 | D69: 10864512 | E69: 10864512 | F69: 75412938430375 | G69: CUIT | H69: 30715804812 | I69: CORREDORES VIALES SOCIEDAD ANONIMA | J69: CUIT | K69: 30710473168 | L69: 1 | M69: $ | U69: 873.58 | V69: 4159.94 | Y69: 4159.94 | Z69: 0 | AA69: 0 | AB69: 166.4 | AC69: 873.58 | AD69: 5199.92 | AE69: sin comp
A70: 14/10/2025 | B70: 1 - Factura A | C70: 5 | D70: 6507 | E70: 6507 | F70: 75413860583282 | G70: CUIT | H70: 30715833243 | I70: BIODINAMICA ASISTENCIA S. R. L. | J70: CUIT | K70: 30710473168 | L70: 1 | M70: $ | U70: 79385.25 | V70: 378025 | Y70: 378025 | Z70: 0 | AA70: 0 | AB70: 0 | AC70: 79385.25 | AD70: 457410.25
A71: 14/10/2025 | B71: 1 - Factura A | C71: 7 | D71: 22647 | E71: 22647 | F71: 75418838773231 | G71: CUIT | H71: 30709214078 | I71: REHAVITA S.A. | J71: CUIT | K71: 30710473168 | L71: 1 | M71: $ | S71: 33133.8 | T71: 315560 | Y71: 315560 | Z71: 0 | AA71: 0 | AB71: 0 | AC71: 33133.8 | AD71: 348693.8
A72: 14/10/2025 | B72: 1 - Factura A | C72: 2059 | D72: 34334 | E72: 34334 | F72: 75416897570101 | G72: CUIT | H72: 30548083156 | I72: COTO CENTRO INTEGRAL DE COMERCIALIZACION SOCIEDAD ANONIMA | J72: CUIT | K72: 30710473168 | L72: 1 | M72: $ | U72: 2506.03 | V72: 11933.46 | Y72: 11933.46 | Z72: 0 | AA72: 0 | AB72: 835.34 | AC72: 2506.03 | AD72: 15274.83
A73: 14/10/2025 | B73: 1 - Factura A | C73: 5 | D73: 6509 | E73: 6509 | F73: 75413867140825 | G73: CUIT | H73: 30715833243 | I73: BIODINAMICA ASISTENCIA S. R. L. | J73: CUIT | K73: 30710473168 | L73: 1 | M73: $ | U73: 24195.15 | V73: 115215 | Y73: 115215 | Z73: 0 | AA73: 0 | AB73: 0 | AC73: 24195.15 | AD73: 139410.15
A74: 14/10/2025 | B74: 1 - Factura A | C74: 104 | D74: 10907502 | E74: 10907502 | F74: 75412951609330 | G74: CUIT | H74: 30715804812 | I74: CORREDORES VIALES SOCIEDAD ANONIMA | J74: CUIT | K74: 30710473168 | L74: 1 | M74: $ | U74: 436.79 | V74: 2079.97 | Y74: 2079.97 | Z74: 0 | AA74: 0 | AB74: 83.2 | AC74: 436.79 | AD74: 2599.96 | AE74: sin comp
A75: 14/10/2025 | B75: 1 - Factura A | C75: 6 | D75: 59344 | E75: 59344 | F75: 75418898964636 | G75: CUIT | H75: 30710177658 | I75: TARGET MEDICAL S.A. | J75: CUIT | K75: 30710473168 | L75: 1 | M75: $ | U75: 174709.92 | V75: 831952 | Y75: 831952 | Z75: 0 | AA75: 0 | AB75: 33278.08 | AC75: 174709.92 | AD75: 1039940
A76: 14/10/2025 | B76: 11 - Factura C | C76: 1 | D76: 1 | E76: 1 | F76: 75410883457213 | G76: CUIT | H76: 20421434450 | I76: GALTIERI WALTER QUIMEY | J76: CUIT | K76: 30710473168 | L76: 1 | M76: $ | AB76: 0 | AD76: 260000
A77: 15/10/2025 | B77: 1 - Factura A | C77: 5 | D77: 6522 | E77: 6522 | F77: 75423002311217 | G77: CUIT | H77: 30715833243 | I77: BIODINAMICA ASISTENCIA S. R. L. | J77: CUIT | K77: 30710473168 | L77: 1 | M77: $ | U77: 21621.6 | V77: 102960 | Y77: 102960 | Z77: 0 | AA77: 0 | AB77: 0 | AC77: 21621.6 | AD77: 124581.6
A78: 15/10/2025 | B78: 1 - Factura A | C78: 5 | D78: 6523 | E78: 6523 | F78: 75423008286348 | G78: CUIT | H78: 30715833243 | I78: BIODINAMICA ASISTENCIA S. R. L. | J78: CUIT | K78: 30710473168 | L78: 1 | M78: $ | U78: 7068.76 | V78: 33660.78 | Y78: 33660.78 | Z78: 0 | AA78: 0 | AB78: 0 | AC78: 7068.76 | AD78: 40729.54
A79: 15/10/2025 | B79: 1 - Factura A | C79: 2031 | D79: 230808 | E79: 230808 | F79: 75420966246058 | G79: CUIT | H79: 30516186670 | I79: DEHEZA SOCIEDAD ANONIMA INDUSTRIAL COMERCIAL FINANCIERA INMOBILIARIA | J79: CUIT | K79: 30710473168 | L79: 1 | M79: $ | U79: 10759.37 | V79: 51235.1 | Y79: 51235.1 | Z79: 0 | AA79: 0 | AB79: 16073.15 | AC79: 10759.37 | AD79: 78067.62
A80: 15/10/2025 | B80: 1 - Factura A | C80: 7 | D80: 22677 | E80: 22677 | F80: 75428036459085 | G80: CUIT | H80: 30709214078 | I80: REHAVITA S.A. | J80: CUIT | K80: 30710473168 | L80: 1 | M80: $ | S80: 91963.2 | T80: 875840 | Y80: 875840 | Z80: 0 | AA80: 0 | AB80: 0 | AC80: 91963.2 | AD80: 967803.2
A81: 16/10/2025 | B81: 1 - Factura A | C81: 711 | D81: 7729611 | E81: 7729611 | F81: 35419067819498 | G81: CUIT | H81: 30677237119 | I81: AUTOPISTAS DEL SOL S A | J81: CUIT | K81: 30710473168 | L81: 1 | M81: $ | U81: 1286.11 | V81: 6124.31 | Y81: 6124.31 | Z81: 0 | AA81: 183.73 | AB81: 244.97 | AC81: 1286.11 | AD81: 7839.12
A82: 08/10/2025 | B82: 1 - Factura A | C82: 5015 | D82: 1018189 | E82: 1018189 | F82: 75414111787024 | G82: CUIT | H82: 30574876474 | I82: AUTOPISTAS URBANAS S. A. | J82: CUIT | K82: 30710473168 | L82: 1 | M82: $ | N82: 0.2 | U82: 7536.02 | V82: 35885.79 | Y82: 35885.99 | Z82: 0 | AA82: 0 | AB82: 4665.16 | AC82: 7536.02 | AD82: 48087.17
A83: 15/10/2025 | B83: 1 - Factura A | C83: 5015 | D83: 1027855 | E83: 1027855 | F83: 75424112493005 | G83: CUIT | H83: 30574876474 | I83: AUTOPISTAS URBANAS S. A. | J83: CUIT | K83: 30710473168 | L83: 1 | M83: $ | N83: 0.09 | U83: 3922.3 | V83: 18677.6 | Y83: 18677.69 | Z83: 0 | AA83: 0 | AB83: 2428.09 | AC83: 3922.3 | AD83: 25028.08
A84: 15/10/2025 | B84: 1 - Factura A | C84: 6 | D84: 127 | E84: 127 | F84: 75426020272672 | G84: CUIT | H84: 30711610096 | I84: 46 SPEED S.A. | J84: CUIT | K84: 30710473168 | L84: 1 | M84: $ | U84: 151200 | V84: 720000 | Y84: 720000 | Z84: 0 | AA84: 0 | AB84: 0 | AC84: 151200 | AD84: 871200
A85: 15/10/2025 | B85: 1 - Factura A | C85: 3 | D85: 7009 | E85: 7009 | F85: 75429006101848 | G85: CUIT | H85: 30707042679 | I85: MEDICAL FOAM S.R.L. | J85: CUIT | K85: 30710473168 | L85: 1 | M85: $ | U85: 336126.84 | V85: 1600604 | Y85: 1600604 | Z85: 0 | AA85: 0 | AB85: 0 | AC85: 336126.84 | AD85: 1936730.8
A86: 15/10/2025 | B86: 1 - Factura A | C86: 4 | D86: 555 | E86: 555 | F86: 75425969134392 | G86: CUIT | H86: 20379223185 | I86: AYALA MAURICIO JUAN JOSE | J86: CUIT | K86: 30710473168 | L86: 1 | M86: $ | U86: 41892.9 | V86: 199490 | Y86: 199490 | Z86: 0 | AA86: 0 | AB86: 0 | AC86: 41892.9 | AD86: 241382.9
A87: 16/10/2025 | B87: 1 - Factura A | C87: 2 | D87: 1613 | E87: 1613 | F87: 75429183332107 | G87: CUIT | H87: 20272865869 | I87: DI FEO MARTIN EZEQUIEL | J87: CUIT | K87: 30710473168 | L87: 1 | M87: $ | U87: 32592 | V87: 155200 | Y87: 155200 | Z87: 0 | AA87: 0 | AB87: 0 | AC87: 32592 | AD87: 187792
A88: 16/10/2025 | B88: 1 - Factura A | C88: 5 | D88: 6531 | E88: 6531 | F88: 75423125367040 | G88: CUIT | H88: 30715833243 | I88: BIODINAMICA ASISTENCIA S. R. L. | J88: CUIT | K88: 30710473168 | L88: 1 | M88: $ | U88: 90768.51 | V88: 432231 | Y88: 432231 | Z88: 0 | AA88: 0 | AB88: 0 | AC88: 90768.51 | AD88: 522999.51
A89: 23/10/2025 | B89: 1 - Factura A | C89: 5015 | D89: 1036311 | E89: 1036311 | F89: 75434997968381 | G89: CUIT | H89: 30574876474 | I89: AUTOPISTAS URBANAS S. A. | J89: CUIT | K89: 30710473168 | L89: 1 | M89: $ | N89: 0.22 | U89: 7513.12 | V89: 35776.78 | Y89: 35777 | Z89: 0 | AA89: 0 | AB89: 4650.99 | AC89: 7513.12 | AD89: 47941.11
A90: 31/10/2025 | B90: 1 - Factura A | C90: 5009 | D90: 1680484 | E90: 1680484 | F90: 75444155618397 | G90: CUIT | H90: 30574876474 | I90: AUTOPISTAS URBANAS S. A. | J90: CUIT | K90: 30710473168 | L90: 1 | M90: $ | N90: 0.03 | U90: 1237.13 | V90: 5891.09 | Y90: 5891.12 | Z90: 0 | AA90: =+V90*0.04 -> 235.6436 | AB90: 765.84 | AC90: 1237.13 | AD90: 7894.09 | AE90: sin comp
A91: 16/10/2025 | B91: 11 - Factura C | C91: 2 | D91: 651 | E91: 651 | F91: 75427155899920 | G91: CUIT | H91: 20247881957 | I91: CAMPA DANIEL JORGE | J91: CUIT | K91: 30710473168 | L91: 1 | M91: $ | AB91: 0 | AD91: 21300
A92: 16/10/2025 | B92: 11 - Factura C | C92: 1 | D92: 44 | E92: 44 | F92: 75421150383363 | G92: CUIT | H92: 20311855671 | I92: GUASCH HECTOR RAUL | J92: CUIT | K92: 30710473168 | L92: 1 | M92: $ | AB92: 0 | AD92: 557300
A93: 16/10/2025 | B93: 11 - Factura C | C93: 5 | D93: 183 | E93: 183 | F93: 75429173819933 | G93: CUIT | H93: 27062343449 | I93: FERREIRA LILIANA INES | J93: CUIT | K93: 30710473168 | L93: 1 | M93: $ | AB93: 0 | AD93: 600000
A94: 16/10/2025 | B94: 11 - Factura C | C94: 3 | D94: 12 | E94: 12 | F94: 75420162876634 | G94: CUIT | H94: 20310489930 | I94: OVIEDO LUIS ALBERTO | J94: CUIT | K94: 30710473168 | L94: 1 | M94: $ | AB94: 0 | AD94: 922580
A95: 16/10/2025 | B95: 11 - Factura C | C95: 5 | D95: 184 | E95: 184 | F95: 75429173906219 | G95: CUIT | H95: 27062343449 | I95: FERREIRA LILIANA INES | J95: CUIT | K95: 30710473168 | L95: 1 | M95: $ | AB95: 0 | AD95: 700000
A96: 17/10/2025 | B96: 1 - Factura A | C96: 4 | D96: 88963 | E96: 88963 | F96: 75426318002119 | G96: CUIT | H96: 30714749206 | I96: EBOX S.A. | J96: CUIT | K96: 30710473168 | L96: 1 | M96: $ | S96: 24325.7 | T96: 231673.3 | U96: 355.17 | V96: 1691.3 | Y96: 233364.6 | Z96: 0 | AA96: 0 | AB96: 0 | AC96: 24680.87 | AD96: 258045.47 | AE96: sin comp
A97: 17/10/2025 | B97: 1 - Factura A | C97: 1055 | D97: 918 | E97: 918 | F97: 75421304979446 | G97: CUIT | H97: 30685849751 | I97: DIA ARGENTINA S A | J97: CUIT | K97: 30710473168 | L97: 1 | M97: $ | U97: 343.64 | V97: 1636.36 | Y97: 1636.36 | Z97: 0 | AA97: 0 | AB97: 0 | AC97: 343.64 | AD97: 1980
A98: 17/10/2025 | B98: 3 - Nota de Crédito A | C98: 3 | D98: 503 | E98: 503 | F98: 75429317561410 | G98: CUIT | H98: 30707042679 | I98: MEDICAL FOAM S.R.L. | J98: CUIT | K98: 30710473168 | L98: 1 | M98: $ | U98: 336126.84 | V98: 1600604 | Y98: 1600604 | Z98: 0 | AA98: 0 | AB98: 0 | AC98: 336126.84 | AD98: 1936730.8
A99: 17/10/2025 | B99: 11 - Factura C | C99: 3 | D99: 13 | E99: 13 | F99: 75420308126642 | G99: CUIT | H99: 20310489930 | I99: OVIEDO LUIS ALBERTO | J99: CUIT | K99: 30710473168 | L99: 1 | M99: $ | AB99: 0 | AD99: 500000
A100: 20/10/2025 | B100: 1 - Factura A | C100: 5 | D100: 67 | E100: 67 | F100: 75423624068395 | G100: CUIT | H100: 20929183143 | I100: MA JUN | J100: CUIT | K100: 30710473168 | L100: 1 | M100: $ | U100: 23100 | V100: 110000 | Y100: 110000 | Z100: 0 | AA100: 0 | AB100: 0 | AC100: 23100 | AD100: 133100
A101: 20/10/2025 | B101: 11 - Factura C | C101: 2 | D101: 14 | E101: 14 | F101: 75421570215782 | G101: CUIT | H101: 27344304551 | I101: BOCCACCI MARIA FLORENCIA | J101: CUIT | K101: 30710473168 | L101: 1 | M101: $ | AB101: 0 | AD101: 600000
A102: 20/10/2025 | B102: 11 - Factura C | C102: 2001 | D102: 971 | E102: 971 | F102: 75428615213447 | G102: CUIT | H102: 27167641798 | I102: STEINER FLAVIA ADRIANA | J102: CUIT | K102: 30710473168 | L102: 1 | M102: $ | AB102: 0 | AD102: 170000
...
