Workbook
Name partner_id: Configuracion!$B$332

Sheet Configuracion
F1: CUIT | G1: Cargar sin guiones
F2: RAZON SOCIAL | G2: Maximo 30 caracteres
A3: CUIT | B3: RAZON SOCIAL | C3: DETALLE | F3: DETALLE | G3: Cargar tipo de gasto
A4: 30628205090 | B4: ALBAMIE SA | C4: CLIENTE
A5: 30711678820 | B5: 2PSI INGENIERIA SRL | C5: PROVEEDOR
A6: 33716367539 | B6: 3PI S.A.S. | C6: PROVEEDOR
A7: 30660373108 | B7: ABC SA | C7: VARIOS
A8: 20300210881 | B8: ABOY DIEGO OSCAR | C8: PROVEEDOR
A9: 27229910782 | B9: ABUGAUCH MARIA DE LOS ANGELES | C9: PROVEEDOR
A10: 20242709897 | B10: ABUGAUCH VICTOR HUGO | C10: PROVEEDOR
A11: 20281669053 | B11: ACOSTA JAVIER GUSTAVO | C11: FLETE
A12: 20174240125 | B12: ACOSTA OSCAR ISIDRO | C12: VARIOS
A13: 30641659106 | B13: AGRISOL SA | C13: VARIOS
A14: 33709914109 | B14: ALAN COLLECTION SA | C14: VARIOS
A15: 20267161616 | B15: ALBAJARI DIEGO MARCOS | C15: VARIOS
... A155: 30537679855 | B155: ESTACION LIMA SA | C155: VARIOS
A156: 30-56864959-8 | B156: EXPRESO BISONTE SRL | C156: FLETE
A157: 30708542349 | B157: EXPRESO FORMOSA SRL | C157: FLETE
A158: 30526582884 | B158: EXPRESO MAR DEL PLATA SA | C158: FLETE
A159: 30577744579 | B159: EXPRESO TROLE SRL | C159: FLETE
A160: 30715949292 | B160: EYPAPEL SAS | C160: GASTOS VARIOS
A161: 30715980807 | B161: FABORT SRL | C161: PROVEEDOR
A162: 20359718765 | B162: FAIL ABRAHAM | C162: VARIOS
A163: 30643518364 | B163: FARMACIA DE MEDRANO SCS | C163: PROVEEDOR
A164: 30692138747 | B164: FARMACITY SA | C164: VARIOS
A165: 33712234429 | B165: FEDAGAS SA | C165: VARIOS
A166: 20353576012 | B166: FEDERICO PABLO FEOLA | C166: VARIOS
A167: 20343766441 | B167: FERNANDEZ MAURO | C167: TALLER
A168: 27062343449 | B168: FERREIRA LILIANA INES | C168: FLETE
... A547: 30604958640 | B547: Aca Salud Coop P.S. Medico A.L | C547: CLIENTE

Sheet Julio 2024
A1: ORTOPEDIA GEMINIS S.A. | J1: 45474
A4: LIBRO IVA COMPRAS
A6: FACTURAS A
A7: FECHA | B7: PTO VTA | C7: FAC A | D7: CUIT | E7: RAZON SOCIAL | F7: NETO | G7: IVA 21% | H7: IVA 27% | I7: IVA 10,5% | J7: P IVA | K7: IIBB CF | L7: IIBB BS | M7: NO GRAV | N7: OTROS | O7: TOTAL | P7: DETALLE
E8: =VLOOKUP(D8,Configuracion!$A$4:$C$591,2,FALSE) -> #N/A | G8: =F8*21% -> 0 | O8: =SUM(F8:N8) -> 0 | P8: =VLOOKUP(D8,Configuracion!$A$4:$C$591,3,FALSE) -> #N/A
E9: =VLOOKUP(D9,Configuracion!$A$4:$C$591,2,FALSE) -> #N/A | G9: =F9*21% -> 0 | O9: =SUM(F9:N9) -> 0 | P9: =VLOOKUP(D9,Configuracion!$A$4:$C$591,3,FALSE) -> #N/A
E10: =VLOOKUP(D10,Configuracion!$A$4:$C$591,2,FALSE) -> #N/A | G10: =F10*21% -> 0 | O10: =SUM(F10:N10) -> 0 | P10: =VLOOKUP(D10,Configuracion!$A$4:$C$591,3,FALSE) -> #N/A
E11: =VLOOKUP(D11,Configuracion!$A$4:$C$591,2,FALSE) -> #N/A | G11: =F11*21% -> 0 | O11: =SUM(F11:N11) -> 0 | P11: =VLOOKUP(D11,Configuracion!$A$4:$C$591,3,FALSE) -> #N/A
A12: TOTAL | F12: =SUM(F8:F11) -> 0 | G12: =SUM(G8:G11) -> 0 | H12: =SUM(H8:H11) -> 0 | I12: =SUM(I8:I11) -> 0 | J12: =SUM(J8:J11) -> 0 | K12: =SUM(K8:K11) -> 0 | L12: =SUM(L8:L11) -> 0 | M12: =SUM(M8:M11) -> 0 | ... O12: =SUM(O8:O11) -> 0
F13: IVA | G13: =G12+H12+I12 -> 0
A15: FACTURAS B/C
A16: FECHA | B16: PTO VTA | C16: FAC C | D16: CUIT | E16: RAZON SOCIAL | F16: TOTAL | G16: DETALLE
E17: =VLOOKUP(D17,Configuracion!$A$4:$C$591,2,FALSE) -> #N/A | G17: =VLOOKUP(D17,Configuracion!$A$4:$C$591,3,FALSE) -> #N/A
E18: =VLOOKUP(D18,Configuracion!$A$4:$C$591,2,FALSE) -> #N/A | G18: =VLOOKUP(D18,Configuracion!$A$4:$C$591,3,FALSE) -> #N/A
E19: =VLOOKUP(D19,Configuracion!$A$4:$C$591,2,FALSE) -> #N/A | G19: =VLOOKUP(D19,Configuracion!$A$4:$C$591,3,FALSE) -> #N/A
E20: =VLOOKUP(D20,Configuracion!$A$4:$C$591,2,FALSE) -> #N/A | G20: =VLOOKUP(D20,Configuracion!$A$4:$C$591,3,FALSE) -> #N/A
E21: =VLOOKUP(D21,Configuracion!$A$4:$C$591,2,FALSE) -> #N/A | G21: =VLOOKUP(D21,Configuracion!$A$4:$C$591,3,FALSE) -> #N/A
E22: =VLOOKUP(D22,Configuracion!$A$4:$C$591,2,FALSE) -> #N/A | G22: =VLOOKUP(D22,Configuracion!$A$4:$C$591,3,FALSE) -> #N/A
E23: =VLOOKUP(D23,Configuracion!$A$4:$C$591,2,FALSE) -> #N/A | G23: =VLOOKUP(D23,Configuracion!$A$4:$C$591,3,FALSE) -> #N/A
E24: =VLOOKUP(D24,Configuracion!$A$4:$C$591,2,FALSE) -> #N/A | G24: =VLOOKUP(D24,Configuracion!$A$4:$C$591,3,FALSE) -> #N/A
A25: TOTAL | F25: =SUM(F17:F24) -> 0
A27: RETENCIONES
A28: FECHA | B28: COMPROBANTE NRO | D28: CUIT | E28: RAZON SOCIAL | F28: GANANCIAS | G28: IVA | H28: IIBB | I28: SUSS
A29: 45485 | B29: 59644 | D29: 30522428163 | E29: =VLOOKUP(D29,Configuracion!$A$4:$C$591,2,FALSE) -> GALENO ARGENTINA SA | F29: 7473.09 | G29: 40200.09 | H29: 3736.76 | I29: 3828.58
A30: 45475 | B30: 55614 | D30: 30522428163 | E30: =VLOOKUP(D30,Configuracion!$A$4:$C$591,2,FALSE) -> GALENO ARGENTINA SA | F30: 0 | G30: 23887.32 | H30: 2016.31 | I30: 2274.98
A31: 45485 | B31: 59642 | D31: 30522428163 | E31: =VLOOKUP(D31,Configuracion!$A$4:$C$591,2,FALSE) -> GALENO ARGENTINA SA | F31: 18354.61 | G31: 102601.53 | H31: 9177.3 | I31: 9771.57
A32: 45481 | B32: 57001 | D32: 30522428163 | E32: =VLOOKUP(D32,Configuracion!$A$4:$C$591,2,FALSE) -> GALENO ARGENTINA SA | F32: 183170 | G32: 972505.93 | H32: 91585 | I32: 92619.61
A33: 45481 | B33: 56919 | D33: 30522428163 | E33: =VLOOKUP(D33,Configuracion!$A$4:$C$591,2,FALSE) -> GALENO ARGENTINA SA | F33: 26347.77 | G33: 138325.79 | H33: 13173.88 | I33: 13173.88
A34: 45481 | B34: 57034 | D34: 30522428163 | E34: =VLOOKUP(D34,Configuracion!$A$4:$C$591,2,FALSE) -> GALENO ARGENTINA SA | F34: 6749.88 | G34: 120681.51 | H34: 3371.67 | I34: 11493.48
A35: 45468 | B35: 53218 | D35: 30522428163 | E35: =VLOOKUP(D35,Configuracion!$A$4:$C$591,2,FALSE) -> GALENO ARGENTINA SA | F35: 738.13 | G35: 4747.73 | H35: 369.06 | I35: 452.16
A36: 45450 | B36: 47651 | D36: 30522428163 | E36: =VLOOKUP(D36,Configuracion!$A$4:$C$591,2,FALSE) -> GALENO ARGENTINA SA | F36: 225303.14 | G36: 1182841.5 | H36: 112651.57 | I36: 112651.57
A37: 45484 | B37: 59037 | D37: 30522428163 | E37: =VLOOKUP(D37,Configuracion!$A$4:$C$591,2,FALSE) -> GALENO ARGENTINA SA | F37: 165627.86 | G37: 871890.5 | H37: 83037.19 | I37: 83037.19
A38: 45484 | B38: 59039 | D38: 30522428163 | E38: =VLOOKUP(D38,Configuracion!$A$4:$C$591,2,FALSE) -> GALENO ARGENTINA SA | F38: 598347.1 | G38: 3141322.3 | H38: 299173.55 | I38: 299173.55
A39: 45481 | B39: 57177 | D39: 30522428163 | E39: =VLOOKUP(D39,Configuracion!$A$4:$C$591,2,FALSE) -> GALENO ARGENTINA SA | F39: 24231.4 | G39: 127214.88 | H39: 12115.7 | I39: 12115.7
A40: 45481 | B40: 57324 | D40: 30522428163 | E40: =VLOOKUP(D40,Configuracion!$A$4:$C$591,2,FALSE) -> GALENO ARGENTINA SA | F40: 38148.76 | G40: 214599.17 | H40: 19074.38 | I40: 20438.02
... A45: 45478 | B45: 56788 | D45: 30522428163 | E45: =VLOOKUP(D45,Configuracion!$A$4:$C$591,2,FALSE) -> GALENO ARGENTINA SA | F45: 544161.98 | G45: 2856850.4 | H45: 272080.99 | I45: 272080.99
A46: 45477 | B46: 124506 | D46: 30590354798 | E46: =VLOOKUP(D46,Configuracion!$A$4:$C$591,2,FALSE) -> ASOCIACION MUTUAL SANCOR SALUD | F46: 29992.07 | H46: 30163.06
A47: 45478 | B47: 124762 | D47: 30590354798 | E47: =VLOOKUP(D47,Configuracion!$A$4:$C$591,2,FALSE) -> ASOCIACION MUTUAL SANCOR SALUD | F47: 27390 | H47: 23966.25
A48: 45498 | B48: 127746 | D48: 30590354798 | E48: =VLOOKUP(D48,Configuracion!$A$4:$C$591,2,FALSE) -> ASOCIACION MUTUAL SANCOR SALUD | F48: 31550.15 | H48: 27606.38
A49: 45495 | B49: 127251 | D49: 30590354798 | E49: =VLOOKUP(D49,Configuracion!$A$4:$C$591,2,FALSE) -> ASOCIACION MUTUAL SANCOR SALUD | F49: 36831.47 | H49: 32227.54
A50: 45481 | B50: 7751 | D50: 30608716390 | E50: =VLOOKUP(D50,Configuracion!$A$4:$C$591,2,FALSE) -> OSTEL | F50: 4679.92 | H50: 4579.96
A51: 45448 | B51: 107217 | D51: 30636196858 | E51: =VLOOKUP(D51,Configuracion!$A$4:$C$591,2,FALSE) -> C.S.J. O.S. Poder Judicial | F51: 99520 | H51: 182000
A52: 45489 | B52: 2873 | D52: 30683032227 | E52: =VLOOKUP(D52,Configuracion!$A$4:$C$591,2,FALSE) -> OS UNION PERSONAL | H52: 143964.22
A53: 45455 | B53: 2845 | D53: 30683032227 | E53: =VLOOKUP(D53,Configuracion!$A$4:$C$591,2,FALSE) -> OS UNION PERSONAL | H53: 127046.28
A54: 45476 | B54: 2860 | D54: 30683032227 | E54: =VLOOKUP(D54,Configuracion!$A$4:$C$591,2,FALSE) -> OS UNION PERSONAL | H54: 24152.89
A55: 45485 | B55: 7881 | D55: 30606274161 | E55: =VLOOKUP(D55,Configuracion!$A$4:$C$591,2,FALSE) -> EGESAC SA | H55: 1269.26
A56: 45485 | B56: 14880 | D56: 30604958640 | E56: =VLOOKUP(D56,Configuracion!$A$4:$C$591,2,FALSE) -> Aca Salud Coop P.S. Medico A.L | F56: 2976.6 | H56: 7560
A57: 45495 | B57: 14947 | D57: 30604958640 | E57: =VLOOKUP(D57,Configuracion!$A$4:$C$591,2,FALSE) -> Aca Salud Coop P.S. Medico A.L | F57: 6986.62 | H57: 3992.36
A58: 45485 | B58: 1922500 | D58: 30685228501 | E58: =VLOOKUP(D58,Configuracion!$A$4:$C$591,2,FALSE) -> GALENO ART SA | F58: 5736.6 | H58: 12390
A59: 45492 | B59: 196 | D59: 30710538014 | E59: =VLOOKUP(D59,Configuracion!$A$4:$C$591,2,FALSE) -> HC HOMECARE INT DOM SA | F59: 5440.4 | H59: =5935.83+11871.65 -> 17807.48
D60: 0 | E60: =VLOOKUP(D60,Configuracion!$A$4:$C$591,2,FALSE) -> #N/A
D61: 0 | E61: =VLOOKUP(D61,Configuracion!$A$4:$C$591,2,FALSE) -> #N/A
D62: 0 | E62: =VLOOKUP(D62,Configuracion!$A$4:$C$591,2,FALSE) -> #N/A
D63: 0 | E63: =VLOOKUP(D63,Configuracion!$A$4:$C$591,2,FALSE) -> #N/A
D64: 0 | E64: =VLOOKUP(D64,Configuracion!$A$4:$C$591,2,FALSE) -> #N/A
D65: 0 | E65: =VLOOKUP(D65,Configuracion!$A$4:$C$591,2,FALSE) -> #N/A
D66: 0 | E66: =VLOOKUP(D66,Configuracion!$A$4:$C$591,2,FALSE) -> #N/A
D67: 0 | E67: =VLOOKUP(D67,Configuracion!$A$4:$C$591,2,FALSE) -> #N/A
D68: 0 | E68: =VLOOKUP(D68,Configuracion!$A$4:$C$591,2,FALSE) -> #N/A
D69: 0 | E69: =VLOOKUP(D69,Configuracion!$A$4:$C$591,2,FALSE) -> #N/A
A70: TOTAL | F70: =SUM(F29:F69) -> 2478314.1 | G70: =SUM(G29:G69) -> 11861105 | H70: =SUM(H29:H69) -> 1756806.8 | I70: =SUM(I29:I69) -> 1129629
A74: LIBRO IVA VENTAS
A76: FACTURA A
A77: FECHA | B77: PTO VTA | C77: NRO FC | D77: CUIT | E77: RAZON SOCIAL | F77: NETO | G77: IVA | H77: NO GRAV. | I77: TOTAL
A78: 45484 | B78: 3 | C78: 8 | D78: 30683032227 | E78: =VLOOKUP(D78,Configuracion!$A$4:$C$591,2,FALSE) -> OS UNION PERSONAL | F78: 2790291.9 | G78: =F78*0.21 -> 585961.29 | I78: =SUM(F78:H78) -> 3376253.2
A79: 45484 | B79: 3 | C79: 9 | D79: 30522428163 | E79: =VLOOKUP(D79,Configuracion!$A$4:$C$591,2,FALSE) -> GALENO ARGENTINA SA | F79: 1221309.3 | G79: =F79*0.21 -> 256474.96 | I79: =SUM(F79:H79) -> 1477784.3
A80: 45484 | B80: 3 | C80: 10 | D80: 30522428163 | E80: =VLOOKUP(D80,Configuracion!$A$4:$C$591,2,FALSE) -> GALENO ARGENTINA SA | F80: 1135289 | G80: =F80*0.21 -> 238410.69 | I80: =SUM(F80:H80) -> 1373699.7
A81: 45485 | B81: 3 | C81: 11 | D81: 30522428163 | E81: =VLOOKUP(D81,Configuracion!$A$4:$C$591,2,FALSE) -> GALENO ARGENTINA SA | F81: 6642975.2 | G81: =F81*0.21 -> 1395024.8 | I81: =SUM(F81:H81) -> 8038000
A82: 45497 | B82: 3 | C82: 21 | D82: 30522428163 | E82: =VLOOKUP(D82,Configuracion!$A$4:$C$591,2,FALSE) -> GALENO ARGENTINA SA | F82: -6642975.2 | G82: =F82*0.21 -> -1395024.8 | I82: =SUM(F82:H82) -> -8038000
A83: 45485 | B83: 3 | C83: 13 | D83: 30522428163 | E83: =VLOOKUP(D83,Configuracion!$A$4:$C$591,2,FALSE) -> GALENO ARGENTINA SA | F83: 6642975.2 | G83: =F83*0.21 -> 1395024.8 | I83: =SUM(F83:H83) -> 8038000
A84: 45497 | B84: 3 | C84: 12 | D84: 30522428163 | E84: =VLOOKUP(D84,Configuracion!$A$4:$C$591,2,FALSE) -> GALENO ARGENTINA SA | F84: 1477685.9 | G84: =F84*0.21 -> 310314.05 | I84: =SUM(F84:H84) -> 1788000
A85: 45497 | B85: 3 | C85: 14 | D85: 30683032227 | E85: =VLOOKUP(D85,Configuracion!$A$4:$C$591,2,FALSE) -> OS UNION PERSONAL | F85: 1670247.9 | G85: =F85*0.21 -> 350752.07 | I85: =SUM(F85:H85) -> 2021000
A86: 45503 | B86: 3 | C86: 15 | D86: 30683032227 | E86: =VLOOKUP(D86,Configuracion!$A$4:$C$591,2,FALSE) -> OS UNION PERSONAL | F86: 1453471.1 | G86: =F86*0.21 -> 305228.92 | I86: =SUM(F86:H86) -> 1758700
E87: =VLOOKUP(D87,Configuracion!$A$4:$C$591,2,FALSE) -> #N/A | G87: =F87*0.21 -> 0 | I87: =SUM(F87:H87) -> 0
E88: =VLOOKUP(D88,Configuracion!$A$4:$C$591,2,FALSE) -> #N/A | G88: =F88*0.21 -> 0 | I88: =SUM(F88:H88) -> 0
E89: =VLOOKUP(D89,Configuracion!$A$4:$C$591,2,FALSE) -> #N/A | G89: =F89*0.21 -> 0 | I89: =SUM(F89:H89) -> 0
E90: =VLOOKUP(D90,Configuracion!$A$4:$C$591,2,FALSE) -> #N/A | G90: =F90*0.21 -> 0 | I90: =SUM(F90:H90) -> 0
E91: =VLOOKUP(D91,Configuracion!$A$4:$C$591,2,FALSE) -> #N/A | G91: =F91*0.21 -> 0 | I91: =SUM(F91:H91) -> 0
E92: =VLOOKUP(D92,Configuracion!$A$4:$C$591,2,FALSE) -> #N/A | G92: =F92*0.21 -> 0 | I92: =SUM(F92:H92) -> 0
E93: =VLOOKUP(D93,Configuracion!$A$4:$C$591,2,FALSE) -> #N/A | G93: =F93*0.21 -> 0 | I93: =SUM(F93:H93) -> 0
E94: =VLOOKUP(D94,Configuracion!$A$4:$C$591,2,FALSE) -> #N/A | G94: =F94*0.21 -> 0 | I94: =SUM(F94:H94) -> 0
E95: =VLOOKUP(D95,Configuracion!$A$4:$C$591,2,FALSE) -> #N/A | G95: =F95*0.21 -> 0 | I95: =SUM(F95:H95) -> 0
A96: TOTAL | F96: =SUM(F78:F95) -> 16391270 | G96: =SUM(G78:G95) -> 3442166.8 | I96: =SUM(I78:I95) -> 19833437
A99: FACTURA B
A100: FECHA | B100: PTO VTA | C100: NRO FC | D100: CUIT | E100: RAZON SOCIAL | F100: NETO | G100: IVA | H100: TOTAL
E101: =VLOOKUP(D101,Configuracion!$A$4:$C$591,2,FALSE) -> #N/A | F101: =H101/1.21 -> 0 | G101: =F101*0.21 -> 0
E102: =VLOOKUP(D102,Configuracion!$A$4:$C$591,2,FALSE) -> #N/A | F102: =H102/1.21 -> 0 | G102: =F102*0.21 -> 0
E103: =VLOOKUP(D103,Configuracion!$A$4:$C$591,2,FALSE) -> #N/A | F103: =H103/1.21 -> 0 | G103: =F103*0.21 -> 0
E104: =VLOOKUP(D104,Configuracion!$A$4:$C$591,2,FALSE) -> #N/A | F104: =H104/1.21 -> 0 | G104: =F104*0.21 -> 0
E105: =VLOOKUP(D105,Configuracion!$A$4:$C$591,2,FALSE) -> #N/A | F105: =H105/1.21 -> 0 | G105: =F105*0.21 -> 0
A106: TOTAL | F106: =SUM(F101:F105) -> 0 | G106: =SUM(G101:G105) -> 0 | H106: =SUM(H101:H105) -> 0
A113: Totales por Tipo de Comprobante - ODOO
B114: Base | C114: IVA | D114: Otros Imp. | E114: Total Compr.
A115: (FCE) A | B115: 12921793 | C115: 2713576.5 | D115: 0 | E115: 15635369
A116: NC FCE A | B116: -1892628.6 | C116: -397451.99 | D116: 0 | E116: -2290080.6
A117: FACTURAS A | B117: 10453142 | C117: 2195159.8 | D117: 0 | E117: 12648302
A118: NC A | B118: -2974245.8 | C118: -624591.62 | D118: 0 | E118: -3598837.4
A119: FACTURAS B | B119: 36050396 | C119: 7570583.3 | D119: 0 | E119: 43620979
A120: NC B | B120: -101652.9 | C120: -21347.1 | D120: 0 | E120: -123000
B121: =SUM(B115:B120) -> 54456803 | C121: =SUM(C115:C120) -> 11435929 | D121: 0 | E121: =SUM(E115:E120) -> 65892732

Sheet Calculo IVA
B1: ORTOPEDIA GEMINIS
A2: Calculo Iva | D2: 45474
B4: VENTAS
B5: Neto | C5: Iva | D5: Total
A6: FAC. "A" | B6: =+'Julio 2024'!F96 -> 16391270 | C6: =(B6*0.21) -> 3442166.8 | D6: =(B6+C6) -> 19833437
A7: FAC. "B" | B7: =+'Julio 2024'!F106 -> 0 | C7: =(B7*0.21) -> 0 | D7: =(B7+C7) -> 0
A8: FAC. "A" - Odoo | B8: =+'Julio 2024'!B115+'Julio 2024'!B117+'Julio 2024'!B118+'Julio 2024'!B116 -> 18508060 | C8: =+B8*0.21 -> 3886692.6 | D8: =(B8+C8) -> 22394753
A9: FAC. "B" - Odoo | B9: =+'Julio 2024'!B119+'Julio 2024'!B120 -> 35948743 | C9: =+B9*0.21 -> 7549236 | D9: =(B9+C9) -> 43497979
B10: =SUM(B6:B9) -> 70848073 | C10: =SUM(C6:C9) -> 14878095 | D10: =SUM(D6:D9) -> 85726168
B13: COMPRAS
B14: Neto | C14: Iva | D14: Total
A16: Compras s/ODOO | B16: 59861425 | C16: 9105103.9 | D16: 85572968
A17: Comprobantes AFIP - Saldo | B17: 536556.15 | C17: 114087.09 | D17: 1561385.3
A18: IVA S/ EXTRACTOS BANCARIOS | C18: 10544.01
B19: =SUM(B15:B18) -> 60397981 | C19: =SUM(C15:C18) -> 9229735 | D19: =SUM(D15:D18) -> 87134353
A22: RETENCIONES | B22: N° Cuit | C22: Importe | D22: Nro. Retencion | E22: Fecha
A23: AFIP - No están informadas las retenciones de IVA en el sistema de AFIP
C38: =+'Julio 2024'!G70 -> 11861105
A40: PERCEPCIONES | B40: N° Cuit | C40: Importe | D40: Nro. Retencion | E40: Fecha
C44: =SUM(C41:C43) -> 0
A46: Total Deducciociones | C46: =+C44+C38 -> 11861105
C49: (Montos en Positivo)
A50: 1er Saldo Tecnico del Período | C50: =+C10-C19 -> 5648360.3
A52: Saldo Tecnico de período Anterior (a favor) | D52: (resta en el total)
A54: Saldo Neto Técnico | C54: =+C50-C52 -> 5648360.3
A58: Saldo L.D. del Período | C58: =+C44+C38 -> 11861105
A60: Saldo L.D. del Período Anterior
A62: Neto S.L.D | C62: =+C58+C60 -> 11861105
A65: I V A | C65: =+C54-C62 -> -6212744.9
A66: NOTA: Sin Tomar posibles Retenciones que se hayan hecho

Sheet Ventas 07
A1: Ventas Libro de IVA 01/07/2024 - 31/07/2024
A2: Ortopedia Geminis S.A.
A4: Fecha | B4: Comprobante | C4: Nombre | D4: Cond. IVA | E4: CUIT o Doc. | F4: Gravado | G4: No Gravado | H4: IVA 2,5% | I4: IVA 5% | J4: IVA 10.5% | K4: IVA 21% | L4: IVA 27% | M4: Otros Imp | N4: Total Compr.
A5: 12/07/2024 | B5: FA-A 0005-00000154 | C5: Muñoz, Marcelo Sebastian | D5: IVA Responsable Inscripto | E5: 20238528543 | F5: 10743.8 | G5: 0 | H5: 0 | I5: 0 | J5: 0 | K5: 2256.2 | L5: 0 | M5: 0 | N5: 13000
A6: 29/07/2024 | B6: FA-A 0005-00000155 | C6: Puertolas, Maximiliano | D6: IVA Responsable Inscripto | E6: 20249404870 | F6: 15123.97 | G6: 0 | H6: 0 | I6: 0 | J6: 0 | K6: 3176.03 | L6: 0 | M6: 0 | N6: 18300
A7: 04/07/2024 | B7: FA-A 0006-00000512 | C7: Galeno Argentina SA | D7: IVA Responsable Inscripto | E7: 30522428163 | F7: 1495867.8 | G7: 0 | H7: 0 | I7: 0 | J7: 0 | K7: 314132.24 | L7: 0 | M7: 0 | N7: 1810000
A8: 10/07/2024 | B8: FA-A 0006-00000513 | C8: Galeno Argentina SA | D8: IVA Responsable Inscripto | E8: 30522428163 | F8: 1267889.9 | G8: 0 | H8: 0 | I8: 0 | J8: 0 | K8: 266256.88 | L8: 0 | M8: 0 | N8: 1534146.8
A9: 10/07/2024 | B9: FA-A 0006-00000514 | C9: Galeno Argentina SA | D9: IVA Responsable Inscripto | E9: 30522428163 | F9: 8704563.9 | G9: 0 | H9: 0 | I9: 0 | J9: 0 | K9: 1827958.4 | L9: 0 | M9: 0 | N9: 10532522
A10: 31/07/2024 | B10: FA-A 0006-00000516 | C10: Galeno Argentina SA | D10: IVA Responsable Inscripto | E10: 30522428163 | F10: 1453471.1 | G10: 0 | H10: 0 | I10: 0 | J10: 0 | K10: 305228.93 | L10: 0 | M10: 0 | N10: 1758700
A11: 02/07/2024 | B11: FA-A 0007-00002024 | C11: Medincare Argentina S.A. | D11: IVA Responsable Inscripto | E11: 30713669004 | F11: 72231.4 | G11: 0 | H11: 0 | I11: 0 | J11: 0 | K11: 15168.59 | L11: 0 | M11: 0 | N11: 87399.99
A12: 02/07/2024 | B12: FA-A 0007-00002025 | C12: Hc Homecare Internacion Domiciliaria S.A. | D12: IVA Responsable Inscripto | E12: 30710538014 | F12: 369049.59 | G12: 0 | H12: 0 | I12: 0 | J12: 0 | K12: 77500.41 | L12: 0 | M12: 0 | N12: 446550
A13: 02/07/2024 | B13: FA-A 0007-00002026 | C13: Login Door S.A | D13: IVA Responsable Inscripto | E13: 30711244383 | F13: 48576.03 | G13: 0 | H13: 0 | I13: 0 | J13: 0 | K13: 10200.97 | L13: 0 | M13: 0 | N13: 58777
A14: 02/07/2024 | B14: FA-A 0007-00002027 | C14: Medicus Sociedad Anonima De Asistencia Medica Y Cientifica | D14: IVA Responsable Inscripto | E14: 30546771314 | F14: 16597.8 | G14: 0 | H14: 0 | I14: 0 | J14: 0 | K14: 3485.54 | L14: 0 | M14: 0 | N14: 20083.34
A15: 03/07/2024 | B15: FA-A 0007-00002028 | C15: MGR IMPLANTES SA | D15: IVA Responsable Inscripto | E15: 30709016012 | F15: 131716.53 | G15: 0 | H15: 0 | I15: 0 | J15: 0 | K15: 27660.47 | L15: 0 | M15: 0 | N15: 159377
A16: 03/07/2024 | B16: FA-A 0007-00002029 | C16: MGR IMPLANTES SA | D16: IVA Responsable Inscripto | E16: 30709016012 | F16: 487603.32 | G16: 0 | H16: 0 | I16: 0 | J16: 0 | K16: 102396.71 | L16: 0 | M16: 0 | N16: 590000.03
... A65: 30/07/2024 | B65: FA-A 0007-00002078 | C65: Aca Salud Cooperativa De Prestacion De Servicios Medico Asistenciales Limitada | D65: IVA Responsable Inscripto | E65: 30604958640 | F65: 400000 | G65: 0 | H65: 0 | I65: 0 | J65: 0 | K65: 84000 | L65: 0 | M65: 0 | N65: 484000
A66: 01/07/2024 | B66: FA-B 0005-00010943 | C66: .CONSUMIDOR FINAL | D66: Consumidor Final | F66: 10743.8 | G66: 0 | H66: 0 | I66: 0 | J66: 0 | K66: 2256.2 | L66: 0 | M66: 0 | N66: 13000
A67: 01/07/2024 | B67: FA-B 0005-00010944 | C67: .CONSUMIDOR FINAL | D67: Consumidor Final | F67: 10743.8 | G67: 0 | H67: 0 | I67: 0 | J67: 0 | K67: 2256.2 | L67: 0 | M67: 0 | N67: 13000
A68: 01/07/2024 | B68: FA-B 0005-00010945 | C68: .CONSUMIDOR FINAL | D68: Consumidor Final | F68: 14462.81 | G68: 0 | H68: 0 | I68: 0 | J68: 0 | K68: 3037.19 | L68: 0 | M68: 0 | N68: 17500
A69: 01/07/2024 | B69: FA-B 0005-00010946 | C69: DIAZ, HECTOR | D69: Consumidor Final | E69: 8286597 | F69: 14462.81 | G69: 0 | H69: 0 | I69: 0 | J69: 0 | K69: 3037.19 | L69: 0 | M69: 0 | N69: 17500
A70: 01/07/2024 | B70: FA-B 0005-00010947 | C70: .CONSUMIDOR FINAL | D70: Consumidor Final | F70: 21487.6 | G70: 0 | H70: 0 | I70: 0 | J70: 0 | K70: 4512.4 | L70: 0 | M70: 0 | N70: 26000
A71: 01/07/2024 | B71: FA-B 0005-00010948 | C71: .CONSUMIDOR FINAL | D71: Consumidor Final | F71: 4628.1 | G71: 0 | H71: 0 | I71: 0 | J71: 0 | K71: 971.9 | L71: 0 | M71: 0 | N71: 5600
A72: 01/07/2024 | B72: FA-B 0005-00010949 | C72: .CONSUMIDOR FINAL | D72: Consumidor Final | F72: 14876.03 | G72: 0 | H72: 0 | I72: 0 | J72: 0 | K72: 3123.97 | L72: 0 | M72: 0 | N72: 18000
A73: 01/07/2024 | B73: FA-B 0005-00010950 | C73: .CONSUMIDOR FINAL | D73: Consumidor Final | F73: 13636.36 | G73: 0 | H73: 0 | I73: 0 | J73: 0 | K73: 2863.64 | L73: 0 | M73: 0 | N73: 16500
A74: 01/07/2024 | B74: FA-B 0005-00010951 | C74: LOUGE BARBARA | D74: Consumidor Final | E74: 25966714 | F74: 29338.84 | G74: 0 | H74: 0 | I74: 0 | J74: 0 | K74: 6161.16 | L74: 0 | M74: 0 | N74: 35500
A75: 01/07/2024 | B75: FA-B 0005-00010952 | C75: .CONSUMIDOR FINAL | D75: Consumidor Final | F75: 14669.42 | G75: 0 | H75: 0 | I75: 0 | J75: 0 | K75: 3080.58 | L75: 0 | M75: 0 | N75: 17750
A76: 01/07/2024 | B76: FA-B 0005-00010953 | C76: .CONSUMIDOR FINAL | D76: Consumidor Final | F76: 10743.8 | G76: 0 | H76: 0 | I76: 0 | J76: 0 | K76: 2256.2 | L76: 0 | M76: 0 | N76: 13000
A77: 01/07/2024 | B77: FA-B 0005-00010954 | C77: .CONSUMIDOR FINAL | D77: Consumidor Final | F77: 19669.42 | G77: 0 | H77: 0 | I77: 0 | J77: 0 | K77: 4130.58 | L77: 0 | M77: 0 | N77: 23800
A78: 01/07/2024 | B78: FA-B 0005-00010955 | C78: .CONSUMIDOR FINAL | D78: Consumidor Final | F78: 14049.59 | G78: 0 | H78: 0 | I78: 0 | J78: 0 | K78: 2950.41 | L78: 0 | M78: 0 | N78: 17000
A79: 01/07/2024 | B79: FA-B 0005-00010956 | C79: .CONSUMIDOR FINAL | D79: Consumidor Final | F79: 38925.62 | G79: 0 | H79: 0 | I79: 0 | J79: 0 | K79: 8174.38 | L79: 0 | M79: 0 | N79: 47100
A80: 01/07/2024 | B80: FA-B 0005-00010957 | C80: .CONSUMIDOR FINAL | D80: Consumidor Final | F80: 13223.14 | G80: 0 | H80: 0 | I80: 0 | J80: 0 | K80: 2776.86 | L80: 0 | M80: 0 | N80: 16000
A81: 02/07/2024 | B81: FA-B 0005-00010958 | C81: .CONSUMIDOR FINAL | D81: Consumidor Final | F81: 19090.91 | G81: 0 | H81: 0 | I81: 0 | J81: 0 | K81: 4009.09 | L81: 0 | M81: 0 | N81: 23100
A82: 02/07/2024 | B82: FA-B 0005-00010959 | C82: .CONSUMIDOR FINAL | D82: Consumidor Final | F82: 24628.1 | G82: 0 | H82: 0 | I82: 0 | J82: 0 | K82: 5171.9 | L82: 0 | M82: 0 | N82: 29800
A83: 02/07/2024 | B83: FA-B 0005-00010960 | C83: .CONSUMIDOR FINAL | D83: Consumidor Final | F83: 21074.38 | G83: 0 | H83: 0 | I83: 0 | J83: 0 | K83: 4425.62 | L83: 0 | M83: 0 | N83: 25500
A84: 02/07/2024 | B84: FA-B 0005-00010961 | C84: .CONSUMIDOR FINAL | D84: Consumidor Final | F84: 21487.6 | G84: 0 | H84: 0 | I84: 0 | J84: 0 | K84: 4512.4 | L84: 0 | M84: 0 | N84: 26000
A85: 02/07/2024 | B85: FA-B 0005-00010962 | C85: .CONSUMIDOR FINAL | D85: Consumidor Final | F85: 68925.62 | G85: 0 | H85: 0 | I85: 0 | J85: 0 | K85: 14474.38 | L85: 0 | M85: 0 | N85: 83400
A86: 02/07/2024 | B86: FA-B 0005-00010963 | C86: .CONSUMIDOR FINAL | D86: Consumidor Final | F86: 16528.93 | G86: 0 | H86: 0 | I86: 0 | J86: 0 | K86: 3471.07 | L86: 0 | M86: 0 | N86: 20000
... A107: 04/07/2024 | B107: FA-B 0005-00010984 | C107: .CONSUMIDOR FINAL | D107: Consumidor Final | F107: 4462.81 | G107: 0 | H107: 0 | I107: 0 | J107: 0 | K107: 937.19 | L107: 0 | M107: 0 | N107: 5400
A108: 04/07/2024 | B108: FA-B 0005-00010985 | C108: LEAL LUIS | D108: Consumidor Final | E108: 30298513 | F108: 33884.3 | G108: 0 | H108: 0 | I108: 0 | J108: 0 | K108: 7115.7 | L108: 0 | M108: 0 | N108: 41000
A109: 04/07/2024 | B109: FA-B 0005-00010986 | C109: .CONSUMIDOR FINAL | D109: Consumidor Final | F109: 10743.8 | G109: 0 | H109: 0 | I109: 0 | J109: 0 | K109: 2256.2 | L109: 0 | M109: 0 | N109: 13000
A110: 04/07/2024 | B110: FA-B 0005-00010987 | C110: .CONSUMIDOR FINAL | D110: Consumidor Final | F110: 22892.56 | G110: 0 | H110: 0 | I110: 0 | J110: 0 | K110: 4807.44 | L110: 0 | M110: 0 | N110: 27700
A111: 04/07/2024 | B111: FA-B 0005-00010988 | C111: .CONSUMIDOR FINAL | D111: Consumidor Final | F111: 34710.74 | G111: 0 | H111: 0 | I111: 0 | J111: 0 | K111: 7289.26 | L111: 0 | M111: 0 | N111: 42000
A112: 04/07/2024 | B112: FA-B 0005-00010989 | C112: .CONSUMIDOR FINAL | D112: Consumidor Final | F112: 4132.23 | G112: 0 | H112: 0 | I112: 0 | J112: 0 | K112: 867.77 | L112: 0 | M112: 0 | N112: 5000
A113: 04/07/2024 | B113: FA-B 0005-00010990 | C113: .CONSUMIDOR FINAL | D113: Consumidor Final | F113: 29338.84 | G113: 0 | H113: 0 | I113: 0 | J113: 0 | K113: 6161.16 | L113: 0 | M113: 0 | N113: 35500
A114: 04/07/2024 | B114: FA-B 0005-00010991 | C114: .CONSUMIDOR FINAL | D114: Consumidor Final | F114: 7438.02 | G114: 0 | H114: 0 | I114: 0 | J114: 0 | K114: 1561.98 | L114: 0 | M114: 0 | N114: 9000
A115: 05/07/2024 | B115: FA-B 0005-00010992 | C115: .CONSUMIDOR FINAL | D115: Consumidor Final | F115: 11487.6 | G115: 0 | H115: 0 | I115: 0 | J115: 0 | K115: 2412.4 | L115: 0 | M115: 0 | N115: 13900
A116: 05/07/2024 | B116: FA-B 0005-00010993 | C116: .CONSUMIDOR FINAL | D116: Consumidor Final | F116: 9917.36 | G116: 0 | H116: 0 | I116: 0 | J116: 0 | K116: 2082.64 | L116: 0 | M116: 0 | N116: 12000
A117: 05/07/2024 | B117: FA-B 0005-00010994 | C117: .CONSUMIDOR FINAL | D117: Consumidor Final | F117: 28925.62 | G117: 0 | H117: 0 | I117: 0 | J117: 0 | K117: 6074.38 | L117: 0 | M117: 0 | N117: 35000
A118: 05/07/2024 | B118: FA-B 0005-00010995 | C118: .CONSUMIDOR FINAL | D118: Consumidor Final | F118: 16528.93 | G118: 0 | H118: 0 | I118: 0 | J118: 0 | K118: 3471.07 | L118: 0 | M118: 0 | N118: 20000
A119: 05/07/2024 | B119: FA-B 0005-00010996 | C119: .CONSUMIDOR FINAL | D119: Consumidor Final | F119: 29338.84 | G119: 0 | H119: 0 | I119: 0 | J119: 0 | K119: 6161.16 | L119: 0 | M119: 0 | N119: 35500
A120: 05/07/2024 | B120: FA-B 0005-00010997 | C120: .CONSUMIDOR FINAL | D120: Consumidor Final | F120: 21487.6 | G120: 0 | H120: 0 | I120: 0 | J120: 0 | K120: 4512.4 | L120: 0 | M120: 0 | N120: 26000
... A127: 08/07/2024 | B127: FA-B 0005-00011004 | C127: .CONSUMIDOR FINAL | D127: Consumidor Final | F127: 21487.6 | G127: 0 | H127: 0 | I127: 0 | J127: 0 | K127: 4512.4 | L127: 0 | M127: 0 | N127: 26000
A128: 08/07/2024 | B128: FA-B 0005-00011005 | C128: PRESAS MARIA EUGENIA | D128: Consumidor Final | E128: 29116688 | F128: 24628.1 | G128: 0 | H128: 0 | I128: 0 | J128: 0 | K128: 5171.9 | L128: 0 | M128: 0 | N128: 29800
A129: 08/07/2024 | B129: FA-B 0005-00011006 | C129: .CONSUMIDOR FINAL | D129: Consumidor Final | F129: 52809.91 | G129: 0 | H129: 0 | I129: 0 | J129: 0 | K129: 11090.09 | L129: 0 | M129: 0 | N129: 63900
A130: 08/07/2024 | B130: FA-B 0005-00011007 | C130: .CONSUMIDOR FINAL | D130: Consumidor Final | F130: 53719.01 | G130: 0 | H130: 0 | I130: 0 | J130: 0 | K130: 11280.99 | L130: 0 | M130: 0 | N130: 65000
A131: 08/07/2024 | B131: FA-B 0005-00011008 | C131: .CONSUMIDOR FINAL | D131: Consumidor Final | F131: 66115.7 | G131: 0 | H131: 0 | I131: 0 | J131: 0 | K131: 13884.3 | L131: 0 | M131: 0 | N131: 80000
A132: 08/07/2024 | B132: FA-B 0005-00011009 | C132: .CONSUMIDOR FINAL | D132: Consumidor Final | F132: 10743.8 | G132: 0 | H132: 0 | I132: 0 | J132: 0 | K132: 2256.2 | L132: 0 | M132: 0 | N132: 13000
A133: 10/07/2024 | B133: FA-B 0005-00011010 | C133: .CONSUMIDOR FINAL | D133: Consumidor Final | F133: 14669.42 | G133: 0 | H133: 0 | I133: 0 | J133: 0 | K133: 3080.58 | L133: 0 | M133: 0 | N133: 17750
A134: 10/07/2024 | B134: FA-B 0005-00011011 | C134: .CONSUMIDOR FINAL | D134: Consumidor Final | F134: 34462.81 | G134: 0 | H134: 0 | I134: 0 | J134: 0 | K134: 7237.19 | L134: 0 | M134: 0 | N134: 41700
A135: 10/07/2024 | B135: FA-B 0005-00011012 | C135: .CONSUMIDOR FINAL | D135: Consumidor Final | F135: 37190.08 | G135: 0 | H135: 0 | I135: 0 | J135: 0 | K135: 7809.92 | L135: 0 | M135: 0 | N135: 45000
A136: 10/07/2024 | B136: FA-B 0005-00011013 | C136: .CONSUMIDOR FINAL | D136: Consumidor Final | F136: 5041.32 | G136: 0 | H136: 0 | I136: 0 | J136: 0 | K136: 1058.68 | L136: 0 | M136: 0 | N136: 6100
A137: 10/07/2024 | B137: FA-B 0005-00011014 | C137: .CONSUMIDOR FINAL | D137: Consumidor Final | F137: 14669.42 | G137: 0 | H137: 0 | I137: 0 | J137: 0 | K137: 3080.58 | L137: 0 | M137: 0 | N137: 17750
A138: 10/07/2024 | B138: FA-B 0005-00011015 | C138: .CONSUMIDOR FINAL | D138: Consumidor Final | F138: 6611.57 | G138: 0 | H138: 0 | I138: 0 | J138: 0 | K138: 1388.43 | L138: 0 | M138: 0 | N138: 8000
A139: 10/07/2024 | B139: FA-B 0005-00011016 | C139: .CONSUMIDOR FINAL | D139: Consumidor Final | F139: 16528.93 | G139: 0 | H139: 0 | I139: 0 | J139: 0 | K139: 3471.07 | L139: 0 | M139: 0 | N139: 20000
A140: 11/07/2024 | B140: FA-B 0005-00011017 | C140: .CONSUMIDOR FINAL | D140: Consumidor Final | F140: 7024.79 | G140: 0 | H140: 0 | I140: 0 | J140: 0 | K140: 1475.21 | L140: 0 | M140: 0 | N140: 8500
... A167: 15/07/2024 | B167: FA-B 0005-00011044 | C167: .CONSUMIDOR FINAL | D167: Consumidor Final | F167: 78512.4 | G167: 0 | H167: 0 | I167: 0 | J167: 0 | K167: 16487.6 | L167: 0 | M167: 0 | N167: 95000
A168: 15/07/2024 | B168: FA-B 0005-00011045 | C168: MATA EVYS DEL VALLE | D168: Consumidor Final | E168: 95857770 | F168: 78512.4 | G168: 0 | H168: 0 | I168: 0 | J168: 0 | K168: 16487.6 | L168: 0 | M168: 0 | N168: 95000
A169: 15/07/2024 | B169: FA-B 0005-00011046 | C169: .CONSUMIDOR FINAL | D169: Consumidor Final | F169: 12314.05 | G169: 0 | H169: 0 | I169: 0 | J169: 0 | K169: 2585.95 | L169: 0 | M169: 0 | N169: 14900
A170: 15/07/2024 | B170: FA-B 0005-00011047 | C170: .CONSUMIDOR FINAL | D170: Consumidor Final | F170: 14669.42 | G170: 0 | H170: 0 | I170: 0 | J170: 0 | K170: 3080.58 | L170: 0 | M170: 0 | N170: 17750
A171: 15/07/2024 | B171: FA-B 0005-00011048 | C171: .CONSUMIDOR FINAL | D171: Consumidor Final | F171: 10743.8 | G171: 0 | H171: 0 | I171: 0 | J171: 0 | K171: 2256.2 | L171: 0 | M171: 0 | N171: 13000
A172: 15/07/2024 | B172: FA-B 0005-00011049 | C172: .CONSUMIDOR FINAL | D172: Consumidor Final | F172: 34462.81 | G172: 0 | H172: 0 | I172: 0 | J172: 0 | K172: 7237.19 | L172: 0 | M172: 0 | N172: 41700
A173: 15/07/2024 | B173: FA-B 0005-00011050 | C173: .CONSUMIDOR FINAL | D173: Consumidor Final | F173: 14669.42 | G173: 0 | H173: 0 | I173: 0 | J173: 0 | K173: 3080.58 | L173: 0 | M173: 0 | N173: 17750
A174: 16/07/2024 | B174: FA-B 0005-00011051 | C174: .CONSUMIDOR FINAL | D174: Consumidor Final | F174: 33884.3 | G174: 0 | H174: 0 | I174: 0 | J174: 0 | K174: 7115.7 | L174: 0 | M174: 0 | N174: 41000
A175: 16/07/2024 | B175: FA-B 0005-00011052 | C175: .CONSUMIDOR FINAL | D175: Consumidor Final | F175: 13223.14 | G175: 0 | H175: 0 | I175: 0 | J175: 0 | K175: 2776.86 | L175: 0 | M175: 0 | N175: 16000
A176: 16/07/2024 | B176: FA-B 0005-00011053 | C176: .CONSUMIDOR FINAL | D176: Consumidor Final | F176: 7438.02 | G176: 0 | H176: 0 | I176: 0 | J176: 0 | K176: 1561.98 | L176: 0 | M176: 0 | N176: 9000
A177: 16/07/2024 | B177: FA-B 0005-00011054 | C177: .CONSUMIDOR FINAL | D177: Consumidor Final | F177: 24545.46 | G177: 0 | H177: 0 | I177: 0 | J177: 0 | K177: 5154.54 | L177: 0 | M177: 0 | N177: 29700
A178: 16/07/2024 | B178: FA-B 0005-00011055 | C178: .CONSUMIDOR FINAL | D178: Consumidor Final | F178: 29338.84 | G178: 0 | H178: 0 | I178: 0 | J178: 0 | K178: 6161.16 | L178: 0 | M178: 0 | N178: 35500
A179: 16/07/2024 | B179: FA-B 0005-00011056 | C179: .CONSUMIDOR FINAL | D179: Consumidor Final | F179: 10330.58 | G179: 0 | H179: 0 | I179: 0 | J179: 0 | K179: 2169.42 | L179: 0 | M179: 0 | N179: 12500
A180: 16/07/2024 | B180: FA-B 0005-00011057 | C180: .CONSUMIDOR FINAL | D180: Consumidor Final | F180: 10743.8 | G180: 0 | H180: 0 | I180: 0 | J180: 0 | K180: 2256.2 | L180: 0 | M180: 0 | N180: 13000
... A237: 22/07/2024 | B237: FA-B 0005-00011114 | C237: .CONSUMIDOR FINAL | D237: Consumidor Final | F237: 16528.93 | G237: 0 | H237: 0 | I237: 0 | J237: 0 | K237: 3471.07 | L237: 0 | M237: 0 | N237: 20000
A238: 22/07/2024 | B238: FA-B 0005-00011115 | C238: AROMATARE HERNÁN | D238: Consumidor Final | E238: 29078770 | F238: 29338.84 | G238: 0 | H238: 0 | I238: 0 | J238: 0 | K238: 6161.16 | L238: 0 | M238: 0 | N238: 35500
A239: 22/07/2024 | B239: FA-B 0005-00011116 | C239: .CONSUMIDOR FINAL | D239: Consumidor Final | F239: 10330.58 | G239: 0 | H239: 0 | I239: 0 | J239: 0 | K239: 2169.42 | L239: 0 | M239: 0 | N239: 12500
A240: 22/07/2024 | B240: FA-B 0005-00011117 | C240: .CONSUMIDOR FINAL | D240: Consumidor Final | F240: 10743.8 | G240: 0 | H240: 0 | I240: 0 | J240: 0 | K240: 2256.2 | L240: 0 | M240: 0 | N240: 13000
A241: 22/07/2024 | B241: FA-B 0005-00011118 | C241: .CONSUMIDOR FINAL | D241: Consumidor Final | F241: 9917.36 | G241: 0 | H241: 0 | I241: 0 | J241: 0 | K241: 2082.64 | L241: 0 | M241: 0 | N241: 12000
A242: 22/07/2024 | B242: FA-B 0005-00011119 | C242: .CONSUMIDOR FINAL | D242: Consumidor Final | F242: 14669.42 | G242: 0 | H242: 0 | I242: 0 | J242: 0 | K242: 3080.58 | L242: 0 | M242: 0 | N242: 17750
A243: 22/07/2024 | B243: FA-B 0005-00011120 | C243: .CONSUMIDOR FINAL | D243: Consumidor Final | F243: 10743.8 | G243: 0 | H243: 0 | I243: 0 | J243: 0 | K243: 2256.2 | L243: 0 | M243: 0 | N243: 13000
A244: 23/07/2024 | B244: FA-B 0005-00011121 | C244: .CONSUMIDOR FINAL | D244: Consumidor Final | F244: 14669.42 | G244: 0 | H244: 0 | I244: 0 | J244: 0 | K244: 3080.58 | L244: 0 | M244: 0 | N244: 17750
A245: 23/07/2024 | B245: FA-B 0005-00011122 | C245: .CONSUMIDOR FINAL | D245: Consumidor Final | F245: 11487.6 | G245: 0 | H245: 0 | I245: 0 | J245: 0 | K245: 2412.4 | L245: 0 | M245: 0 | N245: 13900
A246: 23/07/2024 | B246: FA-B 0005-00011123 | C246: .CONSUMIDOR FINAL | D246: Consumidor Final | F246: 10330.58 | G246: 0 | H246: 0 | I246: 0 | J246: 0 | K246: 2169.42 | L246: 0 | M246: 0 | N246: 12500
A247: 23/07/2024 | B247: FA-B 0005-00011124 | C247: .CONSUMIDOR FINAL | D247: Consumidor Final | F247: 15909.09 | G247: 0 | H247: 0 | I247: 0 | J247: 0 | K247: 3340.91 | L247: 0 | M247: 0 | N247: 19250
A248: 23/07/2024 | B248: FA-B 0005-00011125 | C248: .CONSUMIDOR FINAL | D248: Consumidor Final | F248: 32231.4 | G248: 0 | H248: 0 | I248: 0 | J248: 0 | K248: 6768.6 | L248: 0 | M248: 0 | N248: 39000
A249: 23/07/2024 | B249: FA-B 0005-00011126 | C249: .CONSUMIDOR FINAL | D249: Consumidor Final | F249: 10661.16 | G249: 0 | H249: 0 | I249: 0 | J249: 0 | K249: 2238.84 | L249: 0 | M249: 0 | N249: 12900
A250: 23/07/2024 | B250: FA-B 0005-00011127 | C250: .CONSUMIDOR FINAL | D250: Consumidor Final | F250: 16528.93 | G250: 0 | H250: 0 | I250: 0 | J250: 0 | K250: 3471.07 | L250: 0 | M250: 0 | N250: 20000
... A266: 24/07/2024 | B266: FA-B 0005-00011143 | C266: .CONSUMIDOR FINAL | D266: Consumidor Final | F266: 24793.39 | G266: 0 | H266: 0 | I266: 0 | J266: 0 | K266: 5206.61 | L266: 0 | M266: 0 | N266: 30000
A267: 24/07/2024 | B267: FA-B 0005-00011144 | C267: GOMEZ JUAN PEDRO | D267: Consumidor Final | E267: 13881587 | F267: 29752.07 | G267: 0 | H267: 0 | I267: 0 | J267: 0 | K267: 6247.93 | L267: 0 | M267: 0 | N267: 36000
A268: 24/07/2024 | B268: FA-B 0005-00011145 | C268: .CONSUMIDOR FINAL | D268: Consumidor Final | F268: 14669.42 | G268: 0 | H268: 0 | I268: 0 | J268: 0 | K268: 3080.58 | L268: 0 | M268: 0 | N268: 17750
A269: 25/07/2024 | B269: FA-B 0005-00011146 | C269: GONZALEZ HUGO CESAR | D269: Consumidor Final | E269: 24190411 | F269: 8595.04 | G269: 0 | H269: 0 | I269: 0 | J269: 0 | K269: 1804.96 | L269: 0 | M269: 0 | N269: 10400
A270: 25/07/2024 | B270: FA-B 0005-00011147 | C270: .CONSUMIDOR FINAL | D270: Consumidor Final | F270: 10743.8 | G270: 0 | H270: 0 | I270: 0 | J270: 0 | K270: 2256.2 | L270: 0 | M270: 0 | N270: 13000
A271: 25/07/2024 | B271: FA-B 0005-00011148 | C271: .CONSUMIDOR FINAL | D271: Consumidor Final | F271: 15702.48 | G271: 0 | H271: 0 | I271: 0 | J271: 0 | K271: 3297.52 | L271: 0 | M271: 0 | N271: 19000
A272: 25/07/2024 | B272: FA-B 0005-00011149 | C272: .CONSUMIDOR FINAL | D272: Consumidor Final | F272: 14669.42 | G272: 0 | H272: 0 | I272: 0 | J272: 0 | K272: 3080.58 | L272: 0 | M272: 0 | N272: 17750
...

Sheet Compras 07 
A2: Compras Libro de IVA 01/07/2024 - 31/07/2024
A3: Ortopedia Geminis S.A.
A5: Fecha | B5: Comprobante | C5: Nombre | D5: Cond. IVA | E5: CUIT o Doc. | F5: Gravado | G5: No Gravado | H5: IVA 2,5% | I5: IVA 5% | J5: IVA 10.5% | K5: IVA 21% | L5: IVA 27% | M5: Otros Imp | N5: Total Compr.
A6: 45483 | B6: FA-A 0001-00000831 | C6: Rolls Y Empanadas S.A. | D6: IVA Responsable Inscripto | E6: 30715048066 | F6: 807785 | G6: 0 | H6: 0 | I6: 0 | J6: 0 | K6: 169634.85 | L6: 0 | M6: 0 | N6: 977419.85
A7: 45475 | B7: FA-A 0001-00002313 | C7: Nicolas Tobias Sequeira Y Maria Gabriela Rattner Sociedad De La Seccion Iv Lgs | D7: IVA Responsable Inscripto | E7: 30717179389 | F7: 33884.3 | G7: 0 | H7: 0 | I7: 0 | J7: 0 | K7: 7115.7 | L7: 0 | M7: 0 | N7: 41000
A8: 45474 | B8: FA-A 0001-00003721 | C8: Rehab S.R.L. | D8: IVA Responsable Inscripto | E8: 30715141201 | F8: 196966.09 | G8: 0 | H8: 0 | I8: 0 | J8: 0 | K8: 41362.88 | L8: 0 | M8: 0 | N8: 238328.97
A9: 45490 | B9: FA-A 0001-00003886 | C9: Rehab S.R.L. | D9: IVA Responsable Inscripto | E9: 30715141201 | F9: 3092234.2 | G9: 0 | H9: 0 | I9: 0 | J9: 0 | K9: 649369.19 | L9: 0 | M9: 0 | N9: 3741603.4
A10: 45490 | B10: FA-A 0001-00003887 | C10: Rehab S.R.L. | D10: IVA Responsable Inscripto | E10: 30715141201 | F10: 1426289.1 | G10: 0 | H10: 0 | I10: 0 | J10: 0 | K10: 299520.7 | L10: 0 | M10: 0 | N10: 1725809.8
A11: 45490 | B11: FA-A 0001-00003889 | C11: Rehab S.R.L. | D11: IVA Responsable Inscripto | E11: 30715141201 | F11: 364413 | G11: 0 | H11: 0 | I11: 0 | J11: 0 | K11: 76526.73 | L11: 0 | M11: 0 | N11: 440939.73
A12: 45490 | B12: FA-A 0001-00003890 | C12: Rehab S.R.L. | D12: IVA Responsable Inscripto | E12: 30715141201 | F12: 818170.5 | G12: 0 | H12: 0 | I12: 0 | J12: 0 | K12: 171815.81 | L12: 0 | M12: 0 | N12: 989986.31
A13: 45495 | B13: FA-A 0001-00003956 | C13: Rehab S.R.L. | D13: IVA Responsable Inscripto | E13: 30715141201 | F13: 3832222.5 | G13: 0 | H13: 0 | I13: 0 | J13: 0 | K13: 804766.73 | L13: 0 | M13: 0 | N13: 4636989.2
A14: 45496 | B14: FA-A 0001-00003985 | C14: Rehab S.R.L. | D14: IVA Responsable Inscripto | E14: 30715141201 | F14: 1365747 | G14: 0 | H14: 0 | I14: 0 | J14: 0 | K14: 286806.87 | L14: 0 | M14: 0 | N14: 1652553.9
A15: 45502 | B15: FA-A 0001-00004054 | C15: Rehab S.R.L. | D15: IVA Responsable Inscripto | E15: 30715141201 | F15: 2047644.3 | G15: 0 | H15: 0 | I15: 0 | J15: 0 | K15: 430005.3 | L15: 0 | M15: 0 | N15: 2477649.6
A16: 45499 | B16: FA-A 0002-00000021 | C16: Bard, Marisa Silvia | D16: IVA Responsable Inscripto | E16: 27243660535 | F16: 360000 | G16: 0 | H16: 0 | I16: 0 | J16: 0 | K16: 75600 | L16: 0 | M16: 0 | N16: 435600
A17: 45474 | B17: FA-A 0002-00000212 | C17: CONSORCIO BTOME MITRE 2466 | D17: IVA Responsable Inscripto | E17: 30605344352 | F17: 834000 | G17: 0 | H17: 0 | I17: 0 | J17: 0 | K17: 175140 | L17: 0 | M17: 0 | N17: 1009140
... A115: 45478 | B115: FA-C 2019-00004305 | C115: Murua Pou, Pablo Roberto | D115: Responsable Monotributo | E115: 20277164192 | F115: 0 | G115: 5700 | H115: 0 | I115: 0 | J115: 0 | K115: 0 | L115: 0 | M115: 0 | N115: 5700
A116: 45484 | B116: R-C 0002-00000500 | C116: Sampedro Silivia Herminia | D116: Responsable Monotributo | E116: 27178792178 | G116: 680000 | H116: 0 | I116: 0 | J116: 0 | K116: 0 | L116: 0 | M116: 0 | N116: 680000
A117: 45456 | B117: TF-A 0002-00010354 | C117: LA CAMIONERA MENDOCINA SRL | D117: IVA Responsable Inscripto | E117: 33531122599 | F117: 80000 | G117: 0 | H117: 0 | I117: 0 | J117: 0 | K117: 16800 | L117: 0 | M117: 0 | N117: 96800
A118: 45455 | B118: TF-A0004-00000138 | C118: Gasco Conde, Silvia Monica | D118: IVA Responsable Inscripto | E118: 27942499154 | F118: 16528.93 | G118: 0 | H118: 0 | I118: 0 | J118: 0 | K118: 3471.08 | L118: 0 | M118: 0 | N118: 20000.01
A119: 45503 | B119: TF-A0006-00001564 | C119: Papelera Geopel S.R.L. | D119: IVA Responsable Inscripto | E119: 30716815710 | F119: 13400 | G119: 0 | H119: 0 | I119: 0 | J119: 0 | K119: 2814 | L119: 0 | M119: 0 | N119: 16214
A120: 45487 | B120: TF-A0008-00011937 | C120: Somos Energia S.A. | D120: IVA Responsable Inscripto | E120: 33715594949 | F120: 36231.57 | G120: 0 | H120: 0 | I120: 0 | J120: 0 | K120: 7608.63 | L120: 0 | M120: 3759.8 | N120: 47600
A121: 45493 | B121: TF-A0012-00010431 | C121: Mirvar Sa | D121: IVA Responsable Inscripto | E121: 30685116657 | F121: 36015.72 | G121: 0 | H121: 0 | I121: 0 | J121: 0 | K121: 7563.3 | L121: 0 | M121: 6424.79 | N121: 50003.81
A122: 45474 | B122: TF-A0012-00037786 | C122: Unens S R L | D122: IVA Responsable Inscripto | E122: 33688436279 | F122: 33236.31 | G122: 0 | H122: 0 | I122: 0 | J122: 0 | K122: 6979.63 | L122: 0 | M122: 6187.03 | N122: 46402.97
A123: 45484 | B123: TF-A0015-00035343 | C123: Mirvar Sa | D123: IVA Responsable Inscripto | E123: 30685116657 | F123: 35581.89 | G123: 0 | H123: 0 | I123: 0 | J123: 0 | K123: 7472.2 | L123: 0 | M123: 6347.4 | N123: 49401.49
A124: 45455 | B124: TF-A0020-00010392 | C124: Iacono, Juan | D124: IVA Responsable Inscripto | E124: 20139793170 | F124: 35450.39 | G124: 0 | H124: 0 | I124: 0 | J124: 0 | K124: 7444.58 | L124: 0 | M124: 6161.02 | N124: 49055.99
A125: 45482 | B125: TF-A0024-00018322 | C125: Iacono, Juan | D125: IVA Responsable Inscripto | E125: 20139793170 | F125: 94948.88 | G125: 0 | H125: 0 | I125: 0 | J125: 0 | K125: 19939.26 | L125: 0 | M125: 8618.91 | N125: 123507.05
A126: 45487 | B126: TF-A0024-00018434 | C126: Iacono, Juan | D126: IVA Responsable Inscripto | E126: 20139793170 | F126: 46675.67 | G126: 0 | H126: 0 | I126: 0 | J126: 0 | K126: 9801.89 | L126: 0 | M126: 4323.39 | N126: 60800.95
A127: 45492 | B127: TF-A0024-00018557 | C127: Iacono, Juan | D127: IVA Responsable Inscripto | E127: 20139793170 | F127: 38383.94 | G127: 0 | H127: 0 | I127: 0 | J127: 0 | K127: 8060.63 | L127: 0 | M127: 3555.36 | N127: 49999.93
A128: 45495 | B128: TF-A0024-00018621 | C128: Iacono, Juan | D128: IVA Responsable Inscripto | E128: 20139793170 | F128: 73087.75 | G128: 0 | H128: 0 | I128: 0 | J128: 0 | K128: 15348.43 | L128: 0 | M128: 6769.85 | N128: 95206.03
A129: 45501 | B129: TF-A0024-00018718 | C129: Iacono, Juan | D129: IVA Responsable Inscripto | E129: 20139793170 | F129: 90376.27 | G129: 0 | H129: 0 | I129: 0 | J129: 0 | K129: 18979.02 | L129: 0 | M129: 8272.69 | N129: 117627.98
F130: =SUM(F6:F129) -> 59861425 | G130: =SUM(G6:G129) -> 16517670 | H130: =SUM(H6:H129) -> 0 | I130: =SUM(I6:I129) -> 0 | J130: =SUM(J6:J129) -> 3470207.2 | K130: =SUM(K6:K129) -> 5615042.7 | L130: =SUM(L6:L129) -> 19853.97 | M130: =SUM(M6:M129) -> 88769.43 | N130: =SUM(N6:N129) -> 85572968
H131: =+SUM(H130:L130) -> 9105103.9
B135: Comprobantes AFIP no recepcionados
A138: Fecha | B138: Tipo | C138: Punto de Venta | D138: Número Desde | E138: Número Hasta | F138: Cód. Autorización | G138: Tipo Doc. Emisor | H138: Nro. Doc. Emisor | I138: Denominación Emisor | J138: Tipo Cambio | K138: Moneda | L138: Imp. Neto Gravado | M138: Imp. Neto No Gravado | N138: Imp. Op. Exentas | O138: Otros Tributos | P138: IVA | Q138: Imp. Total
A139: 16/07/2024 | B139: 11 - Factura C | C139: 1 | D139: 12 | F139: 74305085368219 | G139: CUIT | H139: 27443612705 | I139: MIGOYA MORIONDO MARIA INES | J139: 1 | K139: $ | O139: 0 | Q139: 600000
A140: 08/07/2024 | B140: 11 - Factura C | C140: 4 | D140: 35 | F140: 74283166033414 | G140: CUIT | H140: 20272417653 | I140: TACACHO ROLANDO GABRIEL | J140: 1 | K140: $ | O140: 0 | Q140: 260000
A141: 18/07/2024 | B141: 1 - Factura A | C141: 6 | D141: 64 | F141: 74292359557295 | G141: CUIT | H141: 20263640862 | I141: LURASCHI HUMBERTO JOSE | J141: 1 | K141: $ | L141: 75206.62 | M141: 0 | N141: 0 | O141: 0 | P141: 15793.39 | Q141: 91000
A142: 20/07/2024 | B142: 1 - Factura A | C142: 7 | D142: 395 | F142: 74297565435532 | G142: CUIT | H142: 30717409007 | I142: GUPARO S.R.L. | J142: 1 | K142: $ | L142: 46611.57 | M142: 0 | N142: 0 | O142: 0 | P142: 9788.43 | Q142: 56400
A143: 05/07/2024 | B143: 1 - Factura A | C143: 1057 | D143: 569 | F143: 74271882575824 | G143: CUIT | H143: 30685849751 | I143: DIA ARGENTINA S A | J143: 1 | K143: $ | L143: 15545.45 | M143: 0 | N143: 0 | O143: 0 | P143: 3264.55 | Q143: 19431.82
A144: 26/07/2024 | B144: 1 - Factura A | C144: 7 | D144: 1247 | F144: 74306210605040 | G144: CUIT | H144: 30712187316 | I144: ITALOMED PRODUCTOS SRL | J144: 1 | K144: $ | L144: 117224.59 | M144: 0 | N144: 0 | O144: 0 | P144: 24617.16 | Q144: 141841.75
A145: 19/07/2024 | B145: 1 - Factura A | C145: 5 | D145: 1589 | F145: 74294463686236 | G145: CUIT | H145: 30714712604 | I145: DONATO ALFREDO ENRIQUE Y PENSEL FRANCISCO JAVIER SOCIEDAD DE HECHO | J145: 1 | K145: $ | L145: 74214.05 | M145: 0 | N145: 0 | O145: 0 | P145: 15584.95 | Q145: 89799
A146: 29/07/2024 | B146: 1 - Factura A | C146: 18 | D146: 2048 | F146: 74316512167725 | G146: CUIT | H146: 30712049886 | I146: ALGETEC S.R.L. | J146: 1 | K146: $ | L146: 16528.93 | M146: 0 | N146: 0 | O146: 0 | P146: 3471.07 | Q146: 20000
A147: 22/07/2024 | B147: 1 - Factura A | C147: 6136 | D147: 11463 | F147: 34289099540173 | G147: CUIT | H147: 33707675069 | I147: BUS PACK S.A. | J147: 1 | K147: $ | L147: 7933.9 | M147: 0 | N147: 0 | O147: 0 | P147: 1666.12 | Q147: 9600.02
A148: 03/07/2024 | B148: 1 - Factura A | C148: 6 | D148: 13491 | F148: 74273644701506 | G148: CUIT | H148: 27929147893 | I148: CAMEJO GRACIELA | J148: 1 | K148: $ | L148: 7355.37 | M148: 0 | N148: 0 | O148: 0 | P148: 1544.63 | Q148: 8900
A149: 01/07/2024 | B149: 1 - Factura A | C149: 1326 | D149: 1171020 | F149: 74277498249368 | G149: CUIT | H149: 30663288497 | I149: AMX ARGENTINA SOCIEDAD ANONIMA | J149: 1 | K149: $ | L149: 37410 | M149: 0 | N149: 0 | O149: 0 | P149: 9266.4 | Q149: 50532.21
A150: 19/07/2024 | B150: 11 - Factura C | C150: 600 | D150: 1284072 | F150: 74308753465271 | G150: CUIT | H150: 30710573308 | I150: CAMARA DE GRABADORES DE AUTOPARTES DE VEHICULOS AUTOMOTORES Y MOTOVEHICULOS | J150: 1 | K150: $ | O150: 0 | Q150: 40068
A151: 29/07/2024 | B151: 1 - Factura A | C151: 503 | D151: 1406043 | F151: 74312570693695 | G151: CUIT | H151: 30639935872 | I151: CAMINOS DEL RIO URUGUAY S A DE CONSTRUCCIONES Y CONCESIONES VIALES | J151: 1 | K151: $ | L151: 2396.7 | M151: 0 | N151: 0 | O151: 0 | P151: 503.3 | Q151: 2995.87
A152: 07/07/2024 | B152: 1 - Factura A | C152: 12 | D152: 1749992 | F152: 74284155920654 | G152: CUIT | H152: 30709776564 | I152: PROSEGUR ACTIVA ARGENTINA SA | J152: 1 | K152: $ | L152: 110424.62 | M152: 0 | N152: 0 | O152: 0 | P152: 23189.17 | Q152: 138030.79
A153: 15/07/2024 | B153: 1 - Factura A | C153: 113 | D153: 3696756 | F153: 74290264554653 | G153: CUIT | H153: 30577207190 | I153: COORDINACION ECOLOGICA AREA METROPOLITANA SOCIEDAD DEL ESTADO | J153: 1 | K153: $ | L153: 1652.89 | M153: 0 | N153: 0 | O153: 0 | P153: 347.11 | Q153: 2000
A154: 31/07/2024 | B154: 1 - Factura A | C154: 6 | D154: 17094103 | F154: 74317575072057 | G154: CUIT | H154: 30620177497 | I154: POSNET SOCIEDAD DE RESPONSABILIDAD LIMITADA | J154: 1 | K154: $ | L154: 24051.46 | M154: 0 | N154: 0 | O154: 0 | P154: 5050.81 | Q154: 30785.87
L155: =SUM(L139:L154) -> 536556.15 | M155: =SUM(M139:M154) -> 0 | N155: =SUM(N139:N154) -> 0 | O155: =SUM(O139:O154) -> 0 | P155: =SUM(P139:P154) -> 114087.09 | Q155: =SUM(Q139:Q154) -> 1561385.3
B158: IVA Extractos Bancarios
B162: Banco Credicoop
B163: IVA-ALIC ADIC RG 2408 S/COMIS-REC GASTOS | D163: 390
B164: IVA - ALICUOTA INSCRIPTO | D164: 3497.76
B167: Banco Patagonia
B168: IVA Alicuota General | D168: 5906.25
B169: IVA Percepcion | D169: 750
C172: TOTAL IVA S/ EXTRACTOS | D172: =+SUM(D163,D164,D168,D169) -> 10544.01
