Workbook
Name partner_id: Configuracion!$B$332

Sheet Configuracion
F1: CUIT | G1: Cargar sin guiones
F2: RAZON SOCIAL | G2: Maximo 30 caracteres
A3: CUIT | B3: RAZON SOCIAL | C3: DETALLE | F3: DETALLE | G3: Cargar tipo de gasto
A4: 30628205090 | B4: ALBAMIE SA | C4: CLIENTE
A5: 30711678820 | B5: 2PSI INGENIERIA SRL | C5: PROVEEDOR
A6: 33716367539 | B6: 3PI S.A.S. | C6: PROVEEDOR
A7: 30660373108 | B7: ABC SA | C7: VARIOS
A8: 20300210881 | B8: ABOY DIEGO OSCAR | C8: PROVEEDOR
A9: 27229910782 | B9: ABUGAUCH MARIA DE LOS ANGELES | C9: PROVEEDOR
A10: 20242709897 | B10: ABUGAUCH VICTOR HUGO | C10: PROVEEDOR
A11: 20281669053 | B11: ACOSTA JAVIER GUSTAVO | C11: FLETE
A12: 20174240125 | B12: ACOSTA OSCAR ISIDRO | C12: VARIOS
A13: 30641659106 | B13: AGRISOL SA | C13: VARIOS
A14: 33709914109 | B14: ALAN COLLECTION SA | C14: VARIOS
A15: 20267161616 | B15: ALBAJARI DIEGO MARCOS | C15: VARIOS
... A155: 30537679855 | B155: ESTACION LIMA SA | C155: VARIOS
A156: 30-56864959-8 | B156: EXPRESO BISONTE SRL | C156: FLETE
A157: 30708542349 | B157: EXPRESO FORMOSA SRL | C157: FLETE
A158: 30526582884 | B158: EXPRESO MAR DEL PLATA SA | C158: FLETE
A159: 30577744579 | B159: EXPRESO TROLE SRL | C159: FLETE
A160: 30715949292 | B160: EYPAPEL SAS | C160: GASTOS VARIOS
A161: 30715980807 | B161: FABORT SRL | C161: PROVEEDOR
A162: 20359718765 | B162: FAIL ABRAHAM | C162: VARIOS
A163: 30643518364 | B163: FARMACIA DE MEDRANO SCS | C163: PROVEEDOR
A164: 30692138747 | B164: FARMACITY SA | C164: VARIOS
A165: 33712234429 | B165: FEDAGAS SA | C165: VARIOS
A166: 20353576012 | B166: FEDERICO PABLO FEOLA | C166: VARIOS
A167: 20343766441 | B167: FERNANDEZ MAURO | C167: TALLER
A168: 27062343449 | B168: FERREIRA LILIANA INES | C168: FLETE
... A516: 33717383139 | B516: BALINERO SRL | C516: VARIOS

Sheet Abril 2023
A1: ORTOPEDIA GEMINIS S.A. | J1: 45017
A4: LIBRO IVA COMPRAS
A6: FACTURAS A
A7: FECHA | B7: PTO VTA | C7: FAC A | D7: CUIT | E7: RAZON SOCIAL | F7: NETO | G7: IVA 21% | H7: IVA 27% | I7: IVA 10,5% | J7: P IVA | K7: IIBB CF | L7: IIBB BS | M7: NO GRAV | N7: OTROS | O7: TOTAL | P7: DETALLE
A8: 44998 | B8: 13 | C8: 1119 | D8: 33709914109 | E8: =VLOOKUP(D8,Configuracion!$A$4:$C$591,2,FALSE) -> ALAN COLLECTION SA | F8: 5289.26 | G8: =F8*21% -> 1110.7446 | O8: =SUM(F8:N8) -> 6400.0046 | P8: =VLOOKUP(D8,Configuracion!$A$4:$C$591,3,FALSE) -> VARIOS
A9: 44973 | B9: 13 | C9: 1095 | D9: 33709914109 | E9: =VLOOKUP(D9,Configuracion!$A$4:$C$591,2,FALSE) -> ALAN COLLECTION SA | F9: 1322.31 | G9: =F9*21% -> 277.6851 | O9: =SUM(F9:N9) -> 1599.9951 | P9: =VLOOKUP(D9,Configuracion!$A$4:$C$591,3,FALSE) -> VARIOS
A10: 45028 | B10: 13 | C10: 1140 | D10: 33709914109 | E10: =VLOOKUP(D10,Configuracion!$A$4:$C$591,2,FALSE) -> ALAN COLLECTION SA | F10: 2892.56 | G10: =F10*21% -> 607.4376 | O10: =SUM(F10:N10) -> 3499.9976 | P10: =VLOOKUP(D10,Configuracion!$A$4:$C$591,3,FALSE) -> VARIOS
A11: 45036 | B11: 13 | C11: 1150 | D11: 33709914109 | E11: =VLOOKUP(D11,Configuracion!$A$4:$C$591,2,FALSE) -> ALAN COLLECTION SA | F11: 2561.98 | G11: =F11*21% -> 538.0158 | O11: =SUM(F11:N11) -> 3099.9958 | P11: =VLOOKUP(D11,Configuracion!$A$4:$C$591,3,FALSE) -> VARIOS
A12: 11/04/2023 | B12: 8 | C12: 1430 | D12: 30708973501 | E12: =VLOOKUP(D12,Configuracion!$A$4:$C$591,2,FALSE) -> ASIAL SRL | F12: 239840 | G12: =F12*21% -> 50366.4 | O12: =SUM(F12:N12) -> 290206.4 | P12: =VLOOKUP(D12,Configuracion!$A$4:$C$591,3,FALSE) -> INSUMOS
A13: 11/04/2023 | B13: 8 | C13: 1431 | D13: 30708973501 | E13: =VLOOKUP(D13,Configuracion!$A$4:$C$591,2,FALSE) -> ASIAL SRL | F13: 221022 | G13: =F13*21% -> 46414.62 | O13: =SUM(F13:N13) -> 267436.62 | P13: =VLOOKUP(D13,Configuracion!$A$4:$C$591,3,FALSE) -> INSUMOS
A14: 10/04/2023 | B14: 4 | C14: 376 | D14: 20379223185 | E14: =VLOOKUP(D14,Configuracion!$A$4:$C$591,2,FALSE) -> AYALA MAURICIO JUAN JOSE | F14: 47380 | G14: =F14*21% -> 9949.8 | O14: =SUM(F14:N14) -> 57329.8 | P14: =VLOOKUP(D14,Configuracion!$A$4:$C$591,3,FALSE) -> PROVEEDOR
A15: 04/04/2023 | B15: 5 | C15: 2458 | D15: 33714662819 | E15: =VLOOKUP(D15,Configuracion!$A$4:$C$591,2,FALSE) -> AYUDAS TECNICAS SRL | F15: 510444 | G15: =F15*21% -> 107193.24 | O15: =SUM(F15:N15) -> 617637.24 | P15: =VLOOKUP(D15,Configuracion!$A$4:$C$591,3,FALSE) -> PROVEEDOR
A16: 04/04/2023 | B16: 6 | C16: 167 | D16: 33717383139 | E16: =VLOOKUP(D16,Configuracion!$A$4:$C$591,2,FALSE) -> BALINERO SRL | F16: 9330.58 | G16: =F16*21% -> 1959.4218 | O16: =SUM(F16:N16) -> 11290.002 | P16: =VLOOKUP(D16,Configuracion!$A$4:$C$591,3,FALSE) -> VARIOS
A17: 03/04/2023 | B17: 15 | C17: 4280 | D17: 33712276539 | E17: =VLOOKUP(D17,Configuracion!$A$4:$C$591,2,FALSE) -> CASTAÑO AUTOVOX SRL | F17: 10155.9 | G17: =F17*21% -> 2132.739 | K17: 355.46 | M17: 612.55 | O17: =SUM(F17:N17) -> 13256.649 | P17: =VLOOKUP(D17,Configuracion!$A$4:$C$591,3,FALSE) -> VARIOS
A18: 14/04/2023 | B18: 15 | C18: 4365 | D18: 33712276539 | E18: =VLOOKUP(D18,Configuracion!$A$4:$C$591,2,FALSE) -> CASTAÑO AUTOVOX SRL | F18: 12910.24 | G18: =F18*21% -> 2711.1504 | K18: 451.86 | M18: 778.67 | O18: =SUM(F18:N18) -> 16851.92 | P18: =VLOOKUP(D18,Configuracion!$A$4:$C$591,3,FALSE) -> VARIOS
A19: 22/04/2023 | B19: 27 | C19: 4512 | D19: 33712276539 | E19: =VLOOKUP(D19,Configuracion!$A$4:$C$591,2,FALSE) -> CASTAÑO AUTOVOX SRL | F19: 2662.46 | G19: =F19*21% -> 559.1166 | K19: 93.19 | N19: 155.28 | O19: =SUM(F19:N19) -> 3470.0466 | P19: =VLOOKUP(D19,Configuracion!$A$4:$C$591,3,FALSE) -> VARIOS
A20: 03/04/2023 | B20: 2 | C20: 182 | D20: 30605344352 | E20: =VLOOKUP(D20,Configuracion!$A$4:$C$591,2,FALSE) -> CONSORCIO BARTOLME MITRE 2466 | F20: 187880 | G20: =F20*21% -> 39454.8 | O20: =SUM(F20:N20) -> 227334.8 | P20: =VLOOKUP(D20,Configuracion!$A$4:$C$591,3,FALSE) -> CONSORCIO
A21: 14/04/2023 | B21: 2635 | C21: 964 | D21: 33699685459 | E21: =VLOOKUP(D21,Configuracion!$A$4:$C$591,2,FALSE) -> CORREO ANDREANI SA | F21: 1734.39 | G21: =F21*21% -> 364.2219 | O21: =SUM(F21:N21) -> 2098.6119 | P21: =VLOOKUP(D21,Configuracion!$A$4:$C$591,3,FALSE) -> VARIOS
A22: 30/04/2023 | B22: 20 | C22: 146748 | D22: 30696850972 | E22: =VLOOKUP(D22,Configuracion!$A$4:$C$591,2,FALSE) -> CPS COMUNICACIONES SA | F22: 3290.91 | H22: 888.55 | K22: 115.17 | O22: =SUM(F22:N22) -> 4294.63 | P22: =VLOOKUP(D22,Configuracion!$A$4:$C$591,3,FALSE) -> SERVICIO
A23: 03/04/2023 | B23: 3 | C23: 7688 | D23: 20045615473 | E23: =VLOOKUP(D23,Configuracion!$A$4:$C$591,2,FALSE) -> DI FEO HUGO PASCUAL GUILLERMO | F23: 28600 | G23: =F23*21% -> 6006 | O23: =SUM(F23:N23) -> 34606 | P23: =VLOOKUP(D23,Configuracion!$A$4:$C$591,3,FALSE) -> INSUMOS
A24: 13/04/2023 | B24: 3 | C24: 7710 | D24: 20045615473 | E24: =VLOOKUP(D24,Configuracion!$A$4:$C$591,2,FALSE) -> DI FEO HUGO PASCUAL GUILLERMO | F24: 15050 | G24: =F24*21% -> 3160.5 | O24: =SUM(F24:N24) -> 18210.5 | P24: =VLOOKUP(D24,Configuracion!$A$4:$C$591,3,FALSE) -> INSUMOS
A25: 13/04/2023 | B25: 3 | C25: 7713 | D25: 20045615473 | E25: =VLOOKUP(D25,Configuracion!$A$4:$C$591,2,FALSE) -> DI FEO HUGO PASCUAL GUILLERMO | F25: 2795 | G25: =F25*21% -> 586.95 | O25: =SUM(F25:N25) -> 3381.95 | P25: =VLOOKUP(D25,Configuracion!$A$4:$C$591,3,FALSE) -> INSUMOS
A26: 44987 | B26: 3 | C26: 7605 | D26: 20045615473 | E26: =VLOOKUP(D26,Configuracion!$A$4:$C$591,2,FALSE) -> DI FEO HUGO PASCUAL GUILLERMO | F26: 11415 | G26: =F26*21% -> 2397.15 | O26: =SUM(F26:N26) -> 13812.15 | P26: =VLOOKUP(D26,Configuracion!$A$4:$C$591,3,FALSE) -> INSUMOS
A27: 44980 | B27: 907 | C27: 206 | D27: 30685849751 | E27: =VLOOKUP(D27,Configuracion!$A$4:$C$591,2,FALSE) -> DIA ARGENTINA SA | F27: 415.37 | G27: =F27*21% -> 87.2277 | O27: =SUM(F27:N27) -> 502.5977 | P27: =VLOOKUP(D27,Configuracion!$A$4:$C$591,3,FALSE) -> VARIOS
A28: 44942 | B28: 10845 | C28: 63 | D28: 30685849751 | E28: =VLOOKUP(D28,Configuracion!$A$4:$C$591,2,FALSE) -> DIA ARGENTINA SA | F28: 1023.6 | G28: =F28*21% -> 214.956 | O28: =SUM(F28:N28) -> 1238.556 | P28: =VLOOKUP(D28,Configuracion!$A$4:$C$591,3,FALSE) -> VARIOS
A29: 11/04/2023 | B29: 7 | C29: 26677 | D29: 20271532483 | E29: =VLOOKUP(D29,Configuracion!$A$4:$C$591,2,FALSE) -> DIEGO MARTIN RIOS | F29: 1508857.9 | G29: =F29*21% -> 316860.15 | K29: 52810.03 | O29: =SUM(F29:N29) -> 1878528.1 | P29: =VLOOKUP(D29,Configuracion!$A$4:$C$591,3,FALSE) -> PROVEEDOR
A30: 14/04/2023 | B30: 7 | C30: 26710 | D30: 20271532483 | E30: =VLOOKUP(D30,Configuracion!$A$4:$C$591,2,FALSE) -> DIEGO MARTIN RIOS | F30: 1085101.3 | G30: =F30*21% -> 227871.28 | K30: 37978.55 | O30: =SUM(F30:N30) -> 1350951.1 | P30: =VLOOKUP(D30,Configuracion!$A$4:$C$591,3,FALSE) -> PROVEEDOR
A31: 19/04/2023 | B31: 7 | C31: 26744 | D31: 20271532483 | E31: =VLOOKUP(D31,Configuracion!$A$4:$C$591,2,FALSE) -> DIEGO MARTIN RIOS | F31: 561704.08 | G31: =F31*21% -> 117957.86 | K31: 19659.64 | O31: =SUM(F31:N31) -> 699321.58 | P31: =VLOOKUP(D31,Configuracion!$A$4:$C$591,3,FALSE) -> PROVEEDOR
A32: 24/04/2023 | B32: 7 | C32: 26800 | D32: 20271532483 | E32: =VLOOKUP(D32,Configuracion!$A$4:$C$591,2,FALSE) -> DIEGO MARTIN RIOS | F32: 1942261.4 | G32: =F32*21% -> 407874.89 | K32: 67979.15 | O32: =SUM(F32:N32) -> 2418115.4 | P32: =VLOOKUP(D32,Configuracion!$A$4:$C$591,3,FALSE) -> PROVEEDOR
A33: 25/04/2023 | B33: 2 | C33: 7247 | D33: 30694549817 | E33: =VLOOKUP(D33,Configuracion!$A$4:$C$591,2,FALSE) -> DISEÑOS JERY SRL | F33: 364800 | G33: =F33*21% -> 76608 | O33: =SUM(F33:N33) -> 441408 | P33: =VLOOKUP(D33,Configuracion!$A$4:$C$591,3,FALSE) -> PROVEEDOR
A34: 10/04/2023 | B34: 2 | C34: 671 | D34: 20140958213 | E34: =VLOOKUP(D34,Configuracion!$A$4:$C$591,2,FALSE) -> ESPAÑA ALEJANDRO JORGE | F34: 97107.44 | G34: =F34*21% -> 20392.562 | O34: =SUM(F34:N34) -> 117500 | P34: =VLOOKUP(D34,Configuracion!$A$4:$C$591,3,FALSE) -> PROVEEDOR
A35: 45026 | B35: 2 | C35: 671 | D35: 20140958213 | E35: =VLOOKUP(D35,Configuracion!$A$4:$C$591,2,FALSE) -> ESPAÑA ALEJANDRO JORGE | F35: 97107.44 | G35: =F35*21% -> 20392.562 | O35: =SUM(F35:N35) -> 117500 | P35: =VLOOKUP(D35,Configuracion!$A$4:$C$591,3,FALSE) -> PROVEEDOR
A36: 12/04/2023 | B36: 7 | C36: 381 | D36: 30711328498 | E36: =VLOOKUP(D36,Configuracion!$A$4:$C$591,2,FALSE) -> ESPOSITO FRANCISCO ANT Y OT SH | F36: 16363.64 | G36: =F36*21% -> 3436.3644 | O36: =SUM(F36:N36) -> 19800.004 | P36: =VLOOKUP(D36,Configuracion!$A$4:$C$591,3,FALSE) -> GASTOS MOVILIDAD
A37: 26/04/2023 | B37: 11 | C37: 81644 | D37: 30526582884 | E37: =VLOOKUP(D37,Configuracion!$A$4:$C$591,2,FALSE) -> EXPRESO MAR DEL PLATA SA | F37: 3826.45 | G37: =F37*21% -> 803.5545 | O37: =SUM(F37:N37) -> 4630.0045 | P37: =VLOOKUP(D37,Configuracion!$A$4:$C$591,3,FALSE) -> FLETE
A38: 03/04/2023 | B38: 44 | C38: 20505 | D38: 30626009618 | E38: =VLOOKUP(D38,Configuracion!$A$4:$C$591,2,FALSE) -> EXPRESO RIVADAVIA SRL | F38: 1499.07 | G38: =F38*21% -> 314.8047 | O38: =SUM(F38:N38) -> 1813.8747 | P38: =VLOOKUP(D38,Configuracion!$A$4:$C$591,3,FALSE) -> FLETE
A39: 03/04/2023 | B39: 48 | C39: 368332 | D39: 30626009618 | E39: =VLOOKUP(D39,Configuracion!$A$4:$C$591,2,FALSE) -> EXPRESO RIVADAVIA SRL | F39: 5646.21 | G39: =F39*21% -> 1185.7041 | O39: =SUM(F39:N39) -> 6831.9141 | P39: =VLOOKUP(D39,Configuracion!$A$4:$C$591,3,FALSE) -> FLETE
A40: 45035 | B40: 48 | C40: 371809 | D40: 30626009618 | E40: =VLOOKUP(D40,Configuracion!$A$4:$C$591,2,FALSE) -> EXPRESO RIVADAVIA SRL | F40: 5239.67 | G40: =F40*21% -> 1100.3307 | O40: =SUM(F40:N40) -> 6340.0007 | P40: =VLOOKUP(D40,Configuracion!$A$4:$C$591,3,FALSE) -> FLETE
A41: 44971 | B41: 2398 | C41: 669 | D41: 30692138747 | E41: =VLOOKUP(D41,Configuracion!$A$4:$C$591,2,FALSE) -> FARMACITY SA | F41: 2295.05 | G41: =F41*21% -> 481.9605 | K41: 68.85 | O41: =SUM(F41:N41) -> 2845.8605 | P41: =VLOOKUP(D41,Configuracion!$A$4:$C$591,3,FALSE) -> VARIOS
A42: 13/04/2023 | B42: 7 | C42: 1719 | D42: 20284183534 | E42: =VLOOKUP(D42,Configuracion!$A$4:$C$591,2,FALSE) -> FURLANETTO MARTIN | F42: 1735.54 | G42: =F42*21% -> 364.4634 | O42: =SUM(F42:N42) -> 2100.0034 | P42: =VLOOKUP(D42,Configuracion!$A$4:$C$591,3,FALSE) -> VARIOS
A43: 45033 | B43: 7 | C43: 1730 | D43: 20284183534 | E43: =VLOOKUP(D43,Configuracion!$A$4:$C$591,2,FALSE) -> FURLANETTO MARTIN | F43: 2743.84 | G43: =F43*21% -> 576.2064 | O43: =SUM(F43:N43) -> 3320.0464 | P43: =VLOOKUP(D43,Configuracion!$A$4:$C$591,3,FALSE) -> VARIOS
A44: 44953 | B44: 7 | C44: 1511 | D44: 20284183534 | E44: =VLOOKUP(D44,Configuracion!$A$4:$C$591,2,FALSE) -> FURLANETTO MARTIN | F44: 2975.21 | G44: =F44*21% -> 624.7941 | O44: =SUM(F44:N44) -> 3600.0041 | P44: =VLOOKUP(D44,Configuracion!$A$4:$C$591,3,FALSE) -> VARIOS
A45: 44958 | B45: 7 | C45: 1522 | D45: 20284183534 | E45: =VLOOKUP(D45,Configuracion!$A$4:$C$591,2,FALSE) -> FURLANETTO MARTIN | F45: 3115.7 | G45: =F45*21% -> 654.297 | O45: =SUM(F45:N45) -> 3769.997 | P45: =VLOOKUP(D45,Configuracion!$A$4:$C$591,3,FALSE) -> VARIOS
A46: 28/02/2023 | B46: 5 | C46: 1116 | D46: 30712187316 | E46: =VLOOKUP(D46,Configuracion!$A$4:$C$591,2,FALSE) -> ITALOMED PRODUCTOS SRL | F46: 50933.6 | G46: =F46*21% -> 10696.056 | O46: =SUM(F46:N46) -> 61629.656 | P46: =VLOOKUP(D46,Configuracion!$A$4:$C$591,3,FALSE) -> PROVEEDOR
A47: 11/04/2023 | B47: 7 | C47: 781 | D47: 30712187316 | E47: =VLOOKUP(D47,Configuracion!$A$4:$C$591,2,FALSE) -> ITALOMED PRODUCTOS SRL | F47: 37778.22 | G47: =F47*21% -> 7933.4262 | O47: =SUM(F47:N47) -> 45711.646 | P47: =VLOOKUP(D47,Configuracion!$A$4:$C$591,3,FALSE) -> PROVEEDOR
A48: 11/04/2023 | B48: 7 | C48: 782 | D48: 30712187316 | E48: =VLOOKUP(D48,Configuracion!$A$4:$C$591,2,FALSE) -> ITALOMED PRODUCTOS SRL | F48: 39239.64 | G48: =F48*21% -> 8240.3244 | O48: =SUM(F48:N48) -> 47479.964 | P48: =VLOOKUP(D48,Configuracion!$A$4:$C$591,3,FALSE) -> PROVEEDOR
A49: 19/04/2023 | B49: 5 | C49: 1184 | D49: 30712187316 | E49: =VLOOKUP(D49,Configuracion!$A$4:$C$591,2,FALSE) -> ITALOMED PRODUCTOS SRL | F49: 53197.13 | G49: =F49*21% -> 11171.397 | O49: =SUM(F49:N49) -> 64368.527 | P49: =VLOOKUP(D49,Configuracion!$A$4:$C$591,3,FALSE) -> PROVEEDOR
A50: 45013 | B50: 7 | C50: 768 | D50: 30712187316 | E50: =VLOOKUP(D50,Configuracion!$A$4:$C$591,2,FALSE) -> ITALOMED PRODUCTOS SRL | F50: 39239.64 | G50: =F50*21% -> 8240.3244 | O50: =SUM(F50:N50) -> 47479.964 | P50: =VLOOKUP(D50,Configuracion!$A$4:$C$591,3,FALSE) -> PROVEEDOR
A51: 44964 | B51: 5 | C51: 1091 | D51: 30712187316 | E51: =VLOOKUP(D51,Configuracion!$A$4:$C$591,2,FALSE) -> ITALOMED PRODUCTOS SRL | F51: 45822.29 | G51: =F51*21% -> 9622.6809 | O51: =SUM(F51:N51) -> 55444.971 | P51: =VLOOKUP(D51,Configuracion!$A$4:$C$591,3,FALSE) -> PROVEEDOR
A52: 44970 | B52: 5 | C52: 1099 | D52: 30712187316 | E52: =VLOOKUP(D52,Configuracion!$A$4:$C$591,2,FALSE) -> ITALOMED PRODUCTOS SRL | F52: 46362.8 | G52: =F52*21% -> 9736.188 | O52: =SUM(F52:N52) -> 56098.988 | P52: =VLOOKUP(D52,Configuracion!$A$4:$C$591,3,FALSE) -> PROVEEDOR
A53: 44970 | B53: 5 | C53: 1100 | D53: 30712187316 | E53: =VLOOKUP(D53,Configuracion!$A$4:$C$591,2,FALSE) -> ITALOMED PRODUCTOS SRL | F53: 39239.64 | G53: =F53*21% -> 8240.3244 | O53: =SUM(F53:N53) -> 47479.964 | P53: =VLOOKUP(D53,Configuracion!$A$4:$C$591,3,FALSE) -> PROVEEDOR
A54: 45013 | B54: 7 | C54: 767 | D54: 30712187316 | E54: =VLOOKUP(D54,Configuracion!$A$4:$C$591,2,FALSE) -> ITALOMED PRODUCTOS SRL | F54: 39239.64 | G54: =F54*21% -> 8240.3244 | O54: =SUM(F54:N54) -> 47479.964 | P54: =VLOOKUP(D54,Configuracion!$A$4:$C$591,3,FALSE) -> PROVEEDOR
A55: 18/04/2023 | B55: 7 | C55: 3721 | D55: 30709904872 | E55: =VLOOKUP(D55,Configuracion!$A$4:$C$591,2,FALSE) -> LOGISTICA DE LA COSTA SA | F55: 5785.12 | G55: =F55*21% -> 1214.8752 | O55: =SUM(F55:N55) -> 6999.9952 | P55: =VLOOKUP(D55,Configuracion!$A$4:$C$591,3,FALSE) -> FLETE
A56: 45005 | B56: 10 | C56: 91 | D56: 30716229552 | E56: =VLOOKUP(D56,Configuracion!$A$4:$C$591,2,FALSE) -> LUBRICANTES RUTA DE P e H SRL | F56: 1892.56 | G56: =F56*21% -> 397.4376 | O56: =SUM(F56:N56) -> 2289.9976 | P56: =VLOOKUP(D56,Configuracion!$A$4:$C$591,3,FALSE) -> VARIOS
A57: 25/04/2023 | B57: 5 | C57: 15 | D57: 20929183143 | E57: =VLOOKUP(D57,Configuracion!$A$4:$C$591,2,FALSE) -> MA JUN | F57: 9500 | G57: =F57*21% -> 1995 | O57: =SUM(F57:N57) -> 11495 | P57: =VLOOKUP(D57,Configuracion!$A$4:$C$591,3,FALSE) -> VARIOS
A58: 11/04/2023 | B58: 14 | C58: 29971 | D58: 30657715383 | E58: =VLOOKUP(D58,Configuracion!$A$4:$C$591,2,FALSE) -> MADERERA LLAVALLOL SA | F58: 51084.01 | G58: =F58*21% -> 10727.642 | K58: 1787.94 | O58: =SUM(F58:N58) -> 63599.592 | P58: =VLOOKUP(D58,Configuracion!$A$4:$C$591,3,FALSE) -> VARIOS
A59: 45008 | B59: 3 | C59: 5478 | D59: 33708218699 | E59: =VLOOKUP(D59,Configuracion!$A$4:$C$591,2,FALSE) -> MANGGINI PABLO Y M ULISES SH | F59: 3500 | G59: =F59*21% -> 735 | O59: =SUM(F59:N59) -> 4235 | P59: =VLOOKUP(D59,Configuracion!$A$4:$C$591,3,FALSE) -> VARIOS
A60: 24/04/2023 | B60: 3 | C60: 5582 | D60: 33708218699 | E60: =VLOOKUP(D60,Configuracion!$A$4:$C$591,2,FALSE) -> MANGGINI PABLO Y M ULISES SH | F60: 3500 | G60: =F60*21% -> 735 | O60: =SUM(F60:N60) -> 4235 | P60: =VLOOKUP(D60,Configuracion!$A$4:$C$591,3,FALSE) -> VARIOS
A61: 45016 | B61: 3 | C61: 2886 | D61: 27944827345 | E61: =VLOOKUP(D61,Configuracion!$A$4:$C$591,2,FALSE) -> MARLENE ALONZO SANTANDER | F61: 1652.89 | G61: =F61*21% -> 347.1069 | O61: =SUM(F61:N61) -> 1999.9969 | P61: =VLOOKUP(D61,Configuracion!$A$4:$C$591,3,FALSE) -> VARIOS
A62: 05/04/2023 | B62: 12 | C62: 14 | D62: 27202892936 | E62: =VLOOKUP(D62,Configuracion!$A$4:$C$591,2,FALSE) -> MORIONDO ADRIANA INES | F62: 894121.78 | G62: =F62*21% -> 187765.57 | O62: =SUM(F62:N62) -> 1081887.4 | P62: =VLOOKUP(D62,Configuracion!$A$4:$C$591,3,FALSE) -> PROVEEDOR
A63: 03/04/2023 | B63: 3 | C63: 61 | D63: 20334976433 | E63: =VLOOKUP(D63,Configuracion!$A$4:$C$591,2,FALSE) -> NARDOMARINO EZEQUIEL EDUARDO | F63: 119574.38 | G63: =F63*21% -> 25110.62 | O63: =SUM(F63:N63) -> 144685 | P63: =VLOOKUP(D63,Configuracion!$A$4:$C$591,3,FALSE) -> FLETE
A64: 10/04/2023 | B64: 3 | C64: 63 | D64: 20334976433 | E64: =VLOOKUP(D64,Configuracion!$A$4:$C$591,2,FALSE) -> NARDOMARINO EZEQUIEL EDUARDO | F64: 54749.59 | G64: =F64*21% -> 11497.414 | O64: =SUM(F64:N64) -> 66247.004 | P64: =VLOOKUP(D64,Configuracion!$A$4:$C$591,3,FALSE) -> FLETE
A65: 17/04/2023 | B65: 3 | C65: 65 | D65: 20334976433 | E65: =VLOOKUP(D65,Configuracion!$A$4:$C$591,2,FALSE) -> NARDOMARINO EZEQUIEL EDUARDO | F65: 80161.16 | G65: =F65*21% -> 16833.844 | O65: =SUM(F65:N65) -> 96995.004 | P65: =VLOOKUP(D65,Configuracion!$A$4:$C$591,3,FALSE) -> FLETE
A66: 25/04/2023 | B66: 3 | C66: 67 | D66: 20334976433 | E66: =VLOOKUP(D66,Configuracion!$A$4:$C$591,2,FALSE) -> NARDOMARINO EZEQUIEL EDUARDO | F66: 98491 | G66: =F66*21% -> 20683.11 | O66: =SUM(F66:N66) -> 119174.11 | P66: =VLOOKUP(D66,Configuracion!$A$4:$C$591,3,FALSE) -> FLETE
A67: 44998 | B67: 3 | C67: 52 | D67: 20334976433 | E67: =VLOOKUP(D67,Configuracion!$A$4:$C$591,2,FALSE) -> NARDOMARINO EZEQUIEL EDUARDO | F67: 93318.18 | G67: =F67*21% -> 19596.818 | O67: =SUM(F67:N67) -> 112915 | P67: =VLOOKUP(D67,Configuracion!$A$4:$C$591,3,FALSE) -> FLETE
A68: 21/04/2023 | B68: 5 | C68: 2756625 | D68: 30702652975 | E68: =VLOOKUP(D68,Configuracion!$A$4:$C$591,2,FALSE) -> NSS SA - IPLAN | F68: 6248.38 | G68: =F68*21% -> 1312.1598 | K68: 218.69 | O68: =SUM(F68:N68) -> 7779.2298 | P68: =VLOOKUP(D68,Configuracion!$A$4:$C$591,3,FALSE) -> SERVICIO
A69: 19/04/2023 | B69: 1 | C69: 451 | D69: 33716711469 | E69: =VLOOKUP(D69,Configuracion!$A$4:$C$591,2,FALSE) -> ORTOPEDIA SOLER SRL | F69: 80000 | G69: =F69*21% -> 16800 | O69: =SUM(F69:N69) -> 96800 | P69: =VLOOKUP(D69,Configuracion!$A$4:$C$591,3,FALSE) -> PROVEEDOR
A70: 26/04/2023 | B70: 4 | C70: 63589 | D70: 33709738459 | E70: =VLOOKUP(D70,Configuracion!$A$4:$C$591,2,FALSE) -> ORTOPEDICOS ALFOLATEX SA | F70: 196213.45 | G70: =F70*21% -> 41204.825 | O70: =SUM(F70:N70) -> 237418.27 | P70: =VLOOKUP(D70,Configuracion!$A$4:$C$591,3,FALSE) -> PROVEEDOR
A71: 19/04/2023 | B71: 120 | C71: 2449 | D71: 30587197215 | E71: =VLOOKUP(D71,Configuracion!$A$4:$C$591,2,FALSE) -> PANATEL SOCIEDAD ANONIMA | F71: 16528.93 | G71: =F71*21% -> 3471.0753 | O71: =SUM(F71:N71) -> 20000.005 | P71: =VLOOKUP(D71,Configuracion!$A$4:$C$591,3,FALSE) -> VARIOS
A72: 25/04/2023 | B72: 6 | C72: 57287 | D72: 30591633984 | E72: =VLOOKUP(D72,Configuracion!$A$4:$C$591,2,FALSE) -> PANTYMED SA | F72: 147364 | G72: =F72*21% -> 30946.44 | O72: =SUM(F72:N72) -> 178310.44 | P72: =VLOOKUP(D72,Configuracion!$A$4:$C$591,3,FALSE) -> PROVEEDOR
A73: 13/04/2023 | B73: 6 | C73: 897 | D73: 30716815710 | E73: =VLOOKUP(D73,Configuracion!$A$4:$C$591,2,FALSE) -> PAPELERA GEOPEL SRL | F73: 9629.75 | G73: =F73*21% -> 2022.2475 | O73: =SUM(F73:N73) -> 11651.997 | P73: =VLOOKUP(D73,Configuracion!$A$4:$C$591,3,FALSE) -> LIBRERÍA
A74: 19/04/2023 | B74: 6 | C74: 907 | D74: 30716815710 | E74: =VLOOKUP(D74,Configuracion!$A$4:$C$591,2,FALSE) -> PAPELERA GEOPEL SRL | F74: 3217.14 | G74: =F74*21% -> 675.5994 | O74: =SUM(F74:N74) -> 3892.7394 | P74: =VLOOKUP(D74,Configuracion!$A$4:$C$591,3,FALSE) -> LIBRERÍA
A75: 44939 | B75: 6 | C75: 788 | D75: 30716815710 | E75: =VLOOKUP(D75,Configuracion!$A$4:$C$591,2,FALSE) -> PAPELERA GEOPEL SRL | F75: 930 | G75: =F75*21% -> 195.3 | O75: =SUM(F75:N75) -> 1125.3 | P75: =VLOOKUP(D75,Configuracion!$A$4:$C$591,3,FALSE) -> LIBRERÍA
A76: 44966 | B76: 6 | C76: 827 | D76: 30716815710 | E76: =VLOOKUP(D76,Configuracion!$A$4:$C$591,2,FALSE) -> PAPELERA GEOPEL SRL | F76: 1360 | G76: =F76*21% -> 285.6 | O76: =SUM(F76:N76) -> 1645.6 | P76: =VLOOKUP(D76,Configuracion!$A$4:$C$591,3,FALSE) -> LIBRERÍA
A77: 45008 | B77: 4 | C77: 4082 | D77: 20113613646 | E77: =VLOOKUP(D77,Configuracion!$A$4:$C$591,2,FALSE) -> PIETRUSZKA ALBERTO DANIEL | F77: 3438.02 | G77: =F77*21% -> 721.9842 | O77: =SUM(F77:N77) -> 4160.0042 | P77: =VLOOKUP(D77,Configuracion!$A$4:$C$591,3,FALSE) -> VARIOS
A78: 44992 | B78: 12 | C78: 1584245 | D78: 30709776564 | E78: =VLOOKUP(D78,Configuracion!$A$4:$C$591,2,FALSE) -> PROSEGUR ACTIVA ARG SA | F78: 13629.92 | G78: =F78*21% -> 2862.2832 | K78: 477.05 | O78: =SUM(F78:N78) -> 16969.253 | P78: =VLOOKUP(D78,Configuracion!$A$4:$C$591,3,FALSE) -> SEGUROS
A79: 03/04/2023 | B79: 1001 | C79: 234 | D79: 30707370552 | E79: =VLOOKUP(D79,Configuracion!$A$4:$C$591,2,FALSE) -> RAKE SA | F79: 257396.7 | G79: =F79*21% -> 54053.307 | O79: =SUM(F79:N79) -> 311450.01 | P79: =VLOOKUP(D79,Configuracion!$A$4:$C$591,3,FALSE) -> PROVEEDOR
A80: 03/04/2023 | B80: 1001 | C80: 235 | D80: 30707370552 | E80: =VLOOKUP(D80,Configuracion!$A$4:$C$591,2,FALSE) -> RAKE SA | F80: 80991.74 | G80: =F80*21% -> 17008.265 | O80: =SUM(F80:N80) -> 98000.005 | P80: =VLOOKUP(D80,Configuracion!$A$4:$C$591,3,FALSE) -> PROVEEDOR
A81: 03/04/2023 | B81: 1001 | C81: 236 | D81: 30707370552 | E81: =VLOOKUP(D81,Configuracion!$A$4:$C$591,2,FALSE) -> RAKE SA | F81: 260330.58 | G81: =F81*21% -> 54669.422 | O81: =SUM(F81:N81) -> 315000 | P81: =VLOOKUP(D81,Configuracion!$A$4:$C$591,3,FALSE) -> PROVEEDOR
A82: 03/04/2023 | B82: 7 | C82: 15022 | D82: 30709214078 | E82: =VLOOKUP(D82,Configuracion!$A$4:$C$591,2,FALSE) -> REHAVITA SA | F82: 98652 | I82: 10358.46 | O82: =SUM(F82:N82) -> 109010.46 | P82: =VLOOKUP(D82,Configuracion!$A$4:$C$591,3,FALSE) -> PROVEEDOR
A83: 03/04/2023 | B83: 7 | C83: 15023 | D83: 30709214078 | E83: =VLOOKUP(D83,Configuracion!$A$4:$C$591,2,FALSE) -> REHAVITA SA | F83: 98652 | I83: 10358.446 | O83: =SUM(F83:N83) -> 109010.45 | P83: =VLOOKUP(D83,Configuracion!$A$4:$C$591,3,FALSE) -> PROVEEDOR
A84: 05/04/2023 | B84: 7 | C84: 15122 | D84: 30709214078 | E84: =VLOOKUP(D84,Configuracion!$A$4:$C$591,2,FALSE) -> REHAVITA SA | F84: 106144 | I84: 11145.12 | O84: =SUM(F84:N84) -> 117289.12 | P84: =VLOOKUP(D84,Configuracion!$A$4:$C$591,3,FALSE) -> PROVEEDOR
A85: 05/04/2023 | B85: 7 | C85: 15134 | D85: 30709214078 | E85: =VLOOKUP(D85,Configuracion!$A$4:$C$591,2,FALSE) -> REHAVITA SA | F85: 98652 | I85: 10358.46 | O85: =SUM(F85:N85) -> 109010.46 | P85: =VLOOKUP(D85,Configuracion!$A$4:$C$591,3,FALSE) -> PROVEEDOR
A86: 03/04/2023 | B86: 17 | C86: 876 | D86: 30711764921 | E86: =VLOOKUP(D86,Configuracion!$A$4:$C$591,2,FALSE) -> RELIEF CENTER SRL | F86: 10550 | G86: =F86*21% -> 2215.5 | O86: =SUM(F86:N86) -> 12765.5 | P86: =VLOOKUP(D86,Configuracion!$A$4:$C$591,3,FALSE) -> PROVEEDOR
A87: 04/04/2023 | B87: 17 | C87: 878 | D87: 30711764921 | E87: =VLOOKUP(D87,Configuracion!$A$4:$C$591,2,FALSE) -> RELIEF CENTER SRL | F87: 58680 | G87: =F87*21% -> 12322.8 | O87: =SUM(F87:N87) -> 71002.8 | P87: =VLOOKUP(D87,Configuracion!$A$4:$C$591,3,FALSE) -> PROVEEDOR
A88: 44998 | B88: 17 | C88: 826 | D88: 30711764921 | E88: =VLOOKUP(D88,Configuracion!$A$4:$C$591,2,FALSE) -> RELIEF CENTER SRL | F88: 34652 | G88: =F88*21% -> 7276.92 | O88: =SUM(F88:N88) -> 41928.92 | P88: =VLOOKUP(D88,Configuracion!$A$4:$C$591,3,FALSE) -> PROVEEDOR
A89: 45000 | B89: 17 | C89: 833 | D89: 30711764921 | E89: =VLOOKUP(D89,Configuracion!$A$4:$C$591,2,FALSE) -> RELIEF CENTER SRL | F89: 35335 | G89: =F89*21% -> 7420.35 | O89: =SUM(F89:N89) -> 42755.35 | P89: =VLOOKUP(D89,Configuracion!$A$4:$C$591,3,FALSE) -> PROVEEDOR
A90: 45007 | B90: 17 | C90: 842 | D90: 30711764921 | E90: =VLOOKUP(D90,Configuracion!$A$4:$C$591,2,FALSE) -> RELIEF CENTER SRL | F90: 21194 | G90: =F90*21% -> 4450.74 | O90: =SUM(F90:N90) -> 25644.74 | P90: =VLOOKUP(D90,Configuracion!$A$4:$C$591,3,FALSE) -> PROVEEDOR
A91: 31/03/2023 | B91: 1 | C91: 577 | D91: 30715048066 | E91: =VLOOKUP(D91,Configuracion!$A$4:$C$591,2,FALSE) -> ROLLS Y EMPANADAS SA | F91: 300340 | G91: =F91*21% -> 63071.4 | O91: =SUM(F91:N91) -> 363411.4 | P91: =VLOOKUP(D91,Configuracion!$A$4:$C$591,3,FALSE) -> VARIOS
A92: 28/04/2023 | B92: 1 | C92: 591 | D92: 30715048066 | E92: =VLOOKUP(D92,Configuracion!$A$4:$C$591,2,FALSE) -> ROLLS Y EMPANADAS SA | F92: 313910 | G92: =F92*21% -> 65921.1 | O92: =SUM(F92:N92) -> 379831.1 | P92: =VLOOKUP(D92,Configuracion!$A$4:$C$591,3,FALSE) -> VARIOS
A93: 03/04/2023 | B93: 8 | C93: 133545 | D93: 30707927409 | E93: =VLOOKUP(D93,Configuracion!$A$4:$C$591,2,FALSE) -> ROSARIO LOGISTICA SA | F93: 4245 | G93: =F93*21% -> 891.45 | O93: =SUM(F93:N93) -> 5136.45 | P93: =VLOOKUP(D93,Configuracion!$A$4:$C$591,3,FALSE) -> FLETE
A94: 12/04/2023 | B94: 6 | C94: 72430 | D94: 30711553564 | E94: =VLOOKUP(D94,Configuracion!$A$4:$C$591,2,FALSE) -> SALUDTEX SA | F94: 279838 | G94: =F94*21% -> 58765.98 | O94: =SUM(F94:N94) -> 338603.98 | P94: =VLOOKUP(D94,Configuracion!$A$4:$C$591,3,FALSE) -> PROVEEDOR
A95: 24/04/2023 | B95: 6 | C95: 72802 | D95: 30711553564 | E95: =VLOOKUP(D95,Configuracion!$A$4:$C$591,2,FALSE) -> SALUDTEX SA | F95: 60918 | G95: =F95*21% -> 12792.78 | O95: =SUM(F95:N95) -> 73710.78 | P95: =VLOOKUP(D95,Configuracion!$A$4:$C$591,3,FALSE) -> PROVEEDOR
A96: 45006 | B96: 4 | C96: 6878 | D96: 20229905199 | E96: =VLOOKUP(D96,Configuracion!$A$4:$C$591,2,FALSE) -> SURDO HERNAN OMAR | F96: 917.4 | G96: =F96*21% -> 192.654 | O96: =SUM(F96:N96) -> 1110.054 | P96: =VLOOKUP(D96,Configuracion!$A$4:$C$591,3,FALSE) -> VARIOS
A97: 25/04/2023 | B97: 6 | C97: 48008 | D97: 30710177658 | E97: =VLOOKUP(D97,Configuracion!$A$4:$C$591,2,FALSE) -> TARGET MEDICAL SA | F97: 254528 | G97: =F97*21% -> 53450.88 | O97: =SUM(F97:N97) -> 307978.88 | P97: =VLOOKUP(D97,Configuracion!$A$4:$C$591,3,FALSE) -> PROVEEDOR
A98: 09/04/2023 | B98: 948 | C98: 942368 | D98: 30639453975 | E98: =VLOOKUP(D98,Configuracion!$A$4:$C$591,2,FALSE) -> TELEFONICA ARG SA | F98: 9354.22 | H98: 2525.64 | J98: 280.63 | K98: 327.4 | O98: =SUM(F98:N98) -> 12487.89 | P98: =VLOOKUP(D98,Configuracion!$A$4:$C$591,3,FALSE) -> SERVICIO
A99: 44965 | B99: 31 | C99: 12098 | D99: 30708375582 | E99: =VLOOKUP(D99,Configuracion!$A$4:$C$591,2,FALSE) -> TRANSPORTES E.G. SRL | F99: 6702.48 | G99: =F99*21% -> 1407.5208 | O99: =SUM(F99:N99) -> 8110.0008 | P99: =VLOOKUP(D99,Configuracion!$A$4:$C$591,3,FALSE) -> FLETE
A100: 03/04/2023 | B100: 4 | C100: 24600 | D100: 30646150406 | E100: =VLOOKUP(D100,Configuracion!$A$4:$C$591,2,FALSE) -> TRUST SRL | F100: 7449 | G100: =F100*21% -> 1564.29 | O100: =SUM(F100:N100) -> 9013.29 | P100: =VLOOKUP(D100,Configuracion!$A$4:$C$591,3,FALSE) -> PROVEEDOR
A101: 45005 | B101: 6442 | C101: 2066 | D101: 30643922157 | E101: =VLOOKUP(D101,Configuracion!$A$4:$C$591,2,FALSE) -> VIA BARILOCHE SA | F101: 1685.95 | G101: =F101*21% -> 354.0495 | O101: =SUM(F101:N101) -> 2039.9995 | P101: =VLOOKUP(D101,Configuracion!$A$4:$C$591,3,FALSE) -> FLETE
A102: 14/04/2023 | B102: 4 | C102: 35 | D102: 20317488476 | E102: =VLOOKUP(D102,Configuracion!$A$4:$C$591,2,FALSE) -> VILLALBA MIGUEL ANGEL | F102: 61600 | G102: =F102*21% -> 12936 | O102: =SUM(F102:N102) -> 74536 | P102: =VLOOKUP(D102,Configuracion!$A$4:$C$591,3,FALSE) -> PROVEEDOR
A103: 25/04/2023 | B103: 4 | C103: 36 | D103: 20317488476 | E103: =VLOOKUP(D103,Configuracion!$A$4:$C$591,2,FALSE) -> VILLALBA MIGUEL ANGEL | F103: 89300 | G103: =F103*21% -> 18753 | O103: =SUM(F103:N103) -> 108053 | P103: =VLOOKUP(D103,Configuracion!$A$4:$C$591,3,FALSE) -> PROVEEDOR
...

Sheet Calculo IVA
B1: ORTOPEDIA GEMINIS
A2: Calculo Iva | D2: 45017
B4: VENTAS
B5: Neto | C5: Iva | D5: Total
A6: FAC. "A" | B6: =+'Abril 2023'!F227 -> 0 | C6: =(B6*0.21) -> 0 | D6: =(B6+C6) -> 0
A7: FAC. "B" | B7: =+'Abril 2023'!F237 -> 0 | C7: =(B7*0.21) -> 0 | D7: =(B7+C7) -> 0
A8: FAC. "A" - Odoo | B8: =+'Abril 2023'!B246+'Abril 2023'!B248+'Abril 2023'!B249+'Abril 2023'!B247 -> 27597413 | C8: =+B8*0.21 -> 5795456.7 | D8: =(B8+C8) -> 33392869
A9: FAC. "B" - Odoo | B9: =+'Abril 2023'!B250+'Abril 2023'!B251 -> 2558641.9 | C9: =+B9*0.21 -> 537314.79 | D9: =(B9+C9) -> 3095956.7
B10: =SUM(B6:B9) -> 30156055 | C10: =SUM(C6:C9) -> 6332771.5 | D10: =SUM(D6:D9) -> 36488826
B13: COMPRAS
B14: Neto | C14: Iva | D14: Total
B15: =+'Abril 2023'!F120 -> 11859356 | C15: =+'Abril 2023'!G120+'Abril 2023'!H120+'Abril 2023'!I120 -> 2449003 | D15: =(B15+C15) -> 14308359
B17: =SUM(B15:B16) -> 11859356 | C17: =SUM(C15:C16) -> 2449003 | D17: =SUM(D15:D16) -> 14308359
A20: RETENCIONES | B20: N° Cuit | C20: Importe | D20: Nro. Retencion | E20: Fecha
A21: AFIP - No están informadas las retenciones de IVA en el sistema de AFIP
C36: =+'Abril 2023'!G213 -> 2641321.8
A38: PERCEPCIONES | B38: N° Cuit | C38: Importe | D38: Nro. Retencion | E38: Fecha
C42: =SUM(C39:C41) -> 0
A44: Total Deducciociones | C44: =+C42+C36 -> 2641321.8
C47: (Montos en Positivo)
A48: 1er Saldo Tecnico del Período | C48: =+C10-C17 -> 3883768.4
A50: Saldo Tecnico de período Anterior (a favor) | D50: (resta en el total)
A52: Saldo Neto Técnico | C52: =+C48-C50 -> 3883768.4
A56: Saldo L.D. del Período | C56: =+C42+C36 -> 2641321.8
A58: Saldo L.D. del Período Anterior
A60: Neto S.L.D | C60: =+C56+C58 -> 2641321.8
A63: I V A | C63: =+C52-C60 -> 1242446.7
A64: NOTA: Sin Tomar posibles Retenciones que se hayan hecho

Sheet Ventas 04 2023
A2: Ventas Libro de IVA 01/04/2023 - 30/04/2023
A3: Ortopedia Geminis S.A.
A5: Fecha | B5: Comprobante | C5: Nombre | D5: Cond. IVA | E5: CUIT o Doc. | F5: Gravado | G5: No Gravado | H5: IVA 2,5% | I5: IVA 5% | J5: IVA 10.5% | K5: IVA 21% | L5: IVA 27% | M5: Otros Imp | N5: Total Compr.
A6: 03/04/2023 | B6: FA-B 0005-00007644 | C6: .CONSUMIDOR FINAL | D6: Consumidor Final | F6: 3884.3 | G6: 0 | H6: 0 | I6: 0 | J6: 0 | K6: 815.7 | L6: 0 | M6: 0 | N6: 4700
A7: 03/04/2023 | B7: FA-B 0005-00007645 | C7: .CONSUMIDOR FINAL | D7: Consumidor Final | F7: 4958.68 | G7: 0 | H7: 0 | I7: 0 | J7: 0 | K7: 1041.32 | L7: 0 | M7: 0 | N7: 6000
A8: 03/04/2023 | B8: FA-B 0005-00007646 | C8: .CONSUMIDOR FINAL | D8: Consumidor Final | F8: 9710.75 | G8: 0 | H8: 0 | I8: 0 | J8: 0 | K8: 2039.25 | L8: 0 | M8: 0 | N8: 11750
A9: 03/04/2023 | B9: FA-B 0005-00007647 | C9: .CONSUMIDOR FINAL | D9: Consumidor Final | F9: 7272.73 | G9: 0 | H9: 0 | I9: 0 | J9: 0 | K9: 1527.27 | L9: 0 | M9: 0 | N9: 8800
A10: 03/04/2023 | B10: FA-B 0005-00007648 | C10: .CONSUMIDOR FINAL | D10: Consumidor Final | F10: 6446.28 | G10: 0 | H10: 0 | I10: 0 | J10: 0 | K10: 1353.72 | L10: 0 | M10: 0 | N10: 7800
A11: 03/04/2023 | B11: FA-B 0005-00007649 | C11: .CONSUMIDOR FINAL | D11: Consumidor Final | F11: 2314.05 | G11: 0 | H11: 0 | I11: 0 | J11: 0 | K11: 485.95 | L11: 0 | M11: 0 | N11: 2800
A12: 03/04/2023 | B12: FA-B 0005-00007650 | C12: .CONSUMIDOR FINAL | D12: Consumidor Final | F12: 8264.47 | G12: 0 | H12: 0 | I12: 0 | J12: 0 | K12: 1735.53 | L12: 0 | M12: 0 | N12: 10000
A13: 03/04/2023 | B13: FA-B 0005-00007651 | C13: .CONSUMIDOR FINAL | D13: Consumidor Final | F13: 2231.4 | G13: 0 | H13: 0 | I13: 0 | J13: 0 | K13: 468.6 | L13: 0 | M13: 0 | N13: 2700
A14: 03/04/2023 | B14: FA-B 0005-00007652 | C14: .CONSUMIDOR FINAL | D14: Consumidor Final | F14: 7768.6 | G14: 0 | H14: 0 | I14: 0 | J14: 0 | K14: 1631.4 | L14: 0 | M14: 0 | N14: 9400
A15: 03/04/2023 | B15: FA-B 0005-00007653 | C15: .CONSUMIDOR FINAL | D15: Consumidor Final | F15: 15694.21 | G15: 0 | H15: 0 | I15: 0 | J15: 0 | K15: 3295.79 | L15: 0 | M15: 0 | N15: 18990
A16: 03/04/2023 | B16: FA-B 0005-00007654 | C16: .CONSUMIDOR FINAL | D16: Consumidor Final | F16: 12892.56 | G16: 0 | H16: 0 | I16: 0 | J16: 0 | K16: 2707.44 | L16: 0 | M16: 0 | N16: 15600
A17: 03/04/2023 | B17: FA-B 0005-00007655 | C17: .CONSUMIDOR FINAL | D17: Consumidor Final | F17: 4504.13 | G17: 0 | H17: 0 | I17: 0 | J17: 0 | K17: 945.87 | L17: 0 | M17: 0 | N17: 5450
A18: 03/04/2023 | B18: FA-A 0006-00000332 | C18: Galeno Argentina Sociedad Anonima | D18: IVA Responsable Inscripto | E18: 30522428163 | F18: 2042975.2 | G18: 0 | H18: 0 | I18: 0 | J18: 0 | K18: 429024.8 | L18: 0 | M18: 0 | N18: 2472000
A19: 03/04/2023 | B19: FA-A 0007-00001398 | C19: Amparo Salud S.R.L. | D19: IVA Responsable Inscripto | E19: 30715186655 | F19: 58674.1 | G19: 0 | H19: 0 | I19: 0 | J19: 0 | K19: 12321.56 | L19: 0 | M19: 0 | N19: 70995.66
A20: 03/04/2023 | B20: FA-A 0007-00001399 | C20: Amparo Salud S.R.L. | D20: IVA Responsable Inscripto | E20: 30715186655 | F20: 3512.4 | G20: 0 | H20: 0 | I20: 0 | J20: 0 | K20: 737.6 | L20: 0 | M20: 0 | N20: 4250
A21: 03/04/2023 | B21: FA-A 0007-00001400 | C21: Centro Medico Amenabar Srl | D21: IVA Responsable Inscripto | E21: 30707612971 | F21: 8796.31 | G21: 0 | H21: 0 | I21: 0 | J21: 0 | K21: 1847.23 | L21: 0 | M21: 0 | N21: 10643.54
A22: 03/04/2023 | B22: FA-A 0007-00001401 | C22: Ensalud S.A | D22: IVA Responsable Inscripto | E22: 30707118454 | F22: 4003.3 | G22: 0 | H22: 0 | I22: 0 | J22: 0 | K22: 840.69 | L22: 0 | M22: 0 | N22: 4843.99
A23: 03/04/2023 | B23: FA-A 0007-00001402 | C23: Obra Social Del Personal De Las Telecomunicaciones De La Republica Argentina | D23: IVA Responsable Inscripto | E23: 30608716390 | F23: 1487.6 | G23: 0 | H23: 0 | I23: 0 | J23: 0 | K23: 312.4 | L23: 0 | M23: 0 | N23: 1800
A24: 03/04/2023 | B24: FA-A 0007-00001403 | C24: Obra Social Del Personal De Las Telecomunicaciones De La Republica Argentina | D24: IVA Responsable Inscripto | E24: 30608716390 | F24: 6033.06 | G24: 0 | H24: 0 | I24: 0 | J24: 0 | K24: 1266.94 | L24: 0 | M24: 0 | N24: 7300
A25: 03/04/2023 | B25: FA-B 0007-00004229 | C25: GABRIELA VANINA GALLO | D25: Consumidor Final | E25: 26542077 | F25: 8677.69 | G25: 0 | H25: 0 | I25: 0 | J25: 0 | K25: 1822.31 | L25: 0 | M25: 0 | N25: 10500
A26: 03/04/2023 | B26: FA-B 0007-00004230 | C26: LOCOCO, CARMEN | D26: Consumidor Final | E26: 17198648 | F26: 5950.41 | G26: 0 | H26: 0 | I26: 0 | J26: 0 | K26: 1249.59 | L26: 0 | M26: 0 | N26: 7200
A27: 04/04/2023 | B27: FA-B 0005-00007656 | C27: .CONSUMIDOR FINAL | D27: Consumidor Final | F27: 3884.3 | G27: 0 | H27: 0 | I27: 0 | J27: 0 | K27: 815.7 | L27: 0 | M27: 0 | N27: 4700
A28: 04/04/2023 | B28: FA-B 0005-00007657 | C28: .CONSUMIDOR FINAL | D28: Consumidor Final | F28: 5537.19 | G28: 0 | H28: 0 | I28: 0 | J28: 0 | K28: 1162.81 | L28: 0 | M28: 0 | N28: 6700
A29: 04/04/2023 | B29: FA-B 0005-00007658 | C29: .CONSUMIDOR FINAL | D29: Consumidor Final | F29: 6198.35 | G29: 0 | H29: 0 | I29: 0 | J29: 0 | K29: 1301.65 | L29: 0 | M29: 0 | N29: 7500
A30: 04/04/2023 | B30: FA-B 0005-00007659 | C30: .CONSUMIDOR FINAL | D30: Consumidor Final | F30: 3884.3 | G30: 0 | H30: 0 | I30: 0 | J30: 0 | K30: 815.7 | L30: 0 | M30: 0 | N30: 4700
A31: 04/04/2023 | B31: FA-B 0005-00007660 | C31: GALLO, ANDREA | D31: Consumidor Final | E31: 32315178 | F31: 21074.38 | G31: 0 | H31: 0 | I31: 0 | J31: 0 | K31: 4425.62 | L31: 0 | M31: 0 | N31: 25500
A32: 04/04/2023 | B32: FA-B 0005-00007661 | C32: .CONSUMIDOR FINAL | D32: Consumidor Final | F32: 7727.27 | G32: 0 | H32: 0 | I32: 0 | J32: 0 | K32: 1622.73 | L32: 0 | M32: 0 | N32: 9350
A33: 04/04/2023 | B33: FA-B 0005-00007662 | C33: .CONSUMIDOR FINAL | D33: Consumidor Final | F33: 2727.27 | G33: 0 | H33: 0 | I33: 0 | J33: 0 | K33: 572.73 | L33: 0 | M33: 0 | N33: 3300
A34: 04/04/2023 | B34: FA-B 0005-00007663 | C34: .CONSUMIDOR FINAL | D34: Consumidor Final | F34: 1735.54 | G34: 0 | H34: 0 | I34: 0 | J34: 0 | K34: 364.46 | L34: 0 | M34: 0 | N34: 2100
A35: 04/04/2023 | B35: FA-B 0005-00007664 | C35: .CONSUMIDOR FINAL | D35: Consumidor Final | F35: 4132.23 | G35: 0 | H35: 0 | I35: 0 | J35: 0 | K35: 867.77 | L35: 0 | M35: 0 | N35: 5000
A36: 04/04/2023 | B36: FA-B 0005-00007665 | C36: .CONSUMIDOR FINAL | D36: Consumidor Final | F36: 2727.27 | G36: 0 | H36: 0 | I36: 0 | J36: 0 | K36: 572.73 | L36: 0 | M36: 0 | N36: 3300
A37: 04/04/2023 | B37: FA-B 0005-00007666 | C37: .CONSUMIDOR FINAL | D37: Consumidor Final | F37: 4132.23 | G37: 0 | H37: 0 | I37: 0 | J37: 0 | K37: 867.77 | L37: 0 | M37: 0 | N37: 5000
A38: 04/04/2023 | B38: FA-A 0006-00000333 | C38: Galeno Argentina Sociedad Anonima | D38: IVA Responsable Inscripto | E38: 30522428163 | F38: 297527.82 | G38: 0 | H38: 0 | I38: 0 | J38: 0 | K38: 62480.84 | L38: 0 | M38: 0 | N38: 360008.66
A39: 04/04/2023 | B39: FA-A 0006-00000334 | C39: Galeno Argentina Sociedad Anonima | D39: IVA Responsable Inscripto | E39: 30522428163 | F39: 4398512.4 | G39: 0 | H39: 0 | I39: 0 | J39: 0 | K39: 923687.6 | L39: 0 | M39: 0 | N39: 5322200
A40: 04/04/2023 | B40: NC-B 0007-00000136 | C40: Asociacion Mutual Sancor Salud | D40: IVA Sujeto Exento | E40: 30590354798 | F40: -4087.13 | G40: 0 | H40: 0 | I40: 0 | J40: 0 | K40: -858.3 | L40: 0 | M40: 0 | N40: -4945.43
A41: 04/04/2023 | B41: FA-A 0007-00001404 | C41: Galeno Argentina Sociedad Anonima | D41: IVA Responsable Inscripto | E41: 30522428163 | F41: 3681.09 | G41: 0 | H41: 0 | I41: 0 | J41: 0 | K41: 773.03 | L41: 0 | M41: 0 | N41: 4454.12
A42: 04/04/2023 | B42: FA-B 0007-00004231 | C42: COSTA, MARTA CRISTINA | D42: Consumidor Final | E42: 10093884 | F42: 3471.07 | G42: 0 | H42: 0 | I42: 0 | J42: 0 | K42: 728.93 | L42: 0 | M42: 0 | N42: 4200
A43: 04/04/2023 | B43: FA-B 0007-00004232 | C43: HIDALGO OSCAR ATILIO | D43: Consumidor Final | F43: 1487.6 | G43: 0 | H43: 0 | I43: 0 | J43: 0 | K43: 312.4 | L43: 0 | M43: 0 | N43: 1800
A44: 04/04/2023 | B44: FA-B 0007-00004233 | C44: MAQUEIRA, ENZO SEBASTIAN | D44: Consumidor Final | E44: 26317300 | F44: 6446.28 | G44: 0 | H44: 0 | I44: 0 | J44: 0 | K44: 1353.72 | L44: 0 | M44: 0 | N44: 7800
A45: 05/04/2023 | B45: NC-B 0005-00000111 | C45: GALLO, ANDREA | D45: Consumidor Final | E45: 32315178 | F45: -21074.38 | G45: 0 | H45: 0 | I45: 0 | J45: 0 | K45: -4425.62 | L45: 0 | M45: 0 | N45: -25500
A46: 05/04/2023 | B46: FA-B 0005-00007667 | C46: GALLO, ANDREA | D46: Consumidor Final | E46: 32315178 | F46: 21074.38 | G46: 0 | H46: 0 | I46: 0 | J46: 0 | K46: 4425.62 | L46: 0 | M46: 0 | N46: 25500
A47: 05/04/2023 | B47: FA-B 0005-00007668 | C47: .CONSUMIDOR FINAL | D47: Consumidor Final | F47: 4132.23 | G47: 0 | H47: 0 | I47: 0 | J47: 0 | K47: 867.77 | L47: 0 | M47: 0 | N47: 5000
A48: 05/04/2023 | B48: FA-B 0005-00007669 | C48: .CONSUMIDOR FINAL | D48: Consumidor Final | F48: 2842.97 | G48: 0 | H48: 0 | I48: 0 | J48: 0 | K48: 597.03 | L48: 0 | M48: 0 | N48: 3440
A49: 05/04/2023 | B49: FA-B 0005-00007670 | C49: .CONSUMIDOR FINAL | D49: Consumidor Final | F49: 23041.32 | G49: 0 | H49: 0 | I49: 0 | J49: 0 | K49: 4838.68 | L49: 0 | M49: 0 | N49: 27880
A50: 05/04/2023 | B50: FA-B 0005-00007671 | C50: .CONSUMIDOR FINAL | D50: Consumidor Final | F50: 6198.35 | G50: 0 | H50: 0 | I50: 0 | J50: 0 | K50: 1301.65 | L50: 0 | M50: 0 | N50: 7500
A51: 05/04/2023 | B51: FA-B 0005-00007672 | C51: .CONSUMIDOR FINAL | D51: Consumidor Final | F51: 3884.3 | G51: 0 | H51: 0 | I51: 0 | J51: 0 | K51: 815.7 | L51: 0 | M51: 0 | N51: 4700
A52: 05/04/2023 | B52: FA-B 0005-00007673 | C52: .CONSUMIDOR FINAL | D52: Consumidor Final | F52: 4876.03 | G52: 0 | H52: 0 | I52: 0 | J52: 0 | K52: 1023.97 | L52: 0 | M52: 0 | N52: 5900
A53: 05/04/2023 | B53: FA-A 0006-00000335 | C53: Galeno Argentina Sociedad Anonima | D53: IVA Responsable Inscripto | E53: 30522428163 | F53: 2177449.1 | G53: 0 | H53: 0 | I53: 0 | J53: 0 | K53: 457264.32 | L53: 0 | M53: 0 | N53: 2634713.5
A54: 05/04/2023 | B54: FA-A 0007-00001405 | C54: Galeno Argentina Sociedad Anonima | D54: IVA Responsable Inscripto | E54: 30522428163 | F54: 177503.17 | G54: 0 | H54: 0 | I54: 0 | J54: 0 | K54: 37275.67 | L54: 0 | M54: 0 | N54: 214778.84
A55: 05/04/2023 | B55: FA-A 0007-00001406 | C55: Hc Homecare Internacion Domiciliaria S.A. | D55: IVA Responsable Inscripto | E55: 30710538014 | F55: 23828.93 | G55: 0 | H55: 0 | I55: 0 | J55: 0 | K55: 5004.08 | L55: 0 | M55: 0 | N55: 28833.01
A56: 05/04/2023 | B56: FA-A 0007-00001407 | C56: Medicus Sociedad Anonima De Asistencia Medica Y Cientifica | D56: IVA Responsable Inscripto | E56: 30546771314 | F56: 9813.22 | G56: 0 | H56: 0 | I56: 0 | J56: 0 | K56: 2060.78 | L56: 0 | M56: 0 | N56: 11874
A57: 05/04/2023 | B57: FA-A 0007-00001408 | C57: Medincare Argentina S.A. | D57: IVA Responsable Inscripto | E57: 30713669004 | F57: 13541.32 | G57: 0 | H57: 0 | I57: 0 | J57: 0 | K57: 2843.68 | L57: 0 | M57: 0 | N57: 16385
A58: 05/04/2023 | B58: FA-B 0007-00004234 | C58: CORREA RICARDO | D58: Consumidor Final | E58: 4918632 | F58: 4628.1 | G58: 0 | H58: 0 | I58: 0 | J58: 0 | K58: 971.9 | L58: 0 | M58: 0 | N58: 5600
A59: 10/04/2023 | B59: FA-B 0005-00007674 | C59: .CONSUMIDOR FINAL | D59: Consumidor Final | F59: 1322.31 | G59: 0 | H59: 0 | I59: 0 | J59: 0 | K59: 277.69 | L59: 0 | M59: 0 | N59: 1600
A60: 10/04/2023 | B60: FA-B 0005-00007675 | C60: .CONSUMIDOR FINAL | D60: Consumidor Final | F60: 15289.26 | G60: 0 | H60: 0 | I60: 0 | J60: 0 | K60: 3210.74 | L60: 0 | M60: 0 | N60: 18500
A61: 10/04/2023 | B61: FA-B 0005-00007676 | C61: .CONSUMIDOR FINAL | D61: Consumidor Final | F61: 5851.24 | G61: 0 | H61: 0 | I61: 0 | J61: 0 | K61: 1228.76 | L61: 0 | M61: 0 | N61: 7080
A62: 10/04/2023 | B62: FA-B 0005-00007677 | C62: .CONSUMIDOR FINAL | D62: Consumidor Final | F62: 2644.63 | G62: 0 | H62: 0 | I62: 0 | J62: 0 | K62: 555.37 | L62: 0 | M62: 0 | N62: 3200
A63: 10/04/2023 | B63: FA-B 0005-00007678 | C63: .CONSUMIDOR FINAL | D63: Consumidor Final | F63: 2727.27 | G63: 0 | H63: 0 | I63: 0 | J63: 0 | K63: 572.73 | L63: 0 | M63: 0 | N63: 3300
A64: 10/04/2023 | B64: FA-B 0005-00007679 | C64: .CONSUMIDOR FINAL | D64: Consumidor Final | F64: 4876.03 | G64: 0 | H64: 0 | I64: 0 | J64: 0 | K64: 1023.97 | L64: 0 | M64: 0 | N64: 5900
A65: 10/04/2023 | B65: FA-B 0005-00007680 | C65: .CONSUMIDOR FINAL | D65: Consumidor Final | F65: 3884.3 | G65: 0 | H65: 0 | I65: 0 | J65: 0 | K65: 815.7 | L65: 0 | M65: 0 | N65: 4700
A66: 10/04/2023 | B66: FA-B 0005-00007681 | C66: .CONSUMIDOR FINAL | D66: Consumidor Final | F66: 4132.23 | G66: 0 | H66: 0 | I66: 0 | J66: 0 | K66: 867.77 | L66: 0 | M66: 0 | N66: 5000
A67: 10/04/2023 | B67: FA-B 0005-00007682 | C67: .CONSUMIDOR FINAL | D67: Consumidor Final | F67: 5785.12 | G67: 0 | H67: 0 | I67: 0 | J67: 0 | K67: 1214.88 | L67: 0 | M67: 0 | N67: 7000
A68: 10/04/2023 | B68: FA-B 0005-00007683 | C68: .CONSUMIDOR FINAL | D68: Consumidor Final | F68: 6280.99 | G68: 0 | H68: 0 | I68: 0 | J68: 0 | K68: 1319.01 | L68: 0 | M68: 0 | N68: 7600
A69: 10/04/2023 | B69: FA-A 0007-00001409 | C69: Obra Social Union Personal De La Union Del Personal Civil De La Nacion | D69: IVA Responsable Inscripto | E69: 30683032227 | F69: 245305.54 | G69: 0 | H69: 0 | I69: 0 | J69: 0 | K69: 51514.16 | L69: 0 | M69: 0 | N69: 296819.7
A70: 10/04/2023 | B70: FA-A 0007-00001410 | C70: Obra Social Union Personal De La Union Del Personal Civil De La Nacion | D70: IVA Responsable Inscripto | E70: 30683032227 | F70: 21671.65 | G70: 0 | H70: 0 | I70: 0 | J70: 0 | K70: 4551.05 | L70: 0 | M70: 0 | N70: 26222.7
A71: 10/04/2023 | B71: FA-A 0007-00001411 | C71: Medicus Sociedad Anonima De Asistencia Medica Y Cientifica | D71: IVA Responsable Inscripto | E71: 30546771314 | F71: 10247.92 | G71: 0 | H71: 0 | I71: 0 | J71: 0 | K71: 2152.06 | L71: 0 | M71: 0 | N71: 12399.98
A72: 10/04/2023 | B72: FA-A 0007-00001412 | C72: Obra Social Del Personal De Las Telecomunicaciones De La Republica Argentina | D72: IVA Responsable Inscripto | E72: 30608716390 | F72: 1280.99 | G72: 0 | H72: 0 | I72: 0 | J72: 0 | K72: 269.01 | L72: 0 | M72: 0 | N72: 1550
A73: 10/04/2023 | B73: FA-B 0007-00004235 | C73: LORENZO, MERCEDES DELFINA | D73: Consumidor Final | E73: 5077002 | F73: 3719.01 | G73: 0 | H73: 0 | I73: 0 | J73: 0 | K73: 780.99 | L73: 0 | M73: 0 | N73: 4500
A74: 11/04/2023 | B74: FA-B 0005-00007684 | C74: .CONSUMIDOR FINAL | D74: Consumidor Final | F74: 4330.58 | G74: 0 | H74: 0 | I74: 0 | J74: 0 | K74: 909.42 | L74: 0 | M74: 0 | N74: 5240
A75: 11/04/2023 | B75: FA-B 0005-00007685 | C75: .CONSUMIDOR FINAL | D75: Consumidor Final | F75: 5702.48 | G75: 0 | H75: 0 | I75: 0 | J75: 0 | K75: 1197.52 | L75: 0 | M75: 0 | N75: 6900
A76: 11/04/2023 | B76: FA-B 0005-00007686 | C76: .CONSUMIDOR FINAL | D76: Consumidor Final | F76: 7768.6 | G76: 0 | H76: 0 | I76: 0 | J76: 0 | K76: 1631.4 | L76: 0 | M76: 0 | N76: 9400
A77: 11/04/2023 | B77: FA-B 0005-00007687 | C77: .CONSUMIDOR FINAL | D77: Consumidor Final | F77: 6297.52 | G77: 0 | H77: 0 | I77: 0 | J77: 0 | K77: 1322.48 | L77: 0 | M77: 0 | N77: 7620
A78: 11/04/2023 | B78: FA-B 0005-00007688 | C78: .CONSUMIDOR FINAL | D78: Consumidor Final | F78: 15041.33 | G78: 0 | H78: 0 | I78: 0 | J78: 0 | K78: 3158.67 | L78: 0 | M78: 0 | N78: 18200
A79: 11/04/2023 | B79: FA-B 0005-00007689 | C79: CORREA HERNÁN | D79: Consumidor Final | E79: 21851552 | F79: 7272.73 | G79: 0 | H79: 0 | I79: 0 | J79: 0 | K79: 1527.27 | L79: 0 | M79: 0 | N79: 8800
A80: 11/04/2023 | B80: FA-B 0005-00007690 | C80: .CONSUMIDOR FINAL | D80: Consumidor Final | F80: 2396.69 | G80: 0 | H80: 0 | I80: 0 | J80: 0 | K80: 503.31 | L80: 0 | M80: 0 | N80: 2900
A81: 11/04/2023 | B81: FA-B 0005-00007691 | C81: .CONSUMIDOR FINAL | D81: Consumidor Final | F81: 2479.34 | G81: 0 | H81: 0 | I81: 0 | J81: 0 | K81: 520.66 | L81: 0 | M81: 0 | N81: 3000
A82: 11/04/2023 | B82: FA-B 0005-00007692 | C82: .CONSUMIDOR FINAL | D82: Consumidor Final | F82: 7024.79 | G82: 0 | H82: 0 | I82: 0 | J82: 0 | K82: 1475.21 | L82: 0 | M82: 0 | N82: 8500
A83: 11/04/2023 | B83: FA-B 0005-00007693 | C83: .CONSUMIDOR FINAL | D83: Consumidor Final | F83: 7272.73 | G83: 0 | H83: 0 | I83: 0 | J83: 0 | K83: 1527.27 | L83: 0 | M83: 0 | N83: 8800
A84: 11/04/2023 | B84: FA-B 0005-00007694 | C84: .CONSUMIDOR FINAL | D84: Consumidor Final | F84: 2231.4 | G84: 0 | H84: 0 | I84: 0 | J84: 0 | K84: 468.6 | L84: 0 | M84: 0 | N84: 2700
A85: 11/04/2023 | B85: FA-B 0005-00007695 | C85: .CONSUMIDOR FINAL | D85: Consumidor Final | F85: 1652.89 | G85: 0 | H85: 0 | I85: 0 | J85: 0 | K85: 347.11 | L85: 0 | M85: 0 | N85: 2000
A86: 11/04/2023 | B86: FA-B 0005-00007696 | C86: .CONSUMIDOR FINAL | D86: Consumidor Final | F86: 10000 | G86: 0 | H86: 0 | I86: 0 | J86: 0 | K86: 2100 | L86: 0 | M86: 0 | N86: 12100
A87: 11/04/2023 | B87: FA-B 0007-00004236 | C87: Asociacion Mutual Sancor Salud | D87: IVA Sujeto Exento | E87: 30590354798 | F87: 218291.75 | G87: 0 | H87: 0 | I87: 0 | J87: 0 | K87: 45841.27 | L87: 0 | M87: 0 | N87: 264133.02
A88: 12/04/2023 | B88: FA-A 0005-00000133 | C88: Autonavi Srl | D88: IVA Responsable Inscripto | E88: 30708436506 | F88: 8033.06 | G88: 0 | H88: 0 | I88: 0 | J88: 0 | K88: 1686.94 | L88: 0 | M88: 0 | N88: 9720
A89: 12/04/2023 | B89: FA-B 0005-00007697 | C89: .CONSUMIDOR FINAL | D89: Consumidor Final | F89: 6198.35 | G89: 0 | H89: 0 | I89: 0 | J89: 0 | K89: 1301.65 | L89: 0 | M89: 0 | N89: 7500
A90: 12/04/2023 | B90: FA-B 0005-00007698 | C90: .CONSUMIDOR FINAL | D90: Consumidor Final | F90: 3884.3 | G90: 0 | H90: 0 | I90: 0 | J90: 0 | K90: 815.7 | L90: 0 | M90: 0 | N90: 4700
A91: 12/04/2023 | B91: FA-B 0005-00007699 | C91: .CONSUMIDOR FINAL | D91: Consumidor Final | F91: 2314.05 | G91: 0 | H91: 0 | I91: 0 | J91: 0 | K91: 485.95 | L91: 0 | M91: 0 | N91: 2800
A92: 12/04/2023 | B92: FA-B 0005-00007700 | C92: .CONSUMIDOR FINAL | D92: Consumidor Final | F92: 12148.76 | G92: 0 | H92: 0 | I92: 0 | J92: 0 | K92: 2551.24 | L92: 0 | M92: 0 | N92: 14700
A93: 12/04/2023 | B93: FA-B 0005-00007701 | C93: .CONSUMIDOR FINAL | D93: Consumidor Final | F93: 12148.76 | G93: 0 | H93: 0 | I93: 0 | J93: 0 | K93: 2551.24 | L93: 0 | M93: 0 | N93: 14700
A94: 12/04/2023 | B94: FA-B 0005-00007702 | C94: .CONSUMIDOR FINAL | D94: Consumidor Final | F94: 6652.89 | G94: 0 | H94: 0 | I94: 0 | J94: 0 | K94: 1397.11 | L94: 0 | M94: 0 | N94: 8050
A95: 12/04/2023 | B95: FA-B 0005-00007703 | C95: .CONSUMIDOR FINAL | D95: Consumidor Final | F95: 2396.69 | G95: 0 | H95: 0 | I95: 0 | J95: 0 | K95: 503.31 | L95: 0 | M95: 0 | N95: 2900
A96: 12/04/2023 | B96: FA-B 0005-00007704 | C96: .CONSUMIDOR FINAL | D96: Consumidor Final | F96: 3223.14 | G96: 0 | H96: 0 | I96: 0 | J96: 0 | K96: 676.86 | L96: 0 | M96: 0 | N96: 3900
A97: 12/04/2023 | B97: FA-B 0005-00007705 | C97: .CONSUMIDOR FINAL | D97: Consumidor Final | F97: 5785.12 | G97: 0 | H97: 0 | I97: 0 | J97: 0 | K97: 1214.88 | L97: 0 | M97: 0 | N97: 7000
A98: 12/04/2023 | B98: FA-B 0005-00007706 | C98: .CONSUMIDOR FINAL | D98: Consumidor Final | F98: 2066.12 | G98: 0 | H98: 0 | I98: 0 | J98: 0 | K98: 433.88 | L98: 0 | M98: 0 | N98: 2500
A99: 12/04/2023 | B99: FA-B 0005-00007707 | C99: .CONSUMIDOR FINAL | D99: Consumidor Final | F99: 2066.12 | G99: 0 | H99: 0 | I99: 0 | J99: 0 | K99: 433.88 | L99: 0 | M99: 0 | N99: 2500
A100: 12/04/2023 | B100: NC-A 0007-00000085 | C100: Obra Social Del Personal De Las Telecomunicaciones De La Republica Argentina | D100: IVA Responsable Inscripto | E100: 30608716390 | F100: -19421.49 | G100: 0 | H100: 0 | I100: 0 | J100: 0 | K100: -4078.51 | L100: 0 | M100: 0 | N100: -23500
A101: 12/04/2023 | B101: NC-A 0007-00000086 | C101: Obra Social Del Personal De Las Telecomunicaciones De La Republica Argentina | D101: IVA Responsable Inscripto | E101: 30608716390 | F101: -1239.67 | G101: 0 | H101: 0 | I101: 0 | J101: 0 | K101: -260.33 | L101: 0 | M101: 0 | N101: -1500
A102: 12/04/2023 | B102: FA-A 0007-00001413 | C102: Fundacion Empresaria Maderera | D102: IVA Responsable Inscripto | E102: 30657418877 | F102: 2892.56 | G102: 0 | H102: 0 | I102: 0 | J102: 0 | K102: 607.44 | L102: 0 | M102: 0 | N102: 3500
...
