Workbook

Sheet Lista_CUIT
A1: CUIT | B1: RAZON SOCIAL | C1: Tipo de Gasto | D1: PROVINCIA | E1: Columna1
A2: 27309896063 | B2: BATTELLINI MARIA SOLEDAD | C2: Alquiler | G2: Mercaderia
A3: 27309896063 | B3: BATTELLINI MARIA SOLEDAD | C3: Alquiler | G3: Servicios Gas, Luz, etc.
A4: 27309896063 | B4: BATTELLINI MARIA SOLEDAD | C4: Alquiler | G4: Gastos catering
A5: 20131206144 | B5: CHAMORRO MANUEL | C5: Alquiler | G5: Combustibe
A6: 30716010313 | B6: H UNO 1469 S.A. | C6: Alquiler | G6: Gastos Varios
A7: 30716010313 | B7: H Uno 1469 S.A. | C7: Alquiler | G7: Gastos seguridad
A8: 30716010313 | B8: H UNO 1469 S.A. | C8: Alquiler | G8: Librería
A9: 30716010313 | B9: H Uno 1469 S.A. | C9: Alquiler | G9: Gastos mantenimiento
A10: 20174208094 | B10: VILLARUEL OSCAR EDUARDO | C10: Alquiler | G10: Gastos comercializacion
A11: 30709245682 | B11: SOLAR GAS S.A. | C11: Alquiler | G11: Alquiler
A12: 20400073776 | B12: Mizrahi Julian Federico | C12: Alquiler de Filmacion | G12: Honorarios contables
A13: 20400073776 | B13: MIZRAHI JULIAN FEDERICO | C13: Alquiler de Filmacion | G13: Gastos administrativos
... A22: 30716160889 | B22: COMERCIALIZADORA DE BEBIDAS SRL | C22: Catering | G22: Alojamiento-Varios
A23: 30716160889 | B23: COMERCIALIZADORA DE BEBIDAS SRL | C23: Catering
A24: 30715048066 | B24: ROLLS Y EMPANADAS SA | C24: Catering
A25: 30680690967 | B25: ACENAF S.R.L. | C25: Combustible
A26: 30685433296 | B26: ALT. ALBERTO RAFAEL Y ALT H | C26: Combustible
A27: 33707010059 | B27: BUZANCY S.A. | C27: Combustible
A28: 30708251697 | B28: COMBUSTIBLES RUTA 26 S.A | C28: Combustible
A29: 30550847589 | B29: CORAFAL NORTE S.A. | C29: Combustible | D29: BUENOS AIRES
A30: 30701367193 | B30: CUATRO BOCAS S.R.L. | C30: Combustible
A31: 30516186670 | B31: DEHEZA S.A.I.C.F. e I. | C31: Combustible
A32: 30516186670 | B32: DEHEZA S.A.I.C.F. e I. | C32: Combustible
A33: 30708077883 | B33: DONA MARTINA SA | C33: Combustible
A34: 30709781428 | B34: DUAL TIGRE S.A. | C34: Combustible
A35: 30551016117 | B35: EL CURVON SRL | C35: Combustible
A36: 30551016117 | B36: EL CURVON SRL | C36: Combustible
A37: 30708260785 | B37: EREZCANO SA | C37: Combustible
A38: 30568586391 | B38: ESTACION DE SERVICIO AXION | C38: Combustible
A39: 30708549041 | B39: FLORIPO S.A. | C39: Combustible
A40: 30650296997 | B40: GAS PARQUE S.A. | C40: Combustible
A41: 30653466931 | B41: GNC ESCOBAR S.A. | C41: Combustible
... A56: 30627539629 | B56: LEJEM SA | C56: Combustible
A57: 30712212817 | B57: LIQUID GAS S.A. | C57: Combustible | D57: BS AS
A58: 30707949550 | B58: LNG GAS S.A. | C58: Combustible | D58: BS AS
A59: 30716825309 | B59: LOS ACCESOS 3 | C59: Combustible
A60: 30709465801 | B60: LUBRICANTES Y COMBUSTIBLES D'ATRI S.R.L. | C60: Combustible
A61: 30712450327 | B61: MANDOLA HERMANOS S.A. | C61: Combustible
A62: 20217165114 | B62: MARTINO CARLOS ALBERTO | C62: Combustible
A63: 30685116657 | B63: MIRVAR SA | C63: Combustible
A64: 30708456329 | B64: MOVIL GAS S.A. | C64: Combustible
A65: 33608724279 | B65: NAFPUR SA | C65: Combustible
A66: 30707983732 | B66: NAFPUR XXI SA | C66: Combustible
A67: 30717535649 | B67: NIMUR RSL | C67: Combustible
A68: 30717535649 | B68: NIMUR RSL | C68: Combustible
A69: 30678774495 | B69: OPER. DE EST. DE SERV. SA | C69: Combustible
A70: 30678774495 | B70: OPERADORA DE ESTACIONES DE SERVICIOS SA | C70: Combustible
... A85: 30696131003 | B85: Petrolfe S.A. | C85: Combustible
A86: 30-69613100-3 | B86: PETROLFE S.A. | C86: Combustible
A87: 30696131003 | B87: PETROLFE SA | C87: Combustible
A88: 30696131003 | B88: PETROLFE SA | C88: Combustible
A89: 30696131003 | B89: PETROLFE SA | C89: Combustible
A90: 30696131003 | B90: PETROLFE SA | C90: Combustible
A91: 30572365391 | B91: PETROVALLE S.A. | C91: Combustible
A92: 30572365391 | B92: PETROVALLE S.A. | C92: Combustible
A93: 33709344809 | B93: SHELL ALBERDI | C93: Combustible
A94: 33709344809 | B94: SHELL ALBERDI | C94: Combustible
A95: 30574300858 | B95: SHELL SA | C95: Combustible
A96: 30574300858 | B96: SHELL SA | C96: Combustible
A97: 30697289433 | B97: SOLACON S. A. | C97: Combustible
A98: 30517264160 | B98: TRIANGLE SCA | C98: Combustible
... A112: 30717110052 | B112: TAP SERVICES S.A | C112: Comida
A113: 30-71512491-9 | B113: CLEAN LAB S.R.L. | C113: Comida-Limpieza
A114: 30715124919 | B114: CLEAN LAB SRL | C114: Comida-Limpieza
A115: 30715124919 | B115: CLEAN LAB SRL | C115: Comida-Limpieza
A116: 20-13466451-8 | B116: HOKAMA SERGIO ENRIQUE | C116: Comida-Limpieza
A117: 20134664518 | B117: HOKAMA SERGIO ENRIQUE | C117: Comida-Limpieza
A118: 20134664518 | B118: HOKAMA SERGIO ENRIQUE | C118: Comida-Limpieza
A119: 20134664518 | B119: HOKAMA SERGIO ENRIQUE | C119: Comida-Limpieza
A120: 20134664518 | B120: HOKAMA SERGIO ENRIQUE | C120: Comida-Limpieza
A121: 20134664518 | B121: HOKAMA SERGIO ENRIQUE | C121: Comida-Limpieza
A122: 20134664518 | B122: HOKAMA SERGIO ENRIQUE | C122: Comida-Limpieza
A123: 30-58962149-9 | B123: MAKRO SUPERMERCADOS S.A. | C123: Comida-Limpieza
A124: 30589621499 | B124: MAKRO SA | C124: Comida-Limpieza
A125: 30574816870 | B125: AMERICAN EXPRES S.A. | C125: Comisiones Bancarias
A126: 30500001735 | B126: BANCO GALICIA | C126: Comisiones Bancarias
A127: 30500003193 | B127: BBVA FRANCES | C127: Comisiones Bancarias
A128: 30681484635 | B128: IONIC S SOCIEDAD ANONIMA | C128: Elaboración
A129: 30711005966 | B129: LABORATORIOS BIOMIC SRL | C129: Elaboración
A130: 30707603123 | B130: BI ORIENT S.A. | C130: EMBALAJE
A131: 30694547903 | B131: MULTICAJAS S A | C131: EMBALAJE
A132: 30709863076 | B132: Plasticos Salta | C132: EMBALAJE
A133: 30709863076 | B133: Plasticos Salta | C133: EMBALAJE
A134: 30709863076 | B134: Plasticos Salta | C134: EMBALAJE
A135: 30709863076 | B135: Plasticos Salta | C135: EMBALAJE
... A161: 20235723906 | B161: BURNET MICHAUT GASTON KURT | C161: Ferreteria
A162: 20931803124 | B162: CARNUCCIO COSME DAMIAN | C162: Ferreteria | D162: BUENOS AIRES
A163: 33716633379 | B163: GRUPO SMH SRL | C163: Ferreteria
A164: 30715342983 | B164: INSUMOS INDUSTRIALES BULFER | C164: Ferreteria | D164: BS AS
A165: 27293936450 | B165: PELLIZA PAOLA DANIELA | C165: Ferreteria | D165: CABA
A166: 20117862578 | B166: PORCO VICTOR ALBERTO | C166: Ferreteria
A167: 30710802404 | B167: KOHEN ILUMINACION S.A. | C167: Ferreteria
A168: 30710802404 | B168: KOHEN ILUMINACION S.A. | C168: Ferreteria
A169: 20259150249 | B169: BIANCHI CRISTIAN MAXIMILIANO | C169: Ferreteria
A170: 30579939008 | B170: TRANSPORTES LA SEVILLANITA | C170: Flete-Logistica
A171: 30682116028 | B171: BLUE STAR CARGO SRL | C171: Flete-Logistica
A172: 33707675069 | B172: BUS PACK S.A. | C172: Flete-Logistica
A173: 30717264122 | B173: CAPOLOG S.R.L. | C173: Flete-Logistica
A174: 33699685459 | B174: CORREO ANDREANI SA | C174: Flete-Logistica
...

Sheet Ene-22
B1: LIBRO IVA COMPRAS | G1: EUROARGENTINA | N1: 44562
B3: TOTAL COMPRAS | G3: TOTAL CREDITO FISCAL | J3: TOTAL VENTAS NETAS | M3: TOTAL DEBITO FISCAL | P3: RESULTADO
B4: =SUM(compras_mes1[[#Totals],[NETO GRAVADO]])+extracto_banco_mes1[[#Totals],[NETO]] -> 4972359.8 | G4: =compras_mes1[[#Totals],[IVA 21 %]]+compras_mes1[[#Totals],[IVA 27%]]+compras_mes1[[#Totals],[IVA 10,5%]]+extracto_banco_mes1[[#Totals],[IVA 21%]]+extracto_banco_mes1[[#Totals],[IVA 10,5%]] -> 935478.91 | J4: =venta_a_mes1[[#Totals],[IMPORTE NETO]]+ventas_b_mes1[[#Totals],[IMPORTE NETO]] -> 0 | M4: =venta_a_mes1[[#Totals],[IVA 21%]]+venta_a_mes1[[#Totals],[IVA 10,5%]]+ventas_b_mes1[[#Totals],[IVA 21%]]+ventas_b_mes1[[#Totals],[IVA 10,5%]] -> 0 | P4: =G4-M4 -> 935478.91
B8: FECHA | C8: TIPO | D8: PTO VTA | E8: NRO. CPTE | F8: CUIT | G8: RAZON SOCIAL | H8: NETO GRAVADO | I8: IVA 21 % | J8: IVA 27% | K8: IVA 10,5% | L8: PERC. IVA | M8: PERC IIBB BS AS | N8: PERC. IIBB CABA | O8: Otros / No Grav. | P8: TOTAL | Q8: Tipo de Gasto | R8: Provincia
B9: 44580 | C9: 1 | D9: 5 | E9: 18472 | F9: 30715124919 | G9: =IFERROR(IF(compras_mes1[[#This Row],[CUIT]]="","-",VLOOKUP(compras_mes1[[#This Row],[CUIT]],Lista_CUIT[#All],2,0)),"CUIT NO CARGADO") -> CLEAN LAB SRL | H9: 1287.19 | I9: =IF(compras_mes1[[#This Row],[NETO GRAVADO]]="","",compras_mes1[[#This Row],[NETO GRAVADO]]*0.21) -> 270.3099 | O9: 0 | P9: =SUM(compras_mes1[[#This Row],[NETO GRAVADO]:[Otros / No Grav.]]) -> 1557.4999 | Q9: =IFERROR(IF(compras_mes1[[#This Row],[CUIT]]="","-",VLOOKUP(compras_mes1[[#This Row],[CUIT]],Lista_CUIT[#All],3,0)),"CUIT NO CARGADO") -> Comida-Limpieza | R9: =IFERROR(IF(compras_mes1[[#This Row],[CUIT]]="","-",VLOOKUP(compras_mes1[[#This Row],[CUIT]],Lista_CUIT[#All],4,0)),"CUIT NO CARGADO") -> 0
B10: 44580 | C10: 1 | D10: 5 | E10: 18473 | F10: 30715124919 | G10: =IFERROR(IF(compras_mes1[[#This Row],[CUIT]]="","-",VLOOKUP(compras_mes1[[#This Row],[CUIT]],Lista_CUIT[#All],2,0)),"CUIT NO CARGADO") -> CLEAN LAB SRL | H10: 2860.24 | I10: =IF(compras_mes1[[#This Row],[NETO GRAVADO]]="","",compras_mes1[[#This Row],[NETO GRAVADO]]*0.21) -> 600.6504 | O10: 0 | P10: =SUM(compras_mes1[[#This Row],[NETO GRAVADO]:[Otros / No Grav.]]) -> 3460.8904 | Q10: =IFERROR(IF(compras_mes1[[#This Row],[CUIT]]="","-",VLOOKUP(compras_mes1[[#This Row],[CUIT]],Lista_CUIT[#All],3,0)),"CUIT NO CARGADO") -> Comida-Limpieza | R10: =IFERROR(IF(compras_mes1[[#This Row],[CUIT]]="","-",VLOOKUP(compras_mes1[[#This Row],[CUIT]],Lista_CUIT[#All],4,0)),"CUIT NO CARGADO") -> 0
B11: 44580 | C11: 1 | D11: 5 | E11: 18474 | F11: 30715124919 | G11: =IFERROR(IF(compras_mes1[[#This Row],[CUIT]]="","-",VLOOKUP(compras_mes1[[#This Row],[CUIT]],Lista_CUIT[#All],2,0)),"CUIT NO CARGADO") -> CLEAN LAB SRL | H11: 2111.66 | I11: =IF(compras_mes1[[#This Row],[NETO GRAVADO]]="","",compras_mes1[[#This Row],[NETO GRAVADO]]*0.21) -> 443.4486 | O11: 0 | P11: =SUM(compras_mes1[[#This Row],[NETO GRAVADO]:[Otros / No Grav.]]) -> 2555.1086 | Q11: =IFERROR(IF(compras_mes1[[#This Row],[CUIT]]="","-",VLOOKUP(compras_mes1[[#This Row],[CUIT]],Lista_CUIT[#All],3,0)),"CUIT NO CARGADO") -> Comida-Limpieza | R11: =IFERROR(IF(compras_mes1[[#This Row],[CUIT]]="","-",VLOOKUP(compras_mes1[[#This Row],[CUIT]],Lista_CUIT[#All],4,0)),"CUIT NO CARGADO") -> 0
B12: 44580 | C12: 1 | D12: 5 | E12: 18475 | F12: 30715124919 | G12: =IFERROR(IF(compras_mes1[[#This Row],[CUIT]]="","-",VLOOKUP(compras_mes1[[#This Row],[CUIT]],Lista_CUIT[#All],2,0)),"CUIT NO CARGADO") -> CLEAN LAB SRL | H12: 2111.66 | I12: =IF(compras_mes1[[#This Row],[NETO GRAVADO]]="","",compras_mes1[[#This Row],[NETO GRAVADO]]*0.21) -> 443.4486 | O12: 0 | P12: =SUM(compras_mes1[[#This Row],[NETO GRAVADO]:[Otros / No Grav.]]) -> 2555.1086 | Q12: =IFERROR(IF(compras_mes1[[#This Row],[CUIT]]="","-",VLOOKUP(compras_mes1[[#This Row],[CUIT]],Lista_CUIT[#All],3,0)),"CUIT NO CARGADO") -> Comida-Limpieza | R12: =IFERROR(IF(compras_mes1[[#This Row],[CUIT]]="","-",VLOOKUP(compras_mes1[[#This Row],[CUIT]],Lista_CUIT[#All],4,0)),"CUIT NO CARGADO") -> 0
B13: 44580 | C13: 1 | D13: 5 | E13: 18476 | F13: 30715124919 | G13: =IFERROR(IF(compras_mes1[[#This Row],[CUIT]]="","-",VLOOKUP(compras_mes1[[#This Row],[CUIT]],Lista_CUIT[#All],2,0)),"CUIT NO CARGADO") -> CLEAN LAB SRL | H13: 3346.08 | I13: =IF(compras_mes1[[#This Row],[NETO GRAVADO]]="","",compras_mes1[[#This Row],[NETO GRAVADO]]*0.21) -> 702.6768 | O13: 0 | P13: =SUM(compras_mes1[[#This Row],[NETO GRAVADO]:[Otros / No Grav.]]) -> 4048.7568 | Q13: =IFERROR(IF(compras_mes1[[#This Row],[CUIT]]="","-",VLOOKUP(compras_mes1[[#This Row],[CUIT]],Lista_CUIT[#All],3,0)),"CUIT NO CARGADO") -> Comida-Limpieza | R13: =IFERROR(IF(compras_mes1[[#This Row],[CUIT]]="","-",VLOOKUP(compras_mes1[[#This Row],[CUIT]],Lista_CUIT[#All],4,0)),"CUIT NO CARGADO") -> 0
B14: 44580 | C14: 1 | D14: 5 | E14: 18477 | F14: 30715124919 | G14: =IFERROR(IF(compras_mes1[[#This Row],[CUIT]]="","-",VLOOKUP(compras_mes1[[#This Row],[CUIT]],Lista_CUIT[#All],2,0)),"CUIT NO CARGADO") -> CLEAN LAB SRL | H14: 2823.68 | I14: =IF(compras_mes1[[#This Row],[NETO GRAVADO]]="","",compras_mes1[[#This Row],[NETO GRAVADO]]*0.21) -> 592.9728 | O14: 0 | P14: =SUM(compras_mes1[[#This Row],[NETO GRAVADO]:[Otros / No Grav.]]) -> 3416.6528 | Q14: =IFERROR(IF(compras_mes1[[#This Row],[CUIT]]="","-",VLOOKUP(compras_mes1[[#This Row],[CUIT]],Lista_CUIT[#All],3,0)),"CUIT NO CARGADO") -> Comida-Limpieza | R14: =IFERROR(IF(compras_mes1[[#This Row],[CUIT]]="","-",VLOOKUP(compras_mes1[[#This Row],[CUIT]],Lista_CUIT[#All],4,0)),"CUIT NO CARGADO") -> 0
B15: 44580 | C15: 1 | D15: 5 | E15: 18478 | F15: 30715124919 | G15: =IFERROR(IF(compras_mes1[[#This Row],[CUIT]]="","-",VLOOKUP(compras_mes1[[#This Row],[CUIT]],Lista_CUIT[#All],2,0)),"CUIT NO CARGADO") -> CLEAN LAB SRL | H15: 8358.36 | I15: =IF(compras_mes1[[#This Row],[NETO GRAVADO]]="","",compras_mes1[[#This Row],[NETO GRAVADO]]*0.21) -> 1755.2556 | O15: 0 | P15: =SUM(compras_mes1[[#This Row],[NETO GRAVADO]:[Otros / No Grav.]]) -> 10113.616 | Q15: =IFERROR(IF(compras_mes1[[#This Row],[CUIT]]="","-",VLOOKUP(compras_mes1[[#This Row],[CUIT]],Lista_CUIT[#All],3,0)),"CUIT NO CARGADO") -> Comida-Limpieza | R15: =IFERROR(IF(compras_mes1[[#This Row],[CUIT]]="","-",VLOOKUP(compras_mes1[[#This Row],[CUIT]],Lista_CUIT[#All],4,0)),"CUIT NO CARGADO") -> 0
B16: 44582 | C16: 1 | D16: 6 | E16: 1387 | F16: 20134664518 | G16: =IFERROR(IF(compras_mes1[[#This Row],[CUIT]]="","-",VLOOKUP(compras_mes1[[#This Row],[CUIT]],Lista_CUIT[#All],2,0)),"CUIT NO CARGADO") -> HOKAMA SERGIO ENRIQUE | H16: 5773.88 | I16: =IF(compras_mes1[[#This Row],[NETO GRAVADO]]="","",compras_mes1[[#This Row],[NETO GRAVADO]]*0.21) -> 1212.5148 | O16: 0 | P16: =SUM(compras_mes1[[#This Row],[NETO GRAVADO]:[Otros / No Grav.]]) -> 6986.3948 | Q16: =IFERROR(IF(compras_mes1[[#This Row],[CUIT]]="","-",VLOOKUP(compras_mes1[[#This Row],[CUIT]],Lista_CUIT[#All],3,0)),"CUIT NO CARGADO") -> Comida-Limpieza | R16: =IFERROR(IF(compras_mes1[[#This Row],[CUIT]]="","-",VLOOKUP(compras_mes1[[#This Row],[CUIT]],Lista_CUIT[#All],4,0)),"CUIT NO CARGADO") -> 0
B17: 44587 | C17: 1 | D17: 7 | E17: 22309562 | F17: 30574816870 | G17: =IFERROR(IF(compras_mes1[[#This Row],[CUIT]]="","-",VLOOKUP(compras_mes1[[#This Row],[CUIT]],Lista_CUIT[#All],2,0)),"CUIT NO CARGADO") -> AMERICAN EXPRES S.A. | H17: 368.43 | I17: 77.37 | N17: 820.02 | O17: 0 | P17: =SUM(compras_mes1[[#This Row],[NETO GRAVADO]:[Otros / No Grav.]]) -> 1265.82 | Q17: =IFERROR(IF(compras_mes1[[#This Row],[CUIT]]="","-",VLOOKUP(compras_mes1[[#This Row],[CUIT]],Lista_CUIT[#All],3,0)),"CUIT NO CARGADO") -> Comisiones Bancarias | R17: =IFERROR(IF(compras_mes1[[#This Row],[CUIT]]="","-",VLOOKUP(compras_mes1[[#This Row],[CUIT]],Lista_CUIT[#All],4,0)),"CUIT NO CARGADO") -> 0
B18: 44579 | C18: 1 | D18: 10 | E18: 42416 | F18: 30711069360 | G18: =IFERROR(IF(compras_mes1[[#This Row],[CUIT]]="","-",VLOOKUP(compras_mes1[[#This Row],[CUIT]],Lista_CUIT[#All],2,0)),"CUIT NO CARGADO") -> BIDCOM S.R.L. | H18: 162226.24 | K18: 17033.76 | N18: 9733.57 | O18: 0 | P18: =SUM(compras_mes1[[#This Row],[NETO GRAVADO]:[Otros / No Grav.]]) -> 188993.57 | Q18: =IFERROR(IF(compras_mes1[[#This Row],[CUIT]]="","-",VLOOKUP(compras_mes1[[#This Row],[CUIT]],Lista_CUIT[#All],3,0)),"CUIT NO CARGADO") -> Equipos de Informatica | R18: =IFERROR(IF(compras_mes1[[#This Row],[CUIT]]="","-",VLOOKUP(compras_mes1[[#This Row],[CUIT]],Lista_CUIT[#All],4,0)),"CUIT NO CARGADO") -> 0
B19: 44579 | C19: 1 | D19: 10 | E19: 42418 | F19: 30711069360 | G19: =IFERROR(IF(compras_mes1[[#This Row],[CUIT]]="","-",VLOOKUP(compras_mes1[[#This Row],[CUIT]],Lista_CUIT[#All],2,0)),"CUIT NO CARGADO") -> BIDCOM S.R.L. | H19: 27778.62 | I19: =IF(compras_mes1[[#This Row],[NETO GRAVADO]]="","",compras_mes1[[#This Row],[NETO GRAVADO]]*0.21) -> 5833.5102 | N19: 1666.72 | O19: 0 | P19: =SUM(compras_mes1[[#This Row],[NETO GRAVADO]:[Otros / No Grav.]]) -> 35278.85 | Q19: =IFERROR(IF(compras_mes1[[#This Row],[CUIT]]="","-",VLOOKUP(compras_mes1[[#This Row],[CUIT]],Lista_CUIT[#All],3,0)),"CUIT NO CARGADO") -> Equipos de Informatica | R19: =IFERROR(IF(compras_mes1[[#This Row],[CUIT]]="","-",VLOOKUP(compras_mes1[[#This Row],[CUIT]],Lista_CUIT[#All],4,0)),"CUIT NO CARGADO") -> 0
B20: 44583 | C20: 1 | D20: 10 | E20: 42945 | F20: 30711069360 | G20: =IFERROR(IF(compras_mes1[[#This Row],[CUIT]]="","-",VLOOKUP(compras_mes1[[#This Row],[CUIT]],Lista_CUIT[#All],2,0)),"CUIT NO CARGADO") -> BIDCOM S.R.L. | H20: 162226.24 | K20: 17033.76 | N20: 9733.57 | O20: 0 | P20: =SUM(compras_mes1[[#This Row],[NETO GRAVADO]:[Otros / No Grav.]]) -> 188993.57 | Q20: =IFERROR(IF(compras_mes1[[#This Row],[CUIT]]="","-",VLOOKUP(compras_mes1[[#This Row],[CUIT]],Lista_CUIT[#All],3,0)),"CUIT NO CARGADO") -> Equipos de Informatica | R20: =IFERROR(IF(compras_mes1[[#This Row],[CUIT]]="","-",VLOOKUP(compras_mes1[[#This Row],[CUIT]],Lista_CUIT[#All],4,0)),"CUIT NO CARGADO") -> 0
B21: 44582 | C21: 1 | D21: 4 | E21: 4692 | F21: 27293936450 | G21: =IFERROR(IF(compras_mes1[[#This Row],[CUIT]]="","-",VLOOKUP(compras_mes1[[#This Row],[CUIT]],Lista_CUIT[#All],2,0)),"CUIT NO CARGADO") -> PELLIZA PAOLA DANIELA | H21: 5371.9 | I21: =IF(compras_mes1[[#This Row],[NETO GRAVADO]]="","",compras_mes1[[#This Row],[NETO GRAVADO]]*0.21) -> 1128.099 | O21: 0 | P21: =SUM(compras_mes1[[#This Row],[NETO GRAVADO]:[Otros / No Grav.]]) -> 6499.999 | Q21: =IFERROR(IF(compras_mes1[[#This Row],[CUIT]]="","-",VLOOKUP(compras_mes1[[#This Row],[CUIT]],Lista_CUIT[#All],3,0)),"CUIT NO CARGADO") -> Ferreteria | R21: =IFERROR(IF(compras_mes1[[#This Row],[CUIT]]="","-",VLOOKUP(compras_mes1[[#This Row],[CUIT]],Lista_CUIT[#All],4,0)),"CUIT NO CARGADO") -> CABA
B22: 44582 | C22: 1 | D22: 4 | E22: 4693 | F22: 27293936450 | G22: =IFERROR(IF(compras_mes1[[#This Row],[CUIT]]="","-",VLOOKUP(compras_mes1[[#This Row],[CUIT]],Lista_CUIT[#All],2,0)),"CUIT NO CARGADO") -> PELLIZA PAOLA DANIELA | H22: 6714.88 | I22: =IF(compras_mes1[[#This Row],[NETO GRAVADO]]="","",compras_mes1[[#This Row],[NETO GRAVADO]]*0.21) -> 1410.1248 | O22: 0 | P22: =SUM(compras_mes1[[#This Row],[NETO GRAVADO]:[Otros / No Grav.]]) -> 8125.0048 | Q22: =IFERROR(IF(compras_mes1[[#This Row],[CUIT]]="","-",VLOOKUP(compras_mes1[[#This Row],[CUIT]],Lista_CUIT[#All],3,0)),"CUIT NO CARGADO") -> Ferreteria | R22: =IFERROR(IF(compras_mes1[[#This Row],[CUIT]]="","-",VLOOKUP(compras_mes1[[#This Row],[CUIT]],Lista_CUIT[#All],4,0)),"CUIT NO CARGADO") -> CABA
B23: 44579 | C23: 1 | D23: 4 | E23: 41 | F23: 23231010939 | G23: =IFERROR(IF(compras_mes1[[#This Row],[CUIT]]="","-",VLOOKUP(compras_mes1[[#This Row],[CUIT]],Lista_CUIT[#All],2,0)),"CUIT NO CARGADO") -> GARCIA REDONDO ROBERTO SATU | H23: 495.86 | I23: =IF(compras_mes1[[#This Row],[NETO GRAVADO]]="","",compras_mes1[[#This Row],[NETO GRAVADO]]*0.21) -> 104.1306 | O23: 0 | P23: =SUM(compras_mes1[[#This Row],[NETO GRAVADO]:[Otros / No Grav.]]) -> 599.9906 | Q23: =IFERROR(IF(compras_mes1[[#This Row],[CUIT]]="","-",VLOOKUP(compras_mes1[[#This Row],[CUIT]],Lista_CUIT[#All],3,0)),"CUIT NO CARGADO") -> Gastos Varios | R23: =IFERROR(IF(compras_mes1[[#This Row],[CUIT]]="","-",VLOOKUP(compras_mes1[[#This Row],[CUIT]],Lista_CUIT[#All],4,0)),"CUIT NO CARGADO") -> BUENOS AIRES
B24: 44580 | C24: 1 | D24: 113 | E24: 2664972 | F24: 30577207190 | G24: =IFERROR(IF(compras_mes1[[#This Row],[CUIT]]="","-",VLOOKUP(compras_mes1[[#This Row],[CUIT]],Lista_CUIT[#All],2,0)),"CUIT NO CARGADO") -> COORDINACION ECOLOGICA AREA METROPOLITANA SOCIEDAD DEL ESTADO | H24: 1034.71 | I24: =IF(compras_mes1[[#This Row],[NETO GRAVADO]]="","",compras_mes1[[#This Row],[NETO GRAVADO]]*0.21) -> 217.2891 | O24: 0 | P24: =SUM(compras_mes1[[#This Row],[NETO GRAVADO]:[Otros / No Grav.]]) -> 1251.9991 | Q24: =IFERROR(IF(compras_mes1[[#This Row],[CUIT]]="","-",VLOOKUP(compras_mes1[[#This Row],[CUIT]],Lista_CUIT[#All],3,0)),"CUIT NO CARGADO") -> Gastos Varios | R24: =IFERROR(IF(compras_mes1[[#This Row],[CUIT]]="","-",VLOOKUP(compras_mes1[[#This Row],[CUIT]],Lista_CUIT[#All],4,0)),"CUIT NO CARGADO") -> CABA
B25: 44585 | C25: 1 | D25: 8 | E25: 456 | F25: 20388915413 | G25: =IFERROR(IF(compras_mes1[[#This Row],[CUIT]]="","-",VLOOKUP(compras_mes1[[#This Row],[CUIT]],Lista_CUIT[#All],2,0)),"CUIT NO CARGADO") -> GONZALO MARTIN GUENZANI | H25: 21734 | I25: =IF(compras_mes1[[#This Row],[NETO GRAVADO]]="","",compras_mes1[[#This Row],[NETO GRAVADO]]*0.21) -> 4564.14 | O25: 0 | P25: =SUM(compras_mes1[[#This Row],[NETO GRAVADO]:[Otros / No Grav.]]) -> 26298.14 | Q25: =IFERROR(IF(compras_mes1[[#This Row],[CUIT]]="","-",VLOOKUP(compras_mes1[[#This Row],[CUIT]],Lista_CUIT[#All],3,0)),"CUIT NO CARGADO") -> Gastos Varios | R25: =IFERROR(IF(compras_mes1[[#This Row],[CUIT]]="","-",VLOOKUP(compras_mes1[[#This Row],[CUIT]],Lista_CUIT[#All],4,0)),"CUIT NO CARGADO") -> BUENOS AIRES
B26: 44587 | C26: 1 | D26: 4 | E26: 11705 | F26: 20116347742 | G26: =IFERROR(IF(compras_mes1[[#This Row],[CUIT]]="","-",VLOOKUP(compras_mes1[[#This Row],[CUIT]],Lista_CUIT[#All],2,0)),"CUIT NO CARGADO") -> VALDEZ PEDRO ALBERTO | H26: 334.85 | I26: =IF(compras_mes1[[#This Row],[NETO GRAVADO]]="","",compras_mes1[[#This Row],[NETO GRAVADO]]*0.21) -> 70.3185 | O26: 0 | P26: =SUM(compras_mes1[[#This Row],[NETO GRAVADO]:[Otros / No Grav.]]) -> 405.1685 | Q26: =IFERROR(IF(compras_mes1[[#This Row],[CUIT]]="","-",VLOOKUP(compras_mes1[[#This Row],[CUIT]],Lista_CUIT[#All],3,0)),"CUIT NO CARGADO") -> Gastos Varios | R26: =IFERROR(IF(compras_mes1[[#This Row],[CUIT]]="","-",VLOOKUP(compras_mes1[[#This Row],[CUIT]],Lista_CUIT[#All],4,0)),"CUIT NO CARGADO") -> CABA
B27: 44585 | C27: 1 | D27: 4 | E27: 15123 | F27: 30552433595 | G27: =IFERROR(IF(compras_mes1[[#This Row],[CUIT]]="","-",VLOOKUP(compras_mes1[[#This Row],[CUIT]],Lista_CUIT[#All],2,0)),"CUIT NO CARGADO") -> PIROPLAST S.R.L. | H27: 375396.88 | I27: =IF(compras_mes1[[#This Row],[NETO GRAVADO]]="","",compras_mes1[[#This Row],[NETO GRAVADO]]*0.21) -> 78833.345 | O27: 0 | P27: =SUM(compras_mes1[[#This Row],[NETO GRAVADO]:[Otros / No Grav.]]) -> 454230.22 | Q27: =IFERROR(IF(compras_mes1[[#This Row],[CUIT]]="","-",VLOOKUP(compras_mes1[[#This Row],[CUIT]],Lista_CUIT[#All],3,0)),"CUIT NO CARGADO") -> Gtos Comercializacion | R27: =IFERROR(IF(compras_mes1[[#This Row],[CUIT]]="","-",VLOOKUP(compras_mes1[[#This Row],[CUIT]],Lista_CUIT[#All],4,0)),"CUIT NO CARGADO") -> 0
B28: 44590 | C28: 1 | D28: 27 | E28: 196350 | F28: 30703088534 | G28: =IFERROR(IF(compras_mes1[[#This Row],[CUIT]]="","-",VLOOKUP(compras_mes1[[#This Row],[CUIT]],Lista_CUIT[#All],2,0)),"CUIT NO CARGADO") -> MERCADO LIBRE SRL | H28: 64452.7 | I28: =IF(compras_mes1[[#This Row],[NETO GRAVADO]]="","",compras_mes1[[#This Row],[NETO GRAVADO]]*0.21) -> 13535.067 | L28: 1933.6 | N28: 3867.18 | O28: 0 | P28: =SUM(compras_mes1[[#This Row],[NETO GRAVADO]:[Otros / No Grav.]]) -> 83788.547 | Q28: =IFERROR(IF(compras_mes1[[#This Row],[CUIT]]="","-",VLOOKUP(compras_mes1[[#This Row],[CUIT]],Lista_CUIT[#All],3,0)),"CUIT NO CARGADO") -> Gtos Comercializacion | R28: =IFERROR(IF(compras_mes1[[#This Row],[CUIT]]="","-",VLOOKUP(compras_mes1[[#This Row],[CUIT]],Lista_CUIT[#All],4,0)),"CUIT NO CARGADO") -> 0
B29: 44582 | C29: 1 | D29: 10 | E29: 1014 | F29: 23127284369 | G29: =IFERROR(IF(compras_mes1[[#This Row],[CUIT]]="","-",VLOOKUP(compras_mes1[[#This Row],[CUIT]],Lista_CUIT[#All],2,0)),"CUIT NO CARGADO") -> DEALER FX - MONTORRO D. | H29: 10330.1 | I29: =IF(compras_mes1[[#This Row],[NETO GRAVADO]]="","",compras_mes1[[#This Row],[NETO GRAVADO]]*0.21) -> 2169.321 | O29: 0 | P29: =SUM(compras_mes1[[#This Row],[NETO GRAVADO]:[Otros / No Grav.]]) -> 12499.421 | Q29: =IFERROR(IF(compras_mes1[[#This Row],[CUIT]]="","-",VLOOKUP(compras_mes1[[#This Row],[CUIT]],Lista_CUIT[#All],3,0)),"CUIT NO CARGADO") -> Librería | R29: =IFERROR(IF(compras_mes1[[#This Row],[CUIT]]="","-",VLOOKUP(compras_mes1[[#This Row],[CUIT]],Lista_CUIT[#All],4,0)),"CUIT NO CARGADO") -> 0
B30: 44587 | C30: 1 | D30: 22 | E30: 40648 | F30: 30699654309 | G30: =IFERROR(IF(compras_mes1[[#This Row],[CUIT]]="","-",VLOOKUP(compras_mes1[[#This Row],[CUIT]],Lista_CUIT[#All],2,0)),"CUIT NO CARGADO") -> SAN JUAN Y SOLIS SA | H30: 55084.3 | I30: =IF(compras_mes1[[#This Row],[NETO GRAVADO]]="","",compras_mes1[[#This Row],[NETO GRAVADO]]*0.21) -> 11567.703 | O30: 0 | P30: =SUM(compras_mes1[[#This Row],[NETO GRAVADO]:[Otros / No Grav.]]) -> 66652.003 | Q30: =IFERROR(IF(compras_mes1[[#This Row],[CUIT]]="","-",VLOOKUP(compras_mes1[[#This Row],[CUIT]],Lista_CUIT[#All],3,0)),"CUIT NO CARGADO") -> Mantenimiento Auto | R30: =IFERROR(IF(compras_mes1[[#This Row],[CUIT]]="","-",VLOOKUP(compras_mes1[[#This Row],[CUIT]],Lista_CUIT[#All],4,0)),"CUIT NO CARGADO") -> CABA
B31: 44588 | C31: 1 | D31: 301 | E31: 55951 | F31: 30640079378 | G31: =IFERROR(IF(compras_mes1[[#This Row],[CUIT]]="","-",VLOOKUP(compras_mes1[[#This Row],[CUIT]],Lista_CUIT[#All],2,0)),"CUIT NO CARGADO") -> GOMERIAS NEUMEN S.A. | H31: 33411.57 | I31: =IF(compras_mes1[[#This Row],[NETO GRAVADO]]="","",compras_mes1[[#This Row],[NETO GRAVADO]]*0.21) -> 7016.4297 | N31: 2004.69 | O31: 0 | P31: =SUM(compras_mes1[[#This Row],[NETO GRAVADO]:[Otros / No Grav.]]) -> 42432.69 | Q31: =IFERROR(IF(compras_mes1[[#This Row],[CUIT]]="","-",VLOOKUP(compras_mes1[[#This Row],[CUIT]],Lista_CUIT[#All],3,0)),"CUIT NO CARGADO") -> Mantenimiento Auto | R31: =IFERROR(IF(compras_mes1[[#This Row],[CUIT]]="","-",VLOOKUP(compras_mes1[[#This Row],[CUIT]],Lista_CUIT[#All],4,0)),"CUIT NO CARGADO") -> CABA
B32: 44578 | C32: 1 | D32: 10 | E32: 11451 | F32: 30696186932 | G32: =IFERROR(IF(compras_mes1[[#This Row],[CUIT]]="","-",VLOOKUP(compras_mes1[[#This Row],[CUIT]],Lista_CUIT[#All],2,0)),"CUIT NO CARGADO") -> NORDESTNOVA S.A. | H32: 79561.5 | I32: =IF(compras_mes1[[#This Row],[NETO GRAVADO]]="","",compras_mes1[[#This Row],[NETO GRAVADO]]*0.21) -> 16707.915 | O32: 0 | P32: =SUM(compras_mes1[[#This Row],[NETO GRAVADO]:[Otros / No Grav.]]) -> 96269.415 | Q32: =IFERROR(IF(compras_mes1[[#This Row],[CUIT]]="","-",VLOOKUP(compras_mes1[[#This Row],[CUIT]],Lista_CUIT[#All],3,0)),"CUIT NO CARGADO") -> Materia Prima | R32: =IFERROR(IF(compras_mes1[[#This Row],[CUIT]]="","-",VLOOKUP(compras_mes1[[#This Row],[CUIT]],Lista_CUIT[#All],4,0)),"CUIT NO CARGADO") -> 0
B33: 44575 | C33: 1 | D33: 6 | E33: 1898 | F33: 30574603788 | G33: =IFERROR(IF(compras_mes1[[#This Row],[CUIT]]="","-",VLOOKUP(compras_mes1[[#This Row],[CUIT]],Lista_CUIT[#All],2,0)),"CUIT NO CARGADO") -> Codac SRL | H33: 148851 | I33: =IF(compras_mes1[[#This Row],[NETO GRAVADO]]="","",compras_mes1[[#This Row],[NETO GRAVADO]]*0.21) -> 31258.71 | O33: 0 | P33: =SUM(compras_mes1[[#This Row],[NETO GRAVADO]:[Otros / No Grav.]]) -> 180109.71 | Q33: =IFERROR(IF(compras_mes1[[#This Row],[CUIT]]="","-",VLOOKUP(compras_mes1[[#This Row],[CUIT]],Lista_CUIT[#All],3,0)),"CUIT NO CARGADO") -> Mercaderia | R33: =IFERROR(IF(compras_mes1[[#This Row],[CUIT]]="","-",VLOOKUP(compras_mes1[[#This Row],[CUIT]],Lista_CUIT[#All],4,0)),"CUIT NO CARGADO") -> 0
B34: 44578 | C34: 1 | D34: 3 | E34: 5744 | F34: 30708006420 | G34: =IFERROR(IF(compras_mes1[[#This Row],[CUIT]]="","-",VLOOKUP(compras_mes1[[#This Row],[CUIT]],Lista_CUIT[#All],2,0)),"CUIT NO CARGADO") -> MEDILEA S.A. | H34: 239229 | I34: =IF(compras_mes1[[#This Row],[NETO GRAVADO]]="","",compras_mes1[[#This Row],[NETO GRAVADO]]*0.21) -> 50238.09 | O34: 0 | P34: =SUM(compras_mes1[[#This Row],[NETO GRAVADO]:[Otros / No Grav.]]) -> 289467.09 | Q34: =IFERROR(IF(compras_mes1[[#This Row],[CUIT]]="","-",VLOOKUP(compras_mes1[[#This Row],[CUIT]],Lista_CUIT[#All],3,0)),"CUIT NO CARGADO") -> Mercaderia | R34: =IFERROR(IF(compras_mes1[[#This Row],[CUIT]]="","-",VLOOKUP(compras_mes1[[#This Row],[CUIT]],Lista_CUIT[#All],4,0)),"CUIT NO CARGADO") -> 0
B35: 44578 | C35: 1 | D35: 6 | E35: 20654 | F35: 33640878679 | G35: =IFERROR(IF(compras_mes1[[#This Row],[CUIT]]="","-",VLOOKUP(compras_mes1[[#This Row],[CUIT]],Lista_CUIT[#All],2,0)),"CUIT NO CARGADO") -> DHACAM S.R.L. | H35: 55120 | I35: =IF(compras_mes1[[#This Row],[NETO GRAVADO]]="","",compras_mes1[[#This Row],[NETO GRAVADO]]*0.21) -> 11575.2 | O35: 0 | P35: =SUM(compras_mes1[[#This Row],[NETO GRAVADO]:[Otros / No Grav.]]) -> 66695.2 | Q35: =IFERROR(IF(compras_mes1[[#This Row],[CUIT]]="","-",VLOOKUP(compras_mes1[[#This Row],[CUIT]],Lista_CUIT[#All],3,0)),"CUIT NO CARGADO") -> Mercaderia | R35: =IFERROR(IF(compras_mes1[[#This Row],[CUIT]]="","-",VLOOKUP(compras_mes1[[#This Row],[CUIT]],Lista_CUIT[#All],4,0)),"CUIT NO CARGADO") -> 0
B36: 44582 | C36: 1 | D36: 6 | E36: 20679 | F36: 33640878679 | G36: =IFERROR(IF(compras_mes1[[#This Row],[CUIT]]="","-",VLOOKUP(compras_mes1[[#This Row],[CUIT]],Lista_CUIT[#All],2,0)),"CUIT NO CARGADO") -> DHACAM S.R.L. | H36: 116550 | I36: =IF(compras_mes1[[#This Row],[NETO GRAVADO]]="","",compras_mes1[[#This Row],[NETO GRAVADO]]*0.21) -> 24475.5 | O36: 0 | P36: =SUM(compras_mes1[[#This Row],[NETO GRAVADO]:[Otros / No Grav.]]) -> 141025.5 | Q36: =IFERROR(IF(compras_mes1[[#This Row],[CUIT]]="","-",VLOOKUP(compras_mes1[[#This Row],[CUIT]],Lista_CUIT[#All],3,0)),"CUIT NO CARGADO") -> Mercaderia | R36: =IFERROR(IF(compras_mes1[[#This Row],[CUIT]]="","-",VLOOKUP(compras_mes1[[#This Row],[CUIT]],Lista_CUIT[#All],4,0)),"CUIT NO CARGADO") -> 0
B37: 44587 | C37: 1 | D37: 2 | E37: 2971 | F37: 30629863571 | G37: =IFERROR(IF(compras_mes1[[#This Row],[CUIT]]="","-",VLOOKUP(compras_mes1[[#This Row],[CUIT]],Lista_CUIT[#All],2,0)),"CUIT NO CARGADO") -> TECNIMAR S R L | H37: 129681.02 | I37: =IF(compras_mes1[[#This Row],[NETO GRAVADO]]="","",compras_mes1[[#This Row],[NETO GRAVADO]]*0.21) -> 27233.014 | O37: 0 | P37: =SUM(compras_mes1[[#This Row],[NETO GRAVADO]:[Otros / No Grav.]]) -> 156914.03 | Q37: =IFERROR(IF(compras_mes1[[#This Row],[CUIT]]="","-",VLOOKUP(compras_mes1[[#This Row],[CUIT]],Lista_CUIT[#All],3,0)),"CUIT NO CARGADO") -> Mercaderia | R37: =IFERROR(IF(compras_mes1[[#This Row],[CUIT]]="","-",VLOOKUP(compras_mes1[[#This Row],[CUIT]],Lista_CUIT[#All],4,0)),"CUIT NO CARGADO") -> 0
B38: 44587 | C38: 1 | D38: 3 | E38: 5770 | F38: 30708006420 | G38: =IFERROR(IF(compras_mes1[[#This Row],[CUIT]]="","-",VLOOKUP(compras_mes1[[#This Row],[CUIT]],Lista_CUIT[#All],2,0)),"CUIT NO CARGADO") -> MEDILEA S.A. | H38: 84390 | I38: =IF(compras_mes1[[#This Row],[NETO GRAVADO]]="","",compras_mes1[[#This Row],[NETO GRAVADO]]*0.21) -> 17721.9 | O38: 0 | P38: =SUM(compras_mes1[[#This Row],[NETO GRAVADO]:[Otros / No Grav.]]) -> 102111.9 | Q38: =IFERROR(IF(compras_mes1[[#This Row],[CUIT]]="","-",VLOOKUP(compras_mes1[[#This Row],[CUIT]],Lista_CUIT[#All],3,0)),"CUIT NO CARGADO") -> Mercaderia | R38: =IFERROR(IF(compras_mes1[[#This Row],[CUIT]]="","-",VLOOKUP(compras_mes1[[#This Row],[CUIT]],Lista_CUIT[#All],4,0)),"CUIT NO CARGADO") -> 0
B39: 44589 | C39: 1 | D39: 3 | E39: 5780 | F39: 30708006420 | G39: =IFERROR(IF(compras_mes1[[#This Row],[CUIT]]="","-",VLOOKUP(compras_mes1[[#This Row],[CUIT]],Lista_CUIT[#All],2,0)),"CUIT NO CARGADO") -> MEDILEA S.A. | H39: 189500 | I39: =IF(compras_mes1[[#This Row],[NETO GRAVADO]]="","",compras_mes1[[#This Row],[NETO GRAVADO]]*0.21) -> 39795 | O39: 0 | P39: =SUM(compras_mes1[[#This Row],[NETO GRAVADO]:[Otros / No Grav.]]) -> 229295 | Q39: =IFERROR(IF(compras_mes1[[#This Row],[CUIT]]="","-",VLOOKUP(compras_mes1[[#This Row],[CUIT]],Lista_CUIT[#All],3,0)),"CUIT NO CARGADO") -> Mercaderia | R39: =IFERROR(IF(compras_mes1[[#This Row],[CUIT]]="","-",VLOOKUP(compras_mes1[[#This Row],[CUIT]],Lista_CUIT[#All],4,0)),"CUIT NO CARGADO") -> 0
B40: 44579 | C40: 1 | D40: 711 | E40: 2943028 | F40: 30663498513 | G40: =IFERROR(IF(compras_mes1[[#This Row],[CUIT]]="","-",VLOOKUP(compras_mes1[[#This Row],[CUIT]],Lista_CUIT[#All],2,0)),"CUIT NO CARGADO") -> GRUPO CONCES. DEL OESTE SA | H40: 738.84 | I40: =IF(compras_mes1[[#This Row],[NETO GRAVADO]]="","",compras_mes1[[#This Row],[NETO GRAVADO]]*0.21) -> 155.1564 | O40: 0 | P40: =SUM(compras_mes1[[#This Row],[NETO GRAVADO]:[Otros / No Grav.]]) -> 893.9964 | Q40: =IFERROR(IF(compras_mes1[[#This Row],[CUIT]]="","-",VLOOKUP(compras_mes1[[#This Row],[CUIT]],Lista_CUIT[#All],3,0)),"CUIT NO CARGADO") -> Peaje | R40: =IFERROR(IF(compras_mes1[[#This Row],[CUIT]]="","-",VLOOKUP(compras_mes1[[#This Row],[CUIT]],Lista_CUIT[#All],4,0)),"CUIT NO CARGADO") -> 0
B41: 44579 | C41: 1 | D41: 711 | E41: 2521064 | F41: 30677237119 | G41: =IFERROR(IF(compras_mes1[[#This Row],[CUIT]]="","-",VLOOKUP(compras_mes1[[#This Row],[CUIT]],Lista_CUIT[#All],2,0)),"CUIT NO CARGADO") -> AUTOPISTAS DEL SOL S A | H41: 560.8 | I41: =IF(compras_mes1[[#This Row],[NETO GRAVADO]]="","",compras_mes1[[#This Row],[NETO GRAVADO]]*0.21) -> 117.768 | O41: 0 | P41: =SUM(compras_mes1[[#This Row],[NETO GRAVADO]:[Otros / No Grav.]]) -> 678.568 | Q41: =IFERROR(IF(compras_mes1[[#This Row],[CUIT]]="","-",VLOOKUP(compras_mes1[[#This Row],[CUIT]],Lista_CUIT[#All],3,0)),"CUIT NO CARGADO") -> Peaje | R41: =IFERROR(IF(compras_mes1[[#This Row],[CUIT]]="","-",VLOOKUP(compras_mes1[[#This Row],[CUIT]],Lista_CUIT[#All],4,0)),"CUIT NO CARGADO") -> 0
B42: 44585 | C42: 1 | D42: 700 | E42: 340629 | F42: 30715804812 | G42: =IFERROR(IF(compras_mes1[[#This Row],[CUIT]]="","-",VLOOKUP(compras_mes1[[#This Row],[CUIT]],Lista_CUIT[#All],2,0)),"CUIT NO CARGADO") -> CORREDORES VIALES SOCIEDAD ANONIMA | H42: 1295.78 | I42: =IF(compras_mes1[[#This Row],[NETO GRAVADO]]="","",compras_mes1[[#This Row],[NETO GRAVADO]]*0.21) -> 272.1138 | O42: 0 | P42: =SUM(compras_mes1[[#This Row],[NETO GRAVADO]:[Otros / No Grav.]]) -> 1567.8938 | Q42: =IFERROR(IF(compras_mes1[[#This Row],[CUIT]]="","-",VLOOKUP(compras_mes1[[#This Row],[CUIT]],Lista_CUIT[#All],3,0)),"CUIT NO CARGADO") -> Peaje | R42: =IFERROR(IF(compras_mes1[[#This Row],[CUIT]]="","-",VLOOKUP(compras_mes1[[#This Row],[CUIT]],Lista_CUIT[#All],4,0)),"CUIT NO CARGADO") -> 0
B43: 44574 | C43: 1 | D43: 5 | E43: 17 | F43: 30716385961 | G43: =IFERROR(IF(compras_mes1[[#This Row],[CUIT]]="","-",VLOOKUP(compras_mes1[[#This Row],[CUIT]],Lista_CUIT[#All],2,0)),"CUIT NO CARGADO") -> GRUPO VDB TEXTIL S.R.L. | H43: 2317.48 | I43: =IF(compras_mes1[[#This Row],[NETO GRAVADO]]="","",compras_mes1[[#This Row],[NETO GRAVADO]]*0.21) -> 486.6708 | O43: 0 | P43: =SUM(compras_mes1[[#This Row],[NETO GRAVADO]:[Otros / No Grav.]]) -> 2804.1508 | Q43: =IFERROR(IF(compras_mes1[[#This Row],[CUIT]]="","-",VLOOKUP(compras_mes1[[#This Row],[CUIT]],Lista_CUIT[#All],3,0)),"CUIT NO CARGADO") -> Ropa de Trabajo | R43: =IFERROR(IF(compras_mes1[[#This Row],[CUIT]]="","-",VLOOKUP(compras_mes1[[#This Row],[CUIT]],Lista_CUIT[#All],4,0)),"CUIT NO CARGADO") -> CABA
... B46: 44575 | C46: 1 | D46: 13 | E46: 104030 | F46: 30650296997 | G46: =IFERROR(IF(compras_mes1[[#This Row],[CUIT]]="","-",VLOOKUP(compras_mes1[[#This Row],[CUIT]],Lista_CUIT[#All],2,0)),"CUIT NO CARGADO") -> GAS PARQUE S.A. | H46: 3433.55 | I46: =IF(compras_mes1[[#This Row],[NETO GRAVADO]]="","",compras_mes1[[#This Row],[NETO GRAVADO]]*0.21) -> 721.0455 | O46: 7.41 | P46: =SUM(compras_mes1[[#This Row],[NETO GRAVADO]:[Otros / No Grav.]]) -> 4162.0055 | Q46: =IFERROR(IF(compras_mes1[[#This Row],[CUIT]]="","-",VLOOKUP(compras_mes1[[#This Row],[CUIT]],Lista_CUIT[#All],3,0)),"CUIT NO CARGADO") -> Combustible | R46: =IFERROR(IF(compras_mes1[[#This Row],[CUIT]]="","-",VLOOKUP(compras_mes1[[#This Row],[CUIT]],Lista_CUIT[#All],4,0)),"CUIT NO CARGADO") -> 0
B47: 44579 | C47: 1 | D47: 1666 | E47: 17407 | F47: 30589621499 | G47: =IFERROR(IF(compras_mes1[[#This Row],[CUIT]]="","-",VLOOKUP(compras_mes1[[#This Row],[CUIT]],Lista_CUIT[#All],2,0)),"CUIT NO CARGADO") -> MAKRO SA | H47: 8901.95 | I47: 1813.35 | L47: 259.05 | N47: 534.12 | O47: 26.67 | P47: =SUM(compras_mes1[[#This Row],[NETO GRAVADO]:[Otros / No Grav.]]) -> 11535.14 | Q47: =IFERROR(IF(compras_mes1[[#This Row],[CUIT]]="","-",VLOOKUP(compras_mes1[[#This Row],[CUIT]],Lista_CUIT[#All],3,0)),"CUIT NO CARGADO") -> Comida-Limpieza | R47: =IFERROR(IF(compras_mes1[[#This Row],[CUIT]]="","-",VLOOKUP(compras_mes1[[#This Row],[CUIT]],Lista_CUIT[#All],4,0)),"CUIT NO CARGADO") -> 0
B48: 44571 | C48: 1 | D48: 6 | E48: 11563153 | F48: 30620177497 | G48: =IFERROR(IF(compras_mes1[[#This Row],[CUIT]]="","-",VLOOKUP(compras_mes1[[#This Row],[CUIT]],Lista_CUIT[#All],2,0)),"CUIT NO CARGADO") -> POSNET SRL | H48: 1580 | I48: =IF(compras_mes1[[#This Row],[NETO GRAVADO]]="","",compras_mes1[[#This Row],[NETO GRAVADO]]*0.21) -> 331.8 | L48: 47.4 | O48: 94.8 | P48: =SUM(compras_mes1[[#This Row],[NETO GRAVADO]:[Otros / No Grav.]]) -> 2054 | Q48: =IFERROR(IF(compras_mes1[[#This Row],[CUIT]]="","-",VLOOKUP(compras_mes1[[#This Row],[CUIT]],Lista_CUIT[#All],3,0)),"CUIT NO CARGADO") -> Gtos Comercializacion | R48: =IFERROR(IF(compras_mes1[[#This Row],[CUIT]]="","-",VLOOKUP(compras_mes1[[#This Row],[CUIT]],Lista_CUIT[#All],4,0)),"CUIT NO CARGADO") -> 0
B49: 44571 | C49: 1 | D49: 6 | E49: 11563174 | F49: 30620177497 | G49: =IFERROR(IF(compras_mes1[[#This Row],[CUIT]]="","-",VLOOKUP(compras_mes1[[#This Row],[CUIT]],Lista_CUIT[#All],2,0)),"CUIT NO CARGADO") -> POSNET SRL | H49: 1580 | I49: =IF(compras_mes1[[#This Row],[NETO GRAVADO]]="","",compras_mes1[[#This Row],[NETO GRAVADO]]*0.21) -> 331.8 | L49: 47.4 | O49: 94.8 | P49: =SUM(compras_mes1[[#This Row],[NETO GRAVADO]:[Otros / No Grav.]]) -> 2054 | Q49: =IFERROR(IF(compras_mes1[[#This Row],[CUIT]]="","-",VLOOKUP(compras_mes1[[#This Row],[CUIT]],Lista_CUIT[#All],3,0)),"CUIT NO CARGADO") -> Gtos Comercializacion | R49: =IFERROR(IF(compras_mes1[[#This Row],[CUIT]]="","-",VLOOKUP(compras_mes1[[#This Row],[CUIT]],Lista_CUIT[#All],4,0)),"CUIT NO CARGADO") -> 0
B50: 44571 | C50: 1 | D50: 6 | E50: 11563178 | F50: 30620177497 | G50: =IFERROR(IF(compras_mes1[[#This Row],[CUIT]]="","-",VLOOKUP(compras_mes1[[#This Row],[CUIT]],Lista_CUIT[#All],2,0)),"CUIT NO CARGADO") -> POSNET SRL | H50: 1580 | I50: =IF(compras_mes1[[#This Row],[NETO GRAVADO]]="","",compras_mes1[[#This Row],[NETO GRAVADO]]*0.21) -> 331.8 | L50: 47.4 | O50: 94.8 | P50: =SUM(compras_mes1[[#This Row],[NETO GRAVADO]:[Otros / No Grav.]]) -> 2054 | Q50: =IFERROR(IF(compras_mes1[[#This Row],[CUIT]]="","-",VLOOKUP(compras_mes1[[#This Row],[CUIT]],Lista_CUIT[#All],3,0)),"CUIT NO CARGADO") -> Gtos Comercializacion | R50: =IFERROR(IF(compras_mes1[[#This Row],[CUIT]]="","-",VLOOKUP(compras_mes1[[#This Row],[CUIT]],Lista_CUIT[#All],4,0)),"CUIT NO CARGADO") -> 0
B51: 44589 | C51: 1 | D51: 5026 | E51: 4940 | F51: 30695542476 | G51: =IFERROR(IF(compras_mes1[[#This Row],[CUIT]]="","-",VLOOKUP(compras_mes1[[#This Row],[CUIT]],Lista_CUIT[#All],2,0)),"CUIT NO CARGADO") -> PAN AMERICAN ENERGY SL S.AR | H51: 1761.73 | I51: =IF(compras_mes1[[#This Row],[NETO GRAVADO]]="","",compras_mes1[[#This Row],[NETO GRAVADO]]*0.21) -> 369.9633 | O51: 101.59 | P51: =SUM(compras_mes1[[#This Row],[NETO GRAVADO]:[Otros / No Grav.]]) -> 2233.2833 | Q51: =IFERROR(IF(compras_mes1[[#This Row],[CUIT]]="","-",VLOOKUP(compras_mes1[[#This Row],[CUIT]],Lista_CUIT[#All],3,0)),"CUIT NO CARGADO") -> Combustible | R51: =IFERROR(IF(compras_mes1[[#This Row],[CUIT]]="","-",VLOOKUP(compras_mes1[[#This Row],[CUIT]],Lista_CUIT[#All],4,0)),"CUIT NO CARGADO") -> 0
B52: 44570 | C52: 1 | D52: 948 | E52: 536271 | F52: 30639453975 | G52: =IFERROR(IF(compras_mes1[[#This Row],[CUIT]]="","-",VLOOKUP(compras_mes1[[#This Row],[CUIT]],Lista_CUIT[#All],2,0)),"CUIT NO CARGADO") -> TELEFONICA DE ARG S.A. | H52: 2575.32 | I52: 695.34 | L52: 77.26 | O52: 154.52 | P52: =SUM(compras_mes1[[#This Row],[NETO GRAVADO]:[Otros / No Grav.]]) -> 3502.44 | Q52: =IFERROR(IF(compras_mes1[[#This Row],[CUIT]]="","-",VLOOKUP(compras_mes1[[#This Row],[CUIT]],Lista_CUIT[#All],3,0)),"CUIT NO CARGADO") -> Servicios Gas, Luz, etc. | R52: =IFERROR(IF(compras_mes1[[#This Row],[CUIT]]="","-",VLOOKUP(compras_mes1[[#This Row],[CUIT]],Lista_CUIT[#All],4,0)),"CUIT NO CARGADO") -> 0
B53: 44571 | C53: 1 | D53: 6 | E53: 11563220 | F53: 30620177497 | G53: =IFERROR(IF(compras_mes1[[#This Row],[CUIT]]="","-",VLOOKUP(compras_mes1[[#This Row],[CUIT]],Lista_CUIT[#All],2,0)),"CUIT NO CARGADO") -> POSNET SRL | H53: 4740 | I53: =IF(compras_mes1[[#This Row],[NETO GRAVADO]]="","",compras_mes1[[#This Row],[NETO GRAVADO]]*0.21) -> 995.4 | L53: 142.2 | O53: 284.4 | P53: =SUM(compras_mes1[[#This Row],[NETO GRAVADO]:[Otros / No Grav.]]) -> 6162 | Q53: =IFERROR(IF(compras_mes1[[#This Row],[CUIT]]="","-",VLOOKUP(compras_mes1[[#This Row],[CUIT]],Lista_CUIT[#All],3,0)),"CUIT NO CARGADO") -> Gtos Comercializacion | R53: =IFERROR(IF(compras_mes1[[#This Row],[CUIT]]="","-",VLOOKUP(compras_mes1[[#This Row],[CUIT]],Lista_CUIT[#All],4,0)),"CUIT NO CARGADO") -> 0
B54: 44579 | C54: 1 | D54: 5014 | E54: 182365 | F54: 30574876474 | G54: =IFERROR(IF(compras_mes1[[#This Row],[CUIT]]="","-",VLOOKUP(compras_mes1[[#This Row],[CUIT]],Lista_CUIT[#All],2,0)),"CUIT NO CARGADO") -> AUTOPISTAS URBANAS S A | H54: 6649.66 | I54: =IF(compras_mes1[[#This Row],[NETO GRAVADO]]="","",compras_mes1[[#This Row],[NETO GRAVADO]]*0.21) -> 1396.4286 | L54: 199.48 | O54: 614.61 | P54: =SUM(compras_mes1[[#This Row],[NETO GRAVADO]:[Otros / No Grav.]]) -> 8860.1786 | Q54: =IFERROR(IF(compras_mes1[[#This Row],[CUIT]]="","-",VLOOKUP(compras_mes1[[#This Row],[CUIT]],Lista_CUIT[#All],3,0)),"CUIT NO CARGADO") -> Peaje | R54: =IFERROR(IF(compras_mes1[[#This Row],[CUIT]]="","-",VLOOKUP(compras_mes1[[#This Row],[CUIT]],Lista_CUIT[#All],4,0)),"CUIT NO CARGADO") -> 0
B55: 44589 | C55: 1 | D55: 2199 | E55: 14249 | F55: 30548083156 | G55: =IFERROR(IF(compras_mes1[[#This Row],[CUIT]]="","-",VLOOKUP(compras_mes1[[#This Row],[CUIT]],Lista_CUIT[#All],2,0)),"CUIT NO CARGADO") -> COTO S.A. | H55: 30776.92 | I55: 6012.16 | N55: 878.71 | O55: 779.73 | P55: =SUM(compras_mes1[[#This Row],[NETO GRAVADO]:[Otros / No Grav.]]) -> 38447.52 | Q55: =IFERROR(IF(compras_mes1[[#This Row],[CUIT]]="","-",VLOOKUP(compras_mes1[[#This Row],[CUIT]],Lista_CUIT[#All],3,0)),"CUIT NO CARGADO") -> Gastos Varios | R55: =IFERROR(IF(compras_mes1[[#This Row],[CUIT]]="","-",VLOOKUP(compras_mes1[[#This Row],[CUIT]],Lista_CUIT[#All],4,0)),"CUIT NO CARGADO") -> 0
B56: 44572 | C56: 1 | D56: 8263 | E56: 1633 | F56: 30590360763 | G56: =IFERROR(IF(compras_mes1[[#This Row],[CUIT]]="","-",VLOOKUP(compras_mes1[[#This Row],[CUIT]],Lista_CUIT[#All],2,0)),"CUIT NO CARGADO") -> CENCOSUD S.A | H56: 16271.07 | I56: =IF(compras_mes1[[#This Row],[NETO GRAVADO]]="","",compras_mes1[[#This Row],[NETO GRAVADO]]*0.21) -> 3416.9247 | L56: 488.13 | O56: 976.26 | P56: =SUM(compras_mes1[[#This Row],[NETO GRAVADO]:[Otros / No Grav.]]) -> 21152.385 | Q56: =IFERROR(IF(compras_mes1[[#This Row],[CUIT]]="","-",VLOOKUP(compras_mes1[[#This Row],[CUIT]],Lista_CUIT[#All],3,0)),"CUIT NO CARGADO") -> Gastos Varios | R56: =IFERROR(IF(compras_mes1[[#This Row],[CUIT]]="","-",VLOOKUP(compras_mes1[[#This Row],[CUIT]],Lista_CUIT[#All],4,0)),"CUIT NO CARGADO") -> 0
B57: 44571 | C57: 1 | D57: 12 | E57: 49843 | F57: 20130138005 | G57: =IFERROR(IF(compras_mes1[[#This Row],[CUIT]]="","-",VLOOKUP(compras_mes1[[#This Row],[CUIT]],Lista_CUIT[#All],2,0)),"CUIT NO CARGADO") -> YPF KM 296 | H57: 5125.13 | I57: =IF(compras_mes1[[#This Row],[NETO GRAVADO]]="","",compras_mes1[[#This Row],[NETO GRAVADO]]*0.21) -> 1076.2773 | O57: 1398.43 | P57: =SUM(compras_mes1[[#This Row],[NETO GRAVADO]:[Otros / No Grav.]]) -> 7599.8373 | Q57: =IFERROR(IF(compras_mes1[[#This Row],[CUIT]]="","-",VLOOKUP(compras_mes1[[#This Row],[CUIT]],Lista_CUIT[#All],3,0)),"CUIT NO CARGADO") -> Combustible | R57: =IFERROR(IF(compras_mes1[[#This Row],[CUIT]]="","-",VLOOKUP(compras_mes1[[#This Row],[CUIT]],Lista_CUIT[#All],4,0)),"CUIT NO CARGADO") -> 0
B58: 44571 | C58: 1 | D58: 6364 | E58: 5613460 | F58: 30639453738 | G58: =IFERROR(IF(compras_mes1[[#This Row],[CUIT]]="","-",VLOOKUP(compras_mes1[[#This Row],[CUIT]],Lista_CUIT[#All],2,0)),"CUIT NO CARGADO") -> TELECOM ARG SA | H58: 32413.47 | I58: 6891.98 | L58: 972.42 | O58: 1873.03 | P58: =SUM(compras_mes1[[#This Row],[NETO GRAVADO]:[Otros / No Grav.]]) -> 42150.9 | Q58: =IFERROR(IF(compras_mes1[[#This Row],[CUIT]]="","-",VLOOKUP(compras_mes1[[#This Row],[CUIT]],Lista_CUIT[#All],3,0)),"CUIT NO CARGADO") -> Servicios Gas, Luz, etc. | R58: =IFERROR(IF(compras_mes1[[#This Row],[CUIT]]="","-",VLOOKUP(compras_mes1[[#This Row],[CUIT]],Lista_CUIT[#All],4,0)),"CUIT NO CARGADO") -> 0
B59: 44589 | C59: 1 | D59: 4 | E59: 137853 | F59: 30550847589 | G59: =IFERROR(IF(compras_mes1[[#This Row],[CUIT]]="","-",VLOOKUP(compras_mes1[[#This Row],[CUIT]],Lista_CUIT[#All],2,0)),"CUIT NO CARGADO") -> CORAFAL NORTE S.A. | H59: 11132.18 | I59: 2337.76 | O59: 2337.76 | P59: =SUM(compras_mes1[[#This Row],[NETO GRAVADO]:[Otros / No Grav.]]) -> 15807.7 | Q59: =IFERROR(IF(compras_mes1[[#This Row],[CUIT]]="","-",VLOOKUP(compras_mes1[[#This Row],[CUIT]],Lista_CUIT[#All],3,0)),"CUIT NO CARGADO") -> Combustible | R59: =IFERROR(IF(compras_mes1[[#This Row],[CUIT]]="","-",VLOOKUP(compras_mes1[[#This Row],[CUIT]],Lista_CUIT[#All],4,0)),"CUIT NO CARGADO") -> BUENOS AIRES
B60: 44584 | C60: 1 | D60: 6860 | E60: 7835 | F60: 30678774495 | G60: =IFERROR(IF(compras_mes1[[#This Row],[CUIT]]="","-",VLOOKUP(compras_mes1[[#This Row],[CUIT]],Lista_CUIT[#All],2,0)),"CUIT NO CARGADO") -> OPER. DE EST. DE SERV. SA | H60: 7570.14 | I60: =IF(compras_mes1[[#This Row],[NETO GRAVADO]]="","",compras_mes1[[#This Row],[NETO GRAVADO]]*0.21) -> 1589.7294 | O60: 2366.63 | P60: =SUM(compras_mes1[[#This Row],[NETO GRAVADO]:[Otros / No Grav.]]) -> 11526.499 | Q60: =IFERROR(IF(compras_mes1[[#This Row],[CUIT]]="","-",VLOOKUP(compras_mes1[[#This Row],[CUIT]],Lista_CUIT[#All],3,0)),"CUIT NO CARGADO") -> Combustible | R60: =IFERROR(IF(compras_mes1[[#This Row],[CUIT]]="","-",VLOOKUP(compras_mes1[[#This Row],[CUIT]],Lista_CUIT[#All],4,0)),"CUIT NO CARGADO") -> 0
B61: 44592 | C61: 1 | D61: 20 | E61: 718 | F61: 30515800219 | G61: =IFERROR(IF(compras_mes1[[#This Row],[CUIT]]="","-",VLOOKUP(compras_mes1[[#This Row],[CUIT]],Lista_CUIT[#All],2,0)),"CUIT NO CARGADO") -> INCAT SRL | H61: 13262.48 | I61: =IF(compras_mes1[[#This Row],[NETO GRAVADO]]="","",compras_mes1[[#This Row],[NETO GRAVADO]]*0.21) -> 2785.1208 | O61: 2965.22 | P61: =SUM(compras_mes1[[#This Row],[NETO GRAVADO]:[Otros / No Grav.]]) -> 19012.821 | Q61: =IFERROR(IF(compras_mes1[[#This Row],[CUIT]]="","-",VLOOKUP(compras_mes1[[#This Row],[CUIT]],Lista_CUIT[#All],3,0)),"CUIT NO CARGADO") -> Combustible | R61: =IFERROR(IF(compras_mes1[[#This Row],[CUIT]]="","-",VLOOKUP(compras_mes1[[#This Row],[CUIT]],Lista_CUIT[#All],4,0)),"CUIT NO CARGADO") -> 0
B62: 44590 | C62: 1 | D62: 7 | E62: 54951 | F62: 30696131003 | G62: =IFERROR(IF(compras_mes1[[#This Row],[CUIT]]="","-",VLOOKUP(compras_mes1[[#This Row],[CUIT]],Lista_CUIT[#All],2,0)),"CUIT NO CARGADO") -> PETROLFE S.A. | H62: 28728.86 | I62: =IF(compras_mes1[[#This Row],[NETO GRAVADO]]="","",compras_mes1[[#This Row],[NETO GRAVADO]]*0.21) -> 6033.0606 | O62: 8831.59 | P62: =SUM(compras_mes1[[#This Row],[NETO GRAVADO]:[Otros / No Grav.]]) -> 43593.511 | Q62: =IFERROR(IF(compras_mes1[[#This Row],[CUIT]]="","-",VLOOKUP(compras_mes1[[#This Row],[CUIT]],Lista_CUIT[#All],3,0)),"CUIT NO CARGADO") -> Combustible | R62: =IFERROR(IF(compras_mes1[[#This Row],[CUIT]]="","-",VLOOKUP(compras_mes1[[#This Row],[CUIT]],Lista_CUIT[#All],4,0)),"CUIT NO CARGADO") -> 0
B63: 44573 | C63: 1 | D63: 6 | E63: 21490 | F63: 30641221771 | G63: =IFERROR(IF(compras_mes1[[#This Row],[CUIT]]="","-",VLOOKUP(compras_mes1[[#This Row],[CUIT]],Lista_CUIT[#All],2,0)),"CUIT NO CARGADO") -> FARMATRADE S.R.L. | H63: 150075 | I63: =IF(compras_mes1[[#This Row],[NETO GRAVADO]]="","",compras_mes1[[#This Row],[NETO GRAVADO]]*0.21) -> 31515.75 | O63: 9004.5 | P63: =SUM(compras_mes1[[#This Row],[NETO GRAVADO]:[Otros / No Grav.]]) -> 190595.25 | Q63: =IFERROR(IF(compras_mes1[[#This Row],[CUIT]]="","-",VLOOKUP(compras_mes1[[#This Row],[CUIT]],Lista_CUIT[#All],3,0)),"CUIT NO CARGADO") -> Mercaderia | R63: =IFERROR(IF(compras_mes1[[#This Row],[CUIT]]="","-",VLOOKUP(compras_mes1[[#This Row],[CUIT]],Lista_CUIT[#All],4,0)),"CUIT NO CARGADO") -> BUENOS AIRES
B64: 44564 | C64: 1 | D64: 1 | E64: 205 | F64: 20131206144 | G64: =IFERROR(IF(compras_mes1[[#This Row],[CUIT]]="","-",VLOOKUP(compras_mes1[[#This Row],[CUIT]],Lista_CUIT[#All],2,0)),"CUIT NO CARGADO") -> CHAMORRO MANUEL | H64: 18000 | I64: =IF(compras_mes1[[#This Row],[NETO GRAVADO]]="","",compras_mes1[[#This Row],[NETO GRAVADO]]*0.21) -> 3780 | P64: =SUM(compras_mes1[[#This Row],[NETO GRAVADO]:[Otros / No Grav.]]) -> 21780 | Q64: =IFERROR(IF(compras_mes1[[#This Row],[CUIT]]="","-",VLOOKUP(compras_mes1[[#This Row],[CUIT]],Lista_CUIT[#All],3,0)),"CUIT NO CARGADO") -> Alquiler | R64: =IFERROR(IF(compras_mes1[[#This Row],[CUIT]]="","-",VLOOKUP(compras_mes1[[#This Row],[CUIT]],Lista_CUIT[#All],4,0)),"CUIT NO CARGADO") -> 0
B65: 44565 | C65: 1 | D65: 1 | E65: 27 | F65: 30716010313 | G65: =IFERROR(IF(compras_mes1[[#This Row],[CUIT]]="","-",VLOOKUP(compras_mes1[[#This Row],[CUIT]],Lista_CUIT[#All],2,0)),"CUIT NO CARGADO") -> H UNO 1469 S.A. | H65: 32000 | I65: =IF(compras_mes1[[#This Row],[NETO GRAVADO]]="","",compras_mes1[[#This Row],[NETO GRAVADO]]*0.21) -> 6720 | P65: =SUM(compras_mes1[[#This Row],[NETO GRAVADO]:[Otros / No Grav.]]) -> 38720 | Q65: =IFERROR(IF(compras_mes1[[#This Row],[CUIT]]="","-",VLOOKUP(compras_mes1[[#This Row],[CUIT]],Lista_CUIT[#All],3,0)),"CUIT NO CARGADO") -> Alquiler | R65: =IFERROR(IF(compras_mes1[[#This Row],[CUIT]]="","-",VLOOKUP(compras_mes1[[#This Row],[CUIT]],Lista_CUIT[#All],4,0)),"CUIT NO CARGADO") -> 0
B66: 44567 | C66: 1 | D66: 2 | E66: 145 | F66: 27309896063 | G66: =IFERROR(IF(compras_mes1[[#This Row],[CUIT]]="","-",VLOOKUP(compras_mes1[[#This Row],[CUIT]],Lista_CUIT[#All],2,0)),"CUIT NO CARGADO") -> BATTELLINI MARIA SOLEDAD | H66: 18000 | I66: =IF(compras_mes1[[#This Row],[NETO GRAVADO]]="","",compras_mes1[[#This Row],[NETO GRAVADO]]*0.21) -> 3780 | P66: =SUM(compras_mes1[[#This Row],[NETO GRAVADO]:[Otros / No Grav.]]) -> 21780 | Q66: =IFERROR(IF(compras_mes1[[#This Row],[CUIT]]="","-",VLOOKUP(compras_mes1[[#This Row],[CUIT]],Lista_CUIT[#All],3,0)),"CUIT NO CARGADO") -> Alquiler | R66: =IFERROR(IF(compras_mes1[[#This Row],[CUIT]]="","-",VLOOKUP(compras_mes1[[#This Row],[CUIT]],Lista_CUIT[#All],4,0)),"CUIT NO CARGADO") -> 0
B67: 44568 | C67: 1 | D67: 10 | E67: 41268 | F67: 30711069360 | G67: =IFERROR(IF(compras_mes1[[#This Row],[CUIT]]="","-",VLOOKUP(compras_mes1[[#This Row],[CUIT]],Lista_CUIT[#All],2,0)),"CUIT NO CARGADO") -> BIDCOM S.R.L. | H67: 694803.03 | K67: 74110.97 | N67: 41688.18 | P67: =SUM(compras_mes1[[#This Row],[NETO GRAVADO]:[Otros / No Grav.]]) -> 810602.18 | Q67: =IFERROR(IF(compras_mes1[[#This Row],[CUIT]]="","-",VLOOKUP(compras_mes1[[#This Row],[CUIT]],Lista_CUIT[#All],3,0)),"CUIT NO CARGADO") -> Equipos de Informatica | R67: =IFERROR(IF(compras_mes1[[#This Row],[CUIT]]="","-",VLOOKUP(compras_mes1[[#This Row],[CUIT]],Lista_CUIT[#All],4,0)),"CUIT NO CARGADO") -> 0
B68: 44564 | C68: 1 | D68: 5 | E68: 202 | F68: 30711651779 | G68: =IFERROR(IF(compras_mes1[[#This Row],[CUIT]]="","-",VLOOKUP(compras_mes1[[#This Row],[CUIT]],Lista_CUIT[#All],2,0)),"CUIT NO CARGADO") -> INFOSOL BUENOS AIRES S.R.L. | H68: 3305.79 | I68: =IF(compras_mes1[[#This Row],[NETO GRAVADO]]="","",compras_mes1[[#This Row],[NETO GRAVADO]]*0.21) -> 694.2159 | P68: =SUM(compras_mes1[[#This Row],[NETO GRAVADO]:[Otros / No Grav.]]) -> 4000.0059 | Q68: =IFERROR(IF(compras_mes1[[#This Row],[CUIT]]="","-",VLOOKUP(compras_mes1[[#This Row],[CUIT]],Lista_CUIT[#All],3,0)),"CUIT NO CARGADO") -> Equipos de Informatica | R68: =IFERROR(IF(compras_mes1[[#This Row],[CUIT]]="","-",VLOOKUP(compras_mes1[[#This Row],[CUIT]],Lista_CUIT[#All],4,0)),"CUIT NO CARGADO") -> 0
B69: 44592 | C69: 1 | D69: 2 | E69: 572 | F69: 30717264122 | G69: =IFERROR(IF(compras_mes1[[#This Row],[CUIT]]="","-",VLOOKUP(compras_mes1[[#This Row],[CUIT]],Lista_CUIT[#All],2,0)),"CUIT NO CARGADO") -> CAPOLOG S.R.L. | H69: 1156.2 | I69: =IF(compras_mes1[[#This Row],[NETO GRAVADO]]="","",compras_mes1[[#This Row],[NETO GRAVADO]]*0.21) -> 242.802 | P69: =SUM(compras_mes1[[#This Row],[NETO GRAVADO]:[Otros / No Grav.]]) -> 1399.002 | Q69: =IFERROR(IF(compras_mes1[[#This Row],[CUIT]]="","-",VLOOKUP(compras_mes1[[#This Row],[CUIT]],Lista_CUIT[#All],3,0)),"CUIT NO CARGADO") -> Flete-Logistica | R69: =IFERROR(IF(compras_mes1[[#This Row],[CUIT]]="","-",VLOOKUP(compras_mes1[[#This Row],[CUIT]],Lista_CUIT[#All],4,0)),"CUIT NO CARGADO") -> 0
B70: 44566 | C70: 1 | D70: 10 | E70: 753 | F70: 20261696828 | G70: =IFERROR(IF(compras_mes1[[#This Row],[CUIT]]="","-",VLOOKUP(compras_mes1[[#This Row],[CUIT]],Lista_CUIT[#All],2,0)),"CUIT NO CARGADO") -> GARAVAGNO JUAN MATIAS | H70: 15004.94 | I70: =IF(compras_mes1[[#This Row],[NETO GRAVADO]]="","",compras_mes1[[#This Row],[NETO GRAVADO]]*0.21) -> 3151.0374 | P70: =SUM(compras_mes1[[#This Row],[NETO GRAVADO]:[Otros / No Grav.]]) -> 18155.977 | Q70: =IFERROR(IF(compras_mes1[[#This Row],[CUIT]]="","-",VLOOKUP(compras_mes1[[#This Row],[CUIT]],Lista_CUIT[#All],3,0)),"CUIT NO CARGADO") -> Flete-Logistica | R70: =IFERROR(IF(compras_mes1[[#This Row],[CUIT]]="","-",VLOOKUP(compras_mes1[[#This Row],[CUIT]],Lista_CUIT[#All],4,0)),"CUIT NO CARGADO") -> BUENOS AIRES
B71: 44564 | C71: 1 | D71: 1 | E71: 15726 | F71: 20173025557 | G71: =IFERROR(IF(compras_mes1[[#This Row],[CUIT]]="","-",VLOOKUP(compras_mes1[[#This Row],[CUIT]],Lista_CUIT[#All],2,0)),"CUIT NO CARGADO") -> MARAUDA HECTOR | H71: 991.74 | I71: =IF(compras_mes1[[#This Row],[NETO GRAVADO]]="","",compras_mes1[[#This Row],[NETO GRAVADO]]*0.21) -> 208.2654 | P71: =SUM(compras_mes1[[#This Row],[NETO GRAVADO]:[Otros / No Grav.]]) -> 1200.0054 | Q71: =IFERROR(IF(compras_mes1[[#This Row],[CUIT]]="","-",VLOOKUP(compras_mes1[[#This Row],[CUIT]],Lista_CUIT[#All],3,0)),"CUIT NO CARGADO") -> Gastos Varios | R71: =IFERROR(IF(compras_mes1[[#This Row],[CUIT]]="","-",VLOOKUP(compras_mes1[[#This Row],[CUIT]],Lista_CUIT[#All],4,0)),"CUIT NO CARGADO") -> 0
B72: 44565 | C72: 1 | D72: 3 | E72: 386 | F72: 33716659769 | G72: =IFERROR(IF(compras_mes1[[#This Row],[CUIT]]="","-",VLOOKUP(compras_mes1[[#This Row],[CUIT]],Lista_CUIT[#All],2,0)),"CUIT NO CARGADO") -> OPTIMOOD COOLING | H72: 2663.35 | I72: 279.65 | P72: =SUM(compras_mes1[[#This Row],[NETO GRAVADO]:[Otros / No Grav.]]) -> 2943 | Q72: =IFERROR(IF(compras_mes1[[#This Row],[CUIT]]="","-",VLOOKUP(compras_mes1[[#This Row],[CUIT]],Lista_CUIT[#All],3,0)),"CUIT NO CARGADO") -> Gastos Varios | R72: =IFERROR(IF(compras_mes1[[#This Row],[CUIT]]="","-",VLOOKUP(compras_mes1[[#This Row],[CUIT]],Lista_CUIT[#All],4,0)),"CUIT NO CARGADO") -> CABA
B73: 44592 | C73: 1 | D73: 1 | E73: 2176 | F73: 20103906149 | G73: =IFERROR(IF(compras_mes1[[#This Row],[CUIT]]="","-",VLOOKUP(compras_mes1[[#This Row],[CUIT]],Lista_CUIT[#All],2,0)),"CUIT NO CARGADO") -> MC LEAN ROBERTO | H73: 45000 | I73: =IF(compras_mes1[[#This Row],[NETO GRAVADO]]="","",compras_mes1[[#This Row],[NETO GRAVADO]]*0.21) -> 9450 | P73: =SUM(compras_mes1[[#This Row],[NETO GRAVADO]:[Otros / No Grav.]]) -> 54450 | Q73: =IFERROR(IF(compras_mes1[[#This Row],[CUIT]]="","-",VLOOKUP(compras_mes1[[#This Row],[CUIT]],Lista_CUIT[#All],3,0)),"CUIT NO CARGADO") -> Honorarios Contables | R73: =IFERROR(IF(compras_mes1[[#This Row],[CUIT]]="","-",VLOOKUP(compras_mes1[[#This Row],[CUIT]],Lista_CUIT[#All],4,0)),"CUIT NO CARGADO") -> 0
B74: 44564 | C74: 1 | D74: 1 | E74: 2166 | F74: 20103906149 | G74: =IFERROR(IF(compras_mes1[[#This Row],[CUIT]]="","-",VLOOKUP(compras_mes1[[#This Row],[CUIT]],Lista_CUIT[#All],2,0)),"CUIT NO CARGADO") -> MC LEAN ROBERTO | H74: 29504.13 | I74: =IF(compras_mes1[[#This Row],[NETO GRAVADO]]="","",compras_mes1[[#This Row],[NETO GRAVADO]]*0.21) -> 6195.8673 | P74: =SUM(compras_mes1[[#This Row],[NETO GRAVADO]:[Otros / No Grav.]]) -> 35699.997 | Q74: =IFERROR(IF(compras_mes1[[#This Row],[CUIT]]="","-",VLOOKUP(compras_mes1[[#This Row],[CUIT]],Lista_CUIT[#All],3,0)),"CUIT NO CARGADO") -> Honorarios Contables | R74: =IFERROR(IF(compras_mes1[[#This Row],[CUIT]]="","-",VLOOKUP(compras_mes1[[#This Row],[CUIT]],Lista_CUIT[#All],4,0)),"CUIT NO CARGADO") -> 0
B75: 44567 | C75: 1 | D75: 9 | E75: 593 | F75: 30710446047 | G75: =IFERROR(IF(compras_mes1[[#This Row],[CUIT]]="","-",VLOOKUP(compras_mes1[[#This Row],[CUIT]],Lista_CUIT[#All],2,0)),"CUIT NO CARGADO") -> ENSAMBLE GRAFICO S.H. | H75: 189468 | I75: =IF(compras_mes1[[#This Row],[NETO GRAVADO]]="","",compras_mes1[[#This Row],[NETO GRAVADO]]*0.21) -> 39788.28 | P75: =SUM(compras_mes1[[#This Row],[NETO GRAVADO]:[Otros / No Grav.]]) -> 229256.28 | Q75: =IFERROR(IF(compras_mes1[[#This Row],[CUIT]]="","-",VLOOKUP(compras_mes1[[#This Row],[CUIT]],Lista_CUIT[#All],3,0)),"CUIT NO CARGADO") -> Mercaderia | R75: =IFERROR(IF(compras_mes1[[#This Row],[CUIT]]="","-",VLOOKUP(compras_mes1[[#This Row],[CUIT]],Lista_CUIT[#All],4,0)),"CUIT NO CARGADO") -> 0
B76: 44564 | C76: 1 | D76: 6 | E76: 1875 | F76: 30574603788 | G76: =IFERROR(IF(compras_mes1[[#This Row],[CUIT]]="","-",VLOOKUP(compras_mes1[[#This Row],[CUIT]],Lista_CUIT[#All],2,0)),"CUIT NO CARGADO") -> Codac SRL | H76: 197041 | I76: =IF(compras_mes1[[#This Row],[NETO GRAVADO]]="","",compras_mes1[[#This Row],[NETO GRAVADO]]*0.21) -> 41378.61 | P76: =SUM(compras_mes1[[#This Row],[NETO GRAVADO]:[Otros / No Grav.]]) -> 238419.61 | Q76: =IFERROR(IF(compras_mes1[[#This Row],[CUIT]]="","-",VLOOKUP(compras_mes1[[#This Row],[CUIT]],Lista_CUIT[#All],3,0)),"CUIT NO CARGADO") -> Mercaderia | R76: =IFERROR(IF(compras_mes1[[#This Row],[CUIT]]="","-",VLOOKUP(compras_mes1[[#This Row],[CUIT]],Lista_CUIT[#All],4,0)),"CUIT NO CARGADO") -> 0
B77: 44566 | C77: 1 | D77: 2 | E77: 2956 | F77: 30629863571 | G77: =IFERROR(IF(compras_mes1[[#This Row],[CUIT]]="","-",VLOOKUP(compras_mes1[[#This Row],[CUIT]],Lista_CUIT[#All],2,0)),"CUIT NO CARGADO") -> TECNIMAR S R L | H77: 113609.32 | I77: =IF(compras_mes1[[#This Row],[NETO GRAVADO]]="","",compras_mes1[[#This Row],[NETO GRAVADO]]*0.21) -> 23857.957 | P77: =SUM(compras_mes1[[#This Row],[NETO GRAVADO]:[Otros / No Grav.]]) -> 137467.28 | Q77: =IFERROR(IF(compras_mes1[[#This Row],[CUIT]]="","-",VLOOKUP(compras_mes1[[#This Row],[CUIT]],Lista_CUIT[#All],3,0)),"CUIT NO CARGADO") -> Mercaderia | R77: =IFERROR(IF(compras_mes1[[#This Row],[CUIT]]="","-",VLOOKUP(compras_mes1[[#This Row],[CUIT]],Lista_CUIT[#All],4,0)),"CUIT NO CARGADO") -> 0
B78: 44567 | C78: 1 | D78: 6 | E78: 1880 | F78: 30574603788 | G78: =IFERROR(IF(compras_mes1[[#This Row],[CUIT]]="","-",VLOOKUP(compras_mes1[[#This Row],[CUIT]],Lista_CUIT[#All],2,0)),"CUIT NO CARGADO") -> Codac SRL | H78: 374380 | I78: =IF(compras_mes1[[#This Row],[NETO GRAVADO]]="","",compras_mes1[[#This Row],[NETO GRAVADO]]*0.21) -> 78619.8 | P78: =SUM(compras_mes1[[#This Row],[NETO GRAVADO]:[Otros / No Grav.]]) -> 452999.8 | Q78: =IFERROR(IF(compras_mes1[[#This Row],[CUIT]]="","-",VLOOKUP(compras_mes1[[#This Row],[CUIT]],Lista_CUIT[#All],3,0)),"CUIT NO CARGADO") -> Mercaderia | R78: =IFERROR(IF(compras_mes1[[#This Row],[CUIT]]="","-",VLOOKUP(compras_mes1[[#This Row],[CUIT]],Lista_CUIT[#All],4,0)),"CUIT NO CARGADO") -> 0
B79: 44571 | C79: 1 | D79: 2 | E79: 22280 | F79: 30712121781 | G79: =IFERROR(IF(compras_mes1[[#This Row],[CUIT]]="","-",VLOOKUP(compras_mes1[[#This Row],[CUIT]],Lista_CUIT[#All],2,0)),"CUIT NO CARGADO") -> SUTURA S.R.L. | H79: 2637.2 | I79: =IF(compras_mes1[[#This Row],[NETO GRAVADO]]="","",compras_mes1[[#This Row],[NETO GRAVADO]]*0.21) -> 553.812 | P79: =SUM(compras_mes1[[#This Row],[NETO GRAVADO]:[Otros / No Grav.]]) -> 3191.012 | Q79: =IFERROR(IF(compras_mes1[[#This Row],[CUIT]]="","-",VLOOKUP(compras_mes1[[#This Row],[CUIT]],Lista_CUIT[#All],3,0)),"CUIT NO CARGADO") -> Mercaderia | R79: =IFERROR(IF(compras_mes1[[#This Row],[CUIT]]="","-",VLOOKUP(compras_mes1[[#This Row],[CUIT]],Lista_CUIT[#All],4,0)),"CUIT NO CARGADO") -> 0
B80: 44571 | C80: 1 | D80: 3 | E80: 19463 | F80: 30712121781 | G80: =IFERROR(IF(compras_mes1[[#This Row],[CUIT]]="","-",VLOOKUP(compras_mes1[[#This Row],[CUIT]],Lista_CUIT[#All],2,0)),"CUIT NO CARGADO") -> SUTURA S.R.L. | H80: 72713.5 | I80: =IF(compras_mes1[[#This Row],[NETO GRAVADO]]="","",compras_mes1[[#This Row],[NETO GRAVADO]]*0.21) -> 15269.835 | P80: =SUM(compras_mes1[[#This Row],[NETO GRAVADO]:[Otros / No Grav.]]) -> 87983.335 | Q80: =IFERROR(IF(compras_mes1[[#This Row],[CUIT]]="","-",VLOOKUP(compras_mes1[[#This Row],[CUIT]],Lista_CUIT[#All],3,0)),"CUIT NO CARGADO") -> Mercaderia | R80: =IFERROR(IF(compras_mes1[[#This Row],[CUIT]]="","-",VLOOKUP(compras_mes1[[#This Row],[CUIT]],Lista_CUIT[#All],4,0)),"CUIT NO CARGADO") -> 0
B81: 44573 | C81: 1 | D81: 2 | E81: 2965 | F81: 30629863571 | G81: =IFERROR(IF(compras_mes1[[#This Row],[CUIT]]="","-",VLOOKUP(compras_mes1[[#This Row],[CUIT]],Lista_CUIT[#All],2,0)),"CUIT NO CARGADO") -> TECNIMAR S R L | H81: 183080.78 | I81: =IF(compras_mes1[[#This Row],[NETO GRAVADO]]="","",compras_mes1[[#This Row],[NETO GRAVADO]]*0.21) -> 38446.964 | P81: =SUM(compras_mes1[[#This Row],[NETO GRAVADO]:[Otros / No Grav.]]) -> 221527.74 | Q81: =IFERROR(IF(compras_mes1[[#This Row],[CUIT]]="","-",VLOOKUP(compras_mes1[[#This Row],[CUIT]],Lista_CUIT[#All],3,0)),"CUIT NO CARGADO") -> Mercaderia | R81: =IFERROR(IF(compras_mes1[[#This Row],[CUIT]]="","-",VLOOKUP(compras_mes1[[#This Row],[CUIT]],Lista_CUIT[#All],4,0)),"CUIT NO CARGADO") -> 0
B82: 44573 | C82: 1 | D82: 6 | E82: 1889 | F82: 30574603788 | G82: =IFERROR(IF(compras_mes1[[#This Row],[CUIT]]="","-",VLOOKUP(compras_mes1[[#This Row],[CUIT]],Lista_CUIT[#All],2,0)),"CUIT NO CARGADO") -> Codac SRL | H82: 487027 | I82: =IF(compras_mes1[[#This Row],[NETO GRAVADO]]="","",compras_mes1[[#This Row],[NETO GRAVADO]]*0.21) -> 102275.67 | P82: =SUM(compras_mes1[[#This Row],[NETO GRAVADO]:[Otros / No Grav.]]) -> 589302.67 | Q82: =IFERROR(IF(compras_mes1[[#This Row],[CUIT]]="","-",VLOOKUP(compras_mes1[[#This Row],[CUIT]],Lista_CUIT[#All],3,0)),"CUIT NO CARGADO") -> Mercaderia | R82: =IFERROR(IF(compras_mes1[[#This Row],[CUIT]]="","-",VLOOKUP(compras_mes1[[#This Row],[CUIT]],Lista_CUIT[#All],4,0)),"CUIT NO CARGADO") -> 0
B83: 44565 | C83: 1 | D83: 629 | E83: 2905383 | F83: 30663498513 | G83: =IFERROR(IF(compras_mes1[[#This Row],[CUIT]]="","-",VLOOKUP(compras_mes1[[#This Row],[CUIT]],Lista_CUIT[#All],2,0)),"CUIT NO CARGADO") -> GRUPO CONCES. DEL OESTE SA | H83: 939.83 | I83: =IF(compras_mes1[[#This Row],[NETO GRAVADO]]="","",compras_mes1[[#This Row],[NETO GRAVADO]]*0.21) -> 197.3643 | P83: =SUM(compras_mes1[[#This Row],[NETO GRAVADO]:[Otros / No Grav.]]) -> 1137.1943 | Q83: =IFERROR(IF(compras_mes1[[#This Row],[CUIT]]="","-",VLOOKUP(compras_mes1[[#This Row],[CUIT]],Lista_CUIT[#All],3,0)),"CUIT NO CARGADO") -> Peaje | R83: =IFERROR(IF(compras_mes1[[#This Row],[CUIT]]="","-",VLOOKUP(compras_mes1[[#This Row],[CUIT]],Lista_CUIT[#All],4,0)),"CUIT NO CARGADO") -> 0
B84: 44565 | C84: 1 | D84: 711 | E84: 2466697 | F84: 30677237119 | G84: =IFERROR(IF(compras_mes1[[#This Row],[CUIT]]="","-",VLOOKUP(compras_mes1[[#This Row],[CUIT]],Lista_CUIT[#All],2,0)),"CUIT NO CARGADO") -> AUTOPISTAS DEL SOL S A | H84: 1336.1 | I84: =IF(compras_mes1[[#This Row],[NETO GRAVADO]]="","",compras_mes1[[#This Row],[NETO GRAVADO]]*0.21) -> 280.581 | P84: =SUM(compras_mes1[[#This Row],[NETO GRAVADO]:[Otros / No Grav.]]) -> 1616.681 | Q84: =IFERROR(IF(compras_mes1[[#This Row],[CUIT]]="","-",VLOOKUP(compras_mes1[[#This Row],[CUIT]],Lista_CUIT[#All],3,0)),"CUIT NO CARGADO") -> Peaje | R84: =IFERROR(IF(compras_mes1[[#This Row],[CUIT]]="","-",VLOOKUP(compras_mes1[[#This Row],[CUIT]],Lista_CUIT[#All],4,0)),"CUIT NO CARGADO") -> 0
B85: 44565 | C85: 1 | D85: 5014 | E85: 175575 | F85: 30574876474 | G85: =IFERROR(IF(compras_mes1[[#This Row],[CUIT]]="","-",VLOOKUP(compras_mes1[[#This Row],[CUIT]],Lista_CUIT[#All],2,0)),"CUIT NO CARGADO") -> AUTOPISTAS URBANAS S A | H85: 7424.92 | I85: =IF(compras_mes1[[#This Row],[NETO GRAVADO]]="","",compras_mes1[[#This Row],[NETO GRAVADO]]*0.21) -> 1559.2332 | L85: 222.73 | N85: 741.77 | P85: =SUM(compras_mes1[[#This Row],[NETO GRAVADO]:[Otros / No Grav.]]) -> 9948.6532 | Q85: =IFERROR(IF(compras_mes1[[#This Row],[CUIT]]="","-",VLOOKUP(compras_mes1[[#This Row],[CUIT]],Lista_CUIT[#All],3,0)),"CUIT NO CARGADO") -> Peaje | R85: =IFERROR(IF(compras_mes1[[#This Row],[CUIT]]="","-",VLOOKUP(compras_mes1[[#This Row],[CUIT]],Lista_CUIT[#All],4,0)),"CUIT NO CARGADO") -> 0
B86: 44573 | C86: 1 | D86: 50 | E86: 2422371 | F86: 30714112836 | G86: =IFERROR(IF(compras_mes1[[#This Row],[CUIT]]="","-",VLOOKUP(compras_mes1[[#This Row],[CUIT]],Lista_CUIT[#All],2,0)),"CUIT NO CARGADO") -> AUTOPISTAS DE BS AS | H86: 885.12 | I86: =IF(compras_mes1[[#This Row],[NETO GRAVADO]]="","",compras_mes1[[#This Row],[NETO GRAVADO]]*0.21) -> 185.8752 | L86: 26.56 | P86: =SUM(compras_mes1[[#This Row],[NETO GRAVADO]:[Otros / No Grav.]]) -> 1097.5552 | Q86: =IFERROR(IF(compras_mes1[[#This Row],[CUIT]]="","-",VLOOKUP(compras_mes1[[#This Row],[CUIT]],Lista_CUIT[#All],3,0)),"CUIT NO CARGADO") -> Peaje | R86: =IFERROR(IF(compras_mes1[[#This Row],[CUIT]]="","-",VLOOKUP(compras_mes1[[#This Row],[CUIT]],Lista_CUIT[#All],4,0)),"CUIT NO CARGADO") -> 0
B87: 44537 | C87: 1 | D87: 695 | E87: 507 | F87: 30638485733 | G87: =IFERROR(IF(compras_mes1[[#This Row],[CUIT]]="","-",VLOOKUP(compras_mes1[[#This Row],[CUIT]],Lista_CUIT[#All],2,0)),"CUIT NO CARGADO") -> DABRA S.A. | H87: 27227.26 | I87: =IF(compras_mes1[[#This Row],[NETO GRAVADO]]="","",compras_mes1[[#This Row],[NETO GRAVADO]]*0.21) -> 5717.7246 | P87: =SUM(compras_mes1[[#This Row],[NETO GRAVADO]:[Otros / No Grav.]]) -> 32944.985 | Q87: =IFERROR(IF(compras_mes1[[#This Row],[CUIT]]="","-",VLOOKUP(compras_mes1[[#This Row],[CUIT]],Lista_CUIT[#All],3,0)),"CUIT NO CARGADO") -> Ropa de Trabajo | R87: =IFERROR(IF(compras_mes1[[#This Row],[CUIT]]="","-",VLOOKUP(compras_mes1[[#This Row],[CUIT]],Lista_CUIT[#All],4,0)),"CUIT NO CARGADO") -> 0
B88: 44564 | C88: 1 | D88: 943 | E88: 86491 | F88: 30639453975 | G88: =IFERROR(IF(compras_mes1[[#This Row],[CUIT]]="","-",VLOOKUP(compras_mes1[[#This Row],[CUIT]],Lista_CUIT[#All],2,0)),"CUIT NO CARGADO") -> TELEFONICA DE ARG S.A. | H88: 8089.46 | J88: 2184.15 | P88: =SUM(compras_mes1[[#This Row],[NETO GRAVADO]:[Otros / No Grav.]]) -> 10273.61 | Q88: =IFERROR(IF(compras_mes1[[#This Row],[CUIT]]="","-",VLOOKUP(compras_mes1[[#This Row],[CUIT]],Lista_CUIT[#All],3,0)),"CUIT NO CARGADO") -> Servicios Gas, Luz, etc. | R88: =IFERROR(IF(compras_mes1[[#This Row],[CUIT]]="","-",VLOOKUP(compras_mes1[[#This Row],[CUIT]],Lista_CUIT[#All],4,0)),"CUIT NO CARGADO") -> 0
B89: 44565 | C89: 1 | D89: 63 | E89: 1775198 | F89: 30640897267 | G89: =IFERROR(IF(compras_mes1[[#This Row],[CUIT]]="","-",VLOOKUP(compras_mes1[[#This Row],[CUIT]],Lista_CUIT[#All],2,0)),"CUIT NO CARGADO") -> TELECENTRO S.A. | H89: 4425.45 | I89: =IF(compras_mes1[[#This Row],[NETO GRAVADO]]="","",compras_mes1[[#This Row],[NETO GRAVADO]]*0.21) -> 929.3445 | L89: 132.76 | N89: 265.53 | P89: =SUM(compras_mes1[[#This Row],[NETO GRAVADO]:[Otros / No Grav.]]) -> 5753.0845 | Q89: =IFERROR(IF(compras_mes1[[#This Row],[CUIT]]="","-",VLOOKUP(compras_mes1[[#This Row],[CUIT]],Lista_CUIT[#All],3,0)),"CUIT NO CARGADO") -> Servicios Gas, Luz, etc. | R89: =IFERROR(IF(compras_mes1[[#This Row],[CUIT]]="","-",VLOOKUP(compras_mes1[[#This Row],[CUIT]],Lista_CUIT[#All],4,0)),"CUIT NO CARGADO") -> 0
B90: 44565 | C90: 1 | D90: 63 | E90: 1775346 | F90: 30640897267 | G90: =IFERROR(IF(compras_mes1[[#This Row],[CUIT]]="","-",VLOOKUP(compras_mes1[[#This Row],[CUIT]],Lista_CUIT[#All],2,0)),"CUIT NO CARGADO") -> TELECENTRO S.A. | H90: 4180 | I90: =IF(compras_mes1[[#This Row],[NETO GRAVADO]]="","",compras_mes1[[#This Row],[NETO GRAVADO]]*0.21) -> 877.8 | L90: 125.4 | N90: 250.8 | P90: =SUM(compras_mes1[[#This Row],[NETO GRAVADO]:[Otros / No Grav.]]) -> 5434 | Q90: =IFERROR(IF(compras_mes1[[#This Row],[CUIT]]="","-",VLOOKUP(compras_mes1[[#This Row],[CUIT]],Lista_CUIT[#All],3,0)),"CUIT NO CARGADO") -> Servicios Gas, Luz, etc. | R90: =IFERROR(IF(compras_mes1[[#This Row],[CUIT]]="","-",VLOOKUP(compras_mes1[[#This Row],[CUIT]],Lista_CUIT[#All],4,0)),"CUIT NO CARGADO") -> 0
B91: 44565 | C91: 1 | D91: 63 | E91: 1775791 | F91: 30640897267 | G91: =IFERROR(IF(compras_mes1[[#This Row],[CUIT]]="","-",VLOOKUP(compras_mes1[[#This Row],[CUIT]],Lista_CUIT[#All],2,0)),"CUIT NO CARGADO") -> TELECENTRO S.A. | H91: 4425.45 | I91: =IF(compras_mes1[[#This Row],[NETO GRAVADO]]="","",compras_mes1[[#This Row],[NETO GRAVADO]]*0.21) -> 929.3445 | L91: 132.76 | N91: 265.53 | P91: =SUM(compras_mes1[[#This Row],[NETO GRAVADO]:[Otros / No Grav.]]) -> 5753.0845 | Q91: =IFERROR(IF(compras_mes1[[#This Row],[CUIT]]="","-",VLOOKUP(compras_mes1[[#This Row],[CUIT]],Lista_CUIT[#All],3,0)),"CUIT NO CARGADO") -> Servicios Gas, Luz, etc. | R91: =IFERROR(IF(compras_mes1[[#This Row],[CUIT]]="","-",VLOOKUP(compras_mes1[[#This Row],[CUIT]],Lista_CUIT[#All],4,0)),"CUIT NO CARGADO") -> 0
B92: 44567 | C92: 1 | D92: 2 | E92: 28558 | F92: 33714232199 | G92: =IFERROR(IF(compras_mes1[[#This Row],[CUIT]]="","-",VLOOKUP(compras_mes1[[#This Row],[CUIT]],Lista_CUIT[#All],2,0)),"CUIT NO CARGADO") -> NUAGE SYSTEMS S.A | H92: 15876 | I92: =IF(compras_mes1[[#This Row],[NETO GRAVADO]]="","",compras_mes1[[#This Row],[NETO GRAVADO]]*0.21) -> 3333.96 | P92: =SUM(compras_mes1[[#This Row],[NETO GRAVADO]:[Otros / No Grav.]]) -> 19209.96 | Q92: =IFERROR(IF(compras_mes1[[#This Row],[CUIT]]="","-",VLOOKUP(compras_mes1[[#This Row],[CUIT]],Lista_CUIT[#All],3,0)),"CUIT NO CARGADO") -> Servicios Informatica | R92: =IFERROR(IF(compras_mes1[[#This Row],[CUIT]]="","-",VLOOKUP(compras_mes1[[#This Row],[CUIT]],Lista_CUIT[#All],4,0)),"CUIT NO CARGADO") -> 0
B93: Total | H93: =SUBTOTAL(109,compras_mes1[NETO GRAVADO]) -> 4893030.5 | I93: =SUBTOTAL(109,compras_mes1[IVA 21 %]) -> 811246.93 | J93: =SUBTOTAL(109,compras_mes1[IVA 27%]) -> 2184.15 | K93: =SUBTOTAL(109,compras_mes1[IVA 10,5%]) -> 108178.49 | L93: =SUBTOTAL(109,compras_mes1[PERC. IVA]) -> 4854.55 | M93: =SUBTOTAL(109,compras_mes1[PERC IIBB BS AS]) -> 0 | N93: =SUBTOTAL(109,compras_mes1[PERC. IIBB CABA]) -> 72450.39 | O93: =SUBTOTAL(109,compras_mes1[Otros / No Grav.]) -> 32010.76 | P93: =SUBTOTAL(109,compras_mes1[TOTAL]) -> 5923955.7
D98: LIQUIDACION EXTRACTOS BANCARIOS-TARJETAS
D99: FECHA | E99: NRO CPTE | F99: BANCO | G99: NETO | H99: IVA 21% | I99: IVA 10,5% | J99: RET IIBB CABA | K99: PERC IVA | L99: PERC IIBB | M99: No grav. | N99: RET. GAN
D100: 44591 | E100: 2022 | F100: BBVA FRANCES | G100: 8426 | H100: 1769.46 | J100: 33866.28 | K100: 81.9 | L100: 68231.96
D101: 44591 | E101: 2022 | F101: BANCO GALICIA | G101: 2826 | H101: 593.46 | K101: 84.78 | L101: 169.56 | M101: 1890.1 | N101: 930.94
D102: 44591 | E102: 2022 | F102: BBVA - VISA | G102: 355.37 | H102: 74.63 | M102: 37691.84 | N102: 45700.67
D103: 44591 | E103: 2022 | F103: BBVA - MAESTRO | G103: 221.97 | H103: 46.61 | J103: 1238.58
D104: 44591 | E104: 439853 | F104: BANCO GALICIA - VISA | G104: 256 | H104: 53.76 | M104: 447.03
D105: 44591 | E105: 8806134 | F105: BBVA - VISA | G105: 5495 | H105: 1153.95 | K105: 164.85
D106: 44591 | E106: 95492939 | F106: BBVA - CABAL | G106: 174 | H106: 36.55 | K106: 141.26 | L106: 854.75
D107: 44591 | E107: 12022 | F107: BBVA - MASTERCARD | G107: 54685.12 | H107: 8694.05 | K107: 7703.71 | L107: 80694.33 | N107: 2275.94
D108: 44563 | E108: 2325960 | F108: BBVA FRANCES | G108: 0 | M108: 3602.14
D109: 44563 | E109: 2325961 | F109: BBVA FRANCES | G109: 0 | M109: 3600.37
D110: 44563 | E110: 2325962 | F110: BBVA FRANCES | G110: 0 | M110: 8265.14
...

Sheet Feb-22
B1: LIBRO IVA COMPRAS | G1: ='Ene-22'!G1:M1 -> EUROARGENTINA | N1: =EDATE('Ene-22'!N1,1) -> 44593
B3: TOTAL COMPRAS | G3: TOTAL CREDITO FISCAL | J3: TOTAL VENTAS NETAS | M3: TOTAL DEBITO FISCAL | P3: RESULTADO
B4: =SUM(compras_mes2[[#Totals],[NETO GRAVADO]])+extracto_banco_mes2[[#Totals],[NETO]] -> 4108673.2 | G4: =compras_mes2[[#Totals],[IVA 21 %]]+compras_mes2[[#Totals],[IVA 27%]]+compras_mes2[[#Totals],[IVA 10,5%]]+extracto_banco_mes2[[#Totals],[IVA 21%]]+extracto_banco_mes2[[#Totals],[IVA 10,5%]] -> 814677.59 | J4: =venta_a_mes2[[#Totals],[IMPORTE NETO]]+ventas_b_mes2[[#Totals],[IMPORTE NETO]] -> 0 | M4: =venta_a_mes2[[#Totals],[IVA 21%]]+venta_a_mes2[[#Totals],[IVA 10,5%]]+ventas_b_mes2[[#Totals],[IVA 21%]]+ventas_b_mes2[[#Totals],[IVA 10,5%]] -> 0 | P4: =G4-M4 -> 814677.59
B8: FECHA | C8: TIPO | D8: PTO VTA | E8: NRO. CPTE | F8: CUIT | G8: RAZON SOCIAL | H8: NETO GRAVADO | I8: IVA 21 % | J8: IVA 27% | K8: IVA 10,5% | L8: PERC. IVA | M8: PERC IIBB BS AS | N8: PERC. IIBB CABA | O8: Otros / No Grav. | P8: TOTAL | Q8: Tipo de Gasto | R8: Provincia
B9: 44593 | C9: 1 | D9: 1 | E9: 218 | F9: 20131206144 | G9: =IFERROR(IF(compras_mes2[[#This Row],[CUIT]]="","-",VLOOKUP(compras_mes2[[#This Row],[CUIT]],Lista_CUIT[#All],2,0)),"CUIT NO CARGADO") -> CHAMORRO MANUEL | H9: 18000 | I9: =IF(compras_mes2[[#This Row],[NETO GRAVADO]]="","",compras_mes2[[#This Row],[NETO GRAVADO]]*0.21) -> 3780 | P9: =SUM(compras_mes2[[#This Row],[NETO GRAVADO]:[Otros / No Grav.]]) -> 21780 | Q9: =IFERROR(IF(compras_mes2[[#This Row],[CUIT]]="","-",VLOOKUP(compras_mes2[[#This Row],[CUIT]],Lista_CUIT[#All],3,0)),"CUIT NO CARGADO") -> Alquiler | R9: =IFERROR(IF(compras_mes2[[#This Row],[CUIT]]="","-",VLOOKUP(compras_mes2[[#This Row],[CUIT]],Lista_CUIT[#All],4,0)),"CUIT NO CARGADO") -> 0
B10: 44595 | C10: 1 | D10: 1 | E10: 29 | F10: 30716010313 | G10: =IFERROR(IF(compras_mes2[[#This Row],[CUIT]]="","-",VLOOKUP(compras_mes2[[#This Row],[CUIT]],Lista_CUIT[#All],2,0)),"CUIT NO CARGADO") -> H UNO 1469 S.A. | H10: 32000 | I10: =IF(compras_mes2[[#This Row],[NETO GRAVADO]]="","",compras_mes2[[#This Row],[NETO GRAVADO]]*0.21) -> 6720 | P10: =SUM(compras_mes2[[#This Row],[NETO GRAVADO]:[Otros / No Grav.]]) -> 38720 | Q10: =IFERROR(IF(compras_mes2[[#This Row],[CUIT]]="","-",VLOOKUP(compras_mes2[[#This Row],[CUIT]],Lista_CUIT[#All],3,0)),"CUIT NO CARGADO") -> Alquiler | R10: =IFERROR(IF(compras_mes2[[#This Row],[CUIT]]="","-",VLOOKUP(compras_mes2[[#This Row],[CUIT]],Lista_CUIT[#All],4,0)),"CUIT NO CARGADO") -> 0
B11: 44594 | C11: 1 | D11: 8 | E11: 989 | F11: 30712212817 | G11: =IFERROR(IF(compras_mes2[[#This Row],[CUIT]]="","-",VLOOKUP(compras_mes2[[#This Row],[CUIT]],Lista_CUIT[#All],2,0)),"CUIT NO CARGADO") -> LIQUID GAS S.A. | H11: 914.05 | I11: =IF(compras_mes2[[#This Row],[NETO GRAVADO]]="","",compras_mes2[[#This Row],[NETO GRAVADO]]*0.21) -> 191.9505 | P11: =SUM(compras_mes2[[#This Row],[NETO GRAVADO]:[Otros / No Grav.]]) -> 1106.0005 | Q11: =IFERROR(IF(compras_mes2[[#This Row],[CUIT]]="","-",VLOOKUP(compras_mes2[[#This Row],[CUIT]],Lista_CUIT[#All],3,0)),"CUIT NO CARGADO") -> Combustible | R11: =IFERROR(IF(compras_mes2[[#This Row],[CUIT]]="","-",VLOOKUP(compras_mes2[[#This Row],[CUIT]],Lista_CUIT[#All],4,0)),"CUIT NO CARGADO") -> BS AS
B12: 44604 | C12: 1 | D12: 4 | E12: 2964 | F12: 30707949550 | G12: =IFERROR(IF(compras_mes2[[#This Row],[CUIT]]="","-",VLOOKUP(compras_mes2[[#This Row],[CUIT]],Lista_CUIT[#All],2,0)),"CUIT NO CARGADO") -> LNG GAS S.A. | H12: 1283.75 | I12: =IF(compras_mes2[[#This Row],[NETO GRAVADO]]="","",compras_mes2[[#This Row],[NETO GRAVADO]]*0.21) -> 269.5875 | O12: 17.77 | P12: =SUM(compras_mes2[[#This Row],[NETO GRAVADO]:[Otros / No Grav.]]) -> 1571.1075 | Q12: =IFERROR(IF(compras_mes2[[#This Row],[CUIT]]="","-",VLOOKUP(compras_mes2[[#This Row],[CUIT]],Lista_CUIT[#All],3,0)),"CUIT NO CARGADO") -> Combustible | R12: =IFERROR(IF(compras_mes2[[#This Row],[CUIT]]="","-",VLOOKUP(compras_mes2[[#This Row],[CUIT]],Lista_CUIT[#All],4,0)),"CUIT NO CARGADO") -> BS AS
B13: 44608 | C13: 1 | D13: 6866 | E13: 2198 | F13: 30678774495 | G13: =IFERROR(IF(compras_mes2[[#This Row],[CUIT]]="","-",VLOOKUP(compras_mes2[[#This Row],[CUIT]],Lista_CUIT[#All],2,0)),"CUIT NO CARGADO") -> OPER. DE EST. DE SERV. SA | H13: 1611.53 | I13: =IF(compras_mes2[[#This Row],[NETO GRAVADO]]="","",compras_mes2[[#This Row],[NETO GRAVADO]]*0.21) -> 338.4213 | O13: 428.06 | P13: =SUM(compras_mes2[[#This Row],[NETO GRAVADO]:[Otros / No Grav.]]) -> 2378.0113 | Q13: =IFERROR(IF(compras_mes2[[#This Row],[CUIT]]="","-",VLOOKUP(compras_mes2[[#This Row],[CUIT]],Lista_CUIT[#All],3,0)),"CUIT NO CARGADO") -> Combustible | R13: =IFERROR(IF(compras_mes2[[#This Row],[CUIT]]="","-",VLOOKUP(compras_mes2[[#This Row],[CUIT]],Lista_CUIT[#All],4,0)),"CUIT NO CARGADO") -> 0
B14: 44611 | C14: 1 | D14: 7 | E14: 56262 | F14: 30696131003 | G14: =IFERROR(IF(compras_mes2[[#This Row],[CUIT]]="","-",VLOOKUP(compras_mes2[[#This Row],[CUIT]],Lista_CUIT[#All],2,0)),"CUIT NO CARGADO") -> PETROLFE S.A. | H14: 30608.04 | I14: =IF(compras_mes2[[#This Row],[NETO GRAVADO]]="","",compras_mes2[[#This Row],[NETO GRAVADO]]*0.21) -> 6427.6884 | O14: 9263.67 | P14: =SUM(compras_mes2[[#This Row],[NETO GRAVADO]:[Otros / No Grav.]]) -> 46299.398 | Q14: =IFERROR(IF(compras_mes2[[#This Row],[CUIT]]="","-",VLOOKUP(compras_mes2[[#This Row],[CUIT]],Lista_CUIT[#All],3,0)),"CUIT NO CARGADO") -> Combustible | R14: =IFERROR(IF(compras_mes2[[#This Row],[CUIT]]="","-",VLOOKUP(compras_mes2[[#This Row],[CUIT]],Lista_CUIT[#All],4,0)),"CUIT NO CARGADO") -> 0
B15: 44615 | C15: 1 | D15: 7 | E15: 66786 | F15: 30568586391 | G15: =IFERROR(IF(compras_mes2[[#This Row],[CUIT]]="","-",VLOOKUP(compras_mes2[[#This Row],[CUIT]],Lista_CUIT[#All],2,0)),"CUIT NO CARGADO") -> ESTACION DE SERVICIO AXION | H15: 1857.6 | I15: =IF(compras_mes2[[#This Row],[NETO GRAVADO]]="","",compras_mes2[[#This Row],[NETO GRAVADO]]*0.21) -> 390.096 | O15: 25.26 | P15: =SUM(compras_mes2[[#This Row],[NETO GRAVADO]:[Otros / No Grav.]]) -> 2272.956 | Q15: =IFERROR(IF(compras_mes2[[#This Row],[CUIT]]="","-",VLOOKUP(compras_mes2[[#This Row],[CUIT]],Lista_CUIT[#All],3,0)),"CUIT NO CARGADO") -> Combustible | R15: =IFERROR(IF(compras_mes2[[#This Row],[CUIT]]="","-",VLOOKUP(compras_mes2[[#This Row],[CUIT]],Lista_CUIT[#All],4,0)),"CUIT NO CARGADO") -> 0
B16: 44616 | C16: 1 | D16: 20 | E16: 2039 | F16: 30515800219 | G16: =IFERROR(IF(compras_mes2[[#This Row],[CUIT]]="","-",VLOOKUP(compras_mes2[[#This Row],[CUIT]],Lista_CUIT[#All],2,0)),"CUIT NO CARGADO") -> INCAT SRL | H16: 9118.67 | I16: =IF(compras_mes2[[#This Row],[NETO GRAVADO]]="","",compras_mes2[[#This Row],[NETO GRAVADO]]*0.21) -> 1914.9207 | O16: 2708.17 | P16: =SUM(compras_mes2[[#This Row],[NETO GRAVADO]:[Otros / No Grav.]]) -> 13741.761 | Q16: =IFERROR(IF(compras_mes2[[#This Row],[CUIT]]="","-",VLOOKUP(compras_mes2[[#This Row],[CUIT]],Lista_CUIT[#All],3,0)),"CUIT NO CARGADO") -> Combustible | R16: =IFERROR(IF(compras_mes2[[#This Row],[CUIT]]="","-",VLOOKUP(compras_mes2[[#This Row],[CUIT]],Lista_CUIT[#All],4,0)),"CUIT NO CARGADO") -> 0
B17: 44618 | C17: 1 | D17: 5140 | E17: 443 | F17: 30695542476 | G17: =IFERROR(IF(compras_mes2[[#This Row],[CUIT]]="","-",VLOOKUP(compras_mes2[[#This Row],[CUIT]],Lista_CUIT[#All],2,0)),"CUIT NO CARGADO") -> PAN AMERICAN ENERGY SL S.AR | H17: 867.96 | I17: =IF(compras_mes2[[#This Row],[NETO GRAVADO]]="","",compras_mes2[[#This Row],[NETO GRAVADO]]*0.21) -> 182.2716 | O17: 92.76 | P17: =SUM(compras_mes2[[#This Row],[NETO GRAVADO]:[Otros / No Grav.]]) -> 1142.9916 | Q17: =IFERROR(IF(compras_mes2[[#This Row],[CUIT]]="","-",VLOOKUP(compras_mes2[[#This Row],[CUIT]],Lista_CUIT[#All],3,0)),"CUIT NO CARGADO") -> Combustible | R17: =IFERROR(IF(compras_mes2[[#This Row],[CUIT]]="","-",VLOOKUP(compras_mes2[[#This Row],[CUIT]],Lista_CUIT[#All],4,0)),"CUIT NO CARGADO") -> 0
B18: 44618 | C18: 1 | D18: 6 | E18: 1473 | F18: 20134664518 | G18: =IFERROR(IF(compras_mes2[[#This Row],[CUIT]]="","-",VLOOKUP(compras_mes2[[#This Row],[CUIT]],Lista_CUIT[#All],2,0)),"CUIT NO CARGADO") -> HOKAMA SERGIO ENRIQUE | H18: 8666.89 | I18: =IF(compras_mes2[[#This Row],[NETO GRAVADO]]="","",compras_mes2[[#This Row],[NETO GRAVADO]]*0.21) -> 1820.0469 | P18: =SUM(compras_mes2[[#This Row],[NETO GRAVADO]:[Otros / No Grav.]]) -> 10486.937 | Q18: =IFERROR(IF(compras_mes2[[#This Row],[CUIT]]="","-",VLOOKUP(compras_mes2[[#This Row],[CUIT]],Lista_CUIT[#All],3,0)),"CUIT NO CARGADO") -> Comida-Limpieza | R18: =IFERROR(IF(compras_mes2[[#This Row],[CUIT]]="","-",VLOOKUP(compras_mes2[[#This Row],[CUIT]],Lista_CUIT[#All],4,0)),"CUIT NO CARGADO") -> 0
B19: 44606 | C19: 1 | D19: 10 | E19: 45567 | F19: 30711069360 | G19: =IFERROR(IF(compras_mes2[[#This Row],[CUIT]]="","-",VLOOKUP(compras_mes2[[#This Row],[CUIT]],Lista_CUIT[#All],2,0)),"CUIT NO CARGADO") -> BIDCOM S.R.L. | H19: 162226.24 | K19: 17033.76 | N19: 9733.57 | P19: =SUM(compras_mes2[[#This Row],[NETO GRAVADO]:[Otros / No Grav.]]) -> 188993.57 | Q19: =IFERROR(IF(compras_mes2[[#This Row],[CUIT]]="","-",VLOOKUP(compras_mes2[[#This Row],[CUIT]],Lista_CUIT[#All],3,0)),"CUIT NO CARGADO") -> Equipos de Informatica | R19: =IFERROR(IF(compras_mes2[[#This Row],[CUIT]]="","-",VLOOKUP(compras_mes2[[#This Row],[CUIT]],Lista_CUIT[#All],4,0)),"CUIT NO CARGADO") -> 0
B20: 44617 | C20: 1 | D20: 10 | E20: 46833 | F20: 30711069360 | G20: =IFERROR(IF(compras_mes2[[#This Row],[CUIT]]="","-",VLOOKUP(compras_mes2[[#This Row],[CUIT]],Lista_CUIT[#All],2,0)),"CUIT NO CARGADO") -> BIDCOM S.R.L. | H20: 162226.24 | K20: 17033.76 | N20: 9733.57 | P20: =SUM(compras_mes2[[#This Row],[NETO GRAVADO]:[Otros / No Grav.]]) -> 188993.57 | Q20: =IFERROR(IF(compras_mes2[[#This Row],[CUIT]]="","-",VLOOKUP(compras_mes2[[#This Row],[CUIT]],Lista_CUIT[#All],3,0)),"CUIT NO CARGADO") -> Equipos de Informatica | R20: =IFERROR(IF(compras_mes2[[#This Row],[CUIT]]="","-",VLOOKUP(compras_mes2[[#This Row],[CUIT]],Lista_CUIT[#All],4,0)),"CUIT NO CARGADO") -> 0
B21: 44599 | C21: 1 | D21: 2 | E21: 1292 | F21: 20931803124 | G21: =IFERROR(IF(compras_mes2[[#This Row],[CUIT]]="","-",VLOOKUP(compras_mes2[[#This Row],[CUIT]],Lista_CUIT[#All],2,0)),"CUIT NO CARGADO") -> CARNUCCIO COSME DAMIAN | H21: 1847.94 | I21: =IF(compras_mes2[[#This Row],[NETO GRAVADO]]="","",compras_mes2[[#This Row],[NETO GRAVADO]]*0.21) -> 388.0674 | P21: =SUM(compras_mes2[[#This Row],[NETO GRAVADO]:[Otros / No Grav.]]) -> 2236.0074 | Q21: =IFERROR(IF(compras_mes2[[#This Row],[CUIT]]="","-",VLOOKUP(compras_mes2[[#This Row],[CUIT]],Lista_CUIT[#All],3,0)),"CUIT NO CARGADO") -> Ferreteria | R21: =IFERROR(IF(compras_mes2[[#This Row],[CUIT]]="","-",VLOOKUP(compras_mes2[[#This Row],[CUIT]],Lista_CUIT[#All],4,0)),"CUIT NO CARGADO") -> BUENOS AIRES
B22: 44593 | C22: 1 | D22: 1 | E22: 15782 | F22: 20173025557 | G22: =IFERROR(IF(compras_mes2[[#This Row],[CUIT]]="","-",VLOOKUP(compras_mes2[[#This Row],[CUIT]],Lista_CUIT[#All],2,0)),"CUIT NO CARGADO") -> MARAUDA HECTOR | H22: 991.74 | I22: =IF(compras_mes2[[#This Row],[NETO GRAVADO]]="","",compras_mes2[[#This Row],[NETO GRAVADO]]*0.21) -> 208.2654 | P22: =SUM(compras_mes2[[#This Row],[NETO GRAVADO]:[Otros / No Grav.]]) -> 1200.0054 | Q22: =IFERROR(IF(compras_mes2[[#This Row],[CUIT]]="","-",VLOOKUP(compras_mes2[[#This Row],[CUIT]],Lista_CUIT[#All],3,0)),"CUIT NO CARGADO") -> Gastos Varios | R22: =IFERROR(IF(compras_mes2[[#This Row],[CUIT]]="","-",VLOOKUP(compras_mes2[[#This Row],[CUIT]],Lista_CUIT[#All],4,0)),"CUIT NO CARGADO") -> 0
B23: 44593 | C23: 1 | D23: 2188 | E23: 58809 | F23: 30548083156 | G23: =IFERROR(IF(compras_mes2[[#This Row],[CUIT]]="","-",VLOOKUP(compras_mes2[[#This Row],[CUIT]],Lista_CUIT[#All],2,0)),"CUIT NO CARGADO") -> COTO S.A. | H23: 6220.47 | I23: 1193.3 | L23: 153.15 | N23: 323.41 | P23: =SUM(compras_mes2[[#This Row],[NETO GRAVADO]:[Otros / No Grav.]]) -> 7890.33 | Q23: =IFERROR(IF(compras_mes2[[#This Row],[CUIT]]="","-",VLOOKUP(compras_mes2[[#This Row],[CUIT]],Lista_CUIT[#All],3,0)),"CUIT NO CARGADO") -> Gastos Varios | R23: =IFERROR(IF(compras_mes2[[#This Row],[CUIT]]="","-",VLOOKUP(compras_mes2[[#This Row],[CUIT]],Lista_CUIT[#All],4,0)),"CUIT NO CARGADO") -> 0
B24: 44596 | C24: 1 | D24: 4 | E24: 6041 | F24: 33711386179 | G24: =IFERROR(IF(compras_mes2[[#This Row],[CUIT]]="","-",VLOOKUP(compras_mes2[[#This Row],[CUIT]],Lista_CUIT[#All],2,0)),"CUIT NO CARGADO") -> SHOPNOW S.R.L. | H24: 8867.87 | K24: 931.13 | N24: 532.07 | P24: =SUM(compras_mes2[[#This Row],[NETO GRAVADO]:[Otros / No Grav.]]) -> 10331.07 | Q24: =IFERROR(IF(compras_mes2[[#This Row],[CUIT]]="","-",VLOOKUP(compras_mes2[[#This Row],[CUIT]],Lista_CUIT[#All],3,0)),"CUIT NO CARGADO") -> Gastos Varios | R24: =IFERROR(IF(compras_mes2[[#This Row],[CUIT]]="","-",VLOOKUP(compras_mes2[[#This Row],[CUIT]],Lista_CUIT[#All],4,0)),"CUIT NO CARGADO") -> CABA
B25: 44597 | C25: 1 | D25: 1035 | E25: 224 | F25: 30590360763 | G25: =IFERROR(IF(compras_mes2[[#This Row],[CUIT]]="","-",VLOOKUP(compras_mes2[[#This Row],[CUIT]],Lista_CUIT[#All],2,0)),"CUIT NO CARGADO") -> CENCOSUD S.A | H25: 1743.69 | I25: =IF(compras_mes2[[#This Row],[NETO GRAVADO]]="","",compras_mes2[[#This Row],[NETO GRAVADO]]*0.21) -> 366.1749 | N25: 104.04 | O25: 11.79 | P25: =SUM(compras_mes2[[#This Row],[NETO GRAVADO]:[Otros / No Grav.]]) -> 2225.6949 | Q25: =IFERROR(IF(compras_mes2[[#This Row],[CUIT]]="","-",VLOOKUP(compras_mes2[[#This Row],[CUIT]],Lista_CUIT[#All],3,0)),"CUIT NO CARGADO") -> Gastos Varios | R25: =IFERROR(IF(compras_mes2[[#This Row],[CUIT]]="","-",VLOOKUP(compras_mes2[[#This Row],[CUIT]],Lista_CUIT[#All],4,0)),"CUIT NO CARGADO") -> 0
B26: 44597 | C26: 1 | D26: 2199 | E26: 14354 | F26: 30548083156 | G26: =IFERROR(IF(compras_mes2[[#This Row],[CUIT]]="","-",VLOOKUP(compras_mes2[[#This Row],[CUIT]],Lista_CUIT[#All],2,0)),"CUIT NO CARGADO") -> COTO S.A. | H26: 6551.45 | I26: =IF(compras_mes2[[#This Row],[NETO GRAVADO]]="","",compras_mes2[[#This Row],[NETO GRAVADO]]*0.21) -> 1375.8045 | L26: 196.54 | P26: =SUM(compras_mes2[[#This Row],[NETO GRAVADO]:[Otros / No Grav.]]) -> 8123.7945 | Q26: =IFERROR(IF(compras_mes2[[#This Row],[CUIT]]="","-",VLOOKUP(compras_mes2[[#This Row],[CUIT]],Lista_CUIT[#All],3,0)),"CUIT NO CARGADO") -> Gastos Varios | R26: =IFERROR(IF(compras_mes2[[#This Row],[CUIT]]="","-",VLOOKUP(compras_mes2[[#This Row],[CUIT]],Lista_CUIT[#All],4,0)),"CUIT NO CARGADO") -> 0
B27: 44600 | C27: 1 | D27: 3 | E27: 1424 | F27: 20317527501 | G27: =IFERROR(IF(compras_mes2[[#This Row],[CUIT]]="","-",VLOOKUP(compras_mes2[[#This Row],[CUIT]],Lista_CUIT[#All],2,0)),"CUIT NO CARGADO") -> VITALI AGUSTIN | H27: 14710.74 | I27: =IF(compras_mes2[[#This Row],[NETO GRAVADO]]="","",compras_mes2[[#This Row],[NETO GRAVADO]]*0.21) -> 3089.2554 | P27: =SUM(compras_mes2[[#This Row],[NETO GRAVADO]:[Otros / No Grav.]]) -> 17799.995 | Q27: =IFERROR(IF(compras_mes2[[#This Row],[CUIT]]="","-",VLOOKUP(compras_mes2[[#This Row],[CUIT]],Lista_CUIT[#All],3,0)),"CUIT NO CARGADO") -> Gastos Varios | R27: =IFERROR(IF(compras_mes2[[#This Row],[CUIT]]="","-",VLOOKUP(compras_mes2[[#This Row],[CUIT]],Lista_CUIT[#All],4,0)),"CUIT NO CARGADO") -> CABA
B28: 44601 | C28: 1 | D28: 2188 | E28: 59293 | F28: 30548083156 | G28: =IFERROR(IF(compras_mes2[[#This Row],[CUIT]]="","-",VLOOKUP(compras_mes2[[#This Row],[CUIT]],Lista_CUIT[#All],2,0)),"CUIT NO CARGADO") -> COTO S.A. | H28: 8528.64 | I28: 1710.81 | L28: 232.94 | N28: 505.31 | P28: =SUM(compras_mes2[[#This Row],[NETO GRAVADO]:[Otros / No Grav.]]) -> 10977.7 | Q28: =IFERROR(IF(compras_mes2[[#This Row],[CUIT]]="","-",VLOOKUP(compras_mes2[[#This Row],[CUIT]],Lista_CUIT[#All],3,0)),"CUIT NO CARGADO") -> Gastos Varios | R28: =IFERROR(IF(compras_mes2[[#This Row],[CUIT]]="","-",VLOOKUP(compras_mes2[[#This Row],[CUIT]],Lista_CUIT[#All],4,0)),"CUIT NO CARGADO") -> 0
B29: 44604 | C29: 1 | D29: 2199 | E29: 14465 | F29: 30548083156 | G29: =IFERROR(IF(compras_mes2[[#This Row],[CUIT]]="","-",VLOOKUP(compras_mes2[[#This Row],[CUIT]],Lista_CUIT[#All],2,0)),"CUIT NO CARGADO") -> COTO S.A. | H29: 8682.78 | I29: 1612.65 | L29: 198.75 | N29: 506.75 | P29: =SUM(compras_mes2[[#This Row],[NETO GRAVADO]:[Otros / No Grav.]]) -> 11000.93 | Q29: =IFERROR(IF(compras_mes2[[#This Row],[CUIT]]="","-",VLOOKUP(compras_mes2[[#This Row],[CUIT]],Lista_CUIT[#All],3,0)),"CUIT NO CARGADO") -> Gastos Varios | R29: =IFERROR(IF(compras_mes2[[#This Row],[CUIT]]="","-",VLOOKUP(compras_mes2[[#This Row],[CUIT]],Lista_CUIT[#All],4,0)),"CUIT NO CARGADO") -> 0
B30: 44607 | C30: 1 | D30: 1313 | E30: 537 | F30: 30639057999 | G30: =IFERROR(IF(compras_mes2[[#This Row],[CUIT]]="","-",VLOOKUP(compras_mes2[[#This Row],[CUIT]],Lista_CUIT[#All],2,0)),"CUIT NO CARGADO") -> LA OPTICA S.A. | H30: 25640.5 | I30: =IF(compras_mes2[[#This Row],[NETO GRAVADO]]="","",compras_mes2[[#This Row],[NETO GRAVADO]]*0.21) -> 5384.505 | P30: =SUM(compras_mes2[[#This Row],[NETO GRAVADO]:[Otros / No Grav.]]) -> 31025.005 | Q30: =IFERROR(IF(compras_mes2[[#This Row],[CUIT]]="","-",VLOOKUP(compras_mes2[[#This Row],[CUIT]],Lista_CUIT[#All],3,0)),"CUIT NO CARGADO") -> Gastos Varios | R30: =IFERROR(IF(compras_mes2[[#This Row],[CUIT]]="","-",VLOOKUP(compras_mes2[[#This Row],[CUIT]],Lista_CUIT[#All],4,0)),"CUIT NO CARGADO") -> CABA
B31: 44614 | C31: 1 | D31: 1313 | E31: 544 | F31: 30639057999 | G31: =IFERROR(IF(compras_mes2[[#This Row],[CUIT]]="","-",VLOOKUP(compras_mes2[[#This Row],[CUIT]],Lista_CUIT[#All],2,0)),"CUIT NO CARGADO") -> LA OPTICA S.A. | H31: 8885.95 | I31: 1866.05 | P31: =SUM(compras_mes2[[#This Row],[NETO GRAVADO]:[Otros / No Grav.]]) -> 10752 | Q31: =IFERROR(IF(compras_mes2[[#This Row],[CUIT]]="","-",VLOOKUP(compras_mes2[[#This Row],[CUIT]],Lista_CUIT[#All],3,0)),"CUIT NO CARGADO") -> Gastos Varios | R31: =IFERROR(IF(compras_mes2[[#This Row],[CUIT]]="","-",VLOOKUP(compras_mes2[[#This Row],[CUIT]],Lista_CUIT[#All],4,0)),"CUIT NO CARGADO") -> CABA
B32: 44614 | C32: 1 | D32: 2199 | E32: 14618 | F32: 30548083156 | G32: =IFERROR(IF(compras_mes2[[#This Row],[CUIT]]="","-",VLOOKUP(compras_mes2[[#This Row],[CUIT]],Lista_CUIT[#All],2,0)),"CUIT NO CARGADO") -> COTO S.A. | H32: 8075.02 | I32: 1509.15 | L32: 188.94 | N32: 480.97 | P32: =SUM(compras_mes2[[#This Row],[NETO GRAVADO]:[Otros / No Grav.]]) -> 10254.08 | Q32: =IFERROR(IF(compras_mes2[[#This Row],[CUIT]]="","-",VLOOKUP(compras_mes2[[#This Row],[CUIT]],Lista_CUIT[#All],3,0)),"CUIT NO CARGADO") -> Gastos Varios | R32: =IFERROR(IF(compras_mes2[[#This Row],[CUIT]]="","-",VLOOKUP(compras_mes2[[#This Row],[CUIT]],Lista_CUIT[#All],4,0)),"CUIT NO CARGADO") -> 0
B33: 44602 | C33: 1 | D33: 6 | E33: 11704597 | F33: 30620177497 | G33: =IFERROR(IF(compras_mes2[[#This Row],[CUIT]]="","-",VLOOKUP(compras_mes2[[#This Row],[CUIT]],Lista_CUIT[#All],2,0)),"CUIT NO CARGADO") -> POSNET SRL | H33: 1580 | I33: =IF(compras_mes2[[#This Row],[NETO GRAVADO]]="","",compras_mes2[[#This Row],[NETO GRAVADO]]*0.21) -> 331.8 | L33: 47.4 | O33: 94.8 | P33: =SUM(compras_mes2[[#This Row],[NETO GRAVADO]:[Otros / No Grav.]]) -> 2054 | Q33: =IFERROR(IF(compras_mes2[[#This Row],[CUIT]]="","-",VLOOKUP(compras_mes2[[#This Row],[CUIT]],Lista_CUIT[#All],3,0)),"CUIT NO CARGADO") -> Gtos Comercializacion | R33: =IFERROR(IF(compras_mes2[[#This Row],[CUIT]]="","-",VLOOKUP(compras_mes2[[#This Row],[CUIT]],Lista_CUIT[#All],4,0)),"CUIT NO CARGADO") -> 0
B34: 44602 | C34: 1 | D34: 6 | E34: 11704665 | F34: 30620177497 | G34: =IFERROR(IF(compras_mes2[[#This Row],[CUIT]]="","-",VLOOKUP(compras_mes2[[#This Row],[CUIT]],Lista_CUIT[#All],2,0)),"CUIT NO CARGADO") -> POSNET SRL | H34: 1580 | I34: =IF(compras_mes2[[#This Row],[NETO GRAVADO]]="","",compras_mes2[[#This Row],[NETO GRAVADO]]*0.21) -> 331.8 | L34: 47.4 | O34: 94.8 | P34: =SUM(compras_mes2[[#This Row],[NETO GRAVADO]:[Otros / No Grav.]]) -> 2054 | Q34: =IFERROR(IF(compras_mes2[[#This Row],[CUIT]]="","-",VLOOKUP(compras_mes2[[#This Row],[CUIT]],Lista_CUIT[#All],3,0)),"CUIT NO CARGADO") -> Gtos Comercializacion | R34: =IFERROR(IF(compras_mes2[[#This Row],[CUIT]]="","-",VLOOKUP(compras_mes2[[#This Row],[CUIT]],Lista_CUIT[#All],4,0)),"CUIT NO CARGADO") -> 0
B35: 44602 | C35: 1 | D35: 6 | E35: 11741927 | F35: 30620177497 | G35: =IFERROR(IF(compras_mes2[[#This Row],[CUIT]]="","-",VLOOKUP(compras_mes2[[#This Row],[CUIT]],Lista_CUIT[#All],2,0)),"CUIT NO CARGADO") -> POSNET SRL | H35: 1580 | I35: =IF(compras_mes2[[#This Row],[NETO GRAVADO]]="","",compras_mes2[[#This Row],[NETO GRAVADO]]*0.21) -> 331.8 | L35: 47.4 | O35: 94.8 | P35: =SUM(compras_mes2[[#This Row],[NETO GRAVADO]:[Otros / No Grav.]]) -> 2054 | Q35: =IFERROR(IF(compras_mes2[[#This Row],[CUIT]]="","-",VLOOKUP(compras_mes2[[#This Row],[CUIT]],Lista_CUIT[#All],3,0)),"CUIT NO CARGADO") -> Gtos Comercializacion | R35: =IFERROR(IF(compras_mes2[[#This Row],[CUIT]]="","-",VLOOKUP(compras_mes2[[#This Row],[CUIT]],Lista_CUIT[#All],4,0)),"CUIT NO CARGADO") -> 0
B36: 44602 | C36: 1 | D36: 6 | E36: 11741977 | F36: 30620177497 | G36: =IFERROR(IF(compras_mes2[[#This Row],[CUIT]]="","-",VLOOKUP(compras_mes2[[#This Row],[CUIT]],Lista_CUIT[#All],2,0)),"CUIT NO CARGADO") -> POSNET SRL | H36: 4740 | I36: =IF(compras_mes2[[#This Row],[NETO GRAVADO]]="","",compras_mes2[[#This Row],[NETO GRAVADO]]*0.21) -> 995.4 | L36: 142.2 | O36: 284.4 | P36: =SUM(compras_mes2[[#This Row],[NETO GRAVADO]:[Otros / No Grav.]]) -> 6162 | Q36: =IFERROR(IF(compras_mes2[[#This Row],[CUIT]]="","-",VLOOKUP(compras_mes2[[#This Row],[CUIT]],Lista_CUIT[#All],3,0)),"CUIT NO CARGADO") -> Gtos Comercializacion | R36: =IFERROR(IF(compras_mes2[[#This Row],[CUIT]]="","-",VLOOKUP(compras_mes2[[#This Row],[CUIT]],Lista_CUIT[#All],4,0)),"CUIT NO CARGADO") -> 0
B37: 44614 | C37: 1 | D37: 3 | E37: 836 | F37: 30715434276 | G37: =IFERROR(IF(compras_mes2[[#This Row],[CUIT]]="","-",VLOOKUP(compras_mes2[[#This Row],[CUIT]],Lista_CUIT[#All],2,0)),"CUIT NO CARGADO") -> BRUAYAFA S.A. | H37: 142154 | I37: =IF(compras_mes2[[#This Row],[NETO GRAVADO]]="","",compras_mes2[[#This Row],[NETO GRAVADO]]*0.21) -> 29852.34 | P37: =SUM(compras_mes2[[#This Row],[NETO GRAVADO]:[Otros / No Grav.]]) -> 172006.34 | Q37: =IFERROR(IF(compras_mes2[[#This Row],[CUIT]]="","-",VLOOKUP(compras_mes2[[#This Row],[CUIT]],Lista_CUIT[#All],3,0)),"CUIT NO CARGADO") -> Gtos Comercializacion | R37: =IFERROR(IF(compras_mes2[[#This Row],[CUIT]]="","-",VLOOKUP(compras_mes2[[#This Row],[CUIT]],Lista_CUIT[#All],4,0)),"CUIT NO CARGADO") -> 0
B38: 44615 | C38: 1 | D38: 1 | E38: 74466 | F38: 30716620634 | G38: =IFERROR(IF(compras_mes2[[#This Row],[CUIT]]="","-",VLOOKUP(compras_mes2[[#This Row],[CUIT]],Lista_CUIT[#All],2,0)),"CUIT NO CARGADO") -> FIRST LABEL S.R.L. | H38: 41321.49 | I38: =IF(compras_mes2[[#This Row],[NETO GRAVADO]]="","",compras_mes2[[#This Row],[NETO GRAVADO]]*0.21) -> 8677.5129 | P38: =SUM(compras_mes2[[#This Row],[NETO GRAVADO]:[Otros / No Grav.]]) -> 49999.003 | Q38: =IFERROR(IF(compras_mes2[[#This Row],[CUIT]]="","-",VLOOKUP(compras_mes2[[#This Row],[CUIT]],Lista_CUIT[#All],3,0)),"CUIT NO CARGADO") -> Gtos Comercializacion | R38: =IFERROR(IF(compras_mes2[[#This Row],[CUIT]]="","-",VLOOKUP(compras_mes2[[#This Row],[CUIT]],Lista_CUIT[#All],4,0)),"CUIT NO CARGADO") -> CABA
B39: 44620 | C39: 1 | D39: 27 | E39: 214067 | F39: 30703088534 | G39: =IFERROR(IF(compras_mes2[[#This Row],[CUIT]]="","-",VLOOKUP(compras_mes2[[#This Row],[CUIT]],Lista_CUIT[#All],2,0)),"CUIT NO CARGADO") -> MERCADO LIBRE SRL | H39: 76533.69 | I39: =IF(compras_mes2[[#This Row],[NETO GRAVADO]]="","",compras_mes2[[#This Row],[NETO GRAVADO]]*0.21) -> 16072.075 | L39: 2296.02 | N39: 4592.02 | P39: =SUM(compras_mes2[[#This Row],[NETO GRAVADO]:[Otros / No Grav.]]) -> 99493.805 | Q39: =IFERROR(IF(compras_mes2[[#This Row],[CUIT]]="","-",VLOOKUP(compras_mes2[[#This Row],[CUIT]],Lista_CUIT[#All],3,0)),"CUIT NO CARGADO") -> Gtos Comercializacion | R39: =IFERROR(IF(compras_mes2[[#This Row],[CUIT]]="","-",VLOOKUP(compras_mes2[[#This Row],[CUIT]],Lista_CUIT[#All],4,0)),"CUIT NO CARGADO") -> 0
B40: 44620 | C40: 1 | D40: 1 | E40: 2186 | F40: 20103906149 | G40: =IFERROR(IF(compras_mes2[[#This Row],[CUIT]]="","-",VLOOKUP(compras_mes2[[#This Row],[CUIT]],Lista_CUIT[#All],2,0)),"CUIT NO CARGADO") -> MC LEAN ROBERTO | H40: 45000 | I40: =IF(compras_mes2[[#This Row],[NETO GRAVADO]]="","",compras_mes2[[#This Row],[NETO GRAVADO]]*0.21) -> 9450 | P40: =SUM(compras_mes2[[#This Row],[NETO GRAVADO]:[Otros / No Grav.]]) -> 54450 | Q40: =IFERROR(IF(compras_mes2[[#This Row],[CUIT]]="","-",VLOOKUP(compras_mes2[[#This Row],[CUIT]],Lista_CUIT[#All],3,0)),"CUIT NO CARGADO") -> Honorarios Contables | R40: =IFERROR(IF(compras_mes2[[#This Row],[CUIT]]="","-",VLOOKUP(compras_mes2[[#This Row],[CUIT]],Lista_CUIT[#All],4,0)),"CUIT NO CARGADO") -> 0
B41: 44596 | C41: 1 | D41: 3 | E41: 252864 | F41: 33643358749 | G41: =IFERROR(IF(compras_mes2[[#This Row],[CUIT]]="","-",VLOOKUP(compras_mes2[[#This Row],[CUIT]],Lista_CUIT[#All],2,0)),"CUIT NO CARGADO") -> POLYTECH S.A. | H41: 67872.4 | K41: 7126.6 | P41: =SUM(compras_mes2[[#This Row],[NETO GRAVADO]:[Otros / No Grav.]]) -> 74999 | Q41: =IFERROR(IF(compras_mes2[[#This Row],[CUIT]]="","-",VLOOKUP(compras_mes2[[#This Row],[CUIT]],Lista_CUIT[#All],3,0)),"CUIT NO CARGADO") -> Librería | R41: =IFERROR(IF(compras_mes2[[#This Row],[CUIT]]="","-",VLOOKUP(compras_mes2[[#This Row],[CUIT]],Lista_CUIT[#All],4,0)),"CUIT NO CARGADO") -> 0
B42: 44606 | C42: 1 | D42: 3 | E42: 973 | F42: 30711137137 | G42: =IFERROR(IF(compras_mes2[[#This Row],[CUIT]]="","-",VLOOKUP(compras_mes2[[#This Row],[CUIT]],Lista_CUIT[#All],2,0)),"CUIT NO CARGADO") -> ROMO MATERIALES DE LA CONST | H42: 82644.63 | I42: =IF(compras_mes2[[#This Row],[NETO GRAVADO]]="","",compras_mes2[[#This Row],[NETO GRAVADO]]*0.21) -> 17355.372 | P42: =SUM(compras_mes2[[#This Row],[NETO GRAVADO]:[Otros / No Grav.]]) -> 100000 | Q42: =IFERROR(IF(compras_mes2[[#This Row],[CUIT]]="","-",VLOOKUP(compras_mes2[[#This Row],[CUIT]],Lista_CUIT[#All],3,0)),"CUIT NO CARGADO") -> Mantenimiento | R42: =IFERROR(IF(compras_mes2[[#This Row],[CUIT]]="","-",VLOOKUP(compras_mes2[[#This Row],[CUIT]],Lista_CUIT[#All],4,0)),"CUIT NO CARGADO") -> CABA
B43: 44593 | C43: 1 | D43: 2 | E43: 771 | F43: 20172319743 | G43: =IFERROR(IF(compras_mes2[[#This Row],[CUIT]]="","-",VLOOKUP(compras_mes2[[#This Row],[CUIT]],Lista_CUIT[#All],2,0)),"CUIT NO CARGADO") -> IACONIS SERGIO OMAR | H43: 444720 | I43: =IF(compras_mes2[[#This Row],[NETO GRAVADO]]="","",compras_mes2[[#This Row],[NETO GRAVADO]]*0.21) -> 93391.2 | P43: =SUM(compras_mes2[[#This Row],[NETO GRAVADO]:[Otros / No Grav.]]) -> 538111.2 | Q43: =IFERROR(IF(compras_mes2[[#This Row],[CUIT]]="","-",VLOOKUP(compras_mes2[[#This Row],[CUIT]],Lista_CUIT[#All],3,0)),"CUIT NO CARGADO") -> Mercaderia | R43: =IFERROR(IF(compras_mes2[[#This Row],[CUIT]]="","-",VLOOKUP(compras_mes2[[#This Row],[CUIT]],Lista_CUIT[#All],4,0)),"CUIT NO CARGADO") -> BS AS
B44: 44593 | C44: 1 | D44: 30 | E44: 339 | F44: 30502272930 | G44: =IFERROR(IF(compras_mes2[[#This Row],[CUIT]]="","-",VLOOKUP(compras_mes2[[#This Row],[CUIT]],Lista_CUIT[#All],2,0)),"CUIT NO CARGADO") -> TEJILASTIC S.A. | H44: 92460 | I44: =IF(compras_mes2[[#This Row],[NETO GRAVADO]]="","",compras_mes2[[#This Row],[NETO GRAVADO]]*0.21) -> 19416.6 | P44: =SUM(compras_mes2[[#This Row],[NETO GRAVADO]:[Otros / No Grav.]]) -> 111876.6 | Q44: =IFERROR(IF(compras_mes2[[#This Row],[CUIT]]="","-",VLOOKUP(compras_mes2[[#This Row],[CUIT]],Lista_CUIT[#All],3,0)),"CUIT NO CARGADO") -> Mercaderia | R44: =IFERROR(IF(compras_mes2[[#This Row],[CUIT]]="","-",VLOOKUP(compras_mes2[[#This Row],[CUIT]],Lista_CUIT[#All],4,0)),"CUIT NO CARGADO") -> 0
B45: 44593 | C45: 1 | D45: 30 | E45: 339 | F45: 27293459172 | G45: =IFERROR(IF(compras_mes2[[#This Row],[CUIT]]="","-",VLOOKUP(compras_mes2[[#This Row],[CUIT]],Lista_CUIT[#All],2,0)),"CUIT NO CARGADO") -> DUFFY ESTEFANIA | H45: 92460 | I45: =IF(compras_mes2[[#This Row],[NETO GRAVADO]]="","",compras_mes2[[#This Row],[NETO GRAVADO]]*0.21) -> 19416.6 | P45: =SUM(compras_mes2[[#This Row],[NETO GRAVADO]:[Otros / No Grav.]]) -> 111876.6 | Q45: =IFERROR(IF(compras_mes2[[#This Row],[CUIT]]="","-",VLOOKUP(compras_mes2[[#This Row],[CUIT]],Lista_CUIT[#All],3,0)),"CUIT NO CARGADO") -> Mercaderia | R45: =IFERROR(IF(compras_mes2[[#This Row],[CUIT]]="","-",VLOOKUP(compras_mes2[[#This Row],[CUIT]],Lista_CUIT[#All],4,0)),"CUIT NO CARGADO") -> BS AS
B46: 44595 | C46: 1 | D46: 1 | E46: 44 | F46: 20077604627 | G46: =IFERROR(IF(compras_mes2[[#This Row],[CUIT]]="","-",VLOOKUP(compras_mes2[[#This Row],[CUIT]],Lista_CUIT[#All],2,0)),"CUIT NO CARGADO") -> OCAÑO ENRIQUE | H46: 87669.2 | I46: =IF(compras_mes2[[#This Row],[NETO GRAVADO]]="","",compras_mes2[[#This Row],[NETO GRAVADO]]*0.21) -> 18410.532 | P46: =SUM(compras_mes2[[#This Row],[NETO GRAVADO]:[Otros / No Grav.]]) -> 106079.73 | Q46: =IFERROR(IF(compras_mes2[[#This Row],[CUIT]]="","-",VLOOKUP(compras_mes2[[#This Row],[CUIT]],Lista_CUIT[#All],3,0)),"CUIT NO CARGADO") -> Mercaderia | R46: =IFERROR(IF(compras_mes2[[#This Row],[CUIT]]="","-",VLOOKUP(compras_mes2[[#This Row],[CUIT]],Lista_CUIT[#All],4,0)),"CUIT NO CARGADO") -> 0
B47: 44595 | C47: 1 | D47: 2 | E47: 2976 | F47: 30629863571 | G47: =IFERROR(IF(compras_mes2[[#This Row],[CUIT]]="","-",VLOOKUP(compras_mes2[[#This Row],[CUIT]],Lista_CUIT[#All],2,0)),"CUIT NO CARGADO") -> TECNIMAR S R L | H47: 49089.22 | I47: =IF(compras_mes2[[#This Row],[NETO GRAVADO]]="","",compras_mes2[[#This Row],[NETO GRAVADO]]*0.21) -> 10308.736 | P47: =SUM(compras_mes2[[#This Row],[NETO GRAVADO]:[Otros / No Grav.]]) -> 59397.956 | Q47: =IFERROR(IF(compras_mes2[[#This Row],[CUIT]]="","-",VLOOKUP(compras_mes2[[#This Row],[CUIT]],Lista_CUIT[#All],3,0)),"CUIT NO CARGADO") -> Mercaderia | R47: =IFERROR(IF(compras_mes2[[#This Row],[CUIT]]="","-",VLOOKUP(compras_mes2[[#This Row],[CUIT]],Lista_CUIT[#All],4,0)),"CUIT NO CARGADO") -> 0
B48: 44595 | C48: 1 | D48: 7 | E48: 5767 | F48: 30708017759 | G48: =IFERROR(IF(compras_mes2[[#This Row],[CUIT]]="","-",VLOOKUP(compras_mes2[[#This Row],[CUIT]],Lista_CUIT[#All],2,0)),"CUIT NO CARGADO") -> NEW HIGH PACK SA | H48: 169778 | I48: =IF(compras_mes2[[#This Row],[NETO GRAVADO]]="","",compras_mes2[[#This Row],[NETO GRAVADO]]*0.21) -> 35653.38 | N48: 10186.68 | P48: =SUM(compras_mes2[[#This Row],[NETO GRAVADO]:[Otros / No Grav.]]) -> 215618.06 | Q48: =IFERROR(IF(compras_mes2[[#This Row],[CUIT]]="","-",VLOOKUP(compras_mes2[[#This Row],[CUIT]],Lista_CUIT[#All],3,0)),"CUIT NO CARGADO") -> Mercaderia | R48: =IFERROR(IF(compras_mes2[[#This Row],[CUIT]]="","-",VLOOKUP(compras_mes2[[#This Row],[CUIT]],Lista_CUIT[#All],4,0)),"CUIT NO CARGADO") -> 0
B49: 44596 | C49: 1 | D49: 7 | E49: 5774 | F49: 30708017759 | G49: =IFERROR(IF(compras_mes2[[#This Row],[CUIT]]="","-",VLOOKUP(compras_mes2[[#This Row],[CUIT]],Lista_CUIT[#All],2,0)),"CUIT NO CARGADO") -> NEW HIGH PACK SA | H49: 165370 | I49: =IF(compras_mes2[[#This Row],[NETO GRAVADO]]="","",compras_mes2[[#This Row],[NETO GRAVADO]]*0.21) -> 34727.7 | N49: 9922.2 | P49: =SUM(compras_mes2[[#This Row],[NETO GRAVADO]:[Otros / No Grav.]]) -> 210019.9 | Q49: =IFERROR(IF(compras_mes2[[#This Row],[CUIT]]="","-",VLOOKUP(compras_mes2[[#This Row],[CUIT]],Lista_CUIT[#All],3,0)),"CUIT NO CARGADO") -> Mercaderia | R49: =IFERROR(IF(compras_mes2[[#This Row],[CUIT]]="","-",VLOOKUP(compras_mes2[[#This Row],[CUIT]],Lista_CUIT[#All],4,0)),"CUIT NO CARGADO") -> 0
B50: 44600 | C50: 1 | D50: 2 | E50: 2978 | F50: 30629863571 | G50: =IFERROR(IF(compras_mes2[[#This Row],[CUIT]]="","-",VLOOKUP(compras_mes2[[#This Row],[CUIT]],Lista_CUIT[#All],2,0)),"CUIT NO CARGADO") -> TECNIMAR S R L | H50: 92021.37 | I50: =IF(compras_mes2[[#This Row],[NETO GRAVADO]]="","",compras_mes2[[#This Row],[NETO GRAVADO]]*0.21) -> 19324.488 | P50: =SUM(compras_mes2[[#This Row],[NETO GRAVADO]:[Otros / No Grav.]]) -> 111345.86 | Q50: =IFERROR(IF(compras_mes2[[#This Row],[CUIT]]="","-",VLOOKUP(compras_mes2[[#This Row],[CUIT]],Lista_CUIT[#All],3,0)),"CUIT NO CARGADO") -> Mercaderia | R50: =IFERROR(IF(compras_mes2[[#This Row],[CUIT]]="","-",VLOOKUP(compras_mes2[[#This Row],[CUIT]],Lista_CUIT[#All],4,0)),"CUIT NO CARGADO") -> 0
B51: 44602 | C51: 1 | D51: 6 | E51: 1910 | F51: 30574603788 | G51: =IFERROR(IF(compras_mes2[[#This Row],[CUIT]]="","-",VLOOKUP(compras_mes2[[#This Row],[CUIT]],Lista_CUIT[#All],2,0)),"CUIT NO CARGADO") -> Codac SRL | H51: 234228 | I51: =IF(compras_mes2[[#This Row],[NETO GRAVADO]]="","",compras_mes2[[#This Row],[NETO GRAVADO]]*0.21) -> 49187.88 | P51: =SUM(compras_mes2[[#This Row],[NETO GRAVADO]:[Otros / No Grav.]]) -> 283415.88 | Q51: =IFERROR(IF(compras_mes2[[#This Row],[CUIT]]="","-",VLOOKUP(compras_mes2[[#This Row],[CUIT]],Lista_CUIT[#All],3,0)),"CUIT NO CARGADO") -> Mercaderia | R51: =IFERROR(IF(compras_mes2[[#This Row],[CUIT]]="","-",VLOOKUP(compras_mes2[[#This Row],[CUIT]],Lista_CUIT[#All],4,0)),"CUIT NO CARGADO") -> 0
B52: 44603 | C52: 1 | D52: 6 | E52: 20798 | F52: 33640878679 | G52: =IFERROR(IF(compras_mes2[[#This Row],[CUIT]]="","-",VLOOKUP(compras_mes2[[#This Row],[CUIT]],Lista_CUIT[#All],2,0)),"CUIT NO CARGADO") -> DHACAM S.R.L. | H52: 67440 | I52: =IF(compras_mes2[[#This Row],[NETO GRAVADO]]="","",compras_mes2[[#This Row],[NETO GRAVADO]]*0.21) -> 14162.4 | P52: =SUM(compras_mes2[[#This Row],[NETO GRAVADO]:[Otros / No Grav.]]) -> 81602.4 | Q52: =IFERROR(IF(compras_mes2[[#This Row],[CUIT]]="","-",VLOOKUP(compras_mes2[[#This Row],[CUIT]],Lista_CUIT[#All],3,0)),"CUIT NO CARGADO") -> Mercaderia | R52: =IFERROR(IF(compras_mes2[[#This Row],[CUIT]]="","-",VLOOKUP(compras_mes2[[#This Row],[CUIT]],Lista_CUIT[#All],4,0)),"CUIT NO CARGADO") -> 0
B53: 44608 | C53: 1 | D53: 2 | E53: 2985 | F53: 30629863571 | G53: =IFERROR(IF(compras_mes2[[#This Row],[CUIT]]="","-",VLOOKUP(compras_mes2[[#This Row],[CUIT]],Lista_CUIT[#All],2,0)),"CUIT NO CARGADO") -> TECNIMAR S R L | H53: 107904.52 | I53: =IF(compras_mes2[[#This Row],[NETO GRAVADO]]="","",compras_mes2[[#This Row],[NETO GRAVADO]]*0.21) -> 22659.949 | P53: =SUM(compras_mes2[[#This Row],[NETO GRAVADO]:[Otros / No Grav.]]) -> 130564.47 | Q53: =IFERROR(IF(compras_mes2[[#This Row],[CUIT]]="","-",VLOOKUP(compras_mes2[[#This Row],[CUIT]],Lista_CUIT[#All],3,0)),"CUIT NO CARGADO") -> Mercaderia | R53: =IFERROR(IF(compras_mes2[[#This Row],[CUIT]]="","-",VLOOKUP(compras_mes2[[#This Row],[CUIT]],Lista_CUIT[#All],4,0)),"CUIT NO CARGADO") -> 0
B54: 44610 | C54: 1 | D54: 1 | E54: 49 | F54: 20077604627 | G54: =IFERROR(IF(compras_mes2[[#This Row],[CUIT]]="","-",VLOOKUP(compras_mes2[[#This Row],[CUIT]],Lista_CUIT[#All],2,0)),"CUIT NO CARGADO") -> OCAÑO ENRIQUE | H54: 85816.8 | I54: =IF(compras_mes2[[#This Row],[NETO GRAVADO]]="","",compras_mes2[[#This Row],[NETO GRAVADO]]*0.21) -> 18021.528 | P54: =SUM(compras_mes2[[#This Row],[NETO GRAVADO]:[Otros / No Grav.]]) -> 103838.33 | Q54: =IFERROR(IF(compras_mes2[[#This Row],[CUIT]]="","-",VLOOKUP(compras_mes2[[#This Row],[CUIT]],Lista_CUIT[#All],3,0)),"CUIT NO CARGADO") -> Mercaderia | R54: =IFERROR(IF(compras_mes2[[#This Row],[CUIT]]="","-",VLOOKUP(compras_mes2[[#This Row],[CUIT]],Lista_CUIT[#All],4,0)),"CUIT NO CARGADO") -> 0
B55: 44613 | C55: 1 | D55: 2 | E55: 2993 | F55: 30629863571 | G55: =IFERROR(IF(compras_mes2[[#This Row],[CUIT]]="","-",VLOOKUP(compras_mes2[[#This Row],[CUIT]],Lista_CUIT[#All],2,0)),"CUIT NO CARGADO") -> TECNIMAR S R L | H55: 145811.86 | I55: =IF(compras_mes2[[#This Row],[NETO GRAVADO]]="","",compras_mes2[[#This Row],[NETO GRAVADO]]*0.21) -> 30620.491 | P55: =SUM(compras_mes2[[#This Row],[NETO GRAVADO]:[Otros / No Grav.]]) -> 176432.35 | Q55: =IFERROR(IF(compras_mes2[[#This Row],[CUIT]]="","-",VLOOKUP(compras_mes2[[#This Row],[CUIT]],Lista_CUIT[#All],3,0)),"CUIT NO CARGADO") -> Mercaderia | R55: =IFERROR(IF(compras_mes2[[#This Row],[CUIT]]="","-",VLOOKUP(compras_mes2[[#This Row],[CUIT]],Lista_CUIT[#All],4,0)),"CUIT NO CARGADO") -> 0
B56: 44614 | C56: 1 | D56: 2 | E56: 2995 | F56: 30629863571 | G56: =IFERROR(IF(compras_mes2[[#This Row],[CUIT]]="","-",VLOOKUP(compras_mes2[[#This Row],[CUIT]],Lista_CUIT[#All],2,0)),"CUIT NO CARGADO") -> TECNIMAR S R L | H56: 202985.04 | I56: =IF(compras_mes2[[#This Row],[NETO GRAVADO]]="","",compras_mes2[[#This Row],[NETO GRAVADO]]*0.21) -> 42626.858 | P56: =SUM(compras_mes2[[#This Row],[NETO GRAVADO]:[Otros / No Grav.]]) -> 245611.9 | Q56: =IFERROR(IF(compras_mes2[[#This Row],[CUIT]]="","-",VLOOKUP(compras_mes2[[#This Row],[CUIT]],Lista_CUIT[#All],3,0)),"CUIT NO CARGADO") -> Mercaderia | R56: =IFERROR(IF(compras_mes2[[#This Row],[CUIT]]="","-",VLOOKUP(compras_mes2[[#This Row],[CUIT]],Lista_CUIT[#All],4,0)),"CUIT NO CARGADO") -> 0
B57: 44614 | C57: 1 | D57: 6 | E57: 1929 | F57: 30574603788 | G57: =IFERROR(IF(compras_mes2[[#This Row],[CUIT]]="","-",VLOOKUP(compras_mes2[[#This Row],[CUIT]],Lista_CUIT[#All],2,0)),"CUIT NO CARGADO") -> Codac SRL | H57: 309691 | I57: =IF(compras_mes2[[#This Row],[NETO GRAVADO]]="","",compras_mes2[[#This Row],[NETO GRAVADO]]*0.21) -> 65035.11 | P57: =SUM(compras_mes2[[#This Row],[NETO GRAVADO]:[Otros / No Grav.]]) -> 374726.11 | Q57: =IFERROR(IF(compras_mes2[[#This Row],[CUIT]]="","-",VLOOKUP(compras_mes2[[#This Row],[CUIT]],Lista_CUIT[#All],3,0)),"CUIT NO CARGADO") -> Mercaderia | R57: =IFERROR(IF(compras_mes2[[#This Row],[CUIT]]="","-",VLOOKUP(compras_mes2[[#This Row],[CUIT]],Lista_CUIT[#All],4,0)),"CUIT NO CARGADO") -> 0
B58: 44615 | C58: 1 | D58: 1 | E58: 50 | F58: 20077604627 | G58: =IFERROR(IF(compras_mes2[[#This Row],[CUIT]]="","-",VLOOKUP(compras_mes2[[#This Row],[CUIT]],Lista_CUIT[#All],2,0)),"CUIT NO CARGADO") -> OCAÑO ENRIQUE | H58: 83967.3 | I58: =IF(compras_mes2[[#This Row],[NETO GRAVADO]]="","",compras_mes2[[#This Row],[NETO GRAVADO]]*0.21) -> 17633.133 | P58: =SUM(compras_mes2[[#This Row],[NETO GRAVADO]:[Otros / No Grav.]]) -> 101600.43 | Q58: =IFERROR(IF(compras_mes2[[#This Row],[CUIT]]="","-",VLOOKUP(compras_mes2[[#This Row],[CUIT]],Lista_CUIT[#All],3,0)),"CUIT NO CARGADO") -> Mercaderia | R58: =IFERROR(IF(compras_mes2[[#This Row],[CUIT]]="","-",VLOOKUP(compras_mes2[[#This Row],[CUIT]],Lista_CUIT[#All],4,0)),"CUIT NO CARGADO") -> 0
B59: 44617 | C59: 1 | D59: 2 | E59: 2999 | F59: 30629863571 | G59: =IFERROR(IF(compras_mes2[[#This Row],[CUIT]]="","-",VLOOKUP(compras_mes2[[#This Row],[CUIT]],Lista_CUIT[#All],2,0)),"CUIT NO CARGADO") -> TECNIMAR S R L | H59: 265678.04 | I59: =IF(compras_mes2[[#This Row],[NETO GRAVADO]]="","",compras_mes2[[#This Row],[NETO GRAVADO]]*0.21) -> 55792.388 | P59: =SUM(compras_mes2[[#This Row],[NETO GRAVADO]:[Otros / No Grav.]]) -> 321470.43 | Q59: =IFERROR(IF(compras_mes2[[#This Row],[CUIT]]="","-",VLOOKUP(compras_mes2[[#This Row],[CUIT]],Lista_CUIT[#All],3,0)),"CUIT NO CARGADO") -> Mercaderia | R59: =IFERROR(IF(compras_mes2[[#This Row],[CUIT]]="","-",VLOOKUP(compras_mes2[[#This Row],[CUIT]],Lista_CUIT[#All],4,0)),"CUIT NO CARGADO") -> 0
B60: 44617 | C60: 1 | D60: 4 | E60: 33466 | F60: 30585948817 | G60: =IFERROR(IF(compras_mes2[[#This Row],[CUIT]]="","-",VLOOKUP(compras_mes2[[#This Row],[CUIT]],Lista_CUIT[#All],2,0)),"CUIT NO CARGADO") -> GLASCAR | H60: 59625 | I60: =IF(compras_mes2[[#This Row],[NETO GRAVADO]]="","",compras_mes2[[#This Row],[NETO GRAVADO]]*0.21) -> 12521.25 | N60: 3577.5 | P60: =SUM(compras_mes2[[#This Row],[NETO GRAVADO]:[Otros / No Grav.]]) -> 75723.75 | Q60: =IFERROR(IF(compras_mes2[[#This Row],[CUIT]]="","-",VLOOKUP(compras_mes2[[#This Row],[CUIT]],Lista_CUIT[#All],3,0)),"CUIT NO CARGADO") -> Mercaderia | R60: =IFERROR(IF(compras_mes2[[#This Row],[CUIT]]="","-",VLOOKUP(compras_mes2[[#This Row],[CUIT]],Lista_CUIT[#All],4,0)),"CUIT NO CARGADO") -> 0
B61: 44617 | C61: 1 | D61: 15 | E61: 2055 | F61: 30691617773 | G61: =IFERROR(IF(compras_mes2[[#This Row],[CUIT]]="","-",VLOOKUP(compras_mes2[[#This Row],[CUIT]],Lista_CUIT[#All],2,0)),"CUIT NO CARGADO") -> NOVACHEM S R L | H61: 12937.5 | I61: =IF(compras_mes2[[#This Row],[NETO GRAVADO]]="","",compras_mes2[[#This Row],[NETO GRAVADO]]*0.21) -> 2716.875 | P61: =SUM(compras_mes2[[#This Row],[NETO GRAVADO]:[Otros / No Grav.]]) -> 15654.375 | Q61: =IFERROR(IF(compras_mes2[[#This Row],[CUIT]]="","-",VLOOKUP(compras_mes2[[#This Row],[CUIT]],Lista_CUIT[#All],3,0)),"CUIT NO CARGADO") -> Mercaderia | R61: =IFERROR(IF(compras_mes2[[#This Row],[CUIT]]="","-",VLOOKUP(compras_mes2[[#This Row],[CUIT]],Lista_CUIT[#All],4,0)),"CUIT NO CARGADO") -> 0
B62: 44618 | C62: 1 | D62: 2 | E62: 4015 | F62: 23180288899 | G62: =IFERROR(IF(compras_mes2[[#This Row],[CUIT]]="","-",VLOOKUP(compras_mes2[[#This Row],[CUIT]],Lista_CUIT[#All],2,0)),"CUIT NO CARGADO") -> ROMERO EMILIO | H62: 126000 | I62: =IF(compras_mes2[[#This Row],[NETO GRAVADO]]="","",compras_mes2[[#This Row],[NETO GRAVADO]]*0.21) -> 26460 | P62: =SUM(compras_mes2[[#This Row],[NETO GRAVADO]:[Otros / No Grav.]]) -> 152460 | Q62: =IFERROR(IF(compras_mes2[[#This Row],[CUIT]]="","-",VLOOKUP(compras_mes2[[#This Row],[CUIT]],Lista_CUIT[#All],3,0)),"CUIT NO CARGADO") -> Mercaderia | R62: =IFERROR(IF(compras_mes2[[#This Row],[CUIT]]="","-",VLOOKUP(compras_mes2[[#This Row],[CUIT]],Lista_CUIT[#All],4,0)),"CUIT NO CARGADO") -> BUENOS AIRES
B63: 44594 | C63: 1 | D63: 5014 | E63: 189806 | F63: 30574876474 | G63: =IFERROR(IF(compras_mes2[[#This Row],[CUIT]]="","-",VLOOKUP(compras_mes2[[#This Row],[CUIT]],Lista_CUIT[#All],2,0)),"CUIT NO CARGADO") -> AUTOPISTAS URBANAS S A | H63: 6547.7 | I63: =IF(compras_mes2[[#This Row],[NETO GRAVADO]]="","",compras_mes2[[#This Row],[NETO GRAVADO]]*0.21) -> 1375.017 | L63: 196.42 | O63: 649.67 | P63: =SUM(compras_mes2[[#This Row],[NETO GRAVADO]:[Otros / No Grav.]]) -> 8768.807 | Q63: =IFERROR(IF(compras_mes2[[#This Row],[CUIT]]="","-",VLOOKUP(compras_mes2[[#This Row],[CUIT]],Lista_CUIT[#All],3,0)),"CUIT NO CARGADO") -> Peaje | R63: =IFERROR(IF(compras_mes2[[#This Row],[CUIT]]="","-",VLOOKUP(compras_mes2[[#This Row],[CUIT]],Lista_CUIT[#All],4,0)),"CUIT NO CARGADO") -> 0
B64: 44604 | C64: 1 | D64: 50 | E64: 2465701 | F64: 30574876474 | G64: =IFERROR(IF(compras_mes2[[#This Row],[CUIT]]="","-",VLOOKUP(compras_mes2[[#This Row],[CUIT]],Lista_CUIT[#All],2,0)),"CUIT NO CARGADO") -> AUTOPISTAS URBANAS S A | H64: 1303.3 | I64: =IF(compras_mes2[[#This Row],[NETO GRAVADO]]="","",compras_mes2[[#This Row],[NETO GRAVADO]]*0.21) -> 273.693 | L64: 39.1 | P64: =SUM(compras_mes2[[#This Row],[NETO GRAVADO]:[Otros / No Grav.]]) -> 1616.093 | Q64: =IFERROR(IF(compras_mes2[[#This Row],[CUIT]]="","-",VLOOKUP(compras_mes2[[#This Row],[CUIT]],Lista_CUIT[#All],3,0)),"CUIT NO CARGADO") -> Peaje | R64: =IFERROR(IF(compras_mes2[[#This Row],[CUIT]]="","-",VLOOKUP(compras_mes2[[#This Row],[CUIT]],Lista_CUIT[#All],4,0)),"CUIT NO CARGADO") -> 0
B65: 44609 | C65: 1 | D65: 5014 | E65: 195096 | F65: 30574876474 | G65: =IFERROR(IF(compras_mes2[[#This Row],[CUIT]]="","-",VLOOKUP(compras_mes2[[#This Row],[CUIT]],Lista_CUIT[#All],2,0)),"CUIT NO CARGADO") -> AUTOPISTAS URBANAS S A | H65: 7785.48 | I65: =IF(compras_mes2[[#This Row],[NETO GRAVADO]]="","",compras_mes2[[#This Row],[NETO GRAVADO]]*0.21) -> 1634.9508 | L65: 233.55 | O65: 777.95 | P65: =SUM(compras_mes2[[#This Row],[NETO GRAVADO]:[Otros / No Grav.]]) -> 10431.931 | Q65: =IFERROR(IF(compras_mes2[[#This Row],[CUIT]]="","-",VLOOKUP(compras_mes2[[#This Row],[CUIT]],Lista_CUIT[#All],3,0)),"CUIT NO CARGADO") -> Peaje | R65: =IFERROR(IF(compras_mes2[[#This Row],[CUIT]]="","-",VLOOKUP(compras_mes2[[#This Row],[CUIT]],Lista_CUIT[#All],4,0)),"CUIT NO CARGADO") -> 0
B66: 44595 | C66: 1 | D66: 943 | E66: 905455 | F66: 30639453975 | G66: =IFERROR(IF(compras_mes2[[#This Row],[CUIT]]="","-",VLOOKUP(compras_mes2[[#This Row],[CUIT]],Lista_CUIT[#All],2,0)),"CUIT NO CARGADO") -> TELEFONICA DE ARG S.A. | H66: 8114.92 | J66: 2191.03 | L66: 243.45 | O66: 486.9 | P66: =SUM(compras_mes2[[#This Row],[NETO GRAVADO]:[Otros / No Grav.]]) -> 11036.3 | Q66: =IFERROR(IF(compras_mes2[[#This Row],[CUIT]]="","-",VLOOKUP(compras_mes2[[#This Row],[CUIT]],Lista_CUIT[#All],3,0)),"CUIT NO CARGADO") -> Servicios Gas, Luz, etc. | R66: =IFERROR(IF(compras_mes2[[#This Row],[CUIT]]="","-",VLOOKUP(compras_mes2[[#This Row],[CUIT]],Lista_CUIT[#All],4,0)),"CUIT NO CARGADO") -> 0
B67: 44596 | C67: 1 | D67: 63 | E67: 1811974 | F67: 30640897267 | G67: =IFERROR(IF(compras_mes2[[#This Row],[CUIT]]="","-",VLOOKUP(compras_mes2[[#This Row],[CUIT]],Lista_CUIT[#All],2,0)),"CUIT NO CARGADO") -> TELECENTRO S.A. | H67: 4425.45 | I67: =IF(compras_mes2[[#This Row],[NETO GRAVADO]]="","",compras_mes2[[#This Row],[NETO GRAVADO]]*0.21) -> 929.3445 | L67: 132.76 | O67: 265.53 | P67: =SUM(compras_mes2[[#This Row],[NETO GRAVADO]:[Otros / No Grav.]]) -> 5753.0845 | Q67: =IFERROR(IF(compras_mes2[[#This Row],[CUIT]]="","-",VLOOKUP(compras_mes2[[#This Row],[CUIT]],Lista_CUIT[#All],3,0)),"CUIT NO CARGADO") -> Servicios Gas, Luz, etc. | R67: =IFERROR(IF(compras_mes2[[#This Row],[CUIT]]="","-",VLOOKUP(compras_mes2[[#This Row],[CUIT]],Lista_CUIT[#All],4,0)),"CUIT NO CARGADO") -> 0
B68: 44596 | C68: 1 | D68: 63 | E68: 1812122 | F68: 30640897267 | G68: =IFERROR(IF(compras_mes2[[#This Row],[CUIT]]="","-",VLOOKUP(compras_mes2[[#This Row],[CUIT]],Lista_CUIT[#All],2,0)),"CUIT NO CARGADO") -> TELECENTRO S.A. | H68: 4204.79 | I68: =IF(compras_mes2[[#This Row],[NETO GRAVADO]]="","",compras_mes2[[#This Row],[NETO GRAVADO]]*0.21) -> 883.0059 | L68: 126.14 | N68: 252.29 | P68: =SUM(compras_mes2[[#This Row],[NETO GRAVADO]:[Otros / No Grav.]]) -> 5466.2259 | Q68: =IFERROR(IF(compras_mes2[[#This Row],[CUIT]]="","-",VLOOKUP(compras_mes2[[#This Row],[CUIT]],Lista_CUIT[#All],3,0)),"CUIT NO CARGADO") -> Servicios Gas, Luz, etc. | R68: =IFERROR(IF(compras_mes2[[#This Row],[CUIT]]="","-",VLOOKUP(compras_mes2[[#This Row],[CUIT]],Lista_CUIT[#All],4,0)),"CUIT NO CARGADO") -> 0
B69: 44596 | C69: 1 | D69: 63 | E69: 1812560 | F69: 30640897267 | G69: =IFERROR(IF(compras_mes2[[#This Row],[CUIT]]="","-",VLOOKUP(compras_mes2[[#This Row],[CUIT]],Lista_CUIT[#All],2,0)),"CUIT NO CARGADO") -> TELECENTRO S.A. | H69: 4425.45 | I69: =IF(compras_mes2[[#This Row],[NETO GRAVADO]]="","",compras_mes2[[#This Row],[NETO GRAVADO]]*0.21) -> 929.3445 | L69: 132.76 | N69: 265.53 | P69: =SUM(compras_mes2[[#This Row],[NETO GRAVADO]:[Otros / No Grav.]]) -> 5753.0845 | Q69: =IFERROR(IF(compras_mes2[[#This Row],[CUIT]]="","-",VLOOKUP(compras_mes2[[#This Row],[CUIT]],Lista_CUIT[#All],3,0)),"CUIT NO CARGADO") -> Servicios Gas, Luz, etc. | R69: =IFERROR(IF(compras_mes2[[#This Row],[CUIT]]="","-",VLOOKUP(compras_mes2[[#This Row],[CUIT]],Lista_CUIT[#All],4,0)),"CUIT NO CARGADO") -> 0
B70: 44601 | C70: 1 | D70: 948 | E70: 568400 | F70: 30639453975 | G70: =IFERROR(IF(compras_mes2[[#This Row],[CUIT]]="","-",VLOOKUP(compras_mes2[[#This Row],[CUIT]],Lista_CUIT[#All],2,0)),"CUIT NO CARGADO") -> TELEFONICA DE ARG S.A. | H70: 2315.51 | I70: 625.19 | L70: 69.47 | N70: 138.93 | P70: =SUM(compras_mes2[[#This Row],[NETO GRAVADO]:[Otros / No Grav.]]) -> 3149.1 | Q70: =IFERROR(IF(compras_mes2[[#This Row],[CUIT]]="","-",VLOOKUP(compras_mes2[[#This Row],[CUIT]],Lista_CUIT[#All],3,0)),"CUIT NO CARGADO") -> Servicios Gas, Luz, etc. | R70: =IFERROR(IF(compras_mes2[[#This Row],[CUIT]]="","-",VLOOKUP(compras_mes2[[#This Row],[CUIT]],Lista_CUIT[#All],4,0)),"CUIT NO CARGADO") -> 0
B71: 44602 | C71: 1 | D71: 6364 | E71: 5760586 | F71: 30639453738 | G71: =IFERROR(IF(compras_mes2[[#This Row],[CUIT]]="","-",VLOOKUP(compras_mes2[[#This Row],[CUIT]],Lista_CUIT[#All],2,0)),"CUIT NO CARGADO") -> TELECOM ARG SA | H71: 31391.1 | I71: 6677.64 | O71: 2751.92 | P71: =SUM(compras_mes2[[#This Row],[NETO GRAVADO]:[Otros / No Grav.]]) -> 40820.66 | Q71: =IFERROR(IF(compras_mes2[[#This Row],[CUIT]]="","-",VLOOKUP(compras_mes2[[#This Row],[CUIT]],Lista_CUIT[#All],3,0)),"CUIT NO CARGADO") -> Servicios Gas, Luz, etc. | R71: =IFERROR(IF(compras_mes2[[#This Row],[CUIT]]="","-",VLOOKUP(compras_mes2[[#This Row],[CUIT]],Lista_CUIT[#All],4,0)),"CUIT NO CARGADO") -> 0
B72: 44599 | C72: 1 | D72: 2 | E72: 28981 | F72: 33714232199 | G72: =IFERROR(IF(compras_mes2[[#This Row],[CUIT]]="","-",VLOOKUP(compras_mes2[[#This Row],[CUIT]],Lista_CUIT[#All],2,0)),"CUIT NO CARGADO") -> NUAGE SYSTEMS S.A | H72: 16317 | I72: =IF(compras_mes2[[#This Row],[NETO GRAVADO]]="","",compras_mes2[[#This Row],[NETO GRAVADO]]*0.21) -> 3426.57 | P72: =SUM(compras_mes2[[#This Row],[NETO GRAVADO]:[Otros / No Grav.]]) -> 19743.57 | Q72: =IFERROR(IF(compras_mes2[[#This Row],[CUIT]]="","-",VLOOKUP(compras_mes2[[#This Row],[CUIT]],Lista_CUIT[#All],3,0)),"CUIT NO CARGADO") -> Servicios Informatica | R72: =IFERROR(IF(compras_mes2[[#This Row],[CUIT]]="","-",VLOOKUP(compras_mes2[[#This Row],[CUIT]],Lista_CUIT[#All],4,0)),"CUIT NO CARGADO") -> 0
B73: Total | H73: =SUBTOTAL(109,compras_mes2[NETO GRAVADO]) -> 3977617.5 | I73: =SUBTOTAL(109,compras_mes2[IVA 21 %]) -> 748978.97 | J73: =SUBTOTAL(109,compras_mes2[IVA 27%]) -> 2191.03 | K73: =SUBTOTAL(109,compras_mes2[IVA 10,5%]) -> 42125.25 | L73: =SUBTOTAL(109,compras_mes2[PERC. IVA]) -> 4724.39 | M73: =SUBTOTAL(109,compras_mes2[PERC IIBB BS AS]) -> 0 | N73: =SUBTOTAL(109,compras_mes2[PERC. IIBB CABA]) -> 50854.84 | O73: =SUBTOTAL(109,compras_mes2[Otros / No Grav.]) -> 18048.25 | P73: =SUBTOTAL(109,compras_mes2[TOTAL]) -> 4844540.2
D78: LIQUIDACION EXTRACTOS BANCARIOS-TARJETAS
D79: FECHA | E79: NRO CPTE | F79: BANCO | G79: NETO | H79: IVA 21% | I79: IVA 10,5% | J79: RET IIBB CABA | K79: PERC IVA | L79: PERC IIBB BS AS | M79: NO GRAV | N79: Reten. IBB
D80: 44620 | E80: 0308-00022022 | F80: BBVA - MASTERCARD | G80: 89881.11 | H80: 13291.26 | K80: 724.36 | N80: 107932.99
D81: 44594 | E81: 2331319 | F81: BBVA FRANCES | G81: 0 | H81: =extracto_banco_mes2[[#This Row],[NETO]]*0.21 -> 0 | M81: 3600.37
D82: 44594 | E82: 2331320 | F82: BBVA FRANCES | G82: 0 | H82: =extracto_banco_mes2[[#This Row],[NETO]]*0.21 -> 0 | M82: 8265.14
D83: 44594 | E83: 259141 | F83: BBVA FRANCES | G83: 6889.87 | H83: =extracto_banco_mes2[[#This Row],[NETO]]*0.21 -> 1446.8727 | K83: 206.69
D84: 44614 | E84: 7-22375350 | F84: AMERICAN EXPRES S.A. | G84: 7058.83 | H84: =extracto_banco_mes2[[#This Row],[NETO]]*0.21 -> 1482.3543 | J84: 4638.68 | K84: 119.33
D85: 44616 | E85: 1-96327078 | F85: BBVA FRANCES | G85: 6507.7 | I85: 811.03 | J85: 2898.59 | K85: 1763.39 | M85: 526.48
D86: 44620 | E86: 1-440360 | F86: BANCO GALICIA | G86: 320 | H86: =extracto_banco_mes2[[#This Row],[NETO]]*0.21 -> 67.2 | M86: 10.14
D87: 44620 | E87: 1-9242080 | F87: BBVA FRANCES | G87: 10495 | H87: =extracto_banco_mes2[[#This Row],[NETO]]*0.21 -> 2203.95 | K87: 314.85
D88: 44620 | E88: 2022 | F88: BBVA FRANCES | G88: 5840 | H88: =extracto_banco_mes2[[#This Row],[NETO]]*0.21 -> 1226.4 | J88: 259.8 | K88: 81.9 | L88: 32204.72 | M88: 65385.34
D89: 44620 | E89: 2022 | F89: BANCO GALICIA | G89: 3000 | H89: =extracto_banco_mes2[[#This Row],[NETO]]*0.21 -> 630 | J89: 180 | K89: 90 | L89: 1490.47 | M89: 3026.1
D90: 44620 | E90: 2022 | F90: BBVA FRANCES | G90: 355.37 | H90: =extracto_banco_mes2[[#This Row],[NETO]]*0.21 -> 74.6277 | J90: 6905.95 | M90: 15943.79
D91: 44620 | E91: 2022 | F91: BBVA FRANCES | G91: 707.85 | H91: =extracto_banco_mes2[[#This Row],[NETO]]*0.21 -> 148.6485 | J91: 3949.77
D92: Total | G92: =SUBTOTAL(109,extracto_banco_mes2[NETO]) -> 131055.73 | H92: =SUBTOTAL(109,extracto_banco_mes2[IVA 21%]) -> 20571.313 | I92: =SUBTOTAL(109,extracto_banco_mes2[IVA 10,5%]) -> 811.03 | J92: =SUBTOTAL(109,extracto_banco_mes2[RET IIBB CABA]) -> 18832.79 | K92: =SUBTOTAL(109,extracto_banco_mes2[PERC IVA]) -> 3300.52 | L92: =SUBTOTAL(109,extracto_banco_mes2[PERC IIBB BS AS]) -> 33695.19
M94: TOTAL IBA BCOS | N94: =extracto_banco_mes2[[#Totals],[IVA 21%]]+extracto_banco_mes2[[#Totals],[IVA 10,5%]] -> 21382.343
D96: FACTURAS C
D97: FECHA | E97: PTO VTA | F97: FC Nº | G97: CUIT | H97: RAZON SOCIAL | I97: TOTAL | J97: TIPO DE GASTO | K97: Provincia
D98: 44599 | E98: 2 | F98: 2769 | G98: 20136536320 | H98: =IFERROR(IF(factura_c_mes2[[#This Row],[CUIT]]="","-",VLOOKUP(factura_c_mes2[[#This Row],[CUIT]],Lista_CUIT[#All],2,0)),"CUIT NO CARGADO") -> FONTENLA ERNESTO MARIO | I98: 2000 | J98: =IFERROR(IF(factura_c_mes2[[#This Row],[CUIT]]="","-",VLOOKUP(factura_c_mes2[[#This Row],[CUIT]],Lista_CUIT[#All],3,0)),"CUIT NO CARGADO") -> Gastos Varios | K98: =IFERROR(IF(factura_c_mes2[[#This Row],[CUIT]]="","-",VLOOKUP(factura_c_mes2[[#This Row],[CUIT]],Lista_CUIT[#All],4,0)),"CUIT NO CARGADO") -> 0
D99: 44599 | E99: 2 | F99: 2774 | G99: 20136536320 | H99: =IFERROR(IF(factura_c_mes2[[#This Row],[CUIT]]="","-",VLOOKUP(factura_c_mes2[[#This Row],[CUIT]],Lista_CUIT[#All],2,0)),"CUIT NO CARGADO") -> FONTENLA ERNESTO MARIO | I99: 300 | J99: =IFERROR(IF(factura_c_mes2[[#This Row],[CUIT]]="","-",VLOOKUP(factura_c_mes2[[#This Row],[CUIT]],Lista_CUIT[#All],3,0)),"CUIT NO CARGADO") -> Gastos Varios | K99: =IFERROR(IF(factura_c_mes2[[#This Row],[CUIT]]="","-",VLOOKUP(factura_c_mes2[[#This Row],[CUIT]],Lista_CUIT[#All],4,0)),"CUIT NO CARGADO") -> 0
D100: 44616 | E100: 4 | F100: 172 | G100: 30686965801 | H100: =IFERROR(IF(factura_c_mes2[[#This Row],[CUIT]]="","-",VLOOKUP(factura_c_mes2[[#This Row],[CUIT]],Lista_CUIT[#All],2,0)),"CUIT NO CARGADO") -> FEDERACION ARG DE COSMETOLO | I100: 10000 | J100: =IFERROR(IF(factura_c_mes2[[#This Row],[CUIT]]="","-",VLOOKUP(factura_c_mes2[[#This Row],[CUIT]],Lista_CUIT[#All],3,0)),"CUIT NO CARGADO") -> Gastos Cursos | K100: =IFERROR(IF(factura_c_mes2[[#This Row],[CUIT]]="","-",VLOOKUP(factura_c_mes2[[#This Row],[CUIT]],Lista_CUIT[#All],4,0)),"CUIT NO CARGADO") -> 0
D101: 44616 | E101: 1 | F101: 208 | G101: 27343113914 | H101: =IFERROR(IF(factura_c_mes2[[#This Row],[CUIT]]="","-",VLOOKUP(factura_c_mes2[[#This Row],[CUIT]],Lista_CUIT[#All],2,0)),"CUIT NO CARGADO") -> VALORIANI ROMINA GISELA | I101: 19800 | J101: =IFERROR(IF(factura_c_mes2[[#This Row],[CUIT]]="","-",VLOOKUP(factura_c_mes2[[#This Row],[CUIT]],Lista_CUIT[#All],3,0)),"CUIT NO CARGADO") -> Servicios Informatica | K101: =IFERROR(IF(factura_c_mes2[[#This Row],[CUIT]]="","-",VLOOKUP(factura_c_mes2[[#This Row],[CUIT]],Lista_CUIT[#All],4,0)),"CUIT NO CARGADO") -> 0
D102: Total | I102: =SUBTOTAL(109,factura_c_mes2[TOTAL]) -> 32100
B108: LIBRO IVA VENTAS | K108: =N1 -> 44593
B110: VENTAS "A"
B111: FECHA | C111: TIPO | D111: PTO VENTA | E111: Nº FACTURA | F111: CUIT | G111: RAZON SOCIAL | H111: IMPORTE NETO | I111: IVA 21% | J111: IVA 10,5% | K111: EXENTO | L111: TOTAL | M111: Provincia
G112: =IFERROR(IF(venta_a_mes2[[#This Row],[CUIT]]="","-",VLOOKUP(venta_a_mes2[[#This Row],[CUIT]],Lista_CUIT[#All],2,0)),"CUIT NO CARGADO") -> - | I112: =venta_a_mes2[[#This Row],[IMPORTE NETO]]*0.21 -> 0 | L112: =SUM(venta_a_mes2[[#This Row],[IMPORTE NETO]:[EXENTO]]) -> 0
G113: =IFERROR(IF(venta_a_mes2[[#This Row],[CUIT]]="","-",VLOOKUP(venta_a_mes2[[#This Row],[CUIT]],Lista_CUIT[#All],2,0)),"CUIT NO CARGADO") -> - | I113: =venta_a_mes2[[#This Row],[IMPORTE NETO]]*0.21 -> 0 | L113: =SUM(venta_a_mes2[[#This Row],[IMPORTE NETO]:[EXENTO]]) -> 0
G114: =IFERROR(IF(venta_a_mes2[[#This Row],[CUIT]]="","-",VLOOKUP(venta_a_mes2[[#This Row],[CUIT]],Lista_CUIT[#All],2,0)),"CUIT NO CARGADO") -> - | I114: =venta_a_mes2[[#This Row],[IMPORTE NETO]]*0.21 -> 0 | L114: =SUM(venta_a_mes2[[#This Row],[IMPORTE NETO]:[EXENTO]]) -> 0
G115: =IFERROR(IF(venta_a_mes2[[#This Row],[CUIT]]="","-",VLOOKUP(venta_a_mes2[[#This Row],[CUIT]],Lista_CUIT[#All],2,0)),"CUIT NO CARGADO") -> - | I115: =venta_a_mes2[[#This Row],[IMPORTE NETO]]*0.21 -> 0 | L115: =SUM(venta_a_mes2[[#This Row],[IMPORTE NETO]:[EXENTO]]) -> 0
G116: =IFERROR(IF(venta_a_mes2[[#This Row],[CUIT]]="","-",VLOOKUP(venta_a_mes2[[#This Row],[CUIT]],Lista_CUIT[#All],2,0)),"CUIT NO CARGADO") -> - | I116: =venta_a_mes2[[#This Row],[IMPORTE NETO]]*0.21 -> 0 | L116: =SUM(venta_a_mes2[[#This Row],[IMPORTE NETO]:[EXENTO]]) -> 0
...

Sheet Marz-22
B1: LIBRO IVA COMPRAS | G1: EUROARGENTINA | N1: =EDATE('Ene-22'!N1,2) -> 44621
B3: TOTAL COMPRAS | G3: TOTAL CREDITO FISCAL | J3: TOTAL VENTAS NETAS | M3: TOTAL DEBITO FISCAL | P3: RESULTADO
B4: =SUM(compras_mes13[[#Totals],[NETO GRAVADO]])+extracto_banco_mes155[[#Totals],[NETO]] -> 3718075.6 | G4: =compras_mes13[[#Totals],[IVA 21 %]]+compras_mes13[[#Totals],[IVA 27%]]+compras_mes13[[#Totals],[IVA 10,5%]]+extracto_banco_mes155[[#Totals],[IVA 21%]]+extracto_banco_mes155[[#Totals],[IVA 10,5%]] -> 776457.13 | J4: =venta_a_mes153[[#Totals],[IMPORTE NETO]]+ventas_b_mes154[[#Totals],[IMPORTE NETO]] -> 0 | M4: =venta_a_mes153[[#Totals],[IVA 21%]]+venta_a_mes153[[#Totals],[IVA 10,5%]]+ventas_b_mes154[[#Totals],[IVA 21%]]+ventas_b_mes154[[#Totals],[IVA 10,5%]] -> 0 | P4: =G4-M4 -> 776457.13
B8: FECHA | C8: TIPO | D8: PTO VTA | E8: NRO. CPTE | F8: CUIT | G8: RAZON SOCIAL | H8: NETO GRAVADO | I8: IVA 21 % | J8: IVA 27% | K8: IVA 10,5% | L8: PERC. IVA | M8: PERC IIBB BS AS | N8: PERC. IIBB CABA | O8: Otros / No Grav. | P8: TOTAL | Q8: Tipo de Gasto | R8: Provincia
B9: 44649 | C9: 1 | D9: 3008 | E9: 259688 | F9: 30703088534 | G9: =IFERROR(IF(compras_mes13[[#This Row],[CUIT]]="","-",VLOOKUP(compras_mes13[[#This Row],[CUIT]],Lista_CUIT[#All],2,0)),"CUIT NO CARGADO") -> MERCADO LIBRE SRL | H9: 91269.71 | I9: =IF(compras_mes13[[#This Row],[NETO GRAVADO]]="","",compras_mes13[[#This Row],[NETO GRAVADO]]*0.21) -> 19166.639 | O9: 0 | P9: =SUM(compras_mes13[[#This Row],[NETO GRAVADO]:[Otros / No Grav.]]) -> 110436.35 | Q9: =IFERROR(IF(compras_mes13[[#This Row],[CUIT]]="","-",VLOOKUP(compras_mes13[[#This Row],[CUIT]],Lista_CUIT[#All],3,0)),"CUIT NO CARGADO") -> Gtos Comercializacion | R9: =IFERROR(IF(compras_mes13[[#This Row],[CUIT]]="","-",VLOOKUP(compras_mes13[[#This Row],[CUIT]],Lista_CUIT[#All],4,0)),"CUIT NO CARGADO") -> 0
B10: 44649 | C10: 3 | D10: 27 | E10: 20890 | F10: 30703088534 | G10: =IFERROR(IF(compras_mes13[[#This Row],[CUIT]]="","-",VLOOKUP(compras_mes13[[#This Row],[CUIT]],Lista_CUIT[#All],2,0)),"CUIT NO CARGADO") -> MERCADO LIBRE SRL | H10: -119.67 | I10: =IF(compras_mes13[[#This Row],[NETO GRAVADO]]="","",compras_mes13[[#This Row],[NETO GRAVADO]]*0.21) -> -25.1307 | O10: 0 | P10: =SUM(compras_mes13[[#This Row],[NETO GRAVADO]:[Otros / No Grav.]]) -> -144.8007 | Q10: =IFERROR(IF(compras_mes13[[#This Row],[CUIT]]="","-",VLOOKUP(compras_mes13[[#This Row],[CUIT]],Lista_CUIT[#All],3,0)),"CUIT NO CARGADO") -> Gtos Comercializacion | R10: =IFERROR(IF(compras_mes13[[#This Row],[CUIT]]="","-",VLOOKUP(compras_mes13[[#This Row],[CUIT]],Lista_CUIT[#All],4,0)),"CUIT NO CARGADO") -> 0
B11: 44642 | C11: 1 | D11: 10 | E11: 21598 | F11: 20172002448 | G11: =IFERROR(IF(compras_mes13[[#This Row],[CUIT]]="","-",VLOOKUP(compras_mes13[[#This Row],[CUIT]],Lista_CUIT[#All],2,0)),"CUIT NO CARGADO") -> ALVAREZ MIGUEL ANGEL | H11: 5286.03 | I11: =IF(compras_mes13[[#This Row],[NETO GRAVADO]]="","",compras_mes13[[#This Row],[NETO GRAVADO]]*0.21) -> 1110.0663 | O11: 0 | P11: =SUM(compras_mes13[[#This Row],[NETO GRAVADO]:[Otros / No Grav.]]) -> 6396.0963 | Q11: =IFERROR(IF(compras_mes13[[#This Row],[CUIT]]="","-",VLOOKUP(compras_mes13[[#This Row],[CUIT]],Lista_CUIT[#All],3,0)),"CUIT NO CARGADO") -> Librería | R11: =IFERROR(IF(compras_mes13[[#This Row],[CUIT]]="","-",VLOOKUP(compras_mes13[[#This Row],[CUIT]],Lista_CUIT[#All],4,0)),"CUIT NO CARGADO") -> CABA
B12: 44642 | C12: 1 | D12: 10 | E12: 21599 | F12: 20172002448 | G12: =IFERROR(IF(compras_mes13[[#This Row],[CUIT]]="","-",VLOOKUP(compras_mes13[[#This Row],[CUIT]],Lista_CUIT[#All],2,0)),"CUIT NO CARGADO") -> ALVAREZ MIGUEL ANGEL | H12: 5286.03 | I12: =IF(compras_mes13[[#This Row],[NETO GRAVADO]]="","",compras_mes13[[#This Row],[NETO GRAVADO]]*0.21) -> 1110.0663 | O12: 0 | P12: =SUM(compras_mes13[[#This Row],[NETO GRAVADO]:[Otros / No Grav.]]) -> 6396.0963 | Q12: =IFERROR(IF(compras_mes13[[#This Row],[CUIT]]="","-",VLOOKUP(compras_mes13[[#This Row],[CUIT]],Lista_CUIT[#All],3,0)),"CUIT NO CARGADO") -> Librería | R12: =IFERROR(IF(compras_mes13[[#This Row],[CUIT]]="","-",VLOOKUP(compras_mes13[[#This Row],[CUIT]],Lista_CUIT[#All],4,0)),"CUIT NO CARGADO") -> CABA
B13: 44642 | C13: 1 | D13: 10 | E13: 21603 | F13: 20172002448 | G13: =IFERROR(IF(compras_mes13[[#This Row],[CUIT]]="","-",VLOOKUP(compras_mes13[[#This Row],[CUIT]],Lista_CUIT[#All],2,0)),"CUIT NO CARGADO") -> ALVAREZ MIGUEL ANGEL | H13: 5286.03 | I13: =IF(compras_mes13[[#This Row],[NETO GRAVADO]]="","",compras_mes13[[#This Row],[NETO GRAVADO]]*0.21) -> 1110.0663 | O13: 0 | P13: =SUM(compras_mes13[[#This Row],[NETO GRAVADO]:[Otros / No Grav.]]) -> 6396.0963 | Q13: =IFERROR(IF(compras_mes13[[#This Row],[CUIT]]="","-",VLOOKUP(compras_mes13[[#This Row],[CUIT]],Lista_CUIT[#All],3,0)),"CUIT NO CARGADO") -> Librería | R13: =IFERROR(IF(compras_mes13[[#This Row],[CUIT]]="","-",VLOOKUP(compras_mes13[[#This Row],[CUIT]],Lista_CUIT[#All],4,0)),"CUIT NO CARGADO") -> CABA
B14: 44651 | C14: 1 | D14: 20 | E14: 739 | F14: 30674346227 | G14: =IFERROR(IF(compras_mes13[[#This Row],[CUIT]]="","-",VLOOKUP(compras_mes13[[#This Row],[CUIT]],Lista_CUIT[#All],2,0)),"CUIT NO CARGADO") -> IMPRESORA DEL NEA S.A. | H14: 2231.4 | I14: =IF(compras_mes13[[#This Row],[NETO GRAVADO]]="","",compras_mes13[[#This Row],[NETO GRAVADO]]*0.21) -> 468.594 | O14: 0 | P14: =SUM(compras_mes13[[#This Row],[NETO GRAVADO]:[Otros / No Grav.]]) -> 2699.994 | Q14: =IFERROR(IF(compras_mes13[[#This Row],[CUIT]]="","-",VLOOKUP(compras_mes13[[#This Row],[CUIT]],Lista_CUIT[#All],3,0)),"CUIT NO CARGADO") -> Librería | R14: =IFERROR(IF(compras_mes13[[#This Row],[CUIT]]="","-",VLOOKUP(compras_mes13[[#This Row],[CUIT]],Lista_CUIT[#All],4,0)),"CUIT NO CARGADO") -> 0
B15: 44650 | C15: 1 | D15: 5 | E15: 25210 | F15: 30708261110 | G15: =IFERROR(IF(compras_mes13[[#This Row],[CUIT]]="","-",VLOOKUP(compras_mes13[[#This Row],[CUIT]],Lista_CUIT[#All],2,0)),"CUIT NO CARGADO") -> MULTIPLES S.R.L | H15: 44677.5 | I15: =IF(compras_mes13[[#This Row],[NETO GRAVADO]]="","",compras_mes13[[#This Row],[NETO GRAVADO]]*0.21) -> 9382.275 | O15: 0 | P15: =SUM(compras_mes13[[#This Row],[NETO GRAVADO]:[Otros / No Grav.]]) -> 54059.775 | Q15: =IFERROR(IF(compras_mes13[[#This Row],[CUIT]]="","-",VLOOKUP(compras_mes13[[#This Row],[CUIT]],Lista_CUIT[#All],3,0)),"CUIT NO CARGADO") -> Librería | R15: =IFERROR(IF(compras_mes13[[#This Row],[CUIT]]="","-",VLOOKUP(compras_mes13[[#This Row],[CUIT]],Lista_CUIT[#All],4,0)),"CUIT NO CARGADO") -> 0
B16: 44650 | C16: 1 | D16: 10 | E16: 1183 | F16: 23127284369 | G16: =IFERROR(IF(compras_mes13[[#This Row],[CUIT]]="","-",VLOOKUP(compras_mes13[[#This Row],[CUIT]],Lista_CUIT[#All],2,0)),"CUIT NO CARGADO") -> DEALER FX - MONTORRO D. | H16: 8941.72 | I16: =IF(compras_mes13[[#This Row],[NETO GRAVADO]]="","",compras_mes13[[#This Row],[NETO GRAVADO]]*0.21) -> 1877.7612 | O16: 0 | P16: =SUM(compras_mes13[[#This Row],[NETO GRAVADO]:[Otros / No Grav.]]) -> 10819.481 | Q16: =IFERROR(IF(compras_mes13[[#This Row],[CUIT]]="","-",VLOOKUP(compras_mes13[[#This Row],[CUIT]],Lista_CUIT[#All],3,0)),"CUIT NO CARGADO") -> Librería | R16: =IFERROR(IF(compras_mes13[[#This Row],[CUIT]]="","-",VLOOKUP(compras_mes13[[#This Row],[CUIT]],Lista_CUIT[#All],4,0)),"CUIT NO CARGADO") -> 0
B17: 44624 | C17: 1 | D17: 9 | E17: 2067 | F17: 30715173030 | G17: =IFERROR(IF(compras_mes13[[#This Row],[CUIT]]="","-",VLOOKUP(compras_mes13[[#This Row],[CUIT]],Lista_CUIT[#All],2,0)),"CUIT NO CARGADO") -> AUTOGEN S.A. | H17: 19338.84 | I17: =IF(compras_mes13[[#This Row],[NETO GRAVADO]]="","",compras_mes13[[#This Row],[NETO GRAVADO]]*0.21) -> 4061.1564 | O17: 0 | P17: =SUM(compras_mes13[[#This Row],[NETO GRAVADO]:[Otros / No Grav.]]) -> 23399.996 | Q17: =IFERROR(IF(compras_mes13[[#This Row],[CUIT]]="","-",VLOOKUP(compras_mes13[[#This Row],[CUIT]],Lista_CUIT[#All],3,0)),"CUIT NO CARGADO") -> Mantenimiento Auto | R17: =IFERROR(IF(compras_mes13[[#This Row],[CUIT]]="","-",VLOOKUP(compras_mes13[[#This Row],[CUIT]],Lista_CUIT[#All],4,0)),"CUIT NO CARGADO") -> 0
B18: 44630 | C18: 1 | D18: 4 | E18: 104 | F18: 30715833979 | G18: =IFERROR(IF(compras_mes13[[#This Row],[CUIT]]="","-",VLOOKUP(compras_mes13[[#This Row],[CUIT]],Lista_CUIT[#All],2,0)),"CUIT NO CARGADO") -> INTERICCHIA HNOS. SRL | H18: 84297.52 | I18: =IF(compras_mes13[[#This Row],[NETO GRAVADO]]="","",compras_mes13[[#This Row],[NETO GRAVADO]]*0.21) -> 17702.479 | O18: 0 | P18: =SUM(compras_mes13[[#This Row],[NETO GRAVADO]:[Otros / No Grav.]]) -> 102000 | Q18: =IFERROR(IF(compras_mes13[[#This Row],[CUIT]]="","-",VLOOKUP(compras_mes13[[#This Row],[CUIT]],Lista_CUIT[#All],3,0)),"CUIT NO CARGADO") -> Mantenimiento | R18: =IFERROR(IF(compras_mes13[[#This Row],[CUIT]]="","-",VLOOKUP(compras_mes13[[#This Row],[CUIT]],Lista_CUIT[#All],4,0)),"CUIT NO CARGADO") -> BS AS
B19: 44626 | C19: 1 | D19: 1 | E19: 2119 | F19: 30717030679 | G19: =IFERROR(IF(compras_mes13[[#This Row],[CUIT]]="","-",VLOOKUP(compras_mes13[[#This Row],[CUIT]],Lista_CUIT[#All],2,0)),"CUIT NO CARGADO") -> MOTOMERCADO S.A. | H19: 3214.88 | I19: =IF(compras_mes13[[#This Row],[NETO GRAVADO]]="","",compras_mes13[[#This Row],[NETO GRAVADO]]*0.21) -> 675.1248 | O19: 0 | P19: =SUM(compras_mes13[[#This Row],[NETO GRAVADO]:[Otros / No Grav.]]) -> 3890.0048 | Q19: =IFERROR(IF(compras_mes13[[#This Row],[CUIT]]="","-",VLOOKUP(compras_mes13[[#This Row],[CUIT]],Lista_CUIT[#All],3,0)),"CUIT NO CARGADO") -> Mantenimiento Auto | R19: =IFERROR(IF(compras_mes13[[#This Row],[CUIT]]="","-",VLOOKUP(compras_mes13[[#This Row],[CUIT]],Lista_CUIT[#All],4,0)),"CUIT NO CARGADO") -> SANTA FE
B20: 44603 | C20: 1 | D20: 9 | E20: 143 | F20: 30709330760 | G20: =IFERROR(IF(compras_mes13[[#This Row],[CUIT]]="","-",VLOOKUP(compras_mes13[[#This Row],[CUIT]],Lista_CUIT[#All],2,0)),"CUIT NO CARGADO") -> DENETOR S.A. | H20: 1366.95 | I20: =IF(compras_mes13[[#This Row],[NETO GRAVADO]]="","",compras_mes13[[#This Row],[NETO GRAVADO]]*0.21) -> 287.0595 | O20: 0 | P20: =SUM(compras_mes13[[#This Row],[NETO GRAVADO]:[Otros / No Grav.]]) -> 1654.0095 | Q20: =IFERROR(IF(compras_mes13[[#This Row],[CUIT]]="","-",VLOOKUP(compras_mes13[[#This Row],[CUIT]],Lista_CUIT[#All],3,0)),"CUIT NO CARGADO") -> Mercaderia | R20: =IFERROR(IF(compras_mes13[[#This Row],[CUIT]]="","-",VLOOKUP(compras_mes13[[#This Row],[CUIT]],Lista_CUIT[#All],4,0)),"CUIT NO CARGADO") -> CABA
... B35: 44637 | C35: 1 | D35: 1665 | E35: 15095 | F35: 30589621499 | G35: =IFERROR(IF(compras_mes13[[#This Row],[CUIT]]="","-",VLOOKUP(compras_mes13[[#This Row],[CUIT]],Lista_CUIT[#All],2,0)),"CUIT NO CARGADO") -> MAKRO SA | H35: 38223.92 | I35: =IF(compras_mes13[[#This Row],[NETO GRAVADO]]="","",compras_mes13[[#This Row],[NETO GRAVADO]]*0.21) -> 8027.0232 | O35: 3.37 | P35: =SUM(compras_mes13[[#This Row],[NETO GRAVADO]:[Otros / No Grav.]]) -> 46254.313 | Q35: =IFERROR(IF(compras_mes13[[#This Row],[CUIT]]="","-",VLOOKUP(compras_mes13[[#This Row],[CUIT]],Lista_CUIT[#All],3,0)),"CUIT NO CARGADO") -> Comida-Limpieza | R35: =IFERROR(IF(compras_mes13[[#This Row],[CUIT]]="","-",VLOOKUP(compras_mes13[[#This Row],[CUIT]],Lista_CUIT[#All],4,0)),"CUIT NO CARGADO") -> 0
B36: 44643 | C36: 1 | D36: 6 | E36: 2253 | F36: 20117862578 | G36: =IFERROR(IF(compras_mes13[[#This Row],[CUIT]]="","-",VLOOKUP(compras_mes13[[#This Row],[CUIT]],Lista_CUIT[#All],2,0)),"CUIT NO CARGADO") -> PORCO VICTOR ALBERTO | H36: 1652.9 | I36: 424 | L36: 269.24 | O36: 65.05 | P36: =SUM(compras_mes13[[#This Row],[NETO GRAVADO]:[Otros / No Grav.]]) -> 2411.19 | Q36: =IFERROR(IF(compras_mes13[[#This Row],[CUIT]]="","-",VLOOKUP(compras_mes13[[#This Row],[CUIT]],Lista_CUIT[#All],3,0)),"CUIT NO CARGADO") -> Ferreteria | R36: =IFERROR(IF(compras_mes13[[#This Row],[CUIT]]="","-",VLOOKUP(compras_mes13[[#This Row],[CUIT]],Lista_CUIT[#All],4,0)),"CUIT NO CARGADO") -> 0
B37: 44650 | C37: 1 | D37: 2406 | E37: 80336 | F37: 30692296377 | G37: =IFERROR(IF(compras_mes13[[#This Row],[CUIT]]="","-",VLOOKUP(compras_mes13[[#This Row],[CUIT]],Lista_CUIT[#All],2,0)),"CUIT NO CARGADO") -> CORREO ARGENTINO S.A. | H37: 8.26 | I37: 6760.63 | L37: 953.21 | M37: 1735.12 | O37: 99.14 | P37: =SUM(compras_mes13[[#This Row],[NETO GRAVADO]:[Otros / No Grav.]]) -> 9556.36 | Q37: =IFERROR(IF(compras_mes13[[#This Row],[CUIT]]="","-",VLOOKUP(compras_mes13[[#This Row],[CUIT]],Lista_CUIT[#All],3,0)),"CUIT NO CARGADO") -> Flete-Logistica | R37: =IFERROR(IF(compras_mes13[[#This Row],[CUIT]]="","-",VLOOKUP(compras_mes13[[#This Row],[CUIT]],Lista_CUIT[#All],4,0)),"CUIT NO CARGADO") -> 0
B38: 44645 | C38: 1 | D38: 8257 | E38: 3565 | F38: 30590360763 | G38: =IFERROR(IF(compras_mes13[[#This Row],[CUIT]]="","-",VLOOKUP(compras_mes13[[#This Row],[CUIT]],Lista_CUIT[#All],2,0)),"CUIT NO CARGADO") -> CENCOSUD S.A | H38: 491.74 | I38: 7907.63 | L38: 1129.65 | N38: 2543.6 | O38: 148.24 | P38: =SUM(compras_mes13[[#This Row],[NETO GRAVADO]:[Otros / No Grav.]]) -> 12220.86 | Q38: =IFERROR(IF(compras_mes13[[#This Row],[CUIT]]="","-",VLOOKUP(compras_mes13[[#This Row],[CUIT]],Lista_CUIT[#All],3,0)),"CUIT NO CARGADO") -> Gastos Varios | R38: =IFERROR(IF(compras_mes13[[#This Row],[CUIT]]="","-",VLOOKUP(compras_mes13[[#This Row],[CUIT]],Lista_CUIT[#All],4,0)),"CUIT NO CARGADO") -> 0
B39: 44627 | C39: 1 | D39: 1 | E39: 52 | F39: 20077604627 | G39: =IFERROR(IF(compras_mes13[[#This Row],[CUIT]]="","-",VLOOKUP(compras_mes13[[#This Row],[CUIT]],Lista_CUIT[#All],2,0)),"CUIT NO CARGADO") -> OCAÑO ENRIQUE | H39: 104887.2 | I39: =IF(compras_mes13[[#This Row],[NETO GRAVADO]]="","",compras_mes13[[#This Row],[NETO GRAVADO]]*0.21) -> 22026.312 | O39: 550.33 | P39: =SUM(compras_mes13[[#This Row],[NETO GRAVADO]:[Otros / No Grav.]]) -> 127463.84 | Q39: =IFERROR(IF(compras_mes13[[#This Row],[CUIT]]="","-",VLOOKUP(compras_mes13[[#This Row],[CUIT]],Lista_CUIT[#All],3,0)),"CUIT NO CARGADO") -> Mercaderia | R39: =IFERROR(IF(compras_mes13[[#This Row],[CUIT]]="","-",VLOOKUP(compras_mes13[[#This Row],[CUIT]],Lista_CUIT[#All],4,0)),"CUIT NO CARGADO") -> 0
B40: 44631 | C40: 1 | D40: 1313 | E40: 573 | F40: 30639057999 | G40: =IFERROR(IF(compras_mes13[[#This Row],[CUIT]]="","-",VLOOKUP(compras_mes13[[#This Row],[CUIT]],Lista_CUIT[#All],2,0)),"CUIT NO CARGADO") -> LA OPTICA S.A. | H40: 13328.93 | I40: =IF(compras_mes13[[#This Row],[NETO GRAVADO]]="","",compras_mes13[[#This Row],[NETO GRAVADO]]*0.21) -> 2799.0753 | O40: 917.1 | P40: =SUM(compras_mes13[[#This Row],[NETO GRAVADO]:[Otros / No Grav.]]) -> 17045.105 | Q40: =IFERROR(IF(compras_mes13[[#This Row],[CUIT]]="","-",VLOOKUP(compras_mes13[[#This Row],[CUIT]],Lista_CUIT[#All],3,0)),"CUIT NO CARGADO") -> Gastos Varios | R40: =IFERROR(IF(compras_mes13[[#This Row],[CUIT]]="","-",VLOOKUP(compras_mes13[[#This Row],[CUIT]],Lista_CUIT[#All],4,0)),"CUIT NO CARGADO") -> CABA
B41: 44644 | C41: 1 | D41: 8 | E41: 1530 | F41: 30712450327 | G41: =IFERROR(IF(compras_mes13[[#This Row],[CUIT]]="","-",VLOOKUP(compras_mes13[[#This Row],[CUIT]],Lista_CUIT[#All],2,0)),"CUIT NO CARGADO") -> MANDOLA HERMANOS S.A. | H41: 9058.01 | I41: =IF(compras_mes13[[#This Row],[NETO GRAVADO]]="","",compras_mes13[[#This Row],[NETO GRAVADO]]*0.21) -> 1902.1821 | O41: 1042.49 | P41: =SUM(compras_mes13[[#This Row],[NETO GRAVADO]:[Otros / No Grav.]]) -> 12002.682 | Q41: =IFERROR(IF(compras_mes13[[#This Row],[CUIT]]="","-",VLOOKUP(compras_mes13[[#This Row],[CUIT]],Lista_CUIT[#All],3,0)),"CUIT NO CARGADO") -> Combustible | R41: =IFERROR(IF(compras_mes13[[#This Row],[CUIT]]="","-",VLOOKUP(compras_mes13[[#This Row],[CUIT]],Lista_CUIT[#All],4,0)),"CUIT NO CARGADO") -> 0
B42: 44630 | C42: 1 | D42: 6364 | E42: 5906592 | F42: 30639453738 | G42: =IFERROR(IF(compras_mes13[[#This Row],[CUIT]]="","-",VLOOKUP(compras_mes13[[#This Row],[CUIT]],Lista_CUIT[#All],2,0)),"CUIT NO CARGADO") -> TELECOM ARG SA | H42: 31773.15 | I42: =IF(compras_mes13[[#This Row],[NETO GRAVADO]]="","",compras_mes13[[#This Row],[NETO GRAVADO]]*0.21) -> 6672.3615 | O42: 1790 | P42: =SUM(compras_mes13[[#This Row],[NETO GRAVADO]:[Otros / No Grav.]]) -> 40235.512 | Q42: =IFERROR(IF(compras_mes13[[#This Row],[CUIT]]="","-",VLOOKUP(compras_mes13[[#This Row],[CUIT]],Lista_CUIT[#All],3,0)),"CUIT NO CARGADO") -> Servicios Gas, Luz, etc. | R42: =IFERROR(IF(compras_mes13[[#This Row],[CUIT]]="","-",VLOOKUP(compras_mes13[[#This Row],[CUIT]],Lista_CUIT[#All],4,0)),"CUIT NO CARGADO") -> 0
B43: 44605 | C43: 1 | D43: 10 | E43: 37737 | F43: 20130138005 | G43: =IFERROR(IF(compras_mes13[[#This Row],[CUIT]]="","-",VLOOKUP(compras_mes13[[#This Row],[CUIT]],Lista_CUIT[#All],2,0)),"CUIT NO CARGADO") -> YPF KM 296 | H43: 3849.16 | I43: =IF(compras_mes13[[#This Row],[NETO GRAVADO]]="","",compras_mes13[[#This Row],[NETO GRAVADO]]*0.21) -> 808.3236 | O43: 1860.8 | P43: =SUM(compras_mes13[[#This Row],[NETO GRAVADO]:[Otros / No Grav.]]) -> 6518.2836 | Q43: =IFERROR(IF(compras_mes13[[#This Row],[CUIT]]="","-",VLOOKUP(compras_mes13[[#This Row],[CUIT]],Lista_CUIT[#All],3,0)),"CUIT NO CARGADO") -> Combustible | R43: =IFERROR(IF(compras_mes13[[#This Row],[CUIT]]="","-",VLOOKUP(compras_mes13[[#This Row],[CUIT]],Lista_CUIT[#All],4,0)),"CUIT NO CARGADO") -> 0
B44: 44623 | C44: 1 | D44: 1 | E44: 51 | F44: 20077604627 | G44: =IFERROR(IF(compras_mes13[[#This Row],[CUIT]]="","-",VLOOKUP(compras_mes13[[#This Row],[CUIT]],Lista_CUIT[#All],2,0)),"CUIT NO CARGADO") -> OCAÑO ENRIQUE | H44: 85816.8 | I44: =IF(compras_mes13[[#This Row],[NETO GRAVADO]]="","",compras_mes13[[#This Row],[NETO GRAVADO]]*0.21) -> 18021.528 | O44: 1885.16 | P44: =SUM(compras_mes13[[#This Row],[NETO GRAVADO]:[Otros / No Grav.]]) -> 105723.49 | Q44: =IFERROR(IF(compras_mes13[[#This Row],[CUIT]]="","-",VLOOKUP(compras_mes13[[#This Row],[CUIT]],Lista_CUIT[#All],3,0)),"CUIT NO CARGADO") -> Mercaderia | R44: =IFERROR(IF(compras_mes13[[#This Row],[CUIT]]="","-",VLOOKUP(compras_mes13[[#This Row],[CUIT]],Lista_CUIT[#All],4,0)),"CUIT NO CARGADO") -> 0
B45: 44636 | C45: 1 | D45: 5 | E45: 37 | F45: 30707949550 | G45: =IFERROR(IF(compras_mes13[[#This Row],[CUIT]]="","-",VLOOKUP(compras_mes13[[#This Row],[CUIT]],Lista_CUIT[#All],2,0)),"CUIT NO CARGADO") -> LNG GAS S.A. | H45: 7302.44 | I45: =IF(compras_mes13[[#This Row],[NETO GRAVADO]]="","",compras_mes13[[#This Row],[NETO GRAVADO]]*0.21) -> 1533.5124 | O45: 3600.37 | P45: =SUM(compras_mes13[[#This Row],[NETO GRAVADO]:[Otros / No Grav.]]) -> 12436.322 | Q45: =IFERROR(IF(compras_mes13[[#This Row],[CUIT]]="","-",VLOOKUP(compras_mes13[[#This Row],[CUIT]],Lista_CUIT[#All],3,0)),"CUIT NO CARGADO") -> Combustible | R45: =IFERROR(IF(compras_mes13[[#This Row],[CUIT]]="","-",VLOOKUP(compras_mes13[[#This Row],[CUIT]],Lista_CUIT[#All],4,0)),"CUIT NO CARGADO") -> BS AS
B46: 44648 | C46: 1 | D46: 2 | E46: 3023 | F46: 30629863571 | G46: =IFERROR(IF(compras_mes13[[#This Row],[CUIT]]="","-",VLOOKUP(compras_mes13[[#This Row],[CUIT]],Lista_CUIT[#All],2,0)),"CUIT NO CARGADO") -> TECNIMAR S R L | H46: 98333.66 | I46: =IF(compras_mes13[[#This Row],[NETO GRAVADO]]="","",compras_mes13[[#This Row],[NETO GRAVADO]]*0.21) -> 20650.069 | O46: 5476.19 | P46: =SUM(compras_mes13[[#This Row],[NETO GRAVADO]:[Otros / No Grav.]]) -> 124459.92 | Q46: =IFERROR(IF(compras_mes13[[#This Row],[CUIT]]="","-",VLOOKUP(compras_mes13[[#This Row],[CUIT]],Lista_CUIT[#All],3,0)),"CUIT NO CARGADO") -> Mercaderia | R46: =IFERROR(IF(compras_mes13[[#This Row],[CUIT]]="","-",VLOOKUP(compras_mes13[[#This Row],[CUIT]],Lista_CUIT[#All],4,0)),"CUIT NO CARGADO") -> 0
B47: 44634 | C47: 1 | D47: 3 | E47: 5888 | F47: 30708006420 | G47: =IFERROR(IF(compras_mes13[[#This Row],[CUIT]]="","-",VLOOKUP(compras_mes13[[#This Row],[CUIT]],Lista_CUIT[#All],2,0)),"CUIT NO CARGADO") -> MEDILEA S.A. | H47: 153618 | I47: =IF(compras_mes13[[#This Row],[NETO GRAVADO]]="","",compras_mes13[[#This Row],[NETO GRAVADO]]*0.21) -> 32259.78 | O47: 5490.53 | P47: =SUM(compras_mes13[[#This Row],[NETO GRAVADO]:[Otros / No Grav.]]) -> 191368.31 | Q47: =IFERROR(IF(compras_mes13[[#This Row],[CUIT]]="","-",VLOOKUP(compras_mes13[[#This Row],[CUIT]],Lista_CUIT[#All],3,0)),"CUIT NO CARGADO") -> Mercaderia | R47: =IFERROR(IF(compras_mes13[[#This Row],[CUIT]]="","-",VLOOKUP(compras_mes13[[#This Row],[CUIT]],Lista_CUIT[#All],4,0)),"CUIT NO CARGADO") -> 0
B48: 44631 | C48: 1 | D48: 2 | E48: 3008 | F48: 30629863571 | G48: =IFERROR(IF(compras_mes13[[#This Row],[CUIT]]="","-",VLOOKUP(compras_mes13[[#This Row],[CUIT]],Lista_CUIT[#All],2,0)),"CUIT NO CARGADO") -> TECNIMAR S R L | H48: 72405.2 | I48: =IF(compras_mes13[[#This Row],[NETO GRAVADO]]="","",compras_mes13[[#This Row],[NETO GRAVADO]]*0.21) -> 15205.092 | O48: 6258.69 | P48: =SUM(compras_mes13[[#This Row],[NETO GRAVADO]:[Otros / No Grav.]]) -> 93868.982 | Q48: =IFERROR(IF(compras_mes13[[#This Row],[CUIT]]="","-",VLOOKUP(compras_mes13[[#This Row],[CUIT]],Lista_CUIT[#All],3,0)),"CUIT NO CARGADO") -> Mercaderia | R48: =IFERROR(IF(compras_mes13[[#This Row],[CUIT]]="","-",VLOOKUP(compras_mes13[[#This Row],[CUIT]],Lista_CUIT[#All],4,0)),"CUIT NO CARGADO") -> 0
B49: 44646 | C49: 1 | D49: 7 | E49: 58443 | F49: 30696131003 | G49: =IFERROR(IF(compras_mes13[[#This Row],[CUIT]]="","-",VLOOKUP(compras_mes13[[#This Row],[CUIT]],Lista_CUIT[#All],2,0)),"CUIT NO CARGADO") -> PETROLFE S.A. | H49: 20589.17 | I49: =IF(compras_mes13[[#This Row],[NETO GRAVADO]]="","",compras_mes13[[#This Row],[NETO GRAVADO]]*0.21) -> 4323.7257 | O49: 8265.14 | P49: =SUM(compras_mes13[[#This Row],[NETO GRAVADO]:[Otros / No Grav.]]) -> 33178.036 | Q49: =IFERROR(IF(compras_mes13[[#This Row],[CUIT]]="","-",VLOOKUP(compras_mes13[[#This Row],[CUIT]],Lista_CUIT[#All],3,0)),"CUIT NO CARGADO") -> Combustible | R49: =IFERROR(IF(compras_mes13[[#This Row],[CUIT]]="","-",VLOOKUP(compras_mes13[[#This Row],[CUIT]],Lista_CUIT[#All],4,0)),"CUIT NO CARGADO") -> 0
B50: 44623 | C50: 1 | D50: 1 | E50: 15833 | F50: 20173025557 | G50: =IFERROR(IF(compras_mes13[[#This Row],[CUIT]]="","-",VLOOKUP(compras_mes13[[#This Row],[CUIT]],Lista_CUIT[#All],2,0)),"CUIT NO CARGADO") -> MARAUDA HECTOR | H50: 991.74 | I50: =IF(compras_mes13[[#This Row],[NETO GRAVADO]]="","",compras_mes13[[#This Row],[NETO GRAVADO]]*0.21) -> 208.2654 | O50: 132000 | P50: =SUM(compras_mes13[[#This Row],[NETO GRAVADO]:[Otros / No Grav.]]) -> 133200.01 | Q50: =IFERROR(IF(compras_mes13[[#This Row],[CUIT]]="","-",VLOOKUP(compras_mes13[[#This Row],[CUIT]],Lista_CUIT[#All],3,0)),"CUIT NO CARGADO") -> Gastos Varios | R50: =IFERROR(IF(compras_mes13[[#This Row],[CUIT]]="","-",VLOOKUP(compras_mes13[[#This Row],[CUIT]],Lista_CUIT[#All],4,0)),"CUIT NO CARGADO") -> 0
... B53: 44631 | C53: 1 | D53: 3 | E53: 6709 | F53: 30679163317 | G53: =IFERROR(IF(compras_mes13[[#This Row],[CUIT]]="","-",VLOOKUP(compras_mes13[[#This Row],[CUIT]],Lista_CUIT[#All],2,0)),"CUIT NO CARGADO") -> RANKO SRL | H53: 7952.98 | I53: =IF(compras_mes13[[#This Row],[NETO GRAVADO]]="","",compras_mes13[[#This Row],[NETO GRAVADO]]*0.21) -> 1670.1258 | O53: 215276.29 | P53: =SUM(compras_mes13[[#This Row],[NETO GRAVADO]:[Otros / No Grav.]]) -> 224899.4 | Q53: =IFERROR(IF(compras_mes13[[#This Row],[CUIT]]="","-",VLOOKUP(compras_mes13[[#This Row],[CUIT]],Lista_CUIT[#All],3,0)),"CUIT NO CARGADO") -> Gastos Varios | R53: =IFERROR(IF(compras_mes13[[#This Row],[CUIT]]="","-",VLOOKUP(compras_mes13[[#This Row],[CUIT]],Lista_CUIT[#All],4,0)),"CUIT NO CARGADO") -> 0
B54: 44622 | C54: 1 | D54: 1 | E54: 224 | F54: 20131206144 | G54: =IFERROR(IF(compras_mes13[[#This Row],[CUIT]]="","-",VLOOKUP(compras_mes13[[#This Row],[CUIT]],Lista_CUIT[#All],2,0)),"CUIT NO CARGADO") -> CHAMORRO MANUEL | H54: 18000 | I54: =IF(compras_mes13[[#This Row],[NETO GRAVADO]]="","",compras_mes13[[#This Row],[NETO GRAVADO]]*0.21) -> 3780 | P54: =SUM(compras_mes13[[#This Row],[NETO GRAVADO]:[Otros / No Grav.]]) -> 21780 | Q54: =IFERROR(IF(compras_mes13[[#This Row],[CUIT]]="","-",VLOOKUP(compras_mes13[[#This Row],[CUIT]],Lista_CUIT[#All],3,0)),"CUIT NO CARGADO") -> Alquiler | R54: =IFERROR(IF(compras_mes13[[#This Row],[CUIT]]="","-",VLOOKUP(compras_mes13[[#This Row],[CUIT]],Lista_CUIT[#All],4,0)),"CUIT NO CARGADO") -> 0
B55: 44627 | C55: 1 | D55: 1 | E55: 31 | F55: 30716010313 | G55: =IFERROR(IF(compras_mes13[[#This Row],[CUIT]]="","-",VLOOKUP(compras_mes13[[#This Row],[CUIT]],Lista_CUIT[#All],2,0)),"CUIT NO CARGADO") -> H UNO 1469 S.A. | H55: 32000 | I55: =IF(compras_mes13[[#This Row],[NETO GRAVADO]]="","",compras_mes13[[#This Row],[NETO GRAVADO]]*0.21) -> 6720 | P55: =SUM(compras_mes13[[#This Row],[NETO GRAVADO]:[Otros / No Grav.]]) -> 38720 | Q55: =IFERROR(IF(compras_mes13[[#This Row],[CUIT]]="","-",VLOOKUP(compras_mes13[[#This Row],[CUIT]],Lista_CUIT[#All],3,0)),"CUIT NO CARGADO") -> Alquiler | R55: =IFERROR(IF(compras_mes13[[#This Row],[CUIT]]="","-",VLOOKUP(compras_mes13[[#This Row],[CUIT]],Lista_CUIT[#All],4,0)),"CUIT NO CARGADO") -> 0
B56: 44645 | C56: 1 | D56: 6 | E56: 39881 | F56: 30568459500 | G56: =IFERROR(IF(compras_mes13[[#This Row],[CUIT]]="","-",VLOOKUP(compras_mes13[[#This Row],[CUIT]],Lista_CUIT[#All],2,0)),"CUIT NO CARGADO") -> KUKE S.R.L. | H56: 2024.55 | I56: =IF(compras_mes13[[#This Row],[NETO GRAVADO]]="","",compras_mes13[[#This Row],[NETO GRAVADO]]*0.21) -> 425.1555 | P56: =SUM(compras_mes13[[#This Row],[NETO GRAVADO]:[Otros / No Grav.]]) -> 2449.7055 | Q56: =IFERROR(IF(compras_mes13[[#This Row],[CUIT]]="","-",VLOOKUP(compras_mes13[[#This Row],[CUIT]],Lista_CUIT[#All],3,0)),"CUIT NO CARGADO") -> Combustible | R56: =IFERROR(IF(compras_mes13[[#This Row],[CUIT]]="","-",VLOOKUP(compras_mes13[[#This Row],[CUIT]],Lista_CUIT[#All],4,0)),"CUIT NO CARGADO") -> 0
B57: 44621 | C57: 1 | D57: 266 | E57: 4981 | F57: 30572365391 | G57: =IFERROR(IF(compras_mes13[[#This Row],[CUIT]]="","-",VLOOKUP(compras_mes13[[#This Row],[CUIT]],Lista_CUIT[#All],2,0)),"CUIT NO CARGADO") -> PETROVALLE S.A. | H57: 6974.72 | I57: =IF(compras_mes13[[#This Row],[NETO GRAVADO]]="","",compras_mes13[[#This Row],[NETO GRAVADO]]*0.21) -> 1464.6912 | P57: =SUM(compras_mes13[[#This Row],[NETO GRAVADO]:[Otros / No Grav.]]) -> 8439.4112 | Q57: =IFERROR(IF(compras_mes13[[#This Row],[CUIT]]="","-",VLOOKUP(compras_mes13[[#This Row],[CUIT]],Lista_CUIT[#All],3,0)),"CUIT NO CARGADO") -> Combustible | R57: =IFERROR(IF(compras_mes13[[#This Row],[CUIT]]="","-",VLOOKUP(compras_mes13[[#This Row],[CUIT]],Lista_CUIT[#All],4,0)),"CUIT NO CARGADO") -> 0
B58: 44624 | C58: 1 | D58: 7 | E58: 22974 | F58: 30709781428 | G58: =IFERROR(IF(compras_mes13[[#This Row],[CUIT]]="","-",VLOOKUP(compras_mes13[[#This Row],[CUIT]],Lista_CUIT[#All],2,0)),"CUIT NO CARGADO") -> DUAL TIGRE S.A. | H58: 389.8 | I58: =IF(compras_mes13[[#This Row],[NETO GRAVADO]]="","",compras_mes13[[#This Row],[NETO GRAVADO]]*0.21) -> 81.858 | L58: 206.69 | P58: =SUM(compras_mes13[[#This Row],[NETO GRAVADO]:[Otros / No Grav.]]) -> 678.348 | Q58: =IFERROR(IF(compras_mes13[[#This Row],[CUIT]]="","-",VLOOKUP(compras_mes13[[#This Row],[CUIT]],Lista_CUIT[#All],3,0)),"CUIT NO CARGADO") -> Combustible | R58: =IFERROR(IF(compras_mes13[[#This Row],[CUIT]]="","-",VLOOKUP(compras_mes13[[#This Row],[CUIT]],Lista_CUIT[#All],4,0)),"CUIT NO CARGADO") -> 0
B59: 44650 | C59: 1 | D59: 5140 | E59: 497 | F59: 30695542476 | G59: =IFERROR(IF(compras_mes13[[#This Row],[CUIT]]="","-",VLOOKUP(compras_mes13[[#This Row],[CUIT]],Lista_CUIT[#All],2,0)),"CUIT NO CARGADO") -> PAN AMERICAN ENERGY SL S.AR | H59: 1828.91 | I59: =IF(compras_mes13[[#This Row],[NETO GRAVADO]]="","",compras_mes13[[#This Row],[NETO GRAVADO]]*0.21) -> 384.0711 | P59: =SUM(compras_mes13[[#This Row],[NETO GRAVADO]:[Otros / No Grav.]]) -> 2212.9811 | Q59: =IFERROR(IF(compras_mes13[[#This Row],[CUIT]]="","-",VLOOKUP(compras_mes13[[#This Row],[CUIT]],Lista_CUIT[#All],3,0)),"CUIT NO CARGADO") -> Combustible | R59: =IFERROR(IF(compras_mes13[[#This Row],[CUIT]]="","-",VLOOKUP(compras_mes13[[#This Row],[CUIT]],Lista_CUIT[#All],4,0)),"CUIT NO CARGADO") -> 0
B60: 44651 | C60: 1 | D60: 19 | E60: 2906 | F60: 30515800219 | G60: =IFERROR(IF(compras_mes13[[#This Row],[CUIT]]="","-",VLOOKUP(compras_mes13[[#This Row],[CUIT]],Lista_CUIT[#All],2,0)),"CUIT NO CARGADO") -> INCAT SRL | H60: 19797.92 | I60: =IF(compras_mes13[[#This Row],[NETO GRAVADO]]="","",compras_mes13[[#This Row],[NETO GRAVADO]]*0.21) -> 4157.5632 | P60: =SUM(compras_mes13[[#This Row],[NETO GRAVADO]:[Otros / No Grav.]]) -> 23955.483 | Q60: =IFERROR(IF(compras_mes13[[#This Row],[CUIT]]="","-",VLOOKUP(compras_mes13[[#This Row],[CUIT]],Lista_CUIT[#All],3,0)),"CUIT NO CARGADO") -> Combustible | R60: =IFERROR(IF(compras_mes13[[#This Row],[CUIT]]="","-",VLOOKUP(compras_mes13[[#This Row],[CUIT]],Lista_CUIT[#All],4,0)),"CUIT NO CARGADO") -> 0
B61: 44651 | C61: 1 | D61: 7136 | E61: 1938 | F61: 30678774495 | G61: =IFERROR(IF(compras_mes13[[#This Row],[CUIT]]="","-",VLOOKUP(compras_mes13[[#This Row],[CUIT]],Lista_CUIT[#All],2,0)),"CUIT NO CARGADO") -> OPER. DE EST. DE SERV. SA | H61: 12996.8 | I61: =IF(compras_mes13[[#This Row],[NETO GRAVADO]]="","",compras_mes13[[#This Row],[NETO GRAVADO]]*0.21) -> 2729.328 | P61: =SUM(compras_mes13[[#This Row],[NETO GRAVADO]:[Otros / No Grav.]]) -> 15726.128 | Q61: =IFERROR(IF(compras_mes13[[#This Row],[CUIT]]="","-",VLOOKUP(compras_mes13[[#This Row],[CUIT]],Lista_CUIT[#All],3,0)),"CUIT NO CARGADO") -> Combustible | R61: =IFERROR(IF(compras_mes13[[#This Row],[CUIT]]="","-",VLOOKUP(compras_mes13[[#This Row],[CUIT]],Lista_CUIT[#All],4,0)),"CUIT NO CARGADO") -> 0
B62: 44651 | C62: 1 | D62: 2 | E62: 1282 | F62: 30717110052 | G62: =IFERROR(IF(compras_mes13[[#This Row],[CUIT]]="","-",VLOOKUP(compras_mes13[[#This Row],[CUIT]],Lista_CUIT[#All],2,0)),"CUIT NO CARGADO") -> TAP SERVICES S.A | H62: 96.73 | I62: =IF(compras_mes13[[#This Row],[NETO GRAVADO]]="","",compras_mes13[[#This Row],[NETO GRAVADO]]*0.21) -> 20.3133 | P62: =SUM(compras_mes13[[#This Row],[NETO GRAVADO]:[Otros / No Grav.]]) -> 117.0433 | Q62: =IFERROR(IF(compras_mes13[[#This Row],[CUIT]]="","-",VLOOKUP(compras_mes13[[#This Row],[CUIT]],Lista_CUIT[#All],3,0)),"CUIT NO CARGADO") -> Comida | R62: =IFERROR(IF(compras_mes13[[#This Row],[CUIT]]="","-",VLOOKUP(compras_mes13[[#This Row],[CUIT]],Lista_CUIT[#All],4,0)),"CUIT NO CARGADO") -> 0
B63: 44646 | C63: 1 | D63: 6 | E63: 1661 | F63: 20134664518 | G63: =IFERROR(IF(compras_mes13[[#This Row],[CUIT]]="","-",VLOOKUP(compras_mes13[[#This Row],[CUIT]],Lista_CUIT[#All],2,0)),"CUIT NO CARGADO") -> HOKAMA SERGIO ENRIQUE | H63: 15320.29 | I63: =IF(compras_mes13[[#This Row],[NETO GRAVADO]]="","",compras_mes13[[#This Row],[NETO GRAVADO]]*0.21) -> 3217.2609 | M63: 1160.33 | P63: =SUM(compras_mes13[[#This Row],[NETO GRAVADO]:[Otros / No Grav.]]) -> 19697.881 | Q63: =IFERROR(IF(compras_mes13[[#This Row],[CUIT]]="","-",VLOOKUP(compras_mes13[[#This Row],[CUIT]],Lista_CUIT[#All],3,0)),"CUIT NO CARGADO") -> Comida-Limpieza | R63: =IFERROR(IF(compras_mes13[[#This Row],[CUIT]]="","-",VLOOKUP(compras_mes13[[#This Row],[CUIT]],Lista_CUIT[#All],4,0)),"CUIT NO CARGADO") -> 0
B64: 44648 | C64: 1 | D64: 7 | E64: 22443440 | F64: 30574816870 | G64: =IFERROR(IF(compras_mes13[[#This Row],[CUIT]]="","-",VLOOKUP(compras_mes13[[#This Row],[CUIT]],Lista_CUIT[#All],2,0)),"CUIT NO CARGADO") -> AMERICAN EXPRES S.A. | H64: 8904.16 | I64: =IF(compras_mes13[[#This Row],[NETO GRAVADO]]="","",compras_mes13[[#This Row],[NETO GRAVADO]]*0.21) -> 1869.8736 | P64: =SUM(compras_mes13[[#This Row],[NETO GRAVADO]:[Otros / No Grav.]]) -> 10774.034 | Q64: =IFERROR(IF(compras_mes13[[#This Row],[CUIT]]="","-",VLOOKUP(compras_mes13[[#This Row],[CUIT]],Lista_CUIT[#All],3,0)),"CUIT NO CARGADO") -> Comisiones Bancarias | R64: =IFERROR(IF(compras_mes13[[#This Row],[CUIT]]="","-",VLOOKUP(compras_mes13[[#This Row],[CUIT]],Lista_CUIT[#All],4,0)),"CUIT NO CARGADO") -> 0
B65: 44650 | C65: 1 | D65: 1 | E65: 97339008 | F65: 30500003193 | G65: =IFERROR(IF(compras_mes13[[#This Row],[CUIT]]="","-",VLOOKUP(compras_mes13[[#This Row],[CUIT]],Lista_CUIT[#All],2,0)),"CUIT NO CARGADO") -> BBVA FRANCES | H65: 1597.31 | I65: =IF(compras_mes13[[#This Row],[NETO GRAVADO]]="","",compras_mes13[[#This Row],[NETO GRAVADO]]*0.21) -> 335.4351 | P65: =SUM(compras_mes13[[#This Row],[NETO GRAVADO]:[Otros / No Grav.]]) -> 1932.7451 | Q65: =IFERROR(IF(compras_mes13[[#This Row],[CUIT]]="","-",VLOOKUP(compras_mes13[[#This Row],[CUIT]],Lista_CUIT[#All],3,0)),"CUIT NO CARGADO") -> Comisiones Bancarias | R65: =IFERROR(IF(compras_mes13[[#This Row],[CUIT]]="","-",VLOOKUP(compras_mes13[[#This Row],[CUIT]],Lista_CUIT[#All],4,0)),"CUIT NO CARGADO") -> 0
B66: 44646 | C66: 1 | D66: 2 | E66: 2022 | F66: 30707826890 | G66: =IFERROR(IF(compras_mes13[[#This Row],[CUIT]]="","-",VLOOKUP(compras_mes13[[#This Row],[CUIT]],Lista_CUIT[#All],2,0)),"CUIT NO CARGADO") -> JUVIALE S.R.L. | H66: 0 | I66: =IF(compras_mes13[[#This Row],[NETO GRAVADO]]="","",compras_mes13[[#This Row],[NETO GRAVADO]]*0.21) -> 0 | P66: =SUM(compras_mes13[[#This Row],[NETO GRAVADO]:[Otros / No Grav.]]) -> 0 | Q66: =IFERROR(IF(compras_mes13[[#This Row],[CUIT]]="","-",VLOOKUP(compras_mes13[[#This Row],[CUIT]],Lista_CUIT[#All],3,0)),"CUIT NO CARGADO") -> EXPENSAS | R66: =IFERROR(IF(compras_mes13[[#This Row],[CUIT]]="","-",VLOOKUP(compras_mes13[[#This Row],[CUIT]],Lista_CUIT[#All],4,0)),"CUIT NO CARGADO") -> 0
B67: 44636 | C67: 1 | D67: 5 | E67: 14079 | F67: 30715342983 | G67: =IFERROR(IF(compras_mes13[[#This Row],[CUIT]]="","-",VLOOKUP(compras_mes13[[#This Row],[CUIT]],Lista_CUIT[#All],2,0)),"CUIT NO CARGADO") -> INSUMOS INDUSTRIALES BULFER | H67: 14461.98 | I67: =IF(compras_mes13[[#This Row],[NETO GRAVADO]]="","",compras_mes13[[#This Row],[NETO GRAVADO]]*0.21) -> 3037.0158 | P67: =SUM(compras_mes13[[#This Row],[NETO GRAVADO]:[Otros / No Grav.]]) -> 17498.996 | Q67: =IFERROR(IF(compras_mes13[[#This Row],[CUIT]]="","-",VLOOKUP(compras_mes13[[#This Row],[CUIT]],Lista_CUIT[#All],3,0)),"CUIT NO CARGADO") -> Ferreteria | R67: =IFERROR(IF(compras_mes13[[#This Row],[CUIT]]="","-",VLOOKUP(compras_mes13[[#This Row],[CUIT]],Lista_CUIT[#All],4,0)),"CUIT NO CARGADO") -> BS AS
B68: 44648 | C68: 1 | D68: 6 | E68: 2281 | F68: 20117862578 | G68: =IFERROR(IF(compras_mes13[[#This Row],[CUIT]]="","-",VLOOKUP(compras_mes13[[#This Row],[CUIT]],Lista_CUIT[#All],2,0)),"CUIT NO CARGADO") -> PORCO VICTOR ALBERTO | H68: 3305.92 | I68: 3426.57 | P68: =SUM(compras_mes13[[#This Row],[NETO GRAVADO]:[Otros / No Grav.]]) -> 6732.49 | Q68: =IFERROR(IF(compras_mes13[[#This Row],[CUIT]]="","-",VLOOKUP(compras_mes13[[#This Row],[CUIT]],Lista_CUIT[#All],3,0)),"CUIT NO CARGADO") -> Ferreteria | R68: =IFERROR(IF(compras_mes13[[#This Row],[CUIT]]="","-",VLOOKUP(compras_mes13[[#This Row],[CUIT]],Lista_CUIT[#All],4,0)),"CUIT NO CARGADO") -> 0
B69: 44636 | C69: 1 | D69: 3 | E69: 2649 | F69: 30682116028 | G69: =IFERROR(IF(compras_mes13[[#This Row],[CUIT]]="","-",VLOOKUP(compras_mes13[[#This Row],[CUIT]],Lista_CUIT[#All],2,0)),"CUIT NO CARGADO") -> BLUE STAR CARGO SRL | H69: 69177.5 | I69: 583.91 | P69: =SUM(compras_mes13[[#This Row],[NETO GRAVADO]:[Otros / No Grav.]]) -> 69761.41 | Q69: =IFERROR(IF(compras_mes13[[#This Row],[CUIT]]="","-",VLOOKUP(compras_mes13[[#This Row],[CUIT]],Lista_CUIT[#All],3,0)),"CUIT NO CARGADO") -> Flete-Logistica | R69: =IFERROR(IF(compras_mes13[[#This Row],[CUIT]]="","-",VLOOKUP(compras_mes13[[#This Row],[CUIT]],Lista_CUIT[#All],4,0)),"CUIT NO CARGADO") -> 0
B70: 44637 | C70: 1 | D70: 6130 | E70: 1328 | F70: 33707675069 | G70: =IFERROR(IF(compras_mes13[[#This Row],[CUIT]]="","-",VLOOKUP(compras_mes13[[#This Row],[CUIT]],Lista_CUIT[#All],2,0)),"CUIT NO CARGADO") -> BUS PACK S.A. | H70: 942.56 | I70: =IF(compras_mes13[[#This Row],[NETO GRAVADO]]="","",compras_mes13[[#This Row],[NETO GRAVADO]]*0.21) -> 197.9376 | P70: =SUM(compras_mes13[[#This Row],[NETO GRAVADO]:[Otros / No Grav.]]) -> 1140.4976 | Q70: =IFERROR(IF(compras_mes13[[#This Row],[CUIT]]="","-",VLOOKUP(compras_mes13[[#This Row],[CUIT]],Lista_CUIT[#All],3,0)),"CUIT NO CARGADO") -> Flete-Logistica | R70: =IFERROR(IF(compras_mes13[[#This Row],[CUIT]]="","-",VLOOKUP(compras_mes13[[#This Row],[CUIT]],Lista_CUIT[#All],4,0)),"CUIT NO CARGADO") -> 0
B71: 44639 | C71: 1 | D71: 331 | E71: 372572 | F71: 30579939008 | G71: =IFERROR(IF(compras_mes13[[#This Row],[CUIT]]="","-",VLOOKUP(compras_mes13[[#This Row],[CUIT]],Lista_CUIT[#All],2,0)),"CUIT NO CARGADO") -> TRANSPORTES LA SEVILLANITA | H71: 10368.61 | I71: =IF(compras_mes13[[#This Row],[NETO GRAVADO]]="","",compras_mes13[[#This Row],[NETO GRAVADO]]*0.21) -> 2177.4081 | P71: =SUM(compras_mes13[[#This Row],[NETO GRAVADO]:[Otros / No Grav.]]) -> 12546.018 | Q71: =IFERROR(IF(compras_mes13[[#This Row],[CUIT]]="","-",VLOOKUP(compras_mes13[[#This Row],[CUIT]],Lista_CUIT[#All],3,0)),"CUIT NO CARGADO") -> Flete-Logistica | R71: =IFERROR(IF(compras_mes13[[#This Row],[CUIT]]="","-",VLOOKUP(compras_mes13[[#This Row],[CUIT]],Lista_CUIT[#All],4,0)),"CUIT NO CARGADO") -> 0
B72: 44642 | C72: 1 | D72: 6331 | E72: 1356 | F72: 30643922157 | G72: =IFERROR(IF(compras_mes13[[#This Row],[CUIT]]="","-",VLOOKUP(compras_mes13[[#This Row],[CUIT]],Lista_CUIT[#All],2,0)),"CUIT NO CARGADO") -> VIA BARILOCHE SA | H72: 851.24 | I72: =IF(compras_mes13[[#This Row],[NETO GRAVADO]]="","",compras_mes13[[#This Row],[NETO GRAVADO]]*0.21) -> 178.7604 | P72: =SUM(compras_mes13[[#This Row],[NETO GRAVADO]:[Otros / No Grav.]]) -> 1030.0004 | Q72: =IFERROR(IF(compras_mes13[[#This Row],[CUIT]]="","-",VLOOKUP(compras_mes13[[#This Row],[CUIT]],Lista_CUIT[#All],3,0)),"CUIT NO CARGADO") -> Flete-Logistica | R72: =IFERROR(IF(compras_mes13[[#This Row],[CUIT]]="","-",VLOOKUP(compras_mes13[[#This Row],[CUIT]],Lista_CUIT[#All],4,0)),"CUIT NO CARGADO") -> 0
B73: 44634 | C73: 1 | D73: 2 | E73: 7279 | F73: 30714284963 | G73: =IFERROR(IF(compras_mes13[[#This Row],[CUIT]]="","-",VLOOKUP(compras_mes13[[#This Row],[CUIT]],Lista_CUIT[#All],2,0)),"CUIT NO CARGADO") -> ENGYMAN SRL | H73: 22370 | I73: =IF(compras_mes13[[#This Row],[NETO GRAVADO]]="","",compras_mes13[[#This Row],[NETO GRAVADO]]*0.21) -> 4697.7 | P73: =SUM(compras_mes13[[#This Row],[NETO GRAVADO]:[Otros / No Grav.]]) -> 27067.7 | Q73: =IFERROR(IF(compras_mes13[[#This Row],[CUIT]]="","-",VLOOKUP(compras_mes13[[#This Row],[CUIT]],Lista_CUIT[#All],3,0)),"CUIT NO CARGADO") -> Gastos Mantenimiento | R73: =IFERROR(IF(compras_mes13[[#This Row],[CUIT]]="","-",VLOOKUP(compras_mes13[[#This Row],[CUIT]],Lista_CUIT[#All],4,0)),"CUIT NO CARGADO") -> 0
B74: 44634 | C74: 1 | D74: 2 | E74: 7281 | F74: 30714284963 | G74: =IFERROR(IF(compras_mes13[[#This Row],[CUIT]]="","-",VLOOKUP(compras_mes13[[#This Row],[CUIT]],Lista_CUIT[#All],2,0)),"CUIT NO CARGADO") -> ENGYMAN SRL | H74: 700 | I74: =IF(compras_mes13[[#This Row],[NETO GRAVADO]]="","",compras_mes13[[#This Row],[NETO GRAVADO]]*0.21) -> 147 | P74: =SUM(compras_mes13[[#This Row],[NETO GRAVADO]:[Otros / No Grav.]]) -> 847 | Q74: =IFERROR(IF(compras_mes13[[#This Row],[CUIT]]="","-",VLOOKUP(compras_mes13[[#This Row],[CUIT]],Lista_CUIT[#All],3,0)),"CUIT NO CARGADO") -> Gastos Mantenimiento | R74: =IFERROR(IF(compras_mes13[[#This Row],[CUIT]]="","-",VLOOKUP(compras_mes13[[#This Row],[CUIT]],Lista_CUIT[#All],4,0)),"CUIT NO CARGADO") -> 0
B75: 44651 | C75: 1 | D75: 6 | E75: 18333 | F75: 30709407895 | G75: =IFERROR(IF(compras_mes13[[#This Row],[CUIT]]="","-",VLOOKUP(compras_mes13[[#This Row],[CUIT]],Lista_CUIT[#All],2,0)),"CUIT NO CARGADO") -> SISTEMAS GAFF S.A. | H75: 4694.55 | I75: =IF(compras_mes13[[#This Row],[NETO GRAVADO]]="","",compras_mes13[[#This Row],[NETO GRAVADO]]*0.21) -> 985.8555 | P75: =SUM(compras_mes13[[#This Row],[NETO GRAVADO]:[Otros / No Grav.]]) -> 5680.4055 | Q75: =IFERROR(IF(compras_mes13[[#This Row],[CUIT]]="","-",VLOOKUP(compras_mes13[[#This Row],[CUIT]],Lista_CUIT[#All],3,0)),"CUIT NO CARGADO") -> Gastos Varios | R75: =IFERROR(IF(compras_mes13[[#This Row],[CUIT]]="","-",VLOOKUP(compras_mes13[[#This Row],[CUIT]],Lista_CUIT[#All],4,0)),"CUIT NO CARGADO") -> 0
B76: 44628 | C76: 1 | D76: 16 | E76: 60548 | F76: 30711050767 | G76: =IFERROR(IF(compras_mes13[[#This Row],[CUIT]]="","-",VLOOKUP(compras_mes13[[#This Row],[CUIT]],Lista_CUIT[#All],2,0)),"CUIT NO CARGADO") -> DIAMOND SYSTEM S.A. | H76: 5561.09 | I76: =IF(compras_mes13[[#This Row],[NETO GRAVADO]]="","",compras_mes13[[#This Row],[NETO GRAVADO]]*0.21) -> 1167.8289 | P76: =SUM(compras_mes13[[#This Row],[NETO GRAVADO]:[Otros / No Grav.]]) -> 6728.9189 | Q76: =IFERROR(IF(compras_mes13[[#This Row],[CUIT]]="","-",VLOOKUP(compras_mes13[[#This Row],[CUIT]],Lista_CUIT[#All],3,0)),"CUIT NO CARGADO") -> Gastos Varios | R76: =IFERROR(IF(compras_mes13[[#This Row],[CUIT]]="","-",VLOOKUP(compras_mes13[[#This Row],[CUIT]],Lista_CUIT[#All],4,0)),"CUIT NO CARGADO") -> BS AS
B77: 44637 | C77: 1 | D77: 12 | E77: 23901 | F77: 30708247770 | G77: =IFERROR(IF(compras_mes13[[#This Row],[CUIT]]="","-",VLOOKUP(compras_mes13[[#This Row],[CUIT]],Lista_CUIT[#All],2,0)),"CUIT NO CARGADO") -> DUFF SRL | H77: 14271.07 | I77: =IF(compras_mes13[[#This Row],[NETO GRAVADO]]="","",compras_mes13[[#This Row],[NETO GRAVADO]]*0.21) -> 2996.9247 | P77: =SUM(compras_mes13[[#This Row],[NETO GRAVADO]:[Otros / No Grav.]]) -> 17267.995 | Q77: =IFERROR(IF(compras_mes13[[#This Row],[CUIT]]="","-",VLOOKUP(compras_mes13[[#This Row],[CUIT]],Lista_CUIT[#All],3,0)),"CUIT NO CARGADO") -> Gastos Varios | R77: =IFERROR(IF(compras_mes13[[#This Row],[CUIT]]="","-",VLOOKUP(compras_mes13[[#This Row],[CUIT]],Lista_CUIT[#All],4,0)),"CUIT NO CARGADO") -> CABA
B78: 44642 | C78: 1 | D78: 5 | E78: 8670 | F78: 20936626549 | G78: =IFERROR(IF(compras_mes13[[#This Row],[CUIT]]="","-",VLOOKUP(compras_mes13[[#This Row],[CUIT]],Lista_CUIT[#All],2,0)),"CUIT NO CARGADO") -> TROTTA SALVADOR | H78: 892.56 | I78: =IF(compras_mes13[[#This Row],[NETO GRAVADO]]="","",compras_mes13[[#This Row],[NETO GRAVADO]]*0.21) -> 187.4376 | P78: =SUM(compras_mes13[[#This Row],[NETO GRAVADO]:[Otros / No Grav.]]) -> 1079.9976 | Q78: =IFERROR(IF(compras_mes13[[#This Row],[CUIT]]="","-",VLOOKUP(compras_mes13[[#This Row],[CUIT]],Lista_CUIT[#All],3,0)),"CUIT NO CARGADO") -> Gastos Varios | R78: =IFERROR(IF(compras_mes13[[#This Row],[CUIT]]="","-",VLOOKUP(compras_mes13[[#This Row],[CUIT]],Lista_CUIT[#All],4,0)),"CUIT NO CARGADO") -> BS AS
B79: 44642 | C79: 1 | D79: 2000 | E79: 4033 | F79: 20263507690 | G79: =IFERROR(IF(compras_mes13[[#This Row],[CUIT]]="","-",VLOOKUP(compras_mes13[[#This Row],[CUIT]],Lista_CUIT[#All],2,0)),"CUIT NO CARGADO") -> ROTONDO MARCELO ANDRES | H79: 16684.6 | I79: =IF(compras_mes13[[#This Row],[NETO GRAVADO]]="","",compras_mes13[[#This Row],[NETO GRAVADO]]*0.21) -> 3503.766 | P79: =SUM(compras_mes13[[#This Row],[NETO GRAVADO]:[Otros / No Grav.]]) -> 20188.366 | Q79: =IFERROR(IF(compras_mes13[[#This Row],[CUIT]]="","-",VLOOKUP(compras_mes13[[#This Row],[CUIT]],Lista_CUIT[#All],3,0)),"CUIT NO CARGADO") -> Gastos Varios | R79: =IFERROR(IF(compras_mes13[[#This Row],[CUIT]]="","-",VLOOKUP(compras_mes13[[#This Row],[CUIT]],Lista_CUIT[#All],4,0)),"CUIT NO CARGADO") -> BS as
B80: 44643 | C80: 1 | D80: 2 | E80: 5222 | F80: 20243645523 | G80: =IFERROR(IF(compras_mes13[[#This Row],[CUIT]]="","-",VLOOKUP(compras_mes13[[#This Row],[CUIT]],Lista_CUIT[#All],2,0)),"CUIT NO CARGADO") -> POCIECHA LUIS | H80: 5500 | I80: =IF(compras_mes13[[#This Row],[NETO GRAVADO]]="","",compras_mes13[[#This Row],[NETO GRAVADO]]*0.21) -> 1155 | P80: =SUM(compras_mes13[[#This Row],[NETO GRAVADO]:[Otros / No Grav.]]) -> 6655 | Q80: =IFERROR(IF(compras_mes13[[#This Row],[CUIT]]="","-",VLOOKUP(compras_mes13[[#This Row],[CUIT]],Lista_CUIT[#All],3,0)),"CUIT NO CARGADO") -> Gastos Varios | R80: =IFERROR(IF(compras_mes13[[#This Row],[CUIT]]="","-",VLOOKUP(compras_mes13[[#This Row],[CUIT]],Lista_CUIT[#All],4,0)),"CUIT NO CARGADO") -> 0
B81: 44650 | C81: 1 | D81: 5 | E81: 2750 | F81: 20299470645 | G81: =IFERROR(IF(compras_mes13[[#This Row],[CUIT]]="","-",VLOOKUP(compras_mes13[[#This Row],[CUIT]],Lista_CUIT[#All],2,0)),"CUIT NO CARGADO") -> D'ABATE ANDRES PABLO | H81: 17504.13 | I81: =IF(compras_mes13[[#This Row],[NETO GRAVADO]]="","",compras_mes13[[#This Row],[NETO GRAVADO]]*0.21) -> 3675.8673 | P81: =SUM(compras_mes13[[#This Row],[NETO GRAVADO]:[Otros / No Grav.]]) -> 21179.997 | Q81: =IFERROR(IF(compras_mes13[[#This Row],[CUIT]]="","-",VLOOKUP(compras_mes13[[#This Row],[CUIT]],Lista_CUIT[#All],3,0)),"CUIT NO CARGADO") -> Gastos Varios | R81: =IFERROR(IF(compras_mes13[[#This Row],[CUIT]]="","-",VLOOKUP(compras_mes13[[#This Row],[CUIT]],Lista_CUIT[#All],4,0)),"CUIT NO CARGADO") -> 0
... B84: 44627 | C84: 1 | D84: 5 | E84: 18021 | F84: 30616146447 | G84: =IFERROR(IF(compras_mes13[[#This Row],[CUIT]]="","-",VLOOKUP(compras_mes13[[#This Row],[CUIT]],Lista_CUIT[#All],2,0)),"CUIT NO CARGADO") -> EGEO SOCIEDAD DE RESPONSABILIDAD LIMITADA | H84: 32000 | I84: =IF(compras_mes13[[#This Row],[NETO GRAVADO]]="","",compras_mes13[[#This Row],[NETO GRAVADO]]*0.21) -> 6720 | P84: =SUM(compras_mes13[[#This Row],[NETO GRAVADO]:[Otros / No Grav.]]) -> 38720 | Q84: =IFERROR(IF(compras_mes13[[#This Row],[CUIT]]="","-",VLOOKUP(compras_mes13[[#This Row],[CUIT]],Lista_CUIT[#All],3,0)),"CUIT NO CARGADO") -> Gastos Varios | R84: =IFERROR(IF(compras_mes13[[#This Row],[CUIT]]="","-",VLOOKUP(compras_mes13[[#This Row],[CUIT]],Lista_CUIT[#All],4,0)),"CUIT NO CARGADO") -> 0
B85: 44630 | C85: 1 | D85: 4 | E85: 15595 | F85: 30552433595 | G85: =IFERROR(IF(compras_mes13[[#This Row],[CUIT]]="","-",VLOOKUP(compras_mes13[[#This Row],[CUIT]],Lista_CUIT[#All],2,0)),"CUIT NO CARGADO") -> PIROPLAST S.R.L. | H85: 243409.95 | I85: =IF(compras_mes13[[#This Row],[NETO GRAVADO]]="","",compras_mes13[[#This Row],[NETO GRAVADO]]*0.21) -> 51116.09 | N85: 464.49 | P85: =SUM(compras_mes13[[#This Row],[NETO GRAVADO]:[Otros / No Grav.]]) -> 294990.53 | Q85: =IFERROR(IF(compras_mes13[[#This Row],[CUIT]]="","-",VLOOKUP(compras_mes13[[#This Row],[CUIT]],Lista_CUIT[#All],3,0)),"CUIT NO CARGADO") -> Gtos Comercializacion | R85: =IFERROR(IF(compras_mes13[[#This Row],[CUIT]]="","-",VLOOKUP(compras_mes13[[#This Row],[CUIT]],Lista_CUIT[#All],4,0)),"CUIT NO CARGADO") -> 0
B86: 44631 | C86: 1 | D86: 3 | E86: 6707 | F86: 30679163317 | G86: =IFERROR(IF(compras_mes13[[#This Row],[CUIT]]="","-",VLOOKUP(compras_mes13[[#This Row],[CUIT]],Lista_CUIT[#All],2,0)),"CUIT NO CARGADO") -> RANKO SRL | H86: 28853.6 | I86: =IF(compras_mes13[[#This Row],[NETO GRAVADO]]="","",compras_mes13[[#This Row],[NETO GRAVADO]]*0.21) -> 6059.256 | P86: =SUM(compras_mes13[[#This Row],[NETO GRAVADO]:[Otros / No Grav.]]) -> 34912.856 | Q86: =IFERROR(IF(compras_mes13[[#This Row],[CUIT]]="","-",VLOOKUP(compras_mes13[[#This Row],[CUIT]],Lista_CUIT[#All],3,0)),"CUIT NO CARGADO") -> Gastos Varios | R86: =IFERROR(IF(compras_mes13[[#This Row],[CUIT]]="","-",VLOOKUP(compras_mes13[[#This Row],[CUIT]],Lista_CUIT[#All],4,0)),"CUIT NO CARGADO") -> 0
B87: 44631 | C87: 1 | D87: 3 | E87: 6708 | F87: 30679163317 | G87: =IFERROR(IF(compras_mes13[[#This Row],[CUIT]]="","-",VLOOKUP(compras_mes13[[#This Row],[CUIT]],Lista_CUIT[#All],2,0)),"CUIT NO CARGADO") -> RANKO SRL | H87: 19240.68 | I87: =IF(compras_mes13[[#This Row],[NETO GRAVADO]]="","",compras_mes13[[#This Row],[NETO GRAVADO]]*0.21) -> 4040.5428 | P87: =SUM(compras_mes13[[#This Row],[NETO GRAVADO]:[Otros / No Grav.]]) -> 23281.223 | Q87: =IFERROR(IF(compras_mes13[[#This Row],[CUIT]]="","-",VLOOKUP(compras_mes13[[#This Row],[CUIT]],Lista_CUIT[#All],3,0)),"CUIT NO CARGADO") -> Gastos Varios | R87: =IFERROR(IF(compras_mes13[[#This Row],[CUIT]]="","-",VLOOKUP(compras_mes13[[#This Row],[CUIT]],Lista_CUIT[#All],4,0)),"CUIT NO CARGADO") -> 0
B88: 44635 | C88: 1 | D88: 3 | E88: 6715 | F88: 30679163317 | G88: =IFERROR(IF(compras_mes13[[#This Row],[CUIT]]="","-",VLOOKUP(compras_mes13[[#This Row],[CUIT]],Lista_CUIT[#All],2,0)),"CUIT NO CARGADO") -> RANKO SRL | H88: 9090.91 | I88: =IF(compras_mes13[[#This Row],[NETO GRAVADO]]="","",compras_mes13[[#This Row],[NETO GRAVADO]]*0.21) -> 1909.0911 | P88: =SUM(compras_mes13[[#This Row],[NETO GRAVADO]:[Otros / No Grav.]]) -> 11000.001 | Q88: =IFERROR(IF(compras_mes13[[#This Row],[CUIT]]="","-",VLOOKUP(compras_mes13[[#This Row],[CUIT]],Lista_CUIT[#All],3,0)),"CUIT NO CARGADO") -> Gastos Varios | R88: =IFERROR(IF(compras_mes13[[#This Row],[CUIT]]="","-",VLOOKUP(compras_mes13[[#This Row],[CUIT]],Lista_CUIT[#All],4,0)),"CUIT NO CARGADO") -> 0
B89: 44635 | C89: 1 | D89: 5 | E89: 18085 | F89: 30616146447 | G89: =IFERROR(IF(compras_mes13[[#This Row],[CUIT]]="","-",VLOOKUP(compras_mes13[[#This Row],[CUIT]],Lista_CUIT[#All],2,0)),"CUIT NO CARGADO") -> EGEO SOCIEDAD DE RESPONSABILIDAD LIMITADA | H89: 42360 | I89: =IF(compras_mes13[[#This Row],[NETO GRAVADO]]="","",compras_mes13[[#This Row],[NETO GRAVADO]]*0.21) -> 8895.6 | P89: =SUM(compras_mes13[[#This Row],[NETO GRAVADO]:[Otros / No Grav.]]) -> 51255.6 | Q89: =IFERROR(IF(compras_mes13[[#This Row],[CUIT]]="","-",VLOOKUP(compras_mes13[[#This Row],[CUIT]],Lista_CUIT[#All],3,0)),"CUIT NO CARGADO") -> Gastos Varios | R89: =IFERROR(IF(compras_mes13[[#This Row],[CUIT]]="","-",VLOOKUP(compras_mes13[[#This Row],[CUIT]],Lista_CUIT[#All],4,0)),"CUIT NO CARGADO") -> 0
B90: 44635 | C90: 3 | D90: 3 | E90: 381 | F90: 30679163317 | G90: =IFERROR(IF(compras_mes13[[#This Row],[CUIT]]="","-",VLOOKUP(compras_mes13[[#This Row],[CUIT]],Lista_CUIT[#All],2,0)),"CUIT NO CARGADO") -> RANKO SRL | H90: -19999.73 | I90: =IF(compras_mes13[[#This Row],[NETO GRAVADO]]="","",compras_mes13[[#This Row],[NETO GRAVADO]]*0.21) -> -4199.9433 | P90: =SUM(compras_mes13[[#This Row],[NETO GRAVADO]:[Otros / No Grav.]]) -> -24199.673 | Q90: =IFERROR(IF(compras_mes13[[#This Row],[CUIT]]="","-",VLOOKUP(compras_mes13[[#This Row],[CUIT]],Lista_CUIT[#All],3,0)),"CUIT NO CARGADO") -> Gastos Varios | R90: =IFERROR(IF(compras_mes13[[#This Row],[CUIT]]="","-",VLOOKUP(compras_mes13[[#This Row],[CUIT]],Lista_CUIT[#All],4,0)),"CUIT NO CARGADO") -> 0
B91: 44643 | C91: 1 | D91: 5 | E91: 18143 | F91: 30616146447 | G91: =IFERROR(IF(compras_mes13[[#This Row],[CUIT]]="","-",VLOOKUP(compras_mes13[[#This Row],[CUIT]],Lista_CUIT[#All],2,0)),"CUIT NO CARGADO") -> EGEO SOCIEDAD DE RESPONSABILIDAD LIMITADA | H91: 112800 | I91: =IF(compras_mes13[[#This Row],[NETO GRAVADO]]="","",compras_mes13[[#This Row],[NETO GRAVADO]]*0.21) -> 23688 | N91: 856.26 | P91: =SUM(compras_mes13[[#This Row],[NETO GRAVADO]:[Otros / No Grav.]]) -> 137344.26 | Q91: =IFERROR(IF(compras_mes13[[#This Row],[CUIT]]="","-",VLOOKUP(compras_mes13[[#This Row],[CUIT]],Lista_CUIT[#All],3,0)),"CUIT NO CARGADO") -> Gastos Varios | R91: =IFERROR(IF(compras_mes13[[#This Row],[CUIT]]="","-",VLOOKUP(compras_mes13[[#This Row],[CUIT]],Lista_CUIT[#All],4,0)),"CUIT NO CARGADO") -> 0
B92: 44651 | C92: 1 | D92: 2188 | E92: 62352 | F92: 30548083156 | G92: =IFERROR(IF(compras_mes13[[#This Row],[CUIT]]="","-",VLOOKUP(compras_mes13[[#This Row],[CUIT]],Lista_CUIT[#All],2,0)),"CUIT NO CARGADO") -> COTO S.A. | H92: 39428.66 | I92: =IF(compras_mes13[[#This Row],[NETO GRAVADO]]="","",compras_mes13[[#This Row],[NETO GRAVADO]]*0.21) -> 8280.0186 | P92: =SUM(compras_mes13[[#This Row],[NETO GRAVADO]:[Otros / No Grav.]]) -> 47708.679 | Q92: =IFERROR(IF(compras_mes13[[#This Row],[CUIT]]="","-",VLOOKUP(compras_mes13[[#This Row],[CUIT]],Lista_CUIT[#All],3,0)),"CUIT NO CARGADO") -> Gastos Varios | R92: =IFERROR(IF(compras_mes13[[#This Row],[CUIT]]="","-",VLOOKUP(compras_mes13[[#This Row],[CUIT]],Lista_CUIT[#All],4,0)),"CUIT NO CARGADO") -> 0
B93: 44620 | C93: 1 | D93: 7 | E93: 4624 | F93: 20043671430 | G93: =IFERROR(IF(compras_mes13[[#This Row],[CUIT]]="","-",VLOOKUP(compras_mes13[[#This Row],[CUIT]],Lista_CUIT[#All],2,0)),"CUIT NO CARGADO") -> ECHT DANIEL | H93: 8677.69 | I93: =IF(compras_mes13[[#This Row],[NETO GRAVADO]]="","",compras_mes13[[#This Row],[NETO GRAVADO]]*0.21) -> 1822.3149 | P93: =SUM(compras_mes13[[#This Row],[NETO GRAVADO]:[Otros / No Grav.]]) -> 10500.005 | Q93: =IFERROR(IF(compras_mes13[[#This Row],[CUIT]]="","-",VLOOKUP(compras_mes13[[#This Row],[CUIT]],Lista_CUIT[#All],3,0)),"CUIT NO CARGADO") -> Gtos Comercializacion | R93: =IFERROR(IF(compras_mes13[[#This Row],[CUIT]]="","-",VLOOKUP(compras_mes13[[#This Row],[CUIT]],Lista_CUIT[#All],4,0)),"CUIT NO CARGADO") -> CORRIENTES
B94: 44643 | C94: 1 | D94: 6 | E94: 1979 | F94: 30574603788 | G94: =IFERROR(IF(compras_mes13[[#This Row],[CUIT]]="","-",VLOOKUP(compras_mes13[[#This Row],[CUIT]],Lista_CUIT[#All],2,0)),"CUIT NO CARGADO") -> Codac SRL | H94: 73968 | I94: =IF(compras_mes13[[#This Row],[NETO GRAVADO]]="","",compras_mes13[[#This Row],[NETO GRAVADO]]*0.21) -> 15533.28 | L94: 186.06 | M94: 6429.48 | P94: =SUM(compras_mes13[[#This Row],[NETO GRAVADO]:[Otros / No Grav.]]) -> 96116.82 | Q94: =IFERROR(IF(compras_mes13[[#This Row],[CUIT]]="","-",VLOOKUP(compras_mes13[[#This Row],[CUIT]],Lista_CUIT[#All],3,0)),"CUIT NO CARGADO") -> Mercaderia | R94: =IFERROR(IF(compras_mes13[[#This Row],[CUIT]]="","-",VLOOKUP(compras_mes13[[#This Row],[CUIT]],Lista_CUIT[#All],4,0)),"CUIT NO CARGADO") -> 0
B95: Total | H95: =SUBTOTAL(109,compras_mes13[NETO GRAVADO]) -> 3554120.1 | I95: =SUBTOTAL(109,compras_mes13[IVA 21 %]) -> 749794.34 | J95: =SUBTOTAL(109,compras_mes13[IVA 27%]) -> 0 | K95: =SUBTOTAL(109,compras_mes13[IVA 10,5%]) -> 0 | L95: =SUBTOTAL(109,compras_mes13[PERC. IVA]) -> 2744.85 | M95: =SUBTOTAL(109,compras_mes13[PERC IIBB BS AS]) -> 9324.93 | N95: =SUBTOTAL(109,compras_mes13[PERC. IIBB CABA]) -> 3864.35 | O95: =SUBTOTAL(109,compras_mes13[Otros / No Grav.]) -> 657563.89 | P95: =SUBTOTAL(109,compras_mes13[TOTAL]) -> 4977412.5
D100: LIQUIDACION EXTRACTOS BANCARIOS-TARJETAS
D101: FECHA | E101: NRO CPTE | F101: BANCO | G101: NETO | H101: IVA 21% | I101: IVA 10,5% | J101: RET IIBB CABA | K101: PERC IVA | L101: PERC IIBB | M101: No grav. | N101: RET. GAN
D102: 44622 | E102: 2336320 | F102: BBVA | G102: 6889.87 | H102: 1446.87 | K102: 206.69
D103: 44622 | E103: 2336326 | F103: BBVA | M103: 3600.37
D104: 44622 | E104: 2336326 | F104: BBVA | M104: 8265.14
D105: 44650 | E105: 97339008 | F105: BBVA - CABAL | G105: 1597.31 | H105: 229.56 | J105: 1390.26 | K105: 867.41 | N105: 151.16
D106: 44651 | E106: 433960 | F106: GALICIA - VISA | G106: 320 | H106: 10.14 | M106: 67.2
D107: 44651 | E107: 9688236 | F107: BBVA - VISA | G107: 10495 | H107: 2203.95 | K107: 314.85
D108: 44651 | E108: 2022 | F108: BBVA - FRANCES | G108: 8890 | H108: 1866.9 | J108: 336 | K108: 115.5 | M108: 91160.79 | N108: 44900.09
D109: 44651 | E109: 2022 | F109: GALICIA | G109: 3145.77 | H109: 645.31 | J109: 180 | K109: 90 | M109: 3502.24 | N109: 1723.66
D110: 44651 | E110: 2022 | F110: BBVA - VISA | G110: 355.37 | H110: 74.63 | M110: 16200.84 | N110: 29270.26
D111: 44651 | E111: 2022 | F111: BBVA - MESTRO | G111: 876.13 | H111: 183.99 | J111: 4888.83
D112: 44651 | E112: 2022 | F112: BBVS - MASTERCARD | G112: 131386 | H112: 20001.44 | J112: 145794.11
D114: Total | G114: =SUBTOTAL(109,extracto_banco_mes155[NETO]) -> 163955.45 | H114: =SUBTOTAL(109,extracto_banco_mes155[IVA 21%]) -> 26662.79 | I114: =SUBTOTAL(109,extracto_banco_mes155[IVA 10,5%]) -> 0 | J114: =SUBTOTAL(109,extracto_banco_mes155[RET IIBB CABA]) -> 152589.2 | K114: =SUBTOTAL(109,extracto_banco_mes155[PERC IVA]) -> 1594.45 | L114: =SUBTOTAL(109,extracto_banco_mes155[PERC IIBB]) -> 0 | M114: =SUM(extracto_banco_mes155[No grav.]) -> 122796.58 | N114: =SUM(extracto_banco_mes155[RET. GAN]) -> 76045.17
D117: FACTURAS C
D118: FECHA | E118: PTO VTA | F118: FC Nº | G118: CUIT | H118: RAZON SOCIAL | I118: TOTAL | J118: TIPO DE GASTO | K118: Provincia
D119: 44634 | E119: 1 | F119: 1 | G119: 30717223299 | H119: =IFERROR(IF(factura_c_mes152[[#This Row],[CUIT]]="","-",VLOOKUP(factura_c_mes152[[#This Row],[CUIT]],Lista_CUIT[#All],2,0)),"CUIT NO CARGADO") -> ACEPYM | I119: 132000 | J119: =IFERROR(IF(factura_c_mes152[[#This Row],[CUIT]]="","-",VLOOKUP(factura_c_mes152[[#This Row],[CUIT]],Lista_CUIT[#All],3,0)),"CUIT NO CARGADO") -> Mercaderia | K119: =IFERROR(IF(factura_c_mes152[[#This Row],[CUIT]]="","-",VLOOKUP(factura_c_mes152[[#This Row],[CUIT]],Lista_CUIT[#All],4,0)),"CUIT NO CARGADO") -> 0
D120: 44641 | E120: 1 | F120: 2 | G120: 30717223299 | H120: =IFERROR(IF(factura_c_mes152[[#This Row],[CUIT]]="","-",VLOOKUP(factura_c_mes152[[#This Row],[CUIT]],Lista_CUIT[#All],2,0)),"CUIT NO CARGADO") -> ACEPYM | I120: 132000 | J120: =IFERROR(IF(factura_c_mes152[[#This Row],[CUIT]]="","-",VLOOKUP(factura_c_mes152[[#This Row],[CUIT]],Lista_CUIT[#All],3,0)),"CUIT NO CARGADO") -> Mercaderia | K120: =IFERROR(IF(factura_c_mes152[[#This Row],[CUIT]]="","-",VLOOKUP(factura_c_mes152[[#This Row],[CUIT]],Lista_CUIT[#All],4,0)),"CUIT NO CARGADO") -> 0
D121: 44648 | E121: 1 | F121: 72 | G121: 20957969195 | H121: =IFERROR(IF(factura_c_mes152[[#This Row],[CUIT]]="","-",VLOOKUP(factura_c_mes152[[#This Row],[CUIT]],Lista_CUIT[#All],2,0)),"CUIT NO CARGADO") -> AVENDAÑO ONTIVERO LEANDRO J | I121: 140835 | J121: =IFERROR(IF(factura_c_mes152[[#This Row],[CUIT]]="","-",VLOOKUP(factura_c_mes152[[#This Row],[CUIT]],Lista_CUIT[#All],3,0)),"CUIT NO CARGADO") -> Mercaderia | K121: =IFERROR(IF(factura_c_mes152[[#This Row],[CUIT]]="","-",VLOOKUP(factura_c_mes152[[#This Row],[CUIT]],Lista_CUIT[#All],4,0)),"CUIT NO CARGADO") -> 0
H122: =IFERROR(IF(factura_c_mes152[[#This Row],[CUIT]]="","-",VLOOKUP(factura_c_mes152[[#This Row],[CUIT]],Lista_CUIT[#All],2,0)),"CUIT NO CARGADO") -> - | J122: =IFERROR(IF(factura_c_mes152[[#This Row],[CUIT]]="","-",VLOOKUP(factura_c_mes152[[#This Row],[CUIT]],Lista_CUIT[#All],3,0)),"CUIT NO CARGADO") -> - | K122: =IFERROR(IF(factura_c_mes152[[#This Row],[CUIT]]="","-",VLOOKUP(factura_c_mes152[[#This Row],[CUIT]],Lista_CUIT[#All],4,0)),"CUIT NO CARGADO") -> -
D123: Total | I123: =SUBTOTAL(109,factura_c_mes152[TOTAL]) -> 404835
B129: LIBRO IVA VENTAS | K129: =N1 -> 44621
B131: VENTAS "A"
B132: FECHA | C132: TIPO | D132: PTO VENTA | E132: Nº FACTURA | F132: CUIT | G132: RAZON SOCIAL | H132: IMPORTE NETO | I132: IVA 21% | J132: IVA 10,5% | K132: EXENTO | L132: TOTAL | M132: Provincia
G133: =IFERROR(IF(venta_a_mes153[[#This Row],[CUIT]]="","-",VLOOKUP(venta_a_mes153[[#This Row],[CUIT]],Lista_CUIT[#All],2,0)),"CUIT NO CARGADO") -> - | I133: =venta_a_mes153[[#This Row],[IMPORTE NETO]]*0.21 -> 0 | L133: =SUM(venta_a_mes153[[#This Row],[IMPORTE NETO]:[EXENTO]]) -> 0
G134: =IFERROR(IF(venta_a_mes153[[#This Row],[CUIT]]="","-",VLOOKUP(venta_a_mes153[[#This Row],[CUIT]],Lista_CUIT[#All],2,0)),"CUIT NO CARGADO") -> - | I134: =venta_a_mes153[[#This Row],[IMPORTE NETO]]*0.21 -> 0 | L134: =SUM(venta_a_mes153[[#This Row],[IMPORTE NETO]:[EXENTO]]) -> 0
G135: =IFERROR(IF(venta_a_mes153[[#This Row],[CUIT]]="","-",VLOOKUP(venta_a_mes153[[#This Row],[CUIT]],Lista_CUIT[#All],2,0)),"CUIT NO CARGADO") -> - | I135: =venta_a_mes153[[#This Row],[IMPORTE NETO]]*0.21 -> 0 | L135: =SUM(venta_a_mes153[[#This Row],[IMPORTE NETO]:[EXENTO]]) -> 0
...

Sheet Abr-22
B1: LIBRO IVA COMPRAS | G1: ='Ene-22'!G1:M1 -> EUROARGENTINA | N1: =EDATE('Ene-22'!N1,3) -> 44652
B3: TOTAL COMPRAS | G3: TOTAL CREDITO FISCAL | J3: TOTAL VENTAS NETAS | M3: TOTAL DEBITO FISCAL | P3: RESULTADO
B4: =SUM(compras_mes4[[#Totals],[NETO GRAVADO]])+extracto_banco_mes15516[[#Totals],[NETO]] -> 7938454.2 | G4: =compras_mes4[[#Totals],[IVA 21 %]]+compras_mes4[[#Totals],[IVA 27%]]+compras_mes4[[#Totals],[IVA 10,5%]]+extracto_banco_mes15516[[#Totals],[IVA 21%]] -> 1995795.4 | J4: =venta_a_mes4[[#Totals],[IMPORTE NETO]]+#REF! -> #REF! | M4: =venta_a_mes4[[#Totals],[IVA 21%]]+venta_a_mes4[[#Totals],[IVA 10,5%]]+#REF!+#REF! -> #REF! | P4: =G4-M4 -> #REF!
B8: FECHA | C8: TIPO | D8: PTO VTA | E8: NRO. CPTE | F8: CUIT | G8: RAZON SOCIAL | H8: NETO GRAVADO | I8: IVA 21 % | J8: IVA 27% | K8: IVA 10,5% | L8: PERC. IVA | M8: PERC IIBB BS AS | N8: PERC. IIBB CABA | O8: Otros / No Grav. | P8: TOTAL | Q8: Tipo de Gasto | R8: Provincia
B9: 44652 | C9: 1 | D9: 1 | E9: 33 | F9: 30716010313 | G9: =IFERROR(IF(compras_mes4[[#This Row],[CUIT]]="","-",VLOOKUP(compras_mes4[[#This Row],[CUIT]],Lista_CUIT[#All],2,0)),"CUIT NO CARGADO") -> H UNO 1469 S.A. | H9: 32000 | I9: 6720 | P9: 38720 | Q9: =IFERROR(IF(compras_mes4[[#This Row],[CUIT]]="","-",VLOOKUP(compras_mes4[[#This Row],[CUIT]],Lista_CUIT[#All],3,0)),"CUIT NO CARGADO") -> Alquiler | R9: =IFERROR(IF(compras_mes4[[#This Row],[CUIT]]="","-",VLOOKUP(compras_mes4[[#This Row],[CUIT]],Lista_CUIT[#All],4,0)),"CUIT NO CARGADO") -> 0
B10: 44652 | C10: 1 | D10: 1 | E10: 236 | F10: 20131206144 | G10: =IFERROR(IF(compras_mes4[[#This Row],[CUIT]]="","-",VLOOKUP(compras_mes4[[#This Row],[CUIT]],Lista_CUIT[#All],2,0)),"CUIT NO CARGADO") -> CHAMORRO MANUEL | H10: 18000 | I10: 3780 | P10: 21780 | Q10: =IFERROR(IF(compras_mes4[[#This Row],[CUIT]]="","-",VLOOKUP(compras_mes4[[#This Row],[CUIT]],Lista_CUIT[#All],3,0)),"CUIT NO CARGADO") -> Alquiler | R10: =IFERROR(IF(compras_mes4[[#This Row],[CUIT]]="","-",VLOOKUP(compras_mes4[[#This Row],[CUIT]],Lista_CUIT[#All],4,0)),"CUIT NO CARGADO") -> 0
B11: 44657 | C11: 1 | D11: 7 | E11: 4085 | F11: 30716825309 | G11: =IFERROR(IF(compras_mes4[[#This Row],[CUIT]]="","-",VLOOKUP(compras_mes4[[#This Row],[CUIT]],Lista_CUIT[#All],2,0)),"CUIT NO CARGADO") -> LOS ACCESOS 3 | H11: 2624.26 | I11: 551.09 | N11: 726.04 | P11: 3901.39 | Q11: =IFERROR(IF(compras_mes4[[#This Row],[CUIT]]="","-",VLOOKUP(compras_mes4[[#This Row],[CUIT]],Lista_CUIT[#All],3,0)),"CUIT NO CARGADO") -> Combustible | R11: =IFERROR(IF(compras_mes4[[#This Row],[CUIT]]="","-",VLOOKUP(compras_mes4[[#This Row],[CUIT]],Lista_CUIT[#All],4,0)),"CUIT NO CARGADO") -> 0
B12: 44659 | C12: 1 | D12: 14 | E12: 17904 | F12: 30708549041 | G12: =IFERROR(IF(compras_mes4[[#This Row],[CUIT]]="","-",VLOOKUP(compras_mes4[[#This Row],[CUIT]],Lista_CUIT[#All],2,0)),"CUIT NO CARGADO") -> FLORIPO S.A. | H12: 3563.83 | I12: 748.4 | N12: 125.77 | P12: 4438 | Q12: =IFERROR(IF(compras_mes4[[#This Row],[CUIT]]="","-",VLOOKUP(compras_mes4[[#This Row],[CUIT]],Lista_CUIT[#All],3,0)),"CUIT NO CARGADO") -> Combustible | R12: =IFERROR(IF(compras_mes4[[#This Row],[CUIT]]="","-",VLOOKUP(compras_mes4[[#This Row],[CUIT]],Lista_CUIT[#All],4,0)),"CUIT NO CARGADO") -> 0
B13: 44680 | C13: 1 | D13: 14 | E13: 9347 | F13: 33707010059 | G13: =IFERROR(IF(compras_mes4[[#This Row],[CUIT]]="","-",VLOOKUP(compras_mes4[[#This Row],[CUIT]],Lista_CUIT[#All],2,0)),"CUIT NO CARGADO") -> BUZANCY S.A. | H13: 2545.18 | I13: 534.49 | L13: 474.3 | P13: 3553.97 | Q13: =IFERROR(IF(compras_mes4[[#This Row],[CUIT]]="","-",VLOOKUP(compras_mes4[[#This Row],[CUIT]],Lista_CUIT[#All],3,0)),"CUIT NO CARGADO") -> Combustible | R13: =IFERROR(IF(compras_mes4[[#This Row],[CUIT]]="","-",VLOOKUP(compras_mes4[[#This Row],[CUIT]],Lista_CUIT[#All],4,0)),"CUIT NO CARGADO") -> 0
B14: 44657 | C14: 1 | D14: 2036 | E14: 15655 | F14: 30516186670 | G14: =IFERROR(IF(compras_mes4[[#This Row],[CUIT]]="","-",VLOOKUP(compras_mes4[[#This Row],[CUIT]],Lista_CUIT[#All],2,0)),"CUIT NO CARGADO") -> DEHEZA S.A.I.C.F. e I. | H14: 1279.07 | I14: 268.6 | N14: 352.27 | O14: 97.88 | P14: 1997.82 | Q14: =IFERROR(IF(compras_mes4[[#This Row],[CUIT]]="","-",VLOOKUP(compras_mes4[[#This Row],[CUIT]],Lista_CUIT[#All],3,0)),"CUIT NO CARGADO") -> Combustible | R14: =IFERROR(IF(compras_mes4[[#This Row],[CUIT]]="","-",VLOOKUP(compras_mes4[[#This Row],[CUIT]],Lista_CUIT[#All],4,0)),"CUIT NO CARGADO") -> 0
B15: 44663 | C15: 1 | D15: 5141 | E15: 2648 | F15: 30695542476 | G15: =IFERROR(IF(compras_mes4[[#This Row],[CUIT]]="","-",VLOOKUP(compras_mes4[[#This Row],[CUIT]],Lista_CUIT[#All],2,0)),"CUIT NO CARGADO") -> PAN AMERICAN ENERGY SL S.AR | H15: 969.82 | I15: 203.66 | N15: 2101.51 | P15: 3274.99 | Q15: =IFERROR(IF(compras_mes4[[#This Row],[CUIT]]="","-",VLOOKUP(compras_mes4[[#This Row],[CUIT]],Lista_CUIT[#All],3,0)),"CUIT NO CARGADO") -> Combustible | R15: =IFERROR(IF(compras_mes4[[#This Row],[CUIT]]="","-",VLOOKUP(compras_mes4[[#This Row],[CUIT]],Lista_CUIT[#All],4,0)),"CUIT NO CARGADO") -> 0
B16: 44666 | C16: 1 | D16: 11 | E16: 1577 | F16: 30653466931 | G16: =IFERROR(IF(compras_mes4[[#This Row],[CUIT]]="","-",VLOOKUP(compras_mes4[[#This Row],[CUIT]],Lista_CUIT[#All],2,0)),"CUIT NO CARGADO") -> GNC ESCOBAR S.A. | H16: 2762.33 | I16: 580.09 | L16: 759.15 | P16: 4101.57 | Q16: =IFERROR(IF(compras_mes4[[#This Row],[CUIT]]="","-",VLOOKUP(compras_mes4[[#This Row],[CUIT]],Lista_CUIT[#All],3,0)),"CUIT NO CARGADO") -> Combustible | R16: =IFERROR(IF(compras_mes4[[#This Row],[CUIT]]="","-",VLOOKUP(compras_mes4[[#This Row],[CUIT]],Lista_CUIT[#All],4,0)),"CUIT NO CARGADO") -> 0
B17: 44678 | C17: 1 | D17: 6852 | E17: 8581 | F17: 30678774495 | G17: =IFERROR(IF(compras_mes4[[#This Row],[CUIT]]="","-",VLOOKUP(compras_mes4[[#This Row],[CUIT]],Lista_CUIT[#All],2,0)),"CUIT NO CARGADO") -> OPER. DE EST. DE SERV. SA | H17: 6112.44 | I17: 1283.61 | L17: 1706.25 | P17: 9102.3 | Q17: =IFERROR(IF(compras_mes4[[#This Row],[CUIT]]="","-",VLOOKUP(compras_mes4[[#This Row],[CUIT]],Lista_CUIT[#All],3,0)),"CUIT NO CARGADO") -> Combustible | R17: =IFERROR(IF(compras_mes4[[#This Row],[CUIT]]="","-",VLOOKUP(compras_mes4[[#This Row],[CUIT]],Lista_CUIT[#All],4,0)),"CUIT NO CARGADO") -> 0
B18: 44679 | C18: 1 | D18: 20 | E18: 2916 | F18: 30515800219 | G18: =IFERROR(IF(compras_mes4[[#This Row],[CUIT]]="","-",VLOOKUP(compras_mes4[[#This Row],[CUIT]],Lista_CUIT[#All],2,0)),"CUIT NO CARGADO") -> INCAT SRL | H18: 10729.86 | I18: 2253.27 | L18: 2507.37 | P18: 15490.5 | Q18: =IFERROR(IF(compras_mes4[[#This Row],[CUIT]]="","-",VLOOKUP(compras_mes4[[#This Row],[CUIT]],Lista_CUIT[#All],3,0)),"CUIT NO CARGADO") -> Combustible | R18: =IFERROR(IF(compras_mes4[[#This Row],[CUIT]]="","-",VLOOKUP(compras_mes4[[#This Row],[CUIT]],Lista_CUIT[#All],4,0)),"CUIT NO CARGADO") -> 0
B19: 44681 | C19: 1 | D19: 12 | E19: 1240 | F19: 30696131003 | G19: =IFERROR(IF(compras_mes4[[#This Row],[CUIT]]="","-",VLOOKUP(compras_mes4[[#This Row],[CUIT]],Lista_CUIT[#All],2,0)),"CUIT NO CARGADO") -> PETROLFE S.A. | H19: 56337.73 | I19: 11830.92 | N19: 14747.02 | P19: 82915.67 | Q19: =IFERROR(IF(compras_mes4[[#This Row],[CUIT]]="","-",VLOOKUP(compras_mes4[[#This Row],[CUIT]],Lista_CUIT[#All],3,0)),"CUIT NO CARGADO") -> Combustible | R19: =IFERROR(IF(compras_mes4[[#This Row],[CUIT]]="","-",VLOOKUP(compras_mes4[[#This Row],[CUIT]],Lista_CUIT[#All],4,0)),"CUIT NO CARGADO") -> 0
B20: 44663 | C20: 1 | D20: 5 | E20: 2841 | F20: 30714734446 | G20: =IFERROR(IF(compras_mes4[[#This Row],[CUIT]]="","-",VLOOKUP(compras_mes4[[#This Row],[CUIT]],Lista_CUIT[#All],2,0)),"CUIT NO CARGADO") -> GANADERA EL 13 S.R.L | H20: 2944.79 | I20: 618.41 | P20: 3563.2 | Q20: =IFERROR(IF(compras_mes4[[#This Row],[CUIT]]="","-",VLOOKUP(compras_mes4[[#This Row],[CUIT]],Lista_CUIT[#All],3,0)),"CUIT NO CARGADO") -> Comida | R20: =IFERROR(IF(compras_mes4[[#This Row],[CUIT]]="","-",VLOOKUP(compras_mes4[[#This Row],[CUIT]],Lista_CUIT[#All],4,0)),"CUIT NO CARGADO") -> 0
B21: 44681 | C21: 1 | D21: 6 | E21: 1900 | F21: 20134664518 | G21: =IFERROR(IF(compras_mes4[[#This Row],[CUIT]]="","-",VLOOKUP(compras_mes4[[#This Row],[CUIT]],Lista_CUIT[#All],2,0)),"CUIT NO CARGADO") -> HOKAMA SERGIO ENRIQUE | H21: 15009.84 | I21: 3152.07 | P21: 18161.91 | Q21: =IFERROR(IF(compras_mes4[[#This Row],[CUIT]]="","-",VLOOKUP(compras_mes4[[#This Row],[CUIT]],Lista_CUIT[#All],3,0)),"CUIT NO CARGADO") -> Comida-Limpieza | R21: =IFERROR(IF(compras_mes4[[#This Row],[CUIT]]="","-",VLOOKUP(compras_mes4[[#This Row],[CUIT]],Lista_CUIT[#All],4,0)),"CUIT NO CARGADO") -> 0
B22: 44657 | C22: 1 | D22: 3546 | E22: 971 | F22: 30526874249 | G22: =IFERROR(IF(compras_mes4[[#This Row],[CUIT]]="","-",VLOOKUP(compras_mes4[[#This Row],[CUIT]],Lista_CUIT[#All],2,0)),"CUIT NO CARGADO") -> FRAVEGA S A C I E I | H22: 99171.9 | I22: 20826.1 | P22: 119998 | Q22: =IFERROR(IF(compras_mes4[[#This Row],[CUIT]]="","-",VLOOKUP(compras_mes4[[#This Row],[CUIT]],Lista_CUIT[#All],3,0)),"CUIT NO CARGADO") -> Equipos de Informatica | R22: =IFERROR(IF(compras_mes4[[#This Row],[CUIT]]="","-",VLOOKUP(compras_mes4[[#This Row],[CUIT]],Lista_CUIT[#All],4,0)),"CUIT NO CARGADO") -> 0
B23: 44663 | C23: 1 | D23: 2 | E23: 5514 | F23: 30711069360 | G23: =IFERROR(IF(compras_mes4[[#This Row],[CUIT]]="","-",VLOOKUP(compras_mes4[[#This Row],[CUIT]],Lista_CUIT[#All],2,0)),"CUIT NO CARGADO") -> BIDCOM S.R.L. | H23: 314090.5 | K23: 32979.5 | N23: 18845.43 | P23: 365915.43 | Q23: =IFERROR(IF(compras_mes4[[#This Row],[CUIT]]="","-",VLOOKUP(compras_mes4[[#This Row],[CUIT]],Lista_CUIT[#All],3,0)),"CUIT NO CARGADO") -> Equipos de Informatica | R23: =IFERROR(IF(compras_mes4[[#This Row],[CUIT]]="","-",VLOOKUP(compras_mes4[[#This Row],[CUIT]],Lista_CUIT[#All],4,0)),"CUIT NO CARGADO") -> 0
B24: 44665 | C24: 1 | D24: 4 | E24: 49676 | F24: 30716292319 | G24: =IFERROR(IF(compras_mes4[[#This Row],[CUIT]]="","-",VLOOKUP(compras_mes4[[#This Row],[CUIT]],Lista_CUIT[#All],2,0)),"CUIT NO CARGADO") -> NEPTUN CORP S.A. | H24: 147510.41 | K24: 15488.59 | P24: 162999 | Q24: =IFERROR(IF(compras_mes4[[#This Row],[CUIT]]="","-",VLOOKUP(compras_mes4[[#This Row],[CUIT]],Lista_CUIT[#All],3,0)),"CUIT NO CARGADO") -> Equipos de Informatica | R24: =IFERROR(IF(compras_mes4[[#This Row],[CUIT]]="","-",VLOOKUP(compras_mes4[[#This Row],[CUIT]],Lista_CUIT[#All],4,0)),"CUIT NO CARGADO") -> 0
B25: 44678 | C25: 1 | D25: 4 | E25: 50358 | F25: 30716292319 | G25: =IFERROR(IF(compras_mes4[[#This Row],[CUIT]]="","-",VLOOKUP(compras_mes4[[#This Row],[CUIT]],Lista_CUIT[#All],2,0)),"CUIT NO CARGADO") -> NEPTUN CORP S.A. | H25: 57012.67 | K25: 5986.33 | P25: 62999 | Q25: =IFERROR(IF(compras_mes4[[#This Row],[CUIT]]="","-",VLOOKUP(compras_mes4[[#This Row],[CUIT]],Lista_CUIT[#All],3,0)),"CUIT NO CARGADO") -> Equipos de Informatica | R25: =IFERROR(IF(compras_mes4[[#This Row],[CUIT]]="","-",VLOOKUP(compras_mes4[[#This Row],[CUIT]],Lista_CUIT[#All],4,0)),"CUIT NO CARGADO") -> 0
B26: 44677 | C26: 1 | D26: 3 | E26: 2022 | F26: 30707826890 | G26: =IFERROR(IF(compras_mes4[[#This Row],[CUIT]]="","-",VLOOKUP(compras_mes4[[#This Row],[CUIT]],Lista_CUIT[#All],2,0)),"CUIT NO CARGADO") -> JUVIALE S.R.L. | H26: 0 | I26: 0 | L26: 13661.42 | P26: 13661.42 | Q26: =IFERROR(IF(compras_mes4[[#This Row],[CUIT]]="","-",VLOOKUP(compras_mes4[[#This Row],[CUIT]],Lista_CUIT[#All],3,0)),"CUIT NO CARGADO") -> EXPENSAS | R26: =IFERROR(IF(compras_mes4[[#This Row],[CUIT]]="","-",VLOOKUP(compras_mes4[[#This Row],[CUIT]],Lista_CUIT[#All],4,0)),"CUIT NO CARGADO") -> 0
B27: 44665 | C27: 1 | D27: 301 | E27: 10902 | F27: 30686978350 | G27: =IFERROR(IF(compras_mes4[[#This Row],[CUIT]]="","-",VLOOKUP(compras_mes4[[#This Row],[CUIT]],Lista_CUIT[#All],2,0)),"CUIT NO CARGADO") -> SPEED BUSINESS S. A. | H27: 1164.46 | I27: 265.44 | L27: 100 | P27: 1529.9 | Q27: =IFERROR(IF(compras_mes4[[#This Row],[CUIT]]="","-",VLOOKUP(compras_mes4[[#This Row],[CUIT]],Lista_CUIT[#All],3,0)),"CUIT NO CARGADO") -> Flete-Logistica | R27: =IFERROR(IF(compras_mes4[[#This Row],[CUIT]]="","-",VLOOKUP(compras_mes4[[#This Row],[CUIT]],Lista_CUIT[#All],4,0)),"CUIT NO CARGADO") -> 0
B28: 44678 | C28: 1 | D28: 3 | E28: 5220 | F28: 20044410932 | G28: =IFERROR(IF(compras_mes4[[#This Row],[CUIT]]="","-",VLOOKUP(compras_mes4[[#This Row],[CUIT]],Lista_CUIT[#All],2,0)),"CUIT NO CARGADO") -> FRATE NESTOR | H28: 17500 | I28: 3675 | P28: 21175 | Q28: =IFERROR(IF(compras_mes4[[#This Row],[CUIT]]="","-",VLOOKUP(compras_mes4[[#This Row],[CUIT]],Lista_CUIT[#All],3,0)),"CUIT NO CARGADO") -> Flete-Logistica | R28: =IFERROR(IF(compras_mes4[[#This Row],[CUIT]]="","-",VLOOKUP(compras_mes4[[#This Row],[CUIT]],Lista_CUIT[#All],4,0)),"CUIT NO CARGADO") -> 0
B29: 44663 | C29: 1 | D29: 6331 | E29: 1387 | F29: 30643922157 | G29: =IFERROR(IF(compras_mes4[[#This Row],[CUIT]]="","-",VLOOKUP(compras_mes4[[#This Row],[CUIT]],Lista_CUIT[#All],2,0)),"CUIT NO CARGADO") -> VIA BARILOCHE SA | H29: 3223.14 | I29: 676.86 | P29: 3900 | Q29: =IFERROR(IF(compras_mes4[[#This Row],[CUIT]]="","-",VLOOKUP(compras_mes4[[#This Row],[CUIT]],Lista_CUIT[#All],3,0)),"CUIT NO CARGADO") -> Flete-Logistica | R29: =IFERROR(IF(compras_mes4[[#This Row],[CUIT]]="","-",VLOOKUP(compras_mes4[[#This Row],[CUIT]],Lista_CUIT[#All],4,0)),"CUIT NO CARGADO") -> 0
B30: 44652 | C30: 1 | D30: 7 | E30: 359 | F30: 27200553573 | G30: =IFERROR(IF(compras_mes4[[#This Row],[CUIT]]="","-",VLOOKUP(compras_mes4[[#This Row],[CUIT]],Lista_CUIT[#All],2,0)),"CUIT NO CARGADO") -> PREISMAN MANUELA VERONICA | H30: 5991.74 | I30: 1258.27 | P30: 7250.01 | Q30: =IFERROR(IF(compras_mes4[[#This Row],[CUIT]]="","-",VLOOKUP(compras_mes4[[#This Row],[CUIT]],Lista_CUIT[#All],3,0)),"CUIT NO CARGADO") -> Gastos Varios | R30: =IFERROR(IF(compras_mes4[[#This Row],[CUIT]]="","-",VLOOKUP(compras_mes4[[#This Row],[CUIT]],Lista_CUIT[#All],4,0)),"CUIT NO CARGADO") -> 0
B31: 44657 | C31: 1 | D31: 8 | E31: 45381 | F31: 30714295957 | G31: =IFERROR(IF(compras_mes4[[#This Row],[CUIT]]="","-",VLOOKUP(compras_mes4[[#This Row],[CUIT]],Lista_CUIT[#All],2,0)),"CUIT NO CARGADO") -> IT BROKERS S.A. | H31: 5574.38 | I31: 1170.62 | P31: 6745 | Q31: =IFERROR(IF(compras_mes4[[#This Row],[CUIT]]="","-",VLOOKUP(compras_mes4[[#This Row],[CUIT]],Lista_CUIT[#All],3,0)),"CUIT NO CARGADO") -> Gastos Varios | R31: =IFERROR(IF(compras_mes4[[#This Row],[CUIT]]="","-",VLOOKUP(compras_mes4[[#This Row],[CUIT]],Lista_CUIT[#All],4,0)),"CUIT NO CARGADO") -> 0
B32: 44660 | C32: 1 | D32: 54 | E32: 588 | F32: 30709405108 | G32: =IFERROR(IF(compras_mes4[[#This Row],[CUIT]]="","-",VLOOKUP(compras_mes4[[#This Row],[CUIT]],Lista_CUIT[#All],2,0)),"CUIT NO CARGADO") -> MASORIENTE S.R.L. | H32: 9166.59 | I32: 1924.98 | P32: 11091.57 | Q32: =IFERROR(IF(compras_mes4[[#This Row],[CUIT]]="","-",VLOOKUP(compras_mes4[[#This Row],[CUIT]],Lista_CUIT[#All],3,0)),"CUIT NO CARGADO") -> Gastos Varios | R32: =IFERROR(IF(compras_mes4[[#This Row],[CUIT]]="","-",VLOOKUP(compras_mes4[[#This Row],[CUIT]],Lista_CUIT[#All],4,0)),"CUIT NO CARGADO") -> 0
