Workbook
Name partner_id: Configuracion!$B$332

Sheet Configuracion
F1: CUIT | G1: Cargar sin guiones
F2: RAZON SOCIAL | G2: Maximo 30 caracteres
A3: CUIT | B3: RAZON SOCIAL | C3: DETALLE | F3: DETALLE | G3: Cargar tipo de gasto
A4: 30628205090 | B4: ALBAMIE SA | C4: CLIENTE
A5: 30711678820 | B5: 2PSI INGENIERIA SRL | C5: PROVEEDOR
A6: 33716367539 | B6: 3PI S.A.S. | C6: PROVEEDOR
A7: 30660373108 | B7: ABC SA | C7: VARIOS
A8: 20300210881 | B8: ABOY DIEGO OSCAR | C8: PROVEEDOR
A9: 27229910782 | B9: ABUGAUCH MARIA DE LOS ANGELES | C9: PROVEEDOR
A10: 20242709897 | B10: ABUGAUCH VICTOR HUGO | C10: PROVEEDOR
A11: 20281669053 | B11: ACOSTA JAVIER GUSTAVO | C11: FLETE
A12: 20174240125 | B12: ACOSTA OSCAR ISIDRO | C12: VARIOS
A13: 30641659106 | B13: AGRISOL SA | C13: VARIOS
A14: 33709914109 | B14: ALAN COLLECTION SA | C14: VARIOS
A15: 20267161616 | B15: ALBAJARI DIEGO MARCOS | C15: VARIOS
... A155: 30537679855 | B155: ESTACION LIMA SA | C155: VARIOS
A156: 30-56864959-8 | B156: EXPRESO BISONTE SRL | C156: FLETE
A157: 30708542349 | B157: EXPRESO FORMOSA SRL | C157: FLETE
A158: 30526582884 | B158: EXPRESO MAR DEL PLATA SA | C158: FLETE
A159: 30577744579 | B159: EXPRESO TROLE SRL | C159: FLETE
A160: 30715949292 | B160: EYPAPEL SAS | C160: GASTOS VARIOS
A161: 30715980807 | B161: FABORT SRL | C161: PROVEEDOR
A162: 20359718765 | B162: FAIL ABRAHAM | C162: VARIOS
A163: 30643518364 | B163: FARMACIA DE MEDRANO SCS | C163: PROVEEDOR
A164: 30692138747 | B164: FARMACITY SA | C164: VARIOS
A165: 33712234429 | B165: FEDAGAS SA | C165: VARIOS
A166: 20353576012 | B166: FEDERICO PABLO FEOLA | C166: VARIOS
A167: 20343766441 | B167: FERNANDEZ MAURO | C167: TALLER
A168: 27062343449 | B168: FERREIRA LILIANA INES | C168: FLETE
... A567: 27179026967 | B567: ARABIA FABIANA | C567: GASTOS ADMIN

Sheet Oct 24
A1: ORTOPEDIA GEMINIS S.A. | J1: 45566
A4: LIBRO IVA COMPRAS
A6: FACTURAS A
A7: FECHA | B7: PTO VTA | C7: FAC A | D7: CUIT | E7: RAZON SOCIAL | F7: NETO | G7: IVA 21% | H7: IVA 27% | I7: IVA 10,5% | J7: P IVA | K7: IIBB CF | L7: IIBB BS | M7: NO GRAV | N7: OTROS | O7: TOTAL | P7: DETALLE
A8: 45574 | B8: 6 | C8: 1658 | D8: 30716815710 | E8: =VLOOKUP(D8,Configuracion!$A$4:$C$590,2,FALSE) -> PAPELERA GEOPEL SRL | F8: 15700 | G8: =F8*21% -> 3297 | O8: =SUM(F8:N8) -> 18997 | P8: =VLOOKUP(D8,Configuracion!$A$4:$C$590,3,FALSE) -> LIBRERÍA
A9: 45568 | B9: 6 | C9: 19623 | D9: 33715594949 | E9: =VLOOKUP(D9,Configuracion!$A$4:$C$590,2,FALSE) -> SOMOS ENERGIA SA | F9: 90860.71 | G9: =F9*21% -> 19080.749 | N9: 7268.6 | O9: =SUM(F9:N9) -> 117210.06 | P9: =VLOOKUP(D9,Configuracion!$A$4:$C$590,3,FALSE) -> GASTOS VARIOS
A10: 45596 | B10: 1002 | C10: 20230 | D10: 30712289046 | E10: =VLOOKUP(D10,Configuracion!$A$4:$C$590,2,FALSE) -> IMPIERI, PIÑEIRO, RIZZO Y A SA | F10: 45017.3 | G10: =F10*21% -> 9453.633 | M10: 5529.01 | O10: =SUM(F10:N10) -> 59999.943 | P10: =VLOOKUP(D10,Configuracion!$A$4:$C$590,3,FALSE) -> VARIOS
A11: 45593 | B11: 591 | C11: 3828 | D11: 30590360763 | E11: =VLOOKUP(D11,Configuracion!$A$4:$C$590,2,FALSE) -> CENCOSUD S.A. | F11: 51727.69 | G11: =F11*21% -> 10862.815 | J11: 1551.83 | K11: 2586.38 | O11: =SUM(F11:N11) -> 66728.715 | P11: =VLOOKUP(D11,Configuracion!$A$4:$C$590,3,FALSE) -> VARIOS
A12: 45595 | B12: 13 | C12: 1869 | D12: 33709914109 | E12: =VLOOKUP(D12,Configuracion!$A$4:$C$590,2,FALSE) -> ALAN COLLECTION SA | F12: 19008.26 | G12: =F12*21% -> 3991.7346 | O12: =SUM(F12:N12) -> 22999.995 | P12: =VLOOKUP(D12,Configuracion!$A$4:$C$590,3,FALSE) -> VARIOS
A13: 45574 | B13: 6 | C13: 19699 | D13: 33715594949 | E13: =VLOOKUP(D13,Configuracion!$A$4:$C$590,2,FALSE) -> SOMOS ENERGIA SA | F13: 77387.46 | G13: =F13*21% -> 16251.367 | N13: 6354.13 | O13: =SUM(F13:N13) -> 99992.957 | P13: =VLOOKUP(D13,Configuracion!$A$4:$C$590,3,FALSE) -> GASTOS VARIOS
A14: 45578 | B14: 8 | C14: 12982 | D14: 33715594949 | E14: =VLOOKUP(D14,Configuracion!$A$4:$C$590,2,FALSE) -> SOMOS ENERGIA SA | F14: 23224.02 | G14: =F14*21% -> 4877.0442 | N14: 1906.88 | O14: =SUM(F14:N14) -> 30007.944 | P14: =VLOOKUP(D14,Configuracion!$A$4:$C$590,3,FALSE) -> GASTOS VARIOS
A15: 45594 | B15: 8 | C15: 13145 | D15: 33715594949 | E15: =VLOOKUP(D15,Configuracion!$A$4:$C$590,2,FALSE) -> SOMOS ENERGIA SA | F15: 59005.12 | G15: =F15*21% -> 12391.075 | N15: 4844.8 | O15: =SUM(F15:N15) -> 76240.995 | P15: =VLOOKUP(D15,Configuracion!$A$4:$C$590,3,FALSE) -> GASTOS VARIOS
A16: 45588 | B16: 11 | C16: 12631 | D16: 30705740670 | E16: =VLOOKUP(D16,Configuracion!$A$4:$C$590,2,FALSE) -> MAVISUR SA | F16: 51347.06 | G16: =F16*21% -> 10782.883 | N16: 6872.06 | O16: =SUM(F16:N16) -> 69002.003 | P16: =VLOOKUP(D16,Configuracion!$A$4:$C$590,3,FALSE) -> VARIOS
A17: 45581 | B17: 15 | C17: 38379 | D17: 30685116657 | E17: =VLOOKUP(D17,Configuracion!$A$4:$C$590,2,FALSE) -> MIRVAR SA | F17: 48501.78 | G17: =F17*21% -> 10185.374 | N17: 5318.06 | O17: =SUM(F17:N17) -> 64005.214 | P17: =VLOOKUP(D17,Configuracion!$A$4:$C$590,3,FALSE) -> VARIOS
A18: 45586 | B18: 6 | C18: 19833 | D18: 33715594949 | E18: =VLOOKUP(D18,Configuracion!$A$4:$C$590,2,FALSE) -> SOMOS ENERGIA SA | F18: 46435.8 | G18: =F18*21% -> 9751.518 | N18: 3812.75 | O18: =SUM(F18:N18) -> 60000.068 | P18: =VLOOKUP(D18,Configuracion!$A$4:$C$590,3,FALSE) -> GASTOS VARIOS
A19: 45595 | B19: 1002 | C19: 20187 | D19: 30712289046 | E19: =VLOOKUP(D19,Configuracion!$A$4:$C$590,2,FALSE) -> IMPIERI, PIÑEIRO, RIZZO Y A SA | F19: 30011.57 | G19: =F19*21% -> 6302.4297 | K19: 3686.01 | O19: =SUM(F19:N19) -> 40000.01 | P19: =VLOOKUP(D19,Configuracion!$A$4:$C$590,3,FALSE) -> VARIOS
A20: 45589 | B20: 2 | C20: 876 | D20: 20272865869 | E20: =VLOOKUP(D20,Configuracion!$A$4:$C$590,2,FALSE) -> DI FEO MARTIN EZEQUIEL | F20: 133850 | G20: =F20*21% -> 28108.5 | O20: =SUM(F20:N20) -> 161958.5 | P20: =VLOOKUP(D20,Configuracion!$A$4:$C$590,3,FALSE) -> PROVEEDOR
A21: 45582 | B21: 2 | C21: 850 | D21: 20272865869 | E21: =VLOOKUP(D21,Configuracion!$A$4:$C$590,2,FALSE) -> DI FEO MARTIN EZEQUIEL | F21: 106750 | G21: =F21*21% -> 22417.5 | O21: =SUM(F21:N21) -> 129167.5 | P21: =VLOOKUP(D21,Configuracion!$A$4:$C$590,3,FALSE) -> PROVEEDOR
A22: 45582 | B22: 2 | C22: 845 | D22: 20272865869 | E22: =VLOOKUP(D22,Configuracion!$A$4:$C$590,2,FALSE) -> DI FEO MARTIN EZEQUIEL | F22: 109000 | G22: =F22*21% -> 22890 | O22: =SUM(F22:N22) -> 131890 | P22: =VLOOKUP(D22,Configuracion!$A$4:$C$590,3,FALSE) -> PROVEEDOR
A23: 45568 | B23: 2 | C23: 833 | D23: 20272865869 | E23: =VLOOKUP(D23,Configuracion!$A$4:$C$590,2,FALSE) -> DI FEO MARTIN EZEQUIEL | F23: 145500 | G23: =F23*21% -> 30555 | O23: =SUM(F23:N23) -> 176055 | P23: =VLOOKUP(D23,Configuracion!$A$4:$C$590,3,FALSE) -> PROVEEDOR
A24: 45575 | B24: 1 | C24: 5011 | D24: 30715141201 | E24: =VLOOKUP(D24,Configuracion!$A$4:$C$590,2,FALSE) -> REHAB SRL | F24: 43450 | G24: =F24*21% -> 9124.5 | O24: =SUM(F24:N24) -> 52574.5 | P24: =VLOOKUP(D24,Configuracion!$A$4:$C$590,3,FALSE) -> PROVEEDOR
A25: 45579 | B25: 1 | C25: 5027 | D25: 30715141201 | E25: =VLOOKUP(D25,Configuracion!$A$4:$C$590,2,FALSE) -> REHAB SRL | F25: 642844.12 | G25: =F25*21% -> 134997.27 | O25: =SUM(F25:N25) -> 777841.39 | P25: =VLOOKUP(D25,Configuracion!$A$4:$C$590,3,FALSE) -> PROVEEDOR
A26: 45573 | B26: 1 | C26: 4966 | D26: 30715141201 | E26: =VLOOKUP(D26,Configuracion!$A$4:$C$590,2,FALSE) -> REHAB SRL | F26: 267975 | G26: =F26*21% -> 56274.75 | O26: =SUM(F26:N26) -> 324249.75 | P26: =VLOOKUP(D26,Configuracion!$A$4:$C$590,3,FALSE) -> PROVEEDOR
A27: 45573 | B27: 1 | C27: 4972 | D27: 30715141201 | E27: =VLOOKUP(D27,Configuracion!$A$4:$C$590,2,FALSE) -> REHAB SRL | F27: 601618.51 | G27: =F27*21% -> 126339.89 | O27: =SUM(F27:N27) -> 727958.4 | P27: =VLOOKUP(D27,Configuracion!$A$4:$C$590,3,FALSE) -> PROVEEDOR
A28: 45569 | B28: 1 | C28: 4929 | D28: 30715141201 | E28: =VLOOKUP(D28,Configuracion!$A$4:$C$590,2,FALSE) -> REHAB SRL | F28: 99050 | G28: =F28*21% -> 20800.5 | O28: =SUM(F28:N28) -> 119850.5 | P28: =VLOOKUP(D28,Configuracion!$A$4:$C$590,3,FALSE) -> PROVEEDOR
A29: 45569 | B29: 1 | C29: 4933 | D29: 30715141201 | E29: =VLOOKUP(D29,Configuracion!$A$4:$C$590,2,FALSE) -> REHAB SRL | F29: 639938.25 | G29: =F29*21% -> 134387.03 | O29: =SUM(F29:N29) -> 774325.28 | P29: =VLOOKUP(D29,Configuracion!$A$4:$C$590,3,FALSE) -> PROVEEDOR
A30: 45589 | B30: 5 | C30: 160326 | D30: 30598960093 | E30: =VLOOKUP(D30,Configuracion!$A$4:$C$590,2,FALSE) -> SILVESTRIN FABRIS SRL | F30: 1977843 | G30: =F30*21% -> 415347.03 | K30: 98892.15 | O30: =SUM(F30:N30) -> 2492082.2 | P30: =VLOOKUP(D30,Configuracion!$A$4:$C$590,3,FALSE) -> PROVEEDOR
A31: 45575 | B31: 5 | C31: 159946 | D31: 30598960093 | E31: =VLOOKUP(D31,Configuracion!$A$4:$C$590,2,FALSE) -> SILVESTRIN FABRIS SRL | F31: 946021.5 | G31: =F31*21% -> 198664.51 | K31: 47301.08 | O31: =SUM(F31:N31) -> 1191987.1 | P31: =VLOOKUP(D31,Configuracion!$A$4:$C$590,3,FALSE) -> PROVEEDOR
A32: 45573 | B32: 5 | C32: 159832 | D32: 30598960093 | E32: =VLOOKUP(D32,Configuracion!$A$4:$C$590,2,FALSE) -> SILVESTRIN FABRIS SRL | F32: 1586940 | I32: =+F32*0.105 -> 166628.7 | K32: 79347 | O32: =SUM(F32:N32) -> 1832915.7 | P32: =VLOOKUP(D32,Configuracion!$A$4:$C$590,3,FALSE) -> PROVEEDOR
A33: 45566 | B33: 5 | C33: 159587 | D33: 30598960093 | E33: =VLOOKUP(D33,Configuracion!$A$4:$C$590,2,FALSE) -> SILVESTRIN FABRIS SRL | F33: 1464782.4 | G33: =F33*21% -> 307604.3 | K33: 73239.12 | O33: =SUM(F33:N33) -> 1845625.8 | P33: =VLOOKUP(D33,Configuracion!$A$4:$C$590,3,FALSE) -> PROVEEDOR
A34: 45568 | B34: 4 | C34: 38516 | D34: 20289111329 | E34: =VLOOKUP(D34,Configuracion!$A$4:$C$590,2,FALSE) -> R. N. LEDESMA | F34: 1170696.2 | G34: =F34*21% -> 245846.2 | O34: =SUM(F34:N34) -> 1416542.4 | P34: =VLOOKUP(D34,Configuracion!$A$4:$C$590,3,FALSE) -> PROVEEDOR
A35: 45580 | B35: 5 | C35: 32 | D35: 30707370552 | E35: =VLOOKUP(D35,Configuracion!$A$4:$C$590,2,FALSE) -> RAKE SA | F35: 895000 | G35: =F35*21% -> 187950 | O35: =SUM(F35:N35) -> 1082950 | P35: =VLOOKUP(D35,Configuracion!$A$4:$C$590,3,FALSE) -> PROVEEDOR
A36: 45569 | B36: 5 | C36: 27 | D36: 30707370552 | E36: =VLOOKUP(D36,Configuracion!$A$4:$C$590,2,FALSE) -> RAKE SA | F36: 1380000 | G36: =F36*21% -> 289800 | O36: =SUM(F36:N36) -> 1669800 | P36: =VLOOKUP(D36,Configuracion!$A$4:$C$590,3,FALSE) -> PROVEEDOR
A37: 45568 | B37: 4 | C37: 138 | D37: 20317488476 | E37: =VLOOKUP(D37,Configuracion!$A$4:$C$590,2,FALSE) -> VILLALBA MIGUEL ANGEL | F37: 150000 | G37: =F37*21% -> 31500 | O37: =SUM(F37:N37) -> 181500 | P37: =VLOOKUP(D37,Configuracion!$A$4:$C$590,3,FALSE) -> PROVEEDOR
A38: 45569 | B38: 7 | C38: 19168 | D38: 30709214078 | E38: =VLOOKUP(D38,Configuracion!$A$4:$C$590,2,FALSE) -> REHAVITA SA | F38: 59820 | G38: =F38*21% -> 12562.2 | O38: =SUM(F38:N38) -> 72382.2 | P38: =VLOOKUP(D38,Configuracion!$A$4:$C$590,3,FALSE) -> PROVEEDOR
A39: 45569 | B39: 401 | C39: 80 | D39: 30716234114 | E39: =VLOOKUP(D39,Configuracion!$A$4:$C$590,2,FALSE) -> UZUMAKI SAS | F39: 160978.5 | G39: =F39*21% -> 33805.485 | O39: =SUM(F39:N39) -> 194783.98 | P39: =VLOOKUP(D39,Configuracion!$A$4:$C$590,3,FALSE) -> PROVEEDOR
A40: 45569 | B40: 5 | C40: 2859 | D40: 30707267077 | E40: =VLOOKUP(D40,Configuracion!$A$4:$C$590,2,FALSE) -> BARBARO SC | F40: 1388000 | G40: =F40*21% -> 291480 | O40: =SUM(F40:N40) -> 1679480 | P40: =VLOOKUP(D40,Configuracion!$A$4:$C$590,3,FALSE) -> PROVEEDOR
A41: 45567 | B41: 1 | C41: 615464 | D41: 33716307749 | E41: =VLOOKUP(D41,Configuracion!$A$4:$C$590,2,FALSE) -> VERISURE ARG MONITOREO A SA | F41: 40398.88 | G41: =F41*21% -> 8483.7648 | N41: 2019.94 | O41: =SUM(F41:N41) -> 50902.585 | P41: =VLOOKUP(D41,Configuracion!$A$4:$C$590,3,FALSE) -> PROVEEDOR
A42: 45573 | B42: 120 | C42: 5161 | D42: 30587197215 | E42: =VLOOKUP(D42,Configuracion!$A$4:$C$590,2,FALSE) -> PANATEL SOCIEDAD ANONIMA | F42: 68595.04 | G42: =F42*21% -> 14404.958 | K42: 3429.75 | O42: =SUM(F42:N42) -> 86429.748 | P42: =VLOOKUP(D42,Configuracion!$A$4:$C$590,3,FALSE) -> VARIOS
A43: 45572 | B43: 8 | C43: 1698 | D43: 30708973501 | E43: =VLOOKUP(D43,Configuracion!$A$4:$C$590,2,FALSE) -> ASIAL SRL | F43: 767170 | G43: =F43*21% -> 161105.7 | O43: =SUM(F43:N43) -> 928275.7 | P43: =VLOOKUP(D43,Configuracion!$A$4:$C$590,3,FALSE) -> INSUMOS
A44: 45566 | B44: 500 | C44: 1627071 | D44: 30654118767 | E44: =VLOOKUP(D44,Configuracion!$A$4:$C$590,2,FALSE) -> SOLUCIONES MULTIMEDIA SA | F44: 94125.18 | G44: =F44*21% -> 19766.288 | K44: 4706.26 | O44: =SUM(F44:N44) -> 118597.73 | P44: =VLOOKUP(D44,Configuracion!$A$4:$C$590,3,FALSE) -> PROVEEDOR
A45: 45574 | B45: 15 | C45: 3722 | D45: 30688140923 | E45: =VLOOKUP(D45,Configuracion!$A$4:$C$590,2,FALSE) -> COLTEX SRL | F45: 238328.4 | G45: =F45*21% -> 50048.964 | O45: =SUM(F45:N45) -> 288377.36 | P45: =VLOOKUP(D45,Configuracion!$A$4:$C$590,3,FALSE) -> PROVEEDOR
A46: 45580 | B46: 4 | C46: 140 | D46: 20317488476 | E46: =VLOOKUP(D46,Configuracion!$A$4:$C$590,2,FALSE) -> VILLALBA MIGUEL ANGEL | F46: 75000 | G46: =F46*21% -> 15750 | O46: =SUM(F46:N46) -> 90750 | P46: =VLOOKUP(D46,Configuracion!$A$4:$C$590,3,FALSE) -> PROVEEDOR
A47: 45576 | B47: 18 | C47: 2831 | D47: 27940269100 | E47: =VLOOKUP(D47,Configuracion!$A$4:$C$590,2,FALSE) -> LIN YUMEI | F47: 35123.97 | G47: =F47*21% -> 7376.0337 | O47: =SUM(F47:N47) -> 42500.004 | P47: =VLOOKUP(D47,Configuracion!$A$4:$C$590,3,FALSE) -> VARIOS
A48: 45567 | B48: 3051 | C48: 823860 | D48: 30678814357 | E48: =VLOOKUP(D48,Configuracion!$A$4:$C$590,2,FALSE) -> TELEFONICA MOVILES ARG SA | F48: 34996.67 | H48: =+F48*0.27 -> 9449.1009 | J48: 1049.9 | K48: 1839.88 | N48: 1800.97 | O48: =SUM(F48:N48) -> 49136.521 | P48: =VLOOKUP(D48,Configuracion!$A$4:$C$590,3,FALSE) -> SERVICIO
A49: 45574 | B49: 3101 | C49: 185334 | D49: 30678814357 | E49: =VLOOKUP(D49,Configuracion!$A$4:$C$590,2,FALSE) -> TELEFONICA MOVILES ARG SA | F49: 58358.69 | H49: =+F49*0.27 -> 15756.846 | J49: =+F49*0.03 -> 1750.7607 | K49: =+F49*0.05 -> 2917.9345 | O49: =SUM(F49:N49) -> 78784.232 | P49: =VLOOKUP(D49,Configuracion!$A$4:$C$590,3,FALSE) -> SERVICIO
A50: 45575 | B50: 32 | C50: 148954 | D50: 30708847247 | E50: =VLOOKUP(D50,Configuracion!$A$4:$C$590,2,FALSE) -> EXPRESO LANCIONI SA | F50: 48698.3 | G50: =F50*21% -> 10226.643 | K50: 2434.92 | O50: =SUM(F50:N50) -> 61359.863 | P50: =VLOOKUP(D50,Configuracion!$A$4:$C$590,3,FALSE) -> FLETE
A51: 45583 | B51: 13 | C51: 3141 | D51: 20119743959 | E51: =VLOOKUP(D51,Configuracion!$A$4:$C$590,2,FALSE) -> BENNUN FERNANDO RUBEN | F51: 360000 | G51: =F51*21% -> 75600 | O51: =SUM(F51:N51) -> 435600 | P51: =VLOOKUP(D51,Configuracion!$A$4:$C$590,3,FALSE) -> PROVEEDOR
A52: 45587 | B52: 3 | C52: 7855 | D52: 33708218699 | E52: =VLOOKUP(D52,Configuracion!$A$4:$C$590,2,FALSE) -> MANGGINI PABLO Y M ULISES SH | F52: 15000 | G52: =F52*21% -> 3150 | O52: =SUM(F52:N52) -> 18150 | P52: =VLOOKUP(D52,Configuracion!$A$4:$C$590,3,FALSE) -> VARIOS
A53: 45586 | B53: 17 | C53: 10702 | D53: 30661143610 | E53: =VLOOKUP(D53,Configuracion!$A$4:$C$590,2,FALSE) -> ORTOPEDIA BERNAT SRL | F53: 2797795 | G53: =F53*21% -> 587536.95 | K53: =+F53*0.05 -> 139889.75 | O53: =SUM(F53:N53) -> 3525221.7 | P53: =VLOOKUP(D53,Configuracion!$A$4:$C$590,3,FALSE) -> PROVEEDOR
A54: 45588 | B54: 2 | C54: 26 | D54: 27243660535 | E54: =VLOOKUP(D54,Configuracion!$A$4:$C$590,2,FALSE) -> BARD MARISA SILVIA | F54: 360000 | G54: =F54*21% -> 75600 | O54: =SUM(F54:N54) -> 435600 | P54: =VLOOKUP(D54,Configuracion!$A$4:$C$590,3,FALSE) -> GASTOS ADMIN
A55: 45587 | B55: 5 | C55: 3148753 | D55: 30702652975 | E55: =VLOOKUP(D55,Configuracion!$A$4:$C$590,2,FALSE) -> NSS SA - IPLAN | F55: 28528.6 | G55: =F55*21% -> 5991.006 | K55: =+F55*0.05 -> 1426.43 | O55: =SUM(F55:N55) -> 35946.036 | P55: =VLOOKUP(D55,Configuracion!$A$4:$C$590,3,FALSE) -> SERVICIO
A56: 45590 | B56: 2 | C56: 1915 | D56: 30714228060 | E56: =VLOOKUP(D56,Configuracion!$A$4:$C$590,2,FALSE) -> POTA AMOBAMIENTOS SRL | F56: 5240000 | G56: =F56*21% -> 1100400 | O56: =SUM(F56:N56) -> 6340400 | P56: =VLOOKUP(D56,Configuracion!$A$4:$C$590,3,FALSE) -> PROVEEDOR
A57: 45589 | B57: 21 | C57: 476 | D57: 20186310005 | E57: =VLOOKUP(D57,Configuracion!$A$4:$C$590,2,FALSE) -> SUCESION DE SALEME CARAM | F57: 5000 | G57: =F57*21% -> 1050 | O57: =SUM(F57:N57) -> 6050 | P57: =VLOOKUP(D57,Configuracion!$A$4:$C$590,3,FALSE) -> VARIOS
A58: 45589 | B58: 23 | C58: 6148 | D58: 30711776040 | E58: =VLOOKUP(D58,Configuracion!$A$4:$C$590,2,FALSE) -> EXPRESO BICENTENARIO SRL | F58: 12027 | G58: =F58*21% -> 2525.67 | O58: =SUM(F58:N58) -> 14552.67 | P58: =VLOOKUP(D58,Configuracion!$A$4:$C$590,3,FALSE) -> FLETE
A59: 45588 | B59: 2 | C59: 7704 | D59: 20253990903 | E59: =VLOOKUP(D59,Configuracion!$A$4:$C$590,2,FALSE) -> LOPEZ MATIAS | F59: 244415 | G59: =F59*21% -> 51327.15 | O59: =SUM(F59:N59) -> 295742.15 | P59: =VLOOKUP(D59,Configuracion!$A$4:$C$590,3,FALSE) -> PROVEEDOR
A60: 45596 | B60: 4 | C60: 141 | D60: 20317488476 | E60: =VLOOKUP(D60,Configuracion!$A$4:$C$590,2,FALSE) -> VILLALBA MIGUEL ANGEL | F60: 300000 | G60: =F60*21% -> 63000 | O60: =SUM(F60:N60) -> 363000 | P60: =VLOOKUP(D60,Configuracion!$A$4:$C$590,3,FALSE) -> PROVEEDOR
A61: 45589 | B61: 3 | C61: 4307 | D61: 20184052858 | E61: =VLOOKUP(D61,Configuracion!$A$4:$C$590,2,FALSE) -> ABOUD PABLO DANIEL | F61: 16859.52 | G61: =F61*21% -> 3540.4992 | O61: =SUM(F61:N61) -> 20400.019 | P61: =VLOOKUP(D61,Configuracion!$A$4:$C$590,3,FALSE) -> VARIOS
A62: 45594 | B62: 5 | C62: 2002 | D62: 30712187316 | E62: =VLOOKUP(D62,Configuracion!$A$4:$C$590,2,FALSE) -> ITALOMED PRODUCTOS SRL | F62: 289656.77 | G62: =F62*21% -> 60827.922 | O62: =SUM(F62:N62) -> 350484.69 | P62: =VLOOKUP(D62,Configuracion!$A$4:$C$590,3,FALSE) -> PROVEEDOR
A63: 45596 | B63: 2 | C63: 886 | D63: 20272865869 | E63: =VLOOKUP(D63,Configuracion!$A$4:$C$590,2,FALSE) -> DI FEO MARTIN EZEQUIEL | F63: 94400 | G63: =F63*21% -> 19824 | O63: =SUM(F63:N63) -> 114224 | P63: =VLOOKUP(D63,Configuracion!$A$4:$C$590,3,FALSE) -> PROVEEDOR
A64: 45596 | B64: 6 | C64: 54831 | D64: 30710177658 | E64: =VLOOKUP(D64,Configuracion!$A$4:$C$590,2,FALSE) -> TARGET MEDICAL SA | F64: 425830 | G64: =F64*21% -> 89424.3 | O64: =SUM(F64:N64) -> 515254.3 | P64: =VLOOKUP(D64,Configuracion!$A$4:$C$590,3,FALSE) -> PROVEEDOR
A65: 45567 | B65: 2 | C65: 218 | D65: 30605344352 | E65: =VLOOKUP(D65,Configuracion!$A$4:$C$590,2,FALSE) -> CONSORCIO BARTOLME MITRE 2466 | F65: 834000 | G65: =F65*21% -> 175140 | O65: =SUM(F65:N65) -> 1009140 | P65: =VLOOKUP(D65,Configuracion!$A$4:$C$590,3,FALSE) -> CONSORCIO
A66: 45595 | B66: 7 | C66: 19390 | D66: 30709214078 | E66: =VLOOKUP(D66,Configuracion!$A$4:$C$590,2,FALSE) -> REHAVITA SA | F66: 450340 | I66: =+F66*0.105 -> 47285.7 | O66: =SUM(F66:N66) -> 497625.7 | P66: =VLOOKUP(D66,Configuracion!$A$4:$C$590,3,FALSE) -> PROVEEDOR
A67: 45595 | B67: 4 | C67: 38700 | D67: 20289111329 | E67: =VLOOKUP(D67,Configuracion!$A$4:$C$590,2,FALSE) -> R. N. LEDESMA | F67: 973752.97 | G67: =F67*21% -> 204488.12 | O67: =SUM(F67:N67) -> 1178241.1 | P67: =VLOOKUP(D67,Configuracion!$A$4:$C$590,3,FALSE) -> PROVEEDOR
A68: 45595 | B68: 5 | C68: 33 | D68: 20929183143 | E68: =VLOOKUP(D68,Configuracion!$A$4:$C$590,2,FALSE) -> MA JUN | F68: 50000 | G68: =F68*21% -> 10500 | O68: =SUM(F68:N68) -> 60500 | P68: =VLOOKUP(D68,Configuracion!$A$4:$C$590,3,FALSE) -> VARIOS
A69: 45581 | B69: 50 | C69: 3831803 | D69: 30714112836 | E69: =VLOOKUP(D69,Configuracion!$A$4:$C$590,2,FALSE) -> AUTOPISTAS DE BUENOS AIRES (AUBASA) SA | F69: 2892.56 | G69: =F69*21% -> 607.4376 | J69: 86.78 | O69: =SUM(F69:N69) -> 3586.7776 | P69: =VLOOKUP(D69,Configuracion!$A$4:$C$590,3,FALSE) -> GASTOS MOVILIDAD
A70: 45583 | B70: 711 | C70: 6273743 | D70: 30677237119 | E70: =VLOOKUP(D70,Configuracion!$A$4:$C$590,2,FALSE) -> AUTOPISTAS DEL SOL SA | F70: 5459.6 | G70: =F70*21% -> 1146.516 | J70: 163.79 | K70: 272.98 | O70: =SUM(F70:N70) -> 7042.886 | P70: =VLOOKUP(D70,Configuracion!$A$4:$C$590,3,FALSE) -> PEAJE
A71: 45567 | B71: 711 | C71: 6215204 | D71: 30677237119 | E71: =VLOOKUP(D71,Configuracion!$A$4:$C$590,2,FALSE) -> AUTOPISTAS DEL SOL SA | F71: 8703.04 | G71: =F71*21% -> 1827.6384 | J71: 261.09 | K71: 435.15 | O71: =SUM(F71:N71) -> 11226.918 | P71: =VLOOKUP(D71,Configuracion!$A$4:$C$590,3,FALSE) -> PEAJE
A72: 45567 | B72: 629 | C72: 5489145 | D72: 30663498513 | E72: =VLOOKUP(D72,Configuracion!$A$4:$C$590,2,FALSE) -> GRUPO CONC.DEL OESTE SA | F72: 3744.33 | G72: =F72*21% -> 786.3093 | K72: 187.22 | O72: =SUM(F72:N72) -> 4717.8593 | P72: =VLOOKUP(D72,Configuracion!$A$4:$C$590,3,FALSE) -> PEAJE
A73: 45583 | B73: 629 | C73: 5529485 | D73: 30663498513 | E73: =VLOOKUP(D73,Configuracion!$A$4:$C$590,2,FALSE) -> GRUPO CONC.DEL OESTE SA | F73: 2080.48 | G73: =F73*21% -> 436.9008 | K73: 104.02 | O73: =SUM(F73:N73) -> 2621.4008 | P73: =VLOOKUP(D73,Configuracion!$A$4:$C$590,3,FALSE) -> PEAJE
A74: 45573 | B74: 700 | C74: 1972986 | D74: 30715804812 | E74: =VLOOKUP(D74,Configuracion!$A$4:$C$590,2,FALSE) -> CORREDORES VIALES SA | F74: 13297.33 | G74: =F74*21% -> 2792.4393 | K74: 664.87 | O74: =SUM(F74:N74) -> 16754.639 | P74: =VLOOKUP(D74,Configuracion!$A$4:$C$590,3,FALSE) -> GASTOS MOVILIDAD
A75: 45588 | B75: 700 | C75: 2005182 | D75: 30715804812 | E75: =VLOOKUP(D75,Configuracion!$A$4:$C$590,2,FALSE) -> CORREDORES VIALES SA | F75: 8845.22 | G75: =F75*21% -> 1857.4962 | K75: 442.26 | O75: =SUM(F75:N75) -> 11144.976 | P75: =VLOOKUP(D75,Configuracion!$A$4:$C$590,3,FALSE) -> GASTOS MOVILIDAD
A76: 45588 | B76: 5015 | C76: 658066 | D76: 30574876474 | E76: =VLOOKUP(D76,Configuracion!$A$4:$C$590,2,FALSE) -> AUTOPISTAS URBANAS SA | F76: 19646.52 | G76: =F76*21% -> 4125.7692 | N76: =589.4+1964.67 -> 2554.07 | O76: =SUM(F76:N76) -> 26326.359 | P76: =VLOOKUP(D76,Configuracion!$A$4:$C$590,3,FALSE) -> PEAJE
A77: 45580 | B77: 5015 | C77: 654620 | D77: 30574876474 | E77: =VLOOKUP(D77,Configuracion!$A$4:$C$590,2,FALSE) -> AUTOPISTAS URBANAS SA | F77: 13226.3 | G77: =F77*21% -> 2777.523 | N77: =1322.63+396.79 -> 1719.42 | O77: =SUM(F77:N77) -> 17723.243 | P77: =VLOOKUP(D77,Configuracion!$A$4:$C$590,3,FALSE) -> PEAJE
A78: 45573 | B78: 5015 | C78: 653151 | D78: 30574876474 | E78: =VLOOKUP(D78,Configuracion!$A$4:$C$590,2,FALSE) -> AUTOPISTAS URBANAS SA | F78: 17804.16 | G78: =F78*21% -> 3738.8736 | N78: =534.12+1780.42 -> 2314.54 | O78: =SUM(F78:N78) -> 23857.574 | P78: =VLOOKUP(D78,Configuracion!$A$4:$C$590,3,FALSE) -> PEAJE
A79: 45594 | B79: 11 | C79: 10960 | D79: 20211408511 | E79: =VLOOKUP(D79,Configuracion!$A$4:$C$590,2,FALSE) -> GABRIEL ALEJANDRO SEGAL | F79: 325616.76 | I79: =+F79*0.105 -> 34189.76 | K79: 16280.84 | O79: =SUM(F79:N79) -> 376087.36 | P79: =VLOOKUP(D79,Configuracion!$A$4:$C$590,3,FALSE) -> VARIOS
A80: 45590 | B80: 4 | C80: 1202 | D80: 20202500138 | E80: =VLOOKUP(D80,Configuracion!$A$4:$C$590,2,FALSE) -> RAMBAUD DIEGO GABRIEL | F80: 12669.68 | I80: =+F80*0.105 -> 1330.3164 | O80: =SUM(F80:N80) -> 13999.996 | P80: =VLOOKUP(D80,Configuracion!$A$4:$C$590,3,FALSE) -> GASTOS VARIOS
A81: 45587 | B81: 30 | C81: 95031 | D81: 30690212265 | E81: =VLOOKUP(D81,Configuracion!$A$4:$C$590,2,FALSE) -> GIAMPAOLETTI SA | F81: 56248.45 | G81: =F81*21% -> 11812.174 | O81: =SUM(F81:N81) -> 68060.624 | P81: =VLOOKUP(D81,Configuracion!$A$4:$C$590,3,FALSE) -> FLETE
A82: 45584 | B82: 3 | C82: 103 | D82: 20278292429 | E82: =VLOOKUP(D82,Configuracion!$A$4:$C$590,2,FALSE) -> FREDES LUCAS FEDERICO | F82: 18345.49 | G82: =F82*21% -> 3852.5529 | O82: =SUM(F82:N82) -> 22198.043 | P82: =VLOOKUP(D82,Configuracion!$A$4:$C$590,3,FALSE) -> VARIOS
A83: 45566 | B83: 59 | C83: 16596 | D83: 30541849307 | E83: =VLOOKUP(D83,Configuracion!$A$4:$C$590,2,FALSE) -> DIETRICH SA | F83: 330264.46 | G83: =F83*21% -> 69355.537 | K83: 16513.22 | O83: =SUM(F83:N83) -> 416133.22 | P83: =VLOOKUP(D83,Configuracion!$A$4:$C$590,3,FALSE) -> VARIOS
A84: 45567 | B84: 32 | C84: 13658 | D84: 30707304886 | E84: =VLOOKUP(D84,Configuracion!$A$4:$C$590,2,FALSE) -> ARMORAUT SA | F84: 276401.65 | G84: =F84*21% -> 58044.346 | K84: 13820.08 | O84: =SUM(F84:N84) -> 348266.08 | P84: =VLOOKUP(D84,Configuracion!$A$4:$C$590,3,FALSE) -> GASTOS MOVILIDAD
A85: 45574 | B85: 7 | C85: 3332 | D85: 20284183534 | E85: =VLOOKUP(D85,Configuracion!$A$4:$C$590,2,FALSE) -> FURLANETTO MARTIN | F85: 5454.6 | G85: =F85*21% -> 1145.466 | O85: =SUM(F85:N85) -> 6600.066 | P85: =VLOOKUP(D85,Configuracion!$A$4:$C$590,3,FALSE) -> VARIOS
A86: 45591 | B86: 2189 | C86: 78820 | D86: 30548083156 | E86: =VLOOKUP(D86,Configuracion!$A$4:$C$590,2,FALSE) -> COTO CICSA | F86: 5875.26 | G86: =F86*21% -> 1233.8046 | J86: =+F86*0.03 -> 176.2578 | K86: =+F86*0.05 -> 293.763 | O86: =SUM(F86:N86) -> 7579.0854 | P86: =VLOOKUP(D86,Configuracion!$A$4:$C$590,3,FALSE) -> GASTOS VARIOS
A87: 45580 | B87: 1 | C87: 2238 | D87: 33716307749 | E87: =VLOOKUP(D87,Configuracion!$A$4:$C$590,2,FALSE) -> VERISURE ARG MONITOREO A SA | F87: -5399.88 | G87: =F87*21% -> -1133.9748 | O87: =SUM(F87:N87) -> -6533.8548 | P87: =VLOOKUP(D87,Configuracion!$A$4:$C$590,3,FALSE) -> PROVEEDOR
A88: 45583 | B88: 4264 | C88: 4521694 | D88: 30639453738 | E88: =VLOOKUP(D88,Configuracion!$A$4:$C$590,2,FALSE) -> TELECOM ARGENTINA SA | F88: =5950.41+19155.99 -> 25106.4 | G88: =F88*21% -> 5272.344 | J88: =+F88*0.03 -> 753.192 | K88: =+F88*0.05 -> 1255.32 | O88: =SUM(F88:N88) -> 32387.256 | P88: =VLOOKUP(D88,Configuracion!$A$4:$C$590,3,FALSE) -> SERVICIO
A89: 45594 | B89: 12 | C89: 3229486 | D89: 30703088534 | E89: =VLOOKUP(D89,Configuracion!$A$4:$C$590,2,FALSE) -> MERCADOLIBRE SRL | F89: 52814.1 | G89: =F89*21% -> 11090.961 | J89: =+F89*0.03 -> 1584.423 | K89: =+F89*0.05 -> 2640.705 | O89: =SUM(F89:N89) -> 68130.189 | P89: =VLOOKUP(D89,Configuracion!$A$4:$C$590,3,FALSE) -> PROVEEDOR
E90: =VLOOKUP(D90,Configuracion!$A$4:$C$590,2,FALSE) -> #N/A | G90: =F90*21% -> 0 | O90: =SUM(F90:N90) -> 0 | P90: =VLOOKUP(D90,Configuracion!$A$4:$C$590,3,FALSE) -> #N/A
E91: =VLOOKUP(D91,Configuracion!$A$4:$C$590,2,FALSE) -> #N/A | G91: =F91*21% -> 0 | O91: =SUM(F91:N91) -> 0 | P91: =VLOOKUP(D91,Configuracion!$A$4:$C$590,3,FALSE) -> #N/A
E92: =VLOOKUP(D92,Configuracion!$A$4:$C$590,2,FALSE) -> #N/A | G92: =F92*21% -> 0 | O92: =SUM(F92:N92) -> 0 | P92: =VLOOKUP(D92,Configuracion!$A$4:$C$590,3,FALSE) -> #N/A
E93: =VLOOKUP(D93,Configuracion!$A$4:$C$590,2,FALSE) -> #N/A | G93: =F93*21% -> 0 | O93: =SUM(F93:N93) -> 0 | P93: =VLOOKUP(D93,Configuracion!$A$4:$C$590,3,FALSE) -> #N/A
E94: =VLOOKUP(D94,Configuracion!$A$4:$C$590,2,FALSE) -> #N/A | G94: =F94*21% -> 0 | O94: =SUM(F94:N94) -> 0 | P94: =VLOOKUP(D94,Configuracion!$A$4:$C$590,3,FALSE) -> #N/A
E95: =VLOOKUP(D95,Configuracion!$A$4:$C$590,2,FALSE) -> #N/A | G95: =F95*21% -> 0 | O95: =SUM(F95:N95) -> 0 | P95: =VLOOKUP(D95,Configuracion!$A$4:$C$590,3,FALSE) -> #N/A
E96: =VLOOKUP(D96,Configuracion!$A$4:$C$590,2,FALSE) -> #N/A | G96: =F96*21% -> 0 | O96: =SUM(F96:N96) -> 0 | P96: =VLOOKUP(D96,Configuracion!$A$4:$C$590,3,FALSE) -> #N/A
E97: =VLOOKUP(D97,Configuracion!$A$4:$C$590,2,FALSE) -> #N/A | G97: =F97*21% -> 0 | O97: =SUM(F97:N97) -> 0 | P97: =VLOOKUP(D97,Configuracion!$A$4:$C$590,3,FALSE) -> #N/A
E98: =VLOOKUP(D98,Configuracion!$A$4:$C$590,2,FALSE) -> #N/A | G98: =F98*21% -> 0 | O98: =SUM(F98:N98) -> 0 | P98: =VLOOKUP(D98,Configuracion!$A$4:$C$590,3,FALSE) -> #N/A
E99: =VLOOKUP(D99,Configuracion!$A$4:$C$590,2,FALSE) -> #N/A | G99: =F99*21% -> 0 | O99: =SUM(F99:N99) -> 0 | P99: =VLOOKUP(D99,Configuracion!$A$4:$C$590,3,FALSE) -> #N/A
E100: =VLOOKUP(D100,Configuracion!$A$4:$C$590,2,FALSE) -> #N/A | G100: =F100*21% -> 0 | O100: =SUM(F100:N100) -> 0 | P100: =VLOOKUP(D100,Configuracion!$A$4:$C$590,3,FALSE) -> #N/A
E101: =VLOOKUP(D101,Configuracion!$A$4:$C$590,2,FALSE) -> #N/A | G101: =F101*21% -> 0 | O101: =SUM(F101:N101) -> 0 | P101: =VLOOKUP(D101,Configuracion!$A$4:$C$590,3,FALSE) -> #N/A
... E114: =VLOOKUP(D114,Configuracion!$A$4:$C$590,2,FALSE) -> #N/A | G114: =F114*21% -> 0 | O114: =SUM(F114:N114) -> 0 | P114: =VLOOKUP(D114,Configuracion!$A$4:$C$590,3,FALSE) -> #N/A
A115: TOTAL | F115: =SUM(F8:F114) -> 29685781 | G115: =SUM(G8:G114) -> 5715540.4 | H115: =SUM(H8:H114) -> 25205.947 | I115: =SUM(I8:I114) -> 249434.48 | J115: =SUM(J8:J114) -> 7378.0235 | K115: =SUM(K8:K114) -> 514607.09 | L115: =SUM(L8:L114) -> 0 | M115: =SUM(M8:M114) -> 5529.01 | ... O115: =SUM(O8:O114) -> 36250262
...

Sheet Calculo IVA
B1: ORTOPEDIA GEMINIS
A2: Calculo Iva | D2: 45566
B4: VENTAS
B5: Neto | C5: Iva | D5: Total
A6: FAC. "A" | B6: =+'Oct 24'!F200 -> 0 | C6: =(B6*0.21) -> 0 | D6: =(B6+C6) -> 0
A7: FAC. "B" | B7: =+'Oct 24'!F210 -> 0 | C7: =(B7*0.21) -> 0 | D7: =(B7+C7) -> 0
A8: FAC. "A" - | B8: =+'Resumen Ventas 10'!B3+'Resumen Ventas 10'!B5+'Resumen Ventas 10'!B6+'Resumen Ventas 10'!B4 -> 33476168 | C8: =+B8*0.21 -> 7029995.2 | D8: =(B8+C8) -> 40506163
A9: FAC. "B" | B9: =+'Resumen Ventas 10'!B7+'Resumen Ventas 10'!B8 -> 24030351 | C9: =+'Resumen Ventas 10'!C7+'Resumen Ventas 10'!C8 -> 5046373.7 | D9: =(B9+C9) -> 29076724
B10: =SUM(B6:B9) -> 57506519 | C10: =SUM(C6:C9) -> 12076369 | D10: =SUM(D6:D9) -> 69582887
B13: COMPRAS
B14: Neto | C14: Iva | D14: Total
B15: =+'Oct 24'!F115 -> 29685781 | C15: =+('Oct 24'!G115+'Oct 24'!H115+'Oct 24'!I115) -> 5990180.8 | D15: =+'Oct 24'!O115 -> 36250262
A16: Compras s/ODOO
A17: Comprobantes AFIP - Saldo | B17: 433365.78 | C17: 91006.8 | D17: 2741329.5
A18: IVA S/ EXTRACTOS BANCARIOS | C18: =+'Compras 10'!D57 -> 12622.1
B19: =SUM(B15:B18) -> 30119147 | C19: =SUM(C15:C18) -> 6093809.7 | D19: =SUM(D15:D18) -> 38991591
A22: RETENCIONES | B22: N° Cuit | C22: Importe | D22: Nro. Retencion | E22: Fecha
A23: AFIP - No están informadas las retenciones de IVA en el sistema de AFIP
C38: =+'Oct 24'!G183 -> 1213578.6
A40: PERCEPCIONES | B40: N° Cuit | C40: Importe | D40: Nro. Retencion | E40: Fecha
C44: =SUM(C41:C43) -> 0
A46: Total Deducciociones | C46: =+C44+C38 -> 1213578.6
C49: (Montos en Positivo)
A50: 1er Saldo Tecnico del Período | C50: =+C10-C19 -> 5982559.2
A52: Saldo Tecnico de período Anterior (a favor) | D52: (resta en el total)
A54: Saldo Neto Técnico | C54: =+C50-C52 -> 5982559.2
A58: Saldo L.D. del Período | C58: =+C44+C38 -> 1213578.6
A60: Saldo L.D. del Período Anterior
A62: Neto S.L.D | C62: =+C58+C60 -> 1213578.6
A65: I V A | C65: =+C54-C62 -> 4768980.6
A66: NOTA: Sin Tomar posibles Retenciones que se hayan hecho

Sheet Compras 10
A2: Ortopedia Geminis S.A.
A4: Fecha | B4: Comprobante | C4: Nombre | D4: Cond. IVA | E4: CUIT o Doc. | F4: Gravado | G4: No Gravado | H4: IVA 2,5% | I4: IVA 5% | J4: IVA 10.5% | K4: IVA 21% | L4: IVA 27% | M4: Otros Imp | N4: Total Compr.
F6: =SUM(F5:F5) -> 0 | G6: =SUM(G5:G5) -> 0 | H6: =SUM(H5:H5) -> 0 | I6: =SUM(I5:I5) -> 0 | J6: =SUM(J5:J5) -> 0 | K6: =SUM(K5:K5) -> 0 | L6: =SUM(L5:L5) -> 0 | M6: =SUM(M5:M5) -> 0 | N6: =SUM(N5:N5) -> 0
H7: =+SUM(H6:L6) -> 0
B10: Comprobantes AFIP no recepcionados
A13: Fecha | B13: Tipo | C13: Punto de Venta | D13: Número Desde | E13: Número Hasta | F13: Cód. Autorización | G13: Tipo Doc. Emisor | H13: Nro. Doc. Emisor | I13: Denominación Emisor | J13: Tipo Cambio | K13: Moneda | L13: Imp. Neto Gravado | M13: Imp. Neto No Gravado | N13: Imp. Op. Exentas | O13: Otros Tributos | P13: IVA | Q13: Imp. Total
A14: 28/10/2024 | B14: 6 - Factura B | C14: 469 | D14: 272223 | F14: 74440058567706 | G14: CUIT | H14: 30696170580 | I14: AEROPUERTOS ARGENTINA 2000 S A | J14: 1 | K14: $ | L14: 0 | M14: 0 | N14: 0 | O14: 0 | P14: 0 | Q14: -5206.61
A15: 31/10/2024 | B15: 1 - Factura A | C15: 5009 | D15: 1056394 | F15: 74444676246493 | G15: CUIT | H15: 30574876474 | I15: AUTOPISTAS URBANAS S A | J15: 1 | K15: $ | L15: 5655.83 | M15: 0 | N15: 0 | O15: 0 | P15: 1187.72 | Q15: 7578.8
A16: 31/10/2024 | B16: 1 - Factura A | C16: 5015 | D16: 660519 | F16: 74444670715235 | G16: CUIT | H16: 30574876474 | I16: AUTOPISTAS URBANAS S A | J16: 1 | K16: $ | L16: 18764.68 | M16: 0 | N16: 0 | O16: 0 | P16: 3940.57 | Q16: 25144.66
A17: 29/10/2024 | B17: 1 - Factura A | C17: 101 | D17: 8782 | F17: 74449116152602 | G17: CUIT | H17: 33711430879 | I17: BALANZE S.A. | J17: 1 | K17: $ | L17: 125800 | M17: 0 | N17: 0 | O17: 0 | P17: 26418 | Q17: 152218
A18: 15/10/2024 | B18: 1 - Factura A | C18: 113 | D18: 3855807 | F18: 74420895911146 | G18: CUIT | H18: 30577207190 | I18: COORDINACION ECOLOGICA AREA METROPOLITANA SOCIEDAD DEL ESTADO | J18: 1 | K18: $ | L18: 991.73 | M18: 0 | N18: 0 | O18: 0 | P18: 208.27 | Q18: 1200
A19: 31/10/2024 | B19: 1 - Factura A | C19: 113 | D19: 3883633 | F19: 74440822775090 | G19: CUIT | H19: 30577207190 | I19: COORDINACION ECOLOGICA AREA METROPOLITANA SOCIEDAD DEL ESTADO | J19: 1 | K19: $ | L19: 2975.21 | M19: 0 | N19: 0 | O19: 0 | P19: 624.79 | Q19: 3689.26
A20: 15/10/2024 | B20: 1 - Factura A | C20: 104 | D20: 6923432 | F20: 74422530905691 | G20: CUIT | H20: 30715804812 | I20: CORREDORES VIALES SOCIEDAD ANONIMA | J20: 1 | K20: $ | L20: 910.78 | M20: 0 | N20: 0 | O20: 0 | P20: 191.26 | Q20: 1147.58
A21: 11/10/2024 | B21: 1 - Factura A | C21: 3 | D21: 4181 | F21: 74414181067117 | G21: CUIT | H21: 30501077824 | I21: DADAGLIO HNOS S A I C F I A | J21: 1 | K21: $ | L21: 104462.81 | M21: 0 | N21: 0 | O21: 0 | P21: 21937.19 | Q21: 126400.01
A22: 18/10/2024 | B22: 1 - Factura A | C22: 102 | D22: 49564 | F22: 74425010766802 | G22: CUIT | H22: 30701307115 | I22: DESPEGAR COM AR SA | J22: 1 | K22: $ | L22: 4218.89 | M22: 0 | N22: 0 | O22: 0 | P22: 885.97 | Q22: 5315.8
A23: 18/10/2024 | B23: 11 - Factura C | C23: 1 | D23: 15 | G23: CUIT | H23: 27443612705 | I23: MIGOYA MORIONDO MARIA INES | J23: 1 | K23: $ | O23: 0 | Q23: 800000
A24: 02/10/2024 | B24: 11 - Factura C | C24: 1 | D24: 8 | G24: CUIT | H24: 27443612713 | I24: MIGOYA MORIONDO SOFIA | J24: 1 | K24: $ | O24: 0 | Q24: 750000
A25: 24/10/2024 | B25: 1 - Factura A | C25: 2 | D25: 10822 | F25: 74432609825455 | G25: CUIT | H25: 30714331082 | I25: ORTOPEDIA CASA ESCALADA S.R.L. | J25: 1 | K25: $ | L25: 13081.82 | M25: 0 | N25: 0 | O25: 0 | P25: 2747.18 | Q25: 15829
A26: 31/10/2024 | B26: 1 - Factura A | C26: 6 | D26: 17717989 | F26: 74447345508330 | G26: CUIT | H26: 30620177497 | I26: POSNET SOCIEDAD DE RESPONSABILIDAD LIMITADA | J26: 1 | K26: $ | L26: 0 | M26: 0 | N26: 0 | O26: 0 | P26: 0 | Q26: 0
A27: 31/10/2024 | B27: 1 - Factura A | C27: 6 | D27: 17862335 | F27: 74447384891474 | G27: CUIT | H27: 30620177497 | I27: POSNET SOCIEDAD DE RESPONSABILIDAD LIMITADA | J27: 1 | K27: $ | L27: 27263.03 | M27: 0 | N27: 0 | O27: 0 | P27: 5725.24 | Q27: 35169.31
A28: 21/10/2024 | B28: 1 - Factura A | C28: 8 | D28: 100796 | F28: 74434281839124 | G28: CUIT | H28: 30709776564 | I28: PROSEGUR ACTIVA ARGENTINA SA | J28: 1 | K28: $ | L28: 129241 | M28: 0 | N28: 0 | O28: 0 | P28: 27140.61 | Q28: 162843.68
A29: 18/10/2024 | B29: 11 - Factura C | C29: 1 | D29: 254 | G29: CUIT | H29: 27217606255 | I29: SAPUNA MIRIAN KARINA | J29: 1 | K29: $ | O29: 0 | Q29: 163808.35
A30: 19/10/2024 | B30: 11 - Factura C | C30: 1 | D30: 255 | G30: CUIT | H30: 27217606255 | I30: SAPUNA MIRIAN KARINA | J30: 1 | K30: $ | O30: 0 | Q30: 105993.64
A31: 21/10/2024 | B31: 11 - Factura C | C31: 1 | D31: 256 | G31: CUIT | H31: 27217606255 | I31: SAPUNA MIRIAN KARINA | J31: 1 | K31: $ | O31: 0 | Q31: 115629.42
A32: 21/10/2024 | B32: 11 - Factura C | C32: 1 | D32: 257 | G32: CUIT | H32: 27217606255 | I32: SAPUNA MIRIAN KARINA | J32: 1 | K32: $ | O32: 0 | Q32: 96357.85
A33: 28/10/2024 | B33: 11 - Factura C | C33: 1 | D33: 258 | G33: CUIT | H33: 27217606255 | I33: SAPUNA MIRIAN KARINA | J33: 1 | K33: $ | O33: 0 | Q33: 62373.76
A34: 28/10/2024 | B34: 11 - Factura C | C34: 1 | D34: 259 | G34: CUIT | H34: 27217606255 | I34: SAPUNA MIRIAN KARINA | J34: 1 | K34: $ | O34: 0 | Q34: 55245.33
A35: 28/10/2024 | B35: 11 - Factura C | C35: 1 | D35: 260 | G35: CUIT | H35: 27217606255 | I35: SAPUNA MIRIAN KARINA | J35: 1 | K35: $ | O35: 0 | Q35: 60591.65
L40: =SUM(L14:L39) -> 433365.78 | M40: =SUM(M14:M39) -> 0 | N40: =SUM(N14:N39) -> 0 | O40: =SUM(O14:O39) -> 0 | P40: =SUM(P14:P39) -> 91006.8 | Q40: =SUM(Q14:Q39) -> 2741329.5
A44: IVA Extractos Bancarios
B47: Banco Credicoop
B48: IVA-ALIC ADIC RG 2408 S/COMIS-REC GASTOS | D48: 600
B49: IVA - ALICUOTA INSCRIPTO | D49: 4937.1
B52: Banco Patagonia
B53: IVA Alicuota General | D53: 6245
B54: IVA Percepcion | D54: 840
C57: TOTAL IVA S/ EXTRACTOS | D57: =+SUM(D48,D49,D53,D54) -> 12622.1

Sheet afip
A1: Fecha | B1: Tipo | C1: Punto de Venta | D1: Número Desde | E1: Número Hasta | F1: Cód. Autorización | G1: Tipo Doc. Emisor | H1: Nro. Doc. Emisor | I1: Denominación Emisor | J1: Tipo Cambio | K1: Moneda | L1: Imp. Neto Gravado | M1: Imp. Neto No Gravado | N1: Imp. Op. Exentas | O1: Otros Tributos | P1: IVA | Q1: Imp. Total
A2: 01/09/2024 | B2: 1 - Factura A | C2: 2189 | D2: 75919 | F2: 74356447170423 | G2: CUIT | H2: 30548083156 | I2: COTO CENTRO INTEGRAL DE COMERCIALIZACION SOCIEDAD ANONIMA | J2: 1 | K2: $ | L2: 6462.61 | M2: 0 | N2: 0 | O2: 452.38 | P2: 1357.15 | Q2: 8272.14
A3: 02/09/2024 | B3: 1 - Factura A | C3: 500 | D3: 1611886 | F3: 74357098226128 | G3: CUIT | H3: 30654118767 | I3: SOLUCIONES MULTIMEDIA S A | J3: 1 | K3: $ | L3: 89554.36 | M3: 0 | N3: 0 | O3: 0 | P3: 18806.42 | Q3: 112850.92
A4: 02/09/2024 | B4: 1 - Factura A | C4: 1 | D4: 4517 | F4: 74361573927319 | G4: CUIT | H4: 30715141201 | I4: REHAB S.R.L. | J4: 1 | K4: $ | L4: 1216380 | M4: 0 | N4: 0 | O4: 0 | P4: 255439.8 | Q4: 1471819.8
A5: 02/09/2024 | B5: 1 - Factura A | C5: 5 | D5: 158399 | F5: 74363528156508 | G5: CUIT | H5: 30598960093 | I5: SILVESTRIN FABRIS SOC RESP LTDA | J5: 1 | K5: $ | L5: 2376294.2 | M5: 0 | N5: 0 | O5: 0 | P5: 337808.56 | Q5: 2832917.5
A6: 02/09/2024 | B6: 1 - Factura A | C6: 17 | D6: 2245 | F6: 74361547632750 | G6: CUIT | H6: 30711764921 | I6: RELIEF CENTER S.R.L. | J6: 1 | K6: $ | L6: 93973 | M6: 0 | N6: 0 | O6: 0 | P6: 19734.33 | Q6: 113707.33
A7: 02/09/2024 | B7: 1 - Factura A | C7: 3051 | D7: 801967 | F7: 74367703518446 | G7: CUIT | H7: 30678814357 | I7: TELEFONICA MOVILES ARGENTINA SOCIEDAD ANONIMA | J7: 1 | K7: $ | L7: 14407 | M7: 0 | N7: 0 | O7: 0 | P7: 3889.89 | Q7: 20245.61
A8: 02/09/2024 | B8: 1 - Factura A | C8: 2 | D8: 248 | F8: 74363494027429 | G8: CUIT | H8: 27144282383 | I8: SCHEJTER LILA ELISA | J8: 1 | K8: $ | L8: 160000 | M8: 0 | N8: 0 | O8: 0 | P8: 33600 | Q8: 193600
A9: 02/09/2024 | B9: 1 - Factura A | C9: 5 | D9: 102 | F9: 74367559790009 | G9: CUIT | H9: 27329449357 | I9: ANDREANI AGUSTINA SUSANA | J9: 1 | K9: $ | L9: 64100 | M9: 16400 | N9: 0 | O9: 0 | P9: 13461 | Q9: 93961
A10: 02/09/2024 | B10: 11 - Factura C | C10: 3 | D10: 874 | F10: 74363563144286 | G10: CUIT | H10: 20086277523 | I10: BOTINDARI JUAN CARLOS | J10: 1 | K10: $ | O10: 0 | Q10: 275500
A11: 02/09/2024 | B11: 11 - Factura C | C11: 2 | D11: 302 | F11: 74368278674869 | G11: CUIT | H11: 27265832178 | I11: BLASCO MARIA GUADALUPE | J11: 1 | K11: $ | O11: 0 | Q11: 250000
A12: 03/09/2024 | B12: 1 - Factura A | C12: 629 | D12: 5407463 | F12: 34353802937243 | G12: CUIT | H12: 30663498513 | I12: GRUPO CONCESIONARIO DEL OESTE SA | J12: 1 | K12: $ | L12: 2121.64 | M12: 0 | N12: 0 | O12: 0 | P12: 445.54 | Q12: 2673.26
A13: 03/09/2024 | B13: 1 - Factura A | C13: 711 | D13: 6097149 | F13: 34359489663246 | G13: CUIT | H13: 30677237119 | I13: AUTOPISTAS DEL SOL S A | J13: 1 | K13: $ | L13: 7715.05 | M13: 0 | N13: 231.45 | O13: 0 | P13: 1620.16 | Q13: 9952.41
A14: 03/09/2024 | B14: 1 - Factura A | C14: 2635 | D14: 1369 | F14: 34359844249451 | G14: CUIT | H14: 33699685459 | I14: CORREO ANDREANI SA | J14: 1 | K14: $ | L14: 12449.6 | M14: 0 | N14: 0 | O14: 0 | P14: 2614.42 | Q14: 15064.02
A15: 03/09/2024 | B15: 1 - Factura A | C15: 2 | D15: 216 | F15: 74362687536018 | G15: CUIT | H15: 30605344352 | I15: CONSORCIO BARTOLOME MITRE 2466 | J15: 1 | K15: $ | L15: 834000 | M15: 0 | N15: 0 | O15: 0 | P15: 175140 | Q15: 1009140
A16: 04/09/2024 | B16: 1 - Factura A | C16: 17 | D16: 2255 | F16: 74361803741207 | G16: CUIT | H16: 30711764921 | I16: RELIEF CENTER S.R.L. | J16: 1 | K16: $ | L16: 527580 | M16: 0 | N16: 0 | O16: 0 | P16: 110791.8 | Q16: 638371.8
A17: 04/09/2024 | B17: 1 - Factura A | C17: 2 | D17: 50685 | F17: 74365825946417 | G17: CUIT | H17: 30595553535 | I17: RUBRICOM SOCIEDAD ANONIMA | J17: 1 | K17: $ | L17: 4793.39 | M17: 0 | N17: 0 | O17: 0 | P17: 1006.61 | Q17: 5800
A18: 04/09/2024 | B18: 1 - Factura A | C18: 120 | D18: 4949 | F18: 74365804898856 | G18: CUIT | H18: 30587197215 | I18: PANATEL SOCIEDAD ANONIMA | J18: 1 | K18: $ | L18: 68595.04 | M18: 0 | N18: 0 | O18: 0 | P18: 14404.96 | Q18: 86429.75
A19: 04/09/2024 | B19: 1 - Factura A | C19: 7 | D19: 3241 | F19: 74364799883128 | G19: CUIT | H19: 20284183534 | I19: FURLANETTO MARTIN | J19: 1 | K19: $ | L19: 4545.5 | M19: 0 | N19: 0 | O19: 0 | P19: 954.56 | Q19: 5500.06
A20: 04/09/2024 | B20: 1 - Factura A | C20: 120 | D20: 4948 | F20: 74365800262038 | G20: CUIT | H20: 30587197215 | I20: PANATEL SOCIEDAD ANONIMA | J20: 1 | K20: $ | L20: 68595.04 | M20: 0 | N20: 0 | O20: 0 | P20: 14404.96 | Q20: 86429.75
A21: 04/09/2024 | B21: 1 - Factura A | C21: 401 | D21: 66 | F21: 74364797895464 | G21: CUIT | H21: 30716234114 | I21: UZUMAKI S.A.S. | J21: 1305 | K21: USD | L21: 129.3 | M21: 0 | N21: 0 | O21: 0 | P21: 27.15 | Q21: 156.45
A22: 05/09/2024 | B22: 1 - Factura A | C22: 2 | D22: 760 | F22: 74369961703669 | G22: CUIT | H22: 20272865869 | I22: DI FEO MARTIN EZEQUIEL | J22: 1 | K22: $ | L22: 84450 | M22: 0 | N22: 0 | O22: 0 | P22: 17734.5 | Q22: 102184.5
A23: 05/09/2024 | B23: 1 - Factura A | C23: 5 | D23: 5331 | F23: 74363959099503 | G23: CUIT | H23: 30715833243 | I23: BIODINAMICA ASISTENCIA S.R.L. | J23: 1 | K23: $ | L23: 22238.59 | M23: 0 | N23: 0 | O23: 0 | P23: 4670.1 | Q23: 26908.69
... A35: 09/09/2024 | B35: 3 - Nota de Crédito A | C35: 5 | D35: 192 | F35: 74376416376753 | G35: CUIT | H35: 30712187316 | I35: ITALOMED PRODUCTOS SRL | J35: 1 | K35: $ | L35: 293619.94 | M35: 0 | N35: 0 | O35: 0 | P35: 61660.19 | Q35: 355280.13
A36: 09/09/2024 | B36: 11 - Factura C | C36: 1 | D36: 148 | F36: 74370408397319 | G36: CUIT | H36: 27338342840 | I36: CANCINO PAMELA RITA | J36: 1 | K36: $ | O36: 0 | Q36: 276800
A37: 10/09/2024 | B37: 1 - Factura A | C37: 2 | D37: 8403 | F37: 74372567359059 | G37: CUIT | H37: 27363810182 | I37: HECKER LAURA NOEMI | J37: 1 | K37: $ | L37: 3635.54 | M37: 0 | N37: 0 | O37: 0 | P37: 763.46 | Q37: 4399
A38: 10/09/2024 | B38: 1 - Factura A | C38: 5 | D38: 31858 | F38: 74370525870493 | G38: CUIT | H38: 30710804830 | I38: ZG MULTITEC SRL | J38: 1 | K38: $ | L38: 29410.86 | M38: 0 | N38: 0 | O38: 0 | P38: 3088.14 | Q38: 32499
A39: 10/09/2024 | B39: 1 - Factura A | C39: 8 | D39: 1684 | F39: 74371529941038 | G39: CUIT | H39: 30708973501 | I39: ASIAL S.R.L. | J39: 1 | K39: $ | L39: 740255 | M39: 0 | N39: 0 | O39: 0 | P39: 155453.55 | Q39: 895708.55
A40: 10/09/2024 | B40: 1 - Factura A | C40: 3 | D40: 4250 | F40: 74378552751950 | G40: CUIT | H40: 20184052858 | I40: ABOUD PABLO DANIEL | J40: 1 | K40: $ | L40: 16859.48 | M40: 0 | N40: 0 | O40: 0 | P40: 3540.49 | Q40: 20399.95
A41: 10/09/2024 | B41: 11 - Factura C | C41: 3 | D41: 986 | F41: 74379527477577 | G41: CUIT | H41: 20216451679 | I41: VAZQUEZ RICARDO OSCAR | J41: 1 | K41: $ | O41: 0 | Q41: 86000
A42: 11/09/2024 | B42: 1 - Factura A | C42: 1 | D42: 2468 | F42: 74379681409704 | G42: CUIT | H42: 30717179389 | I42: NICOLAS TOBIAS SEQUEIRA Y MARIA GABRIELA RATTNER SOCIEDAD DE LA SECCION IV LGS | J42: 1 | K42: $ | L42: 82644.62 | M42: 0 | N42: 0 | O42: 0 | P42: 17355.37 | Q42: 99999.99
A43: 11/09/2024 | B43: 1 - Factura A | C43: 5 | D43: 3378 | F43: 74379704726153 | G43: CUIT | H43: 30717179389 | I43: NICOLAS TOBIAS SEQUEIRA Y MARIA GABRIELA RATTNER SOCIEDAD DE LA SECCION IV LGS | J43: 1 | K43: $ | L43: 82644.63 | M43: 0 | N43: 0 | O43: 0 | P43: 17355.37 | Q43: 100000
A44: 11/09/2024 | B44: 1 - Factura A | C44: 3 | D44: 7676 | F44: 74379686794320 | G44: CUIT | H44: 33708218699 | I44: MANGGINI PABLO Y MANGGINI ULISES SOC. DE HECHO. | J44: 1 | K44: $ | L44: 15000 | M44: 0 | N44: 0 | O44: 0 | P44: 3150 | Q44: 18150
A45: 11/09/2024 | B45: 11 - Factura C | C45: 1 | D45: 9 | F45: 74373677716509 | G45: CUIT | H45: 20464199633 | I45: OVIEDO JIMENEZ TIZIANO LIONEL | J45: 1 | K45: $ | O45: 0 | Q45: 499950
A46: 12/09/2024 | B46: 1 - Factura A | C46: 2 | D46: 778 | F46: 74379814460759 | G46: CUIT | H46: 20272865869 | I46: DI FEO MARTIN EZEQUIEL | J46: 1 | K46: $ | L46: 128100 | M46: 0 | N46: 0 | O46: 0 | P46: 26901 | Q46: 155001
A47: 12/09/2024 | B47: 1 - Factura A | C47: 4 | D47: 38394 | F47: 74379814609856 | G47: CUIT | H47: 20289111329 | I47: LEDESMA EMILIANO RUBEN | J47: 1 | K47: $ | L47: 585730.8 | M47: 0 | N47: 0 | O47: 0 | P47: 123003.47 | Q47: 708734.27
A48: 12/09/2024 | B48: 1 - Factura A | C48: 5 | D48: 1915 | F48: 74376761404173 | G48: CUIT | H48: 30712187316 | I48: ITALOMED PRODUCTOS SRL | J48: 1 | K48: $ | L48: 254033.05 | M48: 0 | N48: 0 | O48: 0 | P48: 53346.94 | Q48: 307379.99
A49: 12/09/2024 | B49: 1 - Factura A | C49: 5 | D49: 1916 | F49: 74376766353942 | G49: CUIT | H49: 30712187316 | I49: ITALOMED PRODUCTOS SRL | J49: 1 | K49: $ | L49: 472751.65 | M49: 0 | N49: 0 | O49: 0 | P49: 99277.85 | Q49: 572029.5
A50: 13/09/2024 | B50: 1 - Factura A | C50: 1 | D50: 4620 | F50: 74371942773283 | G50: CUIT | H50: 30715141201 | I50: REHAB S.R.L. | J50: 1 | K50: $ | L50: 29295 | M50: 0 | N50: 0 | O50: 0 | P50: 6151.95 | Q50: 35446.95
A51: 13/09/2024 | B51: 1 - Factura A | C51: 5 | D51: 1920 | F51: 74376932362480 | G51: CUIT | H51: 30712187316 | I51: ITALOMED PRODUCTOS SRL | J51: 1 | K51: $ | L51: 34718.6 | M51: 0 | N51: 0 | O51: 0 | P51: 7290.91 | Q51: 42009.51
A52: 13/09/2024 | B52: 1 - Factura A | C52: 2 | D52: 783 | F52: 74379875047216 | G52: CUIT | H52: 20272865869 | I52: DI FEO MARTIN EZEQUIEL | J52: 1 | K52: $ | L52: 9950 | M52: 0 | N52: 0 | O52: 0 | P52: 2089.5 | Q52: 12039.5
A53: 13/09/2024 | B53: 1 - Factura A | C53: 1 | D53: 4613 | F53: 74371932408480 | G53: CUIT | H53: 30715141201 | I53: REHAB S.R.L. | J53: 1 | K53: $ | L53: 3648847.5 | M53: 0 | N53: 0 | O53: 0 | P53: 766257.98 | Q53: 4415105.5
A54: 13/09/2024 | B54: 1 - Factura A | C54: 503 | D54: 1469491 | F54: 74372992481197 | G54: CUIT | H54: 30639935872 | I54: CAMINOS DEL RIO URUGUAY S A DE CONSTRUCCIONES Y CONCESIONES VIALES | J54: 1 | K54: $ | L54: 2934.75 | M54: 0 | N54: 0 | O54: 0 | P54: 616.3 | Q54: 3697.79
A55: 13/09/2024 | B55: 1 - Factura A | C55: 2 | D55: 4940 | F55: 74375873241825 | G55: CUIT | H55: 27117233745 | I55: MANZINI MARTA GRACIELA | J55: 1 | K55: $ | L55: 585519 | M55: 0 | N55: 0 | O55: 0 | P55: 122958.99 | Q55: 708477.99
A56: 13/09/2024 | B56: 1 - Factura A | C56: 3 | D56: 170 | F56: 74383333330765 | G56: CUIT | H56: 20334976433 | I56: NARDOMARINO EZEQUIEL EDUARDO | J56: 1 | K56: $ | L56: 188330 | M56: 0 | N56: 0 | O56: 0 | P56: 39549.3 | Q56: 227879.3
A57: 13/09/2024 | B57: 1 - Factura A | C57: 3 | D57: 171 | F57: 74383357920263 | G57: CUIT | H57: 20334976433 | I57: NARDOMARINO EZEQUIEL EDUARDO | J57: 1 | K57: $ | L57: 153000 | M57: 0 | N57: 0 | O57: 0 | P57: 32130 | Q57: 185130
... A60: 15/09/2024 | B60: 1 - Factura A | C60: 113 | D60: 3802250 | F60: 74380483594334 | G60: CUIT | H60: 30577207190 | I60: COORDINACION ECOLOGICA AREA METROPOLITANA SOCIEDAD DEL ESTADO | J60: 1 | K60: $ | L60: 2975.21 | M60: 0 | N60: 0 | O60: 0 | P60: 624.79 | Q60: 3689.26
A61: 15/09/2024 | B61: 11 - Factura C | C61: 5 | D61: 168 | F61: 74379160231271 | G61: CUIT | H61: 27062343449 | I61: FERREIRA LILIANA INES | J61: 1 | K61: $ | O61: 0 | Q61: 260000
A62: 15/09/2024 | B62: 11 - Factura C | C62: 5 | D62: 169 | F62: 74379160368355 | G62: CUIT | H62: 27062343449 | I62: FERREIRA LILIANA INES | J62: 1 | K62: $ | O62: 0 | Q62: 35000
A63: 16/09/2024 | B63: 1 - Factura A | C63: 5015 | D63: 644558 | F63: 74384236665042 | G63: CUIT | H63: 30574876474 | I63: AUTOPISTAS URBANAS S A | J63: 1 | K63: $ | L63: 12702.19 | M63: 0 | N63: 0 | O63: 0 | P63: 2667.45 | Q63: 17020.92
A64: 16/09/2024 | B64: 1 - Factura A | C64: 6 | D64: 40318 | F64: 74389250556652 | G64: CUIT | H64: 30709459399 | I64: LA JUNIOR S.R.L. | J64: 1 | K64: $ | L64: 11807.44 | M64: 0 | N64: 0 | O64: 0 | P64: 2479.56 | Q64: 14287
A65: 16/09/2024 | B65: 1 - Factura A | C65: 2002 | D65: 72231 | F65: 74385199526054 | G65: CUIT | H65: 30716425165 | I65: MERCADO TOTAL SAS | J65: 1 | K65: $ | L65: 13842.98 | M65: 0 | N65: 0 | O65: 0 | P65: 2907.03 | Q65: 16750
A66: 16/09/2024 | B66: 1 - Factura A | C66: 2 | D66: 249 | F66: 74383195124025 | G66: CUIT | H66: 27144282383 | I66: SCHEJTER LILA ELISA | J66: 1 | K66: $ | L66: 320000 | M66: 0 | N66: 0 | O66: 0 | P66: 67200 | Q66: 387200
A67: 17/09/2024 | B67: 1 - Factura A | C67: 7 | D67: 524 | F67: 74380369713013 | G67: CUIT | H67: 30715630040 | I67: PISOS BODEN S.A. | J67: 1 | K67: $ | L67: 3517469.4 | M67: 0 | N67: 0 | O67: 0 | P67: 738668.58 | Q67: 4256138
A68: 17/09/2024 | B68: 1 - Factura A | C68: 711 | D68: 6155254 | F68: 34379169789485 | G68: CUIT | H68: 30677237119 | I68: AUTOPISTAS DEL SOL S A | J68: 1 | K68: $ | L68: 5515.3 | M68: 0 | N68: 165.46 | O68: 0 | P68: 1158.23 | Q68: 7114.76
A69: 17/09/2024 | B69: 1 - Factura A | C69: 629 | D69: 5447412 | F69: 34373728816629 | G69: CUIT | H69: 30663498513 | I69: GRUPO CONCESIONARIO DEL OESTE SA | J69: 1 | K69: $ | L69: 3440.74 | M69: 0 | N69: 0 | O69: 0 | P69: 722.56 | Q69: 4335.34
A70: 17/09/2024 | B70: 1 - Factura A | C70: 4264 | D70: 4388001 | F70: 74388498673820 | G70: CUIT | H70: 30639453738 | I70: TELECOM ARGENTINA SOCIEDAD ANONIMA | J70: 1 | K70: $ | L70: 24142.14 | M70: 0 | N70: 0 | O70: 0 | P70: 5069.85 | Q70: 30901.93
A71: 17/09/2024 | B71: 11 - Factura C | C71: 1 | D71: 248 | F71: 74395443070489 | G71: CUIT | H71: 27217606255 | I71: SAPUNA MIRIAN KARINA | J71: 1 | K71: $ | O71: 0 | Q71: 50223.03
A72: 17/09/2024 | B72: 11 - Factura C | C72: 1 | D72: 247 | F72: 74395442076201 | G72: CUIT | H72: 27217606255 | I72: SAPUNA MIRIAN KARINA | J72: 1 | K72: $ | O72: 0 | Q72: 56703.42
A73: 18/09/2024 | B73: 1 - Factura A | C73: 2 | D73: 4942 | F73: 74385474906338 | G73: CUIT | H73: 27117233745 | I73: MANZINI MARTA GRACIELA | J73: 1 | K73: $ | L73: 585519 | M73: 0 | N73: 0 | O73: 0 | P73: 122958.99 | Q73: 708477.99
A74: 18/09/2024 | B74: 11 - Factura C | C74: 1 | D74: 70 | F74: 74384470115890 | G74: CUIT | H74: 23281233084 | I74: DRUETTA ANDREA MARIEL | J74: 1 | K74: $ | O74: 0 | Q74: 215000
A75: 18/09/2024 | B75: 11 - Factura C | C75: 1 | D75: 71 | F75: 74384470845746 | G75: CUIT | H75: 23281233084 | I75: DRUETTA ANDREA MARIEL | J75: 1 | K75: $ | O75: 0 | Q75: 215000
A76: 18/09/2024 | B76: 11 - Factura C | C76: 1 | D76: 249 | F76: 74395443331023 | G76: CUIT | H76: 27217606255 | I76: SAPUNA MIRIAN KARINA | J76: 1 | K76: $ | O76: 0 | Q76: 55083.32
A77: 18/09/2024 | B77: 11 - Factura C | C77: 1 | D77: 250 | F77: 74395444517785 | G77: CUIT | H77: 27217606255 | I77: SAPUNA MIRIAN KARINA | J77: 1 | K77: $ | O77: 0 | Q77: 148916.68
A78: 19/09/2024 | B78: 1 - Factura A | C78: 2 | D78: 796 | F78: 74389604255613 | G78: CUIT | H78: 20272865869 | I78: DI FEO MARTIN EZEQUIEL | J78: 1 | K78: $ | L78: 253100 | M78: 0 | N78: 0 | O78: 0 | P78: 53151 | Q78: 306251
A79: 19/09/2024 | B79: 1 - Factura A | C79: 7 | D79: 6066 | F79: 74386569455318 | G79: CUIT | H79: 20131067446 | I79: TRIVEÑO ROMA RAMON | J79: 1 | K79: $ | L79: 278865.6 | M79: 0 | N79: 0 | O79: 0 | P79: 58561.78 | Q79: 337427.38
A80: 19/09/2024 | B80: 1 - Factura A | C80: 11 | D80: 91964 | F80: 74384582154669 | G80: CUIT | H80: 30526582884 | I80: EXPRESO MAR DEL PLATA SOCIEDAD ANONIMA | J80: 1 | K80: $ | L80: 4462.81 | M80: 0 | N80: 0 | O80: 0 | P80: 937.19 | Q80: 5400
A81: 19/09/2024 | B81: 11 - Factura C | C81: 3 | D81: 991 | F81: 74389582435775 | G81: CUIT | H81: 20216451679 | I81: VAZQUEZ RICARDO OSCAR | J81: 1 | K81: $ | O81: 0 | Q81: 160000
A82: 19/09/2024 | B82: 11 - Factura C | C82: 1 | D82: 251 | F82: 74395444759490 | G82: CUIT | H82: 27217606255 | I82: SAPUNA MIRIAN KARINA | J82: 1 | K82: $ | O82: 0 | Q82: 96357.85
A83: 19/09/2024 | B83: 11 - Factura C | C83: 1 | D83: 252 | F83: 74395445013622 | G83: CUIT | H83: 27217606255 | I83: SAPUNA MIRIAN KARINA | J83: 1 | K83: $ | O83: 0 | Q83: 105117.66
A84: 20/09/2024 | B84: 1 - Factura A | C84: 2171 | D84: 6478 | F84: 74386729481785 | G84: CUIT | H84: 30548083156 | I84: COTO CENTRO INTEGRAL DE COMERCIALIZACION SOCIEDAD ANONIMA | J84: 1 | K84: $ | L84: 4109.47 | M84: 0 | N84: 0 | O84: 328.75 | P84: 862.99 | Q84: 5301.21
A85: 20/09/2024 | B85: 1 - Factura A | C85: 17 | D85: 2312 | F85: 74381728297239 | G85: CUIT | H85: 30711764921 | I85: RELIEF CENTER S.R.L. | J85: 1 | K85: $ | L85: 21394 | M85: 0 | N85: 0 | O85: 0 | P85: 4492.74 | Q85: 25886.74
A86: 20/09/2024 | B86: 1 - Factura A | C86: 5 | D86: 3877 | F86: 74380716025151 | G86: CUIT | H86: 20348485580 | I86: NOLASCO ALAN MANUEL | J86: 1 | K86: $ | L86: 29099.82 | M86: 0 | N86: 0 | O86: 0 | P86: 6110.96 | Q86: 35210.78
A87: 20/09/2024 | B87: 1 - Factura A | C87: 5 | D87: 1937 | F87: 74386708279049 | G87: CUIT | H87: 30712187316 | I87: ITALOMED PRODUCTOS SRL | J87: 1 | K87: $ | L87: 213988.29 | M87: 0 | N87: 0 | O87: 0 | P87: 44937.54 | Q87: 258925.83
A88: 20/09/2024 | B88: 1 - Factura A | C88: 2 | D88: 250 | F88: 74383655585682 | G88: CUIT | H88: 27144282383 | I88: SCHEJTER LILA ELISA | J88: 1 | K88: $ | L88: 320000 | M88: 0 | N88: 0 | O88: 0 | P88: 67200 | Q88: 387200
A89: 20/09/2024 | B89: 1 - Factura A | C89: 4 | D89: 136 | F89: 74386719534162 | G89: CUIT | H89: 20317488476 | I89: VILLALBA MIGUEL ANGEL | J89: 1 | K89: $ | L89: 1870000 | M89: 0 | N89: 0 | O89: 0 | P89: 392700 | Q89: 2262700
A90: 20/09/2024 | B90: 11 - Factura C | C90: 1 | D90: 253 | F90: 74395446386733 | G90: CUIT | H90: 27217606255 | I90: SAPUNA MIRIAN KARINA | J90: 1 | K90: $ | O90: 0 | Q90: 87598.05
A91: 21/09/2024 | B91: 11 - Factura C | C91: 1 | D91: 14 | F91: 74395449158811 | G91: CUIT | H91: 27443612705 | I91: MIGOYA MORIONDO MARIA INES | J91: 1 | K91: $ | O91: 0 | Q91: 600000
A92: 23/09/2024 | B92: 1 - Factura A | C92: 5 | D92: 3128526 | F92: 74395012609092 | G92: CUIT | H92: 30702652975 | I92: NSS SA | J92: 1 | K92: $ | L92: 28530.17 | M92: 0 | N92: 0 | O92: 0 | P92: 5991.34 | Q92: 35948.01
A93: 23/09/2024 | B93: 1 - Factura A | C93: 5015 | D93: 648091 | F93: 74394947432580 | G93: CUIT | H93: 30574876474 | I93: AUTOPISTAS URBANAS S A | J93: 1 | K93: $ | L93: 17107.75 | M93: 0 | N93: 0 | O93: 0 | P93: 3592.62 | Q93: 22924.37
A94: 23/09/2024 | B94: 1 - Factura A | C94: 700 | D94: 1936359 | F94: 74392989880786 | G94: CUIT | H94: 30715804812 | I94: CORREDORES VIALES SOCIEDAD ANONIMA | J94: 1 | K94: $ | L94: 6246.93 | M94: 0 | N94: 0 | O94: 0 | P94: 1311.86 | Q94: 7871.14
A95: 23/09/2024 | B95: 1 - Factura A | C95: 700 | D95: 1936360 | F95: 74392989880804 | G95: CUIT | H95: 30715804812 | I95: CORREDORES VIALES SOCIEDAD ANONIMA | J95: 1 | K95: $ | L95: 728.62 | M95: 0 | N95: 0 | O95: 0 | P95: 153.01 | Q95: 881.63
A96: 23/09/2024 | B96: 1 - Factura A | C96: 6 | D96: 85435 | F96: 74394006853805 | G96: CUIT | H96: 30711553564 | I96: SALUDTEX SA | J96: 1 | K96: $ | L96: 999126 | M96: 0 | N96: 0 | O96: 0 | P96: 209816.46 | Q96: 1208942.5
A97: 23/09/2024 | B97: 1 - Factura A | C97: 6 | D97: 54307 | F97: 74398009565100 | G97: CUIT | H97: 30710177658 | I97: TARGET MEDICAL S.A. | J97: 1 | K97: $ | L97: 122080.32 | M97: 0 | N97: 0 | O97: 0 | P97: 25636.86 | Q97: 147717.18
A98: 24/09/2024 | B98: 1 - Factura A | C98: 1055 | D98: 854 | F98: 74391072835510 | G98: CUIT | H98: 30685849751 | I98: DIA ARGENTINA S A | J98: 1 | K98: $ | L98: 6165.28 | M98: 0 | N98: 0 | O98: 0 | P98: 1294.71 | Q98: 7768.25
A99: 24/09/2024 | B99: 1 - Factura A | C99: 2 | D99: 25 | F99: 74395124728024 | G99: CUIT | H99: 27243660535 | I99: BARD MARISA SILVIA | J99: 1 | K99: $ | L99: 360000 | M99: 0 | N99: 0 | O99: 0 | P99: 75600 | Q99: 435600
A100: 25/09/2024 | B100: 1 - Factura A | C100: 6 | D100: 54346 | F100: 74398248406433 | G100: CUIT | H100: 30710177658 | I100: TARGET MEDICAL S.A. | J100: 1 | K100: $ | L100: 356854.44 | M100: 0 | N100: 0 | O100: 0 | P100: 74939.44 | Q100: 431793.88
A101: 25/09/2024 | B101: 1 - Factura A | C101: 4 | D101: 71892 | F101: 74399186438923 | G101: CUIT | H101: 33709738459 | I101: ORTOPEDICOS ALFOLATEX SA | J101: 1 | K101: $ | L101: 655324.52 | M101: 0 | N101: 0 | O101: 0 | P101: 137618.15 | Q101: 792942.67
A102: 25/09/2024 | B102: 1 - Factura A | C102: 4 | D102: 137 | F102: 74396233311030 | G102: CUIT | H102: 20317488476 | I102: VILLALBA MIGUEL ANGEL | J102: 1 | K102: $ | L102: 105000 | M102: 0 | N102: 0 | O102: 0 | P102: 22050 | Q102: 127050
A103: 26/09/2024 | B103: 1 - Factura A | C103: 6 | D103: 54365 | F103: 74398371535029 | G103: CUIT | H103: 30710177658 | I103: TARGET MEDICAL S.A. | J103: 1 | K103: $ | L103: 682125 | M103: 0 | N103: 0 | O103: 0 | P103: 143246.25 | Q103: 825371.25
... A112: 27/09/2024 | B112: 1 - Factura A | C112: 2 | D112: 819 | F112: 74399429730188 | G112: CUIT | H112: 20272865869 | I112: DI FEO MARTIN EZEQUIEL | J112: 1 | K112: $ | L112: 105000 | M112: 0 | N112: 0 | O112: 0 | P112: 22050 | Q112: 127050
A113: 27/09/2024 | B113: 11 - Factura C | C113: 3 | D113: 995 | F113: 74399453320296 | G113: CUIT | H113: 20216451679 | I113: VAZQUEZ RICARDO OSCAR | J113: 1 | K113: $ | O113: 0 | Q113: 160000
A114: 28/09/2024 | B114: 1 - Factura A | C114: 2189 | D114: 77373 | F114: 74396609730132 | G114: CUIT | H114: 30548083156 | I114: COTO CENTRO INTEGRAL DE COMERCIALIZACION SOCIEDAD ANONIMA | J114: 1 | K114: $ | L114: 3905.09 | M114: 0 | N114: 0 | O114: 312.4 | P114: 820.07 | Q114: 5037.56
A115: 28/09/2024 | B115: 1 - Factura A | C115: 2 | D115: 336 | F115: 74409928953266 | G115: CUIT | H115: 27251962559 | I115: CHIARA FLORENCIA | J115: 1 | K115: $ | L115: 42396.71 | M115: 0 | N115: 0 | O115: 0 | P115: 8903.31 | Q115: 51300.01
A116: 29/09/2024 | B116: 1 - Factura A | C116: 25 | D116: 2868796 | F116: 74404735015283 | G116: CUIT | H116: 30703088534 | I116: MERCADOLIBRE S.R.L. | J116: 1 | K116: $ | L116: 37574.04 | M116: 0 | N116: 0 | O116: 3005.92 | P116: 7890.55 | Q116: 48470.51
A117: 30/09/2024 | B117: 1 - Factura A | C117: 6 | D117: 17452146 | F117: 74397511039418 | G117: CUIT | H117: 30620177497 | I117: POSNET SOCIEDAD DE RESPONSABILIDAD LIMITADA | J117: 1 | K117: $ | L117: 0 | M117: 0 | N117: 0 | O117: 0 | P117: 0 | Q117: 0
A118: 30/09/2024 | B118: 1 - Factura A | C118: 6 | D118: 17599524 | F118: 74397542581741 | G118: CUIT | H118: 30620177497 | I118: POSNET SOCIEDAD DE RESPONSABILIDAD LIMITADA | J118: 1 | K118: $ | L118: 26164.14 | M118: 0 | N118: 0 | O118: 0 | P118: 5494.47 | Q118: 33751.74
A119: 30/09/2024 | B119: 1 - Factura A | C119: 5015 | D119: 650706 | F119: 74404997363928 | G119: CUIT | H119: 30574876474 | I119: AUTOPISTAS URBANAS S A | J119: 1 | K119: $ | L119: 24879.27 | M119: 0 | N119: 0 | O119: 0 | P119: 5224.63 | Q119: 33338.2
A120: 30/09/2024 | B120: 1 - Factura A | C120: 20 | D120: 197792 | F120: 74402907225580 | G120: CUIT | H120: 30696850972 | I120: C.P.S. COMUNICACIONES S.A. | J120: 1 | K120: $ | L120: 19732.58 | M120: 0 | N120: 0 | O120: 0 | P120: 5327.8 | Q120: 26047.02
A121: 30/09/2024 | B121: 1 - Factura A | C121: 1 | D121: 591606 | F121: 74409955268089 | G121: CUIT | H121: 33716307749 | I121: VERISURE ARGENTINA MONITOREO DE ALARMAS SA | J121: 1 | K121: $ | L121: 318999 | M121: 0 | N121: 0 | O121: 0 | P121: 66989.79 | Q121: 401938.74
...

Sheet Hoja3
A1: Comprobante no recibido
A4: Fecha | B4: Comprobante | C4: Nombre | D4: Cond. IVA | E4: CUIT o Doc. | F4: Gravado | G4: No Gravado
A5: 02/09/2024 | B5: FA-C 0003-00000874 | C5: BOTINDARI JUAN CARLOS | D5: Responsable Monotributo | E5: 20086277523 | F5: 0 | G5: 275500
A6: 02/09/2024 | B6: 874 | C6: BOTINDARI JUAN CARLOS | E6: 20086277523
A7: 19/09/2024 | B7: FA-A 0007-00006066 | C7: Triveño Roma, Ramon | D7: IVA Responsable Inscripto | E7: 20131067446 | F7: 278865.6 | G7: 0
A8: 19/09/2024 | B8: 6066 | C8: TRIVEÑO ROMA RAMON | E8: 20131067446 | F8: 278865.6 | G8: 0
A9: 10/09/2024 | B9: FA-A 0003-00004250 | C9: Aboud, Pablo Daniel | D9: IVA Responsable Inscripto | E9: 20184052858 | F9: 16859.46 | G9: 0
A10: 30/09/2024 | B10: FA-A 0003-00004276 | C10: Aboud, Pablo Daniel | D10: IVA Responsable Inscripto | E10: 20184052858 | F10: 71074.3 | G10: 0
A11: 10/09/2024 | B11: 4250 | C11: ABOUD PABLO DANIEL | E11: 20184052858 | F11: 16859.48 | G11: 0
A12: 30/09/2024 | B12: 4276 | C12: ABOUD PABLO DANIEL | E12: 20184052858 | F12: 71074.33 | G12: 0
A13: 30/09/2024 | B13: 804 | C13: PAIS HECTOR GUILLERMO | E13: 20214946867 | F13: 37189.24 | G13: 0
A14: 10/09/2024 | B14: FA-C 0003-00000986 | C14: Vazquez, Ricardo Oscar | D14: Responsable Monotributo | E14: 20216451679 | F14: 0 | G14: 86000
A15: 27/09/2024 | B15: FA-C 0003-00000995 | C15: Vazquez, Ricardo Oscar | D15: Responsable Monotributo | E15: 20216451679 | F15: 0 | G15: 160000
A16: 10/09/2024 | B16: 986 | C16: VAZQUEZ RICARDO OSCAR | E16: 20216451679
A17: 19/09/2024 | B17: 991 | C17: VAZQUEZ RICARDO OSCAR | E17: 20216451679
A18: 27/09/2024 | B18: 995 | C18: VAZQUEZ RICARDO OSCAR | E18: 20216451679
A19: 12/09/2024 | B19: FA-A 0002-00000778 | C19: Di Feo, Martin Ezequiel | D19: IVA Responsable Inscripto | E19: 20272865869 | F19: 128100 | G19: 0
A20: 13/09/2024 | B20: FA-A 0002-00000783 | C20: Di Feo, Martin Ezequiel | D20: IVA Responsable Inscripto | E20: 20272865869 | F20: 9950 | G20: 0
A21: 19/09/2024 | B21: FA-A 0002-00000796 | C21: Di Feo, Martin Ezequiel | D21: IVA Responsable Inscripto | E21: 20272865869 | F21: 253100 | G21: 0
A22: 27/09/2024 | B22: FA-A 0002-00000816 | C22: Di Feo, Martin Ezequiel | D22: IVA Responsable Inscripto | E22: 20272865869 | F22: 9800 | G22: 0
A23: 27/09/2024 | B23: FA-A 0002-00000819 | C23: Di Feo, Martin Ezequiel | D23: IVA Responsable Inscripto | E23: 20272865869 | F23: 105000 | G23: 0
A24: 30/09/2024 | B24: FA-A 0002-00000814 | C24: Di Feo, Martin Ezequiel | D24: IVA Responsable Inscripto | E24: 20272865869 | F24: 149150 | G24: 0
A25: 05/09/2024 | B25: 760 | C25: DI FEO MARTIN EZEQUIEL | E25: 20272865869 | F25: 84450 | G25: 0
A26: 12/09/2024 | B26: 778 | C26: DI FEO MARTIN EZEQUIEL | E26: 20272865869 | F26: 128100 | G26: 0
A27: 13/09/2024 | B27: 783 | C27: DI FEO MARTIN EZEQUIEL | E27: 20272865869 | F27: 9950 | G27: 0
A28: 19/09/2024 | B28: 796 | C28: DI FEO MARTIN EZEQUIEL | E28: 20272865869 | F28: 253100 | G28: 0
A29: 26/09/2024 | B29: 814 | C29: DI FEO MARTIN EZEQUIEL | E29: 20272865869 | F29: 149150 | G29: 0
A30: 27/09/2024 | B30: 816 | C30: DI FEO MARTIN EZEQUIEL | E30: 20272865869 | F30: 9800 | G30: 0
A31: 27/09/2024 | B31: 819 | C31: DI FEO MARTIN EZEQUIEL | E31: 20272865869 | F31: 105000 | G31: 0
A32: 04/09/2024 | B32: FA-A 0007-00003241 | C32: Furlanetto, Martin | D32: IVA Responsable Inscripto | E32: 20284183534 | F32: 4545.5 | G32: 0
A33: 26/09/2024 | B33: TF-A0007-00003292 | C33: Furlanetto, Martin | D33: IVA Responsable Inscripto | E33: 20284183534 | F33: 9504.13 | G33: 0
A34: 04/09/2024 | B34: 3241 | C34: FURLANETTO MARTIN | E34: 20284183534 | F34: 4545.5 | G34: 0
A35: 26/09/2024 | B35: 3292 | C35: FURLANETTO MARTIN | E35: 20284183534 | F35: 9504.13 | G35: 0
A36: 12/09/2024 | B36: FA-A 0004-00038394 | C36: Ledesma, Emiliano Ruben | D36: IVA Responsable Inscripto | E36: 20289111329 | F36: 585730.8 | G36: 0
A37: 12/09/2024 | B37: 38394 | C37: LEDESMA EMILIANO RUBEN | E37: 20289111329 | F37: 585730.8 | G37: 0
A38: 20/09/2024 | B38: FA-A 0004-00000136 | C38: Villalba, Miguel Angel | D38: IVA Responsable Inscripto | E38: 20317488476 | F38: 1870000 | G38: 0
A39: 25/09/2024 | B39: FA-A 0004-00000137 | C39: Villalba, Miguel Angel | D39: IVA Responsable Inscripto | E39: 20317488476 | F39: 105000 | G39: 0
A40: 20/09/2024 | B40: 136 | C40: VILLALBA MIGUEL ANGEL | E40: 20317488476 | F40: 1870000 | G40: 0
A41: 25/09/2024 | B41: 137 | C41: VILLALBA MIGUEL ANGEL | E41: 20317488476 | F41: 105000 | G41: 0
A42: 13/09/2024 | B42: NC-A 0003-00000017 | C42: Nardomarino, Ezequiel Eduardo | D42: IVA Responsable Inscripto | E42: 20334976433 | F42: -188330 | G42: 0
A43: 13/09/2024 | B43: FA-A 0003-00000170 | C43: Nardomarino, Ezequiel Eduardo | D43: IVA Responsable Inscripto | E43: 20334976433 | F43: 188330 | G43: 0
A44: 13/09/2024 | B44: FA-A 0003-00000171 | C44: Nardomarino, Ezequiel Eduardo | D44: IVA Responsable Inscripto | E44: 20334976433 | F44: 153000 | G44: 0
A45: 26/09/2024 | B45: FA-A 0003-00000172 | C45: Nardomarino, Ezequiel Eduardo | D45: IVA Responsable Inscripto | E45: 20334976433 | F45: 90000 | G45: 0
A46: 13/09/2024 | B46: 170 | C46: NARDOMARINO EZEQUIEL EDUARDO | E46: 20334976433 | F46: 188330 | G46: 0
A47: 13/09/2024 | B47: 171 | C47: NARDOMARINO EZEQUIEL EDUARDO | E47: 20334976433 | F47: 153000 | G47: 0
A48: 13/09/2024 | B48: 17 | C48: NARDOMARINO EZEQUIEL EDUARDO | E48: 20334976433 | F48: 188330 | G48: 0
A49: 26/09/2024 | B49: 172 | C49: NARDOMARINO EZEQUIEL EDUARDO | E49: 20334976433 | F49: 90000 | G49: 0
A50: 20/09/2024 | B50: FA-A 0005-00003877 | C50: NOLASCO ALAN MANUEL | D50: IVA Responsable Inscripto | E50: 20348485580 | F50: 29099.82 | G50: 0
A51: 20/09/2024 | B51: 3877 | C51: NOLASCO ALAN MANUEL | E51: 20348485580 | F51: 29099.82 | G51: 0
A52: 11/09/2024 | B52: FA-C 0001-00000009 | C52: Oviedo Jimenez, Tiziano Lionel | D52: Responsable Monotributo | E52: 20464199633 | F52: 0 | G52: 499950
A53: 11/09/2024 | B53: 9 | C53: OVIEDO JIMENEZ TIZIANO LIONEL | E53: 20464199633
A54: 26/09/2024 | B54: FA-A 0005-00000032 | C54: MA JUN | D54: IVA Responsable Inscripto | E54: 20929183143 | F54: 50000 | G54: 0
A55: 26/09/2024 | B55: 32 | C55: MA JUN | E55: 20929183143 | F55: 50000 | G55: 0
A56: 18/09/2024 | B56: FA-C 0001-00000070 | C56: Druetta, Andrea Mariel | D56: Responsable Monotributo | E56: 23281233084 | F56: 0 | G56: 215000
A57: 18/09/2024 | B57: FA-C 0001-00000071 | C57: Druetta, Andrea Mariel | D57: Responsable Monotributo | E57: 23281233084 | F57: 0 | G57: 215000
A58: 18/09/2024 | B58: 70 | C58: DRUETTA ANDREA MARIEL | E58: 23281233084
A59: 18/09/2024 | B59: 71 | C59: DRUETTA ANDREA MARIEL | E59: 23281233084
A60: 15/09/2024 | B60: 168 | C60: FERREIRA LILIANA INES | E60: 27062343449
A61: 15/09/2024 | B61: 169 | C61: FERREIRA LILIANA INES | E61: 27062343449
A62: 27/08/2024 | B62: TF-A0005-00002285 | C62: Espada Faraldo, Margarita Mercedes | D62: IVA Responsable Inscripto | E62: 27114789033 | F62: 56363.64 | G62: 0
A63: 28/08/2024 | B63: TF-A0005-00002291 | C63: Espada Faraldo, Margarita Mercedes | D63: IVA Responsable Inscripto | E63: 27114789033 | F63: 10991.74 | G63: 0
A64: 13/09/2024 | B64: FA-A 0002-00004940 | C64: Manzini, Marta Graciela | D64: IVA Responsable Inscripto | E64: 27117233745 | F64: 585519 | G64: 0
A65: 18/09/2024 | B65: FA-A 0002-00004942 | C65: Manzini, Marta Graciela | D65: IVA Responsable Inscripto | E65: 27117233745 | F65: 585519 | G65: 0
A66: 13/09/2024 | B66: 4940 | C66: MANZINI MARTA GRACIELA | E66: 27117233745 | F66: 585519 | G66: 0
A67: 18/09/2024 | B67: 4942 | C67: MANZINI MARTA GRACIELA | E67: 27117233745 | F67: 585519 | G67: 0
A68: 02/09/2024 | B68: FA-A 0002-00000248 | C68: Schejter, Lila Elisa | D68: IVA Responsable Inscripto | E68: 27144282383 | F68: 160000 | G68: 0
A69: 16/09/2024 | B69: FA-A 0002-00000249 | C69: Schejter, Lila Elisa | D69: IVA Responsable Inscripto | E69: 27144282383 | F69: 320000 | G69: 0
A70: 20/09/2024 | B70: FA-A 0002-00000250 | C70: Schejter, Lila Elisa | D70: IVA Responsable Inscripto | E70: 27144282383 | F70: 320000 | G70: 0
A71: 26/09/2024 | B71: FA-A 0002-00000252 | C71: Schejter, Lila Elisa | D71: IVA Responsable Inscripto | E71: 27144282383 | F71: 300000 | G71: 0
A72: 02/09/2024 | B72: 248 | C72: SCHEJTER LILA ELISA | E72: 27144282383 | F72: 160000 | G72: 0
A73: 16/09/2024 | B73: 249 | C73: SCHEJTER LILA ELISA | E73: 27144282383 | F73: 320000 | G73: 0
A74: 20/09/2024 | B74: 250 | C74: SCHEJTER LILA ELISA | E74: 27144282383 | F74: 320000 | G74: 0
A75: 26/09/2024 | B75: 252 | C75: SCHEJTER LILA ELISA | E75: 27144282383 | F75: 300000 | G75: 0
A76: 17/09/2024 | B76: FA-C 0001-00000247 | C76: Sapuna, Mirian Karina | D76: Responsable Monotributo | E76: 27217606255 | F76: 0 | G76: 56703.42
A77: 17/09/2024 | B77: FA-C 0001-00000248 | C77: Sapuna, Mirian Karina | D77: Responsable Monotributo | E77: 27217606255 | F77: 0 | G77: 50223.03
A78: 18/09/2024 | B78: FA-C 0001-00000249 | C78: Sapuna, Mirian Karina | D78: Responsable Monotributo | E78: 27217606255 | F78: 0 | G78: 55083.32
A79: 18/09/2024 | B79: FA-C 0001-00000250 | C79: Sapuna, Mirian Karina | D79: Responsable Monotributo | E79: 27217606255 | F79: 0 | G79: 148916.68
A80: 19/09/2024 | B80: FA-C 0001-00000251 | C80: Sapuna, Mirian Karina | D80: Responsable Monotributo | E80: 27217606255 | F80: 0 | G80: 96357.85
A81: 19/09/2024 | B81: FA-C 0001-00000252 | C81: Sapuna, Mirian Karina | D81: Responsable Monotributo | E81: 27217606255 | F81: 0 | G81: 105117.66
A82: 20/09/2024 | B82: FA-C 0001-00000253 | C82: Sapuna, Mirian Karina | D82: Responsable Monotributo | E82: 27217606255 | F82: 0 | G82: 87598.05
A83: 17/09/2024 | B83: 248 | C83: SAPUNA MIRIAN KARINA | E83: 27217606255
A84: 17/09/2024 | B84: 247 | C84: SAPUNA MIRIAN KARINA | E84: 27217606255
A85: 18/09/2024 | B85: 249 | C85: SAPUNA MIRIAN KARINA | E85: 27217606255
A86: 18/09/2024 | B86: 250 | C86: SAPUNA MIRIAN KARINA | E86: 27217606255
A87: 19/09/2024 | B87: 251 | C87: SAPUNA MIRIAN KARINA | E87: 27217606255
A88: 19/09/2024 | B88: 252 | C88: SAPUNA MIRIAN KARINA | E88: 27217606255
A89: 20/09/2024 | B89: 253 | C89: SAPUNA MIRIAN KARINA | E89: 27217606255
A90: 24/09/2024 | B90: FA-A 0002-00000025 | C90: Bard, Marisa Silvia | D90: IVA Responsable Inscripto | E90: 27243660535 | F90: 360000 | G90: 0
A91: 24/09/2024 | B91: 25 | C91: BARD MARISA SILVIA | E91: 27243660535 | F91: 360000 | G91: 0
A92: 28/09/2024 | B92: 336 | C92: CHIARA FLORENCIA | E92: 27251962559 | F92: 42396.71 | G92: 0
A93: 02/09/2024 | B93: FA-C 0002-00000302 | C93: Blasco, Maria Guadalupe | D93: Responsable Monotributo | E93: 27265832178 | F93: 0 | G93: 250000
A94: 02/09/2024 | B94: 302 | C94: BLASCO MARIA GUADALUPE | E94: 27265832178
A95: 02/09/2024 | B95: FA-A 0005-00000102 | C95: Andreani, Agustina Susana | D95: IVA Responsable Inscripto | E95: 27329449357 | F95: 64100 | G95: 16400
A96: 02/09/2024 | B96: 102 | C96: ANDREANI AGUSTINA SUSANA | E96: 27329449357 | F96: 64100 | G96: 16400
A97: 09/09/2024 | B97: FA-C 0001-00000148 | C97: Cancino, Pamela Rita | D97: Responsable Monotributo | E97: 27338342840 | F97: 0 | G97: 276800
A98: 09/09/2024 | B98: 148 | C98: CANCINO PAMELA RITA | E98: 27338342840
A99: 10/09/2024 | B99: FA-A 0002-00008403 | C99: Hecker, Laura Noemi | D99: IVA Responsable Inscripto | E99: 27363810182 | F99: 3635.54 | G99: 0
A100: 10/09/2024 | B100: 8403 | C100: HECKER LAURA NOEMI | E100: 27363810182 | F100: 3635.54 | G100: 0
A101: 21/09/2024 | B101: FA-C 0001-00000014 | C101: Migoya Moriondo, Maria Ines | D101: Responsable Monotributo | E101: 27443612705 | F101: 0 | G101: 600000
A102: 21/09/2024 | B102: 14 | C102: MIGOYA MORIONDO MARIA INES | E102: 27443612705
...

Sheet Ventas 10
L2: =+SUBTOTAL(109,L7:L507) -> 57506519
A5: Mis Comprobantes Emitidos - CUIT 30710473168
A6: Fecha | B6: Tipo | C6: Punto de Venta | D6: Número Desde | E6: Número Hasta | F6: Cód. Autorización | G6: Tipo Doc. Receptor | H6: Nro. Doc. Receptor | I6: Denominación Receptor | J6: Tipo Cambio | K6: Moneda | L6: Imp. Neto Gravado | M6: Imp. Neto No Gravado | N6: Imp. Op. Exentas | O6: Otros Tributos | P6: IVA | Q6: Imp. Total
A7: 01/10/2024 | B7: 1 - Factura A | C7: 3 | D7: 2122 | F7: 74408937567460 | G7: CUIT | H7: 30522428163 | I7: GALENO ARGENTINA SOCIEDAD ANONIMA | J7: 1 | K7: $ | L7: 166023.57 | M7: 0 | N7: 0 | O7: 0 | P7: 34864.95 | Q7: 200888.54
A8: 01/10/2024 | B8: 1 - Factura A | C8: 3 | D8: 2123 | F8: 74408946814467 | G8: CUIT | H8: 30522428163 | I8: GALENO ARGENTINA SOCIEDAD ANONIMA | J8: 1 | K8: $ | L8: 122793.38 | M8: 0 | N8: 0 | O8: 0 | P8: 25786.61 | Q8: 148580
A9: 01/10/2024 | B9: 201 - Factura de Crédito electrónica MiPyMEs (FCE) A | C9: 3 | D9: 20 | F9: 74408946246916 | G9: CUIT | H9: 30522428163 | I9: GALENO ARGENTINA SOCIEDAD ANONIMA | J9: 1 | K9: $ | L9: 1159994.8 | M9: 0 | N9: 0 | O9: 0 | P9: 243598.9 | Q9: 1403593.6
A10: 01/10/2024 | B10: 201 - Factura de Crédito electrónica MiPyMEs (FCE) A | C10: 3 | D10: 17 | F10: 74408933316107 | G10: CUIT | H10: 30522428163 | I10: GALENO ARGENTINA SOCIEDAD ANONIMA | J10: 1 | K10: $ | L10: 9940284.7 | M10: 0 | N10: 0 | O10: 0 | P10: 2087459.8 | Q10: 12027744
A11: 01/10/2024 | B11: 201 - Factura de Crédito electrónica MiPyMEs (FCE) A | C11: 3 | D11: 18 | F11: 74408933881734 | G11: CUIT | H11: 30522428163 | I11: GALENO ARGENTINA SOCIEDAD ANONIMA | J11: 1 | K11: $ | L11: 1605012.1 | M11: 0 | N11: 0 | O11: 0 | P11: 337052.55 | Q11: 1942064.7
A12: 01/10/2024 | B12: 201 - Factura de Crédito electrónica MiPyMEs (FCE) A | C12: 3 | D12: 19 | F12: 74408938388545 | G12: CUIT | H12: 30522428163 | I12: GALENO ARGENTINA SOCIEDAD ANONIMA | J12: 1 | K12: $ | L12: 1420287.4 | M12: 0 | N12: 0 | O12: 0 | P12: 298260.35 | Q12: 1718547.7
A13: 01/10/2024 | B13: 6 - Factura B | C13: 9 | D13: 1 | F13: 74408943763770 | G13: 99 | H13: 0 | J13: 1 | K13: $ | L13: 1 | M13: 0 | N13: 0 | O13: 0 | P13: 0.21 | Q13: 1.21
A14: 03/10/2024 | B14: 6 - Factura B | C14: 8 | D14: 1 | F14: 74408170661661 | G14: 99 | H14: 0 | J14: 1 | K14: $ | L14: 8264.46 | M14: 0 | N14: 0 | O14: 0 | P14: 1735.54 | Q14: 10000
A15: 01/10/2024 | B15: 6 - Factura B | C15: 9 | D15: 2 | F15: 74408957430844 | G15: 99 | H15: 0 | J15: 1 | K15: $ | L15: 20661.16 | M15: 0 | N15: 0 | O15: 0 | P15: 4338.84 | Q15: 25000
A16: 03/10/2024 | B16: 6 - Factura B | C16: 8 | D16: 2 | F16: 74408171180167 | G16: 99 | H16: 0 | J16: 1 | K16: $ | L16: 6198.35 | M16: 0 | N16: 0 | O16: 0 | P16: 1301.65 | Q16: 7500
A17: 02/10/2024 | B17: 6 - Factura B | C17: 9 | D17: 3 | F17: 74408038377697 | G17: 99 | H17: 0 | J17: 1 | K17: $ | L17: 11487.6 | M17: 0 | N17: 0 | O17: 0 | P17: 2412.4 | Q17: 13900
A18: 03/10/2024 | B18: 6 - Factura B | C18: 8 | D18: 3 | F18: 74408175059410 | G18: 99 | H18: 0 | J18: 1 | K18: $ | L18: 21487.6 | M18: 0 | N18: 0 | O18: 0 | P18: 4512.4 | Q18: 26000
A19: 02/10/2024 | B19: 6 - Factura B | C19: 9 | D19: 4 | F19: 74408040307745 | G19: 99 | H19: 0 | J19: 1 | K19: $ | L19: 23471.07 | M19: 0 | N19: 0 | O19: 0 | P19: 4928.93 | Q19: 28400
A20: 03/10/2024 | B20: 6 - Factura B | C20: 8 | D20: 4 | F20: 74408178473241 | G20: 99 | H20: 0 | J20: 1 | K20: $ | L20: 20661.16 | M20: 0 | N20: 0 | O20: 0 | P20: 4338.84 | Q20: 25000
A21: 02/10/2024 | B21: 6 - Factura B | C21: 9 | D21: 5 | F21: 74408041595038 | G21: 99 | H21: 0 | J21: 1 | K21: $ | L21: 23966.94 | M21: 0 | N21: 0 | O21: 0 | P21: 5033.06 | Q21: 29000
A22: 03/10/2024 | B22: 6 - Factura B | C22: 8 | D22: 5 | F22: 74408179334943 | G22: 99 | H22: 0 | J22: 1 | K22: $ | L22: 4462.81 | M22: 0 | N22: 0 | O22: 0 | P22: 937.19 | Q22: 5400
A23: 02/10/2024 | B23: 6 - Factura B | C23: 9 | D23: 6 | F23: 74408042545709 | G23: 99 | H23: 0 | J23: 1 | K23: $ | L23: 26446.28 | M23: 0 | N23: 0 | O23: 0 | P23: 5553.72 | Q23: 32000
A24: 03/10/2024 | B24: 6 - Factura B | C24: 8 | D24: 6 | F24: 74408181398159 | G24: 99 | H24: 0 | J24: 1 | K24: $ | L24: 21487.6 | M24: 0 | N24: 0 | O24: 0 | P24: 4512.4 | Q24: 26000
... A50: 24/10/2024 | B50: 6 - Factura B | C50: 8 | D50: 19 | F50: 74438605807968 | G50: 99 | H50: 0 | J50: 1 | K50: $ | L50: 21487.6 | M50: 0 | N50: 0 | O50: 0 | P50: 4512.4 | Q50: 26000
A51: 01/10/2024 | B51: 8 - Nota de Crédito B | C51: 7 | D51: 160 | F51: 74408958958205 | G51: 99 | H51: 0 | J51: 1 | K51: $ | L51: -1 | M51: 0 | N51: 0 | O51: 0 | P51: =+L51*0.21 -> -0.21 | Q51: =+SUM(L51+P51) -> -1.21
A52: 02/10/2024 | B52: 1 - Factura A | C52: 7 | D52: 2167 | F52: 74408103654758 | G52: CUIT | H52: 30522428163 | I52: GALENO ARGENTINA SOCIEDAD ANONIMA | J52: 1 | K52: $ | L52: 94164.44 | M52: 0 | N52: 0 | O52: 0 | P52: 19774.53 | Q52: 113938.97
A53: 07/10/2024 | B53: 6 - Factura B | C53: 9 | D53: 20 | F53: 74418695581613 | G53: 99 | H53: 0 | J53: 1 | K53: $ | L53: 7024.79 | M53: 0 | N53: 0 | O53: 0 | P53: 1475.21 | Q53: 8500
A54: 24/10/2024 | B54: 6 - Factura B | C54: 8 | D54: 20 | F54: 74438607760579 | G54: 99 | H54: 0 | J54: 1 | K54: $ | L54: 29338.84 | M54: 0 | N54: 0 | O54: 0 | P54: 6161.16 | Q54: 35500
A55: 07/10/2024 | B55: 6 - Factura B | C55: 9 | D55: 21 | F55: 74418696494142 | G55: 99 | H55: 0 | J55: 1 | K55: $ | L55: 28099.17 | M55: 0 | N55: 0 | O55: 0 | P55: 5900.83 | Q55: 34000
A56: 24/10/2024 | B56: 6 - Factura B | C56: 8 | D56: 21 | F56: 74438612802737 | G56: 99 | H56: 0 | J56: 1 | K56: $ | L56: 10743.8 | M56: 0 | N56: 0 | O56: 0 | P56: 2256.2 | Q56: 13000
A57: 08/10/2024 | B57: 6 - Factura B | C57: 9 | D57: 22 | F57: 74418764489879 | G57: 99 | H57: 0 | J57: 1 | K57: $ | L57: 8595.04 | M57: 0 | N57: 0 | O57: 0 | P57: 1804.96 | Q57: 10400
A58: 24/10/2024 | B58: 6 - Factura B | C58: 8 | D58: 22 | F58: 74438617156130 | G58: 99 | H58: 0 | J58: 1 | K58: $ | L58: 11487.6 | M58: 0 | N58: 0 | O58: 0 | P58: 2412.4 | Q58: 13900
A59: 08/10/2024 | B59: 6 - Factura B | C59: 9 | D59: 23 | F59: 74418769740159 | G59: 99 | H59: 0 | J59: 1 | K59: $ | L59: 10743.8 | M59: 0 | N59: 0 | O59: 0 | P59: 2256.2 | Q59: 13000
A60: 24/10/2024 | B60: 6 - Factura B | C60: 8 | D60: 23 | F60: 74438639281565 | G60: 99 | H60: 0 | J60: 1 | K60: $ | L60: 4958.68 | M60: 0 | N60: 0 | O60: 0 | P60: 1041.32 | Q60: 6000
A61: 08/10/2024 | B61: 6 - Factura B | C61: 9 | D61: 24 | F61: 74418771754336 | G61: 99 | H61: 0 | J61: 1 | K61: $ | L61: 44628.1 | M61: 0 | N61: 0 | O61: 0 | P61: 9371.9 | Q61: 54000
A62: 24/10/2024 | B62: 6 - Factura B | C62: 8 | D62: 24 | F62: 74438643080056 | G62: 99 | H62: 0 | J62: 1 | K62: $ | L62: 8264.46 | M62: 0 | N62: 0 | O62: 0 | P62: 1735.54 | Q62: 10000
A63: 08/10/2024 | B63: 6 - Factura B | C63: 9 | D63: 25 | F63: 74418773946085 | G63: 99 | H63: 0 | J63: 1 | K63: $ | L63: 8595.04 | M63: 0 | N63: 0 | O63: 0 | P63: 1804.96 | Q63: 10400
A64: 24/10/2024 | B64: 6 - Factura B | C64: 8 | D64: 25 | F64: 74438648684078 | G64: 99 | H64: 0 | J64: 1 | K64: $ | L64: 21487.6 | M64: 0 | N64: 0 | O64: 0 | P64: 4512.4 | Q64: 26000
... A88: 10/10/2024 | B88: 6 - Factura B | C88: 9 | D88: 48 | F88: 74418040577125 | G88: 99 | H88: 0 | J88: 1 | K88: $ | L88: 10743.8 | M88: 0 | N88: 0 | O88: 0 | P88: 2256.2 | Q88: 13000
A89: 04/10/2024 | B89: 1 - Factura A | C89: 7 | D89: 2168 | F89: 74408316978690 | G89: CUIT | H89: 30715186655 | I89: AMPARO SALUD S.R.L. | J89: 1 | K89: $ | L89: 474097.79 | M89: 0 | N89: 0 | O89: 0 | P89: 99560.54 | Q89: 573658.33
A90: 04/10/2024 | B90: 1 - Factura A | C90: 7 | D90: 2169 | F90: 74408319440955 | G90: CUIT | H90: 30590412631 | I90: OBRA SOCIAL DEL SINDICATO DE MECANICOS Y AFINES DEL TRANSPORTE AUTOMOTOR | J90: 1 | K90: $ | L90: 411570.25 | M90: 0 | N90: 0 | O90: 0 | P90: 86429.75 | Q90: 498000
A91: 04/10/2024 | B91: 1 - Factura A | C91: 7 | D91: 2170 | F91: 74408321803168 | G91: CUIT | H91: 30500053522 | I91: OBRA SOCIAL DE LA ACTIVIDAD DE SEGUROS, REASEGUROS, CAPITALIZACION Y AHORRO Y PRESTAMO PARA LA VIVI | J91: 1 | K91: $ | L91: 65950.41 | M91: 0 | N91: 0 | O91: 0 | P91: 13849.59 | Q91: 79800
A92: 04/10/2024 | B92: 1 - Factura A | C92: 7 | D92: 2171 | F92: 74408366361334 | G92: CUIT | H92: 30710538014 | I92: HC HOMECARE INTERNACION DOMICILIARIA S.A. | J92: 1 | K92: $ | L92: 418429.75 | M92: 0 | N92: 0 | O92: 0 | P92: 87870.25 | Q92: 506300
A93: 04/10/2024 | B93: 1 - Factura A | C93: 3 | D93: 2124 | F93: 74408327628289 | G93: CUIT | H93: 27301150801 | I93: PANUNTO ELIDA YAMILA | J93: 1 | K93: $ | L93: 21487.62 | M93: 0 | N93: 0 | O93: 0 | P93: 4512.4 | Q93: 26000
A94: 04/10/2024 | B94: 201 - Factura de Crédito electrónica MiPyMEs (FCE) A | C94: 6 | D94: 537 | F94: 74408336991539 | G94: CUIT | H94: 30683032227 | I94: OBRA SOCIAL UNION PERSONAL DE LA UNION DEL PERSONAL CIVIL DE LA NACION | J94: 1 | K94: $ | L94: 3717071 | M94: 0 | N94: 0 | O94: 0 | P94: 780584.92 | Q94: 4497655.9
A95: 10/10/2024 | B95: 6 - Factura B | C95: 9 | D95: 49 | F95: 74418041440212 | G95: 99 | H95: 0 | J95: 1 | K95: $ | L95: 10743.8 | M95: 0 | N95: 0 | O95: 0 | P95: 2256.2 | Q95: 13000
A96: 10/10/2024 | B96: 6 - Factura B | C96: 9 | D96: 50 | F96: 74418046197129 | G96: 99 | H96: 0 | J96: 1 | K96: $ | L96: 51239.67 | M96: 0 | N96: 0 | O96: 0 | P96: 10760.33 | Q96: 62000
A97: 10/10/2024 | B97: 6 - Factura B | C97: 9 | D97: 51 | F97: 74418062659277 | G97: 99 | H97: 0 | J97: 1 | K97: $ | L97: 12396.69 | M97: 0 | N97: 0 | O97: 0 | P97: 2603.31 | Q97: 15000
A98: 10/10/2024 | B98: 6 - Factura B | C98: 9 | D98: 52 | F98: 74418064811168 | G98: 99 | H98: 0 | J98: 1 | K98: $ | L98: 14669.42 | M98: 0 | N98: 0 | O98: 0 | P98: 3080.58 | Q98: 17750
A99: 10/10/2024 | B99: 6 - Factura B | C99: 9 | D99: 53 | F99: 74418070705317 | G99: 99 | H99: 0 | J99: 1 | K99: $ | L99: 14669.42 | M99: 0 | N99: 0 | O99: 0 | P99: 3080.58 | Q99: 17750
A100: 10/10/2024 | B100: 6 - Factura B | C100: 9 | D100: 54 | F100: 74418078402646 | G100: 99 | H100: 0 | J100: 1 | K100: $ | L100: 28925.62 | M100: 0 | N100: 0 | O100: 0 | P100: 6074.38 | Q100: 35000
A101: 10/10/2024 | B101: 6 - Factura B | C101: 9 | D101: 55 | F101: 74418079997217 | G101: 99 | H101: 0 | J101: 1 | K101: $ | L101: 41322.31 | M101: 0 | N101: 0 | O101: 0 | P101: 8677.69 | Q101: 50000
A102: 10/10/2024 | B102: 6 - Factura B | C102: 9 | D102: 56 | F102: 74418081432889 | G102: 99 | H102: 0 | J102: 1 | K102: $ | L102: 16528.93 | M102: 0 | N102: 0 | O102: 0 | P102: 3471.07 | Q102: 20000
A103: 10/10/2024 | B103: 6 - Factura B | C103: 9 | D103: 57 | F103: 74418083374260 | G103: 99 | H103: 0 | J103: 1 | K103: $ | L103: 28099.17 | M103: 0 | N103: 0 | O103: 0 | P103: 5900.83 | Q103: 34000
A104: 10/10/2024 | B104: 6 - Factura B | C104: 9 | D104: 58 | F104: 74418085503450 | G104: 99 | H104: 0 | J104: 1 | K104: $ | L104: 21900.83 | M104: 0 | N104: 0 | O104: 0 | P104: 4599.17 | Q104: 26500
A105: 10/10/2024 | B105: 6 - Factura B | C105: 9 | D105: 59 | F105: 74418088847324 | G105: 99 | H105: 0 | J105: 1 | K105: $ | L105: 29338.84 | M105: 0 | N105: 0 | O105: 0 | P105: 6161.16 | Q105: 35500
A106: 14/10/2024 | B106: 6 - Factura B | C106: 9 | D106: 60 | F106: 74428430670640 | G106: 99 | H106: 0 | J106: 1 | K106: $ | L106: 8264.46 | M106: 0 | N106: 0 | O106: 0 | P106: 1735.54 | Q106: 10000
... A111: 14/10/2024 | B111: 6 - Factura B | C111: 9 | D111: 65 | F111: 74428454886464 | G111: 99 | H111: 0 | J111: 1 | K111: $ | L111: 22314.05 | M111: 0 | N111: 0 | O111: 0 | P111: 4685.95 | Q111: 27000
A112: 07/10/2024 | B112: 1 - Factura A | C112: 7 | D112: 2172 | F112: 74418647857079 | G112: CUIT | H112: 30608716390 | I112: OBRA SOCIAL DEL PERSONAL DE LAS TELECOMUNICACIONES DE LA REPUBLICA ARGENTINA | J112: 1 | K112: $ | L112: 165289.25 | M112: 0 | N112: 0 | O112: 0 | P112: 34710.75 | Q112: 200000
A113: 07/10/2024 | B113: 1 - Factura A | C113: 7 | D113: 2173 | F113: 74418654117062 | G113: CUIT | H113: 30546771314 | I113: MEDICUS SOCIEDAD ANONIMA DE ASISTENCIA MEDICA Y CIENTIFICA | J113: 1 | K113: $ | L113: 47933.88 | M113: 0 | N113: 0 | O113: 0 | P113: 10066.12 | Q113: 58000
A114: 07/10/2024 | B114: 1 - Factura A | C114: 7 | D114: 2174 | F114: 74418669430169 | G114: CUIT | H114: 30546771314 | I114: MEDICUS SOCIEDAD ANONIMA DE ASISTENCIA MEDICA Y CIENTIFICA | J114: 1 | K114: $ | L114: 400826.45 | M114: 0 | N114: 0 | O114: 0 | P114: 84173.55 | Q114: 485000
A115: 07/10/2024 | B115: 1 - Factura A | C115: 7 | D115: 2175 | F115: 74418675357446 | G115: CUIT | H115: 30608716390 | I115: OBRA SOCIAL DEL PERSONAL DE LAS TELECOMUNICACIONES DE LA REPUBLICA ARGENTINA | J115: 1 | K115: $ | L115: 7913.63 | M115: 0 | N115: 0 | O115: 0 | P115: 1661.87 | Q115: 9575.5
A116: 07/10/2024 | B116: 1 - Factura A | C116: 7 | D116: 2176 | F116: 74418689647082 | G116: CUIT | H116: 30608716390 | I116: OBRA SOCIAL DEL PERSONAL DE LAS TELECOMUNICACIONES DE LA REPUBLICA ARGENTINA | J116: 1 | K116: $ | L116: 15000 | M116: 0 | N116: 0 | O116: 0 | P116: 3150 | Q116: 18150
A117: 07/10/2024 | B117: 1 - Factura A | C117: 7 | D117: 2177 | F117: 74418691849336 | G117: CUIT | H117: 30608716390 | I117: OBRA SOCIAL DEL PERSONAL DE LAS TELECOMUNICACIONES DE LA REPUBLICA ARGENTINA | J117: 1 | K117: $ | L117: 48801.65 | M117: 0 | N117: 0 | O117: 0 | P117: 10248.35 | Q117: 59050
A118: 07/10/2024 | B118: 201 - Factura de Crédito electrónica MiPyMEs (FCE) A | C118: 6 | D118: 538 | F118: 74418628285020 | G118: CUIT | H118: 30683032227 | I118: OBRA SOCIAL UNION PERSONAL DE LA UNION DEL PERSONAL CIVIL DE LA NACION | J118: 1 | K118: $ | L118: 1474238.3 | M118: 0 | N118: 0 | O118: 0 | P118: 309590.05 | Q118: 1783828.4
A119: 07/10/2024 | B119: 3 - Nota de Crédito A | C119: 7 | D119: 158 | F119: 74418694995280 | G119: CUIT | H119: 30608716390 | I119: OBRA SOCIAL DEL PERSONAL DE LAS TELECOMUNICACIONES DE LA REPUBLICA ARGENTINA | J119: 1 | K119: $ | L119: -1286.03 | M119: 0 | N119: 0 | O119: 0 | P119: =+L119*0.21 -> -270.0663 | Q119: =+SUM(L119+P119) -> -1556.0963
A120: 14/10/2024 | B120: 6 - Factura B | C120: 9 | D120: 66 | F120: 74428458573628 | G120: 99 | H120: 0 | J120: 1 | K120: $ | L120: 10743.8 | M120: 0 | N120: 0 | O120: 0 | P120: 2256.2 | Q120: 13000
A121: 14/10/2024 | B121: 6 - Factura B | C121: 9 | D121: 67 | F121: 74428467881828 | G121: 99 | H121: 0 | J121: 1 | K121: $ | L121: 10743.8 | M121: 0 | N121: 0 | O121: 0 | P121: 2256.2 | Q121: 13000
A122: 14/10/2024 | B122: 6 - Factura B | C122: 9 | D122: 68 | F122: 74428473743686 | G122: 99 | H122: 0 | J122: 1 | K122: $ | L122: 25289.26 | M122: 0 | N122: 0 | O122: 0 | P122: 5310.74 | Q122: 30600
A123: 14/10/2024 | B123: 6 - Factura B | C123: 9 | D123: 69 | F123: 74428487910166 | G123: 99 | H123: 0 | J123: 1 | K123: $ | L123: 16694.21 | M123: 0 | N123: 0 | O123: 0 | P123: 3505.79 | Q123: 20200
A124: 14/10/2024 | B124: 6 - Factura B | C124: 9 | D124: 70 | F124: 74428489095486 | G124: 99 | H124: 0 | J124: 1 | K124: $ | L124: 13223.14 | M124: 0 | N124: 0 | O124: 0 | P124: 2776.86 | Q124: 16000
A125: 14/10/2024 | B125: 6 - Factura B | C125: 9 | D125: 71 | F125: 74428490731366 | G125: 99 | H125: 0 | J125: 1 | K125: $ | L125: 33884.3 | M125: 0 | N125: 0 | O125: 0 | P125: 7115.7 | Q125: 41000
A126: 14/10/2024 | B126: 6 - Factura B | C126: 9 | D126: 72 | F126: 74428491088784 | G126: 99 | H126: 0 | J126: 1 | K126: $ | L126: 11570.25 | M126: 0 | N126: 0 | O126: 0 | P126: 2429.75 | Q126: 14000
A127: 15/10/2024 | B127: 6 - Factura B | C127: 9 | D127: 73 | F127: 74428548042101 | G127: 99 | H127: 0 | J127: 1 | K127: $ | L127: 28925.62 | M127: 0 | N127: 0 | O127: 0 | P127: 6074.38 | Q127: 35000
A128: 15/10/2024 | B128: 6 - Factura B | C128: 9 | D128: 74 | F128: 74428548507772 | G128: 99 | H128: 0 | J128: 1 | K128: $ | L128: 10743.8 | M128: 0 | N128: 0 | O128: 0 | P128: 2256.2 | Q128: 13000
A129: 15/10/2024 | B129: 6 - Factura B | C129: 9 | D129: 75 | F129: 74428554734956 | G129: 99 | H129: 0 | J129: 1 | K129: $ | L129: 21487.6 | M129: 0 | N129: 0 | O129: 0 | P129: 4512.4 | Q129: 26000
A130: 08/10/2024 | B130: 1 - Factura A | C130: 7 | D130: 2178 | F130: 74418832797315 | G130: CUIT | H130: 30709016012 | I130: MGR IMPLANTES S.A. | J130: 1 | K130: $ | L130: 174660.33 | M130: 0 | N130: 0 | O130: 0 | P130: 36678.67 | Q130: 211339
A131: 08/10/2024 | B131: 3 - Nota de Crédito A | C131: 7 | D131: 159 | F131: 74418816093167 | G131: CUIT | H131: 30522428163 | I131: GALENO ARGENTINA SOCIEDAD ANONIMA | J131: 1 | K131: $ | L131: -8000.5 | M131: 0 | N131: 0 | O131: 0 | P131: =+L131*0.21 -> -1680.105 | Q131: =+SUM(L131+P131) -> -9680.605
A132: 08/10/2024 | B132: 3 - Nota de Crédito A | C132: 7 | D132: 160 | F132: 74418816402502 | G132: CUIT | H132: 30522428163 | I132: GALENO ARGENTINA SOCIEDAD ANONIMA | J132: 1 | K132: $ | L132: -23853.58 | M132: 0 | N132: 0 | O132: 0 | P132: =+L132*0.21 -> -5009.2518 | Q132: =+SUM(L132+P132) -> -28862.832
A133: 08/10/2024 | B133: 3 - Nota de Crédito A | C133: 7 | D133: 161 | F133: 74418816611485 | G133: CUIT | H133: 30522428163 | I133: GALENO ARGENTINA SOCIEDAD ANONIMA | J133: 1 | K133: $ | L133: -9917.36 | M133: 0 | N133: 0 | O133: 0 | P133: =+L133*0.21 -> -2082.6456 | Q133: =+SUM(L133+P133) -> -12000.006
A134: 08/10/2024 | B134: 3 - Nota de Crédito A | C134: 7 | D134: 162 | F134: 74418816792521 | G134: CUIT | H134: 30522428163 | I134: GALENO ARGENTINA SOCIEDAD ANONIMA | J134: 1 | K134: $ | L134: -12179.5 | M134: 0 | N134: 0 | O134: 0 | P134: =+L134*0.21 -> -2557.695 | Q134: =+SUM(L134+P134) -> -14737.195
A135: 08/10/2024 | B135: 3 - Nota de Crédito A | C135: 7 | D135: 163 | F135: 74418817040408 | G135: CUIT | H135: 30522428163 | I135: GALENO ARGENTINA SOCIEDAD ANONIMA | J135: 1 | K135: $ | L135: -14893.82 | M135: 0 | N135: 0 | O135: 0 | P135: =+L135*0.21 -> -3127.7022 | Q135: =+SUM(L135+P135) -> -18021.522
A136: 08/10/2024 | B136: 3 - Nota de Crédito A | C136: 7 | D136: 164 | F136: 74418817280255 | G136: CUIT | H136: 30522428163 | I136: GALENO ARGENTINA SOCIEDAD ANONIMA | J136: 1 | K136: $ | L136: -16863.25 | M136: 0 | N136: 0 | O136: 0 | P136: =+L136*0.21 -> -3541.2825 | Q136: =+SUM(L136+P136) -> -20404.533
A137: 15/10/2024 | B137: 6 - Factura B | C137: 9 | D137: 76 | F137: 74428555873303 | G137: 99 | H137: 0 | J137: 1 | K137: $ | L137: 14876.03 | M137: 0 | N137: 0 | O137: 0 | P137: 3123.97 | Q137: 18000
A138: 15/10/2024 | B138: 6 - Factura B | C138: 9 | D138: 77 | F138: 74428556796814 | G138: 99 | H138: 0 | J138: 1 | K138: $ | L138: 30495.87 | M138: 0 | N138: 0 | O138: 0 | P138: 6404.13 | Q138: 36900
A139: 15/10/2024 | B139: 6 - Factura B | C139: 9 | D139: 78 | F139: 74428578832060 | G139: 99 | H139: 0 | J139: 1 | K139: $ | L139: 14669.42 | M139: 0 | N139: 0 | O139: 0 | P139: 3080.58 | Q139: 17750
A140: 15/10/2024 | B140: 6 - Factura B | C140: 9 | D140: 79 | F140: 74428588600696 | G140: 99 | H140: 0 | J140: 1 | K140: $ | L140: 18181.82 | M140: 0 | N140: 0 | O140: 0 | P140: 3818.18 | Q140: 22000
A141: 15/10/2024 | B141: 6 - Factura B | C141: 9 | D141: 80 | F141: 74428591462137 | G141: 99 | H141: 0 | J141: 1 | K141: $ | L141: 21487.6 | M141: 0 | N141: 0 | O141: 0 | P141: 4512.4 | Q141: 26000
A142: 15/10/2024 | B142: 6 - Factura B | C142: 9 | D142: 81 | F142: 74428595702930 | G142: 99 | H142: 0 | J142: 1 | K142: $ | L142: 16528.93 | M142: 0 | N142: 0 | O142: 0 | P142: 3471.07 | Q142: 20000
A143: 15/10/2024 | B143: 6 - Factura B | C143: 9 | D143: 82 | F143: 74428597920689 | G143: 99 | H143: 0 | J143: 1 | K143: $ | L143: 12396.69 | M143: 0 | N143: 0 | O143: 0 | P143: 2603.31 | Q143: 15000
A144: 16/10/2024 | B144: 6 - Factura B | C144: 9 | D144: 83 | F144: 74428675466257 | G144: 99 | H144: 0 | J144: 1 | K144: $ | L144: 15702.48 | M144: 0 | N144: 0 | O144: 0 | P144: 3297.52 | Q144: 19000
A145: 16/10/2024 | B145: 6 - Factura B | C145: 9 | D145: 84 | F145: 74428683364455 | G145: 99 | H145: 0 | J145: 1 | K145: $ | L145: 13223.14 | M145: 0 | N145: 0 | O145: 0 | P145: 2776.86 | Q145: 16000
A146: 16/10/2024 | B146: 6 - Factura B | C146: 9 | D146: 85 | F146: 74428690814622 | G146: 99 | H146: 0 | J146: 1 | K146: $ | L146: 20661.16 | M146: 0 | N146: 0 | O146: 0 | P146: 4338.84 | Q146: 25000
A147: 16/10/2024 | B147: 6 - Factura B | C147: 9 | D147: 86 | F147: 74428705965823 | G147: 99 | H147: 0 | J147: 1 | K147: $ | L147: 58512.4 | M147: 0 | N147: 0 | O147: 0 | P147: 12287.6 | Q147: 70800
A148: 09/10/2024 | B148: 1 - Factura A | C148: 7 | D148: 2179 | F148: 74418894340309 | G148: CUIT | H148: 30709016012 | I148: MGR IMPLANTES S.A. | J148: 1 | K148: $ | L148: 550413.22 | M148: 0 | N148: 0 | O148: 0 | P148: 115586.78 | Q148: 666000
A149: 09/10/2024 | B149: 1 - Factura A | C149: 7 | D149: 2180 | F149: 74418927703083 | G149: CUIT | H149: 30546771314 | I149: MEDICUS SOCIEDAD ANONIMA DE ASISTENCIA MEDICA Y CIENTIFICA | J149: 1 | K149: $ | L149: 55900.83 | M149: 0 | N149: 0 | O149: 0 | P149: 11739.17 | Q149: 67640
A150: 09/10/2024 | B150: 1 - Factura A | C150: 7 | D150: 2181 | F150: 74418934233149 | G150: CUIT | H150: 30608716390 | I150: OBRA SOCIAL DEL PERSONAL DE LAS TELECOMUNICACIONES DE LA REPUBLICA ARGENTINA | J150: 1 | K150: $ | L150: 7500 | M150: 0 | N150: 0 | O150: 0 | P150: 1575 | Q150: 9075
A151: 09/10/2024 | B151: 1 - Factura A | C151: 7 | D151: 2182 | F151: 74418935073436 | G151: CUIT | H151: 30608716390 | I151: OBRA SOCIAL DEL PERSONAL DE LAS TELECOMUNICACIONES DE LA REPUBLICA ARGENTINA | J151: 1 | K151: $ | L151: 7500 | M151: 0 | N151: 0 | O151: 0 | P151: 1575 | Q151: 9075
A152: 09/10/2024 | B152: 1 - Factura A | C152: 7 | D152: 2183 | F152: 74418938153273 | G152: CUIT | H152: 30608716390 | I152: OBRA SOCIAL DEL PERSONAL DE LAS TELECOMUNICACIONES DE LA REPUBLICA ARGENTINA | J152: 1 | K152: $ | L152: 6384.3 | M152: 0 | N152: 0 | O152: 0 | P152: 1340.7 | Q152: 7725
A153: 09/10/2024 | B153: 1 - Factura A | C153: 7 | D153: 2184 | F153: 74418952953435 | G153: CUIT | H153: 30608716390 | I153: OBRA SOCIAL DEL PERSONAL DE LAS TELECOMUNICACIONES DE LA REPUBLICA ARGENTINA | J153: 1 | K153: $ | L153: 15000 | M153: 0 | N153: 0 | O153: 0 | P153: 3150 | Q153: 18150
A154: 09/10/2024 | B154: 1 - Factura A | C154: 7 | D154: 2185 | F154: 74418953720163 | G154: CUIT | H154: 30608716390 | I154: OBRA SOCIAL DEL PERSONAL DE LAS TELECOMUNICACIONES DE LA REPUBLICA ARGENTINA | J154: 1 | K154: $ | L154: 15000 | M154: 0 | N154: 0 | O154: 0 | P154: 3150 | Q154: 18150
A155: 09/10/2024 | B155: 1 - Factura A | C155: 7 | D155: 2186 | F155: 74418954104801 | G155: CUIT | H155: 30608716390 | I155: OBRA SOCIAL DEL PERSONAL DE LAS TELECOMUNICACIONES DE LA REPUBLICA ARGENTINA | J155: 1 | K155: $ | L155: 36652.89 | M155: 0 | N155: 0 | O155: 0 | P155: 7697.11 | Q155: 44350
...

Sheet Resumen Ventas 10
A1: Totales por Tipo de Comprobante - AFIP
B2: Base | C2: IVA | D2: Otros Imp. | E2: Total Compr.
A3: (FCE) A | B3: 24190611 | C3: =+B3*0.21 -> 5080028.4 | E3: =SUM(B3:D3) -> 29270640
A4: NC FCE A | B4: 0 | C4: =+B4*0.21 -> 0 | E4: =SUM(B4:D4) -> 0
A5: FACTURAS A | B5: 9798831 | C5: =+B5*0.21 -> 2057754.5 | E5: =SUM(B5:D5) -> 11856586
A6: NC A | B6: -513274.69 | C6: =+B6*0.21 -> -107787.68 | E6: =SUM(B6:D6) -> -621062.37
A7: FACTURAS B | B7: 24269479 | C7: =+B7*0.21 -> 5096590.6 | E7: =SUM(B7:D7) -> 29366070
A8: NC B | B8: -239128.26 | C8: =+B8*0.21 -> -50216.935 | E8: =SUM(B8:D8) -> -289345.19
B9: =SUM(B3:B8) -> 57506519 | C9: =SUM(C3:C8) -> 12076369 | D9: 0 | E9: =SUM(E3:E8) -> 69582887
