Workbook

Sheet Lista_CUIT
A1: CUIT | B1: RAZON SOCIAL | C1: Tipo de Gasto | D1: PROVINCIA
A2: 30575019524 | B2: 100000 LAMPARAS SRL | G2: Mercaderia
A3: 30709829730 | B3: 4KRC SA | C3: Mantenimiento | G3: Servicios Gas, Luz, etc.
A4: 30715223704 | B4: 5 CEPAS S.R.L. | C4: MERCADERIA | G4: Gastos catering
A5: 30714869937 | B5: 60 LIBRAS SRL | G5: Combustibe
A6: 30692212130 | B6: A R C CONSTRUCCIONES S.A. | G6: Gastos Varios
A7: 30687722007 | B7: A. RUSSONIELLO SA | C7: SERVICIOS | G7: Gastos seguridad
A8: 30503874497 | B8: A.M. PESCIO S.C.A | C8: Mercaderia | G8: Librería
A9: 30702017498 | B9: ABBS POINT DESING S.A. | G9: Gastos mantenimiento
A10: 20182999661 | B10: ABEL JAVIER KLAINER | C10: Mercaderia | G10: Gastos comercializacion
A11: 30652000076 | B11: ABELSON SA | C11: Mercaderia | G11: Alquiler
A12: 30690536079 | B12: ACCESOR SRL | C12: Gastos Varios | G12: Honorarios contables
A13: 30515585415 | B13: ACEROSALFA SA | C13: Mercaderia | G13: Gastos administrativos
A14: 33711942659 | B14: ACLOS ASOC. CIVIL PARA LA LONG | C14: Mercaderia | G14: Seguro
A15: 30715243349 | B15: ADSE S.A | G15: Extracto
A16: 20174004146 | B16: ADUEARDO FRANCISCO NARDOMARINO | C16: Mercaderia | G16: Flete
A17: 30708555548 | B17: AGH S.A | C17: Mercaderia | G17: Honorarios Legales
A18: 30708263342 | B18: AGRACO S.A | C18: MERCADERIA | G18: Insumo
A19: 30709565075 | B19: AGUA Y SANEAMIENTOS ARG SA | C19: SERVICIOS | G19: Muebles y Utiles
A20: 30500229973 | B20: AKIAN GRAFICA EDITORA SA | C20: Mercaderia | G20: Otros
A21: 30710799241 | B21: ALANAR S.R.L. | G21: Telefonia
A22: 20236101127 | B22: ALEJANDRO DARIO LOPEZ | G22: Alojamiento-Varios
A23: 20291929126 | B23: ALEJANDRO MIGUEL DAUBLER
A24: 30709604887 | B24: ALFABIS SRL. | C24: Mantenimiento
A25: 20083925680 | B25: ALFREDO DANIEL FERNANDEZ | C25: Gastos Varios
A26: 30656038752 | B26: ALFREDO OMAR POTENZA SRL | C26: Mercaderia
A27: 30504563894 | B27: ALI HERMANOS SRL | C27: Mercaderia
A28: 30602699826 | B28: ALKO SRL
A29: 30715190385 | B29: ALL FEDERAL SA.
A30: 23945042079 | B30: ALVARENGA VILLAR LUIS F | C30: Gastos Varios
A31: 20040616498 | B31: ALVAREZ MARCELINO
A32: 30710587147 | B32: AMAKOR SA | C32: SERVICIOS
A33: 30663288497 | B33: AMX ARG SA
A34: 27108310559 | B34: ANA MARIA VALDEZ
A35: 30502375535 | B35: ANAVI S.C.A.
A36: 30709251739 | B36: ANDES LINEAS AEREAS SA
A37: 30709948667 | B37: ANTAGGER SRL | C37: Mercaderia
A38: 30683702060 | B38: ANTARES INDUST. ORTOP SA | C38: Mercaderia
A39: 30715985124 | B39: ANTOLFO S.R.L.
A40: 30714344656 | B40: AQUALAF S.A. | C40: Mercaderia
A41: 30712000372 | B41: AQUÍ MERCEDES SRL | C41: Mercaderia
A42: 30714741167 | B42: ARALIMP S.R.L.
A43: 20927832136 | B43: ARANCIBIA IBACETA CIPRIANO | C43: Gastos Varios
A44: 27135302835 | B44: ARENAS MONICA MARIEL
A45: 27276671109 | B45: AREVALO LORENA ELIZABETH | C45: Mercaderia
A46: 30711597499 | B46: ARGENVODA SA
A47: 30600907553 | B47: ARMAGALLI SA
A48: 30709585262 | B48: ARMY TECHNOLOGIES S.A. | C48: Mantenimiento
A49: 30614941509 | B49: ARREDO
A50: 30560443648 | B50: ARSA ELECTRICIDAD SRL
A51: 30708547790 | B51: ARTELEC ARGENTINA SRL
A52: 30711624402 | B52: ARTES REGIONALES SRL
A53: 20045180620 | B53: ARUGUETE ENRIQUE JORGE | C53: Gastos Varios
A54: 30692175243 | B54: ASAHI MOTORS SA
A55: 30708973501 | B55: ASIAL SRL | C55: Mercaderia
A56: 30590354798 | B56: ASOC. MUTUAL SANCOR SALUD
A57: 30709860840 | B57: AUMECON SA
A58: 30544712833 | B58: AURELIO GUNDIN SA | C58: Mercaderia
A59: 30715031252 | B59: AUTO VENETO S.A.
A60: 30711934754 | B60: AUTOBIZ SA
A61: 30670528592 | B61: AUTOMOTORES FIORASI Y CORRADI
A62: 30574876474 | B62: AUTOP. URBANAS SA
A63: 30677237119 | B63: AUTOPISTAS DEL SOL SA
A64: 30607371799 | B64: AUTOSERVICIO DIARCO SA
A65: 20278462790 | B65: VARAS TOLEDO SEBASTIAN
A66: 30715963872 | B66: MARAKANA SRL
A67: 20083762102 | B67: AVANCE-MAG
A68: 20287830980 | B68: AVILA MARTIN LEONARDO
A69: 30506919009 | B69: AXION ENERGY ARG SA | C69: COMBUSTIBLE
A70: 30535612117 | B70: AYUDA MUT. DEL PERS. DE GENDAR
A71: 33711430879 | B71: BALANZE S.A. | C71: Mercaderia
A72: 20179619483 | B72: BALE JORGE CARLOS
A73: 30711941718 | B73: BALLERINI ATILIO Y SOTO RAUL C | C73: Mercaderia
A74: 30580189411 | B74: BANCO ITAU ARG SA
A75: 30500008454 | B75: BANCO SANTANDER RIO SA | C75: Extracto
A76: 30646362675 | B76: BAUMGARTEN GRAFICA ARG SA
A77: 30712458468 | B77: BEEL SUL S.A. | C77: Gastos Varios
A78: 30714675601 | B78: BELGRANO NEUMATICOS S.A.
A79: 30568222187 | B79: BELLINI HNOS SRL
A80: 27248212646 | B80: BELLOMO MARIA MERCEDES
A81: 27115740666 | B81: BEN Y BEN
A82: 27129411010 | B82: BENITEZ ANA MARIA
A83: 23301961944 | B83: BERGOC CECILIA ANDREA
A84: 30710067763 | B84: BI POOL S.R.L.
A85: 30712387315 | B85: BIALA SRL | C85: Gastos Varios
A86: 30715210637 | B86: BIAUS SRL | C86: Mercaderia
A87: 30712230459 | B87: BIOMAX INSUMOS MEDICOS | C87: Mercaderia
A88: 30697652694 | B88: BISTRO SA
A89: 30712476857 | B89: BODEGA DON BOSCO | C89: MERCADERIA
A90: 30708270462 | B90: body group feliz srl
A91: 23253931159 | B91: BOECHI JUAN
A92: 30655186693 | B92: BOSAN SA
A93: 20389908569 | B93: BOTINDARI JUAN IGNACIO | C93: Honorarios Contables
A94: 30515676178 | B94: BROGAS SA | C94: Mercaderia
A95: 33711821649 | B95: BRUBEN DUDAMERICANA
A96: 30715122657 | B96: BRUNETTE SRL
A97: 30715549871 | B97: BSMS SRL
A98: 20085280512 | B98: BULONERA HURLINGHAM | C98: Mercaderia
A99: 30595442369 | B99: BULONERA MATADEROS SRL | C99: Mercaderia
A100: 27289847141 | B100: BUSACCA PAOLA EDITH | C100: LIBRERÍA
...

Sheet Abr-24
B1: LIBRO IVA COMPRAS | G1: CORITEC S. R. L. | N1: 45017
B3: TOTAL COMPRAS NETAS | G3: TOTAL CREDITO FISCAL | J3: TOTAL VENTAS NETAS | M3: TOTAL DEBITO FISCAL | P3: RESULTADO
B4: =SUM('Abr-24'!$H$37)+'Abr-24'!$G$54 -> 5732005.1 | G4: ='Abr-24'!$I$37+'Abr-24'!$J$37+'Abr-24'!$K$37+I55 -> 1194453.8 | J4: ='Abr-24'!$H$88+'Abr-24'!$H$98 -> 49918615 | M4: ='Abr-24'!$I$88+'Abr-24'!$J$88+'Abr-24'!$I$98+'Abr-24'!$J$98 -> 5303236.8 | P4: =G4-M4 -> -4108783
B8: FECHA | C8: TIPO | D8: PTO VTA | E8: NRO. CPTE | F8: CUIT | G8: RAZON SOCIAL | H8: NETO GRAVADO | I8: IVA 21 % | J8: IVA 27% | K8: IVA 10,5% | L8: PERC. IVA | M8: PERC IIBB BS AS | N8: PERC. IIBB CABA | O8: Otros / No Grav. | P8: TOTAL | Q8: Tipo de Gasto | R8: Provincia
B9: 45412 | C9: 1 | D9: 6 | E9: 14602 | F9: 30707756434 | G9: =IFERROR(IF('Abr-24'!$F9="","-",VLOOKUP('Abr-24'!$F9,Lista_CUIT!$A$1:$D$2241,2,0)),"CUIT NO CARGADO") -> SERVICIO INTEGRAL DE LIMPIEZA SRL | H9: 204000 | I9: ='Abr-24'!$H9*0.21 -> 42840 | P9: =SUM('Abr-24'!$H9:$O9) -> 246840 | Q9: =IFERROR(IF('Abr-24'!$F9="","-",VLOOKUP('Abr-24'!$F9,Lista_CUIT!$A$1:$D$2241,3,0)),"CUIT NO CARGADO") -> Mantenimiento | R9: =IFERROR(IF('Abr-24'!$F9="","-",VLOOKUP('Abr-24'!$F9,Lista_CUIT!$A$1:$D$2241,4,0)),"CUIT NO CARGADO") -> 0
B10: 45400 | C10: 1 | D10: 2 | E10: 197 | F10: 20125142851 | G10: =IFERROR(IF('Abr-24'!$F10="","-",VLOOKUP('Abr-24'!$F10,Lista_CUIT!$A$1:$D$2241,2,0)),"CUIT NO CARGADO") -> FEDERICI NICOLAS JOSE | H10: 319464.15 | I10: ='Abr-24'!$H10*0.21 -> 67087.471 | P10: =SUM('Abr-24'!$H10:$O10) -> 386551.62 | Q10: =IFERROR(IF('Abr-24'!$F10="","-",VLOOKUP('Abr-24'!$F10,Lista_CUIT!$A$1:$D$2241,3,0)),"CUIT NO CARGADO") -> INSUMO | R10: =IFERROR(IF('Abr-24'!$F10="","-",VLOOKUP('Abr-24'!$F10,Lista_CUIT!$A$1:$D$2241,4,0)),"CUIT NO CARGADO") -> 0
B11: 45400 | C11: 1 | D11: 2 | E11: 196 | F11: 20125142851 | G11: =IFERROR(IF('Abr-24'!$F11="","-",VLOOKUP('Abr-24'!$F11,Lista_CUIT!$A$1:$D$2241,2,0)),"CUIT NO CARGADO") -> FEDERICI NICOLAS JOSE | H11: 1234920.6 | I11: ='Abr-24'!$H11*0.21 -> 259333.33 | P11: =SUM('Abr-24'!$H11:$O11) -> 1494253.9 | Q11: =IFERROR(IF('Abr-24'!$F11="","-",VLOOKUP('Abr-24'!$F11,Lista_CUIT!$A$1:$D$2241,3,0)),"CUIT NO CARGADO") -> INSUMO | R11: =IFERROR(IF('Abr-24'!$F11="","-",VLOOKUP('Abr-24'!$F11,Lista_CUIT!$A$1:$D$2241,4,0)),"CUIT NO CARGADO") -> 0
B12: 45393 | C12: 1 | D12: 2 | E12: 2710 | F12: 30709131733 | G12: =IFERROR(IF('Abr-24'!$F12="","-",VLOOKUP('Abr-24'!$F12,Lista_CUIT!$A$1:$D$2241,2,0)),"CUIT NO CARGADO") -> DIGAS SRL | H12: 2758040 | I12: ='Abr-24'!$H12*0.21 -> 579188.4 | P12: =SUM('Abr-24'!$H12:$O12) -> 3337228.4 | Q12: =IFERROR(IF('Abr-24'!$F12="","-",VLOOKUP('Abr-24'!$F12,Lista_CUIT!$A$1:$D$2241,3,0)),"CUIT NO CARGADO") -> INSUMO | R12: =IFERROR(IF('Abr-24'!$F12="","-",VLOOKUP('Abr-24'!$F12,Lista_CUIT!$A$1:$D$2241,4,0)),"CUIT NO CARGADO") -> 0
B13: 45394 | C13: 1 | D13: 2 | E13: 686 | F13: 30718019814 | G13: =IFERROR(IF('Abr-24'!$F13="","-",VLOOKUP('Abr-24'!$F13,Lista_CUIT!$A$1:$D$2241,2,0)),"CUIT NO CARGADO") -> ALDO MOVILE S. CAP I SECC IV | H13: 28224.78 | I13: ='Abr-24'!$H13*0.21 -> 5927.2038 | P13: =SUM('Abr-24'!$H13:$O13) -> 34151.984 | Q13: =IFERROR(IF('Abr-24'!$F13="","-",VLOOKUP('Abr-24'!$F13,Lista_CUIT!$A$1:$D$2241,3,0)),"CUIT NO CARGADO") -> INSUMO | R13: =IFERROR(IF('Abr-24'!$F13="","-",VLOOKUP('Abr-24'!$F13,Lista_CUIT!$A$1:$D$2241,4,0)),"CUIT NO CARGADO") -> 0
B14: 45383 | C14: 1 | D14: 3 | E14: 223848 | F14: 30707135596 | G14: =IFERROR(IF('Abr-24'!$F14="","-",VLOOKUP('Abr-24'!$F14,Lista_CUIT!$A$1:$D$2241,2,0)),"CUIT NO CARGADO") -> CITILAN ARGENTINA S.A. | H14: 15510 | I14: ='Abr-24'!$H14*0.21 -> 3257.1 | P14: =SUM('Abr-24'!$H14:$O14) -> 18767.1 | Q14: =IFERROR(IF('Abr-24'!$F14="","-",VLOOKUP('Abr-24'!$F14,Lista_CUIT!$A$1:$D$2241,3,0)),"CUIT NO CARGADO") -> Telefonia | R14: =IFERROR(IF('Abr-24'!$F14="","-",VLOOKUP('Abr-24'!$F14,Lista_CUIT!$A$1:$D$2241,4,0)),"CUIT NO CARGADO") -> 0
B15: 45383 | C15: 1 | D15: 3 | E15: 744 | F15: 30715402765 | G15: =IFERROR(IF('Abr-24'!$F15="","-",VLOOKUP('Abr-24'!$F15,Lista_CUIT!$A$1:$D$2241,2,0)),"CUIT NO CARGADO") -> RIO 265 S.R.L. | H15: 43801.66 | I15: ='Abr-24'!$H15*0.21 -> 9198.3486 | P15: =SUM('Abr-24'!$H15:$O15) -> 53000.009 | Q15: =IFERROR(IF('Abr-24'!$F15="","-",VLOOKUP('Abr-24'!$F15,Lista_CUIT!$A$1:$D$2241,3,0)),"CUIT NO CARGADO") -> GASTOS VARIOS | R15: =IFERROR(IF('Abr-24'!$F15="","-",VLOOKUP('Abr-24'!$F15,Lista_CUIT!$A$1:$D$2241,4,0)),"CUIT NO CARGADO") -> 0
B16: 45391 | C16: 1 | D16: 1 | E16: 1126 | F16: 30717763692 | G16: =IFERROR(IF('Abr-24'!$F16="","-",VLOOKUP('Abr-24'!$F16,Lista_CUIT!$A$1:$D$2241,2,0)),"CUIT NO CARGADO") -> IGNISMOTORREDUCTORES S. A. | H16: 38016.53 | I16: ='Abr-24'!$H16*0.21 -> 7983.4713 | P16: =SUM('Abr-24'!$H16:$O16) -> 46000.001 | Q16: =IFERROR(IF('Abr-24'!$F16="","-",VLOOKUP('Abr-24'!$F16,Lista_CUIT!$A$1:$D$2241,3,0)),"CUIT NO CARGADO") -> INSUMO | R16: =IFERROR(IF('Abr-24'!$F16="","-",VLOOKUP('Abr-24'!$F16,Lista_CUIT!$A$1:$D$2241,4,0)),"CUIT NO CARGADO") -> 0
B17: 45390 | C17: 1 | D17: 3 | E17: 308 | F17: 20921575743 | G17: =IFERROR(IF('Abr-24'!$F17="","-",VLOOKUP('Abr-24'!$F17,Lista_CUIT!$A$1:$D$2241,2,0)),"CUIT NO CARGADO") -> RIOS GOMEZ JOSE ANTONIO | H17: 447500 | I17: ='Abr-24'!$H17*0.21 -> 93975 | P17: =SUM('Abr-24'!$H17:$O17) -> 541475 | Q17: =IFERROR(IF('Abr-24'!$F17="","-",VLOOKUP('Abr-24'!$F17,Lista_CUIT!$A$1:$D$2241,3,0)),"CUIT NO CARGADO") -> Papeleria | R17: =IFERROR(IF('Abr-24'!$F17="","-",VLOOKUP('Abr-24'!$F17,Lista_CUIT!$A$1:$D$2241,4,0)),"CUIT NO CARGADO") -> 0
B18: 45409 | C18: 1 | D18: 31 | E18: 41586 | F18: 30715209833 | G18: =IFERROR(IF('Abr-24'!$F18="","-",VLOOKUP('Abr-24'!$F18,Lista_CUIT!$A$1:$D$2241,2,0)),"CUIT NO CARGADO") -> GIFEL SRL | H18: 52429.75 | I18: ='Abr-24'!$H18*0.21 -> 11010.247 | P18: =SUM('Abr-24'!$H18:$O18) -> 63439.997 | Q18: =IFERROR(IF('Abr-24'!$F18="","-",VLOOKUP('Abr-24'!$F18,Lista_CUIT!$A$1:$D$2241,3,0)),"CUIT NO CARGADO") -> Gastos Oficina | R18: =IFERROR(IF('Abr-24'!$F18="","-",VLOOKUP('Abr-24'!$F18,Lista_CUIT!$A$1:$D$2241,4,0)),"CUIT NO CARGADO") -> 0
B19: 45406 | C19: 1 | D19: 31 | E19: 41286 | F19: 30715209833 | G19: =IFERROR(IF('Abr-24'!$F19="","-",VLOOKUP('Abr-24'!$F19,Lista_CUIT!$A$1:$D$2241,2,0)),"CUIT NO CARGADO") -> GIFEL SRL | H19: 43561.98 | I19: ='Abr-24'!$H19*0.21 -> 9148.0158 | P19: =SUM('Abr-24'!$H19:$O19) -> 52709.996 | Q19: =IFERROR(IF('Abr-24'!$F19="","-",VLOOKUP('Abr-24'!$F19,Lista_CUIT!$A$1:$D$2241,3,0)),"CUIT NO CARGADO") -> Gastos Oficina | R19: =IFERROR(IF('Abr-24'!$F19="","-",VLOOKUP('Abr-24'!$F19,Lista_CUIT!$A$1:$D$2241,4,0)),"CUIT NO CARGADO") -> 0
B20: 45404 | C20: 1 | D20: 4 | E20: 164 | F20: 30715863916 | G20: =IFERROR(IF('Abr-24'!$F20="","-",VLOOKUP('Abr-24'!$F20,Lista_CUIT!$A$1:$D$2241,2,0)),"CUIT NO CARGADO") -> BULONERA SUR SA | H20: 5173.55 | I20: ='Abr-24'!$H20*0.21 -> 1086.4455 | P20: =SUM('Abr-24'!$H20:$O20) -> 6259.9955 | Q20: =IFERROR(IF('Abr-24'!$F20="","-",VLOOKUP('Abr-24'!$F20,Lista_CUIT!$A$1:$D$2241,3,0)),"CUIT NO CARGADO") -> Ferreteria | R20: =IFERROR(IF('Abr-24'!$F20="","-",VLOOKUP('Abr-24'!$F20,Lista_CUIT!$A$1:$D$2241,4,0)),"CUIT NO CARGADO") -> 0
... B26: 45408 | C26: 1 | D26: 5 | E26: 47 | F26: 27224574679 | G26: =IFERROR(IF('Abr-24'!$F26="","-",VLOOKUP('Abr-24'!$F26,Lista_CUIT!$A$1:$D$2241,2,0)),"CUIT NO CARGADO") -> FERNANDEZ MARCELA ELIZABETH | H26: 18081.6 | I26: ='Abr-24'!$H26*0.21 -> 3797.136 | P26: =SUM('Abr-24'!$H26:$O26) -> 21878.736 | Q26: =IFERROR(IF('Abr-24'!$F26="","-",VLOOKUP('Abr-24'!$F26,Lista_CUIT!$A$1:$D$2241,3,0)),"CUIT NO CARGADO") -> GASTOS VARIOS | R26: =IFERROR(IF('Abr-24'!$F26="","-",VLOOKUP('Abr-24'!$F26,Lista_CUIT!$A$1:$D$2241,4,0)),"CUIT NO CARGADO") -> 0
B27: 02/04/2024 | C27: 1 | D27: 30 | E27: 128138 | F27: 30695056342 | G27: =IFERROR(IF('Abr-24'!$F27="","-",VLOOKUP('Abr-24'!$F27,Lista_CUIT!$A$1:$D$2241,2,0)),"CUIT NO CARGADO") -> AVENIDA MAIPU 4199 S C S | H27: 18238.84 | I27: ='Abr-24'!$H27*0.21 -> 3830.1564 | P27: =SUM('Abr-24'!$H27:$O27) -> 22068.996 | Q27: =IFERROR(IF('Abr-24'!$F27="","-",VLOOKUP('Abr-24'!$F27,Lista_CUIT!$A$1:$D$2241,3,0)),"CUIT NO CARGADO") -> Seg e Higiene | R27: =IFERROR(IF('Abr-24'!$F27="","-",VLOOKUP('Abr-24'!$F27,Lista_CUIT!$A$1:$D$2241,4,0)),"CUIT NO CARGADO") -> 0
B28: 07/04/2024 | C28: 1 | D28: 6 | E28: 2292 | F28: 27236006250 | G28: =IFERROR(IF('Abr-24'!$F28="","-",VLOOKUP('Abr-24'!$F28,Lista_CUIT!$A$1:$D$2241,2,0)),"CUIT NO CARGADO") -> LOKER MARISA TERESITA | H28: 8047.52 | I28: ='Abr-24'!$H28*0.21 -> 1689.9792 | P28: =SUM('Abr-24'!$H28:$O28) -> 9737.4992 | Q28: =IFERROR(IF('Abr-24'!$F28="","-",VLOOKUP('Abr-24'!$F28,Lista_CUIT!$A$1:$D$2241,3,0)),"CUIT NO CARGADO") -> GASTOS VARIOS | R28: =IFERROR(IF('Abr-24'!$F28="","-",VLOOKUP('Abr-24'!$F28,Lista_CUIT!$A$1:$D$2241,4,0)),"CUIT NO CARGADO") -> 0
B29: 08/04/2024 | C29: 1 | D29: 700 | E29: 643864 | F29: 30580111315 | G29: =IFERROR(IF('Abr-24'!$F29="","-",VLOOKUP('Abr-24'!$F29,Lista_CUIT!$A$1:$D$2241,2,0)),"CUIT NO CARGADO") -> DHL EXPRESS (ARGENTINA) S.A. | H29: 13222.5 | I29: ='Abr-24'!$H29*0.21 -> 2776.725 | O29: 545154.86 | P29: =SUM('Abr-24'!$H29:$O29) -> 561154.08 | Q29: =IFERROR(IF('Abr-24'!$F29="","-",VLOOKUP('Abr-24'!$F29,Lista_CUIT!$A$1:$D$2241,3,0)),"CUIT NO CARGADO") -> Gastos Importacion | R29: =IFERROR(IF('Abr-24'!$F29="","-",VLOOKUP('Abr-24'!$F29,Lista_CUIT!$A$1:$D$2241,4,0)),"CUIT NO CARGADO") -> 0
B30: 11/04/2024 | C30: 1 | D30: 2466 | E30: 636157 | F30: 30678814357 | G30: =IFERROR(IF('Abr-24'!$F30="","-",VLOOKUP('Abr-24'!$F30,Lista_CUIT!$A$1:$D$2241,2,0)),"CUIT NO CARGADO") -> TELEFONICA MOVILES ARG | H30: 17540 | J30: ='Abr-24'!$H30*0.27 -> 4735.8 | L30: 526.2 | O30: 923.15 | P30: =SUM('Abr-24'!$H30:$O30) -> 23725.15 | Q30: =IFERROR(IF('Abr-24'!$F30="","-",VLOOKUP('Abr-24'!$F30,Lista_CUIT!$A$1:$D$2241,3,0)),"CUIT NO CARGADO") -> Telefonia | R30: =IFERROR(IF('Abr-24'!$F30="","-",VLOOKUP('Abr-24'!$F30,Lista_CUIT!$A$1:$D$2241,4,0)),"CUIT NO CARGADO") -> 0
B31: 22/04/2024 | C31: 1 | D31: 3 | E31: 334487 | F31: 33643358749 | G31: =IFERROR(IF('Abr-24'!$F31="","-",VLOOKUP('Abr-24'!$F31,Lista_CUIT!$A$1:$D$2241,2,0)),"CUIT NO CARGADO") -> POLYTECH S A | H31: 52487.78 | K31: ='Abr-24'!$H31*0.105 -> 5511.2169 | P31: =SUM('Abr-24'!$H31:$O31) -> 57998.997 | Q31: =IFERROR(IF('Abr-24'!$F31="","-",VLOOKUP('Abr-24'!$F31,Lista_CUIT!$A$1:$D$2241,3,0)),"CUIT NO CARGADO") -> Servicios Informaticos | R31: =IFERROR(IF('Abr-24'!$F31="","-",VLOOKUP('Abr-24'!$F31,Lista_CUIT!$A$1:$D$2241,4,0)),"CUIT NO CARGADO") -> 0
B32: 24/04/2024 | C32: 1 | D32: 3 | E32: 334743 | F32: 33643358749 | G32: =IFERROR(IF('Abr-24'!$F32="","-",VLOOKUP('Abr-24'!$F32,Lista_CUIT!$A$1:$D$2241,2,0)),"CUIT NO CARGADO") -> POLYTECH S A | H32: 45794.57 | K32: ='Abr-24'!$H32*0.105 -> 4808.4298 | P32: =SUM('Abr-24'!$H32:$O32) -> 50603 | Q32: =IFERROR(IF('Abr-24'!$F32="","-",VLOOKUP('Abr-24'!$F32,Lista_CUIT!$A$1:$D$2241,3,0)),"CUIT NO CARGADO") -> Servicios Informaticos | R32: =IFERROR(IF('Abr-24'!$F32="","-",VLOOKUP('Abr-24'!$F32,Lista_CUIT!$A$1:$D$2241,4,0)),"CUIT NO CARGADO") -> 0
B33: 29/04/2024 | C33: 1 | D33: 106 | E33: 729129 | F33: 30594494187 | G33: =IFERROR(IF('Abr-24'!$F33="","-",VLOOKUP('Abr-24'!$F33,Lista_CUIT!$A$1:$D$2241,2,0)),"CUIT NO CARGADO") -> FEDERAL EXPRESS CORPORATION | H33: 0 | I33: ='Abr-24'!$H33*0.21 -> 0 | P33: =SUM('Abr-24'!$H33:$O33) -> 0 | Q33: =IFERROR(IF('Abr-24'!$F33="","-",VLOOKUP('Abr-24'!$F33,Lista_CUIT!$A$1:$D$2241,3,0)),"CUIT NO CARGADO") -> Gastos Importacion | R33: =IFERROR(IF('Abr-24'!$F33="","-",VLOOKUP('Abr-24'!$F33,Lista_CUIT!$A$1:$D$2241,4,0)),"CUIT NO CARGADO") -> 0
B34: 29/04/2024 | C34: 1 | D34: 3 | E34: 2022 | F34: 20401319930 | G34: =IFERROR(IF('Abr-24'!$F34="","-",VLOOKUP('Abr-24'!$F34,Lista_CUIT!$A$1:$D$2241,2,0)),"CUIT NO CARGADO") -> SANTORO FRANCO TOMAS | H34: 23243.8 | I34: ='Abr-24'!$H34*0.21 -> 4881.198 | P34: =SUM('Abr-24'!$H34:$O34) -> 28124.998 | Q34: =IFERROR(IF('Abr-24'!$F34="","-",VLOOKUP('Abr-24'!$F34,Lista_CUIT!$A$1:$D$2241,3,0)),"CUIT NO CARGADO") -> Catering | R34: =IFERROR(IF('Abr-24'!$F34="","-",VLOOKUP('Abr-24'!$F34,Lista_CUIT!$A$1:$D$2241,4,0)),"CUIT NO CARGADO") -> 0
B35: 45411 | C35: 1 | D35: 700 | E35: 651894 | F35: 30580111315 | G35: =IFERROR(IF('Abr-24'!$F35="","-",VLOOKUP('Abr-24'!$F35,Lista_CUIT!$A$1:$D$2241,2,0)),"CUIT NO CARGADO") -> DHL EXPRESS (ARGENTINA) S.A. | I35: ='Abr-24'!$H35*0.21 -> 0 | O35: 274547.4 | P35: =SUM('Abr-24'!$H35:$O35) -> 274547.4 | Q35: =IFERROR(IF('Abr-24'!$F35="","-",VLOOKUP('Abr-24'!$F35,Lista_CUIT!$A$1:$D$2241,3,0)),"CUIT NO CARGADO") -> Gastos Importacion | R35: =IFERROR(IF('Abr-24'!$F35="","-",VLOOKUP('Abr-24'!$F35,Lista_CUIT!$A$1:$D$2241,4,0)),"CUIT NO CARGADO") -> 0
G36: =IFERROR(IF('Abr-24'!$F36="","-",VLOOKUP('Abr-24'!$F36,Lista_CUIT!$A$1:$D$2241,2,0)),"CUIT NO CARGADO") -> - | I36: ='Abr-24'!$H36*0.21 -> 0 | P36: =SUM('Abr-24'!$H36:$O36) -> 0 | Q36: =IFERROR(IF('Abr-24'!$F36="","-",VLOOKUP('Abr-24'!$F36,Lista_CUIT!$A$1:$D$2241,3,0)),"CUIT NO CARGADO") -> - | R36: =IFERROR(IF('Abr-24'!$F36="","-",VLOOKUP('Abr-24'!$F36,Lista_CUIT!$A$1:$D$2241,4,0)),"CUIT NO CARGADO") -> -
B37: Total | H37: =SUBTOTAL(109,'Abr-24'!$H$9:$H$36) -> 5488346.6 | I37: =SUBTOTAL(109,'Abr-24'!$I$9:$I$36) -> 1128230.1 | J37: =SUBTOTAL(109,'Abr-24'!$J$9:$J$36) -> 4735.8 | K37: =SUBTOTAL(109,'Abr-24'!$K$9:$K$36) -> 10319.647 | L37: =SUBTOTAL(109,'Abr-24'!$L$9:$L$36) -> 526.2 | M37: =SUBTOTAL(109,'Abr-24'!$M$9:$M$36) -> 0 | N37: =SUBTOTAL(109,'Abr-24'!$N$9:$N$36) -> 0 | O37: =SUBTOTAL(109,'Abr-24'!$O$9:$O$36) -> 820625.41 | P37: =SUBTOTAL(109,'Abr-24'!$P$9:$P$36) -> 7452783.7
D42: LIQUIDACION EXTRACTOS BANCARIOS-TARJETAS
D43: FECHA | E43: NRO CPTE | F43: BANCO | G43: NETO | H43: IVA 21% | I43: IVA 10,5% | J43: RET IIBB CABA | K43: PERC IVA | L43: PERC IIBB | M43: total
D44: 45386 | E44: 1070357000 | G44: 8615 | H44: ='Abr-24'!$G44*0.21 -> 1809.15 | J44: 258.45 | M44: ='Abr-24'!$G44+'Abr-24'!$H44+'Abr-24'!$I44+'Abr-24'!$J44+'Abr-24'!$K44 -> 10682.6
D45: 45405 | E45: 825-879664 | F45: BIENES EXPORTADOS | G45: 65400 | H45: ='Abr-24'!$G45*0.21 -> 13734 | J45: 1962 | M45: ='Abr-24'!$G45+'Abr-24'!$H45+'Abr-24'!$I45+'Abr-24'!$J45+'Abr-24'!$K45 -> 81096
D46: 45399 | E46: 825-880947 | F46: BIENES EXPORTADOS | G46: 65137.5 | H46: ='Abr-24'!$G46*0.21 -> 13678.875 | J46: 1954.13 | M46: ='Abr-24'!$G46+'Abr-24'!$H46+'Abr-24'!$I46+'Abr-24'!$J46+'Abr-24'!$K46 -> 80770.505
D47: 45393 | E47: 980902000 | F47: COMISION POR AFECTACION SAOFE | G47: 21637.5 | H47: ='Abr-24'!$G47*0.21 -> 4543.875 | J47: 649.13 | M47: ='Abr-24'!$G47+'Abr-24'!$H47+'Abr-24'!$I47+'Abr-24'!$J47+'Abr-24'!$K47 -> 26830.505
D48: 45394 | E48: 980927000 | F48: COMISION POR AFECTACION SAOFE | G48: 21662.5 | H48: ='Abr-24'!$G48*0.21 -> 4549.125 | J48: 649.88 | M48: ='Abr-24'!$G48+'Abr-24'!$H48+'Abr-24'!$I48+'Abr-24'!$J48+'Abr-24'!$K48 -> 26861.505
D49: 45406 | E49: 1073108000 | F49: SEGUIMIENTO PERMISOS DE EMBARQUE | G49: 21825 | H49: ='Abr-24'!$G49*0.21 -> 4583.25 | J49: 654.75 | M49: ='Abr-24'!$G49+'Abr-24'!$H49+'Abr-24'!$I49+'Abr-24'!$J49+'Abr-24'!$K49 -> 27063
F50: BANCO CREDICOOP | G50: 38981 | H50: ='Abr-24'!$G50*0.21 -> 8186.01 | K50: 1036.13 | M50: ='Abr-24'!$G50+'Abr-24'!$H50+'Abr-24'!$I50+'Abr-24'!$J50+'Abr-24'!$K50 -> 48203.14
F51: BANCO CREDICOOP | G51: 400 | H51: ='Abr-24'!$G51*0.21 -> 84 | J51: 53.74 | M51: ='Abr-24'!$G51+'Abr-24'!$H51+'Abr-24'!$I51+'Abr-24'!$J51+'Abr-24'!$K51 -> 537.74
H52: ='Abr-24'!$G52*0.21 -> 0 | M52: ='Abr-24'!$G52+'Abr-24'!$H52+'Abr-24'!$I52+'Abr-24'!$J52+'Abr-24'!$K52 -> 0
H53: ='Abr-24'!$G53*0.21 -> 0 | M53: ='Abr-24'!$G53+'Abr-24'!$H53+'Abr-24'!$I53+'Abr-24'!$J53+'Abr-24'!$K53 -> 0
D54: Total | G54: =SUBTOTAL(109,'Abr-24'!$G$44:$G$53) -> 243658.5 | H54: =SUBTOTAL(109,'Abr-24'!$H$44:$H$53) -> 51168.285 | I54: =SUBTOTAL(109,'Abr-24'!$I$44:$I$53) -> 0 | J54: =SUBTOTAL(109,'Abr-24'!$J$44:$J$53) -> 6182.08 | K54: =SUBTOTAL(109,'Abr-24'!$K$44:$K$53) -> 1036.13 | L54: =SUBTOTAL(109,'Abr-24'!$L$44:$L$53) -> 0
H55: TOTAL: | I55: =SUM('Abr-24'!$H$54:$I$54) -> 51168.285 | J55: > ya esta sumado al total
D58: FACTURAS C
D59: FECHA | E59: PTO VTA | F59: FC Nº | G59: CUIT | H59: RAZON SOCIAL | I59: TOTAL | J59: TIPO DE GASTO | K59: Provincia
D60: 45397 | E60: 2 | F60: 237 | G60: 27173820866 | H60: =IFERROR(IF('Abr-24'!$G60="","-",VLOOKUP('Abr-24'!$G60,Lista_CUIT!$A$1:$D$2241,2,0)),"CUIT NO CARGADO") -> FREIER SANDRA DANIELA | I60: 500000 | J60: =IFERROR(IF('Abr-24'!$G60="","-",VLOOKUP('Abr-24'!$G60,Lista_CUIT!$A$1:$D$2241,3,0)),"CUIT NO CARGADO") -> Honorarios Prof | K60: =IFERROR(IF('Abr-24'!$G60="","-",VLOOKUP('Abr-24'!$G60,Lista_CUIT!$A$1:$D$2241,4,0)),"CUIT NO CARGADO") -> 0
D61: 45387 | E61: 2 | F61: 2 | G61: 23118167279 | H61: =IFERROR(IF('Abr-24'!$G61="","-",VLOOKUP('Abr-24'!$G61,Lista_CUIT!$A$1:$D$2241,2,0)),"CUIT NO CARGADO") -> ABELEDO ENRIQUE JUAN | I61: 780000 | J61: =IFERROR(IF('Abr-24'!$G61="","-",VLOOKUP('Abr-24'!$G61,Lista_CUIT!$A$1:$D$2241,3,0)),"CUIT NO CARGADO") -> Honorarios Admin | K61: =IFERROR(IF('Abr-24'!$G61="","-",VLOOKUP('Abr-24'!$G61,Lista_CUIT!$A$1:$D$2241,4,0)),"CUIT NO CARGADO") -> 0
D62: 45385 | E62: 1 | F62: 24 | G62: 27387896150 | H62: =IFERROR(IF('Abr-24'!$G62="","-",VLOOKUP('Abr-24'!$G62,Lista_CUIT!$A$1:$D$2241,2,0)),"CUIT NO CARGADO") -> LIPANOVICH MARIA SOL | I62: 750000 | J62: =IFERROR(IF('Abr-24'!$G62="","-",VLOOKUP('Abr-24'!$G62,Lista_CUIT!$A$1:$D$2241,3,0)),"CUIT NO CARGADO") -> consultoria informatica | K62: =IFERROR(IF('Abr-24'!$G62="","-",VLOOKUP('Abr-24'!$G62,Lista_CUIT!$A$1:$D$2241,4,0)),"CUIT NO CARGADO") -> 0
D63: 45385 | E63: 3 | F63: 840 | G63: 20086277523 | H63: =IFERROR(IF('Abr-24'!$G63="","-",VLOOKUP('Abr-24'!$G63,Lista_CUIT!$A$1:$D$2241,2,0)),"CUIT NO CARGADO") -> ESTUDIO BOTINDARI | I63: 210000 | J63: =IFERROR(IF('Abr-24'!$G63="","-",VLOOKUP('Abr-24'!$G63,Lista_CUIT!$A$1:$D$2241,3,0)),"CUIT NO CARGADO") -> Honorarios Contables | K63: =IFERROR(IF('Abr-24'!$G63="","-",VLOOKUP('Abr-24'!$G63,Lista_CUIT!$A$1:$D$2241,4,0)),"CUIT NO CARGADO") -> 0
D64: 45383 | E64: 1 | F64: 35 | G64: 20365938688 | H64: =IFERROR(IF('Abr-24'!$G64="","-",VLOOKUP('Abr-24'!$G64,Lista_CUIT!$A$1:$D$2241,2,0)),"CUIT NO CARGADO") -> LIPANOVICH JUAN CRUZ | I64: 750000 | J64: =IFERROR(IF('Abr-24'!$G64="","-",VLOOKUP('Abr-24'!$G64,Lista_CUIT!$A$1:$D$2241,3,0)),"CUIT NO CARGADO") -> SOFTWARE | K64: =IFERROR(IF('Abr-24'!$G64="","-",VLOOKUP('Abr-24'!$G64,Lista_CUIT!$A$1:$D$2241,4,0)),"CUIT NO CARGADO") -> 0
D65: 45386 | E65: 1 | F65: 367 | G65: 27925308868 | H65: =IFERROR(IF('Abr-24'!$G65="","-",VLOOKUP('Abr-24'!$G65,Lista_CUIT!$A$1:$D$2241,2,0)),"CUIT NO CARGADO") -> LOPEZ MOLINA MARIA | I65: 10000 | J65: =IFERROR(IF('Abr-24'!$G65="","-",VLOOKUP('Abr-24'!$G65,Lista_CUIT!$A$1:$D$2241,3,0)),"CUIT NO CARGADO") -> GASTOS VARIOS | K65: =IFERROR(IF('Abr-24'!$G65="","-",VLOOKUP('Abr-24'!$G65,Lista_CUIT!$A$1:$D$2241,4,0)),"CUIT NO CARGADO") -> 0
D66: 45386 | E66: 1 | F66: 1386356 | G66: 30714928577 | H66: =IFERROR(IF('Abr-24'!$G66="","-",VLOOKUP('Abr-24'!$G66,Lista_CUIT!$A$1:$D$2241,2,0)),"CUIT NO CARGADO") -> SIMPLEX VILLI SA | I66: 4742 | J66: =IFERROR(IF('Abr-24'!$G66="","-",VLOOKUP('Abr-24'!$G66,Lista_CUIT!$A$1:$D$2241,3,0)),"CUIT NO CARGADO") -> Gastos Oficina | K66: =IFERROR(IF('Abr-24'!$G66="","-",VLOOKUP('Abr-24'!$G66,Lista_CUIT!$A$1:$D$2241,4,0)),"CUIT NO CARGADO") -> 0
D67: 45390 | E67: 14 | F67: 377601 | G67: 33709901449 | H67: =IFERROR(IF('Abr-24'!$G67="","-",VLOOKUP('Abr-24'!$G67,Lista_CUIT!$A$1:$D$2241,2,0)),"CUIT NO CARGADO") -> CLOVER TEAM SA | I67: 24994 | J67: =IFERROR(IF('Abr-24'!$G67="","-",VLOOKUP('Abr-24'!$G67,Lista_CUIT!$A$1:$D$2241,3,0)),"CUIT NO CARGADO") -> Ferreteria | K67: =IFERROR(IF('Abr-24'!$G67="","-",VLOOKUP('Abr-24'!$G67,Lista_CUIT!$A$1:$D$2241,4,0)),"CUIT NO CARGADO") -> 0
H68: =IFERROR(IF('Abr-24'!$G68="","-",VLOOKUP('Abr-24'!$G68,Lista_CUIT!$A$1:$D$2241,2,0)),"CUIT NO CARGADO") -> - | J68: =IFERROR(IF('Abr-24'!$G68="","-",VLOOKUP('Abr-24'!$G68,Lista_CUIT!$A$1:$D$2241,3,0)),"CUIT NO CARGADO") -> - | K68: =IFERROR(IF('Abr-24'!$G68="","-",VLOOKUP('Abr-24'!$G68,Lista_CUIT!$A$1:$D$2241,4,0)),"CUIT NO CARGADO") -> -
H69: =IFERROR(IF('Abr-24'!$G69="","-",VLOOKUP('Abr-24'!$G69,Lista_CUIT!$A$1:$D$2241,2,0)),"CUIT NO CARGADO") -> - | J69: =IFERROR(IF('Abr-24'!$G69="","-",VLOOKUP('Abr-24'!$G69,Lista_CUIT!$A$1:$D$2241,3,0)),"CUIT NO CARGADO") -> - | K69: =IFERROR(IF('Abr-24'!$G69="","-",VLOOKUP('Abr-24'!$G69,Lista_CUIT!$A$1:$D$2241,4,0)),"CUIT NO CARGADO") -> -
H70: =IFERROR(IF('Abr-24'!$G70="","-",VLOOKUP('Abr-24'!$G70,Lista_CUIT!$A$1:$D$2241,2,0)),"CUIT NO CARGADO") -> - | J70: =IFERROR(IF('Abr-24'!$G70="","-",VLOOKUP('Abr-24'!$G70,Lista_CUIT!$A$1:$D$2241,3,0)),"CUIT NO CARGADO") -> - | K70: =IFERROR(IF('Abr-24'!$G70="","-",VLOOKUP('Abr-24'!$G70,Lista_CUIT!$A$1:$D$2241,4,0)),"CUIT NO CARGADO") -> -
H71: =IFERROR(IF('Abr-24'!$G71="","-",VLOOKUP('Abr-24'!$G71,Lista_CUIT!$A$1:$D$2241,2,0)),"CUIT NO CARGADO") -> - | J71: =IFERROR(IF('Abr-24'!$G71="","-",VLOOKUP('Abr-24'!$G71,Lista_CUIT!$A$1:$D$2241,3,0)),"CUIT NO CARGADO") -> - | K71: =IFERROR(IF('Abr-24'!$G71="","-",VLOOKUP('Abr-24'!$G71,Lista_CUIT!$A$1:$D$2241,4,0)),"CUIT NO CARGADO") -> -
D72: Total | I72: =SUBTOTAL(109,'Abr-24'!$I$60:$I$71) -> 3029736
B74: LIBRO IVA VENTAS | K74: =N1 -> 45017
B76: VENTAS "A"
B77: FECHA | C77: TIPO | D77: PTO VENTA | E77: Nº FACTURA | F77: CUIT | G77: RAZON SOCIAL | H77: IMPORTE NETO | I77: IVA 21% | J77: IVA 10,5% | K77: EXENTO | L77: TOTAL | M77: Provincia
B78: 05/04/2024 | C78: 1 | D78: 3 | E78: 184 | F78: 30638318470 | G78: =IFERROR(IF('Abr-24'!$F78="","-",VLOOKUP('Abr-24'!$F78,Lista_CUIT!$A$1:$D$2241,2,0)),"CUIT NO CARGADO") -> DELTA COMPRESION S R L | H78: 18976465 | I78: 65248.63 | J78: 1959909.5 | L78: =SUM('Abr-24'!$H78:$K78) -> 21001623
B79: 11/04/2024 | C79: 1 | D79: 3 | E79: 185 | F79: 30628274327 | G79: =IFERROR(IF('Abr-24'!$F79="","-",VLOOKUP('Abr-24'!$F79,Lista_CUIT!$A$1:$D$2241,2,0)),"CUIT NO CARGADO") -> AGIRA S A | H79: 11861145 | J79: 1245420.2 | L79: =SUM('Abr-24'!$H79:$K79) -> 13106565
B80: 17/04/2024 | C80: 1 | D80: 3 | E80: 186 | F80: 30638318470 | G80: =IFERROR(IF('Abr-24'!$F80="","-",VLOOKUP('Abr-24'!$F80,Lista_CUIT!$A$1:$D$2241,2,0)),"CUIT NO CARGADO") -> DELTA COMPRESION S R L | H80: 18803400 | J80: 1974361.4 | L80: =SUM('Abr-24'!$H80:$K80) -> 20777761
B81: 29/04/2024 | C81: 1 | D81: 3 | E81: 187 | F81: 30716041596 | G81: =IFERROR(IF('Abr-24'!$F81="","-",VLOOKUP('Abr-24'!$F81,Lista_CUIT!$A$1:$D$2241,2,0)),"CUIT NO CARGADO") -> EXA COMPRESION S.R.L. | H81: 277605 | I81: ='Abr-24'!$H81*0.21 -> 58297.05 | L81: =SUM('Abr-24'!$H81:$K81) -> 335902.05
G82: =IFERROR(IF('Abr-24'!$F82="","-",VLOOKUP('Abr-24'!$F82,Lista_CUIT!$A$1:$D$2241,2,0)),"CUIT NO CARGADO") -> - | I82: ='Abr-24'!$H82*0.21 -> 0 | L82: =SUM('Abr-24'!$H82:$K82) -> 0
G83: =IFERROR(IF('Abr-24'!$F83="","-",VLOOKUP('Abr-24'!$F83,Lista_CUIT!$A$1:$D$2241,2,0)),"CUIT NO CARGADO") -> - | I83: ='Abr-24'!$H83*0.21 -> 0 | L83: =SUM('Abr-24'!$H83:$K83) -> 0
G84: =IFERROR(IF('Abr-24'!$F84="","-",VLOOKUP('Abr-24'!$F84,Lista_CUIT!$A$1:$D$2241,2,0)),"CUIT NO CARGADO") -> - | I84: ='Abr-24'!$H84*0.21 -> 0 | L84: =SUM('Abr-24'!$H84:$K84) -> 0
G85: =IFERROR(IF('Abr-24'!$F85="","-",VLOOKUP('Abr-24'!$F85,Lista_CUIT!$A$1:$D$2241,2,0)),"CUIT NO CARGADO") -> - | I85: ='Abr-24'!$H85*0.21 -> 0 | L85: =SUM('Abr-24'!$H85:$K85) -> 0
G86: =IFERROR(IF('Abr-24'!$F86="","-",VLOOKUP('Abr-24'!$F86,Lista_CUIT!$A$1:$D$2241,2,0)),"CUIT NO CARGADO") -> - | I86: ='Abr-24'!$H86*0.21 -> 0 | L86: =SUM('Abr-24'!$H86:$K86) -> 0
G87: =IFERROR(IF('Abr-24'!$F87="","-",VLOOKUP('Abr-24'!$F87,Lista_CUIT!$A$1:$D$2241,2,0)),"CUIT NO CARGADO") -> - | I87: ='Abr-24'!$H87*0.21 -> 0 | L87: =SUM('Abr-24'!$H87:$K87) -> 0
B88: Total | H88: =SUBTOTAL(109,'Abr-24'!$H$78:$H$87) -> 49918615 | I88: =SUBTOTAL(109,'Abr-24'!$I$78:$I$87) -> 123545.68 | J88: =SUBTOTAL(109,'Abr-24'!$J$78:$J$87) -> 5179691.1 | K88: =SUBTOTAL(109,'Abr-24'!$K$78:$K$87) -> 0 | L88: =SUBTOTAL(109,'Abr-24'!$L$78:$L$87) -> 55221852 | M88: =SUBTOTAL(103,'Abr-24'!$M$78:$M$87) -> 0
B90: VENTAS "B"
B91: FECHA | C91: TIPO | D91: PTO VENTA | E91: Nº FACTURA | F91: CUIT | G91: RAZON SOCIAL | H91: IMPORTE NETO | I91: IVA 21% | J91: IVA 10,5% | K91: EXENTO | L91: TOTAL | M91: Provincia
G92: =IFERROR(IF('Abr-24'!$F92="","-",VLOOKUP('Abr-24'!$F92,Lista_CUIT!$A$1:$D$2241,2,0)),"CUIT NO CARGADO") -> -
B98: Total | H98: =SUBTOTAL(109,'Abr-24'!$H$92:$H$97) -> 0 | I98: =SUBTOTAL(109,'Abr-24'!$I$92:$I$97) -> 0 | J98: =SUBTOTAL(109,'Abr-24'!$J$92:$J$97) -> 0 | K98: =SUBTOTAL(109,'Abr-24'!$K$92:$K$97) -> 0 | L98: =SUBTOTAL(109,'Abr-24'!$L$92:$L$97) -> 0 | M98: =SUBTOTAL(103,'Abr-24'!$M$92:$M$97) -> 0
B101: VENTAS "E"
B102: FECHA | C102: TIPO | D102: PTO VENTA | E102: Nº FACTURA | F102: CUIT | G102: RAZON SOCIAL | H102: USD | I102: Columna2 | J102: Columna1 | K102: TIPO DE CAMBIO2 | L102: TOTAL | M102: Provincia
B103: 16/04/2024 | D103: 30 | E103: 75 | F103: 55000002223 | G103: =IFERROR(IF('Abr-24'!$F103="","-",VLOOKUP('Abr-24'!$F103,Lista_CUIT!$A$1:$D$2241,2,0)),"CUIT NO CARGADO") -> Solution Supply SAC | H103: 2200 | K103: 868.5 | L103: ='Abr-24'!$H103*'Abr-24'!$K103 -> 1910700
B104: 18/04/2024 | D104: 30 | E104: 76 | F104: 55000000050 | G104: =IFERROR(IF('Abr-24'!$F104="","-",VLOOKUP('Abr-24'!$F104,Lista_CUIT!$A$1:$D$2241,2,0)),"CUIT NO CARGADO") -> GAS FUTURO SISTEMAS DE COMPRESSÃO LTDA | H104: 3250 | K104: 866.5 | L104: ='Abr-24'!$H104*'Abr-24'!$K104 -> 2816125
B105: 18/04/2024 | D105: 30 | E105: 18 | F105: 55000000050 | G105: =IFERROR(IF('Abr-24'!$F105="","-",VLOOKUP('Abr-24'!$F105,Lista_CUIT!$A$1:$D$2241,2,0)),"CUIT NO CARGADO") -> GAS FUTURO SISTEMAS DE COMPRESSÃO LTDA | L105: -2200
G106: =IFERROR(IF('Abr-24'!$F106="","-",VLOOKUP('Abr-24'!$F106,Lista_CUIT!$A$1:$D$2241,2,0)),"CUIT NO CARGADO") -> - | I106: ='Abr-24'!$H106*0.21 -> 0
B107: Total | H107: =SUBTOTAL(109,'Abr-24'!$H$103:$H$106) -> 5450 | I107: =SUBTOTAL(109,'Abr-24'!$I$103:$I$106) -> 0 | J107: =SUBTOTAL(109,'Abr-24'!$J$103:$J$106) -> 0 | K107: =SUBTOTAL(109,'Abr-24'!$K$103:$K$106) -> 1735 | L107: =SUBTOTAL(109,'Abr-24'!$L$103:$L$106) -> 4724625 | M107: =SUBTOTAL(103,'Abr-24'!$M$103:$M$106) -> 0
C109: RETENCIONES
C110: FECHA | D110: COMP Nº | E110: Columna1 | F110: CUIT | G110: RAZON SOCIAL | H110: Ganancias | I110: IVA | J110: SUSS | K110: IIBB BSAS | L110: IIBB CABA
G111: =IFERROR(IF('Abr-24'!$F111="","-",VLOOKUP('Abr-24'!$F111,Lista_CUIT!$A$1:$D$2241,2,0)),"CUIT NO CARGADO") -> -
G112: =IFERROR(IF('Abr-24'!$F112="","-",VLOOKUP('Abr-24'!$F112,Lista_CUIT!$A$1:$D$2241,2,0)),"CUIT NO CARGADO") -> -
G113: =IFERROR(IF('Abr-24'!$F113="","-",VLOOKUP('Abr-24'!$F113,Lista_CUIT!$A$1:$D$2241,2,0)),"CUIT NO CARGADO") -> -
G114: =IFERROR(IF('Abr-24'!$F114="","-",VLOOKUP('Abr-24'!$F114,Lista_CUIT!$A$1:$D$2241,2,0)),"CUIT NO CARGADO") -> -
G115: =IFERROR(IF('Abr-24'!$F115="","-",VLOOKUP('Abr-24'!$F115,Lista_CUIT!$A$1:$D$2241,2,0)),"CUIT NO CARGADO") -> -

Sheet May-24
B1: LIBRO IVA COMPRAS | G1: ='Abr-24'!G1:M1 -> CORITEC S. R. L. | N1: 45413
B3: TOTAL COMPRAS | G3: TOTAL CREDITO FISCAL | J3: TOTAL VENTAS NETAS | M3: TOTAL DEBITO FISCAL | P3: RESULTADO
B4: =SUM('May-24'!$H$42)+'May-24'!$G$55 -> 10136411 | G4: ='May-24'!$I$42+'May-24'!$J$42+'May-24'!$K$42+'May-24'!$H$55+'May-24'!$I$55 -> 2130006.9 | J4: =SUM('May-24'!$H$104+'May-24'!$H$116) -> 85616903 | M4: =SUM('May-24'!$I$104+'May-24'!$J$104+'May-24'!$I$116+'May-24'!$J$116) -> 10862134 | P4: =G4-M4 -> -8732126.9
B8: FECHA | C8: TIPO | D8: PTO VTA | E8: NRO. CPTE | F8: CUIT | G8: RAZON SOCIAL | H8: NETO GRAVADO | I8: IVA 21 % | J8: IVA 27% | K8: IVA 10,5% | L8: PERC. IVA | M8: PERC IIBB BS AS | N8: PERC. IIBB CABA | O8: Otros / No Grav. | P8: TOTAL | Q8: Tipo de Gasto | R8: Provincia
B9: 45413 | C9: 1 | D9: 3 | E9: 227312 | F9: 30707135596 | G9: =IFERROR(IF('May-24'!$F9="","-",VLOOKUP('May-24'!$F9,Lista_CUIT!$A$1:$D$2241,2,0)),"CUIT NO CARGADO") -> CITILAN ARGENTINA S.A. | H9: 18742.75 | I9: =IF('May-24'!$H9="","",'May-24'!$H9*0.21) -> 3935.9775 | P9: =SUM('May-24'!$H9:$O9) -> 22678.728 | Q9: =IFERROR(IF('May-24'!$F9="","-",VLOOKUP('May-24'!$F9,Lista_CUIT!$A$1:$D$2241,3,0)),"CUIT NO CARGADO") -> Telefonia | R9: =IFERROR(IF('May-24'!$F9="","-",VLOOKUP('May-24'!$F9,Lista_CUIT!$A$1:$D$2241,4,0)),"CUIT NO CARGADO") -> 0
B10: 45413 | C10: 1 | D10: 3 | E10: 753 | F10: 30715402765 | G10: =IFERROR(IF('May-24'!$F10="","-",VLOOKUP('May-24'!$F10,Lista_CUIT!$A$1:$D$2241,2,0)),"CUIT NO CARGADO") -> RIO 265 S.R.L. | H10: 49586.76 | I10: =IF('May-24'!$H10="","",'May-24'!$H10*0.21) -> 10413.22 | P10: =SUM('May-24'!$H10:$O10) -> 59999.98 | Q10: =IFERROR(IF('May-24'!$F10="","-",VLOOKUP('May-24'!$F10,Lista_CUIT!$A$1:$D$2241,3,0)),"CUIT NO CARGADO") -> GASTOS VARIOS | R10: =IFERROR(IF('May-24'!$F10="","-",VLOOKUP('May-24'!$F10,Lista_CUIT!$A$1:$D$2241,4,0)),"CUIT NO CARGADO") -> 0
B11: 45414 | C11: 1 | D11: 4 | E11: 101074 | F11: 30559932236 | G11: =IFERROR(IF('May-24'!$F11="","-",VLOOKUP('May-24'!$F11,Lista_CUIT!$A$1:$D$2241,2,0)),"CUIT NO CARGADO") -> ELECTRONICA ELEMON S A | H11: 44562.34 | I11: =IF('May-24'!$H11="","",'May-24'!$H11*0.21) -> 9358.0914 | P11: =SUM('May-24'!$H11:$O11) -> 53920.431 | Q11: =IFERROR(IF('May-24'!$F11="","-",VLOOKUP('May-24'!$F11,Lista_CUIT!$A$1:$D$2241,3,0)),"CUIT NO CARGADO") -> Mat. Prima | R11: =IFERROR(IF('May-24'!$F11="","-",VLOOKUP('May-24'!$F11,Lista_CUIT!$A$1:$D$2241,4,0)),"CUIT NO CARGADO") -> 0
B12: 45414 | C12: 1 | D12: 1 | E12: 786 | F12: 30715048066 | G12: =IFERROR(IF('May-24'!$F12="","-",VLOOKUP('May-24'!$F12,Lista_CUIT!$A$1:$D$2241,2,0)),"CUIT NO CARGADO") -> ROLLS Y EMPANADAS SA | H12: 600510 | I12: =IF('May-24'!$H12="","",'May-24'!$H12*0.21) -> 126107.1 | P12: =SUM('May-24'!$H12:$O12) -> 726617.1 | Q12: =IFERROR(IF('May-24'!$F12="","-",VLOOKUP('May-24'!$F12,Lista_CUIT!$A$1:$D$2241,3,0)),"CUIT NO CARGADO") -> CATERING | R12: =IFERROR(IF('May-24'!$F12="","-",VLOOKUP('May-24'!$F12,Lista_CUIT!$A$1:$D$2241,4,0)),"CUIT NO CARGADO") -> 0
B13: 45414 | C13: 1 | D13: 3 | E13: 124 | F13: 20297899830 | G13: =IFERROR(IF('May-24'!$F13="","-",VLOOKUP('May-24'!$F13,Lista_CUIT!$A$1:$D$2241,2,0)),"CUIT NO CARGADO") -> FUNK MATIAS NICOLAS | H13: 5188880 | I13: =IF('May-24'!$H13="","",'May-24'!$H13*0.21) -> 1089664.8 | P13: =SUM('May-24'!$H13:$O13) -> 6278544.8 | Q13: =IFERROR(IF('May-24'!$F13="","-",VLOOKUP('May-24'!$F13,Lista_CUIT!$A$1:$D$2241,3,0)),"CUIT NO CARGADO") -> INSUMO | R13: =IFERROR(IF('May-24'!$F13="","-",VLOOKUP('May-24'!$F13,Lista_CUIT!$A$1:$D$2241,4,0)),"CUIT NO CARGADO") -> 0
B14: 45416 | C14: 1 | D14: 11 | E14: 1508 | F14: 27249663870 | G14: =IFERROR(IF('May-24'!$F14="","-",VLOOKUP('May-24'!$F14,Lista_CUIT!$A$1:$D$2241,2,0)),"CUIT NO CARGADO") -> GRAZIANO TAMARA NATALIA | H14: 19981.49 | I14: =IF('May-24'!$H14="","",'May-24'!$H14*0.21) -> 4196.1129 | P14: =SUM('May-24'!$H14:$O14) -> 24177.603 | Q14: =IFERROR(IF('May-24'!$F14="","-",VLOOKUP('May-24'!$F14,Lista_CUIT!$A$1:$D$2241,3,0)),"CUIT NO CARGADO") -> Servicios Informaticos | R14: =IFERROR(IF('May-24'!$F14="","-",VLOOKUP('May-24'!$F14,Lista_CUIT!$A$1:$D$2241,4,0)),"CUIT NO CARGADO") -> 0
B15: 45416 | C15: 1 | D15: 8 | E15: 3167 | F15: 30715247077 | G15: =IFERROR(IF('May-24'!$F15="","-",VLOOKUP('May-24'!$F15,Lista_CUIT!$A$1:$D$2241,2,0)),"CUIT NO CARGADO") -> MALATEX S.R.L. | H15: 27263.64 | I15: =IF('May-24'!$H15="","",'May-24'!$H15*0.21) -> 5725.3644 | P15: =SUM('May-24'!$H15:$O15) -> 32989.004 | Q15: =IFERROR(IF('May-24'!$F15="","-",VLOOKUP('May-24'!$F15,Lista_CUIT!$A$1:$D$2241,3,0)),"CUIT NO CARGADO") -> Ropa de Trabajo | R15: =IFERROR(IF('May-24'!$F15="","-",VLOOKUP('May-24'!$F15,Lista_CUIT!$A$1:$D$2241,4,0)),"CUIT NO CARGADO") -> 0
B16: 45418 | C16: 1 | D16: 2 | E16: 545 | F16: 30716952408 | G16: =IFERROR(IF('May-24'!$F16="","-",VLOOKUP('May-24'!$F16,Lista_CUIT!$A$1:$D$2241,2,0)),"CUIT NO CARGADO") -> MATECH IMPORT ARGENTINA SAS | H16: 5784.3 | I16: =IF('May-24'!$H16="","",'May-24'!$H16*0.21) -> 1214.703 | P16: =SUM('May-24'!$H16:$O16) -> 6999.003 | Q16: =IFERROR(IF('May-24'!$F16="","-",VLOOKUP('May-24'!$F16,Lista_CUIT!$A$1:$D$2241,3,0)),"CUIT NO CARGADO") -> software | R16: =IFERROR(IF('May-24'!$F16="","-",VLOOKUP('May-24'!$F16,Lista_CUIT!$A$1:$D$2241,4,0)),"CUIT NO CARGADO") -> 0
B17: 45418 | C17: 1 | D17: 100 | E17: 4344 | F17: 30562265844 | G17: =IFERROR(IF('May-24'!$F17="","-",VLOOKUP('May-24'!$F17,Lista_CUIT!$A$1:$D$2241,2,0)),"CUIT NO CARGADO") -> LA MADRILEÑA SOCIEDAD ANONIMA COMERCIAL INDUSTRIAL AGROPECUARIA FINANCIERA E INMOBILIARIA | H17: 69421.49 | I17: =IF('May-24'!$H17="","",'May-24'!$H17*0.21) -> 14578.513 | P17: =SUM('May-24'!$H17:$O17) -> 84000.003 | Q17: =IFERROR(IF('May-24'!$F17="","-",VLOOKUP('May-24'!$F17,Lista_CUIT!$A$1:$D$2241,3,0)),"CUIT NO CARGADO") -> Ropa de Trabajo | R17: =IFERROR(IF('May-24'!$F17="","-",VLOOKUP('May-24'!$F17,Lista_CUIT!$A$1:$D$2241,4,0)),"CUIT NO CARGADO") -> 0
B18: 45418 | C18: 1 | D18: 4 | E18: 15738 | F18: 33717112119 | G18: =IFERROR(IF('May-24'!$F18="","-",VLOOKUP('May-24'!$F18,Lista_CUIT!$A$1:$D$2241,2,0)),"CUIT NO CARGADO") -> PREVENSIS S.R.L. | H18: 16252.06 | I18: =IF('May-24'!$H18="","",'May-24'!$H18*0.21) -> 3412.9326 | P18: =SUM('May-24'!$H18:$O18) -> 19664.993 | Q18: =IFERROR(IF('May-24'!$F18="","-",VLOOKUP('May-24'!$F18,Lista_CUIT!$A$1:$D$2241,3,0)),"CUIT NO CARGADO") -> GASTOS VARIOS | R18: =IFERROR(IF('May-24'!$F18="","-",VLOOKUP('May-24'!$F18,Lista_CUIT!$A$1:$D$2241,4,0)),"CUIT NO CARGADO") -> 0
B19: 45419 | C19: 1 | D19: 3 | E19: 42639 | F19: 30715235419 | G19: =IFERROR(IF('May-24'!$F19="","-",VLOOKUP('May-24'!$F19,Lista_CUIT!$A$1:$D$2241,2,0)),"CUIT NO CARGADO") -> SIFEGA COMPANY | H19: 27825.62 | I19: =IF('May-24'!$H19="","",'May-24'!$H19*0.21) -> 5843.3802 | P19: =SUM('May-24'!$H19:$O19) -> 33669 | Q19: =IFERROR(IF('May-24'!$F19="","-",VLOOKUP('May-24'!$F19,Lista_CUIT!$A$1:$D$2241,3,0)),"CUIT NO CARGADO") -> INSUMO | R19: =IFERROR(IF('May-24'!$F19="","-",VLOOKUP('May-24'!$F19,Lista_CUIT!$A$1:$D$2241,4,0)),"CUIT NO CARGADO") -> 0
B20: 45420 | C20: 1 | D20: 16 | E20: 21955 | F20: 30708508221 | G20: =IFERROR(IF('May-24'!$F20="","-",VLOOKUP('May-24'!$F20,Lista_CUIT!$A$1:$D$2241,2,0)),"CUIT NO CARGADO") -> HERRAJES VEIGA | H20: 6701.02 | I20: =IF('May-24'!$H20="","",'May-24'!$H20*0.21) -> 1407.2142 | P20: =SUM('May-24'!$H20:$O20) -> 8108.2342 | Q20: =IFERROR(IF('May-24'!$F20="","-",VLOOKUP('May-24'!$F20,Lista_CUIT!$A$1:$D$2241,3,0)),"CUIT NO CARGADO") -> mercaderia | R20: =IFERROR(IF('May-24'!$F20="","-",VLOOKUP('May-24'!$F20,Lista_CUIT!$A$1:$D$2241,4,0)),"CUIT NO CARGADO") -> 0
... B22: 45420 | C22: 1 | D22: 2 | E22: 3462 | F22: 30710878974 | G22: =IFERROR(IF('May-24'!$F22="","-",VLOOKUP('May-24'!$F22,Lista_CUIT!$A$1:$D$2241,2,0)),"CUIT NO CARGADO") -> TEBY SRL | H22: 515446 | I22: =IF('May-24'!$H22="","",'May-24'!$H22*0.21) -> 108243.66 | P22: =SUM('May-24'!$H22:$O22) -> 623689.66 | Q22: =IFERROR(IF('May-24'!$F22="","-",VLOOKUP('May-24'!$F22,Lista_CUIT!$A$1:$D$2241,3,0)),"CUIT NO CARGADO") -> Papeleria | R22: =IFERROR(IF('May-24'!$F22="","-",VLOOKUP('May-24'!$F22,Lista_CUIT!$A$1:$D$2241,4,0)),"CUIT NO CARGADO") -> 0
B23: 45423 | C23: 1 | D23: 2466 | E23: 650742 | F23: 30678814357 | G23: =IFERROR(IF('May-24'!$F23="","-",VLOOKUP('May-24'!$F23,Lista_CUIT!$A$1:$D$2241,2,0)),"CUIT NO CARGADO") -> TELEFONICA MOVILES ARG | H23: 22677.35 | J23: ='May-24'!$H23*0.27 -> 6122.8845 | L23: 680.32 | O23: 1138.18 | P23: =SUM('May-24'!$H23:$O23) -> 30618.734 | Q23: =IFERROR(IF('May-24'!$F23="","-",VLOOKUP('May-24'!$F23,Lista_CUIT!$A$1:$D$2241,3,0)),"CUIT NO CARGADO") -> Telefonia | R23: =IFERROR(IF('May-24'!$F23="","-",VLOOKUP('May-24'!$F23,Lista_CUIT!$A$1:$D$2241,4,0)),"CUIT NO CARGADO") -> 0
B24: 45425 | C24: 1 | D24: 9 | E24: 1882 | F24: 30631047145 | G24: =IFERROR(IF('May-24'!$F24="","-",VLOOKUP('May-24'!$F24,Lista_CUIT!$A$1:$D$2241,2,0)),"CUIT NO CARGADO") -> SEMICONDUC. Y COMPON. SRL | H24: 343140 | I24: =IF('May-24'!$H24="","",'May-24'!$H24*0.21) -> 72059.4 | P24: =SUM('May-24'!$H24:$O24) -> 415199.4 | Q24: =IFERROR(IF('May-24'!$F24="","-",VLOOKUP('May-24'!$F24,Lista_CUIT!$A$1:$D$2241,3,0)),"CUIT NO CARGADO") -> Mercaderia | R24: =IFERROR(IF('May-24'!$F24="","-",VLOOKUP('May-24'!$F24,Lista_CUIT!$A$1:$D$2241,4,0)),"CUIT NO CARGADO") -> 0
B25: 45426 | C25: 1 | D25: 8 | E25: 23912 | F25: 30709953482 | G25: =IFERROR(IF('May-24'!$F25="","-",VLOOKUP('May-24'!$F25,Lista_CUIT!$A$1:$D$2241,2,0)),"CUIT NO CARGADO") -> HONRE S.A | H25: 12298.61 | I25: =IF('May-24'!$H25="","",'May-24'!$H25*0.21) -> 2582.7081 | P25: =SUM('May-24'!$H25:$O25) -> 14881.318 | Q25: =IFERROR(IF('May-24'!$F25="","-",VLOOKUP('May-24'!$F25,Lista_CUIT!$A$1:$D$2241,3,0)),"CUIT NO CARGADO") -> GASTOS VARIOS | R25: =IFERROR(IF('May-24'!$F25="","-",VLOOKUP('May-24'!$F25,Lista_CUIT!$A$1:$D$2241,4,0)),"CUIT NO CARGADO") -> 0
B26: 45426 | C26: 1 | D26: 6 | E26: 6245 | F26: 30714743402 | G26: =IFERROR(IF('May-24'!$F26="","-",VLOOKUP('May-24'!$F26,Lista_CUIT!$A$1:$D$2241,2,0)),"CUIT NO CARGADO") -> HERRAMIENTAS DALI SRL | H26: 22512.4 | I26: =IF('May-24'!$H26="","",'May-24'!$H26*0.21) -> 4727.604 | P26: =SUM('May-24'!$H26:$O26) -> 27240.004 | Q26: =IFERROR(IF('May-24'!$F26="","-",VLOOKUP('May-24'!$F26,Lista_CUIT!$A$1:$D$2241,3,0)),"CUIT NO CARGADO") -> REPUESTOS | R26: =IFERROR(IF('May-24'!$F26="","-",VLOOKUP('May-24'!$F26,Lista_CUIT!$A$1:$D$2241,4,0)),"CUIT NO CARGADO") -> 0
B27: 45426 | C27: 1 | D27: 3 | E27: 5725 | F27: 30710585411 | G27: =IFERROR(IF('May-24'!$F27="","-",VLOOKUP('May-24'!$F27,Lista_CUIT!$A$1:$D$2241,2,0)),"CUIT NO CARGADO") -> POSITIF PLANIFIER S.A. | H27: 49725.62 | I27: =IF('May-24'!$H27="","",'May-24'!$H27*0.21) -> 10442.38 | P27: =SUM('May-24'!$H27:$O27) -> 60168 | Q27: =IFERROR(IF('May-24'!$F27="","-",VLOOKUP('May-24'!$F27,Lista_CUIT!$A$1:$D$2241,3,0)),"CUIT NO CARGADO") -> Gastos de Comercializacion | R27: =IFERROR(IF('May-24'!$F27="","-",VLOOKUP('May-24'!$F27,Lista_CUIT!$A$1:$D$2241,4,0)),"CUIT NO CARGADO") -> 0
B28: 45427 | C28: 1 | D28: 8 | E28: 24019 | F28: 30709953482 | G28: =IFERROR(IF('May-24'!$F28="","-",VLOOKUP('May-24'!$F28,Lista_CUIT!$A$1:$D$2241,2,0)),"CUIT NO CARGADO") -> HONRE S.A | H28: 12298.61 | I28: =IF('May-24'!$H28="","",'May-24'!$H28*0.21) -> 2582.7081 | P28: =SUM('May-24'!$H28:$O28) -> 14881.318 | Q28: =IFERROR(IF('May-24'!$F28="","-",VLOOKUP('May-24'!$F28,Lista_CUIT!$A$1:$D$2241,3,0)),"CUIT NO CARGADO") -> GASTOS VARIOS | R28: =IFERROR(IF('May-24'!$F28="","-",VLOOKUP('May-24'!$F28,Lista_CUIT!$A$1:$D$2241,4,0)),"CUIT NO CARGADO") -> 0
B29: 45427 | C29: 1 | D29: 9 | E29: 14039 | F29: 30708600187 | G29: =IFERROR(IF('May-24'!$F29="","-",VLOOKUP('May-24'!$F29,Lista_CUIT!$A$1:$D$2241,2,0)),"CUIT NO CARGADO") -> MAQUINAS Y CONSUMIBLES S.A. | H29: 601160 | I29: =IF('May-24'!$H29="","",'May-24'!$H29*0.21) -> 126243.6 | P29: =SUM('May-24'!$H29:$O29) -> 727403.6 | Q29: =IFERROR(IF('May-24'!$F29="","-",VLOOKUP('May-24'!$F29,Lista_CUIT!$A$1:$D$2241,3,0)),"CUIT NO CARGADO") -> INSUMO | R29: =IFERROR(IF('May-24'!$F29="","-",VLOOKUP('May-24'!$F29,Lista_CUIT!$A$1:$D$2241,4,0)),"CUIT NO CARGADO") -> 0
B30: 45427 | C30: 3 | D30: 8 | E30: 2150 | F30: 30709953482 | G30: =IFERROR(IF('May-24'!$F30="","-",VLOOKUP('May-24'!$F30,Lista_CUIT!$A$1:$D$2241,2,0)),"CUIT NO CARGADO") -> HONRE S.A | H30: -12298.61 | I30: =IF('May-24'!$H30="","",'May-24'!$H30*0.21) -> -2582.7081 | P30: =SUM('May-24'!$H30:$O30) -> -14881.318 | Q30: =IFERROR(IF('May-24'!$F30="","-",VLOOKUP('May-24'!$F30,Lista_CUIT!$A$1:$D$2241,3,0)),"CUIT NO CARGADO") -> GASTOS VARIOS | R30: =IFERROR(IF('May-24'!$F30="","-",VLOOKUP('May-24'!$F30,Lista_CUIT!$A$1:$D$2241,4,0)),"CUIT NO CARGADO") -> 0
B31: 45428 | C31: 1 | D31: 106 | E31: 733821 | F31: 30594494187 | G31: =IFERROR(IF('May-24'!$F31="","-",VLOOKUP('May-24'!$F31,Lista_CUIT!$A$1:$D$2241,2,0)),"CUIT NO CARGADO") -> FEDERAL EXPRESS CORPORATION | H31: 0 | I31: =IF('May-24'!$H31="","",'May-24'!$H31*0.21) -> 0 | O31: 407884.8 | P31: =SUM('May-24'!$H31:$O31) -> 407884.8 | Q31: =IFERROR(IF('May-24'!$F31="","-",VLOOKUP('May-24'!$F31,Lista_CUIT!$A$1:$D$2241,3,0)),"CUIT NO CARGADO") -> Gastos Importacion | R31: =IFERROR(IF('May-24'!$F31="","-",VLOOKUP('May-24'!$F31,Lista_CUIT!$A$1:$D$2241,4,0)),"CUIT NO CARGADO") -> 0
B32: 45432 | C32: 1 | D32: 6 | E32: 782 | F32: 20283509924 | G32: =IFERROR(IF('May-24'!$F32="","-",VLOOKUP('May-24'!$F32,Lista_CUIT!$A$1:$D$2241,2,0)),"CUIT NO CARGADO") -> HEREDIA LEONARDO ADRIAN | H32: 24518.19 | I32: =IF('May-24'!$H32="","",'May-24'!$H32*0.21) -> 5148.8199 | P32: =SUM('May-24'!$H32:$O32) -> 29667.01 | Q32: =IFERROR(IF('May-24'!$F32="","-",VLOOKUP('May-24'!$F32,Lista_CUIT!$A$1:$D$2241,3,0)),"CUIT NO CARGADO") -> INSUMO | R32: =IFERROR(IF('May-24'!$F32="","-",VLOOKUP('May-24'!$F32,Lista_CUIT!$A$1:$D$2241,4,0)),"CUIT NO CARGADO") -> 0
B33: 45434 | C33: 1 | D33: 2 | E33: 8760 | F33: 30711726019 | G33: =IFERROR(IF('May-24'!$F33="","-",VLOOKUP('May-24'!$F33,Lista_CUIT!$A$1:$D$2241,2,0)),"CUIT NO CARGADO") -> MAV GROUP S.A. | H33: 351200 | I33: =IF('May-24'!$H33="","",'May-24'!$H33*0.21) -> 73752 | P33: =SUM('May-24'!$H33:$O33) -> 424952 | Q33: =IFERROR(IF('May-24'!$F33="","-",VLOOKUP('May-24'!$F33,Lista_CUIT!$A$1:$D$2241,3,0)),"CUIT NO CARGADO") -> Gastos Importacion | R33: =IFERROR(IF('May-24'!$F33="","-",VLOOKUP('May-24'!$F33,Lista_CUIT!$A$1:$D$2241,4,0)),"CUIT NO CARGADO") -> 0
B34: 45436 | C34: 1 | D34: 6 | E34: 791 | F34: 20283509924 | G34: =IFERROR(IF('May-24'!$F34="","-",VLOOKUP('May-24'!$F34,Lista_CUIT!$A$1:$D$2241,2,0)),"CUIT NO CARGADO") -> HEREDIA LEONARDO ADRIAN | H34: 49036.38 | I34: =IF('May-24'!$H34="","",'May-24'!$H34*0.21) -> 10297.64 | P34: =SUM('May-24'!$H34:$O34) -> 59334.02 | Q34: =IFERROR(IF('May-24'!$F34="","-",VLOOKUP('May-24'!$F34,Lista_CUIT!$A$1:$D$2241,3,0)),"CUIT NO CARGADO") -> INSUMO | R34: =IFERROR(IF('May-24'!$F34="","-",VLOOKUP('May-24'!$F34,Lista_CUIT!$A$1:$D$2241,4,0)),"CUIT NO CARGADO") -> 0
B35: 45439 | C35: 1 | D35: 3 | E35: 311 | F35: 20921575743 | G35: =IFERROR(IF('May-24'!$F35="","-",VLOOKUP('May-24'!$F35,Lista_CUIT!$A$1:$D$2241,2,0)),"CUIT NO CARGADO") -> RIOS GOMEZ JOSE ANTONIO | H35: 554900 | I35: =IF('May-24'!$H35="","",'May-24'!$H35*0.21) -> 116529 | P35: =SUM('May-24'!$H35:$O35) -> 671429 | Q35: =IFERROR(IF('May-24'!$F35="","-",VLOOKUP('May-24'!$F35,Lista_CUIT!$A$1:$D$2241,3,0)),"CUIT NO CARGADO") -> Papeleria | R35: =IFERROR(IF('May-24'!$F35="","-",VLOOKUP('May-24'!$F35,Lista_CUIT!$A$1:$D$2241,4,0)),"CUIT NO CARGADO") -> 0
B36: 45440 | C36: 1 | D36: 2 | E36: 198 | F36: 20125142851 | G36: =IFERROR(IF('May-24'!$F36="","-",VLOOKUP('May-24'!$F36,Lista_CUIT!$A$1:$D$2241,2,0)),"CUIT NO CARGADO") -> FEDERICI NICOLAS JOSE | H36: 63792.76 | I36: =IF('May-24'!$H36="","",'May-24'!$H36*0.21) -> 13396.48 | P36: =SUM('May-24'!$H36:$O36) -> 77189.24 | Q36: =IFERROR(IF('May-24'!$F36="","-",VLOOKUP('May-24'!$F36,Lista_CUIT!$A$1:$D$2241,3,0)),"CUIT NO CARGADO") -> INSUMO | R36: =IFERROR(IF('May-24'!$F36="","-",VLOOKUP('May-24'!$F36,Lista_CUIT!$A$1:$D$2241,4,0)),"CUIT NO CARGADO") -> 0
B37: 45442 | C37: 1 | D37: 5 | E37: 73679 | F37: 30692857611 | G37: =IFERROR(IF('May-24'!$F37="","-",VLOOKUP('May-24'!$F37,Lista_CUIT!$A$1:$D$2241,2,0)),"CUIT NO CARGADO") -> BAGUI S A | H37: 122817.35 | I37: =IF('May-24'!$H37="","",'May-24'!$H37*0.21) -> 25791.644 | P37: =SUM('May-24'!$H37:$O37) -> 148608.99 | Q37: =IFERROR(IF('May-24'!$F37="","-",VLOOKUP('May-24'!$F37,Lista_CUIT!$A$1:$D$2241,3,0)),"CUIT NO CARGADO") -> INSUMO | R37: =IFERROR(IF('May-24'!$F37="","-",VLOOKUP('May-24'!$F37,Lista_CUIT!$A$1:$D$2241,4,0)),"CUIT NO CARGADO") -> 0
B38: 45443 | C38: 1 | D38: 6 | E38: 14846 | F38: 30707756434 | G38: =IFERROR(IF('May-24'!$F38="","-",VLOOKUP('May-24'!$F38,Lista_CUIT!$A$1:$D$2241,2,0)),"CUIT NO CARGADO") -> SERVICIO INTEGRAL DE LIMPIEZA SRL | H38: 290000 | I38: =IF('May-24'!$H38="","",'May-24'!$H38*0.21) -> 60900 | P38: =SUM('May-24'!$H38:$O38) -> 350900 | Q38: =IFERROR(IF('May-24'!$F38="","-",VLOOKUP('May-24'!$F38,Lista_CUIT!$A$1:$D$2241,3,0)),"CUIT NO CARGADO") -> Mantenimiento | R38: =IFERROR(IF('May-24'!$F38="","-",VLOOKUP('May-24'!$F38,Lista_CUIT!$A$1:$D$2241,4,0)),"CUIT NO CARGADO") -> 0
G39: =IFERROR(IF('May-24'!$F39="","-",VLOOKUP('May-24'!$F39,Lista_CUIT!$A$1:$D$2241,2,0)),"CUIT NO CARGADO") -> - | I39: =IF('May-24'!$H39="","",'May-24'!$H39*0.21) | P39: =SUM('May-24'!$H39:$O39) -> 0 | Q39: =IFERROR(IF('May-24'!$F39="","-",VLOOKUP('May-24'!$F39,Lista_CUIT!$A$1:$D$2241,3,0)),"CUIT NO CARGADO") -> - | R39: =IFERROR(IF('May-24'!$F39="","-",VLOOKUP('May-24'!$F39,Lista_CUIT!$A$1:$D$2241,4,0)),"CUIT NO CARGADO") -> -
G40: =IFERROR(IF('May-24'!$F40="","-",VLOOKUP('May-24'!$F40,Lista_CUIT!$A$1:$D$2241,2,0)),"CUIT NO CARGADO") -> - | I40: =IF('May-24'!$H40="","",'May-24'!$H40*0.21) | P40: =SUM('May-24'!$H40:$O40) -> 0 | Q40: =IFERROR(IF('May-24'!$F40="","-",VLOOKUP('May-24'!$F40,Lista_CUIT!$A$1:$D$2241,3,0)),"CUIT NO CARGADO") -> - | R40: =IFERROR(IF('May-24'!$F40="","-",VLOOKUP('May-24'!$F40,Lista_CUIT!$A$1:$D$2241,4,0)),"CUIT NO CARGADO") -> -
G41: =IFERROR(IF('May-24'!$F41="","-",VLOOKUP('May-24'!$F41,Lista_CUIT!$A$1:$D$2241,2,0)),"CUIT NO CARGADO") -> - | I41: =IF('May-24'!$H41="","",'May-24'!$H41*0.21) | P41: =SUM('May-24'!$H41:$O41) -> 0 | Q41: =IFERROR(IF('May-24'!$F41="","-",VLOOKUP('May-24'!$F41,Lista_CUIT!$A$1:$D$2241,3,0)),"CUIT NO CARGADO") -> - | R41: =IFERROR(IF('May-24'!$F41="","-",VLOOKUP('May-24'!$F41,Lista_CUIT!$A$1:$D$2241,4,0)),"CUIT NO CARGADO") -> -
B42: Total | H42: =SUBTOTAL(109,'May-24'!$H$9:$H$41) -> 10048736 | I42: =SUBTOTAL(109,'May-24'!$I$9:$I$41) -> 2105472.3 | J42: =SUBTOTAL(109,'May-24'!$J$9:$J$41) -> 6122.8845 | K42: =SUBTOTAL(109,'May-24'!$K$9:$K$41) -> 0 | L42: =SUBTOTAL(109,'May-24'!$L$9:$L$41) -> 680.32 | M42: =SUBTOTAL(109,'May-24'!$M$9:$M$41) -> 0 | N42: =SUBTOTAL(109,'May-24'!$N$9:$N$41) -> 0 | O42: =SUBTOTAL(109,'May-24'!$O$9:$O$41) -> 409022.98 | P42: =SUBTOTAL(109,'May-24'!$P$9:$P$41) -> 12570035
D47: LIQUIDACION EXTRACTOS BANCARIOS-TARJETAS
D48: FECHA | E48: NRO CPTE | F48: BANCO | G48: NETO | H48: IVA 21% | I48: IVA 10,5% | J48: RET IIBB CABA | K48: PERC IVA | L48: PERC IIBB
D49: 45432 | F49: CREDICOOP | G49: 22212.5 | H49: ='May-24'!$G49*0.21 -> 4664.625 | K49: 666.38
D50: 45428 | F50: CREDICOOP | G50: 22150 | H50: ='May-24'!$G50*0.21 -> 4651.5 | K50: 664.5
F51: CREDICOOP | G51: 42912.25 | H51: ='May-24'!$G51*0.21 -> 9011.5725 | K51: 360
G52: 400 | H52: ='May-24'!$G52*0.21 -> 84 | J52: 27.76
H53: ='May-24'!$G53*0.21 -> 0
H54: ='May-24'!$G54*0.21 -> 0
D55: Total | G55: =SUBTOTAL(109,'May-24'!$G$49:$G$54) -> 87674.75 | H55: =SUBTOTAL(109,'May-24'!$H$49:$H$54) -> 18411.698 | I55: =SUBTOTAL(109,'May-24'!$I$49:$I$54) -> 0 | J55: =SUBTOTAL(109,'May-24'!$J$49:$J$54) -> 27.76 | K55: =SUBTOTAL(109,'May-24'!$K$49:$K$54) -> 1690.88 | L55: =SUBTOTAL(109,'May-24'!$L$49:$L$54) -> 0
D59: FACTURAS C
D60: FECHA | E60: PTO VTA | F60: FC Nº | G60: CUIT | H60: RAZON SOCIAL | I60: TOTAL | J60: TIPO DE GASTO | K60: Provincia
D61: 45414 | E61: 1 | F61: 36 | G61: 20365938688 | H61: =IFERROR(IF('May-24'!$G61="","-",VLOOKUP('May-24'!$G61,Lista_CUIT!$A$1:$D$2241,2,0)),"CUIT NO CARGADO") -> LIPANOVICH JUAN CRUZ | I61: 750000 | J61: =IFERROR(IF('May-24'!$G61="","-",VLOOKUP('May-24'!$G61,Lista_CUIT!$A$1:$D$2241,3,0)),"CUIT NO CARGADO") -> SOFTWARE | K61: =IFERROR(IF('May-24'!$G61="","-",VLOOKUP('May-24'!$G61,Lista_CUIT!$A$1:$D$2241,4,0)),"CUIT NO CARGADO") -> 0
D62: 45414 | E62: 3 | F62: 849 | G62: 20086277523 | H62: =IFERROR(IF('May-24'!$G62="","-",VLOOKUP('May-24'!$G62,Lista_CUIT!$A$1:$D$2241,2,0)),"CUIT NO CARGADO") -> ESTUDIO BOTINDARI | I62: 210000 | J62: =IFERROR(IF('May-24'!$G62="","-",VLOOKUP('May-24'!$G62,Lista_CUIT!$A$1:$D$2241,3,0)),"CUIT NO CARGADO") -> Honorarios Contables | K62: =IFERROR(IF('May-24'!$G62="","-",VLOOKUP('May-24'!$G62,Lista_CUIT!$A$1:$D$2241,4,0)),"CUIT NO CARGADO") -> 0
D63: 45414 | E63: 2 | F63: 238 | G63: 27173820866 | H63: =IFERROR(IF('May-24'!$G63="","-",VLOOKUP('May-24'!$G63,Lista_CUIT!$A$1:$D$2241,2,0)),"CUIT NO CARGADO") -> FREIER SANDRA DANIELA | I63: 700000 | J63: =IFERROR(IF('May-24'!$G63="","-",VLOOKUP('May-24'!$G63,Lista_CUIT!$A$1:$D$2241,3,0)),"CUIT NO CARGADO") -> Honorarios Prof | K63: =IFERROR(IF('May-24'!$G63="","-",VLOOKUP('May-24'!$G63,Lista_CUIT!$A$1:$D$2241,4,0)),"CUIT NO CARGADO") -> 0
D64: 45414 | E64: 1 | F64: 25 | G64: 27387896150 | H64: =IFERROR(IF('May-24'!$G64="","-",VLOOKUP('May-24'!$G64,Lista_CUIT!$A$1:$D$2241,2,0)),"CUIT NO CARGADO") -> LIPANOVICH MARIA SOL | I64: 750000 | J64: =IFERROR(IF('May-24'!$G64="","-",VLOOKUP('May-24'!$G64,Lista_CUIT!$A$1:$D$2241,3,0)),"CUIT NO CARGADO") -> consultoria informatica | K64: =IFERROR(IF('May-24'!$G64="","-",VLOOKUP('May-24'!$G64,Lista_CUIT!$A$1:$D$2241,4,0)),"CUIT NO CARGADO") -> 0
D65: 45415 | E65: 4 | F65: 25 | G65: 20341462933 | H65: =IFERROR(IF('May-24'!$G65="","-",VLOOKUP('May-24'!$G65,Lista_CUIT!$A$1:$D$2241,2,0)),"CUIT NO CARGADO") -> CASTIGLIONI MATIAS EZEQUIEL | I65: 1015000 | J65: =IFERROR(IF('May-24'!$G65="","-",VLOOKUP('May-24'!$G65,Lista_CUIT!$A$1:$D$2241,3,0)),"CUIT NO CARGADO") -> ASESORAMIENTO | K65: =IFERROR(IF('May-24'!$G65="","-",VLOOKUP('May-24'!$G65,Lista_CUIT!$A$1:$D$2241,4,0)),"CUIT NO CARGADO") -> BUENOS AIRES
D66: 45415 | E66: 2 | F66: 134 | G66: 27125997835 | H66: =IFERROR(IF('May-24'!$G66="","-",VLOOKUP('May-24'!$G66,Lista_CUIT!$A$1:$D$2241,2,0)),"CUIT NO CARGADO") -> DANSKY ULLMANN VIVIANA EVA YOLANDA | I66: 35000 | J66: =IFERROR(IF('May-24'!$G66="","-",VLOOKUP('May-24'!$G66,Lista_CUIT!$A$1:$D$2241,3,0)),"CUIT NO CARGADO") -> Honorarios Prof | K66: =IFERROR(IF('May-24'!$G66="","-",VLOOKUP('May-24'!$G66,Lista_CUIT!$A$1:$D$2241,4,0)),"CUIT NO CARGADO") -> 0
D67: 45419 | E67: 2 | F67: 3 | G67: 23118167279 | H67: =IFERROR(IF('May-24'!$G67="","-",VLOOKUP('May-24'!$G67,Lista_CUIT!$A$1:$D$2241,2,0)),"CUIT NO CARGADO") -> ABELEDO ENRIQUE JUAN | I67: 780000 | J67: =IFERROR(IF('May-24'!$G67="","-",VLOOKUP('May-24'!$G67,Lista_CUIT!$A$1:$D$2241,3,0)),"CUIT NO CARGADO") -> Honorarios Admin | K67: =IFERROR(IF('May-24'!$G67="","-",VLOOKUP('May-24'!$G67,Lista_CUIT!$A$1:$D$2241,4,0)),"CUIT NO CARGADO") -> 0
D68: 45420 | E68: 2 | F68: 98477 | G68: 30554466806 | H68: =IFERROR(IF('May-24'!$G68="","-",VLOOKUP('May-24'!$G68,Lista_CUIT!$A$1:$D$2241,2,0)),"CUIT NO CARGADO") -> ASOCIACION DE IMPORTADORES Y EXPORTADORES DE LA REPUBLICA ARGENTINA | I68: 10000 | J68: =IFERROR(IF('May-24'!$G68="","-",VLOOKUP('May-24'!$G68,Lista_CUIT!$A$1:$D$2241,3,0)),"CUIT NO CARGADO") -> FLETE-LOGISTICA | K68: =IFERROR(IF('May-24'!$G68="","-",VLOOKUP('May-24'!$G68,Lista_CUIT!$A$1:$D$2241,4,0)),"CUIT NO CARGADO") -> 0
D69: 45420 | E69: 2 | F69: 171 | G69: 20136544625 | H69: =IFERROR(IF('May-24'!$G69="","-",VLOOKUP('May-24'!$G69,Lista_CUIT!$A$1:$D$2241,2,0)),"CUIT NO CARGADO") -> RODRIGUEZ DE LA FUEN HECTOR MARCELO | I69: 1000000 | J69: =IFERROR(IF('May-24'!$G69="","-",VLOOKUP('May-24'!$G69,Lista_CUIT!$A$1:$D$2241,3,0)),"CUIT NO CARGADO") -> Honorarios Admin | K69: =IFERROR(IF('May-24'!$G69="","-",VLOOKUP('May-24'!$G69,Lista_CUIT!$A$1:$D$2241,4,0)),"CUIT NO CARGADO") -> 0
D70: 45422 | E70: 2 | F70: 780 | G70: 20400104094 | H70: =IFERROR(IF('May-24'!$G70="","-",VLOOKUP('May-24'!$G70,Lista_CUIT!$A$1:$D$2241,2,0)),"CUIT NO CARGADO") -> FEDERICO BOTINDARI | I70: 50368.5 | J70: =IFERROR(IF('May-24'!$G70="","-",VLOOKUP('May-24'!$G70,Lista_CUIT!$A$1:$D$2241,3,0)),"CUIT NO CARGADO") -> Honorarios Contables | K70: =IFERROR(IF('May-24'!$G70="","-",VLOOKUP('May-24'!$G70,Lista_CUIT!$A$1:$D$2241,4,0)),"CUIT NO CARGADO") -> 0
D71: 45427 | E71: 1 | F71: 1442346 | G71: 30714928577 | H71: =IFERROR(IF('May-24'!$G71="","-",VLOOKUP('May-24'!$G71,Lista_CUIT!$A$1:$D$2241,2,0)),"CUIT NO CARGADO") -> SIMPLEX VILLI SA | I71: 9408 | J71: =IFERROR(IF('May-24'!$G71="","-",VLOOKUP('May-24'!$G71,Lista_CUIT!$A$1:$D$2241,3,0)),"CUIT NO CARGADO") -> Gastos Oficina | K71: =IFERROR(IF('May-24'!$G71="","-",VLOOKUP('May-24'!$G71,Lista_CUIT!$A$1:$D$2241,4,0)),"CUIT NO CARGADO") -> 0
D72: 45432 | E72: 1 | F72: 431 | G72: 27925308868 | H72: =IFERROR(IF('May-24'!$G72="","-",VLOOKUP('May-24'!$G72,Lista_CUIT!$A$1:$D$2241,2,0)),"CUIT NO CARGADO") -> LOPEZ MOLINA MARIA | I72: 10000 | J72: =IFERROR(IF('May-24'!$G72="","-",VLOOKUP('May-24'!$G72,Lista_CUIT!$A$1:$D$2241,3,0)),"CUIT NO CARGADO") -> GASTOS VARIOS | K72: =IFERROR(IF('May-24'!$G72="","-",VLOOKUP('May-24'!$G72,Lista_CUIT!$A$1:$D$2241,4,0)),"CUIT NO CARGADO") -> 0
... D75: 45441 | E75: 9 | F75: 4305086 | G75: 33715179119 | H75: =IFERROR(IF('May-24'!$G75="","-",VLOOKUP('May-24'!$G75,Lista_CUIT!$A$1:$D$2241,2,0)),"CUIT NO CARGADO") -> FONDO DE COOPERACION TECNICA Y FINANCIERA - CECBA - SL Y T - LEY 23.412 | I75: 8500 | J75: =IFERROR(IF('May-24'!$G75="","-",VLOOKUP('May-24'!$G75,Lista_CUIT!$A$1:$D$2241,3,0)),"CUIT NO CARGADO") -> Servicios Informaticos | K75: =IFERROR(IF('May-24'!$G75="","-",VLOOKUP('May-24'!$G75,Lista_CUIT!$A$1:$D$2241,4,0)),"CUIT NO CARGADO") -> 0
H76: =IFERROR(IF('May-24'!$G76="","-",VLOOKUP('May-24'!$G76,Lista_CUIT!$A$1:$D$2241,2,0)),"CUIT NO CARGADO") -> - | J76: =IFERROR(IF('May-24'!$G76="","-",VLOOKUP('May-24'!$G76,Lista_CUIT!$A$1:$D$2241,3,0)),"CUIT NO CARGADO") -> - | K76: =IFERROR(IF('May-24'!$G76="","-",VLOOKUP('May-24'!$G76,Lista_CUIT!$A$1:$D$2241,4,0)),"CUIT NO CARGADO") -> -
H77: =IFERROR(IF('May-24'!$G77="","-",VLOOKUP('May-24'!$G77,Lista_CUIT!$A$1:$D$2241,2,0)),"CUIT NO CARGADO") -> - | J77: =IFERROR(IF('May-24'!$G77="","-",VLOOKUP('May-24'!$G77,Lista_CUIT!$A$1:$D$2241,3,0)),"CUIT NO CARGADO") -> - | K77: =IFERROR(IF('May-24'!$G77="","-",VLOOKUP('May-24'!$G77,Lista_CUIT!$A$1:$D$2241,4,0)),"CUIT NO CARGADO") -> -
D78: Total | I78: =SUBTOTAL(109,'May-24'!$I$61:$I$77) -> 5361220.5
B84: LIBRO IVA VENTAS | K84: =N1 -> 45413
B86: VENTAS "A"
B87: FECHA | C87: TIPO | D87: PTO VENTA | E87: Nº FACTURA | F87: CUIT | G87: RAZON SOCIAL | H87: IMPORTE NETO | I87: IVA 21% | J87: IVA 10,5% | K87: EXENTO | L87: TOTAL | M87: Provincia
B88: 45414 | C88: 1 | D88: 3 | E88: 188 | F88: 30638318470 | G88: =IFERROR(IF('May-24'!$F88="","-",VLOOKUP('May-24'!$F88,Lista_CUIT!$A$1:$D$2241,2,0)),"CUIT NO CARGADO") -> DELTA COMPRESION S R L | H88: 32300970 | I88: =13306995*0.21 -> 2794468.9 | J88: 1994371.9 | L88: =SUM('May-24'!$H88:$K88) -> 37089811
B89: 45421 | C89: 1 | D89: 3 | E89: 189 | F89: 30628274327 | G89: =IFERROR(IF('May-24'!$F89="","-",VLOOKUP('May-24'!$F89,Lista_CUIT!$A$1:$D$2241,2,0)),"CUIT NO CARGADO") -> AGIRA S A | H89: 90100 | I89: ='May-24'!$H89*0.21 -> 18921 | L89: =SUM('May-24'!$H89:$K89) -> 109021
B90: 45421 | C90: 1 | D90: 3 | E90: 190 | F90: 30638318470 | G90: =IFERROR(IF('May-24'!$F90="","-",VLOOKUP('May-24'!$F90,Lista_CUIT!$A$1:$D$2241,2,0)),"CUIT NO CARGADO") -> DELTA COMPRESION S R L | H90: 2443061.5 | I90: =1081200*0.21 -> 227052 | J90: 142997.71 | L90: =SUM('May-24'!$H90:$K90) -> 2813111.2
B91: 45428 | C91: 1 | D91: 3 | E91: 193 | F91: 30718512545 | G91: =IFERROR(IF('May-24'!$F91="","-",VLOOKUP('May-24'!$F91,Lista_CUIT!$A$1:$D$2241,2,0)),"CUIT NO CARGADO") -> MAJUBEN MDP SERVICIOS S.R.L. | H91: 4977500 | J91: ='May-24'!$H91*0.105 -> 522637.5 | L91: =SUM('May-24'!$H91:$K91) -> 5500137.5
B92: 45428 | C92: 1 | D92: 3 | E92: 192 | F92: 20228469492 | G92: =IFERROR(IF('May-24'!$F92="","-",VLOOKUP('May-24'!$F92,Lista_CUIT!$A$1:$D$2241,2,0)),"CUIT NO CARGADO") -> DOMINGUEZ LAGANA GONZALO FABIAN | H92: 3122250 | I92: ='May-24'!$H92*0.21 -> 655672.5 | L92: =SUM('May-24'!$H92:$K92) -> 3777922.5
B93: 45428 | C93: 1 | D93: 3 | E93: 191 | F93: 30628274327 | G93: =IFERROR(IF('May-24'!$F93="","-",VLOOKUP('May-24'!$F93,Lista_CUIT!$A$1:$D$2241,2,0)),"CUIT NO CARGADO") -> AGIRA S A | H93: 362000 | I93: ='May-24'!$H93*0.21 -> 76020 | L93: =SUM('May-24'!$H93:$K93) -> 438020
B94: 45432 | C94: 1 | D94: 3 | E94: 194 | F94: 20228469492 | G94: =IFERROR(IF('May-24'!$F94="","-",VLOOKUP('May-24'!$F94,Lista_CUIT!$A$1:$D$2241,2,0)),"CUIT NO CARGADO") -> DOMINGUEZ LAGANA GONZALO FABIAN | H94: 2086100 | I94: ='May-24'!$H94*0.21 -> 438081 | L94: =SUM('May-24'!$H94:$K94) -> 2524181
B95: 45432 | C95: 3 | D95: 3 | E95: 20 | F95: 20228469492 | G95: =IFERROR(IF('May-24'!$F95="","-",VLOOKUP('May-24'!$F95,Lista_CUIT!$A$1:$D$2241,2,0)),"CUIT NO CARGADO") -> DOMINGUEZ LAGANA GONZALO FABIAN | H95: -3122250 | I95: ='May-24'!$H95*0.21 -> -655672.5 | L95: =SUM('May-24'!$H95:$K95) -> -3777922.5
B96: 45433 | C96: 1 | D96: 3 | E96: 195 | F96: 30638318470 | G96: =IFERROR(IF('May-24'!$F96="","-",VLOOKUP('May-24'!$F96,Lista_CUIT!$A$1:$D$2241,2,0)),"CUIT NO CARGADO") -> DELTA COMPRESION S R L | H96: 19226900 | J96: ='May-24'!$H96*0.105 -> 2018824.5 | L96: =SUM('May-24'!$H96:$K96) -> 21245724
B97: 45435 | C97: 1 | D97: 3 | E97: 196 | F97: 30718512545 | G97: =IFERROR(IF('May-24'!$F97="","-",VLOOKUP('May-24'!$F97,Lista_CUIT!$A$1:$D$2241,2,0)),"CUIT NO CARGADO") -> MAJUBEN MDP SERVICIOS S.R.L. | H97: 363600 | I97: ='May-24'!$H97*0.21 -> 76356 | L97: =SUM('May-24'!$H97:$K97) -> 439956
B98: 45443 | C98: 1 | D98: 3 | E98: 197 | F98: 30638318470 | G98: =IFERROR(IF('May-24'!$F98="","-",VLOOKUP('May-24'!$F98,Lista_CUIT!$A$1:$D$2241,2,0)),"CUIT NO CARGADO") -> DELTA COMPRESION S R L | H98: 23224740 | J98: ='May-24'!$H98*0.105 -> 2438597.7 | L98: =SUM('May-24'!$H98:$K98) -> 25663338
G99: =IFERROR(IF('May-24'!$F99="","-",VLOOKUP('May-24'!$F99,Lista_CUIT!$A$1:$D$2241,2,0)),"CUIT NO CARGADO") -> - | I99: ='May-24'!$H99*0.21 -> 0 | L99: =SUM('May-24'!$H99:$K99) -> 0
G100: =IFERROR(IF('May-24'!$F100="","-",VLOOKUP('May-24'!$F100,Lista_CUIT!$A$1:$D$2241,2,0)),"CUIT NO CARGADO") -> - | I100: ='May-24'!$H100*0.21 -> 0 | L100: =SUM('May-24'!$H100:$K100) -> 0
G101: =IFERROR(IF('May-24'!$F101="","-",VLOOKUP('May-24'!$F101,Lista_CUIT!$A$1:$D$2241,2,0)),"CUIT NO CARGADO") -> - | I101: ='May-24'!$H101*0.21 -> 0 | L101: =SUM('May-24'!$H101:$K101) -> 0
G102: =IFERROR(IF('May-24'!$F102="","-",VLOOKUP('May-24'!$F102,Lista_CUIT!$A$1:$D$2241,2,0)),"CUIT NO CARGADO") -> - | I102: ='May-24'!$H102*0.21 -> 0 | L102: =SUM('May-24'!$H102:$K102) -> 0
G103: =IFERROR(IF('May-24'!$F103="","-",VLOOKUP('May-24'!$F103,Lista_CUIT!$A$1:$D$2241,2,0)),"CUIT NO CARGADO") -> - | I103: ='May-24'!$H103*0.21 -> 0 | L103: =SUM('May-24'!$H103:$K103) -> 0
B104: Total | H104: =SUBTOTAL(109,'May-24'!$H$88:$H$103) -> 85074972 | I104: =SUBTOTAL(109,'May-24'!$I$88:$I$103) -> 3630898.9 | J104: =SUBTOTAL(109,'May-24'!$J$88:$J$103) -> 7117429.3 | K104: =SUBTOTAL(109,'May-24'!$K$88:$K$103) -> 0 | L104: =SUBTOTAL(109,'May-24'!$L$88:$L$103) -> 95823300
B109: VENTAS "B"
B110: FECHA | C110: TIPO | D110: PTO VENTA | E110: Nº FACTURA | F110: CUIT | G110: RAZON SOCIAL | H110: IMPORTE NETO | I110: IVA 21% | J110: IVA 10,5% | K110: EXENTO | L110: TOTAL | M110: Provincia
B111: 45415 | C111: 6 | D111: 3 | E111: 9 | G111: =IFERROR(IF('May-24'!$F111="","-",VLOOKUP('May-24'!$F111,Lista_CUIT!$A$1:$D$2241,2,0)),"CUIT NO CARGADO") -> - | H111: 230914 | I111: ='May-24'!$H111*0.21 -> 48491.94 | L111: ='May-24'!$K111+'May-24'!$J111+'May-24'!$I111+'May-24'!$H111 -> 279405.94
B112: 45422 | C112: 6 | D112: 3 | E112: 10 | G112: =IFERROR(IF('May-24'!$F112="","-",VLOOKUP('May-24'!$F112,Lista_CUIT!$A$1:$D$2241,2,0)),"CUIT NO CARGADO") -> - | H112: 311017.5 | I112: ='May-24'!$H112*0.21 -> 65313.675 | L112: ='May-24'!$K112+'May-24'!$J112+'May-24'!$I112+'May-24'!$H112 -> 376331.17
G113: =IFERROR(IF('May-24'!$F113="","-",VLOOKUP('May-24'!$F113,Lista_CUIT!$A$1:$D$2241,2,0)),"CUIT NO CARGADO") -> - | I113: ='May-24'!$H113*0.21 -> 0 | L113: ='May-24'!$K113+'May-24'!$J113+'May-24'!$I113+'May-24'!$H113 -> 0
G114: =IFERROR(IF('May-24'!$F114="","-",VLOOKUP('May-24'!$F114,Lista_CUIT!$A$1:$D$2241,2,0)),"CUIT NO CARGADO") -> - | I114: ='May-24'!$H114*0.21 -> 0 | L114: ='May-24'!$K114+'May-24'!$J114+'May-24'!$I114+'May-24'!$H114 -> 0
G115: =IFERROR(IF('May-24'!$F115="","-",VLOOKUP('May-24'!$F115,Lista_CUIT!$A$1:$D$2241,2,0)),"CUIT NO CARGADO") -> - | I115: ='May-24'!$H115*0.21 -> 0 | L115: ='May-24'!$K115+'May-24'!$J115+'May-24'!$I115+'May-24'!$H115 -> 0
B116: Total | H116: =SUBTOTAL(109,'May-24'!$H$111:$H$115) -> 541931.5 | I116: =SUBTOTAL(109,'May-24'!$I$111:$I$115) -> 113805.61 | J116: =SUBTOTAL(109,'May-24'!$J$111:$J$115) -> 0 | K116: =SUBTOTAL(109,'May-24'!$K$111:$K$115) -> 0 | L116: =SUBTOTAL(109,'May-24'!$L$111:$L$115) -> 655737.11 | M116: =SUBTOTAL(103,'May-24'!$M$111:$M$115) -> 0
B119: VENTAS "E"
B120: FECHA | C120: TIPO | D120: PTO VENTA | E120: Nº FACTURA | F120: CUIT | G120: RAZON SOCIAL | H120: USD | I120: Columna2 | J120: Columna1 | K120: TIPO DE CAMBIO2 | L120: TOTAL | M120: Provincia
B121: 45414 | D121: 30 | E121: 77 | F121: 55000000050 | G121: =IFERROR(IF('May-24'!$F121="","-",VLOOKUP('May-24'!$F121,Lista_CUIT!$A$1:$D$2241,2,0)),"CUIT NO CARGADO") -> GAS FUTURO SISTEMAS DE COMPRESSÃO LTDA | H121: 14400 | K121: 876.5 | L121: =H121*K121 -> 12621600
B122: 45420 | D122: 30 | E122: 78 | F122: 55000002223 | G122: =IFERROR(IF('May-24'!$F122="","-",VLOOKUP('May-24'!$F122,Lista_CUIT!$A$1:$D$2241,2,0)),"CUIT NO CARGADO") -> Solution Supply SAC | H122: 2180 | K122: 880.5 | L122: =H122*K122 -> 1919490
B123: 45422 | D123: 30 | E123: 79 | F123: 55000000050 | G123: =IFERROR(IF('May-24'!$F123="","-",VLOOKUP('May-24'!$F123,Lista_CUIT!$A$1:$D$2241,2,0)),"CUIT NO CARGADO") -> GAS FUTURO SISTEMAS DE COMPRESSÃO LTDA | H123: 1650 | K123: 882 | L123: =H123*K123 -> 1455300
B124: 45425 | D124: 30 | E124: 82 | F124: 55000002223 | G124: =IFERROR(IF('May-24'!$F124="","-",VLOOKUP('May-24'!$F124,Lista_CUIT!$A$1:$D$2241,2,0)),"CUIT NO CARGADO") -> Solution Supply SAC | H124: 2180 | K124: 882.5 | L124: =H124*K124 -> 1923850
B125: 45425 | D125: 30 | E125: 81 | F125: 55000000050 | G125: =IFERROR(IF('May-24'!$F125="","-",VLOOKUP('May-24'!$F125,Lista_CUIT!$A$1:$D$2241,2,0)),"CUIT NO CARGADO") -> GAS FUTURO SISTEMAS DE COMPRESSÃO LTDA | H125: 1650 | K125: 882.5 | L125: =H125*K125 -> 1456125
B126: 45425 | D126: 30 | E126: 80 | F126: 55000002223 | G126: =IFERROR(IF('May-24'!$F126="","-",VLOOKUP('May-24'!$F126,Lista_CUIT!$A$1:$D$2241,2,0)),"CUIT NO CARGADO") -> Solution Supply SAC | H126: 2180 | K126: 882.5 | L126: =H126*K126 -> 1923850
...

Sheet Jun-24
B1: LIBRO IVA COMPRAS | G1: ='Abr-24'!G1:M1 -> CORITEC S. R. L. | N1: =EDATE('Abr-24'!N1,2) -> 45078
B3: TOTAL COMPRAS | G3: TOTAL CREDITO FISCAL | J3: TOTAL VENTAS NETAS | M3: TOTAL DEBITO FISCAL | P3: RESULTADO
B4: =SUM('Jun-24'!$H$44)+'Jun-24'!$G$54 -> 6085853.2 | G4: ='Jun-24'!$I$44+'Jun-24'!$J$44+'Jun-24'!$K$44+'Jun-24'!$H$54+'Jun-24'!$I$54 -> 1259020 | J4: ='Jun-24'!$H$91+'Jun-24'!$H$102 -> 40888667 | M4: ='Jun-24'!$I$91+'Jun-24'!$J$91+'Jun-24'!$I$102+'Jun-24'!$J$102 -> 4689871.8 | P4: =G4-M4 -> -3430851.9
B8: FECHA | C8: TIPO | D8: PTO VTA | E8: NRO. CPTE | F8: CUIT | G8: RAZON SOCIAL | H8: NETO GRAVADO | I8: IVA 21 % | J8: IVA 27% | K8: IVA 10,5% | L8: PERC. IVA | M8: PERC IIBB BS AS | N8: PERC. IIBB CABA | O8: Otros / No Grav. | P8: TOTAL | Q8: Tipo de Gasto | R8: Provincia
B9: 45444 | C9: 1 | D9: 3 | E9: 228991 | F9: 30707135596 | G9: =IFERROR(IF('Jun-24'!$F9="","-",VLOOKUP('Jun-24'!$F9,Lista_CUIT!$A$1:$D$2241,2,0)),"CUIT NO CARGADO") -> CITILAN ARGENTINA S.A. | H9: 18640 | I9: =IF('Jun-24'!$H9="","",'Jun-24'!$H9*0.21) -> 3914.4 | P9: =SUM('Jun-24'!$H9:$O9) -> 22554.4 | Q9: =IFERROR(IF('Jun-24'!$F9="","-",VLOOKUP('Jun-24'!$F9,Lista_CUIT!$A$1:$D$2241,3,0)),"CUIT NO CARGADO") -> Telefonia | R9: =IFERROR(IF('Jun-24'!$F9="","-",VLOOKUP('Jun-24'!$F9,Lista_CUIT!$A$1:$D$2241,4,0)),"CUIT NO CARGADO") -> 0
B10: 45444 | C10: 1 | D10: 7 | E10: 16187 | F10: 30604413482 | G10: =IFERROR(IF('Jun-24'!$F10="","-",VLOOKUP('Jun-24'!$F10,Lista_CUIT!$A$1:$D$2241,2,0)),"CUIT NO CARGADO") -> BULONERA VIETRI SOCIEDAD DE RESPONSABILIDAD LIMITADA | H10: 96750 | I10: =IF('Jun-24'!$H10="","",'Jun-24'!$H10*0.21) -> 20317.5 | P10: =SUM('Jun-24'!$H10:$O10) -> 117067.5 | Q10: =IFERROR(IF('Jun-24'!$F10="","-",VLOOKUP('Jun-24'!$F10,Lista_CUIT!$A$1:$D$2241,3,0)),"CUIT NO CARGADO") -> INSUMO | R10: =IFERROR(IF('Jun-24'!$F10="","-",VLOOKUP('Jun-24'!$F10,Lista_CUIT!$A$1:$D$2241,4,0)),"CUIT NO CARGADO") -> 0
B11: 45444 | C11: 1 | D11: 3 | E11: 761 | F11: 30715402765 | G11: =IFERROR(IF('Jun-24'!$F11="","-",VLOOKUP('Jun-24'!$F11,Lista_CUIT!$A$1:$D$2241,2,0)),"CUIT NO CARGADO") -> RIO 265 S.R.L. | H11: 54545.48 | I11: =IF('Jun-24'!$H11="","",'Jun-24'!$H11*0.21) -> 11454.551 | P11: =SUM('Jun-24'!$H11:$O11) -> 66000.031 | Q11: =IFERROR(IF('Jun-24'!$F11="","-",VLOOKUP('Jun-24'!$F11,Lista_CUIT!$A$1:$D$2241,3,0)),"CUIT NO CARGADO") -> GASTOS VARIOS | R11: =IFERROR(IF('Jun-24'!$F11="","-",VLOOKUP('Jun-24'!$F11,Lista_CUIT!$A$1:$D$2241,4,0)),"CUIT NO CARGADO") -> 0
B12: 45446 | C12: 1 | D12: 106 | E12: 738981 | F12: 30594494187 | G12: =IFERROR(IF('Jun-24'!$F12="","-",VLOOKUP('Jun-24'!$F12,Lista_CUIT!$A$1:$D$2241,2,0)),"CUIT NO CARGADO") -> FEDERAL EXPRESS CORPORATION | H12: 0 | I12: =IF('Jun-24'!$H12="","",'Jun-24'!$H12*0.21) -> 0 | O12: 294669.05 | P12: =SUM('Jun-24'!$H12:$O12) -> 294669.05 | Q12: =IFERROR(IF('Jun-24'!$F12="","-",VLOOKUP('Jun-24'!$F12,Lista_CUIT!$A$1:$D$2241,3,0)),"CUIT NO CARGADO") -> Gastos Importacion | R12: =IFERROR(IF('Jun-24'!$F12="","-",VLOOKUP('Jun-24'!$F12,Lista_CUIT!$A$1:$D$2241,4,0)),"CUIT NO CARGADO") -> 0
B13: 45446 | C13: 1 | D13: 106 | E13: 738982 | F13: 30594494187 | G13: =IFERROR(IF('Jun-24'!$F13="","-",VLOOKUP('Jun-24'!$F13,Lista_CUIT!$A$1:$D$2241,2,0)),"CUIT NO CARGADO") -> FEDERAL EXPRESS CORPORATION | H13: 0 | I13: =IF('Jun-24'!$H13="","",'Jun-24'!$H13*0.21) -> 0 | O13: 407229.16 | P13: =SUM('Jun-24'!$H13:$O13) -> 407229.16 | Q13: =IFERROR(IF('Jun-24'!$F13="","-",VLOOKUP('Jun-24'!$F13,Lista_CUIT!$A$1:$D$2241,3,0)),"CUIT NO CARGADO") -> Gastos Importacion | R13: =IFERROR(IF('Jun-24'!$F13="","-",VLOOKUP('Jun-24'!$F13,Lista_CUIT!$A$1:$D$2241,4,0)),"CUIT NO CARGADO") -> 0
B14: 45446 | C14: 1 | D14: 7 | E14: 16197 | F14: 30604413482 | G14: =IFERROR(IF('Jun-24'!$F14="","-",VLOOKUP('Jun-24'!$F14,Lista_CUIT!$A$1:$D$2241,2,0)),"CUIT NO CARGADO") -> BULONERA VIETRI SOCIEDAD DE RESPONSABILIDAD LIMITADA | H14: 34800 | I14: =IF('Jun-24'!$H14="","",'Jun-24'!$H14*0.21) -> 7308 | P14: =SUM('Jun-24'!$H14:$O14) -> 42108 | Q14: =IFERROR(IF('Jun-24'!$F14="","-",VLOOKUP('Jun-24'!$F14,Lista_CUIT!$A$1:$D$2241,3,0)),"CUIT NO CARGADO") -> INSUMO | R14: =IFERROR(IF('Jun-24'!$F14="","-",VLOOKUP('Jun-24'!$F14,Lista_CUIT!$A$1:$D$2241,4,0)),"CUIT NO CARGADO") -> 0
B15: 45446 | C15: 1 | D15: 2 | E15: 752 | F15: 20296550184 | G15: =IFERROR(IF('Jun-24'!$F15="","-",VLOOKUP('Jun-24'!$F15,Lista_CUIT!$A$1:$D$2241,2,0)),"CUIT NO CARGADO") -> COSTA DIEGO ALEJANDRO | H15: 575800 | I15: =IF('Jun-24'!$H15="","",'Jun-24'!$H15*0.21) -> 120918 | P15: =SUM('Jun-24'!$H15:$O15) -> 696718 | Q15: =IFERROR(IF('Jun-24'!$F15="","-",VLOOKUP('Jun-24'!$F15,Lista_CUIT!$A$1:$D$2241,3,0)),"CUIT NO CARGADO") -> Mat. Prima | R15: =IFERROR(IF('Jun-24'!$F15="","-",VLOOKUP('Jun-24'!$F15,Lista_CUIT!$A$1:$D$2241,4,0)),"CUIT NO CARGADO") -> 0
B16: 45447 | C16: 1 | D16: 12 | E16: 13219 | F16: 30694497701 | G16: =IFERROR(IF('Jun-24'!$F16="","-",VLOOKUP('Jun-24'!$F16,Lista_CUIT!$A$1:$D$2241,2,0)),"CUIT NO CARGADO") -> DECOR ALUM SRL | H16: 58134.44 | I16: =IF('Jun-24'!$H16="","",'Jun-24'!$H16*0.21) -> 12208.232 | P16: =SUM('Jun-24'!$H16:$O16) -> 70342.672 | Q16: =IFERROR(IF('Jun-24'!$F16="","-",VLOOKUP('Jun-24'!$F16,Lista_CUIT!$A$1:$D$2241,3,0)),"CUIT NO CARGADO") -> INSUMO | R16: =IFERROR(IF('Jun-24'!$F16="","-",VLOOKUP('Jun-24'!$F16,Lista_CUIT!$A$1:$D$2241,4,0)),"CUIT NO CARGADO") -> 0
B17: 45447 | C17: 1 | D17: 4 | E17: 101620 | F17: 30559932236 | G17: =IFERROR(IF('Jun-24'!$F17="","-",VLOOKUP('Jun-24'!$F17,Lista_CUIT!$A$1:$D$2241,2,0)),"CUIT NO CARGADO") -> ELECTRONICA ELEMON S A | H17: 1047897.6 | I17: =857376*0.21 -> 180048.96 | K17: =190521.59*0.105 -> 20004.767 | P17: =SUM('Jun-24'!$H17:$O17) -> 1247951.3 | Q17: =IFERROR(IF('Jun-24'!$F17="","-",VLOOKUP('Jun-24'!$F17,Lista_CUIT!$A$1:$D$2241,3,0)),"CUIT NO CARGADO") -> Mat. Prima | R17: =IFERROR(IF('Jun-24'!$F17="","-",VLOOKUP('Jun-24'!$F17,Lista_CUIT!$A$1:$D$2241,4,0)),"CUIT NO CARGADO") -> 0
B18: 45448 | C18: 1 | D18: 7 | E18: 16226 | F18: 30604413482 | G18: =IFERROR(IF('Jun-24'!$F18="","-",VLOOKUP('Jun-24'!$F18,Lista_CUIT!$A$1:$D$2241,2,0)),"CUIT NO CARGADO") -> BULONERA VIETRI SOCIEDAD DE RESPONSABILIDAD LIMITADA | H18: 368972.81 | I18: =IF('Jun-24'!$H18="","",'Jun-24'!$H18*0.21) -> 77484.29 | P18: =SUM('Jun-24'!$H18:$O18) -> 446457.1 | Q18: =IFERROR(IF('Jun-24'!$F18="","-",VLOOKUP('Jun-24'!$F18,Lista_CUIT!$A$1:$D$2241,3,0)),"CUIT NO CARGADO") -> INSUMO | R18: =IFERROR(IF('Jun-24'!$F18="","-",VLOOKUP('Jun-24'!$F18,Lista_CUIT!$A$1:$D$2241,4,0)),"CUIT NO CARGADO") -> 0
B19: 45449 | C19: 1 | D19: 1 | E19: 812 | F19: 30715048066 | G19: =IFERROR(IF('Jun-24'!$F19="","-",VLOOKUP('Jun-24'!$F19,Lista_CUIT!$A$1:$D$2241,2,0)),"CUIT NO CARGADO") -> ROLLS Y EMPANADAS SA | H19: 685860 | I19: =IF('Jun-24'!$H19="","",'Jun-24'!$H19*0.21) -> 144030.6 | P19: =SUM('Jun-24'!$H19:$O19) -> 829890.6 | Q19: =IFERROR(IF('Jun-24'!$F19="","-",VLOOKUP('Jun-24'!$F19,Lista_CUIT!$A$1:$D$2241,3,0)),"CUIT NO CARGADO") -> CATERING | R19: =IFERROR(IF('Jun-24'!$F19="","-",VLOOKUP('Jun-24'!$F19,Lista_CUIT!$A$1:$D$2241,4,0)),"CUIT NO CARGADO") -> 0
B20: 45449 | C20: 1 | D20: 1 | E20: 800 | F20: 30715048066 | G20: =IFERROR(IF('Jun-24'!$F20="","-",VLOOKUP('Jun-24'!$F20,Lista_CUIT!$A$1:$D$2241,2,0)),"CUIT NO CARGADO") -> ROLLS Y EMPANADAS SA | H20: 621040 | I20: =IF('Jun-24'!$H20="","",'Jun-24'!$H20*0.21) -> 130418.4 | P20: =SUM('Jun-24'!$H20:$O20) -> 751458.4 | Q20: =IFERROR(IF('Jun-24'!$F20="","-",VLOOKUP('Jun-24'!$F20,Lista_CUIT!$A$1:$D$2241,3,0)),"CUIT NO CARGADO") -> CATERING | R20: =IFERROR(IF('Jun-24'!$F20="","-",VLOOKUP('Jun-24'!$F20,Lista_CUIT!$A$1:$D$2241,4,0)),"CUIT NO CARGADO") -> 0
B21: 45450 | C21: 1 | D21: 327 | E21: 367 | F21: 30556565798 | G21: =IFERROR(IF('Jun-24'!$F21="","-",VLOOKUP('Jun-24'!$F21,Lista_CUIT!$A$1:$D$2241,2,0)),"CUIT NO CARGADO") -> VICTOR MASSON TRANSPORTES CRUZ DEL SUR S A | H21: 18042 | I21: =IF('Jun-24'!$H21="","",'Jun-24'!$H21*0.21) -> 3788.82 | P21: =SUM('Jun-24'!$H21:$O21) -> 21830.82 | Q21: =IFERROR(IF('Jun-24'!$F21="","-",VLOOKUP('Jun-24'!$F21,Lista_CUIT!$A$1:$D$2241,3,0)),"CUIT NO CARGADO") -> FLETE-LOGISTICA | R21: =IFERROR(IF('Jun-24'!$F21="","-",VLOOKUP('Jun-24'!$F21,Lista_CUIT!$A$1:$D$2241,4,0)),"CUIT NO CARGADO") -> 0
B22: 45454 | C22: 1 | D22: 2466 | E22: 656251 | F22: 30678814357 | G22: =IFERROR(IF('Jun-24'!$F22="","-",VLOOKUP('Jun-24'!$F22,Lista_CUIT!$A$1:$D$2241,2,0)),"CUIT NO CARGADO") -> TELEFONICA MOVILES ARG | H22: 21524.65 | J22: ='Jun-24'!$H22*0.27 -> 5811.6555 | L22: 645.74 | O22: 1124.2 | P22: =SUM('Jun-24'!$H22:$O22) -> 29106.246 | Q22: =IFERROR(IF('Jun-24'!$F22="","-",VLOOKUP('Jun-24'!$F22,Lista_CUIT!$A$1:$D$2241,3,0)),"CUIT NO CARGADO") -> Telefonia | R22: =IFERROR(IF('Jun-24'!$F22="","-",VLOOKUP('Jun-24'!$F22,Lista_CUIT!$A$1:$D$2241,4,0)),"CUIT NO CARGADO") -> 0
B23: 45456 | C23: 1 | D23: 3 | E23: 238092 | F23: 33658043779 | G23: =IFERROR(IF('Jun-24'!$F23="","-",VLOOKUP('Jun-24'!$F23,Lista_CUIT!$A$1:$D$2241,2,0)),"CUIT NO CARGADO") -> BUREAU VERITAS ARGENTINA SA | H23: 440000 | I23: =IF('Jun-24'!$H23="","",'Jun-24'!$H23*0.21) -> 92400 | P23: =SUM('Jun-24'!$H23:$O23) -> 532400 | Q23: =IFERROR(IF('Jun-24'!$F23="","-",VLOOKUP('Jun-24'!$F23,Lista_CUIT!$A$1:$D$2241,3,0)),"CUIT NO CARGADO") -> Servicios Informaticos | R23: =IFERROR(IF('Jun-24'!$F23="","-",VLOOKUP('Jun-24'!$F23,Lista_CUIT!$A$1:$D$2241,4,0)),"CUIT NO CARGADO") -> 0
B24: 45461 | C24: 1 | D24: 106 | E24: 743680 | F24: 30594494187 | G24: =IFERROR(IF('Jun-24'!$F24="","-",VLOOKUP('Jun-24'!$F24,Lista_CUIT!$A$1:$D$2241,2,0)),"CUIT NO CARGADO") -> FEDERAL EXPRESS CORPORATION | H24: 0 | I24: =IF('Jun-24'!$H24="","",'Jun-24'!$H24*0.21) -> 0 | O24: 398826.94 | P24: =SUM('Jun-24'!$H24:$O24) -> 398826.94 | Q24: =IFERROR(IF('Jun-24'!$F24="","-",VLOOKUP('Jun-24'!$F24,Lista_CUIT!$A$1:$D$2241,3,0)),"CUIT NO CARGADO") -> Gastos Importacion | R24: =IFERROR(IF('Jun-24'!$F24="","-",VLOOKUP('Jun-24'!$F24,Lista_CUIT!$A$1:$D$2241,4,0)),"CUIT NO CARGADO") -> 0
B25: 45468 | C25: 1 | D25: 5 | E25: 11670 | F25: 30716006391 | G25: =IFERROR(IF('Jun-24'!$F25="","-",VLOOKUP('Jun-24'!$F25,Lista_CUIT!$A$1:$D$2241,2,0)),"CUIT NO CARGADO") -> ALLISING | H25: 31885.95 | I25: =IF('Jun-24'!$H25="","",'Jun-24'!$H25*0.21) -> 6696.0495 | P25: =SUM('Jun-24'!$H25:$O25) -> 38581.999 | Q25: =IFERROR(IF('Jun-24'!$F25="","-",VLOOKUP('Jun-24'!$F25,Lista_CUIT!$A$1:$D$2241,3,0)),"CUIT NO CARGADO") -> GASTOS VARIOS | R25: =IFERROR(IF('Jun-24'!$F25="","-",VLOOKUP('Jun-24'!$F25,Lista_CUIT!$A$1:$D$2241,4,0)),"CUIT NO CARGADO") -> 0
B26: 45469 | C26: 1 | D26: 5 | E26: 818 | F26: 20309706197 | G26: =IFERROR(IF('Jun-24'!$F26="","-",VLOOKUP('Jun-24'!$F26,Lista_CUIT!$A$1:$D$2241,2,0)),"CUIT NO CARGADO") -> QUIROGA ARIEL ALEJANDRO | H26: 49585.95 | I26: =IF('Jun-24'!$H26="","",'Jun-24'!$H26*0.21) -> 10413.049 | P26: =SUM('Jun-24'!$H26:$O26) -> 59998.999 | Q26: =IFERROR(IF('Jun-24'!$F26="","-",VLOOKUP('Jun-24'!$F26,Lista_CUIT!$A$1:$D$2241,3,0)),"CUIT NO CARGADO") -> Ropa de Trabajo | R26: =IFERROR(IF('Jun-24'!$F26="","-",VLOOKUP('Jun-24'!$F26,Lista_CUIT!$A$1:$D$2241,4,0)),"CUIT NO CARGADO") -> 0
B27: 45469 | C27: 1 | D27: 2 | E27: 9126 | F27: 33717240249 | G27: =IFERROR(IF('Jun-24'!$F27="","-",VLOOKUP('Jun-24'!$F27,Lista_CUIT!$A$1:$D$2241,2,0)),"CUIT NO CARGADO") -> PERFU FAN S.R.L | H27: 14238 | I27: =IF('Jun-24'!$H27="","",'Jun-24'!$H27*0.21) -> 2989.98 | P27: =SUM('Jun-24'!$H27:$O27) -> 17227.98 | Q27: =IFERROR(IF('Jun-24'!$F27="","-",VLOOKUP('Jun-24'!$F27,Lista_CUIT!$A$1:$D$2241,3,0)),"CUIT NO CARGADO") -> Gastos Oficina | R27: =IFERROR(IF('Jun-24'!$F27="","-",VLOOKUP('Jun-24'!$F27,Lista_CUIT!$A$1:$D$2241,4,0)),"CUIT NO CARGADO") -> 0
B28: 45469 | C28: 1 | D28: 3 | E28: 912 | F28: 27424730608 | G28: =IFERROR(IF('Jun-24'!$F28="","-",VLOOKUP('Jun-24'!$F28,Lista_CUIT!$A$1:$D$2241,2,0)),"CUIT NO CARGADO") -> VAZQUEZ CABRAL WANDA MILENA | H28: 28132.23 | I28: =IF('Jun-24'!$H28="","",'Jun-24'!$H28*0.21) -> 5907.7683 | P28: =SUM('Jun-24'!$H28:$O28) -> 34039.998 | Q28: =IFERROR(IF('Jun-24'!$F28="","-",VLOOKUP('Jun-24'!$F28,Lista_CUIT!$A$1:$D$2241,3,0)),"CUIT NO CARGADO") -> GASTOS VARIOS | R28: =IFERROR(IF('Jun-24'!$F28="","-",VLOOKUP('Jun-24'!$F28,Lista_CUIT!$A$1:$D$2241,4,0)),"CUIT NO CARGADO") -> 0
B29: 45469 | C29: 1 | D29: 7 | E29: 132873 | F29: 20181426846 | G29: =IFERROR(IF('Jun-24'!$F29="","-",VLOOKUP('Jun-24'!$F29,Lista_CUIT!$A$1:$D$2241,2,0)),"CUIT NO CARGADO") -> GRIDEL WALTER DIEGO | H29: 20080.17 | I29: =IF('Jun-24'!$H29="","",'Jun-24'!$H29*0.21) -> 4216.8357 | P29: =SUM('Jun-24'!$H29:$O29) -> 24297.006 | Q29: =IFERROR(IF('Jun-24'!$F29="","-",VLOOKUP('Jun-24'!$F29,Lista_CUIT!$A$1:$D$2241,3,0)),"CUIT NO CARGADO") -> INSUMO | R29: =IFERROR(IF('Jun-24'!$F29="","-",VLOOKUP('Jun-24'!$F29,Lista_CUIT!$A$1:$D$2241,4,0)),"CUIT NO CARGADO") -> 0
B30: 45469 | C30: 1 | D30: 2 | E30: 199 | F30: 20125142851 | G30: =IFERROR(IF('Jun-24'!$F30="","-",VLOOKUP('Jun-24'!$F30,Lista_CUIT!$A$1:$D$2241,2,0)),"CUIT NO CARGADO") -> FEDERICI NICOLAS JOSE | H30: 1269918 | I30: =IF('Jun-24'!$H30="","",'Jun-24'!$H30*0.21) -> 266682.78 | P30: =SUM('Jun-24'!$H30:$O30) -> 1536600.8 | Q30: =IFERROR(IF('Jun-24'!$F30="","-",VLOOKUP('Jun-24'!$F30,Lista_CUIT!$A$1:$D$2241,3,0)),"CUIT NO CARGADO") -> INSUMO | R30: =IFERROR(IF('Jun-24'!$F30="","-",VLOOKUP('Jun-24'!$F30,Lista_CUIT!$A$1:$D$2241,4,0)),"CUIT NO CARGADO") -> 0
B31: 45469 | C31: 1 | D31: 2 | E31: 200 | F31: 20125142851 | G31: =IFERROR(IF('Jun-24'!$F31="","-",VLOOKUP('Jun-24'!$F31,Lista_CUIT!$A$1:$D$2241,2,0)),"CUIT NO CARGADO") -> FEDERICI NICOLAS JOSE | H31: 285937.76 | I31: =IF('Jun-24'!$H31="","",'Jun-24'!$H31*0.21) -> 60046.93 | P31: =SUM('Jun-24'!$H31:$O31) -> 345984.69 | Q31: =IFERROR(IF('Jun-24'!$F31="","-",VLOOKUP('Jun-24'!$F31,Lista_CUIT!$A$1:$D$2241,3,0)),"CUIT NO CARGADO") -> INSUMO | R31: =IFERROR(IF('Jun-24'!$F31="","-",VLOOKUP('Jun-24'!$F31,Lista_CUIT!$A$1:$D$2241,4,0)),"CUIT NO CARGADO") -> 0
B32: 45470 | C32: 1 | D32: 3 | E32: 29970 | F32: 30715002848 | G32: =IFERROR(IF('Jun-24'!$F32="","-",VLOOKUP('Jun-24'!$F32,Lista_CUIT!$A$1:$D$2241,2,0)),"CUIT NO CARGADO") -> MASTER LEADER MUNDIAL S.A. | H32: 11730.57 | I32: =IF('Jun-24'!$H32="","",'Jun-24'!$H32*0.21) -> 2463.4197 | P32: =SUM('Jun-24'!$H32:$O32) -> 14193.99 | Q32: =IFERROR(IF('Jun-24'!$F32="","-",VLOOKUP('Jun-24'!$F32,Lista_CUIT!$A$1:$D$2241,3,0)),"CUIT NO CARGADO") -> INSUMO | R32: =IFERROR(IF('Jun-24'!$F32="","-",VLOOKUP('Jun-24'!$F32,Lista_CUIT!$A$1:$D$2241,4,0)),"CUIT NO CARGADO") -> BUENOS AIRES
B33: 45470 | C33: 1 | D33: 6 | E33: 15075 | F33: 30707756434 | G33: =IFERROR(IF('Jun-24'!$F33="","-",VLOOKUP('Jun-24'!$F33,Lista_CUIT!$A$1:$D$2241,2,0)),"CUIT NO CARGADO") -> SERVICIO INTEGRAL DE LIMPIEZA SRL | H33: 232000 | I33: =IF('Jun-24'!$H33="","",'Jun-24'!$H33*0.21) -> 48720 | P33: =SUM('Jun-24'!$H33:$O33) -> 280720 | Q33: =IFERROR(IF('Jun-24'!$F33="","-",VLOOKUP('Jun-24'!$F33,Lista_CUIT!$A$1:$D$2241,3,0)),"CUIT NO CARGADO") -> Mantenimiento | R33: =IFERROR(IF('Jun-24'!$F33="","-",VLOOKUP('Jun-24'!$F33,Lista_CUIT!$A$1:$D$2241,4,0)),"CUIT NO CARGADO") -> 0
B34: 45470 | C34: 1 | D34: 4 | E34: 12711 | F34: 33710719549 | G34: =IFERROR(IF('Jun-24'!$F34="","-",VLOOKUP('Jun-24'!$F34,Lista_CUIT!$A$1:$D$2241,2,0)),"CUIT NO CARGADO") -> FIVELEC S.R.L. | H34: 34181 | I34: =IF('Jun-24'!$H34="","",'Jun-24'!$H34*0.21) -> 7178.01 | P34: =SUM('Jun-24'!$H34:$O34) -> 41359.01 | Q34: =IFERROR(IF('Jun-24'!$F34="","-",VLOOKUP('Jun-24'!$F34,Lista_CUIT!$A$1:$D$2241,3,0)),"CUIT NO CARGADO") -> INSUMO | R34: =IFERROR(IF('Jun-24'!$F34="","-",VLOOKUP('Jun-24'!$F34,Lista_CUIT!$A$1:$D$2241,4,0)),"CUIT NO CARGADO") -> 0
B35: 45473 | C35: 1 | D35: 700 | E35: 675604 | F35: 30580111315 | G35: =IFERROR(IF('Jun-24'!$F35="","-",VLOOKUP('Jun-24'!$F35,Lista_CUIT!$A$1:$D$2241,2,0)),"CUIT NO CARGADO") -> DHL EXPRESS (ARGENTINA) S.A. | H35: 13957.5 | I35: =IF('Jun-24'!$H35="","",'Jun-24'!$H35*0.21) -> 2931.075 | O35: 654067.06 | P35: =SUM('Jun-24'!$H35:$O35) -> 670955.63 | Q35: =IFERROR(IF('Jun-24'!$F35="","-",VLOOKUP('Jun-24'!$F35,Lista_CUIT!$A$1:$D$2241,3,0)),"CUIT NO CARGADO") -> Gastos Importacion | R35: =IFERROR(IF('Jun-24'!$F35="","-",VLOOKUP('Jun-24'!$F35,Lista_CUIT!$A$1:$D$2241,4,0)),"CUIT NO CARGADO") -> 0
G36: =IFERROR(IF('Jun-24'!$F36="","-",VLOOKUP('Jun-24'!$F36,Lista_CUIT!$A$1:$D$2241,2,0)),"CUIT NO CARGADO") -> - | I36: =IF('Jun-24'!$H36="","",'Jun-24'!$H36*0.21) | P36: =SUM('Jun-24'!$H36:$O36) -> 0 | Q36: =IFERROR(IF('Jun-24'!$F36="","-",VLOOKUP('Jun-24'!$F36,Lista_CUIT!$A$1:$D$2241,3,0)),"CUIT NO CARGADO") -> - | R36: =IFERROR(IF('Jun-24'!$F36="","-",VLOOKUP('Jun-24'!$F36,Lista_CUIT!$A$1:$D$2241,4,0)),"CUIT NO CARGADO") -> -
G37: =IFERROR(IF('Jun-24'!$F37="","-",VLOOKUP('Jun-24'!$F37,Lista_CUIT!$A$1:$D$2241,2,0)),"CUIT NO CARGADO") -> - | I37: =IF('Jun-24'!$H37="","",'Jun-24'!$H37*0.21) | P37: =SUM('Jun-24'!$H37:$O37) -> 0 | Q37: =IFERROR(IF('Jun-24'!$F37="","-",VLOOKUP('Jun-24'!$F37,Lista_CUIT!$A$1:$D$2241,3,0)),"CUIT NO CARGADO") -> - | R37: =IFERROR(IF('Jun-24'!$F37="","-",VLOOKUP('Jun-24'!$F37,Lista_CUIT!$A$1:$D$2241,4,0)),"CUIT NO CARGADO") -> -
G38: =IFERROR(IF('Jun-24'!$F38="","-",VLOOKUP('Jun-24'!$F38,Lista_CUIT!$A$1:$D$2241,2,0)),"CUIT NO CARGADO") -> - | I38: =IF('Jun-24'!$H38="","",'Jun-24'!$H38*0.21) | P38: =SUM('Jun-24'!$H38:$O38) -> 0 | Q38: =IFERROR(IF('Jun-24'!$F38="","-",VLOOKUP('Jun-24'!$F38,Lista_CUIT!$A$1:$D$2241,3,0)),"CUIT NO CARGADO") -> - | R38: =IFERROR(IF('Jun-24'!$F38="","-",VLOOKUP('Jun-24'!$F38,Lista_CUIT!$A$1:$D$2241,4,0)),"CUIT NO CARGADO") -> -
G39: =IFERROR(IF('Jun-24'!$F39="","-",VLOOKUP('Jun-24'!$F39,Lista_CUIT!$A$1:$D$2241,2,0)),"CUIT NO CARGADO") -> - | I39: =IF('Jun-24'!$H39="","",'Jun-24'!$H39*0.21) | P39: =SUM('Jun-24'!$H39:$O39) -> 0 | Q39: =IFERROR(IF('Jun-24'!$F39="","-",VLOOKUP('Jun-24'!$F39,Lista_CUIT!$A$1:$D$2241,3,0)),"CUIT NO CARGADO") -> - | R39: =IFERROR(IF('Jun-24'!$F39="","-",VLOOKUP('Jun-24'!$F39,Lista_CUIT!$A$1:$D$2241,4,0)),"CUIT NO CARGADO") -> -
G40: =IFERROR(IF('Jun-24'!$F40="","-",VLOOKUP('Jun-24'!$F40,Lista_CUIT!$A$1:$D$2241,2,0)),"CUIT NO CARGADO") -> - | I40: =IF('Jun-24'!$H40="","",'Jun-24'!$H40*0.21) | P40: =SUM('Jun-24'!$H40:$O40) -> 0 | Q40: =IFERROR(IF('Jun-24'!$F40="","-",VLOOKUP('Jun-24'!$F40,Lista_CUIT!$A$1:$D$2241,3,0)),"CUIT NO CARGADO") -> - | R40: =IFERROR(IF('Jun-24'!$F40="","-",VLOOKUP('Jun-24'!$F40,Lista_CUIT!$A$1:$D$2241,4,0)),"CUIT NO CARGADO") -> -
G41: =IFERROR(IF('Jun-24'!$F41="","-",VLOOKUP('Jun-24'!$F41,Lista_CUIT!$A$1:$D$2241,2,0)),"CUIT NO CARGADO") -> - | I41: =IF('Jun-24'!$H41="","",'Jun-24'!$H41*0.21) | P41: =SUM('Jun-24'!$H41:$O41) -> 0 | Q41: =IFERROR(IF('Jun-24'!$F41="","-",VLOOKUP('Jun-24'!$F41,Lista_CUIT!$A$1:$D$2241,3,0)),"CUIT NO CARGADO") -> - | R41: =IFERROR(IF('Jun-24'!$F41="","-",VLOOKUP('Jun-24'!$F41,Lista_CUIT!$A$1:$D$2241,4,0)),"CUIT NO CARGADO") -> - | S41: COD 5
G42: =IFERROR(IF('Jun-24'!$F42="","-",VLOOKUP('Jun-24'!$F42,Lista_CUIT!$A$1:$D$2241,2,0)),"CUIT NO CARGADO") -> - | I42: =IF('Jun-24'!$H42="","",'Jun-24'!$H42*0.21) | P42: =SUM('Jun-24'!$H42:$O42) -> 0 | Q42: =IFERROR(IF('Jun-24'!$F42="","-",VLOOKUP('Jun-24'!$F42,Lista_CUIT!$A$1:$D$2241,3,0)),"CUIT NO CARGADO") -> - | R42: =IFERROR(IF('Jun-24'!$F42="","-",VLOOKUP('Jun-24'!$F42,Lista_CUIT!$A$1:$D$2241,4,0)),"CUIT NO CARGADO") -> - | S42: COD 5
G43: =IFERROR(IF('Jun-24'!$F43="","-",VLOOKUP('Jun-24'!$F43,Lista_CUIT!$A$1:$D$2241,2,0)),"CUIT NO CARGADO") -> - | I43: =IF('Jun-24'!$H43="","",'Jun-24'!$H43*0.21) | P43: =SUM('Jun-24'!$H43:$O43) -> 0 | Q43: =IFERROR(IF('Jun-24'!$F43="","-",VLOOKUP('Jun-24'!$F43,Lista_CUIT!$A$1:$D$2241,3,0)),"CUIT NO CARGADO") -> - | R43: =IFERROR(IF('Jun-24'!$F43="","-",VLOOKUP('Jun-24'!$F43,Lista_CUIT!$A$1:$D$2241,4,0)),"CUIT NO CARGADO") -> -
B44: Total | H44: =SUBTOTAL(109,'Jun-24'!$H$9:$H$43) -> 6033654.1 | I44: =SUBTOTAL(109,'Jun-24'!$I$9:$I$43) -> 1222537.7 | J44: =SUBTOTAL(109,'Jun-24'!$J$9:$J$43) -> 5811.6555 | K44: =SUBTOTAL(109,'Jun-24'!$K$9:$K$43) -> 20004.767 | L44: =SUBTOTAL(109,'Jun-24'!$L$9:$L$43) -> 645.74 | M44: =SUBTOTAL(109,'Jun-24'!$M$9:$M$43) -> 0 | N44: =SUBTOTAL(109,'Jun-24'!$N$9:$N$43) -> 0 | O44: =SUBTOTAL(109,'Jun-24'!$O$9:$O$43) -> 1755916.4 | P44: =SUBTOTAL(109,'Jun-24'!$P$9:$P$43) -> 9038570.3
H45: =SUM(H23:H35,H18:H21,H9:H16) -> 4964231.9
D49: LIQUIDACION EXTRACTOS BANCARIOS-TARJETAS
D50: FECHA | E50: NRO CPTE | F50: BANCO | G50: NETO | H50: IVA 21% | I50: IVA 10,5% | J50: RET IIBB CABA | K50: PERC IVA | L50: PERC IIBB
D51: 45473 | E51: 30062024 | F51: CREDICOOP | G51: =450+300+46+175+35060+150+600+12600+2818.11 -> 52199.11 | H51: 10370.01 | I51: 295.9 | K51: 1429.8
H52: ='Jun-24'!$G52*0.21 -> 0
H53: ='Jun-24'!$G53*0.21 -> 0
D54: Total | G54: =SUBTOTAL(109,'Jun-24'!$G$51:$G$53) -> 52199.11 | H54: =SUBTOTAL(109,'Jun-24'!$H$51:$H$53) -> 10370.01 | I54: =SUBTOTAL(109,'Jun-24'!$I$51:$I$53) -> 295.9 | J54: =SUBTOTAL(109,'Jun-24'!$J$51:$J$53) -> 0 | K54: =SUBTOTAL(109,'Jun-24'!$K$51:$K$53) -> 1429.8 | L54: =SUBTOTAL(109,'Jun-24'!$L$51:$L$53) -> 0
D56: FACTURAS C
D57: FECHA | E57: PTO VTA | F57: FC Nº | G57: CUIT | H57: RAZON SOCIAL | I57: TOTAL | J57: TIPO DE GASTO | K57: Provincia
D58: 45444 | E58: 1 | F58: 37 | G58: 20365938688 | H58: =IFERROR(IF('Jun-24'!$G58="","-",VLOOKUP('Jun-24'!$G58,Lista_CUIT!$A$1:$D$2241,2,0)),"CUIT NO CARGADO") -> LIPANOVICH JUAN CRUZ | I58: 750000 | J58: =IFERROR(IF('Jun-24'!$G58="","-",VLOOKUP('Jun-24'!$G58,Lista_CUIT!$A$1:$D$2241,3,0)),"CUIT NO CARGADO") -> SOFTWARE | K58: =IFERROR(IF('Jun-24'!$G58="","-",VLOOKUP('Jun-24'!$G58,Lista_CUIT!$A$1:$D$2241,4,0)),"CUIT NO CARGADO") -> 0
D59: 45444 | E59: 1 | F59: 26 | G59: 27387896150 | H59: =IFERROR(IF('Jun-24'!$G59="","-",VLOOKUP('Jun-24'!$G59,Lista_CUIT!$A$1:$D$2241,2,0)),"CUIT NO CARGADO") -> LIPANOVICH MARIA SOL | I59: 900000 | J59: =IFERROR(IF('Jun-24'!$G59="","-",VLOOKUP('Jun-24'!$G59,Lista_CUIT!$A$1:$D$2241,3,0)),"CUIT NO CARGADO") -> consultoria informatica | K59: =IFERROR(IF('Jun-24'!$G59="","-",VLOOKUP('Jun-24'!$G59,Lista_CUIT!$A$1:$D$2241,4,0)),"CUIT NO CARGADO") -> 0
D60: 45444 | E60: 2 | F60: 242 | G60: 27173820866 | H60: =IFERROR(IF('Jun-24'!$G60="","-",VLOOKUP('Jun-24'!$G60,Lista_CUIT!$A$1:$D$2241,2,0)),"CUIT NO CARGADO") -> FREIER SANDRA DANIELA | I60: 700000 | J60: =IFERROR(IF('Jun-24'!$G60="","-",VLOOKUP('Jun-24'!$G60,Lista_CUIT!$A$1:$D$2241,3,0)),"CUIT NO CARGADO") -> Honorarios Prof | K60: =IFERROR(IF('Jun-24'!$G60="","-",VLOOKUP('Jun-24'!$G60,Lista_CUIT!$A$1:$D$2241,4,0)),"CUIT NO CARGADO") -> 0
D61: 45446 | E61: 3 | F61: 856 | G61: 20086277523 | H61: =IFERROR(IF('Jun-24'!$G61="","-",VLOOKUP('Jun-24'!$G61,Lista_CUIT!$A$1:$D$2241,2,0)),"CUIT NO CARGADO") -> ESTUDIO BOTINDARI | I61: 210000 | J61: =IFERROR(IF('Jun-24'!$G61="","-",VLOOKUP('Jun-24'!$G61,Lista_CUIT!$A$1:$D$2241,3,0)),"CUIT NO CARGADO") -> Honorarios Contables | K61: =IFERROR(IF('Jun-24'!$G61="","-",VLOOKUP('Jun-24'!$G61,Lista_CUIT!$A$1:$D$2241,4,0)),"CUIT NO CARGADO") -> 0
D62: 45446 | E62: 4 | F62: 26 | G62: 20341462933 | H62: =IFERROR(IF('Jun-24'!$G62="","-",VLOOKUP('Jun-24'!$G62,Lista_CUIT!$A$1:$D$2241,2,0)),"CUIT NO CARGADO") -> CASTIGLIONI MATIAS EZEQUIEL | I62: 1015000 | J62: =IFERROR(IF('Jun-24'!$G62="","-",VLOOKUP('Jun-24'!$G62,Lista_CUIT!$A$1:$D$2241,3,0)),"CUIT NO CARGADO") -> ASESORAMIENTO | K62: =IFERROR(IF('Jun-24'!$G62="","-",VLOOKUP('Jun-24'!$G62,Lista_CUIT!$A$1:$D$2241,4,0)),"CUIT NO CARGADO") -> BUENOS AIRES
D63: 45448 | E63: 2 | F63: 4 | G63: 23118167279 | H63: =IFERROR(IF('Jun-24'!$G63="","-",VLOOKUP('Jun-24'!$G63,Lista_CUIT!$A$1:$D$2241,2,0)),"CUIT NO CARGADO") -> ABELEDO ENRIQUE JUAN | I63: 780000 | J63: =IFERROR(IF('Jun-24'!$G63="","-",VLOOKUP('Jun-24'!$G63,Lista_CUIT!$A$1:$D$2241,3,0)),"CUIT NO CARGADO") -> Honorarios Admin | K63: =IFERROR(IF('Jun-24'!$G63="","-",VLOOKUP('Jun-24'!$G63,Lista_CUIT!$A$1:$D$2241,4,0)),"CUIT NO CARGADO") -> 0
D64: 45454 | E64: 2 | F64: 172 | G64: 20136544625 | H64: =IFERROR(IF('Jun-24'!$G64="","-",VLOOKUP('Jun-24'!$G64,Lista_CUIT!$A$1:$D$2241,2,0)),"CUIT NO CARGADO") -> RODRIGUEZ DE LA FUEN HECTOR MARCELO | I64: 600000 | J64: =IFERROR(IF('Jun-24'!$G64="","-",VLOOKUP('Jun-24'!$G64,Lista_CUIT!$A$1:$D$2241,3,0)),"CUIT NO CARGADO") -> Honorarios Admin | K64: =IFERROR(IF('Jun-24'!$G64="","-",VLOOKUP('Jun-24'!$G64,Lista_CUIT!$A$1:$D$2241,4,0)),"CUIT NO CARGADO") -> 0
D65: 45454 | E65: 2 | F65: 796 | G65: 20400104094 | H65: =IFERROR(IF('Jun-24'!$G65="","-",VLOOKUP('Jun-24'!$G65,Lista_CUIT!$A$1:$D$2241,2,0)),"CUIT NO CARGADO") -> FEDERICO BOTINDARI | I65: 60442 | J65: =IFERROR(IF('Jun-24'!$G65="","-",VLOOKUP('Jun-24'!$G65,Lista_CUIT!$A$1:$D$2241,3,0)),"CUIT NO CARGADO") -> Honorarios Contables | K65: =IFERROR(IF('Jun-24'!$G65="","-",VLOOKUP('Jun-24'!$G65,Lista_CUIT!$A$1:$D$2241,4,0)),"CUIT NO CARGADO") -> 0
D66: 45468 | E66: 1 | F66: 332 | G66: 27925308884 | H66: =IFERROR(IF('Jun-24'!$G66="","-",VLOOKUP('Jun-24'!$G66,Lista_CUIT!$A$1:$D$2241,2,0)),"CUIT NO CARGADO") -> LOPEZ LOPEZ FLAVIA | I66: 8000 | J66: =IFERROR(IF('Jun-24'!$G66="","-",VLOOKUP('Jun-24'!$G66,Lista_CUIT!$A$1:$D$2241,3,0)),"CUIT NO CARGADO") -> GASTOS VARIOS | K66: =IFERROR(IF('Jun-24'!$G66="","-",VLOOKUP('Jun-24'!$G66,Lista_CUIT!$A$1:$D$2241,4,0)),"CUIT NO CARGADO") -> 0
D67: 45469 | E67: 2 | F67: 139 | G67: 27125997835 | H67: =IFERROR(IF('Jun-24'!$G67="","-",VLOOKUP('Jun-24'!$G67,Lista_CUIT!$A$1:$D$2241,2,0)),"CUIT NO CARGADO") -> DANSKY ULLMANN VIVIANA EVA YOLANDA | I67: 15000 | J67: =IFERROR(IF('Jun-24'!$G67="","-",VLOOKUP('Jun-24'!$G67,Lista_CUIT!$A$1:$D$2241,3,0)),"CUIT NO CARGADO") -> Honorarios Prof | K67: =IFERROR(IF('Jun-24'!$G67="","-",VLOOKUP('Jun-24'!$G67,Lista_CUIT!$A$1:$D$2241,4,0)),"CUIT NO CARGADO") -> 0
H68: =IFERROR(IF('Jun-24'!$G68="","-",VLOOKUP('Jun-24'!$G68,Lista_CUIT!$A$1:$D$2241,2,0)),"CUIT NO CARGADO") -> - | J68: =IFERROR(IF('Jun-24'!$G68="","-",VLOOKUP('Jun-24'!$G68,Lista_CUIT!$A$1:$D$2241,3,0)),"CUIT NO CARGADO") -> - | K68: =IFERROR(IF('Jun-24'!$G68="","-",VLOOKUP('Jun-24'!$G68,Lista_CUIT!$A$1:$D$2241,4,0)),"CUIT NO CARGADO") -> -
H69: =IFERROR(IF('Jun-24'!$G69="","-",VLOOKUP('Jun-24'!$G69,Lista_CUIT!$A$1:$D$2241,2,0)),"CUIT NO CARGADO") -> - | J69: =IFERROR(IF('Jun-24'!$G69="","-",VLOOKUP('Jun-24'!$G69,Lista_CUIT!$A$1:$D$2241,3,0)),"CUIT NO CARGADO") -> - | K69: =IFERROR(IF('Jun-24'!$G69="","-",VLOOKUP('Jun-24'!$G69,Lista_CUIT!$A$1:$D$2241,4,0)),"CUIT NO CARGADO") -> -
H70: =IFERROR(IF('Jun-24'!$G70="","-",VLOOKUP('Jun-24'!$G70,Lista_CUIT!$A$1:$D$2241,2,0)),"CUIT NO CARGADO") -> - | J70: =IFERROR(IF('Jun-24'!$G70="","-",VLOOKUP('Jun-24'!$G70,Lista_CUIT!$A$1:$D$2241,3,0)),"CUIT NO CARGADO") -> - | K70: =IFERROR(IF('Jun-24'!$G70="","-",VLOOKUP('Jun-24'!$G70,Lista_CUIT!$A$1:$D$2241,4,0)),"CUIT NO CARGADO") -> -
H71: =IFERROR(IF('Jun-24'!$G71="","-",VLOOKUP('Jun-24'!$G71,Lista_CUIT!$A$1:$D$2241,2,0)),"CUIT NO CARGADO") -> - | J71: =IFERROR(IF('Jun-24'!$G71="","-",VLOOKUP('Jun-24'!$G71,Lista_CUIT!$A$1:$D$2241,3,0)),"CUIT NO CARGADO") -> - | K71: =IFERROR(IF('Jun-24'!$G71="","-",VLOOKUP('Jun-24'!$G71,Lista_CUIT!$A$1:$D$2241,4,0)),"CUIT NO CARGADO") -> -
D72: Total | I72: =SUBTOTAL(109,'Jun-24'!$I$58:$I$71) -> 5038442
B78: LIBRO IVA VENTAS | K78: =N1 -> 45078
B80: VENTAS "A"
B81: FECHA | C81: TIPO | D81: PTO VENTA | E81: Nº FACTURA | F81: CUIT | G81: RAZON SOCIAL | H81: IMPORTE NETO | I81: IVA 21% | J81: IVA 10,5% | K81: EXENTO | L81: TOTAL | M81: Provincia
B82: 45453 | C82: 1 | D82: 3 | E82: 199 | F82: 30628274327 | G82: =IFERROR(IF('Jun-24'!$F82="","-",VLOOKUP('Jun-24'!$F82,Lista_CUIT!$A$1:$D$2241,2,0)),"CUIT NO CARGADO") -> AGIRA S A | H82: 274200 | I82: ='Jun-24'!$H82*0.21 -> 57582 | L82: =SUM('Jun-24'!$H82:$K82) -> 331782
B83: 45453 | C83: 1 | D83: 3 | E83: 198 | F83: 30628274327 | G83: =IFERROR(IF('Jun-24'!$F83="","-",VLOOKUP('Jun-24'!$F83,Lista_CUIT!$A$1:$D$2241,2,0)),"CUIT NO CARGADO") -> AGIRA S A | H83: 12256740 | J83: ='Jun-24'!$H83*0.105 -> 1286957.7 | L83: =SUM('Jun-24'!$H83:$K83) -> 13543698
B84: 45457 | C84: 1 | D84: 3 | E84: 200 | F84: 30638318470 | G84: =IFERROR(IF('Jun-24'!$F84="","-",VLOOKUP('Jun-24'!$F84,Lista_CUIT!$A$1:$D$2241,2,0)),"CUIT NO CARGADO") -> DELTA COMPRESION S R L | H84: 25052252 | I84: =230629.08*0.21 -> 48432.107 | J84: =24821623*0.105 -> 2606270.4 | L84: =SUM('Jun-24'!$H84:$K84) -> 27706955
B85: 45467 | C85: 1 | D85: 3 | E85: 201 | F85: 30717260968 | G85: =IFERROR(IF('Jun-24'!$F85="","-",VLOOKUP('Jun-24'!$F85,Lista_CUIT!$A$1:$D$2241,2,0)),"CUIT NO CARGADO") -> 2 IN FLOW COMPAÑIA DE SERVICIOS S. A. | H85: 2904000 | I85: ='Jun-24'!$H85*0.21 -> 609840 | L85: =SUM('Jun-24'!$H85:$K85) -> 3513840
B86: 45467 | C86: 1 | D86: 3 | E86: 202 | F86: 30628274327 | G86: =IFERROR(IF('Jun-24'!$F86="","-",VLOOKUP('Jun-24'!$F86,Lista_CUIT!$A$1:$D$2241,2,0)),"CUIT NO CARGADO") -> AGIRA S A | H86: 12565215 | I86: =274950*0.21 -> 57739.5 | J86: =12290265*0.105 -> 1290477.8 | L86: =SUM('Jun-24'!$H86:$K86) -> 13913432
B87: 45467 | C87: 1 | D87: 3 | E87: 203 | F87: 30628274327 | G87: =IFERROR(IF('Jun-24'!$F87="","-",VLOOKUP('Jun-24'!$F87,Lista_CUIT!$A$1:$D$2241,2,0)),"CUIT NO CARGADO") -> AGIRA S A | H87: 367200 | I87: ='Jun-24'!$H87*0.21 -> 77112 | L87: =SUM('Jun-24'!$H87:$K87) -> 444312
B88: 45467 | C88: 3 | D88: 3 | E88: 21 | F88: 30628274327 | G88: =IFERROR(IF('Jun-24'!$F88="","-",VLOOKUP('Jun-24'!$F88,Lista_CUIT!$A$1:$D$2241,2,0)),"CUIT NO CARGADO") -> AGIRA S A | H88: -12256740 | J88: ='Jun-24'!$H88*0.105 -> -1286957.7 | L88: =SUM('Jun-24'!$H88:$K88) -> -13543698
B89: 45467 | C89: 3 | D89: 3 | E89: 22 | F89: 30628274327 | G89: =IFERROR(IF('Jun-24'!$F89="","-",VLOOKUP('Jun-24'!$F89,Lista_CUIT!$A$1:$D$2241,2,0)),"CUIT NO CARGADO") -> AGIRA S A | H89: -274200 | I89: ='Jun-24'!$H89*0.21 -> -57582 | L89: =SUM('Jun-24'!$H89:$K89) -> -331782
G90: =IFERROR(IF('Jun-24'!$F90="","-",VLOOKUP('Jun-24'!$F90,Lista_CUIT!$A$1:$D$2241,2,0)),"CUIT NO CARGADO") -> - | I90: ='Jun-24'!$H90*0.21 -> 0 | L90: =SUM('Jun-24'!$H90:$K90) -> 0
B91: Total | H91: =SUBTOTAL(109,'Jun-24'!$H$82:$H$90) -> 40888667 | I91: =SUBTOTAL(109,'Jun-24'!$I$82:$I$90) -> 793123.61 | J91: =SUBTOTAL(109,'Jun-24'!$J$82:$J$90) -> 3896748.2 | K91: =SUBTOTAL(109,'Jun-24'!$K$82:$K$90) -> 0 | L91: =SUBTOTAL(109,'Jun-24'!$L$82:$L$90) -> 45578539 | M91: =SUBTOTAL(103,'Jun-24'!$M$82:$M$90) -> 0
B94: VENTAS "B"
B95: FECHA | C95: TIPO | D95: PTO VENTA | E95: Nº FACTURA | F95: CUIT | G95: RAZON SOCIAL | H95: IMPORTE NETO | I95: IVA 21% | J95: IVA 10,5% | K95: EXENTO | L95: TOTAL | M95: Provincia
G96: =IFERROR(IF('Jun-24'!$F96="","-",VLOOKUP('Jun-24'!$F96,Lista_CUIT!$A$1:$D$2241,2,0)),"CUIT NO CARGADO") -> - | L96: =SUM('Jun-24'!$H96:$K96) -> 0
L97: =SUM('Jun-24'!$H97:$K97) -> 0
L98: =SUM('Jun-24'!$H98:$K98) -> 0
L99: =SUM('Jun-24'!$H99:$K99) -> 0
L100: =SUM('Jun-24'!$H100:$K100) -> 0
L101: =SUM('Jun-24'!$H101:$K101) -> 0
B102: Total | H102: =SUBTOTAL(109,'Jun-24'!$H$96:$H$101) -> 0 | I102: =SUBTOTAL(109,'Jun-24'!$I$96:$I$101) -> 0 | J102: =SUBTOTAL(109,'Jun-24'!$J$96:$J$101) -> 0 | K102: =SUBTOTAL(109,'Jun-24'!$K$96:$K$101) -> 0 | L102: =SUBTOTAL(109,'Jun-24'!$L$96:$L$101) -> 0 | M102: =SUBTOTAL(103,'Jun-24'!$M$96:$M$101) -> 0
B105: VENTAS "E"
B106: FECHA | C106: TIPO | D106: PTO VENTA | E106: Nº FACTURA | F106: CUIT | G106: RAZON SOCIAL | H106: USD | I106: Columna2 | J106: Columna1 | K106: TIPO DE CAMBIO2 | L106: TOTAL | M106: Provincia
B107: 45469 | D107: 30 | E107: 87 | F107: 55000000050 | G107: =IFERROR(IF('Jun-24'!$F107="","-",VLOOKUP('Jun-24'!$F107,Lista_CUIT!$A$1:$D$2241,2,0)),"CUIT NO CARGADO") -> GAS FUTURO SISTEMAS DE COMPRESSÃO LTDA | H107: 3175 | K107: 909 | L107: =H107*K107 -> 2886075
G108: =IFERROR(IF('Jun-24'!$F108="","-",VLOOKUP('Jun-24'!$F108,Lista_CUIT!$A$1:$D$2241,2,0)),"CUIT NO CARGADO") -> - | L108: =H108*K108 -> 0
G109: =IFERROR(IF('Jun-24'!$F109="","-",VLOOKUP('Jun-24'!$F109,Lista_CUIT!$A$1:$D$2241,2,0)),"CUIT NO CARGADO") -> - | I109: ='Jun-24'!$H109*0.21 -> 0 | K109: ='Jun-24'!$H109*'Jun-24'!$J109 -> 0 | L109: =H109*K109 -> 0
G110: =IFERROR(IF('Jun-24'!$F110="","-",VLOOKUP('Jun-24'!$F110,Lista_CUIT!$A$1:$D$2241,2,0)),"CUIT NO CARGADO") -> - | I110: ='Jun-24'!$H110*0.21 -> 0 | K110: ='Jun-24'!$H110*'Jun-24'!$J110 -> 0 | L110: =H110*K110 -> 0
G111: =IFERROR(IF('Jun-24'!$F111="","-",VLOOKUP('Jun-24'!$F111,Lista_CUIT!$A$1:$D$2241,2,0)),"CUIT NO CARGADO") -> - | I111: ='Jun-24'!$H111*0.21 -> 0 | K111: ='Jun-24'!$H111*'Jun-24'!$J111 -> 0 | L111: =H111*K111 -> 0
G112: =IFERROR(IF('Jun-24'!$F112="","-",VLOOKUP('Jun-24'!$F112,Lista_CUIT!$A$1:$D$2241,2,0)),"CUIT NO CARGADO") -> - | I112: ='Jun-24'!$H112*0.21 -> 0 | K112: ='Jun-24'!$H112*'Jun-24'!$J112 -> 0 | L112: =H112*K112 -> 0
G113: =IFERROR(IF('Jun-24'!$F113="","-",VLOOKUP('Jun-24'!$F113,Lista_CUIT!$A$1:$D$2241,2,0)),"CUIT NO CARGADO") -> - | I113: ='Jun-24'!$H113*0.21 -> 0 | K113: ='Jun-24'!$H113*'Jun-24'!$J113 -> 0 | L113: =H113*K113 -> 0
G114: =IFERROR(IF('Jun-24'!$F114="","-",VLOOKUP('Jun-24'!$F114,Lista_CUIT!$A$1:$D$2241,2,0)),"CUIT NO CARGADO") -> - | I114: ='Jun-24'!$H114*0.21 -> 0 | K114: ='Jun-24'!$H114*'Jun-24'!$J114 -> 0 | L114: =H114*K114 -> 0
G115: =IFERROR(IF('Jun-24'!$F115="","-",VLOOKUP('Jun-24'!$F115,Lista_CUIT!$A$1:$D$2241,2,0)),"CUIT NO CARGADO") -> - | I115: ='Jun-24'!$H115*0.21 -> 0 | K115: ='Jun-24'!$H115*'Jun-24'!$J115 -> 0 | L115: =H115*K115 -> 0
G116: =IFERROR(IF('Jun-24'!$F116="","-",VLOOKUP('Jun-24'!$F116,Lista_CUIT!$A$1:$D$2241,2,0)),"CUIT NO CARGADO") -> - | I116: ='Jun-24'!$H116*0.21 -> 0 | K116: ='Jun-24'!$H116*'Jun-24'!$J116 -> 0 | L116: =H116*K116 -> 0
G117: =IFERROR(IF('Jun-24'!$F117="","-",VLOOKUP('Jun-24'!$F117,Lista_CUIT!$A$1:$D$2241,2,0)),"CUIT NO CARGADO") -> - | I117: ='Jun-24'!$H117*0.21 -> 0 | K117: ='Jun-24'!$H117*'Jun-24'!$J117 -> 0 | L117: =H117*K117 -> 0
G118: =IFERROR(IF('Jun-24'!$F118="","-",VLOOKUP('Jun-24'!$F118,Lista_CUIT!$A$1:$D$2241,2,0)),"CUIT NO CARGADO") -> - | I118: ='Jun-24'!$H118*0.21 -> 0 | K118: ='Jun-24'!$H118*'Jun-24'!$J118 -> 0 | L118: =H118*K118 -> 0
...

Sheet Jul-24
B1: LIBRO IVA COMPRAS | G1: ='Abr-24'!G1:M1 -> CORITEC S. R. L. | N1: =EDATE('Abr-24'!N1,3) -> 45108
B3: TOTAL COMPRAS | G3: TOTAL CREDITO FISCAL | J3: TOTAL VENTAS NETAS | M3: TOTAL DEBITO FISCAL | P3: RESULTADO
B4: =SUM('Jul-24'!$H$35)+'Jul-24'!$G$47 -> 19384475 | G4: ='Jul-24'!$I$35+'Jul-24'!$J$35+'Jul-24'!$K$35+'Jul-24'!$H$47+'Jul-24'!$I$47 -> 4072459.2 | J4: ='Jul-24'!$H$86+'Jul-24'!$H$96 -> 60193539 | M4: ='Jul-24'!$I$86+'Jul-24'!$J$86+'Jul-24'!$I$96+'Jul-24'!$J$96 -> 6988420.2 | P4: =G4-M4 -> -2915961
B8: FECHA | C8: TIPO | D8: PTO VTA | E8: NRO. CPTE | F8: CUIT | G8: RAZON SOCIAL | H8: NETO GRAVADO | I8: IVA 21 % | J8: IVA 27% | K8: IVA 10,5% | L8: PERC. IVA | M8: PERC IIBB BS AS | N8: PERC. IIBB CABA | O8: Otros / No Grav. | P8: TOTAL | Q8: Tipo de Gasto | R8: Provincia
B9: 01/07/2024 | C9: 1 | D9: 3 | E9: 233013 | F9: 30707135596 | G9: =IFERROR(IF('Jul-24'!$F9="","-",VLOOKUP('Jul-24'!$F9,Lista_CUIT!$A$1:$D$2241,2,0)),"CUIT NO CARGADO") -> CITILAN ARGENTINA S.A. | H9: 18640 | I9: =IF('Jul-24'!$H9="","",'Jul-24'!$H9*0.21) -> 3914.4 | P9: =SUM('Jul-24'!$H9:$O9) -> 22554.4 | Q9: =IFERROR(IF('Jul-24'!$F9="","-",VLOOKUP('Jul-24'!$F9,Lista_CUIT!$A$1:$D$2241,3,0)),"CUIT NO CARGADO") -> Telefonia | R9: =IFERROR(IF('Jul-24'!$F9="","-",VLOOKUP('Jul-24'!$F9,Lista_CUIT!$A$1:$D$2241,4,0)),"CUIT NO CARGADO") -> 0
B10: 01/07/2024 | C10: 1 | D10: 3 | E10: 769 | F10: 30715402765 | G10: =IFERROR(IF('Jul-24'!$F10="","-",VLOOKUP('Jul-24'!$F10,Lista_CUIT!$A$1:$D$2241,2,0)),"CUIT NO CARGADO") -> RIO 265 S.R.L. | H10: 58677.67 | I10: =IF('Jul-24'!$H10="","",'Jul-24'!$H10*0.21) -> 12322.311 | P10: =SUM('Jul-24'!$H10:$O10) -> 70999.981 | Q10: =IFERROR(IF('Jul-24'!$F10="","-",VLOOKUP('Jul-24'!$F10,Lista_CUIT!$A$1:$D$2241,3,0)),"CUIT NO CARGADO") -> GASTOS VARIOS | R10: =IFERROR(IF('Jul-24'!$F10="","-",VLOOKUP('Jul-24'!$F10,Lista_CUIT!$A$1:$D$2241,4,0)),"CUIT NO CARGADO") -> 0
B11: 03/07/2024 | C11: 1 | D11: 5 | E11: 29626 | F11: 30707555404 | G11: =IFERROR(IF('Jul-24'!$F11="","-",VLOOKUP('Jul-24'!$F11,Lista_CUIT!$A$1:$D$2241,2,0)),"CUIT NO CARGADO") -> MAQUINAS E INSUMOS S.R.L. | H11: 70413.12 | I11: =IF('Jul-24'!$H11="","",'Jul-24'!$H11*0.21) -> 14786.755 | P11: =SUM('Jul-24'!$H11:$O11) -> 85199.875 | Q11: =IFERROR(IF('Jul-24'!$F11="","-",VLOOKUP('Jul-24'!$F11,Lista_CUIT!$A$1:$D$2241,3,0)),"CUIT NO CARGADO") -> INSUMO | R11: =IFERROR(IF('Jul-24'!$F11="","-",VLOOKUP('Jul-24'!$F11,Lista_CUIT!$A$1:$D$2241,4,0)),"CUIT NO CARGADO") -> 0
B12: 03/07/2024 | C12: 1 | D12: 5 | E12: 629 | F12: 27264020773 | G12: =IFERROR(IF('Jul-24'!$F12="","-",VLOOKUP('Jul-24'!$F12,Lista_CUIT!$A$1:$D$2241,2,0)),"CUIT NO CARGADO") -> CASTIÑEIRA NATALIA CLAUDIA | H12: 11967.77 | I12: =IF('Jul-24'!$H12="","",'Jul-24'!$H12*0.21) -> 2513.2317 | P12: =SUM('Jul-24'!$H12:$O12) -> 14481.002 | Q12: =IFERROR(IF('Jul-24'!$F12="","-",VLOOKUP('Jul-24'!$F12,Lista_CUIT!$A$1:$D$2241,3,0)),"CUIT NO CARGADO") -> Ropa de Trabajo | R12: =IFERROR(IF('Jul-24'!$F12="","-",VLOOKUP('Jul-24'!$F12,Lista_CUIT!$A$1:$D$2241,4,0)),"CUIT NO CARGADO") -> 0
B13: 03/07/2024 | C13: 1 | D13: 2 | E13: 16433 | F13: 20103565309 | G13: =IFERROR(IF('Jul-24'!$F13="","-",VLOOKUP('Jul-24'!$F13,Lista_CUIT!$A$1:$D$2241,2,0)),"CUIT NO CARGADO") -> CASATI ENRIQUE ARIEL | H13: 530172 | I13: =IF('Jul-24'!$H13="","",'Jul-24'!$H13*0.21) -> 111336.12 | P13: =SUM('Jul-24'!$H13:$O13) -> 641508.12 | Q13: =IFERROR(IF('Jul-24'!$F13="","-",VLOOKUP('Jul-24'!$F13,Lista_CUIT!$A$1:$D$2241,3,0)),"CUIT NO CARGADO") -> Papeleria | R13: =IFERROR(IF('Jul-24'!$F13="","-",VLOOKUP('Jul-24'!$F13,Lista_CUIT!$A$1:$D$2241,4,0)),"CUIT NO CARGADO") -> 0
B14: 04/07/2024 | C14: 1 | D14: 9 | E14: 323 | F14: 20172940162 | G14: =IFERROR(IF('Jul-24'!$F14="","-",VLOOKUP('Jul-24'!$F14,Lista_CUIT!$A$1:$D$2241,2,0)),"CUIT NO CARGADO") -> HERAS MARCELO GABRIEL | H14: 33882.64 | I14: =IF('Jul-24'!$H14="","",'Jul-24'!$H14*0.21) -> 7115.3544 | P14: =SUM('Jul-24'!$H14:$O14) -> 40997.994 | Q14: =IFERROR(IF('Jul-24'!$F14="","-",VLOOKUP('Jul-24'!$F14,Lista_CUIT!$A$1:$D$2241,3,0)),"CUIT NO CARGADO") -> Ropa de Trabajo | R14: =IFERROR(IF('Jul-24'!$F14="","-",VLOOKUP('Jul-24'!$F14,Lista_CUIT!$A$1:$D$2241,4,0)),"CUIT NO CARGADO") -> 0
B15: 05/07/2024 | C15: 1 | D15: 5 | E15: 9868 | F15: 33711557119 | G15: =IFERROR(IF('Jul-24'!$F15="","-",VLOOKUP('Jul-24'!$F15,Lista_CUIT!$A$1:$D$2241,2,0)),"CUIT NO CARGADO") -> ELECTROMINGO S.R.L. | H15: 9876.03 | I15: =IF('Jul-24'!$H15="","",'Jul-24'!$H15*0.21) -> 2073.9663 | P15: =SUM('Jul-24'!$H15:$O15) -> 11949.996 | Q15: =IFERROR(IF('Jul-24'!$F15="","-",VLOOKUP('Jul-24'!$F15,Lista_CUIT!$A$1:$D$2241,3,0)),"CUIT NO CARGADO") -> INSUMO | R15: =IFERROR(IF('Jul-24'!$F15="","-",VLOOKUP('Jul-24'!$F15,Lista_CUIT!$A$1:$D$2241,4,0)),"CUIT NO CARGADO") -> BUENOS AIRES
B16: 08/07/2024 | C16: 1 | D16: 3 | E16: 315 | F16: 20921575743 | G16: =IFERROR(IF('Jul-24'!$F16="","-",VLOOKUP('Jul-24'!$F16,Lista_CUIT!$A$1:$D$2241,2,0)),"CUIT NO CARGADO") -> RIOS GOMEZ JOSE ANTONIO | H16: 207416 | I16: =IF('Jul-24'!$H16="","",'Jul-24'!$H16*0.21) -> 43557.36 | P16: =SUM('Jul-24'!$H16:$O16) -> 250973.36 | Q16: =IFERROR(IF('Jul-24'!$F16="","-",VLOOKUP('Jul-24'!$F16,Lista_CUIT!$A$1:$D$2241,3,0)),"CUIT NO CARGADO") -> Papeleria | R16: =IFERROR(IF('Jul-24'!$F16="","-",VLOOKUP('Jul-24'!$F16,Lista_CUIT!$A$1:$D$2241,4,0)),"CUIT NO CARGADO") -> 0
B17: 10/07/2024 | C17: 1 | D17: 13 | E17: 3504 | F17: 20148841722 | G17: =IFERROR(IF('Jul-24'!$F17="","-",VLOOKUP('Jul-24'!$F17,Lista_CUIT!$A$1:$D$2241,2,0)),"CUIT NO CARGADO") -> CHICO ALEJANDRO | H17: 6859.5 | I17: =IF('Jul-24'!$H17="","",'Jul-24'!$H17*0.21) -> 1440.495 | P17: =SUM('Jul-24'!$H17:$O17) -> 8299.995 | Q17: =IFERROR(IF('Jul-24'!$F17="","-",VLOOKUP('Jul-24'!$F17,Lista_CUIT!$A$1:$D$2241,3,0)),"CUIT NO CARGADO") -> Papeleria | R17: =IFERROR(IF('Jul-24'!$F17="","-",VLOOKUP('Jul-24'!$F17,Lista_CUIT!$A$1:$D$2241,4,0)),"CUIT NO CARGADO") -> 0
B18: 11/07/2024 | C18: 1 | D18: 2466 | E18: 673488 | F18: 30678814357 | G18: =IFERROR(IF('Jul-24'!$F18="","-",VLOOKUP('Jul-24'!$F18,Lista_CUIT!$A$1:$D$2241,2,0)),"CUIT NO CARGADO") -> TELEFONICA MOVILES ARG | H18: 28656.82 | J18: ='Jul-24'!$H18*0.27 -> 7737.3414 | L18: 859.7 | O18: 1442.54 | P18: =SUM('Jul-24'!$H18:$O18) -> 38696.401 | Q18: =IFERROR(IF('Jul-24'!$F18="","-",VLOOKUP('Jul-24'!$F18,Lista_CUIT!$A$1:$D$2241,3,0)),"CUIT NO CARGADO") -> Telefonia | R18: =IFERROR(IF('Jul-24'!$F18="","-",VLOOKUP('Jul-24'!$F18,Lista_CUIT!$A$1:$D$2241,4,0)),"CUIT NO CARGADO") -> 0
B19: 12/07/2024 | C19: 1 | D19: 7 | E19: 9507 | F19: 30709788635 | G19: =IFERROR(IF('Jul-24'!$F19="","-",VLOOKUP('Jul-24'!$F19,Lista_CUIT!$A$1:$D$2241,2,0)),"CUIT NO CARGADO") -> EMELINT S.R.L. | H19: 20700.5 | I19: =IF('Jul-24'!$H19="","",'Jul-24'!$H19*0.21) -> 4347.105 | P19: =SUM('Jul-24'!$H19:$O19) -> 25047.605 | Q19: =IFERROR(IF('Jul-24'!$F19="","-",VLOOKUP('Jul-24'!$F19,Lista_CUIT!$A$1:$D$2241,3,0)),"CUIT NO CARGADO") -> Electronica | R19: =IFERROR(IF('Jul-24'!$F19="","-",VLOOKUP('Jul-24'!$F19,Lista_CUIT!$A$1:$D$2241,4,0)),"CUIT NO CARGADO") -> 0
B20: 15/07/2024 | C20: 1 | D20: 700 | E20: 679343 | F20: 30580111315 | G20: =IFERROR(IF('Jul-24'!$F20="","-",VLOOKUP('Jul-24'!$F20,Lista_CUIT!$A$1:$D$2241,2,0)),"CUIT NO CARGADO") -> DHL EXPRESS (ARGENTINA) S.A. | H20: 14100 | I20: =IF('Jul-24'!$H20="","",'Jul-24'!$H20*0.21) -> 2961 | O20: 489166.6 | P20: =SUM('Jul-24'!$H20:$O20) -> 506227.6 | Q20: =IFERROR(IF('Jul-24'!$F20="","-",VLOOKUP('Jul-24'!$F20,Lista_CUIT!$A$1:$D$2241,3,0)),"CUIT NO CARGADO") -> Gastos Importacion | R20: =IFERROR(IF('Jul-24'!$F20="","-",VLOOKUP('Jul-24'!$F20,Lista_CUIT!$A$1:$D$2241,4,0)),"CUIT NO CARGADO") -> 0
B21: 16/07/2024 | C21: 1 | D21: 106 | E21: 751380 | F21: 30594494187 | G21: =IFERROR(IF('Jul-24'!$F21="","-",VLOOKUP('Jul-24'!$F21,Lista_CUIT!$A$1:$D$2241,2,0)),"CUIT NO CARGADO") -> FEDERAL EXPRESS CORPORATION | H21: 0 | I21: =IF('Jul-24'!$H21="","",'Jul-24'!$H21*0.21) -> 0 | O21: 253290.6 | P21: =SUM('Jul-24'!$H21:$O21) -> 253290.6 | Q21: =IFERROR(IF('Jul-24'!$F21="","-",VLOOKUP('Jul-24'!$F21,Lista_CUIT!$A$1:$D$2241,3,0)),"CUIT NO CARGADO") -> Gastos Importacion | R21: =IFERROR(IF('Jul-24'!$F21="","-",VLOOKUP('Jul-24'!$F21,Lista_CUIT!$A$1:$D$2241,4,0)),"CUIT NO CARGADO") -> 0
B22: 17/07/2024 | C22: 1 | D22: 3 | E22: 7643 | F22: 30710212127 | G22: =IFERROR(IF('Jul-24'!$F22="","-",VLOOKUP('Jul-24'!$F22,Lista_CUIT!$A$1:$D$2241,2,0)),"CUIT NO CARGADO") -> J Y M COMPONENTES ELECTRICOS S.A. | H22: 16655698 | I22: =IF('Jul-24'!$H22="","",'Jul-24'!$H22*0.21) -> 3497696.7 | P22: =SUM('Jul-24'!$H22:$O22) -> 20153395 | Q22: =IFERROR(IF('Jul-24'!$F22="","-",VLOOKUP('Jul-24'!$F22,Lista_CUIT!$A$1:$D$2241,3,0)),"CUIT NO CARGADO") -> INSUMO | R22: =IFERROR(IF('Jul-24'!$F22="","-",VLOOKUP('Jul-24'!$F22,Lista_CUIT!$A$1:$D$2241,4,0)),"CUIT NO CARGADO") -> 0
B23: 22/07/2024 | C23: 1 | D23: 7 | E23: 1777 | F23: 20294608401 | G23: =IFERROR(IF('Jul-24'!$F23="","-",VLOOKUP('Jul-24'!$F23,Lista_CUIT!$A$1:$D$2241,2,0)),"CUIT NO CARGADO") -> MONTELEONE LUCIANO EDUARDO | H23: 14559.96 | I23: =IF('Jul-24'!$H23="","",'Jul-24'!$H23*0.21) -> 3057.5916 | P23: =SUM('Jul-24'!$H23:$O23) -> 17617.552 | Q23: =IFERROR(IF('Jul-24'!$F23="","-",VLOOKUP('Jul-24'!$F23,Lista_CUIT!$A$1:$D$2241,3,0)),"CUIT NO CARGADO") -> INSUMO | R23: =IFERROR(IF('Jul-24'!$F23="","-",VLOOKUP('Jul-24'!$F23,Lista_CUIT!$A$1:$D$2241,4,0)),"CUIT NO CARGADO") -> 0
B24: 23/07/2024 | C24: 3 | D24: 5 | E24: 8289 | F24: 30692857611 | G24: =IFERROR(IF('Jul-24'!$F24="","-",VLOOKUP('Jul-24'!$F24,Lista_CUIT!$A$1:$D$2241,2,0)),"CUIT NO CARGADO") -> BAGUI S A | H24: -161235.36 | I24: =IF('Jul-24'!$H24="","",'Jul-24'!$H24*0.21) -> -33859.426 | P24: =SUM('Jul-24'!$H24:$O24) -> -195094.79 | Q24: =IFERROR(IF('Jul-24'!$F24="","-",VLOOKUP('Jul-24'!$F24,Lista_CUIT!$A$1:$D$2241,3,0)),"CUIT NO CARGADO") -> INSUMO | R24: =IFERROR(IF('Jul-24'!$F24="","-",VLOOKUP('Jul-24'!$F24,Lista_CUIT!$A$1:$D$2241,4,0)),"CUIT NO CARGADO") -> 0
B25: 26/07/2024 | C25: 1 | D25: 5 | E25: 291 | F25: 20177459012 | G25: =IFERROR(IF('Jul-24'!$F25="","-",VLOOKUP('Jul-24'!$F25,Lista_CUIT!$A$1:$D$2241,2,0)),"CUIT NO CARGADO") -> MIRANDA LAGES JORGE MARCELO | H25: 23140.5 | I25: =IF('Jul-24'!$H25="","",'Jul-24'!$H25*0.21) -> 4859.505 | P25: =SUM('Jul-24'!$H25:$O25) -> 28000.005 | Q25: =IFERROR(IF('Jul-24'!$F25="","-",VLOOKUP('Jul-24'!$F25,Lista_CUIT!$A$1:$D$2241,3,0)),"CUIT NO CARGADO") -> ASESORAMIENTO | R25: =IFERROR(IF('Jul-24'!$F25="","-",VLOOKUP('Jul-24'!$F25,Lista_CUIT!$A$1:$D$2241,4,0)),"CUIT NO CARGADO") -> 0
B26: 26/07/2024 | C26: 1 | D26: 2 | E26: 201 | F26: 20125142851 | G26: =IFERROR(IF('Jul-24'!$F26="","-",VLOOKUP('Jul-24'!$F26,Lista_CUIT!$A$1:$D$2241,2,0)),"CUIT NO CARGADO") -> FEDERICI NICOLAS JOSE | H26: 1312058.5 | I26: =IF('Jul-24'!$H26="","",'Jul-24'!$H26*0.21) -> 275532.29 | P26: =SUM('Jul-24'!$H26:$O26) -> 1587590.8 | Q26: =IFERROR(IF('Jul-24'!$F26="","-",VLOOKUP('Jul-24'!$F26,Lista_CUIT!$A$1:$D$2241,3,0)),"CUIT NO CARGADO") -> INSUMO | R26: =IFERROR(IF('Jul-24'!$F26="","-",VLOOKUP('Jul-24'!$F26,Lista_CUIT!$A$1:$D$2241,4,0)),"CUIT NO CARGADO") -> 0
B27: 30/07/2024 | C27: 1 | D27: 6 | E27: 15315 | F27: 30707756434 | G27: =IFERROR(IF('Jul-24'!$F27="","-",VLOOKUP('Jul-24'!$F27,Lista_CUIT!$A$1:$D$2241,2,0)),"CUIT NO CARGADO") -> SERVICIO INTEGRAL DE LIMPIEZA SRL | H27: 320000 | I27: =IF('Jul-24'!$H27="","",'Jul-24'!$H27*0.21) -> 67200 | P27: =SUM('Jul-24'!$H27:$O27) -> 387200 | Q27: =IFERROR(IF('Jul-24'!$F27="","-",VLOOKUP('Jul-24'!$F27,Lista_CUIT!$A$1:$D$2241,3,0)),"CUIT NO CARGADO") -> Mantenimiento | R27: =IFERROR(IF('Jul-24'!$F27="","-",VLOOKUP('Jul-24'!$F27,Lista_CUIT!$A$1:$D$2241,4,0)),"CUIT NO CARGADO") -> 0
B28: 30/07/2024 | C28: 1 | D28: 2 | E28: 712 | F28: 20120109449 | G28: =IFERROR(IF('Jul-24'!$F28="","-",VLOOKUP('Jul-24'!$F28,Lista_CUIT!$A$1:$D$2241,2,0)),"CUIT NO CARGADO") -> PEREZ HORACIO HUGO | H28: 158400 | I28: =IF('Jul-24'!$H28="","",'Jul-24'!$H28*0.21) -> 33264 | P28: =SUM('Jul-24'!$H28:$O28) -> 191664 | Q28: =IFERROR(IF('Jul-24'!$F28="","-",VLOOKUP('Jul-24'!$F28,Lista_CUIT!$A$1:$D$2241,3,0)),"CUIT NO CARGADO") -> INSUMO | R28: =IFERROR(IF('Jul-24'!$F28="","-",VLOOKUP('Jul-24'!$F28,Lista_CUIT!$A$1:$D$2241,4,0)),"CUIT NO CARGADO") -> 0
B29: 30/07/2024 | C29: 1 | D29: 7 | E29: 16733 | F29: 30604413482 | G29: =IFERROR(IF('Jul-24'!$F29="","-",VLOOKUP('Jul-24'!$F29,Lista_CUIT!$A$1:$D$2241,2,0)),"CUIT NO CARGADO") -> BULONERA VIETRI SOCIEDAD DE RESPONSABILIDAD LIMITADA | H29: 16850 | I29: =IF('Jul-24'!$H29="","",'Jul-24'!$H29*0.21) -> 3538.5 | P29: =SUM('Jul-24'!$H29:$O29) -> 20388.5 | Q29: =IFERROR(IF('Jul-24'!$F29="","-",VLOOKUP('Jul-24'!$F29,Lista_CUIT!$A$1:$D$2241,3,0)),"CUIT NO CARGADO") -> INSUMO | R29: =IFERROR(IF('Jul-24'!$F29="","-",VLOOKUP('Jul-24'!$F29,Lista_CUIT!$A$1:$D$2241,4,0)),"CUIT NO CARGADO") -> 0
B30: 31/07/2024 | C30: 1 | D30: 4 | E30: 3715 | F30: 20068864934 | G30: =IFERROR(IF('Jul-24'!$F30="","-",VLOOKUP('Jul-24'!$F30,Lista_CUIT!$A$1:$D$2241,2,0)),"CUIT NO CARGADO") -> LEVIN JACOBO BERNARDO | H30: 19376.03 | I30: =IF('Jul-24'!$H30="","",'Jul-24'!$H30*0.21) -> 4068.9663 | P30: =SUM('Jul-24'!$H30:$O30) -> 23444.996 | Q30: =IFERROR(IF('Jul-24'!$F30="","-",VLOOKUP('Jul-24'!$F30,Lista_CUIT!$A$1:$D$2241,3,0)),"CUIT NO CARGADO") -> INSUMO | R30: =IFERROR(IF('Jul-24'!$F30="","-",VLOOKUP('Jul-24'!$F30,Lista_CUIT!$A$1:$D$2241,4,0)),"CUIT NO CARGADO") -> 0
B31: 31/07/2024 | C31: 1 | D31: 700 | E31: 687713 | F31: 30580111315 | G31: =IFERROR(IF('Jul-24'!$F31="","-",VLOOKUP('Jul-24'!$F31,Lista_CUIT!$A$1:$D$2241,2,0)),"CUIT NO CARGADO") -> DHL EXPRESS (ARGENTINA) S.A. | H31: 14265 | I31: =IF('Jul-24'!$H31="","",'Jul-24'!$H31*0.21) -> 2995.65 | O31: 392905.65 | P31: =SUM('Jul-24'!$H31:$O31) -> 410166.3 | Q31: =IFERROR(IF('Jul-24'!$F31="","-",VLOOKUP('Jul-24'!$F31,Lista_CUIT!$A$1:$D$2241,3,0)),"CUIT NO CARGADO") -> Gastos Importacion | R31: =IFERROR(IF('Jul-24'!$F31="","-",VLOOKUP('Jul-24'!$F31,Lista_CUIT!$A$1:$D$2241,4,0)),"CUIT NO CARGADO") -> 0
G32: =IFERROR(IF('Jul-24'!$F32="","-",VLOOKUP('Jul-24'!$F32,Lista_CUIT!$A$1:$D$2241,2,0)),"CUIT NO CARGADO") -> - | I32: =IF('Jul-24'!$H32="","",'Jul-24'!$H32*0.21) | P32: =SUM('Jul-24'!$H32:$O32) -> 0 | Q32: =IFERROR(IF('Jul-24'!$F32="","-",VLOOKUP('Jul-24'!$F32,Lista_CUIT!$A$1:$D$2241,3,0)),"CUIT NO CARGADO") -> - | R32: =IFERROR(IF('Jul-24'!$F32="","-",VLOOKUP('Jul-24'!$F32,Lista_CUIT!$A$1:$D$2241,4,0)),"CUIT NO CARGADO") -> -
G33: =IFERROR(IF('Jul-24'!$F33="","-",VLOOKUP('Jul-24'!$F33,Lista_CUIT!$A$1:$D$2241,2,0)),"CUIT NO CARGADO") -> - | I33: =IF('Jul-24'!$H33="","",'Jul-24'!$H33*0.21) | P33: =SUM('Jul-24'!$H33:$O33) -> 0 | Q33: =IFERROR(IF('Jul-24'!$F33="","-",VLOOKUP('Jul-24'!$F33,Lista_CUIT!$A$1:$D$2241,3,0)),"CUIT NO CARGADO") -> - | R33: =IFERROR(IF('Jul-24'!$F33="","-",VLOOKUP('Jul-24'!$F33,Lista_CUIT!$A$1:$D$2241,4,0)),"CUIT NO CARGADO") -> - | S33: COD 05
G34: =IFERROR(IF('Jul-24'!$F34="","-",VLOOKUP('Jul-24'!$F34,Lista_CUIT!$A$1:$D$2241,2,0)),"CUIT NO CARGADO") -> - | I34: =IF('Jul-24'!$H34="","",'Jul-24'!$H34*0.21) | P34: =SUM('Jul-24'!$H34:$O34) -> 0 | Q34: =IFERROR(IF('Jul-24'!$F34="","-",VLOOKUP('Jul-24'!$F34,Lista_CUIT!$A$1:$D$2241,3,0)),"CUIT NO CARGADO") -> - | R34: =IFERROR(IF('Jul-24'!$F34="","-",VLOOKUP('Jul-24'!$F34,Lista_CUIT!$A$1:$D$2241,4,0)),"CUIT NO CARGADO") -> - | S34: COD 81
B35: Total | H35: =SUBTOTAL(109,'Jul-24'!$H$9:$H$34) -> 19384475 | I35: =SUBTOTAL(109,'Jul-24'!$I$9:$I$34) -> 4064721.8 | J35: =SUBTOTAL(109,'Jul-24'!$J$9:$J$34) -> 7737.3414 | K35: =SUBTOTAL(109,'Jul-24'!$K$9:$K$34) -> 0 | L35: =SUBTOTAL(109,'Jul-24'!$L$9:$L$34) -> 859.7 | M35: =SUBTOTAL(109,'Jul-24'!$M$9:$M$34) -> 0 | N35: =SUBTOTAL(109,'Jul-24'!$N$9:$N$34) -> 0 | O35: =SUBTOTAL(109,'Jul-24'!$O$9:$O$34) -> 1136805.4 | P35: =SUBTOTAL(109,'Jul-24'!$P$9:$P$34) -> 24594599
D40: LIQUIDACION EXTRACTOS BANCARIOS-TARJETAS
D41: FECHA | E41: NRO CPTE | F41: BANCO | G41: NETO | H41: IVA 21% | I41: IVA 10,5% | J41: RET IIBB CABA | K41: PERC IVA | L41: PERC IIBB
H42: ='Jul-24'!$G42*0.21 -> 0
H43: ='Jul-24'!$G43*0.21 -> 0
H44: ='Jul-24'!$G44*0.21 -> 0
H45: ='Jul-24'!$G45*0.21 -> 0
H46: ='Jul-24'!$G46*0.21 -> 0
D47: Total | G47: =SUBTOTAL(109,'Jul-24'!$G$42:$G$46) -> 0 | H47: =SUBTOTAL(109,'Jul-24'!$H$42:$H$46) -> 0 | I47: =SUBTOTAL(109,'Jul-24'!$I$42:$I$46) -> 0 | J47: =SUBTOTAL(109,'Jul-24'!$J$42:$J$46) -> 0 | K47: =SUBTOTAL(109,'Jul-24'!$K$42:$K$46) -> 0 | L47: =SUBTOTAL(109,'Jul-24'!$L$42:$L$46) -> 0
D51: FACTURAS C
D52: FECHA | E52: PTO VTA | F52: FC Nº | G52: CUIT | H52: RAZON SOCIAL | I52: TOTAL | J52: TIPO DE GASTO | K52: Provincia
D53: 01/07/2024 | E53: 1 | F53: 27 | G53: 27387896150 | H53: =IFERROR(IF('Jul-24'!$G53="","-",VLOOKUP('Jul-24'!$G53,Lista_CUIT!$A$1:$D$2241,2,0)),"CUIT NO CARGADO") -> LIPANOVICH MARIA SOL | I53: 900000 | J53: =IFERROR(IF('Jul-24'!$G53="","-",VLOOKUP('Jul-24'!$G53,Lista_CUIT!$A$1:$D$2241,3,0)),"CUIT NO CARGADO") -> consultoria informatica | K53: =IFERROR(IF('Jul-24'!$G53="","-",VLOOKUP('Jul-24'!$G53,Lista_CUIT!$A$1:$D$2241,4,0)),"CUIT NO CARGADO") -> 0
D54: 01/07/2024 | E54: 4 | F54: 27 | G54: 20341462933 | H54: =IFERROR(IF('Jul-24'!$G54="","-",VLOOKUP('Jul-24'!$G54,Lista_CUIT!$A$1:$D$2241,2,0)),"CUIT NO CARGADO") -> CASTIGLIONI MATIAS EZEQUIEL | I54: 1170000 | J54: =IFERROR(IF('Jul-24'!$G54="","-",VLOOKUP('Jul-24'!$G54,Lista_CUIT!$A$1:$D$2241,3,0)),"CUIT NO CARGADO") -> ASESORAMIENTO | K54: =IFERROR(IF('Jul-24'!$G54="","-",VLOOKUP('Jul-24'!$G54,Lista_CUIT!$A$1:$D$2241,4,0)),"CUIT NO CARGADO") -> BUENOS AIRES
D55: 01/07/2024 | E55: 1 | F55: 38 | G55: 20365938688 | H55: =IFERROR(IF('Jul-24'!$G55="","-",VLOOKUP('Jul-24'!$G55,Lista_CUIT!$A$1:$D$2241,2,0)),"CUIT NO CARGADO") -> LIPANOVICH JUAN CRUZ | I55: 750000 | J55: =IFERROR(IF('Jul-24'!$G55="","-",VLOOKUP('Jul-24'!$G55,Lista_CUIT!$A$1:$D$2241,3,0)),"CUIT NO CARGADO") -> SOFTWARE | K55: =IFERROR(IF('Jul-24'!$G55="","-",VLOOKUP('Jul-24'!$G55,Lista_CUIT!$A$1:$D$2241,4,0)),"CUIT NO CARGADO") -> 0
D56: 01/07/2024 | E56: 2 | F56: 245 | G56: 27173820866 | H56: =IFERROR(IF('Jul-24'!$G56="","-",VLOOKUP('Jul-24'!$G56,Lista_CUIT!$A$1:$D$2241,2,0)),"CUIT NO CARGADO") -> FREIER SANDRA DANIELA | I56: 550000 | J56: =IFERROR(IF('Jul-24'!$G56="","-",VLOOKUP('Jul-24'!$G56,Lista_CUIT!$A$1:$D$2241,3,0)),"CUIT NO CARGADO") -> Honorarios Prof | K56: =IFERROR(IF('Jul-24'!$G56="","-",VLOOKUP('Jul-24'!$G56,Lista_CUIT!$A$1:$D$2241,4,0)),"CUIT NO CARGADO") -> 0
D57: 02/07/2024 | E57: 2 | F57: 5 | G57: 23118167279 | H57: =IFERROR(IF('Jul-24'!$G57="","-",VLOOKUP('Jul-24'!$G57,Lista_CUIT!$A$1:$D$2241,2,0)),"CUIT NO CARGADO") -> ABELEDO ENRIQUE JUAN | I57: 780000 | J57: =IFERROR(IF('Jul-24'!$G57="","-",VLOOKUP('Jul-24'!$G57,Lista_CUIT!$A$1:$D$2241,3,0)),"CUIT NO CARGADO") -> Honorarios Admin | K57: =IFERROR(IF('Jul-24'!$G57="","-",VLOOKUP('Jul-24'!$G57,Lista_CUIT!$A$1:$D$2241,4,0)),"CUIT NO CARGADO") -> 0
D58: 03/07/2024 | E58: 3 | F58: 864 | G58: 20086277523 | H58: =IFERROR(IF('Jul-24'!$G58="","-",VLOOKUP('Jul-24'!$G58,Lista_CUIT!$A$1:$D$2241,2,0)),"CUIT NO CARGADO") -> ESTUDIO BOTINDARI | I58: 210000 | J58: =IFERROR(IF('Jul-24'!$G58="","-",VLOOKUP('Jul-24'!$G58,Lista_CUIT!$A$1:$D$2241,3,0)),"CUIT NO CARGADO") -> Honorarios Contables | K58: =IFERROR(IF('Jul-24'!$G58="","-",VLOOKUP('Jul-24'!$G58,Lista_CUIT!$A$1:$D$2241,4,0)),"CUIT NO CARGADO") -> 0
D59: 03/07/2024 | E59: 1 | F59: 447 | G59: 27925308868 | H59: =IFERROR(IF('Jul-24'!$G59="","-",VLOOKUP('Jul-24'!$G59,Lista_CUIT!$A$1:$D$2241,2,0)),"CUIT NO CARGADO") -> LOPEZ MOLINA MARIA | I59: 18000 | J59: =IFERROR(IF('Jul-24'!$G59="","-",VLOOKUP('Jul-24'!$G59,Lista_CUIT!$A$1:$D$2241,3,0)),"CUIT NO CARGADO") -> GASTOS VARIOS | K59: =IFERROR(IF('Jul-24'!$G59="","-",VLOOKUP('Jul-24'!$G59,Lista_CUIT!$A$1:$D$2241,4,0)),"CUIT NO CARGADO") -> 0
D60: 03/07/2024 | E60: 1 | F60: 108 | G60: 20389908569 | H60: =IFERROR(IF('Jul-24'!$G60="","-",VLOOKUP('Jul-24'!$G60,Lista_CUIT!$A$1:$D$2241,2,0)),"CUIT NO CARGADO") -> BOTINDARI JUAN IGNACIO | I60: 72530 | J60: =IFERROR(IF('Jul-24'!$G60="","-",VLOOKUP('Jul-24'!$G60,Lista_CUIT!$A$1:$D$2241,3,0)),"CUIT NO CARGADO") -> Honorarios Contables | K60: =IFERROR(IF('Jul-24'!$G60="","-",VLOOKUP('Jul-24'!$G60,Lista_CUIT!$A$1:$D$2241,4,0)),"CUIT NO CARGADO") -> 0
D61: 04/07/2024 | E61: 3 | F61: 866 | G61: 20086277523 | H61: =IFERROR(IF('Jul-24'!$G61="","-",VLOOKUP('Jul-24'!$G61,Lista_CUIT!$A$1:$D$2241,2,0)),"CUIT NO CARGADO") -> ESTUDIO BOTINDARI | I61: 60000 | J61: =IFERROR(IF('Jul-24'!$G61="","-",VLOOKUP('Jul-24'!$G61,Lista_CUIT!$A$1:$D$2241,3,0)),"CUIT NO CARGADO") -> Honorarios Contables | K61: =IFERROR(IF('Jul-24'!$G61="","-",VLOOKUP('Jul-24'!$G61,Lista_CUIT!$A$1:$D$2241,4,0)),"CUIT NO CARGADO") -> 0
D62: 12/07/2024 | E62: 1006 | F62: 1014716 | G62: 30715103946 | H62: =IFERROR(IF('Jul-24'!$G62="","-",VLOOKUP('Jul-24'!$G62,Lista_CUIT!$A$1:$D$2241,2,0)),"CUIT NO CARGADO") -> LIBRENTA LIBROS S. A. U. | I62: 30800 | J62: =IFERROR(IF('Jul-24'!$G62="","-",VLOOKUP('Jul-24'!$G62,Lista_CUIT!$A$1:$D$2241,3,0)),"CUIT NO CARGADO") -> Honorarios Admin | K62: =IFERROR(IF('Jul-24'!$G62="","-",VLOOKUP('Jul-24'!$G62,Lista_CUIT!$A$1:$D$2241,4,0)),"CUIT NO CARGADO") -> 0
D63: 15/07/2024 | E63: 3 | F63: 88 | G63: 20403931420 | H63: =IFERROR(IF('Jul-24'!$G63="","-",VLOOKUP('Jul-24'!$G63,Lista_CUIT!$A$1:$D$2241,2,0)),"CUIT NO CARGADO") -> FIORENTINO JORGE IGNACIO | I63: 550000 | J63: =IFERROR(IF('Jul-24'!$G63="","-",VLOOKUP('Jul-24'!$G63,Lista_CUIT!$A$1:$D$2241,3,0)),"CUIT NO CARGADO") -> Honorarios Prof | K63: =IFERROR(IF('Jul-24'!$G63="","-",VLOOKUP('Jul-24'!$G63,Lista_CUIT!$A$1:$D$2241,4,0)),"CUIT NO CARGADO") -> 0
D64: 15/07/2024 | E64: 4 | F64: 65 | G64: 23214737914 | H64: =IFERROR(IF('Jul-24'!$G64="","-",VLOOKUP('Jul-24'!$G64,Lista_CUIT!$A$1:$D$2241,2,0)),"CUIT NO CARGADO") -> SBARRA GABRIELA BEATRIZ | I64: 759880 | J64: =IFERROR(IF('Jul-24'!$G64="","-",VLOOKUP('Jul-24'!$G64,Lista_CUIT!$A$1:$D$2241,3,0)),"CUIT NO CARGADO") -> Honorarios Admin | K64: =IFERROR(IF('Jul-24'!$G64="","-",VLOOKUP('Jul-24'!$G64,Lista_CUIT!$A$1:$D$2241,4,0)),"CUIT NO CARGADO") -> 0
D65: 19/07/2024 | E65: 2 | F65: 173 | G65: 20136544625 | H65: =IFERROR(IF('Jul-24'!$G65="","-",VLOOKUP('Jul-24'!$G65,Lista_CUIT!$A$1:$D$2241,2,0)),"CUIT NO CARGADO") -> RODRIGUEZ DE LA FUEN HECTOR MARCELO | I65: 600000 | J65: =IFERROR(IF('Jul-24'!$G65="","-",VLOOKUP('Jul-24'!$G65,Lista_CUIT!$A$1:$D$2241,3,0)),"CUIT NO CARGADO") -> Honorarios Admin | K65: =IFERROR(IF('Jul-24'!$G65="","-",VLOOKUP('Jul-24'!$G65,Lista_CUIT!$A$1:$D$2241,4,0)),"CUIT NO CARGADO") -> 0
D66: Total | I66: =SUBTOTAL(109,'Jul-24'!$I$53:$I$65) -> 6451210
B72: LIBRO IVA VENTAS | K72: =N1 -> 45108
B74: VENTAS "A"
B75: FECHA | C75: TIPO | D75: PTO VENTA | E75: Nº FACTURA | F75: CUIT | G75: RAZON SOCIAL | H75: IMPORTE NETO | I75: IVA 21% | J75: IVA 10,5% | K75: EXENTO | L75: TOTAL | M75: Provincia
B76: 45474 | C76: 1 | D76: 3 | E76: 204 | F76: 30638318470 | G76: =IFERROR(IF('Jul-24'!$F76="","-",VLOOKUP('Jul-24'!$F76,Lista_CUIT!$A$1:$D$2241,2,0)),"CUIT NO CARGADO") -> DELTA COMPRESION S R L | H76: 23694825 | J76: ='Jul-24'!$H76*0.105 -> 2487956.6 | L76: =SUM('Jul-24'!$H76:$K76) -> 26182782
B77: 45484 | C77: 1 | D77: 3 | E77: 205 | F77: 30628274327 | G77: =IFERROR(IF('Jul-24'!$F77="","-",VLOOKUP('Jul-24'!$F77,Lista_CUIT!$A$1:$D$2241,2,0)),"CUIT NO CARGADO") -> AGIRA S A | H77: 12743445 | I77: =278850*0.21 -> 58558.5 | J77: =12464595*0.105 -> 1308782.5 | L77: =SUM('Jul-24'!$H77:$K77) -> 14110786
B78: 45485 | C78: 1 | D78: 3 | E78: 206 | F78: 30638318470 | G78: =IFERROR(IF('Jul-24'!$F78="","-",VLOOKUP('Jul-24'!$F78,Lista_CUIT!$A$1:$D$2241,2,0)),"CUIT NO CARGADO") -> DELTA COMPRESION S R L | H78: 321480 | I78: ='Jul-24'!$H78*0.21 -> 67510.8 | L78: =SUM('Jul-24'!$H78:$K78) -> 388990.8
B79: 45492 | C79: 1 | D79: 3 | E79: 207 | F79: 30628274327 | G79: =IFERROR(IF('Jul-24'!$F79="","-",VLOOKUP('Jul-24'!$F79,Lista_CUIT!$A$1:$D$2241,2,0)),"CUIT NO CARGADO") -> AGIRA S A | H79: 12921675 | I79: =282750*0.21 -> 59377.5 | J79: 1327087.1 | L79: =SUM('Jul-24'!$H79:$K79) -> 14308140
B80: 45495 | C80: 1 | D80: 3 | E80: 209 | F80: 30668033667 | G80: =IFERROR(IF('Jul-24'!$F80="","-",VLOOKUP('Jul-24'!$F80,Lista_CUIT!$A$1:$D$2241,2,0)),"CUIT NO CARGADO") -> LLANTAY SRL | H80: 1651716 | I80: ='Jul-24'!$H80*0.21 -> 346860.36 | L80: =SUM('Jul-24'!$H80:$K80) -> 1998576.4
B81: 45495 | C81: 1 | D81: 3 | E81: 208 | F81: 20413837635 | G81: =IFERROR(IF('Jul-24'!$F81="","-",VLOOKUP('Jul-24'!$F81,Lista_CUIT!$A$1:$D$2241,2,0)),"CUIT NO CARGADO") -> SUAREZ MATIAS IVAN | H81: 1390620 | I81: ='Jul-24'!$H81*0.21 -> 292030.2 | L81: =SUM('Jul-24'!$H81:$K81) -> 1682650.2
B82: 45496 | C82: 1 | D82: 3 | E82: 211 | F82: 30708548061 | G82: =IFERROR(IF('Jul-24'!$F82="","-",VLOOKUP('Jul-24'!$F82,Lista_CUIT!$A$1:$D$2241,2,0)),"CUIT NO CARGADO") -> PETRO GRUTA S.R.L. | H82: 1651716 | I82: ='Jul-24'!$H82*0.21 -> 346860.36 | L82: =SUM('Jul-24'!$H82:$K82) -> 1998576.4
B83: 45496 | C83: 1 | D83: 3 | E83: 210 | F83: 30710473710 | G83: =IFERROR(IF('Jul-24'!$F83="","-",VLOOKUP('Jul-24'!$F83,Lista_CUIT!$A$1:$D$2241,2,0)),"CUIT NO CARGADO") -> POWER TEKNIC SA | H83: 1677828 | I83: ='Jul-24'!$H83*0.21 -> 352343.88 | L83: =SUM('Jul-24'!$H83:$K83) -> 2030171.9
B84: 45496 | C84: 3 | D84: 3 | E84: 23 | F84: 30668033667 | G84: =IFERROR(IF('Jul-24'!$F84="","-",VLOOKUP('Jul-24'!$F84,Lista_CUIT!$A$1:$D$2241,2,0)),"CUIT NO CARGADO") -> LLANTAY SRL | H84: -1651716 | I84: ='Jul-24'!$H84*0.21 -> -346860.36 | L84: =SUM('Jul-24'!$H84:$K84) -> -1998576.4
B85: 45499 | C85: 1 | D85: 3 | E85: 212 | F85: 30708592532 | G85: =IFERROR(IF('Jul-24'!$F85="","-",VLOOKUP('Jul-24'!$F85,Lista_CUIT!$A$1:$D$2241,2,0)),"CUIT NO CARGADO") -> BASSO INDEPENDENCIA SA | H85: 5791950 | I85: =759600*0.21 -> 159516 | J85: =5032350*0.105 -> 528396.75 | L85: =SUM('Jul-24'!$H85:$K85) -> 6479862.8
B86: Total | H86: =SUBTOTAL(109,'Jul-24'!$H$76:$H$85) -> 60193539 | I86: =SUBTOTAL(109,'Jul-24'!$I$76:$I$85) -> 1336197.2 | J86: =SUBTOTAL(109,'Jul-24'!$J$76:$J$85) -> 5652223 | K86: =SUBTOTAL(109,'Jul-24'!$K$76:$K$85) -> 0 | L86: =SUBTOTAL(109,'Jul-24'!$L$76:$L$85) -> 67181959 | M86: =SUBTOTAL(103,'Jul-24'!$M$76:$M$85) -> 0
B88: VENTAS "B"
B89: FECHA | C89: TIPO | D89: PTO VENTA | E89: Nº FACTURA | F89: CUIT | G89: RAZON SOCIAL | H89: IMPORTE NETO | I89: IVA 21% | J89: IVA 10,5% | K89: EXENTO | L89: TOTAL | M89: Provincia
G90: =IFERROR(IF('Jul-24'!$F90="","-",VLOOKUP('Jul-24'!$F90,Lista_CUIT!$A$1:$D$2241,2,0)),"CUIT NO CARGADO") -> - | I90: ='Jul-24'!$H90*0.21 -> 0 | L90: =SUM('Jul-24'!$H90:$K90) -> 0
I91: ='Jul-24'!$H91*0.21 -> 0 | L91: =SUM('Jul-24'!$H91:$K91) -> 0
I92: ='Jul-24'!$H92*0.21 -> 0 | L92: =SUM('Jul-24'!$H92:$K92) -> 0
I93: ='Jul-24'!$H93*0.21 -> 0 | L93: =SUM('Jul-24'!$H93:$K93) -> 0
I94: ='Jul-24'!$H94*0.21 -> 0 | L94: =SUM('Jul-24'!$H94:$K94) -> 0
I95: ='Jul-24'!$H95*0.21 -> 0 | L95: =SUM('Jul-24'!$H95:$K95) -> 0
B96: Total | H96: =SUBTOTAL(109,'Jul-24'!$H$90:$H$95) -> 0 | I96: =SUBTOTAL(109,'Jul-24'!$I$90:$I$95) -> 0 | J96: =SUBTOTAL(109,'Jul-24'!$J$90:$J$95) -> 0 | K96: =SUBTOTAL(109,'Jul-24'!$K$90:$K$95) -> 0 | L96: =SUBTOTAL(109,'Jul-24'!$L$90:$L$95) -> 0 | M96: =SUBTOTAL(103,'Jul-24'!$M$90:$M$95) -> 0
B99: VENTAS "E"
B100: FECHA | C100: TIPO | D100: PTO VENTA | E100: Nº FACTURA | F100: CUIT | G100: RAZON SOCIAL | H100: USD | I100: TIPO DE CAMBIO2 | J100: TOTAL | K100: Pais
G101: =IFERROR(IF('Jul-24'!$F101="","-",VLOOKUP('Jul-24'!$F101,Lista_CUIT!$A$1:$D$2241,2,0)),"CUIT NO CARGADO") -> - | J101: ='Jul-24'!$H101*'Jul-24'!$I101 -> 0
G102: =IFERROR(IF('Jul-24'!$F102="","-",VLOOKUP('Jul-24'!$F102,Lista_CUIT!$A$1:$D$2241,2,0)),"CUIT NO CARGADO") -> - | J102: ='Jul-24'!$H102*'Jul-24'!$I102 -> 0
B103: Total | H103: =SUBTOTAL(109,'Jul-24'!$H$101:$H$102) -> 0 | I103: =SUBTOTAL(109,'Jul-24'!$I$101:$I$102) -> 0 | J103: =SUBTOTAL(109,'Jul-24'!$J$101:$J$102) -> 0 | K103: =SUBTOTAL(103,'Jul-24'!$K$101:$K$102) -> 0
C107: RETENCIONES
C108: FECHA | D108: COMP Nº | E108: Columna1 | F108: CUIT | G108: RAZON SOCIAL | H108: Ganancias | I108: IVA | J108: SUSS | K108: IIBB BSAS | L108: IIBB CABA
G109: =IFERROR(IF('Jul-24'!$F109="","-",VLOOKUP('Jul-24'!$F109,Lista_CUIT!$A$1:$D$2241,2,0)),"CUIT NO CARGADO") -> - | I109: 9597.94 | J109: 914.09
G110: =IFERROR(IF('Jul-24'!$F110="","-",VLOOKUP('Jul-24'!$F110,Lista_CUIT!$A$1:$D$2241,2,0)),"CUIT NO CARGADO") -> -
G111: =IFERROR(IF('Jul-24'!$F111="","-",VLOOKUP('Jul-24'!$F111,Lista_CUIT!$A$1:$D$2241,2,0)),"CUIT NO CARGADO") -> -
G112: =IFERROR(IF('Jul-24'!$F112="","-",VLOOKUP('Jul-24'!$F112,Lista_CUIT!$A$1:$D$2241,2,0)),"CUIT NO CARGADO") -> -
G113: =IFERROR(IF('Jul-24'!$F113="","-",VLOOKUP('Jul-24'!$F113,Lista_CUIT!$A$1:$D$2241,2,0)),"CUIT NO CARGADO") -> -

Sheet Ago-24
B1: LIBRO IVA COMPRAS | G1: ='Abr-24'!G1:M1 -> CORITEC S. R. L. | N1: =EDATE('Abr-24'!N1,4) -> 45139
B3: TOTAL COMPRAS | G3: TOTAL CREDITO FISCAL | J3: TOTAL VENTAS NETAS | M3: TOTAL DEBITO FISCAL | P3: RESULTADO
B4: =SUM('Ago-24'!$H$48)+'Ago-24'!$G$60 -> 14868505 | G4: ='Ago-24'!$I$48+'Ago-24'!$J$48+'Ago-24'!$K$48+'Ago-24'!$H$60+'Ago-24'!$I$60 -> 3120688.7 | J4: ='Ago-24'!$H$103+'Ago-24'!$H$114 -> 64891119 | M4: ='Ago-24'!$I$103+'Ago-24'!$J$103+'Ago-24'!$I$114+'Ago-24'!$J$114 -> 7523638.3 | P4: =G4-M4 -> -4402949.6
B8: FECHA | C8: TIPO | D8: PTO VTA | E8: NRO. CPTE | F8: CUIT | G8: RAZON SOCIAL | H8: NETO GRAVADO | I8: IVA 21 % | J8: IVA 27% | K8: IVA 10,5% | L8: PERC. IVA | M8: PERC IIBB BS AS | N8: PERC. IIBB CABA | O8: Otros / No Grav. | P8: TOTAL | Q8: Tipo de Gasto | R8: Provincia | S8: Columna1 | T8: Columna2
B9: 09/08/2024 | C9: 1 | D9: 3 | E9: 139 | F9: 20297899830 | G9: =IFERROR(IF('Ago-24'!$F9="","-",VLOOKUP('Ago-24'!$F9,Lista_CUIT!$A$1:$D$2241,2,0)),"CUIT NO CARGADO") -> FUNK MATIAS NICOLAS | H9: 5547040 | I9: =IF('Ago-24'!$H9="","",'Ago-24'!$H9*0.21) -> 1164878.4 | P9: =SUM('Ago-24'!$H9:$O9) -> 6711918.4 | Q9: =IFERROR(IF('Ago-24'!$F9="","-",VLOOKUP('Ago-24'!$F9,Lista_CUIT!$A$1:$D$2241,3,0)),"CUIT NO CARGADO") -> INSUMO | R9: =IFERROR(IF('Ago-24'!$F9="","-",VLOOKUP('Ago-24'!$F9,Lista_CUIT!$A$1:$D$2241,4,0)),"CUIT NO CARGADO") -> 0 | S9: 6711918.4 | T9: ='Ago-24'!$P9-'Ago-24'!$S9 -> 0
B10: 04/08/2024 | C10: 1 | D10: 2 | E10: 202 | F10: 20125142851 | G10: =IFERROR(IF('Ago-24'!$F10="","-",VLOOKUP('Ago-24'!$F10,Lista_CUIT!$A$1:$D$2241,2,0)),"CUIT NO CARGADO") -> FEDERICI NICOLAS JOSE | H10: 351369.9 | I10: =IF('Ago-24'!$H10="","",'Ago-24'!$H10*0.21) -> 73787.679 | P10: =SUM('Ago-24'!$H10:$O10) -> 425157.58 | Q10: =IFERROR(IF('Ago-24'!$F10="","-",VLOOKUP('Ago-24'!$F10,Lista_CUIT!$A$1:$D$2241,3,0)),"CUIT NO CARGADO") -> INSUMO | R10: =IFERROR(IF('Ago-24'!$F10="","-",VLOOKUP('Ago-24'!$F10,Lista_CUIT!$A$1:$D$2241,4,0)),"CUIT NO CARGADO") -> 0 | S10: 425157.58 | T10: ='Ago-24'!$P10-'Ago-24'!$S10 -> -0.00099999999
B11: 27/08/2024 | C11: 1 | D11: 2 | E11: 203 | F11: 20125142851 | G11: =IFERROR(IF('Ago-24'!$F11="","-",VLOOKUP('Ago-24'!$F11,Lista_CUIT!$A$1:$D$2241,2,0)),"CUIT NO CARGADO") -> FEDERICI NICOLAS JOSE | H11: 1349912.9 | I11: =IF('Ago-24'!$H11="","",'Ago-24'!$H11*0.21) -> 283481.7 | P11: =SUM('Ago-24'!$H11:$O11) -> 1633394.6 | Q11: =IFERROR(IF('Ago-24'!$F11="","-",VLOOKUP('Ago-24'!$F11,Lista_CUIT!$A$1:$D$2241,3,0)),"CUIT NO CARGADO") -> INSUMO | R11: =IFERROR(IF('Ago-24'!$F11="","-",VLOOKUP('Ago-24'!$F11,Lista_CUIT!$A$1:$D$2241,4,0)),"CUIT NO CARGADO") -> 0 | S11: 1633394.6 | T11: ='Ago-24'!$P11-'Ago-24'!$S11 -> -0.0194
B12: 10/08/2024 | C12: 1 | D12: 109 | E12: 461 | F12: 30570861278 | G12: =IFERROR(IF('Ago-24'!$F12="","-",VLOOKUP('Ago-24'!$F12,Lista_CUIT!$A$1:$D$2241,2,0)),"CUIT NO CARGADO") -> PINTURERIA ROSMAR S A | H12: 102826.99 | I12: =IF('Ago-24'!$H12="","",'Ago-24'!$H12*0.21) -> 21593.668 | P12: =SUM('Ago-24'!$H12:$O12) -> 124420.66 | Q12: =IFERROR(IF('Ago-24'!$F12="","-",VLOOKUP('Ago-24'!$F12,Lista_CUIT!$A$1:$D$2241,3,0)),"CUIT NO CARGADO") -> pintureria | R12: =IFERROR(IF('Ago-24'!$F12="","-",VLOOKUP('Ago-24'!$F12,Lista_CUIT!$A$1:$D$2241,4,0)),"CUIT NO CARGADO") -> 0 | S12: 124420.66 | T12: ='Ago-24'!$P12-'Ago-24'!$S12 -> -0.0021
B13: 01/08/2024 | C13: 1 | D13: 3 | E13: 777 | F13: 30715402765 | G13: =IFERROR(IF('Ago-24'!$F13="","-",VLOOKUP('Ago-24'!$F13,Lista_CUIT!$A$1:$D$2241,2,0)),"CUIT NO CARGADO") -> RIO 265 S.R.L. | H13: 61983.48 | I13: =IF('Ago-24'!$H13="","",'Ago-24'!$H13*0.21) -> 13016.531 | P13: =SUM('Ago-24'!$H13:$O13) -> 75000.011 | Q13: =IFERROR(IF('Ago-24'!$F13="","-",VLOOKUP('Ago-24'!$F13,Lista_CUIT!$A$1:$D$2241,3,0)),"CUIT NO CARGADO") -> GASTOS VARIOS | R13: =IFERROR(IF('Ago-24'!$F13="","-",VLOOKUP('Ago-24'!$F13,Lista_CUIT!$A$1:$D$2241,4,0)),"CUIT NO CARGADO") -> 0 | S13: 75000.01 | T13: ='Ago-24'!$P13-'Ago-24'!$S13 -> 0.00080000001
B14: 16/08/2024 | C14: 1 | D14: 1 | E14: 838 | F14: 30715048066 | G14: =IFERROR(IF('Ago-24'!$F14="","-",VLOOKUP('Ago-24'!$F14,Lista_CUIT!$A$1:$D$2241,2,0)),"CUIT NO CARGADO") -> ROLLS Y EMPANADAS SA | H14: 753210 | I14: =IF('Ago-24'!$H14="","",'Ago-24'!$H14*0.21) -> 158174.1 | P14: =SUM('Ago-24'!$H14:$O14) -> 911384.1 | Q14: =IFERROR(IF('Ago-24'!$F14="","-",VLOOKUP('Ago-24'!$F14,Lista_CUIT!$A$1:$D$2241,3,0)),"CUIT NO CARGADO") -> CATERING | R14: =IFERROR(IF('Ago-24'!$F14="","-",VLOOKUP('Ago-24'!$F14,Lista_CUIT!$A$1:$D$2241,4,0)),"CUIT NO CARGADO") -> 0 | S14: 911384.1 | T14: ='Ago-24'!$P14-'Ago-24'!$S14 -> 0
B15: 23/08/2024 | C15: 1 | D15: 4 | E15: 1654 | F15: 20268897721 | G15: =IFERROR(IF('Ago-24'!$F15="","-",VLOOKUP('Ago-24'!$F15,Lista_CUIT!$A$1:$D$2241,2,0)),"CUIT NO CARGADO") -> BAIGORRIA DIEGO JORGE | H15: 30316.74 | K15: ='Ago-24'!$H15*0.105 -> 3183.2577 | P15: =SUM('Ago-24'!$H15:$O15) -> 33499.998 | Q15: =IFERROR(IF('Ago-24'!$F15="","-",VLOOKUP('Ago-24'!$F15,Lista_CUIT!$A$1:$D$2241,3,0)),"CUIT NO CARGADO") -> Software Mantenimiento | R15: =IFERROR(IF('Ago-24'!$F15="","-",VLOOKUP('Ago-24'!$F15,Lista_CUIT!$A$1:$D$2241,4,0)),"CUIT NO CARGADO") -> 0 | S15: 33500 | T15: ='Ago-24'!$P15-'Ago-24'!$S15 -> -0.0023
B16: 14/08/2024 | C16: 1 | D16: 5 | E16: 2000 | F16: 20243751544 | G16: =IFERROR(IF('Ago-24'!$F16="","-",VLOOKUP('Ago-24'!$F16,Lista_CUIT!$A$1:$D$2241,2,0)),"CUIT NO CARGADO") -> BALDYGA MARTIN OSCAR | H16: 33016.53 | I16: =IF('Ago-24'!$H16="","",'Ago-24'!$H16*0.21) -> 6933.4713 | P16: =SUM('Ago-24'!$H16:$O16) -> 39950.001 | Q16: =IFERROR(IF('Ago-24'!$F16="","-",VLOOKUP('Ago-24'!$F16,Lista_CUIT!$A$1:$D$2241,3,0)),"CUIT NO CARGADO") -> GASTOS VARIOS | R16: =IFERROR(IF('Ago-24'!$F16="","-",VLOOKUP('Ago-24'!$F16,Lista_CUIT!$A$1:$D$2241,4,0)),"CUIT NO CARGADO") -> 0 | S16: 39950 | T16: ='Ago-24'!$P16-'Ago-24'!$S16 -> 0.0013
B17: 30/08/2024 | C17: 1 | D17: 3 | E17: 2804 | F17: 33717740519 | G17: =IFERROR(IF('Ago-24'!$F17="","-",VLOOKUP('Ago-24'!$F17,Lista_CUIT!$A$1:$D$2241,2,0)),"CUIT NO CARGADO") -> DIMALACK S.R.L. | H17: 20039.96 | I17: =IF('Ago-24'!$H17="","",'Ago-24'!$H17*0.21) -> 4208.3916 | P17: =SUM('Ago-24'!$H17:$O17) -> 24248.352 | Q17: =IFERROR(IF('Ago-24'!$F17="","-",VLOOKUP('Ago-24'!$F17,Lista_CUIT!$A$1:$D$2241,3,0)),"CUIT NO CARGADO") -> Ropa de Trabajo | R17: =IFERROR(IF('Ago-24'!$F17="","-",VLOOKUP('Ago-24'!$F17,Lista_CUIT!$A$1:$D$2241,4,0)),"CUIT NO CARGADO") -> 0 | S17: 24248.35 | T17: ='Ago-24'!$P17-'Ago-24'!$S17 -> 0.0016
B18: 14/08/2024 | C18: 1 | D18: 2 | E18: 2833 | F18: 30709131733 | G18: =IFERROR(IF('Ago-24'!$F18="","-",VLOOKUP('Ago-24'!$F18,Lista_CUIT!$A$1:$D$2241,2,0)),"CUIT NO CARGADO") -> DIGAS SRL | H18: 3141683 | I18: =IF('Ago-24'!$H18="","",'Ago-24'!$H18*0.21) -> 659753.43 | P18: =SUM('Ago-24'!$H18:$O18) -> 3801436.4 | Q18: =IFERROR(IF('Ago-24'!$F18="","-",VLOOKUP('Ago-24'!$F18,Lista_CUIT!$A$1:$D$2241,3,0)),"CUIT NO CARGADO") -> INSUMO | R18: =IFERROR(IF('Ago-24'!$F18="","-",VLOOKUP('Ago-24'!$F18,Lista_CUIT!$A$1:$D$2241,4,0)),"CUIT NO CARGADO") -> 0 | S18: 3801436.4 | T18: ='Ago-24'!$P18-'Ago-24'!$S18 -> 0
B19: 08/08/2024 | C19: 1 | D19: 3 | E19: 3474 | F19: 27214660097 | G19: =IFERROR(IF('Ago-24'!$F19="","-",VLOOKUP('Ago-24'!$F19,Lista_CUIT!$A$1:$D$2241,2,0)),"CUIT NO CARGADO") -> D ANGELO ANDREA FABIANA | H19: 441211 | I19: =IF('Ago-24'!$H19="","",'Ago-24'!$H19*0.21) -> 92654.31 | P19: =SUM('Ago-24'!$H19:$O19) -> 533865.31 | Q19: =IFERROR(IF('Ago-24'!$F19="","-",VLOOKUP('Ago-24'!$F19,Lista_CUIT!$A$1:$D$2241,3,0)),"CUIT NO CARGADO") -> Honorarios Prof | R19: =IFERROR(IF('Ago-24'!$F19="","-",VLOOKUP('Ago-24'!$F19,Lista_CUIT!$A$1:$D$2241,4,0)),"CUIT NO CARGADO") -> 0 | S19: 533865.31 | T19: ='Ago-24'!$P19-'Ago-24'!$S19 -> 0
B20: 30/08/2024 | C20: 1 | D20: 9 | E20: 4889 | F20: 30693449525 | G20: =IFERROR(IF('Ago-24'!$F20="","-",VLOOKUP('Ago-24'!$F20,Lista_CUIT!$A$1:$D$2241,2,0)),"CUIT NO CARGADO") -> PHONEMARK S R L | H20: 27965.24 | I20: =IF('Ago-24'!$H20="","",'Ago-24'!$H20*0.21) -> 5872.7004 | P20: =SUM('Ago-24'!$H20:$O20) -> 33837.94 | Q20: =IFERROR(IF('Ago-24'!$F20="","-",VLOOKUP('Ago-24'!$F20,Lista_CUIT!$A$1:$D$2241,3,0)),"CUIT NO CARGADO") -> GASTOS VARIOS | R20: =IFERROR(IF('Ago-24'!$F20="","-",VLOOKUP('Ago-24'!$F20,Lista_CUIT!$A$1:$D$2241,4,0)),"CUIT NO CARGADO") -> 0 | S20: 33837.94 | T20: ='Ago-24'!$P20-'Ago-24'!$S20 -> 0.0004
B21: 02/08/2024 | C21: 1 | D21: 7 | E21: 5413 | F21: 30685776215 | G21: =IFERROR(IF('Ago-24'!$F21="","-",VLOOKUP('Ago-24'!$F21,Lista_CUIT!$A$1:$D$2241,2,0)),"CUIT NO CARGADO") -> BULCOR SRL | H21: 5076.04 | I21: =IF('Ago-24'!$H21="","",'Ago-24'!$H21*0.21) -> 1065.9684 | P21: =SUM('Ago-24'!$H21:$O21) -> 6142.0084 | Q21: =IFERROR(IF('Ago-24'!$F21="","-",VLOOKUP('Ago-24'!$F21,Lista_CUIT!$A$1:$D$2241,3,0)),"CUIT NO CARGADO") -> INSUMO | R21: =IFERROR(IF('Ago-24'!$F21="","-",VLOOKUP('Ago-24'!$F21,Lista_CUIT!$A$1:$D$2241,4,0)),"CUIT NO CARGADO") -> 0 | S21: 6142.01 | T21: ='Ago-24'!$P21-'Ago-24'!$S21 -> -0.0016
B22: 13/08/2024 | C22: 1 | D22: 3 | E22: 12030 | F22: 20293627127 | G22: =IFERROR(IF('Ago-24'!$F22="","-",VLOOKUP('Ago-24'!$F22,Lista_CUIT!$A$1:$D$2241,2,0)),"CUIT NO CARGADO") -> GONZALEZ FERNANDO ARIEL | H22: 29493.43 | I22: =IF('Ago-24'!$H22="","",'Ago-24'!$H22*0.21) -> 6193.6203 | P22: =SUM('Ago-24'!$H22:$O22) -> 35687.05 | Q22: =IFERROR(IF('Ago-24'!$F22="","-",VLOOKUP('Ago-24'!$F22,Lista_CUIT!$A$1:$D$2241,3,0)),"CUIT NO CARGADO") -> GASTOS VARIOS | R22: =IFERROR(IF('Ago-24'!$F22="","-",VLOOKUP('Ago-24'!$F22,Lista_CUIT!$A$1:$D$2241,4,0)),"CUIT NO CARGADO") -> 0 | S22: 35687.05 | T22: ='Ago-24'!$P22-'Ago-24'!$S22 -> 0.0003
B23: 13/08/2024 | C23: 1 | D23: 15 | E23: 13004 | F23: 30708003316 | G23: =IFERROR(IF('Ago-24'!$F23="","-",VLOOKUP('Ago-24'!$F23,Lista_CUIT!$A$1:$D$2241,2,0)),"CUIT NO CARGADO") -> LOMIR SA | H23: 5751.35 | I23: =IF('Ago-24'!$H23="","",'Ago-24'!$H23*0.21) -> 1207.7835 | P23: =SUM('Ago-24'!$H23:$O23) -> 6959.1335 | Q23: =IFERROR(IF('Ago-24'!$F23="","-",VLOOKUP('Ago-24'!$F23,Lista_CUIT!$A$1:$D$2241,3,0)),"CUIT NO CARGADO") -> Seg e Higiene | R23: =IFERROR(IF('Ago-24'!$F23="","-",VLOOKUP('Ago-24'!$F23,Lista_CUIT!$A$1:$D$2241,4,0)),"CUIT NO CARGADO") -> 0 | S23: 6959.13 | T23: ='Ago-24'!$P23-'Ago-24'!$S23 -> 0.0035
B24: 30/08/2024 | C24: 1 | D24: 6 | E24: 15564 | F24: 30707756434 | G24: =IFERROR(IF('Ago-24'!$F24="","-",VLOOKUP('Ago-24'!$F24,Lista_CUIT!$A$1:$D$2241,2,0)),"CUIT NO CARGADO") -> SERVICIO INTEGRAL DE LIMPIEZA SRL | H24: 276000 | I24: =IF('Ago-24'!$H24="","",'Ago-24'!$H24*0.21) -> 57960 | P24: =SUM('Ago-24'!$H24:$O24) -> 333960 | Q24: =IFERROR(IF('Ago-24'!$F24="","-",VLOOKUP('Ago-24'!$F24,Lista_CUIT!$A$1:$D$2241,3,0)),"CUIT NO CARGADO") -> Mantenimiento | R24: =IFERROR(IF('Ago-24'!$F24="","-",VLOOKUP('Ago-24'!$F24,Lista_CUIT!$A$1:$D$2241,4,0)),"CUIT NO CARGADO") -> 0 | S24: 333960 | T24: ='Ago-24'!$P24-'Ago-24'!$S24 -> 0
B25: 05/08/2024 | C25: 1 | D25: 9 | E25: 16561 | F25: 30708573279 | G25: =IFERROR(IF('Ago-24'!$F25="","-",VLOOKUP('Ago-24'!$F25,Lista_CUIT!$A$1:$D$2241,2,0)),"CUIT NO CARGADO") -> BOTIX SRL | H25: 12839.45 | I25: =IF('Ago-24'!$H25="","",'Ago-24'!$H25*0.21) -> 2696.2845 | P25: =SUM('Ago-24'!$H25:$O25) -> 15535.735 | Q25: =IFERROR(IF('Ago-24'!$F25="","-",VLOOKUP('Ago-24'!$F25,Lista_CUIT!$A$1:$D$2241,3,0)),"CUIT NO CARGADO") -> INSUMO | R25: =IFERROR(IF('Ago-24'!$F25="","-",VLOOKUP('Ago-24'!$F25,Lista_CUIT!$A$1:$D$2241,4,0)),"CUIT NO CARGADO") -> 0 | S25: 15535.74 | T25: ='Ago-24'!$P25-'Ago-24'!$S25 -> -0.0055
B26: 02/08/2024 | C26: 1 | D26: 2 | E26: 16635 | F26: 20103565309 | G26: =IFERROR(IF('Ago-24'!$F26="","-",VLOOKUP('Ago-24'!$F26,Lista_CUIT!$A$1:$D$2241,2,0)),"CUIT NO CARGADO") -> CASATI ENRIQUE ARIEL | H26: 874574.95 | I26: =IF('Ago-24'!$H26="","",'Ago-24'!$H26*0.21) -> 183660.74 | P26: =SUM('Ago-24'!$H26:$O26) -> 1058235.7 | Q26: =IFERROR(IF('Ago-24'!$F26="","-",VLOOKUP('Ago-24'!$F26,Lista_CUIT!$A$1:$D$2241,3,0)),"CUIT NO CARGADO") -> Papeleria | R26: =IFERROR(IF('Ago-24'!$F26="","-",VLOOKUP('Ago-24'!$F26,Lista_CUIT!$A$1:$D$2241,4,0)),"CUIT NO CARGADO") -> 0 | S26: 1058235.7 | T26: ='Ago-24'!$P26-'Ago-24'!$S26 -> -0.0105
B27: 23/08/2024 | C27: 1 | D27: 9 | E27: 17357 | F27: 30641121521 | G27: =IFERROR(IF('Ago-24'!$F27="","-",VLOOKUP('Ago-24'!$F27,Lista_CUIT!$A$1:$D$2241,2,0)),"CUIT NO CARGADO") -> PATERNAL S R L | H27: 17279.34 | I27: =IF('Ago-24'!$H27="","",'Ago-24'!$H27*0.21) -> 3628.6614 | P27: =SUM('Ago-24'!$H27:$O27) -> 20908.001 | Q27: =IFERROR(IF('Ago-24'!$F27="","-",VLOOKUP('Ago-24'!$F27,Lista_CUIT!$A$1:$D$2241,3,0)),"CUIT NO CARGADO") -> INSUMO | R27: =IFERROR(IF('Ago-24'!$F27="","-",VLOOKUP('Ago-24'!$F27,Lista_CUIT!$A$1:$D$2241,4,0)),"CUIT NO CARGADO") -> 0 | S27: 20908 | T27: ='Ago-24'!$P27-'Ago-24'!$S27 -> 0.0014
... B39: 01/08/2024 | C39: 1 | D39: 3 | E39: 237143 | F39: 30707135596 | G39: =IFERROR(IF('Ago-24'!$F39="","-",VLOOKUP('Ago-24'!$F39,Lista_CUIT!$A$1:$D$2241,2,0)),"CUIT NO CARGADO") -> CITILAN ARGENTINA S.A. | H39: 18698.37 | I39: =IF('Ago-24'!$H39="","",'Ago-24'!$H39*0.21) -> 3926.6577 | P39: =SUM('Ago-24'!$H39:$O39) -> 22625.028 | Q39: =IFERROR(IF('Ago-24'!$F39="","-",VLOOKUP('Ago-24'!$F39,Lista_CUIT!$A$1:$D$2241,3,0)),"CUIT NO CARGADO") -> Telefonia | R39: =IFERROR(IF('Ago-24'!$F39="","-",VLOOKUP('Ago-24'!$F39,Lista_CUIT!$A$1:$D$2241,4,0)),"CUIT NO CARGADO") -> 0 | S39: 22625.03 | T39: ='Ago-24'!$P39-'Ago-24'!$S39 -> -0.0023
B40: 11/08/2024 | C40: 1 | D40: 2466 | E40: 687431 | F40: 30678814357 | G40: =IFERROR(IF('Ago-24'!$F40="","-",VLOOKUP('Ago-24'!$F40,Lista_CUIT!$A$1:$D$2241,2,0)),"CUIT NO CARGADO") -> TELEFONICA MOVILES ARG | H40: 24764.6 | J40: ='Ago-24'!$H40*0.27 -> 6686.442 | N40: 742.94 | O40: 1274.99 | P40: =SUM('Ago-24'!$H40:$O40) -> 33468.972 | Q40: =IFERROR(IF('Ago-24'!$F40="","-",VLOOKUP('Ago-24'!$F40,Lista_CUIT!$A$1:$D$2241,3,0)),"CUIT NO CARGADO") -> Telefonia | R40: =IFERROR(IF('Ago-24'!$F40="","-",VLOOKUP('Ago-24'!$F40,Lista_CUIT!$A$1:$D$2241,4,0)),"CUIT NO CARGADO") -> 0 | S40: 33468.97 | T40: ='Ago-24'!$P40-'Ago-24'!$S40 -> 0.002
B41: 14/08/2024 | C41: 1 | D41: 106 | E41: 759157 | F41: 30594494187 | G41: =IFERROR(IF('Ago-24'!$F41="","-",VLOOKUP('Ago-24'!$F41,Lista_CUIT!$A$1:$D$2241,2,0)),"CUIT NO CARGADO") -> FEDERAL EXPRESS CORPORATION | H41: 80430 | I41: =IF('Ago-24'!$H41="","",'Ago-24'!$H41*0.21) -> 16890.3 | O41: 411100.8 | P41: =SUM('Ago-24'!$H41:$O41) -> 508421.1 | Q41: =IFERROR(IF('Ago-24'!$F41="","-",VLOOKUP('Ago-24'!$F41,Lista_CUIT!$A$1:$D$2241,3,0)),"CUIT NO CARGADO") -> Gastos Importacion | R41: =IFERROR(IF('Ago-24'!$F41="","-",VLOOKUP('Ago-24'!$F41,Lista_CUIT!$A$1:$D$2241,4,0)),"CUIT NO CARGADO") -> 0 | S41: 508421.1 | T41: ='Ago-24'!$P41-'Ago-24'!$S41 -> 0
G42: =IFERROR(IF('Ago-24'!$F42="","-",VLOOKUP('Ago-24'!$F42,Lista_CUIT!$A$1:$D$2241,2,0)),"CUIT NO CARGADO") -> - | I42: =IF('Ago-24'!$H42="","",'Ago-24'!$H42*0.21) | P42: =SUM('Ago-24'!$H42:$O42) -> 0 | Q42: =IFERROR(IF('Ago-24'!$F42="","-",VLOOKUP('Ago-24'!$F42,Lista_CUIT!$A$1:$D$2241,3,0)),"CUIT NO CARGADO") -> - | R42: =IFERROR(IF('Ago-24'!$F42="","-",VLOOKUP('Ago-24'!$F42,Lista_CUIT!$A$1:$D$2241,4,0)),"CUIT NO CARGADO") -> - | T42: ='Ago-24'!$P42-'Ago-24'!$S42 -> 0
G43: =IFERROR(IF('Ago-24'!$F43="","-",VLOOKUP('Ago-24'!$F43,Lista_CUIT!$A$1:$D$2241,2,0)),"CUIT NO CARGADO") -> - | I43: =IF('Ago-24'!$H43="","",'Ago-24'!$H43*0.21) | P43: =SUM('Ago-24'!$H43:$O43) -> 0 | Q43: =IFERROR(IF('Ago-24'!$F43="","-",VLOOKUP('Ago-24'!$F43,Lista_CUIT!$A$1:$D$2241,3,0)),"CUIT NO CARGADO") -> - | R43: =IFERROR(IF('Ago-24'!$F43="","-",VLOOKUP('Ago-24'!$F43,Lista_CUIT!$A$1:$D$2241,4,0)),"CUIT NO CARGADO") -> - | T43: ='Ago-24'!$P43-'Ago-24'!$S43 -> 0
G44: =IFERROR(IF('Ago-24'!$F44="","-",VLOOKUP('Ago-24'!$F44,Lista_CUIT!$A$1:$D$2241,2,0)),"CUIT NO CARGADO") -> - | I44: =IF('Ago-24'!$H44="","",'Ago-24'!$H44*0.21) | P44: =SUM('Ago-24'!$H44:$O44) -> 0 | Q44: =IFERROR(IF('Ago-24'!$F44="","-",VLOOKUP('Ago-24'!$F44,Lista_CUIT!$A$1:$D$2241,3,0)),"CUIT NO CARGADO") -> - | R44: =IFERROR(IF('Ago-24'!$F44="","-",VLOOKUP('Ago-24'!$F44,Lista_CUIT!$A$1:$D$2241,4,0)),"CUIT NO CARGADO") -> - | T44: ='Ago-24'!$P44-'Ago-24'!$S44 -> 0
G45: =IFERROR(IF('Ago-24'!$F45="","-",VLOOKUP('Ago-24'!$F45,Lista_CUIT!$A$1:$D$2241,2,0)),"CUIT NO CARGADO") -> - | I45: =IF('Ago-24'!$H45="","",'Ago-24'!$H45*0.21) | P45: =SUM('Ago-24'!$H45:$O45) -> 0 | Q45: =IFERROR(IF('Ago-24'!$F45="","-",VLOOKUP('Ago-24'!$F45,Lista_CUIT!$A$1:$D$2241,3,0)),"CUIT NO CARGADO") -> - | R45: =IFERROR(IF('Ago-24'!$F45="","-",VLOOKUP('Ago-24'!$F45,Lista_CUIT!$A$1:$D$2241,4,0)),"CUIT NO CARGADO") -> - | T45: ='Ago-24'!$P45-'Ago-24'!$S45 -> 0
G46: =IFERROR(IF('Ago-24'!$F46="","-",VLOOKUP('Ago-24'!$F46,Lista_CUIT!$A$1:$D$2241,2,0)),"CUIT NO CARGADO") -> - | I46: =IF('Ago-24'!$H46="","",'Ago-24'!$H46*0.21) | P46: =SUM('Ago-24'!$H46:$O46) -> 0 | Q46: =IFERROR(IF('Ago-24'!$F46="","-",VLOOKUP('Ago-24'!$F46,Lista_CUIT!$A$1:$D$2241,3,0)),"CUIT NO CARGADO") -> - | R46: =IFERROR(IF('Ago-24'!$F46="","-",VLOOKUP('Ago-24'!$F46,Lista_CUIT!$A$1:$D$2241,4,0)),"CUIT NO CARGADO") -> - | T46: ='Ago-24'!$P46-'Ago-24'!$S46 -> 0
G47: =IFERROR(IF('Ago-24'!$F47="","-",VLOOKUP('Ago-24'!$F47,Lista_CUIT!$A$1:$D$2241,2,0)),"CUIT NO CARGADO") -> - | I47: =IF('Ago-24'!$H47="","",'Ago-24'!$H47*0.21) | P47: =SUM('Ago-24'!$H47:$O47) -> 0 | Q47: =IFERROR(IF('Ago-24'!$F47="","-",VLOOKUP('Ago-24'!$F47,Lista_CUIT!$A$1:$D$2241,3,0)),"CUIT NO CARGADO") -> - | R47: =IFERROR(IF('Ago-24'!$F47="","-",VLOOKUP('Ago-24'!$F47,Lista_CUIT!$A$1:$D$2241,4,0)),"CUIT NO CARGADO") -> - | T47: ='Ago-24'!$P47-'Ago-24'!$S47 -> 0
B48: Total | H48: =SUBTOTAL(109,'Ago-24'!$H$9:$H$47) -> 14726118 | I48: =SUBTOTAL(109,'Ago-24'!$I$9:$I$47) -> 3080917.7 | J48: =SUBTOTAL(109,'Ago-24'!$J$9:$J$47) -> 6686.442 | K48: =SUBTOTAL(109,'Ago-24'!$K$9:$K$47) -> 3183.2577 | L48: =SUBTOTAL(109,'Ago-24'!$L$9:$L$47) -> 0 | M48: =SUBTOTAL(109,'Ago-24'!$M$9:$M$47) -> 0 | N48: =SUBTOTAL(109,'Ago-24'!$N$9:$N$47) -> 742.94 | O48: =SUBTOTAL(109,'Ago-24'!$O$9:$O$47) -> 412375.79 | P48: =SUBTOTAL(109,'Ago-24'!$P$9:$P$47) -> 18230024
D53: LIQUIDACION EXTRACTOS BANCARIOS-TARJETAS
D54: FECHA | E54: NRO CPTE | F54: BANCO | G54: NETO | H54: IVA 21% | I54: IVA 10,5% | J54: RET IIBB CABA | K54: PERC IVA | L54: PERC IIBB | M54: TOTAL
D55: 45531 | E55: 892665 | F55: Credicoop | G55: 71250 | H55: ='Ago-24'!$G55*0.21 -> 14962.5 | K55: 2137.5 | M55: =SUM('Ago-24'!$G55:$L55) -> 88350
D56: 45525 | E56: 108771 | F56: Credicoop | G56: 23625 | H56: ='Ago-24'!$G56*0.21 -> 4961.25 | K56: 708.75 | M56: =SUM('Ago-24'!$G56:$L56) -> 29295
D57: 45530 | E57: 1088107 | F57: Credicoop | G57: 23762.5 | H57: ='Ago-24'!$G57*0.21 -> 4990.125 | K57: 712.88 | M57: =SUM('Ago-24'!$G57:$L57) -> 29465.505
D58: 45531 | E58: 1088296 | F58: Credicoop | G58: 23750 | H58: ='Ago-24'!$G58*0.21 -> 4987.5 | K58: 712.5 | M58: =SUM('Ago-24'!$G58:$L58) -> 29450
H59: ='Ago-24'!$G59*0.21 -> 0 | M59: =SUM('Ago-24'!$G59:$L59) -> 0
D60: Total | G60: =SUBTOTAL(109,'Ago-24'!$G$55:$G$59) -> 142387.5 | H60: =SUBTOTAL(109,'Ago-24'!$H$55:$H$59) -> 29901.375 | I60: =SUBTOTAL(109,'Ago-24'!$I$55:$I$59) -> 0 | J60: =SUBTOTAL(109,'Ago-24'!$J$55:$J$59) -> 0 | K60: =SUBTOTAL(109,'Ago-24'!$K$55:$K$59) -> 4271.63 | L60: =SUBTOTAL(109,'Ago-24'!$L$55:$L$59) -> 0
D64: FACTURAS C
D65: FECHA | E65: PTO VTA | F65: FC Nº | G65: CUIT | H65: RAZON SOCIAL | I65: TOTAL | J65: TIPO DE GASTO | K65: Provincia
D66: 01/08/2024 | E66: 1 | F66: 39 | G66: 20365938688 | H66: =IFERROR(IF('Ago-24'!$G66="","-",VLOOKUP('Ago-24'!$G66,Lista_CUIT!$A$1:$D$2241,2,0)),"CUIT NO CARGADO") -> LIPANOVICH JUAN CRUZ | I66: 750000 | J66: =IFERROR(IF('Ago-24'!$G66="","-",VLOOKUP('Ago-24'!$G66,Lista_CUIT!$A$1:$D$2241,3,0)),"CUIT NO CARGADO") -> SOFTWARE | K66: =IFERROR(IF('Ago-24'!$G66="","-",VLOOKUP('Ago-24'!$G66,Lista_CUIT!$A$1:$D$2241,4,0)),"CUIT NO CARGADO") -> 0
D67: 01/08/2024 | E67: 1 | F67: 28 | G67: 27387896150 | H67: =IFERROR(IF('Ago-24'!$G67="","-",VLOOKUP('Ago-24'!$G67,Lista_CUIT!$A$1:$D$2241,2,0)),"CUIT NO CARGADO") -> LIPANOVICH MARIA SOL | I67: 900000 | J67: =IFERROR(IF('Ago-24'!$G67="","-",VLOOKUP('Ago-24'!$G67,Lista_CUIT!$A$1:$D$2241,3,0)),"CUIT NO CARGADO") -> consultoria informatica | K67: =IFERROR(IF('Ago-24'!$G67="","-",VLOOKUP('Ago-24'!$G67,Lista_CUIT!$A$1:$D$2241,4,0)),"CUIT NO CARGADO") -> 0
D68: 01/08/2024 | E68: 2 | F68: 174 | G68: 20136544625 | H68: =IFERROR(IF('Ago-24'!$G68="","-",VLOOKUP('Ago-24'!$G68,Lista_CUIT!$A$1:$D$2241,2,0)),"CUIT NO CARGADO") -> RODRIGUEZ DE LA FUEN HECTOR MARCELO | I68: 813500 | J68: =IFERROR(IF('Ago-24'!$G68="","-",VLOOKUP('Ago-24'!$G68,Lista_CUIT!$A$1:$D$2241,3,0)),"CUIT NO CARGADO") -> Honorarios Admin | K68: =IFERROR(IF('Ago-24'!$G68="","-",VLOOKUP('Ago-24'!$G68,Lista_CUIT!$A$1:$D$2241,4,0)),"CUIT NO CARGADO") -> 0
D69: 01/08/2024 | E69: 2 | F69: 250 | G69: 27173820866 | H69: =IFERROR(IF('Ago-24'!$G69="","-",VLOOKUP('Ago-24'!$G69,Lista_CUIT!$A$1:$D$2241,2,0)),"CUIT NO CARGADO") -> FREIER SANDRA DANIELA | I69: 713000 | J69: =IFERROR(IF('Ago-24'!$G69="","-",VLOOKUP('Ago-24'!$G69,Lista_CUIT!$A$1:$D$2241,3,0)),"CUIT NO CARGADO") -> Honorarios Prof | K69: =IFERROR(IF('Ago-24'!$G69="","-",VLOOKUP('Ago-24'!$G69,Lista_CUIT!$A$1:$D$2241,4,0)),"CUIT NO CARGADO") -> 0
D70: 05/08/2024 | E70: 3 | F70: 873 | G70: 20086277523 | H70: =IFERROR(IF('Ago-24'!$G70="","-",VLOOKUP('Ago-24'!$G70,Lista_CUIT!$A$1:$D$2241,2,0)),"CUIT NO CARGADO") -> ESTUDIO BOTINDARI | I70: 270000 | J70: =IFERROR(IF('Ago-24'!$G70="","-",VLOOKUP('Ago-24'!$G70,Lista_CUIT!$A$1:$D$2241,3,0)),"CUIT NO CARGADO") -> Honorarios Contables | K70: =IFERROR(IF('Ago-24'!$G70="","-",VLOOKUP('Ago-24'!$G70,Lista_CUIT!$A$1:$D$2241,4,0)),"CUIT NO CARGADO") -> 0
D71: 06/08/2024 | E71: 2 | F71: 6 | G71: 23118167279 | H71: =IFERROR(IF('Ago-24'!$G71="","-",VLOOKUP('Ago-24'!$G71,Lista_CUIT!$A$1:$D$2241,2,0)),"CUIT NO CARGADO") -> ABELEDO ENRIQUE JUAN | I71: 780000 | J71: =IFERROR(IF('Ago-24'!$G71="","-",VLOOKUP('Ago-24'!$G71,Lista_CUIT!$A$1:$D$2241,3,0)),"CUIT NO CARGADO") -> Honorarios Admin | K71: =IFERROR(IF('Ago-24'!$G71="","-",VLOOKUP('Ago-24'!$G71,Lista_CUIT!$A$1:$D$2241,4,0)),"CUIT NO CARGADO") -> 0
D72: 07/08/2024 | E72: 3 | F72: 3616 | G72: 20936336826 | H72: =IFERROR(IF('Ago-24'!$G72="","-",VLOOKUP('Ago-24'!$G72,Lista_CUIT!$A$1:$D$2241,2,0)),"CUIT NO CARGADO") -> CUIT NO CARGADO | I72: 9942.7 | J72: =IFERROR(IF('Ago-24'!$G72="","-",VLOOKUP('Ago-24'!$G72,Lista_CUIT!$A$1:$D$2241,3,0)),"CUIT NO CARGADO") -> CUIT NO CARGADO | K72: =IFERROR(IF('Ago-24'!$G72="","-",VLOOKUP('Ago-24'!$G72,Lista_CUIT!$A$1:$D$2241,4,0)),"CUIT NO CARGADO") -> CUIT NO CARGADO
D73: 07/08/2024 | E73: 2 | F73: 251 | G73: 27173820866 | H73: =IFERROR(IF('Ago-24'!$G73="","-",VLOOKUP('Ago-24'!$G73,Lista_CUIT!$A$1:$D$2241,2,0)),"CUIT NO CARGADO") -> FREIER SANDRA DANIELA | I73: 696000 | J73: =IFERROR(IF('Ago-24'!$G73="","-",VLOOKUP('Ago-24'!$G73,Lista_CUIT!$A$1:$D$2241,3,0)),"CUIT NO CARGADO") -> Honorarios Prof | K73: =IFERROR(IF('Ago-24'!$G73="","-",VLOOKUP('Ago-24'!$G73,Lista_CUIT!$A$1:$D$2241,4,0)),"CUIT NO CARGADO") -> 0
D74: 09/08/2024 | E74: 1 | F74: 497 | G74: 27925308868 | H74: =IFERROR(IF('Ago-24'!$G74="","-",VLOOKUP('Ago-24'!$G74,Lista_CUIT!$A$1:$D$2241,2,0)),"CUIT NO CARGADO") -> LOPEZ MOLINA MARIA | I74: 13000 | J74: =IFERROR(IF('Ago-24'!$G74="","-",VLOOKUP('Ago-24'!$G74,Lista_CUIT!$A$1:$D$2241,3,0)),"CUIT NO CARGADO") -> GASTOS VARIOS | K74: =IFERROR(IF('Ago-24'!$G74="","-",VLOOKUP('Ago-24'!$G74,Lista_CUIT!$A$1:$D$2241,4,0)),"CUIT NO CARGADO") -> 0
D75: 12/08/2024 | E75: 1 | F75: 21 | G75: 20338344695 | H75: =IFERROR(IF('Ago-24'!$G75="","-",VLOOKUP('Ago-24'!$G75,Lista_CUIT!$A$1:$D$2241,2,0)),"CUIT NO CARGADO") -> FUERTES DAMIAN MATIAS | I75: 188100 | J75: =IFERROR(IF('Ago-24'!$G75="","-",VLOOKUP('Ago-24'!$G75,Lista_CUIT!$A$1:$D$2241,3,0)),"CUIT NO CARGADO") -> INSUMO | K75: =IFERROR(IF('Ago-24'!$G75="","-",VLOOKUP('Ago-24'!$G75,Lista_CUIT!$A$1:$D$2241,4,0)),"CUIT NO CARGADO") -> 0
D76: 12/08/2024 | E76: 2 | F76: 175 | G76: 20136544625 | H76: =IFERROR(IF('Ago-24'!$G76="","-",VLOOKUP('Ago-24'!$G76,Lista_CUIT!$A$1:$D$2241,2,0)),"CUIT NO CARGADO") -> RODRIGUEZ DE LA FUEN HECTOR MARCELO | I76: 1207000 | J76: =IFERROR(IF('Ago-24'!$G76="","-",VLOOKUP('Ago-24'!$G76,Lista_CUIT!$A$1:$D$2241,3,0)),"CUIT NO CARGADO") -> Honorarios Admin | K76: =IFERROR(IF('Ago-24'!$G76="","-",VLOOKUP('Ago-24'!$G76,Lista_CUIT!$A$1:$D$2241,4,0)),"CUIT NO CARGADO") -> 0
D77: 15/08/2024 | E77: 1 | F77: 113 | G77: 20389908569 | H77: =IFERROR(IF('Ago-24'!$G77="","-",VLOOKUP('Ago-24'!$G77,Lista_CUIT!$A$1:$D$2241,2,0)),"CUIT NO CARGADO") -> BOTINDARI JUAN IGNACIO | I77: 72530 | J77: =IFERROR(IF('Ago-24'!$G77="","-",VLOOKUP('Ago-24'!$G77,Lista_CUIT!$A$1:$D$2241,3,0)),"CUIT NO CARGADO") -> Honorarios Contables | K77: =IFERROR(IF('Ago-24'!$G77="","-",VLOOKUP('Ago-24'!$G77,Lista_CUIT!$A$1:$D$2241,4,0)),"CUIT NO CARGADO") -> 0
... D79: 22/08/2024 | E79: 4 | F79: 28 | G79: 20341462933 | H79: =IFERROR(IF('Ago-24'!$G79="","-",VLOOKUP('Ago-24'!$G79,Lista_CUIT!$A$1:$D$2241,2,0)),"CUIT NO CARGADO") -> CASTIGLIONI MATIAS EZEQUIEL | I79: 1525000 | J79: =IFERROR(IF('Ago-24'!$G79="","-",VLOOKUP('Ago-24'!$G79,Lista_CUIT!$A$1:$D$2241,3,0)),"CUIT NO CARGADO") -> ASESORAMIENTO | K79: =IFERROR(IF('Ago-24'!$G79="","-",VLOOKUP('Ago-24'!$G79,Lista_CUIT!$A$1:$D$2241,4,0)),"CUIT NO CARGADO") -> BUENOS AIRES
H80: =IFERROR(IF('Ago-24'!$G80="","-",VLOOKUP('Ago-24'!$G80,Lista_CUIT!$A$1:$D$2241,2,0)),"CUIT NO CARGADO") -> - | J80: =IFERROR(IF('Ago-24'!$G80="","-",VLOOKUP('Ago-24'!$G80,Lista_CUIT!$A$1:$D$2241,3,0)),"CUIT NO CARGADO") -> - | K80: =IFERROR(IF('Ago-24'!$G80="","-",VLOOKUP('Ago-24'!$G80,Lista_CUIT!$A$1:$D$2241,4,0)),"CUIT NO CARGADO") -> -
H81: =IFERROR(IF('Ago-24'!$G81="","-",VLOOKUP('Ago-24'!$G81,Lista_CUIT!$A$1:$D$2241,2,0)),"CUIT NO CARGADO") -> - | J81: =IFERROR(IF('Ago-24'!$G81="","-",VLOOKUP('Ago-24'!$G81,Lista_CUIT!$A$1:$D$2241,3,0)),"CUIT NO CARGADO") -> - | K81: =IFERROR(IF('Ago-24'!$G81="","-",VLOOKUP('Ago-24'!$G81,Lista_CUIT!$A$1:$D$2241,4,0)),"CUIT NO CARGADO") -> -
H82: =IFERROR(IF('Ago-24'!$G82="","-",VLOOKUP('Ago-24'!$G82,Lista_CUIT!$A$1:$D$2241,2,0)),"CUIT NO CARGADO") -> - | J82: =IFERROR(IF('Ago-24'!$G82="","-",VLOOKUP('Ago-24'!$G82,Lista_CUIT!$A$1:$D$2241,3,0)),"CUIT NO CARGADO") -> - | K82: =IFERROR(IF('Ago-24'!$G82="","-",VLOOKUP('Ago-24'!$G82,Lista_CUIT!$A$1:$D$2241,4,0)),"CUIT NO CARGADO") -> -
H83: =IFERROR(IF('Ago-24'!$G83="","-",VLOOKUP('Ago-24'!$G83,Lista_CUIT!$A$1:$D$2241,2,0)),"CUIT NO CARGADO") -> - | J83: =IFERROR(IF('Ago-24'!$G83="","-",VLOOKUP('Ago-24'!$G83,Lista_CUIT!$A$1:$D$2241,3,0)),"CUIT NO CARGADO") -> - | K83: =IFERROR(IF('Ago-24'!$G83="","-",VLOOKUP('Ago-24'!$G83,Lista_CUIT!$A$1:$D$2241,4,0)),"CUIT NO CARGADO") -> -
D84: Total | I84: =SUBTOTAL(109,'Ago-24'!$I$66:$I$83) -> 8004072.7
B90: LIBRO IVA VENTAS | K90: =N1 -> 45139
B92: VENTAS "A"
B93: FECHA | C93: TIPO | D93: PTO VENTA | E93: Nº FACTURA | F93: CUIT | G93: RAZON SOCIAL | H93: IMPORTE NETO | I93: IVA 21% | J93: IVA 10,5% | K93: EXENTO | L93: TOTAL | M93: Provincia
B94: 07/08/2024 | C94: 1 | D94: 3 | E94: 213 | F94: 20408014019 | G94: =IFERROR(IF('Ago-24'!$F94="","-",VLOOKUP('Ago-24'!$F94,Lista_CUIT!$A$1:$D$2241,2,0)),"CUIT NO CARGADO") -> BRUNETTO LUCAS GASTON | H94: 1132037 | I94: ='Ago-24'!$H94*0.21 -> 237727.77 | L94: =SUM('Ago-24'!$H94:$K94) -> 1369764.8
B95: 12/08/2024 | C95: 1 | D95: 3 | E95: 214 | F95: 30638318470 | G95: =IFERROR(IF('Ago-24'!$F95="","-",VLOOKUP('Ago-24'!$F95,Lista_CUIT!$A$1:$D$2241,2,0)),"CUIT NO CARGADO") -> DELTA COMPRESION S R L | H95: 2682400 | I95: ='Ago-24'!$H95*0.21 -> 563304 | L95: =SUM('Ago-24'!$H95:$K95) -> 3245704
B96: 12/08/2024 | C96: 1 | D96: 3 | E96: 215 | F96: 30638318470 | G96: =IFERROR(IF('Ago-24'!$F96="","-",VLOOKUP('Ago-24'!$F96,Lista_CUIT!$A$1:$D$2241,2,0)),"CUIT NO CARGADO") -> DELTA COMPRESION S R L | H96: 2682400 | I96: ='Ago-24'!$H96*0.21 -> 563304 | L96: =SUM('Ago-24'!$H96:$K96) -> 3245704
B97: 12/08/2024 | C97: 3 | D97: 3 | E97: 24 | F97: 30638318470 | G97: =IFERROR(IF('Ago-24'!$F97="","-",VLOOKUP('Ago-24'!$F97,Lista_CUIT!$A$1:$D$2241,2,0)),"CUIT NO CARGADO") -> DELTA COMPRESION S R L | H97: -2682400 | I97: ='Ago-24'!$H97*0.21 -> -563304 | L97: =SUM('Ago-24'!$H97:$K97) -> -3245704
B98: 14/08/2024 | C98: 3 | D98: 3 | E98: 25 | F98: 30638318470 | G98: =IFERROR(IF('Ago-24'!$F98="","-",VLOOKUP('Ago-24'!$F98,Lista_CUIT!$A$1:$D$2241,2,0)),"CUIT NO CARGADO") -> DELTA COMPRESION S R L | H98: -321480 | I98: ='Ago-24'!$H98*0.21 -> -67510.8 | L98: =SUM('Ago-24'!$H98:$K98) -> -388990.8
B99: 23/08/2024 | C99: 1 | D99: 3 | E99: 216 | F99: 30628274327 | G99: =IFERROR(IF('Ago-24'!$F99="","-",VLOOKUP('Ago-24'!$F99,Lista_CUIT!$A$1:$D$2241,2,0)),"CUIT NO CARGADO") -> AGIRA S A | H99: 17603640 | I99: =385200*0.21 -> 80892 | J99: =17218440*0.105 -> 1807936.2 | L99: =SUM('Ago-24'!$H99:$K99) -> 19492468
B100: 23/08/2024 | C100: 1 | D100: 3 | E100: 217 | F100: 30638318470 | G100: =IFERROR(IF('Ago-24'!$F100="","-",VLOOKUP('Ago-24'!$F100,Lista_CUIT!$A$1:$D$2241,2,0)),"CUIT NO CARGADO") -> DELTA COMPRESION S R L | H100: 40910100 | J100: ='Ago-24'!$H100*0.105 -> 4295560.5 | L100: =SUM('Ago-24'!$H100:$K100) -> 45205660
B101: 27/08/2024 | C101: 1 | D101: 3 | E101: 218 | F101: 30718512545 | G101: =IFERROR(IF('Ago-24'!$F101="","-",VLOOKUP('Ago-24'!$F101,Lista_CUIT!$A$1:$D$2241,2,0)),"CUIT NO CARGADO") -> MAJUBEN MDP SERVICIOS S.R.L. | H101: 1047060 | I101: ='Ago-24'!$H101*0.21 -> 219882.6 | L101: =SUM('Ago-24'!$H101:$K101) -> 1266942.6
B102: 27/08/2024 | C102: 1 | D102: 3 | E102: 219 | F102: 30716403900 | G102: =IFERROR(IF('Ago-24'!$F102="","-",VLOOKUP('Ago-24'!$F102,Lista_CUIT!$A$1:$D$2241,2,0)),"CUIT NO CARGADO") -> PARQUE CONSTITUCION SRL | H102: 1454250 | I102: ='Ago-24'!$H102*0.21 -> 305392.5 | L102: =SUM('Ago-24'!$H102:$K102) -> 1759642.5
B103: Total | H103: =SUBTOTAL(109,'Ago-24'!$H$94:$H$102) -> 64508007 | I103: =SUBTOTAL(109,'Ago-24'!$I$94:$I$102) -> 1339688.1 | J103: =SUBTOTAL(109,'Ago-24'!$J$94:$J$102) -> 6103496.7 | K103: =SUBTOTAL(109,'Ago-24'!$K$94:$K$102) -> 0 | L103: =SUBTOTAL(109,'Ago-24'!$L$94:$L$102) -> 71951192 | M103: =SUBTOTAL(103,'Ago-24'!$M$94:$M$102) -> 0
B106: VENTAS "B"
B107: FECHA | C107: TIPO | D107: PTO VENTA | E107: Nº FACTURA | F107: CUIT | G107: RAZON SOCIAL | H107: IMPORTE NETO | I107: IVA 21% | J107: IVA 10,5% | K107: EXENTO | L107: TOTAL | M107: Provincia
B108: 09/08/2024 | C108: 6 | D108: 3 | E108: 11 | F108: 86809059768 | G108: =IFERROR(IF('Ago-24'!$F108="","-",VLOOKUP('Ago-24'!$F108,Lista_CUIT!$A$1:$D$2241,2,0)),"CUIT NO CARGADO") -> CUIT NO CARGADO | H108: ='Ago-24'!$L108/1.21 -> 383112 | I108: ='Ago-24'!$H108*0.21 -> 80453.52 | L108: 463565.52
H109: ='Ago-24'!$L109/1.21 -> 0 | I109: ='Ago-24'!$H109*0.21 -> 0
H110: ='Ago-24'!$L110/1.21 -> 0 | I110: ='Ago-24'!$H110*0.21 -> 0
H111: ='Ago-24'!$L111/1.21 -> 0 | I111: ='Ago-24'!$H111*0.21 -> 0
H112: ='Ago-24'!$L112/1.21 -> 0 | I112: ='Ago-24'!$H112*0.21 -> 0
H113: ='Ago-24'!$L113/1.21 -> 0 | I113: ='Ago-24'!$H113*0.21 -> 0
B114: Total | H114: =SUBTOTAL(109,'Ago-24'!$H$108:$H$113) -> 383112 | I114: =SUBTOTAL(109,'Ago-24'!$I$108:$I$113) -> 80453.52 | J114: =SUBTOTAL(109,'Ago-24'!$J$108:$J$113) -> 0 | K114: =SUBTOTAL(109,'Ago-24'!$K$108:$K$113) -> 0 | L114: =SUBTOTAL(109,'Ago-24'!$L$108:$L$113) -> 463565.52 | M114: =SUBTOTAL(103,'Ago-24'!$M$108:$M$113) -> 0
B117: VENTAS "E"
B118: FECHA | C118: TIPO | D118: PTO VENTA | E118: Nº FACTURA | F118: CUIT | G118: RAZON SOCIAL | H118: USD | I118: TIPO DE CAMBIO2 | J118: TOTAL | K118: Pais
B119: 45517 | C119: 19 | D119: 30 | E119: 88 | F119: 55000000050 | G119: =IFERROR(IF('Ago-24'!$F119="","-",VLOOKUP('Ago-24'!$F119,Lista_CUIT!$A$1:$D$2241,2,0)),"CUIT NO CARGADO") -> GAS FUTURO SISTEMAS DE COMPRESSÃO LTDA | H119: 6720 | I119: 939.5 | J119: ='Ago-24'!$H119*'Ago-24'!$I119 -> 6313440
B120: 45518 | C120: 19 | D120: 30 | E120: 89 | F120: 55000000050 | G120: =IFERROR(IF('Ago-24'!$F120="","-",VLOOKUP('Ago-24'!$F120,Lista_CUIT!$A$1:$D$2241,2,0)),"CUIT NO CARGADO") -> GAS FUTURO SISTEMAS DE COMPRESSÃO LTDA | H120: 1110 | I120: 940.5 | J120: ='Ago-24'!$H120*'Ago-24'!$I120 -> 1043955
B121: 45523 | C121: 19 | D121: 30 | E121: 91 | F121: 55000000050 | G121: =IFERROR(IF('Ago-24'!$F121="","-",VLOOKUP('Ago-24'!$F121,Lista_CUIT!$A$1:$D$2241,2,0)),"CUIT NO CARGADO") -> GAS FUTURO SISTEMAS DE COMPRESSÃO LTDA | H121: 1920 | I121: 944 | J121: ='Ago-24'!$H121*'Ago-24'!$I121 -> 1812480
B122: 45523 | C122: 19 | D122: 30 | E122: 90 | F122: 55000002096 | G122: =IFERROR(IF('Ago-24'!$F122="","-",VLOOKUP('Ago-24'!$F122,Lista_CUIT!$A$1:$D$2241,2,0)),"CUIT NO CARGADO") -> CUIT NO CARGADO | H122: 5750 | I122: 944 | J122: ='Ago-24'!$H122*'Ago-24'!$I122 -> 5428000
B123: 45527 | C123: 19 | D123: 30 | E123: 92 | F123: 55000000050 | G123: =IFERROR(IF('Ago-24'!$F123="","-",VLOOKUP('Ago-24'!$F123,Lista_CUIT!$A$1:$D$2241,2,0)),"CUIT NO CARGADO") -> GAS FUTURO SISTEMAS DE COMPRESSÃO LTDA | H123: 1920 | I123: 946 | J123: ='Ago-24'!$H123*'Ago-24'!$I123 -> 1816320
G124: =IFERROR(IF('Ago-24'!$F124="","-",VLOOKUP('Ago-24'!$F124,Lista_CUIT!$A$1:$D$2241,2,0)),"CUIT NO CARGADO") -> - | J124: ='Ago-24'!$H124*'Ago-24'!$I124 -> 0
G125: =IFERROR(IF('Ago-24'!$F125="","-",VLOOKUP('Ago-24'!$F125,Lista_CUIT!$A$1:$D$2241,2,0)),"CUIT NO CARGADO") -> - | J125: ='Ago-24'!$H125*'Ago-24'!$I125 -> 0
G126: =IFERROR(IF('Ago-24'!$F126="","-",VLOOKUP('Ago-24'!$F126,Lista_CUIT!$A$1:$D$2241,2,0)),"CUIT NO CARGADO") -> - | J126: ='Ago-24'!$H126*'Ago-24'!$I126 -> 0
G127: =IFERROR(IF('Ago-24'!$F127="","-",VLOOKUP('Ago-24'!$F127,Lista_CUIT!$A$1:$D$2241,2,0)),"CUIT NO CARGADO") -> - | J127: ='Ago-24'!$H127*'Ago-24'!$I127 -> 0
G128: =IFERROR(IF('Ago-24'!$F128="","-",VLOOKUP('Ago-24'!$F128,Lista_CUIT!$A$1:$D$2241,2,0)),"CUIT NO CARGADO") -> - | J128: ='Ago-24'!$H128*'Ago-24'!$I128 -> 0
B129: Total | H129: =SUBTOTAL(109,'Ago-24'!$H$119:$H$128) -> 17420 | J129: =SUBTOTAL(109,'Ago-24'!$J$119:$J$128) -> 16414195 | K129: =SUBTOTAL(103,'Ago-24'!$K$119:$K$128) -> 0
C133: RETENCIONES
C134: FECHA | D134: COMP Nº | E134: Columna1 | F134: CUIT | G134: RAZON SOCIAL | H134: Ganancias | I134: IVA | J134: SUSS | K134: IIBB BSAS | L134: IIBB CABA
G135: =IFERROR(IF('Ago-24'!$F135="","-",VLOOKUP('Ago-24'!$F135,Lista_CUIT!$A$1:$D$2241,2,0)),"CUIT NO CARGADO") -> -
G136: =IFERROR(IF('Ago-24'!$F136="","-",VLOOKUP('Ago-24'!$F136,Lista_CUIT!$A$1:$D$2241,2,0)),"CUIT NO CARGADO") -> -
...

Sheet Sept-24
B1: LIBRO IVA COMPRAS | G1: ='Abr-24'!G1:M1 -> CORITEC S. R. L. | N1: =EDATE('Abr-24'!N1,5) -> 45170
B3: TOTAL COMPRAS | G3: TOTAL CREDITO FISCAL | J3: TOTAL VENTAS NETAS | M3: TOTAL DEBITO FISCAL | P3: RESULTADO
B4: =SUM('Sept-24'!$H$42)+'Sept-24'!$G$53 -> 6088124.7 | G4: ='Sept-24'!$I$42+'Sept-24'!$J$42+'Sept-24'!$K$42+'Sept-24'!$H$53+'Sept-24'!$I$53 -> 1280038.6 | J4: ='Sept-24'!$H$91+'Sept-24'!$H$101 -> 1.2409941e+08 | M4: ='Sept-24'!$I$91+'Sept-24'!$J$91+'Sept-24'!$I$101+'Sept-24'!$J$101 -> 14146938 | P4: =G4-M4 -> -12866899
B8: FECHA | C8: TIPO | D8: PTO VTA | E8: NRO. CPTE | F8: CUIT | G8: RAZON SOCIAL | H8: NETO GRAVADO | I8: IVA 21 % | J8: IVA 27% | K8: IVA 10,5% | L8: PERC. IVA | M8: PERC IIBB BS AS | N8: PERC. IIBB CABA | O8: Otros / No Grav. | P8: TOTAL | Q8: Tipo de Gasto | R8: Provincia
B9: 45536 | C9: 1 | D9: 3 | E9: 785 | F9: 30715402765 | G9: =IFERROR(IF('Sept-24'!$F9="","-",VLOOKUP('Sept-24'!$F9,Lista_CUIT!$A$1:$D$2241,2,0)),"CUIT NO CARGADO") -> RIO 265 S.R.L. | H9: 64462.81 | I9: =IF('Sept-24'!$H9="","",'Sept-24'!$H9*0.21) -> 13537.19 | P9: =SUM('Sept-24'!$H9:$O9) -> 78000 | Q9: =IFERROR(IF('Sept-24'!$F9="","-",VLOOKUP('Sept-24'!$F9,Lista_CUIT!$A$1:$D$2241,3,0)),"CUIT NO CARGADO") -> GASTOS VARIOS | R9: =IFERROR(IF('Sept-24'!$F9="","-",VLOOKUP('Sept-24'!$F9,Lista_CUIT!$A$1:$D$2241,4,0)),"CUIT NO CARGADO") -> 0
B10: 45559 | C10: 1 | D10: 2 | E10: 798 | F10: 20296550184 | G10: =IFERROR(IF('Sept-24'!$F10="","-",VLOOKUP('Sept-24'!$F10,Lista_CUIT!$A$1:$D$2241,2,0)),"CUIT NO CARGADO") -> COSTA DIEGO ALEJANDRO | H10: 251600 | I10: =IF('Sept-24'!$H10="","",'Sept-24'!$H10*0.21) -> 52836 | P10: =SUM('Sept-24'!$H10:$O10) -> 304436 | Q10: =IFERROR(IF('Sept-24'!$F10="","-",VLOOKUP('Sept-24'!$F10,Lista_CUIT!$A$1:$D$2241,3,0)),"CUIT NO CARGADO") -> Mat. Prima | R10: =IFERROR(IF('Sept-24'!$F10="","-",VLOOKUP('Sept-24'!$F10,Lista_CUIT!$A$1:$D$2241,4,0)),"CUIT NO CARGADO") -> 0
B11: 45553 | C11: 1 | D11: 2 | E11: 1335 | F11: 20284880049 | G11: =IFERROR(IF('Sept-24'!$F11="","-",VLOOKUP('Sept-24'!$F11,Lista_CUIT!$A$1:$D$2241,2,0)),"CUIT NO CARGADO") -> MOROLDO EMILIANO DANIEL | H11: 16970.24 | I11: =IF('Sept-24'!$H11="","",'Sept-24'!$H11*0.21) -> 3563.7504 | P11: =SUM('Sept-24'!$H11:$O11) -> 20533.99 | Q11: =IFERROR(IF('Sept-24'!$F11="","-",VLOOKUP('Sept-24'!$F11,Lista_CUIT!$A$1:$D$2241,3,0)),"CUIT NO CARGADO") -> Electronica | R11: =IFERROR(IF('Sept-24'!$F11="","-",VLOOKUP('Sept-24'!$F11,Lista_CUIT!$A$1:$D$2241,4,0)),"CUIT NO CARGADO") -> 0
B12: 45557 | C12: 1 | D12: 3 | E12: 2316 | F12: 20367496836 | G12: =IFERROR(IF('Sept-24'!$F12="","-",VLOOKUP('Sept-24'!$F12,Lista_CUIT!$A$1:$D$2241,2,0)),"CUIT NO CARGADO") -> AYALA COLMAN OSCAR | H12: 105419.65 | I12: =IF('Sept-24'!$H12="","",'Sept-24'!$H12*0.21) -> 22138.126 | P12: =SUM('Sept-24'!$H12:$O12) -> 127557.78 | Q12: =IFERROR(IF('Sept-24'!$F12="","-",VLOOKUP('Sept-24'!$F12,Lista_CUIT!$A$1:$D$2241,3,0)),"CUIT NO CARGADO") -> GASTOS VARIOS | R12: =IFERROR(IF('Sept-24'!$F12="","-",VLOOKUP('Sept-24'!$F12,Lista_CUIT!$A$1:$D$2241,4,0)),"CUIT NO CARGADO") -> 0
B13: 45537 | C13: 1 | D13: 2 | E13: 2850 | F13: 30709131733 | G13: =IFERROR(IF('Sept-24'!$F13="","-",VLOOKUP('Sept-24'!$F13,Lista_CUIT!$A$1:$D$2241,2,0)),"CUIT NO CARGADO") -> DIGAS SRL | H13: 3146238 | I13: =IF('Sept-24'!$H13="","",'Sept-24'!$H13*0.21) -> 660709.98 | P13: =SUM('Sept-24'!$H13:$O13) -> 3806948 | Q13: =IFERROR(IF('Sept-24'!$F13="","-",VLOOKUP('Sept-24'!$F13,Lista_CUIT!$A$1:$D$2241,3,0)),"CUIT NO CARGADO") -> INSUMO | R13: =IFERROR(IF('Sept-24'!$F13="","-",VLOOKUP('Sept-24'!$F13,Lista_CUIT!$A$1:$D$2241,4,0)),"CUIT NO CARGADO") -> 0
B14: 45551 | C14: 1 | D14: 7 | E14: 2854 | F14: 23270085679 | G14: =IFERROR(IF('Sept-24'!$F14="","-",VLOOKUP('Sept-24'!$F14,Lista_CUIT!$A$1:$D$2241,2,0)),"CUIT NO CARGADO") -> GARCIA DIEGO OMAR | H14: 36809.92 | I14: =IF('Sept-24'!$H14="","",'Sept-24'!$H14*0.21) -> 7730.0832 | P14: =SUM('Sept-24'!$H14:$O14) -> 44540.003 | Q14: =IFERROR(IF('Sept-24'!$F14="","-",VLOOKUP('Sept-24'!$F14,Lista_CUIT!$A$1:$D$2241,3,0)),"CUIT NO CARGADO") -> Servicios Informaticos | R14: =IFERROR(IF('Sept-24'!$F14="","-",VLOOKUP('Sept-24'!$F14,Lista_CUIT!$A$1:$D$2241,4,0)),"CUIT NO CARGADO") -> 0
B15: 45554 | C15: 1 | D15: 13 | E15: 3554 | F15: 30710571801 | G15: =IFERROR(IF('Sept-24'!$F15="","-",VLOOKUP('Sept-24'!$F15,Lista_CUIT!$A$1:$D$2241,2,0)),"CUIT NO CARGADO") -> HOGAR ACTUAL SRL | H15: 43214.88 | I15: =IF('Sept-24'!$H15="","",'Sept-24'!$H15*0.21) -> 9075.1248 | P15: =SUM('Sept-24'!$H15:$O15) -> 52290.005 | Q15: =IFERROR(IF('Sept-24'!$F15="","-",VLOOKUP('Sept-24'!$F15,Lista_CUIT!$A$1:$D$2241,3,0)),"CUIT NO CARGADO") -> GASTOS VARIOS | R15: =IFERROR(IF('Sept-24'!$F15="","-",VLOOKUP('Sept-24'!$F15,Lista_CUIT!$A$1:$D$2241,4,0)),"CUIT NO CARGADO") -> 0
B16: 45551 | C16: 1 | D16: 262 | E16: 3731 | F16: 33708711999 | G16: =IFERROR(IF('Sept-24'!$F16="","-",VLOOKUP('Sept-24'!$F16,Lista_CUIT!$A$1:$D$2241,2,0)),"CUIT NO CARGADO") -> MARANSI SA | H16: 1472424.3 | I16: =IF('Sept-24'!$H16="","",'Sept-24'!$H16*0.21) -> 309209.1 | P16: =SUM('Sept-24'!$H16:$O16) -> 1781633.4 | Q16: =IFERROR(IF('Sept-24'!$F16="","-",VLOOKUP('Sept-24'!$F16,Lista_CUIT!$A$1:$D$2241,3,0)),"CUIT NO CARGADO") -> GASTOS VARIOS | R16: =IFERROR(IF('Sept-24'!$F16="","-",VLOOKUP('Sept-24'!$F16,Lista_CUIT!$A$1:$D$2241,4,0)),"CUIT NO CARGADO") -> 0
B17: 45558 | C17: 1 | D17: 4 | E17: 5187 | F17: 30695313140 | G17: =IFERROR(IF('Sept-24'!$F17="","-",VLOOKUP('Sept-24'!$F17,Lista_CUIT!$A$1:$D$2241,2,0)),"CUIT NO CARGADO") -> ELECTRONICA BOUSA | H17: 27271.9 | I17: =IF('Sept-24'!$H17="","",'Sept-24'!$H17*0.21) -> 5727.099 | P17: =SUM('Sept-24'!$H17:$O17) -> 32998.999 | Q17: =IFERROR(IF('Sept-24'!$F17="","-",VLOOKUP('Sept-24'!$F17,Lista_CUIT!$A$1:$D$2241,3,0)),"CUIT NO CARGADO") -> INSUMO | R17: =IFERROR(IF('Sept-24'!$F17="","-",VLOOKUP('Sept-24'!$F17,Lista_CUIT!$A$1:$D$2241,4,0)),"CUIT NO CARGADO") -> 0
B18: 45563 | C18: 1 | D18: 5 | E18: 5388 | F18: 20319259113 | G18: =IFERROR(IF('Sept-24'!$F18="","-",VLOOKUP('Sept-24'!$F18,Lista_CUIT!$A$1:$D$2241,2,0)),"CUIT NO CARGADO") -> SZNEIBERG HERNAN GASTON | H18: 6983.47 | I18: =IF('Sept-24'!$H18="","",'Sept-24'!$H18*0.21) -> 1466.5287 | P18: =SUM('Sept-24'!$H18:$O18) -> 8449.9987 | Q18: =IFERROR(IF('Sept-24'!$F18="","-",VLOOKUP('Sept-24'!$F18,Lista_CUIT!$A$1:$D$2241,3,0)),"CUIT NO CARGADO") -> INSUMO | R18: =IFERROR(IF('Sept-24'!$F18="","-",VLOOKUP('Sept-24'!$F18,Lista_CUIT!$A$1:$D$2241,4,0)),"CUIT NO CARGADO") -> 0
B19: 45558 | C19: 1 | D19: 2 | E19: 7071 | F19: 30717788261 | G19: =IFERROR(IF('Sept-24'!$F19="","-",VLOOKUP('Sept-24'!$F19,Lista_CUIT!$A$1:$D$2241,2,0)),"CUIT NO CARGADO") -> UTILAR SRL | H19: 45493.62 | I19: =IF('Sept-24'!$H19="","",'Sept-24'!$H19*0.21) -> 9553.6602 | P19: =SUM('Sept-24'!$H19:$O19) -> 55047.28 | Q19: =IFERROR(IF('Sept-24'!$F19="","-",VLOOKUP('Sept-24'!$F19,Lista_CUIT!$A$1:$D$2241,3,0)),"CUIT NO CARGADO") -> GASTOS VARIOS | R19: =IFERROR(IF('Sept-24'!$F19="","-",VLOOKUP('Sept-24'!$F19,Lista_CUIT!$A$1:$D$2241,4,0)),"CUIT NO CARGADO") -> 0
B20: 45563 | C20: 1 | D20: 4 | E20: 8100 | F20: 27184156658 | G20: =IFERROR(IF('Sept-24'!$F20="","-",VLOOKUP('Sept-24'!$F20,Lista_CUIT!$A$1:$D$2241,2,0)),"CUIT NO CARGADO") -> GRACIELA MONICA NUBELMAN | H20: 28219.21 | I20: =IF('Sept-24'!$H20="","",'Sept-24'!$H20*0.21) -> 5926.0341 | P20: =SUM('Sept-24'!$H20:$O20) -> 34145.244 | Q20: =IFERROR(IF('Sept-24'!$F20="","-",VLOOKUP('Sept-24'!$F20,Lista_CUIT!$A$1:$D$2241,3,0)),"CUIT NO CARGADO") -> GASTOS VARIOS | R20: =IFERROR(IF('Sept-24'!$F20="","-",VLOOKUP('Sept-24'!$F20,Lista_CUIT!$A$1:$D$2241,4,0)),"CUIT NO CARGADO") -> 0
... B29: 45558 | C29: 1 | D29: 5 | E29: 33307 | F29: 30715491180 | G29: =IFERROR(IF('Sept-24'!$F29="","-",VLOOKUP('Sept-24'!$F29,Lista_CUIT!$A$1:$D$2241,2,0)),"CUIT NO CARGADO") -> ONE CIRCLE SA | H29: 5435.6 | I29: =IF('Sept-24'!$H29="","",'Sept-24'!$H29*0.21) -> 1141.476 | P29: =SUM('Sept-24'!$H29:$O29) -> 6577.076 | Q29: =IFERROR(IF('Sept-24'!$F29="","-",VLOOKUP('Sept-24'!$F29,Lista_CUIT!$A$1:$D$2241,3,0)),"CUIT NO CARGADO") -> GASTOS VARIOS | R29: =IFERROR(IF('Sept-24'!$F29="","-",VLOOKUP('Sept-24'!$F29,Lista_CUIT!$A$1:$D$2241,4,0)),"CUIT NO CARGADO") -> 0
B30: 06/09/2024 | C30: 3 | D30: 106 | E30: 34428 | F30: 30594494187 | G30: =IFERROR(IF('Sept-24'!$F30="","-",VLOOKUP('Sept-24'!$F30,Lista_CUIT!$A$1:$D$2241,2,0)),"CUIT NO CARGADO") -> FEDERAL EXPRESS CORPORATION | I30: =IF('Sept-24'!$H30="","",'Sept-24'!$H30*0.21) | O30: -3225.6 | P30: =SUM('Sept-24'!$H30:$O30) -> -3225.6 | Q30: =IFERROR(IF('Sept-24'!$F30="","-",VLOOKUP('Sept-24'!$F30,Lista_CUIT!$A$1:$D$2241,3,0)),"CUIT NO CARGADO") -> Gastos Importacion | R30: =IFERROR(IF('Sept-24'!$F30="","-",VLOOKUP('Sept-24'!$F30,Lista_CUIT!$A$1:$D$2241,4,0)),"CUIT NO CARGADO") -> 0
B31: 06/09/2024 | C31: 3 | D31: 106 | E31: 34457 | F31: 30594494187 | G31: =IFERROR(IF('Sept-24'!$F31="","-",VLOOKUP('Sept-24'!$F31,Lista_CUIT!$A$1:$D$2241,2,0)),"CUIT NO CARGADO") -> FEDERAL EXPRESS CORPORATION | I31: =IF('Sept-24'!$H31="","",'Sept-24'!$H31*0.21) | O31: -9727.2 | P31: =SUM('Sept-24'!$H31:$O31) -> -9727.2 | Q31: =IFERROR(IF('Sept-24'!$F31="","-",VLOOKUP('Sept-24'!$F31,Lista_CUIT!$A$1:$D$2241,3,0)),"CUIT NO CARGADO") -> Gastos Importacion | R31: =IFERROR(IF('Sept-24'!$F31="","-",VLOOKUP('Sept-24'!$F31,Lista_CUIT!$A$1:$D$2241,4,0)),"CUIT NO CARGADO") -> 0
B32: 45555 | C32: 1 | D32: 2000 | E32: 49527 | F32: 30716932245 | G32: =IFERROR(IF('Sept-24'!$F32="","-",VLOOKUP('Sept-24'!$F32,Lista_CUIT!$A$1:$D$2241,2,0)),"CUIT NO CARGADO") -> GRUPO MEXX SRL | H32: 251238.84 | I32: =IF('Sept-24'!$H32="","",'Sept-24'!$H32*0.21) -> 52760.156 | P32: =SUM('Sept-24'!$H32:$O32) -> 303999 | Q32: =IFERROR(IF('Sept-24'!$F32="","-",VLOOKUP('Sept-24'!$F32,Lista_CUIT!$A$1:$D$2241,3,0)),"CUIT NO CARGADO") -> GASTOS VARIOS | R32: =IFERROR(IF('Sept-24'!$F32="","-",VLOOKUP('Sept-24'!$F32,Lista_CUIT!$A$1:$D$2241,4,0)),"CUIT NO CARGADO") -> 0
B33: 45558 | C33: 1 | D33: 2 | E33: 55169 | F33: 30716831066 | G33: =IFERROR(IF('Sept-24'!$F33="","-",VLOOKUP('Sept-24'!$F33,Lista_CUIT!$A$1:$D$2241,2,0)),"CUIT NO CARGADO") -> DOUBLE G SA | H33: 34694.21 | I33: =IF('Sept-24'!$H33="","",'Sept-24'!$H33*0.21) -> 7285.7841 | P33: =SUM('Sept-24'!$H33:$O33) -> 41979.994 | Q33: =IFERROR(IF('Sept-24'!$F33="","-",VLOOKUP('Sept-24'!$F33,Lista_CUIT!$A$1:$D$2241,3,0)),"CUIT NO CARGADO") -> REPUESTOS | R33: =IFERROR(IF('Sept-24'!$F33="","-",VLOOKUP('Sept-24'!$F33,Lista_CUIT!$A$1:$D$2241,4,0)),"CUIT NO CARGADO") -> 0
B34: 45565 | C34: 1 | D34: 11 | E34: 55853 | F34: 30711526419 | G34: =IFERROR(IF('Sept-24'!$F34="","-",VLOOKUP('Sept-24'!$F34,Lista_CUIT!$A$1:$D$2241,2,0)),"CUIT NO CARGADO") -> ZETABURGOS SRL | H34: 27431.4 | I34: =IF('Sept-24'!$H34="","",'Sept-24'!$H34*0.21) -> 5760.594 | P34: =SUM('Sept-24'!$H34:$O34) -> 33191.994 | Q34: =IFERROR(IF('Sept-24'!$F34="","-",VLOOKUP('Sept-24'!$F34,Lista_CUIT!$A$1:$D$2241,3,0)),"CUIT NO CARGADO") -> INSUMO | R34: =IFERROR(IF('Sept-24'!$F34="","-",VLOOKUP('Sept-24'!$F34,Lista_CUIT!$A$1:$D$2241,4,0)),"CUIT NO CARGADO") -> 0
B35: 45562 | C35: 1 | D35: 4 | E35: 85286 | F35: 30714749206 | G35: =IFERROR(IF('Sept-24'!$F35="","-",VLOOKUP('Sept-24'!$F35,Lista_CUIT!$A$1:$D$2241,2,0)),"CUIT NO CARGADO") -> EBOX SA | H35: 196283.47 | I35: =IF('Sept-24'!$H35="","",'Sept-24'!$H35*0.21) -> 41219.529 | P35: =SUM('Sept-24'!$H35:$O35) -> 237503 | Q35: =IFERROR(IF('Sept-24'!$F35="","-",VLOOKUP('Sept-24'!$F35,Lista_CUIT!$A$1:$D$2241,3,0)),"CUIT NO CARGADO") -> Gastos Oficina | R35: =IFERROR(IF('Sept-24'!$F35="","-",VLOOKUP('Sept-24'!$F35,Lista_CUIT!$A$1:$D$2241,4,0)),"CUIT NO CARGADO") -> 0 | S35: COD 5
B36: 45536 | C36: 1 | D36: 3 | E36: 239291 | F36: 30707135596 | G36: =IFERROR(IF('Sept-24'!$F36="","-",VLOOKUP('Sept-24'!$F36,Lista_CUIT!$A$1:$D$2241,2,0)),"CUIT NO CARGADO") -> CITILAN ARGENTINA S.A. | H36: 21084.94 | I36: =IF('Sept-24'!$H36="","",'Sept-24'!$H36*0.21) -> 4427.8374 | P36: =SUM('Sept-24'!$H36:$O36) -> 25512.777 | Q36: =IFERROR(IF('Sept-24'!$F36="","-",VLOOKUP('Sept-24'!$F36,Lista_CUIT!$A$1:$D$2241,3,0)),"CUIT NO CARGADO") -> Telefonia | R36: =IFERROR(IF('Sept-24'!$F36="","-",VLOOKUP('Sept-24'!$F36,Lista_CUIT!$A$1:$D$2241,4,0)),"CUIT NO CARGADO") -> 0
B37: 45546 | C37: 1 | D37: 2466 | E37: 699353 | F37: 30678814357 | G37: =IFERROR(IF('Sept-24'!$F37="","-",VLOOKUP('Sept-24'!$F37,Lista_CUIT!$A$1:$D$2241,2,0)),"CUIT NO CARGADO") -> TELEFONICA MOVILES ARG | H37: 25540 | J37: ='Sept-24'!$H37*0.27 -> 6895.8 | L37: 766.2 | O37: 1344.2 | P37: =SUM('Sept-24'!$H37:$O37) -> 34546.2 | Q37: =IFERROR(IF('Sept-24'!$F37="","-",VLOOKUP('Sept-24'!$F37,Lista_CUIT!$A$1:$D$2241,3,0)),"CUIT NO CARGADO") -> Telefonia | R37: =IFERROR(IF('Sept-24'!$F37="","-",VLOOKUP('Sept-24'!$F37,Lista_CUIT!$A$1:$D$2241,4,0)),"CUIT NO CARGADO") -> 0
B38: 45537 | C38: 1 | D38: 106 | E38: 766015 | F38: 30594494187 | G38: =IFERROR(IF('Sept-24'!$F38="","-",VLOOKUP('Sept-24'!$F38,Lista_CUIT!$A$1:$D$2241,2,0)),"CUIT NO CARGADO") -> FEDERAL EXPRESS CORPORATION | I38: =IF('Sept-24'!$H38="","",'Sept-24'!$H38*0.21) | O38: 574924.2 | P38: =SUM('Sept-24'!$H38:$O38) -> 574924.2 | Q38: =IFERROR(IF('Sept-24'!$F38="","-",VLOOKUP('Sept-24'!$F38,Lista_CUIT!$A$1:$D$2241,3,0)),"CUIT NO CARGADO") -> Gastos Importacion | R38: =IFERROR(IF('Sept-24'!$F38="","-",VLOOKUP('Sept-24'!$F38,Lista_CUIT!$A$1:$D$2241,4,0)),"CUIT NO CARGADO") -> 0
B39: 45552 | C39: 1 | D39: 106 | E39: 770685 | F39: 30594494187 | G39: =IFERROR(IF('Sept-24'!$F39="","-",VLOOKUP('Sept-24'!$F39,Lista_CUIT!$A$1:$D$2241,2,0)),"CUIT NO CARGADO") -> FEDERAL EXPRESS CORPORATION | I39: =IF('Sept-24'!$H39="","",'Sept-24'!$H39*0.21) | O39: 549129.02 | P39: =SUM('Sept-24'!$H39:$O39) -> 549129.02 | Q39: =IFERROR(IF('Sept-24'!$F39="","-",VLOOKUP('Sept-24'!$F39,Lista_CUIT!$A$1:$D$2241,3,0)),"CUIT NO CARGADO") -> Gastos Importacion | R39: =IFERROR(IF('Sept-24'!$F39="","-",VLOOKUP('Sept-24'!$F39,Lista_CUIT!$A$1:$D$2241,4,0)),"CUIT NO CARGADO") -> 0
B40: 45565 | C40: 1 | D40: 106 | E40: 774913 | F40: 30594494187 | G40: =IFERROR(IF('Sept-24'!$F40="","-",VLOOKUP('Sept-24'!$F40,Lista_CUIT!$A$1:$D$2241,2,0)),"CUIT NO CARGADO") -> FEDERAL EXPRESS CORPORATION | I40: =IF('Sept-24'!$H40="","",'Sept-24'!$H40*0.21) | O40: 193380.26 | P40: =SUM('Sept-24'!$H40:$O40) -> 193380.26 | Q40: =IFERROR(IF('Sept-24'!$F40="","-",VLOOKUP('Sept-24'!$F40,Lista_CUIT!$A$1:$D$2241,3,0)),"CUIT NO CARGADO") -> Gastos Importacion | R40: =IFERROR(IF('Sept-24'!$F40="","-",VLOOKUP('Sept-24'!$F40,Lista_CUIT!$A$1:$D$2241,4,0)),"CUIT NO CARGADO") -> 0
B41: 45563 | C41: 1 | D41: 4 | E41: 1082054 | F41: 30716620634 | G41: =IFERROR(IF('Sept-24'!$F41="","-",VLOOKUP('Sept-24'!$F41,Lista_CUIT!$A$1:$D$2241,2,0)),"CUIT NO CARGADO") -> FIRSTLABEL SRL | H41: 29791.53 | I41: =IF('Sept-24'!$H41="","",'Sept-24'!$H41*0.21) -> 6256.2213 | P41: =SUM('Sept-24'!$H41:$O41) -> 36047.751 | Q41: =IFERROR(IF('Sept-24'!$F41="","-",VLOOKUP('Sept-24'!$F41,Lista_CUIT!$A$1:$D$2241,3,0)),"CUIT NO CARGADO") -> GASTOS VARIOS | R41: =IFERROR(IF('Sept-24'!$F41="","-",VLOOKUP('Sept-24'!$F41,Lista_CUIT!$A$1:$D$2241,4,0)),"CUIT NO CARGADO") -> 0
B42: Total | H42: =SUBTOTAL(109,'Sept-24'!$H$9:$H$41) -> 6004141.7 | I42: =SUBTOTAL(109,'Sept-24'!$I$9:$I$41) -> 1255506.4 | J42: =SUBTOTAL(109,'Sept-24'!$J$9:$J$41) -> 6895.8 | K42: =SUBTOTAL(109,'Sept-24'!$K$9:$K$41) -> 0 | L42: =SUBTOTAL(109,'Sept-24'!$L$9:$L$41) -> 766.2 | M42: =SUBTOTAL(109,'Sept-24'!$M$9:$M$41) -> 0 | N42: =SUBTOTAL(109,'Sept-24'!$N$9:$N$41) -> 0 | O42: =SUBTOTAL(109,'Sept-24'!$O$9:$O$41) -> 1305824.9 | P42: =SUBTOTAL(109,'Sept-24'!$P$9:$P$41) -> 8573135
D47: LIQUIDACION EXTRACTOS BANCARIOS-TARJETAS
D48: FECHA | E48: NRO CPTE | F48: BANCO | G48: NETO | H48: IVA 21% | I48: IVA 10,5% | J48: RET IIBB CABA | K48: PERC IVA | L48: PERC IIBB
F49: Credicoop | G49: 24050 | H49: ='Sept-24'!$G49*0.21 -> 5050.5 | K49: 721.5
F50: Credicoop | G50: 59132.95 | H50: ='Sept-24'!$G50*0.21 -> 12417.919 | K50: 1613.86
F51: Credicoop EXTRACTO | G51: 800 | H51: ='Sept-24'!$G51*0.21 -> 168 | J51: 27.76
H52: ='Sept-24'!$G52*0.21 -> 0
D53: Total | G53: =SUBTOTAL(109,'Sept-24'!$G$49:$G$52) -> 83982.95 | H53: =SUBTOTAL(109,'Sept-24'!$H$49:$H$52) -> 17636.419 | I53: =SUBTOTAL(109,'Sept-24'!$I$49:$I$52) -> 0 | J53: =SUBTOTAL(109,'Sept-24'!$J$49:$J$52) -> 27.76 | K53: =SUBTOTAL(109,'Sept-24'!$K$49:$K$52) -> 2335.36 | L53: =SUBTOTAL(109,'Sept-24'!$L$49:$L$52) -> 0
D55: FACTURAS C
D56: FECHA | E56: PTO VTA | F56: FC Nº | G56: CUIT | H56: RAZON SOCIAL | I56: TOTAL | J56: TIPO DE GASTO | K56: Provincia
D57: 45536 | E57: 1 | F57: 40 | G57: 20365938688 | H57: =IFERROR(IF('Sept-24'!$G57="","-",VLOOKUP('Sept-24'!$G57,Lista_CUIT!$A$1:$D$2241,2,0)),"CUIT NO CARGADO") -> LIPANOVICH JUAN CRUZ | I57: 750000 | J57: =IFERROR(IF('Sept-24'!$G57="","-",VLOOKUP('Sept-24'!$G57,Lista_CUIT!$A$1:$D$2241,3,0)),"CUIT NO CARGADO") -> SOFTWARE | K57: =IFERROR(IF('Sept-24'!$G57="","-",VLOOKUP('Sept-24'!$G57,Lista_CUIT!$A$1:$D$2241,4,0)),"CUIT NO CARGADO") -> 0
D58: 45537 | E58: 1 | F58: 29 | G58: 27387896150 | H58: =IFERROR(IF('Sept-24'!$G58="","-",VLOOKUP('Sept-24'!$G58,Lista_CUIT!$A$1:$D$2241,2,0)),"CUIT NO CARGADO") -> LIPANOVICH MARIA SOL | I58: 900000 | J58: =IFERROR(IF('Sept-24'!$G58="","-",VLOOKUP('Sept-24'!$G58,Lista_CUIT!$A$1:$D$2241,3,0)),"CUIT NO CARGADO") -> consultoria informatica | K58: =IFERROR(IF('Sept-24'!$G58="","-",VLOOKUP('Sept-24'!$G58,Lista_CUIT!$A$1:$D$2241,4,0)),"CUIT NO CARGADO") -> 0
D59: 45537 | E59: 2 | F59: 176 | G59: 20136544625 | H59: =IFERROR(IF('Sept-24'!$G59="","-",VLOOKUP('Sept-24'!$G59,Lista_CUIT!$A$1:$D$2241,2,0)),"CUIT NO CARGADO") -> RODRIGUEZ DE LA FUEN HECTOR MARCELO | I59: 1035000 | J59: =IFERROR(IF('Sept-24'!$G59="","-",VLOOKUP('Sept-24'!$G59,Lista_CUIT!$A$1:$D$2241,3,0)),"CUIT NO CARGADO") -> Honorarios Admin | K59: =IFERROR(IF('Sept-24'!$G59="","-",VLOOKUP('Sept-24'!$G59,Lista_CUIT!$A$1:$D$2241,4,0)),"CUIT NO CARGADO") -> 0
D60: 45537 | E60: 3 | F60: 881 | G60: 20086277523 | H60: =IFERROR(IF('Sept-24'!$G60="","-",VLOOKUP('Sept-24'!$G60,Lista_CUIT!$A$1:$D$2241,2,0)),"CUIT NO CARGADO") -> ESTUDIO BOTINDARI | I60: 270000 | J60: =IFERROR(IF('Sept-24'!$G60="","-",VLOOKUP('Sept-24'!$G60,Lista_CUIT!$A$1:$D$2241,3,0)),"CUIT NO CARGADO") -> Honorarios Contables | K60: =IFERROR(IF('Sept-24'!$G60="","-",VLOOKUP('Sept-24'!$G60,Lista_CUIT!$A$1:$D$2241,4,0)),"CUIT NO CARGADO") -> 0
D61: 45539 | E61: 2 | F61: 7 | G61: 23118167279 | H61: =IFERROR(IF('Sept-24'!$G61="","-",VLOOKUP('Sept-24'!$G61,Lista_CUIT!$A$1:$D$2241,2,0)),"CUIT NO CARGADO") -> ABELEDO ENRIQUE JUAN | I61: 780000 | J61: =IFERROR(IF('Sept-24'!$G61="","-",VLOOKUP('Sept-24'!$G61,Lista_CUIT!$A$1:$D$2241,3,0)),"CUIT NO CARGADO") -> Honorarios Admin | K61: =IFERROR(IF('Sept-24'!$G61="","-",VLOOKUP('Sept-24'!$G61,Lista_CUIT!$A$1:$D$2241,4,0)),"CUIT NO CARGADO") -> 0
D62: 45541 | E62: 1 | F62: 117 | G62: 20389908569 | H62: =IFERROR(IF('Sept-24'!$G62="","-",VLOOKUP('Sept-24'!$G62,Lista_CUIT!$A$1:$D$2241,2,0)),"CUIT NO CARGADO") -> BOTINDARI JUAN IGNACIO | I62: 72530 | J62: =IFERROR(IF('Sept-24'!$G62="","-",VLOOKUP('Sept-24'!$G62,Lista_CUIT!$A$1:$D$2241,3,0)),"CUIT NO CARGADO") -> Honorarios Contables | K62: =IFERROR(IF('Sept-24'!$G62="","-",VLOOKUP('Sept-24'!$G62,Lista_CUIT!$A$1:$D$2241,4,0)),"CUIT NO CARGADO") -> 0
D63: 45544 | E63: 2 | F63: 255 | G63: 27173820866 | H63: =IFERROR(IF('Sept-24'!$G63="","-",VLOOKUP('Sept-24'!$G63,Lista_CUIT!$A$1:$D$2241,2,0)),"CUIT NO CARGADO") -> FREIER SANDRA DANIELA | I63: 985000 | J63: =IFERROR(IF('Sept-24'!$G63="","-",VLOOKUP('Sept-24'!$G63,Lista_CUIT!$A$1:$D$2241,3,0)),"CUIT NO CARGADO") -> Honorarios Prof | K63: =IFERROR(IF('Sept-24'!$G63="","-",VLOOKUP('Sept-24'!$G63,Lista_CUIT!$A$1:$D$2241,4,0)),"CUIT NO CARGADO") -> 0
D64: 45548 | E64: 1 | F64: 538 | G64: 27925308868 | H64: =IFERROR(IF('Sept-24'!$G64="","-",VLOOKUP('Sept-24'!$G64,Lista_CUIT!$A$1:$D$2241,2,0)),"CUIT NO CARGADO") -> LOPEZ MOLINA MARIA | I64: 10000 | J64: =IFERROR(IF('Sept-24'!$G64="","-",VLOOKUP('Sept-24'!$G64,Lista_CUIT!$A$1:$D$2241,3,0)),"CUIT NO CARGADO") -> GASTOS VARIOS | K64: =IFERROR(IF('Sept-24'!$G64="","-",VLOOKUP('Sept-24'!$G64,Lista_CUIT!$A$1:$D$2241,4,0)),"CUIT NO CARGADO") -> 0
D65: 45551 | E65: 4 | F65: 31 | G65: 20341462933 | H65: =IFERROR(IF('Sept-24'!$G65="","-",VLOOKUP('Sept-24'!$G65,Lista_CUIT!$A$1:$D$2241,2,0)),"CUIT NO CARGADO") -> CASTIGLIONI MATIAS EZEQUIEL | I65: 1395000 | J65: =IFERROR(IF('Sept-24'!$G65="","-",VLOOKUP('Sept-24'!$G65,Lista_CUIT!$A$1:$D$2241,3,0)),"CUIT NO CARGADO") -> ASESORAMIENTO | K65: =IFERROR(IF('Sept-24'!$G65="","-",VLOOKUP('Sept-24'!$G65,Lista_CUIT!$A$1:$D$2241,4,0)),"CUIT NO CARGADO") -> BUENOS AIRES
D66: 45553 | E66: 2 | F66: 150 | G66: 27125997835 | H66: =IFERROR(IF('Sept-24'!$G66="","-",VLOOKUP('Sept-24'!$G66,Lista_CUIT!$A$1:$D$2241,2,0)),"CUIT NO CARGADO") -> DANSKY ULLMANN VIVIANA EVA YOLANDA | I66: 10000 | J66: =IFERROR(IF('Sept-24'!$G66="","-",VLOOKUP('Sept-24'!$G66,Lista_CUIT!$A$1:$D$2241,3,0)),"CUIT NO CARGADO") -> Honorarios Prof | K66: =IFERROR(IF('Sept-24'!$G66="","-",VLOOKUP('Sept-24'!$G66,Lista_CUIT!$A$1:$D$2241,4,0)),"CUIT NO CARGADO") -> 0
D67: 45554 | E67: 32 | F67: 148292 | G67: 30690179020 | H67: =IFERROR(IF('Sept-24'!$G67="","-",VLOOKUP('Sept-24'!$G67,Lista_CUIT!$A$1:$D$2241,2,0)),"CUIT NO CARGADO") -> FIRST RATE SA | I67: 30899.5 | J67: =IFERROR(IF('Sept-24'!$G67="","-",VLOOKUP('Sept-24'!$G67,Lista_CUIT!$A$1:$D$2241,3,0)),"CUIT NO CARGADO") -> GASTOS VARIOS | K67: =IFERROR(IF('Sept-24'!$G67="","-",VLOOKUP('Sept-24'!$G67,Lista_CUIT!$A$1:$D$2241,4,0)),"CUIT NO CARGADO") -> 0
D68: 45558 | E68: 4 | F68: 71 | G68: 23214737914 | H68: =IFERROR(IF('Sept-24'!$G68="","-",VLOOKUP('Sept-24'!$G68,Lista_CUIT!$A$1:$D$2241,2,0)),"CUIT NO CARGADO") -> SBARRA GABRIELA BEATRIZ | I68: 1153940 | J68: =IFERROR(IF('Sept-24'!$G68="","-",VLOOKUP('Sept-24'!$G68,Lista_CUIT!$A$1:$D$2241,3,0)),"CUIT NO CARGADO") -> Honorarios Admin | K68: =IFERROR(IF('Sept-24'!$G68="","-",VLOOKUP('Sept-24'!$G68,Lista_CUIT!$A$1:$D$2241,4,0)),"CUIT NO CARGADO") -> 0
... D70: 45564 | E70: 1 | F70: 1117 | G70: 20412228627 | H70: =IFERROR(IF('Sept-24'!$G70="","-",VLOOKUP('Sept-24'!$G70,Lista_CUIT!$A$1:$D$2241,2,0)),"CUIT NO CARGADO") -> EMBOM RODRIGO NICOLAS | I70: 16471.27 | J70: =IFERROR(IF('Sept-24'!$G70="","-",VLOOKUP('Sept-24'!$G70,Lista_CUIT!$A$1:$D$2241,3,0)),"CUIT NO CARGADO") -> GASTOS VARIOS | K70: =IFERROR(IF('Sept-24'!$G70="","-",VLOOKUP('Sept-24'!$G70,Lista_CUIT!$A$1:$D$2241,4,0)),"CUIT NO CARGADO") -> 0
D71: Total | I71: =SUBTOTAL(109,'Sept-24'!$I$57:$I$70) -> 8058840.8
B77: LIBRO IVA VENTAS | K77: =N1 -> 45170
B79: VENTAS "A"
B80: FECHA | C80: TIPO | D80: PTO VENTA | E80: Nº FACTURA | F80: CUIT | G80: RAZON SOCIAL | H80: IMPORTE NETO | I80: IVA 21% | J80: IVA 10,5% | K80: EXENTO | L80: TOTAL | M80: Provincia
B81: 45537 | D81: 3 | E81: 220 | F81: 30638318470 | G81: =IFERROR(IF('Sept-24'!$F81="","-",VLOOKUP('Sept-24'!$F81,Lista_CUIT!$A$1:$D$2241,2,0)),"CUIT NO CARGADO") -> DELTA COMPRESION S R L | H81: 4424328.3 | I81: ='Sept-24'!$H81*0.21 -> 929108.94 | L81: =SUM('Sept-24'!$H81:$K81) -> 5353437.2
B82: 45539 | D82: 3 | E82: 221 | F82: 30687492397 | G82: =IFERROR(IF('Sept-24'!$F82="","-",VLOOKUP('Sept-24'!$F82,Lista_CUIT!$A$1:$D$2241,2,0)),"CUIT NO CARGADO") -> CIUDAD DE EZEIZA SRL | H82: 311520 | I82: ='Sept-24'!$H82*0.21 -> 65419.2 | L82: =SUM('Sept-24'!$H82:$K82) -> 376939.2
B83: 45551 | D83: 3 | E83: 222 | F83: 30628274327 | G83: =IFERROR(IF('Sept-24'!$F83="","-",VLOOKUP('Sept-24'!$F83,Lista_CUIT!$A$1:$D$2241,2,0)),"CUIT NO CARGADO") -> AGIRA S A | H83: 13339830 | I83: 61299 | J83: 1370032.6 | L83: =SUM('Sept-24'!$H83:$K83) -> 14771162
B84: 45553 | D84: 3 | E84: 223 | F84: 20124583463 | G84: =IFERROR(IF('Sept-24'!$F84="","-",VLOOKUP('Sept-24'!$F84,Lista_CUIT!$A$1:$D$2241,2,0)),"CUIT NO CARGADO") -> LUCERO MARIO ALFREDO | H84: 378070 | I84: ='Sept-24'!$H84*0.21 -> 79394.7 | L84: =SUM('Sept-24'!$H84:$K84) -> 457464.7
B85: 45554 | D85: 3 | E85: 224 | F85: 20228469492 | G85: =IFERROR(IF('Sept-24'!$F85="","-",VLOOKUP('Sept-24'!$F85,Lista_CUIT!$A$1:$D$2241,2,0)),"CUIT NO CARGADO") -> DOMINGUEZ LAGANA GONZALO FABIAN | H85: 275380 | I85: ='Sept-24'!$H85*0.21 -> 57829.8 | L85: =SUM('Sept-24'!$H85:$K85) -> 333209.8
B86: 45555 | D86: 3 | E86: 225 | F86: 30638318470 | G86: =IFERROR(IF('Sept-24'!$F86="","-",VLOOKUP('Sept-24'!$F86,Lista_CUIT!$A$1:$D$2241,2,0)),"CUIT NO CARGADO") -> DELTA COMPRESION S R L | H86: 3395689 | I86: ='Sept-24'!$H86*0.21 -> 713094.69 | L86: =SUM('Sept-24'!$H86:$K86) -> 4108783.7
B87: 45559 | D87: 3 | E87: 226 | F87: 30638318470 | G87: =IFERROR(IF('Sept-24'!$F87="","-",VLOOKUP('Sept-24'!$F87,Lista_CUIT!$A$1:$D$2241,2,0)),"CUIT NO CARGADO") -> DELTA COMPRESION S R L | H87: 20878550 | J87: 2192252.7 | L87: =SUM('Sept-24'!$H87:$K87) -> 23070803
B88: 45561 | D88: 3 | E88: 228 | F88: 30638318470 | G88: =IFERROR(IF('Sept-24'!$F88="","-",VLOOKUP('Sept-24'!$F88,Lista_CUIT!$A$1:$D$2241,2,0)),"CUIT NO CARGADO") -> DELTA COMPRESION S R L | H88: 79539652 | J88: ='Sept-24'!$H88*0.105 -> 8351663.5 | L88: =SUM('Sept-24'!$H88:$K88) -> 87891316
B89: 45561 | D89: 3 | E89: 227 | F89: 30638318470 | G89: =IFERROR(IF('Sept-24'!$F89="","-",VLOOKUP('Sept-24'!$F89,Lista_CUIT!$A$1:$D$2241,2,0)),"CUIT NO CARGADO") -> DELTA COMPRESION S R L | H89: 1556393.2 | I89: ='Sept-24'!$H89*0.21 -> 326842.58 | L89: =SUM('Sept-24'!$H89:$K89) -> 1883235.8
G90: =IFERROR(IF('Sept-24'!$F90="","-",VLOOKUP('Sept-24'!$F90,Lista_CUIT!$A$1:$D$2241,2,0)),"CUIT NO CARGADO") -> - | L90: =SUM('Sept-24'!$H90:$K90) -> 0
B91: Total | H91: =SUBTOTAL(109,'Sept-24'!$H$81:$H$90) -> 1.2409941e+08 | I91: =SUBTOTAL(109,'Sept-24'!$I$81:$I$90) -> 2232988.9 | J91: =SUBTOTAL(109,'Sept-24'!$J$81:$J$90) -> 11913949 | K91: =SUBTOTAL(109,'Sept-24'!$K$81:$K$90) -> 0 | L91: =SUBTOTAL(109,'Sept-24'!$L$81:$L$90) -> 1.3824635e+08 | M91: =SUBTOTAL(103,'Sept-24'!$M$81:$M$90) -> 0
B93: VENTAS "B"
B94: FECHA | C94: TIPO | D94: PTO VENTA | E94: Nº FACTURA | F94: CUIT | G94: RAZON SOCIAL | H94: IMPORTE NETO | I94: IVA 21% | J94: IVA 10,5% | K94: EXENTO | L94: TOTAL | M94: Provincia
G95: =IFERROR(IF('Sept-24'!$F95="","-",VLOOKUP('Sept-24'!$F95,Lista_CUIT!$A$1:$D$2241,2,0)),"CUIT NO CARGADO") -> - | L95: =SUM('Sept-24'!$H95:$K95) -> 0
L96: =SUM('Sept-24'!$H96:$K96) -> 0
L97: =SUM('Sept-24'!$H97:$K97) -> 0
L98: =SUM('Sept-24'!$H98:$K98) -> 0
L99: =SUM('Sept-24'!$H99:$K99) -> 0
L100: =SUM('Sept-24'!$H100:$K100) -> 0
B101: Total | H101: =SUBTOTAL(109,'Sept-24'!$H$95:$H$100) -> 0 | I101: =SUBTOTAL(109,'Sept-24'!$I$95:$I$100) -> 0 | J101: =SUBTOTAL(109,'Sept-24'!$J$95:$J$100) -> 0 | K101: =SUBTOTAL(109,'Sept-24'!$K$95:$K$100) -> 0 | L101: =SUBTOTAL(109,'Sept-24'!$L$95:$L$100) -> 0 | M101: =SUBTOTAL(103,'Sept-24'!$M$95:$M$100) -> 0
B103: VENTAS "E"
B104: FECHA | C104: TIPO | D104: PTO VENTA | E104: Nº FACTURA | F104: CUIT | G104: RAZON SOCIAL | H104: USD | I104: IVA 21% | J104: Columna1 | K104: TIPO DE CAMBIO2 | L104: TOTAL | M104: PAIS
B105: 05/09/2024 | D105: 30 | E105: 93 | F105: 55000002223 | H105: 1185 | K105: 954.5 | L105: =+'Sept-24'!$K105*'Sept-24'!$H105 -> 1131082.5
B106: 24/09/2024 | D106: 30 | E106: 94 | F106: 55000000050 | H106: 13400 | K106: 966 | L106: =+'Sept-24'!$K106*'Sept-24'!$H106 -> 12944400
B107: 25/09/2024 | D107: 30 | E107: 96 | H107: 2080 | K107: 966.5 | L107: =+'Sept-24'!$K107*'Sept-24'!$H107 -> 2010320 | M107: =SUBTOTAL(103,'Abr-24'!$M$103:$M$106) -> 0
B108: 25/09/2024 | D108: 30 | E108: 95 | H108: 900 | K108: 966.5 | L108: =+'Sept-24'!$K108*'Sept-24'!$H108 -> 869850
I112: ='Sept-24'!$H112*0.21 -> 0
B113: Total | H113: =SUBTOTAL(109,'Sept-24'!$H$105:$H$112) -> 17565 | I113: =SUBTOTAL(109,'Sept-24'!$I$105:$I$112) -> 0 | J113: =SUBTOTAL(109,'Sept-24'!$J$105:$J$112) -> 0 | K113: =SUBTOTAL(109,'Sept-24'!$K$105:$K$112) -> 3853.5 | L113: =SUM(L105:L106) -> 14075482 | M113: =SUBTOTAL(103,'Sept-24'!$M$105:$M$112) -> 0
C115: RETENCIONES
C116: FECHA | D116: COMP Nº | E116: Columna1 | F116: CUIT | G116: RAZON SOCIAL | H116: Ganancias | I116: IVA | J116: SUSS | K116: IIBB BSAS | L116: IIBB CABA
D117: 11694 | G117: =IFERROR(IF('Sept-24'!$F117="","-",VLOOKUP('Sept-24'!$F117,Lista_CUIT!$A$1:$D$2241,2,0)),"CUIT NO CARGADO") -> -
D118: 11695 | G118: =IFERROR(IF('Sept-24'!$F118="","-",VLOOKUP('Sept-24'!$F118,Lista_CUIT!$A$1:$D$2241,2,0)),"CUIT NO CARGADO") -> -
D119: 11696 | G119: =IFERROR(IF('Sept-24'!$F119="","-",VLOOKUP('Sept-24'!$F119,Lista_CUIT!$A$1:$D$2241,2,0)),"CUIT NO CARGADO") -> -
D120: 11697 | G120: =IFERROR(IF('Sept-24'!$F120="","-",VLOOKUP('Sept-24'!$F120,Lista_CUIT!$A$1:$D$2241,2,0)),"CUIT NO CARGADO") -> -
D121: 11698 | G121: =IFERROR(IF('Sept-24'!$F121="","-",VLOOKUP('Sept-24'!$F121,Lista_CUIT!$A$1:$D$2241,2,0)),"CUIT NO CARGADO") -> -

Sheet Oct-24
B1: LIBRO IVA COMPRAS | G1: ='Abr-24'!G1:M1 -> CORITEC S. R. L. | N1: =EDATE('Abr-24'!N1,6) -> 45200
B3: TOTAL COMPRAS | G3: TOTAL CREDITO FISCAL | J3: TOTAL VENTAS NETAS | M3: TOTAL DEBITO FISCAL | P3: RESULTADO
B4: =SUM('Oct-24'!$H$63)+'Oct-24'!$G$74 -> 3059537.6 | G4: ='Oct-24'!$I$63+'Oct-24'!$J$63+'Oct-24'!$K$63+'Oct-24'!$H$74+'Oct-24'!$I$74 -> 632042.56 | J4: ='Oct-24'!$H$119+'Oct-24'!$H$130 -> 10286191 | M4: ='Oct-24'!$I$119+'Oct-24'!$J$119+'Oct-24'!$I$130+'Oct-24'!$J$130+I141+J141 -> 2177095.8 | P4: =G4-M4 -> -1545053.2
B8: FECHA | C8: TIPO | D8: PTO VTA | E8: NRO. CPTE | F8: CUIT | G8: RAZON SOCIAL | H8: NETO GRAVADO | I8: IVA 21 % | J8: IVA 27% | K8: IVA 10,5% | L8: PERC. IVA | M8: PERC IIBB BS AS | N8: PERC. IIBB CABA | O8: Otros / No Grav. | P8: TOTAL | Q8: Tipo de Gasto | R8: Provincia
B9: 01/10/2024 | C9: 1 | D9: 3 | E9: 242462 | F9: 30707135596 | G9: =IFERROR(IF('Oct-24'!$F9="","-",VLOOKUP('Oct-24'!$F9,Lista_CUIT!$A$1:$D$2241,2,0)),"CUIT NO CARGADO") -> CITILAN ARGENTINA S.A. | H9: 23571.53 | I9: =IF('Oct-24'!$H9="","",'Oct-24'!$H9*0.21) -> 4950.0213 | P9: =SUM('Oct-24'!$H9:$O9) -> 28521.551 | Q9: =IFERROR(IF('Oct-24'!$F9="","-",VLOOKUP('Oct-24'!$F9,Lista_CUIT!$A$1:$D$2241,3,0)),"CUIT NO CARGADO") -> Telefonia | R9: =IFERROR(IF('Oct-24'!$F9="","-",VLOOKUP('Oct-24'!$F9,Lista_CUIT!$A$1:$D$2241,4,0)),"CUIT NO CARGADO") -> 0
B10: 01/10/2024 | C10: 1 | D10: 9002 | E10: 8514 | F10: 30710644809 | G10: =IFERROR(IF('Oct-24'!$F10="","-",VLOOKUP('Oct-24'!$F10,Lista_CUIT!$A$1:$D$2241,2,0)),"CUIT NO CARGADO") -> MAARE S.R.L. | H10: 37388.43 | I10: =IF('Oct-24'!$H10="","",'Oct-24'!$H10*0.21) -> 7851.5703 | P10: =SUM('Oct-24'!$H10:$O10) -> 45240 | Q10: =IFERROR(IF('Oct-24'!$F10="","-",VLOOKUP('Oct-24'!$F10,Lista_CUIT!$A$1:$D$2241,3,0)),"CUIT NO CARGADO") -> Ropa de Trabajo | R10: =IFERROR(IF('Oct-24'!$F10="","-",VLOOKUP('Oct-24'!$F10,Lista_CUIT!$A$1:$D$2241,4,0)),"CUIT NO CARGADO") -> 0
B11: 01/10/2024 | C11: 1 | D11: 4 | E11: 4052 | F11: 27200094331 | G11: =IFERROR(IF('Oct-24'!$F11="","-",VLOOKUP('Oct-24'!$F11,Lista_CUIT!$A$1:$D$2241,2,0)),"CUIT NO CARGADO") -> PEREZ ADRIANA MARINA | H11: 28922.31 | I11: =IF('Oct-24'!$H11="","",'Oct-24'!$H11*0.21) -> 6073.6851 | P11: =SUM('Oct-24'!$H11:$O11) -> 34995.995 | Q11: =IFERROR(IF('Oct-24'!$F11="","-",VLOOKUP('Oct-24'!$F11,Lista_CUIT!$A$1:$D$2241,3,0)),"CUIT NO CARGADO") -> Materiales Electricos | R11: =IFERROR(IF('Oct-24'!$F11="","-",VLOOKUP('Oct-24'!$F11,Lista_CUIT!$A$1:$D$2241,4,0)),"CUIT NO CARGADO") -> 0
B12: 01/10/2024 | C12: 1 | D12: 2 | E12: 204 | F12: 20125142851 | G12: =IFERROR(IF('Oct-24'!$F12="","-",VLOOKUP('Oct-24'!$F12,Lista_CUIT!$A$1:$D$2241,2,0)),"CUIT NO CARGADO") -> FEDERICI NICOLAS JOSE | H12: 200133 | I12: =IF('Oct-24'!$H12="","",'Oct-24'!$H12*0.21) -> 42027.93 | P12: =SUM('Oct-24'!$H12:$O12) -> 242160.93 | Q12: =IFERROR(IF('Oct-24'!$F12="","-",VLOOKUP('Oct-24'!$F12,Lista_CUIT!$A$1:$D$2241,3,0)),"CUIT NO CARGADO") -> INSUMO | R12: =IFERROR(IF('Oct-24'!$F12="","-",VLOOKUP('Oct-24'!$F12,Lista_CUIT!$A$1:$D$2241,4,0)),"CUIT NO CARGADO") -> 0
B13: 01/10/2024 | C13: 1 | D13: 3 | E13: 793 | F13: 30715402765 | G13: =IFERROR(IF('Oct-24'!$F13="","-",VLOOKUP('Oct-24'!$F13,Lista_CUIT!$A$1:$D$2241,2,0)),"CUIT NO CARGADO") -> RIO 265 S.R.L. | H13: 67768.62 | I13: =IF('Oct-24'!$H13="","",'Oct-24'!$H13*0.21) -> 14231.41 | P13: =SUM('Oct-24'!$H13:$O13) -> 82000.03 | Q13: =IFERROR(IF('Oct-24'!$F13="","-",VLOOKUP('Oct-24'!$F13,Lista_CUIT!$A$1:$D$2241,3,0)),"CUIT NO CARGADO") -> GASTOS VARIOS | R13: =IFERROR(IF('Oct-24'!$F13="","-",VLOOKUP('Oct-24'!$F13,Lista_CUIT!$A$1:$D$2241,4,0)),"CUIT NO CARGADO") -> 0
B14: 04/10/2024 | C14: 1 | D14: 4 | E14: 18335 | F14: 30709362875 | G14: =IFERROR(IF('Oct-24'!$F14="","-",VLOOKUP('Oct-24'!$F14,Lista_CUIT!$A$1:$D$2241,2,0)),"CUIT NO CARGADO") -> ELINDAR SRL | H14: 63768.95 | K14: =Table_43[[#This Row],[NETO GRAVADO]]*0.105 -> 6695.7397 | P14: =SUM('Oct-24'!$H14:$O14) -> 70464.69 | Q14: =IFERROR(IF('Oct-24'!$F14="","-",VLOOKUP('Oct-24'!$F14,Lista_CUIT!$A$1:$D$2241,3,0)),"CUIT NO CARGADO") -> REPUESTOS | R14: =IFERROR(IF('Oct-24'!$F14="","-",VLOOKUP('Oct-24'!$F14,Lista_CUIT!$A$1:$D$2241,4,0)),"CUIT NO CARGADO") -> BUENOS AIRES
B15: 04/10/2024 | C15: 1 | D15: 2 | E15: 57001 | F15: 30716831066 | G15: =IFERROR(IF('Oct-24'!$F15="","-",VLOOKUP('Oct-24'!$F15,Lista_CUIT!$A$1:$D$2241,2,0)),"CUIT NO CARGADO") -> DOUBLE G SA | H15: 34694.21 | I15: =IF('Oct-24'!$H15="","",'Oct-24'!$H15*0.21) -> 7285.7841 | P15: =SUM('Oct-24'!$H15:$O15) -> 41979.994 | Q15: =IFERROR(IF('Oct-24'!$F15="","-",VLOOKUP('Oct-24'!$F15,Lista_CUIT!$A$1:$D$2241,3,0)),"CUIT NO CARGADO") -> REPUESTOS | R15: =IFERROR(IF('Oct-24'!$F15="","-",VLOOKUP('Oct-24'!$F15,Lista_CUIT!$A$1:$D$2241,4,0)),"CUIT NO CARGADO") -> 0
B16: 04/10/2024 | C16: 1 | D16: 5 | E16: 4850 | F16: 23342701469 | G16: =IFERROR(IF('Oct-24'!$F16="","-",VLOOKUP('Oct-24'!$F16,Lista_CUIT!$A$1:$D$2241,2,0)),"CUIT NO CARGADO") -> MALETTI ALEJANDRO ARTURO | H16: 110826.45 | I16: =IF('Oct-24'!$H16="","",'Oct-24'!$H16*0.21) -> 23273.554 | P16: =SUM('Oct-24'!$H16:$O16) -> 134100 | Q16: =IFERROR(IF('Oct-24'!$F16="","-",VLOOKUP('Oct-24'!$F16,Lista_CUIT!$A$1:$D$2241,3,0)),"CUIT NO CARGADO") -> GASTOS VARIOS | R16: =IFERROR(IF('Oct-24'!$F16="","-",VLOOKUP('Oct-24'!$F16,Lista_CUIT!$A$1:$D$2241,4,0)),"CUIT NO CARGADO") -> 0
B17: 05/10/2024 | C17: 1 | D17: 89 | E17: 87807 | F17: 30710854072 | G17: =IFERROR(IF('Oct-24'!$F17="","-",VLOOKUP('Oct-24'!$F17,Lista_CUIT!$A$1:$D$2241,2,0)),"CUIT NO CARGADO") -> TIMARO SRL | H17: 31262.81 | I17: =IF('Oct-24'!$H17="","",'Oct-24'!$H17*0.21) -> 6565.1901 | P17: =SUM('Oct-24'!$H17:$O17) -> 37828 | Q17: =IFERROR(IF('Oct-24'!$F17="","-",VLOOKUP('Oct-24'!$F17,Lista_CUIT!$A$1:$D$2241,3,0)),"CUIT NO CARGADO") -> pintureria | R17: =IFERROR(IF('Oct-24'!$F17="","-",VLOOKUP('Oct-24'!$F17,Lista_CUIT!$A$1:$D$2241,4,0)),"CUIT NO CARGADO") -> 0
B18: 08/10/2024 | C18: 1 | D18: 5 | E18: 45028 | F18: 30712387390 | G18: =IFERROR(IF('Oct-24'!$F18="","-",VLOOKUP('Oct-24'!$F18,Lista_CUIT!$A$1:$D$2241,2,0)),"CUIT NO CARGADO") -> MOMA FOOD S.R.L. | H18: 29453.02 | I18: =IF('Oct-24'!$H18="","",'Oct-24'!$H18*0.21) -> 6185.1342 | P18: =SUM('Oct-24'!$H18:$O18) -> 35638.154 | Q18: =IFERROR(IF('Oct-24'!$F18="","-",VLOOKUP('Oct-24'!$F18,Lista_CUIT!$A$1:$D$2241,3,0)),"CUIT NO CARGADO") -> Catering | R18: =IFERROR(IF('Oct-24'!$F18="","-",VLOOKUP('Oct-24'!$F18,Lista_CUIT!$A$1:$D$2241,4,0)),"CUIT NO CARGADO") -> 0
B19: 08/10/2024 | C19: 1 | D19: 23 | E19: 31069 | F19: 30711493596 | G19: =IFERROR(IF('Oct-24'!$F19="","-",VLOOKUP('Oct-24'!$F19,Lista_CUIT!$A$1:$D$2241,2,0)),"CUIT NO CARGADO") -> LBH HOME & HOTEL S.A. | H19: 39743.8 | I19: =IF('Oct-24'!$H19="","",'Oct-24'!$H19*0.21) -> 8346.198 | P19: =SUM('Oct-24'!$H19:$O19) -> 48089.998 | Q19: =IFERROR(IF('Oct-24'!$F19="","-",VLOOKUP('Oct-24'!$F19,Lista_CUIT!$A$1:$D$2241,3,0)),"CUIT NO CARGADO") -> Ropa de Trabajo | R19: =IFERROR(IF('Oct-24'!$F19="","-",VLOOKUP('Oct-24'!$F19,Lista_CUIT!$A$1:$D$2241,4,0)),"CUIT NO CARGADO") -> 0
B20: 09/10/2024 | C20: 1 | D20: 2 | E20: 205 | F20: 20125142851 | G20: =IFERROR(IF('Oct-24'!$F20="","-",VLOOKUP('Oct-24'!$F20,Lista_CUIT!$A$1:$D$2241,2,0)),"CUIT NO CARGADO") -> FEDERICI NICOLAS JOSE | H20: 210049.52 | I20: =IF('Oct-24'!$H20="","",'Oct-24'!$H20*0.21) -> 44110.399 | P20: =SUM('Oct-24'!$H20:$O20) -> 254159.92 | Q20: =IFERROR(IF('Oct-24'!$F20="","-",VLOOKUP('Oct-24'!$F20,Lista_CUIT!$A$1:$D$2241,3,0)),"CUIT NO CARGADO") -> INSUMO | R20: =IFERROR(IF('Oct-24'!$F20="","-",VLOOKUP('Oct-24'!$F20,Lista_CUIT!$A$1:$D$2241,4,0)),"CUIT NO CARGADO") -> 0
