Workbook
Name partner_id: Configuracion!$B$332

Sheet Configuracion
F1: CUIT | G1: Cargar sin guiones
F2: RAZON SOCIAL | G2: Maximo 30 caracteres
A3: CUIT | B3: RAZON SOCIAL | C3: DETALLE | F3: DETALLE | G3: Cargar tipo de gasto
A4: 30628205090 | B4: ALBAMIE SA | C4: CLIENTE
A5: 30711678820 | B5: 2PSI INGENIERIA SRL | C5: PROVEEDOR
A6: 33716367539 | B6: 3PI S.A.S. | C6: PROVEEDOR
A7: 30660373108 | B7: ABC SA | C7: VARIOS
A8: 20300210881 | B8: ABOY DIEGO OSCAR | C8: PROVEEDOR
A9: 27229910782 | B9: ABUGAUCH MARIA DE LOS ANGELES | C9: PROVEEDOR
A10: 20242709897 | B10: ABUGAUCH VICTOR HUGO | C10: PROVEEDOR
A11: 20281669053 | B11: ACOSTA JAVIER GUSTAVO | C11: FLETE
A12: 20174240125 | B12: ACOSTA OSCAR ISIDRO | C12: VARIOS
A13: 30641659106 | B13: AGRISOL SA | C13: VARIOS
A14: 33709914109 | B14: ALAN COLLECTION SA | C14: VARIOS
A15: 20267161616 | B15: ALBAJARI DIEGO MARCOS | C15: VARIOS
... A155: 30537679855 | B155: ESTACION LIMA SA | C155: VARIOS
A156: 30-56864959-8 | B156: EXPRESO BISONTE SRL | C156: FLETE
A157: 30708542349 | B157: EXPRESO FORMOSA SRL | C157: FLETE
A158: 30526582884 | B158: EXPRESO MAR DEL PLATA SA | C158: FLETE
A159: 30577744579 | B159: EXPRESO TROLE SRL | C159: FLETE
A160: 30715949292 | B160: EYPAPEL SAS | C160: GASTOS VARIOS
A161: 30715980807 | B161: FABORT SRL | C161: PROVEEDOR
A162: 20359718765 | B162: FAIL ABRAHAM | C162: VARIOS
A163: 30643518364 | B163: FARMACIA DE MEDRANO SCS | C163: PROVEEDOR
A164: 30692138747 | B164: FARMACITY SA | C164: VARIOS
A165: 33712234429 | B165: FEDAGAS SA | C165: VARIOS
A166: 20353576012 | B166: FEDERICO PABLO FEOLA | C166: VARIOS
A167: 20343766441 | B167: FERNANDEZ MAURO | C167: TALLER
A168: 27062343449 | B168: FERREIRA LILIANA INES | C168: FLETE
... A568: 30587842358 | B568: CLINICA BASILEA SA | C568: CLIENTE

Sheet Nov 24
A1: ORTOPEDIA GEMINIS S.A. | J1: 45597
A4: LIBRO IVA COMPRAS
A6: FACTURAS A
A7: FECHA | B7: PTO VTA | C7: FAC A | D7: CUIT | E7: RAZON SOCIAL | F7: NETO | G7: IVA 21% | H7: IVA 27% | I7: IVA 10,5% | J7: P IVA | K7: IIBB CF | L7: IIBB BS | M7: NO GRAV | N7: OTROS | O7: TOTAL | P7: DETALLE
A8: 45607 | B8: 8 | C8: 13270 | D8: 33715594949 | E8: =VLOOKUP(D8,Configuracion!$A$4:$C$590,2,FALSE) -> SOMOS ENERGIA SA | F8: 80639.13 | G8: =F8*21% -> 16934.217 | K8: 5769.09 | N8: 657.51 | O8: =SUM(F8:N8) -> 103999.95 | P8: =VLOOKUP(D8,Configuracion!$A$4:$C$590,3,FALSE) -> GASTOS VARIOS
A9: 45584 | B9: 12 | C9: 12765 | D9: 30685116657 | E9: =VLOOKUP(D9,Configuracion!$A$4:$C$590,2,FALSE) -> MIRVAR SA | F9: 37736.11 | G9: =F9*21% -> 7924.5831 | N9: 7345.16 | O9: =SUM(F9:N9) -> 53005.853 | P9: =VLOOKUP(D9,Configuracion!$A$4:$C$590,3,FALSE) -> VARIOS
A10: 45623 | B10: 6 | C10: 20262 | D10: 33715594949 | E10: =VLOOKUP(D10,Configuracion!$A$4:$C$590,2,FALSE) -> SOMOS ENERGIA SA | F10: 99460.83 | G10: =F10*21% -> 20886.774 | N10: 12651.36 | O10: =SUM(F10:N10) -> 132998.96 | P10: =VLOOKUP(D10,Configuracion!$A$4:$C$590,3,FALSE) -> GASTOS VARIOS
A11: 45594 | B11: 6 | C11: 19925 | D11: 33715594949 | E11: =VLOOKUP(D11,Configuracion!$A$4:$C$590,2,FALSE) -> SOMOS ENERGIA SA | F11: 34466.21 | G11: =F11*21% -> 7237.9041 | N11: 2639.95 | O11: =SUM(F11:N11) -> 44344.064 | P11: =VLOOKUP(D11,Configuracion!$A$4:$C$590,3,FALSE) -> GASTOS VARIOS
A12: 45598 | B12: 6 | C12: 199958 | D12: 33715594949 | E12: =VLOOKUP(D12,Configuracion!$A$4:$C$590,2,FALSE) -> SOMOS ENERGIA SA | F12: 50154.49 | G12: =F12*21% -> 10532.443 | N12: 3997.11 | O12: =SUM(F12:N12) -> 64684.043 | P12: =VLOOKUP(D12,Configuracion!$A$4:$C$590,3,FALSE) -> GASTOS VARIOS
A13: 45603 | B13: 6 | C13: 20024 | D13: 33715594949 | E13: =VLOOKUP(D13,Configuracion!$A$4:$C$590,2,FALSE) -> SOMOS ENERGIA SA | F13: 67728.33 | G13: =F13*21% -> 14222.949 | N13: 5397.67 | O13: =SUM(F13:N13) -> 87348.949 | P13: =VLOOKUP(D13,Configuracion!$A$4:$C$590,3,FALSE) -> GASTOS VARIOS
A14: 45617 | B14: 8 | C14: 13359 | D14: 33715594949 | E14: =VLOOKUP(D14,Configuracion!$A$4:$C$590,2,FALSE) -> SOMOS ENERGIA SA | F14: 89743.55 | G14: =F14*21% -> 18846.145 | N14: 11415.32 | O14: =SUM(F14:N14) -> 120005.02 | P14: =VLOOKUP(D14,Configuracion!$A$4:$C$590,3,FALSE) -> GASTOS VARIOS
A15: 45616 | B15: 6 | C15: 1710 | D15: 30716815710 | E15: =VLOOKUP(D15,Configuracion!$A$4:$C$590,2,FALSE) -> PAPELERA GEOPEL SRL | F15: 14800 | G15: =F15*21% -> 3108 | O15: =SUM(F15:N15) -> 17908 | P15: =VLOOKUP(D15,Configuracion!$A$4:$C$590,3,FALSE) -> LIBRERÍA
A16: 45615 | B16: 326 | C16: 79605 | D16: 30556565798 | E16: =VLOOKUP(D16,Configuracion!$A$4:$C$590,2,FALSE) -> V M TRASP CRUZ DEL SUR SA | F16: 21901.87 | G16: =F16*21% -> 4599.3927 | O16: =SUM(F16:N16) -> 26501.263 | P16: =VLOOKUP(D16,Configuracion!$A$4:$C$590,3,FALSE) -> FLETE
E17: =VLOOKUP(D17,Configuracion!$A$4:$C$590,2,FALSE) -> #N/A | G17: =F17*21% -> 0 | O17: =SUM(F17:N17) -> 0 | P17: =VLOOKUP(D17,Configuracion!$A$4:$C$590,3,FALSE) -> #N/A
A18: TOTAL | F18: =SUM(F8:F17) -> 496630.52 | G18: =SUM(G8:G17) -> 104292.41 | H18: =SUM(H8:H17) -> 0 | I18: =SUM(I8:I17) -> 0 | J18: =SUM(J8:J17) -> 0 | K18: =SUM(K8:K17) -> 5769.09 | L18: =SUM(L8:L17) -> 0 | M18: =SUM(M8:M17) -> 0 | ... O18: =SUM(O8:O17) -> 650796.1
F19: IVA | G19: =G18+H18+I18 -> 104292.41
A21: FACTURAS B/C
A22: FECHA | B22: PTO VTA | C22: FAC C | D22: CUIT | E22: RAZON SOCIAL | F22: TOTAL | G22: DETALLE
E23: =VLOOKUP(D23,Configuracion!$A$4:$C$590,2,FALSE) -> #N/A | G23: =VLOOKUP(D23,Configuracion!$A$4:$C$590,3,FALSE) -> #N/A
E24: =VLOOKUP(D24,Configuracion!$A$4:$C$590,2,FALSE) -> #N/A | G24: =VLOOKUP(D24,Configuracion!$A$4:$C$590,3,FALSE) -> #N/A
E25: =VLOOKUP(D25,Configuracion!$A$4:$C$590,2,FALSE) -> #N/A | G25: =VLOOKUP(D25,Configuracion!$A$4:$C$590,3,FALSE) -> #N/A
E26: =VLOOKUP(D26,Configuracion!$A$4:$C$590,2,FALSE) -> #N/A | G26: =VLOOKUP(D26,Configuracion!$A$4:$C$590,3,FALSE) -> #N/A
E27: =VLOOKUP(D27,Configuracion!$A$4:$C$590,2,FALSE) -> #N/A | G27: =VLOOKUP(D27,Configuracion!$A$4:$C$590,3,FALSE) -> #N/A
E28: =VLOOKUP(D28,Configuracion!$A$4:$C$590,2,FALSE) -> #N/A | G28: =VLOOKUP(D28,Configuracion!$A$4:$C$590,3,FALSE) -> #N/A
E29: =VLOOKUP(D29,Configuracion!$A$4:$C$590,2,FALSE) -> #N/A | G29: =VLOOKUP(D29,Configuracion!$A$4:$C$590,3,FALSE) -> #N/A
E30: =VLOOKUP(D30,Configuracion!$A$4:$C$590,2,FALSE) -> #N/A | G30: =VLOOKUP(D30,Configuracion!$A$4:$C$590,3,FALSE) -> #N/A
E31: =VLOOKUP(D31,Configuracion!$A$4:$C$590,2,FALSE) -> #N/A | G31: =VLOOKUP(D31,Configuracion!$A$4:$C$590,3,FALSE) -> #N/A
E32: =VLOOKUP(D32,Configuracion!$A$4:$C$590,2,FALSE) -> #N/A | G32: =VLOOKUP(D32,Configuracion!$A$4:$C$590,3,FALSE) -> #N/A
E33: =VLOOKUP(D33,Configuracion!$A$4:$C$590,2,FALSE) -> #N/A | G33: =VLOOKUP(D33,Configuracion!$A$4:$C$590,3,FALSE) -> #N/A
E34: =VLOOKUP(D34,Configuracion!$A$4:$C$590,2,FALSE) -> #N/A | G34: =VLOOKUP(D34,Configuracion!$A$4:$C$590,3,FALSE) -> #N/A
... E41: =VLOOKUP(D41,Configuracion!$A$4:$C$590,2,FALSE) -> #N/A | G41: =VLOOKUP(D41,Configuracion!$A$4:$C$590,3,FALSE) -> #N/A
A42: TOTAL | F42: =SUM(F23:F41) -> 0
A44: RETENCIONES
A45: FECHA | B45: COMPROBANTE NRO | D45: CUIT | E45: RAZON SOCIAL | F45: GANANCIAS | G45: IVA | H45: IIBB | I45: SUSS
A46: 45565 | B46: 86205 | D46: 30522428163 | E46: =VLOOKUP(D46,Configuracion!$A$4:$C$590,2,FALSE) -> GALENO ARGENTINA SA | F46: 36314.96 | G46: 190648.76 | H46: 18157.02 | I46: 18157.02
A47: 45603 | B47: 97789 | D47: 30522428163 | E47: =VLOOKUP(D47,Configuracion!$A$4:$C$590,2,FALSE) -> GALENO ARGENTINA SA | F47: 20231.24 | G47: 106214.87 | H47: 10115.7 | I47: 10115.7
A48: 45566 | B48: 86767 | D48: 30522428163 | E48: =VLOOKUP(D48,Configuracion!$A$4:$C$590,2,FALSE) -> GALENO ARGENTINA SA | F48: 66222.86 | G48: 347671.49 | H48: 33111.57 | I48: 33111.57
A49: 45581 | B49: 92605 | D49: 30522428163 | E49: =VLOOKUP(D49,Configuracion!$A$4:$C$590,2,FALSE) -> GALENO ARGENTINA SA | F49: 127811.57 | G49: 682118.18 | H49: 63905.79 | I49: 64963.64
A50: 45595 | B50: 95940 | D50: 30522428163 | E50: =VLOOKUP(D50,Configuracion!$A$4:$C$590,2,FALSE) -> GALENO ARGENTINA SA | F50: 27865.66 | G50: 187958.68 | H50: 13933.88 | I50: 17900.83
A51: 45603 | B51: 97785 | D51: 30522428163 | E51: =VLOOKUP(D51,Configuracion!$A$4:$C$590,2,FALSE) -> GALENO ARGENTINA SA | F51: 20326.16 | G51: 115380.64 | H51: 10160.7 | I51: 10988.63
A52: 45601 | B52: 97161 | D52: 30522428163 | E52: =VLOOKUP(D52,Configuracion!$A$4:$C$590,2,FALSE) -> GALENO ARGENTINA SA | F52: 259502.53 | G52: 1420272.3 | H52: 131991.26 | I52: 135264.03
A53: 45607 | B53: 79192 | D53: 30585412453 | E53: =VLOOKUP(D53,Configuracion!$A$4:$C$590,2,FALSE) -> OSDOP | F53: 184520 | H53: 94500
A54: 45609 | B54: 7547 | D54: 30608716390 | E54: =VLOOKUP(D54,Configuracion!$A$4:$C$590,2,FALSE) -> OSTEL | H54: 257.17
A55: 45610 | B55: 6210 | D55: 30712136754 | E55: =VLOOKUP(D55,Configuracion!$A$4:$C$590,2,FALSE) -> RSC SA | H55: 2255.21
A56: 45610 | B56: 6180 | D56: 30712136754 | E56: =VLOOKUP(D56,Configuracion!$A$4:$C$590,2,FALSE) -> RSC SA | H56: 2310.62
A57: 45611 | B57: 98384 | D57: 30500053522 | E57: =VLOOKUP(D57,Configuracion!$A$4:$C$590,2,FALSE) -> OBRA SOCIAL DE LA ACTIVIDAD DE SEGUROS, REASEGUROS, CAPITALIZACION Y AHORRO Y PRESTAMO PARA LA VIVIENDA | H57: =3305.79+2131.57 -> 5437.36
A58: 45617 | B58: 149239 | D58: 30500053522 | E58: =VLOOKUP(D58,Configuracion!$A$4:$C$590,2,FALSE) -> OBRA SOCIAL DE LA ACTIVIDAD DE SEGUROS, REASEGUROS, CAPITALIZACION Y AHORRO Y PRESTAMO PARA LA VIVIENDA | F58: 1319.01 | H58: 659.5
A59: 45625 | B59: 149622 | D59: 30500053522 | E59: =VLOOKUP(D59,Configuracion!$A$4:$C$590,2,FALSE) -> OBRA SOCIAL DE LA ACTIVIDAD DE SEGUROS, REASEGUROS, CAPITALIZACION Y AHORRO Y PRESTAMO PARA LA VIVIENDA | F59: 1233.88 | H59: 616.94
A60: 45625 | B60: 6360 | D60: 30587842358 | E60: =VLOOKUP(D60,Configuracion!$A$4:$C$590,2,FALSE) -> CLINICA BASILEA SA | H60: 1611.52
A61: 45615 | B61: 79138 | D61: 30604958640 | E61: =VLOOKUP(D61,Configuracion!$A$4:$C$590,2,FALSE) -> Aca Salud Coop P.S. Medico A.L | F61: 6550.32 | H61: 17760.87
A62: 45621 | B62: 145290 | D62: 30590354798 | E62: =VLOOKUP(D62,Configuracion!$A$4:$C$590,2,FALSE) -> ASOCIACION MUTUAL SANCOR SALUD | F62: 15760 | H62: 11220
A63: 45615 | B63: 144484 | D63: 30590354798 | E63: =VLOOKUP(D63,Configuracion!$A$4:$C$590,2,FALSE) -> ASOCIACION MUTUAL SANCOR SALUD | F63: 70548.88
A64: 45603 | B64: 142735 | D64: 30590354798 | E64: =VLOOKUP(D64,Configuracion!$A$4:$C$590,2,FALSE) -> ASOCIACION MUTUAL SANCOR SALUD | F64: 8460
A65: 45611 | B65: 144200 | D65: 30590354798 | E65: =VLOOKUP(D65,Configuracion!$A$4:$C$590,2,FALSE) -> ASOCIACION MUTUAL SANCOR SALUD | F65: 92821.2
A66: 45611 | B66: 5455 | D66: 30683032227 | E66: =VLOOKUP(D66,Configuracion!$A$4:$C$590,2,FALSE) -> OS UNION PERSONAL | F66: 0 | H66: 583335.15
A67: 45617 | B67: 109347 | D67: 30590412631 | E67: =VLOOKUP(D67,Configuracion!$A$4:$C$590,2,FALSE) -> OSMATA | F67: 5232.4
A68: 45618 | B68: 109467 | D68: 30590412631 | E68: =VLOOKUP(D68,Configuracion!$A$4:$C$590,2,FALSE) -> OSMATA | F68: 3132.23
A69: 45568 | B69: 338243 | D69: 30546771314 | E69: =VLOOKUP(D69,Configuracion!$A$4:$C$590,2,FALSE) -> MEDICUS SA | F69: 2388.83 | G69: 15675.37 | H69: 8397.52
A70: 45579 | B70: 339524 | D70: 30546771314 | E70: =VLOOKUP(D70,Configuracion!$A$4:$C$590,2,FALSE) -> MEDICUS SA | F70: 1024.79 | G70: 4304.13 | H70: 2305.79
A71: 45602 | B71: 290084 | D71: 30546771314 | E71: =VLOOKUP(D71,Configuracion!$A$4:$C$590,2,FALSE) -> MEDICUS SA | G71: 3067.28 | H71: 1643.18
D72: 0 | E72: =VLOOKUP(D72,Configuracion!$A$4:$C$590,2,FALSE) -> #N/A
D73: 0 | E73: =VLOOKUP(D73,Configuracion!$A$4:$C$590,2,FALSE) -> #N/A
D74: 0 | E74: =VLOOKUP(D74,Configuracion!$A$4:$C$590,2,FALSE) -> #N/A
D75: 0 | E75: =VLOOKUP(D75,Configuracion!$A$4:$C$590,2,FALSE) -> #N/A
D76: 0 | E76: =VLOOKUP(D76,Configuracion!$A$4:$C$590,2,FALSE) -> #N/A
D77: 0 | E77: =VLOOKUP(D77,Configuracion!$A$4:$C$590,2,FALSE) -> #N/A
D78: 0 | E78: =VLOOKUP(D78,Configuracion!$A$4:$C$590,2,FALSE) -> #N/A
D79: 0 | E79: =VLOOKUP(D79,Configuracion!$A$4:$C$590,2,FALSE) -> #N/A
D80: 0 | E80: =VLOOKUP(D80,Configuracion!$A$4:$C$590,2,FALSE) -> #N/A
D81: 0 | E81: =VLOOKUP(D81,Configuracion!$A$4:$C$590,2,FALSE) -> #N/A
D82: 0 | E82: =VLOOKUP(D82,Configuracion!$A$4:$C$590,2,FALSE) -> #N/A
D83: 0 | E83: =VLOOKUP(D83,Configuracion!$A$4:$C$590,2,FALSE) -> #N/A
... D85: 0 | E85: =VLOOKUP(D85,Configuracion!$A$4:$C$590,2,FALSE) -> #N/A
A86: TOTAL | F86: =SUM(F46:F85) -> 951266.52 | G86: =SUM(G46:G85) -> 3073311.7 | H86: =SUM(H46:H85) -> 1013686.8 | I86: =SUM(I46:I85) -> 290501.42
A90: LIBRO IVA VENTAS
A92: FACTURA A
A93: FECHA | B93: PTO VTA | C93: NRO FC | D93: CUIT | E93: RAZON SOCIAL | F93: NETO | G93: IVA | H93: NO GRAV. | I93: TOTAL
E94: =VLOOKUP(D94,Configuracion!$A$4:$C$590,2,FALSE) -> #N/A | G94: =F94*0.21 -> 0 | I94: =SUM(F94:H94) -> 0
E95: =VLOOKUP(D95,Configuracion!$A$4:$C$590,2,FALSE) -> #N/A | G95: =F95*0.21 -> 0 | I95: =SUM(F95:H95) -> 0
E96: =VLOOKUP(D96,Configuracion!$A$4:$C$590,2,FALSE) -> #N/A | G96: =F96*0.21 -> 0 | I96: =SUM(F96:H96) -> 0
E97: =VLOOKUP(D97,Configuracion!$A$4:$C$590,2,FALSE) -> #N/A | G97: =F97*0.21 -> 0 | I97: =SUM(F97:H97) -> 0
E98: =VLOOKUP(D98,Configuracion!$A$4:$C$590,2,FALSE) -> #N/A | G98: =F98*0.21 -> 0 | I98: =SUM(F98:H98) -> 0
E99: =VLOOKUP(D99,Configuracion!$A$4:$C$590,2,FALSE) -> #N/A | G99: =F99*0.21 -> 0 | I99: =SUM(F99:H99) -> 0
E100: =VLOOKUP(D100,Configuracion!$A$4:$C$590,2,FALSE) -> #N/A | G100: =F100*0.21 -> 0 | I100: =SUM(F100:H100) -> 0
E101: =VLOOKUP(D101,Configuracion!$A$4:$C$590,2,FALSE) -> #N/A | G101: =F101*0.21 -> 0 | I101: =SUM(F101:H101) -> 0
E102: =VLOOKUP(D102,Configuracion!$A$4:$C$590,2,FALSE) -> #N/A | G102: =F102*0.21 -> 0 | I102: =SUM(F102:H102) -> 0
A103: TOTAL | F103: =SUM(F94:F102) -> 0 | G103: =SUM(G94:G102) -> 0 | I103: =SUM(I94:I102) -> 0
A106: FACTURA B
A107: FECHA | B107: PTO VTA | C107: NRO FC | D107: CUIT | E107: RAZON SOCIAL | F107: NETO | G107: IVA | H107: TOTAL
E108: =VLOOKUP(D108,Configuracion!$A$4:$C$590,2,FALSE) -> #N/A | F108: =H108/1.21 -> 0 | G108: =F108*0.21 -> 0
E109: =VLOOKUP(D109,Configuracion!$A$4:$C$590,2,FALSE) -> #N/A | F109: =H109/1.21 -> 0 | G109: =F109*0.21 -> 0
E110: =VLOOKUP(D110,Configuracion!$A$4:$C$590,2,FALSE) -> #N/A | F110: =H110/1.21 -> 0 | G110: =F110*0.21 -> 0
E111: =VLOOKUP(D111,Configuracion!$A$4:$C$590,2,FALSE) -> #N/A | F111: =H111/1.21 -> 0 | G111: =F111*0.21 -> 0
E112: =VLOOKUP(D112,Configuracion!$A$4:$C$590,2,FALSE) -> #N/A | F112: =H112/1.21 -> 0 | G112: =F112*0.21 -> 0
A113: TOTAL | F113: =SUM(F108:F112) -> 0 | G113: =SUM(G108:G112) -> 0 | H113: =SUM(H108:H112) -> 0

Sheet Calculo IVA
B1: ORTOPEDIA GEMINIS
A2: Calculo Iva | D2: 45597
B4: VENTAS
B5: Neto | C5: Iva | D5: Total
A6: FAC. "A" | B6: =+'Nov 24'!F103 -> 0 | C6: =(B6*0.21) -> 0 | D6: =(B6+C6) -> 0
A7: FAC. "B" | B7: =+'Nov 24'!F113 -> 0 | C7: =(B7*0.21) -> 0 | D7: =(B7+C7) -> 0
A8: FAC. "A" - | B8: =+'Resumen Ventas 11'!B3+'Resumen Ventas 11'!B5+'Resumen Ventas 11'!B6+'Resumen Ventas 11'!B4 -> 53169173 | C8: =+B8*0.21 -> 11165526 | D8: =(B8+C8) -> 64334699
A9: FAC. "B" | B9: =+'Resumen Ventas 11'!B7+'Resumen Ventas 11'!B8 -> 12086889 | C9: =+'Resumen Ventas 11'!C7+'Resumen Ventas 11'!C8 -> 2538246.6 | D9: =(B9+C9) -> 14625135
B10: =SUM(B6:B9) -> 65256062 | C10: =SUM(C6:C9) -> 13703773 | D10: =SUM(D6:D9) -> 78959835
B13: COMPRAS
B14: Neto | C14: Iva | D14: Total
A15: Comprobantes Ticket FA-A | B15: =+'Nov 24'!F18 -> 496630.52 | C15: =+('Nov 24'!G18+'Nov 24'!H18+'Nov 24'!I18) -> 104292.41 | D15: =+'Nov 24'!O18 -> 650796.1
A16: Comprobantes AFIP - Recibidos | B16: 33676874 | C16: 7031917.2 | D16: 50481960
A17: Comprobantes AFIP - No Recibidos | B17: 180184.52 | C17: 36671.52 | D17: 1130925.2
A18: IVA S/ EXTRACTOS BANCARIOS | C18: 15379.32
B19: =SUM(B15:B18) -> 34353689 | C19: =SUM(C15:C18) -> 7188260.4 | D19: =SUM(D15:D18) -> 52263681
A22: RETENCIONES | B22: N° Cuit | C22: Importe | D22: Nro. Retencion | E22: Fecha
A23: AFIP - No están informadas las retenciones de IVA en el sistema de AFIP
C38: =+'Nov 24'!G86 -> 3073311.7
A40: PERCEPCIONES | B40: N° Cuit | C40: Importe | D40: Nro. Retencion | E40: Fecha
C44: =SUM(C41:C43) -> 0
A46: Total Deducciociones | C46: =+C44+C38 -> 3073311.7
C49: (Montos en Positivo)
A50: 1er Saldo Tecnico del Período | C50: =+C10-C19 -> 6515512.6
A52: Saldo Tecnico de período Anterior (a favor) | D52: (resta en el total)
A54: Saldo Neto Técnico | C54: =+C50-C52 -> 6515512.6
A58: Saldo L.D. del Período | C58: =+C44+C38 -> 3073311.7
A60: Saldo L.D. del Período Anterior
A62: Neto S.L.D | C62: =+C58+C60 -> 3073311.7
A65: I V A | C65: =+C54-C62 -> 3442200.9
A66: NOTA: Sin Tomar posibles Retenciones que se hayan hecho

Sheet afip
A1: Fecha | B1: Tipo | C1: Punto de Venta | D1: Número Desde | E1: Número Hasta | F1: Cód. Autorización | G1: Tipo Doc. Emisor | H1: Nro. Doc. Emisor | I1: Denominación Emisor | J1: Tipo Cambio | K1: Moneda | L1: Imp. Neto Gravado | M1: Imp. Neto No Gravado | N1: Imp. Op. Exentas | O1: Otros Tributos | P1: IVA | Q1: Imp. Total
A2: 01/09/2024 | B2: 1 - Factura A | C2: 2189 | D2: 75919 | F2: 74356447170423 | G2: CUIT | H2: 30548083156 | I2: COTO CENTRO INTEGRAL DE COMERCIALIZACION SOCIEDAD ANONIMA | J2: 1 | K2: $ | L2: 6462.61 | M2: 0 | N2: 0 | O2: 452.38 | P2: 1357.15 | Q2: 8272.14
A3: 02/09/2024 | B3: 1 - Factura A | C3: 500 | D3: 1611886 | F3: 74357098226128 | G3: CUIT | H3: 30654118767 | I3: SOLUCIONES MULTIMEDIA S A | J3: 1 | K3: $ | L3: 89554.36 | M3: 0 | N3: 0 | O3: 0 | P3: 18806.42 | Q3: 112850.92
A4: 02/09/2024 | B4: 1 - Factura A | C4: 1 | D4: 4517 | F4: 74361573927319 | G4: CUIT | H4: 30715141201 | I4: REHAB S.R.L. | J4: 1 | K4: $ | L4: 1216380 | M4: 0 | N4: 0 | O4: 0 | P4: 255439.8 | Q4: 1471819.8
A5: 02/09/2024 | B5: 1 - Factura A | C5: 5 | D5: 158399 | F5: 74363528156508 | G5: CUIT | H5: 30598960093 | I5: SILVESTRIN FABRIS SOC RESP LTDA | J5: 1 | K5: $ | L5: 2376294.2 | M5: 0 | N5: 0 | O5: 0 | P5: 337808.56 | Q5: 2832917.5
A6: 02/09/2024 | B6: 1 - Factura A | C6: 17 | D6: 2245 | F6: 74361547632750 | G6: CUIT | H6: 30711764921 | I6: RELIEF CENTER S.R.L. | J6: 1 | K6: $ | L6: 93973 | M6: 0 | N6: 0 | O6: 0 | P6: 19734.33 | Q6: 113707.33
A7: 02/09/2024 | B7: 1 - Factura A | C7: 3051 | D7: 801967 | F7: 74367703518446 | G7: CUIT | H7: 30678814357 | I7: TELEFONICA MOVILES ARGENTINA SOCIEDAD ANONIMA | J7: 1 | K7: $ | L7: 14407 | M7: 0 | N7: 0 | O7: 0 | P7: 3889.89 | Q7: 20245.61
A8: 02/09/2024 | B8: 1 - Factura A | C8: 2 | D8: 248 | F8: 74363494027429 | G8: CUIT | H8: 27144282383 | I8: SCHEJTER LILA ELISA | J8: 1 | K8: $ | L8: 160000 | M8: 0 | N8: 0 | O8: 0 | P8: 33600 | Q8: 193600
A9: 02/09/2024 | B9: 1 - Factura A | C9: 5 | D9: 102 | F9: 74367559790009 | G9: CUIT | H9: 27329449357 | I9: ANDREANI AGUSTINA SUSANA | J9: 1 | K9: $ | L9: 64100 | M9: 16400 | N9: 0 | O9: 0 | P9: 13461 | Q9: 93961
A10: 02/09/2024 | B10: 11 - Factura C | C10: 3 | D10: 874 | F10: 74363563144286 | G10: CUIT | H10: 20086277523 | I10: BOTINDARI JUAN CARLOS | J10: 1 | K10: $ | O10: 0 | Q10: 275500
A11: 02/09/2024 | B11: 11 - Factura C | C11: 2 | D11: 302 | F11: 74368278674869 | G11: CUIT | H11: 27265832178 | I11: BLASCO MARIA GUADALUPE | J11: 1 | K11: $ | O11: 0 | Q11: 250000
A12: 03/09/2024 | B12: 1 - Factura A | C12: 629 | D12: 5407463 | F12: 34353802937243 | G12: CUIT | H12: 30663498513 | I12: GRUPO CONCESIONARIO DEL OESTE SA | J12: 1 | K12: $ | L12: 2121.64 | M12: 0 | N12: 0 | O12: 0 | P12: 445.54 | Q12: 2673.26
A13: 03/09/2024 | B13: 1 - Factura A | C13: 711 | D13: 6097149 | F13: 34359489663246 | G13: CUIT | H13: 30677237119 | I13: AUTOPISTAS DEL SOL S A | J13: 1 | K13: $ | L13: 7715.05 | M13: 0 | N13: 231.45 | O13: 0 | P13: 1620.16 | Q13: 9952.41
A14: 03/09/2024 | B14: 1 - Factura A | C14: 2635 | D14: 1369 | F14: 34359844249451 | G14: CUIT | H14: 33699685459 | I14: CORREO ANDREANI SA | J14: 1 | K14: $ | L14: 12449.6 | M14: 0 | N14: 0 | O14: 0 | P14: 2614.42 | Q14: 15064.02
A15: 03/09/2024 | B15: 1 - Factura A | C15: 2 | D15: 216 | F15: 74362687536018 | G15: CUIT | H15: 30605344352 | I15: CONSORCIO BARTOLOME MITRE 2466 | J15: 1 | K15: $ | L15: 834000 | M15: 0 | N15: 0 | O15: 0 | P15: 175140 | Q15: 1009140
A16: 04/09/2024 | B16: 1 - Factura A | C16: 17 | D16: 2255 | F16: 74361803741207 | G16: CUIT | H16: 30711764921 | I16: RELIEF CENTER S.R.L. | J16: 1 | K16: $ | L16: 527580 | M16: 0 | N16: 0 | O16: 0 | P16: 110791.8 | Q16: 638371.8
A17: 04/09/2024 | B17: 1 - Factura A | C17: 2 | D17: 50685 | F17: 74365825946417 | G17: CUIT | H17: 30595553535 | I17: RUBRICOM SOCIEDAD ANONIMA | J17: 1 | K17: $ | L17: 4793.39 | M17: 0 | N17: 0 | O17: 0 | P17: 1006.61 | Q17: 5800
A18: 04/09/2024 | B18: 1 - Factura A | C18: 120 | D18: 4949 | F18: 74365804898856 | G18: CUIT | H18: 30587197215 | I18: PANATEL SOCIEDAD ANONIMA | J18: 1 | K18: $ | L18: 68595.04 | M18: 0 | N18: 0 | O18: 0 | P18: 14404.96 | Q18: 86429.75
A19: 04/09/2024 | B19: 1 - Factura A | C19: 7 | D19: 3241 | F19: 74364799883128 | G19: CUIT | H19: 20284183534 | I19: FURLANETTO MARTIN | J19: 1 | K19: $ | L19: 4545.5 | M19: 0 | N19: 0 | O19: 0 | P19: 954.56 | Q19: 5500.06
A20: 04/09/2024 | B20: 1 - Factura A | C20: 120 | D20: 4948 | F20: 74365800262038 | G20: CUIT | H20: 30587197215 | I20: PANATEL SOCIEDAD ANONIMA | J20: 1 | K20: $ | L20: 68595.04 | M20: 0 | N20: 0 | O20: 0 | P20: 14404.96 | Q20: 86429.75
A21: 04/09/2024 | B21: 1 - Factura A | C21: 401 | D21: 66 | F21: 74364797895464 | G21: CUIT | H21: 30716234114 | I21: UZUMAKI S.A.S. | J21: 1305 | K21: USD | L21: 129.3 | M21: 0 | N21: 0 | O21: 0 | P21: 27.15 | Q21: 156.45
A22: 05/09/2024 | B22: 1 - Factura A | C22: 2 | D22: 760 | F22: 74369961703669 | G22: CUIT | H22: 20272865869 | I22: DI FEO MARTIN EZEQUIEL | J22: 1 | K22: $ | L22: 84450 | M22: 0 | N22: 0 | O22: 0 | P22: 17734.5 | Q22: 102184.5
A23: 05/09/2024 | B23: 1 - Factura A | C23: 5 | D23: 5331 | F23: 74363959099503 | G23: CUIT | H23: 30715833243 | I23: BIODINAMICA ASISTENCIA S.R.L. | J23: 1 | K23: $ | L23: 22238.59 | M23: 0 | N23: 0 | O23: 0 | P23: 4670.1 | Q23: 26908.69
... A35: 09/09/2024 | B35: 3 - Nota de Crédito A | C35: 5 | D35: 192 | F35: 74376416376753 | G35: CUIT | H35: 30712187316 | I35: ITALOMED PRODUCTOS SRL | J35: 1 | K35: $ | L35: 293619.94 | M35: 0 | N35: 0 | O35: 0 | P35: 61660.19 | Q35: 355280.13
A36: 09/09/2024 | B36: 11 - Factura C | C36: 1 | D36: 148 | F36: 74370408397319 | G36: CUIT | H36: 27338342840 | I36: CANCINO PAMELA RITA | J36: 1 | K36: $ | O36: 0 | Q36: 276800
A37: 10/09/2024 | B37: 1 - Factura A | C37: 2 | D37: 8403 | F37: 74372567359059 | G37: CUIT | H37: 27363810182 | I37: HECKER LAURA NOEMI | J37: 1 | K37: $ | L37: 3635.54 | M37: 0 | N37: 0 | O37: 0 | P37: 763.46 | Q37: 4399
A38: 10/09/2024 | B38: 1 - Factura A | C38: 5 | D38: 31858 | F38: 74370525870493 | G38: CUIT | H38: 30710804830 | I38: ZG MULTITEC SRL | J38: 1 | K38: $ | L38: 29410.86 | M38: 0 | N38: 0 | O38: 0 | P38: 3088.14 | Q38: 32499
A39: 10/09/2024 | B39: 1 - Factura A | C39: 8 | D39: 1684 | F39: 74371529941038 | G39: CUIT | H39: 30708973501 | I39: ASIAL S.R.L. | J39: 1 | K39: $ | L39: 740255 | M39: 0 | N39: 0 | O39: 0 | P39: 155453.55 | Q39: 895708.55
A40: 10/09/2024 | B40: 1 - Factura A | C40: 3 | D40: 4250 | F40: 74378552751950 | G40: CUIT | H40: 20184052858 | I40: ABOUD PABLO DANIEL | J40: 1 | K40: $ | L40: 16859.48 | M40: 0 | N40: 0 | O40: 0 | P40: 3540.49 | Q40: 20399.95
A41: 10/09/2024 | B41: 11 - Factura C | C41: 3 | D41: 986 | F41: 74379527477577 | G41: CUIT | H41: 20216451679 | I41: VAZQUEZ RICARDO OSCAR | J41: 1 | K41: $ | O41: 0 | Q41: 86000
A42: 11/09/2024 | B42: 1 - Factura A | C42: 1 | D42: 2468 | F42: 74379681409704 | G42: CUIT | H42: 30717179389 | I42: NICOLAS TOBIAS SEQUEIRA Y MARIA GABRIELA RATTNER SOCIEDAD DE LA SECCION IV LGS | J42: 1 | K42: $ | L42: 82644.62 | M42: 0 | N42: 0 | O42: 0 | P42: 17355.37 | Q42: 99999.99
A43: 11/09/2024 | B43: 1 - Factura A | C43: 5 | D43: 3378 | F43: 74379704726153 | G43: CUIT | H43: 30717179389 | I43: NICOLAS TOBIAS SEQUEIRA Y MARIA GABRIELA RATTNER SOCIEDAD DE LA SECCION IV LGS | J43: 1 | K43: $ | L43: 82644.63 | M43: 0 | N43: 0 | O43: 0 | P43: 17355.37 | Q43: 100000
A44: 11/09/2024 | B44: 1 - Factura A | C44: 3 | D44: 7676 | F44: 74379686794320 | G44: CUIT | H44: 33708218699 | I44: MANGGINI PABLO Y MANGGINI ULISES SOC. DE HECHO. | J44: 1 | K44: $ | L44: 15000 | M44: 0 | N44: 0 | O44: 0 | P44: 3150 | Q44: 18150
A45: 11/09/2024 | B45: 11 - Factura C | C45: 1 | D45: 9 | F45: 74373677716509 | G45: CUIT | H45: 20464199633 | I45: OVIEDO JIMENEZ TIZIANO LIONEL | J45: 1 | K45: $ | O45: 0 | Q45: 499950
A46: 12/09/2024 | B46: 1 - Factura A | C46: 2 | D46: 778 | F46: 74379814460759 | G46: CUIT | H46: 20272865869 | I46: DI FEO MARTIN EZEQUIEL | J46: 1 | K46: $ | L46: 128100 | M46: 0 | N46: 0 | O46: 0 | P46: 26901 | Q46: 155001
A47: 12/09/2024 | B47: 1 - Factura A | C47: 4 | D47: 38394 | F47: 74379814609856 | G47: CUIT | H47: 20289111329 | I47: LEDESMA EMILIANO RUBEN | J47: 1 | K47: $ | L47: 585730.8 | M47: 0 | N47: 0 | O47: 0 | P47: 123003.47 | Q47: 708734.27
A48: 12/09/2024 | B48: 1 - Factura A | C48: 5 | D48: 1915 | F48: 74376761404173 | G48: CUIT | H48: 30712187316 | I48: ITALOMED PRODUCTOS SRL | J48: 1 | K48: $ | L48: 254033.05 | M48: 0 | N48: 0 | O48: 0 | P48: 53346.94 | Q48: 307379.99
A49: 12/09/2024 | B49: 1 - Factura A | C49: 5 | D49: 1916 | F49: 74376766353942 | G49: CUIT | H49: 30712187316 | I49: ITALOMED PRODUCTOS SRL | J49: 1 | K49: $ | L49: 472751.65 | M49: 0 | N49: 0 | O49: 0 | P49: 99277.85 | Q49: 572029.5
A50: 13/09/2024 | B50: 1 - Factura A | C50: 1 | D50: 4620 | F50: 74371942773283 | G50: CUIT | H50: 30715141201 | I50: REHAB S.R.L. | J50: 1 | K50: $ | L50: 29295 | M50: 0 | N50: 0 | O50: 0 | P50: 6151.95 | Q50: 35446.95
A51: 13/09/2024 | B51: 1 - Factura A | C51: 5 | D51: 1920 | F51: 74376932362480 | G51: CUIT | H51: 30712187316 | I51: ITALOMED PRODUCTOS SRL | J51: 1 | K51: $ | L51: 34718.6 | M51: 0 | N51: 0 | O51: 0 | P51: 7290.91 | Q51: 42009.51
A52: 13/09/2024 | B52: 1 - Factura A | C52: 2 | D52: 783 | F52: 74379875047216 | G52: CUIT | H52: 20272865869 | I52: DI FEO MARTIN EZEQUIEL | J52: 1 | K52: $ | L52: 9950 | M52: 0 | N52: 0 | O52: 0 | P52: 2089.5 | Q52: 12039.5
A53: 13/09/2024 | B53: 1 - Factura A | C53: 1 | D53: 4613 | F53: 74371932408480 | G53: CUIT | H53: 30715141201 | I53: REHAB S.R.L. | J53: 1 | K53: $ | L53: 3648847.5 | M53: 0 | N53: 0 | O53: 0 | P53: 766257.98 | Q53: 4415105.5
A54: 13/09/2024 | B54: 1 - Factura A | C54: 503 | D54: 1469491 | F54: 74372992481197 | G54: CUIT | H54: 30639935872 | I54: CAMINOS DEL RIO URUGUAY S A DE CONSTRUCCIONES Y CONCESIONES VIALES | J54: 1 | K54: $ | L54: 2934.75 | M54: 0 | N54: 0 | O54: 0 | P54: 616.3 | Q54: 3697.79
A55: 13/09/2024 | B55: 1 - Factura A | C55: 2 | D55: 4940 | F55: 74375873241825 | G55: CUIT | H55: 27117233745 | I55: MANZINI MARTA GRACIELA | J55: 1 | K55: $ | L55: 585519 | M55: 0 | N55: 0 | O55: 0 | P55: 122958.99 | Q55: 708477.99
A56: 13/09/2024 | B56: 1 - Factura A | C56: 3 | D56: 170 | F56: 74383333330765 | G56: CUIT | H56: 20334976433 | I56: NARDOMARINO EZEQUIEL EDUARDO | J56: 1 | K56: $ | L56: 188330 | M56: 0 | N56: 0 | O56: 0 | P56: 39549.3 | Q56: 227879.3
A57: 13/09/2024 | B57: 1 - Factura A | C57: 3 | D57: 171 | F57: 74383357920263 | G57: CUIT | H57: 20334976433 | I57: NARDOMARINO EZEQUIEL EDUARDO | J57: 1 | K57: $ | L57: 153000 | M57: 0 | N57: 0 | O57: 0 | P57: 32130 | Q57: 185130
... A60: 15/09/2024 | B60: 1 - Factura A | C60: 113 | D60: 3802250 | F60: 74380483594334 | G60: CUIT | H60: 30577207190 | I60: COORDINACION ECOLOGICA AREA METROPOLITANA SOCIEDAD DEL ESTADO | J60: 1 | K60: $ | L60: 2975.21 | M60: 0 | N60: 0 | O60: 0 | P60: 624.79 | Q60: 3689.26
A61: 15/09/2024 | B61: 11 - Factura C | C61: 5 | D61: 168 | F61: 74379160231271 | G61: CUIT | H61: 27062343449 | I61: FERREIRA LILIANA INES | J61: 1 | K61: $ | O61: 0 | Q61: 260000
A62: 15/09/2024 | B62: 11 - Factura C | C62: 5 | D62: 169 | F62: 74379160368355 | G62: CUIT | H62: 27062343449 | I62: FERREIRA LILIANA INES | J62: 1 | K62: $ | O62: 0 | Q62: 35000
A63: 16/09/2024 | B63: 1 - Factura A | C63: 5015 | D63: 644558 | F63: 74384236665042 | G63: CUIT | H63: 30574876474 | I63: AUTOPISTAS URBANAS S A | J63: 1 | K63: $ | L63: 12702.19 | M63: 0 | N63: 0 | O63: 0 | P63: 2667.45 | Q63: 17020.92
A64: 16/09/2024 | B64: 1 - Factura A | C64: 6 | D64: 40318 | F64: 74389250556652 | G64: CUIT | H64: 30709459399 | I64: LA JUNIOR S.R.L. | J64: 1 | K64: $ | L64: 11807.44 | M64: 0 | N64: 0 | O64: 0 | P64: 2479.56 | Q64: 14287
A65: 16/09/2024 | B65: 1 - Factura A | C65: 2002 | D65: 72231 | F65: 74385199526054 | G65: CUIT | H65: 30716425165 | I65: MERCADO TOTAL SAS | J65: 1 | K65: $ | L65: 13842.98 | M65: 0 | N65: 0 | O65: 0 | P65: 2907.03 | Q65: 16750
A66: 16/09/2024 | B66: 1 - Factura A | C66: 2 | D66: 249 | F66: 74383195124025 | G66: CUIT | H66: 27144282383 | I66: SCHEJTER LILA ELISA | J66: 1 | K66: $ | L66: 320000 | M66: 0 | N66: 0 | O66: 0 | P66: 67200 | Q66: 387200
A67: 17/09/2024 | B67: 1 - Factura A | C67: 7 | D67: 524 | F67: 74380369713013 | G67: CUIT | H67: 30715630040 | I67: PISOS BODEN S.A. | J67: 1 | K67: $ | L67: 3517469.4 | M67: 0 | N67: 0 | O67: 0 | P67: 738668.58 | Q67: 4256138
A68: 17/09/2024 | B68: 1 - Factura A | C68: 711 | D68: 6155254 | F68: 34379169789485 | G68: CUIT | H68: 30677237119 | I68: AUTOPISTAS DEL SOL S A | J68: 1 | K68: $ | L68: 5515.3 | M68: 0 | N68: 165.46 | O68: 0 | P68: 1158.23 | Q68: 7114.76
A69: 17/09/2024 | B69: 1 - Factura A | C69: 629 | D69: 5447412 | F69: 34373728816629 | G69: CUIT | H69: 30663498513 | I69: GRUPO CONCESIONARIO DEL OESTE SA | J69: 1 | K69: $ | L69: 3440.74 | M69: 0 | N69: 0 | O69: 0 | P69: 722.56 | Q69: 4335.34
A70: 17/09/2024 | B70: 1 - Factura A | C70: 4264 | D70: 4388001 | F70: 74388498673820 | G70: CUIT | H70: 30639453738 | I70: TELECOM ARGENTINA SOCIEDAD ANONIMA | J70: 1 | K70: $ | L70: 24142.14 | M70: 0 | N70: 0 | O70: 0 | P70: 5069.85 | Q70: 30901.93
A71: 17/09/2024 | B71: 11 - Factura C | C71: 1 | D71: 248 | F71: 74395443070489 | G71: CUIT | H71: 27217606255 | I71: SAPUNA MIRIAN KARINA | J71: 1 | K71: $ | O71: 0 | Q71: 50223.03
A72: 17/09/2024 | B72: 11 - Factura C | C72: 1 | D72: 247 | F72: 74395442076201 | G72: CUIT | H72: 27217606255 | I72: SAPUNA MIRIAN KARINA | J72: 1 | K72: $ | O72: 0 | Q72: 56703.42
A73: 18/09/2024 | B73: 1 - Factura A | C73: 2 | D73: 4942 | F73: 74385474906338 | G73: CUIT | H73: 27117233745 | I73: MANZINI MARTA GRACIELA | J73: 1 | K73: $ | L73: 585519 | M73: 0 | N73: 0 | O73: 0 | P73: 122958.99 | Q73: 708477.99
A74: 18/09/2024 | B74: 11 - Factura C | C74: 1 | D74: 70 | F74: 74384470115890 | G74: CUIT | H74: 23281233084 | I74: DRUETTA ANDREA MARIEL | J74: 1 | K74: $ | O74: 0 | Q74: 215000
A75: 18/09/2024 | B75: 11 - Factura C | C75: 1 | D75: 71 | F75: 74384470845746 | G75: CUIT | H75: 23281233084 | I75: DRUETTA ANDREA MARIEL | J75: 1 | K75: $ | O75: 0 | Q75: 215000
A76: 18/09/2024 | B76: 11 - Factura C | C76: 1 | D76: 249 | F76: 74395443331023 | G76: CUIT | H76: 27217606255 | I76: SAPUNA MIRIAN KARINA | J76: 1 | K76: $ | O76: 0 | Q76: 55083.32
A77: 18/09/2024 | B77: 11 - Factura C | C77: 1 | D77: 250 | F77: 74395444517785 | G77: CUIT | H77: 27217606255 | I77: SAPUNA MIRIAN KARINA | J77: 1 | K77: $ | O77: 0 | Q77: 148916.68
A78: 19/09/2024 | B78: 1 - Factura A | C78: 2 | D78: 796 | F78: 74389604255613 | G78: CUIT | H78: 20272865869 | I78: DI FEO MARTIN EZEQUIEL | J78: 1 | K78: $ | L78: 253100 | M78: 0 | N78: 0 | O78: 0 | P78: 53151 | Q78: 306251
A79: 19/09/2024 | B79: 1 - Factura A | C79: 7 | D79: 6066 | F79: 74386569455318 | G79: CUIT | H79: 20131067446 | I79: TRIVEÑO ROMA RAMON | J79: 1 | K79: $ | L79: 278865.6 | M79: 0 | N79: 0 | O79: 0 | P79: 58561.78 | Q79: 337427.38
A80: 19/09/2024 | B80: 1 - Factura A | C80: 11 | D80: 91964 | F80: 74384582154669 | G80: CUIT | H80: 30526582884 | I80: EXPRESO MAR DEL PLATA SOCIEDAD ANONIMA | J80: 1 | K80: $ | L80: 4462.81 | M80: 0 | N80: 0 | O80: 0 | P80: 937.19 | Q80: 5400
A81: 19/09/2024 | B81: 11 - Factura C | C81: 3 | D81: 991 | F81: 74389582435775 | G81: CUIT | H81: 20216451679 | I81: VAZQUEZ RICARDO OSCAR | J81: 1 | K81: $ | O81: 0 | Q81: 160000
A82: 19/09/2024 | B82: 11 - Factura C | C82: 1 | D82: 251 | F82: 74395444759490 | G82: CUIT | H82: 27217606255 | I82: SAPUNA MIRIAN KARINA | J82: 1 | K82: $ | O82: 0 | Q82: 96357.85
A83: 19/09/2024 | B83: 11 - Factura C | C83: 1 | D83: 252 | F83: 74395445013622 | G83: CUIT | H83: 27217606255 | I83: SAPUNA MIRIAN KARINA | J83: 1 | K83: $ | O83: 0 | Q83: 105117.66
A84: 20/09/2024 | B84: 1 - Factura A | C84: 2171 | D84: 6478 | F84: 74386729481785 | G84: CUIT | H84: 30548083156 | I84: COTO CENTRO INTEGRAL DE COMERCIALIZACION SOCIEDAD ANONIMA | J84: 1 | K84: $ | L84: 4109.47 | M84: 0 | N84: 0 | O84: 328.75 | P84: 862.99 | Q84: 5301.21
A85: 20/09/2024 | B85: 1 - Factura A | C85: 17 | D85: 2312 | F85: 74381728297239 | G85: CUIT | H85: 30711764921 | I85: RELIEF CENTER S.R.L. | J85: 1 | K85: $ | L85: 21394 | M85: 0 | N85: 0 | O85: 0 | P85: 4492.74 | Q85: 25886.74
A86: 20/09/2024 | B86: 1 - Factura A | C86: 5 | D86: 3877 | F86: 74380716025151 | G86: CUIT | H86: 20348485580 | I86: NOLASCO ALAN MANUEL | J86: 1 | K86: $ | L86: 29099.82 | M86: 0 | N86: 0 | O86: 0 | P86: 6110.96 | Q86: 35210.78
A87: 20/09/2024 | B87: 1 - Factura A | C87: 5 | D87: 1937 | F87: 74386708279049 | G87: CUIT | H87: 30712187316 | I87: ITALOMED PRODUCTOS SRL | J87: 1 | K87: $ | L87: 213988.29 | M87: 0 | N87: 0 | O87: 0 | P87: 44937.54 | Q87: 258925.83
A88: 20/09/2024 | B88: 1 - Factura A | C88: 2 | D88: 250 | F88: 74383655585682 | G88: CUIT | H88: 27144282383 | I88: SCHEJTER LILA ELISA | J88: 1 | K88: $ | L88: 320000 | M88: 0 | N88: 0 | O88: 0 | P88: 67200 | Q88: 387200
A89: 20/09/2024 | B89: 1 - Factura A | C89: 4 | D89: 136 | F89: 74386719534162 | G89: CUIT | H89: 20317488476 | I89: VILLALBA MIGUEL ANGEL | J89: 1 | K89: $ | L89: 1870000 | M89: 0 | N89: 0 | O89: 0 | P89: 392700 | Q89: 2262700
A90: 20/09/2024 | B90: 11 - Factura C | C90: 1 | D90: 253 | F90: 74395446386733 | G90: CUIT | H90: 27217606255 | I90: SAPUNA MIRIAN KARINA | J90: 1 | K90: $ | O90: 0 | Q90: 87598.05
A91: 21/09/2024 | B91: 11 - Factura C | C91: 1 | D91: 14 | F91: 74395449158811 | G91: CUIT | H91: 27443612705 | I91: MIGOYA MORIONDO MARIA INES | J91: 1 | K91: $ | O91: 0 | Q91: 600000
A92: 23/09/2024 | B92: 1 - Factura A | C92: 5 | D92: 3128526 | F92: 74395012609092 | G92: CUIT | H92: 30702652975 | I92: NSS SA | J92: 1 | K92: $ | L92: 28530.17 | M92: 0 | N92: 0 | O92: 0 | P92: 5991.34 | Q92: 35948.01
A93: 23/09/2024 | B93: 1 - Factura A | C93: 5015 | D93: 648091 | F93: 74394947432580 | G93: CUIT | H93: 30574876474 | I93: AUTOPISTAS URBANAS S A | J93: 1 | K93: $ | L93: 17107.75 | M93: 0 | N93: 0 | O93: 0 | P93: 3592.62 | Q93: 22924.37
A94: 23/09/2024 | B94: 1 - Factura A | C94: 700 | D94: 1936359 | F94: 74392989880786 | G94: CUIT | H94: 30715804812 | I94: CORREDORES VIALES SOCIEDAD ANONIMA | J94: 1 | K94: $ | L94: 6246.93 | M94: 0 | N94: 0 | O94: 0 | P94: 1311.86 | Q94: 7871.14
A95: 23/09/2024 | B95: 1 - Factura A | C95: 700 | D95: 1936360 | F95: 74392989880804 | G95: CUIT | H95: 30715804812 | I95: CORREDORES VIALES SOCIEDAD ANONIMA | J95: 1 | K95: $ | L95: 728.62 | M95: 0 | N95: 0 | O95: 0 | P95: 153.01 | Q95: 881.63
A96: 23/09/2024 | B96: 1 - Factura A | C96: 6 | D96: 85435 | F96: 74394006853805 | G96: CUIT | H96: 30711553564 | I96: SALUDTEX SA | J96: 1 | K96: $ | L96: 999126 | M96: 0 | N96: 0 | O96: 0 | P96: 209816.46 | Q96: 1208942.5
A97: 23/09/2024 | B97: 1 - Factura A | C97: 6 | D97: 54307 | F97: 74398009565100 | G97: CUIT | H97: 30710177658 | I97: TARGET MEDICAL S.A. | J97: 1 | K97: $ | L97: 122080.32 | M97: 0 | N97: 0 | O97: 0 | P97: 25636.86 | Q97: 147717.18
A98: 24/09/2024 | B98: 1 - Factura A | C98: 1055 | D98: 854 | F98: 74391072835510 | G98: CUIT | H98: 30685849751 | I98: DIA ARGENTINA S A | J98: 1 | K98: $ | L98: 6165.28 | M98: 0 | N98: 0 | O98: 0 | P98: 1294.71 | Q98: 7768.25
A99: 24/09/2024 | B99: 1 - Factura A | C99: 2 | D99: 25 | F99: 74395124728024 | G99: CUIT | H99: 27243660535 | I99: BARD MARISA SILVIA | J99: 1 | K99: $ | L99: 360000 | M99: 0 | N99: 0 | O99: 0 | P99: 75600 | Q99: 435600
A100: 25/09/2024 | B100: 1 - Factura A | C100: 6 | D100: 54346 | F100: 74398248406433 | G100: CUIT | H100: 30710177658 | I100: TARGET MEDICAL S.A. | J100: 1 | K100: $ | L100: 356854.44 | M100: 0 | N100: 0 | O100: 0 | P100: 74939.44 | Q100: 431793.88
A101: 25/09/2024 | B101: 1 - Factura A | C101: 4 | D101: 71892 | F101: 74399186438923 | G101: CUIT | H101: 33709738459 | I101: ORTOPEDICOS ALFOLATEX SA | J101: 1 | K101: $ | L101: 655324.52 | M101: 0 | N101: 0 | O101: 0 | P101: 137618.15 | Q101: 792942.67
A102: 25/09/2024 | B102: 1 - Factura A | C102: 4 | D102: 137 | F102: 74396233311030 | G102: CUIT | H102: 20317488476 | I102: VILLALBA MIGUEL ANGEL | J102: 1 | K102: $ | L102: 105000 | M102: 0 | N102: 0 | O102: 0 | P102: 22050 | Q102: 127050
A103: 26/09/2024 | B103: 1 - Factura A | C103: 6 | D103: 54365 | F103: 74398371535029 | G103: CUIT | H103: 30710177658 | I103: TARGET MEDICAL S.A. | J103: 1 | K103: $ | L103: 682125 | M103: 0 | N103: 0 | O103: 0 | P103: 143246.25 | Q103: 825371.25
... A112: 27/09/2024 | B112: 1 - Factura A | C112: 2 | D112: 819 | F112: 74399429730188 | G112: CUIT | H112: 20272865869 | I112: DI FEO MARTIN EZEQUIEL | J112: 1 | K112: $ | L112: 105000 | M112: 0 | N112: 0 | O112: 0 | P112: 22050 | Q112: 127050
A113: 27/09/2024 | B113: 11 - Factura C | C113: 3 | D113: 995 | F113: 74399453320296 | G113: CUIT | H113: 20216451679 | I113: VAZQUEZ RICARDO OSCAR | J113: 1 | K113: $ | O113: 0 | Q113: 160000
A114: 28/09/2024 | B114: 1 - Factura A | C114: 2189 | D114: 77373 | F114: 74396609730132 | G114: CUIT | H114: 30548083156 | I114: COTO CENTRO INTEGRAL DE COMERCIALIZACION SOCIEDAD ANONIMA | J114: 1 | K114: $ | L114: 3905.09 | M114: 0 | N114: 0 | O114: 312.4 | P114: 820.07 | Q114: 5037.56
A115: 28/09/2024 | B115: 1 - Factura A | C115: 2 | D115: 336 | F115: 74409928953266 | G115: CUIT | H115: 27251962559 | I115: CHIARA FLORENCIA | J115: 1 | K115: $ | L115: 42396.71 | M115: 0 | N115: 0 | O115: 0 | P115: 8903.31 | Q115: 51300.01
A116: 29/09/2024 | B116: 1 - Factura A | C116: 25 | D116: 2868796 | F116: 74404735015283 | G116: CUIT | H116: 30703088534 | I116: MERCADOLIBRE S.R.L. | J116: 1 | K116: $ | L116: 37574.04 | M116: 0 | N116: 0 | O116: 3005.92 | P116: 7890.55 | Q116: 48470.51
A117: 30/09/2024 | B117: 1 - Factura A | C117: 6 | D117: 17452146 | F117: 74397511039418 | G117: CUIT | H117: 30620177497 | I117: POSNET SOCIEDAD DE RESPONSABILIDAD LIMITADA | J117: 1 | K117: $ | L117: 0 | M117: 0 | N117: 0 | O117: 0 | P117: 0 | Q117: 0
A118: 30/09/2024 | B118: 1 - Factura A | C118: 6 | D118: 17599524 | F118: 74397542581741 | G118: CUIT | H118: 30620177497 | I118: POSNET SOCIEDAD DE RESPONSABILIDAD LIMITADA | J118: 1 | K118: $ | L118: 26164.14 | M118: 0 | N118: 0 | O118: 0 | P118: 5494.47 | Q118: 33751.74
A119: 30/09/2024 | B119: 1 - Factura A | C119: 5015 | D119: 650706 | F119: 74404997363928 | G119: CUIT | H119: 30574876474 | I119: AUTOPISTAS URBANAS S A | J119: 1 | K119: $ | L119: 24879.27 | M119: 0 | N119: 0 | O119: 0 | P119: 5224.63 | Q119: 33338.2
A120: 30/09/2024 | B120: 1 - Factura A | C120: 20 | D120: 197792 | F120: 74402907225580 | G120: CUIT | H120: 30696850972 | I120: C.P.S. COMUNICACIONES S.A. | J120: 1 | K120: $ | L120: 19732.58 | M120: 0 | N120: 0 | O120: 0 | P120: 5327.8 | Q120: 26047.02
A121: 30/09/2024 | B121: 1 - Factura A | C121: 1 | D121: 591606 | F121: 74409955268089 | G121: CUIT | H121: 33716307749 | I121: VERISURE ARGENTINA MONITOREO DE ALARMAS SA | J121: 1 | K121: $ | L121: 318999 | M121: 0 | N121: 0 | O121: 0 | P121: 66989.79 | Q121: 401938.74
...

Sheet Hoja3
A1: Comprobante no recibido
A4: Fecha | B4: Comprobante | C4: Nombre | D4: Cond. IVA | E4: CUIT o Doc. | F4: Gravado | G4: No Gravado
A5: 02/09/2024 | B5: FA-C 0003-00000874 | C5: BOTINDARI JUAN CARLOS | D5: Responsable Monotributo | E5: 20086277523 | F5: 0 | G5: 275500
A6: 02/09/2024 | B6: 874 | C6: BOTINDARI JUAN CARLOS | E6: 20086277523
A7: 19/09/2024 | B7: FA-A 0007-00006066 | C7: Triveño Roma, Ramon | D7: IVA Responsable Inscripto | E7: 20131067446 | F7: 278865.6 | G7: 0
A8: 19/09/2024 | B8: 6066 | C8: TRIVEÑO ROMA RAMON | E8: 20131067446 | F8: 278865.6 | G8: 0
A9: 10/09/2024 | B9: FA-A 0003-00004250 | C9: Aboud, Pablo Daniel | D9: IVA Responsable Inscripto | E9: 20184052858 | F9: 16859.46 | G9: 0
A10: 30/09/2024 | B10: FA-A 0003-00004276 | C10: Aboud, Pablo Daniel | D10: IVA Responsable Inscripto | E10: 20184052858 | F10: 71074.3 | G10: 0
A11: 10/09/2024 | B11: 4250 | C11: ABOUD PABLO DANIEL | E11: 20184052858 | F11: 16859.48 | G11: 0
A12: 30/09/2024 | B12: 4276 | C12: ABOUD PABLO DANIEL | E12: 20184052858 | F12: 71074.33 | G12: 0
A13: 30/09/2024 | B13: 804 | C13: PAIS HECTOR GUILLERMO | E13: 20214946867 | F13: 37189.24 | G13: 0
A14: 10/09/2024 | B14: FA-C 0003-00000986 | C14: Vazquez, Ricardo Oscar | D14: Responsable Monotributo | E14: 20216451679 | F14: 0 | G14: 86000
A15: 27/09/2024 | B15: FA-C 0003-00000995 | C15: Vazquez, Ricardo Oscar | D15: Responsable Monotributo | E15: 20216451679 | F15: 0 | G15: 160000
A16: 10/09/2024 | B16: 986 | C16: VAZQUEZ RICARDO OSCAR | E16: 20216451679
A17: 19/09/2024 | B17: 991 | C17: VAZQUEZ RICARDO OSCAR | E17: 20216451679
A18: 27/09/2024 | B18: 995 | C18: VAZQUEZ RICARDO OSCAR | E18: 20216451679
A19: 12/09/2024 | B19: FA-A 0002-00000778 | C19: Di Feo, Martin Ezequiel | D19: IVA Responsable Inscripto | E19: 20272865869 | F19: 128100 | G19: 0
A20: 13/09/2024 | B20: FA-A 0002-00000783 | C20: Di Feo, Martin Ezequiel | D20: IVA Responsable Inscripto | E20: 20272865869 | F20: 9950 | G20: 0
A21: 19/09/2024 | B21: FA-A 0002-00000796 | C21: Di Feo, Martin Ezequiel | D21: IVA Responsable Inscripto | E21: 20272865869 | F21: 253100 | G21: 0
A22: 27/09/2024 | B22: FA-A 0002-00000816 | C22: Di Feo, Martin Ezequiel | D22: IVA Responsable Inscripto | E22: 20272865869 | F22: 9800 | G22: 0
A23: 27/09/2024 | B23: FA-A 0002-00000819 | C23: Di Feo, Martin Ezequiel | D23: IVA Responsable Inscripto | E23: 20272865869 | F23: 105000 | G23: 0
A24: 30/09/2024 | B24: FA-A 0002-00000814 | C24: Di Feo, Martin Ezequiel | D24: IVA Responsable Inscripto | E24: 20272865869 | F24: 149150 | G24: 0
A25: 05/09/2024 | B25: 760 | C25: DI FEO MARTIN EZEQUIEL | E25: 20272865869 | F25: 84450 | G25: 0
A26: 12/09/2024 | B26: 778 | C26: DI FEO MARTIN EZEQUIEL | E26: 20272865869 | F26: 128100 | G26: 0
A27: 13/09/2024 | B27: 783 | C27: DI FEO MARTIN EZEQUIEL | E27: 20272865869 | F27: 9950 | G27: 0
A28: 19/09/2024 | B28: 796 | C28: DI FEO MARTIN EZEQUIEL | E28: 20272865869 | F28: 253100 | G28: 0
A29: 26/09/2024 | B29: 814 | C29: DI FEO MARTIN EZEQUIEL | E29: 20272865869 | F29: 149150 | G29: 0
A30: 27/09/2024 | B30: 816 | C30: DI FEO MARTIN EZEQUIEL | E30: 20272865869 | F30: 9800 | G30: 0
A31: 27/09/2024 | B31: 819 | C31: DI FEO MARTIN EZEQUIEL | E31: 20272865869 | F31: 105000 | G31: 0
A32: 04/09/2024 | B32: FA-A 0007-00003241 | C32: Furlanetto, Martin | D32: IVA Responsable Inscripto | E32: 20284183534 | F32: 4545.5 | G32: 0
A33: 26/09/2024 | B33: TF-A0007-00003292 | C33: Furlanetto, Martin | D33: IVA Responsable Inscripto | E33: 20284183534 | F33: 9504.13 | G33: 0
A34: 04/09/2024 | B34: 3241 | C34: FURLANETTO MARTIN | E34: 20284183534 | F34: 4545.5 | G34: 0
A35: 26/09/2024 | B35: 3292 | C35: FURLANETTO MARTIN | E35: 20284183534 | F35: 9504.13 | G35: 0
A36: 12/09/2024 | B36: FA-A 0004-00038394 | C36: Ledesma, Emiliano Ruben | D36: IVA Responsable Inscripto | E36: 20289111329 | F36: 585730.8 | G36: 0
A37: 12/09/2024 | B37: 38394 | C37: LEDESMA EMILIANO RUBEN | E37: 20289111329 | F37: 585730.8 | G37: 0
A38: 20/09/2024 | B38: FA-A 0004-00000136 | C38: Villalba, Miguel Angel | D38: IVA Responsable Inscripto | E38: 20317488476 | F38: 1870000 | G38: 0
A39: 25/09/2024 | B39: FA-A 0004-00000137 | C39: Villalba, Miguel Angel | D39: IVA Responsable Inscripto | E39: 20317488476 | F39: 105000 | G39: 0
A40: 20/09/2024 | B40: 136 | C40: VILLALBA MIGUEL ANGEL | E40: 20317488476 | F40: 1870000 | G40: 0
A41: 25/09/2024 | B41: 137 | C41: VILLALBA MIGUEL ANGEL | E41: 20317488476 | F41: 105000 | G41: 0
A42: 13/09/2024 | B42: NC-A 0003-00000017 | C42: Nardomarino, Ezequiel Eduardo | D42: IVA Responsable Inscripto | E42: 20334976433 | F42: -188330 | G42: 0
A43: 13/09/2024 | B43: FA-A 0003-00000170 | C43: Nardomarino, Ezequiel Eduardo | D43: IVA Responsable Inscripto | E43: 20334976433 | F43: 188330 | G43: 0
A44: 13/09/2024 | B44: FA-A 0003-00000171 | C44: Nardomarino, Ezequiel Eduardo | D44: IVA Responsable Inscripto | E44: 20334976433 | F44: 153000 | G44: 0
A45: 26/09/2024 | B45: FA-A 0003-00000172 | C45: Nardomarino, Ezequiel Eduardo | D45: IVA Responsable Inscripto | E45: 20334976433 | F45: 90000 | G45: 0
A46: 13/09/2024 | B46: 170 | C46: NARDOMARINO EZEQUIEL EDUARDO | E46: 20334976433 | F46: 188330 | G46: 0
A47: 13/09/2024 | B47: 171 | C47: NARDOMARINO EZEQUIEL EDUARDO | E47: 20334976433 | F47: 153000 | G47: 0
A48: 13/09/2024 | B48: 17 | C48: NARDOMARINO EZEQUIEL EDUARDO | E48: 20334976433 | F48: 188330 | G48: 0
A49: 26/09/2024 | B49: 172 | C49: NARDOMARINO EZEQUIEL EDUARDO | E49: 20334976433 | F49: 90000 | G49: 0
A50: 20/09/2024 | B50: FA-A 0005-00003877 | C50: NOLASCO ALAN MANUEL | D50: IVA Responsable Inscripto | E50: 20348485580 | F50: 29099.82 | G50: 0
A51: 20/09/2024 | B51: 3877 | C51: NOLASCO ALAN MANUEL | E51: 20348485580 | F51: 29099.82 | G51: 0
A52: 11/09/2024 | B52: FA-C 0001-00000009 | C52: Oviedo Jimenez, Tiziano Lionel | D52: Responsable Monotributo | E52: 20464199633 | F52: 0 | G52: 499950
A53: 11/09/2024 | B53: 9 | C53: OVIEDO JIMENEZ TIZIANO LIONEL | E53: 20464199633
A54: 26/09/2024 | B54: FA-A 0005-00000032 | C54: MA JUN | D54: IVA Responsable Inscripto | E54: 20929183143 | F54: 50000 | G54: 0
A55: 26/09/2024 | B55: 32 | C55: MA JUN | E55: 20929183143 | F55: 50000 | G55: 0
A56: 18/09/2024 | B56: FA-C 0001-00000070 | C56: Druetta, Andrea Mariel | D56: Responsable Monotributo | E56: 23281233084 | F56: 0 | G56: 215000
A57: 18/09/2024 | B57: FA-C 0001-00000071 | C57: Druetta, Andrea Mariel | D57: Responsable Monotributo | E57: 23281233084 | F57: 0 | G57: 215000
A58: 18/09/2024 | B58: 70 | C58: DRUETTA ANDREA MARIEL | E58: 23281233084
A59: 18/09/2024 | B59: 71 | C59: DRUETTA ANDREA MARIEL | E59: 23281233084
A60: 15/09/2024 | B60: 168 | C60: FERREIRA LILIANA INES | E60: 27062343449
A61: 15/09/2024 | B61: 169 | C61: FERREIRA LILIANA INES | E61: 27062343449
A62: 27/08/2024 | B62: TF-A0005-00002285 | C62: Espada Faraldo, Margarita Mercedes | D62: IVA Responsable Inscripto | E62: 27114789033 | F62: 56363.64 | G62: 0
A63: 28/08/2024 | B63: TF-A0005-00002291 | C63: Espada Faraldo, Margarita Mercedes | D63: IVA Responsable Inscripto | E63: 27114789033 | F63: 10991.74 | G63: 0
A64: 13/09/2024 | B64: FA-A 0002-00004940 | C64: Manzini, Marta Graciela | D64: IVA Responsable Inscripto | E64: 27117233745 | F64: 585519 | G64: 0
A65: 18/09/2024 | B65: FA-A 0002-00004942 | C65: Manzini, Marta Graciela | D65: IVA Responsable Inscripto | E65: 27117233745 | F65: 585519 | G65: 0
A66: 13/09/2024 | B66: 4940 | C66: MANZINI MARTA GRACIELA | E66: 27117233745 | F66: 585519 | G66: 0
A67: 18/09/2024 | B67: 4942 | C67: MANZINI MARTA GRACIELA | E67: 27117233745 | F67: 585519 | G67: 0
A68: 02/09/2024 | B68: FA-A 0002-00000248 | C68: Schejter, Lila Elisa | D68: IVA Responsable Inscripto | E68: 27144282383 | F68: 160000 | G68: 0
A69: 16/09/2024 | B69: FA-A 0002-00000249 | C69: Schejter, Lila Elisa | D69: IVA Responsable Inscripto | E69: 27144282383 | F69: 320000 | G69: 0
A70: 20/09/2024 | B70: FA-A 0002-00000250 | C70: Schejter, Lila Elisa | D70: IVA Responsable Inscripto | E70: 27144282383 | F70: 320000 | G70: 0
A71: 26/09/2024 | B71: FA-A 0002-00000252 | C71: Schejter, Lila Elisa | D71: IVA Responsable Inscripto | E71: 27144282383 | F71: 300000 | G71: 0
A72: 02/09/2024 | B72: 248 | C72: SCHEJTER LILA ELISA | E72: 27144282383 | F72: 160000 | G72: 0
A73: 16/09/2024 | B73: 249 | C73: SCHEJTER LILA ELISA | E73: 27144282383 | F73: 320000 | G73: 0
A74: 20/09/2024 | B74: 250 | C74: SCHEJTER LILA ELISA | E74: 27144282383 | F74: 320000 | G74: 0
A75: 26/09/2024 | B75: 252 | C75: SCHEJTER LILA ELISA | E75: 27144282383 | F75: 300000 | G75: 0
A76: 17/09/2024 | B76: FA-C 0001-00000247 | C76: Sapuna, Mirian Karina | D76: Responsable Monotributo | E76: 27217606255 | F76: 0 | G76: 56703.42
A77: 17/09/2024 | B77: FA-C 0001-00000248 | C77: Sapuna, Mirian Karina | D77: Responsable Monotributo | E77: 27217606255 | F77: 0 | G77: 50223.03
A78: 18/09/2024 | B78: FA-C 0001-00000249 | C78: Sapuna, Mirian Karina | D78: Responsable Monotributo | E78: 27217606255 | F78: 0 | G78: 55083.32
A79: 18/09/2024 | B79: FA-C 0001-00000250 | C79: Sapuna, Mirian Karina | D79: Responsable Monotributo | E79: 27217606255 | F79: 0 | G79: 148916.68
A80: 19/09/2024 | B80: FA-C 0001-00000251 | C80: Sapuna, Mirian Karina | D80: Responsable Monotributo | E80: 27217606255 | F80: 0 | G80: 96357.85
A81: 19/09/2024 | B81: FA-C 0001-00000252 | C81: Sapuna, Mirian Karina | D81: Responsable Monotributo | E81: 27217606255 | F81: 0 | G81: 105117.66
A82: 20/09/2024 | B82: FA-C 0001-00000253 | C82: Sapuna, Mirian Karina | D82: Responsable Monotributo | E82: 27217606255 | F82: 0 | G82: 87598.05
A83: 17/09/2024 | B83: 248 | C83: SAPUNA MIRIAN KARINA | E83: 27217606255
A84: 17/09/2024 | B84: 247 | C84: SAPUNA MIRIAN KARINA | E84: 27217606255
A85: 18/09/2024 | B85: 249 | C85: SAPUNA MIRIAN KARINA | E85: 27217606255
A86: 18/09/2024 | B86: 250 | C86: SAPUNA MIRIAN KARINA | E86: 27217606255
A87: 19/09/2024 | B87: 251 | C87: SAPUNA MIRIAN KARINA | E87: 27217606255
A88: 19/09/2024 | B88: 252 | C88: SAPUNA MIRIAN KARINA | E88: 27217606255
A89: 20/09/2024 | B89: 253 | C89: SAPUNA MIRIAN KARINA | E89: 27217606255
A90: 24/09/2024 | B90: FA-A 0002-00000025 | C90: Bard, Marisa Silvia | D90: IVA Responsable Inscripto | E90: 27243660535 | F90: 360000 | G90: 0
A91: 24/09/2024 | B91: 25 | C91: BARD MARISA SILVIA | E91: 27243660535 | F91: 360000 | G91: 0
A92: 28/09/2024 | B92: 336 | C92: CHIARA FLORENCIA | E92: 27251962559 | F92: 42396.71 | G92: 0
A93: 02/09/2024 | B93: FA-C 0002-00000302 | C93: Blasco, Maria Guadalupe | D93: Responsable Monotributo | E93: 27265832178 | F93: 0 | G93: 250000
A94: 02/09/2024 | B94: 302 | C94: BLASCO MARIA GUADALUPE | E94: 27265832178
A95: 02/09/2024 | B95: FA-A 0005-00000102 | C95: Andreani, Agustina Susana | D95: IVA Responsable Inscripto | E95: 27329449357 | F95: 64100 | G95: 16400
A96: 02/09/2024 | B96: 102 | C96: ANDREANI AGUSTINA SUSANA | E96: 27329449357 | F96: 64100 | G96: 16400
A97: 09/09/2024 | B97: FA-C 0001-00000148 | C97: Cancino, Pamela Rita | D97: Responsable Monotributo | E97: 27338342840 | F97: 0 | G97: 276800
A98: 09/09/2024 | B98: 148 | C98: CANCINO PAMELA RITA | E98: 27338342840
A99: 10/09/2024 | B99: FA-A 0002-00008403 | C99: Hecker, Laura Noemi | D99: IVA Responsable Inscripto | E99: 27363810182 | F99: 3635.54 | G99: 0
A100: 10/09/2024 | B100: 8403 | C100: HECKER LAURA NOEMI | E100: 27363810182 | F100: 3635.54 | G100: 0
A101: 21/09/2024 | B101: FA-C 0001-00000014 | C101: Migoya Moriondo, Maria Ines | D101: Responsable Monotributo | E101: 27443612705 | F101: 0 | G101: 600000
A102: 21/09/2024 | B102: 14 | C102: MIGOYA MORIONDO MARIA INES | E102: 27443612705
...

Sheet Resumen Ventas 11
A1: Totales por Tipo de Comprobante - AFIP
B2: Base | C2: IVA | D2: Otros Imp. | E2: Total Compr.
A3: (FCE) A | B3: 47800480 | C3: =+B3*0.21 -> 10038101 | E3: =SUM(B3:D3) -> 57838581
A4: NC FCE A | B4: -3293388.4 | C4: =+B4*0.21 -> -691611.57 | E4: =SUM(B4:D4) -> -3985000
A5: FACTURAS A | B5: 10002680 | C5: =+B5*0.21 -> 2100562.9 | E5: =SUM(B5:D5) -> 12103243
A6: NC A | B6: -1340599.2 | C6: =+B6*0.21 -> -281525.82 | E6: =SUM(B6:D6) -> -1622125
A7: FACTURAS B | B7: 13423197 | C7: =+B7*0.21 -> 2818871.3 | E7: =SUM(B7:D7) -> 16242068
A8: NC B | B8: -1336307.9 | C8: =+B8*0.21 -> -280624.67 | E8: =SUM(B8:D8) -> -1616932.6
B9: =SUM(B3:B8) -> 65256062 | C9: =SUM(C3:C8) -> 13703773 | D9: 0 | E9: =SUM(E3:E8) -> 78959835

Sheet Ventas 11
L3: =+SUBTOTAL(109,L10:L801) -> 13423197
A8: Mis Comprobantes Emitidos - CUIT 30710473168
A9: Fecha | B9: Tipo | C9: Punto de Venta | D9: Número Desde | E9: Número Hasta | F9: Cód. Autorización | G9: Tipo Doc. Receptor | H9: Nro. Doc. Receptor | I9: Denominación Receptor | J9: Tipo Cambio | K9: Moneda | L9: Imp. Neto Gravado | M9: Imp. Neto No Gravado | N9: Imp. Op. Exentas | O9: Otros Tributos | P9: IVA | Q9: Imp. Total
A10: 01/11/2024 | B10: 1 - Factura A | C10: 7 | D10: 2227 | F10: 74448602428030 | G10: CUIT | H10: 30546771314 | I10: MEDICUS SOCIEDAD ANONIMA DE ASISTENCIA MEDICA Y CIENTIFICA | J10: 1 | K10: $ | L10: 104132.23 | M10: 0 | N10: 0 | O10: 0 | P10: 21867.77 | Q10: 126000
A11: 01/11/2024 | B11: 1 - Factura A | C11: 7 | D11: 2226 | F11: 74448600824252 | G11: CUIT | H11: 30546771314 | I11: MEDICUS SOCIEDAD ANONIMA DE ASISTENCIA MEDICA Y CIENTIFICA | J11: 1 | K11: $ | L11: 153884.3 | M11: 0 | N11: 0 | O11: 0 | P11: 32315.7 | Q11: 186200
A12: 01/11/2024 | B12: 6 - Factura B | C12: 9 | D12: 234 | F12: 74448561909174 | G12: 99 | H12: 0 | J12: 1 | K12: $ | L12: 11487.6 | M12: 0 | N12: 0 | O12: 0 | P12: 2412.4 | Q12: 13900
A13: 01/11/2024 | B13: 6 - Factura B | C13: 9 | D13: 240 | F13: 74448598039318 | G13: 99 | H13: 0 | J13: 1 | K13: $ | L13: 20661.16 | M13: 0 | N13: 0 | O13: 0 | P13: 4338.84 | Q13: 25000
A14: 01/11/2024 | B14: 6 - Factura B | C14: 9 | D14: 237 | F14: 74448569238896 | G14: 99 | H14: 0 | J14: 1 | K14: $ | L14: 23471.07 | M14: 0 | N14: 0 | O14: 0 | P14: 4928.93 | Q14: 28400
A15: 01/11/2024 | B15: 6 - Factura B | C15: 9 | D15: 241 | F15: 74448601705798 | G15: 99 | H15: 0 | J15: 1 | K15: $ | L15: 16528.93 | M15: 0 | N15: 0 | O15: 0 | P15: 3471.07 | Q15: 20000
A16: 01/11/2024 | B16: 6 - Factura B | C16: 9 | D16: 239 | F16: 74448589059048 | G16: 99 | H16: 0 | J16: 1 | K16: $ | L16: 9256.19 | M16: 0 | N16: 0 | O16: 0 | P16: 1943.81 | Q16: 11200
A17: 01/11/2024 | B17: 6 - Factura B | C17: 9 | D17: 232 | F17: 74448544837619 | G17: 99 | H17: 0 | J17: 1 | K17: $ | L17: 14669.42 | M17: 0 | N17: 0 | O17: 0 | P17: 3080.58 | Q17: 17750
A18: 01/11/2024 | B18: 6 - Factura B | C18: 9 | D18: 236 | F18: 74448567380131 | G18: 99 | H18: 0 | J18: 1 | K18: $ | L18: 11487.6 | M18: 0 | N18: 0 | O18: 0 | P18: 2412.4 | Q18: 13900
A19: 01/11/2024 | B19: 6 - Factura B | C19: 9 | D19: 235 | F19: 74448564292856 | G19: 99 | H19: 0 | J19: 1 | K19: $ | L19: 85537.18 | M19: 0 | N19: 0 | O19: 0 | P19: 17962.82 | Q19: 103500
A20: 01/11/2024 | B20: 6 - Factura B | C20: 9 | D20: 233 | F20: 74448555084195 | G20: 99 | H20: 0 | J20: 1 | K20: $ | L20: 30495.87 | M20: 0 | N20: 0 | O20: 0 | P20: 6404.13 | Q20: 36900
A21: 01/11/2024 | B21: 6 - Factura B | C21: 9 | D21: 242 | F21: 74448616564521 | G21: 99 | H21: 0 | J21: 1 | K21: $ | L21: 14669.42 | M21: 0 | N21: 0 | O21: 0 | P21: 3080.58 | Q21: 17750
A22: 01/11/2024 | B22: 6 - Factura B | C22: 9 | D22: 238 | F22: 74448577672628 | G22: 99 | H22: 0 | J22: 1 | K22: $ | L22: 14669.42 | M22: 0 | N22: 0 | O22: 0 | P22: 3080.58 | Q22: 17750
A23: 01/11/2024 | B23: 6 - Factura B | C23: 3 | D23: 2862 | F23: 74448548497786 | G23: CUIL | H23: 20078376105 | I23: SCHERNETZKI ANSELMO | J23: 1 | K23: $ | L23: 314049.57 | M23: 0 | N23: 0 | O23: 0 | P23: 65950.41 | Q23: 380000
A24: 01/11/2024 | B24: 6 - Factura B | C24: 3 | D24: 2863 | F24: 74448603364668 | G24: DNI | H24: 35940091 | I24: ROMERO LEONARDO ARIEL | J24: 1 | K24: $ | L24: 12727.29 | M24: 0 | N24: 0 | O24: 0 | P24: 2672.73 | Q24: 15400
A25: 01/11/2024 | B25: 6 - Factura B | C25: 3 | D25: 2864 | F25: 74448610147202 | G25: DNI | H25: 18066137 | I25: RAIDEN RICARDO | J25: 1 | K25: $ | L25: 17355.38 | M25: 0 | N25: 0 | O25: 0 | P25: 3644.63 | Q25: 21000
A26: 04/11/2024 | B26: 1 - Factura A | C26: 7 | D26: 2228 | F26: 74458947045077 | G26: CUIT | H26: 30715186655 | I26: AMPARO SALUD S.R.L. | J26: 1 | K26: $ | L26: 420498.35 | M26: 0 | N26: 0 | O26: 0 | P26: 88304.65 | Q26: 508803
A27: 04/11/2024 | B27: 1 - Factura A | C27: 7 | D27: 2229 | F27: 74458947251680 | G27: CUIT | H27: 30715186655 | I27: AMPARO SALUD S.R.L. | J27: 1 | K27: $ | L27: 56198.35 | M27: 0 | N27: 0 | O27: 0 | P27: 11801.65 | Q27: 68000
A28: 04/11/2024 | B28: 1 - Factura A | C28: 7 | D28: 2231 | F28: 74458951113373 | G28: CUIT | H28: 30711244383 | I28: LOGIN DOOR S.A | J28: 1 | K28: $ | L28: 60331.43 | M28: 0 | N28: 0 | O28: 0 | P28: 12669.6 | Q28: 73001.03
A29: 04/11/2024 | B29: 1 - Factura A | C29: 7 | D29: 2230 | F29: 74458948601244 | G29: CUIT | H29: 30710538014 | I29: HC HOMECARE INTERNACION DOMICILIARIA S.A. | J29: 1 | K29: $ | L29: 436033.06 | M29: 0 | N29: 0 | O29: 0 | P29: 91566.94 | Q29: 527600
A30: 04/11/2024 | B30: 6 - Factura B | C30: 9 | D30: 243 | F30: 74458877910909 | G30: 99 | H30: 0 | J30: 1 | K30: $ | L30: 16942.15 | M30: 0 | N30: 0 | O30: 0 | P30: 3557.85 | Q30: 20500
A31: 04/11/2024 | B31: 6 - Factura B | C31: 9 | D31: 247 | F31: 74458927986748 | G31: 99 | H31: 0 | J31: 1 | K31: $ | L31: 29338.84 | M31: 0 | N31: 0 | O31: 0 | P31: 6161.16 | Q31: 35500
A32: 04/11/2024 | B32: 6 - Factura B | C32: 9 | D32: 245 | F32: 74458922661220 | G32: 99 | H32: 0 | J32: 1 | K32: $ | L32: 10743.8 | M32: 0 | N32: 0 | O32: 0 | P32: 2256.2 | Q32: 13000
A33: 04/11/2024 | B33: 6 - Factura B | C33: 9 | D33: 244 | F33: 74458879179224 | G33: 99 | H33: 0 | J33: 1 | K33: $ | L33: 4132.23 | M33: 0 | N33: 0 | O33: 0 | P33: 867.77 | Q33: 5000
A34: 04/11/2024 | B34: 6 - Factura B | C34: 7 | D34: 5426 | F34: 74458912363535 | G34: DNI | H34: 17198648 | I34: LOCOCO CARMEN CLAUDIA | J34: 1 | K34: $ | L34: 19834.71 | M34: 0 | N34: 0 | O34: 0 | P34: 4165.29 | Q34: 24000
A35: 04/11/2024 | B35: 6 - Factura B | C35: 7 | D35: 5427 | F35: 74458952323313 | G35: CUIT | H35: 30571766287 | I35: OBRA SOCIAL DEL PERSONAL DE LA INDUSTRIA DEL PLASTICO | J35: 1 | K35: $ | L35: 167570.25 | M35: 0 | N35: 0 | O35: 0 | P35: 35189.75 | Q35: 202760
A36: 04/11/2024 | B36: 6 - Factura B | C36: 9 | D36: 246 | F36: 74458924110077 | G36: 99 | H36: 0 | J36: 1 | K36: $ | L36: 8264.46 | M36: 0 | N36: 0 | O36: 0 | P36: 1735.54 | Q36: 10000
A37: 04/11/2024 | B37: 6 - Factura B | C37: 3 | D37: 2865 | F37: 74458902778395 | J37: 1 | K37: $ | L37: 12396.71 | M37: 0 | N37: 0 | O37: 0 | P37: 2603.31 | Q37: 15000
A38: 04/11/2024 | B38: 6 - Factura B | C38: 3 | D38: 2869 | F38: 74458939112061 | J38: 1 | K38: $ | L38: 17355.38 | M38: 0 | N38: 0 | O38: 0 | P38: 3644.63 | Q38: 21000
A39: 04/11/2024 | B39: 6 - Factura B | C39: 3 | D39: 2872 | F39: 74458942253899 | G39: DNI | H39: 18057302 | I39: CARABALLO LUIS FERNANDO | J39: 1 | K39: $ | L39: 18677.67 | M39: 0 | N39: 0 | O39: 0 | P39: 3922.31 | Q39: 22600
A40: 04/11/2024 | B40: 6 - Factura B | C40: 3 | D40: 2867 | F40: 74458937256075 | G40: DNI | H40: 28369491 | I40: BELLIA MARIANA CRISTINA | J40: 1 | K40: $ | L40: 21900.81 | M40: 0 | N40: 0 | O40: 0 | P40: 4599.17 | Q40: 26500
A41: 04/11/2024 | B41: 6 - Factura B | C41: 3 | D41: 2866 | F41: 74458912240084 | G41: DNI | H41: 11987513 | I41: MORGAN SANTIAGO | J41: 1 | K41: $ | L41: 34297.52 | M41: 0 | N41: 0 | O41: 0 | P41: 7202.48 | Q41: 41500
A42: 04/11/2024 | B42: 6 - Factura B | C42: 3 | D42: 2870 | F42: 74458940452154 | G42: DNI | H42: 17795042 | I42: ZUMBO MARIA LAURA | J42: 1 | K42: $ | L42: 35041.33 | M42: 0 | N42: 0 | O42: 0 | P42: 7358.68 | Q42: 42400
A43: 04/11/2024 | B43: 6 - Factura B | C43: 3 | D43: 2868 | F43: 74458937935802 | G43: DNI | H43: 17467464 | I43: ROMERO JUAN CARLOS | J43: 1 | K43: $ | L43: 12727.29 | M43: 0 | N43: 0 | O43: 0 | P43: 2672.73 | Q43: 15400
A44: 04/11/2024 | B44: 6 - Factura B | C44: 3 | D44: 2871 | F44: 74458941173907 | G44: DNI | H44: 18811819 | I44: CLIMENT BORZANI ANA GABRIELA | J44: 1 | K44: $ | L44: 12396.71 | M44: 0 | N44: 0 | O44: 0 | P44: 2603.31 | Q44: 15000
A45: 05/11/2024 | B45: 1 - Factura A | C45: 7 | D45: 2232 | F45: 74458049339978 | G45: CUIT | H45: 30522428163 | I45: GALENO ARGENTINA SOCIEDAD ANONIMA | J45: 1 | K45: $ | L45: 37190.08 | M45: 0 | N45: 0 | O45: 0 | P45: 7809.92 | Q45: 45000
A46: 05/11/2024 | B46: 1 - Factura A | C46: 7 | D46: 2233 | F46: 74458065861742 | G46: CUIT | H46: 30522428163 | I46: GALENO ARGENTINA SOCIEDAD ANONIMA | J46: 1 | K46: $ | L46: 280783.17 | M46: 0 | N46: 0 | O46: 0 | P46: 58964.47 | Q46: 339747.64
A47: 05/11/2024 | B47: 6 - Factura B | C47: 9 | D47: 249 | F47: 74458021990793 | G47: 99 | H47: 0 | J47: 1 | K47: $ | L47: 13966.94 | M47: 0 | N47: 0 | O47: 0 | P47: 2933.06 | Q47: 16900
A48: 05/11/2024 | B48: 6 - Factura B | C48: 9 | D48: 260 | F48: 74458078501717 | G48: 99 | H48: 0 | J48: 1 | K48: $ | L48: 37438.02 | M48: 0 | N48: 0 | O48: 0 | P48: 7861.98 | Q48: 45300
A49: 05/11/2024 | B49: 6 - Factura B | C49: 9 | D49: 255 | F49: 74458057145426 | G49: 99 | H49: 0 | J49: 1 | K49: $ | L49: 61983.47 | M49: 0 | N49: 0 | O49: 0 | P49: 13016.53 | Q49: 75000
A50: 05/11/2024 | B50: 6 - Factura B | C50: 9 | D50: 252 | F50: 74458049013700 | G50: 99 | H50: 0 | J50: 1 | K50: $ | L50: 22314.05 | M50: 0 | N50: 0 | O50: 0 | P50: 4685.95 | Q50: 27000
A51: 05/11/2024 | B51: 6 - Factura B | C51: 9 | D51: 259 | F51: 74458073691041 | G51: 99 | H51: 0 | J51: 1 | K51: $ | L51: 29338.84 | M51: 0 | N51: 0 | O51: 0 | P51: 6161.16 | Q51: 35500
A52: 05/11/2024 | B52: 6 - Factura B | C52: 9 | D52: 248 | F52: 74458009671300 | G52: 99 | H52: 0 | J52: 1 | K52: $ | L52: 10743.8 | M52: 0 | N52: 0 | O52: 0 | P52: 2256.2 | Q52: 13000
A53: 05/11/2024 | B53: 6 - Factura B | C53: 9 | D53: 253 | F53: 74458052352378 | G53: 99 | H53: 0 | J53: 1 | K53: $ | L53: 4958.68 | M53: 0 | N53: 0 | O53: 0 | P53: 1041.32 | Q53: 6000
A54: 05/11/2024 | B54: 6 - Factura B | C54: 9 | D54: 257 | F54: 74458066060110 | G54: 99 | H54: 0 | J54: 1 | K54: $ | L54: 10743.8 | M54: 0 | N54: 0 | O54: 0 | P54: 2256.2 | Q54: 13000
A55: 05/11/2024 | B55: 6 - Factura B | C55: 9 | D55: 251 | F55: 74458044962040 | G55: 99 | H55: 0 | J55: 1 | K55: $ | L55: 33884.3 | M55: 0 | N55: 0 | O55: 0 | P55: 7115.7 | Q55: 41000
A56: 05/11/2024 | B56: 6 - Factura B | C56: 9 | D56: 258 | F56: 74458072253898 | G56: 99 | H56: 0 | J56: 1 | K56: $ | L56: 29338.84 | M56: 0 | N56: 0 | O56: 0 | P56: 6161.16 | Q56: 35500
A57: 05/11/2024 | B57: 6 - Factura B | C57: 9 | D57: 254 | F57: 74458053608148 | G57: 99 | H57: 0 | J57: 1 | K57: $ | L57: 14669.42 | M57: 0 | N57: 0 | O57: 0 | P57: 3080.58 | Q57: 17750
A58: 05/11/2024 | B58: 6 - Factura B | C58: 9 | D58: 250 | F58: 74458037788114 | G58: 99 | H58: 0 | J58: 1 | K58: $ | L58: 7851.24 | M58: 0 | N58: 0 | O58: 0 | P58: 1648.76 | Q58: 9500
A59: 05/11/2024 | B59: 6 - Factura B | C59: 9 | D59: 256 | F59: 74458062063724 | G59: 99 | H59: 0 | J59: 1 | K59: $ | L59: 12396.69 | M59: 0 | N59: 0 | O59: 0 | P59: 2603.31 | Q59: 15000
A60: 05/11/2024 | B60: 6 - Factura B | C60: 7 | D60: 5428 | F60: 74458089106333 | G60: CUIT | H60: 30590354798 | I60: ASOCIACION MUTUAL SANCOR SALUD | J60: 1 | K60: $ | L60: 2003068.1 | M60: 0 | N60: 0 | O60: 0 | P60: 420644.3 | Q60: 2423712.4
A61: 05/11/2024 | B61: 201 - Factura de Crédito electrónica MiPyMEs (FCE) A | C61: 6 | D61: 542 | F61: 74458048932317 | G61: CUIT | H61: 30522428163 | I61: GALENO ARGENTINA SOCIEDAD ANONIMA | J61: 1 | K61: $ | L61: 1239054.9 | M61: 0 | N61: 0 | O61: 0 | P61: 260201.53 | Q61: 1499256.4
A62: 05/11/2024 | B62: 201 - Factura de Crédito electrónica MiPyMEs (FCE) A | C62: 6 | D62: 544 | F62: 74458066762302 | G62: CUIT | H62: 30522428163 | I62: GALENO ARGENTINA SOCIEDAD ANONIMA | J62: 1 | K62: $ | L62: 10127516 | M62: 0 | N62: 0 | O62: 0 | P62: 2126778.3 | Q62: 12254294
A63: 05/11/2024 | B63: 201 - Factura de Crédito electrónica MiPyMEs (FCE) A | C63: 6 | D63: 545 | F63: 74458066973245 | G63: CUIT | H63: 30522428163 | I63: GALENO ARGENTINA SOCIEDAD ANONIMA | J63: 1 | K63: $ | L63: 1419259.6 | M63: 0 | N63: 0 | O63: 0 | P63: 298044.52 | Q63: 1717304.1
A64: 05/11/2024 | B64: 201 - Factura de Crédito electrónica MiPyMEs (FCE) A | C64: 6 | D64: 543 | F64: 74458064657711 | G64: CUIT | H64: 30522428163 | I64: GALENO ARGENTINA SOCIEDAD ANONIMA | J64: 1 | K64: $ | L64: 1519236.2 | M64: 0 | N64: 0 | O64: 0 | P64: 319039.61 | Q64: 1838275.9
A65: 05/11/2024 | B65: 8 - Nota de Crédito B | C65: 3 | D65: 266 | F65: 74458032236942 | G65: DNI | H65: 4404079 | I65: VILLALBA ROLANDO ANTONIO | J65: 1 | K65: $ | L65: -26446.29 | N65: 0 | O65: 0 | P65: =+L65*0.21 -> -5553.7209 | Q65: =SUBTOTAL(9,L65:P65) -> 0
A66: 06/11/2024 | B66: 1 - Factura A | C66: 7 | D66: 2234 | F66: 74458177408760 | G66: CUIT | H66: 30709016012 | I66: MGR IMPLANTES S.A. | J66: 1 | K66: $ | L66: 253842.98 | M66: 0 | N66: 0 | O66: 0 | P66: 53307.02 | Q66: 307150
A67: 06/11/2024 | B67: 6 - Factura B | C67: 9 | D67: 262 | F67: 74458160699668 | G67: 99 | H67: 0 | J67: 1 | K67: $ | L67: 29338.84 | M67: 0 | N67: 0 | O67: 0 | P67: 6161.16 | Q67: 35500
A68: 06/11/2024 | B68: 6 - Factura B | C68: 9 | D68: 272 | F68: 74458223807937 | G68: 99 | H68: 0 | J68: 1 | K68: $ | L68: 13223.14 | M68: 0 | N68: 0 | O68: 0 | P68: 2776.86 | Q68: 16000
A69: 06/11/2024 | B69: 6 - Factura B | C69: 9 | D69: 273 | F69: 74458224058292 | G69: 99 | H69: 0 | J69: 1 | K69: $ | L69: 14462.81 | M69: 0 | N69: 0 | O69: 0 | P69: 3037.19 | Q69: 17500
A70: 06/11/2024 | B70: 6 - Factura B | C70: 9 | D70: 261 | F70: 74458152362723 | G70: 99 | H70: 0 | J70: 1 | K70: $ | L70: 15702.48 | M70: 0 | N70: 0 | O70: 0 | P70: 3297.52 | Q70: 19000
A71: 06/11/2024 | B71: 6 - Factura B | C71: 9 | D71: 274 | F71: 74458224530780 | G71: 99 | H71: 0 | J71: 1 | K71: $ | L71: 29338.84 | M71: 0 | N71: 0 | O71: 0 | P71: 6161.16 | Q71: 35500
A72: 06/11/2024 | B72: 6 - Factura B | C72: 9 | D72: 265 | F72: 74458184377809 | G72: 99 | H72: 0 | J72: 1 | K72: $ | L72: 10495.87 | M72: 0 | N72: 0 | O72: 0 | P72: 2204.13 | Q72: 12700
A73: 06/11/2024 | B73: 6 - Factura B | C73: 9 | D73: 267 | F73: 74458193937264 | G73: 99 | H73: 0 | J73: 1 | K73: $ | L73: 21487.6 | M73: 0 | N73: 0 | O73: 0 | P73: 4512.4 | Q73: 26000
A74: 06/11/2024 | B74: 6 - Factura B | C74: 9 | D74: 266 | F74: 74458187651513 | G74: 99 | H74: 0 | J74: 1 | K74: $ | L74: 7438.02 | M74: 0 | N74: 0 | O74: 0 | P74: 1561.98 | Q74: 9000
A75: 06/11/2024 | B75: 6 - Factura B | C75: 9 | D75: 271 | F75: 74458206637184 | G75: 99 | H75: 0 | J75: 1 | K75: $ | L75: 42975.21 | M75: 0 | N75: 0 | O75: 0 | P75: 9024.79 | Q75: 52000
A76: 06/11/2024 | B76: 6 - Factura B | C76: 9 | D76: 268 | F76: 74458197244219 | G76: 99 | H76: 0 | J76: 1 | K76: $ | L76: 14669.42 | M76: 0 | N76: 0 | O76: 0 | P76: 3080.58 | Q76: 17750
A77: 06/11/2024 | B77: 6 - Factura B | C77: 9 | D77: 276 | F77: 74458228857628 | G77: 99 | H77: 0 | J77: 1 | K77: $ | L77: 25619.83 | M77: 0 | N77: 0 | O77: 0 | P77: 5380.17 | Q77: 31000
A78: 06/11/2024 | B78: 6 - Factura B | C78: 9 | D78: 263 | F78: 74458163424747 | G78: 99 | H78: 0 | J78: 1 | K78: $ | L78: 34462.81 | M78: 0 | N78: 0 | O78: 0 | P78: 7237.19 | Q78: 41700
A79: 06/11/2024 | B79: 6 - Factura B | C79: 9 | D79: 264 | F79: 74458169757607 | G79: 99 | H79: 0 | J79: 1 | K79: $ | L79: 95950.41 | M79: 0 | N79: 0 | O79: 0 | P79: 20149.59 | Q79: 116100
A80: 06/11/2024 | B80: 6 - Factura B | C80: 7 | D80: 5429 | F80: 74458169758226 | G80: CUIT | H80: 30658137642 | I80: OBRA SOCIAL DE LOS TRABAJADORES DE LA INDUSTRIA DEL GAS | J80: 1 | K80: $ | L80: 532818.18 | M80: 0 | N80: 0 | O80: 0 | P80: 111891.82 | Q80: 644710
A81: 06/11/2024 | B81: 6 - Factura B | C81: 9 | D81: 270 | F81: 74458201269551 | G81: 99 | H81: 0 | J81: 1 | K81: $ | L81: 254545.45 | M81: 0 | N81: 0 | O81: 0 | P81: 53454.55 | Q81: 308000
A82: 06/11/2024 | B82: 6 - Factura B | C82: 9 | D82: 275 | F82: 74458226365245 | G82: 99 | H82: 0 | J82: 1 | K82: $ | L82: 19834.71 | M82: 0 | N82: 0 | O82: 0 | P82: 4165.29 | Q82: 24000
A83: 06/11/2024 | B83: 6 - Factura B | C83: 9 | D83: 269 | F83: 74458198132145 | G83: 99 | H83: 0 | J83: 1 | K83: $ | L83: 12809.92 | M83: 0 | N83: 0 | O83: 0 | P83: 2690.08 | Q83: 15500
A84: 06/11/2024 | B84: 6 - Factura B | C84: 3 | D84: 2873 | F84: 74458217626513 | G84: DNI | H84: 30393335 | I84: GASCO LEMOS ERIKA VANESA | J84: 1 | K84: $ | L84: 13636.38 | M84: 0 | N84: 0 | O84: 0 | P84: 2863.64 | Q84: 16500
A85: 06/11/2024 | B85: 8 - Nota de Crédito B | C85: 3 | D85: 269 | F85: 74458203232654 | G85: DNI | H85: 17795042 | I85: ZUMBO MARIA LAURA | J85: 1 | K85: $ | L85: -35041.33 | N85: 0 | O85: 0 | P85: =+L85*0.21 -> -7358.6793 | Q85: =SUBTOTAL(9,L85:P85) -> 0
A86: 06/11/2024 | B86: 8 - Nota de Crédito B | C86: 3 | D86: 270 | F86: 74458203605106 | G86: DNI | H86: 17795042 | I86: ZUMBO MARIA LAURA | J86: 1 | K86: $ | L86: -35041.33 | N86: 0 | O86: 0 | P86: =+L86*0.21 -> -7358.6793 | Q86: =SUBTOTAL(9,L86:P86) -> 0
A87: 06/11/2024 | B87: 8 - Nota de Crédito B | C87: 3 | D87: 267 | F87: 74458169215695 | G87: DNI | H87: 46027091 | I87: BENEIT MORA YAZMIN | J87: 1 | K87: $ | L87: -15619.86 | N87: 0 | O87: 0 | P87: =+L87*0.21 -> -3280.1706 | Q87: =SUBTOTAL(9,L87:P87) -> 0
A88: 06/11/2024 | B88: 8 - Nota de Crédito B | C88: 3 | D88: 268 | F88: 74458169791894 | G88: DNI | H88: 46027091 | I88: BENEIT MORA YAZMIN | J88: 1 | K88: $ | L88: -14876.05 | N88: 0 | O88: 0 | P88: =+L88*0.21 -> -3123.9705 | Q88: =SUBTOTAL(9,L88:P88) -> 0
A89: 06/11/2024 | B89: 8 - Nota de Crédito B | C89: 3 | D89: 271 | F89: 74458207747994 | G89: CUIT | H89: 27137980008 | I89: MEJAIL MARIA CRISTINA | J89: 1 | K89: $ | L89: -22314.05 | N89: 0 | O89: 0 | P89: =+L89*0.21 -> -4685.9505 | Q89: =SUBTOTAL(9,L89:P89) -> 0
A90: 07/11/2024 | B90: 1 - Factura A | C90: 7 | D90: 2235 | F90: 74458360436056 | G90: CUIT | H90: 30709016012 | I90: MGR IMPLANTES S.A. | J90: 1 | K90: $ | L90: 537190.08 | M90: 0 | N90: 0 | O90: 0 | P90: 112809.92 | Q90: 650000
A91: 07/11/2024 | B91: 1 - Factura A | C91: 3 | D91: 2136 | F91: 74458309139036 | G91: CUIT | H91: 30683032227 | I91: OBRA SOCIAL UNION PERSONAL DE LA UNION DEL PERSONAL CIVIL DE LA NACION | J91: 1 | K91: $ | L91: 13214.86 | M91: 0 | N91: 0 | O91: 0 | P91: 2775.12 | Q91: 15990
A92: 07/11/2024 | B92: 1 - Factura A | C92: 3 | D92: 2137 | F92: 74458327277222 | G92: CUIT | H92: 30683032227 | I92: OBRA SOCIAL UNION PERSONAL DE LA UNION DEL PERSONAL CIVIL DE LA NACION | J92: 1 | K92: $ | L92: 181818.19 | M92: 0 | N92: 0 | O92: 0 | P92: 38181.82 | Q92: 220000.01
A93: 07/11/2024 | B93: 6 - Factura B | C93: 9 | D93: 279 | F93: 74458310207389 | G93: 99 | H93: 0 | J93: 1 | K93: $ | L93: 10743.8 | M93: 0 | N93: 0 | O93: 0 | P93: 2256.2 | Q93: 13000
A94: 07/11/2024 | B94: 6 - Factura B | C94: 9 | D94: 277 | F94: 74458298683530 | G94: 99 | H94: 0 | J94: 1 | K94: $ | L94: 14669.42 | M94: 0 | N94: 0 | O94: 0 | P94: 3080.58 | Q94: 17750
A95: 07/11/2024 | B95: 6 - Factura B | C95: 9 | D95: 285 | F95: 74458342848941 | G95: 99 | H95: 0 | J95: 1 | K95: $ | L95: 29338.84 | M95: 0 | N95: 0 | O95: 0 | P95: 6161.16 | Q95: 35500
A96: 07/11/2024 | B96: 6 - Factura B | C96: 9 | D96: 278 | F96: 74458308088456 | G96: 99 | H96: 0 | J96: 1 | K96: $ | L96: 10743.8 | M96: 0 | N96: 0 | O96: 0 | P96: 2256.2 | Q96: 13000
A97: 07/11/2024 | B97: 6 - Factura B | C97: 9 | D97: 281 | F97: 74458331578370 | G97: 99 | H97: 0 | J97: 1 | K97: $ | L97: 14876.03 | M97: 0 | N97: 0 | O97: 0 | P97: 3123.97 | Q97: 18000
A98: 07/11/2024 | B98: 6 - Factura B | C98: 9 | D98: 283 | F98: 74458337532336 | G98: 99 | H98: 0 | J98: 1 | K98: $ | L98: 11487.6 | M98: 0 | N98: 0 | O98: 0 | P98: 2412.4 | Q98: 13900
A99: 07/11/2024 | B99: 6 - Factura B | C99: 9 | D99: 282 | F99: 74458332050822 | G99: 99 | H99: 0 | J99: 1 | K99: $ | L99: 16528.93 | M99: 0 | N99: 0 | O99: 0 | P99: 3471.07 | Q99: 20000
A100: 07/11/2024 | B100: 6 - Factura B | C100: 9 | D100: 280 | F100: 74458320355614 | G100: 99 | H100: 0 | J100: 1 | K100: $ | L100: 10743.8 | M100: 0 | N100: 0 | O100: 0 | P100: 2256.2 | Q100: 13000
A101: 07/11/2024 | B101: 6 - Factura B | C101: 9 | D101: 287 | F101: 74458364741672 | G101: 99 | H101: 0 | J101: 1 | K101: $ | L101: 9504.13 | M101: 0 | N101: 0 | O101: 0 | P101: 1995.87 | Q101: 11500
A102: 07/11/2024 | B102: 6 - Factura B | C102: 9 | D102: 284 | F102: 74458338430375 | G102: 99 | H102: 0 | J102: 1 | K102: $ | L102: 13884.3 | M102: 0 | N102: 0 | O102: 0 | P102: 2915.7 | Q102: 16800
A103: 07/11/2024 | B103: 6 - Factura B | C103: 9 | D103: 286 | F103: 74458347852414 | G103: 99 | H103: 0 | J103: 1 | K103: $ | L103: 14669.42 | M103: 0 | N103: 0 | O103: 0 | P103: 3080.58 | Q103: 17750
A104: 07/11/2024 | B104: 6 - Factura B | C104: 9 | D104: 288 | F104: 74458365563203 | G104: 99 | H104: 0 | J104: 1 | K104: $ | L104: 10743.8 | M104: 0 | N104: 0 | O104: 0 | P104: 2256.2 | Q104: 13000
A105: 07/11/2024 | B105: 201 - Factura de Crédito electrónica MiPyMEs (FCE) A | C105: 3 | D105: 21 | F105: 74458318823336 | G105: CUIT | H105: 30522428163 | I105: GALENO ARGENTINA SOCIEDAD ANONIMA | J105: 1 | K105: $ | L105: 2727966.9 | M105: 0 | N105: 0 | O105: 0 | P105: 572873.05 | Q105: 3300840
A106: 07/11/2024 | B106: 8 - Nota de Crédito B | C106: 3 | D106: 277 | F106: 74458368834741 | G106: DNI | H106: 35112162 | I106: SEVARES BRIAN EZEQUIEL | J106: 1 | K106: $ | L106: -12396.71 | N106: 0 | O106: 0 | P106: =+L106*0.21 -> -2603.3091 | Q106: =SUBTOTAL(9,L106:P106) -> 0
...

Sheet Compras 11
A1: Mis Comprobantes Recibidos - CUIT 30710473168
A2: Fecha | B2: Tipo | C2: Punto de Venta | D2: Número Desde | E2: Número Hasta | F2: Cód. Autorización | G2: Tipo Doc. Emisor | H2: Nro. Doc. Emisor | I2: Denominación Emisor | J2: Tipo Cambio | K2: Moneda | L2: Imp. Neto Gravado | M2: Imp. Neto No Gravado | N2: Imp. Op. Exentas | O2: Otros Tributos | P2: IVA | Q2: Imp. Total
A3: 01/11/2024 | B3: 1 - Factura A | C3: 500 | D3: 1641624 | F3: 74447326861618 | G3: CUIT | H3: 30654118767 | I3: SOLUCIONES MULTIMEDIA S A | J3: 1 | K3: $ | L3: 102077.93 | M3: 0 | N3: 0 | O3: 6359.83 | P3: 21436.37 | Q3: 129874.13
A4: 01/11/2024 | B4: 1 - Factura A | C4: 17 | D4: 10855 | F4: 74440611010248 | G4: CUIT | H4: 30661143610 | I4: ORTOPEDIA BERNAT SRL | J4: 1 | K4: $ | L4: 3950700 | M4: 0 | N4: 0 | O4: 197535 | P4: 829647 | Q4: 4977882
A5: 01/11/2024 | B5: 1 - Factura A | C5: 629 | D5: 5571683 | F5: 34433634355672 | G5: CUIT | H5: 30663498513 | I5: GRUPO CONCESIONARIO DEL OESTE SA | J5: 1 | K5: $ | L5: 6731.58 | M5: 0 | N5: 0 | O5: 336.58 | P5: 1413.6 | Q5: 8481.76
A6: 01/11/2024 | B6: 1 - Factura A | C6: 711 | D6: 6334596 | F6: 34439311727749 | G6: CUIT | H6: 30677237119 | I6: AUTOPISTAS DEL SOL S A | J6: 1 | K6: $ | L6: 3312.36 | M6: 0 | N6: 99.37 | O6: 165.62 | P6: 695.58 | Q6: 4272.93
A7: 01/11/2024 | B7: 1 - Factura A | C7: 2 | D7: 6 | F7: 74440602724999 | G7: CUIT | H7: 20233007820 | I7: MUSSO LUIS ADRIAN | J7: 1 | K7: $ | L7: 23600 | M7: 0 | N7: 0 | O7: 0 | P7: 4956 | Q7: 28556
A8: 01/11/2024 | B8: 11 - Factura C | C8: 3 | D8: 1010 | F8: 74449587504125 | G8: CUIT | H8: 20216451679 | I8: VAZQUEZ RICARDO OSCAR | J8: 1 | K8: $ | O8: 0 | Q8: 400000
A9: 02/11/2024 | B9: 1 - Factura A | C9: 3051 | D9: 831166 | F9: 74447821819310 | G9: CUIT | H9: 30678814357 | I9: TELEFONICA MOVILES ARGENTINA SOCIEDAD ANONIMA | J9: 1 | K9: $ | L9: 28282.81 | M9: 0 | N9: 0 | O9: 3787.98 | P9: 7636.36 | Q9: 39707.15
A10: 04/11/2024 | B10: 1 - Factura A | C10: 5 | D10: 160678 | F10: 74453921324614 | G10: CUIT | H10: 30598960093 | I10: SILVESTRIN FABRIS SOC RESP LTDA | J10: 1 | K10: $ | L10: 393556.5 | M10: 0 | N10: 0 | O10: 19677.83 | P10: 82646.86 | Q10: 495881.19
A11: 04/11/2024 | B11: 1 - Factura A | C11: 6 | D11: 86462 | F11: 74454883728913 | G11: CUIT | H11: 30711553564 | I11: SALUDTEX SA | J11: 1 | K11: $ | L11: 249584 | M11: 0 | N11: 0 | O11: 0 | P11: 52412.64 | Q11: 301996.64
A12: 04/11/2024 | B12: 1 - Factura A | C12: 5 | D12: 160663 | F12: 74453883837723 | G12: CUIT | H12: 30598960093 | I12: SILVESTRIN FABRIS SOC RESP LTDA | J12: 1 | K12: $ | L12: 642151.5 | M12: 0 | N12: 0 | O12: 32107.58 | P12: 134851.81 | Q12: 809110.89
A13: 04/11/2024 | B13: 1 - Factura A | C13: 6 | D13: 86458 | F13: 74454881337054 | G13: CUIT | H13: 30711553564 | I13: SALUDTEX SA | J13: 1 | K13: $ | L13: 1182131.9 | M13: 0 | N13: 0 | O13: 0 | P13: 248247.71 | Q13: 1430379.6
A14: 04/11/2024 | B14: 1 - Factura A | C14: 6 | D14: 86459 | F14: 74454881511572 | G14: CUIT | H14: 30711553564 | I14: SALUDTEX SA | J14: 1 | K14: $ | L14: 831346.9 | M14: 0 | N14: 0 | O14: 0 | P14: 174582.85 | Q14: 1005929.8
A15: 04/11/2024 | B15: 1 - Factura A | C15: 6 | D15: 86460 | F15: 74454881999129 | G15: CUIT | H15: 30711553564 | I15: SALUDTEX SA | J15: 1 | K15: $ | L15: 224853.6 | M15: 0 | N15: 0 | O15: 0 | P15: 47219.26 | Q15: 272072.86
A16: 04/11/2024 | B16: 1 - Factura A | C16: 401 | D16: 100 | F16: 74454890527415 | G16: CUIT | H16: 30716234114 | I16: UZUMAKI S.A.S. | J16: 1220 | K16: USD | L16: =129.3*1220 -> 157746 | M16: 0 | N16: 0 | O16: 0 | P16: =+L16*0.21 -> 33126.66 | Q16: =+P16+L16 -> 190872.66
A17: 04/11/2024 | B17: 1 - Factura A | C17: 1 | D17: 649205 | F17: 74469903137915 | G17: CUIT | H17: 33716307749 | I17: VERISURE ARGENTINA MONITOREO DE ALARMAS SA | J17: 1 | K17: $ | L17: 34999 | M17: 0 | N17: 0 | O17: 1749.95 | P17: 7349.79 | Q17: 44098.74
A18: 04/11/2024 | B18: 1 - Factura A | C18: 2 | D18: 221 | F18: 74452914341353 | G18: CUIT | H18: 30605344352 | I18: CONSORCIO BARTOLOME MITRE 2466 | J18: 1 | K18: $ | L18: 834000 | M18: 0 | N18: 0 | O18: 0 | P18: 175140 | Q18: 1009140
A19: 04/11/2024 | B19: 3 - Nota de Crédito A | C19: 6 | D19: 12145 | F19: 74454883499642 | G19: CUIT | H19: 30711553564 | I19: SALUDTEX SA | J19: 1 | K19: $ | L19: -145916.26 | M19: 0 | N19: 0 | O19: 0 | P19: =+L19*0.21 -> -30642.415 | Q19: =+P19+L19 -> -176558.67
A20: 04/11/2024 | B20: 11 - Factura C | C20: 3 | D20: 9725 | F20: 74456937615061 | G20: CUIT | H20: 20167634436 | I20: DEMARIA AUGUSTO CARLOS | J20: 1 | K20: $ | O20: 0 | Q20: 4570
A21: 04/11/2024 | B21: 11 - Factura C | C21: 2 | D21: 313 | F21: 74448830666315 | G21: CUIT | H21: 27265832178 | I21: BLASCO MARIA GUADALUPE | J21: 1 | K21: $ | O21: 0 | Q21: 3200000
A22: 04/11/2024 | B22: 11 - Factura C | C22: 3 | D22: 893 | F22: 74453925401501 | G22: CUIT | H22: 20086277523 | I22: BOTINDARI JUAN CARLOS | J22: 1 | K22: $ | O22: 0 | Q22: 275500
A23: 06/11/2024 | B23: 1 - Factura A | C23: 1 | D23: 106971 | F23: 74459220885612 | G23: CUIT | H23: 30714864269 | I23: CONTABILIUM S.A. | J23: 1 | K23: $ | L23: 115939.17 | M23: 0 | N23: 0 | O23: 0 | P23: 24347.23 | Q23: 140286.4
A24: 06/11/2024 | B24: 1 - Factura A | C24: 17 | D24: 10884 | F24: 74450210166030 | G24: CUIT | H24: 30661143610 | I24: ORTOPEDIA BERNAT SRL | J24: 1 | K24: $ | L24: 565493.55 | M24: 0 | N24: 0 | O24: 28274.68 | P24: 118753.65 | Q24: 712521.88
A25: 06/11/2024 | B25: 1 - Factura A | C25: 8 | D25: 1712 | F25: 74451209572827 | G25: CUIT | H25: 30708973501 | I25: ASIAL S.R.L. | J25: 1 | K25: $ | L25: 831850 | M25: 0 | N25: 0 | O25: 0 | P25: 174688.5 | Q25: 1006538.5
A26: 06/11/2024 | B26: 11 - Factura C | C26: 1 | D26: 9 | F26: 74453269307006 | G26: CUIT | H26: 27443612713 | I26: MIGOYA MORIONDO SOFIA | J26: 1 | K26: $ | O26: 0 | Q26: 850000
A27: 07/11/2024 | B27: 1 - Factura A | C27: 5015 | D27: 663243 | F27: 74454290535475 | G27: CUIT | H27: 30574876474 | I27: AUTOPISTAS URBANAS S A | J27: 1 | K27: $ | L27: 5655.84 | M27: 0 | N27: 0 | O27: 735.25 | P27: 1187.72 | Q27: 7578.81
A28: 07/11/2024 | B28: 1 - Factura A | C28: 2 | D28: 908 | F28: 74459364672319 | G28: CUIT | H28: 20272865869 | I28: DI FEO MARTIN EZEQUIEL | J28: 1 | K28: $ | L28: 126700 | M28: 0 | N28: 0 | O28: 0 | P28: 26607 | Q28: 153307
A29: 07/11/2024 | B29: 11 - Factura C | C29: 2 | D29: 514 | F29: 74451358198277 | G29: CUIT | H29: 27299725761 | I29: TURSARKISIAN MISISIAN VERONICA GEMA | J29: 1 | K29: $ | O29: 0 | Q29: 460000
A30: 08/11/2024 | B30: 1 - Factura A | C30: 2 | D30: 909 | F30: 74459437726799 | G30: CUIT | H30: 20272865869 | I30: DI FEO MARTIN EZEQUIEL | J30: 1 | K30: $ | L30: 10050 | M30: 0 | N30: 0 | O30: 0 | P30: 2110.5 | Q30: 12160.5
A31: 08/11/2024 | B31: 1 - Factura A | C31: 4 | D31: 38780 | F31: 74459471135405 | G31: CUIT | H31: 20289111329 | I31: LEDESMA EMILIANO RUBEN | J31: 1 | K31: $ | L31: 585348.09 | M31: 0 | N31: 0 | O31: 0 | P31: 122923.1 | Q31: 708271.19
A32: 08/11/2024 | B32: 1 - Factura A | C32: 5 | D32: 2014 | F32: 74456481045397 | G32: CUIT | H32: 30712187316 | I32: ITALOMED PRODUCTOS SRL | J32: 1 | K32: $ | L32: 263903.45 | M32: 0 | N32: 0 | O32: 0 | P32: 55419.72 | Q32: 319323.17
A33: 08/11/2024 | B33: 1 - Factura A | C33: 120 | D33: 5322 | F33: 74455493316593 | G33: CUIT | H33: 30587197215 | I33: PANATEL SOCIEDAD ANONIMA | J33: 1 | K33: $ | L33: 68595.04 | M33: 0 | N33: 0 | O33: 3429.75 | P33: 14404.96 | Q33: 86429.75
A34: 09/11/2024 | B34: 1 - Factura A | C34: 3101 | D34: 197858 | F34: 74457706084453 | G34: CUIT | H34: 30678814357 | I34: TELEFONICA MOVILES ARGENTINA SOCIEDAD ANONIMA | J34: 1 | K34: $ | L34: 68662.57 | M34: 0 | N34: 0 | O34: 5493.01 | P34: 18538.89 | Q34: 92694.47
A35: 11/11/2024 | B35: 1 - Factura A | C35: 2 | D35: 255 | F35: 74463794655257 | G35: CUIT | H35: 27144282383 | I35: SCHEJTER LILA ELISA | J35: 1 | K35: $ | L35: 50000 | M35: 0 | N35: 0 | O35: 0 | P35: 10500 | Q35: 60500
A36: 11/11/2024 | B36: 1 - Factura A | C36: 7 | D36: 6 | F36: 74463805989277 | G36: CUIT | H36: 27325223273 | I36: SOUSA ALDERETE ALEJANDRA MABEL | J36: 1 | K36: $ | L36: 850000 | M36: 0 | N36: 0 | O36: 0 | P36: 178500 | Q36: 1028500
A37: 12/11/2024 | B37: 1 - Factura A | C37: 1 | D37: 5318 | F37: 74461943651694 | G37: CUIT | H37: 30715141201 | I37: REHAB S.R.L. | J37: 1 | K37: $ | L37: 273915 | M37: 0 | N37: 0 | O37: 0 | P37: 57522.15 | Q37: 331437.15
A38: 12/11/2024 | B38: 1 - Factura A | C38: 17 | D38: 2449 | F38: 74461967994767 | G38: CUIT | H38: 30711764921 | I38: RELIEF CENTER S.R.L. | J38: 1 | K38: $ | L38: 305928 | M38: 0 | N38: 0 | O38: 0 | P38: 64244.88 | Q38: 370172.88
A39: 12/11/2024 | B39: 1 - Factura A | C39: 1 | D39: 5319 | F39: 74461944646171 | G39: CUIT | H39: 30715141201 | I39: REHAB S.R.L. | J39: 1 | K39: $ | L39: 665437.5 | M39: 0 | N39: 0 | O39: 0 | P39: 139741.88 | Q39: 805179.38
A40: 12/11/2024 | B40: 1 - Factura A | C40: 5 | D40: 38 | F40: 74462965211526 | G40: CUIT | H40: 30707370552 | I40: RAKE S.A. | J40: 1 | K40: $ | L40: 950000 | M40: 0 | N40: 0 | O40: 0 | P40: 199500 | Q40: 1149500
A41: 12/11/2024 | B41: 11 - Factura C | C41: 1 | D41: 74 | F41: 74464988509063 | G41: CUIT | H41: 23281233084 | I41: DRUETTA ANDREA MARIEL | J41: 1 | K41: $ | O41: 0 | Q41: 240000
A42: 13/11/2024 | B42: 1 - Factura A | C42: 6 | D42: 54963 | F42: 74468097357588 | G42: CUIT | H42: 30710177658 | I42: TARGET MEDICAL S.A. | J42: 1 | K42: $ | L42: 372380 | M42: 0 | N42: 0 | O42: 0 | P42: 78199.8 | Q42: 450579.8
A43: 13/11/2024 | B43: 1 - Factura A | C43: 3 | D43: 7984 | F43: 74469063850739 | G43: CUIT | H43: 33708218699 | I43: MANGGINI PABLO Y MANGGINI ULISES SOC. DE HECHO. | J43: 1 | K43: $ | L43: 19000 | M43: 0 | N43: 0 | O43: 0 | P43: 3990 | Q43: 22990
A44: 13/11/2024 | B44: 11 - Factura C | C44: 2 | D44: 114 | F44: 74468106749889 | G44: CUIT | H44: 27315710508 | I44: RIVERO GABRIELA ROCIO | J44: 1 | K44: $ | O44: 0 | Q44: 440000
A45: 14/11/2024 | B45: 1 - Factura A | C45: 7 | D45: 19529 | F45: 74468190032957 | G45: CUIT | H45: 30709214078 | I45: REHAVITA S.A. | J45: 1 | K45: $ | L45: 1669800 | M45: 0 | N45: 0 | O45: 0 | P45: 350658 | Q45: 2020458
A46: 14/11/2024 | B46: 1 - Factura A | C46: 2 | D46: 10948 | F46: 74462230615067 | G46: CUIT | H46: 30714331082 | I46: ORTOPEDIA CASA ESCALADA S.R.L. | J46: 1 | K46: $ | L46: 438505.63 | M46: 0 | N46: 0 | O46: 0 | P46: 46043.09 | Q46: 484548.72
A47: 14/11/2024 | B47: 1 - Factura A | C47: 32 | D47: 151158 | F47: 74467244260893 | G47: CUIT | H47: 30708847247 | I47: EXPRESO LANCIONI S.A. | J47: 1 | K47: $ | L47: 25084.76 | M47: 0 | N47: 0 | O47: 1254.24 | P47: 5267.8 | Q47: 31606.8
A48: 14/11/2024 | B48: 1 - Factura A | C48: 2 | D48: 920 | F48: 74469229069072 | G48: CUIT | H48: 20272865869 | I48: DI FEO MARTIN EZEQUIEL | J48: 1 | K48: $ | L48: 184250 | M48: 0 | N48: 0 | O48: 0 | P48: 38692.5 | Q48: 222942.5
A49: 14/11/2024 | B49: 1 - Factura A | C49: 7 | D49: 3420 | F49: 74464213293743 | G49: CUIT | H49: 20284183534 | I49: FURLANETTO MARTIN | J49: 1 | K49: $ | L49: 3801.66 | M49: 0 | N49: 0 | O49: 0 | P49: 798.35 | Q49: 4600.01
A50: 14/11/2024 | B50: 11 - Factura C | C50: 3 | D50: 902 | F50: 74463203107635 | G50: CUIT | H50: 20086277523 | I50: BOTINDARI JUAN CARLOS | J50: 1 | K50: $ | O50: 0 | Q50: 145000
A51: 14/11/2024 | B51: 11 - Factura C | C51: 1 | D51: 1 | F51: 74461185430648 | G51: CUIT | H51: 20236043631 | I51: RODRIGUEZ PATRICIO SALVADOR | J51: 1 | K51: $ | O51: 0 | Q51: 500000
A52: 15/11/2024 | B52: 1 - Factura A | C52: 11 | D52: 93020 | F52: 74464338904334 | G52: CUIT | H52: 30526582884 | I52: EXPRESO MAR DEL PLATA SOCIEDAD ANONIMA | J52: 1 | K52: $ | L52: 59818.18 | M52: 0 | N52: 0 | O52: 0 | P52: 12561.82 | Q52: 72380
A53: 16/11/2024 | B53: 1 - Factura A | C53: 5015 | D53: 664668 | F53: 74464508031568 | G53: CUIT | H53: 30574876474 | I53: AUTOPISTAS URBANAS S A | J53: 1 | K53: $ | L53: 16419.08 | M53: 0 | N53: 0 | O53: 2134.48 | P53: 3448 | Q53: 22001.56
A54: 16/11/2024 | B54: 1 - Factura A | C54: 50 | D54: 3901222 | F54: 74466550181364 | G54: CUIT | H54: 30714112836 | I54: AUTOPISTAS DE BUENOS AIRES (AUBASA) SA | J54: 1 | K54: $ | L54: 1818.18 | M54: 0 | N54: 0 | O54: 0 | P54: 381.82 | Q54: 2200
A55: 17/11/2024 | B55: 1 - Factura A | C55: 4 | D55: 1340 | F55: 74464586155301 | G55: CUIT | H55: 30712434704 | I55: BLAUGRANA EVENTOS S.R.L. | J55: 1 | K55: $ | L55: 27438.02 | M55: 0 | N55: 0 | O55: 0 | P55: 5761.98 | Q55: 33200
A56: 17/11/2024 | B56: 1 - Factura A | C56: 629 | D56: 5613318 | F56: 34463990415580 | G56: CUIT | H56: 30663498513 | I56: GRUPO CONCESIONARIO DEL OESTE SA | J56: 1 | K56: $ | L56: 2457.58 | M56: 0 | N56: 0 | O56: 122.88 | P56: 516.08 | Q56: 3096.54
A57: 17/11/2024 | B57: 1 - Factura A | C57: 711 | D57: 6394443 | F57: 34469612843253 | G57: CUIT | H57: 30677237119 | I57: AUTOPISTAS DEL SOL S A | J57: 1 | K57: $ | L57: 3312.36 | M57: 0 | N57: 99.37 | O57: 165.62 | P57: 695.58 | Q57: 4272.93
A58: 18/11/2024 | B58: 1 - Factura A | C58: 2 | D58: 28 | F58: 74475105900652 | G58: CUIT | H58: 27243660535 | I58: BARD MARISA SILVIA | J58: 1 | K58: $ | L58: 414537 | M58: 0 | N58: 0 | O58: 0 | P58: 87052.77 | Q58: 501589.77
A59: 19/11/2024 | B59: 1 - Factura A | C59: 6 | D59: 55038 | F59: 74478753732061 | G59: CUIT | H59: 30710177658 | I59: TARGET MEDICAL S.A. | J59: 1 | K59: $ | L59: 272630 | M59: 0 | N59: 0 | O59: 0 | P59: 57252.3 | Q59: 329882.3
A60: 19/11/2024 | B60: 1 - Factura A | C60: 5 | D60: 161142 | F60: 74473748657612 | G60: CUIT | H60: 30598960093 | I60: SILVESTRIN FABRIS SOC RESP LTDA | J60: 1 | K60: $ | L60: 1576702.5 | M60: 0 | N60: 0 | O60: 78835.13 | P60: 331107.52 | Q60: 1986645.1
A61: 19/11/2024 | B61: 1 - Factura A | C61: 6 | D61: 812 | F61: 74479721006393 | G61: CUIT | H61: 20289111329 | I61: LEDESMA EMILIANO RUBEN | J61: 1 | K61: $ | L61: 1243125 | M61: 0 | N61: 0 | O61: 0 | P61: 261056.25 | Q61: 1504181.2
A62: 19/11/2024 | B62: 1 - Factura A | C62: 4264 | D62: 4655209 | F62: 74478898671690 | G62: CUIT | H62: 30639453738 | I62: TELECOM ARGENTINA SOCIEDAD ANONIMA | J62: 1 | K62: $ | L62: 25106.4 | M62: 0 | N62: 0 | O62: 2008.51 | P62: 5272.34 | Q62: 32387.25
A63: 19/11/2024 | B63: 1 - Factura A | C63: 5 | D63: 34 | F63: 74473808176750 | G63: CUIT | H63: 20929183143 | I63: MA JUN | J63: 1 | K63: $ | L63: 70000 | M63: 0 | N63: 0 | O63: 0 | P63: 14700 | Q63: 84700
A64: 20/11/2024 | B64: 1 - Factura A | C64: 4 | D64: 38881 | F64: 74479851202745 | G64: CUIT | H64: 20289111329 | I64: LEDESMA EMILIANO RUBEN | J64: 1 | K64: $ | L64: 188195.56 | M64: 0 | N64: 0 | O64: 0 | P64: 39521.07 | Q64: 227716.63
A65: 20/11/2024 | B65: 11 - Factura C | C65: 1 | D65: 15 | F65: 74473823813070 | G65: CUIT | H65: 20464199633 | I65: OVIEDO JIMENEZ TIZIANO LIONEL | J65: 1 | K65: $ | O65: 0 | Q65: 759750
A66: 20/11/2024 | B66: 11 - Factura C | C66: 3 | D66: 2379 | F66: 74471832477768 | G66: CUIT | H66: 20182999661 | I66: KLAINER ABEL JAVIER | J66: 1 | K66: $ | O66: 0 | Q66: 14000
A67: 20/11/2024 | B67: 11 - Factura C | C67: 1 | D67: 16 | F67: 74485868422002 | G67: CUIT | H67: 27443612705 | I67: MIGOYA MORIONDO MARIA INES | J67: 1 | K67: $ | O67: 0 | Q67: 450000
A68: 21/11/2024 | B68: 1 - Factura A | C68: 5 | D68: 3171882 | F68: 74475013916155 | G68: CUIT | H68: 30702652975 | I68: NSS SA | J68: 1 | K68: $ | L68: 28528.6 | M68: 0 | N68: 0 | O68: 1426.43 | P68: 5991.01 | Q68: 35946.04
A69: 21/11/2024 | B69: 1 - Factura A | C69: 6 | D69: 55075 | F69: 74478014571317 | G69: CUIT | H69: 30710177658 | I69: TARGET MEDICAL S.A. | J69: 1 | K69: $ | L69: 0 | M69: 0 | N69: 0 | O69: 0 | P69: 0 | Q69: 0
A70: 21/11/2024 | B70: 1 - Factura A | C70: 2 | D70: 938 | F70: 74479020740116 | G70: CUIT | H70: 20272865869 | I70: DI FEO MARTIN EZEQUIEL | J70: 1 | K70: $ | L70: 216450 | M70: 0 | N70: 0 | O70: 0 | P70: 45454.5 | Q70: 261904.5
A71: 21/11/2024 | B71: 1 - Factura A | C71: 2 | D71: 257 | F71: 74473019850081 | G71: CUIT | H71: 27144282383 | I71: SCHEJTER LILA ELISA | J71: 1 | K71: $ | L71: 300000 | M71: 0 | N71: 0 | O71: 0 | P71: 63000 | Q71: 363000
A72: 21/11/2024 | B72: 11 - Factura C | C72: 2 | D72: 515 | F72: 74471026621718 | G72: CUIT | H72: 27299725761 | I72: TURSARKISIAN MISISIAN VERONICA GEMA | J72: 1 | K72: $ | O72: 0 | Q72: 570000
A73: 22/11/2024 | B73: 1 - Factura A | C73: 2 | D73: 7795 | F73: 74477094882209 | G73: CUIT | H73: 30694549817 | I73: DISEÑOS JERY S R L | J73: 1 | K73: $ | L73: 89807.43 | M73: 0 | N73: 0 | O73: 0 | P73: 18859.56 | Q73: 108666.99
A74: 22/11/2024 | B74: 11 - Factura C | C74: 1 | D74: 158 | F74: 74470131360714 | G74: CUIT | H74: 27338342840 | I74: CANCINO PAMELA RITA | J74: 1 | K74: $ | O74: 0 | Q74: 223271
A75: 23/11/2024 | B75: 1 - Factura A | C75: 5015 | D75: 668157 | F75: 74474212487392 | G75: CUIT | H75: 30574876474 | I75: AUTOPISTAS URBANAS S A | J75: 1 | K75: $ | L75: 21292.13 | M75: 0 | N75: 0 | O75: 2767.96 | P75: 4471.33 | Q75: 28531.42
A76: 25/11/2024 | B76: 1 - Factura A | C76: 2 | D76: 39919 | F76: 74480471113802 | G76: CUIT | H76: 30717273520 | I76: SMART IT SOLUTIONS S.R.L | J76: 1 | K76: $ | L76: 6928.1 | M76: 0 | N76: 0 | O76: 0 | P76: 1454.9 | Q76: 8383
A77: 25/11/2024 | B77: 1 - Factura A | C77: 16 | D77: 27 | F77: 74483455137169 | G77: CUIT | H77: 27310367813 | I77: LA BRUNA MARIA VIRGINIA | J77: 1 | K77: $ | L77: 133140.5 | M77: 0 | N77: 0 | O77: 0 | P77: 27959.5 | Q77: 161100
A78: 25/11/2024 | B78: 1 - Factura A | C78: 6 | D78: 87011 | F78: 74484452643029 | G78: CUIT | H78: 30711553564 | I78: SALUDTEX SA | J78: 1 | K78: $ | L78: 78414 | M78: 0 | N78: 0 | O78: 0 | P78: 16466.94 | Q78: 94880.94
A79: 25/11/2024 | B79: 1 - Factura A | C79: 1 | D79: 5468 | F79: 74481385458086 | G79: CUIT | H79: 30715141201 | I79: REHAB S.R.L. | J79: 1 | K79: $ | L79: 7781132.4 | M79: 0 | N79: 0 | O79: 0 | P79: 1634037.8 | Q79: 9415170.2
A80: 25/11/2024 | B80: 11 - Factura C | C80: 1 | D80: 17 | F80: 74485868562394 | G80: CUIT | H80: 27443612705 | I80: MIGOYA MORIONDO MARIA INES | J80: 1 | K80: $ | O80: 0 | Q80: 450000
A81: 26/11/2024 | B81: 1 - Factura A | C81: 1001 | D81: 5588 | F81: 74483571832189 | G81: CUIT | H81: 30715848623 | I81: BIENESTAR Y SOLUCIONES S.R.L. | J81: 1 | K81: $ | L81: 35044.15 | M81: 0 | N81: 0 | O81: 0 | P81: 7359.27 | Q81: 42403.42
A82: 26/11/2024 | B82: 1 - Factura A | C82: 5 | D82: 161347 | F82: 74483576457080 | G82: CUIT | H82: 30598960093 | I82: SILVESTRIN FABRIS SOC RESP LTDA | J82: 1 | K82: $ | L82: 946021.5 | M82: 0 | N82: 0 | O82: 47301.08 | P82: 198664.52 | Q82: 1191987.1
A83: 28/11/2024 | B83: 1 - Factura A | C83: 2 | D83: 952 | F83: 74489852320753 | G83: CUIT | H83: 20272865869 | I83: DI FEO MARTIN EZEQUIEL | J83: 1 | K83: $ | L83: 125000 | M83: 0 | N83: 0 | O83: 0 | P83: 26250 | Q83: 151250
A84: 29/11/2024 | B84: 1 - Factura A | C84: 1000 | D84: 209165 | F84: 74483965400795 | G84: CUIT | H84: 30715123483 | I84: ITPROUSER S.A. | J84: 1 | K84: $ | L84: 11314.04 | M84: 0 | N84: 0 | O84: 471.07 | P84: 2375.95 | Q84: 14161.06
A85: 29/11/2024 | B85: 1 - Factura A | C85: 68 | D85: 68872 | F85: 74484130854044 | G85: CUIT | H85: 30703088534 | I85: MERCADOLIBRE S.R.L. | J85: 1 | K85: $ | L85: 59228.63 | M85: 0 | N85: 0 | O85: 4738.29 | P85: 12438.01 | Q85: 76404.93
A86: 29/11/2024 | B86: 1 - Factura A | C86: 1 | D86: 108 | F86: 74487974528093 | G86: CUIT | H86: 20359609087 | I86: BUGALLO FACUNDO | J86: 1 | K86: $ | L86: 2973555 | M86: 0 | N86: 0 | O86: 0 | P86: 624446.55 | Q86: 3598001.5
A87: 29/11/2024 | B87: 11 - Factura C | C87: 5 | D87: 173 | F87: 74489993015542 | G87: CUIT | H87: 27062343449 | I87: FERREIRA LILIANA INES | J87: 1 | K87: $ | O87: 0 | Q87: 100000
A88: 29/11/2024 | B88: 11 - Factura C | C88: 5 | D88: 172 | F88: 74489992771285 | G88: CUIT | H88: 27062343449 | I88: FERREIRA LILIANA INES | J88: 1 | K88: $ | O88: 0 | Q88: 250000
L89: =SUM(L3:L88) -> 33676874 | M89: =SUM(M3:M88) -> 0 | N89: =SUM(N3:N88) -> 198.74 | O89: =SUM(O3:O88) -> 440878.75 | P89: =SUM(P3:P88) -> 7031917.2 | Q89: =SUM(Q3:Q88) -> 50481960
A100: Comprobantes AFIP no recepcionados
A106: Fecha | B106: Tipo | C106: Punto de Venta | D106: Número Desde | E106: Número Hasta | F106: Cód. Autorización | G106: Tipo Doc. Emisor | H106: Nro. Doc. Emisor | I106: Denominación Emisor | J106: Tipo Cambio | K106: Moneda | L106: Imp. Neto Gravado | M106: Imp. Neto No Gravado | N106: Imp. Op. Exentas | O106: Otros Tributos | P106: IVA | Q106: Imp. Total
A107: 06/11/2024 | B107: 1 - Factura A | C107: 700 | D107: 2041657 | F107: 74452187708519 | G107: CUIT | H107: 30715804812 | I107: CORREDORES VIALES SOCIEDAD ANONIMA | J107: 1 | K107: $ | L107: 1923.32 | M107: 0 | N107: 0 | O107: 0 | P107: 403.9 | Q107: 2327.22
A108: 06/11/2024 | B108: 1 - Factura A | C108: 700 | D108: 2041658 | F108: 74452187708593 | G108: CUIT | H108: 30715804812 | I108: CORREDORES VIALES SOCIEDAD ANONIMA | J108: 1 | K108: $ | L108: 3077.32 | M108: 0 | N108: 0 | O108: 153.87 | P108: 646.24 | Q108: 3877.43
A109: 07/11/2024 | B109: 1 - Factura A | C109: 12 | D109: 1790771 | F109: 74454430790967 | G109: CUIT | H109: 30709776564 | I109: PROSEGUR ACTIVA ARGENTINA SA | J109: 1 | K109: $ | L109: 129241 | M109: 0 | N109: 0 | O109: 6462.05 | P109: 27140.61 | Q109: 162843.68
A110: 14/11/2024 | B110: 1 - Factura A | C110: 5 | D110: 19996 | F110: 74464186228461 | G110: CUIT | H110: 30715668994 | I110: SS METAL MECANICA S.R.L. | J110: 1 | K110: $ | L110: 18420 | M110: 0 | N110: 0 | O110: 0 | P110: 3868.2 | Q110: 22288.2
A111: 15/11/2024 | B111: 3 - Nota de Crédito A | C111: 3177 | D111: 62698 | F111: 74467368972434 | G111: CUIT | H111: 30678814357 | I111: TELEFONICA MOVILES ARGENTINA SOCIEDAD ANONIMA | J111: 1 | K111: $ | L111: -3703.7 | M111: 0 | N111: 0 | O111: -296.3 | P111: -1000 | Q111: -5000
A112: 15/11/2024 | B112: 3 - Nota de Crédito A | C112: 5 | D112: 691 | F112: 74464366952555 | G112: CUIT | H112: 30715668994 | I112: SS METAL MECANICA S.R.L. | J112: 1 | K112: $ | L112: -18420 | M112: 0 | N112: 0 | O112: 0 | P112: -3868.2 | Q112: -22288.2
A113: 16/11/2024 | B113: 1 - Factura A | C113: 5009 | D113: 1067282 | F113: 74464521271177 | G113: CUIT | H113: 30574876474 | I113: AUTOPISTAS URBANAS S A | J113: 1 | K113: $ | L113: 4691.18 | M113: 0 | N113: 0 | O113: 609.85 | P113: 985.14 | Q113: 6286.17
A114: 16/11/2024 | B114: 1 - Factura A | C114: 11 | D114: 65381 | F114: 74462512069738 | G114: CUIT | H114: 30711091552 | I114: BIGBOX S.A. | J114: 1 | K114: $ | L114: 57851.24 | M114: 0 | N114: 0 | O114: 0 | P114: 12148.76 | Q114: 70000
A115: 17/11/2024 | B115: 6 - Factura B | C115: 102 | D115: 4004628 | F115: 74465540132147 | G115: CUIT | H115: 30701307115 | I115: DESPEGAR COM AR SA | J115: 1 | K115: $ | L115: 0 | M115: 0 | N115: 0 | O115: 315.6 | P115: 0 | Q115: 7953.14
...
