Workbook
Name partner_id: Configuracion!$B$332

Sheet Configuracion
F1: CUIT | G1: Cargar sin guiones
F2: RAZON SOCIAL | G2: Maximo 30 caracteres
A3: CUIT | B3: RAZON SOCIAL | C3: DETALLE | F3: DETALLE | G3: Cargar tipo de gasto
A4: 30628205090 | B4: ALBAMIE SA | C4: CLIENTE
A5: 30711678820 | B5: 2PSI INGENIERIA SRL | C5: PROVEEDOR
A6: 33716367539 | B6: 3PI S.A.S. | C6: PROVEEDOR
A7: 30660373108 | B7: ABC SA | C7: VARIOS
A8: 20300210881 | B8: ABOY DIEGO OSCAR | C8: PROVEEDOR
A9: 27229910782 | B9: ABUGAUCH MARIA DE LOS ANGELES | C9: PROVEEDOR
A10: 20242709897 | B10: ABUGAUCH VICTOR HUGO | C10: PROVEEDOR
A11: 20281669053 | B11: ACOSTA JAVIER GUSTAVO | C11: FLETE
A12: 20174240125 | B12: ACOSTA OSCAR ISIDRO | C12: VARIOS
A13: 30641659106 | B13: AGRISOL SA | C13: VARIOS
A14: 33709914109 | B14: ALAN COLLECTION SA | C14: VARIOS
A15: 20267161616 | B15: ALBAJARI DIEGO MARCOS | C15: VARIOS
... A155: 30537679855 | B155: ESTACION LIMA SA | C155: VARIOS
A156: 30-56864959-8 | B156: EXPRESO BISONTE SRL | C156: FLETE
A157: 30708542349 | B157: EXPRESO FORMOSA SRL | C157: FLETE
A158: 30526582884 | B158: EXPRESO MAR DEL PLATA SA | C158: FLETE
A159: 30577744579 | B159: EXPRESO TROLE SRL | C159: FLETE
A160: 30715949292 | B160: EYPAPEL SAS | C160: GASTOS VARIOS
A161: 30715980807 | B161: FABORT SRL | C161: PROVEEDOR
A162: 20359718765 | B162: FAIL ABRAHAM | C162: VARIOS
A163: 30643518364 | B163: FARMACIA DE MEDRANO SCS | C163: PROVEEDOR
A164: 30692138747 | B164: FARMACITY SA | C164: VARIOS
A165: 33712234429 | B165: FEDAGAS SA | C165: VARIOS
A166: 20353576012 | B166: FEDERICO PABLO FEOLA | C166: VARIOS
A167: 20343766441 | B167: FERNANDEZ MAURO | C167: TALLER
A168: 27062343449 | B168: FERREIRA LILIANA INES | C168: FLETE
... A538: 30693066022 | B538: Mg Farmaceutica Sociedad En CS | C538: VARIOS

Sheet AGOSTO
A1: ORTOPEDIA GEMINIS S.A. | J1: 45139
A4: LIBRO IVA COMPRAS
A6: FACTURAS A
A7: FECHA | B7: PTO VTA | C7: FAC A | D7: CUIT | E7: RAZON SOCIAL | F7: NETO | G7: IVA 21% | H7: IVA 27% | I7: IVA 10,5% | J7: P IVA | K7: IIBB CF | L7: IIBB BS | M7: NO GRAV | N7: OTROS | O7: TOTAL | P7: DETALLE
A8: 09/04/2023 | B8: 11 | C8: 1535829 | D8: 30709776564 | E8: =VLOOKUP(D8,Configuracion!$A$4:$C$591,2,FALSE) -> PROSEGUR ACTIVA ARG SA | F8: 14992.91 | G8: =F8*21% -> 3148.5111 | K8: =+F8*0.035 -> 524.75185 | O8: =SUM(F8:N8) -> 18666.173 | P8: =VLOOKUP(D8,Configuracion!$A$4:$C$591,3,FALSE) -> SEGUROS
A9: 45111 | B9: 1055 | C9: 546 | D9: 30685849751 | E9: =VLOOKUP(D9,Configuracion!$A$4:$C$591,2,FALSE) -> DIA ARGENTINA SA | F9: 914.88 | G9: =F9*21% -> 192.1248 | O9: =SUM(F9:N9) -> 1107.0048 | P9: =VLOOKUP(D9,Configuracion!$A$4:$C$591,3,FALSE) -> VARIOS
A10: 45124 | B10: 17 | C10: 1153 | D10: 30711764921 | E10: =VLOOKUP(D10,Configuracion!$A$4:$C$591,2,FALSE) -> RELIEF CENTER SRL | F10: 14834 | G10: =F10*21% -> 3115.14 | O10: =SUM(F10:N10) -> 17949.14 | P10: =VLOOKUP(D10,Configuracion!$A$4:$C$591,3,FALSE) -> PROVEEDOR
A11: 45124 | B11: 4264 | C11: 2395412 | D11: 30639453738 | E11: =VLOOKUP(D11,Configuracion!$A$4:$C$591,2,FALSE) -> TELECOM ARGENTINA SA | F11: =10586.78+3851.24 -> 14438.02 | G11: =F11*21% -> 3031.9842 | J11: 433.14 | K11: 505.33 | O11: =SUM(F11:N11) -> 18408.474 | P11: =VLOOKUP(D11,Configuracion!$A$4:$C$591,3,FALSE) -> SERVICIO
A12: 45124 | B12: 13 | C12: 1208 | D12: 33709914109 | E12: =VLOOKUP(D12,Configuracion!$A$4:$C$591,2,FALSE) -> ALAN COLLECTION SA | F12: 4628.1 | G12: =F12*21% -> 971.901 | O12: =SUM(F12:N12) -> 5600.001 | P12: =VLOOKUP(D12,Configuracion!$A$4:$C$591,3,FALSE) -> VARIOS
A13: 45126 | B13: 17 | C13: 1161 | D13: 30711764921 | E13: =VLOOKUP(D13,Configuracion!$A$4:$C$591,2,FALSE) -> RELIEF CENTER SRL | F13: 39660 | G13: =F13*21% -> 8328.6 | O13: =SUM(F13:N13) -> 47988.6 | P13: =VLOOKUP(D13,Configuracion!$A$4:$C$591,3,FALSE) -> PROVEEDOR
A14: 45127 | B14: 7 | C14: 2010 | D14: 20284183534 | E14: =VLOOKUP(D14,Configuracion!$A$4:$C$591,2,FALSE) -> FURLANETTO MARTIN | F14: 2479.34 | G14: =F14*21% -> 520.6614 | O14: =SUM(F14:N14) -> 3000.0014 | P14: =VLOOKUP(D14,Configuracion!$A$4:$C$591,3,FALSE) -> VARIOS
A15: 45128 | B15: 7 | C15: 2019 | D15: 20284183534 | E15: =VLOOKUP(D15,Configuracion!$A$4:$C$591,2,FALSE) -> FURLANETTO MARTIN | F15: 1818.18 | G15: =F15*21% -> 381.8178 | O15: =SUM(F15:N15) -> 2199.9978 | P15: =VLOOKUP(D15,Configuracion!$A$4:$C$591,3,FALSE) -> VARIOS
A16: 45128 | B16: 7 | C16: 2020 | D16: 20284183534 | E16: =VLOOKUP(D16,Configuracion!$A$4:$C$591,2,FALSE) -> FURLANETTO MARTIN | F16: 851.25 | G16: =F16*21% -> 178.7625 | O16: =SUM(F16:N16) -> 1030.0125 | P16: =VLOOKUP(D16,Configuracion!$A$4:$C$591,3,FALSE) -> VARIOS
A17: 45128 | B17: 7 | C17: 2017 | D17: 20284183534 | E17: =VLOOKUP(D17,Configuracion!$A$4:$C$591,2,FALSE) -> FURLANETTO MARTIN | F17: 404.96 | G17: =F17*21% -> 85.0416 | O17: =SUM(F17:N17) -> 490.0016 | P17: =VLOOKUP(D17,Configuracion!$A$4:$C$591,3,FALSE) -> VARIOS
A18: 45128 | B18: 15 | C18: 23029 | D18: 30685116657 | E18: =VLOOKUP(D18,Configuracion!$A$4:$C$591,2,FALSE) -> MIRVAR SA | F18: 9890.73 | G18: =F18*21% -> 2077.0533 | N18: 1038.34 | O18: =SUM(F18:N18) -> 13006.123 | P18: =VLOOKUP(D18,Configuracion!$A$4:$C$591,3,FALSE) -> VARIOS
A19: 45131 | B19: 7 | C19: 2024 | D19: 20284183534 | E19: =VLOOKUP(D19,Configuracion!$A$4:$C$591,2,FALSE) -> FURLANETTO MARTIN | F19: 1603.31 | G19: =F19*21% -> 336.6951 | O19: =SUM(F19:N19) -> 1940.0051 | P19: =VLOOKUP(D19,Configuracion!$A$4:$C$591,3,FALSE) -> VARIOS
A20: 31/07/2023 | B20: 20 | C20: 156206 | D20: 30696850972 | E20: =VLOOKUP(D20,Configuracion!$A$4:$C$591,2,FALSE) -> CPS COMUNICACIONES SA | F20: 4302.05 | H20: =+F20*0.27 -> 1161.5535 | K20: =+F20*0.035 -> 150.57175 | O20: =SUM(F20:N20) -> 5614.1753 | P20: =VLOOKUP(D20,Configuracion!$A$4:$C$591,3,FALSE) -> SERVICIO
A21: 31/07/2023 | B21: 9044 | C21: 17802 | D21: 30678774495 | E21: =VLOOKUP(D21,Configuracion!$A$4:$C$591,2,FALSE) -> OPERADORA DE ESTAC. DE SERV SA | F21: 11747.47 | G21: =F21*21% -> 2466.9687 | M21: 785.56 | O21: =SUM(F21:N21) -> 14999.999 | P21: =VLOOKUP(D21,Configuracion!$A$4:$C$591,3,FALSE) -> VARIOS
A22: 31/07/2023 | B22: 9044 | C22: 17803 | D22: 30678774495 | E22: =VLOOKUP(D22,Configuracion!$A$4:$C$591,2,FALSE) -> OPERADORA DE ESTAC. DE SERV SA | F22: 2358.12 | G22: =F22*21% -> 495.2052 | M22: 157.69 | O22: =SUM(F22:N22) -> 3011.0152 | P22: =VLOOKUP(D22,Configuracion!$A$4:$C$591,3,FALSE) -> VARIOS
A23: 01/08/2023 | B23: 2 | C23: 190 | D23: 30605344352 | E23: =VLOOKUP(D23,Configuracion!$A$4:$C$591,2,FALSE) -> CONSORCIO BARTOLME MITRE 2466 | F23: 230000 | G23: =F23*21% -> 48300 | O23: =SUM(F23:N23) -> 278300 | P23: =VLOOKUP(D23,Configuracion!$A$4:$C$591,3,FALSE) -> CONSORCIO
A24: 01/08/2023 | B24: 10 | C24: 646 | D24: 23324039759 | E24: =VLOOKUP(D24,Configuracion!$A$4:$C$591,2,FALSE) -> RAGO DIEGO ORLANDO | F24: 17834.72 | G24: =F24*21% -> 3745.2912 | O24: =SUM(F24:N24) -> 21580.011 | P24: =VLOOKUP(D24,Configuracion!$A$4:$C$591,3,FALSE) -> VARIOS
A25: 01/08/2023 | B25: 7 | C25: 16138 | D25: 30709214078 | E25: =VLOOKUP(D25,Configuracion!$A$4:$C$591,2,FALSE) -> REHAVITA SA | F25: 1529952.5 | G25: 302414.59 | I25: 9437.72 | O25: =SUM(F25:N25) -> 1841804.8 | P25: =VLOOKUP(D25,Configuracion!$A$4:$C$591,3,FALSE) -> PROVEEDOR
A26: 01/08/2023 | B26: 7 | C26: 16142 | D26: 30709214078 | E26: =VLOOKUP(D26,Configuracion!$A$4:$C$591,2,FALSE) -> REHAVITA SA | F26: 37740 | I26: 3962.7 | O26: =SUM(F26:N26) -> 41702.7 | P26: =VLOOKUP(D26,Configuracion!$A$4:$C$591,3,FALSE) -> PROVEEDOR
A27: 01/08/2023 | B27: 4 | C27: 56 | D27: 20317488476 | E27: =VLOOKUP(D27,Configuracion!$A$4:$C$591,2,FALSE) -> VILLALBA MIGUEL ANGEL | F27: 170912 | G27: =F27*21% -> 35891.52 | O27: =SUM(F27:N27) -> 206803.52 | P27: =VLOOKUP(D27,Configuracion!$A$4:$C$591,3,FALSE) -> PROVEEDOR
A28: 02/08/2023 | B28: 2 | C28: 7361 | D28: 30694549817 | E28: =VLOOKUP(D28,Configuracion!$A$4:$C$591,2,FALSE) -> DISEÑOS JERY SRL | F28: 477494.37 | G28: =F28*21% -> 100273.82 | O28: =SUM(F28:N28) -> 577768.19 | P28: =VLOOKUP(D28,Configuracion!$A$4:$C$591,3,FALSE) -> PROVEEDOR
A29: 02/08/2023 | B29: 7 | C29: 16163 | D29: 30709214078 | E29: =VLOOKUP(D29,Configuracion!$A$4:$C$591,2,FALSE) -> REHAVITA SA | F29: 90596 | G29: =F29*21% -> 19025.16 | O29: =SUM(F29:N29) -> 109621.16 | P29: =VLOOKUP(D29,Configuracion!$A$4:$C$591,3,FALSE) -> PROVEEDOR
A30: 02/08/2023 | B30: 7 | C30: 16164 | D30: 30709214078 | E30: =VLOOKUP(D30,Configuracion!$A$4:$C$591,2,FALSE) -> REHAVITA SA | F30: 136437.5 | I30: 14325.94 | O30: =SUM(F30:N30) -> 150763.44 | P30: =VLOOKUP(D30,Configuracion!$A$4:$C$591,3,FALSE) -> PROVEEDOR
A31: 45141 | B31: 2 | C31: 6 | D31: 20272865869 | E31: =VLOOKUP(D31,Configuracion!$A$4:$C$591,2,FALSE) -> DI FEO MARTIN EZEQUIEL | F31: 43522.24 | G31: =F31*21% -> 9139.6704 | O31: =SUM(F31:N31) -> 52661.91 | P31: =VLOOKUP(D31,Configuracion!$A$4:$C$591,3,FALSE) -> PROVEEDOR
A32: 45141 | B32: 2 | C32: 1 | D32: 20272865869 | E32: =VLOOKUP(D32,Configuracion!$A$4:$C$591,2,FALSE) -> DI FEO MARTIN EZEQUIEL | F32: -3655.36 | G32: =F32*21% -> -767.6256 | O32: =SUM(F32:N32) -> -4422.9856 | P32: =VLOOKUP(D32,Configuracion!$A$4:$C$591,3,FALSE) -> PROVEEDOR
A33: 03/08/2023 | B33: 7 | C33: 27748 | D33: 20271532483 | E33: =VLOOKUP(D33,Configuracion!$A$4:$C$591,2,FALSE) -> DIEGO MARTIN RIOS | F33: 1362250.2 | G33: =F33*21% -> 286072.54 | K33: 47678.76 | O33: =SUM(F33:N33) -> 1696001.5 | P33: =VLOOKUP(D33,Configuracion!$A$4:$C$591,3,FALSE) -> PROVEEDOR
A34: 03/08/2023 | B34: 7 | C34: 27749 | D34: 20271532483 | E34: =VLOOKUP(D34,Configuracion!$A$4:$C$591,2,FALSE) -> DIEGO MARTIN RIOS | F34: 1702175.8 | G34: =F34*21% -> 357456.92 | K34: 59576.15 | O34: =SUM(F34:N34) -> 2119208.9 | P34: =VLOOKUP(D34,Configuracion!$A$4:$C$591,3,FALSE) -> PROVEEDOR
A35: 03/08/2023 | B35: 7 | C35: 27750 | D35: 20271532483 | E35: =VLOOKUP(D35,Configuracion!$A$4:$C$591,2,FALSE) -> DIEGO MARTIN RIOS | F35: 79172.1 | G35: =F35*21% -> 16626.141 | K35: 2771.02 | O35: =SUM(F35:N35) -> 98569.261 | P35: =VLOOKUP(D35,Configuracion!$A$4:$C$591,3,FALSE) -> PROVEEDOR
A36: 03/08/2023 | B36: 6 | C36: 469 | D36: 20289111329 | E36: =VLOOKUP(D36,Configuracion!$A$4:$C$591,2,FALSE) -> R. N. LEDESMA | F36: 9936277.7 | G36: =F36*21% -> 2086618.3 | O36: =SUM(F36:N36) -> 12022896 | P36: =VLOOKUP(D36,Configuracion!$A$4:$C$591,3,FALSE) -> PROVEEDOR
A37: 03/08/2023 | B37: 6 | C37: 49420 | D37: 30710177658 | E37: =VLOOKUP(D37,Configuracion!$A$4:$C$591,2,FALSE) -> TARGET MEDICAL SA | F37: 196280 | G37: =F37*21% -> 41218.8 | O37: =SUM(F37:N37) -> 237498.8 | P37: =VLOOKUP(D37,Configuracion!$A$4:$C$591,3,FALSE) -> PROVEEDOR
A38: 45141 | B38: 7 | C38: 2070 | D38: 20284183534 | E38: =VLOOKUP(D38,Configuracion!$A$4:$C$591,2,FALSE) -> FURLANETTO MARTIN | F38: 330.58 | G38: =F38*21% -> 69.4218 | O38: =SUM(F38:N38) -> 400.0018 | P38: =VLOOKUP(D38,Configuracion!$A$4:$C$591,3,FALSE) -> VARIOS
A39: 04/08/2023 | B39: 7 | C39: 27775 | D39: 20271532483 | E39: =VLOOKUP(D39,Configuracion!$A$4:$C$591,2,FALSE) -> DIEGO MARTIN RIOS | F39: 51189.36 | G39: =F39*21% -> 10749.766 | K39: 1791.63 | O39: =SUM(F39:N39) -> 63730.756 | P39: =VLOOKUP(D39,Configuracion!$A$4:$C$591,3,FALSE) -> PROVEEDOR
A40: 04/08/2023 | B40: 5054 | C40: 22102 | D40: 30695542476 | E40: =VLOOKUP(D40,Configuracion!$A$4:$C$591,2,FALSE) -> PAN AMERICAN ENERGY SL | F40: 5098.24 | G40: =F40*21% -> 1070.6304 | J40: 152.95 | N40: 331.12 | O40: =SUM(F40:N40) -> 6652.9404 | P40: =VLOOKUP(D40,Configuracion!$A$4:$C$591,3,FALSE) -> INSUMOS
A41: 04/08/2023 | B41: 1 | C41: 650 | D41: 30715048066 | E41: =VLOOKUP(D41,Configuracion!$A$4:$C$591,2,FALSE) -> ROLLS Y EMPANADAS SA | F41: 274910 | G41: =F41*21% -> 57731.1 | O41: =SUM(F41:N41) -> 332641.1 | P41: =VLOOKUP(D41,Configuracion!$A$4:$C$591,3,FALSE) -> VARIOS
A42: 06/08/2023 | B42: 2080 | C42: 86349 | D42: 30548083156 | E42: =VLOOKUP(D42,Configuracion!$A$4:$C$591,2,FALSE) -> COTO CICSA | F42: =52014.39+12239.59 -> 64253.98 | G42: 10923.02 | I42: 1285.16 | J42: =1529.7+183.59 -> 1713.29 | K42: 1920.97 | O42: =SUM(F42:N42) -> 80096.42 | P42: =VLOOKUP(D42,Configuracion!$A$4:$C$591,3,FALSE) -> GASTOS VARIOS
A43: 07/08/2023 | B43: 3 | C43: 90 | D43: 20334976433 | E43: =VLOOKUP(D43,Configuracion!$A$4:$C$591,2,FALSE) -> NARDOMARINO EZEQUIEL EDUARDO | F43: 98482.64 | G43: =F43*21% -> 20681.354 | O43: =SUM(F43:N43) -> 119163.99 | P43: =VLOOKUP(D43,Configuracion!$A$4:$C$591,3,FALSE) -> FLETE
A44: 07/08/2023 | B44: 17 | C44: 1205 | D44: 30711764921 | E44: =VLOOKUP(D44,Configuracion!$A$4:$C$591,2,FALSE) -> RELIEF CENTER SRL | F44: 143680 | G44: =F44*21% -> 30172.8 | O44: =SUM(F44:N44) -> 173852.8 | P44: =VLOOKUP(D44,Configuracion!$A$4:$C$591,3,FALSE) -> PROVEEDOR
A45: 45145 | B45: 13 | C45: 1254 | D45: 33709914109 | E45: =VLOOKUP(D45,Configuracion!$A$4:$C$591,2,FALSE) -> ALAN COLLECTION SA | F45: 3305.79 | G45: =F45*21% -> 694.2159 | O45: =SUM(F45:N45) -> 4000.0059 | P45: =VLOOKUP(D45,Configuracion!$A$4:$C$591,3,FALSE) -> VARIOS
A46: 08/08/2023 | B46: 11 | C46: 1577044 | D46: 30709776564 | E46: =VLOOKUP(D46,Configuracion!$A$4:$C$591,2,FALSE) -> PROSEGUR ACTIVA ARG SA | F46: 22988.52 | G46: =F46*21% -> 4827.5892 | K46: =+F46*0.035 -> 804.5982 | O46: =SUM(F46:N46) -> 28620.707 | P46: =VLOOKUP(D46,Configuracion!$A$4:$C$591,3,FALSE) -> SEGUROS
A47: 08/08/2023 | B47: 2 | C47: 22453 | D47: 23233422029 | E47: =VLOOKUP(D47,Configuracion!$A$4:$C$591,2,FALSE) -> RODOLFO SCHULZE | F47: 169039.5 | G47: =F47*21% -> 35498.295 | O47: =SUM(F47:N47) -> 204537.79 | P47: =VLOOKUP(D47,Configuracion!$A$4:$C$591,3,FALSE) -> PROVEEDOR | Q47: YA FUE AGREGADA ANTES
A48: 09/08/2023 | B48: 30 | C48: 38765 | D48: 30703088534 | E48: =VLOOKUP(D48,Configuracion!$A$4:$C$591,2,FALSE) -> MERCADOLIBRE SRL | F48: 8614.87 | G48: =F48*21% -> 1809.1227 | O48: =SUM(F48:N48) -> 10423.993 | P48: =VLOOKUP(D48,Configuracion!$A$4:$C$591,3,FALSE) -> PROVEEDOR
A49: 09/08/2023 | B49: 9044 | C49: 18170 | D49: 30678774495 | E49: =VLOOKUP(D49,Configuracion!$A$4:$C$591,2,FALSE) -> OPERADORA DE ESTAC. DE SERV SA | F49: 4709.89 | G49: =F49*21% -> 989.0769 | M49: 301.02 | O49: =SUM(F49:N49) -> 5999.9869 | P49: =VLOOKUP(D49,Configuracion!$A$4:$C$591,3,FALSE) -> VARIOS
A50: 09/08/2023 | B50: 9044 | C50: 18171 | D50: 30678774495 | E50: =VLOOKUP(D50,Configuracion!$A$4:$C$591,2,FALSE) -> OPERADORA DE ESTAC. DE SERV SA | F50: 7457.33 | G50: =F50*21% -> 1566.0393 | M50: 476.62 | O50: =SUM(F50:N50) -> 9499.9893 | P50: =VLOOKUP(D50,Configuracion!$A$4:$C$591,3,FALSE) -> VARIOS
A51: 09/08/2023 | B51: 2 | C51: 8941 | D51: 30714331082 | E51: =VLOOKUP(D51,Configuracion!$A$4:$C$591,2,FALSE) -> ORTOPEDIA CASA ESCALADA SRL | F51: 591711.14 | I51: 62129.67 | O51: =SUM(F51:N51) -> 653840.81 | P51: =VLOOKUP(D51,Configuracion!$A$4:$C$591,3,FALSE) -> PROVEEDOR
A52: 09/08/2023 | B52: 2 | C52: 7996 | D52: 30643862928 | E52: =VLOOKUP(D52,Configuracion!$A$4:$C$591,2,FALSE) -> OUTLANDISH SRL | F52: 40571.9 | G52: =F52*21% -> 8520.099 | O52: =SUM(F52:N52) -> 49091.999 | P52: =VLOOKUP(D52,Configuracion!$A$4:$C$591,3,FALSE) -> PROVEEDOR
A53: 09/08/2023 | B53: 948 | C53: 1031903 | D53: 30639453975 | E53: =VLOOKUP(D53,Configuracion!$A$4:$C$591,2,FALSE) -> TELEFONICA ARG SA | F53: =13232.61+133.43 -> 13366.04 | H53: =+F53*0.27 -> 3608.8308 | J53: =+F53*0.03 -> 400.9812 | K53: =+F53*0.035 -> 467.8114 | O53: =SUM(F53:N53) -> 17843.663 | P53: =VLOOKUP(D53,Configuracion!$A$4:$C$591,3,FALSE) -> SERVICIO
A54: 10/08/2023 | B54: 15 | C54: 2343 | D54: 30688140923 | E54: =VLOOKUP(D54,Configuracion!$A$4:$C$591,2,FALSE) -> COLTEX SRL | F54: 269642 | G54: =F54*21% -> 56624.82 | O54: =SUM(F54:N54) -> 326266.82 | P54: =VLOOKUP(D54,Configuracion!$A$4:$C$591,3,FALSE) -> PROVEEDOR
A55: 10/08/2023 | B55: 2 | C55: 17 | D55: 20272865869 | E55: =VLOOKUP(D55,Configuracion!$A$4:$C$591,2,FALSE) -> DI FEO MARTIN EZEQUIEL | F55: 29426.45 | G55: =F55*21% -> 6179.5545 | O55: =SUM(F55:N55) -> 35606.005 | P55: =VLOOKUP(D55,Configuracion!$A$4:$C$591,3,FALSE) -> PROVEEDOR
A56: 10/08/2023 | B56: 1 | C56: 861 | D56: 30715224468 | E56: =VLOOKUP(D56,Configuracion!$A$4:$C$591,2,FALSE) -> MLND SRL | F56: 19000 | G56: =F56*21% -> 3990 | O56: =SUM(F56:N56) -> 22990 | P56: =VLOOKUP(D56,Configuracion!$A$4:$C$591,3,FALSE) -> PROVEEDOR
A57: 10/08/2023 | B57: 17 | C57: 1209 | D57: 30711764921 | E57: =VLOOKUP(D57,Configuracion!$A$4:$C$591,2,FALSE) -> RELIEF CENTER SRL | F57: 29169 | G57: =F57*21% -> 6125.49 | O57: =SUM(F57:N57) -> 35294.49 | P57: =VLOOKUP(D57,Configuracion!$A$4:$C$591,3,FALSE) -> PROVEEDOR
A58: 10/08/2023 | B58: 4 | C58: 61 | D58: 20317488476 | E58: =VLOOKUP(D58,Configuracion!$A$4:$C$591,2,FALSE) -> VILLALBA MIGUEL ANGEL | F58: 289952 | G58: =F58*21% -> 60889.92 | O58: =SUM(F58:N58) -> 350841.92 | P58: =VLOOKUP(D58,Configuracion!$A$4:$C$591,3,FALSE) -> PROVEEDOR
A59: 45148 | B59: 13 | C59: 1256 | D59: 33709914109 | E59: =VLOOKUP(D59,Configuracion!$A$4:$C$591,2,FALSE) -> ALAN COLLECTION SA | F59: 3719.01 | G59: =F59*21% -> 780.9921 | O59: =SUM(F59:N59) -> 4500.0021 | P59: =VLOOKUP(D59,Configuracion!$A$4:$C$591,3,FALSE) -> VARIOS
A60: 45148 | B60: 7 | C60: 2100 | D60: 20284183534 | E60: =VLOOKUP(D60,Configuracion!$A$4:$C$591,2,FALSE) -> FURLANETTO MARTIN | F60: 619.85 | G60: =F60*21% -> 130.1685 | O60: =SUM(F60:N60) -> 750.0185 | P60: =VLOOKUP(D60,Configuracion!$A$4:$C$591,3,FALSE) -> VARIOS
A61: 11/08/2023 | B61: 2 | C61: 7373 | D61: 30694549817 | E61: =VLOOKUP(D61,Configuracion!$A$4:$C$591,2,FALSE) -> DISEÑOS JERY SRL | F61: 537319.47 | G61: =F61*21% -> 112837.09 | O61: =SUM(F61:N61) -> 650156.56 | P61: =VLOOKUP(D61,Configuracion!$A$4:$C$591,3,FALSE) -> PROVEEDOR
A62: 12/08/2023 | B62: 9038 | C62: 14959 | D62: 30678774495 | E62: =VLOOKUP(D62,Configuracion!$A$4:$C$591,2,FALSE) -> OPERADORA DE ESTAC. DE SERV SA | F62: 4710.17 | G62: =F62*21% -> 989.1357 | M62: 300.69 | O62: =SUM(F62:N62) -> 5999.9957 | P62: =VLOOKUP(D62,Configuracion!$A$4:$C$591,3,FALSE) -> VARIOS | Q62: YA FUE AGREGADA ANTES
A63: 12/08/2023 | B63: 9038 | C63: 14960 | D63: 30678774495 | E63: =VLOOKUP(D63,Configuracion!$A$4:$C$591,2,FALSE) -> OPERADORA DE ESTAC. DE SERV SA | F63: 2355.08 | G63: =F63*21% -> 494.5668 | M63: 150.35 | O63: =SUM(F63:N63) -> 2999.9968 | P63: =VLOOKUP(D63,Configuracion!$A$4:$C$591,3,FALSE) -> VARIOS
A64: 14/08/2023 | B64: 3 | C64: 93 | D64: 20334976433 | E64: =VLOOKUP(D64,Configuracion!$A$4:$C$591,2,FALSE) -> NARDOMARINO EZEQUIEL EDUARDO | F64: 137294.21 | G64: =F64*21% -> 28831.784 | O64: =SUM(F64:N64) -> 166125.99 | P64: =VLOOKUP(D64,Configuracion!$A$4:$C$591,3,FALSE) -> FLETE
A65: 14/08/2023 | B65: 4 | C65: 35692 | D65: 20289111329 | E65: =VLOOKUP(D65,Configuracion!$A$4:$C$591,2,FALSE) -> R. N. LEDESMA | F65: 252256.63 | G65: =F65*21% -> 52973.892 | O65: =SUM(F65:N65) -> 305230.52 | P65: =VLOOKUP(D65,Configuracion!$A$4:$C$591,3,FALSE) -> PROVEEDOR
A66: 16/08/2023 | B66: 120 | C66: 3159 | D66: 30587197215 | E66: =VLOOKUP(D66,Configuracion!$A$4:$C$591,2,FALSE) -> PANATEL SOCIEDAD ANONIMA | F66: 21487.6 | G66: =F66*21% -> 4512.396 | O66: =SUM(F66:N66) -> 25999.996 | P66: =VLOOKUP(D66,Configuracion!$A$4:$C$591,3,FALSE) -> VARIOS
A67: 16/08/2023 | B67: 7 | C67: 16311 | D67: 30709214078 | E67: =VLOOKUP(D67,Configuracion!$A$4:$C$591,2,FALSE) -> REHAVITA SA | F67: 1071187 | G67: =F67*21% -> 224949.27 | O67: =SUM(F67:N67) -> 1296136.3 | P67: =VLOOKUP(D67,Configuracion!$A$4:$C$591,3,FALSE) -> PROVEEDOR
A68: 17/08/2023 | B68: 2 | C68: 3 | D68: 20272865869 | E68: =VLOOKUP(D68,Configuracion!$A$4:$C$591,2,FALSE) -> DI FEO MARTIN EZEQUIEL | F68: -4680.58 | G68: =F68*21% -> -982.9218 | O68: =SUM(F68:N68) -> -5663.5018 | P68: =VLOOKUP(D68,Configuracion!$A$4:$C$591,3,FALSE) -> PROVEEDOR
A69: 17/08/2023 | B69: 2 | C69: 31 | D69: 20272865869 | E69: =VLOOKUP(D69,Configuracion!$A$4:$C$591,2,FALSE) -> DI FEO MARTIN EZEQUIEL | F69: 72810.51 | G69: =F69*21% -> 15290.207 | O69: =SUM(F69:N69) -> 88100.717 | P69: =VLOOKUP(D69,Configuracion!$A$4:$C$591,3,FALSE) -> PROVEEDOR
A70: 17/08/2023 | B70: 2 | C70: 35 | D70: 20272865869 | E70: =VLOOKUP(D70,Configuracion!$A$4:$C$591,2,FALSE) -> DI FEO MARTIN EZEQUIEL | F70: 5160.58 | G70: =F70*21% -> 1083.7218 | O70: =SUM(F70:N70) -> 6244.3018 | P70: =VLOOKUP(D70,Configuracion!$A$4:$C$591,3,FALSE) -> PROVEEDOR
A71: 17/08/2023 | B71: 3 | C71: 5985 | D71: 33708218699 | E71: =VLOOKUP(D71,Configuracion!$A$4:$C$591,2,FALSE) -> MANGGINI PABLO Y M ULISES SH | F71: 3500 | G71: =F71*21% -> 735 | O71: =SUM(F71:N71) -> 4235 | P71: =VLOOKUP(D71,Configuracion!$A$4:$C$591,3,FALSE) -> VARIOS
A72: 17/08/2023 | B72: 7780 | C72: 209 | D72: 30678774495 | E72: =VLOOKUP(D72,Configuracion!$A$4:$C$591,2,FALSE) -> OPERADORA DE ESTAC. DE SERV SA | F72: 4008.26 | G72: =F72*21% -> 841.7346 | O72: =SUM(F72:N72) -> 4849.9946 | P72: =VLOOKUP(D72,Configuracion!$A$4:$C$591,3,FALSE) -> VARIOS
A73: 17/08/2023 | B73: 1001 | C73: 278 | D73: 30707370552 | E73: =VLOOKUP(D73,Configuracion!$A$4:$C$591,2,FALSE) -> RAKE SA | F73: 299173.56 | G73: =F73*21% -> 62826.448 | O73: =SUM(F73:N73) -> 362000.01 | P73: =VLOOKUP(D73,Configuracion!$A$4:$C$591,3,FALSE) -> PROVEEDOR
A74: 17/08/2023 | B74: 1001 | C74: 279 | D74: 30707370552 | E74: =VLOOKUP(D74,Configuracion!$A$4:$C$591,2,FALSE) -> RAKE SA | F74: 229752.07 | G74: =F74*21% -> 48247.935 | O74: =SUM(F74:N74) -> 278000 | P74: =VLOOKUP(D74,Configuracion!$A$4:$C$591,3,FALSE) -> PROVEEDOR
A75: 17/08/2023 | B75: 1001 | C75: 280 | D75: 30707370552 | E75: =VLOOKUP(D75,Configuracion!$A$4:$C$591,2,FALSE) -> RAKE SA | F75: 82231.4 | G75: =F75*21% -> 17268.594 | O75: =SUM(F75:N75) -> 99499.994 | P75: =VLOOKUP(D75,Configuracion!$A$4:$C$591,3,FALSE) -> PROVEEDOR
A76: 45155 | B76: 27 | C76: 5724 | D76: 33712276539 | E76: =VLOOKUP(D76,Configuracion!$A$4:$C$591,2,FALSE) -> CASTAÑO AUTOVOX SRL | F76: 12276.11 | G76: =F76*21% -> 2577.9831 | K76: 429.66 | N76: 669.51 | O76: =SUM(F76:N76) -> 15953.263 | P76: =VLOOKUP(D76,Configuracion!$A$4:$C$591,3,FALSE) -> VARIOS
A77: 18/08/2023 | B77: 2 | C77: 3145 | D77: 30661498575 | E77: =VLOOKUP(D77,Configuracion!$A$4:$C$591,2,FALSE) -> ORTOPEDIA GULLONE SRL | F77: 34628.1 | G77: =F77*21% -> 7271.901 | O77: =SUM(F77:N77) -> 41900.001 | P77: =VLOOKUP(D77,Configuracion!$A$4:$C$591,3,FALSE) -> PROVEEDOR
A78: 19/08/2023 | B78: 4264 | C78: 2560668 | D78: 30639453738 | E78: =VLOOKUP(D78,Configuracion!$A$4:$C$591,2,FALSE) -> TELECOM ARGENTINA SA | F78: 15429.75 | G78: =F78*21% -> 3240.2475 | J78: 462.89 | K78: 540.04 | O78: =SUM(F78:N78) -> 19672.928 | P78: =VLOOKUP(D78,Configuracion!$A$4:$C$591,3,FALSE) -> SERVICIO
A79: 22/08/2023 | B79: 3 | C79: 94 | D79: 20334976433 | E79: =VLOOKUP(D79,Configuracion!$A$4:$C$591,2,FALSE) -> NARDOMARINO EZEQUIEL EDUARDO | F79: 60000 | G79: =F79*21% -> 12600 | O79: =SUM(F79:N79) -> 72600 | P79: =VLOOKUP(D79,Configuracion!$A$4:$C$591,3,FALSE) -> FLETE
A80: 45160 | B80: 5 | C80: 2844000 | D80: 30702652975 | E80: =VLOOKUP(D80,Configuracion!$A$4:$C$591,2,FALSE) -> NSS SA - IPLAN | F80: 8185.37 | G80: =F80*21% -> 1718.9277 | K80: =+F80*0.035 -> 286.48795 | O80: =SUM(F80:N80) -> 10190.786 | P80: =VLOOKUP(D80,Configuracion!$A$4:$C$591,3,FALSE) -> SERVICIO | Q80: YA FUE AGREGADA ANTES
A81: 45160 | B81: 22 | C81: 19 | D81: 30693066022 | E81: =VLOOKUP(D81,Configuracion!$A$4:$C$591,2,FALSE) -> Mg Farmaceutica Sociedad En CS | F81: 1033.04 | G81: =F81*21% -> 216.9384 | M81: 14817.18 | O81: =SUM(F81:N81) -> 16067.158 | P81: =VLOOKUP(D81,Configuracion!$A$4:$C$591,3,FALSE) -> VARIOS | Q81: YA FUE AGREGADA ANTES
A82: 23/08/2023 | B82: 15 | C82: 2374 | D82: 30688140923 | E82: =VLOOKUP(D82,Configuracion!$A$4:$C$591,2,FALSE) -> COLTEX SRL | F82: 34363.17 | G82: =F82*21% -> 7216.2657 | O82: =SUM(F82:N82) -> 41579.436 | P82: =VLOOKUP(D82,Configuracion!$A$4:$C$591,3,FALSE) -> PROVEEDOR
A83: 23/08/2023 | B83: 2 | C83: 9039 | D83: 30714331082 | E83: =VLOOKUP(D83,Configuracion!$A$4:$C$591,2,FALSE) -> ORTOPEDIA CASA ESCALADA SRL | F83: 119042.49 | G83: =F83*21% -> 24998.923 | O83: =SUM(F83:N83) -> 144041.41 | P83: =VLOOKUP(D83,Configuracion!$A$4:$C$591,3,FALSE) -> PROVEEDOR
A84: 23/08/2023 | B84: 7 | C84: 16358 | D84: 30709214078 | E84: =VLOOKUP(D84,Configuracion!$A$4:$C$591,2,FALSE) -> REHAVITA SA | F84: 45510 | I84: 4778.55 | O84: =SUM(F84:N84) -> 50288.55 | P84: =VLOOKUP(D84,Configuracion!$A$4:$C$591,3,FALSE) -> PROVEEDOR
A85: 23/08/2023 | B85: 17 | C85: 1247 | D85: 30711764921 | E85: =VLOOKUP(D85,Configuracion!$A$4:$C$591,2,FALSE) -> RELIEF CENTER SRL | F85: 71472 | G85: =F85*21% -> 15009.12 | O85: =SUM(F85:N85) -> 86481.12 | P85: =VLOOKUP(D85,Configuracion!$A$4:$C$591,3,FALSE) -> PROVEEDOR
A86: 24/08/2023 | B86: 3 | C86: 7 | D86: 20396584809 | E86: =VLOOKUP(D86,Configuracion!$A$4:$C$591,2,FALSE) -> DEBELIUCH TOMAS IVAN | F86: 54225 | I86: 5693.62 | O86: =SUM(F86:N86) -> 59918.62 | P86: =VLOOKUP(D86,Configuracion!$A$4:$C$591,3,FALSE) -> PROVEEDOR | Q86: YA FUE AGREGADA ANTES
A87: 24/08/2023 | B87: 2 | C87: 46 | D87: 20272865869 | E87: =VLOOKUP(D87,Configuracion!$A$4:$C$591,2,FALSE) -> DI FEO MARTIN EZEQUIEL | F87: 60158.19 | G87: =F87*21% -> 12633.22 | O87: =SUM(F87:N87) -> 72791.41 | P87: =VLOOKUP(D87,Configuracion!$A$4:$C$591,3,FALSE) -> PROVEEDOR
A88: 24/08/2023 | B88: 7 | C88: 27833 | D88: 20271532483 | E88: =VLOOKUP(D88,Configuracion!$A$4:$C$591,2,FALSE) -> DIEGO MARTIN RIOS | F88: 96000 | G88: =F88*21% -> 20160 | K88: 3360 | O88: =SUM(F88:N88) -> 119520 | P88: =VLOOKUP(D88,Configuracion!$A$4:$C$591,3,FALSE) -> PROVEEDOR
A89: 25/08/2023 | B89: 3 | C89: 144 | D89: 23928499804 | E89: =VLOOKUP(D89,Configuracion!$A$4:$C$591,2,FALSE) -> BRITOS MARIA GABRIELA | F89: 2479.34 | G89: =F89*21% -> 520.6614 | O89: =SUM(F89:N89) -> 3000.0014 | P89: =VLOOKUP(D89,Configuracion!$A$4:$C$591,3,FALSE) -> VARIOS
A90: 25/08/2023 | B90: 3 | C90: 145 | D90: 23928499804 | E90: =VLOOKUP(D90,Configuracion!$A$4:$C$591,2,FALSE) -> BRITOS MARIA GABRIELA | F90: 12148.76 | G90: =F90*21% -> 2551.2396 | O90: =SUM(F90:N90) -> 14700 | P90: =VLOOKUP(D90,Configuracion!$A$4:$C$591,3,FALSE) -> VARIOS
A91: 25/08/2023 | B91: 5 | C91: 19 | D91: 20929183143 | E91: =VLOOKUP(D91,Configuracion!$A$4:$C$591,2,FALSE) -> MA JUN | F91: 12000 | G91: =F91*21% -> 2520 | O91: =SUM(F91:N91) -> 14520 | P91: =VLOOKUP(D91,Configuracion!$A$4:$C$591,3,FALSE) -> VARIOS
A92: 28/08/2023 | B92: 31 | C92: 45772 | D92: 30581106234 | E92: =VLOOKUP(D92,Configuracion!$A$4:$C$591,2,FALSE) -> Transportes Imaz S R L | F92: 6450 | G92: =F92*21% -> 1354.5 | O92: =SUM(F92:N92) -> 7804.5 | P92: =VLOOKUP(D92,Configuracion!$A$4:$C$591,3,FALSE) -> FLETE | Q92: YA FUE AGREGADA ANTES
A93: 28/08/2023 | B93: 4 | C93: 11176 | D93: 33531122599 | E93: =VLOOKUP(D93,Configuracion!$A$4:$C$591,2,FALSE) -> LA CAMIONERA MENDOCINA SRL | F93: 8633.55 | G93: =F93*21% -> 1813.0455 | O93: =SUM(F93:N93) -> 10446.595 | P93: =VLOOKUP(D93,Configuracion!$A$4:$C$591,3,FALSE) -> FLETE | Q93: YA FUE AGREGADA ANTES
A94: 28/08/2023 | B94: 3 | C94: 96 | D94: 20334976433 | E94: =VLOOKUP(D94,Configuracion!$A$4:$C$591,2,FALSE) -> NARDOMARINO EZEQUIEL EDUARDO | F94: 101543.8 | G94: =F94*21% -> 21324.198 | O94: =SUM(F94:N94) -> 122868 | P94: =VLOOKUP(D94,Configuracion!$A$4:$C$591,3,FALSE) -> FLETE | Q94: YA FUE AGREGADA ANTES
A95: 28/08/2023 | B95: 6 | C95: 1074 | D95: 30716815710 | E95: =VLOOKUP(D95,Configuracion!$A$4:$C$591,2,FALSE) -> PAPELERA GEOPEL SRL | F95: 4500 | G95: =F95*21% -> 945 | O95: =SUM(F95:N95) -> 5445 | P95: =VLOOKUP(D95,Configuracion!$A$4:$C$591,3,FALSE) -> LIBRERÍA | Q95: YA FUE AGREGADA ANTES
A96: 28/08/2023 | B96: 6 | C96: 712 | D96: 20247225243 | E96: =VLOOKUP(D96,Configuracion!$A$4:$C$591,2,FALSE) -> VENTO HUGO GABRIEL | F96: 45184 | G96: =F96*21% -> 9488.64 | O96: =SUM(F96:N96) -> 54672.64 | P96: =VLOOKUP(D96,Configuracion!$A$4:$C$591,3,FALSE) -> PROVEEDOR | Q96: YA FUE AGREGADA ANTES
A97: 29/08/2023 | B97: 34 | C97: 540 | D97: 33712276539 | E97: =VLOOKUP(D97,Configuracion!$A$4:$C$591,2,FALSE) -> CASTAÑO AUTOVOX SRL | F97: 12872.83 | G97: =F97*21% -> 2703.2943 | K97: =+F97*0.035 -> 450.54905 | N97: 702.05 | O97: =SUM(F97:N97) -> 16728.723 | P97: =VLOOKUP(D97,Configuracion!$A$4:$C$591,3,FALSE) -> VARIOS
A98: 29/08/2023 | B98: 2635 | C98: 1100 | D98: 33699685459 | E98: =VLOOKUP(D98,Configuracion!$A$4:$C$591,2,FALSE) -> CORREO ANDREANI SA | F98: 4131.41 | G98: =F98*21% -> 867.5961 | O98: =SUM(F98:N98) -> 4999.0061 | P98: =VLOOKUP(D98,Configuracion!$A$4:$C$591,3,FALSE) -> VARIOS
A99: 30/08/2023 | B99: 2 | C99: 45 | D99: 33716367539 | E99: =VLOOKUP(D99,Configuracion!$A$4:$C$591,2,FALSE) -> 3PI S.A.S. | F99: 1633500 | G99: =F99*21% -> 343035 | O99: =SUM(F99:N99) -> 1976535 | P99: =VLOOKUP(D99,Configuracion!$A$4:$C$591,3,FALSE) -> PROVEEDOR
A100: 45168 | B100: 10 | C100: 1993 | D100: 20259150249 | E100: =VLOOKUP(D100,Configuracion!$A$4:$C$591,2,FALSE) -> BIANCHI CRISTIAN MAXIMILIANO | F100: 25611.57 | G100: =F100*21% -> 5378.4297 | O100: =SUM(F100:N100) -> 30990 | P100: =VLOOKUP(D100,Configuracion!$A$4:$C$591,3,FALSE) -> VARIOS
A101: 31/08/2023 | B101: 20 | C101: 159337 | D101: 30696850972 | E101: =VLOOKUP(D101,Configuracion!$A$4:$C$591,2,FALSE) -> CPS COMUNICACIONES SA | F101: 5136.2 | H101: =+F101*0.27 -> 1386.774 | K101: =+F101*0.035 -> 179.767 | O101: =SUM(F101:N101) -> 6702.741 | P101: =VLOOKUP(D101,Configuracion!$A$4:$C$591,3,FALSE) -> SERVICIO
A102: 31/08/2023 | B102: 5 | C102: 851 | D102: 20242126158 | E102: =VLOOKUP(D102,Configuracion!$A$4:$C$591,2,FALSE) -> IALLONARDO SERGIO | F102: 620542.5 | I102: 65156.96 | O102: =SUM(F102:N102) -> 685699.46 | P102: =VLOOKUP(D102,Configuracion!$A$4:$C$591,3,FALSE) -> PROVEEDOR
A103: 31/08/2023 | B103: 4 | C103: 66080 | D103: 33709738459 | E103: =VLOOKUP(D103,Configuracion!$A$4:$C$591,2,FALSE) -> ORTOPEDICOS ALFOLATEX SA | F103: 138702.46 | G103: =F103*21% -> 29127.517 | O103: =SUM(F103:N103) -> 167829.98 | P103: =VLOOKUP(D103,Configuracion!$A$4:$C$591,3,FALSE) -> PROVEEDOR
...

Sheet Calculo IVA
B1: ORTOPEDIA GEMINIS
A2: Calculo Iva | D2: 45139
B4: VENTAS
B5: Neto | C5: Iva | D5: Total
A6: FAC. "A" | B6: =+AGOSTO!F210 -> 3414710.7 | C6: =(B6*0.21) -> 717089.26 | D6: =(B6+C6) -> 4131800
A7: FAC. "B" | B7: =+AGOSTO!F220 -> 0 | C7: =(B7*0.21) -> 0 | D7: =(B7+C7) -> 0
A8: FAC. "A" - Odoo | B8: =+AGOSTO!B229+AGOSTO!B231+AGOSTO!B232+AGOSTO!B230 -> 44881359 | C8: =+B8*0.21 -> 9425085.4 | D8: =(B8+C8) -> 54306445
A9: FAC. "B" - Odoo | B9: =+AGOSTO!B233+AGOSTO!B234 -> 3383620.5 | C9: =+B9*0.21 -> 710560.3 | D9: =(B9+C9) -> 4094180.8
B10: =SUM(B6:B9) -> 51679690 | C10: =SUM(C6:C9) -> 10852735 | D10: =SUM(D6:D9) -> 62532425
B13: COMPRAS
B14: Neto | C14: Iva | D14: Total
B15: =+AGOSTO!F116 -> 24295961 | C15: =+AGOSTO!G116+AGOSTO!H116+AGOSTO!I116 -> 4936749.7 | D15: =(B15+C15) -> 29232711
B17: =SUM(B15:B16) -> 24295961 | C17: =SUM(C15:C16) -> 4936749.7 | D17: =SUM(D15:D16) -> 29232711
A20: RETENCIONES | B20: N° Cuit | C20: Importe | D20: Nro. Retencion | E20: Fecha
A21: AFIP - No están informadas las retenciones de IVA en el sistema de AFIP
C36: =+AGOSTO!G197 -> 957038.24
A38: PERCEPCIONES | B38: N° Cuit | C38: Importe | D38: Nro. Retencion | E38: Fecha
C42: =SUM(C39:C41) -> 0
A44: Total Deducciociones | C44: =+C42+C36 -> 957038.24
C47: (Montos en Positivo)
A48: 1er Saldo Tecnico del Período | C48: =+C10-C17 -> 5915985.3
A50: Saldo Tecnico de período Anterior (a favor) | D50: (resta en el total)
A52: Saldo Neto Técnico | C52: =+C48-C50 -> 5915985.3
A56: Saldo L.D. del Período | C56: =+C42+C36 -> 957038.24
A58: Saldo L.D. del Período Anterior
A60: Neto S.L.D | C60: =+C56+C58 -> 957038.24
A63: I V A | C63: =+C52-C60 -> 4958947
A64: NOTA: Sin Tomar posibles Retenciones que se hayan hecho

Sheet Iva Ventas 08 2023
A2: Ventas Libro de IVA 01/08/2023 - 31/08/2023
A3: Ortopedia Geminis S.A.
A5: Fecha | B5: Comprobante | C5: Nombre | D5: Cond. IVA | E5: CUIT o Doc. | F5: Gravado | G5: No Gravado | H5: IVA 2,5% | I5: IVA 5% | J5: IVA 10.5% | K5: IVA 21% | L5: IVA 27% | M5: Otros Imp | N5: Total Compr.
A6: 01/08/2023 | B6: FA-B 0005-00008505 | C6: .CONSUMIDOR FINAL | D6: Consumidor Final | F6: 3388.43 | G6: 0 | H6: 0 | I6: 0 | J6: 0 | K6: 711.57 | L6: 0 | M6: 0 | N6: 4100
A7: 01/08/2023 | B7: FA-B 0005-00008506 | C7: .CONSUMIDOR FINAL | D7: Consumidor Final | F7: 6694.21 | G7: 0 | H7: 0 | I7: 0 | J7: 0 | K7: 1405.79 | L7: 0 | M7: 0 | N7: 8100
A8: 01/08/2023 | B8: FA-B 0005-00008507 | C8: .CONSUMIDOR FINAL | D8: Consumidor Final | F8: 8760.33 | G8: 0 | H8: 0 | I8: 0 | J8: 0 | K8: 1839.67 | L8: 0 | M8: 0 | N8: 10600
A9: 01/08/2023 | B9: FA-B 0005-00008508 | C9: .CONSUMIDOR FINAL | D9: Consumidor Final | F9: 2520.66 | G9: 0 | H9: 0 | I9: 0 | J9: 0 | K9: 529.34 | L9: 0 | M9: 0 | N9: 3050
A10: 01/08/2023 | B10: FA-B 0005-00008509 | C10: .CONSUMIDOR FINAL | D10: Consumidor Final | F10: 6776.86 | G10: 0 | H10: 0 | I10: 0 | J10: 0 | K10: 1423.14 | L10: 0 | M10: 0 | N10: 8200
A11: 01/08/2023 | B11: FA-B 0005-00008510 | C11: GALIOSTRO MARCELO FABIO | D11: Consumidor Final | E11: 18142775 | F11: 4752.07 | G11: 0 | H11: 0 | I11: 0 | J11: 0 | K11: 997.93 | L11: 0 | M11: 0 | N11: 5750
A12: 01/08/2023 | B12: FA-B 0005-00008511 | C12: .CONSUMIDOR FINAL | D12: Consumidor Final | F12: 7851.24 | G12: 0 | H12: 0 | I12: 0 | J12: 0 | K12: 1648.76 | L12: 0 | M12: 0 | N12: 9500
A13: 01/08/2023 | B13: FA-B 0005-00008512 | C13: .CONSUMIDOR FINAL | D13: Consumidor Final | F13: 1157.02 | G13: 0 | H13: 0 | I13: 0 | J13: 0 | K13: 242.98 | L13: 0 | M13: 0 | N13: 1400
A14: 01/08/2023 | B14: FA-B 0005-00008513 | C14: .CONSUMIDOR FINAL | D14: Consumidor Final | F14: 6776.86 | G14: 0 | H14: 0 | I14: 0 | J14: 0 | K14: 1423.14 | L14: 0 | M14: 0 | N14: 8200
A15: 01/08/2023 | B15: FA-B 0005-00008514 | C15: .CONSUMIDOR FINAL | D15: Consumidor Final | F15: 10743.8 | G15: 0 | H15: 0 | I15: 0 | J15: 0 | K15: 2256.2 | L15: 0 | M15: 0 | N15: 13000
A16: 01/08/2023 | B16: FA-B 0007-00004531 | C16: GIMENEZ, SONIA GLADYS | D16: Consumidor Final | E16: 16124424 | F16: 11157.02 | G16: 0 | H16: 0 | I16: 0 | J16: 0 | K16: 2342.98 | L16: 0 | M16: 0 | N16: 13500
A17: 01/08/2023 | B17: FA-B 0007-00004532 | C17: HIGA MARCELA SANDRA | D17: Consumidor Final | E17: 17968654 | F17: 46115.7 | G17: 0 | H17: 0 | I17: 0 | J17: 0 | K17: 9684.3 | L17: 0 | M17: 0 | N17: 55800
A18: 02/08/2023 | B18: FA-B 0005-00008515 | C18: .CONSUMIDOR FINAL | D18: Consumidor Final | F18: 6776.86 | G18: 0 | H18: 0 | I18: 0 | J18: 0 | K18: 1423.14 | L18: 0 | M18: 0 | N18: 8200
A19: 02/08/2023 | B19: FA-B 0005-00008516 | C19: .CONSUMIDOR FINAL | D19: Consumidor Final | F19: 6280.99 | G19: 0 | H19: 0 | I19: 0 | J19: 0 | K19: 1319.01 | L19: 0 | M19: 0 | N19: 7600
A20: 02/08/2023 | B20: FA-B 0005-00008517 | C20: .CONSUMIDOR FINAL | D20: Consumidor Final | F20: 3388.43 | G20: 0 | H20: 0 | I20: 0 | J20: 0 | K20: 711.57 | L20: 0 | M20: 0 | N20: 4100
A21: 02/08/2023 | B21: FA-B 0005-00008518 | C21: .CONSUMIDOR FINAL | D21: Consumidor Final | F21: 3388.43 | G21: 0 | H21: 0 | I21: 0 | J21: 0 | K21: 711.57 | L21: 0 | M21: 0 | N21: 4100
A22: 02/08/2023 | B22: FA-B 0005-00008519 | C22: .CONSUMIDOR FINAL | D22: Consumidor Final | F22: 10743.8 | G22: 0 | H22: 0 | I22: 0 | J22: 0 | K22: 2256.2 | L22: 0 | M22: 0 | N22: 13000
A23: 02/08/2023 | B23: FA-B 0005-00008520 | C23: .CONSUMIDOR FINAL | D23: Consumidor Final | F23: 6776.86 | G23: 0 | H23: 0 | I23: 0 | J23: 0 | K23: 1423.14 | L23: 0 | M23: 0 | N23: 8200
A24: 02/08/2023 | B24: FA-B 0005-00008521 | C24: .CONSUMIDOR FINAL | D24: Consumidor Final | F24: 4132.23 | G24: 0 | H24: 0 | I24: 0 | J24: 0 | K24: 867.77 | L24: 0 | M24: 0 | N24: 5000
A25: 02/08/2023 | B25: FA-B 0005-00008522 | C25: .CONSUMIDOR FINAL | D25: Consumidor Final | F25: 9090.91 | G25: 0 | H25: 0 | I25: 0 | J25: 0 | K25: 1909.09 | L25: 0 | M25: 0 | N25: 11000
A26: 02/08/2023 | B26: FA-B 0005-00008523 | C26: .CONSUMIDOR FINAL | D26: Consumidor Final | F26: 6033.06 | G26: 0 | H26: 0 | I26: 0 | J26: 0 | K26: 1266.94 | L26: 0 | M26: 0 | N26: 7300
A27: 02/08/2023 | B27: FA-A 0006-00000372 | C27: Galeno Argentina Sociedad Anonima | D27: IVA Responsable Inscripto | E27: 30522428163 | F27: 2706554.2 | G27: 0 | H27: 0 | I27: 0 | J27: 0 | K27: 568376.39 | L27: 0 | M27: 0 | N27: 3274930.6
A28: 02/08/2023 | B28: FA-A 0007-00001546 | C28: Obra Social Del Personal De Las Telecomunicaciones De La Republica Argentina | D28: IVA Responsable Inscripto | E28: 30608716390 | F28: 1072.73 | G28: 0 | H28: 0 | I28: 0 | J28: 0 | K28: 225.27 | L28: 0 | M28: 0 | N28: 1298
A29: 02/08/2023 | B29: FA-A 0007-00001547 | C29: Galeno Argentina Sociedad Anonima | D29: IVA Responsable Inscripto | E29: 30522428163 | F29: 255019.16 | G29: 0 | H29: 0 | I29: 0 | J29: 0 | K29: 53554.02 | L29: 0 | M29: 0 | N29: 308573.18
A30: 02/08/2023 | B30: FA-A 0007-00001548 | C30: Galeno Argentina Sociedad Anonima | D30: IVA Responsable Inscripto | E30: 30522428163 | F30: 16280.99 | G30: 0 | H30: 0 | I30: 0 | J30: 0 | K30: 3419.01 | L30: 0 | M30: 0 | N30: 19700
A31: 02/08/2023 | B31: FA-A 0007-00001549 | C31: Galeno Argentina Sociedad Anonima | D31: IVA Responsable Inscripto | E31: 30522428163 | F31: 10749.24 | G31: 0 | H31: 0 | I31: 0 | J31: 0 | K31: 2257.34 | L31: 0 | M31: 0 | N31: 13006.58
A32: 02/08/2023 | B32: FA-A 0007-00001550 | C32: Galeno Argentina Sociedad Anonima | D32: IVA Responsable Inscripto | E32: 30522428163 | F32: 380473.58 | G32: 0 | H32: 0 | I32: 0 | J32: 0 | K32: 79899.45 | L32: 0 | M32: 0 | N32: 460373.03
A33: 02/08/2023 | B33: FA-A 0007-00001551 | C33: Galeno Argentina Sociedad Anonima | D33: IVA Responsable Inscripto | E33: 30522428163 | F33: 245643.54 | G33: 0 | H33: 0 | I33: 0 | J33: 0 | K33: 51585.14 | L33: 0 | M33: 0 | N33: 297228.68
A34: 02/08/2023 | B34: FA-B 0007-00004533 | C34: ALBARO BRESCIANO | D34: Consumidor Final | F34: 15619.83 | G34: 0 | H34: 0 | I34: 0 | J34: 0 | K34: 3280.17 | L34: 0 | M34: 0 | N34: 18900
A35: 02/08/2023 | B35: FA-B 0007-00004534 | C35: ALEJANDRA SIFFREDI TORRES SANMARCO | D35: Consumidor Final | E35: 5804480 | F35: 5785.12 | G35: 0 | H35: 0 | I35: 0 | J35: 0 | K35: 1214.88 | L35: 0 | M35: 0 | N35: 7000
A36: 02/08/2023 | B36: FA-B 0007-00004535 | C36: GABRIELA VANINA GALLO | D36: Consumidor Final | E36: 26542077 | F36: 12644.62 | G36: 0 | H36: 0 | I36: 0 | J36: 0 | K36: 2655.38 | L36: 0 | M36: 0 | N36: 15300
A37: 02/08/2023 | B37: FA-B 0007-00004536 | C37: MARIA ELENA RODRIGUEZ | D37: Consumidor Final | E37: 382591 | F37: 6611.57 | G37: 0 | H37: 0 | I37: 0 | J37: 0 | K37: 1388.43 | L37: 0 | M37: 0 | N37: 8000
A38: 02/08/2023 | B38: FA-B 0007-00004537 | C38: ENRIQUETA MARIA DEL SOCORRO MAJO | D38: Consumidor Final | E38: 3192296 | F38: 4958.68 | G38: 0 | H38: 0 | I38: 0 | J38: 0 | K38: 1041.32 | L38: 0 | M38: 0 | N38: 6000
A39: 03/08/2023 | B39: FA-B 0005-00008524 | C39: .CONSUMIDOR FINAL | D39: Consumidor Final | F39: 3925.62 | G39: 0 | H39: 0 | I39: 0 | J39: 0 | K39: 824.38 | L39: 0 | M39: 0 | N39: 4750
A40: 03/08/2023 | B40: FA-B 0005-00008525 | C40: .CONSUMIDOR FINAL | D40: Consumidor Final | F40: 10743.8 | G40: 0 | H40: 0 | I40: 0 | J40: 0 | K40: 2256.2 | L40: 0 | M40: 0 | N40: 13000
A41: 03/08/2023 | B41: FA-B 0005-00008526 | C41: .CONSUMIDOR FINAL | D41: Consumidor Final | F41: 10826.45 | G41: 0 | H41: 0 | I41: 0 | J41: 0 | K41: 2273.55 | L41: 0 | M41: 0 | N41: 13100
A42: 03/08/2023 | B42: FA-B 0005-00008527 | C42: .CONSUMIDOR FINAL | D42: Consumidor Final | F42: 6446.28 | G42: 0 | H42: 0 | I42: 0 | J42: 0 | K42: 1353.72 | L42: 0 | M42: 0 | N42: 7800
A43: 03/08/2023 | B43: FA-B 0005-00008528 | C43: .CONSUMIDOR FINAL | D43: Consumidor Final | F43: 909.09 | G43: 0 | H43: 0 | I43: 0 | J43: 0 | K43: 190.91 | L43: 0 | M43: 0 | N43: 1100
A44: 03/08/2023 | B44: FA-B 0005-00008529 | C44: .CONSUMIDOR FINAL | D44: Consumidor Final | F44: 5371.9 | G44: 0 | H44: 0 | I44: 0 | J44: 0 | K44: 1128.1 | L44: 0 | M44: 0 | N44: 6500
A45: 03/08/2023 | B45: FA-B 0005-00008530 | C45: .CONSUMIDOR FINAL | D45: Consumidor Final | F45: 4628.1 | G45: 0 | H45: 0 | I45: 0 | J45: 0 | K45: 971.9 | L45: 0 | M45: 0 | N45: 5600
A46: 03/08/2023 | B46: FA-B 0005-00008531 | C46: .CONSUMIDOR FINAL | D46: Consumidor Final | F46: 2892.56 | G46: 0 | H46: 0 | I46: 0 | J46: 0 | K46: 607.44 | L46: 0 | M46: 0 | N46: 3500
A47: 03/08/2023 | B47: FA-B 0005-00008532 | C47: .CONSUMIDOR FINAL | D47: Consumidor Final | F47: 6611.57 | G47: 0 | H47: 0 | I47: 0 | J47: 0 | K47: 1388.43 | L47: 0 | M47: 0 | N47: 8000
A48: 03/08/2023 | B48: FA-B 0005-00008533 | C48: .CONSUMIDOR FINAL | D48: Consumidor Final | F48: 3388.43 | G48: 0 | H48: 0 | I48: 0 | J48: 0 | K48: 711.57 | L48: 0 | M48: 0 | N48: 4100
A49: 03/08/2023 | B49: FA-B 0005-00008534 | C49: .CONSUMIDOR FINAL | D49: Consumidor Final | F49: 6280.99 | G49: 0 | H49: 0 | I49: 0 | J49: 0 | K49: 1319.01 | L49: 0 | M49: 0 | N49: 7600
A50: 03/08/2023 | B50: FA-B 0005-00008535 | C50: PEREYRA ELSA | D50: Consumidor Final | E50: 14241990 | F50: 15900.83 | G50: 0 | H50: 0 | I50: 0 | J50: 0 | K50: 3339.17 | L50: 0 | M50: 0 | N50: 19240
A51: 03/08/2023 | B51: FA-B 0005-00008536 | C51: .CONSUMIDOR FINAL | D51: Consumidor Final | F51: 8512.4 | G51: 0 | H51: 0 | I51: 0 | J51: 0 | K51: 1787.6 | L51: 0 | M51: 0 | N51: 10300
A52: 03/08/2023 | B52: FA-B 0005-00008537 | C52: .CONSUMIDOR FINAL | D52: Consumidor Final | F52: 8429.75 | G52: 0 | H52: 0 | I52: 0 | J52: 0 | K52: 1770.25 | L52: 0 | M52: 0 | N52: 10200
A53: 03/08/2023 | B53: FA-B 0005-00008538 | C53: .CONSUMIDOR FINAL | D53: Consumidor Final | F53: 2644.63 | G53: 0 | H53: 0 | I53: 0 | J53: 0 | K53: 555.37 | L53: 0 | M53: 0 | N53: 3200
A54: 03/08/2023 | B54: FA-B 0005-00008539 | C54: .CONSUMIDOR FINAL | D54: Consumidor Final | F54: 991.74 | G54: 0 | H54: 0 | I54: 0 | J54: 0 | K54: 208.26 | L54: 0 | M54: 0 | N54: 1200
A55: 03/08/2023 | B55: FA-B 0005-00008540 | C55: .CONSUMIDOR FINAL | D55: Consumidor Final | F55: 11239.67 | G55: 0 | H55: 0 | I55: 0 | J55: 0 | K55: 2360.33 | L55: 0 | M55: 0 | N55: 13600
A56: 03/08/2023 | B56: FA-A 0006-00000373 | C56: Galeno Argentina Sociedad Anonima | D56: IVA Responsable Inscripto | E56: 30522428163 | F56: 4265206.6 | G56: 0 | H56: 0 | I56: 0 | J56: 0 | K56: 895693.38 | L56: 0 | M56: 0 | N56: 5160900
A57: 03/08/2023 | B57: FA-A 0006-00000374 | C57: Galeno Argentina Sociedad Anonima | D57: IVA Responsable Inscripto | E57: 30522428163 | F57: 5242066.1 | G57: 0 | H57: 0 | I57: 0 | J57: 0 | K57: 1100833.9 | L57: 0 | M57: 0 | N57: 6342900
A58: 03/08/2023 | B58: FA-A 0007-00001552 | C58: Obra Social Del Personal De Las Telecomunicaciones De La Republica Argentina | D58: IVA Responsable Inscripto | E58: 30608716390 | F58: 5777.68 | G58: 0 | H58: 0 | I58: 0 | J58: 0 | K58: 1213.31 | L58: 0 | M58: 0 | N58: 6990.99
A59: 03/08/2023 | B59: FA-A 0007-00001553 | C59: Hc Homecare Internacion Domiciliaria S.A. | D59: IVA Responsable Inscripto | E59: 30710538014 | F59: 20395.04 | G59: 0 | H59: 0 | I59: 0 | J59: 0 | K59: 4282.96 | L59: 0 | M59: 0 | N59: 24678
A60: 03/08/2023 | B60: FA-B 0007-00004538 | C60: IZZO, ADRIANA | D60: Consumidor Final | E60: 14547747 | F60: 8181.81 | G60: 0 | H60: 0 | I60: 0 | J60: 0 | K60: 1718.19 | L60: 0 | M60: 0 | N60: 9900
A61: 03/08/2023 | B61: FA-B 0007-00004539 | C61: Chiari Maria Enriqueta del Socorro | D61: Consumidor Final | E61: 13211322 | F61: 4380.16 | G61: 0 | H61: 0 | I61: 0 | J61: 0 | K61: 919.84 | L61: 0 | M61: 0 | N61: 5300
A62: 04/08/2023 | B62: FA-B 0005-00008541 | C62: .CONSUMIDOR FINAL | D62: Consumidor Final | F62: 3925.62 | G62: 0 | H62: 0 | I62: 0 | J62: 0 | K62: 824.38 | L62: 0 | M62: 0 | N62: 4750
A63: 04/08/2023 | B63: FA-B 0005-00008542 | C63: .CONSUMIDOR FINAL | D63: Consumidor Final | F63: 3305.79 | G63: 0 | H63: 0 | I63: 0 | J63: 0 | K63: 694.21 | L63: 0 | M63: 0 | N63: 4000
A64: 04/08/2023 | B64: FA-B 0005-00008543 | C64: .CONSUMIDOR FINAL | D64: Consumidor Final | F64: 9256.2 | G64: 0 | H64: 0 | I64: 0 | J64: 0 | K64: 1943.8 | L64: 0 | M64: 0 | N64: 11200
A65: 04/08/2023 | B65: FA-B 0005-00008544 | C65: .CONSUMIDOR FINAL | D65: Consumidor Final | F65: 13876.03 | G65: 0 | H65: 0 | I65: 0 | J65: 0 | K65: 2913.97 | L65: 0 | M65: 0 | N65: 16790
A66: 04/08/2023 | B66: FA-B 0005-00008545 | C66: .CONSUMIDOR FINAL | D66: Consumidor Final | F66: 8553.72 | G66: 0 | H66: 0 | I66: 0 | J66: 0 | K66: 1796.28 | L66: 0 | M66: 0 | N66: 10350
A67: 04/08/2023 | B67: FA-B 0005-00008546 | C67: .CONSUMIDOR FINAL | D67: Consumidor Final | F67: 6033.06 | G67: 0 | H67: 0 | I67: 0 | J67: 0 | K67: 1266.94 | L67: 0 | M67: 0 | N67: 7300
A68: 04/08/2023 | B68: FA-B 0005-00008547 | C68: .CONSUMIDOR FINAL | D68: Consumidor Final | F68: 6776.86 | G68: 0 | H68: 0 | I68: 0 | J68: 0 | K68: 1423.14 | L68: 0 | M68: 0 | N68: 8200
A69: 04/08/2023 | B69: FA-B 0005-00008548 | C69: .CONSUMIDOR FINAL | D69: Consumidor Final | F69: 6694.21 | G69: 0 | H69: 0 | I69: 0 | J69: 0 | K69: 1405.79 | L69: 0 | M69: 0 | N69: 8100
A70: 04/08/2023 | B70: FA-B 0005-00008549 | C70: .CONSUMIDOR FINAL | D70: Consumidor Final | F70: 6033.06 | G70: 0 | H70: 0 | I70: 0 | J70: 0 | K70: 1266.94 | L70: 0 | M70: 0 | N70: 7300
A71: 04/08/2023 | B71: FA-B 0005-00008550 | C71: .CONSUMIDOR FINAL | D71: Consumidor Final | F71: 1983.47 | G71: 0 | H71: 0 | I71: 0 | J71: 0 | K71: 416.53 | L71: 0 | M71: 0 | N71: 2400
A72: 04/08/2023 | B72: FA-B 0005-00008551 | C72: .CONSUMIDOR FINAL | D72: Consumidor Final | F72: 13553.72 | G72: 0 | H72: 0 | I72: 0 | J72: 0 | K72: 2846.28 | L72: 0 | M72: 0 | N72: 16400
A73: 04/08/2023 | B73: FA-B 0005-00008552 | C73: .CONSUMIDOR FINAL | D73: Consumidor Final | F73: 6024.79 | G73: 0 | H73: 0 | I73: 0 | J73: 0 | K73: 1265.21 | L73: 0 | M73: 0 | N73: 7290
... A76: 04/08/2023 | B76: FA-B 0005-00008555 | C76: .CONSUMIDOR FINAL | D76: Consumidor Final | F76: 11570.25 | G76: 0 | H76: 0 | I76: 0 | J76: 0 | K76: 2429.75 | L76: 0 | M76: 0 | N76: 14000
A77: 04/08/2023 | B77: FA-A 0006 - 00000375 | C77: Galeno (Alq Ambulatorios) | D77: IVA Responsable Inscripto | E77: 30522428163 | F77: 4459509.1 | G77: 0 | H77: 0 | I77: 0 | J77: 0 | K77: 936496.91 | L77: 0 | M77: 0 | N77: 5396006
A78: 04/08/2023 | B78: FA-A 0007-00001554 | C78: Zc Diabetes Srl | D78: IVA Responsable Inscripto | E78: 30710961790 | F78: 46790.08 | G78: 0 | H78: 0 | I78: 0 | J78: 0 | K78: 9825.92 | L78: 0 | M78: 0 | N78: 56616
A79: 04/08/2023 | B79: FA-B 0007-00004540 | C79: Herman Patricia | D79: Consumidor Final | E79: 21645724 | F79: 8677.69 | G79: 0 | H79: 0 | I79: 0 | J79: 0 | K79: 1822.31 | L79: 0 | M79: 0 | N79: 10500
A80: 04/08/2023 | B80: FA-B 0007-00004541 | C80: LOCOCO, CARMEN | D80: Consumidor Final | E80: 17198648 | F80: 7438.02 | G80: 0 | H80: 0 | I80: 0 | J80: 0 | K80: 1561.98 | L80: 0 | M80: 0 | N80: 9000
A81: 04/08/2023 | B81: FA-B 0007-00004542 | C81: GABRIELA VANINA GALLO | D81: Consumidor Final | E81: 26542077 | F81: 12644.63 | G81: 0 | H81: 0 | I81: 0 | J81: 0 | K81: 2655.37 | L81: 0 | M81: 0 | N81: 15300
A82: 04/08/2023 | B82: FA-B 0007-00004543 | C82: VOLPI, ALBERTO JAVIER | D82: Consumidor Final | E82: 21363216 | F82: 6611.57 | G82: 0 | H82: 0 | I82: 0 | J82: 0 | K82: 1388.43 | L82: 0 | M82: 0 | N82: 8000
A83: 07/08/2023 | B83: FA-B 0005-00008556 | C83: .CONSUMIDOR FINAL | D83: Consumidor Final | F83: 2479.34 | G83: 0 | H83: 0 | I83: 0 | J83: 0 | K83: 520.66 | L83: 0 | M83: 0 | N83: 3000
A84: 07/08/2023 | B84: FA-B 0005-00008557 | C84: .CONSUMIDOR FINAL | D84: Consumidor Final | F84: 1074.38 | G84: 0 | H84: 0 | I84: 0 | J84: 0 | K84: 225.62 | L84: 0 | M84: 0 | N84: 1300
A85: 07/08/2023 | B85: FA-B 0005-00008558 | C85: .CONSUMIDOR FINAL | D85: Consumidor Final | F85: 3719.01 | G85: 0 | H85: 0 | I85: 0 | J85: 0 | K85: 780.99 | L85: 0 | M85: 0 | N85: 4500
A86: 07/08/2023 | B86: FA-B 0005-00008559 | C86: .CONSUMIDOR FINAL | D86: Consumidor Final | F86: 8429.75 | G86: 0 | H86: 0 | I86: 0 | J86: 0 | K86: 1770.25 | L86: 0 | M86: 0 | N86: 10200
A87: 07/08/2023 | B87: FA-B 0005-00008560 | C87: .CONSUMIDOR FINAL | D87: Consumidor Final | F87: 826.45 | G87: 0 | H87: 0 | I87: 0 | J87: 0 | K87: 173.55 | L87: 0 | M87: 0 | N87: 1000
A88: 07/08/2023 | B88: FA-B 0005-00008561 | C88: .CONSUMIDOR FINAL | D88: Consumidor Final | F88: 5785.12 | G88: 0 | H88: 0 | I88: 0 | J88: 0 | K88: 1214.88 | L88: 0 | M88: 0 | N88: 7000
A89: 07/08/2023 | B89: FA-B 0005-00008562 | C89: .CONSUMIDOR FINAL | D89: Consumidor Final | F89: 6776.86 | G89: 0 | H89: 0 | I89: 0 | J89: 0 | K89: 1423.14 | L89: 0 | M89: 0 | N89: 8200
A90: 07/08/2023 | B90: FA-B 0005-00008563 | C90: .CONSUMIDOR FINAL | D90: Consumidor Final | F90: 15702.48 | G90: 0 | H90: 0 | I90: 0 | J90: 0 | K90: 3297.52 | L90: 0 | M90: 0 | N90: 19000
A91: 07/08/2023 | B91: FA-B 0005-00008564 | C91: .CONSUMIDOR FINAL | D91: Consumidor Final | F91: 6033.06 | G91: 0 | H91: 0 | I91: 0 | J91: 0 | K91: 1266.94 | L91: 0 | M91: 0 | N91: 7300
A92: 07/08/2023 | B92: FA-A 0007-00001555 | C92: Obra Social Union Personal De La Union Del Personal Civil De La Nacion | D92: IVA Responsable Inscripto | E92: 30683032227 | F92: 345972.53 | G92: 0 | H92: 0 | I92: 0 | J92: 0 | K92: 72654.23 | L92: 0 | M92: 0 | N92: 418626.76
A93: 07/08/2023 | B93: FA-A 0007-00001556 | C93: Obra Social Union Personal De La Union Del Personal Civil De La Nacion | D93: IVA Responsable Inscripto | E93: 30683032227 | F93: 98140.5 | G93: 0 | H93: 0 | I93: 0 | J93: 0 | K93: 20609.51 | L93: 0 | M93: 0 | N93: 118750.01
A94: 07/08/2023 | B94: FA-A 0007-00001557 | C94: Obra Social Union Personal De La Union Del Personal Civil De La Nacion | D94: IVA Responsable Inscripto | E94: 30683032227 | F94: 24380.17 | G94: 0 | H94: 0 | I94: 0 | J94: 0 | K94: 5119.84 | L94: 0 | M94: 0 | N94: 29500.01
A95: 07/08/2023 | B95: FA-A 0007-00001558 | C95: Obra Social Del Personal De Las Telecomunicaciones De La Republica Argentina | D95: IVA Responsable Inscripto | E95: 30608716390 | F95: 8578.51 | G95: 0 | H95: 0 | I95: 0 | J95: 0 | K95: 1801.49 | L95: 0 | M95: 0 | N95: 10380
A96: 07/08/2023 | B96: FA-A 0007-00001559 | C96: Obra Social Del Personal De Las Telecomunicaciones De La Republica Argentina | D96: IVA Responsable Inscripto | E96: 30608716390 | F96: 1972.73 | G96: 0 | H96: 0 | I96: 0 | J96: 0 | K96: 414.27 | L96: 0 | M96: 0 | N96: 2387
A97: 07/08/2023 | B97: FA-A 0007-00001560 | C97: Obra Social Del Personal De Las Telecomunicaciones De La Republica Argentina | D97: IVA Responsable Inscripto | E97: 30608716390 | F97: 8578.51 | G97: 0 | H97: 0 | I97: 0 | J97: 0 | K97: 1801.49 | L97: 0 | M97: 0 | N97: 10380
A98: 07/08/2023 | B98: FA-A 0007-00001561 | C98: Obra Social Del Personal De Las Telecomunicaciones De La Republica Argentina | D98: IVA Responsable Inscripto | E98: 30608716390 | F98: 2676.46 | G98: 0 | H98: 0 | I98: 0 | J98: 0 | K98: 562.06 | L98: 0 | M98: 0 | N98: 3238.52
A99: 07/08/2023 | B99: FA-A 0007-00001562 | C99: Amparo Salud S.R.L. | D99: IVA Responsable Inscripto | E99: 30715186655 | F99: 81080.3 | G99: 0 | H99: 0 | I99: 0 | J99: 0 | K99: 17026.86 | L99: 0 | M99: 0 | N99: 98107.16
A100: 07/08/2023 | B100: FA-A 0007-00001563 | C100: Amparo Salud S.R.L. | D100: IVA Responsable Inscripto | E100: 30715186655 | F100: 5263.64 | G100: 0 | H100: 0 | I100: 0 | J100: 0 | K100: 1105.36 | L100: 0 | M100: 0 | N100: 6369
A101: 07/08/2023 | B101: FA-A 0007-00001564 | C101: Medicus Sociedad Anonima De Asistencia Medica Y Cientifica | D101: IVA Responsable Inscripto | E101: 30546771314 | F101: 6389.31 | G101: 0 | H101: 0 | I101: 0 | J101: 0 | K101: 1341.76 | L101: 0 | M101: 0 | N101: 7731.07
A102: 07/08/2023 | B102: FA-A 0007-00001565 | C102: Login Door S.A | D102: IVA Responsable Inscripto | E102: 30711244383 | F102: 6916.64 | G102: 0 | H102: 0 | I102: 0 | J102: 0 | K102: 1452.49 | L102: 0 | M102: 0 | N102: 8369.13
A103: 07/08/2023 | B103: FA-A 0007-00001566 | C103: Fundacion Empresaria Maderera | D103: IVA Responsable Inscripto | E103: 30657418877 | F103: 3615.51 | G103: 0 | H103: 0 | I103: 0 | J103: 0 | K103: 759.25 | L103: 0 | M103: 0 | N103: 4374.76
... A109: 07/08/2023 | B109: FA-B 0007-00004549 | C109: Obra Social De Los Trabajadores De La Industria Del Gas | D109: IVA Sujeto Exento | E109: 30658137642 | F109: 8846.28 | G109: 0 | H109: 0 | I109: 0 | J109: 0 | K109: 1857.72 | L109: 0 | M109: 0 | N109: 10704
...
