Workbook

Sheet Lista_CUIT
A1: CUIT | B1: RAZON SOCIAL | C1: Tipo de Gasto | D1: PROVINCIA
A2: 30605344352 | B2: CONSORCIO BTOME MITRE 2466 | C2: ALQUILER | G2: Mercaderia
A3: 30717029336 | B3: ECOMOVE SRL | C3: BIENES DE USO | G3: Servicios Gas, Luz, etc.
A4: 30650600238 | B4: PECTAGAR S R L | C4: BIENES DE USO | G4: Gastos catering
A5: 30709317101 | B5: CDTEK SRL | C5: BIENES DE USO | G5: Combustibe
A6: 30716701820 | B6: MENTA GRANIZADA | C6: BIENES DE USO | G6: Gastos Varios
A7: 33708543409 | B7: DAMARFU SA | C7: BIENES DE USO | G7: Gastos seguridad
A8: 30715053744 | B8: FEMEN SA | C8: CARRO PORTA HERRAMIENTAS | G8: Librería
A9: 30715048066 | B9: ROLLS Y EMPANADAS SA | C9: CATERING | G9: Gastos mantenimiento
A10: 20214752868 | B10: RUIZ FERNANDO JAVIER | C10: COCHERA | G10: Gastos comercializacion
A11: 30678774495 | B11: OPER. DE EST. DE SERV. SA | C11: COMBUSTIBLE | G11: Alquiler
A12: 30695542476 | B12: PAN AMERICAN ENERGY LLC | C12: COMBUSTIBLE | G12: Honorarios contables
A13: 30574300858 | B13: SHELL SA | C13: COMBUSTIBLE | G13: Gastos administrativos
... A22: 30615530065 | B22: KINKA SA | C22: COMBUSTIBLE | G22: Alojamiento-Varios
A23: 20217165114 | B23: MARTINO CARLOS ALBERTO | C23: COMBUSTIBLE
A24: 30685116657 | B24: MIRVAR SA | C24: COMBUSTIBLE
A25: 33608724279 | B25: NAFPUR SA | C25: COMBUSTIBLE
A26: 30707983732 | B26: NAFPUR XXI SA | C26: COMBUSTIBLE
A27: 30678774495 | B27: OPER. DE EST. DE SERV. SA | C27: COMBUSTIBLE
A28: 30678774495 | B28: OPER. DE EST. SERV. S.A. | C28: COMBUSTIBLE
A29: 30678774495 | B29: OPER. DE EST. SERV. S.A. | C29: COMBUSTIBLE
A30: 30695542476 | B30: PAN AMERICAN ENERGY LLC. SUC. | C30: COMBUSTIBLE
A31: 30692317951 | B31: POSTA PILAR SA | C31: COMBUSTIBLE
A32: 30677909001 | B32: RERIFE SA | C32: COMBUSTIBLE
A33: 30538456876 | B33: RIO DE JANEIRO SA | C33: COMBUSTIBLE
A34: 30574300858 | B34: SHELL SA | C34: COMBUSTIBLE
... A106: 30662533072 | B106: ULTRALIGHT SRL | C106: Gastos Oficina
A107: 20247521764 | B107: SOBRINO LEANDRO HUGO | C107: Gastos Varios | D107: SOBRINO LEANDRO HUGO
A108: 30-67877449-5 | B108: OPERADORA DE ESTACIONES DE SERVICIOS SA | C108: Gastos Varios
A109: 30690536079 | B109: ACCESOR SRL | C109: Gastos Varios
A110: 27184156658 | B110: NUDELMAN GRACIELA MONICA | C110: Gastos Varios
A111: 20083925680 | B111: ALFREDO DANIEL FERNANDEZ | C111: Gastos Varios
A112: 23945042079 | B112: ALVARENGA VILLAR LUIS F | C112: Gastos Varios
A113: 20927832136 | B113: ARANCIBIA IBACETA CIPRIANO | C113: Gastos Varios
A114: 20045180620 | B114: ARUGUETE ENRIQUE JORGE | C114: Gastos Varios
A115: 30712458468 | B115: BEEL SUL S.A. | C115: Gastos Varios
A116: 30712387315 | B116: BIALA SRL | C116: Gastos Varios
A117: 30590360763 | B117: CENCOSUD S.A. | C117: Gastos Varios
A118: 30702286987 | B118: CINTAS OUTLET SA | C118: Gastos Varios
A119: 30548345525 | B119: Copy Max | C119: Gastos Varios
A120: 30715619055 | B120: PETIT PET SHOP S.R.L | C120: Gastos Varios
... A821: 20275363279 | B821: PEREZ QUESADA LORENZO | C821: Mercaderia
B822: POLYFILM SRL | C822: Mercaderia
A823: 20304776863 | B823: CHRISTIAN MARTIN ESQUIVEL | C823: MOTO
A824: 20265592628 | B824: CRISTIAN D BRESSANI | C824: MOTO
A825: 30711877386 | B825: RAMIREZEI SRL | C825: MUEBLES Y UTILES
A826: 30694444926 | B826: EMPRENDIMIENTOS L&L SRL | C826: MUEBLES Y UTILES
A827: 20261338891 | B827: TIENDA PEPINO | C827: MUEBLES Y UTILES
A828: 30711877386 | B828: RAMIREZEI SRL | C828: MUEBLES Y UTILES
A829: 30500987878 | B829: FV SA | C829: OTROS
A830: 30712273158 | B830: RINGO BS AS S.A. | C830: OTROS
A831: 30715585215 | B831: TRANSPORTES A4 SA | C831: Otros
A832: 30712273158 | B832: RINGO BS AS S.A. | C832: Otros
A833: 30716172011 | B833: EVALUACION MEDIOAMBIENTAL S.R.L. | C833: SERVICIO
A834: 30689153689 | B834: LIBRERÍA INTERNACIONAL | C834: Papeleria e Impresos
... A874: 20260499085 | B874: SABELLI ARIEL OSCAR | C874: TAXI
A875: 30575019524 | B875: 100000 LAMPARAS SRL
A876: 30714869937 | B876: 60 LIBRAS SRL
A877: 30692212130 | B877: A R C CONSTRUCCIONES S.A.
A878: 30702017498 | B878: ABBS POINT DESING S.A.
A879: 30715243349 | B879: ADSE S.A
A880: 30628274327 | B880: AGIRA SA
A881: 30695512476 | B881: PAN AMERICAN ENERGY
A882: 30710799241 | B882: ALANAR S.R.L.
A883: 20236101127 | B883: ALEJANDRO DARIO LOPEZ
A884: 20291929126 | B884: ALEJANDRO MIGUEL DAUBLER
A885: 30602699826 | B885: ALKO SRL
A886: 30715190385 | B886: ALL FEDERAL SA.
... A908: 30677237119 | B908: AUTOPISTAS DEL SOL SA
A909: 30607371799 | B909: AUTOSERVICIO DIARCO SA
A910: 30667187091 | B910: AUTOSTADT S.A.
A911: 30711470804 | B911: AUTOSTRASSE S.A.
A912: 20083762102 | B912: AVANCE-MAG
A913: 20287830980 | B913: AVILA MARTIN LEONARDO
A914: 30535612117 | B914: AYUDA MUT. DEL PERS. DE GENDAR
A915: 20179619483 | B915: BALE JORGE CARLOS
A916: 30580189411 | B916: BANCO ITAU ARG SA
A917: 30646362675 | B917: BAUMGARTEN GRAFICA ARG SA
A918: 30714675601 | B918: BELGRANO NEUMATICOS S.A.
A919: 30568222187 | B919: BELLINI HNOS SRL
A920: 27248212646 | B920: BELLOMO MARIA MERCEDES
A921: 27115740666 | B921: BEN Y BEN
... A1334: 33517381549 | B1334: FLUODINAMICA S A
A1335: 30-70094095-7 | B1335: UPS DE ARGENTINA S A
A1336: 20271587806 | B1336: CABRERA SERGIO GABRIEL
A1337: 30629741077 | B1337: WELCOMETANO SRL
A1338: 30708395443 | B1338: SUPERFOTO SRL
A1339: 27954094354 | B1339: FLORES VIDARTE DIANA ESMERALD
A1340: 20926926846 | B1340: LIAO YU TING
A1341: 30715920642 | B1341: THE GLIMMER TWINS S.R.L.
A1342: 30715536079 | B1342: FRANKFULL S.R.L
A1343: 27044202625 | B1343: BENSABAT GRACIELA NOEMI
A1344: 30715667386 | B1344: DIGITAL SALE SRL
A1345: 30710563639 | B1345: PEDRO CALDERON DE LA BARCA 614
A1346: 30714269336 | B1346: ELECTRO TOOLS SRL
A1347: 23285067359 | B1347: BELOTTI JUAN PABLO
... A1726: 30692857611 | B1726: BAGUI S.A.
A1728: 27387896150 | B1728: LIPANOVICH MARIA SOL | C1728: Servicios Informatica
A1729: 20259150249 | B1729: BIANCHI CRISTIAN MAXIMILIANO | C1729: Gastos Varios
A1730: 20233336735 | B1730: CURA BERNARDO | C1730: Gastos Varios
...

Sheet Abr-22
B1: LIBRO IVA COMPRAS | G1: CORITEC S.R.L. | N1: 44652
B3: TOTAL COMPRAS | G3: TOTAL CREDITO FISCAL | J3: TOTAL VENTAS NETAS | M3: TOTAL DEBITO FISCAL | P3: RESULTADO
B4: =SUM('Abr-22'!$H$51)+'Abr-22'!$G$64 -> 2080834.5 | G4: ='Abr-22'!$I$51+'Abr-22'!$J$51+'Abr-22'!$K$51+'Abr-22'!$H$64+'Abr-22'!$I$64 -> 388881.49 | J4: ='Abr-22'!$H$93+'Abr-22'!$H$100 -> 12289541 | M4: ='Abr-22'!$I$93+'Abr-22'!$J$93+'Abr-22'!$I$100+'Abr-22'!$J$100 -> 1572095.3 | P4: =G4-M4 -> -1183213.8
O7: no esta configurado para q esten en negativo
B8: FECHA | C8: TIPO | D8: PTO VTA | E8: NRO. CPTE | F8: CUIT | G8: RAZON SOCIAL | H8: NETO GRAVADO | I8: IVA 21 % | J8: IVA 27% | K8: IVA 10,5% | L8: PERC. IVA | M8: PERC IIBB BS AS | N8: PERC. IIBB CABA | O8: Otros / No Grav. | P8: TOTAL | Q8: Tipo de Gasto | R8: Provincia
B9: 44652 | C9: 1 | D9: 3 | E9: 153109 | F9: 30707135596 | G9: =IFERROR(IF('Abr-22'!$F9="","-",VLOOKUP('Abr-22'!$F9,Lista_CUIT!$A$1:$D$1871,2,0)),"CUIT NO CARGADO") -> CITILAN ARGENTINA SA | H9: 2725.92 | I9: =IF('Abr-22'!$H9="","",'Abr-22'!$H9*0.21) -> 572.4432 | P9: =SUM('Abr-22'!$H9:$O9) -> 3298.3632 | Q9: =IFERROR(IF('Abr-22'!$F9="","-",VLOOKUP('Abr-22'!$F9,Lista_CUIT!$A$1:$D$1871,3,0)),"CUIT NO CARGADO") -> SERVICIOS GAS, LUZ, ETC | R9: =IFERROR(IF('Abr-22'!$F9="","-",VLOOKUP('Abr-22'!$F9,Lista_CUIT!$A$1:$D$1871,4,0)),"CUIT NO CARGADO") -> 0
B10: 44652 | C10: 1 | D10: 3 | E10: 518 | F10: 30715402765 | G10: =IFERROR(IF('Abr-22'!$F10="","-",VLOOKUP('Abr-22'!$F10,Lista_CUIT!$A$1:$D$1871,2,0)),"CUIT NO CARGADO") -> RIO 265 SRL | H10: 7190.08 | I10: =IF('Abr-22'!$H10="","",'Abr-22'!$H10*0.21) -> 1509.9168 | P10: =SUM('Abr-22'!$H10:$O10) -> 8699.9968 | Q10: =IFERROR(IF('Abr-22'!$F10="","-",VLOOKUP('Abr-22'!$F10,Lista_CUIT!$A$1:$D$1871,3,0)),"CUIT NO CARGADO") -> GTOS VARIOS-ESTACIONAMIENTO HORACIO | R10: =IFERROR(IF('Abr-22'!$F10="","-",VLOOKUP('Abr-22'!$F10,Lista_CUIT!$A$1:$D$1871,4,0)),"CUIT NO CARGADO") -> 0
B11: 44652 | C11: 1 | D11: 3 | E11: 254 | F11: 20921575743 | G11: =IFERROR(IF('Abr-22'!$F11="","-",VLOOKUP('Abr-22'!$F11,Lista_CUIT!$A$1:$D$1871,2,0)),"CUIT NO CARGADO") -> RIOS GOMEZ JOSE ANTONIO | H11: 54000 | I11: =IF('Abr-22'!$H11="","",'Abr-22'!$H11*0.21) -> 11340 | P11: =SUM('Abr-22'!$H11:$O11) -> 65340 | Q11: =IFERROR(IF('Abr-22'!$F11="","-",VLOOKUP('Abr-22'!$F11,Lista_CUIT!$A$1:$D$1871,3,0)),"CUIT NO CARGADO") -> Papeleria e Impresos | R11: =IFERROR(IF('Abr-22'!$F11="","-",VLOOKUP('Abr-22'!$F11,Lista_CUIT!$A$1:$D$1871,4,0)),"CUIT NO CARGADO") -> 0
B12: 44652 | C12: 1 | D12: 2 | E12: 2022 | F12: 30709131733 | G12: =IFERROR(IF('Abr-22'!$F12="","-",VLOOKUP('Abr-22'!$F12,Lista_CUIT!$A$1:$D$1871,2,0)),"CUIT NO CARGADO") -> DIGAS SRL | H12: 193720 | I12: =IF('Abr-22'!$H12="","",'Abr-22'!$H12*0.21) -> 40681.2 | P12: =SUM('Abr-22'!$H12:$O12) -> 234401.2 | Q12: =IFERROR(IF('Abr-22'!$F12="","-",VLOOKUP('Abr-22'!$F12,Lista_CUIT!$A$1:$D$1871,3,0)),"CUIT NO CARGADO") -> INSUMO | R12: =IFERROR(IF('Abr-22'!$F12="","-",VLOOKUP('Abr-22'!$F12,Lista_CUIT!$A$1:$D$1871,4,0)),"CUIT NO CARGADO") -> 0
B13: 44652 | C13: 1 | D13: 7 | E13: 52774 | F13: 30626629942 | G13: =IFERROR(IF('Abr-22'!$F13="","-",VLOOKUP('Abr-22'!$F13,Lista_CUIT!$A$1:$D$1871,2,0)),"CUIT NO CARGADO") -> INSTRUMENTAL PASTEUR S R L | H13: 5619 | K13: 589.995 | P13: =SUM('Abr-22'!$H13:$O13) -> 6208.995 | Q13: =IFERROR(IF('Abr-22'!$F13="","-",VLOOKUP('Abr-22'!$F13,Lista_CUIT!$A$1:$D$1871,3,0)),"CUIT NO CARGADO") -> Gastos Varios | R13: =IFERROR(IF('Abr-22'!$F13="","-",VLOOKUP('Abr-22'!$F13,Lista_CUIT!$A$1:$D$1871,4,0)),"CUIT NO CARGADO") -> 0
B14: 44656 | C14: 1 | D14: 26 | E14: 2356 | F14: 30677470123 | G14: =IFERROR(IF('Abr-22'!$F14="","-",VLOOKUP('Abr-22'!$F14,Lista_CUIT!$A$1:$D$1871,2,0)),"CUIT NO CARGADO") -> NEUMATICOS VERONA SA | H14: 86942.16 | I14: =IF('Abr-22'!$H14="","",'Abr-22'!$H14*0.21) -> 18257.854 | P14: =SUM('Abr-22'!$H14:$O14) -> 105200.01 | Q14: =IFERROR(IF('Abr-22'!$F14="","-",VLOOKUP('Abr-22'!$F14,Lista_CUIT!$A$1:$D$1871,3,0)),"CUIT NO CARGADO") -> Mantenimiento Rodados | R14: =IFERROR(IF('Abr-22'!$F14="","-",VLOOKUP('Abr-22'!$F14,Lista_CUIT!$A$1:$D$1871,4,0)),"CUIT NO CARGADO") -> 0
B15: 44657 | C15: 1 | D15: 60 | E15: 6863 | F15: 30547188760 | G15: =IFERROR(IF('Abr-22'!$F15="","-",VLOOKUP('Abr-22'!$F15,Lista_CUIT!$A$1:$D$1871,2,0)),"CUIT NO CARGADO") -> LONCO HUE SA | H15: 1369.86 | I15: =IF('Abr-22'!$H15="","",'Abr-22'!$H15*0.21) -> 287.6706 | P15: =SUM('Abr-22'!$H15:$O15) -> 1657.5306 | Q15: =IFERROR(IF('Abr-22'!$F15="","-",VLOOKUP('Abr-22'!$F15,Lista_CUIT!$A$1:$D$1871,3,0)),"CUIT NO CARGADO") -> INSUMO | R15: =IFERROR(IF('Abr-22'!$F15="","-",VLOOKUP('Abr-22'!$F15,Lista_CUIT!$A$1:$D$1871,4,0)),"CUIT NO CARGADO") -> 0
B16: 44657 | C16: 1 | D16: 280 | E16: 1358550 | F16: 30580111315 | G16: =IFERROR(IF('Abr-22'!$F16="","-",VLOOKUP('Abr-22'!$F16,Lista_CUIT!$A$1:$D$1871,2,0)),"CUIT NO CARGADO") -> DHL EXPRESS ARG SA | H16: 348336.45 | I16: 703.71 | K16: 36223.193 | O16: -313623.44 | P16: =SUM('Abr-22'!$H16:$O16) -> 71639.912 | Q16: =IFERROR(IF('Abr-22'!$F16="","-",VLOOKUP('Abr-22'!$F16,Lista_CUIT!$A$1:$D$1871,3,0)),"CUIT NO CARGADO") -> GTOS IMP. | R16: =IFERROR(IF('Abr-22'!$F16="","-",VLOOKUP('Abr-22'!$F16,Lista_CUIT!$A$1:$D$1871,4,0)),"CUIT NO CARGADO") -> 0
B17: 44657 | C17: 1 | D17: 60 | E17: 6857 | F17: 30547188760 | G17: =IFERROR(IF('Abr-22'!$F17="","-",VLOOKUP('Abr-22'!$F17,Lista_CUIT!$A$1:$D$1871,2,0)),"CUIT NO CARGADO") -> LONCO HUE SA | H17: 13634.24 | I17: =IF('Abr-22'!$H17="","",'Abr-22'!$H17*0.21) -> 2863.1904 | P17: =SUM('Abr-22'!$H17:$O17) -> 16497.43 | Q17: =IFERROR(IF('Abr-22'!$F17="","-",VLOOKUP('Abr-22'!$F17,Lista_CUIT!$A$1:$D$1871,3,0)),"CUIT NO CARGADO") -> INSUMO | R17: =IFERROR(IF('Abr-22'!$F17="","-",VLOOKUP('Abr-22'!$F17,Lista_CUIT!$A$1:$D$1871,4,0)),"CUIT NO CARGADO") -> 0
B18: 44657 | C18: 1 | D18: 60 | E18: 6862 | F18: 30547188760 | G18: =IFERROR(IF('Abr-22'!$F18="","-",VLOOKUP('Abr-22'!$F18,Lista_CUIT!$A$1:$D$1871,2,0)),"CUIT NO CARGADO") -> LONCO HUE SA | H18: 334224.48 | I18: =IF('Abr-22'!$H18="","",'Abr-22'!$H18*0.21) -> 70187.141 | P18: =SUM('Abr-22'!$H18:$O18) -> 404411.62 | Q18: =IFERROR(IF('Abr-22'!$F18="","-",VLOOKUP('Abr-22'!$F18,Lista_CUIT!$A$1:$D$1871,3,0)),"CUIT NO CARGADO") -> INSUMO | R18: =IFERROR(IF('Abr-22'!$F18="","-",VLOOKUP('Abr-22'!$F18,Lista_CUIT!$A$1:$D$1871,4,0)),"CUIT NO CARGADO") -> 0
B19: 44662 | C19: 1 | D19: 700 | E19: 360195 | F19: 30580111315 | G19: =IFERROR(IF('Abr-22'!$F19="","-",VLOOKUP('Abr-22'!$F19,Lista_CUIT!$A$1:$D$1871,2,0)),"CUIT NO CARGADO") -> DHL EXPRESS ARG SA | I19: =IF('Abr-22'!$H19="","",'Abr-22'!$H19*0.21) | O19: 8033.97 | P19: =SUM('Abr-22'!$H19:$O19) -> 8033.97 | Q19: =IFERROR(IF('Abr-22'!$F19="","-",VLOOKUP('Abr-22'!$F19,Lista_CUIT!$A$1:$D$1871,3,0)),"CUIT NO CARGADO") -> GTOS IMP. | R19: =IFERROR(IF('Abr-22'!$F19="","-",VLOOKUP('Abr-22'!$F19,Lista_CUIT!$A$1:$D$1871,4,0)),"CUIT NO CARGADO") -> 0
B20: 44662 | C20: 1 | D20: 700 | E20: 361293 | F20: 30580111315 | G20: =IFERROR(IF('Abr-22'!$F20="","-",VLOOKUP('Abr-22'!$F20,Lista_CUIT!$A$1:$D$1871,2,0)),"CUIT NO CARGADO") -> DHL EXPRESS ARG SA | I20: =IF('Abr-22'!$H20="","",'Abr-22'!$H20*0.21) | O20: 44108.28 | P20: =SUM('Abr-22'!$H20:$O20) -> 44108.28 | Q20: =IFERROR(IF('Abr-22'!$F20="","-",VLOOKUP('Abr-22'!$F20,Lista_CUIT!$A$1:$D$1871,3,0)),"CUIT NO CARGADO") -> GTOS IMP. | R20: =IFERROR(IF('Abr-22'!$F20="","-",VLOOKUP('Abr-22'!$F20,Lista_CUIT!$A$1:$D$1871,4,0)),"CUIT NO CARGADO") -> 0
B21: 44662 | C21: 1 | D21: 7 | E21: 6293 | F21: 30604413482 | G21: =IFERROR(IF('Abr-22'!$F21="","-",VLOOKUP('Abr-22'!$F21,Lista_CUIT!$A$1:$D$1871,2,0)),"CUIT NO CARGADO") -> BULONERA VIETRI SRL | H21: 98274 | I21: =IF('Abr-22'!$H21="","",'Abr-22'!$H21*0.21) -> 20637.54 | P21: =SUM('Abr-22'!$H21:$O21) -> 118911.54 | Q21: =IFERROR(IF('Abr-22'!$F21="","-",VLOOKUP('Abr-22'!$F21,Lista_CUIT!$A$1:$D$1871,3,0)),"CUIT NO CARGADO") -> INSUMO | R21: =IFERROR(IF('Abr-22'!$F21="","-",VLOOKUP('Abr-22'!$F21,Lista_CUIT!$A$1:$D$1871,4,0)),"CUIT NO CARGADO") -> 0
B22: 44662 | C22: 1 | D22: 2466 | E22: 345117 | F22: 30678814357 | G22: =IFERROR(IF('Abr-22'!$F22="","-",VLOOKUP('Abr-22'!$F22,Lista_CUIT!$A$1:$D$1871,2,0)),"CUIT NO CARGADO") -> Telefonica Moviles Argentina SA | H22: 1765 | J22: 476.55 | O22: 92.89 | P22: =SUM('Abr-22'!$H22:$O22) -> 2334.44 | Q22: =IFERROR(IF('Abr-22'!$F22="","-",VLOOKUP('Abr-22'!$F22,Lista_CUIT!$A$1:$D$1871,3,0)),"CUIT NO CARGADO") -> SERVICIOS GAS, LUZ, ETC | R22: =IFERROR(IF('Abr-22'!$F22="","-",VLOOKUP('Abr-22'!$F22,Lista_CUIT!$A$1:$D$1871,4,0)),"CUIT NO CARGADO") -> 0
B23: 44666 | C23: 1 | D23: 5199 | E23: 12079 | F23: 30695542476 | G23: =IFERROR(IF('Abr-22'!$F23="","-",VLOOKUP('Abr-22'!$F23,Lista_CUIT!$A$1:$D$1871,2,0)),"CUIT NO CARGADO") -> PAN AMERICAN ENERGY LLC | H23: 3603.39 | I23: =IF('Abr-22'!$H23="","",'Abr-22'!$H23*0.21) -> 756.7119 | L23: 108.1 | O23: 779.8 | P23: =SUM('Abr-22'!$H23:$O23) -> 5248.0019 | Q23: =IFERROR(IF('Abr-22'!$F23="","-",VLOOKUP('Abr-22'!$F23,Lista_CUIT!$A$1:$D$1871,3,0)),"CUIT NO CARGADO") -> COMBUSTIBLE | R23: =IFERROR(IF('Abr-22'!$F23="","-",VLOOKUP('Abr-22'!$F23,Lista_CUIT!$A$1:$D$1871,4,0)),"CUIT NO CARGADO") -> 0
B24: 44669 | C24: 1 | D24: 700 | E24: 364547 | F24: 30580111315 | G24: =IFERROR(IF('Abr-22'!$F24="","-",VLOOKUP('Abr-22'!$F24,Lista_CUIT!$A$1:$D$1871,2,0)),"CUIT NO CARGADO") -> DHL EXPRESS ARG SA | I24: =IF('Abr-22'!$H24="","",'Abr-22'!$H24*0.21) | O24: 12877.34 | P24: =SUM('Abr-22'!$H24:$O24) -> 12877.34 | Q24: =IFERROR(IF('Abr-22'!$F24="","-",VLOOKUP('Abr-22'!$F24,Lista_CUIT!$A$1:$D$1871,3,0)),"CUIT NO CARGADO") -> GTOS IMP. | R24: =IFERROR(IF('Abr-22'!$F24="","-",VLOOKUP('Abr-22'!$F24,Lista_CUIT!$A$1:$D$1871,4,0)),"CUIT NO CARGADO") -> 0
B25: 44669 | C25: 1 | D25: 4 | E25: 1886 | F25: 20068864934 | G25: =IFERROR(IF('Abr-22'!$F25="","-",VLOOKUP('Abr-22'!$F25,Lista_CUIT!$A$1:$D$1871,2,0)),"CUIT NO CARGADO") -> DISTRIBUIDORA SANITARIA JACOBO | H25: 1289.26 | I25: =IF('Abr-22'!$H25="","",'Abr-22'!$H25*0.21) -> 270.7446 | P25: =SUM('Abr-22'!$H25:$O25) -> 1560.0046 | Q25: =IFERROR(IF('Abr-22'!$F25="","-",VLOOKUP('Abr-22'!$F25,Lista_CUIT!$A$1:$D$1871,3,0)),"CUIT NO CARGADO") -> INSUMO | R25: =IFERROR(IF('Abr-22'!$F25="","-",VLOOKUP('Abr-22'!$F25,Lista_CUIT!$A$1:$D$1871,4,0)),"CUIT NO CARGADO") -> 0
B26: 44669 | C26: 1 | D26: 2 | E26: 128 | F26: 20125142851 | G26: =IFERROR(IF('Abr-22'!$F26="","-",VLOOKUP('Abr-22'!$F26,Lista_CUIT!$A$1:$D$1871,2,0)),"CUIT NO CARGADO") -> FEDERICI NICOLAS JOSE | H26: 54222.3 | I26: =IF('Abr-22'!$H26="","",'Abr-22'!$H26*0.21) -> 11386.683 | P26: =SUM('Abr-22'!$H26:$O26) -> 65608.983 | Q26: =IFERROR(IF('Abr-22'!$F26="","-",VLOOKUP('Abr-22'!$F26,Lista_CUIT!$A$1:$D$1871,3,0)),"CUIT NO CARGADO") -> INSUMO | R26: =IFERROR(IF('Abr-22'!$F26="","-",VLOOKUP('Abr-22'!$F26,Lista_CUIT!$A$1:$D$1871,4,0)),"CUIT NO CARGADO") -> 0
B27: 44669 | C27: 1 | D27: 2 | E27: 129 | F27: 20125142851 | G27: =IFERROR(IF('Abr-22'!$F27="","-",VLOOKUP('Abr-22'!$F27,Lista_CUIT!$A$1:$D$1871,2,0)),"CUIT NO CARGADO") -> FEDERICI NICOLAS JOSE | H27: 59539.92 | I27: =IF('Abr-22'!$H27="","",'Abr-22'!$H27*0.21) -> 12503.383 | P27: =SUM('Abr-22'!$H27:$O27) -> 72043.303 | Q27: =IFERROR(IF('Abr-22'!$F27="","-",VLOOKUP('Abr-22'!$F27,Lista_CUIT!$A$1:$D$1871,3,0)),"CUIT NO CARGADO") -> INSUMO | R27: =IFERROR(IF('Abr-22'!$F27="","-",VLOOKUP('Abr-22'!$F27,Lista_CUIT!$A$1:$D$1871,4,0)),"CUIT NO CARGADO") -> 0
B28: 44670 | C28: 1 | D28: 4 | E28: 9754 | F28: 33710719549 | G28: =IFERROR(IF('Abr-22'!$F28="","-",VLOOKUP('Abr-22'!$F28,Lista_CUIT!$A$1:$D$1871,2,0)),"CUIT NO CARGADO") -> FIVELEV S.R.L. | H28: 3722.32 | I28: =IF('Abr-22'!$H28="","",'Abr-22'!$H28*0.21) -> 781.6872 | P28: =SUM('Abr-22'!$H28:$O28) -> 4504.0072 | Q28: =IFERROR(IF('Abr-22'!$F28="","-",VLOOKUP('Abr-22'!$F28,Lista_CUIT!$A$1:$D$1871,3,0)),"CUIT NO CARGADO") -> Gastos Varios | R28: =IFERROR(IF('Abr-22'!$F28="","-",VLOOKUP('Abr-22'!$F28,Lista_CUIT!$A$1:$D$1871,4,0)),"CUIT NO CARGADO") -> 0
B29: 44671 | C29: 1 | D29: 1 | E29: 110 | F29: 30715713272 | G29: =IFERROR(IF('Abr-22'!$F29="","-",VLOOKUP('Abr-22'!$F29,Lista_CUIT!$A$1:$D$1871,2,0)),"CUIT NO CARGADO") -> MALAGA GROUP SRL | H29: 191825.21 | I29: =IF('Abr-22'!$H29="","",'Abr-22'!$H29*0.21) -> 40283.294 | P29: =SUM('Abr-22'!$H29:$O29) -> 232108.5 | Q29: =IFERROR(IF('Abr-22'!$F29="","-",VLOOKUP('Abr-22'!$F29,Lista_CUIT!$A$1:$D$1871,3,0)),"CUIT NO CARGADO") -> Gastos Varios | R29: =IFERROR(IF('Abr-22'!$F29="","-",VLOOKUP('Abr-22'!$F29,Lista_CUIT!$A$1:$D$1871,4,0)),"CUIT NO CARGADO") -> 0
B30: 44672 | C30: 3 | D30: 2 | E30: 138 | F30: 30709131733 | G30: =IFERROR(IF('Abr-22'!$F30="","-",VLOOKUP('Abr-22'!$F30,Lista_CUIT!$A$1:$D$1871,2,0)),"CUIT NO CARGADO") -> DIGAS SRL | H30: -193720 | I30: =IF('Abr-22'!$H30="","",'Abr-22'!$H30*0.21) -> -40681.2 | P30: =SUM('Abr-22'!$H30:$O30) -> -234401.2 | Q30: =IFERROR(IF('Abr-22'!$F30="","-",VLOOKUP('Abr-22'!$F30,Lista_CUIT!$A$1:$D$1871,3,0)),"CUIT NO CARGADO") -> INSUMO | R30: =IFERROR(IF('Abr-22'!$F30="","-",VLOOKUP('Abr-22'!$F30,Lista_CUIT!$A$1:$D$1871,4,0)),"CUIT NO CARGADO") -> 0
B31: 44672 | C31: 1 | D31: 5 | E31: 415 | F31: 30716006391 | G31: =IFERROR(IF('Abr-22'!$F31="","-",VLOOKUP('Abr-22'!$F31,Lista_CUIT!$A$1:$D$1871,2,0)),"CUIT NO CARGADO") -> ALISSING | H31: 3077.69 | I31: =IF('Abr-22'!$H31="","",'Abr-22'!$H31*0.21) -> 646.3149 | P31: =SUM('Abr-22'!$H31:$O31) -> 3724.0049 | Q31: =IFERROR(IF('Abr-22'!$F31="","-",VLOOKUP('Abr-22'!$F31,Lista_CUIT!$A$1:$D$1871,3,0)),"CUIT NO CARGADO") -> Gastos Varios | R31: =IFERROR(IF('Abr-22'!$F31="","-",VLOOKUP('Abr-22'!$F31,Lista_CUIT!$A$1:$D$1871,4,0)),"CUIT NO CARGADO") -> 0
B32: 44672 | C32: 1 | D32: 7002 | E32: 3975 | F32: 30678774495 | G32: =IFERROR(IF('Abr-22'!$F32="","-",VLOOKUP('Abr-22'!$F32,Lista_CUIT!$A$1:$D$1871,2,0)),"CUIT NO CARGADO") -> OPER. DE EST. DE SERV. SA | H32: 3230.2 | I32: =IF('Abr-22'!$H32="","",'Abr-22'!$H32*0.21) -> 678.342 | O32: 982.25 | P32: =SUM('Abr-22'!$H32:$O32) -> 4890.792 | Q32: =IFERROR(IF('Abr-22'!$F32="","-",VLOOKUP('Abr-22'!$F32,Lista_CUIT!$A$1:$D$1871,3,0)),"CUIT NO CARGADO") -> COMBUSTIBLE | R32: =IFERROR(IF('Abr-22'!$F32="","-",VLOOKUP('Abr-22'!$F32,Lista_CUIT!$A$1:$D$1871,4,0)),"CUIT NO CARGADO") -> 0
B33: 44672 | C33: 1 | D33: 3 | E33: 16645 | F33: 30707468161 | G33: =IFERROR(IF('Abr-22'!$F33="","-",VLOOKUP('Abr-22'!$F33,Lista_CUIT!$A$1:$D$1871,2,0)),"CUIT NO CARGADO") -> LASERTEC INGENIERIA S.R.L. | H33: 25585 | I33: =IF('Abr-22'!$H33="","",'Abr-22'!$H33*0.21) -> 5372.85 | P33: =SUM('Abr-22'!$H33:$O33) -> 30957.85 | Q33: =IFERROR(IF('Abr-22'!$F33="","-",VLOOKUP('Abr-22'!$F33,Lista_CUIT!$A$1:$D$1871,3,0)),"CUIT NO CARGADO") -> INSUMO | R33: =IFERROR(IF('Abr-22'!$F33="","-",VLOOKUP('Abr-22'!$F33,Lista_CUIT!$A$1:$D$1871,4,0)),"CUIT NO CARGADO") -> 0
B34: 44672 | C34: 1 | D34: 2 | E34: 2055 | F34: 30709131733 | G34: =IFERROR(IF('Abr-22'!$F34="","-",VLOOKUP('Abr-22'!$F34,Lista_CUIT!$A$1:$D$1871,2,0)),"CUIT NO CARGADO") -> DIGAS SRL | H34: 267952.3 | I34: =IF('Abr-22'!$H34="","",'Abr-22'!$H34*0.21) -> 56269.983 | P34: =SUM('Abr-22'!$H34:$O34) -> 324222.28 | Q34: =IFERROR(IF('Abr-22'!$F34="","-",VLOOKUP('Abr-22'!$F34,Lista_CUIT!$A$1:$D$1871,3,0)),"CUIT NO CARGADO") -> INSUMO | R34: =IFERROR(IF('Abr-22'!$F34="","-",VLOOKUP('Abr-22'!$F34,Lista_CUIT!$A$1:$D$1871,4,0)),"CUIT NO CARGADO") -> 0
B35: 44673 | C35: 1 | D35: 106 | E35: 519106 | F35: 30594494187 | G35: =IFERROR(IF('Abr-22'!$F35="","-",VLOOKUP('Abr-22'!$F35,Lista_CUIT!$A$1:$D$1871,2,0)),"CUIT NO CARGADO") -> FEDERAL EXPRESS CORPORATION | H35: 11875 | I35: =IF('Abr-22'!$H35="","",'Abr-22'!$H35*0.21) -> 2493.75 | O35: 130744.03 | P35: =SUM('Abr-22'!$H35:$O35) -> 145112.78 | Q35: =IFERROR(IF('Abr-22'!$F35="","-",VLOOKUP('Abr-22'!$F35,Lista_CUIT!$A$1:$D$1871,3,0)),"CUIT NO CARGADO") -> GTOS IMP. | R35: =IFERROR(IF('Abr-22'!$F35="","-",VLOOKUP('Abr-22'!$F35,Lista_CUIT!$A$1:$D$1871,4,0)),"CUIT NO CARGADO") -> 0
B36: 44673 | C36: 1 | D36: 9 | E36: 1134 | F36: 30631047145 | G36: =IFERROR(IF('Abr-22'!$F36="","-",VLOOKUP('Abr-22'!$F36,Lista_CUIT!$A$1:$D$1871,2,0)),"CUIT NO CARGADO") -> SEMICONDUC. Y COMPON. SRL | H36: 38694 | I36: 3087 | K36: 2519.37 | P36: =SUM('Abr-22'!$H36:$O36) -> 44300.37 | Q36: =IFERROR(IF('Abr-22'!$F36="","-",VLOOKUP('Abr-22'!$F36,Lista_CUIT!$A$1:$D$1871,3,0)),"CUIT NO CARGADO") -> INSUMO | R36: =IFERROR(IF('Abr-22'!$F36="","-",VLOOKUP('Abr-22'!$F36,Lista_CUIT!$A$1:$D$1871,4,0)),"CUIT NO CARGADO") -> 0
B37: 44673 | C37: 1 | D37: 1 | E37: 305 | F37: 20190828205 | G37: =IFERROR(IF('Abr-22'!$F37="","-",VLOOKUP('Abr-22'!$F37,Lista_CUIT!$A$1:$D$1871,2,0)),"CUIT NO CARGADO") -> CARDENAS TORRES CARLOS DAVID | H37: 12669.68 | K37: 1330.3164 | P37: =SUM('Abr-22'!$H37:$O37) -> 13999.996 | Q37: =IFERROR(IF('Abr-22'!$F37="","-",VLOOKUP('Abr-22'!$F37,Lista_CUIT!$A$1:$D$1871,3,0)),"CUIT NO CARGADO") -> INSUMO | R37: =IFERROR(IF('Abr-22'!$F37="","-",VLOOKUP('Abr-22'!$F37,Lista_CUIT!$A$1:$D$1871,4,0)),"CUIT NO CARGADO") -> 0
B38: 44675 | C38: 1 | D38: 30 | E38: 3550 | F38: 20217293791 | G38: =IFERROR(IF('Abr-22'!$F38="","-",VLOOKUP('Abr-22'!$F38,Lista_CUIT!$A$1:$D$1871,2,0)),"CUIT NO CARGADO") -> VELASCO LEIVA DEMIAN | H38: 7462.81 | I38: =IF('Abr-22'!$H38="","",'Abr-22'!$H38*0.21) -> 1567.1901 | P38: =SUM('Abr-22'!$H38:$O38) -> 9030.0001 | Q38: =IFERROR(IF('Abr-22'!$F38="","-",VLOOKUP('Abr-22'!$F38,Lista_CUIT!$A$1:$D$1871,3,0)),"CUIT NO CARGADO") -> Gastos Varios | R38: =IFERROR(IF('Abr-22'!$F38="","-",VLOOKUP('Abr-22'!$F38,Lista_CUIT!$A$1:$D$1871,4,0)),"CUIT NO CARGADO") -> 0
B39: 44677 | C39: 1 | D39: 40 | E39: 1978547 | F39: 30710964277 | G39: =IFERROR(IF('Abr-22'!$F39="","-",VLOOKUP('Abr-22'!$F39,Lista_CUIT!$A$1:$D$1871,2,0)),"CUIT NO CARGADO") -> LAKAUT SA | H39: 2615.26 | I39: =IF('Abr-22'!$H39="","",'Abr-22'!$H39*0.21) -> 549.2046 | P39: =SUM('Abr-22'!$H39:$O39) -> 3164.4646 | Q39: =IFERROR(IF('Abr-22'!$F39="","-",VLOOKUP('Abr-22'!$F39,Lista_CUIT!$A$1:$D$1871,3,0)),"CUIT NO CARGADO") -> GTOS IMP. | R39: =IFERROR(IF('Abr-22'!$F39="","-",VLOOKUP('Abr-22'!$F39,Lista_CUIT!$A$1:$D$1871,4,0)),"CUIT NO CARGADO") -> 0
B40: 44677 | C40: 1 | D40: 3 | E40: 16677 | F40: 30707468161 | G40: =IFERROR(IF('Abr-22'!$F40="","-",VLOOKUP('Abr-22'!$F40,Lista_CUIT!$A$1:$D$1871,2,0)),"CUIT NO CARGADO") -> LASERTEC INGENIERIA S.R.L. | H40: 33460 | I40: =IF('Abr-22'!$H40="","",'Abr-22'!$H40*0.21) -> 7026.6 | P40: =SUM('Abr-22'!$H40:$O40) -> 40486.6 | Q40: =IFERROR(IF('Abr-22'!$F40="","-",VLOOKUP('Abr-22'!$F40,Lista_CUIT!$A$1:$D$1871,3,0)),"CUIT NO CARGADO") -> INSUMO | R40: =IFERROR(IF('Abr-22'!$F40="","-",VLOOKUP('Abr-22'!$F40,Lista_CUIT!$A$1:$D$1871,4,0)),"CUIT NO CARGADO") -> 0
B41: 44678 | C41: 3 | D41: 60 | E41: 462 | F41: 30547188760 | G41: =IFERROR(IF('Abr-22'!$F41="","-",VLOOKUP('Abr-22'!$F41,Lista_CUIT!$A$1:$D$1871,2,0)),"CUIT NO CARGADO") -> LONCO HUE SA | H41: -13634.24 | I41: =IF('Abr-22'!$H41="","",'Abr-22'!$H41*0.21) -> -2863.1904 | P41: =SUM('Abr-22'!$H41:$O41) -> -16497.43 | Q41: =IFERROR(IF('Abr-22'!$F41="","-",VLOOKUP('Abr-22'!$F41,Lista_CUIT!$A$1:$D$1871,3,0)),"CUIT NO CARGADO") -> INSUMO | R41: =IFERROR(IF('Abr-22'!$F41="","-",VLOOKUP('Abr-22'!$F41,Lista_CUIT!$A$1:$D$1871,4,0)),"CUIT NO CARGADO") -> 0
B42: 44678 | C42: 1 | D42: 3 | E42: 845863 | F42: 30712019359 | G42: =IFERROR(IF('Abr-22'!$F42="","-",VLOOKUP('Abr-22'!$F42,Lista_CUIT!$A$1:$D$1871,2,0)),"CUIT NO CARGADO") -> LINKEDSTORE ARGENTINA S.R.L. | H42: 2478.51 | I42: =IF('Abr-22'!$H42="","",'Abr-22'!$H42*0.21) -> 520.4871 | P42: =SUM('Abr-22'!$H42:$O42) -> 2998.9971 | Q42: =IFERROR(IF('Abr-22'!$F42="","-",VLOOKUP('Abr-22'!$F42,Lista_CUIT!$A$1:$D$1871,3,0)),"CUIT NO CARGADO") -> Gastos Varios | R42: =IFERROR(IF('Abr-22'!$F42="","-",VLOOKUP('Abr-22'!$F42,Lista_CUIT!$A$1:$D$1871,4,0)),"CUIT NO CARGADO") -> 0
B43: 44678 | C43: 1 | D43: 12 | E43: 12026 | F43: 30604942051 | G43: =IFERROR(IF('Abr-22'!$F43="","-",VLOOKUP('Abr-22'!$F43,Lista_CUIT!$A$1:$D$1871,2,0)),"CUIT NO CARGADO") -> IMPORTADORA FOTOGRAFICA SA | H43: 25288.62 | I43: =IF('Abr-22'!$H43="","",'Abr-22'!$H43*0.21) -> 5310.6102 | P43: =SUM('Abr-22'!$H43:$O43) -> 30599.23 | Q43: =IFERROR(IF('Abr-22'!$F43="","-",VLOOKUP('Abr-22'!$F43,Lista_CUIT!$A$1:$D$1871,3,0)),"CUIT NO CARGADO") -> Gastos Oficina | R43: =IFERROR(IF('Abr-22'!$F43="","-",VLOOKUP('Abr-22'!$F43,Lista_CUIT!$A$1:$D$1871,4,0)),"CUIT NO CARGADO") -> 0
B44: 44678 | C44: 1 | D44: 3 | E44: 16699 | F44: 30707468161 | G44: =IFERROR(IF('Abr-22'!$F44="","-",VLOOKUP('Abr-22'!$F44,Lista_CUIT!$A$1:$D$1871,2,0)),"CUIT NO CARGADO") -> LASERTEC INGENIERIA S.R.L. | H44: 25746.25 | I44: =IF('Abr-22'!$H44="","",'Abr-22'!$H44*0.21) -> 5406.7125 | P44: =SUM('Abr-22'!$H44:$O44) -> 31152.963 | Q44: =IFERROR(IF('Abr-22'!$F44="","-",VLOOKUP('Abr-22'!$F44,Lista_CUIT!$A$1:$D$1871,3,0)),"CUIT NO CARGADO") -> INSUMO | R44: =IFERROR(IF('Abr-22'!$F44="","-",VLOOKUP('Abr-22'!$F44,Lista_CUIT!$A$1:$D$1871,4,0)),"CUIT NO CARGADO") -> 0
B45: 44679 | C45: 1 | D45: 2 | E45: 130 | F45: 20125142851 | G45: =IFERROR(IF('Abr-22'!$F45="","-",VLOOKUP('Abr-22'!$F45,Lista_CUIT!$A$1:$D$1871,2,0)),"CUIT NO CARGADO") -> FEDERICI NICOLAS JOSE | H45: 13843 | I45: =IF('Abr-22'!$H45="","",'Abr-22'!$H45*0.21) -> 2907.03 | P45: =SUM('Abr-22'!$H45:$O45) -> 16750.03 | Q45: =IFERROR(IF('Abr-22'!$F45="","-",VLOOKUP('Abr-22'!$F45,Lista_CUIT!$A$1:$D$1871,3,0)),"CUIT NO CARGADO") -> INSUMO | R45: =IFERROR(IF('Abr-22'!$F45="","-",VLOOKUP('Abr-22'!$F45,Lista_CUIT!$A$1:$D$1871,4,0)),"CUIT NO CARGADO") -> 0
B46: 44680 | C46: 1 | D46: 5 | E46: 25488 | F46: 30708261110 | G46: =IFERROR(IF('Abr-22'!$F46="","-",VLOOKUP('Abr-22'!$F46,Lista_CUIT!$A$1:$D$1871,2,0)),"CUIT NO CARGADO") -> MULTIPLES SRL | H46: 40791.5 | I46: =IF('Abr-22'!$H46="","",'Abr-22'!$H46*0.21) -> 8566.215 | P46: =SUM('Abr-22'!$H46:$O46) -> 49357.715 | Q46: =IFERROR(IF('Abr-22'!$F46="","-",VLOOKUP('Abr-22'!$F46,Lista_CUIT!$A$1:$D$1871,3,0)),"CUIT NO CARGADO") -> Gastos Varios | R46: =IFERROR(IF('Abr-22'!$F46="","-",VLOOKUP('Abr-22'!$F46,Lista_CUIT!$A$1:$D$1871,4,0)),"CUIT NO CARGADO") -> 0
B47: 44680 | C47: 1 | D47: 2 | E47: 2068 | F47: 30709131733 | G47: =IFERROR(IF('Abr-22'!$F47="","-",VLOOKUP('Abr-22'!$F47,Lista_CUIT!$A$1:$D$1871,2,0)),"CUIT NO CARGADO") -> DIGAS SRL | H47: 128736 | I47: =IF('Abr-22'!$H47="","",'Abr-22'!$H47*0.21) -> 27034.56 | P47: =SUM('Abr-22'!$H47:$O47) -> 155770.56 | Q47: =IFERROR(IF('Abr-22'!$F47="","-",VLOOKUP('Abr-22'!$F47,Lista_CUIT!$A$1:$D$1871,3,0)),"CUIT NO CARGADO") -> INSUMO | R47: =IFERROR(IF('Abr-22'!$F47="","-",VLOOKUP('Abr-22'!$F47,Lista_CUIT!$A$1:$D$1871,4,0)),"CUIT NO CARGADO") -> 0
B48: 44681 | C48: 1 | D48: 700 | E48: 369022 | F48: 30580111315 | G48: =IFERROR(IF('Abr-22'!$F48="","-",VLOOKUP('Abr-22'!$F48,Lista_CUIT!$A$1:$D$1871,2,0)),"CUIT NO CARGADO") -> DHL EXPRESS ARG SA | I48: =IF('Abr-22'!$H48="","",'Abr-22'!$H48*0.21) | O48: 21111.09 | P48: =SUM('Abr-22'!$H48:$O48) -> 21111.09 | Q48: =IFERROR(IF('Abr-22'!$F48="","-",VLOOKUP('Abr-22'!$F48,Lista_CUIT!$A$1:$D$1871,3,0)),"CUIT NO CARGADO") -> GTOS IMP. | R48: =IFERROR(IF('Abr-22'!$F48="","-",VLOOKUP('Abr-22'!$F48,Lista_CUIT!$A$1:$D$1871,4,0)),"CUIT NO CARGADO") -> 0
B49: 44681 | C49: 1 | D49: 1 | E49: 448 | F49: 30715048066 | G49: =IFERROR(IF('Abr-22'!$F49="","-",VLOOKUP('Abr-22'!$F49,Lista_CUIT!$A$1:$D$1871,2,0)),"CUIT NO CARGADO") -> ROLLS Y EMPANADAS SA | H49: 80134 | I49: =IF('Abr-22'!$H49="","",'Abr-22'!$H49*0.21) -> 16828.14 | P49: =SUM('Abr-22'!$H49:$O49) -> 96962.14 | Q49: =IFERROR(IF('Abr-22'!$F49="","-",VLOOKUP('Abr-22'!$F49,Lista_CUIT!$A$1:$D$1871,3,0)),"CUIT NO CARGADO") -> CATERING | R49: =IFERROR(IF('Abr-22'!$F49="","-",VLOOKUP('Abr-22'!$F49,Lista_CUIT!$A$1:$D$1871,4,0)),"CUIT NO CARGADO") -> 0
B50: 44681 | C50: 1 | D50: 280 | E50: 1363392 | F50: 30580111315 | G50: =IFERROR(IF('Abr-22'!$F50="","-",VLOOKUP('Abr-22'!$F50,Lista_CUIT!$A$1:$D$1871,2,0)),"CUIT NO CARGADO") -> DHL EXPRESS ARG SA | H50: 71770.097 | K50: 7535.5085 | O50: -71770.097 | P50: =SUM('Abr-22'!$H50:$O50) -> 7535.5085 | Q50: =IFERROR(IF('Abr-22'!$F50="","-",VLOOKUP('Abr-22'!$F50,Lista_CUIT!$A$1:$D$1871,3,0)),"CUIT NO CARGADO") -> GTOS IMP. | R50: =IFERROR(IF('Abr-22'!$F50="","-",VLOOKUP('Abr-22'!$F50,Lista_CUIT!$A$1:$D$1871,4,0)),"CUIT NO CARGADO") -> 0
B51: Total | H51: =SUBTOTAL(109,'Abr-22'!$H$9:$H$50) -> 2050059.3 | I51: =SUBTOTAL(109,'Abr-22'!$I$9:$I$50) -> 333743.77 | J51: =SUBTOTAL(109,'Abr-22'!$J$9:$J$50) -> 476.55 | K51: =SUBTOTAL(109,'Abr-22'!$K$9:$K$50) -> 48198.383 | L51: =SUBTOTAL(109,'Abr-22'!$L$9:$L$50) -> 108.1 | M51: =SUBTOTAL(109,'Abr-22'!$M$9:$M$50) -> 0 | N51: =SUBTOTAL(109,'Abr-22'!$N$9:$N$50) -> 0 | O51: =SUBTOTAL(109,'Abr-22'!$O$9:$O$50) -> -166663.89 | P51: =SUBTOTAL(109,'Abr-22'!$P$9:$P$50) -> 2265922.2
D56: LIQUIDACION EXTRACTOS BANCARIOS-TARJETAS
D57: FECHA | E57: NRO CPTE | F57: BANCO | G57: NETO | H57: IVA 21% | I57: IVA 10,5% | J57: RET IIBB CABA | K57: PERC IVA | L57: PERC IIBB
D58: 44681 | E58: 30202204 | F58: BANCO CREDICOOP | G58: 2142 | H58: 449.82
D59: 44678 | E59: 981738 | F59: Liq. Importacion | G59: 2876 | H59: 603.96 | J59: 86.28
D60: 44659 | E60: 617-475137 | F60: Liq. Importacion | G60: 12898.4 | H60: 2708.664 | J60: 386.95
D61: 44652 | E61: 617-474384 | F61: Liq. Importacion | G61: 12778.8 | H61: 2683.548 | J61: 383.36
D62: 44681 | E62: 30042022 | F62: VISA CREDITO | G62: 80 | H62: 16.8
D64: Total | G64: =SUBTOTAL(109,'Abr-22'!$G$58:$G$63) -> 30775.2 | H64: =SUBTOTAL(109,'Abr-22'!$H$58:$H$63) -> 6462.792 | I64: =SUBTOTAL(109,'Abr-22'!$I$58:$I$63) -> 0 | J64: =SUBTOTAL(109,'Abr-22'!$J$58:$J$63) -> 856.59 | K64: =SUBTOTAL(109,'Abr-22'!$K$58:$K$63) -> 0 | L64: =SUBTOTAL(109,'Abr-22'!$L$58:$L$63) -> 0
D68: FACTURAS C
D69: FECHA | E69: PTO VTA | F69: FC Nº | G69: CUIT | H69: RAZON SOCIAL | I69: TOTAL | J69: TIPO DE GASTO | K69: Provincia
H70: =IFERROR(IF('Abr-22'!$G70="","-",VLOOKUP('Abr-22'!$G70,Lista_CUIT!$A$1:$D$1871,2,0)),"CUIT NO CARGADO") -> - | J70: =IFERROR(IF('Abr-22'!$G70="","-",VLOOKUP('Abr-22'!$G70,Lista_CUIT!$A$1:$D$1871,3,0)),"CUIT NO CARGADO") -> - | K70: =IFERROR(IF('Abr-22'!$G70="","-",VLOOKUP('Abr-22'!$G70,Lista_CUIT!$A$1:$D$1871,4,0)),"CUIT NO CARGADO") -> -
H71: =IFERROR(IF('Abr-22'!$G71="","-",VLOOKUP('Abr-22'!$G71,Lista_CUIT!$A$1:$D$1871,2,0)),"CUIT NO CARGADO") -> - | J71: =IFERROR(IF('Abr-22'!$G71="","-",VLOOKUP('Abr-22'!$G71,Lista_CUIT!$A$1:$D$1871,3,0)),"CUIT NO CARGADO") -> - | K71: =IFERROR(IF('Abr-22'!$G71="","-",VLOOKUP('Abr-22'!$G71,Lista_CUIT!$A$1:$D$1871,4,0)),"CUIT NO CARGADO") -> -
H72: =IFERROR(IF('Abr-22'!$G72="","-",VLOOKUP('Abr-22'!$G72,Lista_CUIT!$A$1:$D$1871,2,0)),"CUIT NO CARGADO") -> - | J72: =IFERROR(IF('Abr-22'!$G72="","-",VLOOKUP('Abr-22'!$G72,Lista_CUIT!$A$1:$D$1871,3,0)),"CUIT NO CARGADO") -> - | K72: =IFERROR(IF('Abr-22'!$G72="","-",VLOOKUP('Abr-22'!$G72,Lista_CUIT!$A$1:$D$1871,4,0)),"CUIT NO CARGADO") -> -
H73: =IFERROR(IF('Abr-22'!$G73="","-",VLOOKUP('Abr-22'!$G73,Lista_CUIT!$A$1:$D$1871,2,0)),"CUIT NO CARGADO") -> - | J73: =IFERROR(IF('Abr-22'!$G73="","-",VLOOKUP('Abr-22'!$G73,Lista_CUIT!$A$1:$D$1871,3,0)),"CUIT NO CARGADO") -> - | K73: =IFERROR(IF('Abr-22'!$G73="","-",VLOOKUP('Abr-22'!$G73,Lista_CUIT!$A$1:$D$1871,4,0)),"CUIT NO CARGADO") -> -
D74: Total | I74: =SUBTOTAL(109,'Abr-22'!$I$70:$I$73) -> 0
B80: LIBRO IVA VENTAS | K80: =N1 -> 44652
B82: VENTAS "A"
B83: FECHA | C83: TIPO | D83: PTO VENTA | E83: Nº FACTURA | F83: CUIT | G83: RAZON SOCIAL | H83: IMPORTE NETO | I83: IVA 21% | J83: IVA 10,5% | K83: EXENTO | L83: TOTAL | M83: Provincia
B84: 44655 | C84: 1 | D84: 3 | E84: 56 | F84: 30638318470 | G84: =IFERROR(IF('Abr-22'!$F84="","-",VLOOKUP('Abr-22'!$F84,Lista_CUIT!$A$1:$D$1871,2,0)),"CUIT NO CARGADO") -> DELTA COMPRESION S.R.L | H84: 10937798 | I84: 492850.43 | J84: 902043.45 | L84: =SUM('Abr-22'!$H84:$K84) -> 12332692
B85: 44670 | C85: 1 | D85: 3 | E85: 58 | F85: 30708844248 | G85: =IFERROR(IF('Abr-22'!$F85="","-",VLOOKUP('Abr-22'!$F85,Lista_CUIT!$A$1:$D$1871,2,0)),"CUIT NO CARGADO") -> INGENIERIA GAMAR SA | H85: 35907.08 | I85: ='Abr-22'!$H85*0.21 -> 7540.4868 | L85: =SUM('Abr-22'!$H85:$K85) -> 43447.567
B86: 44670 | C86: 1 | D86: 3 | E86: 59 | F86: 30716041596 | G86: =IFERROR(IF('Abr-22'!$F86="","-",VLOOKUP('Abr-22'!$F86,Lista_CUIT!$A$1:$D$1871,2,0)),"CUIT NO CARGADO") -> EXA COMPRESION SRL | H86: 299983.2 | I86: ='Abr-22'!$H86*0.21 -> 62996.472 | L86: =SUM('Abr-22'!$H86:$K86) -> 362979.67
B87: 44670 | C87: 1 | D87: 3 | E87: 57 | F87: 30628274327 | G87: =IFERROR(IF('Abr-22'!$F87="","-",VLOOKUP('Abr-22'!$F87,Lista_CUIT!$A$1:$D$1871,2,0)),"CUIT NO CARGADO") -> AGIRA SA | H87: 1015852.2 | J87: 106664.48 | L87: =SUM('Abr-22'!$H87:$K87) -> 1122516.7
G88: =IFERROR(IF('Abr-22'!$F88="","-",VLOOKUP('Abr-22'!$F88,Lista_CUIT!$A$1:$D$1871,2,0)),"CUIT NO CARGADO") -> - | I88: ='Abr-22'!$H88*0.21 -> 0 | L88: =SUM('Abr-22'!$H88:$K88) -> 0
G89: =IFERROR(IF('Abr-22'!$F89="","-",VLOOKUP('Abr-22'!$F89,Lista_CUIT!$A$1:$D$1871,2,0)),"CUIT NO CARGADO") -> - | I89: ='Abr-22'!$H89*0.21 -> 0 | L89: =SUM('Abr-22'!$H89:$K89) -> 0
G90: =IFERROR(IF('Abr-22'!$F90="","-",VLOOKUP('Abr-22'!$F90,Lista_CUIT!$A$1:$D$1871,2,0)),"CUIT NO CARGADO") -> - | I90: ='Abr-22'!$H90*0.21 -> 0 | L90: =SUM('Abr-22'!$H90:$K90) -> 0
G91: =IFERROR(IF('Abr-22'!$F91="","-",VLOOKUP('Abr-22'!$F91,Lista_CUIT!$A$1:$D$1871,2,0)),"CUIT NO CARGADO") -> - | I91: ='Abr-22'!$H91*0.21 -> 0 | L91: =SUM('Abr-22'!$H91:$K91) -> 0
G92: =IFERROR(IF('Abr-22'!$F92="","-",VLOOKUP('Abr-22'!$F92,Lista_CUIT!$A$1:$D$1871,2,0)),"CUIT NO CARGADO") -> - | I92: ='Abr-22'!$H92*0.21 -> 0 | L92: =SUM('Abr-22'!$H92:$K92) -> 0
B93: Total | H93: =SUBTOTAL(109,'Abr-22'!$H$84:$H$92) -> 12289541 | I93: =SUBTOTAL(109,'Abr-22'!$I$84:$I$92) -> 563387.39 | J93: =SUBTOTAL(109,'Abr-22'!$J$84:$J$92) -> 1008707.9 | K93: =SUBTOTAL(109,'Abr-22'!$K$84:$K$92) -> 0 | L93: =SUBTOTAL(109,'Abr-22'!$L$84:$L$92) -> 13861636 | M93: =SUBTOTAL(103,'Abr-22'!$M$84:$M$92) -> 0
B96: VENTAS "B"
B97: FECHA | C97: TIPO | D97: PTO VENTA | E97: Nº FACTURA | F97: CUIT | G97: RAZON SOCIAL | H97: IMPORTE NETO | I97: IVA 21% | J97: IVA 10,5% | K97: EXENTO | L97: TOTAL | M97: Provincia
L98: =SUM('Abr-22'!$H98:$K98) -> 0
L99: =SUM('Abr-22'!$H99:$K99) -> 0
B100: Total | H100: =SUBTOTAL(109,'Abr-22'!$H$98:$H$99) -> 0 | I100: =SUBTOTAL(109,'Abr-22'!$I$98:$I$99) -> 0 | J100: =SUBTOTAL(109,'Abr-22'!$J$98:$J$99) -> 0 | K100: =SUBTOTAL(109,'Abr-22'!$K$98:$K$99) -> 0 | L100: =SUBTOTAL(109,'Abr-22'!$L$98:$L$99) -> 0 | M100: =SUBTOTAL(103,'Abr-22'!$M$98:$M$99) -> 0
B102: VENTAS EXPORTACION
B103: FECHA | C103: Nº FACTRA | D103: CUIT | E103: RAZON SOCIAL | F103: USD | G103: EUR | H103: T. CAMBIO | I103: TOTAL
B104: 44662 | C104: 45 | F104: 24122.52 | H104: 112.16 | I104: ='Abr-22'!$F104*'Abr-22'!$H104 -> 2705581.8
I105: ='Abr-22'!$F105*'Abr-22'!$H105 -> 0
I106: ='Abr-22'!$F106*'Abr-22'!$H106 -> 0
I107: ='Abr-22'!$F107*'Abr-22'!$H107 -> 0
I108: ='Abr-22'!$F108*'Abr-22'!$H108 -> 0
B109: Total | F109: =SUBTOTAL(109,F104:F108) -> 24122.52 | G109: =SUBTOTAL(109,G104:G108) -> 0 | H109: =SUBTOTAL(109,H104:H108) -> 112.16 | I109: ='Abr-22'!$F109*'Abr-22'!$H109 -> 2705581.8
C112: RETENCIONES
C113: FECHA | D113: COMP Nº | E113: Columna1 | F113: CUIT | G113: RAZON SOCIAL | H113: Ganancias | I113: IVA | J113: SUSS | K113: IIBB BSAS | L113: IIBB CABA
G114: =IFERROR(IF('Abr-22'!$F114="","-",VLOOKUP('Abr-22'!$F114,Lista_CUIT!$A$1:$D$1871,2,0)),"CUIT NO CARGADO") -> -
G115: =IFERROR(IF('Abr-22'!$F115="","-",VLOOKUP('Abr-22'!$F115,Lista_CUIT!$A$1:$D$1871,2,0)),"CUIT NO CARGADO") -> -
G116: =IFERROR(IF('Abr-22'!$F116="","-",VLOOKUP('Abr-22'!$F116,Lista_CUIT!$A$1:$D$1871,2,0)),"CUIT NO CARGADO") -> -
G117: =IFERROR(IF('Abr-22'!$F117="","-",VLOOKUP('Abr-22'!$F117,Lista_CUIT!$A$1:$D$1871,2,0)),"CUIT NO CARGADO") -> -
G118: =IFERROR(IF('Abr-22'!$F118="","-",VLOOKUP('Abr-22'!$F118,Lista_CUIT!$A$1:$D$1871,2,0)),"CUIT NO CARGADO") -> -

Sheet May-22
B1: LIBRO IVA COMPRAS | G1: ='Abr-22'!G1:M1 -> CORITEC S.R.L. | N1: =EDATE('Abr-22'!N1,1) -> 44682
B3: TOTAL COMPRAS | G3: TOTAL CREDITO FISCAL | J3: TOTAL VENTAS NETAS | M3: TOTAL DEBITO FISCAL | P3: RESULTADO
B4: =SUM('May-22'!$H$51)+'May-22'!$G$63 -> 1100107 | G4: ='May-22'!$I$51+'May-22'!$J$51+'May-22'!$K$51+'May-22'!$H$63+'May-22'!$I$63 -> 223910.74 | J4: ='May-22'!$H$100+'May-22'!$H$112 -> 7471351.4 | M4: ='May-22'!$I$100+'May-22'!$J$100+'May-22'!$I$112+'May-22'!$J$112 -> 850836.36 | P4: =G4-M4 -> -626925.62
O7: no esta configurado para que este en negativo
B8: FECHA | C8: TIPO | D8: PTO VTA | E8: NRO. CPTE | F8: CUIT | G8: RAZON SOCIAL | H8: NETO GRAVADO | I8: IVA 21 % | J8: IVA 27% | K8: IVA 10,5% | L8: PERC. IVA | M8: PERC IIBB BS AS | N8: PERC. IIBB CABA | O8: Otros / No Grav. | P8: TOTAL | Q8: Tipo de Gasto | R8: Provincia
B9: 44682 | C9: 1 | D9: 3 | E9: 529 | F9: 30715402765 | G9: =IFERROR(IF('May-22'!$F9="","-",VLOOKUP('May-22'!$F9,Lista_CUIT!$A$1:$D$1871,2,0)),"CUIT NO CARGADO") -> RIO 265 SRL | H9: 7190.08 | I9: ='May-22'!$H9*0.21 -> 1509.9168 | P9: =SUM('May-22'!$H9:$O9) -> 8699.9968 | Q9: =IFERROR(IF('May-22'!$F9="","-",VLOOKUP('May-22'!$F9,Lista_CUIT!$A$1:$D$1871,3,0)),"CUIT NO CARGADO") -> GTOS VARIOS-ESTACIONAMIENTO HORACIO | R9: =IFERROR(IF('May-22'!$F9="","-",VLOOKUP('May-22'!$F9,Lista_CUIT!$A$1:$D$1871,4,0)),"CUIT NO CARGADO") -> 0
B10: 44682 | C10: 1 | D10: 3 | E10: 155932 | F10: 30707135596 | G10: =IFERROR(IF('May-22'!$F10="","-",VLOOKUP('May-22'!$F10,Lista_CUIT!$A$1:$D$1871,2,0)),"CUIT NO CARGADO") -> CITILAN ARGENTINA SA | H10: 2735.95 | I10: ='May-22'!$H10*0.21 -> 574.5495 | P10: =SUM('May-22'!$H10:$O10) -> 3310.4995 | Q10: =IFERROR(IF('May-22'!$F10="","-",VLOOKUP('May-22'!$F10,Lista_CUIT!$A$1:$D$1871,3,0)),"CUIT NO CARGADO") -> SERVICIOS GAS, LUZ, ETC | R10: =IFERROR(IF('May-22'!$F10="","-",VLOOKUP('May-22'!$F10,Lista_CUIT!$A$1:$D$1871,4,0)),"CUIT NO CARGADO") -> 0
B11: 44683 | C11: 1 | D11: 2 | E11: 131 | F11: 20125142851 | G11: =IFERROR(IF('May-22'!$F11="","-",VLOOKUP('May-22'!$F11,Lista_CUIT!$A$1:$D$1871,2,0)),"CUIT NO CARGADO") -> FEDERICI NICOLAS JOSE | H11: 15805 | I11: ='May-22'!$H11*0.21 -> 3319.05 | P11: =SUM('May-22'!$H11:$O11) -> 19124.05 | Q11: =IFERROR(IF('May-22'!$F11="","-",VLOOKUP('May-22'!$F11,Lista_CUIT!$A$1:$D$1871,3,0)),"CUIT NO CARGADO") -> INSUMO | R11: =IFERROR(IF('May-22'!$F11="","-",VLOOKUP('May-22'!$F11,Lista_CUIT!$A$1:$D$1871,4,0)),"CUIT NO CARGADO") -> 0
B12: 44683 | C12: 1 | D12: 4 | E12: 960 | F12: 27208929416 | G12: =IFERROR(IF('May-22'!$F12="","-",VLOOKUP('May-22'!$F12,Lista_CUIT!$A$1:$D$1871,2,0)),"CUIT NO CARGADO") -> FIGARO CARLA SILVINA | H12: 10160.29 | I12: ='May-22'!$H12*0.21 -> 2133.6609 | P12: =SUM('May-22'!$H12:$O12) -> 12293.951 | Q12: =IFERROR(IF('May-22'!$F12="","-",VLOOKUP('May-22'!$F12,Lista_CUIT!$A$1:$D$1871,3,0)),"CUIT NO CARGADO") -> INSUMO | R12: =IFERROR(IF('May-22'!$F12="","-",VLOOKUP('May-22'!$F12,Lista_CUIT!$A$1:$D$1871,4,0)),"CUIT NO CARGADO") -> 0
B13: 44683 | C13: 1 | D13: 9 | E13: 1143 | F13: 30631047145 | G13: =IFERROR(IF('May-22'!$F13="","-",VLOOKUP('May-22'!$F13,Lista_CUIT!$A$1:$D$1871,2,0)),"CUIT NO CARGADO") -> SEMICONDUC. Y COMPON. SRL | H13: 26317.5 | I13: 4827.9 | K13: 349.39 | P13: =SUM('May-22'!$H13:$O13) -> 31494.79 | Q13: =IFERROR(IF('May-22'!$F13="","-",VLOOKUP('May-22'!$F13,Lista_CUIT!$A$1:$D$1871,3,0)),"CUIT NO CARGADO") -> INSUMO | R13: =IFERROR(IF('May-22'!$F13="","-",VLOOKUP('May-22'!$F13,Lista_CUIT!$A$1:$D$1871,4,0)),"CUIT NO CARGADO") -> 0
B14: 44683 | C14: 1 | D14: 11 | E14: 1811 | F14: 30711809429 | G14: =IFERROR(IF('May-22'!$F14="","-",VLOOKUP('May-22'!$F14,Lista_CUIT!$A$1:$D$1871,2,0)),"CUIT NO CARGADO") -> DERPLO SA | H14: 3113.4 | I14: ='May-22'!$H14*0.21 -> 653.814 | P14: =SUM('May-22'!$H14:$O14) -> 3767.214 | Q14: =IFERROR(IF('May-22'!$F14="","-",VLOOKUP('May-22'!$F14,Lista_CUIT!$A$1:$D$1871,3,0)),"CUIT NO CARGADO") -> INSUMO | R14: =IFERROR(IF('May-22'!$F14="","-",VLOOKUP('May-22'!$F14,Lista_CUIT!$A$1:$D$1871,4,0)),"CUIT NO CARGADO") -> 0
B15: 44683 | C15: 1 | D15: 106 | E15: 521748 | F15: 30594494187 | G15: =IFERROR(IF('May-22'!$F15="","-",VLOOKUP('May-22'!$F15,Lista_CUIT!$A$1:$D$1871,2,0)),"CUIT NO CARGADO") -> FEDERAL EXPRESS CORPORATION | I15: ='May-22'!$H15*0.21 -> 0 | O15: 31189.2 | P15: =SUM('May-22'!$H15:$O15) -> 31189.2 | Q15: =IFERROR(IF('May-22'!$F15="","-",VLOOKUP('May-22'!$F15,Lista_CUIT!$A$1:$D$1871,3,0)),"CUIT NO CARGADO") -> GTOS IMP. | R15: =IFERROR(IF('May-22'!$F15="","-",VLOOKUP('May-22'!$F15,Lista_CUIT!$A$1:$D$1871,4,0)),"CUIT NO CARGADO") -> 0
B16: 44683 | C16: 1 | D16: 13 | E16: 763325 | F16: 30700940957 | G16: =IFERROR(IF('May-22'!$F16="","-",VLOOKUP('May-22'!$F16,Lista_CUIT!$A$1:$D$1871,2,0)),"CUIT NO CARGADO") -> UPS de ARGENTINA SA | H16: 63402.51 | K16: 6657.26 | M16: 7289.04 | O16: -63402.51 | P16: =SUM('May-22'!$H16:$O16) -> 13946.3 | Q16: =IFERROR(IF('May-22'!$F16="","-",VLOOKUP('May-22'!$F16,Lista_CUIT!$A$1:$D$1871,3,0)),"CUIT NO CARGADO") -> GTOS IMP. | R16: =IFERROR(IF('May-22'!$F16="","-",VLOOKUP('May-22'!$F16,Lista_CUIT!$A$1:$D$1871,4,0)),"CUIT NO CARGADO") -> 0
B17: 44684 | C17: 1 | D17: 3 | E17: 256 | F17: 20921575743 | G17: =IFERROR(IF('May-22'!$F17="","-",VLOOKUP('May-22'!$F17,Lista_CUIT!$A$1:$D$1871,2,0)),"CUIT NO CARGADO") -> RIOS GOMEZ JOSE ANTONIO | H17: 90720 | I17: ='May-22'!$H17*0.21 -> 19051.2 | P17: =SUM('May-22'!$H17:$O17) -> 109771.2 | Q17: =IFERROR(IF('May-22'!$F17="","-",VLOOKUP('May-22'!$F17,Lista_CUIT!$A$1:$D$1871,3,0)),"CUIT NO CARGADO") -> Papeleria e Impresos | R17: =IFERROR(IF('May-22'!$F17="","-",VLOOKUP('May-22'!$F17,Lista_CUIT!$A$1:$D$1871,4,0)),"CUIT NO CARGADO") -> 0
B18: 44684 | C18: 1 | D18: 3 | E18: 16737 | F18: 30707468161 | G18: =IFERROR(IF('May-22'!$F18="","-",VLOOKUP('May-22'!$F18,Lista_CUIT!$A$1:$D$1871,2,0)),"CUIT NO CARGADO") -> LASERTEC INGENIERIA S.R.L. | H18: 33740 | I18: ='May-22'!$H18*0.21 -> 7085.4 | P18: =SUM('May-22'!$H18:$O18) -> 40825.4 | Q18: =IFERROR(IF('May-22'!$F18="","-",VLOOKUP('May-22'!$F18,Lista_CUIT!$A$1:$D$1871,3,0)),"CUIT NO CARGADO") -> INSUMO | R18: =IFERROR(IF('May-22'!$F18="","-",VLOOKUP('May-22'!$F18,Lista_CUIT!$A$1:$D$1871,4,0)),"CUIT NO CARGADO") -> 0
B19: 44690 | C19: 1 | D19: 2 | E19: 132 | F19: 20125142851 | G19: =IFERROR(IF('May-22'!$F19="","-",VLOOKUP('May-22'!$F19,Lista_CUIT!$A$1:$D$1871,2,0)),"CUIT NO CARGADO") -> FEDERICI NICOLAS JOSE | H19: 21037 | I19: ='May-22'!$H19*0.21 -> 4417.77 | P19: =SUM('May-22'!$H19:$O19) -> 25454.77 | Q19: =IFERROR(IF('May-22'!$F19="","-",VLOOKUP('May-22'!$F19,Lista_CUIT!$A$1:$D$1871,3,0)),"CUIT NO CARGADO") -> INSUMO | R19: =IFERROR(IF('May-22'!$F19="","-",VLOOKUP('May-22'!$F19,Lista_CUIT!$A$1:$D$1871,4,0)),"CUIT NO CARGADO") -> 0
B20: 44690 | C20: 1 | D20: 2 | E20: 765 | F20: 30500805222 | G20: =IFERROR(IF('May-22'!$F20="","-",VLOOKUP('May-22'!$F20,Lista_CUIT!$A$1:$D$1871,2,0)),"CUIT NO CARGADO") -> KAVCIC SRL | H20: 69690 | I20: ='May-22'!$H20*0.21 -> 14634.9 | P20: =SUM('May-22'!$H20:$O20) -> 84324.9 | Q20: =IFERROR(IF('May-22'!$F20="","-",VLOOKUP('May-22'!$F20,Lista_CUIT!$A$1:$D$1871,3,0)),"CUIT NO CARGADO") -> INSUMO | R20: =IFERROR(IF('May-22'!$F20="","-",VLOOKUP('May-22'!$F20,Lista_CUIT!$A$1:$D$1871,4,0)),"CUIT NO CARGADO") -> 0
B21: 44691 | C21: 1 | D21: 31 | E21: 161345 | F21: 30710114176 | G21: =IFERROR(IF('May-22'!$F21="","-",VLOOKUP('May-22'!$F21,Lista_CUIT!$A$1:$D$1871,2,0)),"CUIT NO CARGADO") -> SYMONDS SA. | H21: 31404.13 | I21: ='May-22'!$H21*0.21 -> 6594.8673 | P21: =SUM('May-22'!$H21:$O21) -> 37998.997 | Q21: =IFERROR(IF('May-22'!$F21="","-",VLOOKUP('May-22'!$F21,Lista_CUIT!$A$1:$D$1871,3,0)),"CUIT NO CARGADO") -> Mantenimiento | R21: =IFERROR(IF('May-22'!$F21="","-",VLOOKUP('May-22'!$F21,Lista_CUIT!$A$1:$D$1871,4,0)),"CUIT NO CARGADO") -> 0
B22: 44691 | C22: 1 | D22: 3 | E22: 1743 | F22: 30715461540 | G22: =IFERROR(IF('May-22'!$F22="","-",VLOOKUP('May-22'!$F22,Lista_CUIT!$A$1:$D$1871,2,0)),"CUIT NO CARGADO") -> CAISEN S.R.L. | H22: 875.2 | I22: ='May-22'!$H22*0.21 -> 183.792 | P22: =SUM('May-22'!$H22:$O22) -> 1058.992 | Q22: =IFERROR(IF('May-22'!$F22="","-",VLOOKUP('May-22'!$F22,Lista_CUIT!$A$1:$D$1871,3,0)),"CUIT NO CARGADO") -> Gastos Varios | R22: =IFERROR(IF('May-22'!$F22="","-",VLOOKUP('May-22'!$F22,Lista_CUIT!$A$1:$D$1871,4,0)),"CUIT NO CARGADO") -> 0
B23: 44692 | C23: 1 | D23: 2466 | E23: 357998 | F23: 30678814357 | G23: =IFERROR(IF('May-22'!$F23="","-",VLOOKUP('May-22'!$F23,Lista_CUIT!$A$1:$D$1871,2,0)),"CUIT NO CARGADO") -> Telefonica Moviles Argentina SA | H23: 6911.5 | J23: 1866.11 | N23: 207.34 | O23: 92.89 | P23: =SUM('May-22'!$H23:$O23) -> 9077.84 | Q23: =IFERROR(IF('May-22'!$F23="","-",VLOOKUP('May-22'!$F23,Lista_CUIT!$A$1:$D$1871,3,0)),"CUIT NO CARGADO") -> SERVICIOS GAS, LUZ, ETC | R23: =IFERROR(IF('May-22'!$F23="","-",VLOOKUP('May-22'!$F23,Lista_CUIT!$A$1:$D$1871,4,0)),"CUIT NO CARGADO") -> 0
B24: 44693 | C24: 1 | D24: 2 | E24: 20370 | F24: 30715257099 | G24: =IFERROR(IF('May-22'!$F24="","-",VLOOKUP('May-22'!$F24,Lista_CUIT!$A$1:$D$1871,2,0)),"CUIT NO CARGADO") -> FAS MOTOS | H24: 18834.71 | I24: ='May-22'!$H24*0.21 -> 3955.2891 | P24: =SUM('May-22'!$H24:$O24) -> 22789.999 | Q24: =IFERROR(IF('May-22'!$F24="","-",VLOOKUP('May-22'!$F24,Lista_CUIT!$A$1:$D$1871,3,0)),"CUIT NO CARGADO") -> INSUMO | R24: =IFERROR(IF('May-22'!$F24="","-",VLOOKUP('May-22'!$F24,Lista_CUIT!$A$1:$D$1871,4,0)),"CUIT NO CARGADO") -> 0
B25: 44693 | C25: 1 | D25: 106 | E25: 524430 | F25: 30594494187 | G25: =IFERROR(IF('May-22'!$F25="","-",VLOOKUP('May-22'!$F25,Lista_CUIT!$A$1:$D$1871,2,0)),"CUIT NO CARGADO") -> FEDERAL EXPRESS CORPORATION | H25: 5844 | I25: ='May-22'!$H25*0.21 -> 1227.24 | O25: 4843.83 | P25: =SUM('May-22'!$H25:$O25) -> 11915.07 | Q25: =IFERROR(IF('May-22'!$F25="","-",VLOOKUP('May-22'!$F25,Lista_CUIT!$A$1:$D$1871,3,0)),"CUIT NO CARGADO") -> GTOS IMP. | R25: =IFERROR(IF('May-22'!$F25="","-",VLOOKUP('May-22'!$F25,Lista_CUIT!$A$1:$D$1871,4,0)),"CUIT NO CARGADO") -> 0
B26: 44693 | C26: 1 | D26: 7 | E26: 29271 | F26: 20181426846 | G26: =IFERROR(IF('May-22'!$F26="","-",VLOOKUP('May-22'!$F26,Lista_CUIT!$A$1:$D$1871,2,0)),"CUIT NO CARGADO") -> GRIDEL WALTER DIEGO | H26: 1849.17 | I26: ='May-22'!$H26*0.21 -> 388.3257 | P26: =SUM('May-22'!$H26:$O26) -> 2237.4957 | Q26: =IFERROR(IF('May-22'!$F26="","-",VLOOKUP('May-22'!$F26,Lista_CUIT!$A$1:$D$1871,3,0)),"CUIT NO CARGADO") -> Gastos Oficina | R26: =IFERROR(IF('May-22'!$F26="","-",VLOOKUP('May-22'!$F26,Lista_CUIT!$A$1:$D$1871,4,0)),"CUIT NO CARGADO") -> 0
B27: 44694 | C27: 1 | D27: 5 | E27: 542 | F27: 30707397256 | G27: =IFERROR(IF('May-22'!$F27="","-",VLOOKUP('May-22'!$F27,Lista_CUIT!$A$1:$D$1871,2,0)),"CUIT NO CARGADO") -> GRAFICA Y FOTOGRABADOS LA PLAZA SRL | H27: 315388.2 | I27: ='May-22'!$H27*0.21 -> 66231.522 | P27: =SUM('May-22'!$H27:$O27) -> 381619.72 | Q27: =IFERROR(IF('May-22'!$F27="","-",VLOOKUP('May-22'!$F27,Lista_CUIT!$A$1:$D$1871,3,0)),"CUIT NO CARGADO") -> Fotograbados | R27: =IFERROR(IF('May-22'!$F27="","-",VLOOKUP('May-22'!$F27,Lista_CUIT!$A$1:$D$1871,4,0)),"CUIT NO CARGADO") -> 0
B28: 44694 | C28: 1 | D28: 3 | E28: 170 | F28: 23319824979 | G28: =IFERROR(IF('May-22'!$F28="","-",VLOOKUP('May-22'!$F28,Lista_CUIT!$A$1:$D$1871,2,0)),"CUIT NO CARGADO") -> PEREZ SEBASTIAN LUCAS | H28: 4950.23 | K28: 519.77415 | P28: =SUM('May-22'!$H28:$O28) -> 5470.0041 | Q28: =IFERROR(IF('May-22'!$F28="","-",VLOOKUP('May-22'!$F28,Lista_CUIT!$A$1:$D$1871,3,0)),"CUIT NO CARGADO") -> Gastos Varios | R28: =IFERROR(IF('May-22'!$F28="","-",VLOOKUP('May-22'!$F28,Lista_CUIT!$A$1:$D$1871,4,0)),"CUIT NO CARGADO") -> 0
B29: 44695 | C29: 1 | D29: 6 | E29: 9566 | F29: 30715819461 | G29: =IFERROR(IF('May-22'!$F29="","-",VLOOKUP('May-22'!$F29,Lista_CUIT!$A$1:$D$1871,2,0)),"CUIT NO CARGADO") -> DISTRI AIRES SRL | H29: 4968.6 | I29: ='May-22'!$H29*0.21 -> 1043.406 | P29: =SUM('May-22'!$H29:$O29) -> 6012.006 | Q29: =IFERROR(IF('May-22'!$F29="","-",VLOOKUP('May-22'!$F29,Lista_CUIT!$A$1:$D$1871,3,0)),"CUIT NO CARGADO") -> Papeleria e Impresos | R29: =IFERROR(IF('May-22'!$F29="","-",VLOOKUP('May-22'!$F29,Lista_CUIT!$A$1:$D$1871,4,0)),"CUIT NO CARGADO") -> 0
B30: 44697 | C30: 1 | D30: 9 | E30: 25058 | F30: 30595378695 | G30: =IFERROR(IF('May-22'!$F30="","-",VLOOKUP('May-22'!$F30,Lista_CUIT!$A$1:$D$1871,2,0)),"CUIT NO CARGADO") -> QUIWI SRL | H30: 3372.38 | I30: ='May-22'!$H30*0.21 -> 708.1998 | P30: =SUM('May-22'!$H30:$O30) -> 4080.5798 | Q30: =IFERROR(IF('May-22'!$F30="","-",VLOOKUP('May-22'!$F30,Lista_CUIT!$A$1:$D$1871,3,0)),"CUIT NO CARGADO") -> Mantenimiento | R30: =IFERROR(IF('May-22'!$F30="","-",VLOOKUP('May-22'!$F30,Lista_CUIT!$A$1:$D$1871,4,0)),"CUIT NO CARGADO") -> 0
B31: 44697 | C31: 1 | D31: 3 | E31: 503 | F31: 30716331349 | G31: =IFERROR(IF('May-22'!$F31="","-",VLOOKUP('May-22'!$F31,Lista_CUIT!$A$1:$D$1871,2,0)),"CUIT NO CARGADO") -> STERLING TRADE S.R.L. | I31: ='May-22'!$H31*0.21 -> 0 | O31: 65190 | P31: =SUM('May-22'!$H31:$O31) -> 65190 | Q31: =IFERROR(IF('May-22'!$F31="","-",VLOOKUP('May-22'!$F31,Lista_CUIT!$A$1:$D$1871,3,0)),"CUIT NO CARGADO") -> FLETE | R31: =IFERROR(IF('May-22'!$F31="","-",VLOOKUP('May-22'!$F31,Lista_CUIT!$A$1:$D$1871,4,0)),"CUIT NO CARGADO") -> 0
B32: 44700 | C32: 1 | D32: 1 | E32: 7155 | F32: 33716043989 | G32: =IFERROR(IF('May-22'!$F32="","-",VLOOKUP('May-22'!$F32,Lista_CUIT!$A$1:$D$1871,2,0)),"CUIT NO CARGADO") -> DANIEL Y LUCIO RIAL SOCIEDAD SIMPLE | H32: 15033.1 | I32: ='May-22'!$H32*0.21 -> 3156.951 | P32: =SUM('May-22'!$H32:$O32) -> 18190.051 | Q32: =IFERROR(IF('May-22'!$F32="","-",VLOOKUP('May-22'!$F32,Lista_CUIT!$A$1:$D$1871,3,0)),"CUIT NO CARGADO") -> INSUMO | R32: =IFERROR(IF('May-22'!$F32="","-",VLOOKUP('May-22'!$F32,Lista_CUIT!$A$1:$D$1871,4,0)),"CUIT NO CARGADO") -> 0
B33: 44700 | C33: 1 | D33: 5 | E33: 52946 | F33: 30692857611 | G33: =IFERROR(IF('May-22'!$F33="","-",VLOOKUP('May-22'!$F33,Lista_CUIT!$A$1:$D$1871,2,0)),"CUIT NO CARGADO") -> BAGUI S.A. | H33: 6620.63 | I33: ='May-22'!$H33*0.21 -> 1390.3323 | P33: =SUM('May-22'!$H33:$O33) -> 8010.9623 | Q33: =IFERROR(IF('May-22'!$F33="","-",VLOOKUP('May-22'!$F33,Lista_CUIT!$A$1:$D$1871,3,0)),"CUIT NO CARGADO") -> MAT. PRIM. | R33: =IFERROR(IF('May-22'!$F33="","-",VLOOKUP('May-22'!$F33,Lista_CUIT!$A$1:$D$1871,4,0)),"CUIT NO CARGADO") -> 0
B34: 44700 | C34: 1 | D34: 5 | E34: 52913 | F34: 30692857611 | G34: =IFERROR(IF('May-22'!$F34="","-",VLOOKUP('May-22'!$F34,Lista_CUIT!$A$1:$D$1871,2,0)),"CUIT NO CARGADO") -> BAGUI S.A. | H34: 6373.13 | I34: ='May-22'!$H34*0.21 -> 1338.3573 | P34: =SUM('May-22'!$H34:$O34) -> 7711.4873 | Q34: =IFERROR(IF('May-22'!$F34="","-",VLOOKUP('May-22'!$F34,Lista_CUIT!$A$1:$D$1871,3,0)),"CUIT NO CARGADO") -> MAT. PRIM. | R34: =IFERROR(IF('May-22'!$F34="","-",VLOOKUP('May-22'!$F34,Lista_CUIT!$A$1:$D$1871,4,0)),"CUIT NO CARGADO") -> 0
B35: 44700 | C35: 3 | D35: 5 | E35: 6389 | F35: 30692857611 | G35: =IFERROR(IF('May-22'!$F35="","-",VLOOKUP('May-22'!$F35,Lista_CUIT!$A$1:$D$1871,2,0)),"CUIT NO CARGADO") -> BAGUI S.A. | H35: -6373.13 | I35: ='May-22'!$H35*0.21 -> -1338.3573 | P35: =SUM('May-22'!$H35:$O35) -> -7711.4873 | Q35: =IFERROR(IF('May-22'!$F35="","-",VLOOKUP('May-22'!$F35,Lista_CUIT!$A$1:$D$1871,3,0)),"CUIT NO CARGADO") -> MAT. PRIM. | R35: =IFERROR(IF('May-22'!$F35="","-",VLOOKUP('May-22'!$F35,Lista_CUIT!$A$1:$D$1871,4,0)),"CUIT NO CARGADO") -> 0
B36: 44701 | C36: 1 | D36: 3 | E36: 257 | F36: 20921575743 | G36: =IFERROR(IF('May-22'!$F36="","-",VLOOKUP('May-22'!$F36,Lista_CUIT!$A$1:$D$1871,2,0)),"CUIT NO CARGADO") -> RIOS GOMEZ JOSE ANTONIO | H36: 10350 | I36: ='May-22'!$H36*0.21 -> 2173.5 | P36: =SUM('May-22'!$H36:$O36) -> 12523.5 | Q36: =IFERROR(IF('May-22'!$F36="","-",VLOOKUP('May-22'!$F36,Lista_CUIT!$A$1:$D$1871,3,0)),"CUIT NO CARGADO") -> Papeleria e Impresos | R36: =IFERROR(IF('May-22'!$F36="","-",VLOOKUP('May-22'!$F36,Lista_CUIT!$A$1:$D$1871,4,0)),"CUIT NO CARGADO") -> 0
B37: 44701 | C37: 1 | D37: 6 | E37: 9713 | F37: 30715819461 | G37: =IFERROR(IF('May-22'!$F37="","-",VLOOKUP('May-22'!$F37,Lista_CUIT!$A$1:$D$1871,2,0)),"CUIT NO CARGADO") -> DISTRI AIRES SRL | H37: 4505.79 | I37: ='May-22'!$H37*0.21 -> 946.2159 | P37: =SUM('May-22'!$H37:$O37) -> 5452.0059 | Q37: =IFERROR(IF('May-22'!$F37="","-",VLOOKUP('May-22'!$F37,Lista_CUIT!$A$1:$D$1871,3,0)),"CUIT NO CARGADO") -> Papeleria e Impresos | R37: =IFERROR(IF('May-22'!$F37="","-",VLOOKUP('May-22'!$F37,Lista_CUIT!$A$1:$D$1871,4,0)),"CUIT NO CARGADO") -> 0
B38: 44702 | C38: 1 | D38: 6992 | E38: 7175 | F38: 30678774495 | G38: =IFERROR(IF('May-22'!$F38="","-",VLOOKUP('May-22'!$F38,Lista_CUIT!$A$1:$D$1871,2,0)),"CUIT NO CARGADO") -> OPER. DE EST. DE SERV. SA | H38: 5683.31 | I38: ='May-22'!$H38*0.21 -> 1193.4951 | O38: 1324.09 | P38: =SUM('May-22'!$H38:$O38) -> 8200.8951 | Q38: =IFERROR(IF('May-22'!$F38="","-",VLOOKUP('May-22'!$F38,Lista_CUIT!$A$1:$D$1871,3,0)),"CUIT NO CARGADO") -> COMBUSTIBLE | R38: =IFERROR(IF('May-22'!$F38="","-",VLOOKUP('May-22'!$F38,Lista_CUIT!$A$1:$D$1871,4,0)),"CUIT NO CARGADO") -> 0
B39: 44704 | C39: 1 | D39: 60 | E39: 7117 | F39: 30547188760 | G39: =IFERROR(IF('May-22'!$F39="","-",VLOOKUP('May-22'!$F39,Lista_CUIT!$A$1:$D$1871,2,0)),"CUIT NO CARGADO") -> LONCO HUE SA | H39: 20314.04 | I39: ='May-22'!$H39*0.21 -> 4265.9484 | P39: =SUM('May-22'!$H39:$O39) -> 24579.988 | Q39: =IFERROR(IF('May-22'!$F39="","-",VLOOKUP('May-22'!$F39,Lista_CUIT!$A$1:$D$1871,3,0)),"CUIT NO CARGADO") -> INSUMO | R39: =IFERROR(IF('May-22'!$F39="","-",VLOOKUP('May-22'!$F39,Lista_CUIT!$A$1:$D$1871,4,0)),"CUIT NO CARGADO") -> 0
B40: 44705 | C40: 1 | D40: 5 | E40: 53108 | F40: 30692857611 | G40: =IFERROR(IF('May-22'!$F40="","-",VLOOKUP('May-22'!$F40,Lista_CUIT!$A$1:$D$1871,2,0)),"CUIT NO CARGADO") -> BAGUI S.A. | H40: 12338 | I40: ='May-22'!$H40*0.21 -> 2590.98 | P40: =SUM('May-22'!$H40:$O40) -> 14928.98 | Q40: =IFERROR(IF('May-22'!$F40="","-",VLOOKUP('May-22'!$F40,Lista_CUIT!$A$1:$D$1871,3,0)),"CUIT NO CARGADO") -> MAT. PRIM. | R40: =IFERROR(IF('May-22'!$F40="","-",VLOOKUP('May-22'!$F40,Lista_CUIT!$A$1:$D$1871,4,0)),"CUIT NO CARGADO") -> 0
B41: 44705 | C41: 1 | D41: 5 | E41: 53109 | F41: 30692857611 | G41: =IFERROR(IF('May-22'!$F41="","-",VLOOKUP('May-22'!$F41,Lista_CUIT!$A$1:$D$1871,2,0)),"CUIT NO CARGADO") -> BAGUI S.A. | H41: 125388.8 | I41: ='May-22'!$H41*0.21 -> 26331.648 | P41: =SUM('May-22'!$H41:$O41) -> 151720.45 | Q41: =IFERROR(IF('May-22'!$F41="","-",VLOOKUP('May-22'!$F41,Lista_CUIT!$A$1:$D$1871,3,0)),"CUIT NO CARGADO") -> MAT. PRIM. | R41: =IFERROR(IF('May-22'!$F41="","-",VLOOKUP('May-22'!$F41,Lista_CUIT!$A$1:$D$1871,4,0)),"CUIT NO CARGADO") -> 0
B42: 44706 | C42: 1 | D42: 5199 | E42: 13676 | F42: 30695542476 | G42: =IFERROR(IF('May-22'!$F42="","-",VLOOKUP('May-22'!$F42,Lista_CUIT!$A$1:$D$1871,2,0)),"CUIT NO CARGADO") -> PAN AMERICAN ENERGY LLC | H42: 5252.89 | I42: ='May-22'!$H42*0.21 -> 1103.1069 | O42: 1101.59 | P42: =SUM('May-22'!$H42:$O42) -> 7457.5869 | Q42: =IFERROR(IF('May-22'!$F42="","-",VLOOKUP('May-22'!$F42,Lista_CUIT!$A$1:$D$1871,3,0)),"CUIT NO CARGADO") -> COMBUSTIBLE | R42: =IFERROR(IF('May-22'!$F42="","-",VLOOKUP('May-22'!$F42,Lista_CUIT!$A$1:$D$1871,4,0)),"CUIT NO CARGADO") -> 0
B43: 44707 | C43: 3 | D43: 5 | E43: 6400 | F43: 30692857611 | G43: =IFERROR(IF('May-22'!$F43="","-",VLOOKUP('May-22'!$F43,Lista_CUIT!$A$1:$D$1871,2,0)),"CUIT NO CARGADO") -> BAGUI S.A. | H43: -10185.83 | I43: ='May-22'!$H43*0.21 -> -2139.0243 | P43: =SUM('May-22'!$H43:$O43) -> -12324.854 | Q43: =IFERROR(IF('May-22'!$F43="","-",VLOOKUP('May-22'!$F43,Lista_CUIT!$A$1:$D$1871,3,0)),"CUIT NO CARGADO") -> MAT. PRIM. | R43: =IFERROR(IF('May-22'!$F43="","-",VLOOKUP('May-22'!$F43,Lista_CUIT!$A$1:$D$1871,4,0)),"CUIT NO CARGADO") -> 0
B44: 44707 | C44: 3 | D44: 5 | E44: 6401 | F44: 30692857611 | G44: =IFERROR(IF('May-22'!$F44="","-",VLOOKUP('May-22'!$F44,Lista_CUIT!$A$1:$D$1871,2,0)),"CUIT NO CARGADO") -> BAGUI S.A. | H44: -40851.14 | I44: ='May-22'!$H44*0.21 -> -8578.7394 | P44: =SUM('May-22'!$H44:$O44) -> -49429.879 | Q44: =IFERROR(IF('May-22'!$F44="","-",VLOOKUP('May-22'!$F44,Lista_CUIT!$A$1:$D$1871,3,0)),"CUIT NO CARGADO") -> MAT. PRIM. | R44: =IFERROR(IF('May-22'!$F44="","-",VLOOKUP('May-22'!$F44,Lista_CUIT!$A$1:$D$1871,4,0)),"CUIT NO CARGADO") -> 0
B45: 44707 | C45: 1 | D45: 3 | E45: 202815 | F45: 33658043779 | G45: =IFERROR(IF('May-22'!$F45="","-",VLOOKUP('May-22'!$F45,Lista_CUIT!$A$1:$D$1871,2,0)),"CUIT NO CARGADO") -> BUREAU VERITAS ARGENTINA SA | H45: 83000 | I45: ='May-22'!$H45*0.21 -> 17430 | P45: =SUM('May-22'!$H45:$O45) -> 100430 | Q45: =IFERROR(IF('May-22'!$F45="","-",VLOOKUP('May-22'!$F45,Lista_CUIT!$A$1:$D$1871,3,0)),"CUIT NO CARGADO") -> ISO 9001 | R45: =IFERROR(IF('May-22'!$F45="","-",VLOOKUP('May-22'!$F45,Lista_CUIT!$A$1:$D$1871,4,0)),"CUIT NO CARGADO") -> 0
B46: 44707 | C46: 1 | D46: 106 | E46: 528493 | F46: 30594494187 | G46: =IFERROR(IF('May-22'!$F46="","-",VLOOKUP('May-22'!$F46,Lista_CUIT!$A$1:$D$1871,2,0)),"CUIT NO CARGADO") -> FEDERAL EXPRESS CORPORATION | H46: 7440 | I46: ='May-22'!$H46*0.21 -> 1562.4 | O46: 18610.77 | P46: =SUM('May-22'!$H46:$O46) -> 27613.17 | Q46: =IFERROR(IF('May-22'!$F46="","-",VLOOKUP('May-22'!$F46,Lista_CUIT!$A$1:$D$1871,3,0)),"CUIT NO CARGADO") -> GTOS IMP. | R46: =IFERROR(IF('May-22'!$F46="","-",VLOOKUP('May-22'!$F46,Lista_CUIT!$A$1:$D$1871,4,0)),"CUIT NO CARGADO") -> 0
B47: 44707 | C47: 1 | D47: 5 | E47: 4524 | F47: 30711758905 | G47: =IFERROR(IF('May-22'!$F47="","-",VLOOKUP('May-22'!$F47,Lista_CUIT!$A$1:$D$1871,2,0)),"CUIT NO CARGADO") -> GRUPO FRESHEN SRL | H47: 2199.01 | I47: ='May-22'!$H47*0.21 -> 461.7921 | P47: =SUM('May-22'!$H47:$O47) -> 2660.8021 | Q47: =IFERROR(IF('May-22'!$F47="","-",VLOOKUP('May-22'!$F47,Lista_CUIT!$A$1:$D$1871,3,0)),"CUIT NO CARGADO") -> MAT. PRIM. | R47: =IFERROR(IF('May-22'!$F47="","-",VLOOKUP('May-22'!$F47,Lista_CUIT!$A$1:$D$1871,4,0)),"CUIT NO CARGADO") -> 0
B48: 44709 | C48: 1 | D48: 3 | E48: 893486 | F48: 30712019359 | G48: =IFERROR(IF('May-22'!$F48="","-",VLOOKUP('May-22'!$F48,Lista_CUIT!$A$1:$D$1871,2,0)),"CUIT NO CARGADO") -> LINKEDSTORE ARGENTINA S.R.L. | H48: 2478.51 | I48: ='May-22'!$H48*0.21 -> 520.4871 | P48: =SUM('May-22'!$H48:$O48) -> 2998.9971 | Q48: =IFERROR(IF('May-22'!$F48="","-",VLOOKUP('May-22'!$F48,Lista_CUIT!$A$1:$D$1871,3,0)),"CUIT NO CARGADO") -> Gastos Varios | R48: =IFERROR(IF('May-22'!$F48="","-",VLOOKUP('May-22'!$F48,Lista_CUIT!$A$1:$D$1871,4,0)),"CUIT NO CARGADO") -> 0
B49: 44712 | C49: 1 | D49: 1 | E49: 454 | F49: 30715048066 | G49: =IFERROR(IF('May-22'!$F49="","-",VLOOKUP('May-22'!$F49,Lista_CUIT!$A$1:$D$1871,2,0)),"CUIT NO CARGADO") -> ROLLS Y EMPANADAS SA | H49: 69080 | I49: ='May-22'!$H49*0.21 -> 14506.8 | P49: =SUM('May-22'!$H49:$O49) -> 83586.8 | Q49: =IFERROR(IF('May-22'!$F49="","-",VLOOKUP('May-22'!$F49,Lista_CUIT!$A$1:$D$1871,3,0)),"CUIT NO CARGADO") -> CATERING | R49: =IFERROR(IF('May-22'!$F49="","-",VLOOKUP('May-22'!$F49,Lista_CUIT!$A$1:$D$1871,4,0)),"CUIT NO CARGADO") -> 0
B50: 44712 | C50: 1 | D50: 3 | E50: 2188 | F50: 30715535471 | G50: =IFERROR(IF('May-22'!$F50="","-",VLOOKUP('May-22'!$F50,Lista_CUIT!$A$1:$D$1871,2,0)),"CUIT NO CARGADO") -> DHARMA DE SANTOS Y VACCARO | H50: 11424.79 | I50: ='May-22'!$H50*0.21 -> 2399.2059 | P50: =SUM('May-22'!$H50:$O50) -> 13823.996 | Q50: =IFERROR(IF('May-22'!$F50="","-",VLOOKUP('May-22'!$F50,Lista_CUIT!$A$1:$D$1871,3,0)),"CUIT NO CARGADO") -> FERRETERIA | R50: =IFERROR(IF('May-22'!$F50="","-",VLOOKUP('May-22'!$F50,Lista_CUIT!$A$1:$D$1871,4,0)),"CUIT NO CARGADO") -> 0
B51: Total | H51: =SUBTOTAL(109,'May-22'!$H$9:$H$50) -> 1068381.8 | I51: =SUBTOTAL(109,'May-22'!$I$9:$I$50) -> 207855.9 | J51: =SUBTOTAL(109,'May-22'!$J$9:$J$50) -> 1866.11 | K51: =SUBTOTAL(109,'May-22'!$K$9:$K$50) -> 7526.4242 | L51: =SUBTOTAL(109,'May-22'!$L$9:$L$50) -> 0 | M51: =SUBTOTAL(109,'May-22'!$M$9:$M$50) -> 7289.04 | N51: =SUBTOTAL(109,'May-22'!$N$9:$N$50) -> 207.34 | O51: =SUBTOTAL(109,'May-22'!$O$9:$O$50) -> 58949.86 | P51: =SUBTOTAL(109,'May-22'!$P$9:$P$50) -> 1352076.4
D56: LIQUIDACION EXTRACTOS BANCARIOS-TARJETAS
D57: FECHA | E57: NRO CPTE | F57: BANCO | G57: NETO | H57: IVA 21% | I57: IVA 10,5% | J57: RET IIBB CABA | K57: PERC IVA | L57: PERC IIBB
F58: BANCO CREDICOOP | G58: 1896 | H58: 398.16
D59: 44691 | E59: 617-47869 | F59: Liq. C. i. Vista (mostrador) | G59: 13426.25 | H59: 2819.5125 | J59: 402.79
D60: 44691 | E60: 617-478691 | F60: Liq. C. i. Vista (mostrador) | G60: 13426.25 | H60: 2819.5125 | J60: 402.79
D61: 44684 | E61: 947-86 | F61: Liq. Importacion | G61: 2896.75 | H61: 608.3175 | J61: 86.9
F62: VISA CREDITO | G62: 80 | H62: 16.8
D63: Total | G63: =SUBTOTAL(109,'May-22'!$G$58:$G$62) -> 31725.25 | H63: =SUBTOTAL(109,'May-22'!$H$58:$H$62) -> 6662.3025 | I63: =SUBTOTAL(109,'May-22'!$I$58:$I$62) -> 0 | J63: =SUBTOTAL(109,'May-22'!$J$58:$J$62) -> 892.48 | K63: =SUBTOTAL(109,'May-22'!$K$58:$K$62) -> 0 | L63: =SUBTOTAL(109,'May-22'!$L$58:$L$62) -> 0
D65: FACTURAS C
D66: FECHA | E66: PTO VTA | F66: FC Nº | G66: CUIT | H66: RAZON SOCIAL | I66: TOTAL | J66: TIPO DE GASTO | K66: Provincia
D67: 44684 | E67: 3 | F67: 560 | G67: 20086277523 | H67: =IFERROR(IF('May-22'!$G67="","-",VLOOKUP('May-22'!$G67,Lista_CUIT!$A$1:$D$1871,2,0)),"CUIT NO CARGADO") -> JUAN CARLOS BOTINDARI | I67: 31500 | J67: =IFERROR(IF('May-22'!$G67="","-",VLOOKUP('May-22'!$G67,Lista_CUIT!$A$1:$D$1871,3,0)),"CUIT NO CARGADO") -> HONORARIOS | K67: =IFERROR(IF('May-22'!$G67="","-",VLOOKUP('May-22'!$G67,Lista_CUIT!$A$1:$D$1871,4,0)),"CUIT NO CARGADO") -> 0
D68: 44685 | E68: 2 | F68: 94 | G68: 27397607602 | H68: =IFERROR(IF('May-22'!$G68="","-",VLOOKUP('May-22'!$G68,Lista_CUIT!$A$1:$D$1871,2,0)),"CUIT NO CARGADO") -> RIOS ALDANA SOFIA | I68: 7647.45 | J68: =IFERROR(IF('May-22'!$G68="","-",VLOOKUP('May-22'!$G68,Lista_CUIT!$A$1:$D$1871,3,0)),"CUIT NO CARGADO") -> Honorarios Profesionales | K68: =IFERROR(IF('May-22'!$G68="","-",VLOOKUP('May-22'!$G68,Lista_CUIT!$A$1:$D$1871,4,0)),"CUIT NO CARGADO") -> 0
D69: 44686 | E69: 1 | F69: 84 | G69: 20341465134 | H69: =IFERROR(IF('May-22'!$G69="","-",VLOOKUP('May-22'!$G69,Lista_CUIT!$A$1:$D$1871,2,0)),"CUIT NO CARGADO") -> ABELEDO AGUSTIN ENRIQUE | I69: 42200 | J69: =IFERROR(IF('May-22'!$G69="","-",VLOOKUP('May-22'!$G69,Lista_CUIT!$A$1:$D$1871,3,0)),"CUIT NO CARGADO") -> HONOR. INGENIERO | K69: =IFERROR(IF('May-22'!$G69="","-",VLOOKUP('May-22'!$G69,Lista_CUIT!$A$1:$D$1871,4,0)),"CUIT NO CARGADO") -> 0
D70: 44690 | E70: 1 | F70: 6 | G70: 20338344695 | H70: =IFERROR(IF('May-22'!$G70="","-",VLOOKUP('May-22'!$G70,Lista_CUIT!$A$1:$D$1871,2,0)),"CUIT NO CARGADO") -> FUERTES DAMIAN MATIAS | I70: 17160 | J70: =IFERROR(IF('May-22'!$G70="","-",VLOOKUP('May-22'!$G70,Lista_CUIT!$A$1:$D$1871,3,0)),"CUIT NO CARGADO") -> INSUMO | K70: =IFERROR(IF('May-22'!$G70="","-",VLOOKUP('May-22'!$G70,Lista_CUIT!$A$1:$D$1871,4,0)),"CUIT NO CARGADO") -> 0
D71: 44692 | E71: 3 | F71: 564 | G71: 20086277523 | H71: =IFERROR(IF('May-22'!$G71="","-",VLOOKUP('May-22'!$G71,Lista_CUIT!$A$1:$D$1871,2,0)),"CUIT NO CARGADO") -> JUAN CARLOS BOTINDARI | I71: 8350 | J71: =IFERROR(IF('May-22'!$G71="","-",VLOOKUP('May-22'!$G71,Lista_CUIT!$A$1:$D$1871,3,0)),"CUIT NO CARGADO") -> HONORARIOS | K71: =IFERROR(IF('May-22'!$G71="","-",VLOOKUP('May-22'!$G71,Lista_CUIT!$A$1:$D$1871,4,0)),"CUIT NO CARGADO") -> 0
D72: 44694 | E72: 1 | F72: 106 | G72: 20297899830 | H72: =IFERROR(IF('May-22'!$G72="","-",VLOOKUP('May-22'!$G72,Lista_CUIT!$A$1:$D$1871,2,0)),"CUIT NO CARGADO") -> FUNK MATIAS NICOLAS | I72: 579000 | J72: =IFERROR(IF('May-22'!$G72="","-",VLOOKUP('May-22'!$G72,Lista_CUIT!$A$1:$D$1871,3,0)),"CUIT NO CARGADO") -> Servicios Torneria | K72: =IFERROR(IF('May-22'!$G72="","-",VLOOKUP('May-22'!$G72,Lista_CUIT!$A$1:$D$1871,4,0)),"CUIT NO CARGADO") -> 0
D73: 44694 | E73: 3 | F73: 26 | G73: 20403931420 | H73: =IFERROR(IF('May-22'!$G73="","-",VLOOKUP('May-22'!$G73,Lista_CUIT!$A$1:$D$1871,2,0)),"CUIT NO CARGADO") -> FIORENTINO JORGE IGNACIO | I73: 103875 | J73: =IFERROR(IF('May-22'!$G73="","-",VLOOKUP('May-22'!$G73,Lista_CUIT!$A$1:$D$1871,3,0)),"CUIT NO CARGADO") -> Honorarios Administrativos-Cobranzas y Gestion Clientes | K73: =IFERROR(IF('May-22'!$G73="","-",VLOOKUP('May-22'!$G73,Lista_CUIT!$A$1:$D$1871,4,0)),"CUIT NO CARGADO") -> 0
D74: 44695 | E74: 1 | F74: 6 | G74: 20417805878 | H74: =IFERROR(IF('May-22'!$G74="","-",VLOOKUP('May-22'!$G74,Lista_CUIT!$A$1:$D$1871,2,0)),"CUIT NO CARGADO") -> FERABOLI OSPAL SANTIAGO HERNAN | I74: 129910 | J74: =IFERROR(IF('May-22'!$G74="","-",VLOOKUP('May-22'!$G74,Lista_CUIT!$A$1:$D$1871,3,0)),"CUIT NO CARGADO") -> Control medidores masicos | K74: =IFERROR(IF('May-22'!$G74="","-",VLOOKUP('May-22'!$G74,Lista_CUIT!$A$1:$D$1871,4,0)),"CUIT NO CARGADO") -> 0
D75: 44696 | E75: 2 | F75: 71 | G75: 20244271740 | H75: =IFERROR(IF('May-22'!$G75="","-",VLOOKUP('May-22'!$G75,Lista_CUIT!$A$1:$D$1871,2,0)),"CUIT NO CARGADO") -> KENNEL SEBASTIAN | I75: 164700 | J75: =IFERROR(IF('May-22'!$G75="","-",VLOOKUP('May-22'!$G75,Lista_CUIT!$A$1:$D$1871,3,0)),"CUIT NO CARGADO") -> SOFTWARE MANTENIMIENTO | K75: =IFERROR(IF('May-22'!$G75="","-",VLOOKUP('May-22'!$G75,Lista_CUIT!$A$1:$D$1871,4,0)),"CUIT NO CARGADO") -> 0
D76: 44696 | E76: 2 | F76: 10 | G76: 23326777269 | H76: =IFERROR(IF('May-22'!$G76="","-",VLOOKUP('May-22'!$G76,Lista_CUIT!$A$1:$D$1871,2,0)),"CUIT NO CARGADO") -> DE BONIS IGNACIO LUIS | I76: 120470 | J76: =IFERROR(IF('May-22'!$G76="","-",VLOOKUP('May-22'!$G76,Lista_CUIT!$A$1:$D$1871,3,0)),"CUIT NO CARGADO") -> Control medidores masicos | K76: =IFERROR(IF('May-22'!$G76="","-",VLOOKUP('May-22'!$G76,Lista_CUIT!$A$1:$D$1871,4,0)),"CUIT NO CARGADO") -> 0
D77: 44698 | E77: 1 | F77: 12 | G77: 20365938688 | H77: =IFERROR(IF('May-22'!$G77="","-",VLOOKUP('May-22'!$G77,Lista_CUIT!$A$1:$D$1871,2,0)),"CUIT NO CARGADO") -> LIPANOVICH JUAN CRUZ | I77: 220000 | J77: =IFERROR(IF('May-22'!$G77="","-",VLOOKUP('May-22'!$G77,Lista_CUIT!$A$1:$D$1871,3,0)),"CUIT NO CARGADO") -> Servicios Informatica | K77: =IFERROR(IF('May-22'!$G77="","-",VLOOKUP('May-22'!$G77,Lista_CUIT!$A$1:$D$1871,4,0)),"CUIT NO CARGADO") -> 0
D78: 44700 | E78: 9 | F78: 3180819 | G78: 33715179119 | H78: =IFERROR(IF('May-22'!$G78="","-",VLOOKUP('May-22'!$G78,Lista_CUIT!$A$1:$D$1871,2,0)),"CUIT NO CARGADO") -> NIC ARGENTINA | I78: 475 | J78: =IFERROR(IF('May-22'!$G78="","-",VLOOKUP('May-22'!$G78,Lista_CUIT!$A$1:$D$1871,3,0)),"CUIT NO CARGADO") -> SERVICIOS GAS, LUZ, ETC | K78: =IFERROR(IF('May-22'!$G78="","-",VLOOKUP('May-22'!$G78,Lista_CUIT!$A$1:$D$1871,4,0)),"CUIT NO CARGADO") -> 0
... D83: 44712 | E83: 2 | F83: 109 | G83: 20136544625 | H83: =IFERROR(IF('May-22'!$G83="","-",VLOOKUP('May-22'!$G83,Lista_CUIT!$A$1:$D$1871,2,0)),"CUIT NO CARGADO") -> RODRIGUEZ DE LA FUEN HECTOR MARCELO | I83: 140000 | J83: =IFERROR(IF('May-22'!$G83="","-",VLOOKUP('May-22'!$G83,Lista_CUIT!$A$1:$D$1871,3,0)),"CUIT NO CARGADO") -> Honorarios Administrativos-Cobranzas y Gestion Clientes | K83: =IFERROR(IF('May-22'!$G83="","-",VLOOKUP('May-22'!$G83,Lista_CUIT!$A$1:$D$1871,4,0)),"CUIT NO CARGADO") -> 0
D84: Total | I84: =SUBTOTAL(109,'May-22'!$I$67:$I$83) -> 1704037.4
B87: LIBRO IVA VENTAS | K87: =N1 -> 44682
B89: VENTAS "A"
B90: FECHA | C90: TIPO | D90: PTO VENTA | E90: Nº FACTURA | F90: CUIT | G90: RAZON SOCIAL | H90: IMPORTE NETO | I90: IVA 21% | J90: IVA 10,5% | K90: EXENTO | L90: TOTAL | M90: Provincia
B91: 44687 | C91: 1 | D91: 3 | E91: 60 | F91: 30638318470 | G91: =IFERROR(IF('May-22'!$F91="","-",VLOOKUP('May-22'!$F91,Lista_CUIT!$A$1:$D$1871,2,0)),"CUIT NO CARGADO") -> DELTA COMPRESION S.R.L | H91: 6322056.4 | I91: 124603.82 | J91: 601514.07 | L91: =SUM('May-22'!$H91:$K91) -> 7048174.3
B92: 44694 | C92: 1 | D92: 3 | E92: 61 | F92: 30708984716 | G92: =IFERROR(IF('May-22'!$F92="","-",VLOOKUP('May-22'!$F92,Lista_CUIT!$A$1:$D$1871,2,0)),"CUIT NO CARGADO") -> NATURAL GAS SERVICE SRL | H92: 38500 | I92: ='May-22'!$H92*0.21 -> 8085 | L92: =SUM('May-22'!$H92:$K92) -> 46585
B93: 44700 | C93: 3 | D93: 3 | E93: 11 | F93: 30628274327 | G93: =IFERROR(IF('May-22'!$F93="","-",VLOOKUP('May-22'!$F93,Lista_CUIT!$A$1:$D$1871,2,0)),"CUIT NO CARGADO") -> AGIRA SA | H93: -1015852.2 | J93: -106664.48 | L93: =SUM('May-22'!$H93:$K93) -> -1122516.7
B94: 44705 | C94: 1 | D94: 3 | E94: 62 | F94: 30628274327 | G94: =IFERROR(IF('May-22'!$F94="","-",VLOOKUP('May-22'!$F94,Lista_CUIT!$A$1:$D$1871,2,0)),"CUIT NO CARGADO") -> AGIRA SA | H94: 2126647.2 | J94: 223297.96 | L94: =SUM('May-22'!$H94:$K94) -> 2349945.2
G95: =IFERROR(IF('May-22'!$F95="","-",VLOOKUP('May-22'!$F95,Lista_CUIT!$A$1:$D$1871,2,0)),"CUIT NO CARGADO") -> - | I95: ='May-22'!$H95*0.21 -> 0 | L95: =SUM('May-22'!$H95:$K95) -> 0
G96: =IFERROR(IF('May-22'!$F96="","-",VLOOKUP('May-22'!$F96,Lista_CUIT!$A$1:$D$1871,2,0)),"CUIT NO CARGADO") -> - | I96: ='May-22'!$H96*0.21 -> 0 | L96: =SUM('May-22'!$H96:$K96) -> 0
G97: =IFERROR(IF('May-22'!$F97="","-",VLOOKUP('May-22'!$F97,Lista_CUIT!$A$1:$D$1871,2,0)),"CUIT NO CARGADO") -> - | I97: ='May-22'!$H97*0.21 -> 0 | L97: =SUM('May-22'!$H97:$K97) -> 0
G98: =IFERROR(IF('May-22'!$F98="","-",VLOOKUP('May-22'!$F98,Lista_CUIT!$A$1:$D$1871,2,0)),"CUIT NO CARGADO") -> - | I98: ='May-22'!$H98*0.21 -> 0 | L98: =SUM('May-22'!$H98:$K98) -> 0
G99: =IFERROR(IF('May-22'!$F99="","-",VLOOKUP('May-22'!$F99,Lista_CUIT!$A$1:$D$1871,2,0)),"CUIT NO CARGADO") -> - | I99: ='May-22'!$H99*0.21 -> 0 | L99: =SUM('May-22'!$H99:$K99) -> 0
B100: Total | H100: =SUBTOTAL(109,'May-22'!$H$91:$H$99) -> 7471351.4 | I100: =SUBTOTAL(109,'May-22'!$I$91:$I$99) -> 132688.82 | J100: =SUBTOTAL(109,'May-22'!$J$91:$J$99) -> 718147.54 | K100: =SUBTOTAL(109,'May-22'!$K$91:$K$99) -> 0 | L100: =SUBTOTAL(109,'May-22'!$L$91:$L$99) -> 8322187.7 | M100: =SUBTOTAL(103,'May-22'!$M$91:$M$99) -> 0
B103: VENTAS "B"
B104: FECHA | C104: TIPO | D104: PTO VENTA | E104: Nº FACTURA | F104: CUIT | G104: RAZON SOCIAL | H104: IMPORTE NETO | I104: IVA 21% | J104: IVA 10,5% | K104: EXENTO | L104: TOTAL | M104: Provincia
I105: ='May-22'!$H105*0.21 -> 0
I106: ='May-22'!$H106*0.21 -> 0
I107: ='May-22'!$H107*0.21 -> 0
I108: ='May-22'!$H108*0.21 -> 0
I109: ='May-22'!$H109*0.21 -> 0
I110: ='May-22'!$H110*0.21 -> 0
I111: ='May-22'!$H111*0.21 -> 0
B112: Total | I112: =SUBTOTAL(109,'May-22'!$I$105:$I$111) -> 0 | J112: =SUBTOTAL(109,'May-22'!$J$105:$J$111) -> 0 | K112: =SUBTOTAL(109,'May-22'!$K$105:$K$111) -> 0 | L112: =SUBTOTAL(109,'May-22'!$L$105:$L$111) -> 0 | M112: =SUBTOTAL(103,'May-22'!$M$105:$M$111) -> 0
B114: VENTAS EXPORTACION
B115: FECHA | C115: Nº FACTRA | D115: CUIT | E115: RAZON SOCIAL | F115: USD | G115: EUR | H115: T. CAMBIO | I115: TOTAL
B119: Total
C123: RETENCIONES
C124: FECHA | D124: COMP Nº | E124: Columna1 | F124: CUIT | G124: RAZON SOCIAL | H124: Ganancias | I124: IVA | J124: SUSS | K124: IIBB BSAS | L124: IIBB CABA
...

Sheet Jun-22
B1: LIBRO IVA COMPRAS | G1: ='Abr-22'!G1:M1 -> CORITEC S.R.L. | N1: =EDATE('Abr-22'!N1,2) -> 44713
B3: TOTAL COMPRAS | G3: TOTAL CREDITO FISCAL | J3: TOTAL VENTAS NETAS | M3: TOTAL DEBITO FISCAL | P3: RESULTADO
B4: =SUM('Jun-22'!$H$39)+'Jun-22'!$G$52 -> 2946484.8 | G4: ='Jun-22'!$I$39+'Jun-22'!$J$39+'Jun-22'!$K$39+'Jun-22'!$H$52+'Jun-22'!$I$52 -> 574986.36 | J4: ='Jun-22'!$H$93+'Jun-22'!$H$104 -> 2789657.3 | M4: ='Jun-22'!$I$93+'Jun-22'!$J$93+'Jun-22'!$I$104+'Jun-22'!$J$104 -> 340735.04 | P4: =G4-M4 -> 234251.32
B8: FECHA | C8: TIPO | D8: PTO VTA | E8: NRO. CPTE | F8: CUIT | G8: RAZON SOCIAL | H8: NETO GRAVADO | I8: IVA 21 % | J8: IVA 27% | K8: IVA 10,5% | L8: PERC. IVA | M8: PERC IIBB BS AS | N8: PERC. IIBB CABA | O8: Otros / No Grav. | P8: TOTAL | Q8: Tipo de Gasto | R8: Provincia
B9: 44741 | C9: 1 | D9: 2 | E9: 139 | F9: 20125142851 | G9: =IFERROR(IF('Jun-22'!$F9="","-",VLOOKUP('Jun-22'!$F9,Lista_CUIT!$A$1:$D$1871,2,0)),"CUIT NO CARGADO") -> FEDERICI NICOLAS JOSE | H9: 13908 | I9: =IF('Jun-22'!$H9="","",'Jun-22'!$H9*0.21) -> 2920.68 | P9: =SUM('Jun-22'!$H9:$O9) -> 16828.68 | Q9: =IFERROR(IF('Jun-22'!$F9="","-",VLOOKUP('Jun-22'!$F9,Lista_CUIT!$A$1:$D$1871,3,0)),"CUIT NO CARGADO") -> INSUMO | R9: =IFERROR(IF('Jun-22'!$F9="","-",VLOOKUP('Jun-22'!$F9,Lista_CUIT!$A$1:$D$1871,4,0)),"CUIT NO CARGADO") -> 0
B10: 44736 | C10: 1 | D10: 2 | E10: 138 | F10: 20125142851 | G10: =IFERROR(IF('Jun-22'!$F10="","-",VLOOKUP('Jun-22'!$F10,Lista_CUIT!$A$1:$D$1871,2,0)),"CUIT NO CARGADO") -> FEDERICI NICOLAS JOSE | H10: 15048 | I10: =IF('Jun-22'!$H10="","",'Jun-22'!$H10*0.21) -> 3160.08 | P10: =SUM('Jun-22'!$H10:$O10) -> 18208.08 | Q10: =IFERROR(IF('Jun-22'!$F10="","-",VLOOKUP('Jun-22'!$F10,Lista_CUIT!$A$1:$D$1871,3,0)),"CUIT NO CARGADO") -> INSUMO | R10: =IFERROR(IF('Jun-22'!$F10="","-",VLOOKUP('Jun-22'!$F10,Lista_CUIT!$A$1:$D$1871,4,0)),"CUIT NO CARGADO") -> 0
B11: 44739 | C11: 1 | D11: 1 | E11: 178227 | F11: 30716620634 | G11: =IFERROR(IF('Jun-22'!$F11="","-",VLOOKUP('Jun-22'!$F11,Lista_CUIT!$A$1:$D$1871,2,0)),"CUIT NO CARGADO") -> FIRST LABEL SRL | H11: 7106.61 | I11: =IF('Jun-22'!$H11="","",'Jun-22'!$H11*0.21) -> 1492.3881 | P11: =SUM('Jun-22'!$H11:$O11) -> 8598.9981 | Q11: =IFERROR(IF('Jun-22'!$F11="","-",VLOOKUP('Jun-22'!$F11,Lista_CUIT!$A$1:$D$1871,3,0)),"CUIT NO CARGADO") -> Gastos Varios | R11: =IFERROR(IF('Jun-22'!$F11="","-",VLOOKUP('Jun-22'!$F11,Lista_CUIT!$A$1:$D$1871,4,0)),"CUIT NO CARGADO") -> 0
B12: 44727 | C12: 1 | D12: 5 | E12: 71 | F12: 20235490251 | G12: =IFERROR(IF('Jun-22'!$F12="","-",VLOOKUP('Jun-22'!$F12,Lista_CUIT!$A$1:$D$1871,2,0)),"CUIT NO CARGADO") -> SALAS ARIEL ALFREDO | H12: 1444.21 | I12: =IF('Jun-22'!$H12="","",'Jun-22'!$H12*0.21) -> 303.2841 | P12: =SUM('Jun-22'!$H12:$O12) -> 1747.4941 | Q12: =IFERROR(IF('Jun-22'!$F12="","-",VLOOKUP('Jun-22'!$F12,Lista_CUIT!$A$1:$D$1871,3,0)),"CUIT NO CARGADO") -> Gastos Varios | R12: =IFERROR(IF('Jun-22'!$F12="","-",VLOOKUP('Jun-22'!$F12,Lista_CUIT!$A$1:$D$1871,4,0)),"CUIT NO CARGADO") -> 0
B13: 44718 | C13: 1 | D13: 3 | E13: 2090 | F13: 30716966530 | G13: =IFERROR(IF('Jun-22'!$F13="","-",VLOOKUP('Jun-22'!$F13,Lista_CUIT!$A$1:$D$1871,2,0)),"CUIT NO CARGADO") -> UDACHI SRL | H13: 3872.47 | I13: =IF('Jun-22'!$H13="","",'Jun-22'!$H13*0.21) -> 813.2187 | P13: =SUM('Jun-22'!$H13:$O13) -> 4685.6887 | Q13: =IFERROR(IF('Jun-22'!$F13="","-",VLOOKUP('Jun-22'!$F13,Lista_CUIT!$A$1:$D$1871,3,0)),"CUIT NO CARGADO") -> INSUMO | R13: =IFERROR(IF('Jun-22'!$F13="","-",VLOOKUP('Jun-22'!$F13,Lista_CUIT!$A$1:$D$1871,4,0)),"CUIT NO CARGADO") -> 0
B14: 44736 | C14: 1 | D14: 1 | E14: 467 | F14: 30715048066 | G14: =IFERROR(IF('Jun-22'!$F14="","-",VLOOKUP('Jun-22'!$F14,Lista_CUIT!$A$1:$D$1871,2,0)),"CUIT NO CARGADO") -> ROLLS Y EMPANADAS SA | H14: 119985 | I14: =IF('Jun-22'!$H14="","",'Jun-22'!$H14*0.21) -> 25196.85 | P14: =SUM('Jun-22'!$H14:$O14) -> 145181.85 | Q14: =IFERROR(IF('Jun-22'!$F14="","-",VLOOKUP('Jun-22'!$F14,Lista_CUIT!$A$1:$D$1871,3,0)),"CUIT NO CARGADO") -> CATERING | R14: =IFERROR(IF('Jun-22'!$F14="","-",VLOOKUP('Jun-22'!$F14,Lista_CUIT!$A$1:$D$1871,4,0)),"CUIT NO CARGADO") -> 0
B15: 44735 | C15: 1 | D15: 4 | E15: 87001 | F15: 30559932236 | G15: =IFERROR(IF('Jun-22'!$F15="","-",VLOOKUP('Jun-22'!$F15,Lista_CUIT!$A$1:$D$1871,2,0)),"CUIT NO CARGADO") -> ELECTRONICA ELEMON SA | H15: 22954.1 | K15: 2410.1805 | P15: =SUM('Jun-22'!$H15:$O15) -> 25364.28 | Q15: =IFERROR(IF('Jun-22'!$F15="","-",VLOOKUP('Jun-22'!$F15,Lista_CUIT!$A$1:$D$1871,3,0)),"CUIT NO CARGADO") -> MAT. PRIM. | R15: =IFERROR(IF('Jun-22'!$F15="","-",VLOOKUP('Jun-22'!$F15,Lista_CUIT!$A$1:$D$1871,4,0)),"CUIT NO CARGADO") -> 0
B16: 44735 | C16: 1 | D16: 7 | E16: 1293 | F16: 30709775762 | G16: =IFERROR(IF('Jun-22'!$F16="","-",VLOOKUP('Jun-22'!$F16,Lista_CUIT!$A$1:$D$1871,2,0)),"CUIT NO CARGADO") -> INDUSTRIA BAHIA S.A. | H16: 763743.32 | I16: =IF('Jun-22'!$H16="","",'Jun-22'!$H16*0.21) -> 160386.1 | P16: =SUM('Jun-22'!$H16:$O16) -> 924129.41 | Q16: =IFERROR(IF('Jun-22'!$F16="","-",VLOOKUP('Jun-22'!$F16,Lista_CUIT!$A$1:$D$1871,3,0)),"CUIT NO CARGADO") -> MAT. PRIM. | R16: =IFERROR(IF('Jun-22'!$F16="","-",VLOOKUP('Jun-22'!$F16,Lista_CUIT!$A$1:$D$1871,4,0)),"CUIT NO CARGADO") -> 0
B17: 44713 | C17: 1 | D17: 3 | E17: 540 | F17: 30715402765 | G17: =IFERROR(IF('Jun-22'!$F17="","-",VLOOKUP('Jun-22'!$F17,Lista_CUIT!$A$1:$D$1871,2,0)),"CUIT NO CARGADO") -> RIO 265 SRL | H17: 7190.08 | I17: =IF('Jun-22'!$H17="","",'Jun-22'!$H17*0.21) -> 1509.9168 | P17: =SUM('Jun-22'!$H17:$O17) -> 8699.9968 | Q17: =IFERROR(IF('Jun-22'!$F17="","-",VLOOKUP('Jun-22'!$F17,Lista_CUIT!$A$1:$D$1871,3,0)),"CUIT NO CARGADO") -> GTOS VARIOS-ESTACIONAMIENTO HORACIO | R17: =IFERROR(IF('Jun-22'!$F17="","-",VLOOKUP('Jun-22'!$F17,Lista_CUIT!$A$1:$D$1871,4,0)),"CUIT NO CARGADO") -> 0
B18: 44728 | C18: 1 | D18: 3 | E18: 259 | F18: 20921575743 | G18: =IFERROR(IF('Jun-22'!$F18="","-",VLOOKUP('Jun-22'!$F18,Lista_CUIT!$A$1:$D$1871,2,0)),"CUIT NO CARGADO") -> RIOS GOMEZ JOSE ANTONIO | H18: 13800 | I18: =IF('Jun-22'!$H18="","",'Jun-22'!$H18*0.21) -> 2898 | P18: =SUM('Jun-22'!$H18:$O18) -> 16698 | Q18: =IFERROR(IF('Jun-22'!$F18="","-",VLOOKUP('Jun-22'!$F18,Lista_CUIT!$A$1:$D$1871,3,0)),"CUIT NO CARGADO") -> Papeleria e Impresos | R18: =IFERROR(IF('Jun-22'!$F18="","-",VLOOKUP('Jun-22'!$F18,Lista_CUIT!$A$1:$D$1871,4,0)),"CUIT NO CARGADO") -> 0
B19: 44724 | C19: 1 | D19: 2 | E19: 137 | F19: 20125142851 | G19: =IFERROR(IF('Jun-22'!$F19="","-",VLOOKUP('Jun-22'!$F19,Lista_CUIT!$A$1:$D$1871,2,0)),"CUIT NO CARGADO") -> FEDERICI NICOLAS JOSE | H19: 25878 | I19: =IF('Jun-22'!$H19="","",'Jun-22'!$H19*0.21) -> 5434.38 | P19: =SUM('Jun-22'!$H19:$O19) -> 31312.38 | Q19: =IFERROR(IF('Jun-22'!$F19="","-",VLOOKUP('Jun-22'!$F19,Lista_CUIT!$A$1:$D$1871,3,0)),"CUIT NO CARGADO") -> INSUMO | R19: =IFERROR(IF('Jun-22'!$F19="","-",VLOOKUP('Jun-22'!$F19,Lista_CUIT!$A$1:$D$1871,4,0)),"CUIT NO CARGADO") -> 0
B20: 44720 | C20: 1 | D20: 2 | E20: 136 | F20: 20125142851 | G20: =IFERROR(IF('Jun-22'!$F20="","-",VLOOKUP('Jun-22'!$F20,Lista_CUIT!$A$1:$D$1871,2,0)),"CUIT NO CARGADO") -> FEDERICI NICOLAS JOSE | H20: 23073 | I20: =IF('Jun-22'!$H20="","",'Jun-22'!$H20*0.21) -> 4845.33 | P20: =SUM('Jun-22'!$H20:$O20) -> 27918.33 | Q20: =IFERROR(IF('Jun-22'!$F20="","-",VLOOKUP('Jun-22'!$F20,Lista_CUIT!$A$1:$D$1871,3,0)),"CUIT NO CARGADO") -> INSUMO | R20: =IFERROR(IF('Jun-22'!$F20="","-",VLOOKUP('Jun-22'!$F20,Lista_CUIT!$A$1:$D$1871,4,0)),"CUIT NO CARGADO") -> 0
B21: 44720 | C21: 1 | D21: 2 | E21: 135 | F21: 20125142851 | G21: =IFERROR(IF('Jun-22'!$F21="","-",VLOOKUP('Jun-22'!$F21,Lista_CUIT!$A$1:$D$1871,2,0)),"CUIT NO CARGADO") -> FEDERICI NICOLAS JOSE | H21: 19717.2 | I21: =IF('Jun-22'!$H21="","",'Jun-22'!$H21*0.21) -> 4140.612 | P21: =SUM('Jun-22'!$H21:$O21) -> 23857.812 | Q21: =IFERROR(IF('Jun-22'!$F21="","-",VLOOKUP('Jun-22'!$F21,Lista_CUIT!$A$1:$D$1871,3,0)),"CUIT NO CARGADO") -> INSUMO | R21: =IFERROR(IF('Jun-22'!$F21="","-",VLOOKUP('Jun-22'!$F21,Lista_CUIT!$A$1:$D$1871,4,0)),"CUIT NO CARGADO") -> 0
B22: 44726 | C22: 1 | D22: 10 | E22: 7137 | F22: 20168925582 | G22: =IFERROR(IF('Jun-22'!$F22="","-",VLOOKUP('Jun-22'!$F22,Lista_CUIT!$A$1:$D$1871,2,0)),"CUIT NO CARGADO") -> OXIGENO DORREGO | H22: 12600 | I22: =IF('Jun-22'!$H22="","",'Jun-22'!$H22*0.21) -> 2646 | P22: =SUM('Jun-22'!$H22:$O22) -> 15246 | Q22: =IFERROR(IF('Jun-22'!$F22="","-",VLOOKUP('Jun-22'!$F22,Lista_CUIT!$A$1:$D$1871,3,0)),"CUIT NO CARGADO") -> Gastos Varios | R22: =IFERROR(IF('Jun-22'!$F22="","-",VLOOKUP('Jun-22'!$F22,Lista_CUIT!$A$1:$D$1871,4,0)),"CUIT NO CARGADO") -> 0
B23: 44718 | C23: 1 | D23: 4 | E23: 86493 | F23: 30559932236 | G23: =IFERROR(IF('Jun-22'!$F23="","-",VLOOKUP('Jun-22'!$F23,Lista_CUIT!$A$1:$D$1871,2,0)),"CUIT NO CARGADO") -> ELECTRONICA ELEMON SA | H23: 61271.52 | I23: =IF('Jun-22'!$H23="","",'Jun-22'!$H23*0.21) -> 12867.019 | P23: =SUM('Jun-22'!$H23:$O23) -> 74138.539 | Q23: =IFERROR(IF('Jun-22'!$F23="","-",VLOOKUP('Jun-22'!$F23,Lista_CUIT!$A$1:$D$1871,3,0)),"CUIT NO CARGADO") -> MAT. PRIM. | R23: =IFERROR(IF('Jun-22'!$F23="","-",VLOOKUP('Jun-22'!$F23,Lista_CUIT!$A$1:$D$1871,4,0)),"CUIT NO CARGADO") -> 0
B24: 44719 | C24: 1 | D24: 8 | E24: 33893 | F24: 30655921644 | G24: =IFERROR(IF('Jun-22'!$F24="","-",VLOOKUP('Jun-22'!$F24,Lista_CUIT!$A$1:$D$1871,2,0)),"CUIT NO CARGADO") -> ELECTROCITY | H24: 3932.23 | I24: =IF('Jun-22'!$H24="","",'Jun-22'!$H24*0.21) -> 825.7683 | P24: =SUM('Jun-22'!$H24:$O24) -> 4757.9983 | Q24: =IFERROR(IF('Jun-22'!$F24="","-",VLOOKUP('Jun-22'!$F24,Lista_CUIT!$A$1:$D$1871,3,0)),"CUIT NO CARGADO") -> MAT. PRIM. | R24: =IFERROR(IF('Jun-22'!$F24="","-",VLOOKUP('Jun-22'!$F24,Lista_CUIT!$A$1:$D$1871,4,0)),"CUIT NO CARGADO") -> 0
B25: 44720 | C25: 1 | D25: 2 | E25: 768 | F25: 30500805222 | G25: =IFERROR(IF('Jun-22'!$F25="","-",VLOOKUP('Jun-22'!$F25,Lista_CUIT!$A$1:$D$1871,2,0)),"CUIT NO CARGADO") -> KAVCIC SRL | H25: 40260 | I25: =IF('Jun-22'!$H25="","",'Jun-22'!$H25*0.21) -> 8454.6 | P25: =SUM('Jun-22'!$H25:$O25) -> 48714.6 | Q25: =IFERROR(IF('Jun-22'!$F25="","-",VLOOKUP('Jun-22'!$F25,Lista_CUIT!$A$1:$D$1871,3,0)),"CUIT NO CARGADO") -> INSUMO | R25: =IFERROR(IF('Jun-22'!$F25="","-",VLOOKUP('Jun-22'!$F25,Lista_CUIT!$A$1:$D$1871,4,0)),"CUIT NO CARGADO") -> 0
B26: 44722 | C26: 1 | D26: 3 | E26: 6710 | F26: 30710212127 | G26: =IFERROR(IF('Jun-22'!$F26="","-",VLOOKUP('Jun-22'!$F26,Lista_CUIT!$A$1:$D$1871,2,0)),"CUIT NO CARGADO") -> COMPONENTES ELECTRICOS SA | H26: 827068.98 | I26: =IF('Jun-22'!$H26="","",'Jun-22'!$H26*0.21) -> 173684.49 | P26: =SUM('Jun-22'!$H26:$O26) -> 1000753.5 | Q26: =IFERROR(IF('Jun-22'!$F26="","-",VLOOKUP('Jun-22'!$F26,Lista_CUIT!$A$1:$D$1871,3,0)),"CUIT NO CARGADO") -> INSUMO | R26: =IFERROR(IF('Jun-22'!$F26="","-",VLOOKUP('Jun-22'!$F26,Lista_CUIT!$A$1:$D$1871,4,0)),"CUIT NO CARGADO") -> 0
B27: 44715 | C27: 1 | D27: 3 | E27: 7457 | F27: 30715864262 | G27: =IFERROR(IF('Jun-22'!$F27="","-",VLOOKUP('Jun-22'!$F27,Lista_CUIT!$A$1:$D$1871,2,0)),"CUIT NO CARGADO") -> ACPLIND - FELDMAN SH | H27: 18414 | I27: =IF('Jun-22'!$H27="","",'Jun-22'!$H27*0.21) -> 3866.94 | P27: =SUM('Jun-22'!$H27:$O27) -> 22280.94 | Q27: =IFERROR(IF('Jun-22'!$F27="","-",VLOOKUP('Jun-22'!$F27,Lista_CUIT!$A$1:$D$1871,3,0)),"CUIT NO CARGADO") -> MAT. PRIM. | R27: =IFERROR(IF('Jun-22'!$F27="","-",VLOOKUP('Jun-22'!$F27,Lista_CUIT!$A$1:$D$1871,4,0)),"CUIT NO CARGADO") -> 0
... B31: 44742 | C31: 1 | D31: 4 | E31: 12591 | F31: 23113854499 | G31: =IFERROR(IF('Jun-22'!$F31="","-",VLOOKUP('Jun-22'!$F31,Lista_CUIT!$A$1:$D$1871,2,0)),"CUIT NO CARGADO") -> VAZQUEZ DANIEL OSCAR | H31: 3801.65 | I31: =IF('Jun-22'!$H31="","",'Jun-22'!$H31*0.21) -> 798.3465 | P31: =SUM('Jun-22'!$H31:$O31) -> 4599.9965 | Q31: =IFERROR(IF('Jun-22'!$F31="","-",VLOOKUP('Jun-22'!$F31,Lista_CUIT!$A$1:$D$1871,3,0)),"CUIT NO CARGADO") -> INSUMO | R31: =IFERROR(IF('Jun-22'!$F31="","-",VLOOKUP('Jun-22'!$F31,Lista_CUIT!$A$1:$D$1871,4,0)),"CUIT NO CARGADO") -> 0
B32: 44741 | C32: 1 | D32: 280 | E32: 1375108 | F32: 30580111315 | G32: =IFERROR(IF('Jun-22'!$F32="","-",VLOOKUP('Jun-22'!$F32,Lista_CUIT!$A$1:$D$1871,2,0)),"CUIT NO CARGADO") -> DHL EXPRESS ARG SA | H32: 398923.43 | I32: 786.68 | K32: 41493.05 | O32: -359252.24 | P32: =SUM('Jun-22'!$H32:$O32) -> 81950.92 | Q32: =IFERROR(IF('Jun-22'!$F32="","-",VLOOKUP('Jun-22'!$F32,Lista_CUIT!$A$1:$D$1871,3,0)),"CUIT NO CARGADO") -> GTOS IMP. | R32: =IFERROR(IF('Jun-22'!$F32="","-",VLOOKUP('Jun-22'!$F32,Lista_CUIT!$A$1:$D$1871,4,0)),"CUIT NO CARGADO") -> 0
B33: 44723 | C33: 1 | D33: 2466 | E33: 370888 | F33: 30678814357 | G33: =IFERROR(IF('Jun-22'!$F33="","-",VLOOKUP('Jun-22'!$F33,Lista_CUIT!$A$1:$D$1871,2,0)),"CUIT NO CARGADO") -> Telefonica Moviles Argentina SA | H33: 2148.61 | J33: 580.1247 | M33: 64.46 | O33: 104.58 | P33: =SUM('Jun-22'!$H33:$O33) -> 2897.7747 | Q33: =IFERROR(IF('Jun-22'!$F33="","-",VLOOKUP('Jun-22'!$F33,Lista_CUIT!$A$1:$D$1871,3,0)),"CUIT NO CARGADO") -> SERVICIOS GAS, LUZ, ETC | R33: =IFERROR(IF('Jun-22'!$F33="","-",VLOOKUP('Jun-22'!$F33,Lista_CUIT!$A$1:$D$1871,4,0)),"CUIT NO CARGADO") -> 0
B34: 44729 | C34: 1 | D34: 30 | E34: 4666 | F34: 20217293791 | G34: =IFERROR(IF('Jun-22'!$F34="","-",VLOOKUP('Jun-22'!$F34,Lista_CUIT!$A$1:$D$1871,2,0)),"CUIT NO CARGADO") -> VELASCO LEIVA DEMIAN | H34: 8719.01 | I34: =IF('Jun-22'!$H34="","",'Jun-22'!$H34*0.21) -> 1830.9921 | P34: =SUM('Jun-22'!$H34:$O34) -> 10550.002 | Q34: =IFERROR(IF('Jun-22'!$F34="","-",VLOOKUP('Jun-22'!$F34,Lista_CUIT!$A$1:$D$1871,3,0)),"CUIT NO CARGADO") -> Gastos Varios | R34: =IFERROR(IF('Jun-22'!$F34="","-",VLOOKUP('Jun-22'!$F34,Lista_CUIT!$A$1:$D$1871,4,0)),"CUIT NO CARGADO") -> 0
B35: 44736 | C35: 1 | D35: 1 | E35: 466 | F35: 30715048066 | G35: =IFERROR(IF('Jun-22'!$F35="","-",VLOOKUP('Jun-22'!$F35,Lista_CUIT!$A$1:$D$1871,2,0)),"CUIT NO CARGADO") -> ROLLS Y EMPANADAS SA | H35: 81105 | I35: =IF('Jun-22'!$H35="","",'Jun-22'!$H35*0.21) -> 17032.05 | P35: =SUM('Jun-22'!$H35:$O35) -> 98137.05 | Q35: =IFERROR(IF('Jun-22'!$F35="","-",VLOOKUP('Jun-22'!$F35,Lista_CUIT!$A$1:$D$1871,3,0)),"CUIT NO CARGADO") -> CATERING | R35: =IFERROR(IF('Jun-22'!$F35="","-",VLOOKUP('Jun-22'!$F35,Lista_CUIT!$A$1:$D$1871,4,0)),"CUIT NO CARGADO") -> 0
B36: 44738 | C36: 1 | D36: 3 | E36: 939183 | F36: 30712019359 | G36: =IFERROR(IF('Jun-22'!$F36="","-",VLOOKUP('Jun-22'!$F36,Lista_CUIT!$A$1:$D$1871,2,0)),"CUIT NO CARGADO") -> LINKEDSTORE ARGENTINA S.R.L. | H36: 2478.51 | I36: =IF('Jun-22'!$H36="","",'Jun-22'!$H36*0.21) -> 520.4871 | P36: =SUM('Jun-22'!$H36:$O36) -> 2998.9971 | Q36: =IFERROR(IF('Jun-22'!$F36="","-",VLOOKUP('Jun-22'!$F36,Lista_CUIT!$A$1:$D$1871,3,0)),"CUIT NO CARGADO") -> Gastos Varios | R36: =IFERROR(IF('Jun-22'!$F36="","-",VLOOKUP('Jun-22'!$F36,Lista_CUIT!$A$1:$D$1871,4,0)),"CUIT NO CARGADO") -> 0
B37: 44741 | C37: 1 | D37: 5 | E37: 630 | F37: 30707397256 | G37: =IFERROR(IF('Jun-22'!$F37="","-",VLOOKUP('Jun-22'!$F37,Lista_CUIT!$A$1:$D$1871,2,0)),"CUIT NO CARGADO") -> GRAFICA Y FOTOGRABADOS LA PLAZA SRL | H37: 377201.4 | I37: =IF('Jun-22'!$H37="","",'Jun-22'!$H37*0.21) -> 79212.294 | P37: =SUM('Jun-22'!$H37:$O37) -> 456413.69 | Q37: =IFERROR(IF('Jun-22'!$F37="","-",VLOOKUP('Jun-22'!$F37,Lista_CUIT!$A$1:$D$1871,3,0)),"CUIT NO CARGADO") -> Fotograbados | R37: =IFERROR(IF('Jun-22'!$F37="","-",VLOOKUP('Jun-22'!$F37,Lista_CUIT!$A$1:$D$1871,4,0)),"CUIT NO CARGADO") -> 0
B38: 44741 | C38: 1 | D38: 1 | E38: 28187 | F38: 27332519633 | G38: =IFERROR(IF('Jun-22'!$F38="","-",VLOOKUP('Jun-22'!$F38,Lista_CUIT!$A$1:$D$1871,2,0)),"CUIT NO CARGADO") -> BOJORGE ROMINA VALERIA | H38: 2209.92 | I38: =IF('Jun-22'!$H38="","",'Jun-22'!$H38*0.21) -> 464.0832 | P38: =SUM('Jun-22'!$H38:$O38) -> 2674.0032 | Q38: =IFERROR(IF('Jun-22'!$F38="","-",VLOOKUP('Jun-22'!$F38,Lista_CUIT!$A$1:$D$1871,3,0)),"CUIT NO CARGADO") -> Gastos Oficina | R38: =IFERROR(IF('Jun-22'!$F38="","-",VLOOKUP('Jun-22'!$F38,Lista_CUIT!$A$1:$D$1871,4,0)),"CUIT NO CARGADO") -> 0
B39: Total | H39: =SUBTOTAL(109,'Jun-22'!$H$9:$H$38) -> 2944492.8 | I39: =SUBTOTAL(109,'Jun-22'!$I$9:$I$38) -> 530084.68 | J39: =SUBTOTAL(109,'Jun-22'!$J$9:$J$38) -> 580.1247 | K39: =SUBTOTAL(109,'Jun-22'!$K$9:$K$38) -> 43903.231 | L39: =SUBTOTAL(109,'Jun-22'!$L$9:$L$38) -> 0 | M39: =SUBTOTAL(109,'Jun-22'!$M$9:$M$38) -> 64.46 | N39: =SUBTOTAL(109,'Jun-22'!$N$9:$N$38) -> 0 | O39: =SUBTOTAL(109,'Jun-22'!$O$9:$O$38) -> -359147.66 | P39: =SUBTOTAL(109,'Jun-22'!$P$9:$P$38) -> 3159977.6
D44: LIQUIDACION EXTRACTOS BANCARIOS-TARJETAS
D45: FECHA | E45: NRO CPTE | F45: BANCO | G45: NETO | H45: IVA 21% | I45: IVA 10,5% | J45: RET IIBB CABA | K45: PERC IVA | L45: PERC IIBB
F46: BANCO CREDICOOP | G46: 1912 | H46: 401.52
F47: Liq. Importacion | H47: 0
F48: Cobro Exportacion | H48: 0
F49: VISA CREDITO | G49: 80 | H49: 16.8
F50: AMEX
D52: Total | G52: =SUBTOTAL(109,'Jun-22'!$G$46:$G$51) -> 1992 | H52: =SUBTOTAL(109,'Jun-22'!$H$46:$H$51) -> 418.32 | I52: =SUBTOTAL(109,'Jun-22'!$I$46:$I$51) -> 0 | J52: =SUBTOTAL(109,'Jun-22'!$J$46:$J$51) -> 0 | K52: =SUBTOTAL(109,'Jun-22'!$K$46:$K$51) -> 0 | L52: =SUBTOTAL(109,'Jun-22'!$L$46:$L$51) -> 0
D56: FACTURAS C
D57: FECHA | E57: PTO VTA | F57: FC Nº | G57: CUIT | H57: RAZON SOCIAL | I57: TOTAL | J57: TIPO DE GASTO | K57: Provincia
D58: 44742 | E58: 2 | F58: 111 | G58: 20136544625 | H58: =IFERROR(IF('Jun-22'!$G58="","-",VLOOKUP('Jun-22'!$G58,Lista_CUIT!$A$1:$D$1871,2,0)),"CUIT NO CARGADO") -> RODRIGUEZ DE LA FUEN HECTOR MARCELO | I58: 140000 | J58: =IFERROR(IF('Jun-22'!$G58="","-",VLOOKUP('Jun-22'!$G58,Lista_CUIT!$A$1:$D$1871,3,0)),"CUIT NO CARGADO") -> Honorarios Administrativos-Cobranzas y Gestion Clientes | K58: =IFERROR(IF('Jun-22'!$G58="","-",VLOOKUP('Jun-22'!$G58,Lista_CUIT!$A$1:$D$1871,4,0)),"CUIT NO CARGADO") -> 0
D59: 44734 | E59: 4 | F59: 2 | G59: 20341462933 | H59: =IFERROR(IF('Jun-22'!$G59="","-",VLOOKUP('Jun-22'!$G59,Lista_CUIT!$A$1:$D$1871,2,0)),"CUIT NO CARGADO") -> CASTIGLIONI MATIAS EZEQUIEL | I59: 100000 | J59: =IFERROR(IF('Jun-22'!$G59="","-",VLOOKUP('Jun-22'!$G59,Lista_CUIT!$A$1:$D$1871,3,0)),"CUIT NO CARGADO") -> MAT. PRIM. | K59: =IFERROR(IF('Jun-22'!$G59="","-",VLOOKUP('Jun-22'!$G59,Lista_CUIT!$A$1:$D$1871,4,0)),"CUIT NO CARGADO") -> 0
D60: 44726 | E60: 3 | F60: 578 | G60: 20086277523 | H60: =IFERROR(IF('Jun-22'!$G60="","-",VLOOKUP('Jun-22'!$G60,Lista_CUIT!$A$1:$D$1871,2,0)),"CUIT NO CARGADO") -> JUAN CARLOS BOTINDARI | I60: 8350 | J60: =IFERROR(IF('Jun-22'!$G60="","-",VLOOKUP('Jun-22'!$G60,Lista_CUIT!$A$1:$D$1871,3,0)),"CUIT NO CARGADO") -> HONORARIOS | K60: =IFERROR(IF('Jun-22'!$G60="","-",VLOOKUP('Jun-22'!$G60,Lista_CUIT!$A$1:$D$1871,4,0)),"CUIT NO CARGADO") -> 0
D61: 44718 | E61: 1 | F61: 85 | G61: 20341465134 | H61: =IFERROR(IF('Jun-22'!$G61="","-",VLOOKUP('Jun-22'!$G61,Lista_CUIT!$A$1:$D$1871,2,0)),"CUIT NO CARGADO") -> ABELEDO AGUSTIN ENRIQUE | I61: 79670 | J61: =IFERROR(IF('Jun-22'!$G61="","-",VLOOKUP('Jun-22'!$G61,Lista_CUIT!$A$1:$D$1871,3,0)),"CUIT NO CARGADO") -> HONOR. INGENIERO | K61: =IFERROR(IF('Jun-22'!$G61="","-",VLOOKUP('Jun-22'!$G61,Lista_CUIT!$A$1:$D$1871,4,0)),"CUIT NO CARGADO") -> 0
D62: 44714 | E62: 3 | F62: 575 | G62: 20086277523 | H62: =IFERROR(IF('Jun-22'!$G62="","-",VLOOKUP('Jun-22'!$G62,Lista_CUIT!$A$1:$D$1871,2,0)),"CUIT NO CARGADO") -> JUAN CARLOS BOTINDARI | I62: 31500 | J62: =IFERROR(IF('Jun-22'!$G62="","-",VLOOKUP('Jun-22'!$G62,Lista_CUIT!$A$1:$D$1871,3,0)),"CUIT NO CARGADO") -> HONORARIOS | K62: =IFERROR(IF('Jun-22'!$G62="","-",VLOOKUP('Jun-22'!$G62,Lista_CUIT!$A$1:$D$1871,4,0)),"CUIT NO CARGADO") -> 0
D63: 44742 | E63: 1 | F63: 7 | G63: 20338344695 | H63: =IFERROR(IF('Jun-22'!$G63="","-",VLOOKUP('Jun-22'!$G63,Lista_CUIT!$A$1:$D$1871,2,0)),"CUIT NO CARGADO") -> FUERTES DAMIAN MATIAS | I63: 18090 | J63: =IFERROR(IF('Jun-22'!$G63="","-",VLOOKUP('Jun-22'!$G63,Lista_CUIT!$A$1:$D$1871,3,0)),"CUIT NO CARGADO") -> INSUMO | K63: =IFERROR(IF('Jun-22'!$G63="","-",VLOOKUP('Jun-22'!$G63,Lista_CUIT!$A$1:$D$1871,4,0)),"CUIT NO CARGADO") -> 0
D64: 44718 | E64: 3 | F64: 27 | G64: 20403931420 | H64: =IFERROR(IF('Jun-22'!$G64="","-",VLOOKUP('Jun-22'!$G64,Lista_CUIT!$A$1:$D$1871,2,0)),"CUIT NO CARGADO") -> FIORENTINO JORGE IGNACIO | I64: 104080 | J64: =IFERROR(IF('Jun-22'!$G64="","-",VLOOKUP('Jun-22'!$G64,Lista_CUIT!$A$1:$D$1871,3,0)),"CUIT NO CARGADO") -> Honorarios Administrativos-Cobranzas y Gestion Clientes | K64: =IFERROR(IF('Jun-22'!$G64="","-",VLOOKUP('Jun-22'!$G64,Lista_CUIT!$A$1:$D$1871,4,0)),"CUIT NO CARGADO") -> 0
D65: 44719 | E65: 2 | F65: 11 | G65: 23326777269 | H65: =IFERROR(IF('Jun-22'!$G65="","-",VLOOKUP('Jun-22'!$G65,Lista_CUIT!$A$1:$D$1871,2,0)),"CUIT NO CARGADO") -> DE BONIS IGNACIO LUIS | I65: 120775 | J65: =IFERROR(IF('Jun-22'!$G65="","-",VLOOKUP('Jun-22'!$G65,Lista_CUIT!$A$1:$D$1871,3,0)),"CUIT NO CARGADO") -> Control medidores masicos | K65: =IFERROR(IF('Jun-22'!$G65="","-",VLOOKUP('Jun-22'!$G65,Lista_CUIT!$A$1:$D$1871,4,0)),"CUIT NO CARGADO") -> 0
D66: 44719 | E66: 1 | F66: 7 | G66: 20417805878 | H66: =IFERROR(IF('Jun-22'!$G66="","-",VLOOKUP('Jun-22'!$G66,Lista_CUIT!$A$1:$D$1871,2,0)),"CUIT NO CARGADO") -> FERABOLI OSPAL SANTIAGO HERNAN | I66: 79260 | J66: =IFERROR(IF('Jun-22'!$G66="","-",VLOOKUP('Jun-22'!$G66,Lista_CUIT!$A$1:$D$1871,3,0)),"CUIT NO CARGADO") -> Control medidores masicos | K66: =IFERROR(IF('Jun-22'!$G66="","-",VLOOKUP('Jun-22'!$G66,Lista_CUIT!$A$1:$D$1871,4,0)),"CUIT NO CARGADO") -> 0
D67: 44722 | E67: 2 | F67: 72 | G67: 20244271740 | H67: =IFERROR(IF('Jun-22'!$G67="","-",VLOOKUP('Jun-22'!$G67,Lista_CUIT!$A$1:$D$1871,2,0)),"CUIT NO CARGADO") -> KENNEL SEBASTIAN | I67: 172800 | J67: =IFERROR(IF('Jun-22'!$G67="","-",VLOOKUP('Jun-22'!$G67,Lista_CUIT!$A$1:$D$1871,3,0)),"CUIT NO CARGADO") -> SOFTWARE MANTENIMIENTO | K67: =IFERROR(IF('Jun-22'!$G67="","-",VLOOKUP('Jun-22'!$G67,Lista_CUIT!$A$1:$D$1871,4,0)),"CUIT NO CARGADO") -> 0
D68: 44727 | E68: 1 | F68: 13 | G68: 20365938688 | H68: =IFERROR(IF('Jun-22'!$G68="","-",VLOOKUP('Jun-22'!$G68,Lista_CUIT!$A$1:$D$1871,2,0)),"CUIT NO CARGADO") -> LIPANOVICH JUAN CRUZ | I68: 220000 | J68: =IFERROR(IF('Jun-22'!$G68="","-",VLOOKUP('Jun-22'!$G68,Lista_CUIT!$A$1:$D$1871,3,0)),"CUIT NO CARGADO") -> Servicios Informatica | K68: =IFERROR(IF('Jun-22'!$G68="","-",VLOOKUP('Jun-22'!$G68,Lista_CUIT!$A$1:$D$1871,4,0)),"CUIT NO CARGADO") -> 0
D69: 44731 | E69: 2 | F69: 533 | G69: 20320877947 | H69: =IFERROR(IF('Jun-22'!$G69="","-",VLOOKUP('Jun-22'!$G69,Lista_CUIT!$A$1:$D$1871,2,0)),"CUIT NO CARGADO") -> ROUSSEAU PABLO ANDRES | I69: 9800 | J69: =IFERROR(IF('Jun-22'!$G69="","-",VLOOKUP('Jun-22'!$G69,Lista_CUIT!$A$1:$D$1871,3,0)),"CUIT NO CARGADO") -> SERVICIO | K69: =IFERROR(IF('Jun-22'!$G69="","-",VLOOKUP('Jun-22'!$G69,Lista_CUIT!$A$1:$D$1871,4,0)),"CUIT NO CARGADO") -> 0
H70: =IFERROR(IF('Jun-22'!$G70="","-",VLOOKUP('Jun-22'!$G70,Lista_CUIT!$A$1:$D$1871,2,0)),"CUIT NO CARGADO") -> - | J70: =IFERROR(IF('Jun-22'!$G70="","-",VLOOKUP('Jun-22'!$G70,Lista_CUIT!$A$1:$D$1871,3,0)),"CUIT NO CARGADO") -> - | K70: =IFERROR(IF('Jun-22'!$G70="","-",VLOOKUP('Jun-22'!$G70,Lista_CUIT!$A$1:$D$1871,4,0)),"CUIT NO CARGADO") -> -
H71: =IFERROR(IF('Jun-22'!$G71="","-",VLOOKUP('Jun-22'!$G71,Lista_CUIT!$A$1:$D$1871,2,0)),"CUIT NO CARGADO") -> - | J71: =IFERROR(IF('Jun-22'!$G71="","-",VLOOKUP('Jun-22'!$G71,Lista_CUIT!$A$1:$D$1871,3,0)),"CUIT NO CARGADO") -> - | K71: =IFERROR(IF('Jun-22'!$G71="","-",VLOOKUP('Jun-22'!$G71,Lista_CUIT!$A$1:$D$1871,4,0)),"CUIT NO CARGADO") -> -
H72: =IFERROR(IF('Jun-22'!$G72="","-",VLOOKUP('Jun-22'!$G72,Lista_CUIT!$A$1:$D$1871,2,0)),"CUIT NO CARGADO") -> - | J72: =IFERROR(IF('Jun-22'!$G72="","-",VLOOKUP('Jun-22'!$G72,Lista_CUIT!$A$1:$D$1871,3,0)),"CUIT NO CARGADO") -> - | K72: =IFERROR(IF('Jun-22'!$G72="","-",VLOOKUP('Jun-22'!$G72,Lista_CUIT!$A$1:$D$1871,4,0)),"CUIT NO CARGADO") -> -
H73: =IFERROR(IF('Jun-22'!$G73="","-",VLOOKUP('Jun-22'!$G73,Lista_CUIT!$A$1:$D$1871,2,0)),"CUIT NO CARGADO") -> - | J73: =IFERROR(IF('Jun-22'!$G73="","-",VLOOKUP('Jun-22'!$G73,Lista_CUIT!$A$1:$D$1871,3,0)),"CUIT NO CARGADO") -> - | K73: =IFERROR(IF('Jun-22'!$G73="","-",VLOOKUP('Jun-22'!$G73,Lista_CUIT!$A$1:$D$1871,4,0)),"CUIT NO CARGADO") -> -
D74: Total | I74: =SUBTOTAL(109,'Jun-22'!$I$58:$I$73) -> 1084325
B80: LIBRO IVA VENTAS | K80: =N1 -> 44713
B82: VENTAS "A"
B83: FECHA | C83: TIPO | D83: PTO VENTA | E83: Nº FACTURA | F83: CUIT | G83: RAZON SOCIAL | H83: IMPORTE NETO | I83: IVA 21% | J83: IVA 10,5% | K83: EXENTO | L83: TOTAL | M83: Provincia
B84: 44726 | C84: 1 | D84: 3 | E84: 63 | F84: 30638318470 | G84: =IFERROR(IF('Jun-22'!$F84="","-",VLOOKUP('Jun-22'!$F84,Lista_CUIT!$A$1:$D$1871,2,0)),"CUIT NO CARGADO") -> DELTA COMPRESION S.R.L | H84: 17122 | I84: ='Jun-22'!$H84*0.21 -> 3595.62 | L84: =SUM('Jun-22'!$H84:$K84) -> 20717.62
B85: 44726 | C85: 1 | D85: 3 | E85: 64 | F85: 30638318470 | G85: =IFERROR(IF('Jun-22'!$F85="","-",VLOOKUP('Jun-22'!$F85,Lista_CUIT!$A$1:$D$1871,2,0)),"CUIT NO CARGADO") -> DELTA COMPRESION S.R.L | H85: 327886.3 | I85: ='Jun-22'!$H85*0.21 -> 68856.123 | L85: =SUM('Jun-22'!$H85:$K85) -> 396742.42
B86: 44727 | C86: 1 | D86: 3 | E86: 66 | F86: 23239931359 | G86: =IFERROR(IF('Jun-22'!$F86="","-",VLOOKUP('Jun-22'!$F86,Lista_CUIT!$A$1:$D$1871,2,0)),"CUIT NO CARGADO") -> SAN MIGUEL JOSE MARCELO | H86: 24540 | I86: ='Jun-22'!$H86*0.21 -> 5153.4 | L86: =SUM('Jun-22'!$H86:$K86) -> 29693.4
B87: 44727 | C87: 1 | D87: 3 | E87: 65 | F87: 33717088269 | G87: =IFERROR(IF('Jun-22'!$F87="","-",VLOOKUP('Jun-22'!$F87,Lista_CUIT!$A$1:$D$1871,2,0)),"CUIT NO CARGADO") -> NEXT SERVICE GNC S.R.L. | H87: 1312890 | I87: 18036.9 | J87: 128835 | L87: =SUM('Jun-22'!$H87:$K87) -> 1459761.9
B88: 44734 | C88: 1 | D88: 3 | E88: 67 | F88: 30628274327 | G88: =IFERROR(IF('Jun-22'!$F88="","-",VLOOKUP('Jun-22'!$F88,Lista_CUIT!$A$1:$D$1871,2,0)),"CUIT NO CARGADO") -> AGIRA SA | H88: 1107219 | J88: 116257.99 | L88: =SUM('Jun-22'!$H88:$K88) -> 1223477
G89: =IFERROR(IF('Jun-22'!$F89="","-",VLOOKUP('Jun-22'!$F89,Lista_CUIT!$A$1:$D$1871,2,0)),"CUIT NO CARGADO") -> - | I89: ='Jun-22'!$H89*0.21 -> 0 | L89: =SUM('Jun-22'!$H89:$K89) -> 0
G90: =IFERROR(IF('Jun-22'!$F90="","-",VLOOKUP('Jun-22'!$F90,Lista_CUIT!$A$1:$D$1871,2,0)),"CUIT NO CARGADO") -> - | I90: ='Jun-22'!$H90*0.21 -> 0 | L90: =SUM('Jun-22'!$H90:$K90) -> 0
G91: =IFERROR(IF('Jun-22'!$F91="","-",VLOOKUP('Jun-22'!$F91,Lista_CUIT!$A$1:$D$1871,2,0)),"CUIT NO CARGADO") -> - | I91: ='Jun-22'!$H91*0.21 -> 0 | L91: =SUM('Jun-22'!$H91:$K91) -> 0
G92: =IFERROR(IF('Jun-22'!$F92="","-",VLOOKUP('Jun-22'!$F92,Lista_CUIT!$A$1:$D$1871,2,0)),"CUIT NO CARGADO") -> - | I92: ='Jun-22'!$H92*0.21 -> 0 | L92: =SUM('Jun-22'!$H92:$K92) -> 0
B93: Total | H93: =SUBTOTAL(109,'Jun-22'!$H$84:$H$92) -> 2789657.3 | I93: =SUBTOTAL(109,'Jun-22'!$I$84:$I$92) -> 95642.043 | J93: =SUBTOTAL(109,'Jun-22'!$J$84:$J$92) -> 245092.99 | K93: =SUBTOTAL(109,'Jun-22'!$K$84:$K$92) -> 0 | L93: =SUBTOTAL(109,'Jun-22'!$L$84:$L$92) -> 3130392.3 | M93: =SUBTOTAL(103,'Jun-22'!$M$84:$M$92) -> 0
B96: VENTAS "B"
B97: FECHA | C97: TIPO | D97: PTO VENTA | E97: Nº FACTURA | F97: CUIT | G97: RAZON SOCIAL | H97: IMPORTE NETO | I97: IVA 21% | J97: IVA 10,5% | K97: EXENTO | L97: TOTAL | M97: Provincia
G98: =IFERROR(IF('Jun-22'!$F98="","-",VLOOKUP('Jun-22'!$F98,Lista_CUIT!$A$1:$D$1871,2,0)),"CUIT NO CARGADO") -> - | I98: ='Jun-22'!$H98*0.21 -> 0 | L98: =SUM('Jun-22'!$H98:$K98) -> 0
G99: =IFERROR(IF('Jun-22'!$F99="","-",VLOOKUP('Jun-22'!$F99,Lista_CUIT!$A$1:$D$1871,2,0)),"CUIT NO CARGADO") -> - | I99: ='Jun-22'!$H99*0.21 -> 0 | L99: =SUM('Jun-22'!$H99:$K99) -> 0
G100: =IFERROR(IF('Jun-22'!$F100="","-",VLOOKUP('Jun-22'!$F100,Lista_CUIT!$A$1:$D$1871,2,0)),"CUIT NO CARGADO") -> - | I100: ='Jun-22'!$H100*0.21 -> 0 | L100: =SUM('Jun-22'!$H100:$K100) -> 0
I101: ='Jun-22'!$H101*0.21 -> 0 | L101: =SUM('Jun-22'!$H101:$K101) -> 0
I102: ='Jun-22'!$H102*0.21 -> 0 | L102: =SUM('Jun-22'!$H102:$K102) -> 0
I103: ='Jun-22'!$H103*0.21 -> 0 | L103: =SUM('Jun-22'!$H103:$K103) -> 0
B104: Total | H104: =SUBTOTAL(109,'Jun-22'!$H$98:$H$103) -> 0 | I104: =SUBTOTAL(109,'Jun-22'!$I$98:$I$103) -> 0 | J104: =SUBTOTAL(109,'Jun-22'!$J$98:$J$103) -> 0 | K104: =SUBTOTAL(109,'Jun-22'!$K$98:$K$103) -> 0 | L104: =SUBTOTAL(109,'Jun-22'!$L$98:$L$103) -> 0 | M104: =SUBTOTAL(103,'Jun-22'!$M$98:$M$103) -> 0
C112: RETENCIONES
C113: FECHA | D113: COMP Nº | E113: Columna1 | F113: CUIT | G113: RAZON SOCIAL | H113: Ganancias | I113: IVA | J113: SUSS | K113: IIBB BSAS | L113: IIBB CABA
G114: =IFERROR(IF('Jun-22'!$F114="","-",VLOOKUP('Jun-22'!$F114,Lista_CUIT!$A$1:$D$1871,2,0)),"CUIT NO CARGADO") -> -
G115: =IFERROR(IF('Jun-22'!$F115="","-",VLOOKUP('Jun-22'!$F115,Lista_CUIT!$A$1:$D$1871,2,0)),"CUIT NO CARGADO") -> -
G116: =IFERROR(IF('Jun-22'!$F116="","-",VLOOKUP('Jun-22'!$F116,Lista_CUIT!$A$1:$D$1871,2,0)),"CUIT NO CARGADO") -> -
G117: =IFERROR(IF('Jun-22'!$F117="","-",VLOOKUP('Jun-22'!$F117,Lista_CUIT!$A$1:$D$1871,2,0)),"CUIT NO CARGADO") -> -
G118: =IFERROR(IF('Jun-22'!$F118="","-",VLOOKUP('Jun-22'!$F118,Lista_CUIT!$A$1:$D$1871,2,0)),"CUIT NO CARGADO") -> -

Sheet Jul-22
B1: LIBRO IVA COMPRAS | G1: ='Abr-22'!G1:M1 -> CORITEC S.R.L. | N1: =EDATE('Abr-22'!N1,3) -> 44743
B3: TOTAL COMPRAS | G3: TOTAL CREDITO FISCAL | J3: TOTAL VENTAS NETAS | M3: TOTAL DEBITO FISCAL | P3: RESULTADO
B4: =SUM('Jul-22'!$H$45)+'Jul-22'!$G$62 -> 1408952 | G4: ='Jul-22'!$I$45+'Jul-22'!$J$45+'Jul-22'!$K$45+'Jul-22'!$H$62+'Jul-22'!$I$62 -> 294269.69 | J4: ='Jul-22'!$H$114+'Jul-22'!$H$125 -> -961700.7 | M4: ='Jul-22'!$I$114+'Jul-22'!$J$114+'Jul-22'!$I$125+'Jul-22'!$J$125 -> -85699.152 | P4: =G4-M4 -> 379968.84
B8: FECHA | C8: TIPO | D8: PTO VTA | E8: NRO. CPTE | F8: CUIT | G8: RAZON SOCIAL | H8: NETO GRAVADO | I8: IVA 21 % | J8: IVA 27% | K8: IVA 10,5% | L8: PERC. IVA | M8: PERC IIBB BS AS | N8: PERC. IIBB CABA | O8: Otros / No Grav. | P8: TOTAL | Q8: Tipo de Gasto | R8: Provincia
B9: 44769 | C9: 1 | D9: 106 | E9: 547354 | F9: 30594494187 | G9: =IFERROR(IF('Jul-22'!$F9="","-",VLOOKUP('Jul-22'!$F9,Lista_CUIT!$A$1:$D$1871,2,0)),"CUIT NO CARGADO") -> FEDERAL EXPRESS CORPORATION | H9: 8160 | I9: =IF('Jul-22'!$H9="","",'Jul-22'!$H9*0.21) -> 1713.6 | O9: 14380.38 | P9: =SUM('Jul-22'!$H9:$O9) -> 24253.98 | Q9: =IFERROR(IF('Jul-22'!$F9="","-",VLOOKUP('Jul-22'!$F9,Lista_CUIT!$A$1:$D$1871,3,0)),"CUIT NO CARGADO") -> GTOS IMP. | R9: =IFERROR(IF('Jul-22'!$F9="","-",VLOOKUP('Jul-22'!$F9,Lista_CUIT!$A$1:$D$1871,4,0)),"CUIT NO CARGADO") -> 0
B10: 44769 | C10: 1 | D10: 700 | E10: 405289 | F10: 30580111315 | G10: =IFERROR(IF('Jul-22'!$F10="","-",VLOOKUP('Jul-22'!$F10,Lista_CUIT!$A$1:$D$1871,2,0)),"CUIT NO CARGADO") -> DHL EXPRESS ARG SA | H10: 1839.2381 | I10: =IF('Jul-22'!$H10="","",'Jul-22'!$H10*0.21) -> 386.24 | O10: 15790.96 | P10: =SUM('Jul-22'!$H10:$O10) -> 18016.438 | Q10: =IFERROR(IF('Jul-22'!$F10="","-",VLOOKUP('Jul-22'!$F10,Lista_CUIT!$A$1:$D$1871,3,0)),"CUIT NO CARGADO") -> GTOS IMP. | R10: =IFERROR(IF('Jul-22'!$F10="","-",VLOOKUP('Jul-22'!$F10,Lista_CUIT!$A$1:$D$1871,4,0)),"CUIT NO CARGADO") -> 0
B11: 44768 | C11: 1 | D11: 106 | E11: 546945 | F11: 30594494187 | G11: =IFERROR(IF('Jul-22'!$F11="","-",VLOOKUP('Jul-22'!$F11,Lista_CUIT!$A$1:$D$1871,2,0)),"CUIT NO CARGADO") -> FEDERAL EXPRESS CORPORATION | H11: 6528 | I11: =IF('Jul-22'!$H11="","",'Jul-22'!$H11*0.21) -> 1370.88 | O11: 4464.37 | P11: =SUM('Jul-22'!$H11:$O11) -> 12363.25 | Q11: =IFERROR(IF('Jul-22'!$F11="","-",VLOOKUP('Jul-22'!$F11,Lista_CUIT!$A$1:$D$1871,3,0)),"CUIT NO CARGADO") -> GTOS IMP. | R11: =IFERROR(IF('Jul-22'!$F11="","-",VLOOKUP('Jul-22'!$F11,Lista_CUIT!$A$1:$D$1871,4,0)),"CUIT NO CARGADO") -> 0
B12: 44765 | C12: 1 | D12: 280 | E12: 1379638 | F12: 30580111315 | G12: =IFERROR(IF('Jul-22'!$F12="","-",VLOOKUP('Jul-22'!$F12,Lista_CUIT!$A$1:$D$1871,2,0)),"CUIT NO CARGADO") -> DHL EXPRESS ARG SA | H12: 138562.32 | I12: =IF('Jul-22'!$H12="","",'Jul-22'!$H12*0.21) -> 29098.087 | O12: -113168.31 | P12: =SUM('Jul-22'!$H12:$O12) -> 54492.097 | Q12: =IFERROR(IF('Jul-22'!$F12="","-",VLOOKUP('Jul-22'!$F12,Lista_CUIT!$A$1:$D$1871,3,0)),"CUIT NO CARGADO") -> GTOS IMP. | R12: =IFERROR(IF('Jul-22'!$F12="","-",VLOOKUP('Jul-22'!$F12,Lista_CUIT!$A$1:$D$1871,4,0)),"CUIT NO CARGADO") -> 0
B13: 44764 | C13: 1 | D13: 106 | E13: 546462 | F13: 30594494187 | G13: =IFERROR(IF('Jul-22'!$F13="","-",VLOOKUP('Jul-22'!$F13,Lista_CUIT!$A$1:$D$1871,2,0)),"CUIT NO CARGADO") -> FEDERAL EXPRESS CORPORATION | H13: 6516 | I13: =IF('Jul-22'!$H13="","",'Jul-22'!$H13*0.21) -> 1368.36 | O13: 4456.42 | P13: =SUM('Jul-22'!$H13:$O13) -> 12340.78 | Q13: =IFERROR(IF('Jul-22'!$F13="","-",VLOOKUP('Jul-22'!$F13,Lista_CUIT!$A$1:$D$1871,3,0)),"CUIT NO CARGADO") -> GTOS IMP. | R13: =IFERROR(IF('Jul-22'!$F13="","-",VLOOKUP('Jul-22'!$F13,Lista_CUIT!$A$1:$D$1871,4,0)),"CUIT NO CARGADO") -> 0
B14: 44771 | C14: 1 | D14: 1 | E14: 2057 | F14: 30716872463 | G14: =IFERROR(IF('Jul-22'!$F14="","-",VLOOKUP('Jul-22'!$F14,Lista_CUIT!$A$1:$D$1871,2,0)),"CUIT NO CARGADO") -> COMERCIAL MGM SRL | H14: 15477.69 | I14: =IF('Jul-22'!$H14="","",'Jul-22'!$H14*0.21) -> 3250.3149 | P14: =SUM('Jul-22'!$H14:$O14) -> 18728.005 | Q14: =IFERROR(IF('Jul-22'!$F14="","-",VLOOKUP('Jul-22'!$F14,Lista_CUIT!$A$1:$D$1871,3,0)),"CUIT NO CARGADO") -> Gastos Varios | R14: =IFERROR(IF('Jul-22'!$F14="","-",VLOOKUP('Jul-22'!$F14,Lista_CUIT!$A$1:$D$1871,4,0)),"CUIT NO CARGADO") -> 0
B15: 44770 | C15: 1 | D15: 7 | E15: 26104 | F15: 30715267450 | G15: =IFERROR(IF('Jul-22'!$F15="","-",VLOOKUP('Jul-22'!$F15,Lista_CUIT!$A$1:$D$1871,2,0)),"CUIT NO CARGADO") -> ARCHMAR SRL | H15: 5247.71 | I15: 190.56 | K15: 455.73 | P15: =SUM('Jul-22'!$H15:$O15) -> 5894 | Q15: =IFERROR(IF('Jul-22'!$F15="","-",VLOOKUP('Jul-22'!$F15,Lista_CUIT!$A$1:$D$1871,3,0)),"CUIT NO CARGADO") -> Gastos Varios | R15: =IFERROR(IF('Jul-22'!$F15="","-",VLOOKUP('Jul-22'!$F15,Lista_CUIT!$A$1:$D$1871,4,0)),"CUIT NO CARGADO") -> 0
B16: 44771 | C16: 1 | D16: 7002 | E16: 5382 | F16: 30678774495 | G16: =IFERROR(IF('Jul-22'!$F16="","-",VLOOKUP('Jul-22'!$F16,Lista_CUIT!$A$1:$D$1871,2,0)),"CUIT NO CARGADO") -> OPER. DE EST. DE SERV. SA | H16: 3465.06 | I16: =IF('Jul-22'!$H16="","",'Jul-22'!$H16*0.21) -> 727.6626 | O16: 807.29 | P16: =SUM('Jul-22'!$H16:$O16) -> 5000.0126 | Q16: =IFERROR(IF('Jul-22'!$F16="","-",VLOOKUP('Jul-22'!$F16,Lista_CUIT!$A$1:$D$1871,3,0)),"CUIT NO CARGADO") -> COMBUSTIBLE | R16: =IFERROR(IF('Jul-22'!$F16="","-",VLOOKUP('Jul-22'!$F16,Lista_CUIT!$A$1:$D$1871,4,0)),"CUIT NO CARGADO") -> 0
B17: 44771 | C17: 1 | D17: 2 | E17: 2164 | F17: 30709131733 | G17: =IFERROR(IF('Jul-22'!$F17="","-",VLOOKUP('Jul-22'!$F17,Lista_CUIT!$A$1:$D$1871,2,0)),"CUIT NO CARGADO") -> DIGAS SRL | H17: 346556.26 | I17: =IF('Jul-22'!$H17="","",'Jul-22'!$H17*0.21) -> 72776.815 | P17: =SUM('Jul-22'!$H17:$O17) -> 419333.07 | Q17: =IFERROR(IF('Jul-22'!$F17="","-",VLOOKUP('Jul-22'!$F17,Lista_CUIT!$A$1:$D$1871,3,0)),"CUIT NO CARGADO") -> INSUMO | R17: =IFERROR(IF('Jul-22'!$F17="","-",VLOOKUP('Jul-22'!$F17,Lista_CUIT!$A$1:$D$1871,4,0)),"CUIT NO CARGADO") -> 0
B18: 44740 | C18: 1 | D18: 4 | E18: 39923 | F18: 30679067431 | G18: =IFERROR(IF('Jul-22'!$F18="","-",VLOOKUP('Jul-22'!$F18,Lista_CUIT!$A$1:$D$1871,2,0)),"CUIT NO CARGADO") -> LIBRERÍA PELUFFO SRL | H18: 2181.81 | I18: =IF('Jul-22'!$H18="","",'Jul-22'!$H18*0.21) -> 458.1801 | P18: =SUM('Jul-22'!$H18:$O18) -> 2639.9901 | Q18: =IFERROR(IF('Jul-22'!$F18="","-",VLOOKUP('Jul-22'!$F18,Lista_CUIT!$A$1:$D$1871,3,0)),"CUIT NO CARGADO") -> INSUMO | R18: =IFERROR(IF('Jul-22'!$F18="","-",VLOOKUP('Jul-22'!$F18,Lista_CUIT!$A$1:$D$1871,4,0)),"CUIT NO CARGADO") -> 0
B19: 44762 | C19: 1 | D19: 2 | E19: 142 | F19: 20125142851 | G19: =IFERROR(IF('Jul-22'!$F19="","-",VLOOKUP('Jul-22'!$F19,Lista_CUIT!$A$1:$D$1871,2,0)),"CUIT NO CARGADO") -> FEDERICI NICOLAS JOSE | H19: 5984 | I19: =IF('Jul-22'!$H19="","",'Jul-22'!$H19*0.21) -> 1256.64 | P19: =SUM('Jul-22'!$H19:$O19) -> 7240.64 | Q19: =IFERROR(IF('Jul-22'!$F19="","-",VLOOKUP('Jul-22'!$F19,Lista_CUIT!$A$1:$D$1871,3,0)),"CUIT NO CARGADO") -> INSUMO | R19: =IFERROR(IF('Jul-22'!$F19="","-",VLOOKUP('Jul-22'!$F19,Lista_CUIT!$A$1:$D$1871,4,0)),"CUIT NO CARGADO") -> 0
B20: 44762 | C20: 1 | D20: 2 | E20: 140 | F20: 20125142851 | G20: =IFERROR(IF('Jul-22'!$F20="","-",VLOOKUP('Jul-22'!$F20,Lista_CUIT!$A$1:$D$1871,2,0)),"CUIT NO CARGADO") -> FEDERICI NICOLAS JOSE | H20: 19717.2 | I20: =IF('Jul-22'!$H20="","",'Jul-22'!$H20*0.21) -> 4140.612 | P20: =SUM('Jul-22'!$H20:$O20) -> 23857.812 | Q20: =IFERROR(IF('Jul-22'!$F20="","-",VLOOKUP('Jul-22'!$F20,Lista_CUIT!$A$1:$D$1871,3,0)),"CUIT NO CARGADO") -> INSUMO | R20: =IFERROR(IF('Jul-22'!$F20="","-",VLOOKUP('Jul-22'!$F20,Lista_CUIT!$A$1:$D$1871,4,0)),"CUIT NO CARGADO") -> 0
B21: 44762 | C21: 1 | D21: 2 | E21: 141 | F21: 20125142851 | G21: =IFERROR(IF('Jul-22'!$F21="","-",VLOOKUP('Jul-22'!$F21,Lista_CUIT!$A$1:$D$1871,2,0)),"CUIT NO CARGADO") -> FEDERICI NICOLAS JOSE | H21: 37209.6 | I21: =IF('Jul-22'!$H21="","",'Jul-22'!$H21*0.21) -> 7814.016 | P21: =SUM('Jul-22'!$H21:$O21) -> 45023.616 | Q21: =IFERROR(IF('Jul-22'!$F21="","-",VLOOKUP('Jul-22'!$F21,Lista_CUIT!$A$1:$D$1871,3,0)),"CUIT NO CARGADO") -> INSUMO | R21: =IFERROR(IF('Jul-22'!$F21="","-",VLOOKUP('Jul-22'!$F21,Lista_CUIT!$A$1:$D$1871,4,0)),"CUIT NO CARGADO") -> 0
B22: 44763 | C22: 1 | D22: 3 | E22: 1 | F22: 20297899830 | G22: =IFERROR(IF('Jul-22'!$F22="","-",VLOOKUP('Jul-22'!$F22,Lista_CUIT!$A$1:$D$1871,2,0)),"CUIT NO CARGADO") -> FUNK MATIAS NICOLAS | H22: 55000 | I22: =IF('Jul-22'!$H22="","",'Jul-22'!$H22*0.21) -> 11550 | P22: =SUM('Jul-22'!$H22:$O22) -> 66550 | Q22: =IFERROR(IF('Jul-22'!$F22="","-",VLOOKUP('Jul-22'!$F22,Lista_CUIT!$A$1:$D$1871,3,0)),"CUIT NO CARGADO") -> Servicios Torneria | R22: =IFERROR(IF('Jul-22'!$F22="","-",VLOOKUP('Jul-22'!$F22,Lista_CUIT!$A$1:$D$1871,4,0)),"CUIT NO CARGADO") -> 0
B23: 44761 | C23: 1 | D23: 6 | E23: 14572 | F23: 30538456876 | G23: =IFERROR(IF('Jul-22'!$F23="","-",VLOOKUP('Jul-22'!$F23,Lista_CUIT!$A$1:$D$1871,2,0)),"CUIT NO CARGADO") -> RIO DE JANEIRO SA | H23: 5997.67 | I23: =IF('Jul-22'!$H23="","",'Jul-22'!$H23*0.21) -> 1259.5107 | O23: 643.52 | P23: =SUM('Jul-22'!$H23:$O23) -> 7900.7007 | Q23: =IFERROR(IF('Jul-22'!$F23="","-",VLOOKUP('Jul-22'!$F23,Lista_CUIT!$A$1:$D$1871,3,0)),"CUIT NO CARGADO") -> COMBUSTIBLE | R23: =IFERROR(IF('Jul-22'!$F23="","-",VLOOKUP('Jul-22'!$F23,Lista_CUIT!$A$1:$D$1871,4,0)),"CUIT NO CARGADO") -> 0
B24: 44757 | C24: 1 | D24: 5 | E24: 5817 | F24: 30715357255 | G24: =IFERROR(IF('Jul-22'!$F24="","-",VLOOKUP('Jul-22'!$F24,Lista_CUIT!$A$1:$D$1871,2,0)),"CUIT NO CARGADO") -> LIBECOM SRL | H24: 1584.56 | I24: 78.1 | K24: 127.33 | P24: =SUM('Jul-22'!$H24:$O24) -> 1789.99 | Q24: =IFERROR(IF('Jul-22'!$F24="","-",VLOOKUP('Jul-22'!$F24,Lista_CUIT!$A$1:$D$1871,3,0)),"CUIT NO CARGADO") -> Gastos Oficina | R24: =IFERROR(IF('Jul-22'!$F24="","-",VLOOKUP('Jul-22'!$F24,Lista_CUIT!$A$1:$D$1871,4,0)),"CUIT NO CARGADO") -> 0
B25: 44749 | C25: 1 | D25: 4 | E25: 12472 | F25: 30709362875 | G25: =IFERROR(IF('Jul-22'!$F25="","-",VLOOKUP('Jul-22'!$F25,Lista_CUIT!$A$1:$D$1871,2,0)),"CUIT NO CARGADO") -> ELINDAR SRL | H25: 4845.07 | I25: =IF('Jul-22'!$H25="","",'Jul-22'!$H25*0.21) -> 1017.4647 | P25: =SUM('Jul-22'!$H25:$O25) -> 5862.5347 | Q25: =IFERROR(IF('Jul-22'!$F25="","-",VLOOKUP('Jul-22'!$F25,Lista_CUIT!$A$1:$D$1871,3,0)),"CUIT NO CARGADO") -> INSUMO | R25: =IFERROR(IF('Jul-22'!$F25="","-",VLOOKUP('Jul-22'!$F25,Lista_CUIT!$A$1:$D$1871,4,0)),"CUIT NO CARGADO") -> 0
B26: 44743 | C26: 1 | D26: 3 | E26: 550 | F26: 30715402765 | G26: =IFERROR(IF('Jul-22'!$F26="","-",VLOOKUP('Jul-22'!$F26,Lista_CUIT!$A$1:$D$1871,2,0)),"CUIT NO CARGADO") -> RIO 265 SRL | H26: 7768.6 | I26: =IF('Jul-22'!$H26="","",'Jul-22'!$H26*0.21) -> 1631.406 | P26: =SUM('Jul-22'!$H26:$O26) -> 9400.006 | Q26: =IFERROR(IF('Jul-22'!$F26="","-",VLOOKUP('Jul-22'!$F26,Lista_CUIT!$A$1:$D$1871,3,0)),"CUIT NO CARGADO") -> GTOS VARIOS-ESTACIONAMIENTO HORACIO | R26: =IFERROR(IF('Jul-22'!$F26="","-",VLOOKUP('Jul-22'!$F26,Lista_CUIT!$A$1:$D$1871,4,0)),"CUIT NO CARGADO") -> 0
B27: 44743 | C27: 1 | D27: 3 | E27: 161635 | F27: 30707135596 | G27: =IFERROR(IF('Jul-22'!$F27="","-",VLOOKUP('Jul-22'!$F27,Lista_CUIT!$A$1:$D$1871,2,0)),"CUIT NO CARGADO") -> CITILAN ARGENTINA SA | H27: 3133.28 | I27: =IF('Jul-22'!$H27="","",'Jul-22'!$H27*0.21) -> 657.9888 | P27: =SUM('Jul-22'!$H27:$O27) -> 3791.2688 | Q27: =IFERROR(IF('Jul-22'!$F27="","-",VLOOKUP('Jul-22'!$F27,Lista_CUIT!$A$1:$D$1871,3,0)),"CUIT NO CARGADO") -> SERVICIOS GAS, LUZ, ETC | R27: =IFERROR(IF('Jul-22'!$F27="","-",VLOOKUP('Jul-22'!$F27,Lista_CUIT!$A$1:$D$1871,4,0)),"CUIT NO CARGADO") -> 0
B28: 44747 | C28: 1 | D28: 2 | E28: 517 | F28: 20296550184 | G28: =IFERROR(IF('Jul-22'!$F28="","-",VLOOKUP('Jul-22'!$F28,Lista_CUIT!$A$1:$D$1871,2,0)),"CUIT NO CARGADO") -> COSTA DIEGO ALEJANDRO | H28: 132001.5 | I28: =IF('Jul-22'!$H28="","",'Jul-22'!$H28*0.21) -> 27720.315 | P28: =SUM('Jul-22'!$H28:$O28) -> 159721.82 | Q28: =IFERROR(IF('Jul-22'!$F28="","-",VLOOKUP('Jul-22'!$F28,Lista_CUIT!$A$1:$D$1871,3,0)),"CUIT NO CARGADO") -> MAT. PRIM. | R28: =IFERROR(IF('Jul-22'!$F28="","-",VLOOKUP('Jul-22'!$F28,Lista_CUIT!$A$1:$D$1871,4,0)),"CUIT NO CARGADO") -> 0
B29: 44746 | C29: 1 | D29: 1 | E29: 1508 | F29: 20299039367 | G29: =IFERROR(IF('Jul-22'!$F29="","-",VLOOKUP('Jul-22'!$F29,Lista_CUIT!$A$1:$D$1871,2,0)),"CUIT NO CARGADO") -> ALBERTO IVAN SIRTAUTAS | H29: 1758.68 | I29: =IF('Jul-22'!$H29="","",'Jul-22'!$H29*0.21) -> 369.3228 | P29: =SUM('Jul-22'!$H29:$O29) -> 2128.0028 | Q29: =IFERROR(IF('Jul-22'!$F29="","-",VLOOKUP('Jul-22'!$F29,Lista_CUIT!$A$1:$D$1871,3,0)),"CUIT NO CARGADO") -> Gastos Varios | R29: =IFERROR(IF('Jul-22'!$F29="","-",VLOOKUP('Jul-22'!$F29,Lista_CUIT!$A$1:$D$1871,4,0)),"CUIT NO CARGADO") -> 0
B30: 44745 | C30: 1 | D30: 1 | E30: 362 | F30: 30716807084 | G30: =IFERROR(IF('Jul-22'!$F30="","-",VLOOKUP('Jul-22'!$F30,Lista_CUIT!$A$1:$D$1871,2,0)),"CUIT NO CARGADO") -> MEVAVE SAS | H30: 1704.99 | I30: 42.95 | K30: 157.55 | P30: =SUM('Jul-22'!$H30:$O30) -> 1905.49 | Q30: =IFERROR(IF('Jul-22'!$F30="","-",VLOOKUP('Jul-22'!$F30,Lista_CUIT!$A$1:$D$1871,3,0)),"CUIT NO CARGADO") -> Gastos Oficina | R30: =IFERROR(IF('Jul-22'!$F30="","-",VLOOKUP('Jul-22'!$F30,Lista_CUIT!$A$1:$D$1871,4,0)),"CUIT NO CARGADO") -> 0
B31: 44748 | C31: 1 | D31: 6 | E31: 622 | F31: 30714971782 | G31: =IFERROR(IF('Jul-22'!$F31="","-",VLOOKUP('Jul-22'!$F31,Lista_CUIT!$A$1:$D$1871,2,0)),"CUIT NO CARGADO") -> PINTOS SHMIDT ALDANA MARCELA Y SACK ADRIANA CRISTINA SH | H31: 4925.62 | I31: =IF('Jul-22'!$H31="","",'Jul-22'!$H31*0.21) -> 1034.3802 | P31: =SUM('Jul-22'!$H31:$O31) -> 5960.0002 | Q31: =IFERROR(IF('Jul-22'!$F31="","-",VLOOKUP('Jul-22'!$F31,Lista_CUIT!$A$1:$D$1871,3,0)),"CUIT NO CARGADO") -> INSUMO | R31: =IFERROR(IF('Jul-22'!$F31="","-",VLOOKUP('Jul-22'!$F31,Lista_CUIT!$A$1:$D$1871,4,0)),"CUIT NO CARGADO") -> 0
B32: 44744 | C32: 1 | D32: 3 | E32: 741 | F32: 30716146509 | G32: =IFERROR(IF('Jul-22'!$F32="","-",VLOOKUP('Jul-22'!$F32,Lista_CUIT!$A$1:$D$1871,2,0)),"CUIT NO CARGADO") -> ONLINE MARKET SRL | H32: 1338.1 | I32: =IF('Jul-22'!$H32="","",'Jul-22'!$H32*0.21) -> 281.001 | P32: =SUM('Jul-22'!$H32:$O32) -> 1619.101 | Q32: =IFERROR(IF('Jul-22'!$F32="","-",VLOOKUP('Jul-22'!$F32,Lista_CUIT!$A$1:$D$1871,3,0)),"CUIT NO CARGADO") -> Gastos Oficina | R32: =IFERROR(IF('Jul-22'!$F32="","-",VLOOKUP('Jul-22'!$F32,Lista_CUIT!$A$1:$D$1871,4,0)),"CUIT NO CARGADO") -> 0
B33: 44747 | C33: 1 | D33: 3 | E33: 669 | F33: 30716328178 | G33: =IFERROR(IF('Jul-22'!$F33="","-",VLOOKUP('Jul-22'!$F33,Lista_CUIT!$A$1:$D$1871,2,0)),"CUIT NO CARGADO") -> AJAVISION SAS | H33: 2586.21 | I33: =IF('Jul-22'!$H33="","",'Jul-22'!$H33*0.21) -> 543.1041 | P33: =SUM('Jul-22'!$H33:$O33) -> 3129.3141 | Q33: =IFERROR(IF('Jul-22'!$F33="","-",VLOOKUP('Jul-22'!$F33,Lista_CUIT!$A$1:$D$1871,3,0)),"CUIT NO CARGADO") -> Servicios Informatica | R33: =IFERROR(IF('Jul-22'!$F33="","-",VLOOKUP('Jul-22'!$F33,Lista_CUIT!$A$1:$D$1871,4,0)),"CUIT NO CARGADO") -> 0
B34: 44746 | C34: 1 | D34: 8 | E34: 65151 | F34: 30586172308 | G34: =IFERROR(IF('Jul-22'!$F34="","-",VLOOKUP('Jul-22'!$F34,Lista_CUIT!$A$1:$D$1871,2,0)),"CUIT NO CARGADO") -> SANTA FE COMERCIAL SRL | H34: 413.22 | I34: =IF('Jul-22'!$H34="","",'Jul-22'!$H34*0.21) -> 86.7762 | P34: =SUM('Jul-22'!$H34:$O34) -> 499.9962 | Q34: =IFERROR(IF('Jul-22'!$F34="","-",VLOOKUP('Jul-22'!$F34,Lista_CUIT!$A$1:$D$1871,3,0)),"CUIT NO CARGADO") -> Gastos Varios | R34: =IFERROR(IF('Jul-22'!$F34="","-",VLOOKUP('Jul-22'!$F34,Lista_CUIT!$A$1:$D$1871,4,0)),"CUIT NO CARGADO") -> 0
B35: 44753 | C35: 1 | D35: 2466 | E35: 383725 | F35: 30678814357 | G35: =IFERROR(IF('Jul-22'!$F35="","-",VLOOKUP('Jul-22'!$F35,Lista_CUIT!$A$1:$D$1871,2,0)),"CUIT NO CARGADO") -> Telefonica Moviles Argentina SA | H35: 1987 | J35: 536.49 | O35: 104.58 | P35: =SUM('Jul-22'!$H35:$O35) -> 2628.07 | Q35: =IFERROR(IF('Jul-22'!$F35="","-",VLOOKUP('Jul-22'!$F35,Lista_CUIT!$A$1:$D$1871,3,0)),"CUIT NO CARGADO") -> SERVICIOS GAS, LUZ, ETC | R35: =IFERROR(IF('Jul-22'!$F35="","-",VLOOKUP('Jul-22'!$F35,Lista_CUIT!$A$1:$D$1871,4,0)),"CUIT NO CARGADO") -> 0
B36: 44754 | C36: 1 | D36: 14 | E36: 98 | F36: 30711849587 | G36: =IFERROR(IF('Jul-22'!$F36="","-",VLOOKUP('Jul-22'!$F36,Lista_CUIT!$A$1:$D$1871,2,0)),"CUIT NO CARGADO") -> CORPORACION SAN JUSTO SA | H36: 11487.6 | I36: =IF('Jul-22'!$H36="","",'Jul-22'!$H36*0.21) -> 2412.396 | P36: =SUM('Jul-22'!$H36:$O36) -> 13899.996 | Q36: =IFERROR(IF('Jul-22'!$F36="","-",VLOOKUP('Jul-22'!$F36,Lista_CUIT!$A$1:$D$1871,3,0)),"CUIT NO CARGADO") -> Gastos Varios | R36: =IFERROR(IF('Jul-22'!$F36="","-",VLOOKUP('Jul-22'!$F36,Lista_CUIT!$A$1:$D$1871,4,0)),"CUIT NO CARGADO") -> 0
B37: 44765 | C37: 1 | D37: 122 | E37: 248172 | F37: 30594494187 | G37: =IFERROR(IF('Jul-22'!$F37="","-",VLOOKUP('Jul-22'!$F37,Lista_CUIT!$A$1:$D$1871,2,0)),"CUIT NO CARGADO") -> FEDERAL EXPRESS CORPORATION | H37: 7784.4 | I37: =IF('Jul-22'!$H37="","",'Jul-22'!$H37*0.21) -> 1634.724 | O37: 14380.38 | P37: =SUM('Jul-22'!$H37:$O37) -> 23799.504 | Q37: =IFERROR(IF('Jul-22'!$F37="","-",VLOOKUP('Jul-22'!$F37,Lista_CUIT!$A$1:$D$1871,3,0)),"CUIT NO CARGADO") -> GTOS IMP. | R37: =IFERROR(IF('Jul-22'!$F37="","-",VLOOKUP('Jul-22'!$F37,Lista_CUIT!$A$1:$D$1871,4,0)),"CUIT NO CARGADO") -> 0
B38: 44769 | C38: 1 | D38: 3 | E38: 985936 | F38: 30712019359 | G38: =IFERROR(IF('Jul-22'!$F38="","-",VLOOKUP('Jul-22'!$F38,Lista_CUIT!$A$1:$D$1871,2,0)),"CUIT NO CARGADO") -> LINKEDSTORE ARGENTINA S.R.L. | H38: 2478.51 | I38: =IF('Jul-22'!$H38="","",'Jul-22'!$H38*0.21) -> 520.4871 | P38: =SUM('Jul-22'!$H38:$O38) -> 2998.9971 | Q38: =IFERROR(IF('Jul-22'!$F38="","-",VLOOKUP('Jul-22'!$F38,Lista_CUIT!$A$1:$D$1871,3,0)),"CUIT NO CARGADO") -> Gastos Varios | R38: =IFERROR(IF('Jul-22'!$F38="","-",VLOOKUP('Jul-22'!$F38,Lista_CUIT!$A$1:$D$1871,4,0)),"CUIT NO CARGADO") -> 0
B39: 44770 | C39: 1 | D39: 9 | E39: 46850 | F39: 33715571639 | G39: =IFERROR(IF('Jul-22'!$F39="","-",VLOOKUP('Jul-22'!$F39,Lista_CUIT!$A$1:$D$1871,2,0)),"CUIT NO CARGADO") -> DUAITEK SRL | H39: 701.64 | I39: =IF('Jul-22'!$H39="","",'Jul-22'!$H39*0.21) -> 147.3444 | P39: =SUM('Jul-22'!$H39:$O39) -> 848.9844 | Q39: =IFERROR(IF('Jul-22'!$F39="","-",VLOOKUP('Jul-22'!$F39,Lista_CUIT!$A$1:$D$1871,3,0)),"CUIT NO CARGADO") -> Gastos Varios | R39: =IFERROR(IF('Jul-22'!$F39="","-",VLOOKUP('Jul-22'!$F39,Lista_CUIT!$A$1:$D$1871,4,0)),"CUIT NO CARGADO") -> 0
B40: 44771 | C40: 1 | D40: 3 | E40: 5735 | F40: 20141343700 | G40: =IFERROR(IF('Jul-22'!$F40="","-",VLOOKUP('Jul-22'!$F40,Lista_CUIT!$A$1:$D$1871,2,0)),"CUIT NO CARGADO") -> Roberto A Caffaro | H40: 9417.5 | K40: 988.8375 | P40: =SUM('Jul-22'!$H40:$O40) -> 10406.337 | Q40: =IFERROR(IF('Jul-22'!$F40="","-",VLOOKUP('Jul-22'!$F40,Lista_CUIT!$A$1:$D$1871,3,0)),"CUIT NO CARGADO") -> MAT. PRIM. | R40: =IFERROR(IF('Jul-22'!$F40="","-",VLOOKUP('Jul-22'!$F40,Lista_CUIT!$A$1:$D$1871,4,0)),"CUIT NO CARGADO") -> 0
B41: 44762 | C41: 3 | D41: 1 | E41: 25 | F41: 30715048066 | G41: =IFERROR(IF('Jul-22'!$F41="","-",VLOOKUP('Jul-22'!$F41,Lista_CUIT!$A$1:$D$1871,2,0)),"CUIT NO CARGADO") -> ROLLS Y EMPANADAS SA | H41: -81105 | I41: =IF('Jul-22'!$H41="","",'Jul-22'!$H41*0.21) -> -17032.05 | P41: =SUM('Jul-22'!$H41:$O41) -> -98137.05 | Q41: =IFERROR(IF('Jul-22'!$F41="","-",VLOOKUP('Jul-22'!$F41,Lista_CUIT!$A$1:$D$1871,3,0)),"CUIT NO CARGADO") -> CATERING | R41: =IFERROR(IF('Jul-22'!$F41="","-",VLOOKUP('Jul-22'!$F41,Lista_CUIT!$A$1:$D$1871,4,0)),"CUIT NO CARGADO") -> 0
B42: 44767 | C42: 3 | D42: 122 | E42: 39607 | F42: 30594494187 | G42: =IFERROR(IF('Jul-22'!$F42="","-",VLOOKUP('Jul-22'!$F42,Lista_CUIT!$A$1:$D$1871,2,0)),"CUIT NO CARGADO") -> FEDERAL EXPRESS CORPORATION | H42: -7784.4 | I42: =IF('Jul-22'!$H42="","",'Jul-22'!$H42*0.21) -> -1634.724 | O42: -14380.38 | P42: =SUM('Jul-22'!$H42:$O42) -> -23799.504 | Q42: =IFERROR(IF('Jul-22'!$F42="","-",VLOOKUP('Jul-22'!$F42,Lista_CUIT!$A$1:$D$1871,3,0)),"CUIT NO CARGADO") -> GTOS IMP. | R42: =IFERROR(IF('Jul-22'!$F42="","-",VLOOKUP('Jul-22'!$F42,Lista_CUIT!$A$1:$D$1871,4,0)),"CUIT NO CARGADO") -> 0
B43: 44771 | C43: 1 | D43: 1 | E43: 484 | F43: 30715048066 | G43: =IFERROR(IF('Jul-22'!$F43="","-",VLOOKUP('Jul-22'!$F43,Lista_CUIT!$A$1:$D$1871,2,0)),"CUIT NO CARGADO") -> ROLLS Y EMPANADAS SA | H43: 105405 | I43: =IF('Jul-22'!$H43="","",'Jul-22'!$H43*0.21) -> 22135.05 | P43: =SUM('Jul-22'!$H43:$O43) -> 127540.05 | Q43: =IFERROR(IF('Jul-22'!$F43="","-",VLOOKUP('Jul-22'!$F43,Lista_CUIT!$A$1:$D$1871,3,0)),"CUIT NO CARGADO") -> CATERING | R43: =IFERROR(IF('Jul-22'!$F43="","-",VLOOKUP('Jul-22'!$F43,Lista_CUIT!$A$1:$D$1871,4,0)),"CUIT NO CARGADO") -> 0
B44: 44771 | C44: 1 | D44: 5 | E44: 697 | F44: 30707397256 | G44: =IFERROR(IF('Jul-22'!$F44="","-",VLOOKUP('Jul-22'!$F44,Lista_CUIT!$A$1:$D$1871,2,0)),"CUIT NO CARGADO") -> GRAFICA Y FOTOGRABADOS LA PLAZA SRL | H44: 519889.5 | I44: =IF('Jul-22'!$H44="","",'Jul-22'!$H44*0.21) -> 109176.79 | P44: =SUM('Jul-22'!$H44:$O44) -> 629066.3 | Q44: =IFERROR(IF('Jul-22'!$F44="","-",VLOOKUP('Jul-22'!$F44,Lista_CUIT!$A$1:$D$1871,3,0)),"CUIT NO CARGADO") -> Fotograbados | R44: =IFERROR(IF('Jul-22'!$F44="","-",VLOOKUP('Jul-22'!$F44,Lista_CUIT!$A$1:$D$1871,4,0)),"CUIT NO CARGADO") -> 0
B45: Total | H45: =SUBTOTAL(109,'Jul-22'!$H$9:$H$44) -> 1390764.1 | I45: =SUBTOTAL(109,'Jul-22'!$I$9:$I$44) -> 288184.31 | J45: =SUBTOTAL(109,'Jul-22'!$J$9:$J$44) -> 536.49 | K45: =SUBTOTAL(109,'Jul-22'!$K$9:$K$44) -> 1729.4475 | L45: =SUBTOTAL(109,'Jul-22'!$L$9:$L$44) -> 0 | M45: =SUBTOTAL(109,'Jul-22'!$M$9:$M$44) -> 0 | N45: =SUBTOTAL(109,'Jul-22'!$N$9:$N$44) -> 0 | O45: =SUBTOTAL(109,'Jul-22'!$O$9:$O$44) -> -72520.79 | P45: =SUBTOTAL(109,'Jul-22'!$P$9:$P$44) -> 1608693.6
D50: LIQUIDACION EXTRACTOS BANCARIOS-TARJETAS
D51: FECHA | E51: NRO CPTE | F51: BANCO | G51: NETO | H51: IVA 21% | I51: IVA 10,5% | J51: RET IIBB CABA | K51: PERC IVA | L51: PERC IIBB
F52: BANCO CREDICOOP | G52: 3706.381 | H52: 778.34
D53: 44743 | E53: 617-484161 | F53: Liq. C.i. vista (mostrador) | G53: 14401.45 | H53: 3024.3045 | K53: 432.04
F54: Liq.Registracion | H54: 0
F55: Liq. Pagos Anticipados | H55: 0
F56: Liq. MSD | H56: 0
F57: Anticipos- Fin ext | H57: 0
F58: Liq. Pagos Anticipados | H58: 0
F59: Cobro Exportacion | H59: 0
F60: VISA CREDITO | G60: 80 | H60: 16.8 | J60: 1.78
F61: AMEX
D62: Total | G62: =SUBTOTAL(109,'Jul-22'!$G$52:$G$61) -> 18187.831 | H62: =SUBTOTAL(109,'Jul-22'!$H$52:$H$61) -> 3819.4445 | I62: =SUBTOTAL(109,'Jul-22'!$I$52:$I$61) -> 0 | J62: =SUBTOTAL(109,'Jul-22'!$J$52:$J$61) -> 1.78 | K62: =SUBTOTAL(109,'Jul-22'!$K$52:$K$61) -> 432.04 | L62: =SUBTOTAL(109,'Jul-22'!$L$52:$L$61) -> 0
D65: FACTURAS C
D66: FECHA | E66: PTO VTA | F66: FC Nº | G66: CUIT | H66: RAZON SOCIAL | I66: TOTAL | J66: TIPO DE GASTO | K66: Provincia
D67: 44773 | E67: 2 | F67: 114 | G67: 20136544625 | H67: =IFERROR(IF('Jul-22'!$G67="","-",VLOOKUP('Jul-22'!$G67,Lista_CUIT!$A$1:$D$1871,2,0)),"CUIT NO CARGADO") -> RODRIGUEZ DE LA FUEN HECTOR MARCELO | I67: 170000 | J67: =IFERROR(IF('Jul-22'!$G67="","-",VLOOKUP('Jul-22'!$G67,Lista_CUIT!$A$1:$D$1871,3,0)),"CUIT NO CARGADO") -> Honorarios Administrativos-Cobranzas y Gestion Clientes | K67: =IFERROR(IF('Jul-22'!$G67="","-",VLOOKUP('Jul-22'!$G67,Lista_CUIT!$A$1:$D$1871,4,0)),"CUIT NO CARGADO") -> 0
D68: 44773 | E68: 2 | F68: 4 | G68: 20136544625 | H68: =IFERROR(IF('Jul-22'!$G68="","-",VLOOKUP('Jul-22'!$G68,Lista_CUIT!$A$1:$D$1871,2,0)),"CUIT NO CARGADO") -> RODRIGUEZ DE LA FUEN HECTOR MARCELO | I68: -200000 | J68: =IFERROR(IF('Jul-22'!$G68="","-",VLOOKUP('Jul-22'!$G68,Lista_CUIT!$A$1:$D$1871,3,0)),"CUIT NO CARGADO") -> Honorarios Administrativos-Cobranzas y Gestion Clientes | K68: =IFERROR(IF('Jul-22'!$G68="","-",VLOOKUP('Jul-22'!$G68,Lista_CUIT!$A$1:$D$1871,4,0)),"CUIT NO CARGADO") -> 0
D69: 44773 | E69: 2 | F69: 113 | G69: 20136544625 | H69: =IFERROR(IF('Jul-22'!$G69="","-",VLOOKUP('Jul-22'!$G69,Lista_CUIT!$A$1:$D$1871,2,0)),"CUIT NO CARGADO") -> RODRIGUEZ DE LA FUEN HECTOR MARCELO | I69: 200000 | J69: =IFERROR(IF('Jul-22'!$G69="","-",VLOOKUP('Jul-22'!$G69,Lista_CUIT!$A$1:$D$1871,3,0)),"CUIT NO CARGADO") -> Honorarios Administrativos-Cobranzas y Gestion Clientes | K69: =IFERROR(IF('Jul-22'!$G69="","-",VLOOKUP('Jul-22'!$G69,Lista_CUIT!$A$1:$D$1871,4,0)),"CUIT NO CARGADO") -> 0
D70: 44769 | E70: 6 | F70: 578 | G70: 20200310412 | H70: =IFERROR(IF('Jul-22'!$G70="","-",VLOOKUP('Jul-22'!$G70,Lista_CUIT!$A$1:$D$1871,2,0)),"CUIT NO CARGADO") -> TAMURA ROBERTO | I70: 3042 | J70: =IFERROR(IF('Jul-22'!$G70="","-",VLOOKUP('Jul-22'!$G70,Lista_CUIT!$A$1:$D$1871,3,0)),"CUIT NO CARGADO") -> Gastos Oficina | K70: =IFERROR(IF('Jul-22'!$G70="","-",VLOOKUP('Jul-22'!$G70,Lista_CUIT!$A$1:$D$1871,4,0)),"CUIT NO CARGADO") -> 0
D71: 44767 | E71: 1 | F71: 14 | G71: 20365938688 | H71: =IFERROR(IF('Jul-22'!$G71="","-",VLOOKUP('Jul-22'!$G71,Lista_CUIT!$A$1:$D$1871,2,0)),"CUIT NO CARGADO") -> LIPANOVICH JUAN CRUZ | I71: 330000 | J71: =IFERROR(IF('Jul-22'!$G71="","-",VLOOKUP('Jul-22'!$G71,Lista_CUIT!$A$1:$D$1871,3,0)),"CUIT NO CARGADO") -> Servicios Informatica | K71: =IFERROR(IF('Jul-22'!$G71="","-",VLOOKUP('Jul-22'!$G71,Lista_CUIT!$A$1:$D$1871,4,0)),"CUIT NO CARGADO") -> 0
D72: 44747 | E72: 1 | F72: 86 | G72: 20341465134 | H72: =IFERROR(IF('Jul-22'!$G72="","-",VLOOKUP('Jul-22'!$G72,Lista_CUIT!$A$1:$D$1871,2,0)),"CUIT NO CARGADO") -> ABELEDO AGUSTIN ENRIQUE | I72: 122600 | J72: =IFERROR(IF('Jul-22'!$G72="","-",VLOOKUP('Jul-22'!$G72,Lista_CUIT!$A$1:$D$1871,3,0)),"CUIT NO CARGADO") -> HONOR. INGENIERO | K72: =IFERROR(IF('Jul-22'!$G72="","-",VLOOKUP('Jul-22'!$G72,Lista_CUIT!$A$1:$D$1871,4,0)),"CUIT NO CARGADO") -> 0
D73: 44756 | E73: 3 | F73: 593 | G73: 20086277523 | H73: =IFERROR(IF('Jul-22'!$G73="","-",VLOOKUP('Jul-22'!$G73,Lista_CUIT!$A$1:$D$1871,2,0)),"CUIT NO CARGADO") -> JUAN CARLOS BOTINDARI | I73: 8350 | J73: =IFERROR(IF('Jul-22'!$G73="","-",VLOOKUP('Jul-22'!$G73,Lista_CUIT!$A$1:$D$1871,3,0)),"CUIT NO CARGADO") -> HONORARIOS | K73: =IFERROR(IF('Jul-22'!$G73="","-",VLOOKUP('Jul-22'!$G73,Lista_CUIT!$A$1:$D$1871,4,0)),"CUIT NO CARGADO") -> 0
D74: 44767 | E74: 1 | F74: 6 | G74: 27925308884 | H74: =IFERROR(IF('Jul-22'!$G74="","-",VLOOKUP('Jul-22'!$G74,Lista_CUIT!$A$1:$D$1871,2,0)),"CUIT NO CARGADO") -> LOPEZ LOPEZ FLAVIA | I74: 3000 | J74: =IFERROR(IF('Jul-22'!$G74="","-",VLOOKUP('Jul-22'!$G74,Lista_CUIT!$A$1:$D$1871,3,0)),"CUIT NO CARGADO") -> FLETE | K74: =IFERROR(IF('Jul-22'!$G74="","-",VLOOKUP('Jul-22'!$G74,Lista_CUIT!$A$1:$D$1871,4,0)),"CUIT NO CARGADO") -> 0
D75: 44749 | E75: 1 | F75: 8 | G75: 20417805878 | H75: =IFERROR(IF('Jul-22'!$G75="","-",VLOOKUP('Jul-22'!$G75,Lista_CUIT!$A$1:$D$1871,2,0)),"CUIT NO CARGADO") -> FERABOLI OSPAL SANTIAGO HERNAN | I75: 104720 | J75: =IFERROR(IF('Jul-22'!$G75="","-",VLOOKUP('Jul-22'!$G75,Lista_CUIT!$A$1:$D$1871,3,0)),"CUIT NO CARGADO") -> Control medidores masicos | K75: =IFERROR(IF('Jul-22'!$G75="","-",VLOOKUP('Jul-22'!$G75,Lista_CUIT!$A$1:$D$1871,4,0)),"CUIT NO CARGADO") -> 0
D76: 44747 | E76: 3 | F76: 28 | G76: 20403931420 | H76: =IFERROR(IF('Jul-22'!$G76="","-",VLOOKUP('Jul-22'!$G76,Lista_CUIT!$A$1:$D$1871,2,0)),"CUIT NO CARGADO") -> FIORENTINO JORGE IGNACIO | I76: 104130 | J76: =IFERROR(IF('Jul-22'!$G76="","-",VLOOKUP('Jul-22'!$G76,Lista_CUIT!$A$1:$D$1871,3,0)),"CUIT NO CARGADO") -> Honorarios Administrativos-Cobranzas y Gestion Clientes | K76: =IFERROR(IF('Jul-22'!$G76="","-",VLOOKUP('Jul-22'!$G76,Lista_CUIT!$A$1:$D$1871,4,0)),"CUIT NO CARGADO") -> 0
D77: 44746 | E77: 2 | F77: 12 | G77: 23326777269 | H77: =IFERROR(IF('Jul-22'!$G77="","-",VLOOKUP('Jul-22'!$G77,Lista_CUIT!$A$1:$D$1871,2,0)),"CUIT NO CARGADO") -> DE BONIS IGNACIO LUIS | I77: 90730 | J77: =IFERROR(IF('Jul-22'!$G77="","-",VLOOKUP('Jul-22'!$G77,Lista_CUIT!$A$1:$D$1871,3,0)),"CUIT NO CARGADO") -> Control medidores masicos | K77: =IFERROR(IF('Jul-22'!$G77="","-",VLOOKUP('Jul-22'!$G77,Lista_CUIT!$A$1:$D$1871,4,0)),"CUIT NO CARGADO") -> 0
D78: 44748 | E78: 2 | F78: 843 | G78: 20260499085 | H78: =IFERROR(IF('Jul-22'!$G78="","-",VLOOKUP('Jul-22'!$G78,Lista_CUIT!$A$1:$D$1871,2,0)),"CUIT NO CARGADO") -> SABELLI ARIEL OSCAR | I78: 8000 | J78: =IFERROR(IF('Jul-22'!$G78="","-",VLOOKUP('Jul-22'!$G78,Lista_CUIT!$A$1:$D$1871,3,0)),"CUIT NO CARGADO") -> TAXI | K78: =IFERROR(IF('Jul-22'!$G78="","-",VLOOKUP('Jul-22'!$G78,Lista_CUIT!$A$1:$D$1871,4,0)),"CUIT NO CARGADO") -> 0
D79: 44747 | E79: 2 | F79: 70 | G79: 20220423655 | H79: =IFERROR(IF('Jul-22'!$G79="","-",VLOOKUP('Jul-22'!$G79,Lista_CUIT!$A$1:$D$1871,2,0)),"CUIT NO CARGADO") -> LANDRO FERNANDO GABRIEL | I79: 99485 | J79: =IFERROR(IF('Jul-22'!$G79="","-",VLOOKUP('Jul-22'!$G79,Lista_CUIT!$A$1:$D$1871,3,0)),"CUIT NO CARGADO") -> 0 | K79: =IFERROR(IF('Jul-22'!$G79="","-",VLOOKUP('Jul-22'!$G79,Lista_CUIT!$A$1:$D$1871,4,0)),"CUIT NO CARGADO") -> 0
D80: 44747 | E80: 2 | F80: 82 | G80: 27125997835 | H80: =IFERROR(IF('Jul-22'!$G80="","-",VLOOKUP('Jul-22'!$G80,Lista_CUIT!$A$1:$D$1871,2,0)),"CUIT NO CARGADO") -> DANSKY ULLMANN VIVIANA EVA YOLANDA | I80: 66000 | J80: =IFERROR(IF('Jul-22'!$G80="","-",VLOOKUP('Jul-22'!$G80,Lista_CUIT!$A$1:$D$1871,3,0)),"CUIT NO CARGADO") -> Honorarios Legales | K80: =IFERROR(IF('Jul-22'!$G80="","-",VLOOKUP('Jul-22'!$G80,Lista_CUIT!$A$1:$D$1871,4,0)),"CUIT NO CARGADO") -> 0 | M80: Servicios Juridicos?
D81: 44756 | E81: 1 | F81: 4 | G81: 27925308884 | H81: =IFERROR(IF('Jul-22'!$G81="","-",VLOOKUP('Jul-22'!$G81,Lista_CUIT!$A$1:$D$1871,2,0)),"CUIT NO CARGADO") -> LOPEZ LOPEZ FLAVIA | I81: 8500 | J81: =IFERROR(IF('Jul-22'!$G81="","-",VLOOKUP('Jul-22'!$G81,Lista_CUIT!$A$1:$D$1871,3,0)),"CUIT NO CARGADO") -> FLETE | K81: =IFERROR(IF('Jul-22'!$G81="","-",VLOOKUP('Jul-22'!$G81,Lista_CUIT!$A$1:$D$1871,4,0)),"CUIT NO CARGADO") -> 0
D82: 44746 | E82: 3 | F82: 588 | G82: 20086277523 | H82: =IFERROR(IF('Jul-22'!$G82="","-",VLOOKUP('Jul-22'!$G82,Lista_CUIT!$A$1:$D$1871,2,0)),"CUIT NO CARGADO") -> JUAN CARLOS BOTINDARI | I82: 51900 | J82: =IFERROR(IF('Jul-22'!$G82="","-",VLOOKUP('Jul-22'!$G82,Lista_CUIT!$A$1:$D$1871,3,0)),"CUIT NO CARGADO") -> HONORARIOS | K82: =IFERROR(IF('Jul-22'!$G82="","-",VLOOKUP('Jul-22'!$G82,Lista_CUIT!$A$1:$D$1871,4,0)),"CUIT NO CARGADO") -> 0
D83: 44756 | E83: 3 | F83: 596 | G83: 20086277523 | H83: =IFERROR(IF('Jul-22'!$G83="","-",VLOOKUP('Jul-22'!$G83,Lista_CUIT!$A$1:$D$1871,2,0)),"CUIT NO CARGADO") -> JUAN CARLOS BOTINDARI | I83: 57500 | J83: =IFERROR(IF('Jul-22'!$G83="","-",VLOOKUP('Jul-22'!$G83,Lista_CUIT!$A$1:$D$1871,3,0)),"CUIT NO CARGADO") -> HONORARIOS | K83: =IFERROR(IF('Jul-22'!$G83="","-",VLOOKUP('Jul-22'!$G83,Lista_CUIT!$A$1:$D$1871,4,0)),"CUIT NO CARGADO") -> 0
D84: 44756 | E84: 2 | F84: 206 | G84: 27206941419 | H84: =IFERROR(IF('Jul-22'!$G84="","-",VLOOKUP('Jul-22'!$G84,Lista_CUIT!$A$1:$D$1871,2,0)),"CUIT NO CARGADO") -> DOBARRO PAULA MARCELA | I84: 57500 | J84: =IFERROR(IF('Jul-22'!$G84="","-",VLOOKUP('Jul-22'!$G84,Lista_CUIT!$A$1:$D$1871,3,0)),"CUIT NO CARGADO") -> HONORARIOS CONTABLES | K84: =IFERROR(IF('Jul-22'!$G84="","-",VLOOKUP('Jul-22'!$G84,Lista_CUIT!$A$1:$D$1871,4,0)),"CUIT NO CARGADO") -> 0
D85: 44761 | E85: 2 | F85: 554 | G85: 20320877947 | H85: =IFERROR(IF('Jul-22'!$G85="","-",VLOOKUP('Jul-22'!$G85,Lista_CUIT!$A$1:$D$1871,2,0)),"CUIT NO CARGADO") -> ROUSSEAU PABLO ANDRES | I85: 9800 | J85: =IFERROR(IF('Jul-22'!$G85="","-",VLOOKUP('Jul-22'!$G85,Lista_CUIT!$A$1:$D$1871,3,0)),"CUIT NO CARGADO") -> SERVICIO | K85: =IFERROR(IF('Jul-22'!$G85="","-",VLOOKUP('Jul-22'!$G85,Lista_CUIT!$A$1:$D$1871,4,0)),"CUIT NO CARGADO") -> 0
D86: 44753 | E86: 2 | F86: 3 | G86: 20220423655 | H86: =IFERROR(IF('Jul-22'!$G86="","-",VLOOKUP('Jul-22'!$G86,Lista_CUIT!$A$1:$D$1871,2,0)),"CUIT NO CARGADO") -> LANDRO FERNANDO GABRIEL | I86: -99485 | J86: =IFERROR(IF('Jul-22'!$G86="","-",VLOOKUP('Jul-22'!$G86,Lista_CUIT!$A$1:$D$1871,3,0)),"CUIT NO CARGADO") -> 0 | K86: =IFERROR(IF('Jul-22'!$G86="","-",VLOOKUP('Jul-22'!$G86,Lista_CUIT!$A$1:$D$1871,4,0)),"CUIT NO CARGADO") -> 0
D87: 44748 | E87: 4 | F87: 3 | G87: 20341462933 | H87: =IFERROR(IF('Jul-22'!$G87="","-",VLOOKUP('Jul-22'!$G87,Lista_CUIT!$A$1:$D$1871,2,0)),"CUIT NO CARGADO") -> CASTIGLIONI MATIAS EZEQUIEL | I87: 100000 | J87: =IFERROR(IF('Jul-22'!$G87="","-",VLOOKUP('Jul-22'!$G87,Lista_CUIT!$A$1:$D$1871,3,0)),"CUIT NO CARGADO") -> MAT. PRIM. | K87: =IFERROR(IF('Jul-22'!$G87="","-",VLOOKUP('Jul-22'!$G87,Lista_CUIT!$A$1:$D$1871,4,0)),"CUIT NO CARGADO") -> 0
D88: 44749 | E88: 2 | F88: 73 | G88: 20244271740 | H88: =IFERROR(IF('Jul-22'!$G88="","-",VLOOKUP('Jul-22'!$G88,Lista_CUIT!$A$1:$D$1871,2,0)),"CUIT NO CARGADO") -> KENNEL SEBASTIAN | I88: 167400 | J88: =IFERROR(IF('Jul-22'!$G88="","-",VLOOKUP('Jul-22'!$G88,Lista_CUIT!$A$1:$D$1871,3,0)),"CUIT NO CARGADO") -> SOFTWARE MANTENIMIENTO | K88: =IFERROR(IF('Jul-22'!$G88="","-",VLOOKUP('Jul-22'!$G88,Lista_CUIT!$A$1:$D$1871,4,0)),"CUIT NO CARGADO") -> 0
H89: =IFERROR(IF('Jul-22'!$G89="","-",VLOOKUP('Jul-22'!$G89,Lista_CUIT!$A$1:$D$1871,2,0)),"CUIT NO CARGADO") -> - | J89: =IFERROR(IF('Jul-22'!$G89="","-",VLOOKUP('Jul-22'!$G89,Lista_CUIT!$A$1:$D$1871,3,0)),"CUIT NO CARGADO") -> - | K89: =IFERROR(IF('Jul-22'!$G89="","-",VLOOKUP('Jul-22'!$G89,Lista_CUIT!$A$1:$D$1871,4,0)),"CUIT NO CARGADO") -> -
H90: =IFERROR(IF('Jul-22'!$G90="","-",VLOOKUP('Jul-22'!$G90,Lista_CUIT!$A$1:$D$1871,2,0)),"CUIT NO CARGADO") -> - | J90: =IFERROR(IF('Jul-22'!$G90="","-",VLOOKUP('Jul-22'!$G90,Lista_CUIT!$A$1:$D$1871,3,0)),"CUIT NO CARGADO") -> - | K90: =IFERROR(IF('Jul-22'!$G90="","-",VLOOKUP('Jul-22'!$G90,Lista_CUIT!$A$1:$D$1871,4,0)),"CUIT NO CARGADO") -> -
H91: =IFERROR(IF('Jul-22'!$G91="","-",VLOOKUP('Jul-22'!$G91,Lista_CUIT!$A$1:$D$1871,2,0)),"CUIT NO CARGADO") -> - | J91: =IFERROR(IF('Jul-22'!$G91="","-",VLOOKUP('Jul-22'!$G91,Lista_CUIT!$A$1:$D$1871,3,0)),"CUIT NO CARGADO") -> - | K91: =IFERROR(IF('Jul-22'!$G91="","-",VLOOKUP('Jul-22'!$G91,Lista_CUIT!$A$1:$D$1871,4,0)),"CUIT NO CARGADO") -> -
H92: =IFERROR(IF('Jul-22'!$G92="","-",VLOOKUP('Jul-22'!$G92,Lista_CUIT!$A$1:$D$1871,2,0)),"CUIT NO CARGADO") -> - | J92: =IFERROR(IF('Jul-22'!$G92="","-",VLOOKUP('Jul-22'!$G92,Lista_CUIT!$A$1:$D$1871,3,0)),"CUIT NO CARGADO") -> - | K92: =IFERROR(IF('Jul-22'!$G92="","-",VLOOKUP('Jul-22'!$G92,Lista_CUIT!$A$1:$D$1871,4,0)),"CUIT NO CARGADO") -> -
H93: =IFERROR(IF('Jul-22'!$G93="","-",VLOOKUP('Jul-22'!$G93,Lista_CUIT!$A$1:$D$1871,2,0)),"CUIT NO CARGADO") -> - | J93: =IFERROR(IF('Jul-22'!$G93="","-",VLOOKUP('Jul-22'!$G93,Lista_CUIT!$A$1:$D$1871,3,0)),"CUIT NO CARGADO") -> - | K93: =IFERROR(IF('Jul-22'!$G93="","-",VLOOKUP('Jul-22'!$G93,Lista_CUIT!$A$1:$D$1871,4,0)),"CUIT NO CARGADO") -> -
H94: =IFERROR(IF('Jul-22'!$G94="","-",VLOOKUP('Jul-22'!$G94,Lista_CUIT!$A$1:$D$1871,2,0)),"CUIT NO CARGADO") -> - | J94: =IFERROR(IF('Jul-22'!$G94="","-",VLOOKUP('Jul-22'!$G94,Lista_CUIT!$A$1:$D$1871,3,0)),"CUIT NO CARGADO") -> - | K94: =IFERROR(IF('Jul-22'!$G94="","-",VLOOKUP('Jul-22'!$G94,Lista_CUIT!$A$1:$D$1871,4,0)),"CUIT NO CARGADO") -> -
H95: =IFERROR(IF('Jul-22'!$G95="","-",VLOOKUP('Jul-22'!$G95,Lista_CUIT!$A$1:$D$1871,2,0)),"CUIT NO CARGADO") -> - | J95: =IFERROR(IF('Jul-22'!$G95="","-",VLOOKUP('Jul-22'!$G95,Lista_CUIT!$A$1:$D$1871,3,0)),"CUIT NO CARGADO") -> - | K95: =IFERROR(IF('Jul-22'!$G95="","-",VLOOKUP('Jul-22'!$G95,Lista_CUIT!$A$1:$D$1871,4,0)),"CUIT NO CARGADO") -> -
H96: =IFERROR(IF('Jul-22'!$G96="","-",VLOOKUP('Jul-22'!$G96,Lista_CUIT!$A$1:$D$1871,2,0)),"CUIT NO CARGADO") -> - | J96: =IFERROR(IF('Jul-22'!$G96="","-",VLOOKUP('Jul-22'!$G96,Lista_CUIT!$A$1:$D$1871,3,0)),"CUIT NO CARGADO") -> - | K96: =IFERROR(IF('Jul-22'!$G96="","-",VLOOKUP('Jul-22'!$G96,Lista_CUIT!$A$1:$D$1871,4,0)),"CUIT NO CARGADO") -> -
H97: =IFERROR(IF('Jul-22'!$G97="","-",VLOOKUP('Jul-22'!$G97,Lista_CUIT!$A$1:$D$1871,2,0)),"CUIT NO CARGADO") -> - | J97: =IFERROR(IF('Jul-22'!$G97="","-",VLOOKUP('Jul-22'!$G97,Lista_CUIT!$A$1:$D$1871,3,0)),"CUIT NO CARGADO") -> - | K97: =IFERROR(IF('Jul-22'!$G97="","-",VLOOKUP('Jul-22'!$G97,Lista_CUIT!$A$1:$D$1871,4,0)),"CUIT NO CARGADO") -> -
H98: =IFERROR(IF('Jul-22'!$G98="","-",VLOOKUP('Jul-22'!$G98,Lista_CUIT!$A$1:$D$1871,2,0)),"CUIT NO CARGADO") -> - | J98: =IFERROR(IF('Jul-22'!$G98="","-",VLOOKUP('Jul-22'!$G98,Lista_CUIT!$A$1:$D$1871,3,0)),"CUIT NO CARGADO") -> - | K98: =IFERROR(IF('Jul-22'!$G98="","-",VLOOKUP('Jul-22'!$G98,Lista_CUIT!$A$1:$D$1871,4,0)),"CUIT NO CARGADO") -> -
D99: Total | I99: =SUBTOTAL(109,'Jul-22'!$I$67:$I$98) -> 1463172
B105: LIBRO IVA VENTAS | K105: =N1 -> 44743
B107: VENTAS "A"
B108: FECHA | C108: TIPO | D108: PTO VENTA | E108: Nº FACTURA | F108: CUIT | G108: RAZON SOCIAL | H108: IMPORTE NETO | I108: IVA 21% | J108: IVA 10,5% | K108: EXENTO | L108: TOTAL | M108: Provincia
B109: 44754 | C109: 1 | D109: 3 | E109: 68 | F109: 30710473710 | G109: =IFERROR(IF('Jul-22'!$F109="","-",VLOOKUP('Jul-22'!$F109,Lista_CUIT!$A$1:$D$1871,2,0)),"CUIT NO CARGADO") -> POWER TEKNIC S.A. | H109: 210127.5 | I109: ='Jul-22'!$H109*0.21 -> 44126.775 | L109: =SUM('Jul-22'!$H109:$K109) -> 254254.27
B110: 44754 | C110: 1 | D110: 3 | E110: 69 | F110: 30710473710 | G110: =IFERROR(IF('Jul-22'!$F110="","-",VLOOKUP('Jul-22'!$F110,Lista_CUIT!$A$1:$D$1871,2,0)),"CUIT NO CARGADO") -> POWER TEKNIC S.A. | H110: 133717.5 | I110: ='Jul-22'!$H110*0.21 -> 28080.675 | L110: =SUM('Jul-22'!$H110:$K110) -> 161798.17
B111: 44754 | C111: 3 | D111: 3 | E111: 12 | F111: 30710473710 | G111: =IFERROR(IF('Jul-22'!$F111="","-",VLOOKUP('Jul-22'!$F111,Lista_CUIT!$A$1:$D$1871,2,0)),"CUIT NO CARGADO") -> POWER TEKNIC S.A. | H111: -210127.5 | I111: ='Jul-22'!$H111*0.21 -> -44126.775 | L111: =SUM('Jul-22'!$H111:$K111) -> -254254.27
B112: 44762 | C112: 3 | D112: 3 | E112: 13 | F112: 30628274327 | G112: =IFERROR(IF('Jul-22'!$F112="","-",VLOOKUP('Jul-22'!$F112,Lista_CUIT!$A$1:$D$1871,2,0)),"CUIT NO CARGADO") -> AGIRA SA | H112: -1107219 | J112: -116257.99 | L112: =SUM('Jul-22'!$H112:$K112) -> -1223477
B113: 44770 | C113: 1 | D113: 3 | E113: 70 | F113: 30574668715 | G113: =IFERROR(IF('Jul-22'!$F113="","-",VLOOKUP('Jul-22'!$F113,Lista_CUIT!$A$1:$D$1871,2,0)),"CUIT NO CARGADO") -> ESTACION DE SERVICIOS LAURENCENA S R L | H113: 11800.8 | I113: ='Jul-22'!$H113*0.21 -> 2478.168 | L113: =SUM('Jul-22'!$H113:$K113) -> 14278.968
B114: Total | H114: =SUBTOTAL(109,'Jul-22'!$H$109:$H$113) -> -961700.7 | I114: =SUBTOTAL(109,'Jul-22'!$I$109:$I$113) -> 30558.843 | J114: =SUBTOTAL(109,'Jul-22'!$J$109:$J$113) -> -116257.99 | K114: =SUBTOTAL(109,'Jul-22'!$K$109:$K$113) -> 0 | L114: =SUBTOTAL(109,'Jul-22'!$L$109:$L$113) -> -1047399.9 | M114: =SUBTOTAL(103,'Jul-22'!$M$109:$M$113) -> 0
B117: VENTAS "B"
B118: FECHA | C118: TIPO | D118: PTO VENTA | E118: Nº FACTURA | F118: CUIT | G118: RAZON SOCIAL | H118: IMPORTE NETO | I118: IVA 21% | J118: IVA 10,5% | K118: EXENTO | L118: TOTAL | M118: Provincia
...

Sheet Ago-22
B1: LIBRO IVA COMPRAS | G1: ='Abr-22'!G1:M1 -> CORITEC S.R.L. | N1: =EDATE('Abr-22'!N1,4) -> 44774
B3: TOTAL COMPRAS | G3: TOTAL CREDITO FISCAL | J3: TOTAL VENTAS NETAS | M3: TOTAL DEBITO FISCAL | P3: RESULTADO
B4: =SUM('Ago-22'!$H$50)+'Ago-22'!$G$63 -> 5675678.4 | G4: ='Ago-22'!$I$50+'Ago-22'!$J$50+'Ago-22'!$K$50+'Ago-22'!$H$63+'Ago-22'!$I$63 -> 1120010.3 | J4: ='Ago-22'!$H$101+'Ago-22'!$H$112 -> 13720993 | M4: ='Ago-22'!$I$101+'Ago-22'!$J$101+'Ago-22'!$I$112+'Ago-22'!$J$112 -> 1567231.8 | P4: =G4-M4 -> -447221.48
B8: FECHA | C8: TIPO | D8: PTO VTA | E8: NRO. CPTE | F8: CUIT | G8: RAZON SOCIAL | H8: NETO GRAVADO | I8: IVA 21 % | J8: IVA 27% | K8: IVA 10,5% | L8: PERC. IVA | M8: PERC IIBB BS AS | N8: PERC. IIBB CABA | O8: Otros / No Grav. | P8: TOTAL | Q8: Tipo de Gasto | R8: Provincia
B9: 44792 | C9: 1 | D9: 106 | E9: 555670 | F9: 30594494187 | G9: =IFERROR(IF('Ago-22'!$F9="","-",VLOOKUP('Ago-22'!$F9,Lista_CUIT!$A$1:$D$1871,2,0)),"CUIT NO CARGADO") -> FEDERAL EXPRESS CORPORATION | H9: 14175 | I9: =IF('Ago-22'!$H9="","",'Ago-22'!$H9*0.21) -> 2976.75 | O9: 147823.92 | P9: =SUM('Ago-22'!$H9:$O9) -> 164975.67 | Q9: =IFERROR(IF('Ago-22'!$F9="","-",VLOOKUP('Ago-22'!$F9,Lista_CUIT!$A$1:$D$1871,3,0)),"CUIT NO CARGADO") -> GTOS IMP. | R9: =IFERROR(IF('Ago-22'!$F9="","-",VLOOKUP('Ago-22'!$F9,Lista_CUIT!$A$1:$D$1871,4,0)),"CUIT NO CARGADO") -> 0
B10: 44775 | C10: 1 | D10: 280 | E10: 1381451 | F10: 30580111315 | G10: =IFERROR(IF('Ago-22'!$F10="","-",VLOOKUP('Ago-22'!$F10,Lista_CUIT!$A$1:$D$1871,2,0)),"CUIT NO CARGADO") -> DHL EXPRESS ARG SA | H10: 439627.62 | I10: =IF('Ago-22'!$H10="","",'Ago-22'!$H10*0.21) -> 92321.8 | O10: -366109.49 | P10: =SUM('Ago-22'!$H10:$O10) -> 165839.92 | Q10: =IFERROR(IF('Ago-22'!$F10="","-",VLOOKUP('Ago-22'!$F10,Lista_CUIT!$A$1:$D$1871,3,0)),"CUIT NO CARGADO") -> GTOS IMP. | R10: =IFERROR(IF('Ago-22'!$F10="","-",VLOOKUP('Ago-22'!$F10,Lista_CUIT!$A$1:$D$1871,4,0)),"CUIT NO CARGADO") -> 0
B11: 44783 | C11: 1 | D11: 280 | E11: 1382909 | F11: 30580111315 | G11: =IFERROR(IF('Ago-22'!$F11="","-",VLOOKUP('Ago-22'!$F11,Lista_CUIT!$A$1:$D$1871,2,0)),"CUIT NO CARGADO") -> DHL EXPRESS ARG SA | H11: 418587.01 | I11: 841.49 | K11: 43530.463 | O11: -376890.46 | P11: =SUM('Ago-22'!$H11:$O11) -> 86068.5 | Q11: =IFERROR(IF('Ago-22'!$F11="","-",VLOOKUP('Ago-22'!$F11,Lista_CUIT!$A$1:$D$1871,3,0)),"CUIT NO CARGADO") -> GTOS IMP. | R11: =IFERROR(IF('Ago-22'!$F11="","-",VLOOKUP('Ago-22'!$F11,Lista_CUIT!$A$1:$D$1871,4,0)),"CUIT NO CARGADO") -> 0
B12: 44804 | C12: 1 | D12: 4 | E12: 18961 | F12: 33644560509 | G12: =IFERROR(IF('Ago-22'!$F12="","-",VLOOKUP('Ago-22'!$F12,Lista_CUIT!$A$1:$D$1871,2,0)),"CUIT NO CARGADO") -> ELECTRICIDAD BELTRAME SA | H12: 38192.95 | I12: =IF('Ago-22'!$H12="","",'Ago-22'!$H12*0.21) -> 8020.5195 | P12: =SUM('Ago-22'!$H12:$O12) -> 46213.469 | Q12: =IFERROR(IF('Ago-22'!$F12="","-",VLOOKUP('Ago-22'!$F12,Lista_CUIT!$A$1:$D$1871,3,0)),"CUIT NO CARGADO") -> INSUMO | R12: =IFERROR(IF('Ago-22'!$F12="","-",VLOOKUP('Ago-22'!$F12,Lista_CUIT!$A$1:$D$1871,4,0)),"CUIT NO CARGADO") -> 0
B13: 44803 | C13: 1 | D13: 8 | E13: 158254 | F13: 33606484599 | G13: =IFERROR(IF('Ago-22'!$F13="","-",VLOOKUP('Ago-22'!$F13,Lista_CUIT!$A$1:$D$1871,2,0)),"CUIT NO CARGADO") -> JORVICAL ACEROS SA | H13: 487342.97 | I13: =IF('Ago-22'!$H13="","",'Ago-22'!$H13*0.21) -> 102342.02 | P13: =SUM('Ago-22'!$H13:$O13) -> 589684.99 | Q13: =IFERROR(IF('Ago-22'!$F13="","-",VLOOKUP('Ago-22'!$F13,Lista_CUIT!$A$1:$D$1871,3,0)),"CUIT NO CARGADO") -> MAT. PRIM. | R13: =IFERROR(IF('Ago-22'!$F13="","-",VLOOKUP('Ago-22'!$F13,Lista_CUIT!$A$1:$D$1871,4,0)),"CUIT NO CARGADO") -> 0
B14: 44802 | C14: 1 | D14: 5 | E14: 49509 | F14: 30609968792 | G14: =IFERROR(IF('Ago-22'!$F14="","-",VLOOKUP('Ago-22'!$F14,Lista_CUIT!$A$1:$D$1871,2,0)),"CUIT NO CARGADO") -> ABAC SRL | H14: 465315.84 | I14: =IF('Ago-22'!$H14="","",'Ago-22'!$H14*0.21) -> 97716.326 | P14: =SUM('Ago-22'!$H14:$O14) -> 563032.17 | Q14: =IFERROR(IF('Ago-22'!$F14="","-",VLOOKUP('Ago-22'!$F14,Lista_CUIT!$A$1:$D$1871,3,0)),"CUIT NO CARGADO") -> MAT. PRIM. | R14: =IFERROR(IF('Ago-22'!$F14="","-",VLOOKUP('Ago-22'!$F14,Lista_CUIT!$A$1:$D$1871,4,0)),"CUIT NO CARGADO") -> 0
B15: 44799 | C15: 1 | D15: 2 | E15: 12097 | F15: 20103565309 | G15: =IFERROR(IF('Ago-22'!$F15="","-",VLOOKUP('Ago-22'!$F15,Lista_CUIT!$A$1:$D$1871,2,0)),"CUIT NO CARGADO") -> CASATI ENRIQUE ARIEL | H15: 33840 | I15: =IF('Ago-22'!$H15="","",'Ago-22'!$H15*0.21) -> 7106.4 | P15: =SUM('Ago-22'!$H15:$O15) -> 40946.4 | Q15: =IFERROR(IF('Ago-22'!$F15="","-",VLOOKUP('Ago-22'!$F15,Lista_CUIT!$A$1:$D$1871,3,0)),"CUIT NO CARGADO") -> Gastos Varios | R15: =IFERROR(IF('Ago-22'!$F15="","-",VLOOKUP('Ago-22'!$F15,Lista_CUIT!$A$1:$D$1871,4,0)),"CUIT NO CARGADO") -> 0
B16: 44791 | C16: 1 | D16: 2 | E16: 2188 | F16: 30709131733 | G16: =IFERROR(IF('Ago-22'!$F16="","-",VLOOKUP('Ago-22'!$F16,Lista_CUIT!$A$1:$D$1871,2,0)),"CUIT NO CARGADO") -> DIGAS SRL | H16: 358550 | I16: =IF('Ago-22'!$H16="","",'Ago-22'!$H16*0.21) -> 75295.5 | P16: =SUM('Ago-22'!$H16:$O16) -> 433845.5 | Q16: =IFERROR(IF('Ago-22'!$F16="","-",VLOOKUP('Ago-22'!$F16,Lista_CUIT!$A$1:$D$1871,3,0)),"CUIT NO CARGADO") -> INSUMO | R16: =IFERROR(IF('Ago-22'!$F16="","-",VLOOKUP('Ago-22'!$F16,Lista_CUIT!$A$1:$D$1871,4,0)),"CUIT NO CARGADO") -> 0
B17: 44791 | C17: 1 | D17: 2 | E17: 535 | F17: 20296550184 | G17: =IFERROR(IF('Ago-22'!$F17="","-",VLOOKUP('Ago-22'!$F17,Lista_CUIT!$A$1:$D$1871,2,0)),"CUIT NO CARGADO") -> COSTA DIEGO ALEJANDRO | H17: 16200 | I17: =IF('Ago-22'!$H17="","",'Ago-22'!$H17*0.21) -> 3402 | P17: =SUM('Ago-22'!$H17:$O17) -> 19602 | Q17: =IFERROR(IF('Ago-22'!$F17="","-",VLOOKUP('Ago-22'!$F17,Lista_CUIT!$A$1:$D$1871,3,0)),"CUIT NO CARGADO") -> MAT. PRIM. | R17: =IFERROR(IF('Ago-22'!$F17="","-",VLOOKUP('Ago-22'!$F17,Lista_CUIT!$A$1:$D$1871,4,0)),"CUIT NO CARGADO") -> 0
B18: 44795 | C18: 1 | D18: 700 | E18: 418162 | F18: 30580111315 | G18: =IFERROR(IF('Ago-22'!$F18="","-",VLOOKUP('Ago-22'!$F18,Lista_CUIT!$A$1:$D$1871,2,0)),"CUIT NO CARGADO") -> DHL EXPRESS ARG SA | I18: =IF('Ago-22'!$H18="","",'Ago-22'!$H18*0.21) | O18: 15762.722 | P18: =SUM('Ago-22'!$H18:$O18) -> 15762.722 | Q18: =IFERROR(IF('Ago-22'!$F18="","-",VLOOKUP('Ago-22'!$F18,Lista_CUIT!$A$1:$D$1871,3,0)),"CUIT NO CARGADO") -> GTOS IMP. | R18: =IFERROR(IF('Ago-22'!$F18="","-",VLOOKUP('Ago-22'!$F18,Lista_CUIT!$A$1:$D$1871,4,0)),"CUIT NO CARGADO") -> 0
B19: 44798 | C19: 1 | D19: 4 | E19: 12400 | F19: 30716701820 | G19: =IFERROR(IF('Ago-22'!$F19="","-",VLOOKUP('Ago-22'!$F19,Lista_CUIT!$A$1:$D$1871,2,0)),"CUIT NO CARGADO") -> MENTA GRANIZADA | H19: 211492.18 | K19: 22206.679 | P19: =SUM('Ago-22'!$H19:$O19) -> 233698.86 | Q19: =IFERROR(IF('Ago-22'!$F19="","-",VLOOKUP('Ago-22'!$F19,Lista_CUIT!$A$1:$D$1871,3,0)),"CUIT NO CARGADO") -> BIENES DE USO | R19: =IFERROR(IF('Ago-22'!$F19="","-",VLOOKUP('Ago-22'!$F19,Lista_CUIT!$A$1:$D$1871,4,0)),"CUIT NO CARGADO") -> 0
B20: 44792 | C20: 1 | D20: 3 | E20: 4 | F20: 20297899830 | G20: =IFERROR(IF('Ago-22'!$F20="","-",VLOOKUP('Ago-22'!$F20,Lista_CUIT!$A$1:$D$1871,2,0)),"CUIT NO CARGADO") -> FUNK MATIAS NICOLAS | H20: 266303.8 | I20: =IF('Ago-22'!$H20="","",'Ago-22'!$H20*0.21) -> 55923.798 | P20: =SUM('Ago-22'!$H20:$O20) -> 322227.6 | Q20: =IFERROR(IF('Ago-22'!$F20="","-",VLOOKUP('Ago-22'!$F20,Lista_CUIT!$A$1:$D$1871,3,0)),"CUIT NO CARGADO") -> Servicios Torneria | R20: =IFERROR(IF('Ago-22'!$F20="","-",VLOOKUP('Ago-22'!$F20,Lista_CUIT!$A$1:$D$1871,4,0)),"CUIT NO CARGADO") -> 0
B21: 44795 | C21: 1 | D21: 9 | E21: 1297 | F21: 30631047145 | G21: =IFERROR(IF('Ago-22'!$F21="","-",VLOOKUP('Ago-22'!$F21,Lista_CUIT!$A$1:$D$1871,2,0)),"CUIT NO CARGADO") -> SEMICONDUC. Y COMPON. SRL | H21: 57772 | I21: 9948.94 | K21: 1091.59 | P21: =SUM('Ago-22'!$H21:$O21) -> 68812.53 | Q21: =IFERROR(IF('Ago-22'!$F21="","-",VLOOKUP('Ago-22'!$F21,Lista_CUIT!$A$1:$D$1871,3,0)),"CUIT NO CARGADO") -> INSUMO | R21: =IFERROR(IF('Ago-22'!$F21="","-",VLOOKUP('Ago-22'!$F21,Lista_CUIT!$A$1:$D$1871,4,0)),"CUIT NO CARGADO") -> 0
B22: 44795 | C22: 1 | D22: 9 | E22: 1298 | F22: 30631047145 | G22: =IFERROR(IF('Ago-22'!$F22="","-",VLOOKUP('Ago-22'!$F22,Lista_CUIT!$A$1:$D$1871,2,0)),"CUIT NO CARGADO") -> SEMICONDUC. Y COMPON. SRL | H22: 7865 | I22: =IF('Ago-22'!$H22="","",'Ago-22'!$H22*0.21) -> 1651.65 | P22: =SUM('Ago-22'!$H22:$O22) -> 9516.65 | Q22: =IFERROR(IF('Ago-22'!$F22="","-",VLOOKUP('Ago-22'!$F22,Lista_CUIT!$A$1:$D$1871,3,0)),"CUIT NO CARGADO") -> INSUMO | R22: =IFERROR(IF('Ago-22'!$F22="","-",VLOOKUP('Ago-22'!$F22,Lista_CUIT!$A$1:$D$1871,4,0)),"CUIT NO CARGADO") -> 0
B23: 44791 | C23: 1 | D23: 4 | E23: 3155 | F23: 30714049123 | G23: =IFERROR(IF('Ago-22'!$F23="","-",VLOOKUP('Ago-22'!$F23,Lista_CUIT!$A$1:$D$1871,2,0)),"CUIT NO CARGADO") -> TECNOLOGIA EN SEMICONDUCTORES S | H23: 45364.71 | K23: 4763.2945 | P23: =SUM('Ago-22'!$H23:$O23) -> 50128.005 | Q23: =IFERROR(IF('Ago-22'!$F23="","-",VLOOKUP('Ago-22'!$F23,Lista_CUIT!$A$1:$D$1871,3,0)),"CUIT NO CARGADO") -> Gastos Oficina | R23: =IFERROR(IF('Ago-22'!$F23="","-",VLOOKUP('Ago-22'!$F23,Lista_CUIT!$A$1:$D$1871,4,0)),"CUIT NO CARGADO") -> 0
B24: 44790 | C24: 1 | D24: 4 | E24: 2129 | F24: 20289114212 | G24: =IFERROR(IF('Ago-22'!$F24="","-",VLOOKUP('Ago-22'!$F24,Lista_CUIT!$A$1:$D$1871,2,0)),"CUIT NO CARGADO") -> BADARACCO FRANCO ALEJANDRO ARIEL | H24: 5495.87 | I24: =IF('Ago-22'!$H24="","",'Ago-22'!$H24*0.21) -> 1154.1327 | P24: =SUM('Ago-22'!$H24:$O24) -> 6650.0027 | Q24: =IFERROR(IF('Ago-22'!$F24="","-",VLOOKUP('Ago-22'!$F24,Lista_CUIT!$A$1:$D$1871,3,0)),"CUIT NO CARGADO") -> Gastos Oficina | R24: =IFERROR(IF('Ago-22'!$F24="","-",VLOOKUP('Ago-22'!$F24,Lista_CUIT!$A$1:$D$1871,4,0)),"CUIT NO CARGADO") -> 0
B25: 44794 | C25: 1 | D25: 6992 | E25: 9165 | F25: 30678774495 | G25: =IFERROR(IF('Ago-22'!$F25="","-",VLOOKUP('Ago-22'!$F25,Lista_CUIT!$A$1:$D$1871,2,0)),"CUIT NO CARGADO") -> OPER. DE EST. DE SERV. SA | H25: 4790.88 | I25: =IF('Ago-22'!$H25="","",'Ago-22'!$H25*0.21) -> 1006.0848 | O25: 1003.74 | P25: =SUM('Ago-22'!$H25:$O25) -> 6800.7048 | Q25: =IFERROR(IF('Ago-22'!$F25="","-",VLOOKUP('Ago-22'!$F25,Lista_CUIT!$A$1:$D$1871,3,0)),"CUIT NO CARGADO") -> COMBUSTIBLE | R25: =IFERROR(IF('Ago-22'!$F25="","-",VLOOKUP('Ago-22'!$F25,Lista_CUIT!$A$1:$D$1871,4,0)),"CUIT NO CARGADO") -> 0
B26: 44790 | C26: 1 | D26: 7 | E26: 4231 | F26: 30631515815 | G26: =IFERROR(IF('Ago-22'!$F26="","-",VLOOKUP('Ago-22'!$F26,Lista_CUIT!$A$1:$D$1871,2,0)),"CUIT NO CARGADO") -> M-ELEK SA | H26: 9305.79 | I26: =IF('Ago-22'!$H26="","",'Ago-22'!$H26*0.21) -> 1954.2159 | P26: =SUM('Ago-22'!$H26:$O26) -> 11260.006 | Q26: =IFERROR(IF('Ago-22'!$F26="","-",VLOOKUP('Ago-22'!$F26,Lista_CUIT!$A$1:$D$1871,3,0)),"CUIT NO CARGADO") -> Gastos Oficina | R26: =IFERROR(IF('Ago-22'!$F26="","-",VLOOKUP('Ago-22'!$F26,Lista_CUIT!$A$1:$D$1871,4,0)),"CUIT NO CARGADO") -> 0
B27: 44785 | C27: 1 | D27: 1006 | E27: 773577 | F27: 30538068841 | G27: =IFERROR(IF('Ago-22'!$F27="","-",VLOOKUP('Ago-22'!$F27,Lista_CUIT!$A$1:$D$1871,2,0)),"CUIT NO CARGADO") -> FAMIQ SRL | H27: 784205.8 | I27: =IF('Ago-22'!$H27="","",'Ago-22'!$H27*0.21) -> 164683.22 | P27: =SUM('Ago-22'!$H27:$O27) -> 948889.02 | Q27: =IFERROR(IF('Ago-22'!$F27="","-",VLOOKUP('Ago-22'!$F27,Lista_CUIT!$A$1:$D$1871,3,0)),"CUIT NO CARGADO") -> Gastos Varios | R27: =IFERROR(IF('Ago-22'!$F27="","-",VLOOKUP('Ago-22'!$F27,Lista_CUIT!$A$1:$D$1871,4,0)),"CUIT NO CARGADO") -> 0
B28: 44785 | C28: 1 | D28: 2 | E28: 532 | F28: 20296550184 | G28: =IFERROR(IF('Ago-22'!$F28="","-",VLOOKUP('Ago-22'!$F28,Lista_CUIT!$A$1:$D$1871,2,0)),"CUIT NO CARGADO") -> COSTA DIEGO ALEJANDRO | H28: 30360 | I28: =IF('Ago-22'!$H28="","",'Ago-22'!$H28*0.21) -> 6375.6 | P28: =SUM('Ago-22'!$H28:$O28) -> 36735.6 | Q28: =IFERROR(IF('Ago-22'!$F28="","-",VLOOKUP('Ago-22'!$F28,Lista_CUIT!$A$1:$D$1871,3,0)),"CUIT NO CARGADO") -> MAT. PRIM. | R28: =IFERROR(IF('Ago-22'!$F28="","-",VLOOKUP('Ago-22'!$F28,Lista_CUIT!$A$1:$D$1871,4,0)),"CUIT NO CARGADO") -> 0
B29: 44781 | C29: 1 | D29: 4 | E29: 88182 | F29: 30559932236 | G29: =IFERROR(IF('Ago-22'!$F29="","-",VLOOKUP('Ago-22'!$F29,Lista_CUIT!$A$1:$D$1871,2,0)),"CUIT NO CARGADO") -> ELECTRONICA ELEMON SA | H29: 53041.07 | I29: =IF('Ago-22'!$H29="","",'Ago-22'!$H29*0.21) -> 11138.625 | P29: =SUM('Ago-22'!$H29:$O29) -> 64179.695 | Q29: =IFERROR(IF('Ago-22'!$F29="","-",VLOOKUP('Ago-22'!$F29,Lista_CUIT!$A$1:$D$1871,3,0)),"CUIT NO CARGADO") -> MAT. PRIM. | R29: =IFERROR(IF('Ago-22'!$F29="","-",VLOOKUP('Ago-22'!$F29,Lista_CUIT!$A$1:$D$1871,4,0)),"CUIT NO CARGADO") -> 0
B30: 44774 | C30: 1 | D30: 3 | E30: 560 | F30: 30715402765 | G30: =IFERROR(IF('Ago-22'!$F30="","-",VLOOKUP('Ago-22'!$F30,Lista_CUIT!$A$1:$D$1871,2,0)),"CUIT NO CARGADO") -> RIO 265 SRL | H30: 7768.6 | I30: =IF('Ago-22'!$H30="","",'Ago-22'!$H30*0.21) -> 1631.406 | P30: =SUM('Ago-22'!$H30:$O30) -> 9400.006 | Q30: =IFERROR(IF('Ago-22'!$F30="","-",VLOOKUP('Ago-22'!$F30,Lista_CUIT!$A$1:$D$1871,3,0)),"CUIT NO CARGADO") -> GTOS VARIOS-ESTACIONAMIENTO HORACIO | R30: =IFERROR(IF('Ago-22'!$F30="","-",VLOOKUP('Ago-22'!$F30,Lista_CUIT!$A$1:$D$1871,4,0)),"CUIT NO CARGADO") -> 0
B31: 44781 | C31: 1 | D31: 700 | E31: 412103 | F31: 30580111315 | G31: =IFERROR(IF('Ago-22'!$F31="","-",VLOOKUP('Ago-22'!$F31,Lista_CUIT!$A$1:$D$1871,2,0)),"CUIT NO CARGADO") -> DHL EXPRESS ARG SA | I31: =IF('Ago-22'!$H31="","",'Ago-22'!$H31*0.21) | O31: 35149.537 | P31: =SUM('Ago-22'!$H31:$O31) -> 35149.537 | Q31: =IFERROR(IF('Ago-22'!$F31="","-",VLOOKUP('Ago-22'!$F31,Lista_CUIT!$A$1:$D$1871,3,0)),"CUIT NO CARGADO") -> GTOS IMP. | R31: =IFERROR(IF('Ago-22'!$F31="","-",VLOOKUP('Ago-22'!$F31,Lista_CUIT!$A$1:$D$1871,4,0)),"CUIT NO CARGADO") -> 0
B32: 44783 | C32: 1 | D32: 3 | E32: 6784 | F32: 30710212127 | G32: =IFERROR(IF('Ago-22'!$F32="","-",VLOOKUP('Ago-22'!$F32,Lista_CUIT!$A$1:$D$1871,2,0)),"CUIT NO CARGADO") -> COMPONENTES ELECTRICOS SA | H32: 913821.89 | I32: =IF('Ago-22'!$H32="","",'Ago-22'!$H32*0.21) -> 191902.6 | P32: =SUM('Ago-22'!$H32:$O32) -> 1105724.5 | Q32: =IFERROR(IF('Ago-22'!$F32="","-",VLOOKUP('Ago-22'!$F32,Lista_CUIT!$A$1:$D$1871,3,0)),"CUIT NO CARGADO") -> INSUMO | R32: =IFERROR(IF('Ago-22'!$F32="","-",VLOOKUP('Ago-22'!$F32,Lista_CUIT!$A$1:$D$1871,4,0)),"CUIT NO CARGADO") -> 0
B33: 44783 | C33: 1 | D33: 6 | E33: 4244 | F33: 20289190148 | G33: =IFERROR(IF('Ago-22'!$F33="","-",VLOOKUP('Ago-22'!$F33,Lista_CUIT!$A$1:$D$1871,2,0)),"CUIT NO CARGADO") -> LAROCCA JUAN MARTIN | H33: 4864.7 | I33: =IF('Ago-22'!$H33="","",'Ago-22'!$H33*0.21) -> 1021.587 | P33: =SUM('Ago-22'!$H33:$O33) -> 5886.287 | Q33: =IFERROR(IF('Ago-22'!$F33="","-",VLOOKUP('Ago-22'!$F33,Lista_CUIT!$A$1:$D$1871,3,0)),"CUIT NO CARGADO") -> Gastos Oficina | R33: =IFERROR(IF('Ago-22'!$F33="","-",VLOOKUP('Ago-22'!$F33,Lista_CUIT!$A$1:$D$1871,4,0)),"CUIT NO CARGADO") -> 0
B34: 44776 | C34: 1 | D34: 8 | E34: 157587 | F34: 33606484599 | G34: =IFERROR(IF('Ago-22'!$F34="","-",VLOOKUP('Ago-22'!$F34,Lista_CUIT!$A$1:$D$1871,2,0)),"CUIT NO CARGADO") -> JORVICAL ACEROS SA | H34: 466420.22 | I34: =IF('Ago-22'!$H34="","",'Ago-22'!$H34*0.21) -> 97948.246 | P34: =SUM('Ago-22'!$H34:$O34) -> 564368.47 | Q34: =IFERROR(IF('Ago-22'!$F34="","-",VLOOKUP('Ago-22'!$F34,Lista_CUIT!$A$1:$D$1871,3,0)),"CUIT NO CARGADO") -> MAT. PRIM. | R34: =IFERROR(IF('Ago-22'!$F34="","-",VLOOKUP('Ago-22'!$F34,Lista_CUIT!$A$1:$D$1871,4,0)),"CUIT NO CARGADO") -> 0
B35: 44774 | C35: 1 | D35: 3 | E35: 164538 | F35: 30707135596 | G35: =IFERROR(IF('Ago-22'!$F35="","-",VLOOKUP('Ago-22'!$F35,Lista_CUIT!$A$1:$D$1871,2,0)),"CUIT NO CARGADO") -> CITILAN ARGENTINA SA | H35: 3062.6 | I35: =IF('Ago-22'!$H35="","",'Ago-22'!$H35*0.21) -> 643.146 | P35: =SUM('Ago-22'!$H35:$O35) -> 3705.746 | Q35: =IFERROR(IF('Ago-22'!$F35="","-",VLOOKUP('Ago-22'!$F35,Lista_CUIT!$A$1:$D$1871,3,0)),"CUIT NO CARGADO") -> SERVICIOS GAS, LUZ, ETC | R35: =IFERROR(IF('Ago-22'!$F35="","-",VLOOKUP('Ago-22'!$F35,Lista_CUIT!$A$1:$D$1871,4,0)),"CUIT NO CARGADO") -> 0
B36: 44774 | C36: 1 | D36: 2 | E36: 14593 | F36: 30624684628 | G36: =IFERROR(IF('Ago-22'!$F36="","-",VLOOKUP('Ago-22'!$F36,Lista_CUIT!$A$1:$D$1871,2,0)),"CUIT NO CARGADO") -> MITSUKO ARGENTINA SRL | H36: 153480 | I36: =IF('Ago-22'!$H36="","",'Ago-22'!$H36*0.21) -> 32230.8 | P36: =SUM('Ago-22'!$H36:$O36) -> 185710.8 | Q36: =IFERROR(IF('Ago-22'!$F36="","-",VLOOKUP('Ago-22'!$F36,Lista_CUIT!$A$1:$D$1871,3,0)),"CUIT NO CARGADO") -> MAT. PRIM. | R36: =IFERROR(IF('Ago-22'!$F36="","-",VLOOKUP('Ago-22'!$F36,Lista_CUIT!$A$1:$D$1871,4,0)),"CUIT NO CARGADO") -> 0
B37: 44775 | C37: 1 | D37: 2 | E37: 528 | F37: 20296550184 | G37: =IFERROR(IF('Ago-22'!$F37="","-",VLOOKUP('Ago-22'!$F37,Lista_CUIT!$A$1:$D$1871,2,0)),"CUIT NO CARGADO") -> COSTA DIEGO ALEJANDRO | H37: 35260 | I37: =IF('Ago-22'!$H37="","",'Ago-22'!$H37*0.21) -> 7404.6 | P37: =SUM('Ago-22'!$H37:$O37) -> 42664.6 | Q37: =IFERROR(IF('Ago-22'!$F37="","-",VLOOKUP('Ago-22'!$F37,Lista_CUIT!$A$1:$D$1871,3,0)),"CUIT NO CARGADO") -> MAT. PRIM. | R37: =IFERROR(IF('Ago-22'!$F37="","-",VLOOKUP('Ago-22'!$F37,Lista_CUIT!$A$1:$D$1871,4,0)),"CUIT NO CARGADO") -> 0
B38: 44782 | C38: 1 | D38: 8 | E38: 4848 | F38: 30715619055 | G38: =IFERROR(IF('Ago-22'!$F38="","-",VLOOKUP('Ago-22'!$F38,Lista_CUIT!$A$1:$D$1871,2,0)),"CUIT NO CARGADO") -> PETIT PET SHOP S.R.L | H38: 10412.38 | I38: =IF('Ago-22'!$H38="","",'Ago-22'!$H38*0.21) -> 2186.5998 | P38: =SUM('Ago-22'!$H38:$O38) -> 12598.98 | Q38: =IFERROR(IF('Ago-22'!$F38="","-",VLOOKUP('Ago-22'!$F38,Lista_CUIT!$A$1:$D$1871,3,0)),"CUIT NO CARGADO") -> Gastos Varios | R38: =IFERROR(IF('Ago-22'!$F38="","-",VLOOKUP('Ago-22'!$F38,Lista_CUIT!$A$1:$D$1871,4,0)),"CUIT NO CARGADO") -> 0
B39: 44783 | C39: 1 | D39: 1 | E39: 7388 | F39: 30716993376 | G39: =IFERROR(IF('Ago-22'!$F39="","-",VLOOKUP('Ago-22'!$F39,Lista_CUIT!$A$1:$D$1871,2,0)),"CUIT NO CARGADO") -> DETODONET S.A. | H39: 15616.53 | I39: =IF('Ago-22'!$H39="","",'Ago-22'!$H39*0.21) -> 3279.4713 | P39: =SUM('Ago-22'!$H39:$O39) -> 18896.001 | Q39: =IFERROR(IF('Ago-22'!$F39="","-",VLOOKUP('Ago-22'!$F39,Lista_CUIT!$A$1:$D$1871,3,0)),"CUIT NO CARGADO") -> Gastos Oficina | R39: =IFERROR(IF('Ago-22'!$F39="","-",VLOOKUP('Ago-22'!$F39,Lista_CUIT!$A$1:$D$1871,4,0)),"CUIT NO CARGADO") -> 0
B40: 44784 | C40: 1 | D40: 2466 | E40: 396541 | F40: 30678814357 | G40: =IFERROR(IF('Ago-22'!$F40="","-",VLOOKUP('Ago-22'!$F40,Lista_CUIT!$A$1:$D$1871,2,0)),"CUIT NO CARGADO") -> Telefonica Moviles Argentina SA | H40: 1987 | J40: 536.49 | O40: 104.58 | P40: =SUM('Ago-22'!$H40:$O40) -> 2628.07 | Q40: =IFERROR(IF('Ago-22'!$F40="","-",VLOOKUP('Ago-22'!$F40,Lista_CUIT!$A$1:$D$1871,3,0)),"CUIT NO CARGADO") -> SERVICIOS GAS, LUZ, ETC | R40: =IFERROR(IF('Ago-22'!$F40="","-",VLOOKUP('Ago-22'!$F40,Lista_CUIT!$A$1:$D$1871,4,0)),"CUIT NO CARGADO") -> 0
B41: 44790 | C41: 1 | D41: 5 | E41: 21897 | F41: 30710571801 | G41: =IFERROR(IF('Ago-22'!$F41="","-",VLOOKUP('Ago-22'!$F41,Lista_CUIT!$A$1:$D$1871,2,0)),"CUIT NO CARGADO") -> HOGAR ACTUAL SRL | H41: 6355.37 | I41: =IF('Ago-22'!$H41="","",'Ago-22'!$H41*0.21) -> 1334.6277 | P41: =SUM('Ago-22'!$H41:$O41) -> 7689.9977 | Q41: =IFERROR(IF('Ago-22'!$F41="","-",VLOOKUP('Ago-22'!$F41,Lista_CUIT!$A$1:$D$1871,3,0)),"CUIT NO CARGADO") -> Gastos Oficina | R41: =IFERROR(IF('Ago-22'!$F41="","-",VLOOKUP('Ago-22'!$F41,Lista_CUIT!$A$1:$D$1871,4,0)),"CUIT NO CARGADO") -> 0
B42: 44791 | C42: 1 | D42: 4 | E42: 57078 | F42: 30714749206 | G42: =IFERROR(IF('Ago-22'!$F42="","-",VLOOKUP('Ago-22'!$F42,Lista_CUIT!$A$1:$D$1871,2,0)),"CUIT NO CARGADO") -> EBOX SA | H42: 3890.5 | K42: 408.5025 | P42: =SUM('Ago-22'!$H42:$O42) -> 4299.0025 | Q42: =IFERROR(IF('Ago-22'!$F42="","-",VLOOKUP('Ago-22'!$F42,Lista_CUIT!$A$1:$D$1871,3,0)),"CUIT NO CARGADO") -> Gastos Varios | R42: =IFERROR(IF('Ago-22'!$F42="","-",VLOOKUP('Ago-22'!$F42,Lista_CUIT!$A$1:$D$1871,4,0)),"CUIT NO CARGADO") -> 0
B43: 44791 | C43: 1 | D43: 4 | E43: 57107 | F43: 30714749206 | G43: =IFERROR(IF('Ago-22'!$F43="","-",VLOOKUP('Ago-22'!$F43,Lista_CUIT!$A$1:$D$1871,2,0)),"CUIT NO CARGADO") -> EBOX SA | H43: 254.54 | I43: =IF('Ago-22'!$H43="","",'Ago-22'!$H43*0.21) -> 53.4534 | P43: =SUM('Ago-22'!$H43:$O43) -> 307.9934 | Q43: =IFERROR(IF('Ago-22'!$F43="","-",VLOOKUP('Ago-22'!$F43,Lista_CUIT!$A$1:$D$1871,3,0)),"CUIT NO CARGADO") -> Gastos Varios | R43: =IFERROR(IF('Ago-22'!$F43="","-",VLOOKUP('Ago-22'!$F43,Lista_CUIT!$A$1:$D$1871,4,0)),"CUIT NO CARGADO") -> 0
B44: 44802 | C44: 1 | D44: 3 | E44: 1 | F44: 20386178209 | G44: =IFERROR(IF('Ago-22'!$F44="","-",VLOOKUP('Ago-22'!$F44,Lista_CUIT!$A$1:$D$1871,2,0)),"CUIT NO CARGADO") -> CLEMENTE LUCAS IVAN | H44: 98500 | I44: =IF('Ago-22'!$H44="","",'Ago-22'!$H44*0.21) -> 20685 | P44: =SUM('Ago-22'!$H44:$O44) -> 119185 | Q44: =IFERROR(IF('Ago-22'!$F44="","-",VLOOKUP('Ago-22'!$F44,Lista_CUIT!$A$1:$D$1871,3,0)),"CUIT NO CARGADO") -> Servicios de Publicidad | R44: =IFERROR(IF('Ago-22'!$F44="","-",VLOOKUP('Ago-22'!$F44,Lista_CUIT!$A$1:$D$1871,4,0)),"CUIT NO CARGADO") -> 0
B45: 44803 | C45: 1 | D45: 17 | E45: 8037 | F45: 30534051049 | G45: =IFERROR(IF('Ago-22'!$F45="","-",VLOOKUP('Ago-22'!$F45,Lista_CUIT!$A$1:$D$1871,2,0)),"CUIT NO CARGADO") -> PLIN METAL SA | H45: 21304.2 | I45: =IF('Ago-22'!$H45="","",'Ago-22'!$H45*0.21) -> 4473.882 | P45: =SUM('Ago-22'!$H45:$O45) -> 25778.082 | Q45: =IFERROR(IF('Ago-22'!$F45="","-",VLOOKUP('Ago-22'!$F45,Lista_CUIT!$A$1:$D$1871,3,0)),"CUIT NO CARGADO") -> MAT. PRIM. | R45: =IFERROR(IF('Ago-22'!$F45="","-",VLOOKUP('Ago-22'!$F45,Lista_CUIT!$A$1:$D$1871,4,0)),"CUIT NO CARGADO") -> 0
B46: 44803 | C46: 1 | D46: 106 | E46: 558432 | F46: 30594494187 | G46: =IFERROR(IF('Ago-22'!$F46="","-",VLOOKUP('Ago-22'!$F46,Lista_CUIT!$A$1:$D$1871,2,0)),"CUIT NO CARGADO") -> FEDERAL EXPRESS CORPORATION | H46: 0 | I46: =IF('Ago-22'!$H46="","",'Ago-22'!$H46*0.21) -> 0 | O46: 52410.24 | P46: =SUM('Ago-22'!$H46:$O46) -> 52410.24 | Q46: =IFERROR(IF('Ago-22'!$F46="","-",VLOOKUP('Ago-22'!$F46,Lista_CUIT!$A$1:$D$1871,3,0)),"CUIT NO CARGADO") -> GTOS IMP. | R46: =IFERROR(IF('Ago-22'!$F46="","-",VLOOKUP('Ago-22'!$F46,Lista_CUIT!$A$1:$D$1871,4,0)),"CUIT NO CARGADO") -> 0
B47: 44804 | C47: 1 | D47: 3 | E47: 1033882 | F47: 30712019359 | G47: =IFERROR(IF('Ago-22'!$F47="","-",VLOOKUP('Ago-22'!$F47,Lista_CUIT!$A$1:$D$1871,2,0)),"CUIT NO CARGADO") -> LINKEDSTORE ARGENTINA S.R.L. | H47: 2478.51 | I47: =IF('Ago-22'!$H47="","",'Ago-22'!$H47*0.21) -> 520.4871 | P47: =SUM('Ago-22'!$H47:$O47) -> 2998.9971 | Q47: =IFERROR(IF('Ago-22'!$F47="","-",VLOOKUP('Ago-22'!$F47,Lista_CUIT!$A$1:$D$1871,3,0)),"CUIT NO CARGADO") -> Gastos Varios | R47: =IFERROR(IF('Ago-22'!$F47="","-",VLOOKUP('Ago-22'!$F47,Lista_CUIT!$A$1:$D$1871,4,0)),"CUIT NO CARGADO") -> 0
B48: 44804 | C48: 1 | D48: 1 | E48: 491 | F48: 30715048066 | G48: =IFERROR(IF('Ago-22'!$F48="","-",VLOOKUP('Ago-22'!$F48,Lista_CUIT!$A$1:$D$1871,2,0)),"CUIT NO CARGADO") -> ROLLS Y EMPANADAS SA | H48: 119110 | I48: =IF('Ago-22'!$H48="","",'Ago-22'!$H48*0.21) -> 25013.1 | P48: =SUM('Ago-22'!$H48:$O48) -> 144123.1 | Q48: =IFERROR(IF('Ago-22'!$F48="","-",VLOOKUP('Ago-22'!$F48,Lista_CUIT!$A$1:$D$1871,3,0)),"CUIT NO CARGADO") -> CATERING | R48: =IFERROR(IF('Ago-22'!$F48="","-",VLOOKUP('Ago-22'!$F48,Lista_CUIT!$A$1:$D$1871,4,0)),"CUIT NO CARGADO") -> 0
B49: 44791 | C49: 2 | D49: 1001 | E49: 77776 | F49: 30538068841 | G49: =IFERROR(IF('Ago-22'!$F49="","-",VLOOKUP('Ago-22'!$F49,Lista_CUIT!$A$1:$D$1871,2,0)),"CUIT NO CARGADO") -> FAMIQ SRL | H49: 9802.57 | I49: =IF('Ago-22'!$H49="","",'Ago-22'!$H49*0.21) -> 2058.5397 | P49: =SUM('Ago-22'!$H49:$O49) -> 11861.11 | Q49: =IFERROR(IF('Ago-22'!$F49="","-",VLOOKUP('Ago-22'!$F49,Lista_CUIT!$A$1:$D$1871,3,0)),"CUIT NO CARGADO") -> Gastos Varios | R49: =IFERROR(IF('Ago-22'!$F49="","-",VLOOKUP('Ago-22'!$F49,Lista_CUIT!$A$1:$D$1871,4,0)),"CUIT NO CARGADO") -> 0
B50: Total | H50: =SUBTOTAL(109,'Ago-22'!$H$9:$H$49) -> 5622218.1 | I50: =SUBTOTAL(109,'Ago-22'!$I$9:$I$49) -> 1036246.6 | J50: =SUBTOTAL(109,'Ago-22'!$J$9:$J$49) -> 536.49 | K50: =SUBTOTAL(109,'Ago-22'!$K$9:$K$49) -> 72000.529 | L50: =SUBTOTAL(109,'Ago-22'!$L$9:$L$49) -> 0 | M50: =SUBTOTAL(109,'Ago-22'!$M$9:$M$49) -> 0 | N50: =SUBTOTAL(109,'Ago-22'!$N$9:$N$49) -> 0 | O50: =SUBTOTAL(109,'Ago-22'!$O$9:$O$49) -> -490745.22 | P50: =SUBTOTAL(109,'Ago-22'!$P$9:$P$49) -> 6240256.5
D55: LIQUIDACION EXTRACTOS BANCARIOS-TARJETAS
D56: FECHA | E56: NRO CPTE | F56: BANCO | G56: NETO | H56: IVA 21% | I56: IVA 10,5% | J56: RET IIBB CABA | K56: PERC IVA | L56: PERC IIBB
F57: BANCO CREDICOOP | G57: 2736.0476 | H57: 574.57
D58: 44802 | E58: 617-489658000 | F58: Liq. C. i Vista (mostrador) | G58: 15906.81 | H58: 3340.43 | K58: 477.2
D59: 44802 | E59: 617-489599000 | F59: Liq. C. i Vista (mostrador) | G59: 15835.524 | H59: 3325.46 | K59: 475.07
D60: 44791 | E60: 617-488742000 | F60: Liq. C. i Vista (mostrador) | G60: 15585.952 | H60: 3273.05 | K60: 467.58
D61: 44777 | E61: 993-721000 | F61: Seg. permisos embarque | G61: 3316 | H61: 696.36 | K61: 99.48
F62: VISA CREDITO | G62: 80 | H62: 16.8 | J62: 1.78
D63: Total | G63: =SUBTOTAL(109,'Ago-22'!$G$57:$G$62) -> 53460.333 | H63: =SUBTOTAL(109,'Ago-22'!$H$57:$H$62) -> 11226.67 | I63: =SUBTOTAL(109,'Ago-22'!$I$57:$I$62) -> 0 | J63: =SUBTOTAL(109,'Ago-22'!$J$57:$J$62) -> 1.78 | K63: =SUBTOTAL(109,'Ago-22'!$K$57:$K$62) -> 1519.33 | L63: =SUBTOTAL(109,'Ago-22'!$L$57:$L$62) -> 0
D67: FACTURAS C
D68: FECHA | E68: PTO VTA | F68: FC Nº | G68: CUIT | H68: RAZON SOCIAL | I68: TOTAL | J68: TIPO DE GASTO | K68: Provincia
D69: 44804 | E69: 2 | F69: 117 | G69: 20136544625 | H69: =IFERROR(IF('Ago-22'!$G69="","-",VLOOKUP('Ago-22'!$G69,Lista_CUIT!$A$1:$D$1871,2,0)),"CUIT NO CARGADO") -> RODRIGUEZ DE LA FUEN HECTOR MARCELO | I69: 100000 | J69: =IFERROR(IF('Ago-22'!$G69="","-",VLOOKUP('Ago-22'!$G69,Lista_CUIT!$A$1:$D$1871,3,0)),"CUIT NO CARGADO") -> Honorarios Administrativos-Cobranzas y Gestion Clientes | K69: =IFERROR(IF('Ago-22'!$G69="","-",VLOOKUP('Ago-22'!$G69,Lista_CUIT!$A$1:$D$1871,4,0)),"CUIT NO CARGADO") -> 0
D70: 44804 | E70: 2 | F70: 183 | G70: 27173820866 | H70: =IFERROR(IF('Ago-22'!$G70="","-",VLOOKUP('Ago-22'!$G70,Lista_CUIT!$A$1:$D$1871,2,0)),"CUIT NO CARGADO") -> FREIER SANDRA DANIELA | I70: 100000 | J70: =IFERROR(IF('Ago-22'!$G70="","-",VLOOKUP('Ago-22'!$G70,Lista_CUIT!$A$1:$D$1871,3,0)),"CUIT NO CARGADO") -> HONORARIOS | K70: =IFERROR(IF('Ago-22'!$G70="","-",VLOOKUP('Ago-22'!$G70,Lista_CUIT!$A$1:$D$1871,4,0)),"CUIT NO CARGADO") -> 0
D71: 44803 | E71: 1 | F71: 15 | G71: 20365938688 | H71: =IFERROR(IF('Ago-22'!$G71="","-",VLOOKUP('Ago-22'!$G71,Lista_CUIT!$A$1:$D$1871,2,0)),"CUIT NO CARGADO") -> LIPANOVICH JUAN CRUZ | I71: 330000 | J71: =IFERROR(IF('Ago-22'!$G71="","-",VLOOKUP('Ago-22'!$G71,Lista_CUIT!$A$1:$D$1871,3,0)),"CUIT NO CARGADO") -> Servicios Informatica | K71: =IFERROR(IF('Ago-22'!$G71="","-",VLOOKUP('Ago-22'!$G71,Lista_CUIT!$A$1:$D$1871,4,0)),"CUIT NO CARGADO") -> 0
D72: 44799 | E72: 1 | F72: 15 | G72: 27925308884 | H72: =IFERROR(IF('Ago-22'!$G72="","-",VLOOKUP('Ago-22'!$G72,Lista_CUIT!$A$1:$D$1871,2,0)),"CUIT NO CARGADO") -> LOPEZ LOPEZ FLAVIA | I72: 5800 | J72: =IFERROR(IF('Ago-22'!$G72="","-",VLOOKUP('Ago-22'!$G72,Lista_CUIT!$A$1:$D$1871,3,0)),"CUIT NO CARGADO") -> FLETE | K72: =IFERROR(IF('Ago-22'!$G72="","-",VLOOKUP('Ago-22'!$G72,Lista_CUIT!$A$1:$D$1871,4,0)),"CUIT NO CARGADO") -> 0
D73: 44783 | E73: 2 | F73: 13 | G73: 23326777269 | H73: =IFERROR(IF('Ago-22'!$G73="","-",VLOOKUP('Ago-22'!$G73,Lista_CUIT!$A$1:$D$1871,2,0)),"CUIT NO CARGADO") -> DE BONIS IGNACIO LUIS | I73: 148940 | J73: =IFERROR(IF('Ago-22'!$G73="","-",VLOOKUP('Ago-22'!$G73,Lista_CUIT!$A$1:$D$1871,3,0)),"CUIT NO CARGADO") -> Control medidores masicos | K73: =IFERROR(IF('Ago-22'!$G73="","-",VLOOKUP('Ago-22'!$G73,Lista_CUIT!$A$1:$D$1871,4,0)),"CUIT NO CARGADO") -> 0
D74: 44781 | E74: 2 | F74: 74 | G74: 20244271740 | H74: =IFERROR(IF('Ago-22'!$G74="","-",VLOOKUP('Ago-22'!$G74,Lista_CUIT!$A$1:$D$1871,2,0)),"CUIT NO CARGADO") -> KENNEL SEBASTIAN | I74: 173600 | J74: =IFERROR(IF('Ago-22'!$G74="","-",VLOOKUP('Ago-22'!$G74,Lista_CUIT!$A$1:$D$1871,3,0)),"CUIT NO CARGADO") -> SOFTWARE MANTENIMIENTO | K74: =IFERROR(IF('Ago-22'!$G74="","-",VLOOKUP('Ago-22'!$G74,Lista_CUIT!$A$1:$D$1871,4,0)),"CUIT NO CARGADO") -> 0
D75: 44781 | E75: 3 | F75: 29 | G75: 20403931420 | H75: =IFERROR(IF('Ago-22'!$G75="","-",VLOOKUP('Ago-22'!$G75,Lista_CUIT!$A$1:$D$1871,2,0)),"CUIT NO CARGADO") -> FIORENTINO JORGE IGNACIO | I75: 117120 | J75: =IFERROR(IF('Ago-22'!$G75="","-",VLOOKUP('Ago-22'!$G75,Lista_CUIT!$A$1:$D$1871,3,0)),"CUIT NO CARGADO") -> Honorarios Administrativos-Cobranzas y Gestion Clientes | K75: =IFERROR(IF('Ago-22'!$G75="","-",VLOOKUP('Ago-22'!$G75,Lista_CUIT!$A$1:$D$1871,4,0)),"CUIT NO CARGADO") -> 0
D76: 44785 | E76: 1 | F76: 9 | G76: 20417805878 | H76: =IFERROR(IF('Ago-22'!$G76="","-",VLOOKUP('Ago-22'!$G76,Lista_CUIT!$A$1:$D$1871,2,0)),"CUIT NO CARGADO") -> FERABOLI OSPAL SANTIAGO HERNAN | I76: 127560 | J76: =IFERROR(IF('Ago-22'!$G76="","-",VLOOKUP('Ago-22'!$G76,Lista_CUIT!$A$1:$D$1871,3,0)),"CUIT NO CARGADO") -> Control medidores masicos | K76: =IFERROR(IF('Ago-22'!$G76="","-",VLOOKUP('Ago-22'!$G76,Lista_CUIT!$A$1:$D$1871,4,0)),"CUIT NO CARGADO") -> 0
D77: 44778 | E77: 1 | F77: 87 | G77: 20341465134 | H77: =IFERROR(IF('Ago-22'!$G77="","-",VLOOKUP('Ago-22'!$G77,Lista_CUIT!$A$1:$D$1871,2,0)),"CUIT NO CARGADO") -> ABELEDO AGUSTIN ENRIQUE | I77: 124800 | J77: =IFERROR(IF('Ago-22'!$G77="","-",VLOOKUP('Ago-22'!$G77,Lista_CUIT!$A$1:$D$1871,3,0)),"CUIT NO CARGADO") -> HONOR. INGENIERO | K77: =IFERROR(IF('Ago-22'!$G77="","-",VLOOKUP('Ago-22'!$G77,Lista_CUIT!$A$1:$D$1871,4,0)),"CUIT NO CARGADO") -> 0
D78: 44783 | E78: 3 | F78: 609 | G78: 20086277523 | H78: =IFERROR(IF('Ago-22'!$G78="","-",VLOOKUP('Ago-22'!$G78,Lista_CUIT!$A$1:$D$1871,2,0)),"CUIT NO CARGADO") -> JUAN CARLOS BOTINDARI | I78: 8350 | J78: =IFERROR(IF('Ago-22'!$G78="","-",VLOOKUP('Ago-22'!$G78,Lista_CUIT!$A$1:$D$1871,3,0)),"CUIT NO CARGADO") -> HONORARIOS | K78: =IFERROR(IF('Ago-22'!$G78="","-",VLOOKUP('Ago-22'!$G78,Lista_CUIT!$A$1:$D$1871,4,0)),"CUIT NO CARGADO") -> 0
D79: 44784 | E79: 1 | F79: 9 | G79: 20338344695 | H79: =IFERROR(IF('Ago-22'!$G79="","-",VLOOKUP('Ago-22'!$G79,Lista_CUIT!$A$1:$D$1871,2,0)),"CUIT NO CARGADO") -> FUERTES DAMIAN MATIAS | I79: 19200 | J79: =IFERROR(IF('Ago-22'!$G79="","-",VLOOKUP('Ago-22'!$G79,Lista_CUIT!$A$1:$D$1871,3,0)),"CUIT NO CARGADO") -> INSUMO | K79: =IFERROR(IF('Ago-22'!$G79="","-",VLOOKUP('Ago-22'!$G79,Lista_CUIT!$A$1:$D$1871,4,0)),"CUIT NO CARGADO") -> 0
D80: 44776 | E80: 2 | F80: 115 | G80: 20136544625 | H80: =IFERROR(IF('Ago-22'!$G80="","-",VLOOKUP('Ago-22'!$G80,Lista_CUIT!$A$1:$D$1871,2,0)),"CUIT NO CARGADO") -> RODRIGUEZ DE LA FUEN HECTOR MARCELO | I80: 30000 | J80: =IFERROR(IF('Ago-22'!$G80="","-",VLOOKUP('Ago-22'!$G80,Lista_CUIT!$A$1:$D$1871,3,0)),"CUIT NO CARGADO") -> Honorarios Administrativos-Cobranzas y Gestion Clientes | K80: =IFERROR(IF('Ago-22'!$G80="","-",VLOOKUP('Ago-22'!$G80,Lista_CUIT!$A$1:$D$1871,4,0)),"CUIT NO CARGADO") -> 0
... D82: 44777 | E82: 4 | F82: 4 | G82: 20341462933 | H82: =IFERROR(IF('Ago-22'!$G82="","-",VLOOKUP('Ago-22'!$G82,Lista_CUIT!$A$1:$D$1871,2,0)),"CUIT NO CARGADO") -> CASTIGLIONI MATIAS EZEQUIEL | I82: 195000 | J82: =IFERROR(IF('Ago-22'!$G82="","-",VLOOKUP('Ago-22'!$G82,Lista_CUIT!$A$1:$D$1871,3,0)),"CUIT NO CARGADO") -> MAT. PRIM. | K82: =IFERROR(IF('Ago-22'!$G82="","-",VLOOKUP('Ago-22'!$G82,Lista_CUIT!$A$1:$D$1871,4,0)),"CUIT NO CARGADO") -> 0
D83: Total | I83: =SUBTOTAL(109,'Ago-22'!$I$69:$I$82) -> 1532270
B89: LIBRO IVA VENTAS | K89: =N1 -> 44774
B91: VENTAS "A"
B92: FECHA | C92: TIPO | D92: PTO VENTA | E92: Nº FACTURA | F92: CUIT | G92: RAZON SOCIAL | H92: IMPORTE NETO | I92: IVA 21% | J92: IVA 10,5% | K92: EXENTO | L92: TOTAL | M92: Provincia
B93: 01/08/2022 | C93: 1 | D93: 3 | E93: 71 | F93: 30638318470 | G93: =IFERROR(IF('Ago-22'!$F93="","-",VLOOKUP('Ago-22'!$F93,Lista_CUIT!$A$1:$D$1871,2,0)),"CUIT NO CARGADO") -> DELTA COMPRESION S.R.L | H93: 6093318 | J93: 639798.39 | L93: =SUM('Ago-22'!$H93:$K93) -> 6733116.4
B94: 05/08/2022 | C94: 1 | D94: 3 | E94: 72 | F94: 30638318470 | G94: =IFERROR(IF('Ago-22'!$F94="","-",VLOOKUP('Ago-22'!$F94,Lista_CUIT!$A$1:$D$1871,2,0)),"CUIT NO CARGADO") -> DELTA COMPRESION S.R.L | H94: 1027452.3 | I94: 180463.29 | J94: 17651.77 | L94: =SUM('Ago-22'!$H94:$K94) -> 1225567.4
B95: 05/08/2022 | C95: 1 | D95: 3 | E95: 73 | F95: 30638318470 | G95: =IFERROR(IF('Ago-22'!$F95="","-",VLOOKUP('Ago-22'!$F95,Lista_CUIT!$A$1:$D$1871,2,0)),"CUIT NO CARGADO") -> DELTA COMPRESION S.R.L | H95: 194107.11 | I95: ='Ago-22'!$H95*0.21 -> 40762.493 | L95: =SUM('Ago-22'!$H95:$K95) -> 234869.6
B96: 16/08/2022 | C96: 1 | D96: 3 | E96: 74 | F96: 30638318470 | G96: =IFERROR(IF('Ago-22'!$F96="","-",VLOOKUP('Ago-22'!$F96,Lista_CUIT!$A$1:$D$1871,2,0)),"CUIT NO CARGADO") -> DELTA COMPRESION S.R.L | H96: 3109029 | J96: 326448.04 | L96: =SUM('Ago-22'!$H96:$K96) -> 3435477
B97: 16/08/2022 | C97: 1 | D97: 3 | E97: 75 | F97: 20124583463 | G97: =IFERROR(IF('Ago-22'!$F97="","-",VLOOKUP('Ago-22'!$F97,Lista_CUIT!$A$1:$D$1871,2,0)),"CUIT NO CARGADO") -> CUIT NO CARGADO | H97: 51817.15 | I97: ='Ago-22'!$H97*0.21 -> 10881.602 | L97: =SUM('Ago-22'!$H97:$K97) -> 62698.751
B98: 22/08/2022 | C98: 1 | D98: 3 | E98: 76 | F98: 30638318470 | G98: =IFERROR(IF('Ago-22'!$F98="","-",VLOOKUP('Ago-22'!$F98,Lista_CUIT!$A$1:$D$1871,2,0)),"CUIT NO CARGADO") -> DELTA COMPRESION S.R.L | H98: 3145527 | J98: 330280.33 | L98: =SUM('Ago-22'!$H98:$K98) -> 3475807.3
B99: 22/08/2022 | C99: 1 | D99: 3 | E99: 77 | F99: 30628274327 | G99: =IFERROR(IF('Ago-22'!$F99="","-",VLOOKUP('Ago-22'!$F99,Lista_CUIT!$A$1:$D$1871,2,0)),"CUIT NO CARGADO") -> AGIRA SA | H99: 52425.45 | I99: ='Ago-22'!$H99*0.21 -> 11009.344 | L99: =SUM('Ago-22'!$H99:$K99) -> 63434.794
B100: 25/08/2022 | C100: 1 | D100: 3 | E100: 78 | F100: 30574668715 | G100: =IFERROR(IF('Ago-22'!$F100="","-",VLOOKUP('Ago-22'!$F100,Lista_CUIT!$A$1:$D$1871,2,0)),"CUIT NO CARGADO") -> ESTACION DE SERVICIOS LAURENCENA S R L | H100: 47316.75 | I100: ='Ago-22'!$H100*0.21 -> 9936.5175 | L100: =SUM('Ago-22'!$H100:$K100) -> 57253.268
B101: Total | H101: =SUBTOTAL(109,'Ago-22'!$H$93:$H$100) -> 13720993 | I101: =SUBTOTAL(109,'Ago-22'!$I$93:$I$100) -> 253053.25 | J101: =SUBTOTAL(109,'Ago-22'!$J$93:$J$100) -> 1314178.5 | K101: =SUBTOTAL(109,'Ago-22'!$K$93:$K$100) -> 0 | L101: =SUBTOTAL(109,'Ago-22'!$L$93:$L$100) -> 15288225 | M101: =SUBTOTAL(103,'Ago-22'!$M$93:$M$100) -> 0
B104: VENTAS "B"
B105: FECHA | C105: TIPO | D105: PTO VENTA | E105: Nº FACTURA | F105: CUIT | G105: RAZON SOCIAL | H105: IMPORTE NETO | I105: IVA 21% | J105: IVA 10,5% | K105: EXENTO | L105: TOTAL | M105: Provincia
G106: =IFERROR(IF('Ago-22'!$F106="","-",VLOOKUP('Ago-22'!$F106,Lista_CUIT!$A$1:$D$1871,2,0)),"CUIT NO CARGADO") -> - | I106: ='Ago-22'!$H106*0.21 -> 0 | L106: =SUM('Ago-22'!$H106:$K106) -> 0
G107: =IFERROR(IF('Ago-22'!$F107="","-",VLOOKUP('Ago-22'!$F107,Lista_CUIT!$A$1:$D$1871,2,0)),"CUIT NO CARGADO") -> - | I107: ='Ago-22'!$H107*0.21 -> 0 | L107: =SUM('Ago-22'!$H107:$K107) -> 0
G108: =IFERROR(IF('Ago-22'!$F108="","-",VLOOKUP('Ago-22'!$F108,Lista_CUIT!$A$1:$D$1871,2,0)),"CUIT NO CARGADO") -> - | I108: ='Ago-22'!$H108*0.21 -> 0 | L108: =SUM('Ago-22'!$H108:$K108) -> 0
G109: =IFERROR(IF('Ago-22'!$F109="","-",VLOOKUP('Ago-22'!$F109,Lista_CUIT!$A$1:$D$1871,2,0)),"CUIT NO CARGADO") -> - | I109: ='Ago-22'!$H109*0.21 -> 0 | L109: =SUM('Ago-22'!$H109:$K109) -> 0
G110: =IFERROR(IF('Ago-22'!$F110="","-",VLOOKUP('Ago-22'!$F110,Lista_CUIT!$A$1:$D$1871,2,0)),"CUIT NO CARGADO") -> - | I110: ='Ago-22'!$H110*0.21 -> 0 | L110: =SUM('Ago-22'!$H110:$K110) -> 0
G111: =IFERROR(IF('Ago-22'!$F111="","-",VLOOKUP('Ago-22'!$F111,Lista_CUIT!$A$1:$D$1871,2,0)),"CUIT NO CARGADO") -> - | I111: ='Ago-22'!$H111*0.21 -> 0 | L111: =SUM('Ago-22'!$H111:$K111) -> 0
B112: Total | H112: =SUBTOTAL(109,'Ago-22'!$H$106:$H$111) -> 0 | I112: =SUBTOTAL(109,'Ago-22'!$I$106:$I$111) -> 0 | J112: =SUBTOTAL(109,'Ago-22'!$J$106:$J$111) -> 0 | K112: =SUBTOTAL(109,'Ago-22'!$K$106:$K$111) -> 0 | L112: =SUBTOTAL(109,'Ago-22'!$L$106:$L$111) -> 0 | M112: =SUBTOTAL(103,'Ago-22'!$M$106:$M$111) -> 0
C120: RETENCIONES
C121: FECHA | D121: COMP Nº | E121: Columna1 | F121: CUIT | G121: RAZON SOCIAL | H121: Ganancias | I121: IVA | J121: SUSS | K121: IIBB BSAS | L121: IIBB CABA
G122: =IFERROR(IF('Ago-22'!$F122="","-",VLOOKUP('Ago-22'!$F122,Lista_CUIT!$A$1:$D$1871,2,0)),"CUIT NO CARGADO") -> -
G123: =IFERROR(IF('Ago-22'!$F123="","-",VLOOKUP('Ago-22'!$F123,Lista_CUIT!$A$1:$D$1871,2,0)),"CUIT NO CARGADO") -> -
G124: =IFERROR(IF('Ago-22'!$F124="","-",VLOOKUP('Ago-22'!$F124,Lista_CUIT!$A$1:$D$1871,2,0)),"CUIT NO CARGADO") -> -
G125: =IFERROR(IF('Ago-22'!$F125="","-",VLOOKUP('Ago-22'!$F125,Lista_CUIT!$A$1:$D$1871,2,0)),"CUIT NO CARGADO") -> -
G126: =IFERROR(IF('Ago-22'!$F126="","-",VLOOKUP('Ago-22'!$F126,Lista_CUIT!$A$1:$D$1871,2,0)),"CUIT NO CARGADO") -> -

Sheet Sep-22
B1: LIBRO IVA COMPRAS | G1: ='Abr-22'!G1:M1 -> CORITEC S.R.L. | N1: =EDATE('Abr-22'!N1,5) -> 44805
B3: TOTAL COMPRAS | G3: TOTAL CREDITO FISCAL | J3: TOTAL VENTAS NETAS | M3: TOTAL DEBITO FISCAL | P3: RESULTADO
B4: =SUM('Sep-22'!$H$39)+'Sep-22'!$G$50 -> 5396704.9 | G4: ='Sep-22'!$I$39+'Sep-22'!$J$39+'Sep-22'!$K$39+'Sep-22'!$H$50+'Sep-22'!$I$50 -> 1133454.1 | J4: ='Sep-22'!$H$94+'Sep-22'!$H$105 -> 15626360 | M4: ='Sep-22'!$I$94+'Sep-22'!$J$94+'Sep-22'!$I$105+'Sep-22'!$J$105 -> 1916900.8 | P4: =G4-M4 -> -783446.77
B8: FECHA | C8: TIPO | D8: PTO VTA | E8: NRO. CPTE | F8: CUIT | G8: RAZON SOCIAL | H8: NETO GRAVADO | I8: IVA 21 % | J8: IVA 27% | K8: IVA 10,5% | L8: PERC. IVA | M8: PERC IIBB BS AS | N8: PERC. IIBB CABA | O8: Otros / No Grav. | P8: TOTAL | Q8: Tipo de Gasto | R8: Provincia
B9: 44805 | C9: 1 | D9: 7 | E9: 8715 | F9: 30690966790 | G9: =IFERROR(IF('Sep-22'!$F9="","-",VLOOKUP('Sep-22'!$F9,Lista_CUIT!$A$1:$D$1871,2,0)),"CUIT NO CARGADO") -> SUMINISTROS Y TUBERIAS | H9: 700997.14 | I9: =IF('Sep-22'!$H9="","",'Sep-22'!$H9*0.21) -> 147209.4 | P9: =SUM('Sep-22'!$H9:$O9) -> 848206.54 | Q9: =IFERROR(IF('Sep-22'!$F9="","-",VLOOKUP('Sep-22'!$F9,Lista_CUIT!$A$1:$D$1871,3,0)),"CUIT NO CARGADO") -> INSUMO | R9: =IFERROR(IF('Sep-22'!$F9="","-",VLOOKUP('Sep-22'!$F9,Lista_CUIT!$A$1:$D$1871,4,0)),"CUIT NO CARGADO") -> 0
B10: 44805 | C10: 1 | D10: 3 | E10: 267 | F10: 20921575743 | G10: =IFERROR(IF('Sep-22'!$F10="","-",VLOOKUP('Sep-22'!$F10,Lista_CUIT!$A$1:$D$1871,2,0)),"CUIT NO CARGADO") -> RIOS GOMEZ JOSE ANTONIO | H10: 182227.48 | I10: =IF('Sep-22'!$H10="","",'Sep-22'!$H10*0.21) -> 38267.771 | P10: =SUM('Sep-22'!$H10:$O10) -> 220495.25 | Q10: =IFERROR(IF('Sep-22'!$F10="","-",VLOOKUP('Sep-22'!$F10,Lista_CUIT!$A$1:$D$1871,3,0)),"CUIT NO CARGADO") -> Papeleria e Impresos | R10: =IFERROR(IF('Sep-22'!$F10="","-",VLOOKUP('Sep-22'!$F10,Lista_CUIT!$A$1:$D$1871,4,0)),"CUIT NO CARGADO") -> 0
B11: 44805 | C11: 1 | D11: 3 | E11: 569 | F11: 30715402765 | G11: =IFERROR(IF('Sep-22'!$F11="","-",VLOOKUP('Sep-22'!$F11,Lista_CUIT!$A$1:$D$1871,2,0)),"CUIT NO CARGADO") -> RIO 265 SRL | H11: 7768.62 | I11: =IF('Sep-22'!$H11="","",'Sep-22'!$H11*0.21) -> 1631.4102 | P11: =SUM('Sep-22'!$H11:$O11) -> 9400.0302 | Q11: =IFERROR(IF('Sep-22'!$F11="","-",VLOOKUP('Sep-22'!$F11,Lista_CUIT!$A$1:$D$1871,3,0)),"CUIT NO CARGADO") -> GTOS VARIOS-ESTACIONAMIENTO HORACIO | R11: =IFERROR(IF('Sep-22'!$F11="","-",VLOOKUP('Sep-22'!$F11,Lista_CUIT!$A$1:$D$1871,4,0)),"CUIT NO CARGADO") -> 0
B12: 44806 | C12: 1 | D12: 3 | E12: 166211 | F12: 30707135596 | G12: =IFERROR(IF('Sep-22'!$F12="","-",VLOOKUP('Sep-22'!$F12,Lista_CUIT!$A$1:$D$1871,2,0)),"CUIT NO CARGADO") -> CITILAN ARGENTINA SA | H12: 3075.6 | I12: =IF('Sep-22'!$H12="","",'Sep-22'!$H12*0.21) -> 645.876 | P12: =SUM('Sep-22'!$H12:$O12) -> 3721.476 | Q12: =IFERROR(IF('Sep-22'!$F12="","-",VLOOKUP('Sep-22'!$F12,Lista_CUIT!$A$1:$D$1871,3,0)),"CUIT NO CARGADO") -> SERVICIOS GAS, LUZ, ETC | R12: =IFERROR(IF('Sep-22'!$F12="","-",VLOOKUP('Sep-22'!$F12,Lista_CUIT!$A$1:$D$1871,4,0)),"CUIT NO CARGADO") -> 0
B13: 44809 | C13: 1 | D13: 3 | E13: 5 | F13: 20297899830 | G13: =IFERROR(IF('Sep-22'!$F13="","-",VLOOKUP('Sep-22'!$F13,Lista_CUIT!$A$1:$D$1871,2,0)),"CUIT NO CARGADO") -> FUNK MATIAS NICOLAS | H13: 797337.05 | I13: =IF('Sep-22'!$H13="","",'Sep-22'!$H13*0.21) -> 167440.78 | P13: =SUM('Sep-22'!$H13:$O13) -> 964777.83 | Q13: =IFERROR(IF('Sep-22'!$F13="","-",VLOOKUP('Sep-22'!$F13,Lista_CUIT!$A$1:$D$1871,3,0)),"CUIT NO CARGADO") -> Servicios Torneria | R13: =IFERROR(IF('Sep-22'!$F13="","-",VLOOKUP('Sep-22'!$F13,Lista_CUIT!$A$1:$D$1871,4,0)),"CUIT NO CARGADO") -> 0
B14: 44810 | C14: 1 | D14: 2 | E14: 143 | F14: 20125142851 | G14: =IFERROR(IF('Sep-22'!$F14="","-",VLOOKUP('Sep-22'!$F14,Lista_CUIT!$A$1:$D$1871,2,0)),"CUIT NO CARGADO") -> FEDERICI NICOLAS JOSE | H14: 28747.38 | I14: =IF('Sep-22'!$H14="","",'Sep-22'!$H14*0.21) -> 6036.9498 | P14: =SUM('Sep-22'!$H14:$O14) -> 34784.33 | Q14: =IFERROR(IF('Sep-22'!$F14="","-",VLOOKUP('Sep-22'!$F14,Lista_CUIT!$A$1:$D$1871,3,0)),"CUIT NO CARGADO") -> INSUMO | R14: =IFERROR(IF('Sep-22'!$F14="","-",VLOOKUP('Sep-22'!$F14,Lista_CUIT!$A$1:$D$1871,4,0)),"CUIT NO CARGADO") -> 0
B15: 44810 | C15: 1 | D15: 3 | E15: 4424 | F15: 30709665967 | G15: =IFERROR(IF('Sep-22'!$F15="","-",VLOOKUP('Sep-22'!$F15,Lista_CUIT!$A$1:$D$1871,2,0)),"CUIT NO CARGADO") -> INDUSTRIAS FEMAN SRL | H15: 1585706 | I15: =IF('Sep-22'!$H15="","",'Sep-22'!$H15*0.21) -> 332998.26 | P15: =SUM('Sep-22'!$H15:$O15) -> 1918704.3 | Q15: =IFERROR(IF('Sep-22'!$F15="","-",VLOOKUP('Sep-22'!$F15,Lista_CUIT!$A$1:$D$1871,3,0)),"CUIT NO CARGADO") -> MAT. PRIM. | R15: =IFERROR(IF('Sep-22'!$F15="","-",VLOOKUP('Sep-22'!$F15,Lista_CUIT!$A$1:$D$1871,4,0)),"CUIT NO CARGADO") -> 0
B16: 44811 | C16: 1 | D16: 589 | E16: 1300 | F16: 30590360763 | G16: =IFERROR(IF('Sep-22'!$F16="","-",VLOOKUP('Sep-22'!$F16,Lista_CUIT!$A$1:$D$1871,2,0)),"CUIT NO CARGADO") -> CENCOSUD S.A. | H16: 28999.17 | I16: =IF('Sep-22'!$H16="","",'Sep-22'!$H16*0.21) -> 6089.8257 | P16: =SUM('Sep-22'!$H16:$O16) -> 35088.996 | Q16: =IFERROR(IF('Sep-22'!$F16="","-",VLOOKUP('Sep-22'!$F16,Lista_CUIT!$A$1:$D$1871,3,0)),"CUIT NO CARGADO") -> Gastos Varios | R16: =IFERROR(IF('Sep-22'!$F16="","-",VLOOKUP('Sep-22'!$F16,Lista_CUIT!$A$1:$D$1871,4,0)),"CUIT NO CARGADO") -> 0
B17: 44811 | C17: 1 | D17: 12 | E17: 1223 | F17: 30694497701 | G17: =IFERROR(IF('Sep-22'!$F17="","-",VLOOKUP('Sep-22'!$F17,Lista_CUIT!$A$1:$D$1871,2,0)),"CUIT NO CARGADO") -> DECORALUM SRL | H17: 10445 | I17: =IF('Sep-22'!$H17="","",'Sep-22'!$H17*0.21) -> 2193.45 | P17: =SUM('Sep-22'!$H17:$O17) -> 12638.45 | Q17: =IFERROR(IF('Sep-22'!$F17="","-",VLOOKUP('Sep-22'!$F17,Lista_CUIT!$A$1:$D$1871,3,0)),"CUIT NO CARGADO") -> Gastos Varios | R17: =IFERROR(IF('Sep-22'!$F17="","-",VLOOKUP('Sep-22'!$F17,Lista_CUIT!$A$1:$D$1871,4,0)),"CUIT NO CARGADO") -> 0
B18: 44811 | C18: 1 | D18: 591 | E18: 1119 | F18: 30590360763 | G18: =IFERROR(IF('Sep-22'!$F18="","-",VLOOKUP('Sep-22'!$F18,Lista_CUIT!$A$1:$D$1871,2,0)),"CUIT NO CARGADO") -> CENCOSUD S.A. | H18: 8561.98 | I18: =IF('Sep-22'!$H18="","",'Sep-22'!$H18*0.21) -> 1798.0158 | P18: =SUM('Sep-22'!$H18:$O18) -> 10359.996 | Q18: =IFERROR(IF('Sep-22'!$F18="","-",VLOOKUP('Sep-22'!$F18,Lista_CUIT!$A$1:$D$1871,3,0)),"CUIT NO CARGADO") -> Gastos Varios | R18: =IFERROR(IF('Sep-22'!$F18="","-",VLOOKUP('Sep-22'!$F18,Lista_CUIT!$A$1:$D$1871,4,0)),"CUIT NO CARGADO") -> 0
B19: 44814 | C19: 1 | D19: 2 | E19: 10415 | F19: 30716675447 | G19: =IFERROR(IF('Sep-22'!$F19="","-",VLOOKUP('Sep-22'!$F19,Lista_CUIT!$A$1:$D$1871,2,0)),"CUIT NO CARGADO") -> DIXON TOOLS SA | H19: 2651.24 | I19: =IF('Sep-22'!$H19="","",'Sep-22'!$H19*0.21) -> 556.7604 | P19: =SUM('Sep-22'!$H19:$O19) -> 3208.0004 | Q19: =IFERROR(IF('Sep-22'!$F19="","-",VLOOKUP('Sep-22'!$F19,Lista_CUIT!$A$1:$D$1871,3,0)),"CUIT NO CARGADO") -> Gastos Oficina | R19: =IFERROR(IF('Sep-22'!$F19="","-",VLOOKUP('Sep-22'!$F19,Lista_CUIT!$A$1:$D$1871,4,0)),"CUIT NO CARGADO") -> 0
B20: 44815 | C20: 1 | D20: 2466 | E20: 409365 | F20: 30678814357 | G20: =IFERROR(IF('Sep-22'!$F20="","-",VLOOKUP('Sep-22'!$F20,Lista_CUIT!$A$1:$D$1871,2,0)),"CUIT NO CARGADO") -> Telefonica Moviles Argentina SA | H20: 2433.83 | J20: 657.13 | P20: =SUM('Sep-22'!$H20:$O20) -> 3090.96 | Q20: =IFERROR(IF('Sep-22'!$F20="","-",VLOOKUP('Sep-22'!$F20,Lista_CUIT!$A$1:$D$1871,3,0)),"CUIT NO CARGADO") -> SERVICIOS GAS, LUZ, ETC | R20: =IFERROR(IF('Sep-22'!$F20="","-",VLOOKUP('Sep-22'!$F20,Lista_CUIT!$A$1:$D$1871,4,0)),"CUIT NO CARGADO") -> 0
B21: 44816 | C21: 1 | D21: 2 | E21: 145 | F21: 20125142851 | G21: =IFERROR(IF('Sep-22'!$F21="","-",VLOOKUP('Sep-22'!$F21,Lista_CUIT!$A$1:$D$1871,2,0)),"CUIT NO CARGADO") -> FEDERICI NICOLAS JOSE | H21: 70671.62 | I21: =IF('Sep-22'!$H21="","",'Sep-22'!$H21*0.21) -> 14841.04 | P21: =SUM('Sep-22'!$H21:$O21) -> 85512.66 | Q21: =IFERROR(IF('Sep-22'!$F21="","-",VLOOKUP('Sep-22'!$F21,Lista_CUIT!$A$1:$D$1871,3,0)),"CUIT NO CARGADO") -> INSUMO | R21: =IFERROR(IF('Sep-22'!$F21="","-",VLOOKUP('Sep-22'!$F21,Lista_CUIT!$A$1:$D$1871,4,0)),"CUIT NO CARGADO") -> 0
B22: 44816 | C22: 1 | D22: 16 | E22: 309 | F22: 30716668750 | G22: =IFERROR(IF('Sep-22'!$F22="","-",VLOOKUP('Sep-22'!$F22,Lista_CUIT!$A$1:$D$1871,2,0)),"CUIT NO CARGADO") -> BIKE CLUB SRL | H22: 7554.08 | I22: =IF('Sep-22'!$H22="","",'Sep-22'!$H22*0.21) -> 1586.3568 | P22: =SUM('Sep-22'!$H22:$O22) -> 9140.4368 | Q22: =IFERROR(IF('Sep-22'!$F22="","-",VLOOKUP('Sep-22'!$F22,Lista_CUIT!$A$1:$D$1871,3,0)),"CUIT NO CARGADO") -> Gastos Varios | R22: =IFERROR(IF('Sep-22'!$F22="","-",VLOOKUP('Sep-22'!$F22,Lista_CUIT!$A$1:$D$1871,4,0)),"CUIT NO CARGADO") -> 0
B23: 44816 | C23: 1 | D23: 2 | E23: 144 | F23: 20125142851 | G23: =IFERROR(IF('Sep-22'!$F23="","-",VLOOKUP('Sep-22'!$F23,Lista_CUIT!$A$1:$D$1871,2,0)),"CUIT NO CARGADO") -> FEDERICI NICOLAS JOSE | H23: 64838.76 | I23: =IF('Sep-22'!$H23="","",'Sep-22'!$H23*0.21) -> 13616.14 | P23: =SUM('Sep-22'!$H23:$O23) -> 78454.9 | Q23: =IFERROR(IF('Sep-22'!$F23="","-",VLOOKUP('Sep-22'!$F23,Lista_CUIT!$A$1:$D$1871,3,0)),"CUIT NO CARGADO") -> INSUMO | R23: =IFERROR(IF('Sep-22'!$F23="","-",VLOOKUP('Sep-22'!$F23,Lista_CUIT!$A$1:$D$1871,4,0)),"CUIT NO CARGADO") -> 0
B24: 44817 | C24: 1 | D24: 7 | E24: 8555 | F24: 30604413482 | G24: =IFERROR(IF('Sep-22'!$F24="","-",VLOOKUP('Sep-22'!$F24,Lista_CUIT!$A$1:$D$1871,2,0)),"CUIT NO CARGADO") -> BULONERA VIETRI SRL | H24: 15660 | I24: =IF('Sep-22'!$H24="","",'Sep-22'!$H24*0.21) -> 3288.6 | P24: =SUM('Sep-22'!$H24:$O24) -> 18948.6 | Q24: =IFERROR(IF('Sep-22'!$F24="","-",VLOOKUP('Sep-22'!$F24,Lista_CUIT!$A$1:$D$1871,3,0)),"CUIT NO CARGADO") -> INSUMO | R24: =IFERROR(IF('Sep-22'!$F24="","-",VLOOKUP('Sep-22'!$F24,Lista_CUIT!$A$1:$D$1871,4,0)),"CUIT NO CARGADO") -> 0
B25: 44818 | C25: 1 | D25: 12 | E25: 1700 | F25: 30707097465 | G25: =IFERROR(IF('Sep-22'!$F25="","-",VLOOKUP('Sep-22'!$F25,Lista_CUIT!$A$1:$D$1871,2,0)),"CUIT NO CARGADO") -> BIKE GROUP SA | H25: 28207.24 | I25: =IF('Sep-22'!$H25="","",'Sep-22'!$H25*0.21) -> 5923.5204 | P25: =SUM('Sep-22'!$H25:$O25) -> 34130.76 | Q25: =IFERROR(IF('Sep-22'!$F25="","-",VLOOKUP('Sep-22'!$F25,Lista_CUIT!$A$1:$D$1871,3,0)),"CUIT NO CARGADO") -> INSUMO | R25: =IFERROR(IF('Sep-22'!$F25="","-",VLOOKUP('Sep-22'!$F25,Lista_CUIT!$A$1:$D$1871,4,0)),"CUIT NO CARGADO") -> 0
B26: 44820 | C26: 1 | D26: 5 | E26: 4516 | F26: 33711557119 | G26: =IFERROR(IF('Sep-22'!$F26="","-",VLOOKUP('Sep-22'!$F26,Lista_CUIT!$A$1:$D$1871,2,0)),"CUIT NO CARGADO") -> ELECTROMINGO SRL | H26: 3050.99 | I26: =IF('Sep-22'!$H26="","",'Sep-22'!$H26*0.21) -> 640.7079 | P26: =SUM('Sep-22'!$H26:$O26) -> 3691.6979 | Q26: =IFERROR(IF('Sep-22'!$F26="","-",VLOOKUP('Sep-22'!$F26,Lista_CUIT!$A$1:$D$1871,3,0)),"CUIT NO CARGADO") -> MAT. PRIM. | R26: =IFERROR(IF('Sep-22'!$F26="","-",VLOOKUP('Sep-22'!$F26,Lista_CUIT!$A$1:$D$1871,4,0)),"CUIT NO CARGADO") -> 0
B27: 44823 | C27: 1 | D27: 10 | E27: 9010 | F27: 30702073657 | G27: =IFERROR(IF('Sep-22'!$F27="","-",VLOOKUP('Sep-22'!$F27,Lista_CUIT!$A$1:$D$1871,2,0)),"CUIT NO CARGADO") -> MICROELECTRONICA COMP. SRL | H27: 50397.76 | I27: =IF('Sep-22'!$H27="","",'Sep-22'!$H27*0.21) -> 10583.53 | P27: =SUM('Sep-22'!$H27:$O27) -> 60981.29 | Q27: =IFERROR(IF('Sep-22'!$F27="","-",VLOOKUP('Sep-22'!$F27,Lista_CUIT!$A$1:$D$1871,3,0)),"CUIT NO CARGADO") -> MAT. PRIM. | R27: =IFERROR(IF('Sep-22'!$F27="","-",VLOOKUP('Sep-22'!$F27,Lista_CUIT!$A$1:$D$1871,4,0)),"CUIT NO CARGADO") -> 0
B28: 44823 | C28: 1 | D28: 60 | E28: 7773 | F28: 30547188760 | G28: =IFERROR(IF('Sep-22'!$F28="","-",VLOOKUP('Sep-22'!$F28,Lista_CUIT!$A$1:$D$1871,2,0)),"CUIT NO CARGADO") -> LONCO HUE SA | H28: 78303.49 | I28: =IF('Sep-22'!$H28="","",'Sep-22'!$H28*0.21) -> 16443.733 | P28: =SUM('Sep-22'!$H28:$O28) -> 94747.223 | Q28: =IFERROR(IF('Sep-22'!$F28="","-",VLOOKUP('Sep-22'!$F28,Lista_CUIT!$A$1:$D$1871,3,0)),"CUIT NO CARGADO") -> INSUMO | R28: =IFERROR(IF('Sep-22'!$F28="","-",VLOOKUP('Sep-22'!$F28,Lista_CUIT!$A$1:$D$1871,4,0)),"CUIT NO CARGADO") -> 0
B29: 44824 | C29: 1 | D29: 5 | E29: 802 | F29: 23275937959 | G29: =IFERROR(IF('Sep-22'!$F29="","-",VLOOKUP('Sep-22'!$F29,Lista_CUIT!$A$1:$D$1871,2,0)),"CUIT NO CARGADO") -> ESPOSITO PABLO JOSE | H29: 462.94 | I29: =IF('Sep-22'!$H29="","",'Sep-22'!$H29*0.21) -> 97.2174 | P29: =SUM('Sep-22'!$H29:$O29) -> 560.1574 | Q29: =IFERROR(IF('Sep-22'!$F29="","-",VLOOKUP('Sep-22'!$F29,Lista_CUIT!$A$1:$D$1871,3,0)),"CUIT NO CARGADO") -> Gastos Oficina | R29: =IFERROR(IF('Sep-22'!$F29="","-",VLOOKUP('Sep-22'!$F29,Lista_CUIT!$A$1:$D$1871,4,0)),"CUIT NO CARGADO") -> 0
B30: 44825 | C30: 1 | D30: 2 | E30: 546 | F30: 20296550184 | G30: =IFERROR(IF('Sep-22'!$F30="","-",VLOOKUP('Sep-22'!$F30,Lista_CUIT!$A$1:$D$1871,2,0)),"CUIT NO CARGADO") -> COSTA DIEGO ALEJANDRO | H30: 33560 | I30: =IF('Sep-22'!$H30="","",'Sep-22'!$H30*0.21) -> 7047.6 | P30: =SUM('Sep-22'!$H30:$O30) -> 40607.6 | Q30: =IFERROR(IF('Sep-22'!$F30="","-",VLOOKUP('Sep-22'!$F30,Lista_CUIT!$A$1:$D$1871,3,0)),"CUIT NO CARGADO") -> MAT. PRIM. | R30: =IFERROR(IF('Sep-22'!$F30="","-",VLOOKUP('Sep-22'!$F30,Lista_CUIT!$A$1:$D$1871,4,0)),"CUIT NO CARGADO") -> 0
B31: 44826 | C31: 1 | D31: 1 | E31: 501 | F31: 30715048066 | G31: =IFERROR(IF('Sep-22'!$F31="","-",VLOOKUP('Sep-22'!$F31,Lista_CUIT!$A$1:$D$1871,2,0)),"CUIT NO CARGADO") -> ROLLS Y EMPANADAS SA | H31: 119310 | I31: =IF('Sep-22'!$H31="","",'Sep-22'!$H31*0.21) -> 25055.1 | P31: =SUM('Sep-22'!$H31:$O31) -> 144365.1 | Q31: =IFERROR(IF('Sep-22'!$F31="","-",VLOOKUP('Sep-22'!$F31,Lista_CUIT!$A$1:$D$1871,3,0)),"CUIT NO CARGADO") -> CATERING | R31: =IFERROR(IF('Sep-22'!$F31="","-",VLOOKUP('Sep-22'!$F31,Lista_CUIT!$A$1:$D$1871,4,0)),"CUIT NO CARGADO") -> 0
B32: 44828 | C32: 1 | D32: 3 | E32: 1079695 | F32: 30712019359 | G32: =IFERROR(IF('Sep-22'!$F32="","-",VLOOKUP('Sep-22'!$F32,Lista_CUIT!$A$1:$D$1871,2,0)),"CUIT NO CARGADO") -> LINKEDSTORE ARGENTINA S.R.L. | H32: 3304.96 | I32: =IF('Sep-22'!$H32="","",'Sep-22'!$H32*0.21) -> 694.0416 | P32: =SUM('Sep-22'!$H32:$O32) -> 3999.0016 | Q32: =IFERROR(IF('Sep-22'!$F32="","-",VLOOKUP('Sep-22'!$F32,Lista_CUIT!$A$1:$D$1871,3,0)),"CUIT NO CARGADO") -> Gastos Varios | R32: =IFERROR(IF('Sep-22'!$F32="","-",VLOOKUP('Sep-22'!$F32,Lista_CUIT!$A$1:$D$1871,4,0)),"CUIT NO CARGADO") -> 0
... B36: 44833 | C36: 1 | D36: 5 | E36: 843 | F36: 30707397256 | G36: =IFERROR(IF('Sep-22'!$F36="","-",VLOOKUP('Sep-22'!$F36,Lista_CUIT!$A$1:$D$1871,2,0)),"CUIT NO CARGADO") -> GRAFICA Y FOTOGRABADOS LA PLAZA SRL | H36: 316735.3 | I36: =IF('Sep-22'!$H36="","",'Sep-22'!$H36*0.21) -> 66514.413 | P36: =SUM('Sep-22'!$H36:$O36) -> 383249.71 | Q36: =IFERROR(IF('Sep-22'!$F36="","-",VLOOKUP('Sep-22'!$F36,Lista_CUIT!$A$1:$D$1871,3,0)),"CUIT NO CARGADO") -> Fotograbados | R36: =IFERROR(IF('Sep-22'!$F36="","-",VLOOKUP('Sep-22'!$F36,Lista_CUIT!$A$1:$D$1871,4,0)),"CUIT NO CARGADO") -> 0
B37: 44806 | C37: 1 | D37: 280 | E37: 1387056 | F37: 30580111315 | G37: =IFERROR(IF('Sep-22'!$F37="","-",VLOOKUP('Sep-22'!$F37,Lista_CUIT!$A$1:$D$1871,2,0)),"CUIT NO CARGADO") -> DHL EXPRESS ARG SA | H37: 441703.87 | I37: =IF('Sep-22'!$H37="","",'Sep-22'!$H37*0.21) -> 92757.813 | O37: -367674.56 | P37: =SUM('Sep-22'!$H37:$O37) -> 166787.12 | Q37: =IFERROR(IF('Sep-22'!$F37="","-",VLOOKUP('Sep-22'!$F37,Lista_CUIT!$A$1:$D$1871,3,0)),"CUIT NO CARGADO") -> GTOS IMP. | R37: =IFERROR(IF('Sep-22'!$F37="","-",VLOOKUP('Sep-22'!$F37,Lista_CUIT!$A$1:$D$1871,4,0)),"CUIT NO CARGADO") -> 0
B38: 44819 | C38: 1 | D38: 280 | E38: 1389520 | F38: 30580111315 | G38: =IFERROR(IF('Sep-22'!$F38="","-",VLOOKUP('Sep-22'!$F38,Lista_CUIT!$A$1:$D$1871,2,0)),"CUIT NO CARGADO") -> DHL EXPRESS ARG SA | H38: 452316.64 | I38: =IF('Sep-22'!$H38="","",'Sep-22'!$H38*0.21) -> 94986.495 | O38: -376495.94 | P38: =SUM('Sep-22'!$H38:$O38) -> 170807.2 | Q38: =IFERROR(IF('Sep-22'!$F38="","-",VLOOKUP('Sep-22'!$F38,Lista_CUIT!$A$1:$D$1871,3,0)),"CUIT NO CARGADO") -> GTOS IMP. | R38: =IFERROR(IF('Sep-22'!$F38="","-",VLOOKUP('Sep-22'!$F38,Lista_CUIT!$A$1:$D$1871,4,0)),"CUIT NO CARGADO") -> 0
B39: Total | H39: =SUBTOTAL(109,'Sep-22'!$H$9:$H$38) -> 5376896 | I39: =SUBTOTAL(109,'Sep-22'!$I$9:$I$38) -> 1128637.1 | J39: =SUBTOTAL(109,'Sep-22'!$J$9:$J$38) -> 657.13 | K39: =SUBTOTAL(109,'Sep-22'!$K$9:$K$38) -> 0 | L39: =SUBTOTAL(109,'Sep-22'!$L$9:$L$38) -> 0 | M39: =SUBTOTAL(109,'Sep-22'!$M$9:$M$38) -> 0 | N39: =SUBTOTAL(109,'Sep-22'!$N$9:$N$38) -> 0 | O39: =SUBTOTAL(109,'Sep-22'!$O$9:$O$38) -> -744170.5 | P39: =SUBTOTAL(109,'Sep-22'!$P$9:$P$38) -> 5762019.7
D44: LIQUIDACION EXTRACTOS BANCARIOS-TARJETAS
D45: FECHA | E45: NRO CPTE | F45: BANCO | G45: NETO | H45: IVA 21% | I45: IVA 10,5% | J45: RET IIBB CABA | K45: PERC IVA | L45: PERC IIBB
F46: Anticipos - Fin Ext
D47: 44826 | E47: 617-492518000 | F47: Liq. Pagos Antic. | G47: 16662.35 | H47: 3499.0935 | K47: 499.87
D48: 44834 | F48: Extracto Credicoop | G48: 3018.5238 | H48: 633.89
F49: VISA CREDITO | G49: 128 | H49: 26.88
D50: Total | G50: =SUBTOTAL(109,'Sep-22'!$G$46:$G$49) -> 19808.874 | H50: =SUBTOTAL(109,'Sep-22'!$H$46:$H$49) -> 4159.8635 | I50: =SUBTOTAL(109,'Sep-22'!$I$46:$I$49) -> 0 | J50: =SUBTOTAL(109,'Sep-22'!$J$46:$J$49) -> 0 | K50: =SUBTOTAL(109,'Sep-22'!$K$46:$K$49) -> 499.87 | L50: =SUBTOTAL(109,'Sep-22'!$L$46:$L$49) -> 0
D53: FACTURAS C
D54: FECHA | E54: PTO VTA | F54: FC Nº | G54: CUIT | H54: RAZON SOCIAL | I54: TOTAL | J54: TIPO DE GASTO | K54: Provincia
D55: 01/09/2022 | E55: 2 | F55: 118 | G55: 20136544625 | H55: =IFERROR(IF('Sep-22'!$G55="","-",VLOOKUP('Sep-22'!$G55,Lista_CUIT!$A$1:$D$1871,2,0)),"CUIT NO CARGADO") -> RODRIGUEZ DE LA FUEN HECTOR MARCELO | I55: 40000 | J55: =IFERROR(IF('Sep-22'!$G55="","-",VLOOKUP('Sep-22'!$G55,Lista_CUIT!$A$1:$D$1871,3,0)),"CUIT NO CARGADO") -> Honorarios Administrativos-Cobranzas y Gestion Clientes | K55: =IFERROR(IF('Sep-22'!$G55="","-",VLOOKUP('Sep-22'!$G55,Lista_CUIT!$A$1:$D$1871,4,0)),"CUIT NO CARGADO") -> 0
D56: 01/09/2022 | E56: 3 | F56: 619 | G56: 20086277523 | H56: =IFERROR(IF('Sep-22'!$G56="","-",VLOOKUP('Sep-22'!$G56,Lista_CUIT!$A$1:$D$1871,2,0)),"CUIT NO CARGADO") -> JUAN CARLOS BOTINDARI | I56: 51900 | J56: =IFERROR(IF('Sep-22'!$G56="","-",VLOOKUP('Sep-22'!$G56,Lista_CUIT!$A$1:$D$1871,3,0)),"CUIT NO CARGADO") -> HONORARIOS | K56: =IFERROR(IF('Sep-22'!$G56="","-",VLOOKUP('Sep-22'!$G56,Lista_CUIT!$A$1:$D$1871,4,0)),"CUIT NO CARGADO") -> 0
D57: 05/09/2022 | E57: 1 | F57: 88 | G57: 20341465134 | H57: =IFERROR(IF('Sep-22'!$G57="","-",VLOOKUP('Sep-22'!$G57,Lista_CUIT!$A$1:$D$1871,2,0)),"CUIT NO CARGADO") -> ABELEDO AGUSTIN ENRIQUE | I57: 131400 | J57: =IFERROR(IF('Sep-22'!$G57="","-",VLOOKUP('Sep-22'!$G57,Lista_CUIT!$A$1:$D$1871,3,0)),"CUIT NO CARGADO") -> HONOR. INGENIERO | K57: =IFERROR(IF('Sep-22'!$G57="","-",VLOOKUP('Sep-22'!$G57,Lista_CUIT!$A$1:$D$1871,4,0)),"CUIT NO CARGADO") -> 0
D58: 06/09/2022 | E58: 1 | F58: 17 | G58: 27925308884 | H58: =IFERROR(IF('Sep-22'!$G58="","-",VLOOKUP('Sep-22'!$G58,Lista_CUIT!$A$1:$D$1871,2,0)),"CUIT NO CARGADO") -> LOPEZ LOPEZ FLAVIA | I58: 1000 | J58: =IFERROR(IF('Sep-22'!$G58="","-",VLOOKUP('Sep-22'!$G58,Lista_CUIT!$A$1:$D$1871,3,0)),"CUIT NO CARGADO") -> FLETE | K58: =IFERROR(IF('Sep-22'!$G58="","-",VLOOKUP('Sep-22'!$G58,Lista_CUIT!$A$1:$D$1871,4,0)),"CUIT NO CARGADO") -> 0
D59: 06/09/2022 | E59: 4 | F59: 5 | G59: 20341462933 | H59: =IFERROR(IF('Sep-22'!$G59="","-",VLOOKUP('Sep-22'!$G59,Lista_CUIT!$A$1:$D$1871,2,0)),"CUIT NO CARGADO") -> CASTIGLIONI MATIAS EZEQUIEL | I59: 195000 | J59: =IFERROR(IF('Sep-22'!$G59="","-",VLOOKUP('Sep-22'!$G59,Lista_CUIT!$A$1:$D$1871,3,0)),"CUIT NO CARGADO") -> MAT. PRIM. | K59: =IFERROR(IF('Sep-22'!$G59="","-",VLOOKUP('Sep-22'!$G59,Lista_CUIT!$A$1:$D$1871,4,0)),"CUIT NO CARGADO") -> 0
D60: 06/09/2022 | E60: 1 | F60: 16 | G60: 27925308884 | H60: =IFERROR(IF('Sep-22'!$G60="","-",VLOOKUP('Sep-22'!$G60,Lista_CUIT!$A$1:$D$1871,2,0)),"CUIT NO CARGADO") -> LOPEZ LOPEZ FLAVIA | I60: 8000 | J60: =IFERROR(IF('Sep-22'!$G60="","-",VLOOKUP('Sep-22'!$G60,Lista_CUIT!$A$1:$D$1871,3,0)),"CUIT NO CARGADO") -> FLETE | K60: =IFERROR(IF('Sep-22'!$G60="","-",VLOOKUP('Sep-22'!$G60,Lista_CUIT!$A$1:$D$1871,4,0)),"CUIT NO CARGADO") -> 0
D61: 08/09/2022 | E61: 3 | F61: 621 | G61: 20086277523 | H61: =IFERROR(IF('Sep-22'!$G61="","-",VLOOKUP('Sep-22'!$G61,Lista_CUIT!$A$1:$D$1871,2,0)),"CUIT NO CARGADO") -> JUAN CARLOS BOTINDARI | I61: 9870 | J61: =IFERROR(IF('Sep-22'!$G61="","-",VLOOKUP('Sep-22'!$G61,Lista_CUIT!$A$1:$D$1871,3,0)),"CUIT NO CARGADO") -> HONORARIOS | K61: =IFERROR(IF('Sep-22'!$G61="","-",VLOOKUP('Sep-22'!$G61,Lista_CUIT!$A$1:$D$1871,4,0)),"CUIT NO CARGADO") -> 0
D62: 16/09/2022 | E62: 2 | F62: 75 | G62: 20244271740 | H62: =IFERROR(IF('Sep-22'!$G62="","-",VLOOKUP('Sep-22'!$G62,Lista_CUIT!$A$1:$D$1871,2,0)),"CUIT NO CARGADO") -> KENNEL SEBASTIAN | I62: 195300 | J62: =IFERROR(IF('Sep-22'!$G62="","-",VLOOKUP('Sep-22'!$G62,Lista_CUIT!$A$1:$D$1871,3,0)),"CUIT NO CARGADO") -> SOFTWARE MANTENIMIENTO | K62: =IFERROR(IF('Sep-22'!$G62="","-",VLOOKUP('Sep-22'!$G62,Lista_CUIT!$A$1:$D$1871,4,0)),"CUIT NO CARGADO") -> 0
D63: 16/09/2022 | E63: 3 | F63: 30 | G63: 20403931420 | H63: =IFERROR(IF('Sep-22'!$G63="","-",VLOOKUP('Sep-22'!$G63,Lista_CUIT!$A$1:$D$1871,2,0)),"CUIT NO CARGADO") -> FIORENTINO JORGE IGNACIO | I63: 117050 | J63: =IFERROR(IF('Sep-22'!$G63="","-",VLOOKUP('Sep-22'!$G63,Lista_CUIT!$A$1:$D$1871,3,0)),"CUIT NO CARGADO") -> Honorarios Administrativos-Cobranzas y Gestion Clientes | K63: =IFERROR(IF('Sep-22'!$G63="","-",VLOOKUP('Sep-22'!$G63,Lista_CUIT!$A$1:$D$1871,4,0)),"CUIT NO CARGADO") -> 0
D64: 19/09/2022 | E64: 1 | F64: 10 | G64: 20417805878 | H64: =IFERROR(IF('Sep-22'!$G64="","-",VLOOKUP('Sep-22'!$G64,Lista_CUIT!$A$1:$D$1871,2,0)),"CUIT NO CARGADO") -> FERABOLI OSPAL SANTIAGO HERNAN | I64: 127720 | J64: =IFERROR(IF('Sep-22'!$G64="","-",VLOOKUP('Sep-22'!$G64,Lista_CUIT!$A$1:$D$1871,3,0)),"CUIT NO CARGADO") -> Control medidores masicos | K64: =IFERROR(IF('Sep-22'!$G64="","-",VLOOKUP('Sep-22'!$G64,Lista_CUIT!$A$1:$D$1871,4,0)),"CUIT NO CARGADO") -> 0
D65: 19/09/2022 | E65: 2 | F65: 577 | G65: 20320877947 | H65: =IFERROR(IF('Sep-22'!$G65="","-",VLOOKUP('Sep-22'!$G65,Lista_CUIT!$A$1:$D$1871,2,0)),"CUIT NO CARGADO") -> ROUSSEAU PABLO ANDRES | I65: 9800 | J65: =IFERROR(IF('Sep-22'!$G65="","-",VLOOKUP('Sep-22'!$G65,Lista_CUIT!$A$1:$D$1871,3,0)),"CUIT NO CARGADO") -> SERVICIO | K65: =IFERROR(IF('Sep-22'!$G65="","-",VLOOKUP('Sep-22'!$G65,Lista_CUIT!$A$1:$D$1871,4,0)),"CUIT NO CARGADO") -> 0
D66: 20/09/2022 | E66: 2 | F66: 14 | G66: 23326777269 | H66: =IFERROR(IF('Sep-22'!$G66="","-",VLOOKUP('Sep-22'!$G66,Lista_CUIT!$A$1:$D$1871,2,0)),"CUIT NO CARGADO") -> DE BONIS IGNACIO LUIS | I66: 178230 | J66: =IFERROR(IF('Sep-22'!$G66="","-",VLOOKUP('Sep-22'!$G66,Lista_CUIT!$A$1:$D$1871,3,0)),"CUIT NO CARGADO") -> Control medidores masicos | K66: =IFERROR(IF('Sep-22'!$G66="","-",VLOOKUP('Sep-22'!$G66,Lista_CUIT!$A$1:$D$1871,4,0)),"CUIT NO CARGADO") -> 0
... D70: 26/09/2022 | E70: 2 | F70: 432 | G70: 20400104094 | H70: =IFERROR(IF('Sep-22'!$G70="","-",VLOOKUP('Sep-22'!$G70,Lista_CUIT!$A$1:$D$1871,2,0)),"CUIT NO CARGADO") -> FEDERICO BOTINDARI | I70: 165000 | J70: =IFERROR(IF('Sep-22'!$G70="","-",VLOOKUP('Sep-22'!$G70,Lista_CUIT!$A$1:$D$1871,3,0)),"CUIT NO CARGADO") -> HONORARIOS | K70: =IFERROR(IF('Sep-22'!$G70="","-",VLOOKUP('Sep-22'!$G70,Lista_CUIT!$A$1:$D$1871,4,0)),"CUIT NO CARGADO") -> 0
D71: 27/09/2022 | E71: 2 | F71: 90 | G71: 27125997835 | I71: 66000 | J71: =IFERROR(IF('Sep-22'!$G71="","-",VLOOKUP('Sep-22'!$G71,Lista_CUIT!$A$1:$D$1871,3,0)),"CUIT NO CARGADO") -> Honorarios Legales | K71: =IFERROR(IF('Sep-22'!$G71="","-",VLOOKUP('Sep-22'!$G71,Lista_CUIT!$A$1:$D$1871,4,0)),"CUIT NO CARGADO") -> 0
D72: 27/09/2022 | E72: 2 | F72: 89 | G72: 27125997835 | H72: =IFERROR(IF('Sep-22'!$G72="","-",VLOOKUP('Sep-22'!$G72,Lista_CUIT!$A$1:$D$1871,2,0)),"CUIT NO CARGADO") -> DANSKY ULLMANN VIVIANA EVA YOLANDA | I72: 66000 | J72: =IFERROR(IF('Sep-22'!$G72="","-",VLOOKUP('Sep-22'!$G72,Lista_CUIT!$A$1:$D$1871,3,0)),"CUIT NO CARGADO") -> Honorarios Legales | K72: =IFERROR(IF('Sep-22'!$G72="","-",VLOOKUP('Sep-22'!$G72,Lista_CUIT!$A$1:$D$1871,4,0)),"CUIT NO CARGADO") -> 0
