Workbook

Sheet Lista_CUIT
A1: CUIT | B1: RAZON SOCIAL | C1: Tipo de Gasto | D1: PROVINCIA
A2: =21779325 -> 21779325 | B2: BERAN Claudia Beatriz | C2: Gastos mantenimiento | G2: Mercaderia
A3: =12999779 -> 12999779 | B3: CORBALAN, MAFALDA ISABEL | G3: Servicios Gas, Luz, etc.
A4: =475785 -> 475785 | B4: GARCIA Ricardo Enrique | G4: Gastos catering
A5: =32052462 -> 32052462 | B5: Graells Luis Miguel | G5: Combustibe
A6: 33709585229 | B6: GOOGLE ARGENTINA S.R.L. | C6: Gastos Publicidad y Propaganda | G6: Gastos Varios
A7: 30526874249 | B7: FRAVEGA S A C I E I | C7: Gastos comercializacion | G7: Gastos seguridad
A8: 30716711621 | B8: TC TIENDAS AR S.R.L. | C8: insumos | D8: BUENOS AIRES | G8: Librería
A9: 30713550201 | B9: WAIKI S.A. | G9: Gastos mantenimiento
A10: 20357182914 | B10: GAIGA RENZO MIGUEL | G10: Gastos comercializacion
A11: 30715380567 | B11: SENS GROUP SRL | G11: Alquiler
A12: 33716435909 | B12: F&R S.A.S. | G12: Honorarios contables
A13: 30715313967 | B13: JD SOURCING S.R.L | G13: Gastos administrativos
A14: 27240934499 | B14: VITTOR LORENA MARCELA | G14: Seguro
A15: 20367341808 | B15: FEIDAS FERNANDO EMILIANO | G15: Extracto
A16: 30717477681 | B16: GRUPO FAM SA | G16: Flete
A17: 30717973166 | B17: STM ESTILO S.R.L | G17: Honorarios Legales
A18: 30717170594 | B18: INDUSTRIA4 S.R.L. | G18: Insumo
A19: 30716778041 | B19: PERROS Y GATOS FOOD S.A.S. | G19: Muebles y Utiles
A20: 20284212488 | B20: BARLETTA MAXIMILIANO SEBASTIAN | G20: Otros
... A23: 20252582704 | B23: GARCIA VAUTRIN ANDRES ALBERTO | G23: Gastos Publicidad y Propaganda
A24: 20391525227 | B24: BARISCI MATIAS NICOLAS
A25: 30715380567 | B25: SENS GROUP SRL
A26: 20367341808 | B26: FEIDAS FERNANDO EMILIANO
A27: 33716435909 | B27: F&R S.A.S.
A28: 30708026200 | B28: BORGES BUENOS AIRES SRL
A29: 30707040900 | B29: TODOVISION S.A
A30: 23380288079 | B30: CASTROMAN AGUSTIN | C30: Diseño Grafico
A31: 27341104845 | B31: BOSSI MARIA PAULA | C31: HON. ADMINISTRATIVOS
A32: 20300985158 | B32: GONZALEZ NESTOR RICARDO | C32: Diseño Grafico
A33: 33712058019 | B33: FLEET KYAN SRL
A34: 20369492528 | B34: GRIMALDI NICOLAS
A35: 20202853391 | B35: MATTEO DANIEL ERNESTO
A36: 27165844748 | B36: DENATALE MARCELA BEATRIZ
A37: 30716797437 | B37: PEISER
A38: 20287305460 | B38: LANDI GERONIMO
A39: 30710008635 | B39: CENTRO DE ENTRENAMIENTO DE MANEJO S.A.
A40: 30716914077 | B40: BACANES
A41: 20279415656 | B41: CECCO ALVARO GONZALO
A42: 30681452423 | B42: E S B A LUGANO S A
A43: 30700477920 | B43: ESBA FLORESS A
A44: 30521448608 | B44: INSTITUTO ORSINO SA
A45: 29811544 | B45: ROSSO FAVIO DANIEL
A46: 30710173652 | B46: DATTATEC.COM S.R.L. | C46: Gastos Publicidad y Propaganda
A47: 33708727569 | B47: MARQUISAS SA
A48: 30717465101 | B48: EMPRENDIMIENTOS SHOPGLASS S. R. L.
A49: 20132082198 | B49: FADIGA OSCAR ALBERTO
A50: 30592508830 | B50: INSTITUTO DE ESTUDIOS SUPERIORES DE BUENOS AIRES S A
A51: 20246239364 | B51: ARAUJO CARLOS MARTIN
A52: 30717969061 | B52: FABIO Y RAUL ROSSO S.A.S.
A53: 30516186670 | B53: DEHEZA SOCIEDAD ANONIMA INDUSTRIAL COMERCIAL FINANCIERA INMOBILIARIA | C53: COMBUSTIBLE
A54: 27386311000 | B54: OPANASIUK MACARENA ANTONELLA | C54: Honorarios Profesionales
A55: 20400104094 | B55: BOTINDARI FEDERICO DANIEL | C55: HONORARIOS CONTABLE
A56: 30688955749 | B56: LISERAR S A
A57: 30716234815 | B57: LEVINT PARTNERS S.R.L.
A58: 20319747975 | B58: CRESPO LEONARDO GUILLERMO
A59: 20369499956 | B59: LAMARI FRANCO AGUSTIN
A60: 20178248201 | B60: FRANCISCO ADRIAN MARCELO
A61: 30716549107 | B61: LAMATEC S.R.L.
A62: 20320573948 | B62: CAVALLOTTI MARCOS DANIEL
A63: 20277452872 | B63: GERVASI MAXIMILIANO ARIEL
A64: 20238882975 | B64: NARVAEZ SANTIAGO GABRIEL
A65: 27312707980 | B65: FERRARETTO CARLA ROMINA
A66: 30718044894 | B66: GRUPO NACER ECOLOGICO S.R.L
A67: 30586172308 | B67: SANTA FE COMERCIAL SOCIEDAD DE RESPONSABILIDAD LIMITADA | C67: LIBRERÍA
A68: 30715428349 | B68: NETSHOP GROUP S.R.L. | C68: Gastos Varios
A69: 30718553357 | B69: EMIGRA CON TU MASCOTA S.R.L.
A70: 24368969350 | B70: MARANO CORVALAN MARTIN MARIANO
A71: 20347443787 | B71: YAÑEZ GERMAN
A72: 33717319309 | B72: CONSMITEC S.R.L.
A73: 33715154809 | B73: SUPERMERCADOS BONANNO S.A.
A74: 30718295900 | B74: LAPTOP SERVICE S.R.L.
A75: 23107861939 | B75: GONZALEZ JOSE RAUL
A76: 30715438360 | B76: ERMAN CUSTODIAR S.A.
A77: 30711942412 | B77: FUNDACION EDUCACION PARA EL PROGRESO
A78: 27335747254 | B78: RODRIGUES DAIANA DENISE
A79: 27284608637 | B79: VIANI IVANNA | C79: Alquiler
A80: 30714375241 | B80: POWER-RECORDS S.A
A81: 30715751557 | B81: TIXIT SRL
A82: 30718464931 | B82: FACTUMAR SRL | C82: Serv. Informaticos
A83: 30712186573 | B83: CBGB DISTRIBUCION S.R.L. | C83: Catering
A84: 30718631730 | B84: SIMZ S. R. L. | C84: Serv. Informaticos
A85: 30590360763 | B85: CENCOSUD S A | C85: Gastos Varios
A86: 33718113739 | B86: HERAS ROMEO | C86: Honorarios Profesionales
A87: 30709058807 | B87: LA VALENZIANA S.R.L.
A88: 33716094559 | B88: NORDENPET SRL
A89: 33717568899 | B89: COOPERATIVA DE TRABAJO LOS REMANSEROS LIMITADA | C89: Gastos Varios

Sheet Ene-24
B1: LIBRO IVA COMPRAS | G1: RABLEB SRL | N1: 45292
B3: TOTAL COMPRAS | G3: TOTAL CREDITO FISCAL | J3: TOTAL VENTAS NETAS | M3: TOTAL DEBITO FISCAL | P3: RESULTADO
B4: =SUM(compras_mes1[[#Totals],[NETO GRAVADO]])+extracto_banco_mes1[[#Totals],[NETO]] -> 723376.81 | G4: =compras_mes1[[#Totals],[IVA 21 %]]+compras_mes1[[#Totals],[IVA 27%]]+compras_mes1[[#Totals],[IVA 10,5%]]+extracto_banco_mes1[[#Totals],[IVA 21%]]+extracto_banco_mes1[[#Totals],[IVA 10,5%]] -> 151909.13 | J4: =venta_a_mes1[[#Totals],[IMPORTE NETO]]+ventas_b_mes1[[#Totals],[IMPORTE NETO]] -> 1382498.1 | M4: =venta_a_mes1[[#Totals],[IVA 21%]]+venta_a_mes1[[#Totals],[IVA 10,5%]]+ventas_b_mes1[[#Totals],[IVA 21%]]+ventas_b_mes1[[#Totals],[IVA 10,5%]] -> 290324.6 | P4: =G4-M4 -> -138415.47
B8: FECHA | C8: TIPO | D8: PTO VTA | E8: NRO. CPTE | F8: CUIT | G8: RAZON SOCIAL | H8: NETO GRAVADO | I8: IVA 21 % | J8: IVA 27% | K8: IVA 10,5% | L8: PERC. IVA | M8: PERC IIBB BS AS | N8: PERC. IIBB CABA | O8: Otros / No Grav. | P8: TOTAL | Q8: Tipo de Gasto | R8: Provincia
B9: 45322 | C9: 1 | D9: 11 | E9: 941540 | F9: 33709585229 | G9: =IFERROR(IF(compras_mes1[[#This Row],[CUIT]]="","-",VLOOKUP(compras_mes1[[#This Row],[CUIT]],Lista_CUIT[#All],2,0)),"CUIT NO CARGADO") -> GOOGLE ARGENTINA S.R.L. | H9: 73116.08 | I9: =IF(compras_mes1[[#This Row],[NETO GRAVADO]]="","",compras_mes1[[#This Row],[NETO GRAVADO]]*0.21) -> 15354.377 | L9: 2193.48 | N9: 1096.74 | P9: =SUM(compras_mes1[[#This Row],[NETO GRAVADO]:[Otros / No Grav.]]) -> 91760.677 | Q9: =IFERROR(IF(compras_mes1[[#This Row],[CUIT]]="","-",VLOOKUP(compras_mes1[[#This Row],[CUIT]],Lista_CUIT[#All],3,0)),"CUIT NO CARGADO") -> Gastos Publicidad y Propaganda | R9: =IFERROR(IF(compras_mes1[[#This Row],[CUIT]]="","-",VLOOKUP(compras_mes1[[#This Row],[CUIT]],Lista_CUIT[#All],4,0)),"CUIT NO CARGADO") -> 0
B10: 45322 | C10: 1 | D10: 11 | E10: 937071 | F10: 33709585229 | G10: =IFERROR(IF(compras_mes1[[#This Row],[CUIT]]="","-",VLOOKUP(compras_mes1[[#This Row],[CUIT]],Lista_CUIT[#All],2,0)),"CUIT NO CARGADO") -> GOOGLE ARGENTINA S.R.L. | H10: 31817.43 | I10: =IF(compras_mes1[[#This Row],[NETO GRAVADO]]="","",compras_mes1[[#This Row],[NETO GRAVADO]]*0.21) -> 6681.6603 | L10: 954.52 | N10: 477.26 | P10: =SUM(compras_mes1[[#This Row],[NETO GRAVADO]:[Otros / No Grav.]]) -> 39930.87 | Q10: =IFERROR(IF(compras_mes1[[#This Row],[CUIT]]="","-",VLOOKUP(compras_mes1[[#This Row],[CUIT]],Lista_CUIT[#All],3,0)),"CUIT NO CARGADO") -> Gastos Publicidad y Propaganda | R10: =IFERROR(IF(compras_mes1[[#This Row],[CUIT]]="","-",VLOOKUP(compras_mes1[[#This Row],[CUIT]],Lista_CUIT[#All],4,0)),"CUIT NO CARGADO") -> 0
B11: 45322 | C11: 1 | D11: 11 | E11: 935773 | F11: 33709585229 | G11: =IFERROR(IF(compras_mes1[[#This Row],[CUIT]]="","-",VLOOKUP(compras_mes1[[#This Row],[CUIT]],Lista_CUIT[#All],2,0)),"CUIT NO CARGADO") -> GOOGLE ARGENTINA S.R.L. | H11: 41418.76 | I11: =IF(compras_mes1[[#This Row],[NETO GRAVADO]]="","",compras_mes1[[#This Row],[NETO GRAVADO]]*0.21) -> 8697.9396 | L11: 1242.56 | N11: 621.28 | P11: =SUM(compras_mes1[[#This Row],[NETO GRAVADO]:[Otros / No Grav.]]) -> 51980.54 | Q11: =IFERROR(IF(compras_mes1[[#This Row],[CUIT]]="","-",VLOOKUP(compras_mes1[[#This Row],[CUIT]],Lista_CUIT[#All],3,0)),"CUIT NO CARGADO") -> Gastos Publicidad y Propaganda | R11: =IFERROR(IF(compras_mes1[[#This Row],[CUIT]]="","-",VLOOKUP(compras_mes1[[#This Row],[CUIT]],Lista_CUIT[#All],4,0)),"CUIT NO CARGADO") -> 0
B12: 45322 | C12: 1 | D12: 11 | E12: 936068 | F12: 33709585229 | G12: =IFERROR(IF(compras_mes1[[#This Row],[CUIT]]="","-",VLOOKUP(compras_mes1[[#This Row],[CUIT]],Lista_CUIT[#All],2,0)),"CUIT NO CARGADO") -> GOOGLE ARGENTINA S.R.L. | H12: 477557.3 | I12: =IF(compras_mes1[[#This Row],[NETO GRAVADO]]="","",compras_mes1[[#This Row],[NETO GRAVADO]]*0.21) -> 100287.03 | L12: 14326.72 | N12: 7163.36 | P12: =SUM(compras_mes1[[#This Row],[NETO GRAVADO]:[Otros / No Grav.]]) -> 599334.41 | Q12: =IFERROR(IF(compras_mes1[[#This Row],[CUIT]]="","-",VLOOKUP(compras_mes1[[#This Row],[CUIT]],Lista_CUIT[#All],3,0)),"CUIT NO CARGADO") -> Gastos Publicidad y Propaganda | R12: =IFERROR(IF(compras_mes1[[#This Row],[CUIT]]="","-",VLOOKUP(compras_mes1[[#This Row],[CUIT]],Lista_CUIT[#All],4,0)),"CUIT NO CARGADO") -> 0
B13: 45322 | C13: 1 | D13: 11 | E13: 932631 | F13: 33709585229 | G13: =IFERROR(IF(compras_mes1[[#This Row],[CUIT]]="","-",VLOOKUP(compras_mes1[[#This Row],[CUIT]],Lista_CUIT[#All],2,0)),"CUIT NO CARGADO") -> GOOGLE ARGENTINA S.R.L. | H13: 30522.81 | I13: =IF(compras_mes1[[#This Row],[NETO GRAVADO]]="","",compras_mes1[[#This Row],[NETO GRAVADO]]*0.21) -> 6409.7901 | L13: 915.68 | N13: 457.84 | P13: =SUM(compras_mes1[[#This Row],[NETO GRAVADO]:[Otros / No Grav.]]) -> 38306.12 | Q13: =IFERROR(IF(compras_mes1[[#This Row],[CUIT]]="","-",VLOOKUP(compras_mes1[[#This Row],[CUIT]],Lista_CUIT[#All],3,0)),"CUIT NO CARGADO") -> Gastos Publicidad y Propaganda | R13: =IFERROR(IF(compras_mes1[[#This Row],[CUIT]]="","-",VLOOKUP(compras_mes1[[#This Row],[CUIT]],Lista_CUIT[#All],4,0)),"CUIT NO CARGADO") -> 0
B14: 45322 | C14: 1 | D14: 11 | E14: 931692 | F14: 33709585229 | G14: =IFERROR(IF(compras_mes1[[#This Row],[CUIT]]="","-",VLOOKUP(compras_mes1[[#This Row],[CUIT]],Lista_CUIT[#All],2,0)),"CUIT NO CARGADO") -> GOOGLE ARGENTINA S.R.L. | H14: 68993.02 | I14: =IF(compras_mes1[[#This Row],[NETO GRAVADO]]="","",compras_mes1[[#This Row],[NETO GRAVADO]]*0.21) -> 14488.534 | L14: 2069.79 | N14: 1034.9 | P14: =SUM(compras_mes1[[#This Row],[NETO GRAVADO]:[Otros / No Grav.]]) -> 86586.244 | Q14: =IFERROR(IF(compras_mes1[[#This Row],[CUIT]]="","-",VLOOKUP(compras_mes1[[#This Row],[CUIT]],Lista_CUIT[#All],3,0)),"CUIT NO CARGADO") -> Gastos Publicidad y Propaganda | R14: =IFERROR(IF(compras_mes1[[#This Row],[CUIT]]="","-",VLOOKUP(compras_mes1[[#This Row],[CUIT]],Lista_CUIT[#All],4,0)),"CUIT NO CARGADO") -> 0
B15: 45322 | C15: 3 | D15: 11 | E15: 691643 | F15: 33709585229 | G15: =IFERROR(IF(compras_mes1[[#This Row],[CUIT]]="","-",VLOOKUP(compras_mes1[[#This Row],[CUIT]],Lista_CUIT[#All],2,0)),"CUIT NO CARGADO") -> GOOGLE ARGENTINA S.R.L. | H15: -48.59 | I15: =IF(compras_mes1[[#This Row],[NETO GRAVADO]]="","",compras_mes1[[#This Row],[NETO GRAVADO]]*0.21) -> -10.2039 | P15: =SUM(compras_mes1[[#This Row],[NETO GRAVADO]:[Otros / No Grav.]]) -> -58.7939 | Q15: =IFERROR(IF(compras_mes1[[#This Row],[CUIT]]="","-",VLOOKUP(compras_mes1[[#This Row],[CUIT]],Lista_CUIT[#All],3,0)),"CUIT NO CARGADO") -> Gastos Publicidad y Propaganda | R15: =IFERROR(IF(compras_mes1[[#This Row],[CUIT]]="","-",VLOOKUP(compras_mes1[[#This Row],[CUIT]],Lista_CUIT[#All],4,0)),"CUIT NO CARGADO") -> 0
B16: 45322 | C16: 3 | D16: 11 | E16: 689632 | F16: 33709585229 | G16: =IFERROR(IF(compras_mes1[[#This Row],[CUIT]]="","-",VLOOKUP(compras_mes1[[#This Row],[CUIT]],Lista_CUIT[#All],2,0)),"CUIT NO CARGADO") -> GOOGLE ARGENTINA S.R.L. | H16: 0 | I16: =IF(compras_mes1[[#This Row],[NETO GRAVADO]]="","",compras_mes1[[#This Row],[NETO GRAVADO]]*0.21) -> 0 | P16: =SUM(compras_mes1[[#This Row],[NETO GRAVADO]:[Otros / No Grav.]]) -> 0 | Q16: =IFERROR(IF(compras_mes1[[#This Row],[CUIT]]="","-",VLOOKUP(compras_mes1[[#This Row],[CUIT]],Lista_CUIT[#All],3,0)),"CUIT NO CARGADO") -> Gastos Publicidad y Propaganda | R16: =IFERROR(IF(compras_mes1[[#This Row],[CUIT]]="","-",VLOOKUP(compras_mes1[[#This Row],[CUIT]],Lista_CUIT[#All],4,0)),"CUIT NO CARGADO") -> 0
G17: =IFERROR(IF(compras_mes1[[#This Row],[CUIT]]="","-",VLOOKUP(compras_mes1[[#This Row],[CUIT]],Lista_CUIT[#All],2,0)),"CUIT NO CARGADO") -> - | I17: =IF(compras_mes1[[#This Row],[NETO GRAVADO]]="","",compras_mes1[[#This Row],[NETO GRAVADO]]*0.21) | P17: =SUM(compras_mes1[[#This Row],[NETO GRAVADO]:[Otros / No Grav.]]) -> 0 | Q17: =IFERROR(IF(compras_mes1[[#This Row],[CUIT]]="","-",VLOOKUP(compras_mes1[[#This Row],[CUIT]],Lista_CUIT[#All],3,0)),"CUIT NO CARGADO") -> - | R17: =IFERROR(IF(compras_mes1[[#This Row],[CUIT]]="","-",VLOOKUP(compras_mes1[[#This Row],[CUIT]],Lista_CUIT[#All],4,0)),"CUIT NO CARGADO") -> -
G18: =IFERROR(IF(compras_mes1[[#This Row],[CUIT]]="","-",VLOOKUP(compras_mes1[[#This Row],[CUIT]],Lista_CUIT[#All],2,0)),"CUIT NO CARGADO") -> - | I18: =IF(compras_mes1[[#This Row],[NETO GRAVADO]]="","",compras_mes1[[#This Row],[NETO GRAVADO]]*0.21) | P18: =SUM(compras_mes1[[#This Row],[NETO GRAVADO]:[Otros / No Grav.]]) -> 0 | Q18: =IFERROR(IF(compras_mes1[[#This Row],[CUIT]]="","-",VLOOKUP(compras_mes1[[#This Row],[CUIT]],Lista_CUIT[#All],3,0)),"CUIT NO CARGADO") -> - | R18: =IFERROR(IF(compras_mes1[[#This Row],[CUIT]]="","-",VLOOKUP(compras_mes1[[#This Row],[CUIT]],Lista_CUIT[#All],4,0)),"CUIT NO CARGADO") -> -
B19: Total | H19: =SUBTOTAL(109,compras_mes1[NETO GRAVADO]) -> 723376.81 | I19: =SUBTOTAL(109,compras_mes1[IVA 21 %]) -> 151909.13 | J19: =SUBTOTAL(109,compras_mes1[IVA 27%]) -> 0 | K19: =SUBTOTAL(109,compras_mes1[IVA 10,5%]) -> 0 | L19: =SUBTOTAL(109,compras_mes1[PERC. IVA]) -> 21702.75 | M19: =SUBTOTAL(109,compras_mes1[PERC IIBB BS AS]) -> 0 | N19: =SUBTOTAL(109,compras_mes1[PERC. IIBB CABA]) -> 10851.38 | O19: =SUBTOTAL(109,compras_mes1[Otros / No Grav.]) -> 0 | P19: =SUBTOTAL(109,compras_mes1[TOTAL]) -> 907840.07
D24: LIQUIDACION EXTRACTOS BANCARIOS-TARJETAS
D25: FECHA | E25: NRO CPTE | F25: BANCO | G25: NETO | H25: IVA 21% | I25: IVA 10,5% | J25: RET IIBB CABA | K25: PERC IVA | L25: PERC IIBB
D29: Total | G29: =SUBTOTAL(109,extracto_banco_mes1[NETO]) -> 0 | H29: =SUBTOTAL(109,extracto_banco_mes1[IVA 21%]) -> 0 | I29: =SUBTOTAL(109,extracto_banco_mes1[IVA 10,5%]) -> 0 | J29: =SUBTOTAL(109,extracto_banco_mes1[RET IIBB CABA]) -> 0 | K29: =SUBTOTAL(109,extracto_banco_mes1[PERC IVA]) -> 0 | L29: =SUBTOTAL(109,extracto_banco_mes1[PERC IIBB]) -> 0
D33: FACTURAS C
D34: FECHA | E34: PTO VTA | F34: FC Nº | G34: CUIT | H34: RAZON SOCIAL | I34: TOTAL | J34: TIPO DE GASTO | K34: Provincia
D35: 45293 | E35: 2 | F35: 698 | G35: 20400104094 | H35: =IFERROR(IF(factura_c_mes1[[#This Row],[CUIT]]="","-",VLOOKUP(factura_c_mes1[[#This Row],[CUIT]],Lista_CUIT[#All],2,0)),"CUIT NO CARGADO") -> BOTINDARI FEDERICO DANIEL | I35: 46500 | J35: =IFERROR(IF(factura_c_mes1[[#This Row],[CUIT]]="","-",VLOOKUP(factura_c_mes1[[#This Row],[CUIT]],Lista_CUIT[#All],3,0)),"CUIT NO CARGADO") -> HONORARIOS CONTABLE | K35: =IFERROR(IF(factura_c_mes1[[#This Row],[CUIT]]="","-",VLOOKUP(factura_c_mes1[[#This Row],[CUIT]],Lista_CUIT[#All],4,0)),"CUIT NO CARGADO") -> 0
D36: 45294 | E36: 1 | F36: 299 | G36: 27386311000 | H36: =IFERROR(IF(factura_c_mes1[[#This Row],[CUIT]]="","-",VLOOKUP(factura_c_mes1[[#This Row],[CUIT]],Lista_CUIT[#All],2,0)),"CUIT NO CARGADO") -> OPANASIUK MACARENA ANTONELLA | I36: 500000 | J36: =IFERROR(IF(factura_c_mes1[[#This Row],[CUIT]]="","-",VLOOKUP(factura_c_mes1[[#This Row],[CUIT]],Lista_CUIT[#All],3,0)),"CUIT NO CARGADO") -> Honorarios Profesionales | K36: =IFERROR(IF(factura_c_mes1[[#This Row],[CUIT]]="","-",VLOOKUP(factura_c_mes1[[#This Row],[CUIT]],Lista_CUIT[#All],4,0)),"CUIT NO CARGADO") -> 0
H37: =IFERROR(IF(factura_c_mes1[[#This Row],[CUIT]]="","-",VLOOKUP(factura_c_mes1[[#This Row],[CUIT]],Lista_CUIT[#All],2,0)),"CUIT NO CARGADO") -> - | J37: =IFERROR(IF(factura_c_mes1[[#This Row],[CUIT]]="","-",VLOOKUP(factura_c_mes1[[#This Row],[CUIT]],Lista_CUIT[#All],3,0)),"CUIT NO CARGADO") -> - | K37: =IFERROR(IF(factura_c_mes1[[#This Row],[CUIT]]="","-",VLOOKUP(factura_c_mes1[[#This Row],[CUIT]],Lista_CUIT[#All],4,0)),"CUIT NO CARGADO") -> -
D38: Total | I38: =SUBTOTAL(109,factura_c_mes1[TOTAL]) -> 546500
B44: LIBRO IVA VENTAS | K44: =N1 -> 45292
B46: VENTAS "A"
B47: FECHA | C47: TIPO | D47: PTO VENTA | E47: Nº FACTURA | F47: CUIT | G47: RAZON SOCIAL | H47: IMPORTE NETO | I47: IVA 21% | J47: IVA 10,5% | K47: EXENTO | L47: TOTAL | M47: Provincia
B48: 45293 | C48: 1 | D48: 2 | E48: 6 | F48: 30715380567 | G48: =IFERROR(IF(venta_a_mes1[[#This Row],[CUIT]]="","-",VLOOKUP(venta_a_mes1[[#This Row],[CUIT]],Lista_CUIT[#All],2,0)),"CUIT NO CARGADO") -> SENS GROUP SRL | H48: 184981.05 | I48: =venta_a_mes1[[#This Row],[IMPORTE NETO]]*0.21 -> 38846.02 | L48: =SUM(venta_a_mes1[[#This Row],[IMPORTE NETO]:[EXENTO]]) -> 223827.07
B49: 45293 | C49: 1 | D49: 1 | E49: 107 | F49: 30717973166 | G49: =IFERROR(IF(venta_a_mes1[[#This Row],[CUIT]]="","-",VLOOKUP(venta_a_mes1[[#This Row],[CUIT]],Lista_CUIT[#All],2,0)),"CUIT NO CARGADO") -> STM ESTILO S.R.L | H49: 37685.95 | I49: =venta_a_mes1[[#This Row],[IMPORTE NETO]]*0.21 -> 7914.0495 | L49: =SUM(venta_a_mes1[[#This Row],[IMPORTE NETO]:[EXENTO]]) -> 45599.999
B50: 45293 | C50: 1 | D50: 1 | E50: 105 | F50: 30717170594 | G50: =IFERROR(IF(venta_a_mes1[[#This Row],[CUIT]]="","-",VLOOKUP(venta_a_mes1[[#This Row],[CUIT]],Lista_CUIT[#All],2,0)),"CUIT NO CARGADO") -> INDUSTRIA4 S.R.L. | H50: 75371.9 | I50: =venta_a_mes1[[#This Row],[IMPORTE NETO]]*0.21 -> 15828.099 | L50: =SUM(venta_a_mes1[[#This Row],[IMPORTE NETO]:[EXENTO]]) -> 91199.999
B51: 45293 | C51: 1 | D51: 1 | E51: 111 | F51: 20279415656 | G51: =IFERROR(IF(venta_a_mes1[[#This Row],[CUIT]]="","-",VLOOKUP(venta_a_mes1[[#This Row],[CUIT]],Lista_CUIT[#All],2,0)),"CUIT NO CARGADO") -> CECCO ALVARO GONZALO | H51: 75371.9 | I51: =venta_a_mes1[[#This Row],[IMPORTE NETO]]*0.21 -> 15828.099 | L51: =SUM(venta_a_mes1[[#This Row],[IMPORTE NETO]:[EXENTO]]) -> 91199.999
B52: 45293 | C52: 1 | D52: 1 | E52: 110 | F52: 20287305460 | G52: =IFERROR(IF(venta_a_mes1[[#This Row],[CUIT]]="","-",VLOOKUP(venta_a_mes1[[#This Row],[CUIT]],Lista_CUIT[#All],2,0)),"CUIT NO CARGADO") -> LANDI GERONIMO | H52: 37685.95 | I52: =venta_a_mes1[[#This Row],[IMPORTE NETO]]*0.21 -> 7914.0495 | L52: =SUM(venta_a_mes1[[#This Row],[IMPORTE NETO]:[EXENTO]]) -> 45599.999
B53: 45293 | C53: 1 | D53: 1 | E53: 104 | F53: 20284212488 | G53: =IFERROR(IF(venta_a_mes1[[#This Row],[CUIT]]="","-",VLOOKUP(venta_a_mes1[[#This Row],[CUIT]],Lista_CUIT[#All],2,0)),"CUIT NO CARGADO") -> BARLETTA MAXIMILIANO SEBASTIAN | H53: 37685.95 | I53: =venta_a_mes1[[#This Row],[IMPORTE NETO]]*0.21 -> 7914.0495 | L53: =SUM(venta_a_mes1[[#This Row],[IMPORTE NETO]:[EXENTO]]) -> 45599.999
B54: 45293 | C54: 1 | D54: 1 | E54: 115 | F54: 30717465101 | G54: =IFERROR(IF(venta_a_mes1[[#This Row],[CUIT]]="","-",VLOOKUP(venta_a_mes1[[#This Row],[CUIT]],Lista_CUIT[#All],2,0)),"CUIT NO CARGADO") -> EMPRENDIMIENTOS SHOPGLASS S. R. L. | H54: 37685.95 | I54: =venta_a_mes1[[#This Row],[IMPORTE NETO]]*0.21 -> 7914.0495 | L54: =SUM(venta_a_mes1[[#This Row],[IMPORTE NETO]:[EXENTO]]) -> 45599.999
B55: 45293 | C55: 1 | D55: 1 | E55: 106 | F55: 30717170594 | G55: =IFERROR(IF(venta_a_mes1[[#This Row],[CUIT]]="","-",VLOOKUP(venta_a_mes1[[#This Row],[CUIT]],Lista_CUIT[#All],2,0)),"CUIT NO CARGADO") -> INDUSTRIA4 S.R.L. | H55: 37685.95 | I55: =venta_a_mes1[[#This Row],[IMPORTE NETO]]*0.21 -> 7914.0495 | L55: =SUM(venta_a_mes1[[#This Row],[IMPORTE NETO]:[EXENTO]]) -> 45599.999
B56: 45293 | C56: 1 | D56: 1 | E56: 114 | F56: 30717969061 | G56: =IFERROR(IF(venta_a_mes1[[#This Row],[CUIT]]="","-",VLOOKUP(venta_a_mes1[[#This Row],[CUIT]],Lista_CUIT[#All],2,0)),"CUIT NO CARGADO") -> FABIO Y RAUL ROSSO S.A.S. | H56: 37685.95 | I56: =venta_a_mes1[[#This Row],[IMPORTE NETO]]*0.21 -> 7914.0495 | L56: =SUM(venta_a_mes1[[#This Row],[IMPORTE NETO]:[EXENTO]]) -> 45599.999
B57: 45293 | C57: 1 | D57: 1 | E57: 103 | F57: 30717477681 | G57: =IFERROR(IF(venta_a_mes1[[#This Row],[CUIT]]="","-",VLOOKUP(venta_a_mes1[[#This Row],[CUIT]],Lista_CUIT[#All],2,0)),"CUIT NO CARGADO") -> GRUPO FAM SA | H57: 52479.33 | I57: =venta_a_mes1[[#This Row],[IMPORTE NETO]]*0.21 -> 11020.659 | L57: =SUM(venta_a_mes1[[#This Row],[IMPORTE NETO]:[EXENTO]]) -> 63499.989
B58: 45293 | C58: 1 | D58: 1 | E58: 113 | F58: 30715941763 | G58: =IFERROR(IF(venta_a_mes1[[#This Row],[CUIT]]="","-",VLOOKUP(venta_a_mes1[[#This Row],[CUIT]],Lista_CUIT[#All],2,0)),"CUIT NO CARGADO") -> TOURMALHYN S.R.L. | H58: 20661.14 | I58: =venta_a_mes1[[#This Row],[IMPORTE NETO]]*0.21 -> 4338.8394 | L58: =SUM(venta_a_mes1[[#This Row],[IMPORTE NETO]:[EXENTO]]) -> 24999.979
B59: 45293 | C59: 1 | D59: 1 | E59: 109 | F59: 20252582704 | G59: =IFERROR(IF(venta_a_mes1[[#This Row],[CUIT]]="","-",VLOOKUP(venta_a_mes1[[#This Row],[CUIT]],Lista_CUIT[#All],2,0)),"CUIT NO CARGADO") -> GARCIA VAUTRIN ANDRES ALBERTO | H59: 75371.9 | I59: =venta_a_mes1[[#This Row],[IMPORTE NETO]]*0.21 -> 15828.099 | L59: =SUM(venta_a_mes1[[#This Row],[IMPORTE NETO]:[EXENTO]]) -> 91199.999
... B68: 45302 | C68: 3 | D68: 2 | E68: 1 | F68: 30715380567 | G68: =IFERROR(IF(venta_a_mes1[[#This Row],[CUIT]]="","-",VLOOKUP(venta_a_mes1[[#This Row],[CUIT]],Lista_CUIT[#All],2,0)),"CUIT NO CARGADO") -> SENS GROUP SRL | H68: -184981.05 | I68: =venta_a_mes1[[#This Row],[IMPORTE NETO]]*0.21 -> -38846.02 | L68: =SUM(venta_a_mes1[[#This Row],[IMPORTE NETO]:[EXENTO]]) -> -223827.07
B69: Total | H69: =SUBTOTAL(109,venta_a_mes1[IMPORTE NETO]) -> 1250266.6 | I69: =SUBTOTAL(109,venta_a_mes1[IVA 21%]) -> 262555.99 | J69: =SUBTOTAL(109,venta_a_mes1[IVA 10,5%]) -> 0 | K69: =SUBTOTAL(109,venta_a_mes1[EXENTO]) -> 0 | L69: =SUBTOTAL(109,venta_a_mes1[TOTAL]) -> 1512822.6 | M69: =SUBTOTAL(103,venta_a_mes1[Provincia]) -> 0
B70: VENTAS "B"
B71: FECHA | C71: TIPO | D71: PTO VENTA | E71: Nº FACTURA | F71: CUIT | G71: RAZON SOCIAL | H71: IMPORTE NETO | I71: IVA 21% | J71: IVA 10,5% | K71: EXENTO | L71: TOTAL | M71: Provincia
B72: 45293 | C72: 6 | D72: 1 | E72: 20 | F72: 30521448608 | G72: =IFERROR(IF(ventas_b_mes1[[#This Row],[CUIT]]="","-",VLOOKUP(ventas_b_mes1[[#This Row],[CUIT]],Lista_CUIT[#All],2,0)),"CUIT NO CARGADO") -> INSTITUTO ORSINO SA | H72: 33057.86 | I72: =ventas_b_mes1[[#This Row],[IMPORTE NETO]]*0.21 -> 6942.1506 | L72: =SUM(ventas_b_mes1[[#This Row],[IMPORTE NETO]:[EXENTO]]) -> 40000.011
B73: 45293 | C73: 6 | D73: 1 | E73: 19 | F73: 30700477920 | G73: =IFERROR(IF(ventas_b_mes1[[#This Row],[CUIT]]="","-",VLOOKUP(ventas_b_mes1[[#This Row],[CUIT]],Lista_CUIT[#All],2,0)),"CUIT NO CARGADO") -> ESBA FLORESS A | H73: 33057.86 | I73: =ventas_b_mes1[[#This Row],[IMPORTE NETO]]*0.21 -> 6942.1506 | L73: =SUM(ventas_b_mes1[[#This Row],[IMPORTE NETO]:[EXENTO]]) -> 40000.011
B74: 45293 | C74: 6 | D74: 1 | E74: 18 | F74: 30681452423 | G74: =IFERROR(IF(ventas_b_mes1[[#This Row],[CUIT]]="","-",VLOOKUP(ventas_b_mes1[[#This Row],[CUIT]],Lista_CUIT[#All],2,0)),"CUIT NO CARGADO") -> E S B A LUGANO S A | H74: 33057.86 | I74: =ventas_b_mes1[[#This Row],[IMPORTE NETO]]*0.21 -> 6942.1506 | L74: =SUM(ventas_b_mes1[[#This Row],[IMPORTE NETO]:[EXENTO]]) -> 40000.011
B75: 45293 | C75: 6 | D75: 1 | E75: 21 | F75: 30592508830 | G75: =IFERROR(IF(ventas_b_mes1[[#This Row],[CUIT]]="","-",VLOOKUP(ventas_b_mes1[[#This Row],[CUIT]],Lista_CUIT[#All],2,0)),"CUIT NO CARGADO") -> INSTITUTO DE ESTUDIOS SUPERIORES DE BUENOS AIRES S A | H75: 33057.86 | I75: =ventas_b_mes1[[#This Row],[IMPORTE NETO]]*0.21 -> 6942.1506 | L75: =SUM(ventas_b_mes1[[#This Row],[IMPORTE NETO]:[EXENTO]]) -> 40000.011
G76: =IFERROR(IF(ventas_b_mes1[[#This Row],[CUIT]]="","-",VLOOKUP(ventas_b_mes1[[#This Row],[CUIT]],Lista_CUIT[#All],2,0)),"CUIT NO CARGADO") -> - | I76: =ventas_b_mes1[[#This Row],[IMPORTE NETO]]*0.21 -> 0 | L76: =SUM(ventas_b_mes1[[#This Row],[IMPORTE NETO]:[EXENTO]]) -> 0
I77: =ventas_b_mes1[[#This Row],[IMPORTE NETO]]*0.21 -> 0 | L77: =SUM(ventas_b_mes1[[#This Row],[IMPORTE NETO]:[EXENTO]]) -> 0
B78: Total | H78: =SUBTOTAL(109,ventas_b_mes1[IMPORTE NETO]) -> 132231.44 | I78: =SUBTOTAL(109,ventas_b_mes1[IVA 21%]) -> 27768.602 | J78: =SUBTOTAL(109,ventas_b_mes1[IVA 10,5%]) -> 0 | K78: =SUBTOTAL(109,ventas_b_mes1[EXENTO]) -> 0 | L78: =SUBTOTAL(109,ventas_b_mes1[TOTAL]) -> 160000.04 | M78: =SUBTOTAL(103,ventas_b_mes1[Provincia]) -> 0
C86: RETENCIONES
C87: FECHA | D87: COMP Nº | E87: Columna1 | F87: CUIT | G87: RAZON SOCIAL | H87: Ganancias | I87: IVA | J87: SUSS | K87: IIBB BSAS | L87: IIBB CABA
G88: =IFERROR(IF(retenciones_mes1[[#This Row],[CUIT]]="","-",VLOOKUP(retenciones_mes1[[#This Row],[CUIT]],Lista_CUIT[#All],2,0)),"CUIT NO CARGADO") -> -
G89: =IFERROR(IF(retenciones_mes1[[#This Row],[CUIT]]="","-",VLOOKUP(retenciones_mes1[[#This Row],[CUIT]],Lista_CUIT[#All],2,0)),"CUIT NO CARGADO") -> -
G90: =IFERROR(IF(retenciones_mes1[[#This Row],[CUIT]]="","-",VLOOKUP(retenciones_mes1[[#This Row],[CUIT]],Lista_CUIT[#All],2,0)),"CUIT NO CARGADO") -> -
G91: =IFERROR(IF(retenciones_mes1[[#This Row],[CUIT]]="","-",VLOOKUP(retenciones_mes1[[#This Row],[CUIT]],Lista_CUIT[#All],2,0)),"CUIT NO CARGADO") -> -
G92: =IFERROR(IF(retenciones_mes1[[#This Row],[CUIT]]="","-",VLOOKUP(retenciones_mes1[[#This Row],[CUIT]],Lista_CUIT[#All],2,0)),"CUIT NO CARGADO") -> -

Sheet Feb-24
B1: LIBRO IVA COMPRAS | G1: ='Ene-24'!G1:M1 -> RABLEB SRL | N1: =EDATE('Ene-24'!N1,1) -> 45323
B3: TOTAL COMPRAS | G3: TOTAL CREDITO FISCAL | J3: TOTAL VENTAS NETAS | M3: TOTAL DEBITO FISCAL | P3: RESULTADO
B4: =SUM(compras_mes2[[#Totals],[NETO GRAVADO]])+extracto_banco_mes2[[#Totals],[NETO]] -> 908825.01 | G4: =compras_mes2[[#Totals],[IVA 21 %]]+compras_mes2[[#Totals],[IVA 27%]]+compras_mes2[[#Totals],[IVA 10,5%]]+extracto_banco_mes2[[#Totals],[IVA 21%]]+extracto_banco_mes2[[#Totals],[IVA 10,5%]] -> 190853.25 | J4: =venta_a_mes2[[#Totals],[IMPORTE NETO]]+ventas_b_mes2[[#Totals],[IMPORTE NETO]] -> 1292484.6 | M4: =venta_a_mes2[[#Totals],[IVA 21%]]+venta_a_mes2[[#Totals],[IVA 10,5%]]+ventas_b_mes2[[#Totals],[IVA 21%]]+ventas_b_mes2[[#Totals],[IVA 10,5%]] -> 271421.77 | P4: =G4-M4 -> -80568.517
B8: FECHA | C8: TIPO | D8: PTO VTA | E8: NRO. CPTE | F8: CUIT | G8: RAZON SOCIAL | H8: NETO GRAVADO | I8: IVA 21 % | J8: IVA 27% | K8: IVA 10,5% | L8: PERC. IVA | M8: PERC IIBB BS AS | N8: PERC. IIBB CABA | O8: Otros / No Grav. | P8: TOTAL | Q8: Tipo de Gasto | R8: Provincia
B9: 29/02/2024 | C9: 1 | D9: 11 | E9: 945335 | F9: 33709585229 | G9: =IFERROR(IF(compras_mes2[[#This Row],[CUIT]]="","-",VLOOKUP(compras_mes2[[#This Row],[CUIT]],Lista_CUIT[#All],2,0)),"CUIT NO CARGADO") -> GOOGLE ARGENTINA S.R.L. | H9: 30120.52 | I9: =compras_mes2[[#This Row],[NETO GRAVADO]]*0.21 -> 6325.3092 | N9: 451.81 | O9: 903.62 | P9: =SUM(compras_mes2[[#This Row],[NETO GRAVADO]:[Otros / No Grav.]]) -> 37801.259 | Q9: =IFERROR(IF(compras_mes2[[#This Row],[CUIT]]="","-",VLOOKUP(compras_mes2[[#This Row],[CUIT]],Lista_CUIT[#All],3,0)),"CUIT NO CARGADO") -> Gastos Publicidad y Propaganda | R9: =IFERROR(IF(compras_mes2[[#This Row],[CUIT]]="","-",VLOOKUP(compras_mes2[[#This Row],[CUIT]],Lista_CUIT[#All],4,0)),"CUIT NO CARGADO") -> 0
B10: 29/02/2024 | C10: 1 | D10: 11 | E10: 945919 | F10: 33709585229 | G10: =IFERROR(IF(compras_mes2[[#This Row],[CUIT]]="","-",VLOOKUP(compras_mes2[[#This Row],[CUIT]],Lista_CUIT[#All],2,0)),"CUIT NO CARGADO") -> GOOGLE ARGENTINA S.R.L. | H10: 428219.51 | I10: =compras_mes2[[#This Row],[NETO GRAVADO]]*0.21 -> 89926.097 | N10: 6423.29 | O10: 12846.59 | P10: =SUM(compras_mes2[[#This Row],[NETO GRAVADO]:[Otros / No Grav.]]) -> 537415.49 | Q10: =IFERROR(IF(compras_mes2[[#This Row],[CUIT]]="","-",VLOOKUP(compras_mes2[[#This Row],[CUIT]],Lista_CUIT[#All],3,0)),"CUIT NO CARGADO") -> Gastos Publicidad y Propaganda | R10: =IFERROR(IF(compras_mes2[[#This Row],[CUIT]]="","-",VLOOKUP(compras_mes2[[#This Row],[CUIT]],Lista_CUIT[#All],4,0)),"CUIT NO CARGADO") -> 0
B11: 29/02/2024 | C11: 1 | D11: 11 | E11: 950110 | F11: 33709585229 | G11: =IFERROR(IF(compras_mes2[[#This Row],[CUIT]]="","-",VLOOKUP(compras_mes2[[#This Row],[CUIT]],Lista_CUIT[#All],2,0)),"CUIT NO CARGADO") -> GOOGLE ARGENTINA S.R.L. | H11: 34780.14 | I11: =compras_mes2[[#This Row],[NETO GRAVADO]]*0.21 -> 7303.8294 | N11: 521.7 | O11: 1043.4 | P11: =SUM(compras_mes2[[#This Row],[NETO GRAVADO]:[Otros / No Grav.]]) -> 43649.069 | Q11: =IFERROR(IF(compras_mes2[[#This Row],[CUIT]]="","-",VLOOKUP(compras_mes2[[#This Row],[CUIT]],Lista_CUIT[#All],3,0)),"CUIT NO CARGADO") -> Gastos Publicidad y Propaganda | R11: =IFERROR(IF(compras_mes2[[#This Row],[CUIT]]="","-",VLOOKUP(compras_mes2[[#This Row],[CUIT]],Lista_CUIT[#All],4,0)),"CUIT NO CARGADO") -> 0
B12: 29/02/2024 | C12: 1 | D12: 11 | E12: 950338 | F12: 33709585229 | G12: =IFERROR(IF(compras_mes2[[#This Row],[CUIT]]="","-",VLOOKUP(compras_mes2[[#This Row],[CUIT]],Lista_CUIT[#All],2,0)),"CUIT NO CARGADO") -> GOOGLE ARGENTINA S.R.L. | H12: 58023.31 | I12: =compras_mes2[[#This Row],[NETO GRAVADO]]*0.21 -> 12184.895 | N12: 870.35 | O12: 1740.7 | P12: =SUM(compras_mes2[[#This Row],[NETO GRAVADO]:[Otros / No Grav.]]) -> 72819.255 | Q12: =IFERROR(IF(compras_mes2[[#This Row],[CUIT]]="","-",VLOOKUP(compras_mes2[[#This Row],[CUIT]],Lista_CUIT[#All],3,0)),"CUIT NO CARGADO") -> Gastos Publicidad y Propaganda | R12: =IFERROR(IF(compras_mes2[[#This Row],[CUIT]]="","-",VLOOKUP(compras_mes2[[#This Row],[CUIT]],Lista_CUIT[#All],4,0)),"CUIT NO CARGADO") -> 0
B13: 29/02/2024 | C13: 1 | D13: 11 | E13: 951705 | F13: 33709585229 | G13: =IFERROR(IF(compras_mes2[[#This Row],[CUIT]]="","-",VLOOKUP(compras_mes2[[#This Row],[CUIT]],Lista_CUIT[#All],2,0)),"CUIT NO CARGADO") -> GOOGLE ARGENTINA S.R.L. | H13: 246532.43 | I13: =compras_mes2[[#This Row],[NETO GRAVADO]]*0.21 -> 51771.81 | N13: 3697.99 | O13: 7395.97 | P13: =SUM(compras_mes2[[#This Row],[NETO GRAVADO]:[Otros / No Grav.]]) -> 309398.2 | Q13: =IFERROR(IF(compras_mes2[[#This Row],[CUIT]]="","-",VLOOKUP(compras_mes2[[#This Row],[CUIT]],Lista_CUIT[#All],3,0)),"CUIT NO CARGADO") -> Gastos Publicidad y Propaganda | R13: =IFERROR(IF(compras_mes2[[#This Row],[CUIT]]="","-",VLOOKUP(compras_mes2[[#This Row],[CUIT]],Lista_CUIT[#All],4,0)),"CUIT NO CARGADO") -> 0
B14: 29/02/2024 | C14: 1 | D14: 11 | E14: 948578 | F14: 33709585229 | G14: =IFERROR(IF(compras_mes2[[#This Row],[CUIT]]="","-",VLOOKUP(compras_mes2[[#This Row],[CUIT]],Lista_CUIT[#All],2,0)),"CUIT NO CARGADO") -> GOOGLE ARGENTINA S.R.L. | H14: 61234.13 | I14: =compras_mes2[[#This Row],[NETO GRAVADO]]*0.21 -> 12859.167 | N14: 918.51 | O14: 1837.02 | P14: =SUM(compras_mes2[[#This Row],[NETO GRAVADO]:[Otros / No Grav.]]) -> 76848.827 | Q14: =IFERROR(IF(compras_mes2[[#This Row],[CUIT]]="","-",VLOOKUP(compras_mes2[[#This Row],[CUIT]],Lista_CUIT[#All],3,0)),"CUIT NO CARGADO") -> Gastos Publicidad y Propaganda | R14: =IFERROR(IF(compras_mes2[[#This Row],[CUIT]]="","-",VLOOKUP(compras_mes2[[#This Row],[CUIT]],Lista_CUIT[#All],4,0)),"CUIT NO CARGADO") -> 0
B15: 29/02/2024 | C15: 1 | D15: 11 | E15: 943854 | F15: 33709585229 | G15: =IFERROR(IF(compras_mes2[[#This Row],[CUIT]]="","-",VLOOKUP(compras_mes2[[#This Row],[CUIT]],Lista_CUIT[#All],2,0)),"CUIT NO CARGADO") -> GOOGLE ARGENTINA S.R.L. | H15: 18570.74 | I15: =compras_mes2[[#This Row],[NETO GRAVADO]]*0.21 -> 3899.8554 | N15: 557.12 | O15: 278.56 | P15: =SUM(compras_mes2[[#This Row],[NETO GRAVADO]:[Otros / No Grav.]]) -> 23306.275 | Q15: =IFERROR(IF(compras_mes2[[#This Row],[CUIT]]="","-",VLOOKUP(compras_mes2[[#This Row],[CUIT]],Lista_CUIT[#All],3,0)),"CUIT NO CARGADO") -> Gastos Publicidad y Propaganda | R15: =IFERROR(IF(compras_mes2[[#This Row],[CUIT]]="","-",VLOOKUP(compras_mes2[[#This Row],[CUIT]],Lista_CUIT[#All],4,0)),"CUIT NO CARGADO") -> 0
B16: 29/02/2024 | C16: 1 | D16: 11 | E16: 943049 | F16: 33709585229 | G16: =IFERROR(IF(compras_mes2[[#This Row],[CUIT]]="","-",VLOOKUP(compras_mes2[[#This Row],[CUIT]],Lista_CUIT[#All],2,0)),"CUIT NO CARGADO") -> GOOGLE ARGENTINA S.R.L. | H16: 31927.67 | I16: =compras_mes2[[#This Row],[NETO GRAVADO]]*0.21 -> 6704.8107 | N16: 478.92 | O16: 957.83 | P16: =SUM(compras_mes2[[#This Row],[NETO GRAVADO]:[Otros / No Grav.]]) -> 40069.231 | Q16: =IFERROR(IF(compras_mes2[[#This Row],[CUIT]]="","-",VLOOKUP(compras_mes2[[#This Row],[CUIT]],Lista_CUIT[#All],3,0)),"CUIT NO CARGADO") -> Gastos Publicidad y Propaganda | R16: =IFERROR(IF(compras_mes2[[#This Row],[CUIT]]="","-",VLOOKUP(compras_mes2[[#This Row],[CUIT]],Lista_CUIT[#All],4,0)),"CUIT NO CARGADO") -> 0
B17: 29/02/2024 | C17: 3 | D17: 11 | E17: 698844 | F17: 33709585229 | G17: =IFERROR(IF(compras_mes2[[#This Row],[CUIT]]="","-",VLOOKUP(compras_mes2[[#This Row],[CUIT]],Lista_CUIT[#All],2,0)),"CUIT NO CARGADO") -> GOOGLE ARGENTINA S.R.L. | H17: -583.44 | I17: =compras_mes2[[#This Row],[NETO GRAVADO]]*0.21 -> -122.5224 | N17: -8.75 | P17: =SUM(compras_mes2[[#This Row],[NETO GRAVADO]:[Otros / No Grav.]]) -> -714.7124 | Q17: =IFERROR(IF(compras_mes2[[#This Row],[CUIT]]="","-",VLOOKUP(compras_mes2[[#This Row],[CUIT]],Lista_CUIT[#All],3,0)),"CUIT NO CARGADO") -> Gastos Publicidad y Propaganda | R17: =IFERROR(IF(compras_mes2[[#This Row],[CUIT]]="","-",VLOOKUP(compras_mes2[[#This Row],[CUIT]],Lista_CUIT[#All],4,0)),"CUIT NO CARGADO") -> 0
B18: Total | H18: =SUBTOTAL(109,compras_mes2[NETO GRAVADO]) -> 908825.01 | I18: =SUBTOTAL(109,compras_mes2[IVA 21 %]) -> 190853.25 | J18: =SUBTOTAL(109,compras_mes2[IVA 27%]) -> 0 | K18: =SUBTOTAL(109,compras_mes2[IVA 10,5%]) -> 0 | L18: =SUBTOTAL(109,compras_mes2[PERC. IVA]) -> 0 | M18: =SUBTOTAL(109,compras_mes2[PERC IIBB BS AS]) -> 0 | N18: =SUBTOTAL(109,compras_mes2[PERC. IIBB CABA]) -> 13910.94 | O18: =SUBTOTAL(109,compras_mes2[Otros / No Grav.]) -> 27003.69 | P18: =SUBTOTAL(109,compras_mes2[TOTAL]) -> 1140592.9
D23: LIQUIDACION EXTRACTOS BANCARIOS-TARJETAS
D24: FECHA | E24: NRO CPTE | F24: BANCO | G24: NETO | H24: IVA 21% | I24: IVA 10,5% | J24: RET IIBB CABA | K24: PERC IVA | L24: PERC IIBB
D28: Total | G28: =SUBTOTAL(109,extracto_banco_mes2[NETO]) -> 0 | H28: =SUBTOTAL(109,extracto_banco_mes2[IVA 21%]) -> 0 | I28: =SUBTOTAL(109,extracto_banco_mes2[IVA 10,5%]) -> 0 | J28: =SUBTOTAL(109,extracto_banco_mes2[RET IIBB CABA]) -> 0 | K28: =SUBTOTAL(109,extracto_banco_mes2[PERC IVA]) -> 0 | L28: =SUBTOTAL(109,extracto_banco_mes2[PERC IIBB]) -> 0
D32: FACTURAS C
D33: FECHA | E33: PTO VTA | F33: FC Nº | G33: CUIT | H33: RAZON SOCIAL | I33: TOTAL | J33: TIPO DE GASTO | K33: Provincia
D34: 05/02/2024 | E34: 2 | F34: 716 | G34: 20400104094 | H34: =IFERROR(IF(factura_c_mes2[[#This Row],[CUIT]]="","-",VLOOKUP(factura_c_mes2[[#This Row],[CUIT]],Lista_CUIT[#All],2,0)),"CUIT NO CARGADO") -> BOTINDARI FEDERICO DANIEL | I34: 46500 | J34: =IFERROR(IF(factura_c_mes2[[#This Row],[CUIT]]="","-",VLOOKUP(factura_c_mes2[[#This Row],[CUIT]],Lista_CUIT[#All],3,0)),"CUIT NO CARGADO") -> HONORARIOS CONTABLE | K34: =IFERROR(IF(factura_c_mes2[[#This Row],[CUIT]]="","-",VLOOKUP(factura_c_mes2[[#This Row],[CUIT]],Lista_CUIT[#All],4,0)),"CUIT NO CARGADO") -> 0
D35: 11/02/2024 | E35: 3 | F35: 401 | G35: 20178248201 | H35: =IFERROR(IF(factura_c_mes2[[#This Row],[CUIT]]="","-",VLOOKUP(factura_c_mes2[[#This Row],[CUIT]],Lista_CUIT[#All],2,0)),"CUIT NO CARGADO") -> FRANCISCO ADRIAN MARCELO | I35: 47500 | J35: =IFERROR(IF(factura_c_mes2[[#This Row],[CUIT]]="","-",VLOOKUP(factura_c_mes2[[#This Row],[CUIT]],Lista_CUIT[#All],3,0)),"CUIT NO CARGADO") -> 0 | K35: =IFERROR(IF(factura_c_mes2[[#This Row],[CUIT]]="","-",VLOOKUP(factura_c_mes2[[#This Row],[CUIT]],Lista_CUIT[#All],4,0)),"CUIT NO CARGADO") -> 0
H36: =IFERROR(IF(factura_c_mes2[[#This Row],[CUIT]]="","-",VLOOKUP(factura_c_mes2[[#This Row],[CUIT]],Lista_CUIT[#All],2,0)),"CUIT NO CARGADO") -> - | J36: =IFERROR(IF(factura_c_mes2[[#This Row],[CUIT]]="","-",VLOOKUP(factura_c_mes2[[#This Row],[CUIT]],Lista_CUIT[#All],3,0)),"CUIT NO CARGADO") -> - | K36: =IFERROR(IF(factura_c_mes2[[#This Row],[CUIT]]="","-",VLOOKUP(factura_c_mes2[[#This Row],[CUIT]],Lista_CUIT[#All],4,0)),"CUIT NO CARGADO") -> -
H37: =IFERROR(IF(factura_c_mes2[[#This Row],[CUIT]]="","-",VLOOKUP(factura_c_mes2[[#This Row],[CUIT]],Lista_CUIT[#All],2,0)),"CUIT NO CARGADO") -> - | J37: =IFERROR(IF(factura_c_mes2[[#This Row],[CUIT]]="","-",VLOOKUP(factura_c_mes2[[#This Row],[CUIT]],Lista_CUIT[#All],3,0)),"CUIT NO CARGADO") -> - | K37: =IFERROR(IF(factura_c_mes2[[#This Row],[CUIT]]="","-",VLOOKUP(factura_c_mes2[[#This Row],[CUIT]],Lista_CUIT[#All],4,0)),"CUIT NO CARGADO") -> -
D38: Total | I38: =SUBTOTAL(109,factura_c_mes2[TOTAL]) -> 94000
B44: LIBRO IVA VENTAS | K44: =N1 -> 45323
B46: VENTAS "A"
B47: FECHA | C47: TIPO | D47: PTO VENTA | E47: Nº FACTURA | F47: CUIT | G47: RAZON SOCIAL | H47: IMPORTE NETO | I47: IVA 21% | J47: IVA 10,5% | K47: EXENTO | L47: TOTAL | M47: Provincia
B48: 01/02/2024 | C48: 1 | D48: 1 | E48: 125 | F48: 20284212488 | G48: =IFERROR(IF(venta_a_mes2[[#This Row],[CUIT]]="","-",VLOOKUP(venta_a_mes2[[#This Row],[CUIT]],Lista_CUIT[#All],2,0)),"CUIT NO CARGADO") -> BARLETTA MAXIMILIANO SEBASTIAN | H48: 37685.95 | I48: =venta_a_mes2[[#This Row],[IMPORTE NETO]]*0.21 -> 7914.0495 | L48: =SUM(venta_a_mes2[[#This Row],[IMPORTE NETO]:[EXENTO]]) -> 45599.999
B49: 01/02/2024 | C49: 1 | D49: 1 | E49: 132 | F49: 20287305460 | G49: =IFERROR(IF(venta_a_mes2[[#This Row],[CUIT]]="","-",VLOOKUP(venta_a_mes2[[#This Row],[CUIT]],Lista_CUIT[#All],2,0)),"CUIT NO CARGADO") -> LANDI GERONIMO | H49: 37685.95 | I49: =venta_a_mes2[[#This Row],[IMPORTE NETO]]*0.21 -> 7914.0495 | L49: =SUM(venta_a_mes2[[#This Row],[IMPORTE NETO]:[EXENTO]]) -> 45599.999
B50: 01/02/2024 | C50: 1 | D50: 1 | E50: 138 | F50: 20132082198 | G50: =IFERROR(IF(venta_a_mes2[[#This Row],[CUIT]]="","-",VLOOKUP(venta_a_mes2[[#This Row],[CUIT]],Lista_CUIT[#All],2,0)),"CUIT NO CARGADO") -> FADIGA OSCAR ALBERTO | H50: 37685.95 | I50: =venta_a_mes2[[#This Row],[IMPORTE NETO]]*0.21 -> 7914.0495 | L50: =SUM(venta_a_mes2[[#This Row],[IMPORTE NETO]:[EXENTO]]) -> 45599.999
B51: 01/02/2024 | C51: 1 | D51: 1 | E51: 136 | F51: 30717969061 | G51: =IFERROR(IF(venta_a_mes2[[#This Row],[CUIT]]="","-",VLOOKUP(venta_a_mes2[[#This Row],[CUIT]],Lista_CUIT[#All],2,0)),"CUIT NO CARGADO") -> FABIO Y RAUL ROSSO S.A.S. | H51: 37685.95 | I51: =venta_a_mes2[[#This Row],[IMPORTE NETO]]*0.21 -> 7914.0495 | L51: =SUM(venta_a_mes2[[#This Row],[IMPORTE NETO]:[EXENTO]]) -> 45599.999
B52: 01/02/2024 | C52: 1 | D52: 1 | E52: 137 | F52: 30717465101 | G52: =IFERROR(IF(venta_a_mes2[[#This Row],[CUIT]]="","-",VLOOKUP(venta_a_mes2[[#This Row],[CUIT]],Lista_CUIT[#All],2,0)),"CUIT NO CARGADO") -> EMPRENDIMIENTOS SHOPGLASS S. R. L. | H52: 37685.95 | I52: =venta_a_mes2[[#This Row],[IMPORTE NETO]]*0.21 -> 7914.0495 | L52: =SUM(venta_a_mes2[[#This Row],[IMPORTE NETO]:[EXENTO]]) -> 45599.999
B53: 01/02/2024 | C53: 1 | D53: 1 | E53: 131 | F53: 20252582704 | G53: =IFERROR(IF(venta_a_mes2[[#This Row],[CUIT]]="","-",VLOOKUP(venta_a_mes2[[#This Row],[CUIT]],Lista_CUIT[#All],2,0)),"CUIT NO CARGADO") -> GARCIA VAUTRIN ANDRES ALBERTO | H53: 75371.9 | I53: =venta_a_mes2[[#This Row],[IMPORTE NETO]]*0.21 -> 15828.099 | L53: =SUM(venta_a_mes2[[#This Row],[IMPORTE NETO]:[EXENTO]]) -> 91199.999
B54: 01/02/2024 | C54: 1 | D54: 1 | E54: 124 | F54: 30717477681 | G54: =IFERROR(IF(venta_a_mes2[[#This Row],[CUIT]]="","-",VLOOKUP(venta_a_mes2[[#This Row],[CUIT]],Lista_CUIT[#All],2,0)),"CUIT NO CARGADO") -> GRUPO FAM SA | H54: 52479.33 | I54: =venta_a_mes2[[#This Row],[IMPORTE NETO]]*0.21 -> 11020.659 | L54: =SUM(venta_a_mes2[[#This Row],[IMPORTE NETO]:[EXENTO]]) -> 63499.989
B55: 01/02/2024 | C55: 1 | D55: 1 | E55: 123 | F55: 30716914077 | G55: =IFERROR(IF(venta_a_mes2[[#This Row],[CUIT]]="","-",VLOOKUP(venta_a_mes2[[#This Row],[CUIT]],Lista_CUIT[#All],2,0)),"CUIT NO CARGADO") -> BACANES | H55: 96694.24 | I55: =venta_a_mes2[[#This Row],[IMPORTE NETO]]*0.21 -> 20305.79 | L55: =SUM(venta_a_mes2[[#This Row],[IMPORTE NETO]:[EXENTO]]) -> 117000.03
B56: 01/02/2024 | C56: 1 | D56: 1 | E56: 127 | F56: 30717170594 | G56: =IFERROR(IF(venta_a_mes2[[#This Row],[CUIT]]="","-",VLOOKUP(venta_a_mes2[[#This Row],[CUIT]],Lista_CUIT[#All],2,0)),"CUIT NO CARGADO") -> INDUSTRIA4 S.R.L. | H56: 37685.95 | I56: =venta_a_mes2[[#This Row],[IMPORTE NETO]]*0.21 -> 7914.0495 | L56: =SUM(venta_a_mes2[[#This Row],[IMPORTE NETO]:[EXENTO]]) -> 45599.999
B57: 01/02/2024 | C57: 1 | D57: 1 | E57: 122 | F57: 20369499956 | G57: =IFERROR(IF(venta_a_mes2[[#This Row],[CUIT]]="","-",VLOOKUP(venta_a_mes2[[#This Row],[CUIT]],Lista_CUIT[#All],2,0)),"CUIT NO CARGADO") -> LAMARI FRANCO AGUSTIN | H57: 96694.24 | I57: =venta_a_mes2[[#This Row],[IMPORTE NETO]]*0.21 -> 20305.79 | L57: =SUM(venta_a_mes2[[#This Row],[IMPORTE NETO]:[EXENTO]]) -> 117000.03
B58: 01/02/2024 | C58: 1 | D58: 1 | E58: 135 | F58: 30715941763 | G58: =IFERROR(IF(venta_a_mes2[[#This Row],[CUIT]]="","-",VLOOKUP(venta_a_mes2[[#This Row],[CUIT]],Lista_CUIT[#All],2,0)),"CUIT NO CARGADO") -> TOURMALHYN S.R.L. | H58: 20661.14 | I58: =venta_a_mes2[[#This Row],[IMPORTE NETO]]*0.21 -> 4338.8394 | L58: =SUM(venta_a_mes2[[#This Row],[IMPORTE NETO]:[EXENTO]]) -> 24999.979
B59: 01/02/2024 | C59: 1 | D59: 1 | E59: 130 | F59: 27165844748 | G59: =IFERROR(IF(venta_a_mes2[[#This Row],[CUIT]]="","-",VLOOKUP(venta_a_mes2[[#This Row],[CUIT]],Lista_CUIT[#All],2,0)),"CUIT NO CARGADO") -> DENATALE MARCELA BEATRIZ | H59: 96694.24 | I59: =venta_a_mes2[[#This Row],[IMPORTE NETO]]*0.21 -> 20305.79 | L59: =SUM(venta_a_mes2[[#This Row],[IMPORTE NETO]:[EXENTO]]) -> 117000.03
... B66: 09/02/2024 | C66: 3 | D66: 1 | E66: 8 | F66: 30717170594 | G66: =IFERROR(IF(venta_a_mes2[[#This Row],[CUIT]]="","-",VLOOKUP(venta_a_mes2[[#This Row],[CUIT]],Lista_CUIT[#All],2,0)),"CUIT NO CARGADO") -> INDUSTRIA4 S.R.L. | H66: -37685.95 | I66: =venta_a_mes2[[#This Row],[IMPORTE NETO]]*0.21 -> -7914.0495 | L66: =SUM(venta_a_mes2[[#This Row],[IMPORTE NETO]:[EXENTO]]) -> -45599.999
B67: Total | H67: =SUBTOTAL(109,venta_a_mes2[IMPORTE NETO]) -> 1160253.2 | I67: =SUBTOTAL(109,venta_a_mes2[IVA 21%]) -> 243653.17 | J67: =SUBTOTAL(109,venta_a_mes2[IVA 10,5%]) -> 0 | K67: =SUBTOTAL(109,venta_a_mes2[EXENTO]) -> 0 | L67: =SUBTOTAL(109,venta_a_mes2[TOTAL]) -> 1403906.4 | M67: =SUBTOTAL(103,venta_a_mes2[Provincia]) -> 0
B69: VENTAS "B"
B70: FECHA | C70: TIPO | D70: PTO VENTA | E70: Nº FACTURA | F70: CUIT | G70: RAZON SOCIAL | H70: IMPORTE NETO | I70: IVA 21% | J70: IVA 10,5% | K70: EXENTO | L70: TOTAL | M70: Provincia
B71: 01/02/2024 | C71: 6 | D71: 1 | E71: 25 | F71: 30592508830 | G71: =IFERROR(IF(ventas_b_mes2[[#This Row],[CUIT]]="","-",VLOOKUP(ventas_b_mes2[[#This Row],[CUIT]],Lista_CUIT[#All],2,0)),"CUIT NO CARGADO") -> INSTITUTO DE ESTUDIOS SUPERIORES DE BUENOS AIRES S A | H71: =ventas_b_mes2[[#This Row],[TOTAL]]/1.21 -> 33057.851 | I71: =ventas_b_mes2[[#This Row],[IMPORTE NETO]]*0.21 -> 6942.1488 | L71: 40000
B72: 01/02/2024 | C72: 6 | D72: 1 | E72: 24 | F72: 30521448608 | G72: =IFERROR(IF(ventas_b_mes2[[#This Row],[CUIT]]="","-",VLOOKUP(ventas_b_mes2[[#This Row],[CUIT]],Lista_CUIT[#All],2,0)),"CUIT NO CARGADO") -> INSTITUTO ORSINO SA | H72: =ventas_b_mes2[[#This Row],[TOTAL]]/1.21 -> 33057.851 | I72: =ventas_b_mes2[[#This Row],[IMPORTE NETO]]*0.21 -> 6942.1488 | L72: 40000
B73: 01/02/2024 | C73: 6 | D73: 1 | E73: 23 | F73: 30700477920 | G73: =IFERROR(IF(ventas_b_mes2[[#This Row],[CUIT]]="","-",VLOOKUP(ventas_b_mes2[[#This Row],[CUIT]],Lista_CUIT[#All],2,0)),"CUIT NO CARGADO") -> ESBA FLORESS A | H73: =ventas_b_mes2[[#This Row],[TOTAL]]/1.21 -> 33057.851 | I73: =ventas_b_mes2[[#This Row],[IMPORTE NETO]]*0.21 -> 6942.1488 | L73: 40000
B74: 01/02/2024 | C74: 6 | D74: 1 | E74: 22 | F74: 30681452423 | G74: =IFERROR(IF(ventas_b_mes2[[#This Row],[CUIT]]="","-",VLOOKUP(ventas_b_mes2[[#This Row],[CUIT]],Lista_CUIT[#All],2,0)),"CUIT NO CARGADO") -> E S B A LUGANO S A | H74: =ventas_b_mes2[[#This Row],[TOTAL]]/1.21 -> 33057.851 | I74: =ventas_b_mes2[[#This Row],[IMPORTE NETO]]*0.21 -> 6942.1488 | L74: 40000
G75: =IFERROR(IF(ventas_b_mes2[[#This Row],[CUIT]]="","-",VLOOKUP(ventas_b_mes2[[#This Row],[CUIT]],Lista_CUIT[#All],2,0)),"CUIT NO CARGADO") -> - | H75: =ventas_b_mes2[[#This Row],[TOTAL]]/1.21 -> 0 | I75: =ventas_b_mes2[[#This Row],[IMPORTE NETO]]*0.21 -> 0
G76: =IFERROR(IF(ventas_b_mes2[[#This Row],[CUIT]]="","-",VLOOKUP(ventas_b_mes2[[#This Row],[CUIT]],Lista_CUIT[#All],2,0)),"CUIT NO CARGADO") -> - | H76: =ventas_b_mes2[[#This Row],[TOTAL]]/1.21 -> 0 | I76: =ventas_b_mes2[[#This Row],[IMPORTE NETO]]*0.21 -> 0
B77: Total | H77: =SUBTOTAL(109,ventas_b_mes2[IMPORTE NETO]) -> 132231.4 | I77: =SUBTOTAL(109,ventas_b_mes2[IVA 21%]) -> 27768.595 | J77: =SUBTOTAL(109,ventas_b_mes2[IVA 10,5%]) -> 0 | K77: =SUBTOTAL(109,ventas_b_mes2[EXENTO]) -> 0 | L77: =SUBTOTAL(109,ventas_b_mes2[TOTAL]) -> 160000 | M77: =SUBTOTAL(103,ventas_b_mes2[Provincia]) -> 0
C85: RETENCIONES
C86: FECHA | D86: COMP Nº | E86: Columna1 | F86: CUIT | G86: RAZON SOCIAL | H86: Ganancias | I86: IVA | J86: SUSS | K86: IIBB BSAS | L86: IIBB CABA
G87: =IFERROR(IF(Retenciones_mes2[[#This Row],[CUIT]]="","-",VLOOKUP(Retenciones_mes2[[#This Row],[CUIT]],Lista_CUIT[#All],2,0)),"CUIT NO CARGADO") -> -
G88: =IFERROR(IF(Retenciones_mes2[[#This Row],[CUIT]]="","-",VLOOKUP(Retenciones_mes2[[#This Row],[CUIT]],Lista_CUIT[#All],2,0)),"CUIT NO CARGADO") -> -
G89: =IFERROR(IF(Retenciones_mes2[[#This Row],[CUIT]]="","-",VLOOKUP(Retenciones_mes2[[#This Row],[CUIT]],Lista_CUIT[#All],2,0)),"CUIT NO CARGADO") -> -
G90: =IFERROR(IF(Retenciones_mes2[[#This Row],[CUIT]]="","-",VLOOKUP(Retenciones_mes2[[#This Row],[CUIT]],Lista_CUIT[#All],2,0)),"CUIT NO CARGADO") -> -
G91: =IFERROR(IF(Retenciones_mes2[[#This Row],[CUIT]]="","-",VLOOKUP(Retenciones_mes2[[#This Row],[CUIT]],Lista_CUIT[#All],2,0)),"CUIT NO CARGADO") -> -

Sheet Mar-24
B1: LIBRO IVA COMPRAS | G1: ='Ene-24'!G1:M1 -> RABLEB SRL | N1: =EDATE('Ene-24'!N1,2) -> 45352
B3: TOTAL COMPRAS | G3: TOTAL CREDITO FISCAL | J3: TOTAL VENTAS NETAS | M3: TOTAL DEBITO FISCAL | P3: RESULTADO
B4: =SUM(compras_mes3[[#Totals],[NETO GRAVADO]])+extracto_banco_mes3[[#Totals],[NETO]] -> 1081034.2 | G4: =compras_mes3[[#Totals],[IVA 21 %]]+compras_mes3[[#Totals],[IVA 27%]]+compras_mes3[[#Totals],[IVA 10,5%]]+extracto_banco_mes3[[#Totals],[IVA 21%]]+extracto_banco_mes3[[#Totals],[IVA 10,5%]] -> 227017.17 | J4: =venta_a_mes3[[#Totals],[IMPORTE NETO]]+ventas_b_mes3[[#Totals],[IMPORTE NETO]] -> 1876164.1 | M4: =venta_a_mes3[[#Totals],[IVA 21%]]+venta_a_mes3[[#Totals],[IVA 10,5%]]+ventas_b_mes3[[#Totals],[IVA 21%]]+ventas_b_mes3[[#Totals],[IVA 10,5%]] -> 393994.46 | P4: =G4-M4 -> -166977.29
B8: FECHA | C8: TIPO | D8: PTO VTA | E8: NRO. CPTE | F8: CUIT | G8: RAZON SOCIAL | H8: NETO GRAVADO | I8: IVA 21 % | J8: IVA 27% | K8: IVA 10,5% | L8: PERC. IVA | M8: PERC IIBB BS AS | N8: PERC. IIBB CABA | O8: Otros / No Grav. | P8: TOTAL | Q8: Tipo de Gasto | R8: Provincia
B9: 31/03/2024 | C9: 1 | D9: 11 | E9: 964700 | F9: 33709585229 | G9: =IFERROR(IF(compras_mes3[[#This Row],[CUIT]]="","-",VLOOKUP(compras_mes3[[#This Row],[CUIT]],Lista_CUIT[#All],2,0)),"CUIT NO CARGADO") -> GOOGLE ARGENTINA S.R.L. | H9: 28962.51 | I9: =IF(compras_mes3[[#This Row],[NETO GRAVADO]]="","",compras_mes3[[#This Row],[NETO GRAVADO]]*0.21) -> 6082.1271 | N9: 434.44 | O9: 868.88 | P9: =SUM(compras_mes3[[#This Row],[NETO GRAVADO]:[Otros / No Grav.]]) -> 36347.957 | Q9: =IFERROR(IF(compras_mes3[[#This Row],[CUIT]]="","-",VLOOKUP(compras_mes3[[#This Row],[CUIT]],Lista_CUIT[#All],3,0)),"CUIT NO CARGADO") -> Gastos Publicidad y Propaganda | R9: =IFERROR(IF(compras_mes3[[#This Row],[CUIT]]="","-",VLOOKUP(compras_mes3[[#This Row],[CUIT]],Lista_CUIT[#All],4,0)),"CUIT NO CARGADO") -> 0
B10: 31/03/2024 | C10: 1 | D10: 11 | E10: 957922 | F10: 33709585229 | G10: =IFERROR(IF(compras_mes3[[#This Row],[CUIT]]="","-",VLOOKUP(compras_mes3[[#This Row],[CUIT]],Lista_CUIT[#All],2,0)),"CUIT NO CARGADO") -> GOOGLE ARGENTINA S.R.L. | H10: 5316.32 | I10: =IF(compras_mes3[[#This Row],[NETO GRAVADO]]="","",compras_mes3[[#This Row],[NETO GRAVADO]]*0.21) -> 1116.4272 | N10: 79.74 | O10: 159.49 | P10: =SUM(compras_mes3[[#This Row],[NETO GRAVADO]:[Otros / No Grav.]]) -> 6671.9772 | Q10: =IFERROR(IF(compras_mes3[[#This Row],[CUIT]]="","-",VLOOKUP(compras_mes3[[#This Row],[CUIT]],Lista_CUIT[#All],3,0)),"CUIT NO CARGADO") -> Gastos Publicidad y Propaganda | R10: =IFERROR(IF(compras_mes3[[#This Row],[CUIT]]="","-",VLOOKUP(compras_mes3[[#This Row],[CUIT]],Lista_CUIT[#All],4,0)),"CUIT NO CARGADO") -> 0
B11: 31/03/2024 | C11: 1 | D11: 11 | E11: 959718 | F11: 33709585229 | G11: =IFERROR(IF(compras_mes3[[#This Row],[CUIT]]="","-",VLOOKUP(compras_mes3[[#This Row],[CUIT]],Lista_CUIT[#All],2,0)),"CUIT NO CARGADO") -> GOOGLE ARGENTINA S.R.L. | H11: 9324.4 | I11: =IF(compras_mes3[[#This Row],[NETO GRAVADO]]="","",compras_mes3[[#This Row],[NETO GRAVADO]]*0.21) -> 1958.124 | N11: 139.87 | O11: 279.73 | P11: =SUM(compras_mes3[[#This Row],[NETO GRAVADO]:[Otros / No Grav.]]) -> 11702.124 | Q11: =IFERROR(IF(compras_mes3[[#This Row],[CUIT]]="","-",VLOOKUP(compras_mes3[[#This Row],[CUIT]],Lista_CUIT[#All],3,0)),"CUIT NO CARGADO") -> Gastos Publicidad y Propaganda | R11: =IFERROR(IF(compras_mes3[[#This Row],[CUIT]]="","-",VLOOKUP(compras_mes3[[#This Row],[CUIT]],Lista_CUIT[#All],4,0)),"CUIT NO CARGADO") -> 0
B12: 31/03/2024 | C12: 1 | D12: 11 | E12: 960009 | F12: 33709585229 | G12: =IFERROR(IF(compras_mes3[[#This Row],[CUIT]]="","-",VLOOKUP(compras_mes3[[#This Row],[CUIT]],Lista_CUIT[#All],2,0)),"CUIT NO CARGADO") -> GOOGLE ARGENTINA S.R.L. | H12: 291853.48 | I12: =IF(compras_mes3[[#This Row],[NETO GRAVADO]]="","",compras_mes3[[#This Row],[NETO GRAVADO]]*0.21) -> 61289.231 | N12: 4377.8 | O12: 8755.6 | P12: =SUM(compras_mes3[[#This Row],[NETO GRAVADO]:[Otros / No Grav.]]) -> 366276.11 | Q12: =IFERROR(IF(compras_mes3[[#This Row],[CUIT]]="","-",VLOOKUP(compras_mes3[[#This Row],[CUIT]],Lista_CUIT[#All],3,0)),"CUIT NO CARGADO") -> Gastos Publicidad y Propaganda | R12: =IFERROR(IF(compras_mes3[[#This Row],[CUIT]]="","-",VLOOKUP(compras_mes3[[#This Row],[CUIT]],Lista_CUIT[#All],4,0)),"CUIT NO CARGADO") -> 0
B13: 31/03/2024 | C13: 1 | D13: 11 | E13: 960015 | F13: 33709585229 | G13: =IFERROR(IF(compras_mes3[[#This Row],[CUIT]]="","-",VLOOKUP(compras_mes3[[#This Row],[CUIT]],Lista_CUIT[#All],2,0)),"CUIT NO CARGADO") -> GOOGLE ARGENTINA S.R.L. | H13: 571266.35 | I13: =IF(compras_mes3[[#This Row],[NETO GRAVADO]]="","",compras_mes3[[#This Row],[NETO GRAVADO]]*0.21) -> 119965.93 | N13: 8569 | O13: 17137.99 | P13: =SUM(compras_mes3[[#This Row],[NETO GRAVADO]:[Otros / No Grav.]]) -> 716939.27 | Q13: =IFERROR(IF(compras_mes3[[#This Row],[CUIT]]="","-",VLOOKUP(compras_mes3[[#This Row],[CUIT]],Lista_CUIT[#All],3,0)),"CUIT NO CARGADO") -> Gastos Publicidad y Propaganda | R13: =IFERROR(IF(compras_mes3[[#This Row],[CUIT]]="","-",VLOOKUP(compras_mes3[[#This Row],[CUIT]],Lista_CUIT[#All],4,0)),"CUIT NO CARGADO") -> 0
B14: 31/03/2024 | C14: 1 | D14: 11 | E14: 967082 | F14: 33709585229 | G14: =IFERROR(IF(compras_mes3[[#This Row],[CUIT]]="","-",VLOOKUP(compras_mes3[[#This Row],[CUIT]],Lista_CUIT[#All],2,0)),"CUIT NO CARGADO") -> GOOGLE ARGENTINA S.R.L. | H14: 98213.46 | I14: =IF(compras_mes3[[#This Row],[NETO GRAVADO]]="","",compras_mes3[[#This Row],[NETO GRAVADO]]*0.21) -> 20624.827 | N14: 1473.2 | O14: 2946.4 | P14: =SUM(compras_mes3[[#This Row],[NETO GRAVADO]:[Otros / No Grav.]]) -> 123257.89 | Q14: =IFERROR(IF(compras_mes3[[#This Row],[CUIT]]="","-",VLOOKUP(compras_mes3[[#This Row],[CUIT]],Lista_CUIT[#All],3,0)),"CUIT NO CARGADO") -> Gastos Publicidad y Propaganda | R14: =IFERROR(IF(compras_mes3[[#This Row],[CUIT]]="","-",VLOOKUP(compras_mes3[[#This Row],[CUIT]],Lista_CUIT[#All],4,0)),"CUIT NO CARGADO") -> 0
B15: 31/03/2024 | C15: 1 | D15: 11 | E15: 965149 | F15: 33709585229 | G15: =IFERROR(IF(compras_mes3[[#This Row],[CUIT]]="","-",VLOOKUP(compras_mes3[[#This Row],[CUIT]],Lista_CUIT[#All],2,0)),"CUIT NO CARGADO") -> GOOGLE ARGENTINA S.R.L. | H15: 30531.42 | I15: =IF(compras_mes3[[#This Row],[NETO GRAVADO]]="","",compras_mes3[[#This Row],[NETO GRAVADO]]*0.21) -> 6411.5982 | N15: 457.97 | O15: 915.94 | P15: =SUM(compras_mes3[[#This Row],[NETO GRAVADO]:[Otros / No Grav.]]) -> 38316.928 | Q15: =IFERROR(IF(compras_mes3[[#This Row],[CUIT]]="","-",VLOOKUP(compras_mes3[[#This Row],[CUIT]],Lista_CUIT[#All],3,0)),"CUIT NO CARGADO") -> Gastos Publicidad y Propaganda | R15: =IFERROR(IF(compras_mes3[[#This Row],[CUIT]]="","-",VLOOKUP(compras_mes3[[#This Row],[CUIT]],Lista_CUIT[#All],4,0)),"CUIT NO CARGADO") -> 0
B16: 31/03/2024 | C16: 1 | D16: 11 | E16: 967210 | F16: 33709585229 | G16: =IFERROR(IF(compras_mes3[[#This Row],[CUIT]]="","-",VLOOKUP(compras_mes3[[#This Row],[CUIT]],Lista_CUIT[#All],2,0)),"CUIT NO CARGADO") -> GOOGLE ARGENTINA S.R.L. | H16: 47758.97 | I16: =IF(compras_mes3[[#This Row],[NETO GRAVADO]]="","",compras_mes3[[#This Row],[NETO GRAVADO]]*0.21) -> 10029.384 | N16: 716.38 | O16: 1432.77 | P16: =SUM(compras_mes3[[#This Row],[NETO GRAVADO]:[Otros / No Grav.]]) -> 59937.504 | Q16: =IFERROR(IF(compras_mes3[[#This Row],[CUIT]]="","-",VLOOKUP(compras_mes3[[#This Row],[CUIT]],Lista_CUIT[#All],3,0)),"CUIT NO CARGADO") -> Gastos Publicidad y Propaganda | R16: =IFERROR(IF(compras_mes3[[#This Row],[CUIT]]="","-",VLOOKUP(compras_mes3[[#This Row],[CUIT]],Lista_CUIT[#All],4,0)),"CUIT NO CARGADO") -> 0
B17: 31/03/2024 | C17: 3 | D17: 11 | E17: 707678 | F17: 33709585229 | G17: =IFERROR(IF(compras_mes3[[#This Row],[CUIT]]="","-",VLOOKUP(compras_mes3[[#This Row],[CUIT]],Lista_CUIT[#All],2,0)),"CUIT NO CARGADO") -> GOOGLE ARGENTINA S.R.L. | H17: -2192.75 | I17: =IF(compras_mes3[[#This Row],[NETO GRAVADO]]="","",compras_mes3[[#This Row],[NETO GRAVADO]]*0.21) -> -460.4775 | N17: -32.89 | O17: -65.78 | P17: =SUM(compras_mes3[[#This Row],[NETO GRAVADO]:[Otros / No Grav.]]) -> -2751.8975 | Q17: =IFERROR(IF(compras_mes3[[#This Row],[CUIT]]="","-",VLOOKUP(compras_mes3[[#This Row],[CUIT]],Lista_CUIT[#All],3,0)),"CUIT NO CARGADO") -> Gastos Publicidad y Propaganda | R17: =IFERROR(IF(compras_mes3[[#This Row],[CUIT]]="","-",VLOOKUP(compras_mes3[[#This Row],[CUIT]],Lista_CUIT[#All],4,0)),"CUIT NO CARGADO") -> 0
G18: =IFERROR(IF(compras_mes3[[#This Row],[CUIT]]="","-",VLOOKUP(compras_mes3[[#This Row],[CUIT]],Lista_CUIT[#All],2,0)),"CUIT NO CARGADO") -> - | I18: =IF(compras_mes3[[#This Row],[NETO GRAVADO]]="","",compras_mes3[[#This Row],[NETO GRAVADO]]*0.21) | P18: =SUM(compras_mes3[[#This Row],[NETO GRAVADO]:[Otros / No Grav.]]) -> 0 | Q18: =IFERROR(IF(compras_mes3[[#This Row],[CUIT]]="","-",VLOOKUP(compras_mes3[[#This Row],[CUIT]],Lista_CUIT[#All],3,0)),"CUIT NO CARGADO") -> - | R18: =IFERROR(IF(compras_mes3[[#This Row],[CUIT]]="","-",VLOOKUP(compras_mes3[[#This Row],[CUIT]],Lista_CUIT[#All],4,0)),"CUIT NO CARGADO") -> -
G19: =IFERROR(IF(compras_mes3[[#This Row],[CUIT]]="","-",VLOOKUP(compras_mes3[[#This Row],[CUIT]],Lista_CUIT[#All],2,0)),"CUIT NO CARGADO") -> - | I19: =IF(compras_mes3[[#This Row],[NETO GRAVADO]]="","",compras_mes3[[#This Row],[NETO GRAVADO]]*0.21) | P19: =SUM(compras_mes3[[#This Row],[NETO GRAVADO]:[Otros / No Grav.]]) -> 0 | Q19: =IFERROR(IF(compras_mes3[[#This Row],[CUIT]]="","-",VLOOKUP(compras_mes3[[#This Row],[CUIT]],Lista_CUIT[#All],3,0)),"CUIT NO CARGADO") -> - | R19: =IFERROR(IF(compras_mes3[[#This Row],[CUIT]]="","-",VLOOKUP(compras_mes3[[#This Row],[CUIT]],Lista_CUIT[#All],4,0)),"CUIT NO CARGADO") -> -
B20: Total | H20: =SUBTOTAL(109,compras_mes3[NETO GRAVADO]) -> 1081034.2 | I20: =SUBTOTAL(109,compras_mes3[IVA 21 %]) -> 227017.17 | J20: =SUBTOTAL(109,compras_mes3[IVA 27%]) -> 0 | K20: =SUBTOTAL(109,compras_mes3[IVA 10,5%]) -> 0 | L20: =SUBTOTAL(109,compras_mes3[PERC. IVA]) -> 0 | M20: =SUBTOTAL(109,compras_mes3[PERC IIBB BS AS]) -> 0 | N20: =SUBTOTAL(109,compras_mes3[PERC. IIBB CABA]) -> 16215.51 | O20: =SUBTOTAL(109,compras_mes3[Otros / No Grav.]) -> 32431.02 | P20: =SUBTOTAL(109,compras_mes3[TOTAL]) -> 1356697.9
D25: LIQUIDACION EXTRACTOS BANCARIOS-TARJETAS
D26: FECHA | E26: NRO CPTE | F26: BANCO | G26: NETO | H26: IVA 21% | I26: IVA 10,5% | J26: RET IIBB CABA | K26: PERC IVA | L26: PERC IIBB
D30: Total | G30: =SUBTOTAL(109,extracto_banco_mes3[NETO]) -> 0 | H30: =SUBTOTAL(109,extracto_banco_mes3[IVA 21%]) -> 0 | I30: =SUBTOTAL(109,extracto_banco_mes3[IVA 10,5%]) -> 0 | J30: =SUBTOTAL(109,extracto_banco_mes3[RET IIBB CABA]) -> 0 | K30: =SUBTOTAL(109,extracto_banco_mes3[PERC IVA]) -> 0 | L30: =SUBTOTAL(109,extracto_banco_mes3[PERC IIBB]) -> 0
D34: FACTURAS C
D35: FECHA | E35: PTO VTA | F35: FC Nº | G35: CUIT | H35: RAZON SOCIAL | I35: TOTAL | J35: TIPO DE GASTO | K35: Provincia
D36: 04/03/2024 | E36: 2 | F36: 732 | G36: 20400104094 | H36: =IFERROR(IF(factura_c_mes3[[#This Row],[CUIT]]="","-",VLOOKUP(factura_c_mes3[[#This Row],[CUIT]],Lista_CUIT[#All],2,0)),"CUIT NO CARGADO") -> BOTINDARI FEDERICO DANIEL | I36: 75000 | J36: =IFERROR(IF(factura_c_mes3[[#This Row],[CUIT]]="","-",VLOOKUP(factura_c_mes3[[#This Row],[CUIT]],Lista_CUIT[#All],3,0)),"CUIT NO CARGADO") -> HONORARIOS CONTABLE | K36: =IFERROR(IF(factura_c_mes3[[#This Row],[CUIT]]="","-",VLOOKUP(factura_c_mes3[[#This Row],[CUIT]],Lista_CUIT[#All],4,0)),"CUIT NO CARGADO") -> 0
D37: 05/03/2024 | E37: 1 | F37: 300 | G37: 27386311000 | H37: =IFERROR(IF(factura_c_mes3[[#This Row],[CUIT]]="","-",VLOOKUP(factura_c_mes3[[#This Row],[CUIT]],Lista_CUIT[#All],2,0)),"CUIT NO CARGADO") -> OPANASIUK MACARENA ANTONELLA | I37: 250000 | J37: =IFERROR(IF(factura_c_mes3[[#This Row],[CUIT]]="","-",VLOOKUP(factura_c_mes3[[#This Row],[CUIT]],Lista_CUIT[#All],3,0)),"CUIT NO CARGADO") -> Honorarios Profesionales | K37: =IFERROR(IF(factura_c_mes3[[#This Row],[CUIT]]="","-",VLOOKUP(factura_c_mes3[[#This Row],[CUIT]],Lista_CUIT[#All],4,0)),"CUIT NO CARGADO") -> 0
H38: =IFERROR(IF(factura_c_mes3[[#This Row],[CUIT]]="","-",VLOOKUP(factura_c_mes3[[#This Row],[CUIT]],Lista_CUIT[#All],2,0)),"CUIT NO CARGADO") -> - | J38: =IFERROR(IF(factura_c_mes3[[#This Row],[CUIT]]="","-",VLOOKUP(factura_c_mes3[[#This Row],[CUIT]],Lista_CUIT[#All],3,0)),"CUIT NO CARGADO") -> - | K38: =IFERROR(IF(factura_c_mes3[[#This Row],[CUIT]]="","-",VLOOKUP(factura_c_mes3[[#This Row],[CUIT]],Lista_CUIT[#All],4,0)),"CUIT NO CARGADO") -> -
H39: =IFERROR(IF(factura_c_mes3[[#This Row],[CUIT]]="","-",VLOOKUP(factura_c_mes3[[#This Row],[CUIT]],Lista_CUIT[#All],2,0)),"CUIT NO CARGADO") -> - | J39: =IFERROR(IF(factura_c_mes3[[#This Row],[CUIT]]="","-",VLOOKUP(factura_c_mes3[[#This Row],[CUIT]],Lista_CUIT[#All],3,0)),"CUIT NO CARGADO") -> - | K39: =IFERROR(IF(factura_c_mes3[[#This Row],[CUIT]]="","-",VLOOKUP(factura_c_mes3[[#This Row],[CUIT]],Lista_CUIT[#All],4,0)),"CUIT NO CARGADO") -> -
D40: Total | I40: =SUBTOTAL(109,factura_c_mes3[TOTAL]) -> 325000
B46: LIBRO IVA VENTAS | K46: =N1 -> 45352
B48: VENTAS "A"
B49: FECHA | C49: TIPO | D49: PTO VENTA | E49: Nº FACTURA | F49: CUIT | G49: RAZON SOCIAL | H49: IMPORTE NETO | I49: IVA 21% | J49: IVA 10,5% | K49: EXENTO | L49: TOTAL | M49: Provincia
B50: 01/03/2024 | C50: 1 | D50: 1 | E50: 150 | F50: 30715941763 | G50: =IFERROR(IF(venta_a_mes3[[#This Row],[CUIT]]="","-",VLOOKUP(venta_a_mes3[[#This Row],[CUIT]],Lista_CUIT[#All],2,0)),"CUIT NO CARGADO") -> TOURMALHYN S.R.L. | H50: 20661.14 | I50: =venta_a_mes3[[#This Row],[IMPORTE NETO]]*0.21 -> 4338.8394 | L50: =SUM(venta_a_mes3[[#This Row],[IMPORTE NETO]:[EXENTO]]) -> 24999.979
B51: 01/03/2024 | C51: 1 | D51: 1 | E51: 151 | F51: 30717969061 | G51: =IFERROR(IF(venta_a_mes3[[#This Row],[CUIT]]="","-",VLOOKUP(venta_a_mes3[[#This Row],[CUIT]],Lista_CUIT[#All],2,0)),"CUIT NO CARGADO") -> FABIO Y RAUL ROSSO S.A.S. | H51: 37685.95 | I51: =venta_a_mes3[[#This Row],[IMPORTE NETO]]*0.21 -> 7914.0495 | L51: =SUM(venta_a_mes3[[#This Row],[IMPORTE NETO]:[EXENTO]]) -> 45599.999
B52: 01/03/2024 | C52: 1 | D52: 1 | E52: 154 | F52: 30688955749 | G52: =IFERROR(IF(venta_a_mes3[[#This Row],[CUIT]]="","-",VLOOKUP(venta_a_mes3[[#This Row],[CUIT]],Lista_CUIT[#All],2,0)),"CUIT NO CARGADO") -> LISERAR S A | H52: 96694.24 | I52: =venta_a_mes3[[#This Row],[IMPORTE NETO]]*0.21 -> 20305.79 | L52: =SUM(venta_a_mes3[[#This Row],[IMPORTE NETO]:[EXENTO]]) -> 117000.03
B53: 01/03/2024 | C53: 1 | D53: 1 | E53: 146 | F53: 27165844748 | G53: =IFERROR(IF(venta_a_mes3[[#This Row],[CUIT]]="","-",VLOOKUP(venta_a_mes3[[#This Row],[CUIT]],Lista_CUIT[#All],2,0)),"CUIT NO CARGADO") -> DENATALE MARCELA BEATRIZ | H53: 96694.24 | I53: =venta_a_mes3[[#This Row],[IMPORTE NETO]]*0.21 -> 20305.79 | L53: =SUM(venta_a_mes3[[#This Row],[IMPORTE NETO]:[EXENTO]]) -> 117000.03
B54: 01/03/2024 | C54: 1 | D54: 1 | E54: 148 | F54: 20279415656 | G54: =IFERROR(IF(venta_a_mes3[[#This Row],[CUIT]]="","-",VLOOKUP(venta_a_mes3[[#This Row],[CUIT]],Lista_CUIT[#All],2,0)),"CUIT NO CARGADO") -> CECCO ALVARO GONZALO | H54: 75371.9 | I54: =venta_a_mes3[[#This Row],[IMPORTE NETO]]*0.21 -> 15828.099 | L54: =SUM(venta_a_mes3[[#This Row],[IMPORTE NETO]:[EXENTO]]) -> 91199.999
B55: 01/03/2024 | C55: 1 | D55: 1 | E55: 143 | F55: 20284212488 | G55: =IFERROR(IF(venta_a_mes3[[#This Row],[CUIT]]="","-",VLOOKUP(venta_a_mes3[[#This Row],[CUIT]],Lista_CUIT[#All],2,0)),"CUIT NO CARGADO") -> BARLETTA MAXIMILIANO SEBASTIAN | H55: 37685.95 | I55: =venta_a_mes3[[#This Row],[IMPORTE NETO]]*0.21 -> 7914.0495 | L55: =SUM(venta_a_mes3[[#This Row],[IMPORTE NETO]:[EXENTO]]) -> 45599.999
B56: 01/03/2024 | C56: 1 | D56: 1 | E56: 149 | F56: 20367341808 | G56: =IFERROR(IF(venta_a_mes3[[#This Row],[CUIT]]="","-",VLOOKUP(venta_a_mes3[[#This Row],[CUIT]],Lista_CUIT[#All],2,0)),"CUIT NO CARGADO") -> FEIDAS FERNANDO EMILIANO | H56: 49586.76 | I56: =venta_a_mes3[[#This Row],[IMPORTE NETO]]*0.21 -> 10413.22 | L56: =SUM(venta_a_mes3[[#This Row],[IMPORTE NETO]:[EXENTO]]) -> 59999.98
B57: 01/03/2024 | C57: 1 | D57: 1 | E57: 145 | F57: 30717973166 | G57: =IFERROR(IF(venta_a_mes3[[#This Row],[CUIT]]="","-",VLOOKUP(venta_a_mes3[[#This Row],[CUIT]],Lista_CUIT[#All],2,0)),"CUIT NO CARGADO") -> STM ESTILO S.R.L | H57: 37685.95 | I57: =venta_a_mes3[[#This Row],[IMPORTE NETO]]*0.21 -> 7914.0495 | L57: =SUM(venta_a_mes3[[#This Row],[IMPORTE NETO]:[EXENTO]]) -> 45599.999
B58: 01/03/2024 | C58: 1 | D58: 1 | E58: 144 | F58: 30715380567 | G58: =IFERROR(IF(venta_a_mes3[[#This Row],[CUIT]]="","-",VLOOKUP(venta_a_mes3[[#This Row],[CUIT]],Lista_CUIT[#All],2,0)),"CUIT NO CARGADO") -> SENS GROUP SRL | H58: 141205.24 | I58: =venta_a_mes3[[#This Row],[IMPORTE NETO]]*0.21 -> 29653.1 | L58: =SUM(venta_a_mes3[[#This Row],[IMPORTE NETO]:[EXENTO]]) -> 170858.34
B59: 01/03/2024 | C59: 1 | D59: 1 | E59: 142 | F59: 30717477681 | G59: =IFERROR(IF(venta_a_mes3[[#This Row],[CUIT]]="","-",VLOOKUP(venta_a_mes3[[#This Row],[CUIT]],Lista_CUIT[#All],2,0)),"CUIT NO CARGADO") -> GRUPO FAM SA | H59: 52479.33 | I59: =venta_a_mes3[[#This Row],[IMPORTE NETO]]*0.21 -> 11020.659 | L59: =SUM(venta_a_mes3[[#This Row],[IMPORTE NETO]:[EXENTO]]) -> 63499.989
B60: 01/03/2024 | C60: 1 | D60: 1 | E60: 141 | F60: 30716914077 | G60: =IFERROR(IF(venta_a_mes3[[#This Row],[CUIT]]="","-",VLOOKUP(venta_a_mes3[[#This Row],[CUIT]],Lista_CUIT[#All],2,0)),"CUIT NO CARGADO") -> BACANES | H60: 96694.24 | I60: =venta_a_mes3[[#This Row],[IMPORTE NETO]]*0.21 -> 20305.79 | L60: =SUM(venta_a_mes3[[#This Row],[IMPORTE NETO]:[EXENTO]]) -> 117000.03
B61: 01/03/2024 | C61: 1 | D61: 1 | E61: 147 | F61: 20287305460 | G61: =IFERROR(IF(venta_a_mes3[[#This Row],[CUIT]]="","-",VLOOKUP(venta_a_mes3[[#This Row],[CUIT]],Lista_CUIT[#All],2,0)),"CUIT NO CARGADO") -> LANDI GERONIMO | H61: 37685.95 | I61: =venta_a_mes3[[#This Row],[IMPORTE NETO]]*0.21 -> 7914.0495 | L61: =SUM(venta_a_mes3[[#This Row],[IMPORTE NETO]:[EXENTO]]) -> 45599.999
... B68: 20/03/2024 | C68: 1 | D68: 1 | E68: 157 | F68: 20277452872 | G68: =IFERROR(IF(venta_a_mes3[[#This Row],[CUIT]]="","-",VLOOKUP(venta_a_mes3[[#This Row],[CUIT]],Lista_CUIT[#All],2,0)),"CUIT NO CARGADO") -> GERVASI MAXIMILIANO ARIEL | H68: 390909.1 | I68: =venta_a_mes3[[#This Row],[IMPORTE NETO]]*0.21 -> 82090.911 | L68: =SUM(venta_a_mes3[[#This Row],[IMPORTE NETO]:[EXENTO]]) -> 473000.01
B69: Total | H69: =SUBTOTAL(109,venta_a_mes3[IMPORTE NETO]) -> 1644759.1 | I69: =SUBTOTAL(109,venta_a_mes3[IVA 21%]) -> 345399.41 | J69: =SUBTOTAL(109,venta_a_mes3[IVA 10,5%]) -> 0 | K69: =SUBTOTAL(109,venta_a_mes3[EXENTO]) -> 0 | L69: =SUBTOTAL(109,venta_a_mes3[TOTAL]) -> 1990158.5 | M69: =SUBTOTAL(103,venta_a_mes3[Provincia]) -> 0
B71: VENTAS "B"
B72: FECHA | C72: TIPO | D72: PTO VENTA | E72: Nº FACTURA | F72: CUIT | G72: RAZON SOCIAL | H72: IMPORTE NETO | I72: IVA 21% | J72: IVA 10,5% | K72: EXENTO | L72: TOTAL | M72: Provincia
B73: 01/03/2024 | C73: 6 | D73: 1 | E73: 30 | F73: 20252582704 | G73: =IFERROR(IF(ventas_b_mes3[[#This Row],[CUIT]]="","-",VLOOKUP(ventas_b_mes3[[#This Row],[CUIT]],Lista_CUIT[#All],2,0)),"CUIT NO CARGADO") -> GARCIA VAUTRIN ANDRES ALBERTO | H73: 99173.57 | I73: =ventas_b_mes3[[#This Row],[IMPORTE NETO]]*0.21 -> 20826.45 | L73: =SUM(ventas_b_mes3[[#This Row],[IMPORTE NETO]:[EXENTO]]) -> 120000.02
B74: 01/03/2024 | C74: 6 | D74: 1 | E74: 28 | F74: 30521448608 | G74: =IFERROR(IF(ventas_b_mes3[[#This Row],[CUIT]]="","-",VLOOKUP(ventas_b_mes3[[#This Row],[CUIT]],Lista_CUIT[#All],2,0)),"CUIT NO CARGADO") -> INSTITUTO ORSINO SA | H74: 33057.86 | I74: =ventas_b_mes3[[#This Row],[IMPORTE NETO]]*0.21 -> 6942.1506 | L74: =SUM(ventas_b_mes3[[#This Row],[IMPORTE NETO]:[EXENTO]]) -> 40000.011
B75: 01/03/2024 | C75: 6 | D75: 1 | E75: 29 | F75: 30592508830 | G75: =IFERROR(IF(ventas_b_mes3[[#This Row],[CUIT]]="","-",VLOOKUP(ventas_b_mes3[[#This Row],[CUIT]],Lista_CUIT[#All],2,0)),"CUIT NO CARGADO") -> INSTITUTO DE ESTUDIOS SUPERIORES DE BUENOS AIRES S A | H75: 33057.86 | I75: =ventas_b_mes3[[#This Row],[IMPORTE NETO]]*0.21 -> 6942.1506 | L75: =SUM(ventas_b_mes3[[#This Row],[IMPORTE NETO]:[EXENTO]]) -> 40000.011
B76: 01/03/2024 | C76: 6 | D76: 1 | E76: 27 | F76: 30700477920 | G76: =IFERROR(IF(ventas_b_mes3[[#This Row],[CUIT]]="","-",VLOOKUP(ventas_b_mes3[[#This Row],[CUIT]],Lista_CUIT[#All],2,0)),"CUIT NO CARGADO") -> ESBA FLORESS A | H76: 33057.86 | I76: =ventas_b_mes3[[#This Row],[IMPORTE NETO]]*0.21 -> 6942.1506 | L76: =SUM(ventas_b_mes3[[#This Row],[IMPORTE NETO]:[EXENTO]]) -> 40000.011
B77: 01/03/2024 | C77: 6 | D77: 1 | E77: 26 | F77: 30681452423 | G77: =IFERROR(IF(ventas_b_mes3[[#This Row],[CUIT]]="","-",VLOOKUP(ventas_b_mes3[[#This Row],[CUIT]],Lista_CUIT[#All],2,0)),"CUIT NO CARGADO") -> E S B A LUGANO S A | H77: 33057.86 | I77: =ventas_b_mes3[[#This Row],[IMPORTE NETO]]*0.21 -> 6942.1506 | L77: =SUM(ventas_b_mes3[[#This Row],[IMPORTE NETO]:[EXENTO]]) -> 40000.011
I78: =ventas_b_mes3[[#This Row],[IMPORTE NETO]]*0.21 -> 0 | L78: =SUM(ventas_b_mes3[[#This Row],[IMPORTE NETO]:[EXENTO]]) -> 0
B79: Total | H79: =SUBTOTAL(109,ventas_b_mes3[IMPORTE NETO]) -> 231405.01 | I79: =SUBTOTAL(109,ventas_b_mes3[IVA 21%]) -> 48595.052 | J79: =SUBTOTAL(109,ventas_b_mes3[IVA 10,5%]) -> 0 | K79: =SUBTOTAL(109,ventas_b_mes3[EXENTO]) -> 0 | L79: =SUBTOTAL(109,ventas_b_mes3[TOTAL]) -> 280000.06 | M79: =SUBTOTAL(103,ventas_b_mes3[Provincia]) -> 0
C87: RETENCIONES
C88: FECHA | D88: COMP Nº | E88: Columna1 | F88: CUIT | G88: RAZON SOCIAL | H88: Ganancias | I88: IVA | J88: SUSS | K88: IIBB BSAS | L88: IIBB CABA
G89: =IFERROR(IF(Retenciones_mes3[[#This Row],[CUIT]]="","-",VLOOKUP(Retenciones_mes3[[#This Row],[CUIT]],Lista_CUIT[#All],2,0)),"CUIT NO CARGADO") -> -
G90: =IFERROR(IF(Retenciones_mes3[[#This Row],[CUIT]]="","-",VLOOKUP(Retenciones_mes3[[#This Row],[CUIT]],Lista_CUIT[#All],2,0)),"CUIT NO CARGADO") -> -
G91: =IFERROR(IF(Retenciones_mes3[[#This Row],[CUIT]]="","-",VLOOKUP(Retenciones_mes3[[#This Row],[CUIT]],Lista_CUIT[#All],2,0)),"CUIT NO CARGADO") -> -
G92: =IFERROR(IF(Retenciones_mes3[[#This Row],[CUIT]]="","-",VLOOKUP(Retenciones_mes3[[#This Row],[CUIT]],Lista_CUIT[#All],2,0)),"CUIT NO CARGADO") -> -
G93: =IFERROR(IF(Retenciones_mes3[[#This Row],[CUIT]]="","-",VLOOKUP(Retenciones_mes3[[#This Row],[CUIT]],Lista_CUIT[#All],2,0)),"CUIT NO CARGADO") -> -

Sheet Abr-24
B1: LIBRO IVA COMPRAS | G1: ='Ene-24'!G1:M1 -> RABLEB SRL | N1: =EDATE('Ene-24'!N1,3) -> 45383
B3: TOTAL COMPRAS | G3: TOTAL CREDITO FISCAL | J3: TOTAL VENTAS NETAS | M3: TOTAL DEBITO FISCAL | P3: RESULTADO
B4: =SUM(compras_mes4[[#Totals],[NETO GRAVADO]])+extracto_banco_mes4[[#Totals],[NETO]] -> 1085466.4 | G4: =compras_mes4[[#Totals],[IVA 21 %]]+compras_mes4[[#Totals],[IVA 27%]]+compras_mes4[[#Totals],[IVA 10,5%]]+extracto_banco_mes4[[#Totals],[IVA 21%]]+extracto_banco_mes4[[#Totals],[IVA 10,5%]] -> 227947.95 | J4: =venta_a_mes4[[#Totals],[IMPORTE NETO]]+ventas_b_mes4[[#Totals],[IMPORTE NETO]] -> 1892977 | M4: =venta_a_mes4[[#Totals],[IVA 21%]]+venta_a_mes4[[#Totals],[IVA 10,5%]]+ventas_b_mes4[[#Totals],[IVA 21%]]+ventas_b_mes4[[#Totals],[IVA 10,5%]] -> 397525.18 | P4: =G4-M4 -> -169577.23
B8: FECHA | C8: TIPO | D8: PTO VTA | E8: NRO. CPTE | F8: CUIT | G8: RAZON SOCIAL | H8: NETO GRAVADO | I8: IVA 21 % | J8: IVA 27% | K8: IVA 10,5% | L8: PERC. IVA | M8: PERC IIBB BS AS | N8: PERC. IIBB CABA | O8: Otros / No Grav. | P8: TOTAL | Q8: Tipo de Gasto | R8: Provincia
B9: 45408 | C9: 1 | D9: 11 | E9: 967928 | F9: 33709585229 | G9: =IFERROR(IF(compras_mes4[[#This Row],[CUIT]]="","-",VLOOKUP(compras_mes4[[#This Row],[CUIT]],Lista_CUIT[#All],2,0)),"CUIT NO CARGADO") -> GOOGLE ARGENTINA S.R.L. | H9: 10880.12 | I9: =IF(compras_mes4[[#This Row],[NETO GRAVADO]]="","",compras_mes4[[#This Row],[NETO GRAVADO]]*0.21) -> 2284.8252 | L9: 326.4 | N9: 163.2 | P9: =SUM(compras_mes4[[#This Row],[NETO GRAVADO]:[Otros / No Grav.]]) -> 13654.545 | Q9: =IFERROR(IF(compras_mes4[[#This Row],[CUIT]]="","-",VLOOKUP(compras_mes4[[#This Row],[CUIT]],Lista_CUIT[#All],3,0)),"CUIT NO CARGADO") -> Gastos Publicidad y Propaganda | R9: =IFERROR(IF(compras_mes4[[#This Row],[CUIT]]="","-",VLOOKUP(compras_mes4[[#This Row],[CUIT]],Lista_CUIT[#All],4,0)),"CUIT NO CARGADO") -> 0
B10: 45412 | C10: 1 | D10: 11 | E10: 976843 | F10: 33709585229 | G10: =IFERROR(IF(compras_mes4[[#This Row],[CUIT]]="","-",VLOOKUP(compras_mes4[[#This Row],[CUIT]],Lista_CUIT[#All],2,0)),"CUIT NO CARGADO") -> GOOGLE ARGENTINA S.R.L. | H10: 173192.04 | I10: =IF(compras_mes4[[#This Row],[NETO GRAVADO]]="","",compras_mes4[[#This Row],[NETO GRAVADO]]*0.21) -> 36370.328 | L10: 5195.76 | N10: 2597.88 | P10: =SUM(compras_mes4[[#This Row],[NETO GRAVADO]:[Otros / No Grav.]]) -> 217356.01 | Q10: =IFERROR(IF(compras_mes4[[#This Row],[CUIT]]="","-",VLOOKUP(compras_mes4[[#This Row],[CUIT]],Lista_CUIT[#All],3,0)),"CUIT NO CARGADO") -> Gastos Publicidad y Propaganda | R10: =IFERROR(IF(compras_mes4[[#This Row],[CUIT]]="","-",VLOOKUP(compras_mes4[[#This Row],[CUIT]],Lista_CUIT[#All],4,0)),"CUIT NO CARGADO") -> 0
B11: 45412 | C11: 1 | D11: 11 | E11: 971874 | F11: 33709585229 | G11: =IFERROR(IF(compras_mes4[[#This Row],[CUIT]]="","-",VLOOKUP(compras_mes4[[#This Row],[CUIT]],Lista_CUIT[#All],2,0)),"CUIT NO CARGADO") -> GOOGLE ARGENTINA S.R.L. | H11: 152788.55 | I11: =IF(compras_mes4[[#This Row],[NETO GRAVADO]]="","",compras_mes4[[#This Row],[NETO GRAVADO]]*0.21) -> 32085.595 | L11: 4583.66 | N11: 2291.83 | P11: =SUM(compras_mes4[[#This Row],[NETO GRAVADO]:[Otros / No Grav.]]) -> 191749.64 | Q11: =IFERROR(IF(compras_mes4[[#This Row],[CUIT]]="","-",VLOOKUP(compras_mes4[[#This Row],[CUIT]],Lista_CUIT[#All],3,0)),"CUIT NO CARGADO") -> Gastos Publicidad y Propaganda | R11: =IFERROR(IF(compras_mes4[[#This Row],[CUIT]]="","-",VLOOKUP(compras_mes4[[#This Row],[CUIT]],Lista_CUIT[#All],4,0)),"CUIT NO CARGADO") -> 0
B12: 45412 | C12: 1 | D12: 11 | E12: 969884 | F12: 33709585229 | G12: =IFERROR(IF(compras_mes4[[#This Row],[CUIT]]="","-",VLOOKUP(compras_mes4[[#This Row],[CUIT]],Lista_CUIT[#All],2,0)),"CUIT NO CARGADO") -> GOOGLE ARGENTINA S.R.L. | H12: 32999.28 | I12: =IF(compras_mes4[[#This Row],[NETO GRAVADO]]="","",compras_mes4[[#This Row],[NETO GRAVADO]]*0.21) -> 6929.8488 | L12: 989.98 | N12: 494.99 | P12: =SUM(compras_mes4[[#This Row],[NETO GRAVADO]:[Otros / No Grav.]]) -> 41414.099 | Q12: =IFERROR(IF(compras_mes4[[#This Row],[CUIT]]="","-",VLOOKUP(compras_mes4[[#This Row],[CUIT]],Lista_CUIT[#All],3,0)),"CUIT NO CARGADO") -> Gastos Publicidad y Propaganda | R12: =IFERROR(IF(compras_mes4[[#This Row],[CUIT]]="","-",VLOOKUP(compras_mes4[[#This Row],[CUIT]],Lista_CUIT[#All],4,0)),"CUIT NO CARGADO") -> 0
B13: 45412 | C13: 1 | D13: 11 | E13: 971340 | F13: 33709585229 | G13: =IFERROR(IF(compras_mes4[[#This Row],[CUIT]]="","-",VLOOKUP(compras_mes4[[#This Row],[CUIT]],Lista_CUIT[#All],2,0)),"CUIT NO CARGADO") -> GOOGLE ARGENTINA S.R.L. | H13: 597227.95 | I13: =IF(compras_mes4[[#This Row],[NETO GRAVADO]]="","",compras_mes4[[#This Row],[NETO GRAVADO]]*0.21) -> 125417.87 | L13: 17916.84 | N13: 8958.42 | P13: =SUM(compras_mes4[[#This Row],[NETO GRAVADO]:[Otros / No Grav.]]) -> 749521.08 | Q13: =IFERROR(IF(compras_mes4[[#This Row],[CUIT]]="","-",VLOOKUP(compras_mes4[[#This Row],[CUIT]],Lista_CUIT[#All],3,0)),"CUIT NO CARGADO") -> Gastos Publicidad y Propaganda | R13: =IFERROR(IF(compras_mes4[[#This Row],[CUIT]]="","-",VLOOKUP(compras_mes4[[#This Row],[CUIT]],Lista_CUIT[#All],4,0)),"CUIT NO CARGADO") -> 0
B14: 45412 | C14: 1 | D14: 11 | E14: 977142 | F14: 33709585229 | G14: =IFERROR(IF(compras_mes4[[#This Row],[CUIT]]="","-",VLOOKUP(compras_mes4[[#This Row],[CUIT]],Lista_CUIT[#All],2,0)),"CUIT NO CARGADO") -> GOOGLE ARGENTINA S.R.L. | H14: 52051.21 | I14: =IF(compras_mes4[[#This Row],[NETO GRAVADO]]="","",compras_mes4[[#This Row],[NETO GRAVADO]]*0.21) -> 10930.754 | L14: 1561.54 | N14: 780.77 | P14: =SUM(compras_mes4[[#This Row],[NETO GRAVADO]:[Otros / No Grav.]]) -> 65324.274 | Q14: =IFERROR(IF(compras_mes4[[#This Row],[CUIT]]="","-",VLOOKUP(compras_mes4[[#This Row],[CUIT]],Lista_CUIT[#All],3,0)),"CUIT NO CARGADO") -> Gastos Publicidad y Propaganda | R14: =IFERROR(IF(compras_mes4[[#This Row],[CUIT]]="","-",VLOOKUP(compras_mes4[[#This Row],[CUIT]],Lista_CUIT[#All],4,0)),"CUIT NO CARGADO") -> 0
B15: 45412 | C15: 1 | D15: 11 | E15: 977820 | F15: 33709585229 | G15: =IFERROR(IF(compras_mes4[[#This Row],[CUIT]]="","-",VLOOKUP(compras_mes4[[#This Row],[CUIT]],Lista_CUIT[#All],2,0)),"CUIT NO CARGADO") -> GOOGLE ARGENTINA S.R.L. | H15: 3153.56 | I15: =IF(compras_mes4[[#This Row],[NETO GRAVADO]]="","",compras_mes4[[#This Row],[NETO GRAVADO]]*0.21) -> 662.2476 | L15: 94.61 | N15: 47.3 | P15: =SUM(compras_mes4[[#This Row],[NETO GRAVADO]:[Otros / No Grav.]]) -> 3957.7176 | Q15: =IFERROR(IF(compras_mes4[[#This Row],[CUIT]]="","-",VLOOKUP(compras_mes4[[#This Row],[CUIT]],Lista_CUIT[#All],3,0)),"CUIT NO CARGADO") -> Gastos Publicidad y Propaganda | R15: =IFERROR(IF(compras_mes4[[#This Row],[CUIT]]="","-",VLOOKUP(compras_mes4[[#This Row],[CUIT]],Lista_CUIT[#All],4,0)),"CUIT NO CARGADO") -> 0
B16: 45412 | C16: 1 | D16: 11 | E16: 978859 | F16: 33709585229 | G16: =IFERROR(IF(compras_mes4[[#This Row],[CUIT]]="","-",VLOOKUP(compras_mes4[[#This Row],[CUIT]],Lista_CUIT[#All],2,0)),"CUIT NO CARGADO") -> GOOGLE ARGENTINA S.R.L. | H16: 12713.65 | I16: =IF(compras_mes4[[#This Row],[NETO GRAVADO]]="","",compras_mes4[[#This Row],[NETO GRAVADO]]*0.21) -> 2669.8665 | L16: 381.41 | N16: 190.7 | P16: =SUM(compras_mes4[[#This Row],[NETO GRAVADO]:[Otros / No Grav.]]) -> 15955.627 | Q16: =IFERROR(IF(compras_mes4[[#This Row],[CUIT]]="","-",VLOOKUP(compras_mes4[[#This Row],[CUIT]],Lista_CUIT[#All],3,0)),"CUIT NO CARGADO") -> Gastos Publicidad y Propaganda | R16: =IFERROR(IF(compras_mes4[[#This Row],[CUIT]]="","-",VLOOKUP(compras_mes4[[#This Row],[CUIT]],Lista_CUIT[#All],4,0)),"CUIT NO CARGADO") -> 0
B17: 45412 | C17: 1 | D17: 11 | E17: 978488 | F17: 33709585229 | G17: =IFERROR(IF(compras_mes4[[#This Row],[CUIT]]="","-",VLOOKUP(compras_mes4[[#This Row],[CUIT]],Lista_CUIT[#All],2,0)),"CUIT NO CARGADO") -> GOOGLE ARGENTINA S.R.L. | H17: 50460.06 | I17: =IF(compras_mes4[[#This Row],[NETO GRAVADO]]="","",compras_mes4[[#This Row],[NETO GRAVADO]]*0.21) -> 10596.613 | L17: 1513.8 | N17: 756.9 | P17: =SUM(compras_mes4[[#This Row],[NETO GRAVADO]:[Otros / No Grav.]]) -> 63327.373 | Q17: =IFERROR(IF(compras_mes4[[#This Row],[CUIT]]="","-",VLOOKUP(compras_mes4[[#This Row],[CUIT]],Lista_CUIT[#All],3,0)),"CUIT NO CARGADO") -> Gastos Publicidad y Propaganda | R17: =IFERROR(IF(compras_mes4[[#This Row],[CUIT]]="","-",VLOOKUP(compras_mes4[[#This Row],[CUIT]],Lista_CUIT[#All],4,0)),"CUIT NO CARGADO") -> 0
B18: 45412 | C18: 3 | D18: 11 | E18: 713776 | F18: 33709585229 | G18: =IFERROR(IF(compras_mes4[[#This Row],[CUIT]]="","-",VLOOKUP(compras_mes4[[#This Row],[CUIT]],Lista_CUIT[#All],2,0)),"CUIT NO CARGADO") -> GOOGLE ARGENTINA S.R.L. | I18: =IF(compras_mes4[[#This Row],[NETO GRAVADO]]="","",compras_mes4[[#This Row],[NETO GRAVADO]]*0.21) | P18: =SUM(compras_mes4[[#This Row],[NETO GRAVADO]:[Otros / No Grav.]]) -> 0 | Q18: =IFERROR(IF(compras_mes4[[#This Row],[CUIT]]="","-",VLOOKUP(compras_mes4[[#This Row],[CUIT]],Lista_CUIT[#All],3,0)),"CUIT NO CARGADO") -> Gastos Publicidad y Propaganda | R18: =IFERROR(IF(compras_mes4[[#This Row],[CUIT]]="","-",VLOOKUP(compras_mes4[[#This Row],[CUIT]],Lista_CUIT[#All],4,0)),"CUIT NO CARGADO") -> 0
B19: Total | H19: =SUBTOTAL(109,compras_mes4[NETO GRAVADO]) -> 1085466.4 | I19: =SUBTOTAL(109,compras_mes4[IVA 21 %]) -> 227947.95 | J19: =SUBTOTAL(109,compras_mes4[IVA 27%]) -> 0 | K19: =SUBTOTAL(109,compras_mes4[IVA 10,5%]) -> 0 | L19: =SUBTOTAL(109,compras_mes4[PERC. IVA]) -> 32564 | M19: =SUBTOTAL(109,compras_mes4[PERC IIBB BS AS]) -> 0 | N19: =SUBTOTAL(109,compras_mes4[PERC. IIBB CABA]) -> 16281.99 | O19: =SUBTOTAL(109,compras_mes4[Otros / No Grav.]) -> 0 | P19: =SUBTOTAL(109,compras_mes4[TOTAL]) -> 1362260.4
D24: LIQUIDACION EXTRACTOS BANCARIOS-TARJETAS
D25: FECHA | E25: NRO CPTE | F25: BANCO | G25: NETO | H25: IVA 21% | I25: IVA 10,5% | J25: RET IIBB CABA | K25: PERC IVA | L25: PERC IIBB
D29: Total | G29: =SUBTOTAL(109,extracto_banco_mes4[NETO]) -> 0 | H29: =SUBTOTAL(109,extracto_banco_mes4[IVA 21%]) -> 0 | I29: =SUBTOTAL(109,extracto_banco_mes4[IVA 10,5%]) -> 0 | J29: =SUBTOTAL(109,extracto_banco_mes4[RET IIBB CABA]) -> 0 | K29: =SUBTOTAL(109,extracto_banco_mes4[PERC IVA]) -> 0 | L29: =SUBTOTAL(109,extracto_banco_mes4[PERC IIBB]) -> 0
D33: FACTURAS C
D34: FECHA | E34: PTO VTA | F34: FC Nº | G34: CUIT | H34: RAZON SOCIAL | I34: TOTAL | J34: TIPO DE GASTO | K34: Provincia
D35: 45385 | E35: 2 | F35: 105 | G35: 27341104845 | H35: =IFERROR(IF(factura_c_mes4[[#This Row],[CUIT]]="","-",VLOOKUP(factura_c_mes4[[#This Row],[CUIT]],Lista_CUIT[#All],2,0)),"CUIT NO CARGADO") -> BOSSI MARIA PAULA | I35: 94668 | J35: =IFERROR(IF(factura_c_mes4[[#This Row],[CUIT]]="","-",VLOOKUP(factura_c_mes4[[#This Row],[CUIT]],Lista_CUIT[#All],3,0)),"CUIT NO CARGADO") -> HON. ADMINISTRATIVOS | K35: =IFERROR(IF(factura_c_mes4[[#This Row],[CUIT]]="","-",VLOOKUP(factura_c_mes4[[#This Row],[CUIT]],Lista_CUIT[#All],4,0)),"CUIT NO CARGADO") -> 0
D36: 45385 | E36: 2 | F36: 751 | G36: 20400104094 | H36: =IFERROR(IF(factura_c_mes4[[#This Row],[CUIT]]="","-",VLOOKUP(factura_c_mes4[[#This Row],[CUIT]],Lista_CUIT[#All],2,0)),"CUIT NO CARGADO") -> BOTINDARI FEDERICO DANIEL | I36: 50000 | J36: =IFERROR(IF(factura_c_mes4[[#This Row],[CUIT]]="","-",VLOOKUP(factura_c_mes4[[#This Row],[CUIT]],Lista_CUIT[#All],3,0)),"CUIT NO CARGADO") -> HONORARIOS CONTABLE | K36: =IFERROR(IF(factura_c_mes4[[#This Row],[CUIT]]="","-",VLOOKUP(factura_c_mes4[[#This Row],[CUIT]],Lista_CUIT[#All],4,0)),"CUIT NO CARGADO") -> 0
D37: 45387 | E37: 2 | F37: 41 | G37: 23380288079 | H37: =IFERROR(IF(factura_c_mes4[[#This Row],[CUIT]]="","-",VLOOKUP(factura_c_mes4[[#This Row],[CUIT]],Lista_CUIT[#All],2,0)),"CUIT NO CARGADO") -> CASTROMAN AGUSTIN | I37: 130811.8 | J37: =IFERROR(IF(factura_c_mes4[[#This Row],[CUIT]]="","-",VLOOKUP(factura_c_mes4[[#This Row],[CUIT]],Lista_CUIT[#All],3,0)),"CUIT NO CARGADO") -> Diseño Grafico | K37: =IFERROR(IF(factura_c_mes4[[#This Row],[CUIT]]="","-",VLOOKUP(factura_c_mes4[[#This Row],[CUIT]],Lista_CUIT[#All],4,0)),"CUIT NO CARGADO") -> 0
D38: 45412 | E38: 1 | F38: 301 | G38: 27386311000 | H38: =IFERROR(IF(factura_c_mes4[[#This Row],[CUIT]]="","-",VLOOKUP(factura_c_mes4[[#This Row],[CUIT]],Lista_CUIT[#All],2,0)),"CUIT NO CARGADO") -> OPANASIUK MACARENA ANTONELLA | I38: 250000 | J38: =IFERROR(IF(factura_c_mes4[[#This Row],[CUIT]]="","-",VLOOKUP(factura_c_mes4[[#This Row],[CUIT]],Lista_CUIT[#All],3,0)),"CUIT NO CARGADO") -> Honorarios Profesionales | K38: =IFERROR(IF(factura_c_mes4[[#This Row],[CUIT]]="","-",VLOOKUP(factura_c_mes4[[#This Row],[CUIT]],Lista_CUIT[#All],4,0)),"CUIT NO CARGADO") -> 0
D39: Total | I39: =SUBTOTAL(109,factura_c_mes4[TOTAL]) -> 525479.8
B45: LIBRO IVA VENTAS | K45: =N1 -> 45383
B47: VENTAS "A"
B48: FECHA | C48: TIPO | D48: PTO VENTA | E48: Nº FACTURA | F48: CUIT | G48: RAZON SOCIAL | H48: IMPORTE NETO | I48: IVA 21% | J48: IVA 10,5% | K48: EXENTO | L48: TOTAL | M48: Provincia
B49: 45385 | C49: 1 | D49: 2 | E49: 7 | F49: 20279415656 | G49: =IFERROR(IF(venta_a_mes4[[#This Row],[CUIT]]="","-",VLOOKUP(venta_a_mes4[[#This Row],[CUIT]],Lista_CUIT[#All],2,0)),"CUIT NO CARGADO") -> CECCO ALVARO GONZALO | H49: 75371.9 | I49: =venta_a_mes4[[#This Row],[IMPORTE NETO]]*0.21 -> 15828.099 | L49: =SUM(venta_a_mes4[[#This Row],[IMPORTE NETO]:[EXENTO]]) -> 91199.999
B50: 45385 | C50: 1 | D50: 1 | E50: 158 | F50: 30716549107 | G50: =IFERROR(IF(venta_a_mes4[[#This Row],[CUIT]]="","-",VLOOKUP(venta_a_mes4[[#This Row],[CUIT]],Lista_CUIT[#All],2,0)),"CUIT NO CARGADO") -> LAMATEC S.R.L. | H50: 108264.48 | I50: =venta_a_mes4[[#This Row],[IMPORTE NETO]]*0.21 -> 22735.541 | L50: =SUM(venta_a_mes4[[#This Row],[IMPORTE NETO]:[EXENTO]]) -> 131000.02
B51: 45385 | C51: 1 | D51: 1 | E51: 159 | F51: 20369499956 | G51: =IFERROR(IF(venta_a_mes4[[#This Row],[CUIT]]="","-",VLOOKUP(venta_a_mes4[[#This Row],[CUIT]],Lista_CUIT[#All],2,0)),"CUIT NO CARGADO") -> LAMARI FRANCO AGUSTIN | H51: 108264.48 | I51: =venta_a_mes4[[#This Row],[IMPORTE NETO]]*0.21 -> 22735.541 | L51: =SUM(venta_a_mes4[[#This Row],[IMPORTE NETO]:[EXENTO]]) -> 131000.02
B52: 45385 | C52: 1 | D52: 1 | E52: 160 | F52: 30716914077 | G52: =IFERROR(IF(venta_a_mes4[[#This Row],[CUIT]]="","-",VLOOKUP(venta_a_mes4[[#This Row],[CUIT]],Lista_CUIT[#All],2,0)),"CUIT NO CARGADO") -> BACANES | H52: 108264.48 | I52: =venta_a_mes4[[#This Row],[IMPORTE NETO]]*0.21 -> 22735.541 | L52: =SUM(venta_a_mes4[[#This Row],[IMPORTE NETO]:[EXENTO]]) -> 131000.02
B53: 45385 | C53: 1 | D53: 1 | E53: 161 | F53: 30717477681 | G53: =IFERROR(IF(venta_a_mes4[[#This Row],[CUIT]]="","-",VLOOKUP(venta_a_mes4[[#This Row],[CUIT]],Lista_CUIT[#All],2,0)),"CUIT NO CARGADO") -> GRUPO FAM SA | H53: 61157.05 | I53: =venta_a_mes4[[#This Row],[IMPORTE NETO]]*0.21 -> 12842.98 | L53: =SUM(venta_a_mes4[[#This Row],[IMPORTE NETO]:[EXENTO]]) -> 74000.031
B54: 45385 | C54: 1 | D54: 1 | E54: 162 | F54: 20284212488 | G54: =IFERROR(IF(venta_a_mes4[[#This Row],[CUIT]]="","-",VLOOKUP(venta_a_mes4[[#This Row],[CUIT]],Lista_CUIT[#All],2,0)),"CUIT NO CARGADO") -> BARLETTA MAXIMILIANO SEBASTIAN | H54: 47107.43 | I54: =venta_a_mes4[[#This Row],[IMPORTE NETO]]*0.21 -> 9892.5603 | L54: =SUM(venta_a_mes4[[#This Row],[IMPORTE NETO]:[EXENTO]]) -> 56999.99
B55: 45385 | C55: 1 | D55: 1 | E55: 163 | F55: 30715380567 | G55: =IFERROR(IF(venta_a_mes4[[#This Row],[CUIT]]="","-",VLOOKUP(venta_a_mes4[[#This Row],[CUIT]],Lista_CUIT[#All],2,0)),"CUIT NO CARGADO") -> SENS GROUP SRL | H55: 196971.43 | I55: =venta_a_mes4[[#This Row],[IMPORTE NETO]]*0.21 -> 41364 | L55: =SUM(venta_a_mes4[[#This Row],[IMPORTE NETO]:[EXENTO]]) -> 238335.43
B56: 45385 | C56: 1 | D56: 1 | E56: 164 | F56: 30717973166 | G56: =IFERROR(IF(venta_a_mes4[[#This Row],[CUIT]]="","-",VLOOKUP(venta_a_mes4[[#This Row],[CUIT]],Lista_CUIT[#All],2,0)),"CUIT NO CARGADO") -> STM ESTILO S.R.L | H56: 47107.43 | I56: =venta_a_mes4[[#This Row],[IMPORTE NETO]]*0.21 -> 9892.5603 | L56: =SUM(venta_a_mes4[[#This Row],[IMPORTE NETO]:[EXENTO]]) -> 56999.99
B57: 45385 | C57: 1 | D57: 1 | E57: 165 | F57: 27165844748 | G57: =IFERROR(IF(venta_a_mes4[[#This Row],[CUIT]]="","-",VLOOKUP(venta_a_mes4[[#This Row],[CUIT]],Lista_CUIT[#All],2,0)),"CUIT NO CARGADO") -> DENATALE MARCELA BEATRIZ | H57: 108264.48 | I57: =venta_a_mes4[[#This Row],[IMPORTE NETO]]*0.21 -> 22735.541 | L57: =SUM(venta_a_mes4[[#This Row],[IMPORTE NETO]:[EXENTO]]) -> 131000.02
B58: 45385 | C58: 1 | D58: 1 | E58: 166 | F58: 20287305460 | G58: =IFERROR(IF(venta_a_mes4[[#This Row],[CUIT]]="","-",VLOOKUP(venta_a_mes4[[#This Row],[CUIT]],Lista_CUIT[#All],2,0)),"CUIT NO CARGADO") -> LANDI GERONIMO | H58: 47107.43 | I58: =venta_a_mes4[[#This Row],[IMPORTE NETO]]*0.21 -> 9892.5603 | L58: =SUM(venta_a_mes4[[#This Row],[IMPORTE NETO]:[EXENTO]]) -> 56999.99
B59: 45385 | C59: 1 | D59: 1 | E59: 167 | F59: 20367341808 | G59: =IFERROR(IF(venta_a_mes4[[#This Row],[CUIT]]="","-",VLOOKUP(venta_a_mes4[[#This Row],[CUIT]],Lista_CUIT[#All],2,0)),"CUIT NO CARGADO") -> FEIDAS FERNANDO EMILIANO | H59: 54545.48 | I59: =venta_a_mes4[[#This Row],[IMPORTE NETO]]*0.21 -> 11454.551 | L59: =SUM(venta_a_mes4[[#This Row],[IMPORTE NETO]:[EXENTO]]) -> 66000.031
B60: 45385 | C60: 1 | D60: 1 | E60: 168 | F60: 30715941763 | G60: =IFERROR(IF(venta_a_mes4[[#This Row],[CUIT]]="","-",VLOOKUP(venta_a_mes4[[#This Row],[CUIT]],Lista_CUIT[#All],2,0)),"CUIT NO CARGADO") -> TOURMALHYN S.R.L. | H60: 24793.38 | I60: =venta_a_mes4[[#This Row],[IMPORTE NETO]]*0.21 -> 5206.6098 | L60: =SUM(venta_a_mes4[[#This Row],[IMPORTE NETO]:[EXENTO]]) -> 29999.99
... B68: 45387 | C68: 3 | D68: 1 | E68: 9 | F68: 30717477681 | G68: =IFERROR(IF(venta_a_mes4[[#This Row],[CUIT]]="","-",VLOOKUP(venta_a_mes4[[#This Row],[CUIT]],Lista_CUIT[#All],2,0)),"CUIT NO CARGADO") -> GRUPO FAM SA | H68: -61157.05 | I68: =venta_a_mes4[[#This Row],[IMPORTE NETO]]*0.21 -> -12842.98 | L68: =SUM(venta_a_mes4[[#This Row],[IMPORTE NETO]:[EXENTO]]) -> -74000.031
G69: =IFERROR(IF(venta_a_mes4[[#This Row],[CUIT]]="","-",VLOOKUP(venta_a_mes4[[#This Row],[CUIT]],Lista_CUIT[#All],2,0)),"CUIT NO CARGADO") -> - | I69: =venta_a_mes4[[#This Row],[IMPORTE NETO]]*0.21 -> 0 | L69: =SUM(venta_a_mes4[[#This Row],[IMPORTE NETO]:[EXENTO]]) -> 0
B70: Total | H70: =SUBTOTAL(109,venta_a_mes4[IMPORTE NETO]) -> 1743390.2 | I70: =SUBTOTAL(109,venta_a_mes4[IVA 21%]) -> 366111.95 | J70: =SUBTOTAL(109,venta_a_mes4[IVA 10,5%]) -> 0 | K70: =SUBTOTAL(109,venta_a_mes4[EXENTO]) -> 0 | L70: =SUBTOTAL(109,venta_a_mes4[TOTAL]) -> 2109502.2 | M70: =SUBTOTAL(103,venta_a_mes4[Provincia]) -> 0
B73: VENTAS "B"
B74: FECHA | C74: TIPO | D74: PTO VENTA | E74: Nº FACTURA | F74: CUIT | G74: RAZON SOCIAL | H74: IMPORTE NETO | I74: IVA 21% | J74: IVA 10,5% | K74: EXENTO | L74: TOTAL | M74: Provincia
B75: 45385 | C75: 6 | D75: 1 | E75: 31 | F75: 30592508830 | G75: =IFERROR(IF(ventas_b_mes4[[#This Row],[CUIT]]="","-",VLOOKUP(ventas_b_mes4[[#This Row],[CUIT]],Lista_CUIT[#All],2,0)),"CUIT NO CARGADO") -> INSTITUTO DE ESTUDIOS SUPERIORES DE BUENOS AIRES S A | H75: 41322.33 | I75: 8677.69 | L75: =SUM(ventas_b_mes4[[#This Row],[IMPORTE NETO]:[EXENTO]]) -> 50000.02
B76: 45385 | C76: 6 | D76: 1 | E76: 32 | F76: 20252582704 | G76: =IFERROR(IF(ventas_b_mes4[[#This Row],[CUIT]]="","-",VLOOKUP(ventas_b_mes4[[#This Row],[CUIT]],Lista_CUIT[#All],2,0)),"CUIT NO CARGADO") -> GARCIA VAUTRIN ANDRES ALBERTO | H76: 108264.48 | I76: 22735.54 | L76: =SUM(ventas_b_mes4[[#This Row],[IMPORTE NETO]:[EXENTO]]) -> 131000.02
L77: =SUM(ventas_b_mes4[[#This Row],[IMPORTE NETO]:[EXENTO]]) -> 0
L78: =SUM(ventas_b_mes4[[#This Row],[IMPORTE NETO]:[EXENTO]]) -> 0
L79: =SUM(ventas_b_mes4[[#This Row],[IMPORTE NETO]:[EXENTO]]) -> 0
L80: =SUM(ventas_b_mes4[[#This Row],[IMPORTE NETO]:[EXENTO]]) -> 0
B81: Total | H81: =SUBTOTAL(109,ventas_b_mes4[IMPORTE NETO]) -> 149586.81 | I81: =SUBTOTAL(109,ventas_b_mes4[IVA 21%]) -> 31413.23 | J81: =SUBTOTAL(109,ventas_b_mes4[IVA 10,5%]) -> 0 | K81: =SUBTOTAL(109,ventas_b_mes4[EXENTO]) -> 0 | L81: =SUBTOTAL(109,ventas_b_mes4[TOTAL]) -> 181000.04 | M81: =SUBTOTAL(103,ventas_b_mes4[Provincia]) -> 0
C89: RETENCIONES
C90: FECHA | D90: COMP Nº | E90: Columna1 | F90: CUIT | G90: RAZON SOCIAL | H90: Ganancias | I90: IVA | J90: SUSS | K90: IIBB BSAS | L90: IIBB CABA
G91: =IFERROR(IF(Retenciones_mes4[[#This Row],[CUIT]]="","-",VLOOKUP(Retenciones_mes4[[#This Row],[CUIT]],Lista_CUIT[#All],2,0)),"CUIT NO CARGADO") -> -
G92: =IFERROR(IF(Retenciones_mes4[[#This Row],[CUIT]]="","-",VLOOKUP(Retenciones_mes4[[#This Row],[CUIT]],Lista_CUIT[#All],2,0)),"CUIT NO CARGADO") -> -
G93: =IFERROR(IF(Retenciones_mes4[[#This Row],[CUIT]]="","-",VLOOKUP(Retenciones_mes4[[#This Row],[CUIT]],Lista_CUIT[#All],2,0)),"CUIT NO CARGADO") -> -
G94: =IFERROR(IF(Retenciones_mes4[[#This Row],[CUIT]]="","-",VLOOKUP(Retenciones_mes4[[#This Row],[CUIT]],Lista_CUIT[#All],2,0)),"CUIT NO CARGADO") -> -
G95: =IFERROR(IF(Retenciones_mes4[[#This Row],[CUIT]]="","-",VLOOKUP(Retenciones_mes4[[#This Row],[CUIT]],Lista_CUIT[#All],2,0)),"CUIT NO CARGADO") -> -

Sheet May-24
B1: LIBRO IVA COMPRAS | G1: ='Ene-24'!G1:M1 -> RABLEB SRL | N1: =EDATE('Ene-24'!N1,4) -> 45413
B3: TOTAL COMPRAS | G3: TOTAL CREDITO FISCAL | J3: TOTAL VENTAS NETAS | M3: TOTAL DEBITO FISCAL | P3: RESULTADO
B4: =SUM(compras_mes5[[#Totals],[NETO GRAVADO]])+extracto_banco_mes5[[#Totals],[NETO]] -> 1224307 | G4: =compras_mes5[[#Totals],[IVA 21 %]]+compras_mes5[[#Totals],[IVA 27%]]+compras_mes5[[#Totals],[IVA 10,5%]]+extracto_banco_mes5[[#Totals],[IVA 21%]]+extracto_banco_mes5[[#Totals],[IVA 10,5%]] -> 257104.47 | J4: =venta_a_mes5[[#Totals],[IMPORTE NETO]]+ventas_b_mes5[[#Totals],[IMPORTE NETO]] -> 2238151 | M4: =venta_a_mes5[[#Totals],[IVA 21%]]+venta_a_mes5[[#Totals],[IVA 10,5%]]+ventas_b_mes5[[#Totals],[IVA 21%]]+ventas_b_mes5[[#Totals],[IVA 10,5%]] -> 470011.71 | P4: =G4-M4 -> -212907.24
B8: FECHA | C8: TIPO | D8: PTO VTA | E8: NRO. CPTE | F8: CUIT | G8: RAZON SOCIAL | H8: NETO GRAVADO | I8: IVA 21 % | J8: IVA 27% | K8: IVA 10,5% | L8: PERC. IVA | M8: PERC IIBB BS AS | N8: PERC. IIBB CABA | O8: Otros / No Grav. | P8: TOTAL | Q8: Tipo de Gasto | R8: Provincia
B9: 45439 | C9: 1 | D9: 8 | E9: 79142 | F9: 30586172308 | G9: =IFERROR(IF(compras_mes5[[#This Row],[CUIT]]="","-",VLOOKUP(compras_mes5[[#This Row],[CUIT]],Lista_CUIT[#All],2,0)),"CUIT NO CARGADO") -> SANTA FE COMERCIAL SOCIEDAD DE RESPONSABILIDAD LIMITADA | H9: 4132.23 | I9: =IF(compras_mes5[[#This Row],[NETO GRAVADO]]="","",compras_mes5[[#This Row],[NETO GRAVADO]]*0.21) -> 867.7683 | P9: =SUM(compras_mes5[[#This Row],[NETO GRAVADO]:[Otros / No Grav.]]) -> 4999.9983 | Q9: =IFERROR(IF(compras_mes5[[#This Row],[CUIT]]="","-",VLOOKUP(compras_mes5[[#This Row],[CUIT]],Lista_CUIT[#All],3,0)),"CUIT NO CARGADO") -> LIBRERÍA | R9: =IFERROR(IF(compras_mes5[[#This Row],[CUIT]]="","-",VLOOKUP(compras_mes5[[#This Row],[CUIT]],Lista_CUIT[#All],4,0)),"CUIT NO CARGADO") -> 0
B10: 45440 | C10: 1 | D10: 3 | E10: 34509 | F10: 30715428349 | G10: =IFERROR(IF(compras_mes5[[#This Row],[CUIT]]="","-",VLOOKUP(compras_mes5[[#This Row],[CUIT]],Lista_CUIT[#All],2,0)),"CUIT NO CARGADO") -> NETSHOP GROUP S.R.L. | H10: 65120.36 | I10: =IF(compras_mes5[[#This Row],[NETO GRAVADO]]="","",compras_mes5[[#This Row],[NETO GRAVADO]]*0.21) -> 13675.276 | P10: =SUM(compras_mes5[[#This Row],[NETO GRAVADO]:[Otros / No Grav.]]) -> 78795.636 | Q10: =IFERROR(IF(compras_mes5[[#This Row],[CUIT]]="","-",VLOOKUP(compras_mes5[[#This Row],[CUIT]],Lista_CUIT[#All],3,0)),"CUIT NO CARGADO") -> Gastos Varios | R10: =IFERROR(IF(compras_mes5[[#This Row],[CUIT]]="","-",VLOOKUP(compras_mes5[[#This Row],[CUIT]],Lista_CUIT[#All],4,0)),"CUIT NO CARGADO") -> 0
B11: 45440 | C11: 1 | D11: 3 | E11: 34510 | F11: 30715428349 | G11: =IFERROR(IF(compras_mes5[[#This Row],[CUIT]]="","-",VLOOKUP(compras_mes5[[#This Row],[CUIT]],Lista_CUIT[#All],2,0)),"CUIT NO CARGADO") -> NETSHOP GROUP S.R.L. | H11: 130240.71 | I11: =IF(compras_mes5[[#This Row],[NETO GRAVADO]]="","",compras_mes5[[#This Row],[NETO GRAVADO]]*0.21) -> 27350.549 | P11: =SUM(compras_mes5[[#This Row],[NETO GRAVADO]:[Otros / No Grav.]]) -> 157591.26 | Q11: =IFERROR(IF(compras_mes5[[#This Row],[CUIT]]="","-",VLOOKUP(compras_mes5[[#This Row],[CUIT]],Lista_CUIT[#All],3,0)),"CUIT NO CARGADO") -> Gastos Varios | R11: =IFERROR(IF(compras_mes5[[#This Row],[CUIT]]="","-",VLOOKUP(compras_mes5[[#This Row],[CUIT]],Lista_CUIT[#All],4,0)),"CUIT NO CARGADO") -> 0
B12: 45443 | C12: 1 | D12: 11 | E12: 983202 | F12: 33709585229 | G12: =IFERROR(IF(compras_mes5[[#This Row],[CUIT]]="","-",VLOOKUP(compras_mes5[[#This Row],[CUIT]],Lista_CUIT[#All],2,0)),"CUIT NO CARGADO") -> GOOGLE ARGENTINA S.R.L. | H12: 19157.55 | I12: =IF(compras_mes5[[#This Row],[NETO GRAVADO]]="","",compras_mes5[[#This Row],[NETO GRAVADO]]*0.21) -> 4023.0855 | N12: 287.36 | O12: 574.73 | P12: =SUM(compras_mes5[[#This Row],[NETO GRAVADO]:[Otros / No Grav.]]) -> 24042.726 | Q12: =IFERROR(IF(compras_mes5[[#This Row],[CUIT]]="","-",VLOOKUP(compras_mes5[[#This Row],[CUIT]],Lista_CUIT[#All],3,0)),"CUIT NO CARGADO") -> Gastos Publicidad y Propaganda | R12: =IFERROR(IF(compras_mes5[[#This Row],[CUIT]]="","-",VLOOKUP(compras_mes5[[#This Row],[CUIT]],Lista_CUIT[#All],4,0)),"CUIT NO CARGADO") -> 0
B13: 45443 | C13: 1 | D13: 11 | E13: 987835 | F13: 33709585229 | G13: =IFERROR(IF(compras_mes5[[#This Row],[CUIT]]="","-",VLOOKUP(compras_mes5[[#This Row],[CUIT]],Lista_CUIT[#All],2,0)),"CUIT NO CARGADO") -> GOOGLE ARGENTINA S.R.L. | H13: 63483.31 | I13: =IF(compras_mes5[[#This Row],[NETO GRAVADO]]="","",compras_mes5[[#This Row],[NETO GRAVADO]]*0.21) -> 13331.495 | N13: 952.25 | O13: 1904.5 | P13: =SUM(compras_mes5[[#This Row],[NETO GRAVADO]:[Otros / No Grav.]]) -> 79671.555 | Q13: =IFERROR(IF(compras_mes5[[#This Row],[CUIT]]="","-",VLOOKUP(compras_mes5[[#This Row],[CUIT]],Lista_CUIT[#All],3,0)),"CUIT NO CARGADO") -> Gastos Publicidad y Propaganda | R13: =IFERROR(IF(compras_mes5[[#This Row],[CUIT]]="","-",VLOOKUP(compras_mes5[[#This Row],[CUIT]],Lista_CUIT[#All],4,0)),"CUIT NO CARGADO") -> 0
B14: 45443 | C14: 1 | D14: 11 | E14: 987160 | F14: 33709585229 | G14: =IFERROR(IF(compras_mes5[[#This Row],[CUIT]]="","-",VLOOKUP(compras_mes5[[#This Row],[CUIT]],Lista_CUIT[#All],2,0)),"CUIT NO CARGADO") -> GOOGLE ARGENTINA S.R.L. | H14: 618160.16 | I14: =IF(compras_mes5[[#This Row],[NETO GRAVADO]]="","",compras_mes5[[#This Row],[NETO GRAVADO]]*0.21) -> 129813.63 | N14: 9272.4 | O14: 18544.8 | P14: =SUM(compras_mes5[[#This Row],[NETO GRAVADO]:[Otros / No Grav.]]) -> 775790.99 | Q14: =IFERROR(IF(compras_mes5[[#This Row],[CUIT]]="","-",VLOOKUP(compras_mes5[[#This Row],[CUIT]],Lista_CUIT[#All],3,0)),"CUIT NO CARGADO") -> Gastos Publicidad y Propaganda | R14: =IFERROR(IF(compras_mes5[[#This Row],[CUIT]]="","-",VLOOKUP(compras_mes5[[#This Row],[CUIT]],Lista_CUIT[#All],4,0)),"CUIT NO CARGADO") -> 0
B15: 45443 | C15: 1 | D15: 11 | E15: 981752 | F15: 33709585229 | G15: =IFERROR(IF(compras_mes5[[#This Row],[CUIT]]="","-",VLOOKUP(compras_mes5[[#This Row],[CUIT]],Lista_CUIT[#All],2,0)),"CUIT NO CARGADO") -> GOOGLE ARGENTINA S.R.L. | H15: 53213.88 | I15: =IF(compras_mes5[[#This Row],[NETO GRAVADO]]="","",compras_mes5[[#This Row],[NETO GRAVADO]]*0.21) -> 11174.915 | N15: 798.21 | O15: 1596.42 | P15: =SUM(compras_mes5[[#This Row],[NETO GRAVADO]:[Otros / No Grav.]]) -> 66783.425 | Q15: =IFERROR(IF(compras_mes5[[#This Row],[CUIT]]="","-",VLOOKUP(compras_mes5[[#This Row],[CUIT]],Lista_CUIT[#All],3,0)),"CUIT NO CARGADO") -> Gastos Publicidad y Propaganda | R15: =IFERROR(IF(compras_mes5[[#This Row],[CUIT]]="","-",VLOOKUP(compras_mes5[[#This Row],[CUIT]],Lista_CUIT[#All],4,0)),"CUIT NO CARGADO") -> 0
B16: 45443 | C16: 1 | D16: 11 | E16: 992129 | F16: 33709585229 | G16: =IFERROR(IF(compras_mes5[[#This Row],[CUIT]]="","-",VLOOKUP(compras_mes5[[#This Row],[CUIT]],Lista_CUIT[#All],2,0)),"CUIT NO CARGADO") -> GOOGLE ARGENTINA S.R.L. | H16: 226574.05 | I16: =IF(compras_mes5[[#This Row],[NETO GRAVADO]]="","",compras_mes5[[#This Row],[NETO GRAVADO]]*0.21) -> 47580.55 | N16: 3398.61 | O16: 6797.22 | P16: =SUM(compras_mes5[[#This Row],[NETO GRAVADO]:[Otros / No Grav.]]) -> 284350.43 | Q16: =IFERROR(IF(compras_mes5[[#This Row],[CUIT]]="","-",VLOOKUP(compras_mes5[[#This Row],[CUIT]],Lista_CUIT[#All],3,0)),"CUIT NO CARGADO") -> Gastos Publicidad y Propaganda | R16: =IFERROR(IF(compras_mes5[[#This Row],[CUIT]]="","-",VLOOKUP(compras_mes5[[#This Row],[CUIT]],Lista_CUIT[#All],4,0)),"CUIT NO CARGADO") -> 0
B17: 45443 | C17: 1 | D17: 11 | E17: 991112 | F17: 33709585229 | G17: =IFERROR(IF(compras_mes5[[#This Row],[CUIT]]="","-",VLOOKUP(compras_mes5[[#This Row],[CUIT]],Lista_CUIT[#All],2,0)),"CUIT NO CARGADO") -> GOOGLE ARGENTINA S.R.L. | H17: 131779.5 | I17: =IF(compras_mes5[[#This Row],[NETO GRAVADO]]="","",compras_mes5[[#This Row],[NETO GRAVADO]]*0.21) -> 27673.695 | N17: 1976.69 | O17: 3953.39 | P17: =SUM(compras_mes5[[#This Row],[NETO GRAVADO]:[Otros / No Grav.]]) -> 165383.28 | Q17: =IFERROR(IF(compras_mes5[[#This Row],[CUIT]]="","-",VLOOKUP(compras_mes5[[#This Row],[CUIT]],Lista_CUIT[#All],3,0)),"CUIT NO CARGADO") -> Gastos Publicidad y Propaganda | R17: =IFERROR(IF(compras_mes5[[#This Row],[CUIT]]="","-",VLOOKUP(compras_mes5[[#This Row],[CUIT]],Lista_CUIT[#All],4,0)),"CUIT NO CARGADO") -> 0
B18: 45443 | C18: 1 | D18: 11 | E18: 992009 | F18: 33709585229 | G18: =IFERROR(IF(compras_mes5[[#This Row],[CUIT]]="","-",VLOOKUP(compras_mes5[[#This Row],[CUIT]],Lista_CUIT[#All],2,0)),"CUIT NO CARGADO") -> GOOGLE ARGENTINA S.R.L. | H18: 21804.16 | I18: =IF(compras_mes5[[#This Row],[NETO GRAVADO]]="","",compras_mes5[[#This Row],[NETO GRAVADO]]*0.21) -> 4578.8736 | N18: 327.06 | O18: 654.12 | P18: =SUM(compras_mes5[[#This Row],[NETO GRAVADO]:[Otros / No Grav.]]) -> 27364.214 | Q18: =IFERROR(IF(compras_mes5[[#This Row],[CUIT]]="","-",VLOOKUP(compras_mes5[[#This Row],[CUIT]],Lista_CUIT[#All],3,0)),"CUIT NO CARGADO") -> Gastos Publicidad y Propaganda | R18: =IFERROR(IF(compras_mes5[[#This Row],[CUIT]]="","-",VLOOKUP(compras_mes5[[#This Row],[CUIT]],Lista_CUIT[#All],4,0)),"CUIT NO CARGADO") -> 0
B19: 45443 | C19: 3 | D19: 11 | E19: 723909 | F19: 33709585229 | G19: =IFERROR(IF(compras_mes5[[#This Row],[CUIT]]="","-",VLOOKUP(compras_mes5[[#This Row],[CUIT]],Lista_CUIT[#All],2,0)),"CUIT NO CARGADO") -> GOOGLE ARGENTINA S.R.L. | H19: -42662.98 | I19: =IF(compras_mes5[[#This Row],[NETO GRAVADO]]="","",compras_mes5[[#This Row],[NETO GRAVADO]]*0.21) -> -8959.2258 | N19: -639.94 | O19: -1279.89 | P19: =SUM(compras_mes5[[#This Row],[NETO GRAVADO]:[Otros / No Grav.]]) -> -53542.036 | Q19: =IFERROR(IF(compras_mes5[[#This Row],[CUIT]]="","-",VLOOKUP(compras_mes5[[#This Row],[CUIT]],Lista_CUIT[#All],3,0)),"CUIT NO CARGADO") -> Gastos Publicidad y Propaganda | R19: =IFERROR(IF(compras_mes5[[#This Row],[CUIT]]="","-",VLOOKUP(compras_mes5[[#This Row],[CUIT]],Lista_CUIT[#All],4,0)),"CUIT NO CARGADO") -> 0
B20: 45443 | C20: 3 | D20: 11 | E20: 726541 | F20: 33709585229 | G20: =IFERROR(IF(compras_mes5[[#This Row],[CUIT]]="","-",VLOOKUP(compras_mes5[[#This Row],[CUIT]],Lista_CUIT[#All],2,0)),"CUIT NO CARGADO") -> GOOGLE ARGENTINA S.R.L. | H20: -65083.75 | I20: =IF(compras_mes5[[#This Row],[NETO GRAVADO]]="","",compras_mes5[[#This Row],[NETO GRAVADO]]*0.21) -> -13667.587 | N20: -976.26 | O20: -1952.51 | P20: =SUM(compras_mes5[[#This Row],[NETO GRAVADO]:[Otros / No Grav.]]) -> -81680.107 | Q20: =IFERROR(IF(compras_mes5[[#This Row],[CUIT]]="","-",VLOOKUP(compras_mes5[[#This Row],[CUIT]],Lista_CUIT[#All],3,0)),"CUIT NO CARGADO") -> Gastos Publicidad y Propaganda | R20: =IFERROR(IF(compras_mes5[[#This Row],[CUIT]]="","-",VLOOKUP(compras_mes5[[#This Row],[CUIT]],Lista_CUIT[#All],4,0)),"CUIT NO CARGADO") -> 0
B21: 45443 | C21: 3 | D21: 11 | E21: 724444 | F21: 33709585229 | G21: =IFERROR(IF(compras_mes5[[#This Row],[CUIT]]="","-",VLOOKUP(compras_mes5[[#This Row],[CUIT]],Lista_CUIT[#All],2,0)),"CUIT NO CARGADO") -> GOOGLE ARGENTINA S.R.L. | H21: -1612.17 | I21: =IF(compras_mes5[[#This Row],[NETO GRAVADO]]="","",compras_mes5[[#This Row],[NETO GRAVADO]]*0.21) -> -338.5557 | N21: -24.18 | P21: =SUM(compras_mes5[[#This Row],[NETO GRAVADO]:[Otros / No Grav.]]) -> -1974.9057 | Q21: =IFERROR(IF(compras_mes5[[#This Row],[CUIT]]="","-",VLOOKUP(compras_mes5[[#This Row],[CUIT]],Lista_CUIT[#All],3,0)),"CUIT NO CARGADO") -> Gastos Publicidad y Propaganda | R21: =IFERROR(IF(compras_mes5[[#This Row],[CUIT]]="","-",VLOOKUP(compras_mes5[[#This Row],[CUIT]],Lista_CUIT[#All],4,0)),"CUIT NO CARGADO") -> 0
G22: =IFERROR(IF(compras_mes5[[#This Row],[CUIT]]="","-",VLOOKUP(compras_mes5[[#This Row],[CUIT]],Lista_CUIT[#All],2,0)),"CUIT NO CARGADO") -> - | I22: =IF(compras_mes5[[#This Row],[NETO GRAVADO]]="","",compras_mes5[[#This Row],[NETO GRAVADO]]*0.21) | P22: =SUM(compras_mes5[[#This Row],[NETO GRAVADO]:[Otros / No Grav.]]) -> 0 | Q22: =IFERROR(IF(compras_mes5[[#This Row],[CUIT]]="","-",VLOOKUP(compras_mes5[[#This Row],[CUIT]],Lista_CUIT[#All],3,0)),"CUIT NO CARGADO") -> - | R22: =IFERROR(IF(compras_mes5[[#This Row],[CUIT]]="","-",VLOOKUP(compras_mes5[[#This Row],[CUIT]],Lista_CUIT[#All],4,0)),"CUIT NO CARGADO") -> -
B23: Total | H23: =SUBTOTAL(109,compras_mes5[NETO GRAVADO]) -> 1224307 | I23: =SUBTOTAL(109,compras_mes5[IVA 21 %]) -> 257104.47 | J23: =SUBTOTAL(109,compras_mes5[IVA 27%]) -> 0 | K23: =SUBTOTAL(109,compras_mes5[IVA 10,5%]) -> 0 | L23: =SUBTOTAL(109,compras_mes5[PERC. IVA]) -> 0 | M23: =SUBTOTAL(109,compras_mes5[PERC IIBB BS AS]) -> 0 | N23: =SUBTOTAL(109,compras_mes5[PERC. IIBB CABA]) -> 15372.2 | O23: =SUBTOTAL(109,compras_mes5[Otros / No Grav.]) -> 30792.78 | P23: =SUBTOTAL(109,compras_mes5[TOTAL]) -> 1527576.5
D28: LIQUIDACION EXTRACTOS BANCARIOS-TARJETAS
D29: FECHA | E29: NRO CPTE | F29: BANCO | G29: NETO | H29: IVA 21% | I29: IVA 10,5% | J29: RET IIBB CABA | K29: PERC IVA | L29: PERC IIBB
D33: Total | G33: =SUBTOTAL(109,extracto_banco_mes5[NETO]) -> 0 | H33: =SUBTOTAL(109,extracto_banco_mes5[IVA 21%]) -> 0 | I33: =SUBTOTAL(109,extracto_banco_mes5[IVA 10,5%]) -> 0 | J33: =SUBTOTAL(109,extracto_banco_mes5[RET IIBB CABA]) -> 0 | K33: =SUBTOTAL(109,extracto_banco_mes5[PERC IVA]) -> 0 | L33: =SUBTOTAL(109,extracto_banco_mes5[PERC IIBB]) -> 0
D37: FACTURAS C
D38: FECHA | E38: PTO VTA | F38: FC Nº | G38: CUIT | H38: RAZON SOCIAL | I38: TOTAL | J38: TIPO DE GASTO | K38: Provincia
D39: 45414 | E39: 2 | F39: 769 | G39: 20400104094 | H39: =IFERROR(IF(factura_c_mes5[[#This Row],[CUIT]]="","-",VLOOKUP(factura_c_mes5[[#This Row],[CUIT]],Lista_CUIT[#All],2,0)),"CUIT NO CARGADO") -> BOTINDARI FEDERICO DANIEL | I39: 80000 | J39: =IFERROR(IF(factura_c_mes5[[#This Row],[CUIT]]="","-",VLOOKUP(factura_c_mes5[[#This Row],[CUIT]],Lista_CUIT[#All],3,0)),"CUIT NO CARGADO") -> HONORARIOS CONTABLE | K39: =IFERROR(IF(factura_c_mes5[[#This Row],[CUIT]]="","-",VLOOKUP(factura_c_mes5[[#This Row],[CUIT]],Lista_CUIT[#All],4,0)),"CUIT NO CARGADO") -> 0
D40: 45414 | E40: 2 | F40: 108 | G40: 27341104845 | H40: =IFERROR(IF(factura_c_mes5[[#This Row],[CUIT]]="","-",VLOOKUP(factura_c_mes5[[#This Row],[CUIT]],Lista_CUIT[#All],2,0)),"CUIT NO CARGADO") -> BOSSI MARIA PAULA | I40: 104135 | J40: =IFERROR(IF(factura_c_mes5[[#This Row],[CUIT]]="","-",VLOOKUP(factura_c_mes5[[#This Row],[CUIT]],Lista_CUIT[#All],3,0)),"CUIT NO CARGADO") -> HON. ADMINISTRATIVOS | K40: =IFERROR(IF(factura_c_mes5[[#This Row],[CUIT]]="","-",VLOOKUP(factura_c_mes5[[#This Row],[CUIT]],Lista_CUIT[#All],4,0)),"CUIT NO CARGADO") -> 0
D41: 45418 | E41: 2 | F41: 42 | G41: 23380288079 | H41: =IFERROR(IF(factura_c_mes5[[#This Row],[CUIT]]="","-",VLOOKUP(factura_c_mes5[[#This Row],[CUIT]],Lista_CUIT[#All],2,0)),"CUIT NO CARGADO") -> CASTROMAN AGUSTIN | I41: 143893 | J41: =IFERROR(IF(factura_c_mes5[[#This Row],[CUIT]]="","-",VLOOKUP(factura_c_mes5[[#This Row],[CUIT]],Lista_CUIT[#All],3,0)),"CUIT NO CARGADO") -> Diseño Grafico | K41: =IFERROR(IF(factura_c_mes5[[#This Row],[CUIT]]="","-",VLOOKUP(factura_c_mes5[[#This Row],[CUIT]],Lista_CUIT[#All],4,0)),"CUIT NO CARGADO") -> 0
D42: 45419 | E42: 1 | F42: 302 | G42: 27386311000 | H42: =IFERROR(IF(factura_c_mes5[[#This Row],[CUIT]]="","-",VLOOKUP(factura_c_mes5[[#This Row],[CUIT]],Lista_CUIT[#All],2,0)),"CUIT NO CARGADO") -> OPANASIUK MACARENA ANTONELLA | I42: 250000 | J42: =IFERROR(IF(factura_c_mes5[[#This Row],[CUIT]]="","-",VLOOKUP(factura_c_mes5[[#This Row],[CUIT]],Lista_CUIT[#All],3,0)),"CUIT NO CARGADO") -> Honorarios Profesionales | K42: =IFERROR(IF(factura_c_mes5[[#This Row],[CUIT]]="","-",VLOOKUP(factura_c_mes5[[#This Row],[CUIT]],Lista_CUIT[#All],4,0)),"CUIT NO CARGADO") -> 0
D43: 45420 | E43: 51 | F43: 160 | G43: 20300985158 | H43: =IFERROR(IF(factura_c_mes5[[#This Row],[CUIT]]="","-",VLOOKUP(factura_c_mes5[[#This Row],[CUIT]],Lista_CUIT[#All],2,0)),"CUIT NO CARGADO") -> GONZALEZ NESTOR RICARDO | I43: 330000 | J43: =IFERROR(IF(factura_c_mes5[[#This Row],[CUIT]]="","-",VLOOKUP(factura_c_mes5[[#This Row],[CUIT]],Lista_CUIT[#All],3,0)),"CUIT NO CARGADO") -> Diseño Grafico | K43: =IFERROR(IF(factura_c_mes5[[#This Row],[CUIT]]="","-",VLOOKUP(factura_c_mes5[[#This Row],[CUIT]],Lista_CUIT[#All],4,0)),"CUIT NO CARGADO") -> 0
D44: Total | I44: =SUBTOTAL(109,factura_c_mes5[TOTAL]) -> 908028
B49: LIBRO IVA VENTAS | K49: =N1 -> 45413
B51: VENTAS "A"
B52: FECHA | C52: TIPO | D52: PTO VENTA | E52: Nº FACTURA | F52: CUIT | G52: RAZON SOCIAL | H52: IMPORTE NETO | I52: IVA 21% | J52: IVA 10,5% | K52: EXENTO | L52: TOTAL | M52: Provincia
B53: 45414 | C53: 1 | D53: 1 | E53: 192 | F53: 30715380567 | G53: =IFERROR(IF(venta_a_mes5[[#This Row],[CUIT]]="","-",VLOOKUP(venta_a_mes5[[#This Row],[CUIT]],Lista_CUIT[#All],2,0)),"CUIT NO CARGADO") -> SENS GROUP SRL | H53: 189721.1 | I53: =venta_a_mes5[[#This Row],[IMPORTE NETO]]*0.21 -> 39841.431 | L53: =SUM(venta_a_mes5[[#This Row],[IMPORTE NETO]:[EXENTO]]) -> 229562.53
B54: 45414 | C54: 1 | D54: 1 | E54: 183 | F54: 20279415656 | G54: =IFERROR(IF(venta_a_mes5[[#This Row],[CUIT]]="","-",VLOOKUP(venta_a_mes5[[#This Row],[CUIT]],Lista_CUIT[#All],2,0)),"CUIT NO CARGADO") -> CECCO ALVARO GONZALO | H54: 75371.9 | I54: =venta_a_mes5[[#This Row],[IMPORTE NETO]]*0.21 -> 15828.099 | L54: =SUM(venta_a_mes5[[#This Row],[IMPORTE NETO]:[EXENTO]]) -> 91199.999
B55: 45414 | C55: 1 | D55: 1 | E55: 187 | F55: 20132082198 | G55: =IFERROR(IF(venta_a_mes5[[#This Row],[CUIT]]="","-",VLOOKUP(venta_a_mes5[[#This Row],[CUIT]],Lista_CUIT[#All],2,0)),"CUIT NO CARGADO") -> FADIGA OSCAR ALBERTO | H55: 47107.43 | I55: =venta_a_mes5[[#This Row],[IMPORTE NETO]]*0.21 -> 9892.5603 | L55: =SUM(venta_a_mes5[[#This Row],[IMPORTE NETO]:[EXENTO]]) -> 56999.99
B56: 45414 | C56: 1 | D56: 1 | E56: 182 | F56: 20287305460 | G56: =IFERROR(IF(venta_a_mes5[[#This Row],[CUIT]]="","-",VLOOKUP(venta_a_mes5[[#This Row],[CUIT]],Lista_CUIT[#All],2,0)),"CUIT NO CARGADO") -> LANDI GERONIMO | H56: 47107.43 | I56: =venta_a_mes5[[#This Row],[IMPORTE NETO]]*0.21 -> 9892.5603 | L56: =SUM(venta_a_mes5[[#This Row],[IMPORTE NETO]:[EXENTO]]) -> 56999.99
B57: 45414 | C57: 1 | D57: 1 | E57: 181 | F57: 27165844748 | G57: =IFERROR(IF(venta_a_mes5[[#This Row],[CUIT]]="","-",VLOOKUP(venta_a_mes5[[#This Row],[CUIT]],Lista_CUIT[#All],2,0)),"CUIT NO CARGADO") -> DENATALE MARCELA BEATRIZ | H57: 108264.48 | I57: =venta_a_mes5[[#This Row],[IMPORTE NETO]]*0.21 -> 22735.541 | L57: =SUM(venta_a_mes5[[#This Row],[IMPORTE NETO]:[EXENTO]]) -> 131000.02
B58: 45414 | C58: 1 | D58: 1 | E58: 189 | F58: 30716234815 | G58: =IFERROR(IF(venta_a_mes5[[#This Row],[CUIT]]="","-",VLOOKUP(venta_a_mes5[[#This Row],[CUIT]],Lista_CUIT[#All],2,0)),"CUIT NO CARGADO") -> LEVINT PARTNERS S.R.L. | H58: 108264.48 | I58: =venta_a_mes5[[#This Row],[IMPORTE NETO]]*0.21 -> 22735.541 | L58: =SUM(venta_a_mes5[[#This Row],[IMPORTE NETO]:[EXENTO]]) -> 131000.02
B59: 45414 | C59: 1 | D59: 1 | E59: 188 | F59: 30688955749 | G59: =IFERROR(IF(venta_a_mes5[[#This Row],[CUIT]]="","-",VLOOKUP(venta_a_mes5[[#This Row],[CUIT]],Lista_CUIT[#All],2,0)),"CUIT NO CARGADO") -> LISERAR S A | H59: 108264.48 | I59: =venta_a_mes5[[#This Row],[IMPORTE NETO]]*0.21 -> 22735.541 | L59: =SUM(venta_a_mes5[[#This Row],[IMPORTE NETO]:[EXENTO]]) -> 131000.02
B60: 45414 | C60: 1 | D60: 1 | E60: 186 | F60: 30717465101 | G60: =IFERROR(IF(venta_a_mes5[[#This Row],[CUIT]]="","-",VLOOKUP(venta_a_mes5[[#This Row],[CUIT]],Lista_CUIT[#All],2,0)),"CUIT NO CARGADO") -> EMPRENDIMIENTOS SHOPGLASS S. R. L. | H60: 47107.43 | I60: =venta_a_mes5[[#This Row],[IMPORTE NETO]]*0.21 -> 9892.5603 | L60: =SUM(venta_a_mes5[[#This Row],[IMPORTE NETO]:[EXENTO]]) -> 56999.99
B61: 45414 | C61: 1 | D61: 1 | E61: 180 | F61: 30717973166 | G61: =IFERROR(IF(venta_a_mes5[[#This Row],[CUIT]]="","-",VLOOKUP(venta_a_mes5[[#This Row],[CUIT]],Lista_CUIT[#All],2,0)),"CUIT NO CARGADO") -> STM ESTILO S.R.L | H61: 47107.43 | I61: =venta_a_mes5[[#This Row],[IMPORTE NETO]]*0.21 -> 9892.5603 | L61: =SUM(venta_a_mes5[[#This Row],[IMPORTE NETO]:[EXENTO]]) -> 56999.99
B62: 45414 | C62: 1 | D62: 1 | E62: 178 | F62: 30716914077 | G62: =IFERROR(IF(venta_a_mes5[[#This Row],[CUIT]]="","-",VLOOKUP(venta_a_mes5[[#This Row],[CUIT]],Lista_CUIT[#All],2,0)),"CUIT NO CARGADO") -> BACANES | H62: 108264.48 | I62: =venta_a_mes5[[#This Row],[IMPORTE NETO]]*0.21 -> 22735.541 | L62: =SUM(venta_a_mes5[[#This Row],[IMPORTE NETO]:[EXENTO]]) -> 131000.02
B63: 45414 | C63: 1 | D63: 1 | E63: 179 | F63: 20284212488 | G63: =IFERROR(IF(venta_a_mes5[[#This Row],[CUIT]]="","-",VLOOKUP(venta_a_mes5[[#This Row],[CUIT]],Lista_CUIT[#All],2,0)),"CUIT NO CARGADO") -> BARLETTA MAXIMILIANO SEBASTIAN | H63: 47107.43 | I63: =venta_a_mes5[[#This Row],[IMPORTE NETO]]*0.21 -> 9892.5603 | L63: =SUM(venta_a_mes5[[#This Row],[IMPORTE NETO]:[EXENTO]]) -> 56999.99
B64: 45414 | C64: 1 | D64: 1 | E64: 193 | F64: 27312707980 | G64: =IFERROR(IF(venta_a_mes5[[#This Row],[CUIT]]="","-",VLOOKUP(venta_a_mes5[[#This Row],[CUIT]],Lista_CUIT[#All],2,0)),"CUIT NO CARGADO") -> FERRARETTO CARLA ROMINA | H64: 390909.1 | I64: =venta_a_mes5[[#This Row],[IMPORTE NETO]]*0.21 -> 82090.911 | L64: =SUM(venta_a_mes5[[#This Row],[IMPORTE NETO]:[EXENTO]]) -> 473000.01
... B72: 45415 | C72: 1 | D72: 1 | E72: 194 | F72: 30718044894 | G72: =IFERROR(IF(venta_a_mes5[[#This Row],[CUIT]]="","-",VLOOKUP(venta_a_mes5[[#This Row],[CUIT]],Lista_CUIT[#All],2,0)),"CUIT NO CARGADO") -> GRUPO NACER ECOLOGICO S.R.L | H72: 312727.29 | I72: =venta_a_mes5[[#This Row],[IMPORTE NETO]]*0.21 -> 65672.731 | L72: =SUM(venta_a_mes5[[#This Row],[IMPORTE NETO]:[EXENTO]]) -> 378400.02
B73: Total | H73: =SUBTOTAL(109,venta_a_mes5[IMPORTE NETO]) -> 2041456.8 | I73: =SUBTOTAL(109,venta_a_mes5[IVA 21%]) -> 428705.92 | J73: =SUBTOTAL(109,venta_a_mes5[IVA 10,5%]) -> 0 | K73: =SUBTOTAL(109,venta_a_mes5[EXENTO]) -> 0 | L73: =SUBTOTAL(109,venta_a_mes5[TOTAL]) -> 2470162.7 | M73: =SUBTOTAL(103,venta_a_mes5[Provincia]) -> 0
B75: VENTAS "B"
B76: FECHA | C76: TIPO | D76: PTO VENTA | E76: Nº FACTURA | F76: CUIT | G76: RAZON SOCIAL | H76: IMPORTE NETO | I76: IVA 21% | J76: IVA 10,5% | K76: EXENTO | L76: TOTAL | M76: Provincia
B77: 45414 | C77: 6 | D77: 1 | E77: 34 | F77: 20252582704 | G77: =IFERROR(IF(ventas_b_mes5[[#This Row],[CUIT]]="","-",VLOOKUP(ventas_b_mes5[[#This Row],[CUIT]],Lista_CUIT[#All],2,0)),"CUIT NO CARGADO") -> GARCIA VAUTRIN ANDRES ALBERTO | H77: 108264.48 | I77: =ventas_b_mes5[[#This Row],[IMPORTE NETO]]*0.21 -> 22735.541 | L77: =SUM(ventas_b_mes5[[#This Row],[IMPORTE NETO]:[EXENTO]]) -> 131000.02
B78: 45414 | C78: 6 | D78: 1 | E78: 33 | F78: 30592508830 | G78: =IFERROR(IF(ventas_b_mes5[[#This Row],[CUIT]]="","-",VLOOKUP(ventas_b_mes5[[#This Row],[CUIT]],Lista_CUIT[#All],2,0)),"CUIT NO CARGADO") -> INSTITUTO DE ESTUDIOS SUPERIORES DE BUENOS AIRES S A | H78: 41322.33 | I78: =ventas_b_mes5[[#This Row],[IMPORTE NETO]]*0.21 -> 8677.6893 | L78: =SUM(ventas_b_mes5[[#This Row],[IMPORTE NETO]:[EXENTO]]) -> 50000.019
B79: 45414 | C79: 6 | D79: 1 | E79: 35 | F79: 29811544 | G79: =IFERROR(IF(ventas_b_mes5[[#This Row],[CUIT]]="","-",VLOOKUP(ventas_b_mes5[[#This Row],[CUIT]],Lista_CUIT[#All],2,0)),"CUIT NO CARGADO") -> ROSSO FAVIO DANIEL | H79: 47107.43 | I79: =ventas_b_mes5[[#This Row],[IMPORTE NETO]]*0.21 -> 9892.5603 | L79: =SUM(ventas_b_mes5[[#This Row],[IMPORTE NETO]:[EXENTO]]) -> 56999.99
G80: =IFERROR(IF(ventas_b_mes5[[#This Row],[CUIT]]="","-",VLOOKUP(ventas_b_mes5[[#This Row],[CUIT]],Lista_CUIT[#All],2,0)),"CUIT NO CARGADO") -> - | I80: =ventas_b_mes5[[#This Row],[IMPORTE NETO]]*0.21 -> 0 | L80: =SUM(ventas_b_mes5[[#This Row],[IMPORTE NETO]:[EXENTO]]) -> 0
G81: =IFERROR(IF(ventas_b_mes5[[#This Row],[CUIT]]="","-",VLOOKUP(ventas_b_mes5[[#This Row],[CUIT]],Lista_CUIT[#All],2,0)),"CUIT NO CARGADO") -> - | I81: =ventas_b_mes5[[#This Row],[IMPORTE NETO]]*0.21 -> 0 | L81: =SUM(ventas_b_mes5[[#This Row],[IMPORTE NETO]:[EXENTO]]) -> 0
G82: =IFERROR(IF(ventas_b_mes5[[#This Row],[CUIT]]="","-",VLOOKUP(ventas_b_mes5[[#This Row],[CUIT]],Lista_CUIT[#All],2,0)),"CUIT NO CARGADO") -> - | I82: =ventas_b_mes5[[#This Row],[IMPORTE NETO]]*0.21 -> 0 | L82: =SUM(ventas_b_mes5[[#This Row],[IMPORTE NETO]:[EXENTO]]) -> 0
B83: Total | H83: =SUBTOTAL(109,ventas_b_mes5[IMPORTE NETO]) -> 196694.24 | I83: =SUBTOTAL(109,ventas_b_mes5[IVA 21%]) -> 41305.79 | J83: =SUBTOTAL(109,ventas_b_mes5[IVA 10,5%]) -> 0 | K83: =SUBTOTAL(109,ventas_b_mes5[EXENTO]) -> 0 | L83: =SUBTOTAL(109,ventas_b_mes5[TOTAL]) -> 238000.03 | M83: =SUBTOTAL(103,ventas_b_mes5[Provincia]) -> 0
C91: RETENCIONES
C92: FECHA | D92: COMP Nº | E92: Columna1 | F92: CUIT | G92: RAZON SOCIAL | H92: Ganancias | I92: IVA | J92: SUSS | K92: IIBB BSAS | L92: IIBB CABA
G93: =IFERROR(IF(Retenciones_mes5[[#This Row],[CUIT]]="","-",VLOOKUP(Retenciones_mes5[[#This Row],[CUIT]],Lista_CUIT[#All],2,0)),"CUIT NO CARGADO") -> -
G94: =IFERROR(IF(Retenciones_mes5[[#This Row],[CUIT]]="","-",VLOOKUP(Retenciones_mes5[[#This Row],[CUIT]],Lista_CUIT[#All],2,0)),"CUIT NO CARGADO") -> -
G95: =IFERROR(IF(Retenciones_mes5[[#This Row],[CUIT]]="","-",VLOOKUP(Retenciones_mes5[[#This Row],[CUIT]],Lista_CUIT[#All],2,0)),"CUIT NO CARGADO") -> -
G96: =IFERROR(IF(Retenciones_mes5[[#This Row],[CUIT]]="","-",VLOOKUP(Retenciones_mes5[[#This Row],[CUIT]],Lista_CUIT[#All],2,0)),"CUIT NO CARGADO") -> -
G97: =IFERROR(IF(Retenciones_mes5[[#This Row],[CUIT]]="","-",VLOOKUP(Retenciones_mes5[[#This Row],[CUIT]],Lista_CUIT[#All],2,0)),"CUIT NO CARGADO") -> -

Sheet Jun-24
B1: LIBRO IVA COMPRAS | G1: ='Ene-24'!G1:M1 -> RABLEB SRL | N1: =EDATE('Ene-24'!N1,5) -> 45444
B3: TOTAL COMPRAS | G3: TOTAL CREDITO FISCAL | J3: TOTAL VENTAS NETAS | M3: TOTAL DEBITO FISCAL | P3: RESULTADO
B4: =SUM(compras_mes6[[#Totals],[NETO GRAVADO]])+extracto_banco_mes6[[#Totals],[NETO]] -> 1573035.3 | G4: =compras_mes6[[#Totals],[IVA 21 %]]+compras_mes6[[#Totals],[IVA 27%]]+compras_mes6[[#Totals],[IVA 10,5%]]+extracto_banco_mes6[[#Totals],[IVA 21%]]+extracto_banco_mes6[[#Totals],[IVA 10,5%]] -> 330337.42 | J4: =venta_a_mes6[[#Totals],[IMPORTE NETO]]+ventas_b_mes6[[#Totals],[IMPORTE NETO]] -> 3200311 | M4: =venta_a_mes6[[#Totals],[IVA 21%]]+venta_a_mes6[[#Totals],[IVA 10,5%]]+ventas_b_mes6[[#Totals],[IVA 21%]]+ventas_b_mes6[[#Totals],[IVA 10,5%]] -> 672065.3 | P4: =G4-M4 -> -341727.88
B8: FECHA | C8: TIPO | D8: PTO VTA | E8: NRO. CPTE | F8: CUIT | G8: RAZON SOCIAL | H8: NETO GRAVADO | I8: IVA 21 % | J8: IVA 27% | K8: IVA 10,5% | L8: PERC. IVA | M8: PERC IIBB BS AS | N8: PERC. IIBB CABA | O8: Otros / No Grav. | P8: TOTAL | Q8: Tipo de Gasto | R8: Provincia
B9: 45456 | C9: 1 | D9: 3 | E9: 800 | F9: 33717568899 | G9: =IFERROR(IF(compras_mes6[[#This Row],[CUIT]]="","-",VLOOKUP(compras_mes6[[#This Row],[CUIT]],Lista_CUIT[#All],2,0)),"CUIT NO CARGADO") -> COOPERATIVA DE TRABAJO LOS REMANSEROS LIMITADA | H9: 81611.57 | I9: =IF(compras_mes6[[#This Row],[NETO GRAVADO]]="","",compras_mes6[[#This Row],[NETO GRAVADO]]*0.21) -> 17138.43 | P9: =SUM(compras_mes6[[#This Row],[NETO GRAVADO]:[Otros / No Grav.]]) -> 98750 | Q9: =IFERROR(IF(compras_mes6[[#This Row],[CUIT]]="","-",VLOOKUP(compras_mes6[[#This Row],[CUIT]],Lista_CUIT[#All],3,0)),"CUIT NO CARGADO") -> Gastos Varios | R9: =IFERROR(IF(compras_mes6[[#This Row],[CUIT]]="","-",VLOOKUP(compras_mes6[[#This Row],[CUIT]],Lista_CUIT[#All],4,0)),"CUIT NO CARGADO") -> 0
B10: 45458 | C10: 1 | D10: 2 | E10: 1270285 | F10: 30710173652 | G10: =IFERROR(IF(compras_mes6[[#This Row],[CUIT]]="","-",VLOOKUP(compras_mes6[[#This Row],[CUIT]],Lista_CUIT[#All],2,0)),"CUIT NO CARGADO") -> DATTATEC.COM S.R.L. | H10: 21760.33 | I10: =IF(compras_mes6[[#This Row],[NETO GRAVADO]]="","",compras_mes6[[#This Row],[NETO GRAVADO]]*0.21) -> 4569.6693 | P10: =SUM(compras_mes6[[#This Row],[NETO GRAVADO]:[Otros / No Grav.]]) -> 26329.999 | Q10: =IFERROR(IF(compras_mes6[[#This Row],[CUIT]]="","-",VLOOKUP(compras_mes6[[#This Row],[CUIT]],Lista_CUIT[#All],3,0)),"CUIT NO CARGADO") -> Gastos Publicidad y Propaganda | R10: =IFERROR(IF(compras_mes6[[#This Row],[CUIT]]="","-",VLOOKUP(compras_mes6[[#This Row],[CUIT]],Lista_CUIT[#All],4,0)),"CUIT NO CARGADO") -> 0
B11: 45473 | C11: 1 | D11: 11 | E11: 999355 | F11: 33709585229 | G11: =IFERROR(IF(compras_mes6[[#This Row],[CUIT]]="","-",VLOOKUP(compras_mes6[[#This Row],[CUIT]],Lista_CUIT[#All],2,0)),"CUIT NO CARGADO") -> GOOGLE ARGENTINA S.R.L. | H11: 75234.16 | I11: =IF(compras_mes6[[#This Row],[NETO GRAVADO]]="","",compras_mes6[[#This Row],[NETO GRAVADO]]*0.21) -> 15799.174 | N11: 1128.51 | O11: 2257.02 | P11: =SUM(compras_mes6[[#This Row],[NETO GRAVADO]:[Otros / No Grav.]]) -> 94418.864 | Q11: =IFERROR(IF(compras_mes6[[#This Row],[CUIT]]="","-",VLOOKUP(compras_mes6[[#This Row],[CUIT]],Lista_CUIT[#All],3,0)),"CUIT NO CARGADO") -> Gastos Publicidad y Propaganda | R11: =IFERROR(IF(compras_mes6[[#This Row],[CUIT]]="","-",VLOOKUP(compras_mes6[[#This Row],[CUIT]],Lista_CUIT[#All],4,0)),"CUIT NO CARGADO") -> 0
B12: 45473 | C12: 1 | D12: 11 | E12: 1005061 | F12: 33709585229 | G12: =IFERROR(IF(compras_mes6[[#This Row],[CUIT]]="","-",VLOOKUP(compras_mes6[[#This Row],[CUIT]],Lista_CUIT[#All],2,0)),"CUIT NO CARGADO") -> GOOGLE ARGENTINA S.R.L. | H12: 156948.22 | I12: =IF(compras_mes6[[#This Row],[NETO GRAVADO]]="","",compras_mes6[[#This Row],[NETO GRAVADO]]*0.21) -> 32959.126 | N12: 2354.22 | O12: 4708.45 | P12: =SUM(compras_mes6[[#This Row],[NETO GRAVADO]:[Otros / No Grav.]]) -> 196970.02 | Q12: =IFERROR(IF(compras_mes6[[#This Row],[CUIT]]="","-",VLOOKUP(compras_mes6[[#This Row],[CUIT]],Lista_CUIT[#All],3,0)),"CUIT NO CARGADO") -> Gastos Publicidad y Propaganda | R12: =IFERROR(IF(compras_mes6[[#This Row],[CUIT]]="","-",VLOOKUP(compras_mes6[[#This Row],[CUIT]],Lista_CUIT[#All],4,0)),"CUIT NO CARGADO") -> 0
B13: 45473 | C13: 1 | D13: 11 | E13: 1000544 | F13: 33709585229 | G13: =IFERROR(IF(compras_mes6[[#This Row],[CUIT]]="","-",VLOOKUP(compras_mes6[[#This Row],[CUIT]],Lista_CUIT[#All],2,0)),"CUIT NO CARGADO") -> GOOGLE ARGENTINA S.R.L. | H13: 19614.3 | I13: =IF(compras_mes6[[#This Row],[NETO GRAVADO]]="","",compras_mes6[[#This Row],[NETO GRAVADO]]*0.21) -> 4119.003 | N13: 294.21 | O13: 588.43 | P13: =SUM(compras_mes6[[#This Row],[NETO GRAVADO]:[Otros / No Grav.]]) -> 24615.943 | Q13: =IFERROR(IF(compras_mes6[[#This Row],[CUIT]]="","-",VLOOKUP(compras_mes6[[#This Row],[CUIT]],Lista_CUIT[#All],3,0)),"CUIT NO CARGADO") -> Gastos Publicidad y Propaganda | R13: =IFERROR(IF(compras_mes6[[#This Row],[CUIT]]="","-",VLOOKUP(compras_mes6[[#This Row],[CUIT]],Lista_CUIT[#All],4,0)),"CUIT NO CARGADO") -> 0
B14: 45473 | C14: 1 | D14: 11 | E14: 998023 | F14: 33709585229 | G14: =IFERROR(IF(compras_mes6[[#This Row],[CUIT]]="","-",VLOOKUP(compras_mes6[[#This Row],[CUIT]],Lista_CUIT[#All],2,0)),"CUIT NO CARGADO") -> GOOGLE ARGENTINA S.R.L. | H14: 51990.82 | I14: =IF(compras_mes6[[#This Row],[NETO GRAVADO]]="","",compras_mes6[[#This Row],[NETO GRAVADO]]*0.21) -> 10918.072 | N14: 779.86 | O14: 1559.72 | P14: =SUM(compras_mes6[[#This Row],[NETO GRAVADO]:[Otros / No Grav.]]) -> 65248.472 | Q14: =IFERROR(IF(compras_mes6[[#This Row],[CUIT]]="","-",VLOOKUP(compras_mes6[[#This Row],[CUIT]],Lista_CUIT[#All],3,0)),"CUIT NO CARGADO") -> Gastos Publicidad y Propaganda | R14: =IFERROR(IF(compras_mes6[[#This Row],[CUIT]]="","-",VLOOKUP(compras_mes6[[#This Row],[CUIT]],Lista_CUIT[#All],4,0)),"CUIT NO CARGADO") -> 0
B15: 45473 | C15: 1 | D15: 11 | E15: 1003551 | F15: 33709585229 | G15: =IFERROR(IF(compras_mes6[[#This Row],[CUIT]]="","-",VLOOKUP(compras_mes6[[#This Row],[CUIT]],Lista_CUIT[#All],2,0)),"CUIT NO CARGADO") -> GOOGLE ARGENTINA S.R.L. | H15: 1002105.4 | I15: =IF(compras_mes6[[#This Row],[NETO GRAVADO]]="","",compras_mes6[[#This Row],[NETO GRAVADO]]*0.21) -> 210442.13 | N15: 15031.58 | O15: 30063.16 | P15: =SUM(compras_mes6[[#This Row],[NETO GRAVADO]:[Otros / No Grav.]]) -> 1257642.2 | Q15: =IFERROR(IF(compras_mes6[[#This Row],[CUIT]]="","-",VLOOKUP(compras_mes6[[#This Row],[CUIT]],Lista_CUIT[#All],3,0)),"CUIT NO CARGADO") -> Gastos Publicidad y Propaganda | R15: =IFERROR(IF(compras_mes6[[#This Row],[CUIT]]="","-",VLOOKUP(compras_mes6[[#This Row],[CUIT]],Lista_CUIT[#All],4,0)),"CUIT NO CARGADO") -> 0
B16: 45473 | C16: 1 | D16: 11 | E16: 1007901 | F16: 33709585229 | G16: =IFERROR(IF(compras_mes6[[#This Row],[CUIT]]="","-",VLOOKUP(compras_mes6[[#This Row],[CUIT]],Lista_CUIT[#All],2,0)),"CUIT NO CARGADO") -> GOOGLE ARGENTINA S.R.L. | H16: 62111.89 | I16: =IF(compras_mes6[[#This Row],[NETO GRAVADO]]="","",compras_mes6[[#This Row],[NETO GRAVADO]]*0.21) -> 13043.497 | N16: 931.68 | O16: 1863.36 | P16: =SUM(compras_mes6[[#This Row],[NETO GRAVADO]:[Otros / No Grav.]]) -> 77950.427 | Q16: =IFERROR(IF(compras_mes6[[#This Row],[CUIT]]="","-",VLOOKUP(compras_mes6[[#This Row],[CUIT]],Lista_CUIT[#All],3,0)),"CUIT NO CARGADO") -> Gastos Publicidad y Propaganda | R16: =IFERROR(IF(compras_mes6[[#This Row],[CUIT]]="","-",VLOOKUP(compras_mes6[[#This Row],[CUIT]],Lista_CUIT[#All],4,0)),"CUIT NO CARGADO") -> 0
B17: 45473 | C17: 1 | D17: 11 | E17: 1007377 | F17: 33709585229 | G17: =IFERROR(IF(compras_mes6[[#This Row],[CUIT]]="","-",VLOOKUP(compras_mes6[[#This Row],[CUIT]],Lista_CUIT[#All],2,0)),"CUIT NO CARGADO") -> GOOGLE ARGENTINA S.R.L. | H17: 105484.16 | I17: =IF(compras_mes6[[#This Row],[NETO GRAVADO]]="","",compras_mes6[[#This Row],[NETO GRAVADO]]*0.21) -> 22151.674 | N17: 1582.26 | O17: 3164.52 | P17: =SUM(compras_mes6[[#This Row],[NETO GRAVADO]:[Otros / No Grav.]]) -> 132382.61 | Q17: =IFERROR(IF(compras_mes6[[#This Row],[CUIT]]="","-",VLOOKUP(compras_mes6[[#This Row],[CUIT]],Lista_CUIT[#All],3,0)),"CUIT NO CARGADO") -> Gastos Publicidad y Propaganda | R17: =IFERROR(IF(compras_mes6[[#This Row],[CUIT]]="","-",VLOOKUP(compras_mes6[[#This Row],[CUIT]],Lista_CUIT[#All],4,0)),"CUIT NO CARGADO") -> 0
B18: 45473 | C18: 3 | D18: 11 | E18: 735006 | F18: 33709585229 | G18: =IFERROR(IF(compras_mes6[[#This Row],[CUIT]]="","-",VLOOKUP(compras_mes6[[#This Row],[CUIT]],Lista_CUIT[#All],2,0)),"CUIT NO CARGADO") -> GOOGLE ARGENTINA S.R.L. | H18: -22337.02 | I18: =IF(compras_mes6[[#This Row],[NETO GRAVADO]]="","",compras_mes6[[#This Row],[NETO GRAVADO]]*0.21) -> -4690.7742 | N18: -335.06 | O18: -670.11 | P18: =SUM(compras_mes6[[#This Row],[NETO GRAVADO]:[Otros / No Grav.]]) -> -28032.964 | Q18: =IFERROR(IF(compras_mes6[[#This Row],[CUIT]]="","-",VLOOKUP(compras_mes6[[#This Row],[CUIT]],Lista_CUIT[#All],3,0)),"CUIT NO CARGADO") -> Gastos Publicidad y Propaganda | R18: =IFERROR(IF(compras_mes6[[#This Row],[CUIT]]="","-",VLOOKUP(compras_mes6[[#This Row],[CUIT]],Lista_CUIT[#All],4,0)),"CUIT NO CARGADO") -> 0
B19: 45473 | C19: 3 | D19: 11 | E19: 733418 | F19: 33709585229 | G19: =IFERROR(IF(compras_mes6[[#This Row],[CUIT]]="","-",VLOOKUP(compras_mes6[[#This Row],[CUIT]],Lista_CUIT[#All],2,0)),"CUIT NO CARGADO") -> GOOGLE ARGENTINA S.R.L. | H19: -4322.12 | I19: =IF(compras_mes6[[#This Row],[NETO GRAVADO]]="","",compras_mes6[[#This Row],[NETO GRAVADO]]*0.21) -> -907.6452 | N19: -64.83 | O19: -129.66 | P19: =SUM(compras_mes6[[#This Row],[NETO GRAVADO]:[Otros / No Grav.]]) -> -5424.2552 | Q19: =IFERROR(IF(compras_mes6[[#This Row],[CUIT]]="","-",VLOOKUP(compras_mes6[[#This Row],[CUIT]],Lista_CUIT[#All],3,0)),"CUIT NO CARGADO") -> Gastos Publicidad y Propaganda | R19: =IFERROR(IF(compras_mes6[[#This Row],[CUIT]]="","-",VLOOKUP(compras_mes6[[#This Row],[CUIT]],Lista_CUIT[#All],4,0)),"CUIT NO CARGADO") -> 0
B20: 45473 | C20: 3 | D20: 11 | E20: 737428 | F20: 33709585229 | G20: =IFERROR(IF(compras_mes6[[#This Row],[CUIT]]="","-",VLOOKUP(compras_mes6[[#This Row],[CUIT]],Lista_CUIT[#All],2,0)),"CUIT NO CARGADO") -> GOOGLE ARGENTINA S.R.L. | H20: -29.27 | I20: =IF(compras_mes6[[#This Row],[NETO GRAVADO]]="","",compras_mes6[[#This Row],[NETO GRAVADO]]*0.21) -> -6.1467 | P20: =SUM(compras_mes6[[#This Row],[NETO GRAVADO]:[Otros / No Grav.]]) -> -35.4167 | Q20: =IFERROR(IF(compras_mes6[[#This Row],[CUIT]]="","-",VLOOKUP(compras_mes6[[#This Row],[CUIT]],Lista_CUIT[#All],3,0)),"CUIT NO CARGADO") -> Gastos Publicidad y Propaganda | R20: =IFERROR(IF(compras_mes6[[#This Row],[CUIT]]="","-",VLOOKUP(compras_mes6[[#This Row],[CUIT]],Lista_CUIT[#All],4,0)),"CUIT NO CARGADO") -> 0
B21: Total | H21: =SUBTOTAL(109,compras_mes6[NETO GRAVADO]) -> 1550172.4 | I21: =SUBTOTAL(109,compras_mes6[IVA 21 %]) -> 325536.21 | J21: =SUBTOTAL(109,compras_mes6[IVA 27%]) -> 0 | K21: =SUBTOTAL(109,compras_mes6[IVA 10,5%]) -> 0 | L21: =SUBTOTAL(109,compras_mes6[PERC. IVA]) -> 0 | M21: =SUBTOTAL(109,compras_mes6[PERC IIBB BS AS]) -> 0 | N21: =SUBTOTAL(109,compras_mes6[PERC. IIBB CABA]) -> 21702.43 | O21: =SUBTOTAL(109,compras_mes6[Otros / No Grav.]) -> 43404.89 | P21: =SUBTOTAL(109,compras_mes6[TOTAL]) -> 1940815.9
K24: =compras_mes6[[#Totals],[NETO GRAVADO]]+compras_mes6[[#Totals],[Otros / No Grav.]] -> 1593577.3
D26: LIQUIDACION EXTRACTOS BANCARIOS-TARJETAS
D27: FECHA | E27: NRO CPTE | F27: BANCO | G27: NETO | H27: IVA 21% | I27: IVA 10,5% | J27: RET IIBB CABA | K27: PERC IVA | L27: PERC IIBB
D28: 45473 | F28: GALICIA | G28: =22862.9 -> 22862.9 | H28: =extracto_banco_mes6[[#This Row],[NETO]]*0.21 -> 4801.209 | K28: =685.89 -> 685.89 | L28: =342.94 -> 342.94
D31: Total | G31: =SUBTOTAL(109,extracto_banco_mes6[NETO]) -> 22862.9 | H31: =SUBTOTAL(109,extracto_banco_mes6[IVA 21%]) -> 4801.209 | I31: =SUBTOTAL(109,extracto_banco_mes6[IVA 10,5%]) -> 0 | J31: =SUBTOTAL(109,extracto_banco_mes6[RET IIBB CABA]) -> 0 | K31: =SUBTOTAL(109,extracto_banco_mes6[PERC IVA]) -> 685.89 | L31: =SUBTOTAL(109,extracto_banco_mes6[PERC IIBB]) -> 342.94
D35: FACTURAS C
D36: FECHA | E36: PTO VTA | F36: FC Nº | G36: CUIT | H36: RAZON SOCIAL | I36: TOTAL | J36: TIPO DE GASTO | K36: Provincia
D37: 45446 | E37: 2 | F37: 786 | G37: 20400104094 | H37: =IFERROR(IF(factura_c_mes6[[#This Row],[CUIT]]="","-",VLOOKUP(factura_c_mes6[[#This Row],[CUIT]],Lista_CUIT[#All],2,0)),"CUIT NO CARGADO") -> BOTINDARI FEDERICO DANIEL | I37: 80000 | J37: =IFERROR(IF(factura_c_mes6[[#This Row],[CUIT]]="","-",VLOOKUP(factura_c_mes6[[#This Row],[CUIT]],Lista_CUIT[#All],3,0)),"CUIT NO CARGADO") -> HONORARIOS CONTABLE | K37: =IFERROR(IF(factura_c_mes6[[#This Row],[CUIT]]="","-",VLOOKUP(factura_c_mes6[[#This Row],[CUIT]],Lista_CUIT[#All],4,0)),"CUIT NO CARGADO") -> 0
D38: 45446 | E38: 2 | F38: 113 | G38: 27341104845 | H38: =IFERROR(IF(factura_c_mes6[[#This Row],[CUIT]]="","-",VLOOKUP(factura_c_mes6[[#This Row],[CUIT]],Lista_CUIT[#All],2,0)),"CUIT NO CARGADO") -> BOSSI MARIA PAULA | I38: 119755 | J38: =IFERROR(IF(factura_c_mes6[[#This Row],[CUIT]]="","-",VLOOKUP(factura_c_mes6[[#This Row],[CUIT]],Lista_CUIT[#All],3,0)),"CUIT NO CARGADO") -> HON. ADMINISTRATIVOS | K38: =IFERROR(IF(factura_c_mes6[[#This Row],[CUIT]]="","-",VLOOKUP(factura_c_mes6[[#This Row],[CUIT]],Lista_CUIT[#All],4,0)),"CUIT NO CARGADO") -> 0
D39: 45447 | E39: 2 | F39: 43 | G39: 23380288079 | H39: =IFERROR(IF(factura_c_mes6[[#This Row],[CUIT]]="","-",VLOOKUP(factura_c_mes6[[#This Row],[CUIT]],Lista_CUIT[#All],2,0)),"CUIT NO CARGADO") -> CASTROMAN AGUSTIN | I39: 165476.95 | J39: =IFERROR(IF(factura_c_mes6[[#This Row],[CUIT]]="","-",VLOOKUP(factura_c_mes6[[#This Row],[CUIT]],Lista_CUIT[#All],3,0)),"CUIT NO CARGADO") -> Diseño Grafico | K39: =IFERROR(IF(factura_c_mes6[[#This Row],[CUIT]]="","-",VLOOKUP(factura_c_mes6[[#This Row],[CUIT]],Lista_CUIT[#All],4,0)),"CUIT NO CARGADO") -> 0
D40: 45449 | E40: 51 | F40: 161 | G40: 20300985158 | H40: =IFERROR(IF(factura_c_mes6[[#This Row],[CUIT]]="","-",VLOOKUP(factura_c_mes6[[#This Row],[CUIT]],Lista_CUIT[#All],2,0)),"CUIT NO CARGADO") -> GONZALEZ NESTOR RICARDO | I40: 380000 | J40: =IFERROR(IF(factura_c_mes6[[#This Row],[CUIT]]="","-",VLOOKUP(factura_c_mes6[[#This Row],[CUIT]],Lista_CUIT[#All],3,0)),"CUIT NO CARGADO") -> Diseño Grafico | K40: =IFERROR(IF(factura_c_mes6[[#This Row],[CUIT]]="","-",VLOOKUP(factura_c_mes6[[#This Row],[CUIT]],Lista_CUIT[#All],4,0)),"CUIT NO CARGADO") -> 0
D41: 45449 | E41: 1 | F41: 303 | G41: 27386311000 | H41: =IFERROR(IF(factura_c_mes6[[#This Row],[CUIT]]="","-",VLOOKUP(factura_c_mes6[[#This Row],[CUIT]],Lista_CUIT[#All],2,0)),"CUIT NO CARGADO") -> OPANASIUK MACARENA ANTONELLA | I41: 250000 | J41: =IFERROR(IF(factura_c_mes6[[#This Row],[CUIT]]="","-",VLOOKUP(factura_c_mes6[[#This Row],[CUIT]],Lista_CUIT[#All],3,0)),"CUIT NO CARGADO") -> Honorarios Profesionales | K41: =IFERROR(IF(factura_c_mes6[[#This Row],[CUIT]]="","-",VLOOKUP(factura_c_mes6[[#This Row],[CUIT]],Lista_CUIT[#All],4,0)),"CUIT NO CARGADO") -> 0
D42: Total | I42: =SUBTOTAL(109,factura_c_mes6[TOTAL]) -> 995231.95
B47: LIBRO IVA VENTAS | K47: =N1 -> 45444
B49: VENTAS "A"
B50: FECHA | C50: TIPO | D50: PTO VENTA | E50: Nº FACTURA | F50: CUIT | G50: RAZON SOCIAL | H50: IMPORTE NETO | I50: IVA 21% | J50: IVA 10,5% | K50: EXENTO | L50: TOTAL | M50: Provincia
B51: 45446 | C51: 1 | D51: 1 | E51: 195 | F51: 30716549107 | G51: =IFERROR(IF(venta_a_mes6[[#This Row],[CUIT]]="","-",VLOOKUP(venta_a_mes6[[#This Row],[CUIT]],Lista_CUIT[#All],2,0)),"CUIT NO CARGADO") -> LAMATEC S.R.L. | H51: 108264.48 | I51: =venta_a_mes6[[#This Row],[IMPORTE NETO]]*0.21 -> 22735.541 | L51: =SUM(venta_a_mes6[[#This Row],[IMPORTE NETO]:[EXENTO]]) -> 131000.02
B52: 45446 | C52: 1 | D52: 1 | E52: 207 | F52: 30688955749 | G52: =IFERROR(IF(venta_a_mes6[[#This Row],[CUIT]]="","-",VLOOKUP(venta_a_mes6[[#This Row],[CUIT]],Lista_CUIT[#All],2,0)),"CUIT NO CARGADO") -> LISERAR S A | H52: 108264.48 | I52: =venta_a_mes6[[#This Row],[IMPORTE NETO]]*0.21 -> 22735.541 | L52: =SUM(venta_a_mes6[[#This Row],[IMPORTE NETO]:[EXENTO]]) -> 131000.02
B53: 45446 | C53: 1 | D53: 1 | E53: 196 | F53: 20369499956 | G53: =IFERROR(IF(venta_a_mes6[[#This Row],[CUIT]]="","-",VLOOKUP(venta_a_mes6[[#This Row],[CUIT]],Lista_CUIT[#All],2,0)),"CUIT NO CARGADO") -> LAMARI FRANCO AGUSTIN | H53: 108264.48 | I53: =venta_a_mes6[[#This Row],[IMPORTE NETO]]*0.21 -> 22735.541 | L53: =SUM(venta_a_mes6[[#This Row],[IMPORTE NETO]:[EXENTO]]) -> 131000.02
B54: 45446 | C54: 1 | D54: 1 | E54: 208 | F54: 30716234815 | G54: =IFERROR(IF(venta_a_mes6[[#This Row],[CUIT]]="","-",VLOOKUP(venta_a_mes6[[#This Row],[CUIT]],Lista_CUIT[#All],2,0)),"CUIT NO CARGADO") -> LEVINT PARTNERS S.R.L. | H54: 108264.48 | I54: =venta_a_mes6[[#This Row],[IMPORTE NETO]]*0.21 -> 22735.541 | L54: =SUM(venta_a_mes6[[#This Row],[IMPORTE NETO]:[EXENTO]]) -> 131000.02
B55: 45446 | C55: 1 | D55: 1 | E55: 202 | F55: 20279415656 | G55: =IFERROR(IF(venta_a_mes6[[#This Row],[CUIT]]="","-",VLOOKUP(venta_a_mes6[[#This Row],[CUIT]],Lista_CUIT[#All],2,0)),"CUIT NO CARGADO") -> CECCO ALVARO GONZALO | H55: 75371.9 | I55: =venta_a_mes6[[#This Row],[IMPORTE NETO]]*0.21 -> 15828.099 | L55: =SUM(venta_a_mes6[[#This Row],[IMPORTE NETO]:[EXENTO]]) -> 91199.999
B56: 45446 | C56: 1 | D56: 1 | E56: 209 | F56: 20320573948 | G56: =IFERROR(IF(venta_a_mes6[[#This Row],[CUIT]]="","-",VLOOKUP(venta_a_mes6[[#This Row],[CUIT]],Lista_CUIT[#All],2,0)),"CUIT NO CARGADO") -> CAVALLOTTI MARCOS DANIEL | H56: 108264.48 | I56: =venta_a_mes6[[#This Row],[IMPORTE NETO]]*0.21 -> 22735.541 | L56: =SUM(venta_a_mes6[[#This Row],[IMPORTE NETO]:[EXENTO]]) -> 131000.02
B57: 45446 | C57: 1 | D57: 1 | E57: 213 | F57: 20238882975 | G57: =IFERROR(IF(venta_a_mes6[[#This Row],[CUIT]]="","-",VLOOKUP(venta_a_mes6[[#This Row],[CUIT]],Lista_CUIT[#All],2,0)),"CUIT NO CARGADO") -> NARVAEZ SANTIAGO GABRIEL | H57: 390909.1 | I57: =venta_a_mes6[[#This Row],[IMPORTE NETO]]*0.21 -> 82090.911 | L57: =SUM(venta_a_mes6[[#This Row],[IMPORTE NETO]:[EXENTO]]) -> 473000.01
B58: 45446 | C58: 1 | D58: 1 | E58: 203 | F58: 20367341808 | G58: =IFERROR(IF(venta_a_mes6[[#This Row],[CUIT]]="","-",VLOOKUP(venta_a_mes6[[#This Row],[CUIT]],Lista_CUIT[#All],2,0)),"CUIT NO CARGADO") -> FEIDAS FERNANDO EMILIANO | H58: 54545.48 | I58: =venta_a_mes6[[#This Row],[IMPORTE NETO]]*0.21 -> 11454.551 | L58: =SUM(venta_a_mes6[[#This Row],[IMPORTE NETO]:[EXENTO]]) -> 66000.031
B59: 45446 | C59: 1 | D59: 1 | E59: 197 | F59: 30716914077 | G59: =IFERROR(IF(venta_a_mes6[[#This Row],[CUIT]]="","-",VLOOKUP(venta_a_mes6[[#This Row],[CUIT]],Lista_CUIT[#All],2,0)),"CUIT NO CARGADO") -> BACANES | H59: 157024.81 | I59: =venta_a_mes6[[#This Row],[IMPORTE NETO]]*0.21 -> 32975.21 | L59: =SUM(venta_a_mes6[[#This Row],[IMPORTE NETO]:[EXENTO]]) -> 190000.02
B60: 45446 | C60: 1 | D60: 1 | E60: 204 | F60: 30715941763 | G60: =IFERROR(IF(venta_a_mes6[[#This Row],[CUIT]]="","-",VLOOKUP(venta_a_mes6[[#This Row],[CUIT]],Lista_CUIT[#All],2,0)),"CUIT NO CARGADO") -> TOURMALHYN S.R.L. | H60: 24793.38 | I60: =venta_a_mes6[[#This Row],[IMPORTE NETO]]*0.21 -> 5206.6098 | L60: =SUM(venta_a_mes6[[#This Row],[IMPORTE NETO]:[EXENTO]]) -> 29999.99
B61: 45446 | C61: 1 | D61: 1 | E61: 198 | F61: 30718295900 | G61: =IFERROR(IF(venta_a_mes6[[#This Row],[CUIT]]="","-",VLOOKUP(venta_a_mes6[[#This Row],[CUIT]],Lista_CUIT[#All],2,0)),"CUIT NO CARGADO") -> LAPTOP SERVICE S.R.L. | H61: 47107.43 | I61: =venta_a_mes6[[#This Row],[IMPORTE NETO]]*0.21 -> 9892.5603 | L61: =SUM(venta_a_mes6[[#This Row],[IMPORTE NETO]:[EXENTO]]) -> 56999.99
B62: 45446 | C62: 1 | D62: 1 | E62: 210 | F62: 20277452872 | G62: =IFERROR(IF(venta_a_mes6[[#This Row],[CUIT]]="","-",VLOOKUP(venta_a_mes6[[#This Row],[CUIT]],Lista_CUIT[#All],2,0)),"CUIT NO CARGADO") -> GERVASI MAXIMILIANO ARIEL | H62: 390909.1 | I62: =venta_a_mes6[[#This Row],[IMPORTE NETO]]*0.21 -> 82090.911 | L62: =SUM(venta_a_mes6[[#This Row],[IMPORTE NETO]:[EXENTO]]) -> 473000.01
... B71: 45470 | C71: 1 | D71: 1 | E71: 215 | F71: 33717319309 | G71: =IFERROR(IF(venta_a_mes6[[#This Row],[CUIT]]="","-",VLOOKUP(venta_a_mes6[[#This Row],[CUIT]],Lista_CUIT[#All],2,0)),"CUIT NO CARGADO") -> CONSMITEC S.R.L. | H71: 390909.1 | I71: =venta_a_mes6[[#This Row],[IMPORTE NETO]]*0.21 -> 82090.911 | L71: =SUM(venta_a_mes6[[#This Row],[IMPORTE NETO]:[EXENTO]]) -> 473000.01
B72: Total | H72: =SUBTOTAL(109,venta_a_mes6[IMPORTE NETO]) -> 3050724.1 | I72: =SUBTOTAL(109,venta_a_mes6[IVA 21%]) -> 640652.07 | J72: =SUBTOTAL(109,venta_a_mes6[IVA 10,5%]) -> 0 | K72: =SUBTOTAL(109,venta_a_mes6[EXENTO]) -> 0 | L72: =SUBTOTAL(109,venta_a_mes6[TOTAL]) -> 3691376.2 | M72: =SUBTOTAL(103,venta_a_mes6[Provincia]) -> 0
B74: VENTAS "B"
B75: FECHA | C75: TIPO | D75: PTO VENTA | E75: Nº FACTURA | F75: CUIT | G75: RAZON SOCIAL | H75: IMPORTE NETO | I75: IVA 21% | J75: IVA 10,5% | K75: EXENTO | L75: TOTAL | M75: Provincia
B76: 45446 | C76: 6 | D76: 1 | E76: 36 | F76: 30592508830 | G76: =IFERROR(IF(ventas_b_mes6[[#This Row],[CUIT]]="","-",VLOOKUP(ventas_b_mes6[[#This Row],[CUIT]],Lista_CUIT[#All],2,0)),"CUIT NO CARGADO") -> INSTITUTO DE ESTUDIOS SUPERIORES DE BUENOS AIRES S A | H76: 41322.33 | I76: 8677.69 | L76: =SUM(ventas_b_mes6[[#This Row],[IMPORTE NETO]:[EXENTO]]) -> 50000.02
B77: 45446 | C77: 6 | D77: 1 | E77: 37 | F77: 20252582704 | G77: =IFERROR(IF(ventas_b_mes6[[#This Row],[CUIT]]="","-",VLOOKUP(ventas_b_mes6[[#This Row],[CUIT]],Lista_CUIT[#All],2,0)),"CUIT NO CARGADO") -> GARCIA VAUTRIN ANDRES ALBERTO | H77: 108264.48 | I77: 22735.54 | L77: =SUM(ventas_b_mes6[[#This Row],[IMPORTE NETO]:[EXENTO]]) -> 131000.02
B78: 45446 | C78: 6 | D78: 1 | E78: 38 | F78: 29811544 | G78: =IFERROR(IF(ventas_b_mes6[[#This Row],[CUIT]]="","-",VLOOKUP(ventas_b_mes6[[#This Row],[CUIT]],Lista_CUIT[#All],2,0)),"CUIT NO CARGADO") -> ROSSO FAVIO DANIEL | H78: 47107.43 | I78: 9892.56 | L78: =SUM(ventas_b_mes6[[#This Row],[IMPORTE NETO]:[EXENTO]]) -> 56999.99
B79: 45455 | C79: 8 | D79: 1 | E79: 1 | F79: 29811544 | G79: =IFERROR(IF(ventas_b_mes6[[#This Row],[CUIT]]="","-",VLOOKUP(ventas_b_mes6[[#This Row],[CUIT]],Lista_CUIT[#All],2,0)),"CUIT NO CARGADO") -> ROSSO FAVIO DANIEL | H79: -47107.43 | I79: -9892.56 | L79: =SUM(ventas_b_mes6[[#This Row],[IMPORTE NETO]:[EXENTO]]) -> -56999.99
G80: =IFERROR(IF(ventas_b_mes6[[#This Row],[CUIT]]="","-",VLOOKUP(ventas_b_mes6[[#This Row],[CUIT]],Lista_CUIT[#All],2,0)),"CUIT NO CARGADO") -> - | L80: =SUM(ventas_b_mes6[[#This Row],[IMPORTE NETO]:[EXENTO]]) -> 0
G81: =IFERROR(IF(ventas_b_mes6[[#This Row],[CUIT]]="","-",VLOOKUP(ventas_b_mes6[[#This Row],[CUIT]],Lista_CUIT[#All],2,0)),"CUIT NO CARGADO") -> - | L81: =SUM(ventas_b_mes6[[#This Row],[IMPORTE NETO]:[EXENTO]]) -> 0
B82: Total | H82: =SUBTOTAL(109,ventas_b_mes6[IMPORTE NETO]) -> 149586.81 | I82: =SUBTOTAL(109,ventas_b_mes6[IVA 21%]) -> 31413.23 | J82: =SUBTOTAL(109,ventas_b_mes6[IVA 10,5%]) -> 0 | K82: =SUBTOTAL(109,ventas_b_mes6[EXENTO]) -> 0 | L82: =SUBTOTAL(109,ventas_b_mes6[TOTAL]) -> 181000.04 | M82: =SUBTOTAL(103,ventas_b_mes6[Provincia]) -> 0
C90: RETENCIONES
C91: FECHA | D91: COMP Nº | E91: Columna1 | F91: CUIT | G91: RAZON SOCIAL | H91: Ganancias | I91: IVA | J91: SUSS | K91: IIBB BSAS | L91: IIBB CABA
G92: =IFERROR(IF(Retenciones_mes6[[#This Row],[CUIT]]="","-",VLOOKUP(Retenciones_mes6[[#This Row],[CUIT]],Lista_CUIT[#All],2,0)),"CUIT NO CARGADO") -> -
G93: =IFERROR(IF(Retenciones_mes6[[#This Row],[CUIT]]="","-",VLOOKUP(Retenciones_mes6[[#This Row],[CUIT]],Lista_CUIT[#All],2,0)),"CUIT NO CARGADO") -> -
G94: =IFERROR(IF(Retenciones_mes6[[#This Row],[CUIT]]="","-",VLOOKUP(Retenciones_mes6[[#This Row],[CUIT]],Lista_CUIT[#All],2,0)),"CUIT NO CARGADO") -> -
G95: =IFERROR(IF(Retenciones_mes6[[#This Row],[CUIT]]="","-",VLOOKUP(Retenciones_mes6[[#This Row],[CUIT]],Lista_CUIT[#All],2,0)),"CUIT NO CARGADO") -> -
G96: =IFERROR(IF(Retenciones_mes6[[#This Row],[CUIT]]="","-",VLOOKUP(Retenciones_mes6[[#This Row],[CUIT]],Lista_CUIT[#All],2,0)),"CUIT NO CARGADO") -> -

Sheet Jul-24
B1: LIBRO IVA COMPRAS | G1: ='Ene-24'!G1:M1 -> RABLEB SRL | N1: =EDATE('Ene-24'!N1,6) -> 45474
B3: TOTAL COMPRAS | G3: TOTAL CREDITO FISCAL | J3: TOTAL VENTAS NETAS | M3: TOTAL DEBITO FISCAL | P3: RESULTADO
B4: =SUM(compras_mes7[[#Totals],[NETO GRAVADO]])+extracto_banco_mes7[[#Totals],[NETO]] -> 2027191 | G4: =compras_mes7[[#Totals],[IVA 21 %]]+compras_mes7[[#Totals],[IVA 27%]]+compras_mes7[[#Totals],[IVA 10,5%]]+extracto_banco_mes7[[#Totals],[IVA 21%]]+extracto_banco_mes7[[#Totals],[IVA 10,5%]] -> 425710.1 | J4: =venta_a_mes7[[#Totals],[IMPORTE NETO]]+ventas_b_mes7[[#Totals],[IMPORTE NETO]] -> 3971762.7 | M4: =venta_a_mes7[[#Totals],[IVA 21%]]+venta_a_mes7[[#Totals],[IVA 10,5%]]+ventas_b_mes7[[#Totals],[IVA 21%]]+ventas_b_mes7[[#Totals],[IVA 10,5%]] -> 834070.17 | P4: =G4-M4 -> -408360.07
B8: FECHA | C8: TIPO | D8: PTO VTA | E8: NRO. CPTE | F8: CUIT | G8: RAZON SOCIAL | H8: NETO GRAVADO | I8: IVA 21 % | J8: IVA 27% | K8: IVA 10,5% | L8: PERC. IVA | M8: PERC IIBB BS AS | N8: PERC. IIBB CABA | O8: Otros / No Grav. | P8: TOTAL | Q8: Tipo de Gasto | R8: Provincia
B9: 45504 | C9: 1 | D9: 11 | E9: 1010849 | F9: 33709585229 | G9: =IFERROR(IF(compras_mes7[[#This Row],[CUIT]]="","-",VLOOKUP(compras_mes7[[#This Row],[CUIT]],Lista_CUIT[#All],2,0)),"CUIT NO CARGADO") -> GOOGLE ARGENTINA S.R.L. | H9: 47329.95 | I9: =IF(compras_mes7[[#This Row],[NETO GRAVADO]]="","",compras_mes7[[#This Row],[NETO GRAVADO]]*0.21) -> 9939.2895 | L9: 1419.9 | N9: 709.95 | P9: =SUM(compras_mes7[[#This Row],[NETO GRAVADO]:[Otros / No Grav.]]) -> 59399.089 | Q9: =IFERROR(IF(compras_mes7[[#This Row],[CUIT]]="","-",VLOOKUP(compras_mes7[[#This Row],[CUIT]],Lista_CUIT[#All],3,0)),"CUIT NO CARGADO") -> Gastos Publicidad y Propaganda | R9: =IFERROR(IF(compras_mes7[[#This Row],[CUIT]]="","-",VLOOKUP(compras_mes7[[#This Row],[CUIT]],Lista_CUIT[#All],4,0)),"CUIT NO CARGADO") -> 0
B10: 45504 | C10: 1 | D10: 11 | E10: 1012724 | F10: 33709585229 | G10: =IFERROR(IF(compras_mes7[[#This Row],[CUIT]]="","-",VLOOKUP(compras_mes7[[#This Row],[CUIT]],Lista_CUIT[#All],2,0)),"CUIT NO CARGADO") -> GOOGLE ARGENTINA S.R.L. | H10: 170196.82 | I10: =IF(compras_mes7[[#This Row],[NETO GRAVADO]]="","",compras_mes7[[#This Row],[NETO GRAVADO]]*0.21) -> 35741.332 | L10: 5105.9 | N10: 2552.95 | P10: =SUM(compras_mes7[[#This Row],[NETO GRAVADO]:[Otros / No Grav.]]) -> 213597 | Q10: =IFERROR(IF(compras_mes7[[#This Row],[CUIT]]="","-",VLOOKUP(compras_mes7[[#This Row],[CUIT]],Lista_CUIT[#All],3,0)),"CUIT NO CARGADO") -> Gastos Publicidad y Propaganda | R10: =IFERROR(IF(compras_mes7[[#This Row],[CUIT]]="","-",VLOOKUP(compras_mes7[[#This Row],[CUIT]],Lista_CUIT[#All],4,0)),"CUIT NO CARGADO") -> 0
B11: 45504 | C11: 1 | D11: 11 | E11: 1013282 | F11: 33709585229 | G11: =IFERROR(IF(compras_mes7[[#This Row],[CUIT]]="","-",VLOOKUP(compras_mes7[[#This Row],[CUIT]],Lista_CUIT[#All],2,0)),"CUIT NO CARGADO") -> GOOGLE ARGENTINA S.R.L. | H11: 460135.35 | I11: =IF(compras_mes7[[#This Row],[NETO GRAVADO]]="","",compras_mes7[[#This Row],[NETO GRAVADO]]*0.21) -> 96628.423 | L11: 13804.06 | N11: 6902.03 | P11: =SUM(compras_mes7[[#This Row],[NETO GRAVADO]:[Otros / No Grav.]]) -> 577469.86 | Q11: =IFERROR(IF(compras_mes7[[#This Row],[CUIT]]="","-",VLOOKUP(compras_mes7[[#This Row],[CUIT]],Lista_CUIT[#All],3,0)),"CUIT NO CARGADO") -> Gastos Publicidad y Propaganda | R11: =IFERROR(IF(compras_mes7[[#This Row],[CUIT]]="","-",VLOOKUP(compras_mes7[[#This Row],[CUIT]],Lista_CUIT[#All],4,0)),"CUIT NO CARGADO") -> 0
B12: 45504 | C12: 1 | D12: 11 | E12: 1016543 | F12: 33709585229 | G12: =IFERROR(IF(compras_mes7[[#This Row],[CUIT]]="","-",VLOOKUP(compras_mes7[[#This Row],[CUIT]],Lista_CUIT[#All],2,0)),"CUIT NO CARGADO") -> GOOGLE ARGENTINA S.R.L. | H12: 222327.26 | I12: =IF(compras_mes7[[#This Row],[NETO GRAVADO]]="","",compras_mes7[[#This Row],[NETO GRAVADO]]*0.21) -> 46688.725 | L12: 6669.82 | N12: 3334.91 | P12: =SUM(compras_mes7[[#This Row],[NETO GRAVADO]:[Otros / No Grav.]]) -> 279020.71 | Q12: =IFERROR(IF(compras_mes7[[#This Row],[CUIT]]="","-",VLOOKUP(compras_mes7[[#This Row],[CUIT]],Lista_CUIT[#All],3,0)),"CUIT NO CARGADO") -> Gastos Publicidad y Propaganda | R12: =IFERROR(IF(compras_mes7[[#This Row],[CUIT]]="","-",VLOOKUP(compras_mes7[[#This Row],[CUIT]],Lista_CUIT[#All],4,0)),"CUIT NO CARGADO") -> 0
B13: 45504 | C13: 1 | D13: 11 | E13: 1019440 | F13: 33709585229 | G13: =IFERROR(IF(compras_mes7[[#This Row],[CUIT]]="","-",VLOOKUP(compras_mes7[[#This Row],[CUIT]],Lista_CUIT[#All],2,0)),"CUIT NO CARGADO") -> GOOGLE ARGENTINA S.R.L. | H13: 950719.91 | I13: =IF(compras_mes7[[#This Row],[NETO GRAVADO]]="","",compras_mes7[[#This Row],[NETO GRAVADO]]*0.21) -> 199651.18 | L13: 28521.6 | N13: 14260.8 | P13: =SUM(compras_mes7[[#This Row],[NETO GRAVADO]:[Otros / No Grav.]]) -> 1193153.5 | Q13: =IFERROR(IF(compras_mes7[[#This Row],[CUIT]]="","-",VLOOKUP(compras_mes7[[#This Row],[CUIT]],Lista_CUIT[#All],3,0)),"CUIT NO CARGADO") -> Gastos Publicidad y Propaganda | R13: =IFERROR(IF(compras_mes7[[#This Row],[CUIT]]="","-",VLOOKUP(compras_mes7[[#This Row],[CUIT]],Lista_CUIT[#All],4,0)),"CUIT NO CARGADO") -> 0
B14: 45504 | C14: 1 | D14: 11 | E14: 1019862 | F14: 33709585229 | G14: =IFERROR(IF(compras_mes7[[#This Row],[CUIT]]="","-",VLOOKUP(compras_mes7[[#This Row],[CUIT]],Lista_CUIT[#All],2,0)),"CUIT NO CARGADO") -> GOOGLE ARGENTINA S.R.L. | H14: 55769.92 | I14: =IF(compras_mes7[[#This Row],[NETO GRAVADO]]="","",compras_mes7[[#This Row],[NETO GRAVADO]]*0.21) -> 11711.683 | L14: 1673.1 | N14: 836.55 | P14: =SUM(compras_mes7[[#This Row],[NETO GRAVADO]:[Otros / No Grav.]]) -> 69991.253 | Q14: =IFERROR(IF(compras_mes7[[#This Row],[CUIT]]="","-",VLOOKUP(compras_mes7[[#This Row],[CUIT]],Lista_CUIT[#All],3,0)),"CUIT NO CARGADO") -> Gastos Publicidad y Propaganda | R14: =IFERROR(IF(compras_mes7[[#This Row],[CUIT]]="","-",VLOOKUP(compras_mes7[[#This Row],[CUIT]],Lista_CUIT[#All],4,0)),"CUIT NO CARGADO") -> 0
B15: 45504 | C15: 1 | D15: 11 | E15: 1020132 | F15: 33709585229 | G15: =IFERROR(IF(compras_mes7[[#This Row],[CUIT]]="","-",VLOOKUP(compras_mes7[[#This Row],[CUIT]],Lista_CUIT[#All],2,0)),"CUIT NO CARGADO") -> GOOGLE ARGENTINA S.R.L. | H15: 37672.54 | I15: =IF(compras_mes7[[#This Row],[NETO GRAVADO]]="","",compras_mes7[[#This Row],[NETO GRAVADO]]*0.21) -> 7911.2334 | L15: 1130.18 | N15: 565.09 | P15: =SUM(compras_mes7[[#This Row],[NETO GRAVADO]:[Otros / No Grav.]]) -> 47279.043 | Q15: =IFERROR(IF(compras_mes7[[#This Row],[CUIT]]="","-",VLOOKUP(compras_mes7[[#This Row],[CUIT]],Lista_CUIT[#All],3,0)),"CUIT NO CARGADO") -> Gastos Publicidad y Propaganda | R15: =IFERROR(IF(compras_mes7[[#This Row],[CUIT]]="","-",VLOOKUP(compras_mes7[[#This Row],[CUIT]],Lista_CUIT[#All],4,0)),"CUIT NO CARGADO") -> 0
B16: 45504 | C16: 1 | D16: 11 | E16: 1022178 | F16: 33709585229 | G16: =IFERROR(IF(compras_mes7[[#This Row],[CUIT]]="","-",VLOOKUP(compras_mes7[[#This Row],[CUIT]],Lista_CUIT[#All],2,0)),"CUIT NO CARGADO") -> GOOGLE ARGENTINA S.R.L. | H16: 59797.84 | I16: =IF(compras_mes7[[#This Row],[NETO GRAVADO]]="","",compras_mes7[[#This Row],[NETO GRAVADO]]*0.21) -> 12557.546 | L16: 1793.94 | N16: 896.97 | P16: =SUM(compras_mes7[[#This Row],[NETO GRAVADO]:[Otros / No Grav.]]) -> 75046.296 | Q16: =IFERROR(IF(compras_mes7[[#This Row],[CUIT]]="","-",VLOOKUP(compras_mes7[[#This Row],[CUIT]],Lista_CUIT[#All],3,0)),"CUIT NO CARGADO") -> Gastos Publicidad y Propaganda | R16: =IFERROR(IF(compras_mes7[[#This Row],[CUIT]]="","-",VLOOKUP(compras_mes7[[#This Row],[CUIT]],Lista_CUIT[#All],4,0)),"CUIT NO CARGADO") -> 0
B17: 45504 | C17: 3 | D17: 11 | E17: 744050 | F17: 33709585229 | G17: =IFERROR(IF(compras_mes7[[#This Row],[CUIT]]="","-",VLOOKUP(compras_mes7[[#This Row],[CUIT]],Lista_CUIT[#All],2,0)),"CUIT NO CARGADO") -> GOOGLE ARGENTINA S.R.L. | H17: -362.27 | I17: =IF(compras_mes7[[#This Row],[NETO GRAVADO]]="","",compras_mes7[[#This Row],[NETO GRAVADO]]*0.21) -> -76.0767 | P17: =SUM(compras_mes7[[#This Row],[NETO GRAVADO]:[Otros / No Grav.]]) -> -438.3467 | Q17: =IFERROR(IF(compras_mes7[[#This Row],[CUIT]]="","-",VLOOKUP(compras_mes7[[#This Row],[CUIT]],Lista_CUIT[#All],3,0)),"CUIT NO CARGADO") -> Gastos Publicidad y Propaganda | R17: =IFERROR(IF(compras_mes7[[#This Row],[CUIT]]="","-",VLOOKUP(compras_mes7[[#This Row],[CUIT]],Lista_CUIT[#All],4,0)),"CUIT NO CARGADO") -> 0
B18: 45504 | C18: 3 | D18: 11 | E18: 741863 | F18: 33709585229 | G18: =IFERROR(IF(compras_mes7[[#This Row],[CUIT]]="","-",VLOOKUP(compras_mes7[[#This Row],[CUIT]],Lista_CUIT[#All],2,0)),"CUIT NO CARGADO") -> GOOGLE ARGENTINA S.R.L. | H18: -21.36 | I18: =IF(compras_mes7[[#This Row],[NETO GRAVADO]]="","",compras_mes7[[#This Row],[NETO GRAVADO]]*0.21) -> -4.4856 | P18: =SUM(compras_mes7[[#This Row],[NETO GRAVADO]:[Otros / No Grav.]]) -> -25.8456 | Q18: =IFERROR(IF(compras_mes7[[#This Row],[CUIT]]="","-",VLOOKUP(compras_mes7[[#This Row],[CUIT]],Lista_CUIT[#All],3,0)),"CUIT NO CARGADO") -> Gastos Publicidad y Propaganda | R18: =IFERROR(IF(compras_mes7[[#This Row],[CUIT]]="","-",VLOOKUP(compras_mes7[[#This Row],[CUIT]],Lista_CUIT[#All],4,0)),"CUIT NO CARGADO") -> 0
B19: Total | H19: =SUBTOTAL(109,compras_mes7[NETO GRAVADO]) -> 2003566 | I19: =SUBTOTAL(109,compras_mes7[IVA 21 %]) -> 420748.85 | J19: =SUBTOTAL(109,compras_mes7[IVA 27%]) -> 0 | K19: =SUBTOTAL(109,compras_mes7[IVA 10,5%]) -> 0 | L19: =SUBTOTAL(109,compras_mes7[PERC. IVA]) -> 60118.5 | M19: =SUBTOTAL(109,compras_mes7[PERC IIBB BS AS]) -> 0 | N19: =SUBTOTAL(109,compras_mes7[PERC. IIBB CABA]) -> 30059.25 | O19: =SUBTOTAL(109,compras_mes7[Otros / No Grav.]) -> 0 | P19: =SUBTOTAL(109,compras_mes7[TOTAL]) -> 2514492.6
D24: LIQUIDACION EXTRACTOS BANCARIOS-TARJETAS
D25: FECHA | E25: NRO CPTE | F25: BANCO | G25: NETO | H25: IVA 21% | I25: IVA 10,5% | J25: RET IIBB CABA | K25: PERC IVA | L25: PERC IIBB
F26: GALICIA | G26: =23625 -> 23625 | H26: =extracto_banco_mes7[[#This Row],[NETO]]*0.21 -> 4961.25 | K26: =708.75 -> 708.75 | L26: =354.38 -> 354.38
D29: Total | G29: =SUBTOTAL(109,extracto_banco_mes7[NETO]) -> 23625 | H29: =SUBTOTAL(109,extracto_banco_mes7[IVA 21%]) -> 4961.25 | I29: =SUBTOTAL(109,extracto_banco_mes7[IVA 10,5%]) -> 0 | J29: =SUBTOTAL(109,extracto_banco_mes7[RET IIBB CABA]) -> 0 | K29: =SUBTOTAL(109,extracto_banco_mes7[PERC IVA]) -> 708.75 | L29: =SUBTOTAL(109,extracto_banco_mes7[PERC IIBB]) -> 354.38
D33: FACTURAS C
D34: FECHA | E34: PTO VTA | F34: FC Nº | G34: CUIT | H34: RAZON SOCIAL | I34: TOTAL | J34: TIPO DE GASTO | K34: Provincia
D35: 01/07/2024 | E35: 2 | F35: 44 | G35: 23380288079 | H35: =IFERROR(IF(factura_c_mes7[[#This Row],[CUIT]]="","-",VLOOKUP(factura_c_mes7[[#This Row],[CUIT]],Lista_CUIT[#All],2,0)),"CUIT NO CARGADO") -> CASTROMAN AGUSTIN | I35: 248216 | J35: =IFERROR(IF(factura_c_mes7[[#This Row],[CUIT]]="","-",VLOOKUP(factura_c_mes7[[#This Row],[CUIT]],Lista_CUIT[#All],3,0)),"CUIT NO CARGADO") -> Diseño Grafico | K35: =IFERROR(IF(factura_c_mes7[[#This Row],[CUIT]]="","-",VLOOKUP(factura_c_mes7[[#This Row],[CUIT]],Lista_CUIT[#All],4,0)),"CUIT NO CARGADO") -> 0
D36: 01/07/2024 | E36: 2 | F36: 116 | G36: 27341104845 | H36: =IFERROR(IF(factura_c_mes7[[#This Row],[CUIT]]="","-",VLOOKUP(factura_c_mes7[[#This Row],[CUIT]],Lista_CUIT[#All],2,0)),"CUIT NO CARGADO") -> BOSSI MARIA PAULA | I36: 179633 | J36: =IFERROR(IF(factura_c_mes7[[#This Row],[CUIT]]="","-",VLOOKUP(factura_c_mes7[[#This Row],[CUIT]],Lista_CUIT[#All],3,0)),"CUIT NO CARGADO") -> HON. ADMINISTRATIVOS | K36: =IFERROR(IF(factura_c_mes7[[#This Row],[CUIT]]="","-",VLOOKUP(factura_c_mes7[[#This Row],[CUIT]],Lista_CUIT[#All],4,0)),"CUIT NO CARGADO") -> 0
D37: 03/07/2024 | E37: 2 | F37: 802 | G37: 20400104094 | H37: =IFERROR(IF(factura_c_mes7[[#This Row],[CUIT]]="","-",VLOOKUP(factura_c_mes7[[#This Row],[CUIT]],Lista_CUIT[#All],2,0)),"CUIT NO CARGADO") -> BOTINDARI FEDERICO DANIEL | I37: 80000 | J37: =IFERROR(IF(factura_c_mes7[[#This Row],[CUIT]]="","-",VLOOKUP(factura_c_mes7[[#This Row],[CUIT]],Lista_CUIT[#All],3,0)),"CUIT NO CARGADO") -> HONORARIOS CONTABLE | K37: =IFERROR(IF(factura_c_mes7[[#This Row],[CUIT]]="","-",VLOOKUP(factura_c_mes7[[#This Row],[CUIT]],Lista_CUIT[#All],4,0)),"CUIT NO CARGADO") -> 0
D38: 05/07/2024 | E38: 1 | F38: 304 | G38: 27386311000 | H38: =IFERROR(IF(factura_c_mes7[[#This Row],[CUIT]]="","-",VLOOKUP(factura_c_mes7[[#This Row],[CUIT]],Lista_CUIT[#All],2,0)),"CUIT NO CARGADO") -> OPANASIUK MACARENA ANTONELLA | I38: 450000 | J38: =IFERROR(IF(factura_c_mes7[[#This Row],[CUIT]]="","-",VLOOKUP(factura_c_mes7[[#This Row],[CUIT]],Lista_CUIT[#All],3,0)),"CUIT NO CARGADO") -> Honorarios Profesionales | K38: =IFERROR(IF(factura_c_mes7[[#This Row],[CUIT]]="","-",VLOOKUP(factura_c_mes7[[#This Row],[CUIT]],Lista_CUIT[#All],4,0)),"CUIT NO CARGADO") -> 0
D39: 05/07/2024 | E39: 51 | F39: 162 | G39: 20300985158 | H39: =IFERROR(IF(factura_c_mes7[[#This Row],[CUIT]]="","-",VLOOKUP(factura_c_mes7[[#This Row],[CUIT]],Lista_CUIT[#All],2,0)),"CUIT NO CARGADO") -> GONZALEZ NESTOR RICARDO | I39: 400000 | J39: =IFERROR(IF(factura_c_mes7[[#This Row],[CUIT]]="","-",VLOOKUP(factura_c_mes7[[#This Row],[CUIT]],Lista_CUIT[#All],3,0)),"CUIT NO CARGADO") -> Diseño Grafico | K39: =IFERROR(IF(factura_c_mes7[[#This Row],[CUIT]]="","-",VLOOKUP(factura_c_mes7[[#This Row],[CUIT]],Lista_CUIT[#All],4,0)),"CUIT NO CARGADO") -> 0
D40: Total | I40: =SUBTOTAL(109,factura_c_mes7[TOTAL]) -> 1357849
B45: LIBRO IVA VENTAS | K45: =N1 -> 45474
B47: VENTAS "A"
B48: FECHA | C48: TIPO | D48: PTO VENTA | E48: Nº FACTURA | F48: CUIT | G48: RAZON SOCIAL | H48: IMPORTE NETO | I48: IVA 21% | J48: IVA 10,5% | K48: EXENTO | L48: TOTAL | M48: Provincia
B49: 01/07/2024 | C49: 1 | D49: 1 | E49: 221 | F49: 20287305460 | G49: =IFERROR(IF(venta_a_mes7[[#This Row],[CUIT]]="","-",VLOOKUP(venta_a_mes7[[#This Row],[CUIT]],Lista_CUIT[#All],2,0)),"CUIT NO CARGADO") -> LANDI GERONIMO | H49: 58677.67 | I49: =venta_a_mes7[[#This Row],[IMPORTE NETO]]*0.21 -> 12322.311 | L49: =SUM(venta_a_mes7[[#This Row],[IMPORTE NETO]:[EXENTO]]) -> 70999.981
B50: 01/07/2024 | C50: 1 | D50: 1 | E50: 226 | F50: 20132082198 | G50: =IFERROR(IF(venta_a_mes7[[#This Row],[CUIT]]="","-",VLOOKUP(venta_a_mes7[[#This Row],[CUIT]],Lista_CUIT[#All],2,0)),"CUIT NO CARGADO") -> FADIGA OSCAR ALBERTO | H50: 113223.14 | I50: =venta_a_mes7[[#This Row],[IMPORTE NETO]]*0.21 -> 23776.859 | L50: =SUM(venta_a_mes7[[#This Row],[IMPORTE NETO]:[EXENTO]]) -> 137000
B51: 01/07/2024 | C51: 1 | D51: 1 | E51: 216 | F51: 30716549107 | G51: =IFERROR(IF(venta_a_mes7[[#This Row],[CUIT]]="","-",VLOOKUP(venta_a_mes7[[#This Row],[CUIT]],Lista_CUIT[#All],2,0)),"CUIT NO CARGADO") -> LAMATEC S.R.L. | H51: 132231.43 | I51: =venta_a_mes7[[#This Row],[IMPORTE NETO]]*0.21 -> 27768.6 | L51: =SUM(venta_a_mes7[[#This Row],[IMPORTE NETO]:[EXENTO]]) -> 160000.03
B52: 01/07/2024 | C52: 1 | D52: 1 | E52: 227 | F52: 30688955749 | G52: =IFERROR(IF(venta_a_mes7[[#This Row],[CUIT]]="","-",VLOOKUP(venta_a_mes7[[#This Row],[CUIT]],Lista_CUIT[#All],2,0)),"CUIT NO CARGADO") -> LISERAR S A | H52: 132231.43 | I52: =venta_a_mes7[[#This Row],[IMPORTE NETO]]*0.21 -> 27768.6 | L52: =SUM(venta_a_mes7[[#This Row],[IMPORTE NETO]:[EXENTO]]) -> 160000.03
B53: 01/07/2024 | C53: 1 | D53: 1 | E53: 228 | F53: 30716234815 | G53: =IFERROR(IF(venta_a_mes7[[#This Row],[CUIT]]="","-",VLOOKUP(venta_a_mes7[[#This Row],[CUIT]],Lista_CUIT[#All],2,0)),"CUIT NO CARGADO") -> LEVINT PARTNERS S.R.L. | H53: 132231.43 | I53: =venta_a_mes7[[#This Row],[IMPORTE NETO]]*0.21 -> 27768.6 | L53: =SUM(venta_a_mes7[[#This Row],[IMPORTE NETO]:[EXENTO]]) -> 160000.03
B54: 01/07/2024 | C54: 1 | D54: 1 | E54: 222 | F54: 20279415656 | G54: =IFERROR(IF(venta_a_mes7[[#This Row],[CUIT]]="","-",VLOOKUP(venta_a_mes7[[#This Row],[CUIT]],Lista_CUIT[#All],2,0)),"CUIT NO CARGADO") -> CECCO ALVARO GONZALO | H54: 94214.86 | I54: =venta_a_mes7[[#This Row],[IMPORTE NETO]]*0.21 -> 19785.121 | L54: =SUM(venta_a_mes7[[#This Row],[IMPORTE NETO]:[EXENTO]]) -> 113999.98
B55: 01/07/2024 | C55: 1 | D55: 1 | E55: 229 | F55: 20320573948 | G55: =IFERROR(IF(venta_a_mes7[[#This Row],[CUIT]]="","-",VLOOKUP(venta_a_mes7[[#This Row],[CUIT]],Lista_CUIT[#All],2,0)),"CUIT NO CARGADO") -> CAVALLOTTI MARCOS DANIEL | H55: 132231.43 | I55: =venta_a_mes7[[#This Row],[IMPORTE NETO]]*0.21 -> 27768.6 | L55: =SUM(venta_a_mes7[[#This Row],[IMPORTE NETO]:[EXENTO]]) -> 160000.03
B56: 01/07/2024 | C56: 1 | D56: 1 | E56: 230 | F56: 20238882975 | G56: =IFERROR(IF(venta_a_mes7[[#This Row],[CUIT]]="","-",VLOOKUP(venta_a_mes7[[#This Row],[CUIT]],Lista_CUIT[#All],2,0)),"CUIT NO CARGADO") -> NARVAEZ SANTIAGO GABRIEL | H56: 390909.1 | I56: =venta_a_mes7[[#This Row],[IMPORTE NETO]]*0.21 -> 82090.911 | L56: =SUM(venta_a_mes7[[#This Row],[IMPORTE NETO]:[EXENTO]]) -> 473000.01
B57: 01/07/2024 | C57: 1 | D57: 1 | E57: 223 | F57: 20367341808 | G57: =IFERROR(IF(venta_a_mes7[[#This Row],[CUIT]]="","-",VLOOKUP(venta_a_mes7[[#This Row],[CUIT]],Lista_CUIT[#All],2,0)),"CUIT NO CARGADO") -> FEIDAS FERNANDO EMILIANO | H57: 58677.67 | I57: =venta_a_mes7[[#This Row],[IMPORTE NETO]]*0.21 -> 12322.311 | L57: =SUM(venta_a_mes7[[#This Row],[IMPORTE NETO]:[EXENTO]]) -> 70999.981
B58: 01/07/2024 | C58: 1 | D58: 1 | E58: 231 | F58: 30717969061 | G58: =IFERROR(IF(venta_a_mes7[[#This Row],[CUIT]]="","-",VLOOKUP(venta_a_mes7[[#This Row],[CUIT]],Lista_CUIT[#All],2,0)),"CUIT NO CARGADO") -> FABIO Y RAUL ROSSO S.A.S. | H58: 58677.67 | I58: =venta_a_mes7[[#This Row],[IMPORTE NETO]]*0.21 -> 12322.311 | L58: =SUM(venta_a_mes7[[#This Row],[IMPORTE NETO]:[EXENTO]]) -> 70999.981
B59: 01/07/2024 | C59: 1 | D59: 1 | E59: 224 | F59: 30715941763 | G59: =IFERROR(IF(venta_a_mes7[[#This Row],[CUIT]]="","-",VLOOKUP(venta_a_mes7[[#This Row],[CUIT]],Lista_CUIT[#All],2,0)),"CUIT NO CARGADO") -> TOURMALHYN S.R.L. | H59: 30578.52 | I59: =venta_a_mes7[[#This Row],[IMPORTE NETO]]*0.21 -> 6421.4892 | L59: =SUM(venta_a_mes7[[#This Row],[IMPORTE NETO]:[EXENTO]]) -> 37000.009
B60: 01/07/2024 | C60: 1 | D60: 1 | E60: 232 | F60: 30718044894 | G60: =IFERROR(IF(venta_a_mes7[[#This Row],[CUIT]]="","-",VLOOKUP(venta_a_mes7[[#This Row],[CUIT]],Lista_CUIT[#All],2,0)),"CUIT NO CARGADO") -> GRUPO NACER ECOLOGICO S.R.L | H60: 312727.29 | I60: =venta_a_mes7[[#This Row],[IMPORTE NETO]]*0.21 -> 65672.731 | L60: =SUM(venta_a_mes7[[#This Row],[IMPORTE NETO]:[EXENTO]]) -> 378400.02
... B73: 26/07/2024 | C73: 1 | D73: 1 | E73: 238 | F73: 30718553357 | G73: =IFERROR(IF(venta_a_mes7[[#This Row],[CUIT]]="","-",VLOOKUP(venta_a_mes7[[#This Row],[CUIT]],Lista_CUIT[#All],2,0)),"CUIT NO CARGADO") -> EMIGRA CON TU MASCOTA S.R.L. | H73: 428099.19 | I73: =venta_a_mes7[[#This Row],[IMPORTE NETO]]*0.21 -> 89900.83 | L73: =SUM(venta_a_mes7[[#This Row],[IMPORTE NETO]:[EXENTO]]) -> 518000.02
B74: Total | H74: =SUBTOTAL(109,venta_a_mes7[IMPORTE NETO]) -> 3729613.9 | I74: =SUBTOTAL(109,venta_a_mes7[IVA 21%]) -> 783218.93 | J74: =SUBTOTAL(109,venta_a_mes7[IVA 10,5%]) -> 0 | K74: =SUBTOTAL(109,venta_a_mes7[EXENTO]) -> 0 | L74: =SUBTOTAL(109,venta_a_mes7[TOTAL]) -> 4512832.9 | M74: =SUBTOTAL(103,venta_a_mes7[Provincia]) -> 0
B75: VENTAS "B"
B76: FECHA | C76: TIPO | D76: PTO VENTA | E76: Nº FACTURA | F76: CUIT | G76: RAZON SOCIAL | H76: IMPORTE NETO | I76: IVA 21% | J76: IVA 10,5% | K76: EXENTO | L76: TOTAL | M76: Provincia
B77: 01/07/2024 | C77: 6 | D77: 1 | E77: 39 | F77: 30592508830 | G77: =IFERROR(IF(ventas_b_mes7[[#This Row],[CUIT]]="","-",VLOOKUP(ventas_b_mes7[[#This Row],[CUIT]],Lista_CUIT[#All],2,0)),"CUIT NO CARGADO") -> INSTITUTO DE ESTUDIOS SUPERIORES DE BUENOS AIRES S A | H77: 51239.67 | I77: =ventas_b_mes7[[#This Row],[IMPORTE NETO]]*0.21 -> 10760.331 | L77: =SUM(ventas_b_mes7[[#This Row],[IMPORTE NETO]:[EXENTO]]) -> 62000.001
B78: 01/07/2024 | C78: 6 | D78: 1 | E78: 40 | F78: 20252582704 | G78: =IFERROR(IF(ventas_b_mes7[[#This Row],[CUIT]]="","-",VLOOKUP(ventas_b_mes7[[#This Row],[CUIT]],Lista_CUIT[#All],2,0)),"CUIT NO CARGADO") -> GARCIA VAUTRIN ANDRES ALBERTO | H78: 190909.1 | I78: =ventas_b_mes7[[#This Row],[IMPORTE NETO]]*0.21 -> 40090.911 | L78: =SUM(ventas_b_mes7[[#This Row],[IMPORTE NETO]:[EXENTO]]) -> 231000.01
G79: =IFERROR(IF(ventas_b_mes7[[#This Row],[CUIT]]="","-",VLOOKUP(ventas_b_mes7[[#This Row],[CUIT]],Lista_CUIT[#All],2,0)),"CUIT NO CARGADO") -> - | I79: =ventas_b_mes7[[#This Row],[IMPORTE NETO]]*0.21 -> 0 | L79: =SUM(ventas_b_mes7[[#This Row],[IMPORTE NETO]:[EXENTO]]) -> 0
G80: =IFERROR(IF(ventas_b_mes7[[#This Row],[CUIT]]="","-",VLOOKUP(ventas_b_mes7[[#This Row],[CUIT]],Lista_CUIT[#All],2,0)),"CUIT NO CARGADO") -> - | I80: =ventas_b_mes7[[#This Row],[IMPORTE NETO]]*0.21 -> 0 | L80: =SUM(ventas_b_mes7[[#This Row],[IMPORTE NETO]:[EXENTO]]) -> 0
G81: =IFERROR(IF(ventas_b_mes7[[#This Row],[CUIT]]="","-",VLOOKUP(ventas_b_mes7[[#This Row],[CUIT]],Lista_CUIT[#All],2,0)),"CUIT NO CARGADO") -> - | I81: =ventas_b_mes7[[#This Row],[IMPORTE NETO]]*0.21 -> 0 | L81: =SUM(ventas_b_mes7[[#This Row],[IMPORTE NETO]:[EXENTO]]) -> 0
G82: =IFERROR(IF(ventas_b_mes7[[#This Row],[CUIT]]="","-",VLOOKUP(ventas_b_mes7[[#This Row],[CUIT]],Lista_CUIT[#All],2,0)),"CUIT NO CARGADO") -> - | I82: =ventas_b_mes7[[#This Row],[IMPORTE NETO]]*0.21 -> 0 | L82: =SUM(ventas_b_mes7[[#This Row],[IMPORTE NETO]:[EXENTO]]) -> 0
G83: =IFERROR(IF(ventas_b_mes7[[#This Row],[CUIT]]="","-",VLOOKUP(ventas_b_mes7[[#This Row],[CUIT]],Lista_CUIT[#All],2,0)),"CUIT NO CARGADO") -> - | I83: =ventas_b_mes7[[#This Row],[IMPORTE NETO]]*0.21 -> 0 | L83: =SUM(ventas_b_mes7[[#This Row],[IMPORTE NETO]:[EXENTO]]) -> 0
B84: Total | H84: =SUBTOTAL(109,ventas_b_mes7[IMPORTE NETO]) -> 242148.77 | I84: =SUBTOTAL(109,ventas_b_mes7[IVA 21%]) -> 50851.242 | J84: =SUBTOTAL(109,ventas_b_mes7[IVA 10,5%]) -> 0 | K84: =SUBTOTAL(109,ventas_b_mes7[EXENTO]) -> 0 | L84: =SUBTOTAL(109,ventas_b_mes7[TOTAL]) -> 293000.01 | M84: =SUBTOTAL(103,ventas_b_mes7[Provincia]) -> 0
C91: RETENCIONES
C92: FECHA | D92: COMP Nº | E92: Columna1 | F92: CUIT | G92: RAZON SOCIAL | H92: Ganancias | I92: IVA | J92: SUSS | K92: IIBB BSAS | L92: IIBB CABA
G93: =IFERROR(IF(Retenciones_mes7[[#This Row],[CUIT]]="","-",VLOOKUP(Retenciones_mes7[[#This Row],[CUIT]],Lista_CUIT[#All],2,0)),"CUIT NO CARGADO") -> -
G94: =IFERROR(IF(Retenciones_mes7[[#This Row],[CUIT]]="","-",VLOOKUP(Retenciones_mes7[[#This Row],[CUIT]],Lista_CUIT[#All],2,0)),"CUIT NO CARGADO") -> -
G95: =IFERROR(IF(Retenciones_mes7[[#This Row],[CUIT]]="","-",VLOOKUP(Retenciones_mes7[[#This Row],[CUIT]],Lista_CUIT[#All],2,0)),"CUIT NO CARGADO") -> -
G96: =IFERROR(IF(Retenciones_mes7[[#This Row],[CUIT]]="","-",VLOOKUP(Retenciones_mes7[[#This Row],[CUIT]],Lista_CUIT[#All],2,0)),"CUIT NO CARGADO") -> -
G97: =IFERROR(IF(Retenciones_mes7[[#This Row],[CUIT]]="","-",VLOOKUP(Retenciones_mes7[[#This Row],[CUIT]],Lista_CUIT[#All],2,0)),"CUIT NO CARGADO") -> -

Sheet Ago-24
B1: LIBRO IVA COMPRAS | G1: ='Ene-24'!G1:M1 -> RABLEB SRL | N1: =EDATE('Ene-24'!N1,7) -> 45505
B3: TOTAL COMPRAS | G3: TOTAL CREDITO FISCAL | J3: TOTAL VENTAS NETAS | M3: TOTAL DEBITO FISCAL | P3: RESULTADO
B4: =SUM(compras_mes8[[#Totals],[NETO GRAVADO]])+extracto_banco_mes8[[#Totals],[NETO]] -> 2617487.5 | G4: =compras_mes8[[#Totals],[IVA 21 %]]+compras_mes8[[#Totals],[IVA 27%]]+compras_mes8[[#Totals],[IVA 10,5%]]+extracto_banco_mes8[[#Totals],[IVA 21%]]+extracto_banco_mes8[[#Totals],[IVA 10,5%]] -> 549672.37 | J4: =venta_a_mes8[[#Totals],[IMPORTE NETO]]+ventas_b_mes8[[#Totals],[IMPORTE NETO]] -> 4939289.2 | M4: =venta_a_mes8[[#Totals],[IVA 21%]]+venta_a_mes8[[#Totals],[IVA 10,5%]]+ventas_b_mes8[[#Totals],[IVA 21%]]+ventas_b_mes8[[#Totals],[IVA 10,5%]] -> 1037250.7 | P4: =G4-M4 -> -487578.37
B8: FECHA | C8: TIPO | D8: PTO VTA | E8: NRO. CPTE | F8: CUIT | G8: RAZON SOCIAL | H8: NETO GRAVADO | I8: IVA 21 % | J8: IVA 27% | K8: IVA 10,5% | L8: PERC. IVA | M8: PERC IIBB BS AS | N8: PERC. IIBB CABA | O8: Otros / No Grav. | P8: TOTAL | Q8: Tipo de Gasto | R8: Provincia
B9: 45535 | C9: 3 | D9: 11 | E9: 749565 | F9: 33709585229 | G9: =IFERROR(IF(compras_mes8[[#This Row],[CUIT]]="","-",VLOOKUP(compras_mes8[[#This Row],[CUIT]],Lista_CUIT[#All],2,0)),"CUIT NO CARGADO") -> GOOGLE ARGENTINA S.R.L. | H9: -2966.06 | I9: =IF(compras_mes8[[#This Row],[NETO GRAVADO]]="","",compras_mes8[[#This Row],[NETO GRAVADO]]*0.21) -> -622.8726 | L9: -88.98 | N9: -44.49 | P9: =SUM(compras_mes8[[#This Row],[NETO GRAVADO]:[Otros / No Grav.]]) -> -3722.4026 | Q9: =IFERROR(IF(compras_mes8[[#This Row],[CUIT]]="","-",VLOOKUP(compras_mes8[[#This Row],[CUIT]],Lista_CUIT[#All],3,0)),"CUIT NO CARGADO") -> Gastos Publicidad y Propaganda | R9: =IFERROR(IF(compras_mes8[[#This Row],[CUIT]]="","-",VLOOKUP(compras_mes8[[#This Row],[CUIT]],Lista_CUIT[#All],4,0)),"CUIT NO CARGADO") -> 0
B10: 45535 | C10: 3 | D10: 11 | E10: 750212 | F10: 33709585229 | G10: =IFERROR(IF(compras_mes8[[#This Row],[CUIT]]="","-",VLOOKUP(compras_mes8[[#This Row],[CUIT]],Lista_CUIT[#All],2,0)),"CUIT NO CARGADO") -> GOOGLE ARGENTINA S.R.L. | H10: -81.66 | I10: =IF(compras_mes8[[#This Row],[NETO GRAVADO]]="","",compras_mes8[[#This Row],[NETO GRAVADO]]*0.21) -> -17.1486 | P10: =SUM(compras_mes8[[#This Row],[NETO GRAVADO]:[Otros / No Grav.]]) -> -98.8086 | Q10: =IFERROR(IF(compras_mes8[[#This Row],[CUIT]]="","-",VLOOKUP(compras_mes8[[#This Row],[CUIT]],Lista_CUIT[#All],3,0)),"CUIT NO CARGADO") -> Gastos Publicidad y Propaganda | R10: =IFERROR(IF(compras_mes8[[#This Row],[CUIT]]="","-",VLOOKUP(compras_mes8[[#This Row],[CUIT]],Lista_CUIT[#All],4,0)),"CUIT NO CARGADO") -> 0
B11: 45535 | C11: 3 | D11: 11 | E11: 753903 | F11: 33709585229 | G11: =IFERROR(IF(compras_mes8[[#This Row],[CUIT]]="","-",VLOOKUP(compras_mes8[[#This Row],[CUIT]],Lista_CUIT[#All],2,0)),"CUIT NO CARGADO") -> GOOGLE ARGENTINA S.R.L. | H11: -665.39 | I11: =IF(compras_mes8[[#This Row],[NETO GRAVADO]]="","",compras_mes8[[#This Row],[NETO GRAVADO]]*0.21) -> -139.7319 | N11: -9.98 | P11: =SUM(compras_mes8[[#This Row],[NETO GRAVADO]:[Otros / No Grav.]]) -> -815.1019 | Q11: =IFERROR(IF(compras_mes8[[#This Row],[CUIT]]="","-",VLOOKUP(compras_mes8[[#This Row],[CUIT]],Lista_CUIT[#All],3,0)),"CUIT NO CARGADO") -> Gastos Publicidad y Propaganda | R11: =IFERROR(IF(compras_mes8[[#This Row],[CUIT]]="","-",VLOOKUP(compras_mes8[[#This Row],[CUIT]],Lista_CUIT[#All],4,0)),"CUIT NO CARGADO") -> 0
B12: 45535 | C12: 1 | D12: 11 | E12: 1028597 | F12: 33709585229 | G12: =IFERROR(IF(compras_mes8[[#This Row],[CUIT]]="","-",VLOOKUP(compras_mes8[[#This Row],[CUIT]],Lista_CUIT[#All],2,0)),"CUIT NO CARGADO") -> GOOGLE ARGENTINA S.R.L. | H12: 51387.95 | I12: =IF(compras_mes8[[#This Row],[NETO GRAVADO]]="","",compras_mes8[[#This Row],[NETO GRAVADO]]*0.21) -> 10791.469 | L12: 1541.64 | N12: 770.82 | P12: =SUM(compras_mes8[[#This Row],[NETO GRAVADO]:[Otros / No Grav.]]) -> 64491.879 | Q12: =IFERROR(IF(compras_mes8[[#This Row],[CUIT]]="","-",VLOOKUP(compras_mes8[[#This Row],[CUIT]],Lista_CUIT[#All],3,0)),"CUIT NO CARGADO") -> Gastos Publicidad y Propaganda | R12: =IFERROR(IF(compras_mes8[[#This Row],[CUIT]]="","-",VLOOKUP(compras_mes8[[#This Row],[CUIT]],Lista_CUIT[#All],4,0)),"CUIT NO CARGADO") -> 0
B13: 45535 | C13: 1 | D13: 11 | E13: 1029271 | F13: 33709585229 | G13: =IFERROR(IF(compras_mes8[[#This Row],[CUIT]]="","-",VLOOKUP(compras_mes8[[#This Row],[CUIT]],Lista_CUIT[#All],2,0)),"CUIT NO CARGADO") -> GOOGLE ARGENTINA S.R.L. | H13: 1535345.3 | I13: =IF(compras_mes8[[#This Row],[NETO GRAVADO]]="","",compras_mes8[[#This Row],[NETO GRAVADO]]*0.21) -> 322422.51 | L13: 46060.36 | N13: 23030.18 | P13: =SUM(compras_mes8[[#This Row],[NETO GRAVADO]:[Otros / No Grav.]]) -> 1926858.3 | Q13: =IFERROR(IF(compras_mes8[[#This Row],[CUIT]]="","-",VLOOKUP(compras_mes8[[#This Row],[CUIT]],Lista_CUIT[#All],3,0)),"CUIT NO CARGADO") -> Gastos Publicidad y Propaganda | R13: =IFERROR(IF(compras_mes8[[#This Row],[CUIT]]="","-",VLOOKUP(compras_mes8[[#This Row],[CUIT]],Lista_CUIT[#All],4,0)),"CUIT NO CARGADO") -> 0
B14: 45535 | C14: 1 | D14: 11 | E14: 1029549 | F14: 33709585229 | G14: =IFERROR(IF(compras_mes8[[#This Row],[CUIT]]="","-",VLOOKUP(compras_mes8[[#This Row],[CUIT]],Lista_CUIT[#All],2,0)),"CUIT NO CARGADO") -> GOOGLE ARGENTINA S.R.L. | H14: 44276.94 | I14: =IF(compras_mes8[[#This Row],[NETO GRAVADO]]="","",compras_mes8[[#This Row],[NETO GRAVADO]]*0.21) -> 9298.1574 | L14: 1328.31 | N14: 664.15 | P14: =SUM(compras_mes8[[#This Row],[NETO GRAVADO]:[Otros / No Grav.]]) -> 55567.557 | Q14: =IFERROR(IF(compras_mes8[[#This Row],[CUIT]]="","-",VLOOKUP(compras_mes8[[#This Row],[CUIT]],Lista_CUIT[#All],3,0)),"CUIT NO CARGADO") -> Gastos Publicidad y Propaganda | R14: =IFERROR(IF(compras_mes8[[#This Row],[CUIT]]="","-",VLOOKUP(compras_mes8[[#This Row],[CUIT]],Lista_CUIT[#All],4,0)),"CUIT NO CARGADO") -> 0
B15: 45535 | C15: 1 | D15: 11 | E15: 1030118 | F15: 33709585229 | G15: =IFERROR(IF(compras_mes8[[#This Row],[CUIT]]="","-",VLOOKUP(compras_mes8[[#This Row],[CUIT]],Lista_CUIT[#All],2,0)),"CUIT NO CARGADO") -> GOOGLE ARGENTINA S.R.L. | H15: 396877.22 | I15: =IF(compras_mes8[[#This Row],[NETO GRAVADO]]="","",compras_mes8[[#This Row],[NETO GRAVADO]]*0.21) -> 83344.216 | L15: 11906.32 | N15: 5953.16 | P15: =SUM(compras_mes8[[#This Row],[NETO GRAVADO]:[Otros / No Grav.]]) -> 498080.92 | Q15: =IFERROR(IF(compras_mes8[[#This Row],[CUIT]]="","-",VLOOKUP(compras_mes8[[#This Row],[CUIT]],Lista_CUIT[#All],3,0)),"CUIT NO CARGADO") -> Gastos Publicidad y Propaganda | R15: =IFERROR(IF(compras_mes8[[#This Row],[CUIT]]="","-",VLOOKUP(compras_mes8[[#This Row],[CUIT]],Lista_CUIT[#All],4,0)),"CUIT NO CARGADO") -> 0
B16: 45535 | C16: 1 | D16: 11 | E16: 1032507 | F16: 33709585229 | G16: =IFERROR(IF(compras_mes8[[#This Row],[CUIT]]="","-",VLOOKUP(compras_mes8[[#This Row],[CUIT]],Lista_CUIT[#All],2,0)),"CUIT NO CARGADO") -> GOOGLE ARGENTINA S.R.L. | H16: 178584.58 | I16: =IF(compras_mes8[[#This Row],[NETO GRAVADO]]="","",compras_mes8[[#This Row],[NETO GRAVADO]]*0.21) -> 37502.762 | L16: 5357.54 | N16: 2678.77 | P16: =SUM(compras_mes8[[#This Row],[NETO GRAVADO]:[Otros / No Grav.]]) -> 224123.65 | Q16: =IFERROR(IF(compras_mes8[[#This Row],[CUIT]]="","-",VLOOKUP(compras_mes8[[#This Row],[CUIT]],Lista_CUIT[#All],3,0)),"CUIT NO CARGADO") -> Gastos Publicidad y Propaganda | R16: =IFERROR(IF(compras_mes8[[#This Row],[CUIT]]="","-",VLOOKUP(compras_mes8[[#This Row],[CUIT]],Lista_CUIT[#All],4,0)),"CUIT NO CARGADO") -> 0
B17: 45535 | C17: 1 | D17: 11 | E17: 1036627 | F17: 33709585229 | G17: =IFERROR(IF(compras_mes8[[#This Row],[CUIT]]="","-",VLOOKUP(compras_mes8[[#This Row],[CUIT]],Lista_CUIT[#All],2,0)),"CUIT NO CARGADO") -> GOOGLE ARGENTINA S.R.L. | H17: 60580.29 | I17: =IF(compras_mes8[[#This Row],[NETO GRAVADO]]="","",compras_mes8[[#This Row],[NETO GRAVADO]]*0.21) -> 12721.861 | L17: 1817.41 | N17: 908.7 | P17: =SUM(compras_mes8[[#This Row],[NETO GRAVADO]:[Otros / No Grav.]]) -> 76028.261 | Q17: =IFERROR(IF(compras_mes8[[#This Row],[CUIT]]="","-",VLOOKUP(compras_mes8[[#This Row],[CUIT]],Lista_CUIT[#All],3,0)),"CUIT NO CARGADO") -> Gastos Publicidad y Propaganda | R17: =IFERROR(IF(compras_mes8[[#This Row],[CUIT]]="","-",VLOOKUP(compras_mes8[[#This Row],[CUIT]],Lista_CUIT[#All],4,0)),"CUIT NO CARGADO") -> 0
B18: 45535 | C18: 1 | D18: 11 | E18: 1036913 | F18: 33709585229 | G18: =IFERROR(IF(compras_mes8[[#This Row],[CUIT]]="","-",VLOOKUP(compras_mes8[[#This Row],[CUIT]],Lista_CUIT[#All],2,0)),"CUIT NO CARGADO") -> GOOGLE ARGENTINA S.R.L. | H18: 325798.3 | I18: =IF(compras_mes8[[#This Row],[NETO GRAVADO]]="","",compras_mes8[[#This Row],[NETO GRAVADO]]*0.21) -> 68417.643 | L18: 9773.95 | N18: 4886.97 | P18: =SUM(compras_mes8[[#This Row],[NETO GRAVADO]:[Otros / No Grav.]]) -> 408876.86 | Q18: =IFERROR(IF(compras_mes8[[#This Row],[CUIT]]="","-",VLOOKUP(compras_mes8[[#This Row],[CUIT]],Lista_CUIT[#All],3,0)),"CUIT NO CARGADO") -> Gastos Publicidad y Propaganda | R18: =IFERROR(IF(compras_mes8[[#This Row],[CUIT]]="","-",VLOOKUP(compras_mes8[[#This Row],[CUIT]],Lista_CUIT[#All],4,0)),"CUIT NO CARGADO") -> 0
G19: =IFERROR(IF(compras_mes8[[#This Row],[CUIT]]="","-",VLOOKUP(compras_mes8[[#This Row],[CUIT]],Lista_CUIT[#All],2,0)),"CUIT NO CARGADO") -> - | I19: =IF(compras_mes8[[#This Row],[NETO GRAVADO]]="","",compras_mes8[[#This Row],[NETO GRAVADO]]*0.21) | P19: =SUM(compras_mes8[[#This Row],[NETO GRAVADO]:[Otros / No Grav.]]) -> 0 | Q19: =IFERROR(IF(compras_mes8[[#This Row],[CUIT]]="","-",VLOOKUP(compras_mes8[[#This Row],[CUIT]],Lista_CUIT[#All],3,0)),"CUIT NO CARGADO") -> - | R19: =IFERROR(IF(compras_mes8[[#This Row],[CUIT]]="","-",VLOOKUP(compras_mes8[[#This Row],[CUIT]],Lista_CUIT[#All],4,0)),"CUIT NO CARGADO") -> -
G20: =IFERROR(IF(compras_mes8[[#This Row],[CUIT]]="","-",VLOOKUP(compras_mes8[[#This Row],[CUIT]],Lista_CUIT[#All],2,0)),"CUIT NO CARGADO") -> - | I20: =IF(compras_mes8[[#This Row],[NETO GRAVADO]]="","",compras_mes8[[#This Row],[NETO GRAVADO]]*0.21) | P20: =SUM(compras_mes8[[#This Row],[NETO GRAVADO]:[Otros / No Grav.]]) -> 0 | Q20: =IFERROR(IF(compras_mes8[[#This Row],[CUIT]]="","-",VLOOKUP(compras_mes8[[#This Row],[CUIT]],Lista_CUIT[#All],3,0)),"CUIT NO CARGADO") -> - | R20: =IFERROR(IF(compras_mes8[[#This Row],[CUIT]]="","-",VLOOKUP(compras_mes8[[#This Row],[CUIT]],Lista_CUIT[#All],4,0)),"CUIT NO CARGADO") -> -
G21: =IFERROR(IF(compras_mes8[[#This Row],[CUIT]]="","-",VLOOKUP(compras_mes8[[#This Row],[CUIT]],Lista_CUIT[#All],2,0)),"CUIT NO CARGADO") -> - | I21: =IF(compras_mes8[[#This Row],[NETO GRAVADO]]="","",compras_mes8[[#This Row],[NETO GRAVADO]]*0.21) | P21: =SUM(compras_mes8[[#This Row],[NETO GRAVADO]:[Otros / No Grav.]]) -> 0 | Q21: =IFERROR(IF(compras_mes8[[#This Row],[CUIT]]="","-",VLOOKUP(compras_mes8[[#This Row],[CUIT]],Lista_CUIT[#All],3,0)),"CUIT NO CARGADO") -> - | R21: =IFERROR(IF(compras_mes8[[#This Row],[CUIT]]="","-",VLOOKUP(compras_mes8[[#This Row],[CUIT]],Lista_CUIT[#All],4,0)),"CUIT NO CARGADO") -> -
G22: =IFERROR(IF(compras_mes8[[#This Row],[CUIT]]="","-",VLOOKUP(compras_mes8[[#This Row],[CUIT]],Lista_CUIT[#All],2,0)),"CUIT NO CARGADO") -> - | I22: =IF(compras_mes8[[#This Row],[NETO GRAVADO]]="","",compras_mes8[[#This Row],[NETO GRAVADO]]*0.21) | P22: =SUM(compras_mes8[[#This Row],[NETO GRAVADO]:[Otros / No Grav.]]) -> 0 | Q22: =IFERROR(IF(compras_mes8[[#This Row],[CUIT]]="","-",VLOOKUP(compras_mes8[[#This Row],[CUIT]],Lista_CUIT[#All],3,0)),"CUIT NO CARGADO") -> - | R22: =IFERROR(IF(compras_mes8[[#This Row],[CUIT]]="","-",VLOOKUP(compras_mes8[[#This Row],[CUIT]],Lista_CUIT[#All],4,0)),"CUIT NO CARGADO") -> -
B23: Total | H23: =SUBTOTAL(109,compras_mes8[NETO GRAVADO]) -> 2589137.5 | I23: =SUBTOTAL(109,compras_mes8[IVA 21 %]) -> 543718.87 | J23: =SUBTOTAL(109,compras_mes8[IVA 27%]) -> 0 | K23: =SUBTOTAL(109,compras_mes8[IVA 10,5%]) -> 0 | L23: =SUBTOTAL(109,compras_mes8[PERC. IVA]) -> 77696.55 | M23: =SUBTOTAL(109,compras_mes8[PERC IIBB BS AS]) -> 0 | N23: =SUBTOTAL(109,compras_mes8[PERC. IIBB CABA]) -> 38838.28 | O23: =SUBTOTAL(109,compras_mes8[Otros / No Grav.]) -> 0 | P23: =SUBTOTAL(109,compras_mes8[TOTAL]) -> 3249391.2
D28: LIQUIDACION EXTRACTOS BANCARIOS-TARJETAS
D29: FECHA | E29: NRO CPTE | F29: BANCO | G29: NETO | H29: IVA 21% | I29: IVA 10,5% | J29: RET IIBB CABA | K29: PERC IVA | L29: PERC IIBB
F30: GALICIA | G30: 28350 | H30: =extracto_banco_mes8[[#This Row],[NETO]]*0.21 -> 5953.5 | K30: 850.5 | L30: 425.25
D33: Total | G33: =SUBTOTAL(109,extracto_banco_mes8[NETO]) -> 28350 | H33: =SUBTOTAL(109,extracto_banco_mes8[IVA 21%]) -> 5953.5 | I33: =SUBTOTAL(109,extracto_banco_mes8[IVA 10,5%]) -> 0 | J33: =SUBTOTAL(109,extracto_banco_mes8[RET IIBB CABA]) -> 0 | K33: =SUBTOTAL(109,extracto_banco_mes8[PERC IVA]) -> 850.5 | L33: =SUBTOTAL(109,extracto_banco_mes8[PERC IIBB]) -> 425.25
D37: FACTURAS C
D38: FECHA | E38: PTO VTA | F38: FC Nº | G38: CUIT | H38: RAZON SOCIAL | I38: TOTAL | J38: TIPO DE GASTO | K38: Provincia
D39: 45509 | E39: 2 | F39: 820 | G39: 20400104094 | H39: =IFERROR(IF(factura_c_mes8[[#This Row],[CUIT]]="","-",VLOOKUP(factura_c_mes8[[#This Row],[CUIT]],Lista_CUIT[#All],2,0)),"CUIT NO CARGADO") -> BOTINDARI FEDERICO DANIEL | I39: 80000 | J39: =IFERROR(IF(factura_c_mes8[[#This Row],[CUIT]]="","-",VLOOKUP(factura_c_mes8[[#This Row],[CUIT]],Lista_CUIT[#All],3,0)),"CUIT NO CARGADO") -> HONORARIOS CONTABLE | K39: =IFERROR(IF(factura_c_mes8[[#This Row],[CUIT]]="","-",VLOOKUP(factura_c_mes8[[#This Row],[CUIT]],Lista_CUIT[#All],4,0)),"CUIT NO CARGADO") -> 0
D40: 45511 | E40: 2 | F40: 45 | G40: 23380288079 | H40: =IFERROR(IF(factura_c_mes8[[#This Row],[CUIT]]="","-",VLOOKUP(factura_c_mes8[[#This Row],[CUIT]],Lista_CUIT[#All],2,0)),"CUIT NO CARGADO") -> CASTROMAN AGUSTIN | I40: 165477 | J40: =IFERROR(IF(factura_c_mes8[[#This Row],[CUIT]]="","-",VLOOKUP(factura_c_mes8[[#This Row],[CUIT]],Lista_CUIT[#All],3,0)),"CUIT NO CARGADO") -> Diseño Grafico | K40: =IFERROR(IF(factura_c_mes8[[#This Row],[CUIT]]="","-",VLOOKUP(factura_c_mes8[[#This Row],[CUIT]],Lista_CUIT[#All],4,0)),"CUIT NO CARGADO") -> 0
D41: 45512 | E41: 1 | F41: 284 | G41: 20347443787 | H41: =IFERROR(IF(factura_c_mes8[[#This Row],[CUIT]]="","-",VLOOKUP(factura_c_mes8[[#This Row],[CUIT]],Lista_CUIT[#All],2,0)),"CUIT NO CARGADO") -> YAÑEZ GERMAN | I41: 119755 | J41: =IFERROR(IF(factura_c_mes8[[#This Row],[CUIT]]="","-",VLOOKUP(factura_c_mes8[[#This Row],[CUIT]],Lista_CUIT[#All],3,0)),"CUIT NO CARGADO") -> 0 | K41: =IFERROR(IF(factura_c_mes8[[#This Row],[CUIT]]="","-",VLOOKUP(factura_c_mes8[[#This Row],[CUIT]],Lista_CUIT[#All],4,0)),"CUIT NO CARGADO") -> 0
D42: 45530 | E42: 1 | F42: 306 | G42: 27386311000 | H42: =IFERROR(IF(factura_c_mes8[[#This Row],[CUIT]]="","-",VLOOKUP(factura_c_mes8[[#This Row],[CUIT]],Lista_CUIT[#All],2,0)),"CUIT NO CARGADO") -> OPANASIUK MACARENA ANTONELLA | I42: 450000 | J42: =IFERROR(IF(factura_c_mes8[[#This Row],[CUIT]]="","-",VLOOKUP(factura_c_mes8[[#This Row],[CUIT]],Lista_CUIT[#All],3,0)),"CUIT NO CARGADO") -> Honorarios Profesionales | K42: =IFERROR(IF(factura_c_mes8[[#This Row],[CUIT]]="","-",VLOOKUP(factura_c_mes8[[#This Row],[CUIT]],Lista_CUIT[#All],4,0)),"CUIT NO CARGADO") -> 0
D43: Total | I43: =SUBTOTAL(109,factura_c_mes8[TOTAL]) -> 815232
B49: LIBRO IVA VENTAS | K49: =N1 -> 45505
B51: VENTAS "A"
B52: FECHA | C52: TIPO | D52: PTO VENTA | E52: Nº FACTURA | F52: CUIT | G52: RAZON SOCIAL | H52: IMPORTE NETO | I52: IVA 21% | J52: IVA 10,5% | K52: EXENTO | L52: TOTAL | M52: Provincia
B53: 45505 | C53: 1 | D53: 1 | E53: 244 | F53: 20279415656 | G53: =IFERROR(IF(venta_a_mes8[[#This Row],[CUIT]]="","-",VLOOKUP(venta_a_mes8[[#This Row],[CUIT]],Lista_CUIT[#All],2,0)),"CUIT NO CARGADO") -> CECCO ALVARO GONZALO | H53: 94214.86 | I53: =venta_a_mes8[[#This Row],[IMPORTE NETO]]*0.21 -> 19785.121 | L53: =SUM(venta_a_mes8[[#This Row],[IMPORTE NETO]:[EXENTO]]) -> 113999.98
B54: 45505 | C54: 1 | D54: 1 | E54: 255 | F54: 33717319309 | G54: =IFERROR(IF(venta_a_mes8[[#This Row],[CUIT]]="","-",VLOOKUP(venta_a_mes8[[#This Row],[CUIT]],Lista_CUIT[#All],2,0)),"CUIT NO CARGADO") -> CONSMITEC S.R.L. | H54: 390909.1 | I54: =venta_a_mes8[[#This Row],[IMPORTE NETO]]*0.21 -> 82090.911 | L54: =SUM(venta_a_mes8[[#This Row],[IMPORTE NETO]:[EXENTO]]) -> 473000.01
B55: 45505 | C55: 1 | D55: 1 | E55: 245 | F55: 20367341808 | G55: =IFERROR(IF(venta_a_mes8[[#This Row],[CUIT]]="","-",VLOOKUP(venta_a_mes8[[#This Row],[CUIT]],Lista_CUIT[#All],2,0)),"CUIT NO CARGADO") -> FEIDAS FERNANDO EMILIANO | H55: 58677.67 | I55: =venta_a_mes8[[#This Row],[IMPORTE NETO]]*0.21 -> 12322.311 | L55: =SUM(venta_a_mes8[[#This Row],[IMPORTE NETO]:[EXENTO]]) -> 70999.981
B56: 45505 | C56: 1 | D56: 1 | E56: 246 | F56: 30715941763 | G56: =IFERROR(IF(venta_a_mes8[[#This Row],[CUIT]]="","-",VLOOKUP(venta_a_mes8[[#This Row],[CUIT]],Lista_CUIT[#All],2,0)),"CUIT NO CARGADO") -> TOURMALHYN S.R.L. | H56: 30578.52 | I56: =venta_a_mes8[[#This Row],[IMPORTE NETO]]*0.21 -> 6421.4892 | L56: =SUM(venta_a_mes8[[#This Row],[IMPORTE NETO]:[EXENTO]]) -> 37000.009
B57: 45505 | C57: 1 | D57: 1 | E57: 247 | F57: 30717465101 | G57: =IFERROR(IF(venta_a_mes8[[#This Row],[CUIT]]="","-",VLOOKUP(venta_a_mes8[[#This Row],[CUIT]],Lista_CUIT[#All],2,0)),"CUIT NO CARGADO") -> EMPRENDIMIENTOS SHOPGLASS S. R. L. | H57: 58677.67 | I57: =venta_a_mes8[[#This Row],[IMPORTE NETO]]*0.21 -> 12322.311 | L57: =SUM(venta_a_mes8[[#This Row],[IMPORTE NETO]:[EXENTO]]) -> 70999.981
B58: 45505 | C58: 1 | D58: 1 | E58: 256 | F58: 30715380567 | G58: =IFERROR(IF(venta_a_mes8[[#This Row],[CUIT]]="","-",VLOOKUP(venta_a_mes8[[#This Row],[CUIT]],Lista_CUIT[#All],2,0)),"CUIT NO CARGADO") -> SENS GROUP SRL | H58: 253338.67 | I58: =venta_a_mes8[[#This Row],[IMPORTE NETO]]*0.21 -> 53201.121 | L58: =SUM(venta_a_mes8[[#This Row],[IMPORTE NETO]:[EXENTO]]) -> 306539.79
B59: 45505 | C59: 1 | D59: 1 | E59: 257 | F59: 33715154809 | G59: =IFERROR(IF(venta_a_mes8[[#This Row],[CUIT]]="","-",VLOOKUP(venta_a_mes8[[#This Row],[CUIT]],Lista_CUIT[#All],2,0)),"CUIT NO CARGADO") -> SUPERMERCADOS BONANNO S.A. | H59: 428099.19 | I59: =venta_a_mes8[[#This Row],[IMPORTE NETO]]*0.21 -> 89900.83 | L59: =SUM(venta_a_mes8[[#This Row],[IMPORTE NETO]:[EXENTO]]) -> 518000.02
B60: 45505 | C60: 1 | D60: 1 | E60: 248 | F60: 20132082198 | G60: =IFERROR(IF(venta_a_mes8[[#This Row],[CUIT]]="","-",VLOOKUP(venta_a_mes8[[#This Row],[CUIT]],Lista_CUIT[#All],2,0)),"CUIT NO CARGADO") -> FADIGA OSCAR ALBERTO | H60: 113223.14 | I60: =venta_a_mes8[[#This Row],[IMPORTE NETO]]*0.21 -> 23776.859 | L60: =SUM(venta_a_mes8[[#This Row],[IMPORTE NETO]:[EXENTO]]) -> 137000
B61: 45505 | C61: 1 | D61: 1 | E61: 249 | F61: 30688955749 | G61: =IFERROR(IF(venta_a_mes8[[#This Row],[CUIT]]="","-",VLOOKUP(venta_a_mes8[[#This Row],[CUIT]],Lista_CUIT[#All],2,0)),"CUIT NO CARGADO") -> LISERAR S A | H61: 132231.43 | I61: =venta_a_mes8[[#This Row],[IMPORTE NETO]]*0.21 -> 27768.6 | L61: =SUM(venta_a_mes8[[#This Row],[IMPORTE NETO]:[EXENTO]]) -> 160000.03
B62: 45505 | C62: 1 | D62: 1 | E62: 239 | F62: 30716549107 | G62: =IFERROR(IF(venta_a_mes8[[#This Row],[CUIT]]="","-",VLOOKUP(venta_a_mes8[[#This Row],[CUIT]],Lista_CUIT[#All],2,0)),"CUIT NO CARGADO") -> LAMATEC S.R.L. | H62: 132231.43 | I62: =venta_a_mes8[[#This Row],[IMPORTE NETO]]*0.21 -> 27768.6 | L62: =SUM(venta_a_mes8[[#This Row],[IMPORTE NETO]:[EXENTO]]) -> 160000.03
B63: 45505 | C63: 1 | D63: 1 | E63: 250 | F63: 30716234815 | G63: =IFERROR(IF(venta_a_mes8[[#This Row],[CUIT]]="","-",VLOOKUP(venta_a_mes8[[#This Row],[CUIT]],Lista_CUIT[#All],2,0)),"CUIT NO CARGADO") -> LEVINT PARTNERS S.R.L. | H63: 132231.43 | I63: =venta_a_mes8[[#This Row],[IMPORTE NETO]]*0.21 -> 27768.6 | L63: =SUM(venta_a_mes8[[#This Row],[IMPORTE NETO]:[EXENTO]]) -> 160000.03
B64: 45505 | C64: 1 | D64: 1 | E64: 240 | F64: 30718295900 | G64: =IFERROR(IF(venta_a_mes8[[#This Row],[CUIT]]="","-",VLOOKUP(venta_a_mes8[[#This Row],[CUIT]],Lista_CUIT[#All],2,0)),"CUIT NO CARGADO") -> LAPTOP SERVICE S.R.L. | H64: 58677.67 | I64: =venta_a_mes8[[#This Row],[IMPORTE NETO]]*0.21 -> 12322.311 | L64: =SUM(venta_a_mes8[[#This Row],[IMPORTE NETO]:[EXENTO]]) -> 70999.981
... B75: 45530 | C75: 1 | D75: 1 | E75: 260 | F75: 30715438360 | G75: =IFERROR(IF(venta_a_mes8[[#This Row],[CUIT]]="","-",VLOOKUP(venta_a_mes8[[#This Row],[CUIT]],Lista_CUIT[#All],2,0)),"CUIT NO CARGADO") -> ERMAN CUSTODIAR S.A. | H75: 758677.71 | I75: =venta_a_mes8[[#This Row],[IMPORTE NETO]]*0.21 -> 159322.32 | L75: =SUM(venta_a_mes8[[#This Row],[IMPORTE NETO]:[EXENTO]]) -> 918000.03
B76: Total | H76: =SUBTOTAL(109,venta_a_mes8[IMPORTE NETO]) -> 4697140.4 | I76: =SUBTOTAL(109,venta_a_mes8[IVA 21%]) -> 986399.49 | J76: =SUBTOTAL(109,venta_a_mes8[IVA 10,5%]) -> 0 | K76: =SUBTOTAL(109,venta_a_mes8[EXENTO]) -> 0 | L76: =SUBTOTAL(109,venta_a_mes8[TOTAL]) -> 5683539.9 | M76: =SUBTOTAL(103,venta_a_mes8[Provincia]) -> 0
B79: VENTAS "B"
B80: FECHA | C80: TIPO | D80: PTO VENTA | E80: Nº FACTURA | F80: CUIT | G80: RAZON SOCIAL | H80: IMPORTE NETO | I80: IVA 21% | J80: IVA 10,5% | K80: EXENTO | L80: TOTAL | M80: Provincia
B81: 45505 | C81: 6 | D81: 1 | E81: 41 | F81: 30592508830 | G81: =IFERROR(IF(ventas_b_mes8[[#This Row],[CUIT]]="","-",VLOOKUP(ventas_b_mes8[[#This Row],[CUIT]],Lista_CUIT[#All],2,0)),"CUIT NO CARGADO") -> INSTITUTO DE ESTUDIOS SUPERIORES DE BUENOS AIRES S A | H81: 51239.67 | I81: =ventas_b_mes8[[#This Row],[IMPORTE NETO]]*0.21 -> 10760.331 | L81: =SUM(ventas_b_mes8[[#This Row],[IMPORTE NETO]:[EXENTO]]) -> 62000.001
B82: 45505 | C82: 6 | D82: 1 | E82: 42 | F82: 20252582704 | G82: =IFERROR(IF(ventas_b_mes8[[#This Row],[CUIT]]="","-",VLOOKUP(ventas_b_mes8[[#This Row],[CUIT]],Lista_CUIT[#All],2,0)),"CUIT NO CARGADO") -> GARCIA VAUTRIN ANDRES ALBERTO | H82: 190909.1 | I82: =ventas_b_mes8[[#This Row],[IMPORTE NETO]]*0.21 -> 40090.911 | L82: =SUM(ventas_b_mes8[[#This Row],[IMPORTE NETO]:[EXENTO]]) -> 231000.01
G83: =IFERROR(IF(ventas_b_mes8[[#This Row],[CUIT]]="","-",VLOOKUP(ventas_b_mes8[[#This Row],[CUIT]],Lista_CUIT[#All],2,0)),"CUIT NO CARGADO") -> - | I83: =ventas_b_mes8[[#This Row],[IMPORTE NETO]]*0.21 -> 0 | L83: =SUM(ventas_b_mes8[[#This Row],[IMPORTE NETO]:[EXENTO]]) -> 0
G84: =IFERROR(IF(ventas_b_mes8[[#This Row],[CUIT]]="","-",VLOOKUP(ventas_b_mes8[[#This Row],[CUIT]],Lista_CUIT[#All],2,0)),"CUIT NO CARGADO") -> - | I84: =ventas_b_mes8[[#This Row],[IMPORTE NETO]]*0.21 -> 0 | L84: =SUM(ventas_b_mes8[[#This Row],[IMPORTE NETO]:[EXENTO]]) -> 0
B85: Total | H85: =SUBTOTAL(109,ventas_b_mes8[IMPORTE NETO]) -> 242148.77 | I85: =SUBTOTAL(109,ventas_b_mes8[IVA 21%]) -> 50851.242 | J85: =SUBTOTAL(109,ventas_b_mes8[IVA 10,5%]) -> 0 | K85: =SUBTOTAL(109,ventas_b_mes8[EXENTO]) -> 0 | L85: =SUBTOTAL(109,ventas_b_mes8[TOTAL]) -> 293000.01 | M85: =SUBTOTAL(103,ventas_b_mes8[Provincia]) -> 0
C93: RETENCIONES
C94: FECHA | D94: COMP Nº | E94: Columna1 | F94: CUIT | G94: RAZON SOCIAL | H94: Ganancias | I94: IVA | J94: SUSS | K94: IIBB BSAS | L94: IIBB CABA
G95: =IFERROR(IF(Retenciones_mes8[[#This Row],[CUIT]]="","-",VLOOKUP(Retenciones_mes8[[#This Row],[CUIT]],Lista_CUIT[#All],2,0)),"CUIT NO CARGADO") -> -
G96: =IFERROR(IF(Retenciones_mes8[[#This Row],[CUIT]]="","-",VLOOKUP(Retenciones_mes8[[#This Row],[CUIT]],Lista_CUIT[#All],2,0)),"CUIT NO CARGADO") -> -
G97: =IFERROR(IF(Retenciones_mes8[[#This Row],[CUIT]]="","-",VLOOKUP(Retenciones_mes8[[#This Row],[CUIT]],Lista_CUIT[#All],2,0)),"CUIT NO CARGADO") -> -
G98: =IFERROR(IF(Retenciones_mes8[[#This Row],[CUIT]]="","-",VLOOKUP(Retenciones_mes8[[#This Row],[CUIT]],Lista_CUIT[#All],2,0)),"CUIT NO CARGADO") -> -
G99: =IFERROR(IF(Retenciones_mes8[[#This Row],[CUIT]]="","-",VLOOKUP(Retenciones_mes8[[#This Row],[CUIT]],Lista_CUIT[#All],2,0)),"CUIT NO CARGADO") -> -

Sheet Sep-24
B1: LIBRO IVA COMPRAS | G1: ='Ene-24'!G1:M1 -> RABLEB SRL | N1: =EDATE('Ene-24'!N1,8) -> 45536
B3: TOTAL COMPRAS | G3: TOTAL CREDITO FISCAL | J3: TOTAL VENTAS NETAS | M3: TOTAL DEBITO FISCAL | P3: RESULTADO
B4: =SUM(compras_mes9[[#Totals],[NETO GRAVADO]])+extracto_banco_mes9[[#Totals],[NETO]] -> 2944317.5 | G4: =compras_mes9[[#Totals],[IVA 21 %]]+compras_mes9[[#Totals],[IVA 27%]]+compras_mes9[[#Totals],[IVA 10,5%]]+extracto_banco_mes9[[#Totals],[IVA 21%]]+extracto_banco_mes9[[#Totals],[IVA 10,5%]] -> 618306.68 | J4: =venta_a_mes9[[#Totals],[IMPORTE NETO]]+ventas_b_mes9[[#Totals],[IMPORTE NETO]] -> 4357663.4 | M4: =venta_a_mes9[[#Totals],[IVA 21%]]+venta_a_mes9[[#Totals],[IVA 10,5%]]+ventas_b_mes9[[#Totals],[IVA 21%]]+ventas_b_mes9[[#Totals],[IVA 10,5%]] -> 915109.32 | P4: =G4-M4 -> -296802.64
B8: FECHA | C8: TIPO | D8: PTO VTA | E8: NRO. CPTE | F8: CUIT | G8: RAZON SOCIAL | H8: NETO GRAVADO | I8: IVA 21 % | J8: IVA 27% | K8: IVA 10,5% | L8: PERC. IVA | M8: PERC IIBB BS AS | N8: PERC. IIBB CABA | O8: Otros / No Grav. | P8: TOTAL | Q8: Tipo de Gasto | R8: Provincia
B9: 22/09/2024 | C9: 1 | D9: 2 | E9: 1339026 | F9: 30710173652 | G9: =IFERROR(IF(compras_mes9[[#This Row],[CUIT]]="","-",VLOOKUP(compras_mes9[[#This Row],[CUIT]],Lista_CUIT[#All],2,0)),"CUIT NO CARGADO") -> DATTATEC.COM S.R.L. | H9: 23719.01 | I9: =IF(compras_mes9[[#This Row],[NETO GRAVADO]]="","",compras_mes9[[#This Row],[NETO GRAVADO]]*0.21) -> 4980.9921 | P9: =SUM(compras_mes9[[#This Row],[NETO GRAVADO]:[Otros / No Grav.]]) -> 28700.002 | Q9: =IFERROR(IF(compras_mes9[[#This Row],[CUIT]]="","-",VLOOKUP(compras_mes9[[#This Row],[CUIT]],Lista_CUIT[#All],3,0)),"CUIT NO CARGADO") -> Gastos Publicidad y Propaganda | R9: =IFERROR(IF(compras_mes9[[#This Row],[CUIT]]="","-",VLOOKUP(compras_mes9[[#This Row],[CUIT]],Lista_CUIT[#All],4,0)),"CUIT NO CARGADO") -> 0
B10: 30/09/2024 | C10: 1 | D10: 11 | E10: 1046644 | F10: 33709585229 | G10: =IFERROR(IF(compras_mes9[[#This Row],[CUIT]]="","-",VLOOKUP(compras_mes9[[#This Row],[CUIT]],Lista_CUIT[#All],2,0)),"CUIT NO CARGADO") -> GOOGLE ARGENTINA S.R.L. | H10: 54616.84 | I10: =IF(compras_mes9[[#This Row],[NETO GRAVADO]]="","",compras_mes9[[#This Row],[NETO GRAVADO]]*0.21) -> 11469.536 | N10: 819.25 | O10: 1638.51 | P10: =SUM(compras_mes9[[#This Row],[NETO GRAVADO]:[Otros / No Grav.]]) -> 68544.136 | Q10: =IFERROR(IF(compras_mes9[[#This Row],[CUIT]]="","-",VLOOKUP(compras_mes9[[#This Row],[CUIT]],Lista_CUIT[#All],3,0)),"CUIT NO CARGADO") -> Gastos Publicidad y Propaganda | R10: =IFERROR(IF(compras_mes9[[#This Row],[CUIT]]="","-",VLOOKUP(compras_mes9[[#This Row],[CUIT]],Lista_CUIT[#All],4,0)),"CUIT NO CARGADO") -> 0
B11: 30/09/2024 | C11: 1 | D11: 11 | E11: 1042488 | F11: 33709585229 | G11: =IFERROR(IF(compras_mes9[[#This Row],[CUIT]]="","-",VLOOKUP(compras_mes9[[#This Row],[CUIT]],Lista_CUIT[#All],2,0)),"CUIT NO CARGADO") -> GOOGLE ARGENTINA S.R.L. | H11: 137455.68 | I11: =IF(compras_mes9[[#This Row],[NETO GRAVADO]]="","",compras_mes9[[#This Row],[NETO GRAVADO]]*0.21) -> 28865.693 | N11: 2061.84 | O11: 4123.67 | P11: =SUM(compras_mes9[[#This Row],[NETO GRAVADO]:[Otros / No Grav.]]) -> 172506.88 | Q11: =IFERROR(IF(compras_mes9[[#This Row],[CUIT]]="","-",VLOOKUP(compras_mes9[[#This Row],[CUIT]],Lista_CUIT[#All],3,0)),"CUIT NO CARGADO") -> Gastos Publicidad y Propaganda | R11: =IFERROR(IF(compras_mes9[[#This Row],[CUIT]]="","-",VLOOKUP(compras_mes9[[#This Row],[CUIT]],Lista_CUIT[#All],4,0)),"CUIT NO CARGADO") -> 0
B12: 30/09/2024 | C12: 1 | D12: 11 | E12: 1050854 | F12: 33709585229 | G12: =IFERROR(IF(compras_mes9[[#This Row],[CUIT]]="","-",VLOOKUP(compras_mes9[[#This Row],[CUIT]],Lista_CUIT[#All],2,0)),"CUIT NO CARGADO") -> GOOGLE ARGENTINA S.R.L. | H12: 324880.23 | I12: =IF(compras_mes9[[#This Row],[NETO GRAVADO]]="","",compras_mes9[[#This Row],[NETO GRAVADO]]*0.21) -> 68224.848 | N12: 4873.2 | O12: 9746.41 | P12: =SUM(compras_mes9[[#This Row],[NETO GRAVADO]:[Otros / No Grav.]]) -> 407724.69 | Q12: =IFERROR(IF(compras_mes9[[#This Row],[CUIT]]="","-",VLOOKUP(compras_mes9[[#This Row],[CUIT]],Lista_CUIT[#All],3,0)),"CUIT NO CARGADO") -> Gastos Publicidad y Propaganda | R12: =IFERROR(IF(compras_mes9[[#This Row],[CUIT]]="","-",VLOOKUP(compras_mes9[[#This Row],[CUIT]],Lista_CUIT[#All],4,0)),"CUIT NO CARGADO") -> 0
B13: 30/09/2024 | C13: 1 | D13: 11 | E13: 1045416 | F13: 33709585229 | G13: =IFERROR(IF(compras_mes9[[#This Row],[CUIT]]="","-",VLOOKUP(compras_mes9[[#This Row],[CUIT]],Lista_CUIT[#All],2,0)),"CUIT NO CARGADO") -> GOOGLE ARGENTINA S.R.L. | H13: 29364.37 | I13: =IF(compras_mes9[[#This Row],[NETO GRAVADO]]="","",compras_mes9[[#This Row],[NETO GRAVADO]]*0.21) -> 6166.5177 | N13: 440.47 | O13: 880.93 | P13: =SUM(compras_mes9[[#This Row],[NETO GRAVADO]:[Otros / No Grav.]]) -> 36852.288 | Q13: =IFERROR(IF(compras_mes9[[#This Row],[CUIT]]="","-",VLOOKUP(compras_mes9[[#This Row],[CUIT]],Lista_CUIT[#All],3,0)),"CUIT NO CARGADO") -> Gastos Publicidad y Propaganda | R13: =IFERROR(IF(compras_mes9[[#This Row],[CUIT]]="","-",VLOOKUP(compras_mes9[[#This Row],[CUIT]],Lista_CUIT[#All],4,0)),"CUIT NO CARGADO") -> 0
B14: 30/09/2024 | C14: 1 | D14: 11 | E14: 1048850 | F14: 33709585229 | G14: =IFERROR(IF(compras_mes9[[#This Row],[CUIT]]="","-",VLOOKUP(compras_mes9[[#This Row],[CUIT]],Lista_CUIT[#All],2,0)),"CUIT NO CARGADO") -> GOOGLE ARGENTINA S.R.L. | H14: 152000 | I14: =IF(compras_mes9[[#This Row],[NETO GRAVADO]]="","",compras_mes9[[#This Row],[NETO GRAVADO]]*0.21) -> 31920 | N14: 2280 | O14: 4560 | P14: =SUM(compras_mes9[[#This Row],[NETO GRAVADO]:[Otros / No Grav.]]) -> 190760 | Q14: =IFERROR(IF(compras_mes9[[#This Row],[CUIT]]="","-",VLOOKUP(compras_mes9[[#This Row],[CUIT]],Lista_CUIT[#All],3,0)),"CUIT NO CARGADO") -> Gastos Publicidad y Propaganda | R14: =IFERROR(IF(compras_mes9[[#This Row],[CUIT]]="","-",VLOOKUP(compras_mes9[[#This Row],[CUIT]],Lista_CUIT[#All],4,0)),"CUIT NO CARGADO") -> 0
B15: 30/09/2024 | C15: 1 | D15: 11 | E15: 1051331 | F15: 33709585229 | G15: =IFERROR(IF(compras_mes9[[#This Row],[CUIT]]="","-",VLOOKUP(compras_mes9[[#This Row],[CUIT]],Lista_CUIT[#All],2,0)),"CUIT NO CARGADO") -> GOOGLE ARGENTINA S.R.L. | H15: 223091.09 | I15: =IF(compras_mes9[[#This Row],[NETO GRAVADO]]="","",compras_mes9[[#This Row],[NETO GRAVADO]]*0.21) -> 46849.129 | N15: 3346.37 | O15: 6692.73 | P15: =SUM(compras_mes9[[#This Row],[NETO GRAVADO]:[Otros / No Grav.]]) -> 279979.32 | Q15: =IFERROR(IF(compras_mes9[[#This Row],[CUIT]]="","-",VLOOKUP(compras_mes9[[#This Row],[CUIT]],Lista_CUIT[#All],3,0)),"CUIT NO CARGADO") -> Gastos Publicidad y Propaganda | R15: =IFERROR(IF(compras_mes9[[#This Row],[CUIT]]="","-",VLOOKUP(compras_mes9[[#This Row],[CUIT]],Lista_CUIT[#All],4,0)),"CUIT NO CARGADO") -> 0
B16: 30/09/2024 | C16: 1 | D16: 11 | E16: 1040173 | F16: 33709585229 | G16: =IFERROR(IF(compras_mes9[[#This Row],[CUIT]]="","-",VLOOKUP(compras_mes9[[#This Row],[CUIT]],Lista_CUIT[#All],2,0)),"CUIT NO CARGADO") -> GOOGLE ARGENTINA S.R.L. | H16: 2047352.9 | I16: =IF(compras_mes9[[#This Row],[NETO GRAVADO]]="","",compras_mes9[[#This Row],[NETO GRAVADO]]*0.21) -> 429944.11 | N16: 30710.29 | O16: 61420.59 | P16: =SUM(compras_mes9[[#This Row],[NETO GRAVADO]:[Otros / No Grav.]]) -> 2569427.9 | Q16: =IFERROR(IF(compras_mes9[[#This Row],[CUIT]]="","-",VLOOKUP(compras_mes9[[#This Row],[CUIT]],Lista_CUIT[#All],3,0)),"CUIT NO CARGADO") -> Gastos Publicidad y Propaganda | R16: =IFERROR(IF(compras_mes9[[#This Row],[CUIT]]="","-",VLOOKUP(compras_mes9[[#This Row],[CUIT]],Lista_CUIT[#All],4,0)),"CUIT NO CARGADO") -> 0
B17: 30/09/2024 | C17: 3 | D17: 11 | E17: 754552 | F17: 33709585229 | G17: =IFERROR(IF(compras_mes9[[#This Row],[CUIT]]="","-",VLOOKUP(compras_mes9[[#This Row],[CUIT]],Lista_CUIT[#All],2,0)),"CUIT NO CARGADO") -> GOOGLE ARGENTINA S.R.L. | H17: -11501.92 | I17: =IF(compras_mes9[[#This Row],[NETO GRAVADO]]="","",compras_mes9[[#This Row],[NETO GRAVADO]]*0.21) -> -2415.4032 | N17: -172.53 | O17: -345.06 | P17: =SUM(compras_mes9[[#This Row],[NETO GRAVADO]:[Otros / No Grav.]]) -> -14434.913 | Q17: =IFERROR(IF(compras_mes9[[#This Row],[CUIT]]="","-",VLOOKUP(compras_mes9[[#This Row],[CUIT]],Lista_CUIT[#All],3,0)),"CUIT NO CARGADO") -> Gastos Publicidad y Propaganda | R17: =IFERROR(IF(compras_mes9[[#This Row],[CUIT]]="","-",VLOOKUP(compras_mes9[[#This Row],[CUIT]],Lista_CUIT[#All],4,0)),"CUIT NO CARGADO") -> 0
B18: 30/09/2024 | C18: 3 | D18: 11 | E18: 756529 | F18: 33709585229 | G18: =IFERROR(IF(compras_mes9[[#This Row],[CUIT]]="","-",VLOOKUP(compras_mes9[[#This Row],[CUIT]],Lista_CUIT[#All],2,0)),"CUIT NO CARGADO") -> GOOGLE ARGENTINA S.R.L. | H18: -10.67 | I18: =IF(compras_mes9[[#This Row],[NETO GRAVADO]]="","",compras_mes9[[#This Row],[NETO GRAVADO]]*0.21) -> -2.2407 | P18: =SUM(compras_mes9[[#This Row],[NETO GRAVADO]:[Otros / No Grav.]]) -> -12.9107 | Q18: =IFERROR(IF(compras_mes9[[#This Row],[CUIT]]="","-",VLOOKUP(compras_mes9[[#This Row],[CUIT]],Lista_CUIT[#All],3,0)),"CUIT NO CARGADO") -> Gastos Publicidad y Propaganda | R18: =IFERROR(IF(compras_mes9[[#This Row],[CUIT]]="","-",VLOOKUP(compras_mes9[[#This Row],[CUIT]],Lista_CUIT[#All],4,0)),"CUIT NO CARGADO") -> 0
B19: 30/09/2024 | C19: 3 | D19: 11 | E19: 760209 | F19: 33709585229 | G19: =IFERROR(IF(compras_mes9[[#This Row],[CUIT]]="","-",VLOOKUP(compras_mes9[[#This Row],[CUIT]],Lista_CUIT[#All],2,0)),"CUIT NO CARGADO") -> GOOGLE ARGENTINA S.R.L. | H19: -65000 | I19: =IF(compras_mes9[[#This Row],[NETO GRAVADO]]="","",compras_mes9[[#This Row],[NETO GRAVADO]]*0.21) -> -13650 | N19: -975 | O19: -1950 | P19: =SUM(compras_mes9[[#This Row],[NETO GRAVADO]:[Otros / No Grav.]]) -> -81575 | Q19: =IFERROR(IF(compras_mes9[[#This Row],[CUIT]]="","-",VLOOKUP(compras_mes9[[#This Row],[CUIT]],Lista_CUIT[#All],3,0)),"CUIT NO CARGADO") -> Gastos Publicidad y Propaganda | R19: =IFERROR(IF(compras_mes9[[#This Row],[CUIT]]="","-",VLOOKUP(compras_mes9[[#This Row],[CUIT]],Lista_CUIT[#All],4,0)),"CUIT NO CARGADO") -> 0
B20: 30/09/2024 | C20: 3 | D20: 11 | E20: 761942 | F20: 33709585229 | G20: =IFERROR(IF(compras_mes9[[#This Row],[CUIT]]="","-",VLOOKUP(compras_mes9[[#This Row],[CUIT]],Lista_CUIT[#All],2,0)),"CUIT NO CARGADO") -> GOOGLE ARGENTINA S.R.L. | H20: 0 | I20: =IF(compras_mes9[[#This Row],[NETO GRAVADO]]="","",compras_mes9[[#This Row],[NETO GRAVADO]]*0.21) -> 0 | P20: =SUM(compras_mes9[[#This Row],[NETO GRAVADO]:[Otros / No Grav.]]) -> 0 | Q20: =IFERROR(IF(compras_mes9[[#This Row],[CUIT]]="","-",VLOOKUP(compras_mes9[[#This Row],[CUIT]],Lista_CUIT[#All],3,0)),"CUIT NO CARGADO") -> Gastos Publicidad y Propaganda | R20: =IFERROR(IF(compras_mes9[[#This Row],[CUIT]]="","-",VLOOKUP(compras_mes9[[#This Row],[CUIT]],Lista_CUIT[#All],4,0)),"CUIT NO CARGADO") -> 0
G21: =IFERROR(IF(compras_mes9[[#This Row],[CUIT]]="","-",VLOOKUP(compras_mes9[[#This Row],[CUIT]],Lista_CUIT[#All],2,0)),"CUIT NO CARGADO") -> - | I21: =IF(compras_mes9[[#This Row],[NETO GRAVADO]]="","",compras_mes9[[#This Row],[NETO GRAVADO]]*0.21) | P21: =SUM(compras_mes9[[#This Row],[NETO GRAVADO]:[Otros / No Grav.]]) -> 0 | Q21: =IFERROR(IF(compras_mes9[[#This Row],[CUIT]]="","-",VLOOKUP(compras_mes9[[#This Row],[CUIT]],Lista_CUIT[#All],3,0)),"CUIT NO CARGADO") -> - | R21: =IFERROR(IF(compras_mes9[[#This Row],[CUIT]]="","-",VLOOKUP(compras_mes9[[#This Row],[CUIT]],Lista_CUIT[#All],4,0)),"CUIT NO CARGADO") -> -
G22: =IFERROR(IF(compras_mes9[[#This Row],[CUIT]]="","-",VLOOKUP(compras_mes9[[#This Row],[CUIT]],Lista_CUIT[#All],2,0)),"CUIT NO CARGADO") -> - | I22: =IF(compras_mes9[[#This Row],[NETO GRAVADO]]="","",compras_mes9[[#This Row],[NETO GRAVADO]]*0.21) | P22: =SUM(compras_mes9[[#This Row],[NETO GRAVADO]:[Otros / No Grav.]]) -> 0 | Q22: =IFERROR(IF(compras_mes9[[#This Row],[CUIT]]="","-",VLOOKUP(compras_mes9[[#This Row],[CUIT]],Lista_CUIT[#All],3,0)),"CUIT NO CARGADO") -> - | R22: =IFERROR(IF(compras_mes9[[#This Row],[CUIT]]="","-",VLOOKUP(compras_mes9[[#This Row],[CUIT]],Lista_CUIT[#All],4,0)),"CUIT NO CARGADO") -> -
B23: Total | H23: =SUBTOTAL(109,compras_mes9[NETO GRAVADO]) -> 2915967.5 | I23: =SUBTOTAL(109,compras_mes9[IVA 21 %]) -> 612353.18 | J23: =SUBTOTAL(109,compras_mes9[IVA 27%]) -> 0 | K23: =SUBTOTAL(109,compras_mes9[IVA 10,5%]) -> 0 | L23: =SUBTOTAL(109,compras_mes9[PERC. IVA]) -> 0 | M23: =SUBTOTAL(109,compras_mes9[PERC IIBB BS AS]) -> 0 | N23: =SUBTOTAL(109,compras_mes9[PERC. IIBB CABA]) -> 43383.89 | O23: =SUBTOTAL(109,compras_mes9[Otros / No Grav.]) -> 86767.78 | P23: =SUBTOTAL(109,compras_mes9[TOTAL]) -> 3658472.4
L25: =compras_mes9[[#Totals],[NETO GRAVADO]]+compras_mes9[[#Totals],[Otros / No Grav.]] -> 3002735.3
D28: LIQUIDACION EXTRACTOS BANCARIOS-TARJETAS
D29: FECHA | E29: NRO CPTE | F29: BANCO | G29: NETO | H29: IVA 21% | I29: IVA 10,5% | J29: RET IIBB CABA | K29: PERC IVA | L29: PERC IIBB
F30: Galicia | G30: 28350 | H30: =extracto_banco_mes9[[#This Row],[NETO]]*0.21 -> 5953.5 | K30: 850.5
H31: =extracto_banco_mes9[[#This Row],[NETO]]*0.21 -> 0
H32: =extracto_banco_mes9[[#This Row],[NETO]]*0.21 -> 0
D33: Total | G33: =SUBTOTAL(109,extracto_banco_mes9[NETO]) -> 28350 | H33: =SUBTOTAL(109,extracto_banco_mes9[IVA 21%]) -> 5953.5 | I33: =SUBTOTAL(109,extracto_banco_mes9[IVA 10,5%]) -> 0 | J33: =SUBTOTAL(109,extracto_banco_mes9[RET IIBB CABA]) -> 0 | K33: =SUBTOTAL(109,extracto_banco_mes9[PERC IVA]) -> 850.5 | L33: =SUBTOTAL(109,extracto_banco_mes9[PERC IIBB]) -> 0
D37: FACTURAS C
D38: FECHA | E38: PTO VTA | F38: FC Nº | G38: CUIT | H38: RAZON SOCIAL | I38: TOTAL | J38: TIPO DE GASTO | K38: Provincia
D39: 02/09/2024 | E39: 2 | F39: 834 | G39: 20400104094 | H39: =IFERROR(IF(factura_c_mes9[[#This Row],[CUIT]]="","-",VLOOKUP(factura_c_mes9[[#This Row],[CUIT]],Lista_CUIT[#All],2,0)),"CUIT NO CARGADO") -> BOTINDARI FEDERICO DANIEL | I39: 80000 | J39: =IFERROR(IF(factura_c_mes9[[#This Row],[CUIT]]="","-",VLOOKUP(factura_c_mes9[[#This Row],[CUIT]],Lista_CUIT[#All],3,0)),"CUIT NO CARGADO") -> HONORARIOS CONTABLE | K39: =IFERROR(IF(factura_c_mes9[[#This Row],[CUIT]]="","-",VLOOKUP(factura_c_mes9[[#This Row],[CUIT]],Lista_CUIT[#All],4,0)),"CUIT NO CARGADO") -> 0
D40: 02/09/2024 | E40: 2 | F40: 46 | G40: 23380288079 | H40: =IFERROR(IF(factura_c_mes9[[#This Row],[CUIT]]="","-",VLOOKUP(factura_c_mes9[[#This Row],[CUIT]],Lista_CUIT[#All],2,0)),"CUIT NO CARGADO") -> CASTROMAN AGUSTIN | I40: 205000 | J40: =IFERROR(IF(factura_c_mes9[[#This Row],[CUIT]]="","-",VLOOKUP(factura_c_mes9[[#This Row],[CUIT]],Lista_CUIT[#All],3,0)),"CUIT NO CARGADO") -> Diseño Grafico | K40: =IFERROR(IF(factura_c_mes9[[#This Row],[CUIT]]="","-",VLOOKUP(factura_c_mes9[[#This Row],[CUIT]],Lista_CUIT[#All],4,0)),"CUIT NO CARGADO") -> 0
D41: 02/09/2024 | E41: 2 | F41: 843 | G41: 20400104094 | H41: =IFERROR(IF(factura_c_mes9[[#This Row],[CUIT]]="","-",VLOOKUP(factura_c_mes9[[#This Row],[CUIT]],Lista_CUIT[#All],2,0)),"CUIT NO CARGADO") -> BOTINDARI FEDERICO DANIEL | I41: 40000 | J41: =IFERROR(IF(factura_c_mes9[[#This Row],[CUIT]]="","-",VLOOKUP(factura_c_mes9[[#This Row],[CUIT]],Lista_CUIT[#All],3,0)),"CUIT NO CARGADO") -> HONORARIOS CONTABLE | K41: =IFERROR(IF(factura_c_mes9[[#This Row],[CUIT]]="","-",VLOOKUP(factura_c_mes9[[#This Row],[CUIT]],Lista_CUIT[#All],4,0)),"CUIT NO CARGADO") -> 0
D42: 04/09/2024 | E42: 5 | F42: 331039 | G42: 30711942412 | H42: =IFERROR(IF(factura_c_mes9[[#This Row],[CUIT]]="","-",VLOOKUP(factura_c_mes9[[#This Row],[CUIT]],Lista_CUIT[#All],2,0)),"CUIT NO CARGADO") -> FUNDACION EDUCACION PARA EL PROGRESO | I42: 161530 | J42: =IFERROR(IF(factura_c_mes9[[#This Row],[CUIT]]="","-",VLOOKUP(factura_c_mes9[[#This Row],[CUIT]],Lista_CUIT[#All],3,0)),"CUIT NO CARGADO") -> 0 | K42: =IFERROR(IF(factura_c_mes9[[#This Row],[CUIT]]="","-",VLOOKUP(factura_c_mes9[[#This Row],[CUIT]],Lista_CUIT[#All],4,0)),"CUIT NO CARGADO") -> 0
